{
  "type": "Feature",
  "properties": {
    "gn:admin1_code":"16.0",
    "gn:asciiname":"Wongeoseok",
    "gn:country_code":"KR",
    "gn:dem":172,
    "gn:feature_class":"P",
    "gn:feature_code":"PPL",
    "gn:name":"Wongeoseok",
    "gn:population":0,
    "gn:timezone":"Asia/Seoul",
    "iso:country":"KR",
    "name:kor_x_preferred":[
        "\uc6d0\uac70\uc11d"
    ],
    "name:kor_x_variant":[
        "W\u014fn\u2019g\u014fs\u014fk"
    ],
    "wof:name":"Wongeoseok",
    "wof:placetype":"locality"
},
  "geometry": {"coordinates":[127.05298999999999,34.82192],"type":"Point"}
}