{
  "type": "Feature",
  "properties": {
    "gn:admin1_code":"13.0",
    "gn:asciiname":"Gyeonjinbawi",
    "gn:country_code":"KR",
    "gn:dem":79,
    "gn:feature_class":"P",
    "gn:feature_code":"PPL",
    "gn:name":"Gyeonjinbawi",
    "gn:population":0,
    "gn:timezone":"Asia/Seoul",
    "iso:country":"KR",
    "name:kor_x_preferred":[
        "\uacac\uc9c4\ubc14\uc704"
    ],
    "name:und_x_variant":[
        "Chongjunbau-ri",
        "Piam-ni",
        "\uacac\uc900\ubc14\uc704",
        "Ky\u014fnjinbawi",
        "Ky\u014fnjunbawi",
        "Gyeonjinbawi"
    ],
    "wof:name":"Gyeonjinbawi",
    "wof:placetype":"locality"
},
  "geometry": {"coordinates":[126.91481,37.80732],"type":"Point"}
}