{
  "type": "Feature",
  "properties": {
    "gn:admin1_code":"14.0",
    "gn:asciiname":"Pulmu-gol",
    "gn:country_code":"KR",
    "gn:dem":23,
    "gn:feature_class":"P",
    "gn:feature_code":"PPL",
    "gn:name":"Pulmu-gol",
    "gn:population":0,
    "gn:timezone":"Asia/Seoul",
    "iso:country":"KR",
    "name:und_x_variant":[
        "\ubd88\ubb34\uace8",
        "Pulmu-gol"
    ],
    "wof:name":"Pulmu-gol",
    "wof:placetype":"locality"
},
  "geometry": {"coordinates":[129.47,36.7278],"type":"Point"}
}