{
  "type": "Feature",
  "properties": {
    "gn:admin1_code":"16.0",
    "gn:asciiname":"Mangchuk",
    "gn:country_code":"KR",
    "gn:dem":15,
    "gn:feature_class":"P",
    "gn:feature_code":"PPL",
    "gn:name":"Mangchuk",
    "gn:population":0,
    "gn:timezone":"Asia/Seoul",
    "iso:country":"KR",
    "name:kor_x_preferred":[
        "Mangch\u2019uk"
    ],
    "name:kor_x_variant":[
        "\ub9dd\ucd95"
    ],
    "wof:name":"Mangchuk",
    "wof:placetype":"locality"
},
  "geometry": {"coordinates":[126.64861000000001,34.37972],"type":"Point"}
}