{
  "type": "Feature",
  "properties": {
    "gn:admin1_code":"16.0",
    "gn:asciiname":"Yeongdeung-ri",
    "gn:country_code":"KR",
    "gn:dem":3,
    "gn:feature_class":"P",
    "gn:feature_code":"PPL",
    "gn:name":"Yeongdeung-ri",
    "gn:population":0,
    "gn:timezone":"Asia/Seoul",
    "iso:country":"KR",
    "name:kor_x_preferred":[
        "\uc601\ub4f1\ub9ac"
    ],
    "name:und_x_variant":[
        "Y\u014fngdong-ni",
        "Y\u014fngh\u016dngni",
        "Y\u014fngh\u016dng",
        "Yeongdeung-ri",
        "Y\u014fngd\u016dng-ni"
    ],
    "wof:name":"Yeongdeung-ri",
    "wof:placetype":"locality"
},
  "geometry": {"coordinates":[126.71538,34.81934],"type":"Point"}
}