{
  "type": "Feature",
  "properties": {
    "gn:admin1_code":"3.0",
    "gn:asciiname":"Kasan",
    "gn:country_code":"KR",
    "gn:dem":5,
    "gn:feature_class":"P",
    "gn:feature_code":"PPL",
    "gn:name":"Kasan",
    "gn:population":0,
    "gn:timezone":"Asia/Seoul",
    "iso:country":"KR",
    "name:bar_x_preferred":[
        "Kasan"
    ],
    "name:ceb_x_preferred":[
        "Kasan"
    ],
    "name:deu_x_preferred":[
        "Kasan"
    ],
    "name:ita_x_preferred":[
        "Kasan"
    ],
    "name:rus_x_preferred":[
        "\u041a\u0430\u0441\u0430\u043d"
    ],
    "name:swe_x_preferred":[
        "Kasan"
    ],
    "name:ukr_x_preferred":[
        "\u041a\u0430\u0441\u0430\u043d"
    ],
    "wof:name":"Kasan",
    "wof:placetype":"locality"
},
  "geometry": {"coordinates":[126.705,35.90611],"type":"Point"}
}