{
  "type": "Feature",
  "properties": {
    "gn:admin1_code":"13.0",
    "gn:admin2_code":"P'aju-si",
    "gn:asciiname":"Yulmindong",
    "gn:country_code":"KR",
    "gn:dem":24,
    "gn:feature_class":"P",
    "gn:feature_code":"PPL",
    "gn:name":"Yulmindong",
    "gn:population":0,
    "gn:timezone":"Asia/Seoul",
    "iso:country":"KR",
    "name:kor_x_preferred":[
        "\uc728\ubbfc\ub3d9"
    ],
    "wof:name":"Yulmindong",
    "wof:placetype":"locality"
},
  "geometry": {"coordinates":[126.75988999999998,37.91645],"type":"Point"}
}