{
  "type": "Feature",
  "properties": {
    "gn:admin1_code":"13.0",
    "gn:asciiname":"Dongmaru",
    "gn:country_code":"KR",
    "gn:dem":59,
    "gn:feature_class":"P",
    "gn:feature_code":"PPL",
    "gn:name":"Dongmaru",
    "gn:population":0,
    "gn:timezone":"Asia/Seoul",
    "iso:country":"KR",
    "name:kor_x_preferred":[
        "\ub3d9\ub9c8\ub8e8"
    ],
    "wof:name":"Dongmaru",
    "wof:placetype":"locality"
},
  "geometry": {"coordinates":[127.66956,37.23625],"type":"Point"}
}