{
  "type": "Feature",
  "properties": {
    "gn:admin1_code":"14.0",
    "gn:asciiname":"Hong-gol",
    "gn:country_code":"KR",
    "gn:dem":402,
    "gn:feature_class":"P",
    "gn:feature_code":"PPL",
    "gn:name":"Hong-gol",
    "gn:population":0,
    "gn:timezone":"Asia/Seoul",
    "iso:country":"KR",
    "name:und_x_variant":[
        "\ud64d\uace8",
        "Hong-gol"
    ],
    "wof:name":"Hong-gol",
    "wof:placetype":"locality"
},
  "geometry": {"coordinates":[129.0796,36.267],"type":"Point"}
}