{
  "type": "Feature",
  "properties": {
    "gn:admin1_code":"13.0",
    "gn:asciiname":"Araetmal",
    "gn:country_code":"KR",
    "gn:dem":59,
    "gn:feature_class":"P",
    "gn:feature_code":"PPL",
    "gn:name":"Araetmal",
    "gn:population":0,
    "gn:timezone":"Asia/Seoul",
    "iso:country":"KR",
    "name:kor_x_preferred":[
        "\uc544\ub7ab\ub9d0"
    ],
    "wof:name":"Araetmal",
    "wof:placetype":"locality"
},
  "geometry": {"coordinates":[127.24008000000001,37.07912],"type":"Point"}
}