{
  "type": "Feature",
  "properties": {
    "iso:country":"KR",
    "qs:name":"\ubcc0\ub3d9",
    "qs:name_adm0":"\ud55c\uad6d",
    "qs:name_adm1":"\ub300\uc804",
    "qs:photos":3,
    "qs:photos_1k":1,
    "qs:photos_9k":1,
    "qs:photos_9r":1,
    "qs:photos_all":3,
    "qs:photos_sr":1,
    "qs:placetype":"Suburb",
    "qs:pop_sr":"0",
    "wof:name":"\ubcc0\ub3d9",
    "wof:placetype":"neighbourhood"
},
  "geometry": {"coordinates":[127.7788,37.0943],"type":"Point"}
}