{
  "type": "Feature",
  "properties": {
    "gn:admin1_code":"19.0",
    "gn:admin2_code":"25050.0",
    "gn:asciiname":"Daedeok",
    "gn:country_code":"KR",
    "gn:dem":48,
    "gn:feature_class":"P",
    "gn:feature_code":"PPL",
    "gn:name":"Daedeok",
    "gn:population":0,
    "gn:timezone":"Asia/Seoul",
    "iso:country":"KR",
    "wof:name":"Daedeok",
    "wof:placetype":"locality"
},
  "geometry": {"coordinates":[127.41368,36.34669],"type":"Point"}
}