{
  "type": "Feature",
  "properties": {
    "iso:country":"KR",
    "qs:name":"\uc591\ub3552\ub3d9",
    "qs:name_adm0":"\ud55c\uad6d",
    "qs:name_adm1":"\uacbd\uc0c1\ub0a8\ub3c4",
    "qs:photos":247,
    "qs:photos_1k":50,
    "qs:photos_9k":1,
    "qs:photos_9r":4,
    "qs:photos_all":247,
    "qs:photos_sr":4,
    "qs:placetype":"LocalAdmin",
    "qs:pop_sr":"0",
    "wof:name":"\uc591\ub3552\ub3d9",
    "wof:placetype":"localadmin"
},
  "geometry": {"coordinates":[128.57522900000001,35.221922],"type":"Point"}
}