{
  "type": "Feature",
  "properties": {
    "gn:admin1_code":"13.0",
    "gn:asciiname":"Sorisil",
    "gn:country_code":"KR",
    "gn:dem":14,
    "gn:feature_class":"P",
    "gn:feature_code":"PPL",
    "gn:name":"S\u014frisil",
    "gn:population":0,
    "gn:timezone":"Asia/Seoul",
    "iso:country":"KR",
    "name:kor_x_preferred":[
        "\uc11c\ub9ac\uc2e4"
    ],
    "name:kor_x_variant":[
        "S\u014frisil"
    ],
    "wof:name":"Sorisil",
    "wof:placetype":"locality"
},
  "geometry": {"coordinates":[126.80361000000001,37.09028],"type":"Point"}
}