{
  "type": "Feature",
  "properties": {
    "gn:admin1_code":"5.0",
    "gn:asciiname":"Yopsong-dong",
    "gn:country_code":"KR",
    "gn:dem":163,
    "gn:feature_class":"P",
    "gn:feature_code":"PPL",
    "gn:name":"Y\u014fps\u014fng-dong",
    "gn:population":0,
    "gn:timezone":"Asia/Seoul",
    "iso:country":"KR",
    "name:und_x_variant":[
        "\uc5fd\uc131\ub3d9",
        "Y\u014fps\u014fng-dong"
    ],
    "wof:name":"Yopsong-dong",
    "wof:placetype":"locality"
},
  "geometry": {"coordinates":[127.672,36.3709],"type":"Point"}
}