{
  "type": "Feature",
  "properties": {
    "gn:admin1_code":"5.0",
    "gn:asciiname":"Solchi",
    "gn:country_code":"KR",
    "gn:dem":287,
    "gn:feature_class":"P",
    "gn:feature_code":"PPL",
    "gn:name":"Solchi",
    "gn:population":0,
    "gn:timezone":"Asia/Seoul",
    "iso:country":"KR",
    "name:kor_x_preferred":[
        "\uc194\uce58"
    ],
    "name:kor_x_variant":[
        "Solch\u2019i"
    ],
    "wof:name":"Solchi",
    "wof:placetype":"locality"
},
  "geometry": {"coordinates":[128.1396,37.08057],"type":"Point"}
}