{
  "type": "Feature",
  "properties": {
    "gn:admin1_code":"16.0",
    "gn:asciiname":"Taedong",
    "gn:cc2":"KR",
    "gn:country_code":"KR",
    "gn:dem":152,
    "gn:feature_class":"P",
    "gn:feature_code":"PPL",
    "gn:name":"Taedong",
    "gn:population":0,
    "gn:timezone":"Asia/Seoul",
    "iso:country":"KR",
    "name:und_x_variant":[
        "Taedong-ni",
        "Taedong"
    ],
    "wof:name":"Taedong",
    "wof:placetype":"locality"
},
  "geometry": {"coordinates":[127.25,34.23333],"type":"Point"}
}