{
  "type": "Feature",
  "properties": {
    "gn:admin1_code":"16.0",
    "gn:asciiname":"Taedong",
    "gn:cc2":"KR",
    "gn:country_code":"KR",
    "gn:dem":152,
    "gn:feature_class":"P",
    "gn:feature_code":"PPL",
    "gn:name":"Taedong",
    "gn:population":0,
    "gn:timezone":"Asia/Seoul",
    "iso:country":"KR",
    "name:ara_x_preferred":[
        "\u062a\u0627\u064a\u062f\u0648\u0646\u063a"
    ],
    "name:ben_x_preferred":[
        "\u09a4\u09be\u09df\u09c7\u09a6\u0982"
    ],
    "name:deu_x_preferred":[
        "Taedong"
    ],
    "name:ell_x_preferred":[
        "\u03a4\u03b1\u03b5\u03bd\u03c4\u03cc\u03bd\u03b3\u03ba"
    ],
    "name:eng_x_preferred":[
        "Taedong"
    ],
    "name:fas_x_preferred":[
        "\u062a\u0627\u0626\u062f\u0648\u0646\u06af"
    ],
    "name:fra_x_preferred":[
        "Taedong"
    ],
    "name:heb_x_preferred":[
        "\u05d8\u05d9\u05d9\u05d3\u05d5\u05e0\u05d2"
    ],
    "name:hin_x_preferred":[
        "\u0924\u093e\u090f\u0926\u094b\u0902\u0917"
    ],
    "name:hun_x_preferred":[
        "Tedong"
    ],
    "name:ind_x_preferred":[
        "Taedong"
    ],
    "name:ita_x_preferred":[
        "Taedong"
    ],
    "name:jpn_x_preferred":[
        "\u5927\u540c\u6c5f"
    ],
    "name:kor_x_preferred":[
        "\ub300\ub3d9"
    ],
    "name:nld_x_preferred":[
        "Taedong"
    ],
    "name:pol_x_preferred":[
        "Taedong"
    ],
    "name:por_x_preferred":[
        "Taedong"
    ],
    "name:rus_x_preferred":[
        "\u0422\u044d\u0434\u043e\u043d\u0433\u0430\u043d"
    ],
    "name:spa_x_preferred":[
        "Taedong"
    ],
    "name:swe_x_preferred":[
        "Taedong"
    ],
    "name:tur_x_preferred":[
        "Taedong"
    ],
    "name:ukr_x_preferred":[
        "\u0422\u0430\u0439\u0434\u0443\u043d"
    ],
    "name:und_x_variant":[
        "Taedong-ni",
        "Taedong"
    ],
    "name:urd_x_preferred":[
        "\u0679\u0627\u0626\u06cc\u0688\u0648\u0646\u06af"
    ],
    "name:vie_x_preferred":[
        "Taedong"
    ],
    "name:zho_cn_x_preferred":[
        "\u5927\u540c"
    ],
    "name:zho_tw_x_preferred":[
        "\u5927\u540c"
    ],
    "wof:name":"Taedong",
    "wof:placetype":"locality"
},
  "geometry": {"coordinates":[127.25,34.23333],"type":"Point"}
}