{
  "type": "Feature",
  "properties": {
    "gn:admin1_code":"14.0",
    "gn:asciiname":"Naksang-ni",
    "gn:country_code":"KR",
    "gn:dem":56,
    "gn:feature_class":"P",
    "gn:feature_code":"PPL",
    "gn:name":"Naksang-ni",
    "gn:population":0,
    "gn:timezone":"Asia/Seoul",
    "iso:country":"KR",
    "name:eng_x_preferred":[
        "Naksang"
    ],
    "name:eng_x_variant":[
        "Naksang-ni"
    ],
    "name:und_x_variant":[
        "\ub099\uc0c1\ub9ac",
        "Naksang-ni"
    ],
    "wof:name":"Naksang",
    "wof:placetype":"locality"
},
  "geometry": {"coordinates":[128.20079999999999,36.4502],"type":"Point"}
}