{
  "type": "Feature",
  "properties": {
    "gn:admin1_code":"14.0",
    "gn:asciiname":"P'osang-ni",
    "gn:country_code":"KR",
    "gn:dem":50,
    "gn:feature_class":"P",
    "gn:feature_code":"PPLL",
    "gn:name":"P\u2019osang-ni",
    "gn:population":0,
    "gn:timezone":"Asia/Seoul",
    "iso:country":"KR",
    "name:und_x_variant":[
        "\ud3ec\uc0c1\ub9ac",
        "P\u2019osang-ni"
    ],
    "wof:name":"P'osang-ni",
    "wof:placetype":"locality"
},
  "geometry": {"coordinates":[128.25432000000001,36.24439],"type":"Point"}
}