{
  "type": "Feature",
  "properties": {
    "gn:admin1_code":"16.0",
    "gn:asciiname":"Pungnyu-ri",
    "gn:country_code":"KR",
    "gn:dem":67,
    "gn:feature_class":"P",
    "gn:feature_code":"PPLL",
    "gn:name":"Pungnyu-ri",
    "gn:population":0,
    "gn:timezone":"Asia/Seoul",
    "iso:country":"KR",
    "name:kor_x_preferred":[
        "\ud48d\ub958\ub9ac"
    ],
    "name:kor_x_variant":[
        "P\u2019ungnyu-ri"
    ],
    "name:und_x_variant":[
        "P\u2019ungyu-ri",
        "Pungnyu-ri"
    ],
    "wof:name":"Pungnyu-ri",
    "wof:placetype":"locality"
},
  "geometry": {"coordinates":[127.24196999999999,34.67306],"type":"Point"}
}