{
  "type": "Feature",
  "properties": {
    "gn:admin1_code":"14.0",
    "gn:asciiname":"Piming-gol",
    "gn:country_code":"KR",
    "gn:dem":80,
    "gn:feature_class":"P",
    "gn:feature_code":"PPL",
    "gn:name":"Piming-gol",
    "gn:population":0,
    "gn:timezone":"Asia/Seoul",
    "iso:country":"KR",
    "name:und_x_variant":[
        "\ube44\ubc0d\uace8",
        "Piming-gol"
    ],
    "wof:name":"Piming-gol",
    "wof:placetype":"locality"
},
  "geometry": {"coordinates":[129.18996000000001,36.0111],"type":"Point"}
}