{
  "type": "Feature",
  "properties": {
    "gn:admin1_code":"20.0",
    "gn:asciiname":"Yangmak",
    "gn:country_code":"KR",
    "gn:dem":244,
    "gn:feature_class":"P",
    "gn:feature_code":"PPL",
    "gn:name":"Yangmak",
    "gn:population":0,
    "gn:timezone":"Asia/Seoul",
    "iso:country":"KR",
    "name:und_x_variant":[
        "\uc591\ub9c9",
        "Yangmak"
    ],
    "wof:name":"Yangmak",
    "wof:placetype":"locality"
},
  "geometry": {"coordinates":[127.86772999999999,35.68886],"type":"Point"}
}