{
  "type": "Feature",
  "properties": {
    "gn:admin1_code":"17.0",
    "gn:asciiname":"Daechuwon",
    "gn:country_code":"KR",
    "gn:dem":66,
    "gn:feature_class":"P",
    "gn:feature_code":"PPL",
    "gn:name":"Daechuwon",
    "gn:population":0,
    "gn:timezone":"Asia/Seoul",
    "iso:country":"KR",
    "name:kor_x_preferred":[
        "\ub300\ucd94\uc6d0"
    ],
    "wof:name":"Daechuwon",
    "wof:placetype":"locality"
},
  "geometry": {"coordinates":[127.09949,36.69498],"type":"Point"}
}