{
  "type": "Feature",
  "properties": {
    "gn:admin1_code":"6.0",
    "gn:asciiname":"Jeika-ri",
    "gn:country_code":"KR",
    "gn:dem":24,
    "gn:feature_class":"P",
    "gn:feature_code":"PPL",
    "gn:name":"Jeika-ri",
    "gn:population":0,
    "gn:timezone":"Asia/Seoul",
    "iso:country":"KR",
    "name:und_x_variant":[
        "\uc815\ud558\ub3d9",
        "Ch\u014fngha",
        "Ch\u014fngha-dong"
    ],
    "wof:name":"Jeika-ri",
    "wof:placetype":"locality"
},
  "geometry": {"coordinates":[129.18780000000001,37.4399],"type":"Point"}
}