{
  "type": "Feature",
  "properties": {
    "gn:admin1_code":"20.0",
    "gn:admin2_code":"Chinhae-si",
    "gn:asciiname":"Sado",
    "gn:country_code":"KR",
    "gn:dem":4,
    "gn:feature_class":"P",
    "gn:feature_code":"PPL",
    "gn:name":"Sado",
    "gn:population":0,
    "gn:timezone":"Asia/Seoul",
    "iso:country":"KR",
    "name:kor_x_preferred":[
        "\uc0ac\ub3c4"
    ],
    "wof:name":"Sado",
    "wof:placetype":"locality"
},
  "geometry": {"coordinates":[128.75986,35.10471],"type":"Point"}
}