{
  "type": "Feature",
  "properties": {
    "gn:admin1_code":"20.0",
    "gn:admin2_code":"Chinhae-si",
    "gn:asciiname":"Sado",
    "gn:country_code":"KR",
    "gn:dem":4,
    "gn:feature_class":"P",
    "gn:feature_code":"PPL",
    "gn:name":"Sado",
    "gn:population":0,
    "gn:timezone":"Asia/Seoul",
    "iso:country":"KR",
    "name:cat_x_preferred":[
        "Sado"
    ],
    "name:ceb_x_preferred":[
        "Sado"
    ],
    "name:ces_x_preferred":[
        "Sado"
    ],
    "name:deu_x_preferred":[
        "Sado"
    ],
    "name:est_x_preferred":[
        "Sado"
    ],
    "name:fra_x_preferred":[
        "Sado"
    ],
    "name:heb_x_preferred":[
        "\u05e1\u05d0\u05d3\u05d5"
    ],
    "name:ind_x_preferred":[
        "Sado"
    ],
    "name:ita_x_preferred":[
        "Sado"
    ],
    "name:kor_x_preferred":[
        "\uc0ac\ub3c4"
    ],
    "name:lit_x_preferred":[
        "Sado"
    ],
    "name:nld_x_preferred":[
        "Sado"
    ],
    "name:nor_x_preferred":[
        "Sado"
    ],
    "name:pol_x_preferred":[
        "Sado"
    ],
    "name:por_x_preferred":[
        "Sado"
    ],
    "name:ron_x_preferred":[
        "Sado"
    ],
    "name:rus_x_preferred":[
        "\u0421\u0430\u0434\u043e"
    ],
    "name:spa_x_preferred":[
        "Sado"
    ],
    "name:ukr_x_preferred":[
        "\u0421\u0430\u0434\u043e"
    ],
    "wof:name":"Sado",
    "wof:placetype":"locality"
},
  "geometry": {"coordinates":[128.75986,35.10471],"type":"Point"}
}