{
  "type": "Feature",
  "properties": {
    "gn:admin1_code":"17.0",
    "gn:asciiname":"T'ap-tong",
    "gn:country_code":"KR",
    "gn:dem":167,
    "gn:feature_class":"P",
    "gn:feature_code":"PPL",
    "gn:name":"T\u2019ap-tong",
    "gn:population":0,
    "gn:timezone":"Asia/Seoul",
    "iso:country":"KR",
    "name:und_x_variant":[
        "\ud0d1\ub3d9",
        "T\u2019ap-tong"
    ],
    "wof:name":"T'ap-tong",
    "wof:placetype":"locality"
},
  "geometry": {"coordinates":[126.6579,36.3466],"type":"Point"}
}