{
  "type": "Feature",
  "properties": {
    "gn:admin1_code":"20.0",
    "gn:asciiname":"Tangsonggok",
    "gn:country_code":"KR",
    "gn:dem":32,
    "gn:feature_class":"P",
    "gn:feature_code":"PPL",
    "gn:name":"Tangs\u014fnggok",
    "gn:population":0,
    "gn:timezone":"Asia/Seoul",
    "iso:country":"KR",
    "name:und_x_variant":[
        "\ub2f9\uc131\uace1",
        "Tangs\u014fnggok"
    ],
    "wof:name":"Tangsonggok",
    "wof:placetype":"locality"
},
  "geometry": {"coordinates":[128.39605,35.37464],"type":"Point"}
}