{
  "type": "Feature",
  "properties": {
    "gn:admin1_code":"16.0",
    "gn:asciiname":"Singi",
    "gn:country_code":"KR",
    "gn:dem":19,
    "gn:feature_class":"P",
    "gn:feature_code":"PPL",
    "gn:name":"Singi",
    "gn:population":0,
    "gn:timezone":"Asia/Seoul",
    "iso:country":"KR",
    "name:deu_x_preferred":[
        "Singi"
    ],
    "name:kor_x_preferred":[
        "\uc2e0\uae30"
    ],
    "name:nor_x_preferred":[
        "Singi"
    ],
    "name:swe_x_preferred":[
        "Singi"
    ],
    "name:und_x_variant":[
        "Sin\u2019gi-ri",
        "Sin\u2019gi",
        "Singi"
    ],
    "wof:name":"Singi",
    "wof:placetype":"locality"
},
  "geometry": {"coordinates":[126.65721000000001,34.91311],"type":"Point"}
}