{
  "type": "Feature",
  "properties": {
    "gn:admin1_code":"20.0",
    "gn:asciiname":"Suan",
    "gn:country_code":"KR",
    "gn:dem":11,
    "gn:feature_class":"P",
    "gn:feature_code":"PPL",
    "gn:name":"Suan",
    "gn:population":0,
    "gn:timezone":"Asia/Seoul",
    "iso:country":"KR",
    "name:ceb_x_preferred":[
        "Suan"
    ],
    "name:heb_x_preferred":[
        "\u05e1\u05d5\u05d0\u05df"
    ],
    "name:ita_x_preferred":[
        "Suan"
    ],
    "name:kor_x_preferred":[
        "\uc218\uc548"
    ],
    "name:swe_x_preferred":[
        "Suan"
    ],
    "name:tgl_x_preferred":[
        "Suan"
    ],
    "wof:name":"Suan",
    "wof:placetype":"locality"
},
  "geometry": {"coordinates":[128.93659,35.2295],"type":"Point"}
}