{
  "type": "Feature",
  "properties": {
    "gn:admin1_code":"13.0",
    "gn:asciiname":"Danghyeon",
    "gn:country_code":"KR",
    "gn:dem":11,
    "gn:feature_class":"P",
    "gn:feature_code":"PPL",
    "gn:name":"Danghyeon",
    "gn:population":0,
    "gn:timezone":"Asia/Seoul",
    "iso:country":"KR",
    "name:und_x_variant":[
        "\ub2f9\ud604",
        "Tanghy\u014fn",
        "Danghyeon"
    ],
    "wof:name":"Danghyeon",
    "wof:placetype":"locality"
},
  "geometry": {"coordinates":[126.91045,36.96883],"type":"Point"}
}