{
  "type": "Feature",
  "properties": {
    "gn:admin1_code":"13.0",
    "gn:asciiname":"Yatapsam-dong",
    "gn:country_code":"KR",
    "gn:dem":73,
    "gn:feature_class":"P",
    "gn:feature_code":"PPL",
    "gn:name":"Yatapsam-dong",
    "gn:population":0,
    "gn:timezone":"Asia/Seoul",
    "iso:country":"KR",
    "name:und_x_variant":[
        "\uc57c\ud0d13\ub3d9",
        "Yatapsam-dong",
        "Yat\u2019apsam-dong"
    ],
    "wof:name":"Yatapsam-dong",
    "wof:placetype":"locality"
},
  "geometry": {"coordinates":[127.15111,37.40556],"type":"Point"}
}