{
  "type": "Feature",
  "properties": {
    "gn:admin1_code":"3.0",
    "gn:asciiname":"Songsu",
    "gn:country_code":"KR",
    "gn:dem":191,
    "gn:feature_class":"P",
    "gn:feature_code":"PPL",
    "gn:name":"S\u014fngsu",
    "gn:population":0,
    "gn:timezone":"Asia/Seoul",
    "iso:country":"KR",
    "name:und_x_variant":[
        "\uc131\uc218",
        "S\u014fngsu"
    ],
    "wof:name":"Songsu",
    "wof:placetype":"locality"
},
  "geometry": {"coordinates":[127.33899,35.6298],"type":"Point"}
}