{
  "type": "Feature",
  "properties": {
    "iso:country":"KR",
    "name:eng_x_preferred":[
        "Hyeondo-myeon"
    ],
    "name:kor_x_preferred":[
        "\ud604\ub3c4\uba74"
    ],
    "qs:name":"\ud604\ub3c4\uba74",
    "qs:name_adm0":"\ud55c\uad6d",
    "qs:name_adm1":"\ucda9\uccad\ubd81\ub3c4",
    "qs:photos":30,
    "qs:photos_1k":6,
    "qs:photos_9k":1,
    "qs:photos_9r":2,
    "qs:photos_all":30,
    "qs:photos_sr":2,
    "qs:placetype":"LocalAdmin",
    "qs:pop_sr":"0",
    "wof:name":"Hyeondo-myeon",
    "wof:placetype":"localadmin"
},
  "geometry": {"coordinates":[127.441406,36.625558],"type":"Point"}
}