{
  "type": "Feature",
  "properties": {
    "gn:admin1_code":"3.0",
    "gn:asciiname":"Tonggujom",
    "gn:country_code":"KR",
    "gn:dem":425,
    "gn:feature_class":"P",
    "gn:feature_code":"PPL",
    "gn:name":"Tongguj\u014fm",
    "gn:population":0,
    "gn:timezone":"Asia/Seoul",
    "iso:country":"KR",
    "name:und_x_variant":[
        "\ub3d9\uad6c\uc810",
        "Tongguj\u014fm"
    ],
    "wof:name":"Tonggujom",
    "wof:placetype":"locality"
},
  "geometry": {"coordinates":[127.50042999999999,35.75647],"type":"Point"}
}