{
  "type": "Feature",
  "properties": {
    "gn:admin1_code":"13.0",
    "gn:asciiname":"Beomti",
    "gn:country_code":"KR",
    "gn:dem":67,
    "gn:feature_class":"P",
    "gn:feature_code":"PPL",
    "gn:name":"Beomti",
    "gn:population":0,
    "gn:timezone":"Asia/Seoul",
    "iso:country":"KR",
    "name:kor_x_preferred":[
        "\ubc94\ud2f0"
    ],
    "wof:name":"Beomti",
    "wof:placetype":"locality"
},
  "geometry": {"coordinates":[127.23927,37.1042],"type":"Point"}
}