{
  "type": "Feature",
  "properties": {
    "gn:admin1_code":"5.0",
    "gn:asciiname":"Saum-ni",
    "gn:cc2":"KR",
    "gn:country_code":"KR",
    "gn:dem":70,
    "gn:feature_class":"P",
    "gn:feature_code":"PPL",
    "gn:name":"Sa\u016dm-ni",
    "gn:population":0,
    "gn:timezone":"Asia/Seoul",
    "iso:country":"KR",
    "name:eng_x_preferred":[
        "Saum"
    ],
    "name:eng_x_variant":[
        "Saum-ni"
    ],
    "name:und_x_variant":[
        "Sa\u016dm-ri",
        "Sa\u016dm-ni"
    ],
    "wof:name":"Saum",
    "wof:placetype":"locality"
},
  "geometry": {"coordinates":[127.55028,36.43083],"type":"Point"}
}