{
  "type": "Feature",
  "properties": {
    "gn:admin1_code":"1.0",
    "gn:admin2_code":"Namjeju-gun",
    "gn:asciiname":"T'osal-li",
    "gn:country_code":"KR",
    "gn:dem":86,
    "gn:feature_class":"P",
    "gn:feature_code":"PPL",
    "gn:name":"T\u2019osal-li",
    "gn:population":0,
    "gn:timezone":"Asia/Seoul",
    "iso:country":"KR",
    "name:und_x_variant":[
        "T\u2019osan il-li",
        "T\u2019osan-ni",
        "T\u2019osal-li"
    ],
    "wof:name":"T'osal-li",
    "wof:placetype":"locality"
},
  "geometry": {"coordinates":[126.765,33.32722],"type":"Point"}
}