{
  "type": "Feature",
  "properties": {
    "gn:admin1_code":"6.0",
    "gn:asciiname":"Yumokchong",
    "gn:country_code":"KR",
    "gn:dem":363,
    "gn:feature_class":"P",
    "gn:feature_code":"PPL",
    "gn:name":"Yumokch\u014fng",
    "gn:population":0,
    "gn:timezone":"Asia/Seoul",
    "iso:country":"KR",
    "name:kor_x_preferred":[
        "\uc720\ubaa9\uc815"
    ],
    "name:kor_x_variant":[
        "Yumokch\u014fng"
    ],
    "wof:name":"Yumokchong",
    "wof:placetype":"locality"
},
  "geometry": {"coordinates":[128.30330000000001,37.2835],"type":"Point"}
}