{
  "type": "Feature",
  "properties": {
    "gn:admin1_code":"14.0",
    "gn:asciiname":"Gureongma",
    "gn:country_code":"KR",
    "gn:dem":248,
    "gn:feature_class":"P",
    "gn:feature_code":"PPL",
    "gn:name":"Gureongma",
    "gn:population":0,
    "gn:timezone":"Asia/Seoul",
    "iso:country":"KR",
    "name:kor_x_preferred":[
        "\uad6c\ub801\ub9c8"
    ],
    "wof:name":"Gureongma",
    "wof:placetype":"locality"
},
  "geometry": {"coordinates":[128.73478,36.94652],"type":"Point"}
}