{
  "type": "Feature",
  "properties": {
    "gn:admin1_code":"6.0",
    "gn:asciiname":"Jangjabeol",
    "gn:country_code":"KR",
    "gn:dem":191,
    "gn:feature_class":"P",
    "gn:feature_code":"PPL",
    "gn:name":"Jangjabeol",
    "gn:population":0,
    "gn:timezone":"Asia/Seoul",
    "iso:country":"KR",
    "name:kor_x_preferred":[
        "\uc7a5\uc790\ubc8c"
    ],
    "wof:name":"Jangjabeol",
    "wof:placetype":"locality"
},
  "geometry": {"coordinates":[127.22069999999999,38.20737],"type":"Point"}
}