{
  "type": "Feature",
  "properties": {
    "gn:admin1_code":"20.0",
    "gn:asciiname":"Won'go-ri",
    "gn:country_code":"KR",
    "gn:dem":240,
    "gn:feature_class":"P",
    "gn:feature_code":"PPL",
    "gn:name":"W\u014fn\u2019g\u014f-ri",
    "gn:population":0,
    "gn:timezone":"Asia/Seoul",
    "iso:country":"KR",
    "name:und_x_variant":[
        "\uc6d0\uac70\ub9ac",
        "W\u014fn\u2019g\u014f-ri"
    ],
    "wof:name":"Won'go-ri",
    "wof:placetype":"locality"
},
  "geometry": {"coordinates":[127.89246,35.62578],"type":"Point"}
}