{
  "type": "Feature",
  "properties": {
    "gn:admin1_code":"3.0",
    "gn:asciiname":"Samdong-ni",
    "gn:country_code":"KR",
    "gn:dem":55,
    "gn:feature_class":"P",
    "gn:feature_code":"PPL",
    "gn:name":"Samdong-ni",
    "gn:population":0,
    "gn:timezone":"Asia/Seoul",
    "iso:country":"KR",
    "name:eng_x_preferred":[
        "Samdong"
    ],
    "name:eng_x_variant":[
        "Samdong-ni"
    ],
    "name:und_x_variant":[
        "\uc0bc\ub3d9\ub9ac",
        "Samdong-ni"
    ],
    "wof:name":"Samdong",
    "wof:placetype":"locality"
},
  "geometry": {"coordinates":[127.07847,35.79901],"type":"Point"}
}