{
  "type": "Feature",
  "properties": {
    "gn:admin1_code":"14.0",
    "gn:asciiname":"Chung-ni",
    "gn:cc2":"KR",
    "gn:country_code":"KR",
    "gn:dem":187,
    "gn:feature_class":"P",
    "gn:feature_code":"PPL",
    "gn:name":"Chung-ni",
    "gn:population":0,
    "gn:timezone":"Asia/Seoul",
    "iso:country":"KR",
    "name:und_x_variant":[
        "W\u014fn-kol",
        "Wan\u2019yok",
        "Wan\u2019gol",
        "Chung-ni"
    ],
    "wof:name":"Chung-ni",
    "wof:placetype":"locality"
},
  "geometry": {"coordinates":[128.58333000000002,36.15],"type":"Point"}
}