{
  "type": "Feature",
  "properties": {
    "gn:admin1_code":"16.0",
    "gn:asciiname":"Bangha",
    "gn:country_code":"KR",
    "gn:dem":21,
    "gn:feature_class":"P",
    "gn:feature_code":"PPL",
    "gn:name":"Bangha",
    "gn:population":0,
    "gn:timezone":"Asia/Seoul",
    "iso:country":"KR",
    "name:kor_x_preferred":[
        "\ubc29\ud558"
    ],
    "wof:name":"Bangha",
    "wof:placetype":"locality"
},
  "geometry": {"coordinates":[126.63924,34.95737],"type":"Point"}
}