{
  "type": "Feature",
  "properties": {
    "gn:admin1_code":"5.0",
    "gn:asciiname":"Tapjeong",
    "gn:country_code":"KR",
    "gn:dem":75,
    "gn:feature_class":"P",
    "gn:feature_code":"PPL",
    "gn:name":"Tapjeong",
    "gn:population":0,
    "gn:timezone":"Asia/Seoul",
    "iso:country":"KR",
    "name:kor_x_preferred":[
        "\ud0d1\uc815"
    ],
    "name:kor_x_variant":[
        "T\u2019apch\u014fng"
    ],
    "wof:name":"Tapjeong",
    "wof:placetype":"locality"
},
  "geometry": {"coordinates":[127.86497,37.01871],"type":"Point"}
}