{
  "type": "Feature",
  "properties": {
    "iso:country":"KR",
    "name:eng_x_preferred":[
        "Sinhyeon-eup"
    ],
    "name:kor_x_preferred":[
        "\uc2e0\ud604\uc74d"
    ],
    "qs:name":"\uc2e0\ud604\uc74d",
    "qs:name_adm0":"\ud55c\uad6d",
    "qs:name_adm1":"\uacbd\uc0c1\ub0a8\ub3c4",
    "qs:photos":4,
    "qs:photos_1k":1,
    "qs:photos_9k":1,
    "qs:photos_9r":1,
    "qs:photos_all":4,
    "qs:photos_sr":1,
    "qs:placetype":"LocalAdmin",
    "qs:pop_sr":"0",
    "wof:name":"Sinhyeon-eup",
    "wof:placetype":"localadmin"
},
  "geometry": {"coordinates":[128.60681500000001,34.789276],"type":"Point"}
}