{
  "type": "Feature",
  "properties": {
    "gn:admin1_code":"13.0",
    "gn:admin2_code":"Ich'\u014fn-si",
    "gn:asciiname":"Yangdal-mal",
    "gn:country_code":"KR",
    "gn:dem":74,
    "gn:feature_class":"P",
    "gn:feature_code":"PPL",
    "gn:name":"Yangdal-mal",
    "gn:population":0,
    "gn:timezone":"Asia/Seoul",
    "iso:country":"KR",
    "name:kor_x_preferred":[
        "\uc591\ub2ec\ub9d0"
    ],
    "wof:name":"Yangdal-mal",
    "wof:placetype":"locality"
},
  "geometry": {"coordinates":[127.43611,37.24583],"type":"Point"}
}