{
  "type": "Feature",
  "properties": {
    "gn:admin1_code":"13.0",
    "gn:asciiname":"Makbaji",
    "gn:country_code":"KR",
    "gn:dem":150,
    "gn:feature_class":"P",
    "gn:feature_code":"PPL",
    "gn:name":"Makbaji",
    "gn:population":0,
    "gn:timezone":"Asia/Seoul",
    "iso:country":"KR",
    "name:kor_x_preferred":[
        "\ub9c9\ubc14\uc9c0"
    ],
    "name:und_x_variant":[
        "Makbaji"
    ],
    "wof:name":"Makbaji",
    "wof:placetype":"locality"
},
  "geometry": {"coordinates":[127.32810000000001,37.6644],"type":"Point"}
}