{
  "type": "Feature",
  "properties": {
    "gn:admin1_code":"14.0",
    "gn:asciiname":"Sinwol",
    "gn:country_code":"KR",
    "gn:dem":137,
    "gn:feature_class":"P",
    "gn:feature_code":"PPL",
    "gn:name":"Sinwol",
    "gn:population":0,
    "gn:timezone":"Asia/Seoul",
    "iso:country":"KR",
    "name:kor_x_preferred":[
        "\uc2e0\uc6d4"
    ],
    "wof:name":"Sinwol",
    "wof:placetype":"locality"
},
  "geometry": {"coordinates":[128.6446,36.11186],"type":"Point"}
}