{
  "type": "Feature",
  "properties": {
    "gn:admin1_code":"5.0",
    "gn:asciiname":"Changsongbaegi",
    "gn:country_code":"KR",
    "gn:dem":203,
    "gn:feature_class":"P",
    "gn:feature_code":"PPL",
    "gn:name":"Changs\u014fngbaegi",
    "gn:population":0,
    "gn:timezone":"Asia/Seoul",
    "iso:country":"KR",
    "name:und_x_variant":[
        "\uc7a5\uc131\ubc30\uae30",
        "Changs\u014fngbaegi"
    ],
    "wof:name":"Changsongbaegi",
    "wof:placetype":"locality"
},
  "geometry": {"coordinates":[127.75069999999999,36.2956],"type":"Point"}
}