{
  "type": "Feature",
  "properties": {
    "gn:admin1_code":"15.0",
    "gn:asciiname":"Geolmi",
    "gn:country_code":"KR",
    "gn:dem":43,
    "gn:feature_class":"P",
    "gn:feature_code":"PPL",
    "gn:name":"Geolmi",
    "gn:population":0,
    "gn:timezone":"Asia/Seoul",
    "iso:country":"KR",
    "name:und_x_variant":[
        "\uac78\ubbf8",
        "K\u014flmi",
        "Geolmi"
    ],
    "wof:name":"Geolmi",
    "wof:placetype":"locality"
},
  "geometry": {"coordinates":[128.42086,35.75107],"type":"Point"}
}