{
  "type": "Feature",
  "properties": {
    "gn:admin1_code":"14.0",
    "gn:asciiname":"Songsim-gol",
    "gn:country_code":"KR",
    "gn:dem":133,
    "gn:feature_class":"P",
    "gn:feature_code":"PPL",
    "gn:name":"S\u014fngsim-gol",
    "gn:population":0,
    "gn:timezone":"Asia/Seoul",
    "iso:country":"KR",
    "name:und_x_variant":[
        "S\u014fngsim-gol",
        "\uc131\uc2ec\uace8"
    ],
    "wof:name":"Songsim-gol",
    "wof:placetype":"locality"
},
  "geometry": {"coordinates":[129.3125,37.02583],"type":"Point"}
}