{
  "type": "Feature",
  "properties": {
    "gn:admin1_code":"17.0",
    "gn:asciiname":"Hwangwon",
    "gn:country_code":"KR",
    "gn:dem":8,
    "gn:feature_class":"P",
    "gn:feature_code":"PPL",
    "gn:name":"Hwangw\u014fn",
    "gn:population":0,
    "gn:timezone":"Asia/Seoul",
    "iso:country":"KR",
    "name:und_x_variant":[
        "\ud669\uc6d0",
        "Hwangw\u014fn"
    ],
    "wof:name":"Hwangwon",
    "wof:placetype":"locality"
},
  "geometry": {"coordinates":[126.8069,36.8171],"type":"Point"}
}