{
  "type": "Feature",
  "properties": {
    "gn:admin1_code":"6.0",
    "gn:asciiname":"Dongondong",
    "gn:country_code":"KR",
    "gn:dem":145,
    "gn:feature_class":"P",
    "gn:feature_code":"PPL",
    "gn:name":"Dongondong",
    "gn:population":0,
    "gn:timezone":"Asia/Seoul",
    "iso:country":"KR",
    "name:kor_x_preferred":[
        "\ub3d9\uc628\ub3d9"
    ],
    "wof:name":"Dongondong",
    "wof:placetype":"locality"
},
  "geometry": {"coordinates":[127.28601999999999,38.13863],"type":"Point"}
}