{
  "type": "Feature",
  "properties": {
    "gn:admin1_code":"6.0",
    "gn:asciiname":"Ssari-gol",
    "gn:country_code":"KR",
    "gn:dem":380,
    "gn:feature_class":"P",
    "gn:feature_code":"PPL",
    "gn:name":"Ssari-gol",
    "gn:population":0,
    "gn:timezone":"Asia/Seoul",
    "iso:country":"KR",
    "name:kor_x_preferred":[
        "\uc2f8\ub9ac\uace8"
    ],
    "wof:name":"Ssari-gol",
    "wof:placetype":"locality"
},
  "geometry": {"coordinates":[127.9089,37.6188],"type":"Point"}
}