{
  "type": "Feature",
  "properties": {
    "gn:admin1_code":"11.0",
    "gn:asciiname":"Hongjeil-tong",
    "gn:country_code":"KR",
    "gn:dem":70,
    "gn:feature_class":"P",
    "gn:feature_code":"PPL",
    "gn:name":"Hongjeil-tong",
    "gn:population":0,
    "gn:timezone":"Asia/Seoul",
    "iso:country":"KR",
    "name:eng_x_preferred":[
        "Hongjeil"
    ],
    "name:eng_x_variant":[
        "Hongjeil-tong"
    ],
    "name:und_x_variant":[
        "\ud64d\uc81c1\ub3d9",
        "Hongjeil-tong"
    ],
    "wof:name":"Hongjeil",
    "wof:placetype":"locality"
},
  "geometry": {"coordinates":[126.94113,37.58695],"type":"Point"}
}