{
  "type": "Feature",
  "properties": {
    "gn:admin1_code":"16.0",
    "gn:asciiname":"Baedeuri",
    "gn:country_code":"KR",
    "gn:dem":13,
    "gn:feature_class":"P",
    "gn:feature_code":"PPL",
    "gn:name":"Baedeuri",
    "gn:population":0,
    "gn:timezone":"Asia/Seoul",
    "iso:country":"KR",
    "name:kor_x_preferred":[
        "\ubc30\ub4dc\ub9ac"
    ],
    "name:und_x_variant":[
        "\ubc30\ub2e4\ub9ac",
        "Paeda-ri",
        "Baedeuri"
    ],
    "wof:name":"Baedeuri",
    "wof:placetype":"locality"
},
  "geometry": {"coordinates":[126.53863,34.70784],"type":"Point"}
}