{
  "type": "Feature",
  "properties": {
    "gn:admin1_code":"6.0",
    "gn:asciiname":"Ot'ansam-ni",
    "gn:country_code":"KR",
    "gn:dem":189,
    "gn:feature_class":"P",
    "gn:feature_code":"PPL",
    "gn:name":"Ot\u2019ansam-ni",
    "gn:population":0,
    "gn:timezone":"Asia/Seoul",
    "iso:country":"KR",
    "name:eng_x_preferred":[
        "Ot'ansam"
    ],
    "name:eng_x_variant":[
        "Ot'ansam-ni"
    ],
    "name:und_x_variant":[
        "\uc624\ud0c43\ub9ac",
        "Ot\u2019ansam-ni"
    ],
    "wof:name":"Ot'ansam",
    "wof:placetype":"locality"
},
  "geometry": {"coordinates":[127.60194,38.04139],"type":"Point"}
}