{
  "type": "Feature",
  "properties": {
    "gn:admin1_code":"5.0",
    "gn:asciiname":"Yolmanggul",
    "gn:country_code":"KR",
    "gn:dem":149,
    "gn:feature_class":"P",
    "gn:feature_code":"PPL",
    "gn:name":"Y\u014flmanggul",
    "gn:population":0,
    "gn:timezone":"Asia/Seoul",
    "iso:country":"KR",
    "name:und_x_variant":[
        "\uc5f4\ub9dd\uad74",
        "Y\u014flmanggul"
    ],
    "wof:name":"Yolmanggul",
    "wof:placetype":"locality"
},
  "geometry": {"coordinates":[127.517,36.4961],"type":"Point"}
}