{
  "type": "Feature",
  "properties": {
    "gn:admin1_code":"15.0",
    "gn:asciiname":"Keungoldong",
    "gn:country_code":"KR",
    "gn:dem":199,
    "gn:feature_class":"P",
    "gn:feature_code":"PPL",
    "gn:name":"Keungoldong",
    "gn:population":0,
    "gn:timezone":"Asia/Seoul",
    "iso:country":"KR",
    "name:kor_x_preferred":[
        "\ud070\uace8\ub3d9"
    ],
    "wof:name":"Keungoldong",
    "wof:placetype":"locality"
},
  "geometry": {"coordinates":[128.66848000000002,35.7626],"type":"Point"}
}