{
  "type": "Feature",
  "properties": {
    "gn:admin1_code":"18.0",
    "gn:asciiname":"Songnim",
    "gn:country_code":"KR",
    "gn:dem":48,
    "gn:feature_class":"P",
    "gn:feature_code":"PPL",
    "gn:name":"Songnim",
    "gn:population":0,
    "gn:timezone":"Asia/Seoul",
    "iso:country":"KR",
    "name:kor_x_preferred":[
        "\uc1a1\ub9bc"
    ],
    "wof:name":"Songnim",
    "wof:placetype":"locality"
},
  "geometry": {"coordinates":[126.72880000000001,35.18781],"type":"Point"}
}