{
  "type": "Feature",
  "properties": {
    "gn:admin1_code":"13.0",
    "gn:admin2_code":"Yongin-si",
    "gn:asciiname":"Yeomti",
    "gn:country_code":"KR",
    "gn:dem":126,
    "gn:feature_class":"P",
    "gn:feature_code":"PPL",
    "gn:name":"Yeomti",
    "gn:population":0,
    "gn:timezone":"Asia/Seoul",
    "iso:country":"KR",
    "name:kor_x_preferred":[
        "\uc5fc\uce58"
    ],
    "name:kor_x_variant":[
        "Y\u014fmch\u2019i",
        "\uc5fc\ud2f0"
    ],
    "name:und_x_variant":[
        "Yeomchi",
        "Yeomti"
    ],
    "wof:name":"Yeomti",
    "wof:placetype":"locality"
},
  "geometry": {"coordinates":[127.23426000000001,37.19354000000001],"type":"Point"}
}