{
  "type": "Feature",
  "properties": {
    "gn:admin1_code":"13.0",
    "gn:asciiname":"Byeokdong",
    "gn:country_code":"KR",
    "gn:dem":15,
    "gn:feature_class":"P",
    "gn:feature_code":"PPL",
    "gn:name":"Byeokdong",
    "gn:population":0,
    "gn:timezone":"Asia/Seoul",
    "iso:country":"KR",
    "name:und_x_variant":[
        "\ubcbd\ub3d9",
        "Byeokdong",
        "Py\u014fk-tong"
    ],
    "wof:name":"Byeokdong",
    "wof:placetype":"locality"
},
  "geometry": {"coordinates":[126.98135000000001,37.03486],"type":"Point"}
}