{
  "type": "Feature",
  "properties": {
    "gn:admin1_code":"16.0",
    "gn:asciiname":"Haban",
    "gn:cc2":"KR",
    "gn:country_code":"KR",
    "gn:dem":15,
    "gn:feature_class":"P",
    "gn:feature_code":"PPL",
    "gn:name":"Haban",
    "gn:population":0,
    "gn:timezone":"Asia/Seoul",
    "iso:country":"KR",
    "name:und_x_variant":[
        "Hap\u2019an-ni",
        "Haban-ni",
        "Haban"
    ],
    "wof:name":"Haban",
    "wof:placetype":"locality"
},
  "geometry": {"coordinates":[127.53361,34.44278],"type":"Point"}
}