{
  "type": "Feature",
  "properties": {
    "gn:admin1_code":"14.0",
    "gn:asciiname":"Dongchibeondeogi",
    "gn:country_code":"KR",
    "gn:dem":90,
    "gn:feature_class":"P",
    "gn:feature_code":"PPL",
    "gn:name":"Dongchibeondeogi",
    "gn:population":0,
    "gn:timezone":"Asia/Seoul",
    "iso:country":"KR",
    "name:kor_x_preferred":[
        "\ub3d9\uce58\ubc88\ub355\uc774"
    ],
    "wof:name":"Dongchibeondeogi",
    "wof:placetype":"locality"
},
  "geometry": {"coordinates":[129.40171000000001,35.91022],"type":"Point"}
}