{
  "type": "Feature",
  "properties": {
    "gn:admin1_code":"21.0",
    "gn:asciiname":"Yaum",
    "gn:cc2":"KR",
    "gn:country_code":"KR",
    "gn:dem":25,
    "gn:feature_class":"P",
    "gn:feature_code":"PPL",
    "gn:name":"Ya\u016dm",
    "gn:population":0,
    "gn:timezone":"Asia/Seoul",
    "iso:country":"KR",
    "name:und_x_variant":[
        "Ya\u016dm-dong",
        "Ya\u016dm-ni",
        "Ya\u016dm"
    ],
    "wof:name":"Yaum",
    "wof:placetype":"locality"
},
  "geometry": {"coordinates":[129.34999999999999,35.51667],"type":"Point"}
}