{
  "type": "Feature",
  "properties": {
    "gn:admin1_code":"16.0",
    "gn:asciiname":"Myonjol-li",
    "gn:cc2":"KR",
    "gn:country_code":"KR",
    "gn:dem":11,
    "gn:feature_class":"P",
    "gn:feature_code":"PPL",
    "gn:name":"My\u014fnj\u014fl-li",
    "gn:population":0,
    "gn:timezone":"Asia/Seoul",
    "iso:country":"KR",
    "name:und_x_variant":[
        "My\u014fnj\u014fn-ni",
        "My\u014fnj\u014fn-dong",
        "My\u014fnj\u014fl-li"
    ],
    "wof:name":"Myonjol-li",
    "wof:placetype":"locality"
},
  "geometry": {"coordinates":[126.02806,34.86611],"type":"Point"}
}