{
  "type": "Feature",
  "properties": {
    "gn:admin1_code":"16.0",
    "gn:asciiname":"Daejeong",
    "gn:country_code":"KR",
    "gn:dem":66,
    "gn:feature_class":"P",
    "gn:feature_code":"PPL",
    "gn:name":"Daejeong",
    "gn:population":0,
    "gn:timezone":"Asia/Seoul",
    "iso:country":"KR",
    "name:kor_x_preferred":[
        "\uc678\ucd94"
    ],
    "name:kor_x_variant":[
        "Oech\u2019u",
        "\ub300\uc815"
    ],
    "wof:name":"Daejeong",
    "wof:placetype":"locality"
},
  "geometry": {"coordinates":[127.29078,34.88015],"type":"Point"}
}