{
  "type": "Feature",
  "properties": {
    "gn:admin1_code":"13.0",
    "gn:asciiname":"Bakkatdodalmi",
    "gn:country_code":"KR",
    "gn:dem":110,
    "gn:feature_class":"P",
    "gn:feature_code":"PPL",
    "gn:name":"Bakkatdodalmi",
    "gn:population":0,
    "gn:timezone":"Asia/Seoul",
    "iso:country":"KR",
    "name:kor_x_preferred":[
        "\ubc14\uae65\ub3c4\ub2ec\ubbf8"
    ],
    "name:und_x_variant":[
        "Pakkattodalmi"
    ],
    "wof:name":"Bakkatdodalmi",
    "wof:placetype":"locality"
},
  "geometry": {"coordinates":[127.56489999999999,37.0757],"type":"Point"}
}