{
  "type": "Feature",
  "properties": {
    "gn:admin1_code":"16.0",
    "gn:asciiname":"Ullyong-ni",
    "gn:cc2":"KR",
    "gn:country_code":"KR",
    "gn:dem":151,
    "gn:feature_class":"P",
    "gn:feature_code":"PPL",
    "gn:name":"Ullyong-ni",
    "gn:population":0,
    "gn:timezone":"Asia/Seoul",
    "iso:country":"KR",
    "name:eng_x_preferred":[
        "Ullyong"
    ],
    "name:eng_x_variant":[
        "Ullyong-ni"
    ],
    "name:und_x_variant":[
        "Unyong-ni",
        "Ullyong-ni"
    ],
    "wof:name":"Ullyong",
    "wof:placetype":"locality"
},
  "geometry": {"coordinates":[127.20305999999999,35.09389],"type":"Point"}
}