{
  "type": "Feature",
  "properties": {
    "gn:admin1_code":"6.0",
    "gn:asciiname":"T'ok-kol",
    "gn:country_code":"KR",
    "gn:dem":794,
    "gn:feature_class":"P",
    "gn:feature_code":"PPL",
    "gn:name":"T\u2019\u014fk-kol",
    "gn:population":0,
    "gn:timezone":"Asia/Seoul",
    "iso:country":"KR",
    "name:kor_x_preferred":[
        "\ud131\uace8"
    ],
    "name:kor_x_variant":[
        "T\u2019\u014fk-kol"
    ],
    "wof:name":"T'ok-kol",
    "wof:placetype":"locality"
},
  "geometry": {"coordinates":[128.917,37.2897],"type":"Point"}
}