{
  "type": "Feature",
  "properties": {
    "gn:admin1_code":"17.0",
    "gn:asciiname":"Hu-dong",
    "gn:country_code":"KR",
    "gn:dem":60,
    "gn:feature_class":"P",
    "gn:feature_code":"PPL",
    "gn:name":"Hu-dong",
    "gn:population":0,
    "gn:timezone":"Asia/Seoul",
    "iso:country":"KR",
    "name:und_x_variant":[
        "\ud6c4\ub3d9",
        "Hu-dong"
    ],
    "wof:name":"Hu-dong",
    "wof:placetype":"locality"
},
  "geometry": {"coordinates":[126.943,36.4266],"type":"Point"}
}