{
  "type": "Feature",
  "properties": {
    "gn:admin1_code":"14.0",
    "gn:asciiname":"Baengnokdong",
    "gn:country_code":"KR",
    "gn:dem":383,
    "gn:feature_class":"P",
    "gn:feature_code":"PPL",
    "gn:name":"Baengnokdong",
    "gn:population":0,
    "gn:timezone":"Asia/Seoul",
    "iso:country":"KR",
    "name:kor_x_preferred":[
        "\ubc31\ub85d\ub3d9"
    ],
    "wof:name":"Baengnokdong",
    "wof:placetype":"locality"
},
  "geometry": {"coordinates":[128.62532999999999,35.72827],"type":"Point"}
}