{
  "type": "Feature",
  "properties": {
    "gn:admin1_code":"14.0",
    "gn:asciiname":"Wolp'yong",
    "gn:country_code":"KR",
    "gn:dem":140,
    "gn:feature_class":"P",
    "gn:feature_code":"PPL",
    "gn:name":"W\u014flp\u2019y\u014fng",
    "gn:population":0,
    "gn:timezone":"Asia/Seoul",
    "iso:country":"KR",
    "name:und_x_variant":[
        "\uc6d4\ud3c9",
        "W\u014flp\u2019y\u014fng"
    ],
    "wof:name":"Wolp'yong",
    "wof:placetype":"locality"
},
  "geometry": {"coordinates":[128.79640000000001,36.3055],"type":"Point"}
}