{
  "type": "Feature",
  "properties": {
    "gn:admin1_code":"6.0",
    "gn:asciiname":"Yok-kol",
    "gn:country_code":"KR",
    "gn:dem":235,
    "gn:feature_class":"P",
    "gn:feature_code":"PPL",
    "gn:name":"Y\u014fk-kol",
    "gn:population":0,
    "gn:timezone":"Asia/Seoul",
    "iso:country":"KR",
    "name:kor_x_preferred":[
        "\uc5ed\uace8"
    ],
    "name:kor_x_variant":[
        "Y\u014fk-kol"
    ],
    "wof:name":"Yok-kol",
    "wof:placetype":"locality"
},
  "geometry": {"coordinates":[128.07216,37.442],"type":"Point"}
}