{
  "type": "Feature",
  "properties": {
    "gn:admin1_code":"16.0",
    "gn:asciiname":"Anyangdong",
    "gn:country_code":"KR",
    "gn:dem":39,
    "gn:feature_class":"P",
    "gn:feature_code":"PPL",
    "gn:name":"Anyangdong",
    "gn:population":0,
    "gn:timezone":"Asia/Seoul",
    "iso:country":"KR",
    "name:kor_x_preferred":[
        "\uc548\uc591\ub3d9"
    ],
    "wof:name":"Anyangdong",
    "wof:placetype":"locality"
},
  "geometry": {"coordinates":[127.59111,34.68979],"type":"Point"}
}