{
  "type": "Feature",
  "properties": {
    "gn:admin1_code":"16.0",
    "gn:asciiname":"Taesingol",
    "gn:country_code":"KR",
    "gn:dem":26,
    "gn:feature_class":"P",
    "gn:feature_code":"PPL",
    "gn:name":"Taesingol",
    "gn:population":0,
    "gn:timezone":"Asia/Seoul",
    "iso:country":"KR",
    "name:kor_x_preferred":[
        "\ud0dc\uc2e0\uace8"
    ],
    "wof:name":"Taesingol",
    "wof:placetype":"locality"
},
  "geometry": {"coordinates":[126.75533,34.98363],"type":"Point"}
}