{
  "type": "Feature",
  "properties": {
    "gn:admin1_code":"14.0",
    "gn:asciiname":"Hangsil",
    "gn:country_code":"KR",
    "gn:dem":83,
    "gn:feature_class":"P",
    "gn:feature_code":"PPL",
    "gn:name":"Hangsil",
    "gn:population":0,
    "gn:timezone":"Asia/Seoul",
    "iso:country":"KR",
    "name:und_x_variant":[
        "\ud56d\uc2e4",
        "Hangsil"
    ],
    "wof:name":"Hangsil",
    "wof:placetype":"locality"
},
  "geometry": {"coordinates":[129.398,36.8773],"type":"Point"}
}