{
  "type": "Feature",
  "properties": {
    "gn:admin1_code":"14.0",
    "gn:asciiname":"Sabak-kol",
    "gn:cc2":"KR",
    "gn:country_code":"KR",
    "gn:dem":114,
    "gn:feature_class":"P",
    "gn:feature_code":"PPL",
    "gn:name":"Sabak-kol",
    "gn:population":0,
    "gn:timezone":"Asia/Seoul",
    "iso:country":"KR",
    "name:und_x_variant":[
        "Saba-kol",
        "Sabang-ni",
        "Saba-gol",
        "Sabak-kol"
    ],
    "wof:name":"Sabak-kol",
    "wof:placetype":"locality"
},
  "geometry": {"coordinates":[129.15638999999999,35.97194000000001],"type":"Point"}
}