{
  "type": "Feature",
  "properties": {
    "gn:admin1_code":"17.0",
    "gn:asciiname":"Eumdalli",
    "gn:country_code":"KR",
    "gn:dem":127,
    "gn:feature_class":"P",
    "gn:feature_code":"PPL",
    "gn:name":"Eumdalli",
    "gn:population":0,
    "gn:timezone":"Asia/Seoul",
    "iso:country":"KR",
    "name:und_x_variant":[
        "\uc74c\ub2ec\ub9ac",
        "\u016cmdal-li",
        "Eumdalli"
    ],
    "wof:name":"Eumdalli",
    "wof:placetype":"locality"
},
  "geometry": {"coordinates":[127.26714,36.24897],"type":"Point"}
}