{
  "type": "Feature",
  "properties": {
    "gn:admin1_code":"20.0",
    "gn:asciiname":"Kyo-dong",
    "gn:cc2":"KR",
    "gn:country_code":"KR",
    "gn:dem":39,
    "gn:feature_class":"P",
    "gn:feature_code":"PPL",
    "gn:name":"Kyo-dong",
    "gn:population":0,
    "gn:timezone":"Asia/Seoul",
    "iso:country":"KR",
    "name:und_x_variant":[
        "Kyo-ri",
        "Kyo-dong"
    ],
    "wof:name":"Kyo-dong",
    "wof:placetype":"locality"
},
  "geometry": {"coordinates":[129.02306000000002,35.34083],"type":"Point"}
}