{
  "type": "Feature",
  "properties": {
    "gn:admin1_code":"12.0",
    "gn:asciiname":"Changmal",
    "gn:country_code":"KR",
    "gn:dem":22,
    "gn:feature_class":"P",
    "gn:feature_code":"PPL",
    "gn:name":"Changmal",
    "gn:population":0,
    "gn:timezone":"Asia/Seoul",
    "iso:country":"KR",
    "name:und_x_variant":[
        "\ucc3d\ub9d0",
        "Changmal",
        "Ch\u2019ang-mal"
    ],
    "wof:name":"Changmal",
    "wof:placetype":"locality"
},
  "geometry": {"coordinates":[126.31453999999999,37.73799],"type":"Point"}
}