{
  "type": "Feature",
  "properties": {
    "gn:admin1_code":"16.0",
    "gn:asciiname":"Songi-ri",
    "gn:country_code":"KR",
    "gn:dem":112,
    "gn:feature_class":"P",
    "gn:feature_code":"PPL",
    "gn:name":"Songi-ri",
    "gn:population":0,
    "gn:timezone":"Asia/Seoul",
    "iso:country":"KR",
    "wof:name":"Songi-ri",
    "wof:placetype":"locality"
},
  "geometry": {"coordinates":[126.14306000000001,35.28861],"type":"Point"}
}