{
  "type": "Feature",
  "properties": {
    "iso:country":"KR",
    "qs:name":"\uace0\ud765\uc74d",
    "qs:name_adm0":"\ud55c\uad6d",
    "qs:name_adm1":"\uc804\ub77c\ub0a8\ub3c4",
    "qs:photos":2,
    "qs:photos_1k":1,
    "qs:photos_9k":1,
    "qs:photos_9r":1,
    "qs:photos_all":2,
    "qs:photos_sr":1,
    "qs:placetype":"LocalAdmin",
    "qs:pop_sr":"0",
    "wof:name":"\uace0\ud765\uc74d",
    "wof:placetype":"localadmin"
},
  "geometry": {"coordinates":[127.12520499999999,34.510093],"type":"Point"}
}