{
  "type": "Feature",
  "properties": {
    "gn:admin1_code":"11.0",
    "gn:asciiname":"Samjon-dong",
    "gn:country_code":"KR",
    "gn:dem":20,
    "gn:feature_class":"P",
    "gn:feature_code":"PPL",
    "gn:name":"Samj\u014fn-dong",
    "gn:population":0,
    "gn:timezone":"Asia/Seoul",
    "iso:country":"KR",
    "name:und_x_variant":[
        "\uc0bc\uc804\ub3d9",
        "Samj\u014fn-dong"
    ],
    "wof:name":"Samjon-dong",
    "wof:placetype":"locality"
},
  "geometry": {"coordinates":[127.0924,37.5053],"type":"Point"}
}