{
  "type": "Feature",
  "properties": {
    "gn:admin1_code":"13.0",
    "gn:asciiname":"Sagijeom",
    "gn:country_code":"KR",
    "gn:dem":118,
    "gn:feature_class":"P",
    "gn:feature_code":"PPL",
    "gn:name":"Sagijeom",
    "gn:population":0,
    "gn:timezone":"Asia/Seoul",
    "iso:country":"KR",
    "name:kor_x_preferred":[
        "\uc0ac\uae30\uc810"
    ],
    "name:und_x_variant":[
        "Sagij\u014fm"
    ],
    "wof:name":"Sagijeom",
    "wof:placetype":"locality"
},
  "geometry": {"coordinates":[127.26253,37.94753],"type":"Point"}
}