{
  "type": "Feature",
  "properties": {
    "gn:admin1_code":"5.0",
    "gn:asciiname":"Okpak-kol",
    "gn:country_code":"KR",
    "gn:dem":114,
    "gn:feature_class":"P",
    "gn:feature_code":"PPL",
    "gn:name":"Okpak-kol",
    "gn:population":0,
    "gn:timezone":"Asia/Seoul",
    "iso:country":"KR",
    "name:und_x_variant":[
        "\uc625\ubc15\uace8",
        "Okpak-kol"
    ],
    "wof:name":"Okpak-kol",
    "wof:placetype":"locality"
},
  "geometry": {"coordinates":[127.6831,36.3262],"type":"Point"}
}