{
  "type": "Feature",
  "properties": {
    "gn:admin1_code":"6.0",
    "gn:asciiname":"Pyongsan",
    "gn:country_code":"KR",
    "gn:dem":339,
    "gn:feature_class":"P",
    "gn:feature_code":"PPL",
    "gn:name":"Py\u014fngsan",
    "gn:population":0,
    "gn:timezone":"Asia/Seoul",
    "iso:country":"KR",
    "name:kor_x_preferred":[
        "\ubcd1\uc0b0"
    ],
    "name:kor_x_variant":[
        "Py\u014fngsan"
    ],
    "wof:name":"Pyongsan",
    "wof:placetype":"locality"
},
  "geometry": {"coordinates":[128.59479999999999,37.2445],"type":"Point"}
}