{
  "type": "Feature",
  "properties": {
    "gn:admin1_code":"6.0",
    "gn:asciiname":"Tumok",
    "gn:country_code":"KR",
    "gn:dem":587,
    "gn:feature_class":"P",
    "gn:feature_code":"PPL",
    "gn:name":"Tumok",
    "gn:population":0,
    "gn:timezone":"Asia/Seoul",
    "iso:country":"KR",
    "name:und_x_variant":[
        "Dumog",
        "Dumok",
        "Tumok"
    ],
    "wof:name":"Tumok",
    "wof:placetype":"locality"
},
  "geometry": {"coordinates":[127.59972,38.30361],"type":"Point"}
}