{
  "type": "Feature",
  "properties": {
    "gn:admin1_code":"20.0",
    "gn:asciiname":"Yonggung",
    "gn:country_code":"KR",
    "gn:dem":201,
    "gn:feature_class":"P",
    "gn:feature_code":"PPL",
    "gn:name":"Yonggung",
    "gn:population":0,
    "gn:timezone":"Asia/Seoul",
    "iso:country":"KR",
    "name:und_x_variant":[
        "\uc6a9\uad81",
        "Yonggung"
    ],
    "wof:name":"Yonggung",
    "wof:placetype":"locality"
},
  "geometry": {"coordinates":[128.28923999999998,35.10227],"type":"Point"}
}