{
  "type": "Feature",
  "properties": {
    "gn:admin1_code":"16.0",
    "gn:asciiname":"Chung-ni",
    "gn:country_code":"KR",
    "gn:dem":16,
    "gn:feature_class":"P",
    "gn:feature_code":"PPL",
    "gn:name":"Chung-ni",
    "gn:population":0,
    "gn:timezone":"Asia/Seoul",
    "iso:country":"KR",
    "name:kor_x_preferred":[
        "\uc911\ub9ac"
    ],
    "wof:name":"Chung-ni",
    "wof:placetype":"locality"
},
  "geometry": {"coordinates":[126.59417000000001,34.16444],"type":"Point"}
}