{
  "type": "Feature",
  "properties": {
    "gn:admin1_code":"0.0",
    "gn:asciiname":"Tuji",
    "gn:cc2":"KR",
    "gn:country_code":"KR",
    "gn:dem":71,
    "gn:feature_class":"P",
    "gn:feature_code":"PPL",
    "gn:name":"Tuji",
    "gn:population":0,
    "gn:timezone":"Asia/Seoul",
    "iso:country":"KR",
    "name:und_x_variant":[
        "Tuji-dong",
        "Tuji"
    ],
    "wof:name":"Tuji",
    "wof:placetype":"locality"
},
  "geometry": {"coordinates":[127.25,35.11667],"type":"Point"}
}