{
  "type": "Feature",
  "properties": {
    "gn:admin1_code":"5.0",
    "gn:asciiname":"Araepaso",
    "gn:country_code":"KR",
    "gn:dem":181,
    "gn:feature_class":"P",
    "gn:feature_code":"PPL",
    "gn:name":"Araepaso",
    "gn:population":0,
    "gn:timezone":"Asia/Seoul",
    "iso:country":"KR",
    "name:kor_x_preferred":[
        "\uc544\ub798\ud30c\uc18c"
    ],
    "name:kor_x_variant":[
        "P\u2019aso"
    ],
    "wof:name":"Araepaso",
    "wof:placetype":"locality"
},
  "geometry": {"coordinates":[127.84658,36.93746],"type":"Point"}
}