{
  "type": "Feature",
  "properties": {
    "gn:admin1_code":"14.0",
    "gn:asciiname":"Byeollae",
    "gn:country_code":"KR",
    "gn:dem":83,
    "gn:feature_class":"P",
    "gn:feature_code":"PPL",
    "gn:name":"Byeollae",
    "gn:population":0,
    "gn:timezone":"Asia/Seoul",
    "iso:country":"KR",
    "name:kor_x_preferred":[
        "\ubcc4\ub0b4"
    ],
    "wof:name":"Byeollae",
    "wof:placetype":"locality"
},
  "geometry": {"coordinates":[129.22071,35.74257],"type":"Point"}
}