{
  "type": "Feature",
  "properties": {
    "gn:admin1_code":"6.0",
    "gn:asciiname":"Matpawi",
    "gn:country_code":"KR",
    "gn:dem":248,
    "gn:feature_class":"P",
    "gn:feature_code":"PPL",
    "gn:name":"Matpawi",
    "gn:population":0,
    "gn:timezone":"Asia/Seoul",
    "iso:country":"KR",
    "name:und_x_variant":[
        "\ub9de\ubc14\uc704",
        "Mappawi"
    ],
    "wof:name":"Matpawi",
    "wof:placetype":"locality"
},
  "geometry": {"coordinates":[127.97866,37.69684],"type":"Point"}
}