{
  "type": "Feature",
  "properties": {
    "gn:admin1_code":"5.0",
    "gn:asciiname":"Neutijaengi",
    "gn:country_code":"KR",
    "gn:dem":308,
    "gn:feature_class":"P",
    "gn:feature_code":"PPL",
    "gn:name":"Neutijaengi",
    "gn:population":0,
    "gn:timezone":"Asia/Seoul",
    "iso:country":"KR",
    "name:kor_x_preferred":[
        "\ub290\ud2f0\uc7c1\uc774"
    ],
    "wof:name":"Neutijaengi",
    "wof:placetype":"locality"
},
  "geometry": {"coordinates":[128.35173999999998,36.95819],"type":"Point"}
}