{
  "type": "Feature",
  "properties": {
    "gn:admin1_code":"14.0",
    "gn:asciiname":"Dwitteulmal",
    "gn:country_code":"KR",
    "gn:dem":51,
    "gn:feature_class":"P",
    "gn:feature_code":"PPL",
    "gn:name":"Dwitteulmal",
    "gn:population":0,
    "gn:timezone":"Asia/Seoul",
    "iso:country":"KR",
    "name:kor_x_preferred":[
        "\ub4a4\ub730\ub9d0"
    ],
    "wof:name":"Dwitteulmal",
    "wof:placetype":"locality"
},
  "geometry": {"coordinates":[129.20553000000001,35.79789],"type":"Point"}
}