{
  "type": "Feature",
  "properties": {
    "gn:admin1_code":"16.0",
    "gn:asciiname":"Jusan",
    "gn:country_code":"KR",
    "gn:dem":135,
    "gn:feature_class":"P",
    "gn:feature_code":"PPL",
    "gn:name":"Jusan",
    "gn:population":0,
    "gn:timezone":"Asia/Seoul",
    "iso:country":"KR",
    "name:kor_x_preferred":[
        "\uc8fc\uc0b0"
    ],
    "name:und_x_variant":[
        "Chusan",
        "Jusan"
    ],
    "wof:name":"Jusan",
    "wof:placetype":"locality"
},
  "geometry": {"coordinates":[127.14491,34.9811],"type":"Point"}
}