{
  "type": "Feature",
  "properties": {
    "gn:admin1_code":"6.0",
    "gn:asciiname":"Anggeumbadi",
    "gn:country_code":"KR",
    "gn:dem":376,
    "gn:feature_class":"P",
    "gn:feature_code":"PPL",
    "gn:name":"Anggeumbadi",
    "gn:population":0,
    "gn:timezone":"Asia/Seoul",
    "iso:country":"KR",
    "name:kor_x_preferred":[
        "\uc559\uae08\ubc1b\uc774"
    ],
    "name:und_x_variant":[
        "Angg\u016dmbat",
        "\uc559\uae08\ubc2d",
        "Anggeumbadi"
    ],
    "wof:name":"Anggeumbadi",
    "wof:placetype":"locality"
},
  "geometry": {"coordinates":[128.13403,38.14158],"type":"Point"}
}