{
  "type": "Feature",
  "properties": {
    "gn:admin1_code":"18.0",
    "gn:asciiname":"Banwolchon",
    "gn:country_code":"KR",
    "gn:dem":17,
    "gn:feature_class":"P",
    "gn:feature_code":"PPL",
    "gn:name":"Banwolchon",
    "gn:population":0,
    "gn:timezone":"Asia/Seoul",
    "iso:country":"KR",
    "name:kor_x_preferred":[
        "\ubc18\uc6d4\ucd0c"
    ],
    "wof:name":"Banwolchon",
    "wof:placetype":"locality"
},
  "geometry": {"coordinates":[126.82051,35.05825],"type":"Point"}
}