{
  "type": "Feature",
  "properties": {
    "gn:admin1_code":"14.0",
    "gn:asciiname":"Ansasan",
    "gn:country_code":"KR",
    "gn:dem":40,
    "gn:feature_class":"P",
    "gn:feature_code":"PPL",
    "gn:name":"Ansasan",
    "gn:population":0,
    "gn:timezone":"Asia/Seoul",
    "iso:country":"KR",
    "name:und_x_variant":[
        "\uc548\uc0ac\uc0b0",
        "Ansasan"
    ],
    "wof:name":"Ansasan",
    "wof:placetype":"locality"
},
  "geometry": {"coordinates":[129.22936999999999,36.06318],"type":"Point"}
}