{
  "type": "Feature",
  "properties": {
    "gn:admin1_code":"14.0",
    "gn:asciiname":"Sangchon",
    "gn:country_code":"KR",
    "gn:dem":206,
    "gn:feature_class":"P",
    "gn:feature_code":"PPL",
    "gn:name":"Sangchon",
    "gn:population":0,
    "gn:timezone":"Asia/Seoul",
    "iso:country":"KR",
    "name:kor_x_preferred":[
        "\uc0c1\ucd0c"
    ],
    "name:und_x_variant":[
        "Chung-ma\u016dl"
    ],
    "wof:name":"Sangchon",
    "wof:placetype":"locality"
},
  "geometry": {"coordinates":[128.82383000000002,36.75081],"type":"Point"}
}