{
  "type": "Feature",
  "properties": {
    "gn:admin1_code":"6.0",
    "gn:asciiname":"Migu",
    "gn:country_code":"KR",
    "gn:dem":415,
    "gn:feature_class":"P",
    "gn:feature_code":"PPL",
    "gn:name":"Migu",
    "gn:population":0,
    "gn:timezone":"Asia/Seoul",
    "iso:country":"KR",
    "name:heb_x_preferred":[
        "\u05de\u05d9\u05d2\u05d5"
    ],
    "name:kor_x_preferred":[
        "\ubbf8\uad6c"
    ],
    "wof:name":"Migu",
    "wof:placetype":"locality"
},
  "geometry": {"coordinates":[128.5856,37.2106],"type":"Point"}
}