{
  "type": "Feature",
  "properties": {
    "gn:admin1_code":"0.0",
    "gn:asciiname":"Ondong",
    "gn:cc2":"KR",
    "gn:country_code":"KR",
    "gn:dem":-9999,
    "gn:feature_class":"P",
    "gn:feature_code":"PPL",
    "gn:name":"Ondong",
    "gn:population":0,
    "gn:timezone":"Asia/Seoul",
    "iso:country":"KR",
    "name:und_x_variant":[
        "Onsekiho",
        "Ontoruho",
        "Ondolgae",
        "Ondolp\u2019o",
        "Ondong"
    ],
    "wof:name":"Ondong",
    "wof:placetype":"locality"
},
  "geometry": {"coordinates":[127.73333,34.88333],"type":"Point"}
}