{
  "type": "Feature",
  "properties": {
    "gn:admin1_code":"17.0",
    "gn:asciiname":"Tarasil",
    "gn:country_code":"KR",
    "gn:dem":16,
    "gn:feature_class":"P",
    "gn:feature_code":"PPL",
    "gn:name":"Tarasil",
    "gn:population":0,
    "gn:timezone":"Asia/Seoul",
    "iso:country":"KR",
    "name:und_x_variant":[
        "W\u014flgong-ni",
        "\ub2ec\uc544\uc2e4",
        "Tarasil"
    ],
    "wof:name":"Tarasil",
    "wof:placetype":"locality"
},
  "geometry": {"coordinates":[126.7448,36.9557],"type":"Point"}
}