{
  "type": "Feature",
  "properties": {
    "gn:admin1_code":"6.0",
    "gn:asciiname":"Muae",
    "gn:country_code":"KR",
    "gn:dem":339,
    "gn:feature_class":"P",
    "gn:feature_code":"PPL",
    "gn:name":"Muae",
    "gn:population":0,
    "gn:timezone":"Asia/Seoul",
    "iso:country":"KR",
    "name:kor_x_preferred":[
        "\ubb34\uc560"
    ],
    "wof:name":"Muae",
    "wof:placetype":"locality"
},
  "geometry": {"coordinates":[127.97359,37.93269],"type":"Point"}
}