{
  "type": "Feature",
  "properties": {
    "gn:admin1_code":"6.0",
    "gn:admin2_code":"32020",
    "gn:asciiname":"Munmak",
    "gn:country_code":"KR",
    "gn:dem":75,
    "gn:feature_class":"P",
    "gn:feature_code":"PPL",
    "gn:name":"Munmak",
    "gn:population":0,
    "gn:timezone":"Asia/Seoul",
    "iso:country":"KR",
    "name:kor_x_preferred":[
        "\ubb38\ub9c9"
    ],
    "name:und_x_variant":[
        "Bummaku-ri",
        "Munmang-ni",
        "Bunmakuri",
        "Munmak"
    ],
    "wof:name":"Munmak",
    "wof:placetype":"locality"
},
  "geometry": {"coordinates":[127.8188,37.3113],"type":"Point"}
}