{
  "type": "Feature",
  "properties": {
    "gn:admin1_code":"11.0",
    "gn:asciiname":"Bangogae",
    "gn:country_code":"KR",
    "gn:dem":24,
    "gn:feature_class":"P",
    "gn:feature_code":"PPL",
    "gn:name":"Bangogae",
    "gn:population":0,
    "gn:timezone":"Asia/Seoul",
    "iso:country":"KR",
    "name:kor_x_preferred":[
        "\ubc18\uace0\uac1c"
    ],
    "name:und_x_variant":[
        "\ubc24\uace0\uac1c",
        "Bamgogae",
        "Pamgogae",
        "Bangogae"
    ],
    "wof:name":"Bangogae",
    "wof:placetype":"locality"
},
  "geometry": {"coordinates":[127.10643,37.46352],"type":"Point"}
}