{
  "type": "Feature",
  "properties": {
    "gn:admin1_code":"14.0",
    "gn:asciiname":"Sinyang",
    "gn:country_code":"KR",
    "gn:dem":45,
    "gn:feature_class":"P",
    "gn:feature_code":"PPL",
    "gn:name":"Sinyang",
    "gn:population":0,
    "gn:timezone":"Asia/Seoul",
    "iso:country":"KR",
    "name:kor_x_preferred":[
        "\uc2e0\uc591"
    ],
    "name:nor_x_preferred":[
        "Sinyang"
    ],
    "name:und_x_variant":[
        "Sinyang-dong"
    ],
    "wof:name":"Sinyang",
    "wof:placetype":"locality"
},
  "geometry": {"coordinates":[129.30531999999999,36.43088],"type":"Point"}
}