{
  "type": "Feature",
  "properties": {
    "gn:admin1_code":"16.0",
    "gn:asciiname":"Donggu-ri",
    "gn:country_code":"KR",
    "gn:dem":338,
    "gn:feature_class":"P",
    "gn:feature_code":"PPL",
    "gn:name":"Donggu-ri",
    "gn:population":0,
    "gn:timezone":"Asia/Seoul",
    "iso:country":"KR",
    "name:kor_x_preferred":[
        "\ub3d9\uad6c\ub9ac"
    ],
    "name:und_x_variant":[
        "Tonggu-ri",
        "Tonggu",
        "Donggu-ri"
    ],
    "wof:name":"Donggu-ri",
    "wof:placetype":"locality"
},
  "geometry": {"coordinates":[126.99024,35.08411],"type":"Point"}
}