{
  "type": "Feature",
  "properties": {
    "iso:country":"KR",
    "name:kor_x_preferred":[
        "\uc218\uc601\ub3d9"
    ],
    "name:und_x_variant":[
        "Yongdong-ni"
    ],
    "qs:gn_adm0_cc":"KR",
    "qs:gn_fcode":"PPL",
    "qs:gn_local":1838524,
    "qs:gn_namadm1":"20",
    "qs:gn_name":"Yongdong",
    "qs:local_max":2765,
    "qs:local_sum":24552,
    "qs:localhoods":60,
    "qs:name":"\uc218\uc601\ub3d9",
    "qs:name_adm0":"\ud55c\uad6d",
    "qs:name_adm1":"\ubd80\uc0b0",
    "qs:name_adm2":"\uc218\uc601\uad6c",
    "qs:name_lau":"\uc218\uc601\ub3d9",
    "qs:name_local":"\ubd80\uc0b0",
    "qs:photo_max":30,
    "qs:photo_sum":94,
    "qs:placetype":"Suburb",
    "qs:quad_count":11,
    "qs:woe_adm0":23424868,
    "qs:woe_adm1":2345968,
    "qs:woe_adm2":28289298,
    "qs:woe_lau":28806136,
    "qs:woe_local":1132447,
    "qs:woe_ver":"7.10.0",
    "wof:lang":[
        "kor"
    ],
    "wof:name":"\uc218\uc601\ub3d9",
    "wof:placetype":"neighbourhood"
},
  "geometry": {"coordinates":[129.119338,35.174161],"type":"Point"}
}