{
  "type": "Feature",
  "properties": {
    "gn:admin1_code":"16.0",
    "gn:asciiname":"Songhak",
    "gn:country_code":"KR",
    "gn:dem":318,
    "gn:feature_class":"P",
    "gn:feature_code":"PPL",
    "gn:name":"Songhak",
    "gn:population":0,
    "gn:timezone":"Asia/Seoul",
    "iso:country":"KR",
    "name:kor_x_preferred":[
        "\uc1a1\ud559"
    ],
    "wof:name":"Songhak",
    "wof:placetype":"locality"
},
  "geometry": {"coordinates":[127.41540999999999,34.98157],"type":"Point"}
}