{
  "type": "Feature",
  "properties": {
    "gn:admin1_code":"14.0",
    "gn:asciiname":"Tenson",
    "gn:country_code":"KR",
    "gn:dem":180,
    "gn:feature_class":"P",
    "gn:feature_code":"PPL",
    "gn:name":"Tenson",
    "gn:population":0,
    "gn:timezone":"Asia/Seoul",
    "iso:country":"KR",
    "name:und_x_variant":[
        "\uc810\ucd0c",
        "Ch\u014fm-ch\u2019on"
    ],
    "wof:name":"Tenson",
    "wof:placetype":"locality"
},
  "geometry": {"coordinates":[128.3229,36.0417],"type":"Point"}
}