{
  "type": "Feature",
  "properties": {
    "gn:admin1_code":"6.0",
    "gn:asciiname":"Ahopsa-ri",
    "gn:country_code":"KR",
    "gn:dem":347,
    "gn:feature_class":"P",
    "gn:feature_code":"PPL",
    "gn:name":"Ahopsa-ri",
    "gn:population":0,
    "gn:timezone":"Asia/Seoul",
    "iso:country":"KR",
    "name:kor_x_preferred":[
        "\uc544\ud649\uc0ac\ub9ac"
    ],
    "name:und_x_variant":[
        "Kusa-ri",
        "Ahopsa-ri"
    ],
    "wof:name":"Ahopsa-ri",
    "wof:placetype":"locality"
},
  "geometry": {"coordinates":[128.14439999999999,37.5469],"type":"Point"}
}