{
  "type": "Feature",
  "properties": {
    "gn:admin1_code":"17.0",
    "gn:asciiname":"Milmu",
    "gn:country_code":"KR",
    "gn:dem":208,
    "gn:feature_class":"P",
    "gn:feature_code":"PPL",
    "gn:name":"Milmu",
    "gn:population":0,
    "gn:timezone":"Asia/Seoul",
    "iso:country":"KR",
    "name:und_x_variant":[
        "S\u014fngsan",
        "\uc131\uc0b0"
    ],
    "wof:name":"Milmu",
    "wof:placetype":"locality"
},
  "geometry": {"coordinates":[127.4522,36.0312],"type":"Point"}
}