{
  "type": "Feature",
  "properties": {
    "gn:admin1_code":"16.0",
    "gn:asciiname":"Yeongjeong",
    "gn:country_code":"KR",
    "gn:dem":67,
    "gn:feature_class":"P",
    "gn:feature_code":"PPL",
    "gn:name":"Yeongjeong",
    "gn:population":0,
    "gn:timezone":"Asia/Seoul",
    "iso:country":"KR",
    "name:kor_x_preferred":[
        "\uc601\uc815"
    ],
    "wof:name":"Yeongjeong",
    "wof:placetype":"locality"
},
  "geometry": {"coordinates":[126.65237,35.04985],"type":"Point"}
}