{
  "type": "Feature",
  "properties": {
    "gn:admin1_code":"5.0",
    "gn:asciiname":"Saegeori",
    "gn:country_code":"KR",
    "gn:dem":102,
    "gn:feature_class":"P",
    "gn:feature_code":"PPL",
    "gn:name":"Saegeori",
    "gn:population":0,
    "gn:timezone":"Asia/Seoul",
    "iso:country":"KR",
    "name:und_x_variant":[
        "\uc0c8\uac70\ub9ac",
        "Saeg\u014f-ri",
        "Saegeori"
    ],
    "wof:name":"Saegeori",
    "wof:placetype":"locality"
},
  "geometry": {"coordinates":[127.53807,36.38206],"type":"Point"}
}