{
  "type": "Feature",
  "properties": {
    "gn:admin1_code":"13.0",
    "gn:asciiname":"Jeonjimi",
    "gn:country_code":"KR",
    "gn:dem":26,
    "gn:feature_class":"P",
    "gn:feature_code":"PPL",
    "gn:name":"Jeonjimi",
    "gn:population":0,
    "gn:timezone":"Asia/Seoul",
    "iso:country":"KR",
    "name:kor_x_preferred":[
        "\uc804\uc9c0\ubbf8"
    ],
    "wof:name":"Jeonjimi",
    "wof:placetype":"locality"
},
  "geometry": {"coordinates":[126.81909,37.76846],"type":"Point"}
}