{
  "type": "Feature",
  "properties": {
    "gn:admin1_code":"14.0",
    "gn:asciiname":"Ttanggol",
    "gn:country_code":"KR",
    "gn:dem":183,
    "gn:feature_class":"P",
    "gn:feature_code":"PPL",
    "gn:name":"Ttanggol",
    "gn:population":0,
    "gn:timezone":"Asia/Seoul",
    "iso:country":"KR",
    "name:kor_x_preferred":[
        "\ub545\uace8"
    ],
    "wof:name":"Ttanggol",
    "wof:placetype":"locality"
},
  "geometry": {"coordinates":[128.83876999999998,36.07267],"type":"Point"}
}