{
  "type": "Feature",
  "properties": {
    "gn:admin1_code":"6.0",
    "gn:asciiname":"Ch'ongduru",
    "gn:country_code":"KR",
    "gn:dem":297,
    "gn:feature_class":"P",
    "gn:feature_code":"PPL",
    "gn:name":"Ch\u2019\u014fngduru",
    "gn:population":0,
    "gn:timezone":"Asia/Seoul",
    "iso:country":"KR",
    "name:kor_x_preferred":[
        "\uccad\ub450\ub8e8"
    ],
    "name:kor_x_variant":[
        "Ch\u2019\u014fngduru"
    ],
    "wof:name":"Ch'ongduru",
    "wof:placetype":"locality"
},
  "geometry": {"coordinates":[128.18389999999999,37.5838],"type":"Point"}
}