{
  "type": "Feature",
  "properties": {
    "gn:admin1_code":"14.0",
    "gn:asciiname":"Jegunggol",
    "gn:country_code":"KR",
    "gn:dem":110,
    "gn:feature_class":"P",
    "gn:feature_code":"PPL",
    "gn:name":"Jegunggol",
    "gn:population":0,
    "gn:timezone":"Asia/Seoul",
    "iso:country":"KR",
    "name:kor_x_preferred":[
        "\uc81c\uad81\uace8"
    ],
    "wof:name":"Jegunggol",
    "wof:placetype":"locality"
},
  "geometry": {"coordinates":[128.23353999999998,36.55385],"type":"Point"}
}