{
  "type": "Feature",
  "properties": {
    "gn:admin1_code":"16.0",
    "gn:asciiname":"Sokkyo-ri",
    "gn:country_code":"KR",
    "gn:dem":28,
    "gn:feature_class":"P",
    "gn:feature_code":"PPL",
    "gn:name":"S\u014fkkyo-ri",
    "gn:population":0,
    "gn:timezone":"Asia/Seoul",
    "iso:country":"KR",
    "name:kor_x_preferred":[
        "\uc11d\uad50\ub9ac"
    ],
    "name:kor_x_variant":[
        "S\u014fkkyo-ri"
    ],
    "name:und_x_variant":[
        "Sekky\u014d-ri",
        "S\u014fkkyo"
    ],
    "wof:name":"Sokkyo-ri",
    "wof:placetype":"locality"
},
  "geometry": {"coordinates":[126.81028000000001,34.63361],"type":"Point"}
}