{
  "type": "Feature",
  "properties": {
    "gn:admin1_code":"20.0",
    "gn:asciiname":"Mosi-gol",
    "gn:country_code":"KR",
    "gn:dem":54,
    "gn:feature_class":"P",
    "gn:feature_code":"PPL",
    "gn:name":"Mosi-gol",
    "gn:population":0,
    "gn:timezone":"Asia/Seoul",
    "iso:country":"KR",
    "name:und_x_variant":[
        "\ubaa8\uc2dc\uace8",
        "Mosi-gol"
    ],
    "wof:name":"Mosi-gol",
    "wof:placetype":"locality"
},
  "geometry": {"coordinates":[128.32432,35.16204],"type":"Point"}
}