{
  "type": "Feature",
  "properties": {
    "gn:admin1_code":"6.0",
    "gn:asciiname":"Wondang-ri",
    "gn:country_code":"KR",
    "gn:dem":280,
    "gn:feature_class":"P",
    "gn:feature_code":"PPL",
    "gn:name":"Wondang-ri",
    "gn:population":0,
    "gn:timezone":"Asia/Seoul",
    "iso:country":"KR",
    "name:kor_x_preferred":[
        "\uc6d0\ub2f9\ub9ac"
    ],
    "name:kor_x_variant":[
        "W\u014fndang-ni"
    ],
    "wof:name":"Wondang-ri",
    "wof:placetype":"locality"
},
  "geometry": {"coordinates":[128.04083,38.18611],"type":"Point"}
}