{
  "type": "Feature",
  "properties": {
    "gn:admin1_code":"5.0",
    "gn:asciiname":"Jinyak",
    "gn:country_code":"KR",
    "gn:dem":72,
    "gn:feature_class":"P",
    "gn:feature_code":"PPL",
    "gn:name":"Jinyak",
    "gn:population":0,
    "gn:timezone":"Asia/Seoul",
    "iso:country":"KR",
    "name:kor_x_preferred":[
        "\uc9c4\uc57d"
    ],
    "wof:name":"Jinyak",
    "wof:placetype":"locality"
},
  "geometry": {"coordinates":[127.40273999999999,36.62146],"type":"Point"}
}