{
  "type": "Feature",
  "properties": {
    "gn:admin1_code":"17.0",
    "gn:asciiname":"Taegungt'o",
    "gn:country_code":"KR",
    "gn:dem":22,
    "gn:feature_class":"P",
    "gn:feature_code":"PPL",
    "gn:name":"Taegungt\u2019\u014f",
    "gn:population":0,
    "gn:timezone":"Asia/Seoul",
    "iso:country":"KR",
    "name:und_x_variant":[
        "\ub300\uad81\ud130",
        "Taegungt\u2019\u014f"
    ],
    "wof:name":"Taegungt'o",
    "wof:placetype":"locality"
},
  "geometry": {"coordinates":[126.7944,36.2588],"type":"Point"}
}