{
  "type": "Feature",
  "properties": {
    "gn:admin1_code":"16.0",
    "gn:asciiname":"Wondong",
    "gn:country_code":"KR",
    "gn:dem":60,
    "gn:feature_class":"P",
    "gn:feature_code":"PPL",
    "gn:name":"Wondong",
    "gn:population":0,
    "gn:timezone":"Asia/Seoul",
    "iso:country":"KR",
    "name:kor_x_preferred":[
        "\uc6d0\ub3d9"
    ],
    "wof:name":"Wondong",
    "wof:placetype":"locality"
},
  "geometry": {"coordinates":[126.91023,35.03135],"type":"Point"}
}