{
  "type": "Feature",
  "properties": {
    "gn:admin1_code":"3.0",
    "gn:asciiname":"Pultang",
    "gn:country_code":"KR",
    "gn:dem":116,
    "gn:feature_class":"P",
    "gn:feature_code":"PPL",
    "gn:name":"Pultang",
    "gn:population":0,
    "gn:timezone":"Asia/Seoul",
    "iso:country":"KR",
    "name:und_x_variant":[
        "\ubd88\ub2f9",
        "Pultang"
    ],
    "wof:name":"Pultang",
    "wof:placetype":"locality"
},
  "geometry": {"coordinates":[127.1996,36.0184],"type":"Point"}
}