{
  "type": "Feature",
  "properties": {
    "gn:admin1_code":"14.0",
    "gn:asciiname":"Jangsari",
    "gn:country_code":"KR",
    "gn:dem":106,
    "gn:feature_class":"P",
    "gn:feature_code":"PPL",
    "gn:name":"Jangsari",
    "gn:population":0,
    "gn:timezone":"Asia/Seoul",
    "iso:country":"KR",
    "name:kor_x_preferred":[
        "\uc7a5\uc0ac\ub9ac"
    ],
    "wof:name":"Jangsari",
    "wof:placetype":"locality"
},
  "geometry": {"coordinates":[128.65422000000001,36.49763],"type":"Point"}
}