{
  "type": "Feature",
  "properties": {
    "gn:admin1_code":"14.0",
    "gn:asciiname":"Deobungol",
    "gn:country_code":"KR",
    "gn:dem":27,
    "gn:feature_class":"P",
    "gn:feature_code":"PPL",
    "gn:name":"Deobungol",
    "gn:population":0,
    "gn:timezone":"Asia/Seoul",
    "iso:country":"KR",
    "name:kor_x_preferred":[
        "\ub354\ubd84\uace8"
    ],
    "wof:name":"Deobungol",
    "wof:placetype":"locality"
},
  "geometry": {"coordinates":[128.41374999999999,35.91903],"type":"Point"}
}