{
  "type": "Feature",
  "properties": {
    "gn:admin1_code":"6.0",
    "gn:asciiname":"Chom-ch'on",
    "gn:country_code":"KR",
    "gn:dem":738,
    "gn:feature_class":"P",
    "gn:feature_code":"PPL",
    "gn:name":"Ch\u014fm-ch\u2019on",
    "gn:population":0,
    "gn:timezone":"Asia/Seoul",
    "iso:country":"KR",
    "name:kor_x_preferred":[
        "\uc810\ucd0c"
    ],
    "name:kor_x_variant":[
        "Ch\u014fm-ch\u2019on"
    ],
    "wof:name":"Chom-ch'on",
    "wof:placetype":"locality"
},
  "geometry": {"coordinates":[128.9922,37.3055],"type":"Point"}
}