{
  "type": "Feature",
  "properties": {
    "gn:admin1_code":"5.0",
    "gn:asciiname":"Pun'ga",
    "gn:country_code":"KR",
    "gn:dem":117,
    "gn:feature_class":"P",
    "gn:feature_code":"PPL",
    "gn:name":"Pun\u2019ga",
    "gn:population":0,
    "gn:timezone":"Asia/Seoul",
    "iso:country":"KR",
    "wof:name":"Pun'ga",
    "wof:placetype":"locality"
},
  "geometry": {"coordinates":[127.52972,36.56417],"type":"Point"}
}