{
  "type": "Feature",
  "properties": {
    "gn:admin1_code":"17.0",
    "gn:asciiname":"Simokchong",
    "gn:country_code":"KR",
    "gn:dem":29,
    "gn:feature_class":"P",
    "gn:feature_code":"PPL",
    "gn:name":"Simokch\u014fng",
    "gn:population":0,
    "gn:timezone":"Asia/Seoul",
    "iso:country":"KR",
    "name:und_x_variant":[
        "\uc2dc\ubaa9\uc815",
        "Simokch\u014fng"
    ],
    "wof:name":"Simokchong",
    "wof:placetype":"locality"
},
  "geometry": {"coordinates":[126.84,36.2779],"type":"Point"}
}