{
  "type": "Feature",
  "properties": {
    "gn:admin1_code":"14.0",
    "gn:asciiname":"Chakchom",
    "gn:country_code":"KR",
    "gn:dem":334,
    "gn:feature_class":"P",
    "gn:feature_code":"PPL",
    "gn:name":"Chakch\u014fm",
    "gn:population":0,
    "gn:timezone":"Asia/Seoul",
    "iso:country":"KR",
    "name:und_x_variant":[
        "\uc791\uc810",
        "Chakch\u014fm"
    ],
    "wof:name":"Chakchom",
    "wof:placetype":"locality"
},
  "geometry": {"coordinates":[128.0548,36.2114],"type":"Point"}
}