{
  "type": "Feature",
  "properties": {
    "gn:admin1_code":"13.0",
    "gn:asciiname":"Geonneomal",
    "gn:country_code":"KR",
    "gn:dem":141,
    "gn:feature_class":"P",
    "gn:feature_code":"PPL",
    "gn:name":"Geonneomal",
    "gn:population":0,
    "gn:timezone":"Asia/Seoul",
    "iso:country":"KR",
    "name:kor_x_preferred":[
        "\uac74\ub108\ub9d0"
    ],
    "wof:name":"Geonneomal",
    "wof:placetype":"locality"
},
  "geometry": {"coordinates":[127.3613,37.77003],"type":"Point"}
}