{
  "type": "Feature",
  "properties": {
    "gn:admin1_code":"6.0",
    "gn:asciiname":"Geomuseok",
    "gn:country_code":"KR",
    "gn:dem":268,
    "gn:feature_class":"P",
    "gn:feature_code":"PPL",
    "gn:name":"Geomuseok",
    "gn:population":0,
    "gn:timezone":"Asia/Seoul",
    "iso:country":"KR",
    "name:kor_x_preferred":[
        "\uac80\uc6b0\uc11d"
    ],
    "name:und_x_variant":[
        "H\u016dks\u014fng-ni",
        "K\u014fmsegi",
        "K\u014fmus\u014fk",
        "K\u014fmunsegi",
        "K\u014fm\u016dns\u014fk",
        "Geomuseok"
    ],
    "wof:name":"Geomuseok",
    "wof:placetype":"locality"
},
  "geometry": {"coordinates":[128.26093,38.01021],"type":"Point"}
}