{
  "type": "Feature",
  "properties": {
    "gn:admin1_code":"6.0",
    "gn:asciiname":"Anjeoul",
    "gn:country_code":"KR",
    "gn:dem":673,
    "gn:feature_class":"P",
    "gn:feature_code":"PPL",
    "gn:name":"Anjeoul",
    "gn:population":0,
    "gn:timezone":"Asia/Seoul",
    "iso:country":"KR",
    "name:kor_x_preferred":[
        "\ub0b4\uc800\uc6b8"
    ],
    "name:kor_x_variant":[
        "Naej\u014ful",
        "\uc548\uc800\uc6b8"
    ],
    "wof:name":"Anjeoul",
    "wof:placetype":"locality"
},
  "geometry": {"coordinates":[128.21408,37.98207],"type":"Point"}
}