{
  "type": "Feature",
  "properties": {
    "gn:admin1_code":"11.0",
    "gn:asciiname":"Taehung-dong",
    "gn:country_code":"KR",
    "gn:dem":21,
    "gn:feature_class":"P",
    "gn:feature_code":"PPL",
    "gn:name":"Taeh\u016dng-dong",
    "gn:population":0,
    "gn:timezone":"Asia/Seoul",
    "iso:country":"KR",
    "name:und_x_variant":[
        "Taeh\u016dng-j\u014fng",
        "\ub300\ud765\ub3d9",
        "Taeh\u016dng-dong"
    ],
    "wof:name":"Taehung-dong",
    "wof:placetype":"locality"
},
  "geometry": {"coordinates":[126.9427,37.54883],"type":"Point"}
}