{
  "type": "Feature",
  "properties": {
    "gn:admin1_code":"14.0",
    "gn:asciiname":"Kaech'oktan",
    "gn:country_code":"KR",
    "gn:dem":69,
    "gn:feature_class":"P",
    "gn:feature_code":"PPL",
    "gn:name":"Kaech\u2019\u014fktan",
    "gn:population":0,
    "gn:timezone":"Asia/Seoul",
    "iso:country":"KR",
    "name:und_x_variant":[
        "\uac1c\ucc99\ub2e8",
        "Kaech\u2019\u014fktan"
    ],
    "wof:name":"Kaech'oktan",
    "wof:placetype":"locality"
},
  "geometry": {"coordinates":[129.29383000000001,36.12612],"type":"Point"}
}