{
  "type": "Feature",
  "properties": {
    "gn:admin1_code":"19.0",
    "gn:asciiname":"Songjeol",
    "gn:country_code":"KR",
    "gn:dem":96,
    "gn:feature_class":"P",
    "gn:feature_code":"PPL",
    "gn:name":"Songjeol",
    "gn:population":0,
    "gn:timezone":"Asia/Seoul",
    "iso:country":"KR",
    "name:und_x_variant":[
        "\uc1a1\uc808",
        "Songj\u014fl",
        "Songjeol"
    ],
    "wof:name":"Songjeol",
    "wof:placetype":"locality"
},
  "geometry": {"coordinates":[127.40845,36.26906],"type":"Point"}
}