{
  "type": "Feature",
  "properties": {
    "gn:admin1_code":"13.0",
    "gn:asciiname":"Mulmakgol",
    "gn:country_code":"KR",
    "gn:dem":149,
    "gn:feature_class":"P",
    "gn:feature_code":"PPL",
    "gn:name":"Mulmakgol",
    "gn:population":0,
    "gn:timezone":"Asia/Seoul",
    "iso:country":"KR",
    "name:kor_x_preferred":[
        "\ubb3c\ub9c9\uace8"
    ],
    "name:und_x_variant":[
        "Mulmak-kol"
    ],
    "wof:name":"Mulmakgol",
    "wof:placetype":"locality"
},
  "geometry": {"coordinates":[127.27539,37.72535],"type":"Point"}
}