{
  "type": "Feature",
  "properties": {
    "gn:admin1_code":"5.0",
    "gn:asciiname":"Mandoe",
    "gn:country_code":"KR",
    "gn:dem":126,
    "gn:feature_class":"P",
    "gn:feature_code":"PPL",
    "gn:name":"Mandoe",
    "gn:population":0,
    "gn:timezone":"Asia/Seoul",
    "iso:country":"KR",
    "name:kor_x_preferred":[
        "\ub9cc\ub418"
    ],
    "wof:name":"Mandoe",
    "wof:placetype":"locality"
},
  "geometry": {"coordinates":[127.41945,36.95255],"type":"Point"}
}