{
  "type": "Feature",
  "properties": {
    "gn:admin1_code":"13.0",
    "gn:asciiname":"Soldani",
    "gn:country_code":"KR",
    "gn:dem":56,
    "gn:feature_class":"P",
    "gn:feature_code":"PPL",
    "gn:name":"Soldani",
    "gn:population":0,
    "gn:timezone":"Asia/Seoul",
    "iso:country":"KR",
    "name:kor_x_preferred":[
        "\uc19f\ub2e8\uc774"
    ],
    "name:kor_x_variant":[
        "\uc194\ub2e8\uc774"
    ],
    "name:und_x_variant":[
        "Sotdani",
        "Sottani",
        "Soldani"
    ],
    "wof:name":"Soldani",
    "wof:placetype":"locality"
},
  "geometry": {"coordinates":[127.55562999999999,37.24745],"type":"Point"}
}