{
  "type": "Feature",
  "properties": {
    "gn:admin1_code":"13.0",
    "gn:asciiname":"Yangjimal",
    "gn:country_code":"KR",
    "gn:dem":118,
    "gn:feature_class":"P",
    "gn:feature_code":"PPL",
    "gn:name":"Yangjimal",
    "gn:population":0,
    "gn:timezone":"Asia/Seoul",
    "iso:country":"KR",
    "name:und_x_variant":[
        "\uc591\uc9c0\ub9d0",
        "Yangjimal"
    ],
    "wof:name":"Yangjimal",
    "wof:placetype":"locality"
},
  "geometry": {"coordinates":[127.18268,37.95683],"type":"Point"}
}