{
  "type": "Feature",
  "properties": {
    "gn:admin1_code":"14.0",
    "gn:asciiname":"Waenma",
    "gn:country_code":"KR",
    "gn:dem":175,
    "gn:feature_class":"P",
    "gn:feature_code":"PPL",
    "gn:name":"Waenma",
    "gn:population":0,
    "gn:timezone":"Asia/Seoul",
    "iso:country":"KR",
    "name:kor_x_preferred":[
        "\uc66f\ub9c8"
    ],
    "wof:name":"Waenma",
    "wof:placetype":"locality"
},
  "geometry": {"coordinates":[128.75735,36.60623],"type":"Point"}
}