{
  "type": "Feature",
  "properties": {
    "gn:admin1_code":"6.0",
    "gn:asciiname":"Ssangyongdae",
    "gn:country_code":"KR",
    "gn:dem":467,
    "gn:feature_class":"P",
    "gn:feature_code":"PPL",
    "gn:name":"Ssangyongdae",
    "gn:population":0,
    "gn:timezone":"Asia/Seoul",
    "iso:country":"KR",
    "name:kor_x_preferred":[
        "\uc30d\uc6a9\ub300"
    ],
    "wof:name":"Ssangyongdae",
    "wof:placetype":"locality"
},
  "geometry": {"coordinates":[128.18115,37.98528],"type":"Point"}
}