{
  "type": "Feature",
  "properties": {
    "gn:admin1_code":"20.0",
    "gn:asciiname":"Pongsan",
    "gn:country_code":"KR",
    "gn:dem":196,
    "gn:feature_class":"P",
    "gn:feature_code":"PPL",
    "gn:name":"Pongsan",
    "gn:population":0,
    "gn:timezone":"Asia/Seoul",
    "iso:country":"KR",
    "name:und_x_variant":[
        "\ubd09\uc0b0",
        "Pongsan"
    ],
    "wof:name":"Pongsan",
    "wof:placetype":"locality"
},
  "geometry": {"coordinates":[128.04158000000001,35.62615],"type":"Point"}
}