{
  "type": "Feature",
  "properties": {
    "gn:admin1_code":"14.0",
    "gn:asciiname":"Sasilbat",
    "gn:country_code":"KR",
    "gn:dem":349,
    "gn:feature_class":"P",
    "gn:feature_code":"PPL",
    "gn:name":"Sasilbat",
    "gn:population":0,
    "gn:timezone":"Asia/Seoul",
    "iso:country":"KR",
    "name:und_x_variant":[
        "\uc0ac\uc2e4\ubc2d",
        "Sasilbat"
    ],
    "wof:name":"Sasilbat",
    "wof:placetype":"locality"
},
  "geometry": {"coordinates":[129.21789999999999,36.9475],"type":"Point"}
}