{
  "type": "Feature",
  "properties": {
    "gn:admin1_code":"6.0",
    "gn:asciiname":"Hasungan-dong",
    "gn:country_code":"KR",
    "gn:dem":143,
    "gn:feature_class":"P",
    "gn:feature_code":"PPL",
    "gn:name":"Has\u016dngan-dong",
    "gn:population":0,
    "gn:timezone":"Asia/Seoul",
    "iso:country":"KR",
    "name:kor_x_preferred":[
        "Has\u016dngan-dong"
    ],
    "name:kor_x_variant":[
        "\ud558\uc2b9\uc548\ub3d9"
    ],
    "name:und_x_variant":[
        "S\u016dngan-dong"
    ],
    "wof:name":"Hasungan-dong",
    "wof:placetype":"locality"
},
  "geometry": {"coordinates":[127.88306,37.30944],"type":"Point"}
}