{
  "type": "Feature",
  "properties": {
    "gn:admin1_code":"17.0",
    "gn:asciiname":"Meoriseori",
    "gn:country_code":"KR",
    "gn:dem":138,
    "gn:feature_class":"P",
    "gn:feature_code":"PPL",
    "gn:name":"Meoriseori",
    "gn:population":0,
    "gn:timezone":"Asia/Seoul",
    "iso:country":"KR",
    "name:kor_x_preferred":[
        "\uba38\ub9ac\uc11c\ub9ac"
    ],
    "wof:name":"Meoriseori",
    "wof:placetype":"locality"
},
  "geometry": {"coordinates":[126.95197,36.73086],"type":"Point"}
}