{
  "type": "Feature",
  "properties": {
    "gn:admin1_code":"17.0",
    "gn:asciiname":"Seobok",
    "gn:country_code":"KR",
    "gn:dem":61,
    "gn:feature_class":"P",
    "gn:feature_code":"PPL",
    "gn:name":"Seobok",
    "gn:population":0,
    "gn:timezone":"Asia/Seoul",
    "iso:country":"KR",
    "name:und_x_variant":[
        "\uc11c\ubcf5",
        "S\u014fbok",
        "Seobok"
    ],
    "wof:name":"Seobok",
    "wof:placetype":"locality"
},
  "geometry": {"coordinates":[127.32241,36.47216],"type":"Point"}
}