{
  "type": "Feature",
  "properties": {
    "gn:admin1_code":"14.0",
    "gn:asciiname":"Tongsan",
    "gn:country_code":"KR",
    "gn:dem":247,
    "gn:feature_class":"P",
    "gn:feature_code":"PPL",
    "gn:name":"Tongsan",
    "gn:population":0,
    "gn:timezone":"Asia/Seoul",
    "iso:country":"KR",
    "name:und_x_variant":[
        "Tongsan-dong",
        "\ub3d9\uc0b0",
        "Tongsan"
    ],
    "wof:name":"Tongsan",
    "wof:placetype":"locality"
},
  "geometry": {"coordinates":[129.03639999999999,36.5935],"type":"Point"}
}