{
  "type": "Feature",
  "properties": {
    "gn:admin1_code":"11.0",
    "gn:asciiname":"Soulsiripkaengsaengwon",
    "gn:country_code":"KR",
    "gn:dem":122,
    "gn:feature_class":"P",
    "gn:feature_code":"PPLR",
    "gn:name":"S\u014fulsiripkaengsaengw\u014fn",
    "gn:population":0,
    "gn:timezone":"Asia/Seoul",
    "iso:country":"KR",
    "name:und_x_variant":[
        "\uc11c\uc6b8\uc2dc\ub9bd\uac31\uc0dd\uc6d0",
        "S\u014fulsiripkaengsaengw\u014fn"
    ],
    "wof:name":"Soulsiripkaengsaengwon",
    "wof:placetype":"locality"
},
  "geometry": {"coordinates":[126.9045,37.6076],"type":"Point"}
}