{
  "type": "Feature",
  "properties": {
    "gn:admin1_code":"20.0",
    "gn:asciiname":"Amang-ni",
    "gn:country_code":"KR",
    "gn:dem":25,
    "gn:feature_class":"P",
    "gn:feature_code":"PPL",
    "gn:name":"Amang-ni",
    "gn:population":0,
    "gn:timezone":"Asia/Seoul",
    "iso:country":"KR",
    "name:und_x_variant":[
        "\uc544\ub9c9\ub9ac",
        "Amang-ni"
    ],
    "wof:name":"Amang-ni",
    "wof:placetype":"locality"
},
  "geometry": {"coordinates":[128.26935,35.56031],"type":"Point"}
}