{
  "type": "Feature",
  "properties": {
    "gn:admin1_code":"6.0",
    "gn:asciiname":"Geoneomal",
    "gn:country_code":"KR",
    "gn:dem":103,
    "gn:feature_class":"P",
    "gn:feature_code":"PPL",
    "gn:name":"Geoneomal",
    "gn:population":0,
    "gn:timezone":"Asia/Seoul",
    "iso:country":"KR",
    "name:und_x_variant":[
        "\uac74\ub108\ub9d0",
        "K\u014fnn\u014f-mal",
        "Geoneomal"
    ],
    "wof:name":"Geoneomal",
    "wof:placetype":"locality"
},
  "geometry": {"coordinates":[127.70935,37.8058],"type":"Point"}
}