{
  "type": "Feature",
  "properties": {
    "gn:admin1_code":"6.0",
    "gn:asciiname":"Seowon",
    "gn:country_code":"KR",
    "gn:dem":88,
    "gn:feature_class":"P",
    "gn:feature_code":"PPL",
    "gn:name":"Seowon",
    "gn:population":0,
    "gn:timezone":"Asia/Seoul",
    "iso:country":"KR",
    "name:und_x_variant":[
        "Shoin-ri",
        "S\u014fw\u014fn-ni",
        "\uc11c\uc6d0",
        "Seowon",
        "S\u014fw\u014fn"
    ],
    "wof:name":"Seowon",
    "wof:placetype":"locality"
},
  "geometry": {"coordinates":[127.67361,37.96453],"type":"Point"}
}