{
  "type": "Feature",
  "properties": {
    "gn:admin1_code":"6.0",
    "gn:asciiname":"Seowon",
    "gn:country_code":"KR",
    "gn:dem":88,
    "gn:feature_class":"P",
    "gn:feature_code":"PPL",
    "gn:name":"Seowon",
    "gn:population":0,
    "gn:timezone":"Asia/Seoul",
    "iso:country":"KR",
    "name:deu_x_preferred":[
        "Seowon"
    ],
    "name:fra_x_preferred":[
        "Seowon"
    ],
    "name:hun_x_preferred":[
        "Szovon"
    ],
    "name:hye_x_preferred":[
        "\u054d\u0578\u057e\u0578\u0576"
    ],
    "name:ind_x_preferred":[
        "Seowon"
    ],
    "name:por_x_preferred":[
        "Seowon"
    ],
    "name:rus_x_preferred":[
        "\u0421\u043e\u0432\u043e\u043d"
    ],
    "name:spa_x_preferred":[
        "Seowon"
    ],
    "name:und_x_variant":[
        "Shoin-ri",
        "S\u014fw\u014fn-ni",
        "\uc11c\uc6d0",
        "S\u014fw\u014fn"
    ],
    "name:war_x_preferred":[
        "Seowon"
    ],
    "wof:name":"Seowon",
    "wof:placetype":"locality"
},
  "geometry": {"coordinates":[127.67361,37.96453],"type":"Point"}
}