{
  "type": "Feature",
  "properties": {
    "gn:admin1_code":"20.0",
    "gn:asciiname":"Chojon",
    "gn:cc2":"KR",
    "gn:country_code":"KR",
    "gn:dem":45,
    "gn:feature_class":"P",
    "gn:feature_code":"PPL",
    "gn:name":"Choj\u014fn",
    "gn:population":0,
    "gn:timezone":"Asia/Seoul",
    "iso:country":"KR",
    "name:und_x_variant":[
        "Choj\u014fl-li",
        "Choj\u014fn-ni",
        "Choj\u014fn"
    ],
    "wof:name":"Chojon",
    "wof:placetype":"locality"
},
  "geometry": {"coordinates":[128.75083000000001,35.23528],"type":"Point"}
}