{
  "type": "Feature",
  "properties": {
    "gn:admin1_code":"12.0",
    "gn:asciiname":"Paemgol",
    "gn:country_code":"KR",
    "gn:dem":42,
    "gn:feature_class":"P",
    "gn:feature_code":"PPL",
    "gn:name":"Paemgol",
    "gn:population":0,
    "gn:timezone":"Asia/Seoul",
    "iso:country":"KR",
    "name:kor_x_preferred":[
        "\ubc40\uace8"
    ],
    "wof:name":"Paemgol",
    "wof:placetype":"locality"
},
  "geometry": {"coordinates":[126.67667,37.63083],"type":"Point"}
}