{
  "type": "Feature",
  "properties": {
    "gn:admin1_code":"17.0",
    "gn:asciiname":"Panwol",
    "gn:country_code":"KR",
    "gn:dem":23,
    "gn:feature_class":"P",
    "gn:feature_code":"PPL",
    "gn:name":"Panw\u014fl",
    "gn:population":0,
    "gn:timezone":"Asia/Seoul",
    "iso:country":"KR",
    "name:und_x_variant":[
        "\ubc18\uc6d4",
        "Panw\u014fl"
    ],
    "wof:name":"Panwol",
    "wof:placetype":"locality"
},
  "geometry": {"coordinates":[126.8017,36.9008],"type":"Point"}
}