{
  "type": "Feature",
  "properties": {
    "gn:admin1_code":"0.0",
    "gn:asciiname":"Mangjae-ri",
    "gn:country_code":"KR",
    "gn:dem":55,
    "gn:feature_class":"P",
    "gn:feature_code":"PPL",
    "gn:name":"Mangjae-ri",
    "gn:population":0,
    "gn:timezone":"Asia/Seoul",
    "iso:country":"KR",
    "name:und_x_variant":[
        "Mangch\u2019i-ri",
        "Mangjae-ri",
        "Mangch\u2019i"
    ],
    "wof:name":"Mangjae-ri",
    "wof:placetype":"locality"
},
  "geometry": {"coordinates":[128.66666999999998,34.81667],"type":"Point"}
}