{
  "type": "Feature",
  "properties": {
    "gn:admin1_code":"16.0",
    "gn:asciiname":"Puho-ri",
    "gn:country_code":"KR",
    "gn:dem":19,
    "gn:feature_class":"P",
    "gn:feature_code":"PPL",
    "gn:name":"Puho-ri",
    "gn:population":0,
    "gn:timezone":"Asia/Seoul",
    "iso:country":"KR",
    "name:kor_x_preferred":[
        "\ubd80\ud638\ub9ac"
    ],
    "wof:name":"Puho-ri",
    "wof:placetype":"locality"
},
  "geometry": {"coordinates":[126.51139000000001,34.54417],"type":"Point"}
}