{
  "type": "Feature",
  "properties": {
    "gn:admin1_code":"13.0",
    "gn:asciiname":"Sinjang il-dong",
    "gn:country_code":"KR",
    "gn:dem":32,
    "gn:feature_class":"P",
    "gn:feature_code":"PPL",
    "gn:name":"Sinjang il-dong",
    "gn:population":0,
    "gn:timezone":"Asia/Seoul",
    "iso:country":"KR",
    "name:kor_x_preferred":[
        "\uc2e0\uc7a51\ub3d9"
    ],
    "name:und_x_variant":[
        "Sinjang il-dong"
    ],
    "wof:name":"Sinjang il-dong",
    "wof:placetype":"locality"
},
  "geometry": {"coordinates":[127.20738,37.53886],"type":"Point"}
}