{
  "type": "Feature",
  "properties": {
    "gn:admin1_code":"10.0",
    "gn:asciiname":"Amgol",
    "gn:country_code":"KR",
    "gn:dem":53,
    "gn:feature_class":"P",
    "gn:feature_code":"PPL",
    "gn:name":"Amgol",
    "gn:population":0,
    "gn:timezone":"Asia/Seoul",
    "iso:country":"KR",
    "name:kor_x_preferred":[
        "\uc554\uace8"
    ],
    "wof:name":"Amgol",
    "wof:placetype":"locality"
},
  "geometry": {"coordinates":[129.27930000000001,35.35290999999999],"type":"Point"}
}