{
  "type": "Feature",
  "properties": {
    "gn:admin1_code":"6.0",
    "gn:asciiname":"Todunnaru",
    "gn:country_code":"KR",
    "gn:dem":131,
    "gn:feature_class":"P",
    "gn:feature_code":"PPL",
    "gn:name":"Todunnaru",
    "gn:population":0,
    "gn:timezone":"Asia/Seoul",
    "iso:country":"KR",
    "name:kor_x_preferred":[
        "\ub3c4\ub454\ub098\ub8e8"
    ],
    "wof:name":"Todunnaru",
    "wof:placetype":"locality"
},
  "geometry": {"coordinates":[127.836,37.6953],"type":"Point"}
}