{
  "type": "Feature",
  "properties": {
    "gn:admin1_code":"20.0",
    "gn:asciiname":"T'ungjom",
    "gn:country_code":"KR",
    "gn:dem":209,
    "gn:feature_class":"P",
    "gn:feature_code":"PPL",
    "gn:name":"T\u2019ungj\u014fm",
    "gn:population":0,
    "gn:timezone":"Asia/Seoul",
    "iso:country":"KR",
    "name:und_x_variant":[
        "\ud241\uc810",
        "T\u2019ungj\u014fm"
    ],
    "wof:name":"T'ungjom",
    "wof:placetype":"locality"
},
  "geometry": {"coordinates":[127.98677000000001,35.58253],"type":"Point"}
}