{
  "type": "Feature",
  "properties": {
    "gn:admin1_code":"16.0",
    "gn:asciiname":"Dodeok",
    "gn:country_code":"KR",
    "gn:dem":182,
    "gn:feature_class":"P",
    "gn:feature_code":"PPL",
    "gn:name":"Dodeok",
    "gn:population":0,
    "gn:timezone":"Asia/Seoul",
    "iso:country":"KR",
    "name:kor_x_preferred":[
        "\ub3c4\ub355"
    ],
    "name:kor_x_variant":[
        "Tod\u014fk"
    ],
    "wof:name":"Dodeok",
    "wof:placetype":"locality"
},
  "geometry": {"coordinates":[127.05723,34.75504],"type":"Point"}
}