{
  "type": "Feature",
  "properties": {
    "gn:admin1_code":"14.0",
    "gn:asciiname":"Albong",
    "gn:cc2":"KR",
    "gn:country_code":"KR",
    "gn:dem":446,
    "gn:feature_class":"P",
    "gn:feature_code":"PPL",
    "gn:name":"Albong",
    "gn:population":0,
    "gn:timezone":"Asia/Seoul",
    "iso:country":"KR",
    "name:und_x_variant":[
        "Nanbong",
        "Albong"
    ],
    "wof:name":"Albong",
    "wof:placetype":"locality"
},
  "geometry": {"coordinates":[130.86000000000001,37.51],"type":"Point"}
}