{
  "type": "Feature",
  "properties": {
    "gn:admin1_code":"20.0",
    "gn:asciiname":"Yon'gi-ri",
    "gn:country_code":"KR",
    "gn:dem":9,
    "gn:feature_class":"P",
    "gn:feature_code":"PPL",
    "gn:name":"Y\u014fn\u2019gi-ri",
    "gn:population":0,
    "gn:timezone":"Asia/Seoul",
    "iso:country":"KR",
    "name:und_x_variant":[
        "Y\u014fn\u2019gi-dong",
        "\uc5f0\uae30\ub9ac",
        "Y\u014fn\u2019gi",
        "Y\u014fn\u2019gi-ri"
    ],
    "wof:name":"Yon'gi-ri",
    "wof:placetype":"locality"
},
  "geometry": {"coordinates":[128.46634,34.8724],"type":"Point"}
}