{
  "type": "Feature",
  "properties": {
    "gn:admin1_code":"20.0",
    "gn:asciiname":"Tokch'on",
    "gn:country_code":"KR",
    "gn:dem":20,
    "gn:feature_class":"P",
    "gn:feature_code":"PPL",
    "gn:name":"T\u014fkch\u2019\u014fn",
    "gn:population":0,
    "gn:timezone":"Asia/Seoul",
    "iso:country":"KR",
    "name:und_x_variant":[
        "\ub355\ucc9c",
        "T\u014fkch\u2019\u014fn"
    ],
    "wof:name":"Tokch'on",
    "wof:placetype":"locality"
},
  "geometry": {"coordinates":[128.39266000000001,35.28751],"type":"Point"}
}