{
  "type": "Feature",
  "properties": {
    "gn:admin1_code":"16.0",
    "gn:asciiname":"Wangma",
    "gn:country_code":"KR",
    "gn:dem":66,
    "gn:feature_class":"P",
    "gn:feature_code":"PPL",
    "gn:name":"Wangma",
    "gn:population":0,
    "gn:timezone":"Asia/Seoul",
    "iso:country":"KR",
    "name:kor_x_preferred":[
        "\ub355\uc804"
    ],
    "wof:name":"Wangma",
    "wof:placetype":"locality"
},
  "geometry": {"coordinates":[126.92111,34.55694],"type":"Point"}
}