{
  "type": "Feature",
  "properties": {
    "gn:admin1_code":"16.0",
    "gn:asciiname":"Yongchu",
    "gn:country_code":"KR",
    "gn:dem":219,
    "gn:feature_class":"P",
    "gn:feature_code":"PPL",
    "gn:name":"Yongchu",
    "gn:population":0,
    "gn:timezone":"Asia/Seoul",
    "iso:country":"KR",
    "name:kor_x_preferred":[
        "\uc6a9\ucd94"
    ],
    "name:kor_x_variant":[
        "Yongch\u2019u"
    ],
    "wof:name":"Yongchu",
    "wof:placetype":"locality"
},
  "geometry": {"coordinates":[127.01349,34.70038],"type":"Point"}
}