{
  "type": "Feature",
  "properties": {
    "gn:admin1_code":"6.0",
    "gn:asciiname":"Tulmeji",
    "gn:country_code":"KR",
    "gn:dem":445,
    "gn:feature_class":"P",
    "gn:feature_code":"PPL",
    "gn:name":"T\u016dlmeji",
    "gn:population":0,
    "gn:timezone":"Asia/Seoul",
    "iso:country":"KR",
    "name:kor_x_preferred":[
        "\ub4e4\uba54\uc9c0"
    ],
    "name:kor_x_variant":[
        "T\u016dlmeji"
    ],
    "wof:name":"Tulmeji",
    "wof:placetype":"locality"
},
  "geometry": {"coordinates":[128.24522999999999,37.59208],"type":"Point"}
}