{
  "type": "Feature",
  "properties": {
    "gn:admin1_code":"17.0",
    "gn:asciiname":"Changnae-gol",
    "gn:country_code":"KR",
    "gn:dem":29,
    "gn:feature_class":"P",
    "gn:feature_code":"PPL",
    "gn:name":"Changnae-gol",
    "gn:population":0,
    "gn:timezone":"Asia/Seoul",
    "iso:country":"KR",
    "name:und_x_variant":[
        "\uc7a5\ub0b4\uace8",
        "Changnae-gol"
    ],
    "wof:name":"Changnae-gol",
    "wof:placetype":"locality"
},
  "geometry": {"coordinates":[126.73779999999999,36.9212],"type":"Point"}
}