{
  "type": "Feature",
  "properties": {
    "gn:admin1_code":"5.0",
    "gn:asciiname":"Saedeul",
    "gn:country_code":"KR",
    "gn:dem":85,
    "gn:feature_class":"P",
    "gn:feature_code":"PPL",
    "gn:name":"Saedeul",
    "gn:population":0,
    "gn:timezone":"Asia/Seoul",
    "iso:country":"KR",
    "name:kor_x_preferred":[
        "\uc0c8\ub4e4"
    ],
    "name:kor_x_variant":[
        "Saed\u016dl"
    ],
    "wof:name":"Saedeul",
    "wof:placetype":"locality"
},
  "geometry": {"coordinates":[127.60436,37.03987],"type":"Point"}
}