{
  "type": "Feature",
  "properties": {
    "gn:admin1_code":"5.0",
    "gn:asciiname":"Singaechon",
    "gn:country_code":"KR",
    "gn:dem":137,
    "gn:feature_class":"P",
    "gn:feature_code":"PPL",
    "gn:name":"Singaechon",
    "gn:population":0,
    "gn:timezone":"Asia/Seoul",
    "iso:country":"KR",
    "name:kor_x_preferred":[
        "\uc2e0\uac1c\ucd0c"
    ],
    "name:und_x_variant":[
        "Sinmunch\u2019\u014fn",
        "Sin\u2019gaech\u2019\u014fn",
        "Singaechon"
    ],
    "wof:name":"Singaechon",
    "wof:placetype":"locality"
},
  "geometry": {"coordinates":[127.59122000000001,36.97218],"type":"Point"}
}