{
  "type": "Feature",
  "properties": {
    "gn:admin1_code":"3.0",
    "gn:asciiname":"Mangbat",
    "gn:country_code":"KR",
    "gn:dem":343,
    "gn:feature_class":"P",
    "gn:feature_code":"PPL",
    "gn:name":"Mangbat",
    "gn:population":0,
    "gn:timezone":"Asia/Seoul",
    "iso:country":"KR",
    "name:und_x_variant":[
        "\ub9dd\ubc2d",
        "Mangbat"
    ],
    "wof:name":"Mangbat",
    "wof:placetype":"locality"
},
  "geometry": {"coordinates":[127.26737,35.55522],"type":"Point"}
}