{
  "type": "Feature",
  "properties": {
    "gn:admin1_code":"20.0",
    "gn:asciiname":"Suyo-dong",
    "gn:country_code":"KR",
    "gn:dem":295,
    "gn:feature_class":"P",
    "gn:feature_code":"PPL",
    "gn:name":"Suy\u014f-dong",
    "gn:population":0,
    "gn:timezone":"Asia/Seoul",
    "iso:country":"KR",
    "name:und_x_variant":[
        "Suy\u014f",
        "\uc218\uc5ec\ub3d9",
        "Suy\u014f-dong"
    ],
    "wof:name":"Suyo-dong",
    "wof:placetype":"locality"
},
  "geometry": {"coordinates":[127.76761999999999,35.59415999999999],"type":"Point"}
}