{
  "type": "Feature",
  "properties": {
    "gn:country":"KR",
    "gn:fcode":"PPL",
    "gn:population":19842,
    "iso:country":"KR",
    "name:kor_x_preferred":[
        "P\u014flgyo"
    ],
    "name:kor_x_variant":[
        "\ubc8c\uad50"
    ],
    "name:und_x_variant":[
        "Bakky\u014d-ri"
    ],
    "qs:name":"Beolgyo",
    "qs:photos_9r":0,
    "qs:photos_sr":0,
    "qs:pop_sr":"6",
    "wof:name":"Beolgyo",
    "wof:placetype":"locality",
    "wof:population":19842
},
  "geometry": {"coordinates":[127.34293,34.84494],"type":"Point"}
}