{
  "type": "Feature",
  "properties": {
    "gn:admin1_code":"14.0",
    "gn:asciiname":"Sangdokch'on",
    "gn:country_code":"KR",
    "gn:dem":212,
    "gn:feature_class":"P",
    "gn:feature_code":"PPL",
    "gn:name":"Sangd\u014fkch\u2019\u014fn",
    "gn:population":0,
    "gn:timezone":"Asia/Seoul",
    "iso:country":"KR",
    "name:und_x_variant":[
        "\uc0c1\ub355\ucc9c",
        "Sangd\u014fkch\u2019\u014fn"
    ],
    "wof:name":"Sangdokch'on",
    "wof:placetype":"locality"
},
  "geometry": {"coordinates":[129.02889999999999,36.4168],"type":"Point"}
}