{
  "type": "Feature",
  "properties": {
    "gn:admin1_code":"14.0",
    "gn:asciiname":"Majidong",
    "gn:country_code":"KR",
    "gn:dem":131,
    "gn:feature_class":"P",
    "gn:feature_code":"PPL",
    "gn:name":"Majidong",
    "gn:population":0,
    "gn:timezone":"Asia/Seoul",
    "iso:country":"KR",
    "name:kor_x_preferred":[
        "\ub9c8\uc9c0\ub3d9"
    ],
    "wof:name":"Majidong",
    "wof:placetype":"locality"
},
  "geometry": {"coordinates":[128.71267,36.54055],"type":"Point"}
}