{
  "type": "Feature",
  "properties": {
    "gn:admin1_code":"19.0",
    "gn:asciiname":"Milmeori",
    "gn:country_code":"KR",
    "gn:dem":66,
    "gn:feature_class":"P",
    "gn:feature_code":"PPL",
    "gn:name":"Milmeori",
    "gn:population":0,
    "gn:timezone":"Asia/Seoul",
    "iso:country":"KR",
    "name:kor_x_preferred":[
        "\ubc00\uba38\ub9ac"
    ],
    "wof:name":"Milmeori",
    "wof:placetype":"locality"
},
  "geometry": {"coordinates":[127.31314999999999,36.3283],"type":"Point"}
}