{
  "type": "Feature",
  "properties": {
    "gn:admin1_code":"15.0",
    "gn:asciiname":"Seongdam",
    "gn:country_code":"KR",
    "gn:dem":25,
    "gn:feature_class":"P",
    "gn:feature_code":"PPL",
    "gn:name":"Seongdam",
    "gn:population":0,
    "gn:timezone":"Asia/Seoul",
    "iso:country":"KR",
    "name:und_x_variant":[
        "\uc131\ub2f4",
        "S\u014fngdam",
        "Seongdam"
    ],
    "wof:name":"Seongdam",
    "wof:placetype":"locality"
},
  "geometry": {"coordinates":[128.40527,35.64097],"type":"Point"}
}