{
  "type": "Feature",
  "properties": {
    "gn:admin1_code":"14.0",
    "gn:asciiname":"Wondoyang",
    "gn:country_code":"KR",
    "gn:dem":86,
    "gn:feature_class":"P",
    "gn:feature_code":"PPL",
    "gn:name":"Wondoyang",
    "gn:population":0,
    "gn:timezone":"Asia/Seoul",
    "iso:country":"KR",
    "name:kor_x_preferred":[
        "\uc6d0\ub3c4\uc591"
    ],
    "wof:name":"Wondoyang",
    "wof:placetype":"locality"
},
  "geometry": {"coordinates":[128.48684,36.56444000000001],"type":"Point"}
}