{
  "type": "Feature",
  "properties": {
    "gn:admin1_code":"20.0",
    "gn:asciiname":"Saemaeul",
    "gn:country_code":"KR",
    "gn:dem":23,
    "gn:feature_class":"P",
    "gn:feature_code":"PPL",
    "gn:name":"Saemaeul",
    "gn:population":0,
    "gn:timezone":"Asia/Seoul",
    "iso:country":"KR",
    "name:und_x_variant":[
        "\uc0c8\ub9c8\uc744",
        "Sae-ma\u016dl",
        "Saemaeul"
    ],
    "wof:name":"Saemaeul",
    "wof:placetype":"locality"
},
  "geometry": {"coordinates":[128.33597,35.56205],"type":"Point"}
}