{
  "type": "Feature",
  "properties": {
    "gn:admin1_code":"16.0",
    "gn:asciiname":"Dokjagul",
    "gn:country_code":"KR",
    "gn:dem":37,
    "gn:feature_class":"P",
    "gn:feature_code":"PPL",
    "gn:name":"Dokjagul",
    "gn:population":0,
    "gn:timezone":"Asia/Seoul",
    "iso:country":"KR",
    "name:kor_x_preferred":[
        "\ub3c5\uc790\uad74"
    ],
    "wof:name":"Dokjagul",
    "wof:placetype":"locality"
},
  "geometry": {"coordinates":[126.80185,34.96855],"type":"Point"}
}