{
  "type": "Feature",
  "properties": {
    "gn:admin1_code":"5.0",
    "gn:asciiname":"Hwasong-ni",
    "gn:cc2":"KR",
    "gn:country_code":"KR",
    "gn:dem":148,
    "gn:feature_class":"P",
    "gn:feature_code":"PPL",
    "gn:name":"Hwas\u014fng-ni",
    "gn:population":0,
    "gn:timezone":"Asia/Seoul",
    "iso:country":"KR",
    "name:und_x_variant":[
        "Hwas\u014fng-ri",
        "Hwas\u014fng-ni"
    ],
    "wof:name":"Hwasong-ni",
    "wof:placetype":"locality"
},
  "geometry": {"coordinates":[127.60889,36.80417],"type":"Point"}
}