{
  "type": "Feature",
  "properties": {
    "gn:admin1_code":"20.0",
    "gn:asciiname":"Sinp'ung",
    "gn:country_code":"KR",
    "gn:dem":90,
    "gn:feature_class":"P",
    "gn:feature_code":"PPL",
    "gn:name":"Sinp\u2019ung",
    "gn:population":0,
    "gn:timezone":"Asia/Seoul",
    "iso:country":"KR",
    "name:und_x_variant":[
        "Shinp\u2019ung",
        "Sinp\u2019ung-ni",
        "Sinp\u2019ung"
    ],
    "wof:name":"Sinp'ung",
    "wof:placetype":"locality"
},
  "geometry": {"coordinates":[127.99527999999999,35.18861],"type":"Point"}
}