{
  "type": "Feature",
  "properties": {
    "iso:country":"KR",
    "qs:name":"\uc11d\ubb38\uba74",
    "qs:name_adm0":"\ud55c\uad6d",
    "qs:name_adm1":"\ucda9\uccad\ub0a8\ub3c4",
    "qs:photos":3,
    "qs:photos_1k":1,
    "qs:photos_9k":1,
    "qs:photos_9r":1,
    "qs:photos_all":3,
    "qs:photos_sr":1,
    "qs:placetype":"LocalAdmin",
    "qs:pop_sr":"0",
    "wof:name":"\uc11d\ubb38\uba74",
    "wof:placetype":"localadmin"
},
  "geometry": {"coordinates":[126.58859200000001,36.907764],"type":"Point"}
}