{
  "type": "Feature",
  "properties": {
    "gn:admin1_code":"6.0",
    "gn:asciiname":"Deungdae-ri",
    "gn:country_code":"KR",
    "gn:dem":509,
    "gn:feature_class":"P",
    "gn:feature_code":"PPL",
    "gn:name":"Deungdae-ri",
    "gn:population":0,
    "gn:timezone":"Asia/Seoul",
    "iso:country":"KR",
    "name:und_x_variant":[
        "T\u016dngdae-ri"
    ],
    "wof:name":"Deungdae-ri",
    "wof:placetype":"locality"
},
  "geometry": {"coordinates":[127.77417,38.31278],"type":"Point"}
}