{
  "type": "Feature",
  "properties": {
    "gn:admin1_code":"6.0",
    "gn:asciiname":"Kyodong-ni",
    "gn:country_code":"KR",
    "gn:dem":13,
    "gn:feature_class":"P",
    "gn:feature_code":"PPL",
    "gn:name":"Kyodong-ni",
    "gn:population":0,
    "gn:timezone":"Asia/Seoul",
    "iso:country":"KR",
    "name:kor_x_preferred":[
        "\uad50\ub3d9\ub9ac"
    ],
    "wof:name":"Kyodong-ni",
    "wof:placetype":"locality"
},
  "geometry": {"coordinates":[128.44499999999999,38.38028],"type":"Point"}
}