{
  "type": "Feature",
  "properties": {
    "gn:admin1_code":"17.0",
    "gn:asciiname":"Chongp'yong-dong",
    "gn:country_code":"KR",
    "gn:dem":36,
    "gn:feature_class":"P",
    "gn:feature_code":"PPL",
    "gn:name":"Chongp\u2019y\u014fng-dong",
    "gn:population":0,
    "gn:timezone":"Asia/Seoul",
    "iso:country":"KR",
    "name:und_x_variant":[
        "Chongp\u2019y\u014fng-ni",
        "Chongp\u2019y\u014fng-dong"
    ],
    "wof:name":"Chongp'yong-dong",
    "wof:placetype":"locality"
},
  "geometry": {"coordinates":[126.53333000000001,36.48333],"type":"Point"}
}