{
  "type": "Feature",
  "properties": {
    "gn:admin1_code":"13.0",
    "gn:asciiname":"Namcheon",
    "gn:country_code":"KR",
    "gn:dem":84,
    "gn:feature_class":"P",
    "gn:feature_code":"PPL",
    "gn:name":"Namcheon",
    "gn:population":0,
    "gn:timezone":"Asia/Seoul",
    "iso:country":"KR",
    "name:kor_x_preferred":[
        "\ub0a8\ucc9c"
    ],
    "name:kor_x_variant":[
        "Nam-ch\u2019on"
    ],
    "wof:name":"Namcheon",
    "wof:placetype":"locality"
},
  "geometry": {"coordinates":[127.61862000000001,37.09623],"type":"Point"}
}