{
  "type": "Feature",
  "properties": {
    "gn:admin1_code":"21.0",
    "gn:asciiname":"Eunha",
    "gn:country_code":"KR",
    "gn:dem":108,
    "gn:feature_class":"P",
    "gn:feature_code":"PPL",
    "gn:name":"Eunha",
    "gn:population":0,
    "gn:timezone":"Asia/Seoul",
    "iso:country":"KR",
    "name:kor_x_preferred":[
        "\uc740\ud558"
    ],
    "wof:name":"Eunha",
    "wof:placetype":"locality"
},
  "geometry": {"coordinates":[129.16551000000001,35.45792],"type":"Point"}
}