{
  "type": "Feature",
  "properties": {
    "gn:admin1_code":"6.0",
    "gn:asciiname":"Yongjang-gol",
    "gn:country_code":"KR",
    "gn:dem":673,
    "gn:feature_class":"P",
    "gn:feature_code":"PPL",
    "gn:name":"Yongjang-gol",
    "gn:population":0,
    "gn:timezone":"Asia/Seoul",
    "iso:country":"KR",
    "name:kor_x_preferred":[
        "\uc6a9\uc7a5\uace8"
    ],
    "wof:name":"Yongjang-gol",
    "wof:placetype":"locality"
},
  "geometry": {"coordinates":[128.3528,37.7304],"type":"Point"}
}