{
  "type": "Feature",
  "properties": {
    "gn:admin1_code":"12.0",
    "gn:asciiname":"Taemasan",
    "gn:country_code":"KR",
    "gn:dem":35,
    "gn:feature_class":"P",
    "gn:feature_code":"PPL",
    "gn:name":"Taemasan",
    "gn:population":0,
    "gn:timezone":"Asia/Seoul",
    "iso:country":"KR",
    "name:kor_x_preferred":[
        "\ub300\ub9c8\uc0b0"
    ],
    "wof:name":"Taemasan",
    "wof:placetype":"locality"
},
  "geometry": {"coordinates":[126.64,37.63722],"type":"Point"}
}