{
  "type": "Feature",
  "properties": {
    "gn:admin1_code":"17.0",
    "gn:asciiname":"Nuraengi",
    "gn:country_code":"KR",
    "gn:dem":84,
    "gn:feature_class":"P",
    "gn:feature_code":"PPL",
    "gn:name":"N\u016draengi",
    "gn:population":0,
    "gn:timezone":"Asia/Seoul",
    "iso:country":"KR",
    "name:und_x_variant":[
        "\ub290\ub7ad\uc774",
        "N\u016draengi"
    ],
    "wof:name":"Nuraengi",
    "wof:placetype":"locality"
},
  "geometry": {"coordinates":[126.774,36.4984],"type":"Point"}
}