{
  "type": "Feature",
  "properties": {
    "gn:country":"KR",
    "gn:fcode":"PPL",
    "gn:pop":0,
    "iso:country":"KR",
    "name:kor_x_preferred":[
        "\uc1a1\uc554\ub3d9"
    ],
    "name:unk_x_variant":[
        "Songam-dong"
    ],
    "qs:name":"\uc6a9\uc5541\ub3d9",
    "qs:name_adm0":"\ud55c\uad6d",
    "qs:name_adm1":"\ucda9\uccad\ubd81\ub3c4",
    "qs:photos":1,
    "qs:photos_1k":1,
    "qs:photos_9k":1,
    "qs:photos_9r":1,
    "qs:photos_all":1,
    "qs:photos_sr":1,
    "qs:placetype":"Suburb",
    "qs:pop_sr":"0",
    "wof:name":"\uc6a9\uc5541\ub3d9",
    "wof:placetype":"neighbourhood",
    "wof:population":0
},
  "geometry": {"coordinates":[128.06989999999999,37.4369],"type":"Point"}
}