{
  "type": "Feature",
  "properties": {
    "gn:admin1_code":"16.0",
    "gn:asciiname":"Sandu",
    "gn:country_code":"KR",
    "gn:dem":60,
    "gn:feature_class":"P",
    "gn:feature_code":"PPL",
    "gn:name":"Sandu",
    "gn:population":0,
    "gn:timezone":"Asia/Seoul",
    "iso:country":"KR",
    "name:ceb_x_preferred":[
        "Sandu"
    ],
    "name:deu_x_preferred":[
        "Sandu"
    ],
    "name:fra_x_preferred":[
        "Sandu"
    ],
    "name:ita_x_preferred":[
        "Sandu"
    ],
    "name:kor_x_preferred":[
        "\uc0b0\ub450"
    ],
    "name:pol_x_preferred":[
        "Sandu"
    ],
    "name:por_x_preferred":[
        "Sandu"
    ],
    "name:ron_x_preferred":[
        "Sandu"
    ],
    "name:rus_x_preferred":[
        "\u0421\u0430\u043d\u0434\u0443"
    ],
    "name:swe_x_preferred":[
        "Sandu"
    ],
    "name:ukr_x_preferred":[
        "\u0421\u0430\u043d\u0434\u0443"
    ],
    "name:und_x_variant":[
        "Mae-bong"
    ],
    "wof:name":"Sandu",
    "wof:placetype":"locality"
},
  "geometry": {"coordinates":[126.90611,34.70528],"type":"Point"}
}