{
  "type": "Feature",
  "properties": {
    "gn:admin1_code":"13.0",
    "gn:asciiname":"Sudongch'odunghakkyosongch'onbun'gyo",
    "gn:country_code":"KR",
    "gn:dem":91,
    "gn:feature_class":"P",
    "gn:feature_code":"PPL",
    "gn:name":"Sudongch\u2019od\u016dnghakkyosongch\u2019\u014fnbun\u2019gyo",
    "gn:population":0,
    "gn:timezone":"Asia/Seoul",
    "iso:country":"KR",
    "name:und_x_variant":[
        "\uc548\uad70\uc548",
        "Sudongch\u2019od\u016dnghakkyosongch\u2019\u014fnbun\u2019gyo"
    ],
    "wof:name":"Sudongch'odunghakkyosongch'onbun'gyo",
    "wof:placetype":"locality"
},
  "geometry": {"coordinates":[127.31870000000001,37.7025],"type":"Point"}
}