{
  "type": "Feature",
  "properties": {
    "gn:admin1_code":"5.0",
    "gn:asciiname":"Munam",
    "gn:country_code":"KR",
    "gn:dem":149,
    "gn:feature_class":"P",
    "gn:feature_code":"PPL",
    "gn:name":"Munam",
    "gn:population":0,
    "gn:timezone":"Asia/Seoul",
    "iso:country":"KR",
    "name:kor_x_preferred":[
        "\ubb38\ubc14\uc704"
    ],
    "name:kor_x_variant":[
        "\ubb38\uc554"
    ],
    "name:und_x_variant":[
        "Munbawi",
        "Munam"
    ],
    "wof:name":"Munam",
    "wof:placetype":"locality"
},
  "geometry": {"coordinates":[127.73896999999999,37.04451],"type":"Point"}
}