{
  "type": "Feature",
  "properties": {
    "gn:admin1_code":"5.0",
    "gn:asciiname":"Oryugol",
    "gn:country_code":"KR",
    "gn:dem":88,
    "gn:feature_class":"P",
    "gn:feature_code":"PPL",
    "gn:name":"Oryugol",
    "gn:population":0,
    "gn:timezone":"Asia/Seoul",
    "iso:country":"KR",
    "name:kor_x_preferred":[
        "\uc624\ub958\uace8"
    ],
    "wof:name":"Oryugol",
    "wof:placetype":"locality"
},
  "geometry": {"coordinates":[127.47257,36.977],"type":"Point"}
}