{
  "type": "Feature",
  "properties": {
    "gn:admin1_code":"16.0",
    "gn:asciiname":"Tokchung-ni",
    "gn:cc2":"KR",
    "gn:country_code":"KR",
    "gn:dem":41,
    "gn:feature_class":"P",
    "gn:feature_code":"PPL",
    "gn:name":"T\u014fkchung-ni",
    "gn:population":0,
    "gn:timezone":"Asia/Seoul",
    "iso:country":"KR",
    "name:und_x_variant":[
        "T\u014fksan-ni",
        "T\u014fkchung-ni"
    ],
    "wof:name":"Tokchung-ni",
    "wof:placetype":"locality"
},
  "geometry": {"coordinates":[127.36611000000001,34.49528],"type":"Point"}
}