{
  "type": "Feature",
  "properties": {
    "gn:admin1_code":"16.0",
    "gn:asciiname":"Sindeok",
    "gn:country_code":"KR",
    "gn:dem":13,
    "gn:feature_class":"P",
    "gn:feature_code":"PPL",
    "gn:name":"Sindeok",
    "gn:population":0,
    "gn:timezone":"Asia/Seoul",
    "iso:country":"KR",
    "name:kor_x_preferred":[
        "\uc2e0\ub355"
    ],
    "name:kor_x_variant":[
        "Sind\u014fk"
    ],
    "name:und_x_variant":[
        "T\u014fkh\u016dng-ni",
        "Sindeok"
    ],
    "wof:name":"Sindeok",
    "wof:placetype":"locality"
},
  "geometry": {"coordinates":[126.53610999999999,34.75194],"type":"Point"}
}