{
  "type": "Feature",
  "properties": {
    "gn:admin1_code":"16.0",
    "gn:asciiname":"Jungchon",
    "gn:country_code":"KR",
    "gn:dem":19,
    "gn:feature_class":"P",
    "gn:feature_code":"PPL",
    "gn:name":"Jungchon",
    "gn:population":0,
    "gn:timezone":"Asia/Seoul",
    "iso:country":"KR",
    "name:kor_x_preferred":[
        "Chungch\u2019on"
    ],
    "name:kor_x_variant":[
        "\uc911\ucd0c"
    ],
    "wof:name":"Jungchon",
    "wof:placetype":"locality"
},
  "geometry": {"coordinates":[126.82342,34.434],"type":"Point"}
}