{
  "type": "Feature",
  "properties": {
    "gn:admin1_code":"13.0",
    "gn:asciiname":"Dogidong",
    "gn:country_code":"KR",
    "gn:dem":42,
    "gn:feature_class":"P",
    "gn:feature_code":"PPL",
    "gn:name":"Dogidong",
    "gn:population":0,
    "gn:timezone":"Asia/Seoul",
    "iso:country":"KR",
    "name:kor_x_preferred":[
        "\ub3c4\uae30\ub3d9"
    ],
    "name:und_x_variant":[
        "Togi-dong",
        "Togi-ri",
        "Dogidong"
    ],
    "wof:name":"Dogidong",
    "wof:placetype":"locality"
},
  "geometry": {"coordinates":[127.26261,36.99801],"type":"Point"}
}