{
  "type": "Feature",
  "properties": {
    "gn:admin1_code":"14.0",
    "gn:asciiname":"Seolleum",
    "gn:country_code":"KR",
    "gn:dem":113,
    "gn:feature_class":"P",
    "gn:feature_code":"PPL",
    "gn:name":"Seolleum",
    "gn:population":0,
    "gn:timezone":"Asia/Seoul",
    "iso:country":"KR",
    "name:kor_x_preferred":[
        "\uc124\ub2a0"
    ],
    "wof:name":"Seolleum",
    "wof:placetype":"locality"
},
  "geometry": {"coordinates":[128.46541000000002,36.57973],"type":"Point"}
}