{
  "type": "Feature",
  "properties": {
    "gn:admin1_code":"16.0",
    "gn:asciiname":"Wolbi",
    "gn:country_code":"KR",
    "gn:dem":41,
    "gn:feature_class":"P",
    "gn:feature_code":"PPL",
    "gn:name":"Wolbi",
    "gn:population":0,
    "gn:timezone":"Asia/Seoul",
    "iso:country":"KR",
    "name:kor_x_preferred":[
        "\uc6d4\ube44"
    ],
    "name:und_x_variant":[
        "Kaewoli",
        "W\u014flbi",
        "Wolbi"
    ],
    "wof:name":"Wolbi",
    "wof:placetype":"locality"
},
  "geometry": {"coordinates":[126.72847,34.78377],"type":"Point"}
}