{
  "type": "Feature",
  "properties": {
    "gn:admin1_code":"16.0",
    "gn:asciiname":"Tungch'on",
    "gn:country_code":"KR",
    "gn:dem":233,
    "gn:feature_class":"P",
    "gn:feature_code":"PPL",
    "gn:name":"T\u016dngch\u2019on",
    "gn:population":0,
    "gn:timezone":"Asia/Seoul",
    "iso:country":"KR",
    "name:und_x_variant":[
        "Tungch\u2019on-ni",
        "T\u016dngch\u2019on"
    ],
    "wof:name":"Tungch'on",
    "wof:placetype":"locality"
},
  "geometry": {"coordinates":[126.96666999999999,34.76667],"type":"Point"}
}