{
  "type": "Feature",
  "properties": {
    "gn:admin1_code":"20.0",
    "gn:asciiname":"Kumsong",
    "gn:cc2":"KR",
    "gn:country_code":"KR",
    "gn:dem":44,
    "gn:feature_class":"P",
    "gn:feature_code":"PPL",
    "gn:name":"K\u016dms\u014fng",
    "gn:population":0,
    "gn:timezone":"Asia/Seoul",
    "iso:country":"KR",
    "name:und_x_variant":[
        "K\u016dms\u014fng-ni",
        "K\u016dms\u014fng"
    ],
    "wof:name":"Kumsong",
    "wof:placetype":"locality"
},
  "geometry": {"coordinates":[127.96666999999999,35.13333],"type":"Point"}
}