{
  "type": "Feature",
  "properties": {
    "gn:admin1_code":"1.0",
    "gn:asciiname":"Mung-ni",
    "gn:country_code":"KR",
    "gn:dem":18,
    "gn:feature_class":"P",
    "gn:feature_code":"PPL",
    "gn:name":"Mung-ni",
    "gn:population":0,
    "gn:timezone":"Asia/Seoul",
    "iso:country":"KR",
    "name:eng_x_preferred":[
        "Mung"
    ],
    "name:eng_x_variant":[
        "Mung-ni"
    ],
    "name:kor_x_preferred":[
        "\ubb35 \ub9ac"
    ],
    "name:und_x_variant":[
        "Muk-ri",
        "Mung-ni"
    ],
    "wof:name":"Mung",
    "wof:placetype":"locality"
},
  "geometry": {"coordinates":[126.31528,33.94583],"type":"Point"}
}