{
  "type": "Feature",
  "properties": {
    "gn:admin1_code":"3.0",
    "gn:asciiname":"Wonsongch'on",
    "gn:country_code":"KR",
    "gn:dem":468,
    "gn:feature_class":"P",
    "gn:feature_code":"PPL",
    "gn:name":"W\u014fnsongch\u2019\u014fn",
    "gn:population":0,
    "gn:timezone":"Asia/Seoul",
    "iso:country":"KR",
    "name:und_x_variant":[
        "\uc6d0\uc1a1\ucc9c",
        "W\u014fnsongch\u2019\u014fn"
    ],
    "wof:name":"Wonsongch'on",
    "wof:placetype":"locality"
},
  "geometry": {"coordinates":[127.49975999999999,35.64348],"type":"Point"}
}