{
  "type": "Feature",
  "properties": {
    "gn:admin1_code":"6.0",
    "gn:asciiname":"Halmigol",
    "gn:country_code":"KR",
    "gn:dem":407,
    "gn:feature_class":"P",
    "gn:feature_code":"PPL",
    "gn:name":"Halmigol",
    "gn:population":0,
    "gn:timezone":"Asia/Seoul",
    "iso:country":"KR",
    "name:kor_x_preferred":[
        "\ud560\ubbf8\uace8"
    ],
    "wof:name":"Halmigol",
    "wof:placetype":"locality"
},
  "geometry": {"coordinates":[128.06405000000001,37.8295],"type":"Point"}
}