{
  "type": "Feature",
  "properties": {
    "gn:admin1_code":"17.0",
    "gn:asciiname":"Ch'owang-ni",
    "gn:country_code":"KR",
    "gn:dem":7,
    "gn:feature_class":"P",
    "gn:feature_code":"PPL",
    "gn:name":"Ch\u2019owang-ni",
    "gn:population":0,
    "gn:timezone":"Asia/Seoul",
    "iso:country":"KR",
    "wof:name":"Ch'owang-ni",
    "wof:placetype":"locality"
},
  "geometry": {"coordinates":[126.86667,36.15],"type":"Point"}
}