{
  "type": "Feature",
  "properties": {
    "gn:admin1_code":"13.0",
    "gn:asciiname":"Hambae",
    "gn:country_code":"KR",
    "gn:dem":28,
    "gn:feature_class":"P",
    "gn:feature_code":"PPL",
    "gn:name":"Hambae",
    "gn:population":0,
    "gn:timezone":"Asia/Seoul",
    "iso:country":"KR",
    "name:kor_x_preferred":[
        "\ud568\ubc30"
    ],
    "wof:name":"Hambae",
    "wof:placetype":"locality"
},
  "geometry": {"coordinates":[126.6032,37.63405],"type":"Point"}
}