{
  "type": "Feature",
  "properties": {
    "gn:admin1_code":"6.0",
    "gn:asciiname":"Kanjitei",
    "gn:country_code":"KR",
    "gn:dem":11,
    "gn:feature_class":"P",
    "gn:feature_code":"PPL",
    "gn:name":"Kanjitei",
    "gn:population":0,
    "gn:timezone":"Asia/Seoul",
    "iso:country":"KR",
    "name:und_x_variant":[
        "Hanch\u2019ij\u014f",
        "Hanjimit",
        "Hanjaemit",
        "\ud55c\uce58\ubc11",
        "Hanch\u2019imit"
    ],
    "wof:name":"Kanjitei",
    "wof:placetype":"locality"
},
  "geometry": {"coordinates":[129.1985,37.4134],"type":"Point"}
}