{
  "type": "Feature",
  "properties": {
    "gn:admin1_code":"6.0",
    "gn:asciiname":"Sottaengi",
    "gn:country_code":"KR",
    "gn:dem":285,
    "gn:feature_class":"P",
    "gn:feature_code":"PPL",
    "gn:name":"Sottaengi",
    "gn:population":0,
    "gn:timezone":"Asia/Seoul",
    "iso:country":"KR",
    "name:kor_x_preferred":[
        "\uc19f\ud0f1\uc774"
    ],
    "name:kor_x_variant":[
        "Sott\u2019aengi"
    ],
    "wof:name":"Sottaengi",
    "wof:placetype":"locality"
},
  "geometry": {"coordinates":[128.08501000000001,37.99335],"type":"Point"}
}