{
  "type": "Feature",
  "properties": {
    "gn:admin1_code":"17.0",
    "gn:asciiname":"Umnae-ri",
    "gn:country_code":"KR",
    "gn:dem":53,
    "gn:feature_class":"P",
    "gn:feature_code":"PPL",
    "gn:name":"\u016cmnae-ri",
    "gn:population":0,
    "gn:timezone":"Asia/Seoul",
    "iso:country":"KR",
    "name:und_x_variant":[
        "\u016cmnae-ri",
        "\uc74d\ub0b4\ub9ac"
    ],
    "wof:name":"Umnae-ri",
    "wof:placetype":"locality"
},
  "geometry": {"coordinates":[126.60917000000001,36.30361],"type":"Point"}
}