{
  "type": "Feature",
  "properties": {
    "gn:admin1_code":"6.0",
    "gn:asciiname":"Chonui-dong",
    "gn:country_code":"KR",
    "gn:dem":568,
    "gn:feature_class":"P",
    "gn:feature_code":"PPL",
    "gn:name":"Ch\u014fn\u016di-dong",
    "gn:population":0,
    "gn:timezone":"Asia/Seoul",
    "iso:country":"KR",
    "name:kor_x_preferred":[
        "\uc804\uc758\ub3d9"
    ],
    "name:kor_x_variant":[
        "Ch\u014fn\u016di-dong"
    ],
    "wof:name":"Chonui-dong",
    "wof:placetype":"locality"
},
  "geometry": {"coordinates":[128.37,37.5006],"type":"Point"}
}