{
  "type": "Feature",
  "properties": {
    "gn:admin1_code":"5.0",
    "gn:asciiname":"Damsari",
    "gn:country_code":"KR",
    "gn:dem":82,
    "gn:feature_class":"P",
    "gn:feature_code":"PPL",
    "gn:name":"Damsari",
    "gn:population":0,
    "gn:timezone":"Asia/Seoul",
    "iso:country":"KR",
    "name:kor_x_preferred":[
        "\ub2f4\uc0ac\ub9ac"
    ],
    "name:und_x_variant":[
        "Tamsa-ri"
    ],
    "wof:name":"Damsari",
    "wof:placetype":"locality"
},
  "geometry": {"coordinates":[127.6023,37.05557],"type":"Point"}
}