{
  "type": "Feature",
  "properties": {
    "gn:admin1_code":"14.0",
    "gn:asciiname":"Imjon-dong",
    "gn:country_code":"KR",
    "gn:dem":737,
    "gn:feature_class":"P",
    "gn:feature_code":"PPL",
    "gn:name":"Imj\u014fn-dong",
    "gn:population":0,
    "gn:timezone":"Asia/Seoul",
    "iso:country":"KR",
    "name:und_x_variant":[
        "\uc784\uc804\ub3d9",
        "Imj\u014fn-dong"
    ],
    "wof:name":"Imjon-dong",
    "wof:placetype":"locality"
},
  "geometry": {"coordinates":[129.1722,36.9589],"type":"Point"}
}