{
  "type": "Feature",
  "properties": {
    "gn:admin1_code":"20.0",
    "gn:asciiname":"Yangam",
    "gn:country_code":"KR",
    "gn:dem":389,
    "gn:feature_class":"P",
    "gn:feature_code":"PPL",
    "gn:name":"Yangam",
    "gn:population":0,
    "gn:timezone":"Asia/Seoul",
    "iso:country":"KR",
    "name:und_x_variant":[
        "\uc591\uc554",
        "Yangam"
    ],
    "wof:name":"Yangam",
    "wof:placetype":"locality"
},
  "geometry": {"coordinates":[127.97926,35.76442],"type":"Point"}
}