{
  "type": "Feature",
  "properties": {
    "gn:admin1_code":"16.0",
    "gn:asciiname":"Hanagwol-li",
    "gn:country_code":"KR",
    "gn:dem":7,
    "gn:feature_class":"P",
    "gn:feature_code":"PPL",
    "gn:name":"Hanagw\u014fl-li",
    "gn:population":0,
    "gn:timezone":"Asia/Seoul",
    "iso:country":"KR",
    "name:und_x_variant":[
        "\ud558\ub099\uc6d4\ub9ac",
        "Haragw\u014fl-li",
        "Hanagw\u014fl-li"
    ],
    "wof:name":"Hanagwol-li",
    "wof:placetype":"locality"
},
  "geometry": {"coordinates":[126.12894,35.19403],"type":"Point"}
}