{
  "type": "Feature",
  "properties": {
    "gn:admin1_code":"14.0",
    "gn:asciiname":"Gassan",
    "gn:country_code":"KR",
    "gn:dem":63,
    "gn:feature_class":"P",
    "gn:feature_code":"PPL",
    "gn:name":"Gassan",
    "gn:population":0,
    "gn:timezone":"Asia/Seoul",
    "iso:country":"KR",
    "name:kor_x_preferred":[
        "\uac13\uc0b0"
    ],
    "wof:name":"Gassan",
    "wof:placetype":"locality"
},
  "geometry": {"coordinates":[129.32608999999999,36.07604],"type":"Point"}
}