{
  "type": "Feature",
  "properties": {
    "gn:admin1_code":"13.0",
    "gn:asciiname":"Gugeongni",
    "gn:country_code":"KR",
    "gn:dem":32,
    "gn:feature_class":"P",
    "gn:feature_code":"PPL",
    "gn:name":"Gugeongni",
    "gn:population":0,
    "gn:timezone":"Asia/Seoul",
    "iso:country":"KR",
    "name:und_x_variant":[
        "\uad6c\uc5b5\ub9ac",
        "Gueok-ri",
        "Ku\u014fng-ni",
        "Gugeongni"
    ],
    "wof:name":"Gugeongni",
    "wof:placetype":"locality"
},
  "geometry": {"coordinates":[127.02073,37.0744],"type":"Point"}
}