{
  "type": "Feature",
  "properties": {
    "gn:admin1_code":"14.0",
    "gn:asciiname":"Paego",
    "gn:country_code":"KR",
    "gn:dem":300,
    "gn:feature_class":"P",
    "gn:feature_code":"PPL",
    "gn:name":"Paeg\u014f",
    "gn:population":0,
    "gn:timezone":"Asia/Seoul",
    "iso:country":"KR",
    "name:und_x_variant":[
        "\ubc31\uc5b4",
        "Paeg\u014f"
    ],
    "wof:name":"Paego",
    "wof:placetype":"locality"
},
  "geometry": {"coordinates":[128.00523999999999,36.05071],"type":"Point"}
}