{
  "type": "Feature",
  "properties": {
    "gn:admin1_code":"17.0",
    "gn:asciiname":"Gaechi",
    "gn:country_code":"KR",
    "gn:dem":128,
    "gn:feature_class":"P",
    "gn:feature_code":"PPL",
    "gn:name":"Gaechi",
    "gn:population":0,
    "gn:timezone":"Asia/Seoul",
    "iso:country":"KR",
    "name:und_x_variant":[
        "\uac1c\uce58",
        "Kaech\u2019i",
        "Gaechi"
    ],
    "wof:name":"Gaechi",
    "wof:placetype":"locality"
},
  "geometry": {"coordinates":[127.3777,36.18384],"type":"Point"}
}