{
  "type": "Feature",
  "properties": {
    "gn:admin1_code":"6.0",
    "gn:asciiname":"Jiin-ri",
    "gn:country_code":"KR",
    "gn:dem":207,
    "gn:feature_class":"P",
    "gn:feature_code":"PPL",
    "gn:name":"Jiin-ri",
    "gn:population":0,
    "gn:timezone":"Asia/Seoul",
    "iso:country":"KR",
    "name:kor_x_preferred":[
        "\uc790\uc740\ub9ac"
    ],
    "name:kor_x_variant":[
        "Cha\u016dl-li"
    ],
    "name:und_x_variant":[
        "Cha\u016dm-ni",
        "Cha\u016dn"
    ],
    "wof:name":"Jiin-ri",
    "wof:placetype":"locality"
},
  "geometry": {"coordinates":[128.01639,37.8675],"type":"Point"}
}