{
  "type": "Feature",
  "properties": {
    "gn:admin1_code":"14.0",
    "gn:asciiname":"Golma",
    "gn:country_code":"KR",
    "gn:dem":481,
    "gn:feature_class":"P",
    "gn:feature_code":"PPL",
    "gn:name":"Golma",
    "gn:population":0,
    "gn:timezone":"Asia/Seoul",
    "iso:country":"KR",
    "name:kor_x_preferred":[
        "\uace8\ub9c8"
    ],
    "name:und_x_variant":[
        "Kolma",
        "Golma"
    ],
    "wof:name":"Golma",
    "wof:placetype":"locality"
},
  "geometry": {"coordinates":[128.83366999999998,37.00982],"type":"Point"}
}