{
  "type": "Feature",
  "properties": {
    "gn:admin1_code":"5.0",
    "gn:asciiname":"Hakpyeong",
    "gn:country_code":"KR",
    "gn:dem":54,
    "gn:feature_class":"P",
    "gn:feature_code":"PPL",
    "gn:name":"Hakpyeong",
    "gn:population":0,
    "gn:timezone":"Asia/Seoul",
    "iso:country":"KR",
    "name:kor_x_preferred":[
        "\ud559\ud3c9"
    ],
    "wof:name":"Hakpyeong",
    "wof:placetype":"locality"
},
  "geometry": {"coordinates":[127.54125000000001,36.72566],"type":"Point"}
}