{
  "type": "Feature",
  "properties": {
    "gn:admin1_code":"13.0",
    "gn:asciiname":"Seohyeon-dong",
    "gn:country_code":"KR",
    "gn:dem":238,
    "gn:feature_class":"P",
    "gn:feature_code":"PPLL",
    "gn:name":"Seohyeon-dong",
    "gn:population":0,
    "gn:timezone":"Asia/Seoul",
    "iso:country":"KR",
    "name:kor_x_preferred":[
        "\uc11c\ud604\ub3d9"
    ],
    "name:und_x_variant":[
        "Seohyeon-dong",
        "S\u014fhy\u014fn-dong"
    ],
    "wof:name":"Seohyeon-dong",
    "wof:placetype":"locality"
},
  "geometry": {"coordinates":[127.17278,37.37361],"type":"Point"}
}