{
  "type": "Feature",
  "properties": {
    "gn:admin1_code":"5.0",
    "gn:asciiname":"Gagokgol",
    "gn:country_code":"KR",
    "gn:dem":55,
    "gn:feature_class":"P",
    "gn:feature_code":"PPL",
    "gn:name":"Gagokgol",
    "gn:population":0,
    "gn:timezone":"Asia/Seoul",
    "iso:country":"KR",
    "name:kor_x_preferred":[
        "\uac00\uace1\uace8"
    ],
    "wof:name":"Gagokgol",
    "wof:placetype":"locality"
},
  "geometry": {"coordinates":[127.46119,36.72321],"type":"Point"}
}