{
  "type": "Feature",
  "properties": {
    "gn:admin1_code":"13.0",
    "gn:asciiname":"Myeongjang",
    "gn:country_code":"KR",
    "gn:dem":113,
    "gn:feature_class":"P",
    "gn:feature_code":"PPL",
    "gn:name":"Myeongjang",
    "gn:population":0,
    "gn:timezone":"Asia/Seoul",
    "iso:country":"KR",
    "name:kor_x_preferred":[
        "\uba85\uc7a5"
    ],
    "name:und_x_variant":[
        "\uba85\uc7a5",
        "Myeongjang"
    ],
    "wof:name":"Myeongjang",
    "wof:placetype":"locality"
},
  "geometry": {"coordinates":[127.4794,37.6673],"type":"Point"}
}