{
  "type": "Feature",
  "properties": {
    "gn:admin1_code":"6.0",
    "gn:asciiname":"Jomjae",
    "gn:country_code":"KR",
    "gn:dem":59,
    "gn:feature_class":"P",
    "gn:feature_code":"PPL",
    "gn:name":"Jomjae",
    "gn:population":0,
    "gn:timezone":"Asia/Seoul",
    "iso:country":"KR",
    "name:kor_x_preferred":[
        "\uc880\uc7ac"
    ],
    "name:und_x_variant":[
        "Chomjae"
    ],
    "wof:name":"Jomjae",
    "wof:placetype":"locality"
},
  "geometry": {"coordinates":[127.75251000000002,37.18909],"type":"Point"}
}