{
  "type": "Feature",
  "properties": {
    "gn:admin1_code":"13.0",
    "gn:asciiname":"Guteoaraet-mal",
    "gn:country_code":"KR",
    "gn:dem":50,
    "gn:feature_class":"P",
    "gn:feature_code":"PPL",
    "gn:name":"Guteoaraet-mal",
    "gn:population":0,
    "gn:timezone":"Asia/Seoul",
    "iso:country":"KR",
    "name:und_x_variant":[
        "\uad6c\ud130\uc544\ub7ab\ub9d0",
        "Guteoaraet-mal",
        "Kut\u2019\u014faraen-mal"
    ],
    "wof:name":"Guteoaraet-mal",
    "wof:placetype":"locality"
},
  "geometry": {"coordinates":[127.31610999999999,37.4875],"type":"Point"}
}