{
  "type": "Feature",
  "properties": {
    "gn:admin1_code":"5.0",
    "gn:asciiname":"Samgeori",
    "gn:country_code":"KR",
    "gn:dem":174,
    "gn:feature_class":"P",
    "gn:feature_code":"PPL",
    "gn:name":"Samgeori",
    "gn:population":0,
    "gn:timezone":"Asia/Seoul",
    "iso:country":"KR",
    "name:kor_x_preferred":[
        "\uc0bc\uac70\ub9ac"
    ],
    "wof:name":"Samgeori",
    "wof:placetype":"locality"
},
  "geometry": {"coordinates":[128.31424999999999,36.93561],"type":"Point"}
}