{
  "type": "Feature",
  "properties": {
    "gn:admin1_code":"6.0",
    "gn:asciiname":"Imokdong",
    "gn:country_code":"KR",
    "gn:dem":316,
    "gn:feature_class":"P",
    "gn:feature_code":"PPL",
    "gn:name":"Imokdong",
    "gn:population":0,
    "gn:timezone":"Asia/Seoul",
    "iso:country":"KR",
    "name:kor_x_preferred":[
        "\uc774\ubaa9\ub3d9"
    ],
    "wof:name":"Imokdong",
    "wof:placetype":"locality"
},
  "geometry": {"coordinates":[128.19902999999999,38.24219],"type":"Point"}
}