{
  "type": "Feature",
  "properties": {
    "gn:admin1_code":"14.0",
    "gn:asciiname":"Sangnam",
    "gn:country_code":"KR",
    "gn:dem":101,
    "gn:feature_class":"P",
    "gn:feature_code":"PPL",
    "gn:name":"Sangnam",
    "gn:population":0,
    "gn:timezone":"Asia/Seoul",
    "iso:country":"KR",
    "name:und_x_variant":[
        "\uc0c1\ub0a8",
        "Sangnam"
    ],
    "wof:name":"Sangnam",
    "wof:placetype":"locality"
},
  "geometry": {"coordinates":[128.12280000000001,36.1717],"type":"Point"}
}