{
  "type": "Feature",
  "properties": {
    "gn:admin1_code":"14.0",
    "gn:asciiname":"Jungcheon",
    "gn:country_code":"KR",
    "gn:dem":172,
    "gn:feature_class":"P",
    "gn:feature_code":"PPL",
    "gn:name":"Jungcheon",
    "gn:population":0,
    "gn:timezone":"Asia/Seoul",
    "iso:country":"KR",
    "name:kor_x_preferred":[
        "\uc911\ucc9c"
    ],
    "wof:name":"Jungcheon",
    "wof:placetype":"locality"
},
  "geometry": {"coordinates":[128.82782,36.6872],"type":"Point"}
}