{
  "type": "Feature",
  "properties": {
    "gn:admin1_code":"13.0",
    "gn:asciiname":"Hohyeondong",
    "gn:country_code":"KR",
    "gn:dem":274,
    "gn:feature_class":"P",
    "gn:feature_code":"PPLL",
    "gn:name":"Hohyeondong",
    "gn:population":0,
    "gn:timezone":"Asia/Seoul",
    "iso:country":"KR",
    "name:kor_x_preferred":[
        "\ud638\ud604\ub3d9"
    ],
    "name:und_x_variant":[
        "Hohy\u014fn-dong"
    ],
    "wof:name":"Hohyeondong",
    "wof:placetype":"locality"
},
  "geometry": {"coordinates":[127.32735,38.05598],"type":"Point"}
}