{
  "type": "Feature",
  "properties": {
    "gn:admin1_code":"17.0",
    "gn:asciiname":"Myeonsil",
    "gn:country_code":"KR",
    "gn:dem":64,
    "gn:feature_class":"P",
    "gn:feature_code":"PPL",
    "gn:name":"Myeonsil",
    "gn:population":0,
    "gn:timezone":"Asia/Seoul",
    "iso:country":"KR",
    "name:kor_x_preferred":[
        "\uba74\uc2e4"
    ],
    "wof:name":"Myeonsil",
    "wof:placetype":"locality"
},
  "geometry": {"coordinates":[127.31071,36.7681],"type":"Point"}
}