{
  "type": "Feature",
  "properties": {
    "gn:admin1_code":"17.0",
    "gn:asciiname":"Simp'o-dong",
    "gn:country_code":"KR",
    "gn:dem":24,
    "gn:feature_class":"P",
    "gn:feature_code":"PPL",
    "gn:name":"Simp\u2019o-dong",
    "gn:population":0,
    "gn:timezone":"Asia/Seoul",
    "iso:country":"KR",
    "name:und_x_variant":[
        "\uc2ec\ud3ec\ub3d9",
        "Simp\u2019o-dong"
    ],
    "wof:name":"Simp'o-dong",
    "wof:placetype":"locality"
},
  "geometry": {"coordinates":[126.5223,36.5112],"type":"Point"}
}