{
  "type": "Feature",
  "properties": {
    "gn:admin1_code":"17.0",
    "gn:asciiname":"Ansimdae",
    "gn:country_code":"KR",
    "gn:dem":179,
    "gn:feature_class":"P",
    "gn:feature_code":"PPL",
    "gn:name":"Ansimdae",
    "gn:population":0,
    "gn:timezone":"Asia/Seoul",
    "iso:country":"KR",
    "name:kor_x_preferred":[
        "\uc548\uc2ec\ub300"
    ],
    "wof:name":"Ansimdae",
    "wof:placetype":"locality"
},
  "geometry": {"coordinates":[127.04689,36.66016],"type":"Point"}
}