{
  "type": "Feature",
  "properties": {
    "gn:admin1_code":"5.0",
    "gn:asciiname":"Dogasil",
    "gn:country_code":"KR",
    "gn:dem":118,
    "gn:feature_class":"P",
    "gn:feature_code":"PPL",
    "gn:name":"Dogasil",
    "gn:population":0,
    "gn:timezone":"Asia/Seoul",
    "iso:country":"KR",
    "name:und_x_variant":[
        "\ub3c4\uac00\uc2e4",
        "Togasil",
        "Dogasil"
    ],
    "wof:name":"Dogasil",
    "wof:placetype":"locality"
},
  "geometry": {"coordinates":[127.64073999999999,36.39897],"type":"Point"}
}