{
  "type": "Feature",
  "properties": {
    "gn:admin1_code":"17.0",
    "gn:asciiname":"Anttul",
    "gn:country_code":"KR",
    "gn:dem":51,
    "gn:feature_class":"P",
    "gn:feature_code":"PPL",
    "gn:name":"Antt\u016dl",
    "gn:population":0,
    "gn:timezone":"Asia/Seoul",
    "iso:country":"KR",
    "name:und_x_variant":[
        "\uc548\ub730",
        "Antt\u016dl"
    ],
    "wof:name":"Anttul",
    "wof:placetype":"locality"
},
  "geometry": {"coordinates":[126.7598,36.5381],"type":"Point"}
}