{
  "type": "Feature",
  "properties": {
    "gn:admin1_code":"5.0",
    "gn:asciiname":"Gajeonggae",
    "gn:country_code":"KR",
    "gn:dem":105,
    "gn:feature_class":"P",
    "gn:feature_code":"PPL",
    "gn:name":"Gajeonggae",
    "gn:population":0,
    "gn:timezone":"Asia/Seoul",
    "iso:country":"KR",
    "name:kor_x_preferred":[
        "\uac00\uc9d5\uac1c"
    ],
    "name:kor_x_variant":[
        "\uac00\uc815\uac1c"
    ],
    "name:und_x_variant":[
        "Gajinggae",
        "Kajinggae",
        "Gajeonggae"
    ],
    "wof:name":"Gajeonggae",
    "wof:placetype":"locality"
},
  "geometry": {"coordinates":[127.60288,37.01002],"type":"Point"}
}