{
  "type": "Feature",
  "properties": {
    "gn:admin1_code":"17.0",
    "gn:asciiname":"Usong",
    "gn:country_code":"KR",
    "gn:dem":30,
    "gn:feature_class":"P",
    "gn:feature_code":"PPL",
    "gn:name":"Us\u014fng",
    "gn:population":0,
    "gn:timezone":"Asia/Seoul",
    "iso:country":"KR",
    "name:und_x_variant":[
        "\uc6b0\uc131",
        "Us\u014fng"
    ],
    "wof:name":"Usong",
    "wof:placetype":"locality"
},
  "geometry": {"coordinates":[127.0526,36.4713],"type":"Point"}
}