{
  "type": "Feature",
  "properties": {
    "gn:admin1_code":"11.0",
    "gn:asciiname":"Bongcheon 4-dong",
    "gn:country_code":"KR",
    "gn:dem":83,
    "gn:feature_class":"P",
    "gn:feature_code":"PPL",
    "gn:name":"Bongcheon 4-dong",
    "gn:population":0,
    "gn:timezone":"Asia/Seoul",
    "iso:country":"KR",
    "name:eng_x_preferred":[
        "Bongcheon 4-dong"
    ],
    "name:eng_x_variant":[
        "Bongcheon 4(sa)-dong"
    ],
    "name:kor_x_preferred":[
        "\ubd09\ucc9c4\ub3d9"
    ],
    "wof:name":"Bongcheon 4-dong",
    "wof:placetype":"locality"
},
  "geometry": {"coordinates":[126.94833,37.47667],"type":"Point"}
}