{
  "type": "Feature",
  "properties": {
    "gn:admin1_code":"15.0",
    "gn:asciiname":"Imgok",
    "gn:country_code":"KR",
    "gn:dem":219,
    "gn:feature_class":"P",
    "gn:feature_code":"PPL",
    "gn:name":"Imgok",
    "gn:population":0,
    "gn:timezone":"Asia/Seoul",
    "iso:country":"KR",
    "name:und_x_variant":[
        "\uc784\uace1",
        "Imgok"
    ],
    "wof:name":"Imgok",
    "wof:placetype":"locality"
},
  "geometry": {"coordinates":[128.65752000000001,35.72861],"type":"Point"}
}