{
  "type": "Feature",
  "properties": {
    "gn:admin1_code":"14.0",
    "gn:asciiname":"Kyoch'on-dong",
    "gn:country_code":"KR",
    "gn:dem":8,
    "gn:feature_class":"P",
    "gn:feature_code":"PPL",
    "gn:name":"Kyoch\u2019on-dong",
    "gn:population":0,
    "gn:timezone":"Asia/Seoul",
    "iso:country":"KR",
    "name:und_x_variant":[
        "\uad50\ucd0c\ub3d9",
        "Kyoch\u2019on-dong"
    ],
    "wof:name":"Kyoch'on-dong",
    "wof:placetype":"locality"
},
  "geometry": {"coordinates":[129.416,36.5436],"type":"Point"}
}