{
  "type": "Feature",
  "properties": {
    "gn:admin1_code":"13.0",
    "gn:asciiname":"Beol-mal",
    "gn:country_code":"KR",
    "gn:dem":59,
    "gn:feature_class":"P",
    "gn:feature_code":"PPL",
    "gn:name":"Beol-mal",
    "gn:population":0,
    "gn:timezone":"Asia/Seoul",
    "iso:country":"KR",
    "name:und_x_variant":[
        "\ubc8c\ub9d0",
        "Beol-mal",
        "P\u014fl-mal"
    ],
    "wof:name":"Beol-mal",
    "wof:placetype":"locality"
},
  "geometry": {"coordinates":[127.61528,37.40417],"type":"Point"}
}