{
  "type": "Feature",
  "properties": {
    "gn:admin1_code":"20.0",
    "gn:asciiname":"Chongyang",
    "gn:country_code":"KR",
    "gn:dem":59,
    "gn:feature_class":"P",
    "gn:feature_code":"PPL",
    "gn:name":"Ch\u014fngyang",
    "gn:population":0,
    "gn:timezone":"Asia/Seoul",
    "iso:country":"KR",
    "name:und_x_variant":[
        "\uc815\uc591",
        "Ch\u014fngyang"
    ],
    "wof:name":"Chongyang",
    "wof:placetype":"locality"
},
  "geometry": {"coordinates":[128.16322,35.5485],"type":"Point"}
}