{
  "type": "Feature",
  "properties": {
    "gn:admin1_code":"13.0",
    "gn:asciiname":"Dokbakgol",
    "gn:country_code":"KR",
    "gn:dem":103,
    "gn:feature_class":"P",
    "gn:feature_code":"PPL",
    "gn:name":"Dokbakgol",
    "gn:population":0,
    "gn:timezone":"Asia/Seoul",
    "iso:country":"KR",
    "name:und_x_variant":[
        "\ub3c5\ubc15\uace8",
        "Tokpak-kol",
        "Dokbakgol"
    ],
    "wof:name":"Dokbakgol",
    "wof:placetype":"locality"
},
  "geometry": {"coordinates":[127.0805,37.825],"type":"Point"}
}