{
  "type": "Feature",
  "properties": {
    "gn:admin1_code":"20.0",
    "gn:asciiname":"Taejo",
    "gn:country_code":"KR",
    "gn:dem":23,
    "gn:feature_class":"P",
    "gn:feature_code":"PPL",
    "gn:name":"Taejo",
    "gn:population":0,
    "gn:timezone":"Asia/Seoul",
    "iso:country":"KR",
    "name:und_x_variant":[
        "\ub300\uc870",
        "Taejo"
    ],
    "wof:name":"Taejo",
    "wof:placetype":"locality"
},
  "geometry": {"coordinates":[128.44874999999999,35.5386],"type":"Point"}
}