{
  "type": "Feature",
  "properties": {
    "gn:admin1_code":"20.0",
    "gn:asciiname":"Taejo",
    "gn:country_code":"KR",
    "gn:dem":23,
    "gn:feature_class":"P",
    "gn:feature_code":"PPL",
    "gn:name":"Taejo",
    "gn:population":0,
    "gn:timezone":"Asia/Seoul",
    "iso:country":"KR",
    "name:ara_x_preferred":[
        "\u062a\u0627\u064a\u062c\u0648"
    ],
    "name:ces_x_preferred":[
        "Tch\u00e4d\u017eo"
    ],
    "name:deu_x_preferred":[
        "Taejo"
    ],
    "name:hun_x_preferred":[
        "Thedzso"
    ],
    "name:ind_x_preferred":[
        "Taejo"
    ],
    "name:nor_x_preferred":[
        "Taejo"
    ],
    "name:slk_x_preferred":[
        "Tch\u00e4d\u017eo"
    ],
    "name:tha_x_preferred":[
        "\u0e1e\u0e23\u0e30\u0e40\u0e08\u0e49\u0e32\u0e41\u0e17\u0e42\u0e08"
    ],
    "name:und_x_variant":[
        "\ub300\uc870"
    ],
    "wof:name":"Taejo",
    "wof:placetype":"locality"
},
  "geometry": {"coordinates":[128.44874999999999,35.5386],"type":"Point"}
}