{
  "type": "Feature",
  "properties": {
    "gn:admin1_code":"20.0",
    "gn:asciiname":"Taedae",
    "gn:country_code":"KR",
    "gn:dem":189,
    "gn:feature_class":"P",
    "gn:feature_code":"PPL",
    "gn:name":"Taedae",
    "gn:population":0,
    "gn:timezone":"Asia/Seoul",
    "iso:country":"KR",
    "name:und_x_variant":[
        "\ub300\ub300",
        "Taedae"
    ],
    "wof:name":"Taedae",
    "wof:placetype":"locality"
},
  "geometry": {"coordinates":[127.70883000000001,35.53218],"type":"Point"}
}