{
  "type": "Feature",
  "properties": {
    "gn:admin1_code":"5.0",
    "gn:asciiname":"Sanguigol",
    "gn:country_code":"KR",
    "gn:dem":342,
    "gn:feature_class":"P",
    "gn:feature_code":"PPL",
    "gn:name":"Sanguigol",
    "gn:population":0,
    "gn:timezone":"Asia/Seoul",
    "iso:country":"KR",
    "name:kor_x_preferred":[
        "\uc0c1\uc758\uace8"
    ],
    "wof:name":"Sanguigol",
    "wof:placetype":"locality"
},
  "geometry": {"coordinates":[128.43615,36.98034000000001],"type":"Point"}
}