{
  "type": "Feature",
  "properties": {
    "gn:admin1_code":"13.0",
    "gn:asciiname":"Seojae",
    "gn:country_code":"KR",
    "gn:dem":16,
    "gn:feature_class":"P",
    "gn:feature_code":"PPL",
    "gn:name":"Seojae",
    "gn:population":0,
    "gn:timezone":"Asia/Seoul",
    "iso:country":"KR",
    "name:und_x_variant":[
        "\uc11c\uc7ac",
        "S\u014fjae",
        "Seojae"
    ],
    "wof:name":"Seojae",
    "wof:placetype":"locality"
},
  "geometry": {"coordinates":[127.11971,36.98621],"type":"Point"}
}