{
  "type": "Feature",
  "properties": {
    "gn:admin1_code":"13.0",
    "gn:asciiname":"Jeam-ni",
    "gn:country_code":"KR",
    "gn:dem":40,
    "gn:feature_class":"P",
    "gn:feature_code":"PPL",
    "gn:name":"Jeam-ni",
    "gn:population":0,
    "gn:timezone":"Asia/Seoul",
    "iso:country":"KR",
    "name:eng_x_preferred":[
        "Jeam"
    ],
    "name:eng_x_variant":[
        "Jeam-ni"
    ],
    "name:kor_x_preferred":[
        "\uc81c\uc554\ub9ac"
    ],
    "wof:name":"Jeam",
    "wof:placetype":"locality"
},
  "geometry": {"coordinates":[126.89,37.12361],"type":"Point"}
}