{
  "type": "Feature",
  "properties": {
    "gn:admin1_code":"3.0",
    "gn:asciiname":"Taejung-ni",
    "gn:country_code":"KR",
    "gn:dem":7,
    "gn:feature_class":"P",
    "gn:feature_code":"PPL",
    "gn:name":"Taejung-ni",
    "gn:population":0,
    "gn:timezone":"Asia/Seoul",
    "iso:country":"KR",
    "name:eng_x_preferred":[
        "Taejung"
    ],
    "name:eng_x_variant":[
        "Taejung-ni"
    ],
    "wof:name":"Taejung",
    "wof:placetype":"locality"
},
  "geometry": {"coordinates":[126.77889,35.69056],"type":"Point"}
}