{
  "type": "Feature",
  "properties": {
    "gn:admin1_code":"5.0",
    "gn:asciiname":"Onsudong",
    "gn:country_code":"KR",
    "gn:dem":105,
    "gn:feature_class":"P",
    "gn:feature_code":"PPL",
    "gn:name":"Onsudong",
    "gn:population":0,
    "gn:timezone":"Asia/Seoul",
    "iso:country":"KR",
    "name:kor_x_preferred":[
        "\uc628\uc218\ub3d9"
    ],
    "wof:name":"Onsudong",
    "wof:placetype":"locality"
},
  "geometry": {"coordinates":[127.42082000000001,36.94743],"type":"Point"}
}