{
  "type": "Feature",
  "properties": {
    "gn:admin1_code":"14.0",
    "gn:asciiname":"Gwanam",
    "gn:country_code":"KR",
    "gn:dem":64,
    "gn:feature_class":"P",
    "gn:feature_code":"PPL",
    "gn:name":"Gwanam",
    "gn:population":0,
    "gn:timezone":"Asia/Seoul",
    "iso:country":"KR",
    "name:kor_x_preferred":[
        "\uad00\uc554"
    ],
    "wof:name":"Gwanam",
    "wof:placetype":"locality"
},
  "geometry": {"coordinates":[128.21206000000001,36.55886],"type":"Point"}
}