{
  "type": "Feature",
  "properties": {
    "gn:admin1_code":"1.0",
    "gn:asciiname":"Jungdong",
    "gn:country_code":"KR",
    "gn:dem":20,
    "gn:feature_class":"P",
    "gn:feature_code":"PPL",
    "gn:name":"Jungdong",
    "gn:population":0,
    "gn:timezone":"Asia/Seoul",
    "iso:country":"KR",
    "name:kor_x_preferred":[
        "\uc911\ub3d9"
    ],
    "name:und_x_variant":[
        "Chung-dong"
    ],
    "wof:name":"Jungdong",
    "wof:placetype":"locality"
},
  "geometry": {"coordinates":[126.29658999999999,33.43816],"type":"Point"}
}