{
  "type": "Feature",
  "properties": {
    "gn:admin1_code":"14.0",
    "gn:asciiname":"Changgok",
    "gn:country_code":"KR",
    "gn:dem":264,
    "gn:feature_class":"P",
    "gn:feature_code":"PPL",
    "gn:name":"Changgok",
    "gn:population":0,
    "gn:timezone":"Asia/Seoul",
    "iso:country":"KR",
    "name:und_x_variant":[
        "\uc7a5\uace1",
        "Changgok"
    ],
    "wof:name":"Changgok",
    "wof:placetype":"locality"
},
  "geometry": {"coordinates":[127.97291,35.9153],"type":"Point"}
}