{
  "type": "Feature",
  "properties": {
    "gn:admin1_code":"5.0",
    "gn:asciiname":"P'aengjong",
    "gn:country_code":"KR",
    "gn:dem":171,
    "gn:feature_class":"P",
    "gn:feature_code":"PPL",
    "gn:name":"P\u2019aengj\u014fng",
    "gn:population":0,
    "gn:timezone":"Asia/Seoul",
    "iso:country":"KR",
    "name:und_x_variant":[
        "\ud33d\uc815",
        "P\u2019aengj\u014fng"
    ],
    "wof:name":"P'aengjong",
    "wof:placetype":"locality"
},
  "geometry": {"coordinates":[127.717,36.3926],"type":"Point"}
}