{
  "type": "Feature",
  "properties": {
    "gn:admin1_code":"13.0",
    "gn:asciiname":"Chobunmok",
    "gn:country_code":"KR",
    "gn:dem":163,
    "gn:feature_class":"P",
    "gn:feature_code":"PPL",
    "gn:name":"Chobunmok",
    "gn:population":0,
    "gn:timezone":"Asia/Seoul",
    "iso:country":"KR",
    "name:und_x_variant":[
        "\uc870\ubd84\ubaa9",
        "Jobunmok",
        "Chobunmok"
    ],
    "wof:name":"Chobunmok",
    "wof:placetype":"locality"
},
  "geometry": {"coordinates":[127.23193999999999,37.45278],"type":"Point"}
}