{
  "type": "Feature",
  "properties": {
    "gn:admin1_code":"13.0",
    "gn:asciiname":"Hwalsan",
    "gn:country_code":"KR",
    "gn:dem":60,
    "gn:feature_class":"P",
    "gn:feature_code":"PPL",
    "gn:name":"Hwalsan",
    "gn:population":0,
    "gn:timezone":"Asia/Seoul",
    "iso:country":"KR",
    "name:kor_x_preferred":[
        "\ud65c\uc0b0"
    ],
    "wof:name":"Hwalsan",
    "wof:placetype":"locality"
},
  "geometry": {"coordinates":[127.5338,37.2417],"type":"Point"}
}