{
  "type": "Feature",
  "properties": {
    "gn:admin1_code":"6.0",
    "gn:asciiname":"Urung-gol",
    "gn:country_code":"KR",
    "gn:dem":257,
    "gn:feature_class":"P",
    "gn:feature_code":"PPL",
    "gn:name":"Ur\u016dng-gol",
    "gn:population":0,
    "gn:timezone":"Asia/Seoul",
    "iso:country":"KR",
    "name:kor_x_preferred":[
        "\uc6b0\ub989\uace8"
    ],
    "name:kor_x_variant":[
        "Ur\u016dng-gol"
    ],
    "wof:name":"Urung-gol",
    "wof:placetype":"locality"
},
  "geometry": {"coordinates":[128.5899,37.1194],"type":"Point"}
}