{
  "type": "Feature",
  "properties": {
    "gn:admin1_code":"20.0",
    "gn:asciiname":"Chunggwon",
    "gn:country_code":"KR",
    "gn:dem":242,
    "gn:feature_class":"P",
    "gn:feature_code":"PPL",
    "gn:name":"Chunggw\u014fn",
    "gn:population":0,
    "gn:timezone":"Asia/Seoul",
    "iso:country":"KR",
    "name:und_x_variant":[
        "\uc911\uad8c",
        "Chunggw\u014fn"
    ],
    "wof:name":"Chunggwon",
    "wof:placetype":"locality"
},
  "geometry": {"coordinates":[128.28097,35.49738],"type":"Point"}
}