{
  "type": "Feature",
  "properties": {
    "iso:country":"KR",
    "name:eng_x_preferred":[
        "Jungang-dong"
    ],
    "name:kor_x_preferred":[
        "\uc911\uc559\ub3d9"
    ],
    "qs:name":"\uc911\uc559\ub3d9",
    "qs:name_adm0":"\ud55c\uad6d",
    "qs:name_adm1":"\uacbd\uc0c1\ubd81\ub3c4",
    "qs:photos":23,
    "qs:photos_1k":5,
    "qs:photos_9k":1,
    "qs:photos_9r":1,
    "qs:photos_all":23,
    "qs:photos_sr":1,
    "qs:placetype":"LocalAdmin",
    "qs:pop_sr":"0",
    "wof:name":"Jungang-dong",
    "wof:placetype":"localadmin"
},
  "geometry": {"coordinates":[128.731956,35.822986],"type":"Point"}
}