{
  "type": "Feature",
  "properties": {
    "gn:admin1_code":"6.0",
    "gn:asciiname":"Chaengbeol",
    "gn:country_code":"KR",
    "gn:dem":110,
    "gn:feature_class":"P",
    "gn:feature_code":"PPL",
    "gn:name":"Chaengbeol",
    "gn:population":0,
    "gn:timezone":"Asia/Seoul",
    "iso:country":"KR",
    "name:und_x_variant":[
        "\ucc59\ubc8c",
        "Ch\u2019aengb\u014fl",
        "Chaengbeol"
    ],
    "wof:name":"Chaengbeol",
    "wof:placetype":"locality"
},
  "geometry": {"coordinates":[127.65196,38.0527],"type":"Point"}
}