{
  "type": "Feature",
  "properties": {
    "gn:admin1_code":"16.0",
    "gn:asciiname":"Gwangam",
    "gn:country_code":"KR",
    "gn:dem":18,
    "gn:feature_class":"P",
    "gn:feature_code":"PPL",
    "gn:name":"Gwangam",
    "gn:population":0,
    "gn:timezone":"Asia/Seoul",
    "iso:country":"KR",
    "name:kor_x_preferred":[
        "\uad11\uc554"
    ],
    "name:und_x_variant":[
        "Kwangbau",
        "Kwangam",
        "Gwangam"
    ],
    "wof:name":"Gwangam",
    "wof:placetype":"locality"
},
  "geometry": {"coordinates":[127.53917,34.80860999999999],"type":"Point"}
}