{
  "type": "Feature",
  "properties": {
    "gn:admin1_code":"14.0",
    "gn:asciiname":"Hudang-dong",
    "gn:country_code":"KR",
    "gn:dem":39,
    "gn:feature_class":"P",
    "gn:feature_code":"PPL",
    "gn:name":"Hudang-dong",
    "gn:population":0,
    "gn:timezone":"Asia/Seoul",
    "iso:country":"KR",
    "name:und_x_variant":[
        "\ud6c4\ub2f9\ub3d9",
        "Twittang",
        "Hudang-dong"
    ],
    "wof:name":"Hudang-dong",
    "wof:placetype":"locality"
},
  "geometry": {"coordinates":[129.4117,37.06800000000001],"type":"Point"}
}