{
  "type": "Feature",
  "properties": {
    "gn:admin1_code":"16.0",
    "gn:asciiname":"Maheul",
    "gn:country_code":"KR",
    "gn:dem":80,
    "gn:feature_class":"P",
    "gn:feature_code":"PPL",
    "gn:name":"Maheul",
    "gn:population":0,
    "gn:timezone":"Asia/Seoul",
    "iso:country":"KR",
    "name:kor_x_preferred":[
        "\ub9c8\ud758"
    ],
    "name:und_x_variant":[
        "Madong-ni",
        "Mah\u016dl",
        "Maheul"
    ],
    "wof:name":"Maheul",
    "wof:placetype":"locality"
},
  "geometry": {"coordinates":[127.69874,34.95128],"type":"Point"}
}