{
  "type": "Feature",
  "properties": {
    "gn:admin1_code":"16.0",
    "gn:asciiname":"Nagok",
    "gn:country_code":"KR",
    "gn:dem":62,
    "gn:feature_class":"P",
    "gn:feature_code":"PPL",
    "gn:name":"Nagok",
    "gn:population":0,
    "gn:timezone":"Asia/Seoul",
    "iso:country":"KR",
    "name:kor_x_preferred":[
        "\ub098\uace1"
    ],
    "name:und_x_variant":[
        "Nagong-ni"
    ],
    "wof:name":"Nagok",
    "wof:placetype":"locality"
},
  "geometry": {"coordinates":[126.96411000000001,35.05406],"type":"Point"}
}