{
  "type": "Feature",
  "properties": {
    "gn:admin1_code":"13.0",
    "gn:asciiname":"Haengjachon",
    "gn:country_code":"KR",
    "gn:dem":54,
    "gn:feature_class":"P",
    "gn:feature_code":"PPL",
    "gn:name":"Haengjachon",
    "gn:population":0,
    "gn:timezone":"Asia/Seoul",
    "iso:country":"KR",
    "name:und_x_variant":[
        "\ud589\uc790\ucd0c",
        "Haengjachon",
        "Haengjach\u2019on"
    ],
    "wof:name":"Haengjachon",
    "wof:placetype":"locality"
},
  "geometry": {"coordinates":[127.56056,37.31278],"type":"Point"}
}