{
  "type": "Feature",
  "properties": {
    "gn:admin1_code":"6.0",
    "gn:asciiname":"Hwangjong-dong",
    "gn:country_code":"KR",
    "gn:dem":434,
    "gn:feature_class":"P",
    "gn:feature_code":"PPL",
    "gn:name":"Hwangj\u014fng-dong",
    "gn:population":0,
    "gn:timezone":"Asia/Seoul",
    "iso:country":"KR",
    "name:kor_x_preferred":[
        "\ud669\uc815\ub3d9"
    ],
    "name:kor_x_variant":[
        "Hwangj\u014fng-dong"
    ],
    "wof:name":"Hwangjong-dong",
    "wof:placetype":"locality"
},
  "geometry": {"coordinates":[128.15360000000001,37.304],"type":"Point"}
}