{
  "type": "Feature",
  "properties": {
    "iso:country":"KR",
    "name:eng_x_preferred":[
        "Gwacheon-si"
    ],
    "name:kor_x_preferred":[
        "\uacfc\ucc9c\uc2dc"
    ],
    "qs:name":"\uacfc\ucc9c\uc2dc",
    "qs:name_adm0":"\ud55c\uad6d",
    "qs:name_adm1":"\uacbd\uae30\ub3c4",
    "qs:photos":1893,
    "qs:photos_1k":384,
    "qs:photos_9k":8,
    "qs:photos_9r":9,
    "qs:photos_all":1893,
    "qs:photos_sr":15,
    "qs:placetype":"Town",
    "qs:pop_sr":"0",
    "wof:name":"Gwacheon-si",
    "wof:placetype":"locality"
},
  "geometry": {"coordinates":[126.994,37.430398],"type":"Point"}
}