{
  "type": "Feature",
  "properties": {
    "gn:admin1_code":"13.0",
    "gn:asciiname":"Sinheungdong",
    "gn:country_code":"KR",
    "gn:dem":115,
    "gn:feature_class":"P",
    "gn:feature_code":"PPL",
    "gn:name":"Sinheungdong",
    "gn:population":0,
    "gn:timezone":"Asia/Seoul",
    "iso:country":"KR",
    "name:kor_x_preferred":[
        "\uc2e0\ud765\ub3d9"
    ],
    "wof:name":"Sinheungdong",
    "wof:placetype":"locality"
},
  "geometry": {"coordinates":[127.20601000000001,38.10141],"type":"Point"}
}