{
  "type": "Feature",
  "properties": {
    "gn:admin1_code":"6.0",
    "gn:asciiname":"Yangjimal",
    "gn:country_code":"KR",
    "gn:dem":21,
    "gn:feature_class":"P",
    "gn:feature_code":"PPL",
    "gn:name":"Yangjimal",
    "gn:population":0,
    "gn:timezone":"Asia/Seoul",
    "iso:country":"KR",
    "name:kor_x_preferred":[
        "\uc591\uc9c0\ub9d0"
    ],
    "wof:name":"Yangjimal",
    "wof:placetype":"locality"
},
  "geometry": {"coordinates":[128.745,37.9704],"type":"Point"}
}