{
  "type": "Feature",
  "properties": {
    "gn:admin1_code":"20.0",
    "gn:asciiname":"Oejukko",
    "gn:country_code":"KR",
    "gn:dem":40,
    "gn:feature_class":"P",
    "gn:feature_code":"PPL",
    "gn:name":"Oejukko",
    "gn:population":0,
    "gn:timezone":"Asia/Seoul",
    "iso:country":"KR",
    "name:und_x_variant":[
        "\uc678\uc8fd\uace0",
        "Oejukko"
    ],
    "wof:name":"Oejukko",
    "wof:placetype":"locality"
},
  "geometry": {"coordinates":[128.29853,35.56626],"type":"Point"}
}