{
  "type": "Feature",
  "properties": {
    "gn:admin1_code":"17.0",
    "gn:asciiname":"Sondol",
    "gn:country_code":"KR",
    "gn:dem":62,
    "gn:feature_class":"P",
    "gn:feature_code":"PPL",
    "gn:name":"S\u014fndol",
    "gn:population":0,
    "gn:timezone":"Asia/Seoul",
    "iso:country":"KR",
    "name:und_x_variant":[
        "\uc120\ub3cc",
        "S\u014fndol"
    ],
    "wof:name":"Sondol",
    "wof:placetype":"locality"
},
  "geometry": {"coordinates":[127.2469,36.4858],"type":"Point"}
}