{
  "type": "Feature",
  "properties": {
    "gn:admin1_code":"14.0",
    "gn:asciiname":"Galgung",
    "gn:country_code":"KR",
    "gn:dem":353,
    "gn:feature_class":"P",
    "gn:feature_code":"PPL",
    "gn:name":"Galgung",
    "gn:population":0,
    "gn:timezone":"Asia/Seoul",
    "iso:country":"KR",
    "name:kor_x_preferred":[
        "\uac08\uad81"
    ],
    "wof:name":"Galgung",
    "wof:placetype":"locality"
},
  "geometry": {"coordinates":[128.4828,36.76582],"type":"Point"}
}