{
  "type": "Feature",
  "properties": {
    "gn:admin1_code":"17.0",
    "gn:asciiname":"Maensani",
    "gn:country_code":"KR",
    "gn:dem":110,
    "gn:feature_class":"P",
    "gn:feature_code":"PPL",
    "gn:name":"Maensani",
    "gn:population":0,
    "gn:timezone":"Asia/Seoul",
    "iso:country":"KR",
    "name:und_x_variant":[
        "\ub9e8\uc0b0\uc774",
        "Maensani"
    ],
    "wof:name":"Maensani",
    "wof:placetype":"locality"
},
  "geometry": {"coordinates":[127.37520000000001,36.2277],"type":"Point"}
}