{
  "type": "Feature",
  "properties": {
    "gn:admin1_code":"6.0",
    "gn:asciiname":"Beodeongmal",
    "gn:country_code":"KR",
    "gn:dem":64,
    "gn:feature_class":"P",
    "gn:feature_code":"PPL",
    "gn:name":"Beodeongmal",
    "gn:population":0,
    "gn:timezone":"Asia/Seoul",
    "iso:country":"KR",
    "name:kor_x_preferred":[
        "\ubc84\ub369\ub9d0"
    ],
    "name:kor_x_variant":[
        "P\u014fd\u014fng-mal"
    ],
    "wof:name":"Beodeongmal",
    "wof:placetype":"locality"
},
  "geometry": {"coordinates":[127.75314,37.21147],"type":"Point"}
}