{
  "type": "Feature",
  "properties": {
    "gn:admin1_code":"20.0",
    "gn:asciiname":"Byeongsaseong",
    "gn:country_code":"KR",
    "gn:dem":26,
    "gn:feature_class":"P",
    "gn:feature_code":"PPL",
    "gn:name":"Byeongsaseong",
    "gn:population":0,
    "gn:timezone":"Asia/Seoul",
    "iso:country":"KR",
    "name:kor_x_preferred":[
        "\ubcd1\uc0ac\uc131"
    ],
    "wof:name":"Byeongsaseong",
    "wof:placetype":"locality"
},
  "geometry": {"coordinates":[128.70882,35.0104],"type":"Point"}
}