{
  "type": "Feature",
  "properties": {
    "gn:admin1_code":"3.0",
    "gn:asciiname":"Wonimun",
    "gn:country_code":"KR",
    "gn:dem":23,
    "gn:feature_class":"P",
    "gn:feature_code":"PPL",
    "gn:name":"W\u014fnimun",
    "gn:population":0,
    "gn:timezone":"Asia/Seoul",
    "iso:country":"KR",
    "name:und_x_variant":[
        "\uc6d0\uc774\ubb38",
        "W\u014fnimun"
    ],
    "wof:name":"Wonimun",
    "wof:placetype":"locality"
},
  "geometry": {"coordinates":[127.00581,35.83159000000001],"type":"Point"}
}