{
  "type": "Feature",
  "properties": {
    "gn:admin1_code":"20.0",
    "gn:asciiname":"Hayong",
    "gn:country_code":"KR",
    "gn:dem":89,
    "gn:feature_class":"P",
    "gn:feature_code":"PPL",
    "gn:name":"Hayong",
    "gn:population":0,
    "gn:timezone":"Asia/Seoul",
    "iso:country":"KR",
    "name:und_x_variant":[
        "\ud558\uc6a9",
        "Hayong"
    ],
    "wof:name":"Hayong",
    "wof:placetype":"locality"
},
  "geometry": {"coordinates":[128.27950000000001,35.38164000000001],"type":"Point"}
}