{
  "type": "Feature",
  "properties": {
    "gn:admin1_code":"16.0",
    "gn:asciiname":"Hodong",
    "gn:country_code":"KR",
    "gn:dem":164,
    "gn:feature_class":"P",
    "gn:feature_code":"PPL",
    "gn:name":"Hodong",
    "gn:population":0,
    "gn:timezone":"Asia/Seoul",
    "iso:country":"KR",
    "name:kor_x_preferred":[
        "\ud638\ub3d9"
    ],
    "wof:name":"Hodong",
    "wof:placetype":"locality"
},
  "geometry": {"coordinates":[127.00765,34.99974],"type":"Point"}
}