{
  "type": "Feature",
  "properties": {
    "gn:admin1_code":"6.0",
    "gn:asciiname":"Maltari",
    "gn:country_code":"KR",
    "gn:dem":394,
    "gn:feature_class":"P",
    "gn:feature_code":"PPL",
    "gn:name":"Maltari",
    "gn:population":0,
    "gn:timezone":"Asia/Seoul",
    "iso:country":"KR",
    "name:kor_x_preferred":[
        "\uba4b\ub2e4\ub9ac"
    ],
    "name:kor_x_variant":[
        "M\u014ftta-ri"
    ],
    "wof:name":"Maltari",
    "wof:placetype":"locality"
},
  "geometry": {"coordinates":[128.36959999999999,37.4309],"type":"Point"}
}