{
  "type": "Feature",
  "properties": {
    "gn:admin1_code":"17.0",
    "gn:asciiname":"Sinhyangchon",
    "gn:country_code":"KR",
    "gn:dem":33,
    "gn:feature_class":"P",
    "gn:feature_code":"PPL",
    "gn:name":"Sinhyangchon",
    "gn:population":0,
    "gn:timezone":"Asia/Seoul",
    "iso:country":"KR",
    "name:und_x_variant":[
        "\uc2e0\ud5a5\ucd0c",
        "Sinhyang-ch\u2019on",
        "Sinhyangchon"
    ],
    "wof:name":"Sinhyangchon",
    "wof:placetype":"locality"
},
  "geometry": {"coordinates":[127.157,36.937],"type":"Point"}
}