{
  "type": "Feature",
  "properties": {
    "gn:admin1_code":"17.0",
    "gn:asciiname":"Sangnyong",
    "gn:country_code":"KR",
    "gn:dem":50,
    "gn:feature_class":"P",
    "gn:feature_code":"PPL",
    "gn:name":"Sangnyong",
    "gn:population":0,
    "gn:timezone":"Asia/Seoul",
    "iso:country":"KR",
    "name:kor_x_preferred":[
        "\uc0c1\ub8e1"
    ],
    "wof:name":"Sangnyong",
    "wof:placetype":"locality"
},
  "geometry": {"coordinates":[127.31122000000001,36.53369],"type":"Point"}
}