{
  "type": "Feature",
  "properties": {
    "gn:admin1_code":"13.0",
    "gn:asciiname":"Mangnung-ni",
    "gn:country_code":"KR",
    "gn:dem":205,
    "gn:feature_class":"P",
    "gn:feature_code":"PPL",
    "gn:name":"Mangn\u016dng-ni",
    "gn:population":0,
    "gn:timezone":"Asia/Seoul",
    "iso:country":"KR",
    "name:kor_x_preferred":[
        "\ub9dd\ub2a5\ub9ac"
    ],
    "name:kor_x_variant":[
        "Mangn\u016dng-ni"
    ],
    "wof:name":"Mangnung-ni",
    "wof:placetype":"locality"
},
  "geometry": {"coordinates":[127.6374,37.548],"type":"Point"}
}