{
  "type": "Feature",
  "properties": {
    "gn:admin1_code":"20.0",
    "gn:asciiname":"Osakgol",
    "gn:country_code":"KR",
    "gn:dem":31,
    "gn:feature_class":"P",
    "gn:feature_code":"PPL",
    "gn:name":"Osakgol",
    "gn:population":0,
    "gn:timezone":"Asia/Seoul",
    "iso:country":"KR",
    "name:kor_x_preferred":[
        "\uc624\uc0ad\uace8"
    ],
    "wof:name":"Osakgol",
    "wof:placetype":"locality"
},
  "geometry": {"coordinates":[128.45958000000002,35.55889000000001],"type":"Point"}
}