{
  "type": "Feature",
  "properties": {
    "gn:admin1_code":"21.0",
    "gn:asciiname":"Panho",
    "gn:country_code":"KR",
    "gn:dem":113,
    "gn:feature_class":"P",
    "gn:feature_code":"PPL",
    "gn:name":"Panho",
    "gn:population":0,
    "gn:timezone":"Asia/Seoul",
    "iso:country":"KR",
    "wof:name":"Panho",
    "wof:placetype":"locality"
},
  "geometry": {"coordinates":[129.18333000000001,35.56667],"type":"Point"}
}