{
  "type": "Feature",
  "properties": {
    "gn:admin1_code":"14.0",
    "gn:asciiname":"Chip'um",
    "gn:country_code":"KR",
    "gn:dem":213,
    "gn:feature_class":"P",
    "gn:feature_code":"PPL",
    "gn:name":"Chip\u2019um",
    "gn:population":0,
    "gn:timezone":"Asia/Seoul",
    "iso:country":"KR",
    "name:und_x_variant":[
        "\uc9c0\ud488",
        "Chip\u2019um"
    ],
    "wof:name":"Chip'um",
    "wof:placetype":"locality"
},
  "geometry": {"coordinates":[129.18119999999999,36.482],"type":"Point"}
}