{
  "type": "Feature",
  "properties": {
    "gn:admin1_code":"17.0",
    "gn:asciiname":"Wonjul",
    "gn:country_code":"KR",
    "gn:dem":183,
    "gn:feature_class":"P",
    "gn:feature_code":"PPL",
    "gn:name":"W\u014fnjul",
    "gn:population":0,
    "gn:timezone":"Asia/Seoul",
    "iso:country":"KR",
    "name:und_x_variant":[
        "\uc6d0\uc904",
        "W\u014fnjul"
    ],
    "wof:name":"Wonjul",
    "wof:placetype":"locality"
},
  "geometry": {"coordinates":[127.48990000000001,36.0925],"type":"Point"}
}