{
  "type": "Feature",
  "properties": {
    "gn:admin1_code":"16.0",
    "gn:asciiname":"Hwanggokdong",
    "gn:country_code":"KR",
    "gn:dem":142,
    "gn:feature_class":"P",
    "gn:feature_code":"PPL",
    "gn:name":"Hwanggokdong",
    "gn:population":0,
    "gn:timezone":"Asia/Seoul",
    "iso:country":"KR",
    "name:kor_x_preferred":[
        "\ud669\uace1\ub3d9"
    ],
    "name:und_x_variant":[
        "Hwanggong-ni",
        "Hwanggok",
        "Hwanggokdong"
    ],
    "wof:name":"Hwanggokdong",
    "wof:placetype":"locality"
},
  "geometry": {"coordinates":[126.78744,34.76307],"type":"Point"}
}