{
  "type": "Feature",
  "properties": {
    "gn:admin1_code":"5.0",
    "gn:admin2_code":"\u016cms\u014fng-gun",
    "gn:asciiname":"Seongmi",
    "gn:country_code":"KR",
    "gn:dem":100,
    "gn:feature_class":"P",
    "gn:feature_code":"PPL",
    "gn:name":"Seongmi",
    "gn:population":0,
    "gn:timezone":"Asia/Seoul",
    "iso:country":"KR",
    "name:kor_x_preferred":[
        "\uc131\ubbf8"
    ],
    "name:kor_x_variant":[
        "S\u014fngmi"
    ],
    "wof:name":"Seongmi",
    "wof:placetype":"locality"
},
  "geometry": {"coordinates":[127.48032000000001,37.00262],"type":"Point"}
}