{
  "type": "Feature",
  "properties": {
    "gn:admin1_code":"17.0",
    "gn:asciiname":"Yedong-ni",
    "gn:country_code":"KR",
    "gn:dem":41,
    "gn:feature_class":"P",
    "gn:feature_code":"PPL",
    "gn:name":"Yed\u014fng-ni",
    "gn:population":0,
    "gn:timezone":"Asia/Seoul",
    "iso:country":"KR",
    "name:eng_x_preferred":[
        "Yedong"
    ],
    "name:eng_x_variant":[
        "Yedong-ni"
    ],
    "name:und_x_variant":[
        "\uc608\ub355\ub9ac",
        "Yed\u014fng-ni"
    ],
    "wof:name":"Yedong",
    "wof:placetype":"locality"
},
  "geometry": {"coordinates":[126.50320000000001,36.8549],"type":"Point"}
}