{
  "type": "Feature",
  "properties": {
    "gn:admin1_code":"6.0",
    "gn:asciiname":"Podulch'i",
    "gn:country_code":"KR",
    "gn:dem":683,
    "gn:feature_class":"P",
    "gn:feature_code":"PPL",
    "gn:name":"P\u014fd\u016dlch\u2019i",
    "gn:population":0,
    "gn:timezone":"Asia/Seoul",
    "iso:country":"KR",
    "name:kor_x_preferred":[
        "\ubc84\ub4e4\uce58"
    ],
    "name:kor_x_variant":[
        "P\u014fd\u016dlch\u2019i"
    ],
    "wof:name":"Podulch'i",
    "wof:placetype":"locality"
},
  "geometry": {"coordinates":[128.97630000000001,37.1365],"type":"Point"}
}