{
  "type": "Feature",
  "properties": {
    "gn:admin1_code":"16.0",
    "gn:asciiname":"Hukch'on",
    "gn:country_code":"KR",
    "gn:dem":41,
    "gn:feature_class":"P",
    "gn:feature_code":"PPL",
    "gn:name":"H\u016dkch\u2019\u014fn",
    "gn:population":0,
    "gn:timezone":"Asia/Seoul",
    "iso:country":"KR",
    "name:kor_x_preferred":[
        "\ud751\ucc9c"
    ],
    "name:kor_x_variant":[
        "H\u016dkch\u2019\u014fn"
    ],
    "wof:name":"Hukch'on",
    "wof:placetype":"locality"
},
  "geometry": {"coordinates":[126.68138999999999,34.56806],"type":"Point"}
}