{
  "type": "Feature",
  "properties": {
    "gn:admin1_code":"5.0",
    "gn:asciiname":"Seodangmal",
    "gn:country_code":"KR",
    "gn:dem":163,
    "gn:feature_class":"P",
    "gn:feature_code":"PPL",
    "gn:name":"Seodangmal",
    "gn:population":0,
    "gn:timezone":"Asia/Seoul",
    "iso:country":"KR",
    "name:kor_x_preferred":[
        "\uc11c\ub2f9\ub9d0"
    ],
    "wof:name":"Seodangmal",
    "wof:placetype":"locality"
},
  "geometry": {"coordinates":[128.15541000000002,36.97552],"type":"Point"}
}