{
  "type": "Feature",
  "properties": {
    "gn:admin1_code":"14.0",
    "gn:asciiname":"Tansu",
    "gn:country_code":"KR",
    "gn:dem":237,
    "gn:feature_class":"P",
    "gn:feature_code":"PPL",
    "gn:name":"Tansu",
    "gn:population":0,
    "gn:timezone":"Asia/Seoul",
    "iso:country":"KR",
    "name:und_x_variant":[
        "\ub2e8\uc218",
        "Tansu"
    ],
    "wof:name":"Tansu",
    "wof:placetype":"locality"
},
  "geometry": {"coordinates":[127.99079999999999,36.0171],"type":"Point"}
}