{
  "type": "Feature",
  "properties": {
    "gn:admin1_code":"0.0",
    "gn:asciiname":"Chungt'ong-gol",
    "gn:country_code":"KR",
    "gn:dem":384,
    "gn:feature_class":"P",
    "gn:feature_code":"PPL",
    "gn:name":"Chungt\u2019ong-gol",
    "gn:population":0,
    "gn:timezone":"Asia/Seoul",
    "iso:country":"KR",
    "name:und_x_variant":[
        "Chungt\u2019ong",
        "Chungt\u2019ong-kol",
        "Chungt\u2019ong-gol"
    ],
    "wof:name":"Chungt'ong-gol",
    "wof:placetype":"locality"
},
  "geometry": {"coordinates":[128.55000000000001,34.88333],"type":"Point"}
}