{
  "type": "Feature",
  "properties": {
    "gn:admin1_code":"6.0",
    "gn:asciiname":"Umdal-mal",
    "gn:country_code":"KR",
    "gn:dem":184,
    "gn:feature_class":"P",
    "gn:feature_code":"PPL",
    "gn:name":"\u016cmdal-mal",
    "gn:population":0,
    "gn:timezone":"Asia/Seoul",
    "iso:country":"KR",
    "name:kor_x_preferred":[
        "\uc74c\ub2ec\ub9d0"
    ],
    "name:kor_x_variant":[
        "\u016cmdal-mal"
    ],
    "wof:name":"Umdal-mal",
    "wof:placetype":"locality"
},
  "geometry": {"coordinates":[127.883,37.6586],"type":"Point"}
}