{
  "type": "Feature",
  "properties": {
    "gn:admin1_code":"14.0",
    "gn:asciiname":"Sop'yon",
    "gn:country_code":"KR",
    "gn:dem":275,
    "gn:feature_class":"P",
    "gn:feature_code":"PPL",
    "gn:name":"S\u014fp\u2019y\u014fn",
    "gn:population":0,
    "gn:timezone":"Asia/Seoul",
    "iso:country":"KR",
    "name:und_x_variant":[
        "\uc11c\ud3b8",
        "S\u014fp\u2019y\u014fn"
    ],
    "wof:name":"Sop'yon",
    "wof:placetype":"locality"
},
  "geometry": {"coordinates":[129.12389999999999,36.7003],"type":"Point"}
}