{
  "type": "Feature",
  "properties": {
    "gn:admin1_code":"17.0",
    "gn:asciiname":"Pulmusil",
    "gn:country_code":"KR",
    "gn:dem":61,
    "gn:feature_class":"P",
    "gn:feature_code":"PPL",
    "gn:name":"Pulmusil",
    "gn:population":0,
    "gn:timezone":"Asia/Seoul",
    "iso:country":"KR",
    "name:und_x_variant":[
        "\ubd88\ubb34\uc2e4",
        "Pulmusil"
    ],
    "wof:name":"Pulmusil",
    "wof:placetype":"locality"
},
  "geometry": {"coordinates":[126.9464,36.8535],"type":"Point"}
}