{
  "type": "Feature",
  "properties": {
    "gn:admin1_code":"6.0",
    "gn:asciiname":"Hwajeonmin Jeongchakji",
    "gn:country_code":"KR",
    "gn:dem":383,
    "gn:feature_class":"P",
    "gn:feature_code":"PPL",
    "gn:name":"Hwajeonmin Jeongchakji",
    "gn:population":0,
    "gn:timezone":"Asia/Seoul",
    "iso:country":"KR",
    "name:kor_x_preferred":[
        "\ud654\uc804\ubbfc\uc815\ucc29\uc9c0"
    ],
    "name:kor_x_variant":[
        "Hwaj\u014fnminch\u014fngch\u2019akchi"
    ],
    "wof:name":"Hwajeonmin Jeongchakji",
    "wof:placetype":"locality"
},
  "geometry": {"coordinates":[128.06971999999999,38.18778],"type":"Point"}
}