{
  "type": "Feature",
  "properties": {
    "gn:admin1_code":"5.0",
    "gn:asciiname":"Hasi-ri",
    "gn:country_code":"KR",
    "gn:dem":177,
    "gn:feature_class":"P",
    "gn:feature_code":"PPL",
    "gn:name":"Hasi-ri",
    "gn:population":0,
    "gn:timezone":"Asia/Seoul",
    "iso:country":"KR",
    "name:kor_x_preferred":[
        "\ud558\uc2dc\ub9ac"
    ],
    "wof:name":"Hasi-ri",
    "wof:placetype":"locality"
},
  "geometry": {"coordinates":[128.30629999999999,37.0397],"type":"Point"}
}