{
  "type": "Feature",
  "properties": {
    "gn:admin1_code":"14.0",
    "gn:asciiname":"Kwich'on",
    "gn:country_code":"KR",
    "gn:dem":109,
    "gn:feature_class":"P",
    "gn:feature_code":"PPL",
    "gn:name":"Kwich\u2019\u014fn",
    "gn:population":0,
    "gn:timezone":"Asia/Seoul",
    "iso:country":"KR",
    "name:und_x_variant":[
        "\uadc0\ucc9c",
        "Kwich\u2019\u014fn"
    ],
    "wof:name":"Kwich'on",
    "wof:placetype":"locality"
},
  "geometry": {"coordinates":[128.74170000000001,36.322],"type":"Point"}
}