{
  "type": "Feature",
  "properties": {
    "gn:admin1_code":"17.0",
    "gn:asciiname":"Heonteogol",
    "gn:country_code":"KR",
    "gn:dem":82,
    "gn:feature_class":"P",
    "gn:feature_code":"PPL",
    "gn:name":"Heonteogol",
    "gn:population":0,
    "gn:timezone":"Asia/Seoul",
    "iso:country":"KR",
    "name:kor_x_preferred":[
        "\ud5cc\ud130\uace8"
    ],
    "wof:name":"Heonteogol",
    "wof:placetype":"locality"
},
  "geometry": {"coordinates":[127.23575,36.62499],"type":"Point"}
}