{
  "type": "Feature",
  "properties": {
    "gn:admin1_code":"16.0",
    "gn:asciiname":"Donggeo",
    "gn:country_code":"KR",
    "gn:dem":18,
    "gn:feature_class":"P",
    "gn:feature_code":"PPL",
    "gn:name":"Donggeo",
    "gn:population":0,
    "gn:timezone":"Asia/Seoul",
    "iso:country":"KR",
    "name:kor_x_preferred":[
        "\uac70\uc57c"
    ],
    "name:kor_x_variant":[
        "K\u014fya",
        "\ub3d9\uac70"
    ],
    "wof:name":"Donggeo",
    "wof:placetype":"locality"
},
  "geometry": {"coordinates":[127.36685,34.7193],"type":"Point"}
}