{
  "type": "Feature",
  "properties": {
    "gn:admin1_code":"6.0",
    "gn:asciiname":"Su-dong",
    "gn:country_code":"KR",
    "gn:dem":265,
    "gn:feature_class":"P",
    "gn:feature_code":"PPL",
    "gn:name":"Su-dong",
    "gn:population":0,
    "gn:timezone":"Asia/Seoul",
    "iso:country":"KR",
    "name:kor_x_preferred":[
        "\uc218\ub3d9"
    ],
    "wof:name":"Su-dong",
    "wof:placetype":"locality"
},
  "geometry": {"coordinates":[128.6123,37.2908],"type":"Point"}
}