{
  "type": "Feature",
  "properties": {
    "gn:admin1_code":"5.0",
    "gn:asciiname":"Ganamujeong",
    "gn:country_code":"KR",
    "gn:dem":194,
    "gn:feature_class":"P",
    "gn:feature_code":"PPL",
    "gn:name":"Ganamujeong",
    "gn:population":0,
    "gn:timezone":"Asia/Seoul",
    "iso:country":"KR",
    "name:kor_x_preferred":[
        "\uac00\ub098\ubb34\uc815"
    ],
    "name:und_x_variant":[
        "Kaj\u014fng",
        "Kanamuj\u014fng",
        "Ganamujeong"
    ],
    "wof:name":"Ganamujeong",
    "wof:placetype":"locality"
},
  "geometry": {"coordinates":[127.76137,36.76584],"type":"Point"}
}