{
  "type": "Feature",
  "properties": {
    "gn:admin1_code":"6.0",
    "gn:asciiname":"Chohang-dong",
    "gn:country_code":"KR",
    "gn:dem":630,
    "gn:feature_class":"P",
    "gn:feature_code":"PPL",
    "gn:name":"Chohang-dong",
    "gn:population":0,
    "gn:timezone":"Asia/Seoul",
    "iso:country":"KR",
    "name:kor_x_preferred":[
        "\uc870\ud56d\ub3d9"
    ],
    "wof:name":"Chohang-dong",
    "wof:placetype":"locality"
},
  "geometry": {"coordinates":[128.39519000000001,37.75929],"type":"Point"}
}