{
  "type": "Feature",
  "properties": {
    "gn:admin1_code":"13.0",
    "gn:asciiname":"Saemalchon",
    "gn:country_code":"KR",
    "gn:dem":63,
    "gn:feature_class":"P",
    "gn:feature_code":"PPL",
    "gn:name":"Saemalchon",
    "gn:population":0,
    "gn:timezone":"Asia/Seoul",
    "iso:country":"KR",
    "name:kor_x_preferred":[
        "\uc0c8\ub9d0\ucd0c"
    ],
    "wof:name":"Saemalchon",
    "wof:placetype":"locality"
},
  "geometry": {"coordinates":[126.90518,37.70415],"type":"Point"}
}