{
  "type": "Feature",
  "properties": {
    "gn:admin1_code":"19.0",
    "gn:asciiname":"Komundul",
    "gn:country_code":"KR",
    "gn:dem":97,
    "gn:feature_class":"P",
    "gn:feature_code":"PPL",
    "gn:name":"K\u014fmund\u016dl",
    "gn:population":0,
    "gn:timezone":"Asia/Seoul",
    "iso:country":"KR",
    "name:und_x_variant":[
        "\uac70\ubb38\ub4e4",
        "K\u014fmund\u016dl"
    ],
    "wof:name":"Komundul",
    "wof:placetype":"locality"
},
  "geometry": {"coordinates":[127.345,36.2531],"type":"Point"}
}