{
  "type": "Feature",
  "properties": {
    "gn:admin1_code":"6.0",
    "gn:asciiname":"Tulmaejae",
    "gn:country_code":"KR",
    "gn:dem":352,
    "gn:feature_class":"P",
    "gn:feature_code":"PPL",
    "gn:name":"T\u016dlmaejae",
    "gn:population":0,
    "gn:timezone":"Asia/Seoul",
    "iso:country":"KR",
    "name:kor_x_preferred":[
        "\ub4e4\ub9e4\uc7ac"
    ],
    "name:kor_x_variant":[
        "T\u016dlmaejae"
    ],
    "wof:name":"Tulmaejae",
    "wof:placetype":"locality"
},
  "geometry": {"coordinates":[128.85509999999999,37.6117],"type":"Point"}
}