{
  "type": "Feature",
  "properties": {
    "gn:admin1_code":"13.0",
    "gn:asciiname":"Dongmak",
    "gn:country_code":"KR",
    "gn:dem":32,
    "gn:feature_class":"P",
    "gn:feature_code":"PPL",
    "gn:name":"Dongmak",
    "gn:population":0,
    "gn:timezone":"Asia/Seoul",
    "iso:country":"KR",
    "name:kor_x_preferred":[
        "\ub3d9\ub9c9"
    ],
    "name:und_x_variant":[
        "Dongmak"
    ],
    "wof:name":"Dongmak",
    "wof:placetype":"locality"
},
  "geometry": {"coordinates":[127.23480000000001,37.5635],"type":"Point"}
}