{
  "type": "Feature",
  "properties": {
    "gn:admin1_code":"16.0",
    "gn:asciiname":"Maehyol-li",
    "gn:country_code":"KR",
    "gn:dem":199,
    "gn:feature_class":"P",
    "gn:feature_code":"PPL",
    "gn:name":"Maehy\u014fl-li",
    "gn:population":0,
    "gn:timezone":"Asia/Seoul",
    "iso:country":"KR",
    "name:kor_x_preferred":[
        "\ub9e4\ud604\ub9ac"
    ],
    "name:kor_x_variant":[
        "Maehy\u014fl-li"
    ],
    "wof:name":"Maehyol-li",
    "wof:placetype":"locality"
},
  "geometry": {"coordinates":[127.27056,34.79691],"type":"Point"}
}