{
  "type": "Feature",
  "properties": {
    "gn:admin1_code":"3.0",
    "gn:asciiname":"Panghyol-li",
    "gn:country_code":"KR",
    "gn:dem":215,
    "gn:feature_class":"P",
    "gn:feature_code":"PPLL",
    "gn:name":"Panghy\u014fl-li",
    "gn:population":0,
    "gn:timezone":"Asia/Seoul",
    "iso:country":"KR",
    "name:und_x_variant":[
        "\ubc29\ud604\ub9ac",
        "Panghy\u014fl-li"
    ],
    "wof:name":"Panghyol-li",
    "wof:placetype":"locality"
},
  "geometry": {"coordinates":[127.1384,35.57181],"type":"Point"}
}