{
  "type": "Feature",
  "properties": {
    "gn:admin1_code":"13.0",
    "gn:asciiname":"Wagok",
    "gn:country_code":"KR",
    "gn:dem":24,
    "gn:feature_class":"P",
    "gn:feature_code":"PPL",
    "gn:name":"Wagok",
    "gn:population":0,
    "gn:timezone":"Asia/Seoul",
    "iso:country":"KR",
    "name:kor_x_preferred":[
        "\uc640\uace1"
    ],
    "name:und_x_variant":[
        "Gakoku",
        "Wakok",
        "Wagok",
        "Waggok"
    ],
    "wof:name":"Wagok",
    "wof:placetype":"locality"
},
  "geometry": {"coordinates":[127.09310000000001,37.09147],"type":"Point"}
}