{
  "type": "Feature",
  "properties": {
    "gn:admin1_code":"5.0",
    "gn:asciiname":"Motinmal",
    "gn:country_code":"KR",
    "gn:dem":79,
    "gn:feature_class":"P",
    "gn:feature_code":"PPL",
    "gn:name":"Motinmal",
    "gn:population":0,
    "gn:timezone":"Asia/Seoul",
    "iso:country":"KR",
    "name:kor_x_preferred":[
        "\ubaa8\ud2f4\ub9d0"
    ],
    "wof:name":"Motinmal",
    "wof:placetype":"locality"
},
  "geometry": {"coordinates":[127.89142,37.01374000000001],"type":"Point"}
}