{
  "type": "Feature",
  "properties": {
    "gn:admin1_code":"14.0",
    "gn:asciiname":"Jeongjamaeul",
    "gn:country_code":"KR",
    "gn:dem":117,
    "gn:feature_class":"P",
    "gn:feature_code":"PPL",
    "gn:name":"Jeongjamaeul",
    "gn:population":0,
    "gn:timezone":"Asia/Seoul",
    "iso:country":"KR",
    "name:kor_x_preferred":[
        "\uc815\uc790\ub9c8\uc744"
    ],
    "wof:name":"Jeongjamaeul",
    "wof:placetype":"locality"
},
  "geometry": {"coordinates":[129.31159,35.78138],"type":"Point"}
}