{
  "type": "Feature",
  "properties": {
    "gn:admin1_code":"16.0",
    "gn:asciiname":"Gokgang",
    "gn:country_code":"KR",
    "gn:dem":22,
    "gn:feature_class":"P",
    "gn:feature_code":"PPL",
    "gn:name":"Gokgang",
    "gn:population":0,
    "gn:timezone":"Asia/Seoul",
    "iso:country":"KR",
    "name:kor_x_preferred":[
        "\uace1\uac15"
    ],
    "name:und_x_variant":[
        "Kokkang-ni",
        "Kokang",
        "Gokgang"
    ],
    "wof:name":"Gokgang",
    "wof:placetype":"locality"
},
  "geometry": {"coordinates":[127.44667,34.64115],"type":"Point"}
}