{
  "type": "Feature",
  "properties": {
    "gn:admin1_code":"3.0",
    "gn:asciiname":"Kyo-dong",
    "gn:country_code":"KR",
    "gn:dem":331,
    "gn:feature_class":"P",
    "gn:feature_code":"PPL",
    "gn:name":"Kyo-dong",
    "gn:population":0,
    "gn:timezone":"Asia/Seoul",
    "iso:country":"KR",
    "name:und_x_variant":[
        "Kyo-gol",
        "\uad50\ub3d9",
        "Kyo-dong"
    ],
    "wof:name":"Kyo-dong",
    "wof:placetype":"locality"
},
  "geometry": {"coordinates":[127.58669,35.90798],"type":"Point"}
}