{
  "type": "Feature",
  "properties": {
    "gn:admin1_code":"13.0",
    "gn:asciiname":"Gajaeul",
    "gn:country_code":"KR",
    "gn:dem":150,
    "gn:feature_class":"P",
    "gn:feature_code":"PPL",
    "gn:name":"Gajaeul",
    "gn:population":0,
    "gn:timezone":"Asia/Seoul",
    "iso:country":"KR",
    "name:kor_x_preferred":[
        "\uac00\uc7ac\uc6b8"
    ],
    "name:und_x_variant":[
        "Kajaeul",
        "Gajaeul"
    ],
    "wof:name":"Gajaeul",
    "wof:placetype":"locality"
},
  "geometry": {"coordinates":[127.21297,37.84755],"type":"Point"}
}