{
  "type": "Feature",
  "properties": {
    "gn:admin1_code":"16.0",
    "gn:asciiname":"Yondong-ni",
    "gn:cc2":"KR",
    "gn:country_code":"KR",
    "gn:dem":10,
    "gn:feature_class":"P",
    "gn:feature_code":"PPL",
    "gn:name":"Y\u014fndong-ni",
    "gn:population":0,
    "gn:timezone":"Asia/Seoul",
    "iso:country":"KR",
    "name:und_x_variant":[
        "Rend\u014d-ri",
        "Y\u014fndong-ni"
    ],
    "wof:name":"Yondong-ni",
    "wof:placetype":"locality"
},
  "geometry": {"coordinates":[126.16388999999999,34.38194],"type":"Point"}
}