{
  "type": "Feature",
  "properties": {
    "gn:admin1_code":"5.0",
    "gn:asciiname":"Jigaemit",
    "gn:country_code":"KR",
    "gn:dem":104,
    "gn:feature_class":"P",
    "gn:feature_code":"PPL",
    "gn:name":"Jigaemit",
    "gn:population":0,
    "gn:timezone":"Asia/Seoul",
    "iso:country":"KR",
    "name:kor_x_preferred":[
        "\uc9c0\uac1c\ubc11"
    ],
    "wof:name":"Jigaemit",
    "wof:placetype":"locality"
},
  "geometry": {"coordinates":[127.77754,37.09679000000001],"type":"Point"}
}