{
  "type": "Feature",
  "properties": {
    "gn:admin1_code":"14.0",
    "gn:asciiname":"Chungt'o",
    "gn:country_code":"KR",
    "gn:dem":114,
    "gn:feature_class":"P",
    "gn:feature_code":"PPL",
    "gn:name":"Chungt\u2019\u014f",
    "gn:population":0,
    "gn:timezone":"Asia/Seoul",
    "iso:country":"KR",
    "name:und_x_variant":[
        "\uc911\ud130",
        "Chungt\u2019\u014f"
    ],
    "wof:name":"Chungt'o",
    "wof:placetype":"locality"
},
  "geometry": {"coordinates":[128.28826000000001,35.88473],"type":"Point"}
}