{
  "type": "Feature",
  "properties": {
    "gn:admin1_code":"14.0",
    "gn:asciiname":"Buzan",
    "gn:country_code":"KR",
    "gn:dem":544,
    "gn:feature_class":"P",
    "gn:feature_code":"PPL",
    "gn:name":"Buzan",
    "gn:population":0,
    "gn:timezone":"Asia/Seoul",
    "iso:country":"KR",
    "name:und_x_variant":[
        "P\u2019osan-dong",
        "Busan-d\u014d",
        "P\u2019osal-li",
        "\ud3ec\uc0b0",
        "P\u2019osan"
    ],
    "wof:name":"Buzan",
    "wof:placetype":"locality"
},
  "geometry": {"coordinates":[129.21090000000001,36.5061],"type":"Point"}
}