{
  "type": "Feature",
  "properties": {
    "gn:admin1_code":"20.0",
    "gn:asciiname":"Ch'ugye",
    "gn:country_code":"KR",
    "gn:dem":185,
    "gn:feature_class":"P",
    "gn:feature_code":"PPL",
    "gn:name":"Ch\u2019ugye",
    "gn:population":0,
    "gn:timezone":"Asia/Seoul",
    "iso:country":"KR",
    "name:und_x_variant":[
        "Ch\u2019uge-ri",
        "Ch\u2019ugye"
    ],
    "wof:name":"Ch'ugye",
    "wof:placetype":"locality"
},
  "geometry": {"coordinates":[128.23333,35.01667],"type":"Point"}
}