{
  "type": "Feature",
  "properties": {
    "gn:admin1_code":"6.0",
    "gn:asciiname":"Josanggol",
    "gn:country_code":"KR",
    "gn:dem":324,
    "gn:feature_class":"P",
    "gn:feature_code":"PPL",
    "gn:name":"Josanggol",
    "gn:population":0,
    "gn:timezone":"Asia/Seoul",
    "iso:country":"KR",
    "name:kor_x_preferred":[
        "\uc870\uc0c1\uace8"
    ],
    "name:und_x_variant":[
        "Chosang-gol",
        "Josanggol"
    ],
    "wof:name":"Josanggol",
    "wof:placetype":"locality"
},
  "geometry": {"coordinates":[128.14391000000001,37.76995],"type":"Point"}
}