{
  "type": "Feature",
  "properties": {
    "gn:admin1_code":"17.0",
    "gn:asciiname":"Gungni",
    "gn:country_code":"KR",
    "gn:dem":42,
    "gn:feature_class":"P",
    "gn:feature_code":"PPL",
    "gn:name":"Gungni",
    "gn:population":0,
    "gn:timezone":"Asia/Seoul",
    "iso:country":"KR",
    "name:kor_x_preferred":[
        "\uad81\ub9ac"
    ],
    "wof:name":"Gungni",
    "wof:placetype":"locality"
},
  "geometry": {"coordinates":[127.15962,36.72805],"type":"Point"}
}