{
  "type": "Feature",
  "properties": {
    "gn:admin1_code":"14.0",
    "gn:asciiname":"Unbong",
    "gn:country_code":"KR",
    "gn:dem":311,
    "gn:feature_class":"P",
    "gn:feature_code":"PPL",
    "gn:name":"Unbong",
    "gn:population":0,
    "gn:timezone":"Asia/Seoul",
    "iso:country":"KR",
    "name:und_x_variant":[
        "\uc6b4\ubd09",
        "Unbong"
    ],
    "wof:name":"Unbong",
    "wof:placetype":"locality"
},
  "geometry": {"coordinates":[128.25069999999999,36.0547],"type":"Point"}
}