{
  "type": "Feature",
  "properties": {
    "gn:admin1_code":"6.0",
    "gn:asciiname":"Seonpyeong",
    "gn:country_code":"KR",
    "gn:dem":185,
    "gn:feature_class":"P",
    "gn:feature_code":"PPL",
    "gn:name":"Seonpyeong",
    "gn:population":0,
    "gn:timezone":"Asia/Seoul",
    "iso:country":"KR",
    "name:kor_x_preferred":[
        "\uc120\ud3c9"
    ],
    "name:kor_x_variant":[
        "S\u014fnp\u2019y\u014fng"
    ],
    "wof:name":"Seonpyeong",
    "wof:placetype":"locality"
},
  "geometry": {"coordinates":[128.01840000000001,37.8374],"type":"Point"}
}