{
  "type": "Feature",
  "properties": {
    "gn:admin1_code":"13.0",
    "gn:asciiname":"Chomal",
    "gn:country_code":"KR",
    "gn:dem":57,
    "gn:feature_class":"P",
    "gn:feature_code":"PPL",
    "gn:name":"Chomal",
    "gn:population":0,
    "gn:timezone":"Asia/Seoul",
    "iso:country":"KR",
    "name:und_x_variant":[
        "Soch\u2019on-ni",
        "Ch\u2019och\u2019on-ni",
        "\ucd08\ub9d0",
        "Ch\u2019o-mal",
        "Chomal"
    ],
    "wof:name":"Chomal",
    "wof:placetype":"locality"
},
  "geometry": {"coordinates":[127.06927,37.9941],"type":"Point"}
}