{
  "type": "Feature",
  "properties": {
    "gn:admin1_code":"13.0",
    "gn:asciiname":"Ambangjukdeul",
    "gn:country_code":"KR",
    "gn:dem":24,
    "gn:feature_class":"P",
    "gn:feature_code":"PPL",
    "gn:name":"Ambangjukdeul",
    "gn:population":0,
    "gn:timezone":"Asia/Seoul",
    "iso:country":"KR",
    "name:kor_x_preferred":[
        "\uc554\ubc29\uc8fd\ub4e4"
    ],
    "wof:name":"Ambangjukdeul",
    "wof:placetype":"locality"
},
  "geometry": {"coordinates":[126.78258999999998,37.41684],"type":"Point"}
}