{
  "type": "Feature",
  "properties": {
    "gn:admin1_code":"20.0",
    "gn:asciiname":"Tokp'yong",
    "gn:country_code":"KR",
    "gn:dem":247,
    "gn:feature_class":"P",
    "gn:feature_code":"PPL",
    "gn:name":"T\u014fkp\u2019y\u014fng",
    "gn:population":0,
    "gn:timezone":"Asia/Seoul",
    "iso:country":"KR",
    "name:und_x_variant":[
        "\ub355\ud3c9",
        "T\u014fkp\u2019y\u014fng"
    ],
    "wof:name":"Tokp'yong",
    "wof:placetype":"locality"
},
  "geometry": {"coordinates":[127.67507000000001,35.5268],"type":"Point"}
}