{
  "type": "Feature",
  "properties": {
    "gn:admin1_code":"6.0",
    "gn:asciiname":"Pungamdong",
    "gn:country_code":"KR",
    "gn:dem":44,
    "gn:feature_class":"P",
    "gn:feature_code":"PPL",
    "gn:name":"Pungamdong",
    "gn:population":0,
    "gn:timezone":"Asia/Seoul",
    "iso:country":"KR",
    "name:kor_x_preferred":[
        "\ud48d\uc554\ub3d9"
    ],
    "name:und_x_variant":[
        "P\u2019ungam-dong",
        "Pungamdong"
    ],
    "wof:name":"Pungamdong",
    "wof:placetype":"locality"
},
  "geometry": {"coordinates":[128.68554,38.00633],"type":"Point"}
}