{
  "type": "Feature",
  "properties": {
    "gn:admin1_code":"14.0",
    "gn:asciiname":"K'ongbak-kol",
    "gn:country_code":"KR",
    "gn:dem":322,
    "gn:feature_class":"P",
    "gn:feature_code":"PPL",
    "gn:name":"K\u2019ongbak-kol",
    "gn:population":0,
    "gn:timezone":"Asia/Seoul",
    "iso:country":"KR",
    "name:und_x_variant":[
        "K\u2019ongbat-kol",
        "K\u2019ongbak-kol"
    ],
    "wof:name":"K'ongbak-kol",
    "wof:placetype":"locality"
},
  "geometry": {"coordinates":[129.03649999999999,36.2541],"type":"Point"}
}