{
  "type": "Feature",
  "properties": {
    "gn:admin1_code":"14.0",
    "gn:asciiname":"Gaseop",
    "gn:country_code":"KR",
    "gn:dem":262,
    "gn:feature_class":"P",
    "gn:feature_code":"PPL",
    "gn:name":"Gaseop",
    "gn:population":0,
    "gn:timezone":"Asia/Seoul",
    "iso:country":"KR",
    "name:kor_x_preferred":[
        "\uac00\uc12d"
    ],
    "name:und_x_variant":[
        "Kas\u014fm-ni",
        "Kas\u014fp",
        "Kas\u014fm",
        "Gaseop"
    ],
    "wof:name":"Gaseop",
    "wof:placetype":"locality"
},
  "geometry": {"coordinates":[128.1799,36.68048],"type":"Point"}
}