{
  "type": "Feature",
  "properties": {
    "gn:admin1_code":"6.0",
    "gn:asciiname":"Tokko-ri",
    "gn:country_code":"KR",
    "gn:dem":121,
    "gn:feature_class":"P",
    "gn:feature_code":"PPL",
    "gn:name":"T\u014fkk\u014f-ri",
    "gn:population":0,
    "gn:timezone":"Asia/Seoul",
    "iso:country":"KR",
    "name:kor_x_preferred":[
        "\ub355\uac70\ub9ac"
    ],
    "name:kor_x_variant":[
        "T\u014fkk\u014f-ri"
    ],
    "wof:name":"Tokko-ri",
    "wof:placetype":"locality"
},
  "geometry": {"coordinates":[127.7654,37.6603],"type":"Point"}
}