{
  "type": "Feature",
  "properties": {
    "gn:admin1_code":"19.0",
    "gn:asciiname":"Oriul",
    "gn:country_code":"KR",
    "gn:dem":106,
    "gn:feature_class":"P",
    "gn:feature_code":"PPL",
    "gn:name":"Oriul",
    "gn:population":0,
    "gn:timezone":"Asia/Seoul",
    "iso:country":"KR",
    "name:kor_x_preferred":[
        "\uc624\ub9ac\uc6b8"
    ],
    "wof:name":"Oriul",
    "wof:placetype":"locality"
},
  "geometry": {"coordinates":[127.31726,36.22372],"type":"Point"}
}