{
  "type": "Feature",
  "properties": {
    "gn:admin1_code":"16.0",
    "gn:asciiname":"Balsan",
    "gn:country_code":"KR",
    "gn:dem":43,
    "gn:feature_class":"P",
    "gn:feature_code":"PPL",
    "gn:name":"Balsan",
    "gn:population":0,
    "gn:timezone":"Asia/Seoul",
    "iso:country":"KR",
    "name:und_x_variant":[
        "\ubc1c\uc0b0",
        "Palsan",
        "Balsan"
    ],
    "wof:name":"Balsan",
    "wof:placetype":"locality"
},
  "geometry": {"coordinates":[126.73222,34.64472],"type":"Point"}
}