{
  "type": "Feature",
  "properties": {
    "gn:admin1_code":"17.0",
    "gn:asciiname":"Baenggol",
    "gn:country_code":"KR",
    "gn:dem":51,
    "gn:feature_class":"P",
    "gn:feature_code":"PPL",
    "gn:name":"Baenggol",
    "gn:population":0,
    "gn:timezone":"Asia/Seoul",
    "iso:country":"KR",
    "name:kor_x_preferred":[
        "\ubc45\uace8"
    ],
    "wof:name":"Baenggol",
    "wof:placetype":"locality"
},
  "geometry": {"coordinates":[127.16191999999999,36.72309],"type":"Point"}
}