{
  "type": "Feature",
  "properties": {
    "gn:admin1_code":"14.0",
    "gn:asciiname":"Nambangdong",
    "gn:country_code":"KR",
    "gn:dem":175,
    "gn:feature_class":"P",
    "gn:feature_code":"PPL",
    "gn:name":"Nambangdong",
    "gn:population":0,
    "gn:timezone":"Asia/Seoul",
    "iso:country":"KR",
    "name:kor_x_preferred":[
        "\ub0a8\ubc29\ub3d9"
    ],
    "wof:name":"Nambangdong",
    "wof:placetype":"locality"
},
  "geometry": {"coordinates":[128.67796000000001,36.09548],"type":"Point"}
}