{
  "type": "Feature",
  "properties": {
    "gn:admin1_code":"12.0",
    "gn:asciiname":"Unmaul",
    "gn:country_code":"KR",
    "gn:dem":20,
    "gn:feature_class":"P",
    "gn:feature_code":"PPL",
    "gn:name":"Unma\u016dl",
    "gn:population":0,
    "gn:timezone":"Asia/Seoul",
    "iso:country":"KR",
    "name:kor_x_preferred":[
        "\uc6c3\ub9c8\uc744"
    ],
    "name:kor_x_variant":[
        "Unma\u016dl"
    ],
    "wof:name":"Unmaul",
    "wof:placetype":"locality"
},
  "geometry": {"coordinates":[126.66556,37.64028],"type":"Point"}
}