{
  "type": "Feature",
  "properties": {
    "gn:admin1_code":"13.0",
    "gn:asciiname":"Kwangdong-ni",
    "gn:country_code":"KR",
    "gn:dem":64,
    "gn:feature_class":"P",
    "gn:feature_code":"PPLL",
    "gn:name":"Kwangdong-ni",
    "gn:population":0,
    "gn:timezone":"Asia/Seoul",
    "iso:country":"KR",
    "name:und_x_variant":[
        "\uad11\ub3d9\ub9ac",
        "Gwangdong-ri",
        "Kwangdong-ni"
    ],
    "wof:name":"Kwangdong-ni",
    "wof:placetype":"locality"
},
  "geometry": {"coordinates":[127.31833,37.46389],"type":"Point"}
}