{
  "type": "Feature",
  "properties": {
    "gn:admin1_code":"21.0",
    "gn:asciiname":"Soepyeong",
    "gn:country_code":"KR",
    "gn:dem":150,
    "gn:feature_class":"P",
    "gn:feature_code":"PPL",
    "gn:name":"Soepyeong",
    "gn:population":0,
    "gn:timezone":"Asia/Seoul",
    "iso:country":"KR",
    "name:kor_x_preferred":[
        "\uc1e0\ud3c9"
    ],
    "wof:name":"Soepyeong",
    "wof:placetype":"locality"
},
  "geometry": {"coordinates":[129.42923999999999,35.55826],"type":"Point"}
}