{
  "type": "Feature",
  "properties": {
    "gn:admin1_code":"20.0",
    "gn:asciiname":"Sonaesil",
    "gn:country_code":"KR",
    "gn:dem":227,
    "gn:feature_class":"P",
    "gn:feature_code":"PPL",
    "gn:name":"Sonaesil",
    "gn:population":0,
    "gn:timezone":"Asia/Seoul",
    "iso:country":"KR",
    "name:und_x_variant":[
        "\uc18c\ub0b4\uc2e4",
        "Sonaesil"
    ],
    "wof:name":"Sonaesil",
    "wof:placetype":"locality"
},
  "geometry": {"coordinates":[127.92323,35.66515],"type":"Point"}
}