{
  "type": "Feature",
  "properties": {
    "gn:admin1_code":"5.0",
    "gn:asciiname":"Geureoksil",
    "gn:country_code":"KR",
    "gn:dem":333,
    "gn:feature_class":"P",
    "gn:feature_code":"PPL",
    "gn:name":"Geureoksil",
    "gn:population":0,
    "gn:timezone":"Asia/Seoul",
    "iso:country":"KR",
    "name:kor_x_preferred":[
        "\uae00\uc5b5\uc2e4"
    ],
    "wof:name":"Geureoksil",
    "wof:placetype":"locality"
},
  "geometry": {"coordinates":[127.6823,36.76094000000001],"type":"Point"}
}