{
  "type": "Feature",
  "properties": {
    "gn:admin1_code":"14.0",
    "gn:asciiname":"Dotonggol",
    "gn:country_code":"KR",
    "gn:dem":225,
    "gn:feature_class":"P",
    "gn:feature_code":"PPL",
    "gn:name":"Dotonggol",
    "gn:population":0,
    "gn:timezone":"Asia/Seoul",
    "iso:country":"KR",
    "name:kor_x_preferred":[
        "\ub3c4\ud1b5\uace8"
    ],
    "name:und_x_variant":[
        "Tot\u2019ong-gol"
    ],
    "wof:name":"Dotonggol",
    "wof:placetype":"locality"
},
  "geometry": {"coordinates":[129.38971999999998,35.84962],"type":"Point"}
}