{
  "type": "Feature",
  "properties": {
    "gn:admin1_code":"3.0",
    "gn:asciiname":"Songjong-ni",
    "gn:country_code":"KR",
    "gn:dem":186,
    "gn:feature_class":"P",
    "gn:feature_code":"PPL",
    "gn:name":"Songj\u014fng-ni",
    "gn:population":0,
    "gn:timezone":"Asia/Seoul",
    "iso:country":"KR",
    "name:eng_x_preferred":[
        "Songjong"
    ],
    "name:eng_x_variant":[
        "Songjong-ni"
    ],
    "name:und_x_variant":[
        "\uc1a1\uc815\ub9ac",
        "Songj\u014fng-ni"
    ],
    "wof:name":"Songjong",
    "wof:placetype":"locality"
},
  "geometry": {"coordinates":[127.29778,35.82704],"type":"Point"}
}