{
  "type": "Feature",
  "properties": {
    "gn:admin1_code":"13.0",
    "gn:asciiname":"Umigi",
    "gn:country_code":"KR",
    "gn:dem":82,
    "gn:feature_class":"P",
    "gn:feature_code":"PPL",
    "gn:name":"Umigi",
    "gn:population":0,
    "gn:timezone":"Asia/Seoul",
    "iso:country":"KR",
    "name:kor_x_preferred":[
        "\uc6b0\ubbf8\uae30"
    ],
    "wof:name":"Umigi",
    "wof:placetype":"locality"
},
  "geometry": {"coordinates":[127.64892999999999,37.239],"type":"Point"}
}