{
  "type": "Feature",
  "properties": {
    "gn:admin1_code":"14.0",
    "gn:asciiname":"Songch'ol-li",
    "gn:country_code":"KR",
    "gn:dem":95,
    "gn:feature_class":"P",
    "gn:feature_code":"PPLL",
    "gn:name":"Songch\u2019\u014fl-li",
    "gn:population":0,
    "gn:timezone":"Asia/Seoul",
    "iso:country":"KR",
    "name:und_x_variant":[
        "\uc1a1\ucc9c\ub9ac",
        "Songch\u2019\u014fl-li"
    ],
    "wof:name":"Songch'ol-li",
    "wof:placetype":"locality"
},
  "geometry": {"coordinates":[128.27033,36.16045],"type":"Point"}
}