{
  "type": "Feature",
  "properties": {
    "gn:admin1_code":"16.0",
    "gn:asciiname":"Tonmong-ni",
    "gn:cc2":"KR",
    "gn:country_code":"KR",
    "gn:dem":15,
    "gn:feature_class":"P",
    "gn:feature_code":"PPL",
    "gn:name":"Tonmong-ni",
    "gn:population":0,
    "gn:timezone":"Asia/Seoul",
    "iso:country":"KR",
    "name:eng_x_preferred":[
        "Tonmong"
    ],
    "name:eng_x_variant":[
        "Tonmong-ni"
    ],
    "name:und_x_variant":[
        "Tonmok",
        "Tonmong-ni"
    ],
    "wof:name":"Tonmong",
    "wof:placetype":"locality"
},
  "geometry": {"coordinates":[125.8275,34.60722],"type":"Point"}
}