{
  "type": "Feature",
  "properties": {
    "gn:admin1_code":"5.0",
    "gn:asciiname":"Puk-kol",
    "gn:country_code":"KR",
    "gn:dem":167,
    "gn:feature_class":"P",
    "gn:feature_code":"PPL",
    "gn:name":"Puk-kol",
    "gn:population":0,
    "gn:timezone":"Asia/Seoul",
    "iso:country":"KR",
    "name:und_x_variant":[
        "\ubd93\uace8",
        "Puk-kol"
    ],
    "wof:name":"Puk-kol",
    "wof:placetype":"locality"
},
  "geometry": {"coordinates":[127.7851,36.3959],"type":"Point"}
}