{
  "type": "Feature",
  "properties": {
    "gn:admin1_code":"6.0",
    "gn:asciiname":"Wolbu-dong",
    "gn:country_code":"KR",
    "gn:dem":597,
    "gn:feature_class":"P",
    "gn:feature_code":"PPL",
    "gn:name":"W\u014flbu-dong",
    "gn:population":0,
    "gn:timezone":"Asia/Seoul",
    "iso:country":"KR",
    "name:kor_x_preferred":[
        "\uc6d4\ubd80\ub3d9"
    ],
    "name:kor_x_variant":[
        "W\u014flbu-dong"
    ],
    "wof:name":"Wolbu-dong",
    "wof:placetype":"locality"
},
  "geometry": {"coordinates":[128.73769999999999,37.4891],"type":"Point"}
}