{
  "type": "Feature",
  "properties": {
    "gn:admin1_code":"16.0",
    "gn:asciiname":"Osong-dong",
    "gn:country_code":"KR",
    "gn:dem":25,
    "gn:feature_class":"P",
    "gn:feature_code":"PPL",
    "gn:name":"Os\u014fng-dong",
    "gn:population":0,
    "gn:timezone":"Asia/Seoul",
    "iso:country":"KR",
    "name:kor_x_preferred":[
        "Os\u014fng-dong"
    ],
    "wof:name":"Osong-dong",
    "wof:placetype":"locality"
},
  "geometry": {"coordinates":[126.79083,34.59722],"type":"Point"}
}