{
  "type": "Feature",
  "properties": {
    "gn:admin1_code":"20.0",
    "gn:asciiname":"Sin'go-ri",
    "gn:country_code":"KR",
    "gn:dem":46,
    "gn:feature_class":"P",
    "gn:feature_code":"PPL",
    "gn:name":"Sin\u2019g\u014f-ri",
    "gn:population":0,
    "gn:timezone":"Asia/Seoul",
    "iso:country":"KR",
    "name:und_x_variant":[
        "\uc2e0\uac70\ub9ac",
        "Sin\u2019g\u014f-ri"
    ],
    "wof:name":"Sin'go-ri",
    "wof:placetype":"locality"
},
  "geometry": {"coordinates":[128.47891999999999,34.77881],"type":"Point"}
}