{
  "type": "Feature",
  "properties": {
    "gn:admin1_code":"13.0",
    "gn:asciiname":"Dongchang",
    "gn:country_code":"KR",
    "gn:dem":27,
    "gn:feature_class":"P",
    "gn:feature_code":"PPL",
    "gn:name":"Dongchang",
    "gn:population":0,
    "gn:timezone":"Asia/Seoul",
    "iso:country":"KR",
    "name:ceb_x_preferred":[
        "Dongchang"
    ],
    "name:deu_x_preferred":[
        "Dongchang"
    ],
    "name:kor_x_preferred":[
        "\ub3d9\ucc3d"
    ],
    "name:und_x_variant":[
        "\ub3d9\ucc3d\ub9ac",
        "Tongch\u2019ang-ni",
        "Dongchang"
    ],
    "wof:name":"Dongchang",
    "wof:placetype":"locality"
},
  "geometry": {"coordinates":[127.03573,36.97195],"type":"Point"}
}