{
  "type": "Feature",
  "properties": {
    "gn:admin1_code":"13.0",
    "gn:admin2_code":"P'aju-si",
    "gn:asciiname":"Gasinae",
    "gn:country_code":"KR",
    "gn:dem":28,
    "gn:feature_class":"P",
    "gn:feature_code":"PPL",
    "gn:name":"Gasinae",
    "gn:population":0,
    "gn:timezone":"Asia/Seoul",
    "iso:country":"KR",
    "name:kor_x_preferred":[
        "\uac00\uc2dc\ub0b4"
    ],
    "name:und_x_variant":[
        "Kasinae"
    ],
    "wof:name":"Gasinae",
    "wof:placetype":"locality"
},
  "geometry": {"coordinates":[126.71662000000001,37.78127],"type":"Point"}
}