{
  "type": "Feature",
  "properties": {
    "gn:admin1_code":"13.0",
    "gn:asciiname":"Punt'ogol",
    "gn:country_code":"KR",
    "gn:dem":26,
    "gn:feature_class":"P",
    "gn:feature_code":"PPL",
    "gn:name":"Punt\u2019ogol",
    "gn:population":0,
    "gn:timezone":"Asia/Seoul",
    "iso:country":"KR",
    "name:kor_x_preferred":[
        "\ubd84\ud1a0\uace8"
    ],
    "name:kor_x_variant":[
        "Punt\u2019ogol"
    ],
    "wof:name":"Punt'ogol",
    "wof:placetype":"locality"
},
  "geometry": {"coordinates":[126.80972,37.06917],"type":"Point"}
}