{
  "type": "Feature",
  "properties": {
    "gn:admin1_code":"17.0",
    "gn:asciiname":"Yang-ch'on",
    "gn:country_code":"KR",
    "gn:dem":11,
    "gn:feature_class":"P",
    "gn:feature_code":"PPL",
    "gn:name":"Yang-ch\u2019on",
    "gn:population":0,
    "gn:timezone":"Asia/Seoul",
    "iso:country":"KR",
    "name:und_x_variant":[
        "\uc591\ucd0c",
        "Yang-ch\u2019on"
    ],
    "wof:name":"Yang-ch'on",
    "wof:placetype":"locality"
},
  "geometry": {"coordinates":[126.75449999999999,36.7544],"type":"Point"}
}