{
  "type": "Feature",
  "properties": {
    "gn:admin1_code":"20.0",
    "gn:asciiname":"Chisep'o-ri",
    "gn:country_code":"KR",
    "gn:dem":18,
    "gn:feature_class":"P",
    "gn:feature_code":"PPL",
    "gn:name":"Chisep\u2019o-ri",
    "gn:population":0,
    "gn:timezone":"Asia/Seoul",
    "iso:country":"KR",
    "name:und_x_variant":[
        "Chisep\u2019o",
        "Chisep\u2019o-ri"
    ],
    "wof:name":"Chisep'o-ri",
    "wof:placetype":"locality"
},
  "geometry": {"coordinates":[128.70972,34.82556],"type":"Point"}
}