{
  "type": "Feature",
  "properties": {
    "gn:admin1_code":"16.0",
    "gn:asciiname":"Jangsu",
    "gn:country_code":"KR",
    "gn:dem":56,
    "gn:feature_class":"P",
    "gn:feature_code":"PPL",
    "gn:name":"Jangsu",
    "gn:population":0,
    "gn:timezone":"Asia/Seoul",
    "iso:country":"KR",
    "name:und_x_variant":[
        "\uc7a5\uc218",
        "Changsu",
        "Jangsu"
    ],
    "wof:name":"Jangsu",
    "wof:placetype":"locality"
},
  "geometry": {"coordinates":[126.60907,34.69823],"type":"Point"}
}