{
  "type": "Feature",
  "properties": {
    "gn:admin1_code":"13.0",
    "gn:admin2_code":"P'aju-si",
    "gn:asciiname":"Gonjiul",
    "gn:country_code":"KR",
    "gn:dem":44,
    "gn:feature_class":"P",
    "gn:feature_code":"PPL",
    "gn:name":"Gonjiul",
    "gn:population":0,
    "gn:timezone":"Asia/Seoul",
    "iso:country":"KR",
    "name:kor_x_preferred":[
        "\uace4\uc9c0\uc6b8"
    ],
    "name:und_x_variant":[
        "Konjiul"
    ],
    "wof:name":"Gonjiul",
    "wof:placetype":"locality"
},
  "geometry": {"coordinates":[126.85272999999999,37.9526],"type":"Point"}
}