{
  "type": "Feature",
  "properties": {
    "gn:country":"KR",
    "gn:fcode":"ADM3",
    "gn:population":0,
    "iso:country":"KR",
    "name:ceb_x_preferred":[
        "Dasa-eup"
    ],
    "name:eng_x_preferred":[
        "Dasa-eup"
    ],
    "name:eng_x_variant":[
        "Dasa"
    ],
    "name:fas_x_preferred":[
        "\u062f\u0627\u0633\u0627-\u0648\u067e"
    ],
    "name:jpn_x_preferred":[
        "\u591a\u65af\u9091"
    ],
    "name:kor_x_preferred":[
        "\ub2e4\uc0ac\uc74d"
    ],
    "name:swe_x_preferred":[
        "Dasa-eup"
    ],
    "name:zho_x_preferred":[
        "\u591a\u65af\u9091"
    ],
    "qs:name":"Tasa-\u016dp",
    "qs:photos_9r":0,
    "qs:photos_sr":0,
    "qs:pop_sr":"0",
    "wd:wordcount":65,
    "wof:name":"Tasa-\u016dp",
    "wof:placetype":"localadmin",
    "wof:population":0
},
  "geometry": {"coordinates":[128.46886000000001,35.87545],"type":"Point"}
}