{
  "type": "Feature",
  "properties": {
    "gn:admin1_code":"16.0",
    "gn:asciiname":"Ch'odang",
    "gn:country_code":"KR",
    "gn:dem":24,
    "gn:feature_class":"P",
    "gn:feature_code":"PPL",
    "gn:name":"Ch\u2019odang",
    "gn:population":0,
    "gn:timezone":"Asia/Seoul",
    "iso:country":"KR",
    "name:kor_x_preferred":[
        "Ch\u2019odang"
    ],
    "wof:name":"Ch'odang",
    "wof:placetype":"locality"
},
  "geometry": {"coordinates":[126.87944,34.49528],"type":"Point"}
}