{
  "type": "Feature",
  "properties": {
    "gn:admin1_code":"19.0",
    "gn:asciiname":"Araetchangmyeong",
    "gn:country_code":"KR",
    "gn:dem":76,
    "gn:feature_class":"P",
    "gn:feature_code":"PPL",
    "gn:name":"Araetchangmyeong",
    "gn:population":0,
    "gn:timezone":"Asia/Seoul",
    "iso:country":"KR",
    "name:kor_x_preferred":[
        "\uc544\ub7ab\ucc3d\uba85"
    ],
    "wof:name":"Araetchangmyeong",
    "wof:placetype":"locality"
},
  "geometry": {"coordinates":[127.38146999999999,36.28552],"type":"Point"}
}