{
  "type": "Feature",
  "properties": {
    "gn:admin1_code":"16.0",
    "gn:asciiname":"Saemmal",
    "gn:country_code":"KR",
    "gn:dem":57,
    "gn:feature_class":"P",
    "gn:feature_code":"PPL",
    "gn:name":"Saemmal",
    "gn:population":0,
    "gn:timezone":"Asia/Seoul",
    "iso:country":"KR",
    "name:kor_x_preferred":[
        "\uc0d8\ub9d0"
    ],
    "wof:name":"Saemmal",
    "wof:placetype":"locality"
},
  "geometry": {"coordinates":[126.80446000000001,34.95123],"type":"Point"}
}