{
  "type": "Feature",
  "properties": {
    "gn:admin1_code":"17.0",
    "gn:asciiname":"Milmaru",
    "gn:country_code":"KR",
    "gn:dem":27,
    "gn:feature_class":"P",
    "gn:feature_code":"PPL",
    "gn:name":"Milmaru",
    "gn:population":0,
    "gn:timezone":"Asia/Seoul",
    "iso:country":"KR",
    "name:und_x_variant":[
        "\ubc00\ub9c8\ub8e8",
        "Milmaru"
    ],
    "wof:name":"Milmaru",
    "wof:placetype":"locality"
},
  "geometry": {"coordinates":[126.87,36.8627],"type":"Point"}
}