{
  "type": "Feature",
  "properties": {
    "gn:admin1_code":"14.0",
    "gn:asciiname":"Umjima",
    "gn:country_code":"KR",
    "gn:dem":81,
    "gn:feature_class":"P",
    "gn:feature_code":"PPL",
    "gn:name":"\u016cmjima",
    "gn:population":0,
    "gn:timezone":"Asia/Seoul",
    "iso:country":"KR",
    "name:und_x_variant":[
        "\uc74c\uc9c0\ub9c8",
        "\u016cmjima"
    ],
    "wof:name":"Umjima",
    "wof:placetype":"locality"
},
  "geometry": {"coordinates":[128.22409999999999,36.3848],"type":"Point"}
}