{
  "type": "Feature",
  "properties": {
    "gn:admin1_code":"6.0",
    "gn:asciiname":"Sangt'o",
    "gn:country_code":"KR",
    "gn:dem":582,
    "gn:feature_class":"P",
    "gn:feature_code":"PPL",
    "gn:name":"Sangt\u2019\u014f",
    "gn:population":0,
    "gn:timezone":"Asia/Seoul",
    "iso:country":"KR",
    "name:kor_x_preferred":[
        "\uc0c1\ud130"
    ],
    "name:kor_x_variant":[
        "Sangt\u2019\u014f"
    ],
    "wof:name":"Sangt'o",
    "wof:placetype":"locality"
},
  "geometry": {"coordinates":[128.12139999999999,37.2915],"type":"Point"}
}