{
  "type": "Feature",
  "properties": {
    "gn:admin1_code":"14.0",
    "gn:asciiname":"Mokpang",
    "gn:country_code":"KR",
    "gn:dem":340,
    "gn:feature_class":"P",
    "gn:feature_code":"PPL",
    "gn:name":"M\u014fkpang",
    "gn:population":0,
    "gn:timezone":"Asia/Seoul",
    "iso:country":"KR",
    "name:und_x_variant":[
        "\uba39\ubc29",
        "M\u014fkpang"
    ],
    "wof:name":"Mokpang",
    "wof:placetype":"locality"
},
  "geometry": {"coordinates":[128.09732,35.94592],"type":"Point"}
}