{
  "type": "Feature",
  "properties": {
    "gn:admin1_code":"16.0",
    "gn:asciiname":"Simite",
    "gn:country_code":"KR",
    "gn:dem":25,
    "gn:feature_class":"P",
    "gn:feature_code":"PPL",
    "gn:name":"Simite",
    "gn:population":0,
    "gn:timezone":"Asia/Seoul",
    "iso:country":"KR",
    "name:kor_x_preferred":[
        "\uc2dc\ubc11\uc5d0"
    ],
    "wof:name":"Simite",
    "wof:placetype":"locality"
},
  "geometry": {"coordinates":[126.66291,34.94663],"type":"Point"}
}