{
  "type": "Feature",
  "properties": {
    "gn:admin1_code":"12.0",
    "gn:asciiname":"Osoeri",
    "gn:country_code":"KR",
    "gn:dem":18,
    "gn:feature_class":"P",
    "gn:feature_code":"PPL",
    "gn:name":"Osoeri",
    "gn:population":0,
    "gn:timezone":"Asia/Seoul",
    "iso:country":"KR",
    "name:kor_x_preferred":[
        "\uc624\uc1e0\ub9ac"
    ],
    "wof:name":"Osoeri",
    "wof:placetype":"locality"
},
  "geometry": {"coordinates":[126.80278,37.54139],"type":"Point"}
}