{
  "type": "Feature",
  "properties": {
    "gn:admin1_code":"20.0",
    "gn:asciiname":"Yonggang-ni",
    "gn:country_code":"KR",
    "gn:dem":258,
    "gn:feature_class":"P",
    "gn:feature_code":"PPL",
    "gn:name":"Yonggang-ni",
    "gn:population":0,
    "gn:timezone":"Asia/Seoul",
    "iso:country":"KR",
    "wof:name":"Yonggang-ni",
    "wof:placetype":"locality"
},
  "geometry": {"coordinates":[127.63639000000001,35.24139],"type":"Point"}
}