{
  "type": "Feature",
  "properties": {
    "gn:admin1_code":"13.0",
    "gn:asciiname":"P'yong-ch'on",
    "gn:country_code":"KR",
    "gn:dem":239,
    "gn:feature_class":"P",
    "gn:feature_code":"PPL",
    "gn:name":"P\u2019y\u014fng-ch\u2019on",
    "gn:population":0,
    "gn:timezone":"Asia/Seoul",
    "iso:country":"KR",
    "name:kor_x_preferred":[
        "\ud3c9\ucd0c"
    ],
    "name:kor_x_variant":[
        "P\u2019y\u014fng-ch\u2019on"
    ],
    "wof:name":"P'yong-ch'on",
    "wof:placetype":"locality"
},
  "geometry": {"coordinates":[127.50020000000001,37.6246],"type":"Point"}
}