{
  "type": "Feature",
  "properties": {
    "gn:admin1_code":"13.0",
    "gn:asciiname":"Hyeonchang",
    "gn:country_code":"KR",
    "gn:dem":57,
    "gn:feature_class":"P",
    "gn:feature_code":"PPL",
    "gn:name":"Hyeonchang",
    "gn:population":0,
    "gn:timezone":"Asia/Seoul",
    "iso:country":"KR",
    "name:kor_x_preferred":[
        "\ud604\ucc3d"
    ],
    "name:und_x_variant":[
        "Hy\u014fnch\u2019ang",
        "Hyeonchang"
    ],
    "wof:name":"Hyeonchang",
    "wof:placetype":"locality"
},
  "geometry": {"coordinates":[127.16004,37.69785],"type":"Point"}
}