{
  "type": "Feature",
  "properties": {
    "gn:admin1_code":"6.0",
    "gn:asciiname":"Togijeom",
    "gn:country_code":"KR",
    "gn:dem":49,
    "gn:feature_class":"P",
    "gn:feature_code":"PPL",
    "gn:name":"Togijeom",
    "gn:population":0,
    "gn:timezone":"Asia/Seoul",
    "iso:country":"KR",
    "name:kor_x_preferred":[
        "\ud1a0\uae30\uc810"
    ],
    "wof:name":"Togijeom",
    "wof:placetype":"locality"
},
  "geometry": {"coordinates":[128.40381000000002,38.44965],"type":"Point"}
}