{
  "type": "Feature",
  "properties": {
    "gn:admin1_code":"16.0",
    "gn:asciiname":"Byeoram",
    "gn:country_code":"KR",
    "gn:dem":11,
    "gn:feature_class":"P",
    "gn:feature_code":"PPL",
    "gn:name":"Byeoram",
    "gn:population":0,
    "gn:timezone":"Asia/Seoul",
    "iso:country":"KR",
    "name:kor_x_preferred":[
        "\ubcc4\uc554"
    ],
    "name:und_x_variant":[
        "Py\u014fram-ni",
        "Py\u014fram",
        "Byeoram"
    ],
    "wof:name":"Byeoram",
    "wof:placetype":"locality"
},
  "geometry": {"coordinates":[126.34056,34.69833],"type":"Point"}
}