{
  "type": "Feature",
  "properties": {
    "gn:admin1_code":"6.0",
    "gn:asciiname":"Kumal-li",
    "gn:country_code":"KR",
    "gn:dem":134,
    "gn:feature_class":"P",
    "gn:feature_code":"PPL",
    "gn:name":"Kumal-li",
    "gn:population":0,
    "gn:timezone":"Asia/Seoul",
    "iso:country":"KR",
    "name:und_x_variant":[
        "\uad6c\ub9cc\ub9ac",
        "Kumal-li"
    ],
    "wof:name":"Kumal-li",
    "wof:placetype":"locality"
},
  "geometry": {"coordinates":[127.76443999999999,38.09639],"type":"Point"}
}