{
  "type": "Feature",
  "properties": {
    "gn:admin1_code":"5.0",
    "gn:asciiname":"Chit'ong",
    "gn:country_code":"KR",
    "gn:dem":472,
    "gn:feature_class":"P",
    "gn:feature_code":"PPL",
    "gn:name":"Chit\u2019ong",
    "gn:population":0,
    "gn:timezone":"Asia/Seoul",
    "iso:country":"KR",
    "name:und_x_variant":[
        "\uc9c0\ud1b5",
        "Chit\u2019ong"
    ],
    "wof:name":"Chit'ong",
    "wof:placetype":"locality"
},
  "geometry": {"coordinates":[127.84999999999999,36.0973],"type":"Point"}
}