{
  "type": "Feature",
  "properties": {
    "gn:admin1_code":"13.0",
    "gn:asciiname":"Jochimi",
    "gn:country_code":"KR",
    "gn:dem":138,
    "gn:feature_class":"P",
    "gn:feature_code":"PPL",
    "gn:name":"Jochimi",
    "gn:population":0,
    "gn:timezone":"Asia/Seoul",
    "iso:country":"KR",
    "name:kor_x_preferred":[
        "\uc870\uce68\uc774"
    ],
    "name:kor_x_variant":[
        "Choch\u2019imi"
    ],
    "wof:name":"Jochimi",
    "wof:placetype":"locality"
},
  "geometry": {"coordinates":[127.35572000000001,37.99435],"type":"Point"}
}