{
  "type": "Feature",
  "properties": {
    "gn:admin1_code":"14.0",
    "gn:asciiname":"Kwanghan",
    "gn:country_code":"KR",
    "gn:dem":52,
    "gn:feature_class":"P",
    "gn:feature_code":"PPL",
    "gn:name":"Kwanghan",
    "gn:population":0,
    "gn:timezone":"Asia/Seoul",
    "iso:country":"KR",
    "name:und_x_variant":[
        "Kwanghan-dong",
        "\uad11\ud55c",
        "Kwanghan"
    ],
    "wof:name":"Kwanghan",
    "wof:placetype":"locality"
},
  "geometry": {"coordinates":[128.20189999999999,36.1769],"type":"Point"}
}