{
  "type": "Feature",
  "properties": {
    "gn:admin1_code":"14.0",
    "gn:asciiname":"Dwideul",
    "gn:country_code":"KR",
    "gn:dem":73,
    "gn:feature_class":"P",
    "gn:feature_code":"PPL",
    "gn:name":"Dwideul",
    "gn:population":0,
    "gn:timezone":"Asia/Seoul",
    "iso:country":"KR",
    "name:kor_x_preferred":[
        "\ub4a4\ub4e4"
    ],
    "wof:name":"Dwideul",
    "wof:placetype":"locality"
},
  "geometry": {"coordinates":[129.14218,35.80833],"type":"Point"}
}