{
  "type": "Feature",
  "properties": {
    "gn:admin1_code":"17.0",
    "gn:asciiname":"Pyeongjaemal",
    "gn:country_code":"KR",
    "gn:dem":97,
    "gn:feature_class":"P",
    "gn:feature_code":"PPL",
    "gn:name":"Pyeongjaemal",
    "gn:population":0,
    "gn:timezone":"Asia/Seoul",
    "iso:country":"KR",
    "name:kor_x_preferred":[
        "\ud3c9\uc7ac\ub9d0"
    ],
    "wof:name":"Pyeongjaemal",
    "wof:placetype":"locality"
},
  "geometry": {"coordinates":[127.1521,36.38687],"type":"Point"}
}