{
  "type": "Feature",
  "properties": {
    "gn:admin1_code":"6.0",
    "gn:asciiname":"Hasanji",
    "gn:country_code":"KR",
    "gn:dem":384,
    "gn:feature_class":"P",
    "gn:feature_code":"PPL",
    "gn:name":"Hasanji",
    "gn:population":0,
    "gn:timezone":"Asia/Seoul",
    "iso:country":"KR",
    "name:kor_x_preferred":[
        "\ud558\uc0b0\uc9c0"
    ],
    "wof:name":"Hasanji",
    "wof:placetype":"locality"
},
  "geometry": {"coordinates":[128.41409999999999,37.2912],"type":"Point"}
}