{
  "type": "Feature",
  "properties": {
    "gn:admin1_code":"13.0",
    "gn:asciiname":"Gisan",
    "gn:country_code":"KR",
    "gn:dem":24,
    "gn:feature_class":"P",
    "gn:feature_code":"PPL",
    "gn:name":"Gisan",
    "gn:population":0,
    "gn:timezone":"Asia/Seoul",
    "iso:country":"KR",
    "name:und_x_variant":[
        "\uae30\uc0b0",
        "Gisan",
        "Kisan"
    ],
    "wof:name":"Gisan",
    "wof:placetype":"locality"
},
  "geometry": {"coordinates":[126.91932,37.0269],"type":"Point"}
}