{
  "type": "Feature",
  "properties": {
    "gn:admin1_code":"6.0",
    "gn:asciiname":"Nogoso",
    "gn:country_code":"KR",
    "gn:dem":418,
    "gn:feature_class":"P",
    "gn:feature_code":"PPL",
    "gn:name":"Nogoso",
    "gn:population":0,
    "gn:timezone":"Asia/Seoul",
    "iso:country":"KR",
    "name:kor_x_preferred":[
        "\ub178\uace0\uc18c"
    ],
    "wof:name":"Nogoso",
    "wof:placetype":"locality"
},
  "geometry": {"coordinates":[128.11869999999999,37.3537],"type":"Point"}
}