{
  "type": "Feature",
  "properties": {
    "gn:admin1_code":"13.0",
    "gn:asciiname":"Jinjeop",
    "gn:country_code":"KR",
    "gn:dem":72,
    "gn:feature_class":"P",
    "gn:feature_code":"PPLA3",
    "gn:name":"Jinjeop",
    "gn:population":0,
    "gn:timezone":"Asia/Seoul",
    "iso:country":"KR",
    "name:kor_x_preferred":[
        "\uc9c4\uc811"
    ],
    "wof:name":"Jinjeop",
    "wof:placetype":"locality"
},
  "geometry": {"coordinates":[127.18992,37.72722],"type":"Point"}
}