{
  "type": "Feature",
  "properties": {
    "gn:admin1_code":"20.0",
    "gn:asciiname":"Ch'o-dong",
    "gn:country_code":"KR",
    "gn:dem":240,
    "gn:feature_class":"P",
    "gn:feature_code":"PPL",
    "gn:name":"Ch\u2019o-dong",
    "gn:population":0,
    "gn:timezone":"Asia/Seoul",
    "iso:country":"KR",
    "name:und_x_variant":[
        "\ucd08\ub3d9",
        "Ch\u2019o-dong"
    ],
    "wof:name":"Ch'o-dong",
    "wof:placetype":"locality"
},
  "geometry": {"coordinates":[127.85862,35.70493],"type":"Point"}
}