{
  "type": "Feature",
  "properties": {
    "gn:admin1_code":"18.0",
    "gn:asciiname":"Bohwachon",
    "gn:country_code":"KR",
    "gn:dem":30,
    "gn:feature_class":"P",
    "gn:feature_code":"PPL",
    "gn:name":"Bohwachon",
    "gn:population":0,
    "gn:timezone":"Asia/Seoul",
    "iso:country":"KR",
    "name:kor_x_preferred":[
        "\ubcf4\ud654\ucd0c"
    ],
    "wof:name":"Bohwachon",
    "wof:placetype":"locality"
},
  "geometry": {"coordinates":[126.76348,35.20686],"type":"Point"}
}