{
  "type": "Feature",
  "properties": {
    "gn:admin1_code":"17.0",
    "gn:asciiname":"Dongpyeon",
    "gn:country_code":"KR",
    "gn:dem":196,
    "gn:feature_class":"P",
    "gn:feature_code":"PPL",
    "gn:name":"Dongpyeon",
    "gn:population":0,
    "gn:timezone":"Asia/Seoul",
    "iso:country":"KR",
    "name:und_x_variant":[
        "Tongp\u2019y\u014fn-ri",
        "Tongp\u2019y\u014fl-li",
        "Tongp\u2019y\u014fn",
        "\ub3d9\ud3b8",
        "Dongpyeon"
    ],
    "wof:name":"Dongpyeon",
    "wof:placetype":"locality"
},
  "geometry": {"coordinates":[127.5262,36.17972],"type":"Point"}
}