{
  "type": "Feature",
  "properties": {
    "gn:admin1_code":"14.0",
    "gn:asciiname":"Buseok",
    "gn:country_code":"KR",
    "gn:dem":290,
    "gn:feature_class":"P",
    "gn:feature_code":"PPL",
    "gn:name":"Buseok",
    "gn:population":0,
    "gn:timezone":"Asia/Seoul",
    "iso:country":"KR",
    "name:kor_x_preferred":[
        "\ubd80\uc11d"
    ],
    "name:kor_x_variant":[
        "Pus\u014fk"
    ],
    "wof:name":"Buseok",
    "wof:placetype":"locality"
},
  "geometry": {"coordinates":[128.65434999999999,36.97849],"type":"Point"}
}