{
  "type": "Feature",
  "properties": {
    "gn:admin1_code":"16.0",
    "gn:asciiname":"Sandeung",
    "gn:country_code":"KR",
    "gn:dem":-9999,
    "gn:feature_class":"P",
    "gn:feature_code":"PPL",
    "gn:name":"Sandeung",
    "gn:population":0,
    "gn:timezone":"Asia/Seoul",
    "iso:country":"KR",
    "name:kor_x_preferred":[
        "\uc0b0\ub4f1"
    ],
    "name:kor_x_variant":[
        "Sand\u016dng"
    ],
    "wof:name":"Sandeung",
    "wof:placetype":"locality"
},
  "geometry": {"coordinates":[127.4126,34.81182],"type":"Point"}
}