{
  "type": "Feature",
  "properties": {
    "gn:admin1_code":"20.0",
    "gn:asciiname":"T'aep'ong-dong",
    "gn:country_code":"KR",
    "gn:dem":23,
    "gn:feature_class":"P",
    "gn:feature_code":"PPL",
    "gn:name":"T\u2019aep\u2019ong-dong",
    "gn:population":0,
    "gn:timezone":"Asia/Seoul",
    "iso:country":"KR",
    "wof:name":"T'aep'ong-dong",
    "wof:placetype":"locality"
},
  "geometry": {"coordinates":[128.42527999999999,34.84778],"type":"Point"}
}