{
  "type": "Feature",
  "properties": {
    "gn:admin1_code":"13.0",
    "gn:admin2_code":"Yongin-si",
    "gn:asciiname":"Yangjulli",
    "gn:country_code":"KR",
    "gn:dem":155,
    "gn:feature_class":"P",
    "gn:feature_code":"PPL",
    "gn:name":"Yangjulli",
    "gn:population":0,
    "gn:timezone":"Asia/Seoul",
    "iso:country":"KR",
    "name:kor_x_preferred":[
        "\uc591\uc900\ub9ac"
    ],
    "name:und_x_variant":[
        "Yangjun-ri"
    ],
    "wof:name":"Yangjulli",
    "wof:placetype":"locality"
},
  "geometry": {"coordinates":[127.35702000000001,37.13929],"type":"Point"}
}