{
  "type": "Feature",
  "properties": {
    "gn:admin1_code":"13.0",
    "gn:asciiname":"Ch'aeryong",
    "gn:country_code":"KR",
    "gn:dem":11,
    "gn:feature_class":"P",
    "gn:feature_code":"PPL",
    "gn:name":"Ch\u2019aery\u014fng",
    "gn:population":0,
    "gn:timezone":"Asia/Seoul",
    "iso:country":"KR",
    "name:kor_x_preferred":[
        "\ucc44\ub839"
    ],
    "name:kor_x_variant":[
        "Ch\u2019aery\u014fng"
    ],
    "name:und_x_variant":[
        "Ch\u2019agy\u014fng",
        "Ch\u2019aegy\u014fng-dong",
        "Ch\u2019aegy\u014fng"
    ],
    "wof:name":"Ch'aeryong",
    "wof:placetype":"locality"
},
  "geometry": {"coordinates":[126.67333000000001,37.21194000000001],"type":"Point"}
}