{
  "type": "Feature",
  "properties": {
    "gn:admin1_code":"11.0",
    "gn:asciiname":"Samsongil-tong",
    "gn:country_code":"KR",
    "gn:dem":35,
    "gn:feature_class":"P",
    "gn:feature_code":"PPL",
    "gn:name":"Sams\u014fngil-tong",
    "gn:population":0,
    "gn:timezone":"Asia/Seoul",
    "iso:country":"KR",
    "name:eng_x_preferred":[
        "Samsongil"
    ],
    "name:eng_x_variant":[
        "Samsongil-tong"
    ],
    "name:und_x_variant":[
        "\uc0bc\uc1311\ub3d9",
        "Sams\u014fngil-tong"
    ],
    "wof:name":"Samsongil",
    "wof:placetype":"locality"
},
  "geometry": {"coordinates":[127.05934000000001,37.51621],"type":"Point"}
}