{
  "type": "Feature",
  "properties": {
    "gn:admin1_code":"17.0",
    "gn:asciiname":"Samhwa-ri",
    "gn:country_code":"KR",
    "gn:dem":16,
    "gn:feature_class":"P",
    "gn:feature_code":"PPL",
    "gn:name":"Samhwa-ri",
    "gn:population":0,
    "gn:timezone":"Asia/Seoul",
    "iso:country":"KR",
    "name:und_x_variant":[
        "\uc0bc\ud654\ub9ac",
        "Samhwa-ri"
    ],
    "wof:name":"Samhwa-ri",
    "wof:placetype":"locality"
},
  "geometry": {"coordinates":[126.5887,36.9705],"type":"Point"}
}