{
  "type": "Feature",
  "properties": {
    "gn:admin1_code":"17.0",
    "gn:asciiname":"Taesup-kol",
    "gn:country_code":"KR",
    "gn:dem":17,
    "gn:feature_class":"P",
    "gn:feature_code":"PPL",
    "gn:name":"Taesup-kol",
    "gn:population":0,
    "gn:timezone":"Asia/Seoul",
    "iso:country":"KR",
    "name:und_x_variant":[
        "\ub300\uc232\uace8",
        "Taesup-kol"
    ],
    "wof:name":"Taesup-kol",
    "wof:placetype":"locality"
},
  "geometry": {"coordinates":[126.49679999999999,36.6435],"type":"Point"}
}