{
  "type": "Feature",
  "properties": {
    "gn:admin1_code":"14.0",
    "gn:asciiname":"Utchugol",
    "gn:country_code":"KR",
    "gn:dem":304,
    "gn:feature_class":"P",
    "gn:feature_code":"PPL",
    "gn:name":"Utchugol",
    "gn:population":0,
    "gn:timezone":"Asia/Seoul",
    "iso:country":"KR",
    "name:kor_x_preferred":[
        "\uc6c7\ucd94\uace8"
    ],
    "wof:name":"Utchugol",
    "wof:placetype":"locality"
},
  "geometry": {"coordinates":[128.31974,36.71601],"type":"Point"}
}