{
  "type": "Feature",
  "properties": {
    "gn:admin1_code":"20.0",
    "gn:asciiname":"P'yongnim-ni",
    "gn:country_code":"KR",
    "gn:dem":17,
    "gn:feature_class":"P",
    "gn:feature_code":"PPL",
    "gn:name":"P\u2019y\u014fngnim-ni",
    "gn:population":0,
    "gn:timezone":"Asia/Seoul",
    "iso:country":"KR",
    "name:und_x_variant":[
        "\ud3c9\ub9bc\ub9ac",
        "P\u2019y\u014fngnim",
        "P\u2019y\u014fngnim-ni"
    ],
    "wof:name":"P'yongnim-ni",
    "wof:placetype":"locality"
},
  "geometry": {"coordinates":[128.45318999999998,35.33405],"type":"Point"}
}