{
  "type": "Feature",
  "properties": {
    "gn:admin1_code":"16.0",
    "gn:asciiname":"Ch'udong-ni",
    "gn:country_code":"KR",
    "gn:dem":190,
    "gn:feature_class":"P",
    "gn:feature_code":"PPL",
    "gn:name":"Ch\u2019udong-ni",
    "gn:population":0,
    "gn:timezone":"Asia/Seoul",
    "iso:country":"KR",
    "name:kor_x_preferred":[
        "\ucd94\ub3d9\ub9ac"
    ],
    "name:kor_x_variant":[
        "Ch\u2019udong-ni"
    ],
    "wof:name":"Ch'udong-ni",
    "wof:placetype":"locality"
},
  "geometry": {"coordinates":[127.28596,34.87506],"type":"Point"}
}