{
  "type": "Feature",
  "properties": {
    "gn:admin1_code":"13.0",
    "gn:asciiname":"Haryongsangdong",
    "gn:country_code":"KR",
    "gn:dem":134,
    "gn:feature_class":"P",
    "gn:feature_code":"PPL",
    "gn:name":"Haryongsangdong",
    "gn:population":0,
    "gn:timezone":"Asia/Seoul",
    "iso:country":"KR",
    "name:kor_x_preferred":[
        "\ud558\ub8e1\uc0c1\ub3d9"
    ],
    "name:und_x_variant":[
        "\ud558\ub8e1\uc0c1",
        "Haryongsang",
        "Haryongsangdong"
    ],
    "wof:name":"Haryongsangdong",
    "wof:placetype":"locality"
},
  "geometry": {"coordinates":[127.13203,37.81778],"type":"Point"}
}