{
  "type": "Feature",
  "properties": {
    "gn:admin1_code":"12.0",
    "gn:asciiname":"Ullegi",
    "gn:country_code":"KR",
    "gn:dem":25,
    "gn:feature_class":"P",
    "gn:feature_code":"PPL",
    "gn:name":"Ullegi",
    "gn:population":0,
    "gn:timezone":"Asia/Seoul",
    "iso:country":"KR",
    "name:kor_x_preferred":[
        "\uc6b8\ub124\uae30"
    ],
    "name:und_x_variant":[
        "Ulnegi",
        "Ullegi"
    ],
    "wof:name":"Ullegi",
    "wof:placetype":"locality"
},
  "geometry": {"coordinates":[126.47360999999999,37.71418],"type":"Point"}
}