{
  "type": "Feature",
  "properties": {
    "gn:admin1_code":"20.0",
    "gn:asciiname":"Tamu",
    "gn:country_code":"KR",
    "gn:dem":30,
    "gn:feature_class":"P",
    "gn:feature_code":"PPL",
    "gn:name":"Tamu",
    "gn:population":0,
    "gn:timezone":"Asia/Seoul",
    "iso:country":"KR",
    "name:und_x_variant":[
        "\ub2e4\ubb34",
        "Tamu"
    ],
    "wof:name":"Tamu",
    "wof:placetype":"locality"
},
  "geometry": {"coordinates":[128.26929999999999,35.17923],"type":"Point"}
}