{
  "type": "Feature",
  "properties": {
    "gn:admin1_code":"3.0",
    "gn:asciiname":"Youch'i",
    "gn:country_code":"KR",
    "gn:dem":240,
    "gn:feature_class":"P",
    "gn:feature_code":"PPL",
    "gn:name":"Y\u014fuch\u2019i",
    "gn:population":0,
    "gn:timezone":"Asia/Seoul",
    "iso:country":"KR",
    "name:und_x_variant":[
        "Y\u014fu-ri",
        "Y\u014fu-ni",
        "\uc5ec\uc6b0\uce58",
        "Y\u014fuch\u2019i"
    ],
    "wof:name":"Youch'i",
    "wof:placetype":"locality"
},
  "geometry": {"coordinates":[127.09963999999999,35.60368],"type":"Point"}
}