{
  "type": "Feature",
  "properties": {
    "gn:admin1_code":"17.0",
    "gn:asciiname":"Togye-ri",
    "gn:country_code":"KR",
    "gn:dem":46,
    "gn:feature_class":"P",
    "gn:feature_code":"PPL",
    "gn:name":"Togye-ri",
    "gn:population":0,
    "gn:timezone":"Asia/Seoul",
    "iso:country":"KR",
    "name:und_x_variant":[
        "Handa-ri",
        "\ub3c4\uacc4\ub9ac",
        "Togye-ri"
    ],
    "wof:name":"Togye-ri",
    "wof:placetype":"locality"
},
  "geometry": {"coordinates":[127.2093,36.4941],"type":"Point"}
}