{
  "type": "Feature",
  "properties": {
    "gn:admin1_code":"13.0",
    "gn:asciiname":"Wonmeoru",
    "gn:country_code":"KR",
    "gn:dem":14,
    "gn:feature_class":"P",
    "gn:feature_code":"PPL",
    "gn:name":"Wonmeoru",
    "gn:population":0,
    "gn:timezone":"Asia/Seoul",
    "iso:country":"KR",
    "name:und_x_variant":[
        "\uc6d0\uba38\ub8e8",
        "Wonmeoru",
        "W\u014fnm\u014fru"
    ],
    "wof:name":"Wonmeoru",
    "wof:placetype":"locality"
},
  "geometry": {"coordinates":[126.53451,37.69419],"type":"Point"}
}