{
  "type": "Feature",
  "properties": {
    "gn:admin1_code":"16.0",
    "gn:asciiname":"Sagu",
    "gn:country_code":"KR",
    "gn:dem":44,
    "gn:feature_class":"P",
    "gn:feature_code":"PPL",
    "gn:name":"Sagu",
    "gn:population":0,
    "gn:timezone":"Asia/Seoul",
    "iso:country":"KR",
    "name:ceb_x_preferred":[
        "Sagu"
    ],
    "name:eus_x_preferred":[
        "Sagu"
    ],
    "name:ita_x_preferred":[
        "Sagu"
    ],
    "name:kor_x_preferred":[
        "\uc0ac\uad6c"
    ],
    "name:nld_x_preferred":[
        "Sagu"
    ],
    "wof:name":"Sagu",
    "wof:placetype":"locality"
},
  "geometry": {"coordinates":[127.00613,34.64850999999999],"type":"Point"}
}