{
  "type": "Feature",
  "properties": {
    "gn:admin1_code":"14.0",
    "gn:asciiname":"Uttaet'i",
    "gn:country_code":"KR",
    "gn:dem":533,
    "gn:feature_class":"P",
    "gn:feature_code":"PPL",
    "gn:name":"Uttaet\u2019i",
    "gn:population":0,
    "gn:timezone":"Asia/Seoul",
    "iso:country":"KR",
    "name:und_x_variant":[
        "\uc6c3\ub300\ud2f0",
        "Uttaet\u2019i"
    ],
    "wof:name":"Uttaet'i",
    "wof:placetype":"locality"
},
  "geometry": {"coordinates":[129.1097,36.8228],"type":"Point"}
}