{
  "type": "Feature",
  "properties": {
    "gn:admin1_code":"3.0",
    "gn:asciiname":"Hoesa",
    "gn:country_code":"KR",
    "gn:dem":283,
    "gn:feature_class":"P",
    "gn:feature_code":"PPL",
    "gn:name":"Hoesa",
    "gn:population":0,
    "gn:timezone":"Asia/Seoul",
    "iso:country":"KR",
    "name:und_x_variant":[
        "\ud68c\uc0ac",
        "Hoesa"
    ],
    "wof:name":"Hoesa",
    "wof:placetype":"locality"
},
  "geometry": {"coordinates":[127.48721999999999,35.82448],"type":"Point"}
}