{
  "type": "Feature",
  "properties": {
    "gn:admin1_code":"17.0",
    "gn:asciiname":"Hach'ol-li",
    "gn:country_code":"KR",
    "gn:dem":72,
    "gn:feature_class":"P",
    "gn:feature_code":"PPL",
    "gn:name":"Hach\u2019\u014fl-li",
    "gn:population":0,
    "gn:timezone":"Asia/Seoul",
    "iso:country":"KR",
    "name:und_x_variant":[
        "\ud558\ucc9c\ub9ac",
        "Hach\u2019\u014fl-li"
    ],
    "wof:name":"Hach'ol-li",
    "wof:placetype":"locality"
},
  "geometry": {"coordinates":[126.8943,36.6084],"type":"Point"}
}