{
  "type": "Feature",
  "properties": {
    "gn:country":"KR",
    "iso:country":"KR",
    "qs:name":"\uc9c0\uc0b0\uba74",
    "qs:name_adm0":"\ud55c\uad6d",
    "qs:name_adm1":"\uc804\ub77c\ub0a8\ub3c4",
    "qs:photos":2,
    "qs:photos_1k":1,
    "qs:photos_9k":1,
    "qs:photos_9r":1,
    "qs:photos_all":2,
    "qs:photos_sr":1,
    "qs:placetype":"LocalAdmin",
    "qs:pop_sr":"0",
    "wof:name":"\uc9c0\uc0b0\uba74",
    "wof:placetype":"localadmin"
},
  "geometry": {"coordinates":[126.21333799999999,34.310272],"type":"Point"}
}