{
  "type": "Feature",
  "properties": {
    "gn:admin1_code":"14.0",
    "gn:asciiname":"Borigol",
    "gn:country_code":"KR",
    "gn:dem":19,
    "gn:feature_class":"P",
    "gn:feature_code":"PPL",
    "gn:name":"Borigol",
    "gn:population":0,
    "gn:timezone":"Asia/Seoul",
    "iso:country":"KR",
    "name:kor_x_preferred":[
        "\ubcf4\ub9ac\uace8"
    ],
    "wof:name":"Borigol",
    "wof:placetype":"locality"
},
  "geometry": {"coordinates":[129.50961000000001,35.82725999999999],"type":"Point"}
}