{
  "type": "Feature",
  "properties": {
    "gn:admin1_code":"14.0",
    "gn:asciiname":"Sae-maul",
    "gn:country_code":"KR",
    "gn:dem":152,
    "gn:feature_class":"P",
    "gn:feature_code":"PPL",
    "gn:name":"Sae-ma\u016dl",
    "gn:population":0,
    "gn:timezone":"Asia/Seoul",
    "iso:country":"KR",
    "wof:name":"Sae-maul",
    "wof:placetype":"locality"
},
  "geometry": {"coordinates":[128.44777999999999,36.235],"type":"Point"}
}