{
  "type": "Feature",
  "properties": {
    "gn:admin1_code":"6.0",
    "gn:asciiname":"Pallang 1-ri",
    "gn:country_code":"KR",
    "gn:dem":370,
    "gn:feature_class":"P",
    "gn:feature_code":"PPL",
    "gn:name":"Pallang 1-ri",
    "gn:population":0,
    "gn:timezone":"Asia/Seoul",
    "iso:country":"KR",
    "name:kor_x_preferred":[
        "\ud314\ub7911\ub9ac"
    ],
    "name:kor_x_variant":[
        "P\u2019allangil-li"
    ],
    "wof:name":"Pallang 1-ri",
    "wof:placetype":"locality"
},
  "geometry": {"coordinates":[128.06471999999999,38.21],"type":"Point"}
}