{
  "type": "Feature",
  "properties": {
    "gn:admin1_code":"14.0",
    "gn:asciiname":"Sa-ch'on",
    "gn:country_code":"KR",
    "gn:dem":134,
    "gn:feature_class":"P",
    "gn:feature_code":"PPL",
    "gn:name":"Sa-ch\u2019on",
    "gn:population":0,
    "gn:timezone":"Asia/Seoul",
    "iso:country":"KR",
    "name:und_x_variant":[
        "\uc0ac\ucd0c",
        "Sa-ch\u2019on"
    ],
    "wof:name":"Sa-ch'on",
    "wof:placetype":"locality"
},
  "geometry": {"coordinates":[128.0857,36.228],"type":"Point"}
}