{
  "type": "Feature",
  "properties": {
    "gn:admin1_code":"6.0",
    "gn:asciiname":"Ojong-ni",
    "gn:country_code":"KR",
    "gn:dem":34,
    "gn:feature_class":"P",
    "gn:feature_code":"PPL",
    "gn:name":"Oj\u014fng-ni",
    "gn:population":0,
    "gn:timezone":"Asia/Seoul",
    "iso:country":"KR",
    "name:eng_x_preferred":[
        "Ojong"
    ],
    "name:eng_x_variant":[
        "Ojong-ni"
    ],
    "name:und_x_variant":[
        "Oj\u014fng-ni",
        "\uc624\uc815\ub9ac"
    ],
    "wof:name":"Ojong",
    "wof:placetype":"locality"
},
  "geometry": {"coordinates":[128.44602,38.40194],"type":"Point"}
}