{
  "type": "Feature",
  "properties": {
    "gn:admin1_code":"16.0",
    "gn:asciiname":"Singi",
    "gn:country_code":"KR",
    "gn:dem":28,
    "gn:feature_class":"P",
    "gn:feature_code":"PPL",
    "gn:name":"Singi",
    "gn:population":0,
    "gn:timezone":"Asia/Seoul",
    "iso:country":"KR",
    "name:deu_x_preferred":[
        "Singi"
    ],
    "name:kor_x_preferred":[
        "Sin\u2019gi"
    ],
    "name:kor_x_variant":[
        "\uc2e0\uae30"
    ],
    "name:nor_x_preferred":[
        "Singi"
    ],
    "name:swe_x_preferred":[
        "Singi"
    ],
    "wof:name":"Singi",
    "wof:placetype":"locality"
},
  "geometry": {"coordinates":[126.84639,34.655],"type":"Point"}
}