{
  "type": "Feature",
  "properties": {
    "gn:admin1_code":"14.0",
    "gn:asciiname":"Munsan",
    "gn:country_code":"KR",
    "gn:dem":84,
    "gn:feature_class":"P",
    "gn:feature_code":"PPL",
    "gn:name":"Munsan",
    "gn:population":0,
    "gn:timezone":"Asia/Seoul",
    "iso:country":"KR",
    "name:ceb_x_preferred":[
        "Munsan-eup"
    ],
    "name:fra_x_preferred":[
        "Munsan"
    ],
    "name:kor_x_preferred":[
        "\ubb38\uc0b0\uc74d"
    ],
    "name:und_x_variant":[
        "\ubb38\uc0b0"
    ],
    "wof:name":"Munsan",
    "wof:placetype":"locality"
},
  "geometry": {"coordinates":[128.08940000000001,36.1471],"type":"Point"}
}