{
  "type": "Feature",
  "properties": {
    "gn:admin1_code":"17.0",
    "gn:asciiname":"Sanggum-ni",
    "gn:country_code":"KR",
    "gn:dem":31,
    "gn:feature_class":"P",
    "gn:feature_code":"PPL",
    "gn:name":"Sangg\u016dm-ni",
    "gn:population":0,
    "gn:timezone":"Asia/Seoul",
    "iso:country":"KR",
    "name:eng_x_preferred":[
        "Sanggum"
    ],
    "name:eng_x_variant":[
        "Sanggum-ni"
    ],
    "wof:name":"Sanggum",
    "wof:placetype":"locality"
},
  "geometry": {"coordinates":[126.84999999999999,36.18333],"type":"Point"}
}