{
  "type": "Feature",
  "properties": {
    "gn:admin1_code":"13.0",
    "gn:asciiname":"Mangwol-ri",
    "gn:country_code":"KR",
    "gn:dem":32,
    "gn:feature_class":"P",
    "gn:feature_code":"PPL",
    "gn:name":"Mangwol-ri",
    "gn:population":0,
    "gn:timezone":"Asia/Seoul",
    "iso:country":"KR",
    "name:und_x_variant":[
        "\ub9dd\uc6d4\ub9ac",
        "Mangwol-ri",
        "Mangw\u014fl-li"
    ],
    "wof:name":"Mangwol-ri",
    "wof:placetype":"locality"
},
  "geometry": {"coordinates":[127.01278000000001,37.15278],"type":"Point"}
}