{
  "type": "Feature",
  "properties": {
    "gn:admin1_code":"20.0",
    "gn:asciiname":"Noryang-ni",
    "gn:cc2":"KR",
    "gn:country_code":"KR",
    "gn:dem":26,
    "gn:feature_class":"P",
    "gn:feature_code":"PPL",
    "gn:name":"Noryang-ni",
    "gn:population":0,
    "gn:timezone":"Asia/Seoul",
    "iso:country":"KR",
    "name:und_x_variant":[
        "Kunoryang",
        "Rory\u014dshi",
        "Noryangjin",
        "Rory\u014dshin",
        "Rory\u014dri",
        "Noryang-ni"
    ],
    "wof:name":"Noryang-ni",
    "wof:placetype":"locality"
},
  "geometry": {"coordinates":[127.86194,34.94972],"type":"Point"}
}