{
  "type": "Feature",
  "properties": {
    "gn:admin1_code":"14.0",
    "gn:asciiname":"Silli",
    "gn:country_code":"KR",
    "gn:dem":114,
    "gn:feature_class":"P",
    "gn:feature_code":"PPL",
    "gn:name":"Silli",
    "gn:population":0,
    "gn:timezone":"Asia/Seoul",
    "iso:country":"KR",
    "name:und_x_variant":[
        "\uc2e0\ub9ac",
        "Sin-ri",
        "Silli"
    ],
    "wof:name":"Silli",
    "wof:placetype":"locality"
},
  "geometry": {"coordinates":[129.25981999999999,36.09499],"type":"Point"}
}