{
  "type": "Feature",
  "properties": {
    "gn:admin1_code":"13.0",
    "gn:asciiname":"Tangjingae",
    "gn:country_code":"KR",
    "gn:dem":54,
    "gn:feature_class":"P",
    "gn:feature_code":"PPL",
    "gn:name":"Tangjingae",
    "gn:population":0,
    "gn:timezone":"Asia/Seoul",
    "iso:country":"KR",
    "name:und_x_variant":[
        "\ub2f9\uc9c4\uac1c",
        "Dangjingae"
    ],
    "wof:name":"Tangjingae",
    "wof:placetype":"locality"
},
  "geometry": {"coordinates":[126.93889,37.2925],"type":"Point"}
}