{
  "type": "Feature",
  "properties": {
    "gn:admin1_code":"14.0",
    "gn:asciiname":"Jungsan",
    "gn:country_code":"KR",
    "gn:dem":165,
    "gn:feature_class":"P",
    "gn:feature_code":"PPL",
    "gn:name":"Jungsan",
    "gn:population":0,
    "gn:timezone":"Asia/Seoul",
    "iso:country":"KR",
    "name:kor_x_preferred":[
        "\uc911\uc0b0"
    ],
    "wof:name":"Jungsan",
    "wof:placetype":"locality"
},
  "geometry": {"coordinates":[128.51804999999999,36.74135],"type":"Point"}
}