{
  "type": "Feature",
  "properties": {
    "gn:admin1_code":"5.0",
    "gn:asciiname":"Chokha-ri",
    "gn:country_code":"KR",
    "gn:dem":108,
    "gn:feature_class":"P",
    "gn:feature_code":"PPLL",
    "gn:name":"Ch\u014fkha-ri",
    "gn:population":0,
    "gn:timezone":"Asia/Seoul",
    "iso:country":"KR",
    "name:und_x_variant":[
        "\uc801\ud558\ub9ac",
        "Ch\u014fkha-ri"
    ],
    "wof:name":"Chokha-ri",
    "wof:placetype":"locality"
},
  "geometry": {"coordinates":[127.62893,36.27956],"type":"Point"}
}