{
  "type": "Feature",
  "properties": {
    "gn:admin1_code":"13.0",
    "gn:asciiname":"Uiwang",
    "gn:country_code":"KR",
    "gn:dem":38,
    "gn:feature_class":"P",
    "gn:feature_code":"PPL",
    "gn:name":"Uiwang",
    "gn:population":0,
    "gn:timezone":"Asia/Seoul",
    "iso:country":"KR",
    "name:und_x_variant":[
        "\uc758\uc655",
        "Uiwang",
        "\u016ciwang"
    ],
    "wof:name":"Uiwang",
    "wof:placetype":"locality"
},
  "geometry": {"coordinates":[126.94777999999999,37.36528],"type":"Point"}
}