{
  "type": "Feature",
  "properties": {
    "gn:admin1_code":"13.0",
    "gn:asciiname":"Uiwang",
    "gn:country_code":"KR",
    "gn:dem":38,
    "gn:feature_class":"P",
    "gn:feature_code":"PPL",
    "gn:name":"Uiwang",
    "gn:population":0,
    "gn:timezone":"Asia/Seoul",
    "iso:country":"KR",
    "name:ara_x_preferred":[
        "\u064a\u0648\u0627\u0646\u063a"
    ],
    "name:ceb_x_preferred":[
        "Uiwang-si"
    ],
    "name:ces_x_preferred":[
        "Uiwang"
    ],
    "name:epo_x_preferred":[
        "Uivan"
    ],
    "name:fas_x_preferred":[
        "\u0627\u0648\u0648\u0627\u0646\u06af"
    ],
    "name:fin_x_preferred":[
        "Uiwang"
    ],
    "name:fra_x_preferred":[
        "Uiwang"
    ],
    "name:hak_x_preferred":[
        "Uiwang S\u1e73"
    ],
    "name:ita_x_preferred":[
        "Uiwang"
    ],
    "name:jpn_x_preferred":[
        "\u7fa9\u738b\u5e02"
    ],
    "name:kat_x_preferred":[
        "\u10d8\u10d8\u10d5\u10d0\u10dc\u10d8"
    ],
    "name:kor_x_preferred":[
        "\uc758\uc655\uc2dc"
    ],
    "name:nld_x_preferred":[
        "Uiwang"
    ],
    "name:nor_x_preferred":[
        "Uiwang"
    ],
    "name:pol_x_preferred":[
        "Uiwang"
    ],
    "name:rus_x_preferred":[
        "\u042b\u0439\u0432\u0430\u043d"
    ],
    "name:sco_x_preferred":[
        "Uiwang"
    ],
    "name:slk_x_preferred":[
        "Uiwang"
    ],
    "name:spa_x_preferred":[
        "Uiwang"
    ],
    "name:swe_x_preferred":[
        "Uiwang"
    ],
    "name:tgl_x_preferred":[
        "Uiwang"
    ],
    "name:tha_x_preferred":[
        "\u0e2d\u0e36\u0e22\u0e27\u0e31\u0e07"
    ],
    "name:tur_x_preferred":[
        "Uiwang"
    ],
    "name:und_x_variant":[
        "\uc758\uc655",
        "Uiwang",
        "\u016ciwang"
    ],
    "name:urd_x_preferred":[
        "\u0627\u0648\u0626\u06cc\u0648\u0627\u0646\u06af"
    ],
    "name:vie_x_preferred":[
        "Uiwang"
    ],
    "name:war_x_preferred":[
        "Uiwang"
    ],
    "name:zho_x_preferred":[
        "\u7fa9\u738b\u5e02"
    ],
    "wof:name":"Uiwang",
    "wof:placetype":"locality"
},
  "geometry": {"coordinates":[126.94777999999999,37.36528],"type":"Point"}
}