{
  "type": "Feature",
  "properties": {
    "gn:admin1_code":"16.0",
    "gn:asciiname":"Tol-li",
    "gn:country_code":"KR",
    "gn:dem":65,
    "gn:feature_class":"P",
    "gn:feature_code":"PPL",
    "gn:name":"T\u014fl-li",
    "gn:population":0,
    "gn:timezone":"Asia/Seoul",
    "iso:country":"KR",
    "name:kor_x_preferred":[
        "T\u014fl-li"
    ],
    "wof:name":"Tol-li",
    "wof:placetype":"locality"
},
  "geometry": {"coordinates":[126.90555999999999,34.17222],"type":"Point"}
}