{
  "type": "Feature",
  "properties": {
    "gn:admin1_code":"14.0",
    "gn:asciiname":"Soja-gol",
    "gn:country_code":"KR",
    "gn:dem":391,
    "gn:feature_class":"P",
    "gn:feature_code":"PPL",
    "gn:name":"S\u014fja-gol",
    "gn:population":0,
    "gn:timezone":"Asia/Seoul",
    "iso:country":"KR",
    "name:und_x_variant":[
        "\uc11c\uc790\uace8",
        "S\u014fja-gol"
    ],
    "wof:name":"Soja-gol",
    "wof:placetype":"locality"
},
  "geometry": {"coordinates":[129.05410000000001,36.9208],"type":"Point"}
}