{
  "type": "Feature",
  "properties": {
    "gn:admin1_code":"17.0",
    "gn:asciiname":"Oech'on",
    "gn:country_code":"KR",
    "gn:dem":19,
    "gn:feature_class":"P",
    "gn:feature_code":"PPL",
    "gn:name":"Oech\u2019\u014fn",
    "gn:population":0,
    "gn:timezone":"Asia/Seoul",
    "iso:country":"KR",
    "name:und_x_variant":[
        "\uc678\ucc9c",
        "Oech\u2019\u014fn"
    ],
    "wof:name":"Oech'on",
    "wof:placetype":"locality"
},
  "geometry": {"coordinates":[126.797,36.694],"type":"Point"}
}