{
  "type": "Feature",
  "properties": {
    "gn:admin1_code":"6.0",
    "gn:asciiname":"Hasongdong",
    "gn:country_code":"KR",
    "gn:dem":263,
    "gn:feature_class":"P",
    "gn:feature_code":"PPL",
    "gn:name":"Hasongdong",
    "gn:population":0,
    "gn:timezone":"Asia/Seoul",
    "iso:country":"KR",
    "name:kor_x_preferred":[
        "\ud558\uc1a1\ub3d9"
    ],
    "wof:name":"Hasongdong",
    "wof:placetype":"locality"
},
  "geometry": {"coordinates":[127.43295999999999,38.21267],"type":"Point"}
}