{
  "type": "Feature",
  "properties": {
    "gn:admin1_code":"17.0",
    "gn:asciiname":"Ballimi",
    "gn:country_code":"KR",
    "gn:dem":31,
    "gn:feature_class":"P",
    "gn:feature_code":"PPL",
    "gn:name":"Ballimi",
    "gn:population":0,
    "gn:timezone":"Asia/Seoul",
    "iso:country":"KR",
    "name:und_x_variant":[
        "\ubc1c\ub9bc\uc774",
        "Pallimi",
        "Ballimi"
    ],
    "wof:name":"Ballimi",
    "wof:placetype":"locality"
},
  "geometry": {"coordinates":[127.28635,36.45685],"type":"Point"}
}