{
  "type": "Feature",
  "properties": {
    "gn:admin1_code":"14.0",
    "gn:asciiname":"Konch'on",
    "gn:country_code":"KR",
    "gn:dem":263,
    "gn:feature_class":"P",
    "gn:feature_code":"PPL",
    "gn:name":"Konch\u2019\u014fn",
    "gn:population":0,
    "gn:timezone":"Asia/Seoul",
    "iso:country":"KR",
    "name:und_x_variant":[
        "\uace4\ucc9c",
        "Konch\u2019\u014fn"
    ],
    "wof:name":"Konch'on",
    "wof:placetype":"locality"
},
  "geometry": {"coordinates":[128.02149,36.19261],"type":"Point"}
}