{
  "type": "Feature",
  "properties": {
    "gn:admin1_code":"5.0",
    "gn:asciiname":"Mojinae",
    "gn:country_code":"KR",
    "gn:dem":181,
    "gn:feature_class":"P",
    "gn:feature_code":"PPL",
    "gn:name":"Mojinae",
    "gn:population":0,
    "gn:timezone":"Asia/Seoul",
    "iso:country":"KR",
    "name:und_x_variant":[
        "\ubaa8\uc9c0\ub0b4",
        "Mojinae"
    ],
    "wof:name":"Mojinae",
    "wof:placetype":"locality"
},
  "geometry": {"coordinates":[127.7051,36.1039],"type":"Point"}
}