{
  "type": "Feature",
  "properties": {
    "gn:admin1_code":"15.0",
    "gn:asciiname":"Wissotgol",
    "gn:country_code":"KR",
    "gn:dem":82,
    "gn:feature_class":"P",
    "gn:feature_code":"PPL",
    "gn:name":"Wissotgol",
    "gn:population":0,
    "gn:timezone":"Asia/Seoul",
    "iso:country":"KR",
    "name:kor_x_preferred":[
        "\uc717\uc19f\uace8"
    ],
    "wof:name":"Wissotgol",
    "wof:placetype":"locality"
},
  "geometry": {"coordinates":[128.59358,35.94843],"type":"Point"}
}