{
  "type": "Feature",
  "properties": {
    "gn:admin1_code":"3.0",
    "gn:asciiname":"Okkaenae",
    "gn:country_code":"KR",
    "gn:dem":278,
    "gn:feature_class":"P",
    "gn:feature_code":"PPL",
    "gn:name":"\u014ekkaenae",
    "gn:population":0,
    "gn:timezone":"Asia/Seoul",
    "iso:country":"KR",
    "name:und_x_variant":[
        "\uc5b4\uae68\ub0b4",
        "\u014ekkaenae"
    ],
    "wof:name":"Okkaenae",
    "wof:placetype":"locality"
},
  "geometry": {"coordinates":[127.54743000000001,35.53814000000001],"type":"Point"}
}