{
  "type": "Feature",
  "properties": {
    "gn:admin1_code":"20.0",
    "gn:asciiname":"An-gok-ri",
    "gn:country_code":"KR",
    "gn:dem":31,
    "gn:feature_class":"P",
    "gn:feature_code":"PPL",
    "gn:name":"An-gok-ri",
    "gn:population":0,
    "gn:timezone":"Asia/Seoul",
    "iso:country":"KR",
    "name:und_x_variant":[
        "An\u2019gong-ni",
        "An\u2019gok"
    ],
    "wof:name":"An-gok-ri",
    "wof:placetype":"locality"
},
  "geometry": {"coordinates":[128.83972,35.30139000000001],"type":"Point"}
}