{
  "type": "Feature",
  "properties": {
    "gn:admin1_code":"17.0",
    "gn:asciiname":"Oji-ri",
    "gn:country_code":"KR",
    "gn:dem":7,
    "gn:feature_class":"P",
    "gn:feature_code":"PPLL",
    "gn:name":"Oji-ri",
    "gn:population":0,
    "gn:timezone":"Asia/Seoul",
    "iso:country":"KR",
    "name:und_x_variant":[
        "\uc624\uc9c0\ub9ac",
        "Oji-ri"
    ],
    "wof:name":"Oji-ri",
    "wof:placetype":"locality"
},
  "geometry": {"coordinates":[126.37090000000001,36.9578],"type":"Point"}
}