{
  "type": "Feature",
  "properties": {
    "gn:admin1_code":"16.0",
    "gn:asciiname":"Baengnyeondong",
    "gn:country_code":"KR",
    "gn:dem":73,
    "gn:feature_class":"P",
    "gn:feature_code":"PPL",
    "gn:name":"Baengnyeondong",
    "gn:population":0,
    "gn:timezone":"Asia/Seoul",
    "iso:country":"KR",
    "name:kor_x_preferred":[
        "\ubc31\ub828\ub3d9"
    ],
    "wof:name":"Baengnyeondong",
    "wof:placetype":"locality"
},
  "geometry": {"coordinates":[126.97393,35.032],"type":"Point"}
}