{
  "type": "Feature",
  "properties": {
    "gn:admin1_code":"17.0",
    "gn:asciiname":"Saem-gol",
    "gn:country_code":"KR",
    "gn:dem":42,
    "gn:feature_class":"P",
    "gn:feature_code":"PPL",
    "gn:name":"Saem-gol",
    "gn:population":0,
    "gn:timezone":"Asia/Seoul",
    "iso:country":"KR",
    "name:und_x_variant":[
        "Ch\u014fng-dong",
        "Saem-kol",
        "\uc0d8\uace8",
        "Saem-gol"
    ],
    "wof:name":"Saem-gol",
    "wof:placetype":"locality"
},
  "geometry": {"coordinates":[126.4062,36.743],"type":"Point"}
}