{
  "type": "Feature",
  "properties": {
    "gn:admin1_code":"20.0",
    "gn:asciiname":"Wonjon",
    "gn:cc2":"KR",
    "gn:country_code":"KR",
    "gn:dem":33,
    "gn:feature_class":"P",
    "gn:feature_code":"PPL",
    "gn:name":"W\u014fnj\u014fn",
    "gn:population":0,
    "gn:timezone":"Asia/Seoul",
    "iso:country":"KR",
    "name:und_x_variant":[
        "W\u014fnj\u014fl-li",
        "W\u014fnj\u014fn"
    ],
    "wof:name":"Wonjon",
    "wof:placetype":"locality"
},
  "geometry": {"coordinates":[127.94056,35.10694],"type":"Point"}
}