{
  "type": "Feature",
  "properties": {
    "gn:admin1_code":"14.0",
    "gn:asciiname":"Sam-dong",
    "gn:country_code":"KR",
    "gn:dem":413,
    "gn:feature_class":"P",
    "gn:feature_code":"PPL",
    "gn:name":"Sam-dong",
    "gn:population":0,
    "gn:timezone":"Asia/Seoul",
    "iso:country":"KR",
    "wof:name":"Sam-dong",
    "wof:placetype":"locality"
},
  "geometry": {"coordinates":[128.92056000000002,36.86833],"type":"Point"}
}