{
  "type": "Feature",
  "properties": {
    "gn:admin1_code":"3.0",
    "gn:asciiname":"Anbang",
    "gn:country_code":"KR",
    "gn:dem":276,
    "gn:feature_class":"P",
    "gn:feature_code":"PPL",
    "gn:name":"Anbang",
    "gn:population":0,
    "gn:timezone":"Asia/Seoul",
    "iso:country":"KR",
    "name:deu_x_preferred":[
        "Anbang"
    ],
    "name:fra_x_preferred":[
        "Anbang"
    ],
    "name:kor_x_preferred":[
        "\uc548\ubc29 \ubcf4\ud5d8"
    ],
    "name:und_x_variant":[
        "\uc548\ubc29"
    ],
    "name:zho_x_preferred":[
        "\u5b89\u90a6\u4fdd\u9669"
    ],
    "wof:name":"Anbang",
    "wof:placetype":"locality"
},
  "geometry": {"coordinates":[127.35269,35.76143],"type":"Point"}
}