{
  "type": "Feature",
  "properties": {
    "gn:admin1_code":"17.0",
    "gn:asciiname":"Tokok",
    "gn:country_code":"KR",
    "gn:dem":41,
    "gn:feature_class":"P",
    "gn:feature_code":"PPL",
    "gn:name":"Tokok",
    "gn:population":0,
    "gn:timezone":"Asia/Seoul",
    "iso:country":"KR",
    "name:und_x_variant":[
        "\ub3c4\uace1",
        "Tokok"
    ],
    "wof:name":"Tokok",
    "wof:placetype":"locality"
},
  "geometry": {"coordinates":[126.6139,36.828],"type":"Point"}
}