{
  "type": "Feature",
  "properties": {
    "gn:admin1_code":"14.0",
    "gn:asciiname":"Seongmitdong",
    "gn:country_code":"KR",
    "gn:dem":128,
    "gn:feature_class":"P",
    "gn:feature_code":"PPL",
    "gn:name":"Seongmitdong",
    "gn:population":0,
    "gn:timezone":"Asia/Seoul",
    "iso:country":"KR",
    "name:kor_x_preferred":[
        "\uc131\ubc11\ub3d9"
    ],
    "wof:name":"Seongmitdong",
    "wof:placetype":"locality"
},
  "geometry": {"coordinates":[128.78813,36.04521],"type":"Point"}
}