{
  "type": "Feature",
  "properties": {
    "gn:admin1_code":"11.0",
    "gn:asciiname":"Kumhosaga-dong",
    "gn:country_code":"KR",
    "gn:dem":28,
    "gn:feature_class":"P",
    "gn:feature_code":"PPL",
    "gn:name":"K\u016dmhosaga-dong",
    "gn:population":0,
    "gn:timezone":"Asia/Seoul",
    "iso:country":"KR",
    "name:und_x_variant":[
        "\uae08\ud6384\uac00\ub3d9",
        "K\u016dmhosaga-dong"
    ],
    "wof:name":"Kumhosaga-dong",
    "wof:placetype":"locality"
},
  "geometry": {"coordinates":[127.02273999999998,37.54354],"type":"Point"}
}