{
  "type": "Feature",
  "properties": {
    "gn:admin1_code":"16.0",
    "gn:asciiname":"Pyeongsan",
    "gn:country_code":"KR",
    "gn:dem":40,
    "gn:feature_class":"P",
    "gn:feature_code":"PPL",
    "gn:name":"Pyeongsan",
    "gn:population":0,
    "gn:timezone":"Asia/Seoul",
    "iso:country":"KR",
    "name:kor_x_preferred":[
        "\ud3c9\uc0b0"
    ],
    "wof:name":"Pyeongsan",
    "wof:placetype":"locality"
},
  "geometry": {"coordinates":[126.78876,35.23945],"type":"Point"}
}