{
  "type": "Feature",
  "properties": {
    "gn:admin1_code":"6.0",
    "gn:asciiname":"Sem-mal",
    "gn:country_code":"KR",
    "gn:dem":443,
    "gn:feature_class":"P",
    "gn:feature_code":"PPL",
    "gn:name":"Sem-mal",
    "gn:population":0,
    "gn:timezone":"Asia/Seoul",
    "iso:country":"KR",
    "wof:name":"Sem-mal",
    "wof:placetype":"locality"
},
  "geometry": {"coordinates":[128.65111000000002,37.35639000000001],"type":"Point"}
}