{
  "type": "Feature",
  "properties": {
    "gn:admin1_code":"16.0",
    "gn:asciiname":"Tangho-ri",
    "gn:country_code":"KR",
    "gn:dem":155,
    "gn:feature_class":"P",
    "gn:feature_code":"PPL",
    "gn:name":"Tangho-ri",
    "gn:population":0,
    "gn:timezone":"Asia/Seoul",
    "iso:country":"KR",
    "name:und_x_variant":[
        "Tangp\u2019o"
    ],
    "wof:name":"Tangho-ri",
    "wof:placetype":"locality"
},
  "geometry": {"coordinates":[126.28333000000001,34.73333],"type":"Point"}
}