{
  "type": "Feature",
  "properties": {
    "gn:admin1_code":"14.0",
    "gn:asciiname":"Hanjok-tong",
    "gn:country_code":"KR",
    "gn:dem":244,
    "gn:feature_class":"P",
    "gn:feature_code":"PPL",
    "gn:name":"Hanj\u014fk-tong",
    "gn:population":0,
    "gn:timezone":"Asia/Seoul",
    "iso:country":"KR",
    "name:und_x_variant":[
        "\ud55c\uc801\ub3d9",
        "Hanj\u014fk-tong"
    ],
    "wof:name":"Hanjok-tong",
    "wof:placetype":"locality"
},
  "geometry": {"coordinates":[127.95877,35.98047000000001],"type":"Point"}
}