{
  "type": "Feature",
  "properties": {
    "gn:admin1_code":"16.0",
    "gn:asciiname":"Songjeong",
    "gn:country_code":"KR",
    "gn:dem":45,
    "gn:feature_class":"P",
    "gn:feature_code":"PPL",
    "gn:name":"Songjeong",
    "gn:population":0,
    "gn:timezone":"Asia/Seoul",
    "iso:country":"KR",
    "name:kor_x_preferred":[
        "Songj\u014fng"
    ],
    "name:und_x_variant":[
        "\uc1a1\uc815",
        "Songjeong"
    ],
    "wof:name":"Songjeong",
    "wof:placetype":"locality"
},
  "geometry": {"coordinates":[126.57738999999999,34.61879],"type":"Point"}
}