{
  "type": "Feature",
  "properties": {
    "gn:admin1_code":"16.0",
    "gn:asciiname":"Changsa-ri",
    "gn:country_code":"KR",
    "gn:dem":7,
    "gn:feature_class":"P",
    "gn:feature_code":"PPL",
    "gn:name":"Changsa-ri",
    "gn:population":0,
    "gn:timezone":"Asia/Seoul",
    "iso:country":"KR",
    "name:kor_x_preferred":[
        "\uc775\uae08"
    ],
    "name:kor_x_variant":[
        "Ikk\u016dm"
    ],
    "name:und_x_variant":[
        "Ikk\u016dm-ni"
    ],
    "wof:name":"Changsa-ri",
    "wof:placetype":"locality"
},
  "geometry": {"coordinates":[127.39202,34.51071],"type":"Point"}
}