{
  "type": "Feature",
  "properties": {
    "gn:admin1_code":"16.0",
    "gn:asciiname":"Taekchon",
    "gn:country_code":"KR",
    "gn:dem":13,
    "gn:feature_class":"P",
    "gn:feature_code":"PPL",
    "gn:name":"Taekchon",
    "gn:population":0,
    "gn:timezone":"Asia/Seoul",
    "iso:country":"KR",
    "name:kor_x_preferred":[
        "\ud0dd\ucd0c"
    ],
    "wof:name":"Taekchon",
    "wof:placetype":"locality"
},
  "geometry": {"coordinates":[126.69789,35.00364],"type":"Point"}
}