{
  "type": "Feature",
  "properties": {
    "gn:admin1_code":"5.0",
    "gn:asciiname":"Sae-gol",
    "gn:country_code":"KR",
    "gn:dem":200,
    "gn:feature_class":"P",
    "gn:feature_code":"PPL",
    "gn:name":"Sae-gol",
    "gn:population":0,
    "gn:timezone":"Asia/Seoul",
    "iso:country":"KR",
    "name:und_x_variant":[
        "\uc0c8\uace8",
        "Sae-gol"
    ],
    "wof:name":"Sae-gol",
    "wof:placetype":"locality"
},
  "geometry": {"coordinates":[127.7199,36.3964],"type":"Point"}
}