{
  "type": "Feature",
  "properties": {
    "gn:admin1_code":"14.0",
    "gn:asciiname":"Mon-maul",
    "gn:country_code":"KR",
    "gn:dem":172,
    "gn:feature_class":"P",
    "gn:feature_code":"PPL",
    "gn:name":"Mon-ma\u016dl",
    "gn:population":0,
    "gn:timezone":"Asia/Seoul",
    "iso:country":"KR",
    "name:und_x_variant":[
        "\ubabb\ub9c8\uc744",
        "Mon-ma\u016dl"
    ],
    "wof:name":"Mon-maul",
    "wof:placetype":"locality"
},
  "geometry": {"coordinates":[129.23689999999999,36.4292],"type":"Point"}
}