{
  "type": "Feature",
  "properties": {
    "gn:admin1_code":"17.0",
    "gn:asciiname":"Tolmoru",
    "gn:country_code":"KR",
    "gn:dem":16,
    "gn:feature_class":"P",
    "gn:feature_code":"PPL",
    "gn:name":"Tolmoru",
    "gn:population":0,
    "gn:timezone":"Asia/Seoul",
    "iso:country":"KR",
    "name:und_x_variant":[
        "\ub3cc\ubaa8\ub8e8",
        "Dolmoru",
        "Tolmoru"
    ],
    "wof:name":"Tolmoru",
    "wof:placetype":"locality"
},
  "geometry": {"coordinates":[126.52778000000001,37.02472],"type":"Point"}
}