{
  "type": "Feature",
  "properties": {
    "gn:admin1_code":"5.0",
    "gn:asciiname":"Motan",
    "gn:country_code":"KR",
    "gn:dem":169,
    "gn:feature_class":"P",
    "gn:feature_code":"PPL",
    "gn:name":"Motan",
    "gn:population":0,
    "gn:timezone":"Asia/Seoul",
    "iso:country":"KR",
    "name:kor_x_preferred":[
        "\ubabb\uc548"
    ],
    "wof:name":"Motan",
    "wof:placetype":"locality"
},
  "geometry": {"coordinates":[128.15375,37.00869],"type":"Point"}
}