{
  "type": "Feature",
  "properties": {
    "gn:admin1_code":"13.0",
    "gn:asciiname":"Nangyuri",
    "gn:country_code":"KR",
    "gn:dem":144,
    "gn:feature_class":"P",
    "gn:feature_code":"PPL",
    "gn:name":"Nangyuri",
    "gn:population":0,
    "gn:timezone":"Asia/Seoul",
    "iso:country":"KR",
    "name:kor_x_preferred":[
        "\ub0ad\uc720\ub9ac"
    ],
    "wof:name":"Nangyuri",
    "wof:placetype":"locality"
},
  "geometry": {"coordinates":[127.32598,38.00936],"type":"Point"}
}