{
  "type": "Feature",
  "properties": {
    "gn:admin1_code":"6.0",
    "gn:asciiname":"Oksil",
    "gn:country_code":"KR",
    "gn:dem":440,
    "gn:feature_class":"P",
    "gn:feature_code":"PPL",
    "gn:name":"\u014eksil",
    "gn:population":0,
    "gn:timezone":"Asia/Seoul",
    "iso:country":"KR",
    "name:kor_x_preferred":[
        "\uc5b5\uc2e4"
    ],
    "name:kor_x_variant":[
        "\u014eksil"
    ],
    "wof:name":"Oksil",
    "wof:placetype":"locality"
},
  "geometry": {"coordinates":[128.76070000000001,37.3496],"type":"Point"}
}