{
  "type": "Feature",
  "properties": {
    "gn:admin1_code":"5.0",
    "gn:asciiname":"Dongsanmal",
    "gn:country_code":"KR",
    "gn:dem":233,
    "gn:feature_class":"P",
    "gn:feature_code":"PPL",
    "gn:name":"Dongsanmal",
    "gn:population":0,
    "gn:timezone":"Asia/Seoul",
    "iso:country":"KR",
    "name:kor_x_preferred":[
        "\ub3d9\uc0b0\ub9d0"
    ],
    "wof:name":"Dongsanmal",
    "wof:placetype":"locality"
},
  "geometry": {"coordinates":[127.65898,36.62655],"type":"Point"}
}