{
  "type": "Feature",
  "properties": {
    "gn:admin1_code":"10.0",
    "gn:asciiname":"Okpo",
    "gn:country_code":"KR",
    "gn:dem":39,
    "gn:feature_class":"P",
    "gn:feature_code":"PPL",
    "gn:name":"Okpo",
    "gn:population":0,
    "gn:timezone":"Asia/Seoul",
    "iso:country":"KR",
    "name:kor_x_preferred":[
        "\uc625\ud3ec"
    ],
    "wof:name":"Okpo",
    "wof:placetype":"locality"
},
  "geometry": {"coordinates":[128.83806999999999,35.11857],"type":"Point"}
}