{
  "type": "Feature",
  "properties": {
    "gn:admin1_code":"14.0",
    "gn:asciiname":"Jirye",
    "gn:country_code":"KR",
    "gn:dem":193,
    "gn:feature_class":"P",
    "gn:feature_code":"PPL",
    "gn:name":"Jirye",
    "gn:population":0,
    "gn:timezone":"Asia/Seoul",
    "iso:country":"KR",
    "name:kor_x_preferred":[
        "\uc9c0\ub840"
    ],
    "wof:name":"Jirye",
    "wof:placetype":"locality"
},
  "geometry": {"coordinates":[128.76785000000001,36.71774],"type":"Point"}
}