{
  "type": "Feature",
  "properties": {
    "gn:admin1_code":"6.0",
    "gn:asciiname":"Ip'yong",
    "gn:country_code":"KR",
    "gn:dem":295,
    "gn:feature_class":"P",
    "gn:feature_code":"PPL",
    "gn:name":"Ip\u2019y\u014fng",
    "gn:population":0,
    "gn:timezone":"Asia/Seoul",
    "iso:country":"KR",
    "name:kor_x_preferred":[
        "\uc774\ud3c9"
    ],
    "name:kor_x_variant":[
        "Ip\u2019y\u014fng"
    ],
    "wof:name":"Ip'yong",
    "wof:placetype":"locality"
},
  "geometry": {"coordinates":[128.61609999999999,37.3704],"type":"Point"}
}