{
  "type": "Feature",
  "properties": {
    "gn:admin1_code":"14.0",
    "gn:asciiname":"Jaegunggol",
    "gn:country_code":"KR",
    "gn:dem":185,
    "gn:feature_class":"P",
    "gn:feature_code":"PPL",
    "gn:name":"Jaegunggol",
    "gn:population":0,
    "gn:timezone":"Asia/Seoul",
    "iso:country":"KR",
    "name:kor_x_preferred":[
        "\uc7ac\uad81\uace8"
    ],
    "wof:name":"Jaegunggol",
    "wof:placetype":"locality"
},
  "geometry": {"coordinates":[128.87773000000001,36.575],"type":"Point"}
}