{
  "type": "Feature",
  "properties": {
    "gn:admin1_code":"18.0",
    "gn:asciiname":"Yodong",
    "gn:country_code":"KR",
    "gn:dem":41,
    "gn:feature_class":"P",
    "gn:feature_code":"PPL",
    "gn:name":"Yodong",
    "gn:population":0,
    "gn:timezone":"Asia/Seoul",
    "iso:country":"KR",
    "name:kor_x_preferred":[
        "\uc694\ub3d9"
    ],
    "wof:name":"Yodong",
    "wof:placetype":"locality"
},
  "geometry": {"coordinates":[126.75288999999999,35.09689],"type":"Point"}
}