{
  "type": "Feature",
  "properties": {
    "gn:admin1_code":"13.0",
    "gn:asciiname":"Myeokjeol",
    "gn:country_code":"KR",
    "gn:dem":9,
    "gn:feature_class":"P",
    "gn:feature_code":"PPL",
    "gn:name":"Myeokjeol",
    "gn:population":0,
    "gn:timezone":"Asia/Seoul",
    "iso:country":"KR",
    "name:kor_x_preferred":[
        "\uba71\uc808"
    ],
    "name:kor_x_variant":[
        "My\u014fkch\u014fl"
    ],
    "wof:name":"Myeokjeol",
    "wof:placetype":"locality"
},
  "geometry": {"coordinates":[126.73151,37.65544000000001],"type":"Point"}
}