{
  "type": "Feature",
  "properties": {
    "gn:admin1_code":"13.0",
    "gn:asciiname":"Dunmal",
    "gn:country_code":"KR",
    "gn:dem":76,
    "gn:feature_class":"P",
    "gn:feature_code":"PPL",
    "gn:name":"Dunmal",
    "gn:population":0,
    "gn:timezone":"Asia/Seoul",
    "iso:country":"KR",
    "name:kor_x_preferred":[
        "\ub454\ub9d0"
    ],
    "name:und_x_variant":[
        "Tun-mal"
    ],
    "wof:name":"Dunmal",
    "wof:placetype":"locality"
},
  "geometry": {"coordinates":[127.62090999999999,37.11419],"type":"Point"}
}