{
  "type": "Feature",
  "properties": {
    "gn:admin1_code":"14.0",
    "gn:asciiname":"Singi",
    "gn:country_code":"KR",
    "gn:dem":160,
    "gn:feature_class":"P",
    "gn:feature_code":"PPL",
    "gn:name":"Singi",
    "gn:population":0,
    "gn:timezone":"Asia/Seoul",
    "iso:country":"KR",
    "name:und_x_variant":[
        "\uc2e0\uae30",
        "Sin\u2019gi",
        "Singi"
    ],
    "wof:name":"Singi",
    "wof:placetype":"locality"
},
  "geometry": {"coordinates":[128.57731999999999,35.66111],"type":"Point"}
}