{
  "type": "Feature",
  "properties": {
    "gn:admin1_code":"16.0",
    "gn:asciiname":"Sunyong-ni",
    "gn:cc2":"KR",
    "gn:country_code":"KR",
    "gn:dem":37,
    "gn:feature_class":"P",
    "gn:feature_code":"PPL",
    "gn:name":"Sunyong-ni",
    "gn:population":0,
    "gn:timezone":"Asia/Seoul",
    "iso:country":"KR",
    "name:eng_x_preferred":[
        "Sunyong"
    ],
    "name:eng_x_variant":[
        "Sunyong-ni"
    ],
    "name:und_x_variant":[
        "Suyong-ni",
        "Sunyong-ni"
    ],
    "wof:name":"Sunyong",
    "wof:placetype":"locality"
},
  "geometry": {"coordinates":[126.49472,35.23139],"type":"Point"}
}