{
  "type": "Feature",
  "properties": {
    "gn:admin1_code":"17.0",
    "gn:asciiname":"Chungsal-li",
    "gn:country_code":"KR",
    "gn:dem":34,
    "gn:feature_class":"P",
    "gn:feature_code":"PPL",
    "gn:name":"Ch\u016dngsal-li",
    "gn:population":0,
    "gn:timezone":"Asia/Seoul",
    "iso:country":"KR",
    "name:und_x_variant":[
        "\uc99d\uc0b0\ub9ac",
        "Ch\u016dngsal-li"
    ],
    "wof:name":"Chungsal-li",
    "wof:placetype":"locality"
},
  "geometry": {"coordinates":[127.0046,36.2541],"type":"Point"}
}