{
  "type": "Feature",
  "properties": {
    "gn:admin1_code":"17.0",
    "gn:asciiname":"Toeneji",
    "gn:country_code":"KR",
    "gn:dem":14,
    "gn:feature_class":"P",
    "gn:feature_code":"PPL",
    "gn:name":"Toeneji",
    "gn:population":0,
    "gn:timezone":"Asia/Seoul",
    "iso:country":"KR",
    "name:und_x_variant":[
        "\ub418\ub124\uc9c0",
        "Toeneji"
    ],
    "wof:name":"Toeneji",
    "wof:placetype":"locality"
},
  "geometry": {"coordinates":[126.3969,36.5086],"type":"Point"}
}