{
  "type": "Feature",
  "properties": {
    "gn:admin1_code":"20.0",
    "gn:asciiname":"Kye-dong",
    "gn:cc2":"KR",
    "gn:country_code":"KR",
    "gn:dem":2,
    "gn:feature_class":"P",
    "gn:feature_code":"PPL",
    "gn:name":"Kye-dong",
    "gn:population":0,
    "gn:timezone":"Asia/Seoul",
    "iso:country":"KR",
    "name:und_x_variant":[
        "Ke-dong",
        "Kye-dong"
    ],
    "wof:name":"Kye-dong",
    "wof:placetype":"locality"
},
  "geometry": {"coordinates":[127.76667,35.06667],"type":"Point"}
}