{
  "type": "Feature",
  "properties": {
    "gn:admin1_code":"14.0",
    "gn:asciiname":"Chilmaesil",
    "gn:country_code":"KR",
    "gn:dem":99,
    "gn:feature_class":"P",
    "gn:feature_code":"PPL",
    "gn:name":"Chilmaesil",
    "gn:population":0,
    "gn:timezone":"Asia/Seoul",
    "iso:country":"KR",
    "name:und_x_variant":[
        "\uc9c8\ub9e4\uc2e4",
        "Chilmaesil"
    ],
    "wof:name":"Chilmaesil",
    "wof:placetype":"locality"
},
  "geometry": {"coordinates":[128.19479999999999,36.2711],"type":"Point"}
}