{
  "type": "Feature",
  "properties": {
    "gn:admin1_code":"5.0",
    "gn:asciiname":"Chit'al-li",
    "gn:country_code":"KR",
    "gn:dem":104,
    "gn:feature_class":"P",
    "gn:feature_code":"PPL",
    "gn:name":"Chit\u2019al-li",
    "gn:population":0,
    "gn:timezone":"Asia/Seoul",
    "iso:country":"KR",
    "name:und_x_variant":[
        "Chit\u2019an-ni",
        "\uc9c0\ud0c4\ub9ac",
        "Chit\u2019al-li"
    ],
    "wof:name":"Chit'al-li",
    "wof:placetype":"locality"
},
  "geometry": {"coordinates":[127.6747,36.2475],"type":"Point"}
}