{
  "type": "Feature",
  "properties": {
    "gn:admin1_code":"13.0",
    "gn:asciiname":"Seogeunbo",
    "gn:country_code":"KR",
    "gn:dem":13,
    "gn:feature_class":"P",
    "gn:feature_code":"PPL",
    "gn:name":"Seogeunbo",
    "gn:population":0,
    "gn:timezone":"Asia/Seoul",
    "iso:country":"KR",
    "name:und_x_variant":[
        "\uc11c\uadfc\ubcf4",
        "S\u014fg\u016dnbo",
        "Seogeunbo"
    ],
    "wof:name":"Seogeunbo",
    "wof:placetype":"locality"
},
  "geometry": {"coordinates":[127.04813,36.93596],"type":"Point"}
}