{
  "type": "Feature",
  "properties": {
    "gn:admin1_code":"19.0",
    "gn:asciiname":"Bangamoe",
    "gn:country_code":"KR",
    "gn:dem":83,
    "gn:feature_class":"P",
    "gn:feature_code":"PPL",
    "gn:name":"Bangamoe",
    "gn:population":0,
    "gn:timezone":"Asia/Seoul",
    "iso:country":"KR",
    "name:und_x_variant":[
        "\ubc29\uc544\ubafc",
        "Pangamoe",
        "Bangamoe"
    ],
    "wof:name":"Bangamoe",
    "wof:placetype":"locality"
},
  "geometry": {"coordinates":[127.39230000000001,36.27146],"type":"Point"}
}