{
  "type": "Feature",
  "properties": {
    "gn:admin1_code":"13.0",
    "gn:asciiname":"Samni",
    "gn:country_code":"KR",
    "gn:dem":33,
    "gn:feature_class":"P",
    "gn:feature_code":"PPL",
    "gn:name":"Samni",
    "gn:population":0,
    "gn:timezone":"Asia/Seoul",
    "iso:country":"KR",
    "name:kor_x_preferred":[
        "\uc0bc\ub9ac"
    ],
    "name:und_x_variant":[
        "\uc0bc\ub9ac",
        "Samni"
    ],
    "wof:name":"Samni",
    "wof:placetype":"locality"
},
  "geometry": {"coordinates":[127.22920000000001,37.593],"type":"Point"}
}