{
  "type": "Feature",
  "properties": {
    "gn:admin1_code":"5.0",
    "gn:asciiname":"Wonsowon",
    "gn:country_code":"KR",
    "gn:dem":203,
    "gn:feature_class":"P",
    "gn:feature_code":"PPL",
    "gn:name":"W\u014fns\u014fw\u014fn",
    "gn:population":0,
    "gn:timezone":"Asia/Seoul",
    "iso:country":"KR",
    "name:und_x_variant":[
        "\uc6d0\uc11c\uc6d0",
        "W\u014fns\u014fw\u014fn"
    ],
    "wof:name":"Wonsowon",
    "wof:placetype":"locality"
},
  "geometry": {"coordinates":[127.7234,36.4104],"type":"Point"}
}