{
  "type": "Feature",
  "properties": {
    "gn:admin1_code":"6.0",
    "gn:asciiname":"Soyongjon",
    "gn:country_code":"KR",
    "gn:dem":500,
    "gn:feature_class":"P",
    "gn:feature_code":"PPL",
    "gn:name":"Soyongj\u014fn",
    "gn:population":0,
    "gn:timezone":"Asia/Seoul",
    "iso:country":"KR",
    "name:kor_x_preferred":[
        "\uc18c\uc6a9\uc804"
    ],
    "name:kor_x_variant":[
        "Soyongj\u014fn"
    ],
    "wof:name":"Soyongjon",
    "wof:placetype":"locality"
},
  "geometry": {"coordinates":[128.4691,37.3272],"type":"Point"}
}