{
  "type": "Feature",
  "properties": {
    "gn:admin1_code":"14.0",
    "gn:asciiname":"Yeongyang Gun",
    "gn:country_code":"KR",
    "gn:dem":233,
    "gn:feature_class":"P",
    "gn:feature_code":"PPL",
    "gn:name":"Yeongyang Gun",
    "gn:population":0,
    "gn:timezone":"Asia/Seoul",
    "iso:country":"KR",
    "name:und_x_variant":[
        "Eiy\u014d-gun",
        "\uc601\uc591",
        "Y\u014fngyang",
        "Eiy\u014d"
    ],
    "wof:name":"Yeongyang Gun",
    "wof:placetype":"locality"
},
  "geometry": {"coordinates":[129.1139,36.6648],"type":"Point"}
}