{
  "type": "Feature",
  "properties": {
    "gn:admin1_code":"14.0",
    "gn:asciiname":"Pakkisil",
    "gn:country_code":"KR",
    "gn:dem":409,
    "gn:feature_class":"P",
    "gn:feature_code":"PPL",
    "gn:name":"Pakkisil",
    "gn:population":0,
    "gn:timezone":"Asia/Seoul",
    "iso:country":"KR",
    "name:und_x_variant":[
        "Suha",
        "Pakkisil",
        "\ubc16\uc774\uc2e4"
    ],
    "wof:name":"Pakkisil",
    "wof:placetype":"locality"
},
  "geometry": {"coordinates":[128.19130000000001,36.3009],"type":"Point"}
}