{
  "type": "Feature",
  "properties": {
    "gn:admin1_code":"20.0",
    "gn:asciiname":"Chungam",
    "gn:country_code":"KR",
    "gn:dem":175,
    "gn:feature_class":"P",
    "gn:feature_code":"PPL",
    "gn:name":"Chungam",
    "gn:population":0,
    "gn:timezone":"Asia/Seoul",
    "iso:country":"KR",
    "name:und_x_variant":[
        "\uc911\uc554",
        "Chungam"
    ],
    "wof:name":"Chungam",
    "wof:placetype":"locality"
},
  "geometry": {"coordinates":[127.83951,35.51211],"type":"Point"}
}