{
  "type": "Feature",
  "properties": {
    "gn:admin1_code":"20.0",
    "gn:asciiname":"Un'gok",
    "gn:country_code":"KR",
    "gn:dem":448,
    "gn:feature_class":"P",
    "gn:feature_code":"PPL",
    "gn:name":"Un\u2019gok",
    "gn:population":0,
    "gn:timezone":"Asia/Seoul",
    "iso:country":"KR",
    "name:und_x_variant":[
        "\uc6b4\uace1",
        "Un\u2019gok"
    ],
    "wof:name":"Un'gok",
    "wof:placetype":"locality"
},
  "geometry": {"coordinates":[127.67989,35.62661],"type":"Point"}
}