{
  "type": "Feature",
  "properties": {
    "gn:admin1_code":"17.0",
    "gn:asciiname":"Araettok-kol",
    "gn:country_code":"KR",
    "gn:dem":19,
    "gn:feature_class":"P",
    "gn:feature_code":"PPL",
    "gn:name":"Araettok-kol",
    "gn:population":0,
    "gn:timezone":"Asia/Seoul",
    "iso:country":"KR",
    "name:und_x_variant":[
        "\uc544\ub7ab\ub3c5\uace8",
        "Araettok-kol"
    ],
    "wof:name":"Araettok-kol",
    "wof:placetype":"locality"
},
  "geometry": {"coordinates":[126.5718,36.8776],"type":"Point"}
}