{
  "type": "Feature",
  "properties": {
    "gn:admin1_code":"16.0",
    "gn:asciiname":"P'ungnam-ni",
    "gn:country_code":"KR",
    "gn:dem":17,
    "gn:feature_class":"P",
    "gn:feature_code":"PPLL",
    "gn:name":"P\u2019ungnam-ni",
    "gn:population":0,
    "gn:timezone":"Asia/Seoul",
    "iso:country":"KR",
    "name:kor_x_preferred":[
        "P\u2019ungnam-ni"
    ],
    "name:und_x_variant":[
        "Tongp\u2019ung-ni",
        "P\u2019ungnam",
        "H\u014dnan-ri"
    ],
    "wof:name":"P'ungnam-ni",
    "wof:placetype":"locality"
},
  "geometry": {"coordinates":[127.24207,34.52053],"type":"Point"}
}