{
  "type": "Feature",
  "properties": {
    "gn:admin1_code":"17.0",
    "gn:asciiname":"Sindang-ni",
    "gn:cc2":"KR",
    "gn:country_code":"KR",
    "gn:dem":18,
    "gn:feature_class":"P",
    "gn:feature_code":"PPL",
    "gn:name":"Sindang-ni",
    "gn:population":0,
    "gn:timezone":"Asia/Seoul",
    "iso:country":"KR",
    "name:und_x_variant":[
        "Sindang",
        "Sindang-ni"
    ],
    "wof:name":"Sindang-ni",
    "wof:placetype":"locality"
},
  "geometry": {"coordinates":[127.08111,36.23556],"type":"Point"}
}