{
  "type": "Feature",
  "properties": {
    "iso:country":"KR",
    "qs:name":"\uc7a5\uc548\uad6c",
    "qs:name_adm0":"\ud55c\uad6d",
    "qs:name_adm1":"\uacbd\uae30\ub3c4",
    "qs:photos":6,
    "qs:photos_1k":1,
    "qs:photos_9k":9,
    "qs:photos_9r":9,
    "qs:photos_all":2083,
    "qs:photos_sr":1,
    "qs:placetype":"LocalAdmin",
    "qs:pop_sr":"0",
    "wof:name":"\uc7a5\uc548\uad6c",
    "wof:placetype":"localadmin"
},
  "geometry": {"coordinates":[127.01002099999999,37.295251],"type":"Point"}
}