{
  "type": "Feature",
  "properties": {
    "gn:admin1_code":"14.0",
    "gn:asciiname":"Inju",
    "gn:country_code":"KR",
    "gn:dem":21,
    "gn:feature_class":"P",
    "gn:feature_code":"PPL",
    "gn:name":"Inju",
    "gn:population":0,
    "gn:timezone":"Asia/Seoul",
    "iso:country":"KR",
    "name:ceb_x_preferred":[
        "Inju"
    ],
    "name:est_x_preferred":[
        "Inju"
    ],
    "name:hye_x_preferred":[
        "\u053b\u0576\u0575\u0578\u0582"
    ],
    "name:kor_x_preferred":[
        "\uc778\uc8fc"
    ],
    "name:pol_x_preferred":[
        "Inju"
    ],
    "name:swe_x_preferred":[
        "Inju"
    ],
    "name:vol_x_preferred":[
        "Inju"
    ],
    "wof:name":"Inju",
    "wof:placetype":"locality"
},
  "geometry": {"coordinates":[129.33949999999999,35.98319],"type":"Point"}
}