{
  "type": "Feature",
  "properties": {
    "gn:admin1_code":"14.0",
    "gn:asciiname":"Hakgye",
    "gn:country_code":"KR",
    "gn:dem":10,
    "gn:feature_class":"P",
    "gn:feature_code":"PPL",
    "gn:name":"Hakgye",
    "gn:population":0,
    "gn:timezone":"Asia/Seoul",
    "iso:country":"KR",
    "name:kor_x_preferred":[
        "\ud559\uacc4"
    ],
    "wof:name":"Hakgye",
    "wof:placetype":"locality"
},
  "geometry": {"coordinates":[129.50231000000002,35.92868],"type":"Point"}
}