{
  "type": "Feature",
  "properties": {
    "gn:admin1_code":"14.0",
    "gn:asciiname":"Domi",
    "gn:country_code":"KR",
    "gn:dem":97,
    "gn:feature_class":"P",
    "gn:feature_code":"PPL",
    "gn:name":"Domi",
    "gn:population":0,
    "gn:timezone":"Asia/Seoul",
    "iso:country":"KR",
    "name:ceb_x_preferred":[
        "Domi"
    ],
    "name:deu_x_preferred":[
        "Domi"
    ],
    "name:fin_x_preferred":[
        "Domi"
    ],
    "name:fra_x_preferred":[
        "Domi"
    ],
    "name:kor_x_preferred":[
        "\ub3c4\ubbf8"
    ],
    "name:rus_x_preferred":[
        "\u0414\u043e\u043c\u0438"
    ],
    "name:ukr_x_preferred":[
        "\u0414\u043e\u043c\u0456"
    ],
    "wof:name":"Domi",
    "wof:placetype":"locality"
},
  "geometry": {"coordinates":[128.33436,36.61433],"type":"Point"}
}