{
  "type": "Feature",
  "properties": {
    "gn:admin1_code":"14.0",
    "gn:asciiname":"Kankoku",
    "gn:country_code":"KR",
    "gn:dem":291,
    "gn:feature_class":"P",
    "gn:feature_code":"PPL",
    "gn:name":"Kankoku",
    "gn:population":0,
    "gn:timezone":"Asia/Seoul",
    "iso:country":"KR",
    "name:und_x_variant":[
        "\uad00\uace1",
        "Kwan\u2019gok"
    ],
    "wof:name":"Kankoku",
    "wof:placetype":"locality"
},
  "geometry": {"coordinates":[129.16849999999999,36.5146],"type":"Point"}
}