{
  "type": "Feature",
  "properties": {
    "gn:admin1_code":"3.0",
    "gn:asciiname":"Mogok",
    "gn:country_code":"KR",
    "gn:dem":281,
    "gn:feature_class":"P",
    "gn:feature_code":"PPL",
    "gn:name":"Mogok",
    "gn:population":0,
    "gn:timezone":"Asia/Seoul",
    "iso:country":"KR",
    "name:und_x_variant":[
        "\ubaa8\uace1",
        "Mosil",
        "Mogok"
    ],
    "wof:name":"Mogok",
    "wof:placetype":"locality"
},
  "geometry": {"coordinates":[127.47598000000001,35.89165999999999],"type":"Point"}
}