{
  "type": "Feature",
  "properties": {
    "gn:admin1_code":"6.0",
    "gn:asciiname":"Myongp'a-ri",
    "gn:country_code":"KR",
    "gn:dem":30,
    "gn:feature_class":"P",
    "gn:feature_code":"PPL",
    "gn:name":"My\u014fngp\u2019a-ri",
    "gn:population":0,
    "gn:timezone":"Asia/Seoul",
    "iso:country":"KR",
    "wof:name":"Myongp'a-ri",
    "wof:placetype":"locality"
},
  "geometry": {"coordinates":[128.40000000000001,38.53333],"type":"Point"}
}