{
  "type": "Feature",
  "properties": {
    "gn:admin1_code":"3.0",
    "gn:asciiname":"Chukdong",
    "gn:country_code":"KR",
    "gn:dem":51,
    "gn:feature_class":"P",
    "gn:feature_code":"PPL",
    "gn:name":"Chukdong",
    "gn:population":0,
    "gn:timezone":"Asia/Seoul",
    "iso:country":"KR",
    "name:kor_x_preferred":[
        "\ucd95\ub3d9"
    ],
    "wof:name":"Chukdong",
    "wof:placetype":"locality"
},
  "geometry": {"coordinates":[126.64068,35.36597000000001],"type":"Point"}
}