{
  "type": "Feature",
  "properties": {
    "gn:admin1_code":"13.0",
    "gn:asciiname":"Munhwachon",
    "gn:country_code":"KR",
    "gn:dem":34,
    "gn:feature_class":"P",
    "gn:feature_code":"PPL",
    "gn:name":"Munhwachon",
    "gn:population":0,
    "gn:timezone":"Asia/Seoul",
    "iso:country":"KR",
    "name:und_x_variant":[
        "\ubb38\ud654\ucd0c",
        "Munhwachon",
        "Munhwach\u2019on"
    ],
    "wof:name":"Munhwachon",
    "wof:placetype":"locality"
},
  "geometry": {"coordinates":[126.91722,37.13333],"type":"Point"}
}