{
  "type": "Feature",
  "properties": {
    "gn:admin1_code":"6.0",
    "gn:asciiname":"Anhul-li",
    "gn:country_code":"KR",
    "gn:dem":596,
    "gn:feature_class":"P",
    "gn:feature_code":"PPL",
    "gn:name":"Anh\u016dl-li",
    "gn:population":0,
    "gn:timezone":"Asia/Seoul",
    "iso:country":"KR",
    "name:und_x_variant":[
        "Anh\u016dl-li",
        "\uc548\ud758\ub9ac"
    ],
    "wof:name":"Anhul-li",
    "wof:placetype":"locality"
},
  "geometry": {"coordinates":[128.38442000000001,38.29599],"type":"Point"}
}