{
  "type": "Feature",
  "properties": {
    "gn:admin1_code":"14.0",
    "gn:asciiname":"Ch'oech'onmot",
    "gn:country_code":"KR",
    "gn:dem":134,
    "gn:feature_class":"P",
    "gn:feature_code":"PPL",
    "gn:name":"Ch\u2019oech\u2019onmot",
    "gn:population":0,
    "gn:timezone":"Asia/Seoul",
    "iso:country":"KR",
    "name:und_x_variant":[
        "\ucd5c\ucd0c\ubabb",
        "Ch\u2019oech\u2019onmot"
    ],
    "wof:name":"Ch'oech'onmot",
    "wof:placetype":"locality"
},
  "geometry": {"coordinates":[129.3142,36.6159],"type":"Point"}
}