{
  "type": "Feature",
  "properties": {
    "gn:admin1_code":"3.0",
    "gn:asciiname":"Oeryang",
    "gn:country_code":"KR",
    "gn:dem":207,
    "gn:feature_class":"P",
    "gn:feature_code":"PPL",
    "gn:name":"Oeryang",
    "gn:population":0,
    "gn:timezone":"Asia/Seoul",
    "iso:country":"KR",
    "name:und_x_variant":[
        "\uc678\ub7c9",
        "Oeryang"
    ],
    "wof:name":"Oeryang",
    "wof:placetype":"locality"
},
  "geometry": {"coordinates":[127.14700000000001,35.668],"type":"Point"}
}