{
  "type": "Feature",
  "properties": {
    "gn:admin1_code":"16.0",
    "gn:asciiname":"Daeandong",
    "gn:country_code":"KR",
    "gn:dem":23,
    "gn:feature_class":"P",
    "gn:feature_code":"PPL",
    "gn:name":"Daeandong",
    "gn:population":0,
    "gn:timezone":"Asia/Seoul",
    "iso:country":"KR",
    "name:kor_x_preferred":[
        "\ub300\uc548\ub3d9"
    ],
    "name:und_x_variant":[
        "Taean-dong"
    ],
    "wof:name":"Daeandong",
    "wof:placetype":"locality"
},
  "geometry": {"coordinates":[126.45128,34.82952],"type":"Point"}
}