{
  "type": "Feature",
  "properties": {
    "gn:admin1_code":"3.0",
    "gn:asciiname":"Unjong-ni",
    "gn:country_code":"KR",
    "gn:dem":235,
    "gn:feature_class":"P",
    "gn:feature_code":"PPLL",
    "gn:name":"Unj\u014fng-ni",
    "gn:population":0,
    "gn:timezone":"Asia/Seoul",
    "iso:country":"KR",
    "name:und_x_variant":[
        "\uc6b4\uc815\ub9ac",
        "Unj\u014fng-ni"
    ],
    "wof:name":"Unjong-ni",
    "wof:placetype":"locality"
},
  "geometry": {"coordinates":[127.10316,35.57336],"type":"Point"}
}