{
  "type": "Feature",
  "properties": {
    "gn:admin1_code":"16.0",
    "gn:asciiname":"Kangdong",
    "gn:country_code":"KR",
    "gn:dem":12,
    "gn:feature_class":"P",
    "gn:feature_code":"PPL",
    "gn:name":"Kangdong",
    "gn:population":0,
    "gn:timezone":"Asia/Seoul",
    "iso:country":"KR",
    "name:kor_x_preferred":[
        "\uac15\ub3d9"
    ],
    "name:und_x_variant":[
        "Kangdong-ni",
        "Kangdong"
    ],
    "wof:name":"Kangdong",
    "wof:placetype":"locality"
},
  "geometry": {"coordinates":[127.26294,34.51491],"type":"Point"}
}