{
  "type": "Feature",
  "properties": {
    "gn:admin1_code":"13.0",
    "gn:asciiname":"Songsinsaemaul",
    "gn:country_code":"KR",
    "gn:dem":28,
    "gn:feature_class":"P",
    "gn:feature_code":"PPL",
    "gn:name":"Songsinsaema\u016dl",
    "gn:population":0,
    "gn:timezone":"Asia/Seoul",
    "iso:country":"KR",
    "name:kor_x_preferred":[
        "\uc131\uc2e0\uc0c8\ub9c8\uc744"
    ],
    "name:kor_x_variant":[
        "Songsinsaema\u016dl"
    ],
    "wof:name":"Songsinsaemaul",
    "wof:placetype":"locality"
},
  "geometry": {"coordinates":[126.83528,37.62861],"type":"Point"}
}