{
  "type": "Feature",
  "properties": {
    "gn:admin1_code":"14.0",
    "gn:asciiname":"Haecheon",
    "gn:country_code":"KR",
    "gn:dem":349,
    "gn:feature_class":"P",
    "gn:feature_code":"PPL",
    "gn:name":"Haecheon",
    "gn:population":0,
    "gn:timezone":"Asia/Seoul",
    "iso:country":"KR",
    "name:kor_x_preferred":[
        "\ud574\ucc9c"
    ],
    "name:und_x_variant":[
        "Sangsuch\u2019\u014fn",
        "Haech\u2019\u014fn",
        "Haecheon"
    ],
    "wof:name":"Haecheon",
    "wof:placetype":"locality"
},
  "geometry": {"coordinates":[128.97898000000001,36.63686],"type":"Point"}
}