{
  "type": "Feature",
  "properties": {
    "gn:admin1_code":"6.0",
    "gn:asciiname":"Mena-gol",
    "gn:country_code":"KR",
    "gn:dem":296,
    "gn:feature_class":"P",
    "gn:feature_code":"PPL",
    "gn:name":"Mena-gol",
    "gn:population":0,
    "gn:timezone":"Asia/Seoul",
    "iso:country":"KR",
    "name:kor_x_preferred":[
        "\uba54\ub098\uace8"
    ],
    "wof:name":"Mena-gol",
    "wof:placetype":"locality"
},
  "geometry": {"coordinates":[128.10299999999998,37.4596],"type":"Point"}
}