{
  "type": "Feature",
  "properties": {
    "gn:admin1_code":"14.0",
    "gn:asciiname":"Ach'on",
    "gn:country_code":"KR",
    "gn:dem":97,
    "gn:feature_class":"P",
    "gn:feature_code":"PPL",
    "gn:name":"Ach\u2019\u014fn",
    "gn:population":0,
    "gn:timezone":"Asia/Seoul",
    "iso:country":"KR",
    "name:und_x_variant":[
        "Ach\u2019\u014fn",
        "\uc544\ucc9c"
    ],
    "wof:name":"Ach'on",
    "wof:placetype":"locality"
},
  "geometry": {"coordinates":[128.1157,36.17739],"type":"Point"}
}