{
  "type": "Feature",
  "properties": {
    "gn:admin1_code":"16.0",
    "gn:asciiname":"Tonghak-tong",
    "gn:country_code":"KR",
    "gn:dem":23,
    "gn:feature_class":"P",
    "gn:feature_code":"PPL",
    "gn:name":"Tonghak-tong",
    "gn:population":0,
    "gn:timezone":"Asia/Seoul",
    "iso:country":"KR",
    "name:und_x_variant":[
        "\ub3d9\ud559\ub3d9",
        "Tonghak-tong"
    ],
    "wof:name":"Tonghak-tong",
    "wof:placetype":"locality"
},
  "geometry": {"coordinates":[126.72444,34.53639],"type":"Point"}
}