{
  "type": "Feature",
  "properties": {
    "gn:admin1_code":"20.0",
    "gn:asciiname":"Namok",
    "gn:country_code":"KR",
    "gn:dem":154,
    "gn:feature_class":"P",
    "gn:feature_code":"PPL",
    "gn:name":"Namok",
    "gn:population":0,
    "gn:timezone":"Asia/Seoul",
    "iso:country":"KR",
    "name:und_x_variant":[
        "\ub0a8\uc625",
        "Namok"
    ],
    "wof:name":"Namok",
    "wof:placetype":"locality"
},
  "geometry": {"coordinates":[128.13426999999999,35.61894],"type":"Point"}
}