{
  "type": "Feature",
  "properties": {
    "iso:country":"KR",
    "name:ceb_x_preferred":[
        "Dongcheon-dong"
    ],
    "name:eng_x_preferred":[
        "Dongcheon-dong"
    ],
    "name:fas_x_preferred":[
        "\u062f\u0648\u0646\u06af\u0686\u0626\u0648\u0646-\u062f\u0648\u0646\u06af"
    ],
    "name:kor_x_preferred":[
        "\ub3d9\ucc9c\ub3d9"
    ],
    "name:kor_x_variant":[
        "\uace0\uae30\ub3d9"
    ],
    "name:swe_x_preferred":[
        "Dongcheon-dong"
    ],
    "name:zho_x_preferred":[
        "\u6771\u5ddd\u6d1e"
    ],
    "wof:lang":[
        "kor"
    ],
    "wof:name":"\ub3d9\ucc9c\ub3d9",
    "wof:placetype":"neighbourhood"
},
  "geometry": {"coordinates":[127.049936,37.353593],"type":"Point"}
}