{
  "type": "Feature",
  "properties": {
    "gn:admin1_code":"6.0",
    "gn:asciiname":"P'yongbat",
    "gn:country_code":"KR",
    "gn:dem":730,
    "gn:feature_class":"P",
    "gn:feature_code":"PPL",
    "gn:name":"P\u2019y\u014fngbat",
    "gn:population":0,
    "gn:timezone":"Asia/Seoul",
    "iso:country":"KR",
    "name:kor_x_preferred":[
        "\ud3c9\ubc2d"
    ],
    "name:kor_x_variant":[
        "P\u2019y\u014fngbat"
    ],
    "wof:name":"P'yongbat",
    "wof:placetype":"locality"
},
  "geometry": {"coordinates":[128.83959999999999,37.3208],"type":"Point"}
}