{
  "type": "Feature",
  "properties": {
    "gn:admin1_code":"6.0",
    "gn:asciiname":"Witt'ong-gol",
    "gn:country_code":"KR",
    "gn:dem":869,
    "gn:feature_class":"P",
    "gn:feature_code":"PPL",
    "gn:name":"Witt\u2019ong-gol",
    "gn:population":0,
    "gn:timezone":"Asia/Seoul",
    "iso:country":"KR",
    "name:und_x_variant":[
        "\uc717\ud1b5\uace8",
        "Witt\u2019ong-gol"
    ],
    "wof:name":"Witt'ong-gol",
    "wof:placetype":"locality"
},
  "geometry": {"coordinates":[129.05779999999999,37.1664],"type":"Point"}
}