{
  "type": "Feature",
  "properties": {
    "gn:admin1_code":"13.0",
    "gn:asciiname":"Yang-dong",
    "gn:country_code":"KR",
    "gn:dem":118,
    "gn:feature_class":"P",
    "gn:feature_code":"PPL",
    "gn:name":"Yang-dong",
    "gn:population":0,
    "gn:timezone":"Asia/Seoul",
    "iso:country":"KR",
    "name:kor_x_preferred":[
        "\uc591\ub3d9"
    ],
    "wof:name":"Yang-dong",
    "wof:placetype":"locality"
},
  "geometry": {"coordinates":[127.51949999999999,37.6735],"type":"Point"}
}