{
  "type": "Feature",
  "properties": {
    "gn:admin1_code":"21.0",
    "gn:asciiname":"Goldungi",
    "gn:country_code":"KR",
    "gn:dem":63,
    "gn:feature_class":"P",
    "gn:feature_code":"PPL",
    "gn:name":"Goldungi",
    "gn:population":0,
    "gn:timezone":"Asia/Seoul",
    "iso:country":"KR",
    "name:kor_x_preferred":[
        "\uace8\ub454\uae30"
    ],
    "wof:name":"Goldungi",
    "wof:placetype":"locality"
},
  "geometry": {"coordinates":[129.18223999999998,35.53491],"type":"Point"}
}