{
  "type": "Feature",
  "properties": {
    "gn:admin1_code":"1.0",
    "gn:asciiname":"Jungsangdong",
    "gn:country_code":"KR",
    "gn:dem":23,
    "gn:feature_class":"P",
    "gn:feature_code":"PPL",
    "gn:name":"Jungsangdong",
    "gn:population":0,
    "gn:timezone":"Asia/Seoul",
    "iso:country":"KR",
    "name:kor_x_preferred":[
        "\uc911\uc0c1\ub3d9"
    ],
    "wof:name":"Jungsangdong",
    "wof:placetype":"locality"
},
  "geometry": {"coordinates":[126.18404,33.3066],"type":"Point"}
}