{
  "type": "Feature",
  "properties": {
    "gn:admin1_code":"16.0",
    "gn:asciiname":"Bokgil",
    "gn:country_code":"KR",
    "gn:dem":13,
    "gn:feature_class":"P",
    "gn:feature_code":"PPL",
    "gn:name":"Bokgil",
    "gn:population":0,
    "gn:timezone":"Asia/Seoul",
    "iso:country":"KR",
    "name:kor_x_preferred":[
        "\ubcf5\uae38"
    ],
    "name:und_x_variant":[
        "Pokki-ri",
        "Pokkil-li",
        "Bokgil"
    ],
    "wof:name":"Bokgil",
    "wof:placetype":"locality"
},
  "geometry": {"coordinates":[126.39409000000001,34.89637],"type":"Point"}
}