{
  "type": "Feature",
  "properties": {
    "gn:admin1_code":"16.0",
    "gn:asciiname":"Hwagi",
    "gn:country_code":"KR",
    "gn:dem":31,
    "gn:feature_class":"P",
    "gn:feature_code":"PPL",
    "gn:name":"Hwagi",
    "gn:population":0,
    "gn:timezone":"Asia/Seoul",
    "iso:country":"KR",
    "name:kor_x_preferred":[
        "\ud654\uae30"
    ],
    "wof:name":"Hwagi",
    "wof:placetype":"locality"
},
  "geometry": {"coordinates":[126.76506000000001,34.98222],"type":"Point"}
}