{
  "type": "Feature",
  "properties": {
    "gn:admin1_code":"13.0",
    "gn:asciiname":"Wonjeokbong",
    "gn:country_code":"KR",
    "gn:dem":77,
    "gn:feature_class":"P",
    "gn:feature_code":"PPL",
    "gn:name":"Wonjeokbong",
    "gn:population":0,
    "gn:timezone":"Asia/Seoul",
    "iso:country":"KR",
    "name:und_x_variant":[
        "\uc6d0\uc801\ubd09",
        "Wonjeokbong",
        "W\u014fnj\u014fkpong"
    ],
    "wof:name":"Wonjeokbong",
    "wof:placetype":"locality"
},
  "geometry": {"coordinates":[127.03824,37.07812],"type":"Point"}
}