{
  "type": "Feature",
  "properties": {
    "gn:admin1_code":"6.0",
    "gn:asciiname":"Mundeul",
    "gn:country_code":"KR",
    "gn:dem":120,
    "gn:feature_class":"P",
    "gn:feature_code":"PPL",
    "gn:name":"Mundeul",
    "gn:population":0,
    "gn:timezone":"Asia/Seoul",
    "iso:country":"KR",
    "name:kor_x_preferred":[
        "\ubb38\ud2c0"
    ],
    "name:kor_x_variant":[
        "Munt\u2019\u016dl",
        "\ubb38\ub4e4"
    ],
    "wof:name":"Mundeul",
    "wof:placetype":"locality"
},
  "geometry": {"coordinates":[127.80973,37.708],"type":"Point"}
}