{
  "type": "Feature",
  "properties": {
    "gn:admin1_code":"14.0",
    "gn:asciiname":"Taejae-ri",
    "gn:country_code":"KR",
    "gn:dem":93,
    "gn:feature_class":"P",
    "gn:feature_code":"PPL",
    "gn:name":"Taejae-ri",
    "gn:population":0,
    "gn:timezone":"Asia/Seoul",
    "iso:country":"KR",
    "name:und_x_variant":[
        "Daizaid\u014d",
        "Taisai-d\u014d",
        "Taejae-dong",
        "Taizaid\u014d",
        "\ub300\uc7ac\ub9ac",
        "Taejae",
        "Taejae-ri"
    ],
    "wof:name":"Taejae-ri",
    "wof:placetype":"locality"
},
  "geometry": {"coordinates":[128.90333999999999,35.87753],"type":"Point"}
}