{
  "type": "Feature",
  "properties": {
    "gn:admin1_code":"16.0",
    "gn:asciiname":"Talsan",
    "gn:cc2":"KR",
    "gn:country_code":"KR",
    "gn:dem":14,
    "gn:feature_class":"P",
    "gn:feature_code":"PPL",
    "gn:name":"Talsan",
    "gn:population":0,
    "gn:timezone":"Asia/Seoul",
    "iso:country":"KR",
    "name:und_x_variant":[
        "Gessan-ri",
        "W\u014flsan-ni",
        "Talsan"
    ],
    "wof:name":"Talsan",
    "wof:placetype":"locality"
},
  "geometry": {"coordinates":[126.2625,34.70056],"type":"Point"}
}