{
  "type": "Feature",
  "properties": {
    "gn:admin1_code":"16.0",
    "gn:asciiname":"Sinchon",
    "gn:country_code":"KR",
    "gn:dem":53,
    "gn:feature_class":"P",
    "gn:feature_code":"PPL",
    "gn:name":"Sinchon",
    "gn:population":0,
    "gn:timezone":"Asia/Seoul",
    "iso:country":"KR",
    "name:kor_x_preferred":[
        "\uc2e0\ucd0c"
    ],
    "name:kor_x_variant":[
        "Sinch\u2019on"
    ],
    "name:zho_x_preferred":[
        "\u65b0\u6751"
    ],
    "wof:name":"Sinchon",
    "wof:placetype":"locality"
},
  "geometry": {"coordinates":[127.45763999999998,34.89052],"type":"Point"}
}