{
  "type": "Feature",
  "properties": {
    "gn:admin1_code":"18.0",
    "gn:asciiname":"Ponch'on",
    "gn:country_code":"KR",
    "gn:dem":52,
    "gn:feature_class":"P",
    "gn:feature_code":"PPL",
    "gn:name":"Ponch\u2019on",
    "gn:population":0,
    "gn:timezone":"Asia/Seoul",
    "iso:country":"KR",
    "name:und_x_variant":[
        "Pongch\u2019on-ni",
        "Ponch\u2019on-ni",
        "Ponch\u2019on"
    ],
    "wof:name":"Ponch'on",
    "wof:placetype":"locality"
},
  "geometry": {"coordinates":[126.88388999999999,35.21611],"type":"Point"}
}