{
  "type": "Feature",
  "properties": {
    "gn:admin1_code":"16.0",
    "gn:asciiname":"Chongmak",
    "gn:country_code":"KR",
    "gn:dem":37,
    "gn:feature_class":"P",
    "gn:feature_code":"PPL",
    "gn:name":"Ch\u014fngmak",
    "gn:population":0,
    "gn:timezone":"Asia/Seoul",
    "iso:country":"KR",
    "name:kor_x_preferred":[
        "\uc815\ub9c9"
    ],
    "name:kor_x_variant":[
        "Ch\u014fngmak"
    ],
    "wof:name":"Chongmak",
    "wof:placetype":"locality"
},
  "geometry": {"coordinates":[127.25725,34.58295],"type":"Point"}
}