{
  "type": "Feature",
  "properties": {
    "gn:admin1_code":"17.0",
    "gn:asciiname":"Sambong-ni",
    "gn:country_code":"KR",
    "gn:dem":57,
    "gn:feature_class":"P",
    "gn:feature_code":"PPL",
    "gn:name":"Sambong-ni",
    "gn:population":0,
    "gn:timezone":"Asia/Seoul",
    "iso:country":"KR",
    "name:eng_x_preferred":[
        "Sambong"
    ],
    "name:eng_x_variant":[
        "Sambong-ni"
    ],
    "name:und_x_variant":[
        "\uc0bc\ubd09\ub9ac",
        "Sambong-ni"
    ],
    "wof:name":"Sambong",
    "wof:placetype":"locality"
},
  "geometry": {"coordinates":[127.1581,36.8922],"type":"Point"}
}