{
  "type": "Feature",
  "properties": {
    "gn:admin1_code":"14.0",
    "gn:asciiname":"Sin'gye",
    "gn:country_code":"KR",
    "gn:dem":105,
    "gn:feature_class":"P",
    "gn:feature_code":"PPL",
    "gn:name":"Sin\u2019gye",
    "gn:population":0,
    "gn:timezone":"Asia/Seoul",
    "iso:country":"KR",
    "name:und_x_variant":[
        "\uc2e0\uacc4",
        "Sin\u2019gye"
    ],
    "wof:name":"Sin'gye",
    "wof:placetype":"locality"
},
  "geometry": {"coordinates":[128.13299999999998,36.027],"type":"Point"}
}