{
  "type": "Feature",
  "properties": {
    "iso:country":"KR",
    "name:eng_x_preferred":[
        "Geonguk-dong"
    ],
    "name:kor_x_preferred":[
        "\uac74\uad6d\ub3d9"
    ],
    "name:kor_x_variant":[
        "\uac74\uad6d\ub3d9"
    ],
    "qs:gn_adm0_cc":"KR",
    "qs:gn_local":1841811,
    "qs:gn_nam_loc":"Kwangju",
    "qs:gn_namadm1":"18",
    "qs:local_max":1454,
    "qs:local_sum":2956,
    "qs:localhoods":12,
    "qs:name":"\uac74\uad6d\ub3d9",
    "qs:name_adm0":"\ud55c\uad6d",
    "qs:name_adm1":"\uad11\uc8fc",
    "qs:name_adm2":"\ubd81\uad6c",
    "qs:name_lau":"\uac74\uad6d\ub3d9",
    "qs:name_local":"\uad11\uc8fc",
    "qs:photo_max":22,
    "qs:photo_sum":45,
    "qs:placetype":"Suburb",
    "qs:quad_count":7,
    "qs:woe_adm0":23424868,
    "qs:woe_adm1":2345974,
    "qs:woe_adm2":28289120,
    "qs:woe_lau":28806505,
    "qs:woe_local":1132481,
    "qs:woe_ver":"7.10.0",
    "wof:lang":[
        "kor"
    ],
    "wof:name":"Geonguk-dong",
    "wof:placetype":"neighbourhood"
},
  "geometry": {"coordinates":[126.880066,35.226027],"type":"Point"}
}