{
  "type": "Feature",
  "properties": {
    "gn:admin1_code":"6.0",
    "gn:asciiname":"Hwajinminchon",
    "gn:country_code":"KR",
    "gn:dem":70,
    "gn:feature_class":"P",
    "gn:feature_code":"PPL",
    "gn:name":"Hwajinminchon",
    "gn:population":0,
    "gn:timezone":"Asia/Seoul",
    "iso:country":"KR",
    "name:kor_x_preferred":[
        "\ud654\uc9c4\ubbfc\ucd0c"
    ],
    "wof:name":"Hwajinminchon",
    "wof:placetype":"locality"
},
  "geometry": {"coordinates":[128.51168999999999,38.2425],"type":"Point"}
}