{
  "type": "Feature",
  "properties": {
    "gn:admin1_code":"19.0",
    "gn:asciiname":"Jangbattang",
    "gn:country_code":"KR",
    "gn:dem":90,
    "gn:feature_class":"P",
    "gn:feature_code":"PPL",
    "gn:name":"Jangbattang",
    "gn:population":0,
    "gn:timezone":"Asia/Seoul",
    "iso:country":"KR",
    "name:kor_x_preferred":[
        "\uc7a5\ubc2d\ud0d5"
    ],
    "wof:name":"Jangbattang",
    "wof:placetype":"locality"
},
  "geometry": {"coordinates":[127.31704000000001,36.23006],"type":"Point"}
}