{
  "type": "Feature",
  "properties": {
    "gn:admin1_code":"3.0",
    "gn:asciiname":"Noun",
    "gn:country_code":"KR",
    "gn:dem":59,
    "gn:feature_class":"P",
    "gn:feature_code":"PPL",
    "gn:name":"No\u016dn",
    "gn:population":0,
    "gn:timezone":"Asia/Seoul",
    "iso:country":"KR",
    "name:und_x_variant":[
        "\ub178\uc740",
        "No\u016dn"
    ],
    "wof:name":"Noun",
    "wof:placetype":"locality"
},
  "geometry": {"coordinates":[127.03973000000001,35.61947],"type":"Point"}
}