{
  "type": "Feature",
  "properties": {
    "gn:admin1_code":"16.0",
    "gn:asciiname":"Borim",
    "gn:country_code":"KR",
    "gn:dem":142,
    "gn:feature_class":"P",
    "gn:feature_code":"PPL",
    "gn:name":"Borim",
    "gn:population":0,
    "gn:timezone":"Asia/Seoul",
    "iso:country":"KR",
    "name:kor_x_preferred":[
        "\ubcf4\ub9bc"
    ],
    "name:und_x_variant":[
        "Porim",
        "Borim"
    ],
    "wof:name":"Borim",
    "wof:placetype":"locality"
},
  "geometry": {"coordinates":[127.06986999999999,34.79528],"type":"Point"}
}