{
  "type": "Feature",
  "properties": {
    "gn:admin1_code":"13.0",
    "gn:asciiname":"Boan",
    "gn:country_code":"KR",
    "gn:dem":80,
    "gn:feature_class":"P",
    "gn:feature_code":"PPL",
    "gn:name":"Boan",
    "gn:population":0,
    "gn:timezone":"Asia/Seoul",
    "iso:country":"KR",
    "name:und_x_variant":[
        "\ubcf4\uc548",
        "Poan",
        "Boan"
    ],
    "wof:name":"Boan",
    "wof:placetype":"locality"
},
  "geometry": {"coordinates":[127.07084,37.9279],"type":"Point"}
}