{
  "type": "Feature",
  "properties": {
    "gn:admin1_code":"0.0",
    "gn:asciiname":"Rinhi",
    "gn:country_code":"KR",
    "gn:dem":11,
    "gn:feature_class":"P",
    "gn:feature_code":"PPL",
    "gn:name":"Rinhi",
    "gn:population":0,
    "gn:timezone":"Asia/Seoul",
    "iso:country":"KR",
    "name:und_x_variant":[
        "Rimpa",
        "Imp\u2019a",
        "Rinhi",
        "Rinha",
        "Imp\u2019i"
    ],
    "wof:name":"Rinhi",
    "wof:placetype":"locality"
},
  "geometry": {"coordinates":[126.84999999999999,35.98333],"type":"Point"}
}