{
  "type": "Feature",
  "properties": {
    "gn:admin1_code":"20.0",
    "gn:asciiname":"Sangjo",
    "gn:country_code":"KR",
    "gn:dem":549,
    "gn:feature_class":"P",
    "gn:feature_code":"PPL",
    "gn:name":"Sangjo",
    "gn:population":0,
    "gn:timezone":"Asia/Seoul",
    "iso:country":"KR",
    "name:und_x_variant":[
        "\uc0c1\uc870",
        "Sangjo"
    ],
    "wof:name":"Sangjo",
    "wof:placetype":"locality"
},
  "geometry": {"coordinates":[127.65429,35.57803],"type":"Point"}
}