{
  "type": "Feature",
  "properties": {
    "gn:admin1_code":"13.0",
    "gn:asciiname":"Paegyang-dong",
    "gn:country_code":"KR",
    "gn:dem":24,
    "gn:feature_class":"P",
    "gn:feature_code":"PPL",
    "gn:name":"Paegyang-dong",
    "gn:population":0,
    "gn:timezone":"Asia/Seoul",
    "iso:country":"KR",
    "name:kor_x_preferred":[
        "\ubc31\uc591\ub3d9"
    ],
    "wof:name":"Paegyang-dong",
    "wof:placetype":"locality"
},
  "geometry": {"coordinates":[126.84332999999999,37.62833],"type":"Point"}
}