{
  "type": "Feature",
  "properties": {
    "gn:admin1_code":"17.0",
    "gn:asciiname":"Saengsong",
    "gn:country_code":"KR",
    "gn:dem":99,
    "gn:feature_class":"P",
    "gn:feature_code":"PPL",
    "gn:name":"Saengsong",
    "gn:population":0,
    "gn:timezone":"Asia/Seoul",
    "iso:country":"KR",
    "name:kor_x_preferred":[
        "\uc0dd\uc1a1"
    ],
    "wof:name":"Saengsong",
    "wof:placetype":"locality"
},
  "geometry": {"coordinates":[127.18565,36.66244],"type":"Point"}
}