{
  "type": "Feature",
  "properties": {
    "gn:admin1_code":"14.0",
    "gn:asciiname":"Sin'gi",
    "gn:country_code":"KR",
    "gn:dem":83,
    "gn:feature_class":"P",
    "gn:feature_code":"PPL",
    "gn:name":"Sin\u2019gi",
    "gn:population":0,
    "gn:timezone":"Asia/Seoul",
    "iso:country":"KR",
    "name:und_x_variant":[
        "\uc2e0\uae30",
        "Sin\u2019gi"
    ],
    "wof:name":"Sin'gi",
    "wof:placetype":"locality"
},
  "geometry": {"coordinates":[128.66638999999998,35.65737],"type":"Point"}
}