{
  "type": "Feature",
  "properties": {
    "gn:admin1_code":"14.0",
    "gn:asciiname":"Daegol",
    "gn:country_code":"KR",
    "gn:dem":164,
    "gn:feature_class":"P",
    "gn:feature_code":"PPL",
    "gn:name":"Daegol",
    "gn:population":0,
    "gn:timezone":"Asia/Seoul",
    "iso:country":"KR",
    "name:kor_x_preferred":[
        "\ub300\uace8"
    ],
    "wof:name":"Daegol",
    "wof:placetype":"locality"
},
  "geometry": {"coordinates":[128.40146999999999,36.6831],"type":"Point"}
}