{
  "type": "Feature",
  "properties": {
    "gn:admin1_code":"14.0",
    "gn:asciiname":"Jegong",
    "gn:country_code":"KR",
    "gn:dem":204,
    "gn:feature_class":"P",
    "gn:feature_code":"PPL",
    "gn:name":"Jegong",
    "gn:population":0,
    "gn:timezone":"Asia/Seoul",
    "iso:country":"KR",
    "name:kor_x_preferred":[
        "\uc81c\uacf5"
    ],
    "wof:name":"Jegong",
    "wof:placetype":"locality"
},
  "geometry": {"coordinates":[129.10217,35.75749000000001],"type":"Point"}
}