{
  "type": "Feature",
  "properties": {
    "gn:admin1_code":"20.0",
    "gn:asciiname":"Ku-ch'on",
    "gn:country_code":"KR",
    "gn:dem":21,
    "gn:feature_class":"P",
    "gn:feature_code":"PPL",
    "gn:name":"Ku-ch\u2019on",
    "gn:population":0,
    "gn:timezone":"Asia/Seoul",
    "iso:country":"KR",
    "name:und_x_variant":[
        "\uad6c\ucd0c",
        "Ku-ch\u2019on"
    ],
    "wof:name":"Ku-ch'on",
    "wof:placetype":"locality"
},
  "geometry": {"coordinates":[128.34151,34.88878],"type":"Point"}
}