{
  "type": "Feature",
  "properties": {
    "gn:admin1_code":"5.0",
    "gn:asciiname":"Changhwa",
    "gn:country_code":"KR",
    "gn:dem":159,
    "gn:feature_class":"P",
    "gn:feature_code":"PPL",
    "gn:name":"Changhwa",
    "gn:population":0,
    "gn:timezone":"Asia/Seoul",
    "iso:country":"KR",
    "name:und_x_variant":[
        "\uc7a5\ud654",
        "Changhwa"
    ],
    "wof:name":"Changhwa",
    "wof:placetype":"locality"
},
  "geometry": {"coordinates":[127.6284,36.1933],"type":"Point"}
}