{
  "type": "Feature",
  "properties": {
    "gn:admin1_code":"17.0",
    "gn:asciiname":"Pom-mal",
    "gn:country_code":"KR",
    "gn:dem":80,
    "gn:feature_class":"P",
    "gn:feature_code":"PPL",
    "gn:name":"P\u014fm-mal",
    "gn:population":0,
    "gn:timezone":"Asia/Seoul",
    "iso:country":"KR",
    "name:und_x_variant":[
        "\ubc94\ub9d0",
        "P\u014fm-mal"
    ],
    "wof:name":"Pom-mal",
    "wof:placetype":"locality"
},
  "geometry": {"coordinates":[127.1153,36.3586],"type":"Point"}
}