{
  "type": "Feature",
  "properties": {
    "gn:admin1_code":"5.0",
    "gn:asciiname":"Saeteomal",
    "gn:country_code":"KR",
    "gn:dem":228,
    "gn:feature_class":"P",
    "gn:feature_code":"PPL",
    "gn:name":"Saeteomal",
    "gn:population":0,
    "gn:timezone":"Asia/Seoul",
    "iso:country":"KR",
    "name:kor_x_preferred":[
        "\uc0c8\ud130\ub9d0"
    ],
    "wof:name":"Saeteomal",
    "wof:placetype":"locality"
},
  "geometry": {"coordinates":[127.65949999999999,36.62465],"type":"Point"}
}