{
  "type": "Feature",
  "properties": {
    "gn:admin1_code":"13.0",
    "gn:asciiname":"Woryanggol",
    "gn:country_code":"KR",
    "gn:dem":71,
    "gn:feature_class":"P",
    "gn:feature_code":"PPL",
    "gn:name":"Woryanggol",
    "gn:population":0,
    "gn:timezone":"Asia/Seoul",
    "iso:country":"KR",
    "name:kor_x_preferred":[
        "\uc6d4\uc591\uace8"
    ],
    "name:kor_x_variant":[
        "W\u014fryang-gol"
    ],
    "wof:name":"Woryanggol",
    "wof:placetype":"locality"
},
  "geometry": {"coordinates":[127.51878000000001,37.24677],"type":"Point"}
}