{
  "type": "Feature",
  "properties": {
    "gn:admin1_code":"14.0",
    "gn:asciiname":"Chinda-ri",
    "gn:country_code":"KR",
    "gn:dem":319,
    "gn:feature_class":"P",
    "gn:feature_code":"PPL",
    "gn:name":"Chinda-ri",
    "gn:population":0,
    "gn:timezone":"Asia/Seoul",
    "iso:country":"KR",
    "name:und_x_variant":[
        "\uc9c4\ub2e4\ub9ac",
        "Chinda-ri"
    ],
    "wof:name":"Chinda-ri",
    "wof:placetype":"locality"
},
  "geometry": {"coordinates":[127.96379,36.44024],"type":"Point"}
}