{
  "type": "Feature",
  "properties": {
    "gn:admin1_code":"5.0",
    "gn:asciiname":"Naedong",
    "gn:country_code":"KR",
    "gn:dem":192,
    "gn:feature_class":"P",
    "gn:feature_code":"PPL",
    "gn:name":"Naedong",
    "gn:population":0,
    "gn:timezone":"Asia/Seoul",
    "iso:country":"KR",
    "name:kor_x_preferred":[
        "\ub0b4\ub3d9"
    ],
    "wof:name":"Naedong",
    "wof:placetype":"locality"
},
  "geometry": {"coordinates":[127.73577,37.10084000000001],"type":"Point"}
}