{
  "type": "Feature",
  "properties": {
    "gn:admin1_code":"14.0",
    "gn:asciiname":"Jatgol",
    "gn:country_code":"KR",
    "gn:dem":65,
    "gn:feature_class":"P",
    "gn:feature_code":"PPL",
    "gn:name":"Jatgol",
    "gn:population":0,
    "gn:timezone":"Asia/Seoul",
    "iso:country":"KR",
    "name:kor_x_preferred":[
        "\uc7a6\uace8"
    ],
    "wof:name":"Jatgol",
    "wof:placetype":"locality"
},
  "geometry": {"coordinates":[128.20491000000001,36.55324],"type":"Point"}
}