{
  "type": "Feature",
  "properties": {
    "gn:admin1_code":"16.0",
    "gn:asciiname":"olyudong",
    "gn:country_code":"KR",
    "gn:dem":67,
    "gn:feature_class":"P",
    "gn:feature_code":"PPL",
    "gn:name":"\uc624\ub958\ub3d9",
    "gn:population":0,
    "gn:timezone":"Asia/Seoul",
    "iso:country":"KR",
    "wof:name":"olyudong",
    "wof:placetype":"locality"
},
  "geometry": {"coordinates":[126.65167,34.62556],"type":"Point"}
}