{
  "type": "Feature",
  "properties": {
    "gn:admin1_code":"3.0",
    "gn:asciiname":"Chi-dong",
    "gn:country_code":"KR",
    "gn:dem":309,
    "gn:feature_class":"P",
    "gn:feature_code":"PPL",
    "gn:name":"Chi-dong",
    "gn:population":0,
    "gn:timezone":"Asia/Seoul",
    "iso:country":"KR",
    "name:und_x_variant":[
        "\uc9c0\ub3d9",
        "Chi-dong"
    ],
    "wof:name":"Chi-dong",
    "wof:placetype":"locality"
},
  "geometry": {"coordinates":[127.39305,35.70618],"type":"Point"}
}