{
  "type": "Feature",
  "properties": {
    "gn:admin1_code":"20.0",
    "gn:asciiname":"Polt'ong-gol",
    "gn:country_code":"KR",
    "gn:dem":24,
    "gn:feature_class":"P",
    "gn:feature_code":"PPL",
    "gn:name":"P\u014flt\u2019ong-gol",
    "gn:population":0,
    "gn:timezone":"Asia/Seoul",
    "iso:country":"KR",
    "name:und_x_variant":[
        "\ubc8c\ud1b5\uace8",
        "P\u014flt\u2019ong-gol"
    ],
    "wof:name":"Polt'ong-gol",
    "wof:placetype":"locality"
},
  "geometry": {"coordinates":[128.49213,34.77913],"type":"Point"}
}