{
  "type": "Feature",
  "properties": {
    "gn:admin1_code":"14.0",
    "gn:asciiname":"Chuk-ch'on",
    "gn:country_code":"KR",
    "gn:dem":103,
    "gn:feature_class":"P",
    "gn:feature_code":"PPL",
    "gn:name":"Chuk-ch\u2019on",
    "gn:population":0,
    "gn:timezone":"Asia/Seoul",
    "iso:country":"KR",
    "name:und_x_variant":[
        "\uc8fd\ucd0c",
        "Chuk-ch\u2019on"
    ],
    "wof:name":"Chuk-ch'on",
    "wof:placetype":"locality"
},
  "geometry": {"coordinates":[128.6926,35.68178],"type":"Point"}
}