{
  "type": "Feature",
  "properties": {
    "gn:admin1_code":"15.0",
    "gn:asciiname":"Hwabaengnok",
    "gn:country_code":"KR",
    "gn:dem":301,
    "gn:feature_class":"P",
    "gn:feature_code":"PPL",
    "gn:name":"Hwabaengnok",
    "gn:population":0,
    "gn:timezone":"Asia/Seoul",
    "iso:country":"KR",
    "name:und_x_variant":[
        "Habaek-tong",
        "\ud654\ubc31\ub85d",
        "Habaengnok",
        "Hwabaengnok"
    ],
    "wof:name":"Hwabaengnok",
    "wof:placetype":"locality"
},
  "geometry": {"coordinates":[128.63679999999999,35.71626],"type":"Point"}
}