{
  "type": "Feature",
  "properties": {
    "gn:admin1_code":"5.0",
    "gn:asciiname":"Naesu-ri",
    "gn:cc2":"KR",
    "gn:country_code":"KR",
    "gn:dem":48,
    "gn:feature_class":"P",
    "gn:feature_code":"PPL",
    "gn:name":"Naesu-ri",
    "gn:population":0,
    "gn:timezone":"Asia/Seoul",
    "iso:country":"KR",
    "name:und_x_variant":[
        "Naech\u2019u-ri",
        "Naesu-ri"
    ],
    "wof:name":"Naesu-ri",
    "wof:placetype":"locality"
},
  "geometry": {"coordinates":[127.53139,36.72778],"type":"Point"}
}