{
  "type": "Feature",
  "properties": {
    "gn:admin1_code":"3.0",
    "gn:asciiname":"Yangsaeng-dong",
    "gn:country_code":"KR",
    "gn:dem":264,
    "gn:feature_class":"P",
    "gn:feature_code":"PPL",
    "gn:name":"Yangsaeng-dong",
    "gn:population":0,
    "gn:timezone":"Asia/Seoul",
    "iso:country":"KR",
    "name:und_x_variant":[
        "\uc591\uc0dd\ub3d9",
        "Yangsaeng-dong"
    ],
    "wof:name":"Yangsaeng-dong",
    "wof:placetype":"locality"
},
  "geometry": {"coordinates":[127.07447000000001,35.67827],"type":"Point"}
}