{
  "type": "Feature",
  "properties": {
    "gn:admin1_code":"14.0",
    "gn:asciiname":"Sohwadong",
    "gn:country_code":"KR",
    "gn:dem":232,
    "gn:feature_class":"P",
    "gn:feature_code":"PPL",
    "gn:name":"Sohwadong",
    "gn:population":0,
    "gn:timezone":"Asia/Seoul",
    "iso:country":"KR",
    "name:kor_x_preferred":[
        "\uc18c\ud654\ub3d9"
    ],
    "wof:name":"Sohwadong",
    "wof:placetype":"locality"
},
  "geometry": {"coordinates":[128.70126000000002,36.06349],"type":"Point"}
}