{
  "type": "Feature",
  "properties": {
    "gn:admin1_code":"6.0",
    "gn:asciiname":"Pombau",
    "gn:country_code":"KR",
    "gn:dem":489,
    "gn:feature_class":"P",
    "gn:feature_code":"PPL",
    "gn:name":"P\u014fmbau",
    "gn:population":0,
    "gn:timezone":"Asia/Seoul",
    "iso:country":"KR",
    "name:kor_x_preferred":[
        "\ubc94\ubc14\uc6b0"
    ],
    "name:kor_x_variant":[
        "P\u014fmbau"
    ],
    "wof:name":"Pombau",
    "wof:placetype":"locality"
},
  "geometry": {"coordinates":[128.1814,37.4727],"type":"Point"}
}