{
  "type": "Feature",
  "properties": {
    "gn:admin1_code":"13.0",
    "gn:admin2_code":"Ans\u014fng-si",
    "gn:asciiname":"Baemjaengi",
    "gn:country_code":"KR",
    "gn:dem":110,
    "gn:feature_class":"P",
    "gn:feature_code":"PPL",
    "gn:name":"Baemjaengi",
    "gn:population":0,
    "gn:timezone":"Asia/Seoul",
    "iso:country":"KR",
    "name:kor_x_preferred":[
        "\ubc40\uc7c1\uc774"
    ],
    "name:und_x_variant":[
        "Paemjaengi",
        "Baemjaengi"
    ],
    "wof:name":"Baemjaengi",
    "wof:placetype":"locality"
},
  "geometry": {"coordinates":[127.49719,37.07621],"type":"Point"}
}