{
  "type": "Feature",
  "properties": {
    "gn:admin1_code":"6.0",
    "gn:asciiname":"Sodo-ri",
    "gn:country_code":"KR",
    "gn:dem":561,
    "gn:feature_class":"P",
    "gn:feature_code":"PPL",
    "gn:name":"Sodo-ri",
    "gn:population":0,
    "gn:timezone":"Asia/Seoul",
    "iso:country":"KR",
    "name:und_x_variant":[
        "Ch\u2019angdong-ni"
    ],
    "wof:name":"Sodo-ri",
    "wof:placetype":"locality"
},
  "geometry": {"coordinates":[128.37861000000001,37.61583],"type":"Point"}
}