{
  "type": "Feature",
  "properties": {
    "gn:admin1_code":"5.0",
    "gn:asciiname":"Sutgol",
    "gn:country_code":"KR",
    "gn:dem":325,
    "gn:feature_class":"P",
    "gn:feature_code":"PPL",
    "gn:name":"Sutgol",
    "gn:population":0,
    "gn:timezone":"Asia/Seoul",
    "iso:country":"KR",
    "name:aze_x_preferred":[
        "S\u00fcd g\u00f6l\u00fc"
    ],
    "name:kor_x_preferred":[
        "\uc22b\uace8"
    ],
    "name:tur_x_preferred":[
        "S\u00fct g\u00f6l\u00fc"
    ],
    "wof:name":"Sutgol",
    "wof:placetype":"locality"
},
  "geometry": {"coordinates":[127.61017,36.67012],"type":"Point"}
}