{
  "type": "Feature",
  "properties": {
    "gn:admin1_code":"13.0",
    "gn:admin2_code":"Kimp'o-si",
    "gn:asciiname":"Yongyeondong",
    "gn:country_code":"KR",
    "gn:dem":18,
    "gn:feature_class":"P",
    "gn:feature_code":"PPL",
    "gn:name":"Yongyeondong",
    "gn:population":0,
    "gn:timezone":"Asia/Seoul",
    "iso:country":"KR",
    "name:kor_x_preferred":[
        "\uc6a9\uc5f0\ub3d9"
    ],
    "name:kor_x_variant":[
        "Yongy\u014fn-dong"
    ],
    "wof:name":"Yongyeondong",
    "wof:placetype":"locality"
},
  "geometry": {"coordinates":[126.55208,37.75852],"type":"Point"}
}