{
  "type": "Feature",
  "properties": {
    "gn:admin1_code":"12.0",
    "gn:asciiname":"Wolguri",
    "gn:country_code":"KR",
    "gn:dem":15,
    "gn:feature_class":"P",
    "gn:feature_code":"PPL",
    "gn:name":"Wolguri",
    "gn:population":0,
    "gn:timezone":"Asia/Seoul",
    "iso:country":"KR",
    "name:kor_x_preferred":[
        "\uc6d4\uad6c\ub9ac"
    ],
    "name:und_x_variant":[
        "W\u014flgu-ri",
        "W\u014fn\u2019gu-ri",
        "Wolguri"
    ],
    "wof:name":"Wolguri",
    "wof:placetype":"locality"
},
  "geometry": {"coordinates":[126.23788999999999,37.77059000000001],"type":"Point"}
}