{
  "type": "Feature",
  "properties": {
    "gn:admin1_code":"14.0",
    "gn:asciiname":"Gyemyeongwon",
    "gn:country_code":"KR",
    "gn:dem":131,
    "gn:feature_class":"P",
    "gn:feature_code":"PPL",
    "gn:name":"Gyemyeongwon",
    "gn:population":0,
    "gn:timezone":"Asia/Seoul",
    "iso:country":"KR",
    "name:kor_x_preferred":[
        "\uacc4\uba85\uc6d0"
    ],
    "wof:name":"Gyemyeongwon",
    "wof:placetype":"locality"
},
  "geometry": {"coordinates":[128.60388,36.61114],"type":"Point"}
}