{
  "type": "Feature",
  "properties": {
    "gn:admin1_code":"16.0",
    "gn:asciiname":"Daepo",
    "gn:country_code":"KR",
    "gn:dem":11,
    "gn:feature_class":"P",
    "gn:feature_code":"PPL",
    "gn:name":"Daepo",
    "gn:population":0,
    "gn:timezone":"Asia/Seoul",
    "iso:country":"KR",
    "name:kor_x_preferred":[
        "\ub300\ud3ec"
    ],
    "name:kor_x_variant":[
        "Taep\u2019o"
    ],
    "wof:name":"Daepo",
    "wof:placetype":"locality"
},
  "geometry": {"coordinates":[127.39387000000001,34.79344],"type":"Point"}
}