{
  "type": "Feature",
  "properties": {
    "gn:admin1_code":"1.0",
    "gn:asciiname":"Myeongnyundong",
    "gn:country_code":"KR",
    "gn:dem":31,
    "gn:feature_class":"P",
    "gn:feature_code":"PPL",
    "gn:name":"Myeongnyundong",
    "gn:population":0,
    "gn:timezone":"Asia/Seoul",
    "iso:country":"KR",
    "name:kor_x_preferred":[
        "\uba85\ub95c\ub3d9"
    ],
    "wof:name":"Myeongnyundong",
    "wof:placetype":"locality"
},
  "geometry": {"coordinates":[126.65174,33.27683],"type":"Point"}
}