{
  "type": "Feature",
  "properties": {
    "gn:admin1_code":"16.0",
    "gn:asciiname":"Chil-li",
    "gn:cc2":"KR",
    "gn:country_code":"KR",
    "gn:dem":7,
    "gn:feature_class":"P",
    "gn:feature_code":"PPL",
    "gn:name":"Chil-li",
    "gn:population":0,
    "gn:timezone":"Asia/Seoul",
    "iso:country":"KR",
    "name:und_x_variant":[
        "Chin-ni",
        "Chil-li"
    ],
    "wof:name":"Chil-li",
    "wof:placetype":"locality"
},
  "geometry": {"coordinates":[126.11417,35.085],"type":"Point"}
}