{
  "type": "Feature",
  "properties": {
    "gn:admin1_code":"6.0",
    "gn:admin2_code":"Ch'\u014flw\u014fn-gun",
    "gn:asciiname":"Yongam",
    "gn:country_code":"KR",
    "gn:dem":250,
    "gn:feature_class":"P",
    "gn:feature_code":"PPL",
    "gn:name":"Yongam",
    "gn:population":0,
    "gn:timezone":"Asia/Seoul",
    "iso:country":"KR",
    "name:kor_x_preferred":[
        "\uc6a9\uc554"
    ],
    "wof:name":"Yongam",
    "wof:placetype":"locality"
},
  "geometry": {"coordinates":[127.49403999999998,38.27144000000001],"type":"Point"}
}