{
  "type": "Feature",
  "properties": {
    "gn:admin1_code":"5.0",
    "gn:asciiname":"Witmaeul",
    "gn:country_code":"KR",
    "gn:dem":174,
    "gn:feature_class":"P",
    "gn:feature_code":"PPL",
    "gn:name":"Witmaeul",
    "gn:population":0,
    "gn:timezone":"Asia/Seoul",
    "iso:country":"KR",
    "name:kor_x_preferred":[
        "\uc717\ub9c8\uc744"
    ],
    "wof:name":"Witmaeul",
    "wof:placetype":"locality"
},
  "geometry": {"coordinates":[128.31493,36.96902],"type":"Point"}
}