{
  "type": "Feature",
  "properties": {
    "gn:admin1_code":"5.0",
    "gn:asciiname":"Araetdaesil",
    "gn:country_code":"KR",
    "gn:dem":132,
    "gn:feature_class":"P",
    "gn:feature_code":"PPL",
    "gn:name":"Araetdaesil",
    "gn:population":0,
    "gn:timezone":"Asia/Seoul",
    "iso:country":"KR",
    "name:kor_x_preferred":[
        "\uc544\ub7ab\ub300\uc2e4"
    ],
    "name:und_x_variant":[
        "Araettaesil"
    ],
    "wof:name":"Araetdaesil",
    "wof:placetype":"locality"
},
  "geometry": {"coordinates":[127.50566999999999,37.03525],"type":"Point"}
}