{
  "type": "Feature",
  "properties": {
    "gn:admin1_code":"5.0",
    "gn:asciiname":"Buyeonjeosuji",
    "gn:country_code":"KR",
    "gn:dem":90,
    "gn:feature_class":"P",
    "gn:feature_code":"PPL",
    "gn:name":"Buyeonjeosuji",
    "gn:population":0,
    "gn:timezone":"Asia/Seoul",
    "iso:country":"KR",
    "name:kor_x_preferred":[
        "\ubd80\uc5f0\uc800\uc218\uc9c0"
    ],
    "wof:name":"Buyeonjeosuji",
    "wof:placetype":"locality"
},
  "geometry": {"coordinates":[127.5735,36.73705],"type":"Point"}
}