{
  "type": "Feature",
  "properties": {
    "gn:admin1_code":"3.0",
    "gn:asciiname":"Wonp'yong-ch'on",
    "gn:country_code":"KR",
    "gn:dem":96,
    "gn:feature_class":"P",
    "gn:feature_code":"PPL",
    "gn:name":"W\u014fnp\u2019y\u014fng-ch\u2019on",
    "gn:population":0,
    "gn:timezone":"Asia/Seoul",
    "iso:country":"KR",
    "name:und_x_variant":[
        "\uc6d0\ud3c9\ucd0c",
        "W\u014fnp\u2019y\u014fng-ch\u2019on"
    ],
    "wof:name":"Wonp'yong-ch'on",
    "wof:placetype":"locality"
},
  "geometry": {"coordinates":[127.15751000000002,35.76492000000001],"type":"Point"}
}