{
  "type": "Feature",
  "properties": {
    "gn:admin1_code":"3.0",
    "gn:asciiname":"Pakksulch'i",
    "gn:country_code":"KR",
    "gn:dem":272,
    "gn:feature_class":"P",
    "gn:feature_code":"PPL",
    "gn:name":"Pakks\u016dlch\u2019i",
    "gn:population":0,
    "gn:timezone":"Asia/Seoul",
    "iso:country":"KR",
    "name:und_x_variant":[
        "\ubc16\uc2ac\uce58",
        "Pakks\u016dlch\u2019i"
    ],
    "wof:name":"Pakksulch'i",
    "wof:placetype":"locality"
},
  "geometry": {"coordinates":[127.26142,35.68869],"type":"Point"}
}