{
  "type": "Feature",
  "properties": {
    "gn:admin1_code":"14.0",
    "gn:asciiname":"Pujon",
    "gn:country_code":"KR",
    "gn:dem":213,
    "gn:feature_class":"P",
    "gn:feature_code":"PPL",
    "gn:name":"Puj\u014fn",
    "gn:population":0,
    "gn:timezone":"Asia/Seoul",
    "iso:country":"KR",
    "name:und_x_variant":[
        "\ubd80\uc804",
        "Puj\u014fn"
    ],
    "wof:name":"Pujon",
    "wof:placetype":"locality"
},
  "geometry": {"coordinates":[129.08096,36.069],"type":"Point"}
}