{
  "type": "Feature",
  "properties": {
    "gn:admin1_code":"12.0",
    "gn:asciiname":"Baegungok",
    "gn:country_code":"KR",
    "gn:dem":57,
    "gn:feature_class":"P",
    "gn:feature_code":"PPL",
    "gn:name":"Baegungok",
    "gn:population":0,
    "gn:timezone":"Asia/Seoul",
    "iso:country":"KR",
    "name:kor_x_preferred":[
        "\ubc31\uc6b4\uace1"
    ],
    "wof:name":"Baegungok",
    "wof:placetype":"locality"
},
  "geometry": {"coordinates":[126.4794,37.66903],"type":"Point"}
}