{
  "type": "Feature",
  "properties": {
    "gn:admin1_code":"21.0",
    "gn:asciiname":"Sangseonpil",
    "gn:country_code":"KR",
    "gn:dem":409,
    "gn:feature_class":"P",
    "gn:feature_code":"PPL",
    "gn:name":"Sangseonpil",
    "gn:population":0,
    "gn:timezone":"Asia/Seoul",
    "iso:country":"KR",
    "name:kor_x_preferred":[
        "\uc0c1\uc120\ud544"
    ],
    "wof:name":"Sangseonpil",
    "wof:placetype":"locality"
},
  "geometry": {"coordinates":[129.12201999999999,35.66635],"type":"Point"}
}