{
  "type": "Feature",
  "properties": {
    "gn:admin1_code":"17.0",
    "gn:asciiname":"Paengnip'o",
    "gn:country_code":"KR",
    "gn:dem":26,
    "gn:feature_class":"P",
    "gn:feature_code":"PPL",
    "gn:name":"Paengnip\u2019o",
    "gn:population":0,
    "gn:timezone":"Asia/Seoul",
    "iso:country":"KR",
    "name:und_x_variant":[
        "\ubc31\ub9ac\ud3ec",
        "Paengnip\u2019o"
    ],
    "wof:name":"Paengnip'o",
    "wof:placetype":"locality"
},
  "geometry": {"coordinates":[126.1555,36.8139],"type":"Point"}
}