{
  "type": "Feature",
  "properties": {
    "gn:admin1_code":"6.0",
    "gn:asciiname":"Buchaedeul",
    "gn:country_code":"KR",
    "gn:dem":199,
    "gn:feature_class":"P",
    "gn:feature_code":"PPL",
    "gn:name":"Buchaedeul",
    "gn:population":0,
    "gn:timezone":"Asia/Seoul",
    "iso:country":"KR",
    "name:kor_x_preferred":[
        "\ubd80\ucc44\ub4e4"
    ],
    "wof:name":"Buchaedeul",
    "wof:placetype":"locality"
},
  "geometry": {"coordinates":[128.01908999999998,37.83617],"type":"Point"}
}