{
  "type": "Feature",
  "properties": {
    "gn:admin1_code":"16.0",
    "gn:asciiname":"Pungnyu",
    "gn:country_code":"KR",
    "gn:dem":10,
    "gn:feature_class":"P",
    "gn:feature_code":"PPL",
    "gn:name":"Pungnyu",
    "gn:population":0,
    "gn:timezone":"Asia/Seoul",
    "iso:country":"KR",
    "name:kor_x_preferred":[
        "\ud48d\ub958"
    ],
    "name:kor_x_variant":[
        "P\u2019ungnyu"
    ],
    "wof:name":"Pungnyu",
    "wof:placetype":"locality"
},
  "geometry": {"coordinates":[127.46026999999999,34.85363],"type":"Point"}
}