{
  "type": "Feature",
  "properties": {
    "gn:admin1_code":"17.0",
    "gn:asciiname":"K'unsuk-kol",
    "gn:country_code":"KR",
    "gn:dem":149,
    "gn:feature_class":"P",
    "gn:feature_code":"PPL",
    "gn:name":"K\u2019\u016dnsuk-kol",
    "gn:population":0,
    "gn:timezone":"Asia/Seoul",
    "iso:country":"KR",
    "name:und_x_variant":[
        "\ud070\uc22b\uace8",
        "K\u2019\u016dnsuk-kol"
    ],
    "wof:name":"K'unsuk-kol",
    "wof:placetype":"locality"
},
  "geometry": {"coordinates":[126.99169999999999,36.8479],"type":"Point"}
}