{
  "type": "Feature",
  "properties": {
    "gn:admin1_code":"13.0",
    "gn:admin2_code":"Ans\u014fng-si",
    "gn:asciiname":"Dangbuk",
    "gn:country_code":"KR",
    "gn:dem":132,
    "gn:feature_class":"P",
    "gn:feature_code":"PPL",
    "gn:name":"Dangbuk",
    "gn:population":0,
    "gn:timezone":"Asia/Seoul",
    "iso:country":"KR",
    "name:kor_x_preferred":[
        "\ub2f9\ubd81"
    ],
    "name:und_x_variant":[
        "Tangbuk",
        "Dangbuk"
    ],
    "wof:name":"Dangbuk",
    "wof:placetype":"locality"
},
  "geometry": {"coordinates":[127.43916000000002,37.05878],"type":"Point"}
}