{
  "type": "Feature",
  "properties": {
    "gn:admin1_code":"11.0",
    "gn:asciiname":"Changansam-dong",
    "gn:country_code":"KR",
    "gn:dem":20,
    "gn:feature_class":"P",
    "gn:feature_code":"PPL",
    "gn:name":"Changansam-dong",
    "gn:population":0,
    "gn:timezone":"Asia/Seoul",
    "iso:country":"KR",
    "name:und_x_variant":[
        "\uc7a5\uc5483\ub3d9",
        "Changansam-dong"
    ],
    "wof:name":"Changansam-dong",
    "wof:placetype":"locality"
},
  "geometry": {"coordinates":[127.07153,37.56608],"type":"Point"}
}