{
  "type": "Feature",
  "properties": {
    "gn:admin1_code":"11.0",
    "gn:asciiname":"Mangu-dong",
    "gn:country_code":"KR",
    "gn:dem":64,
    "gn:feature_class":"P",
    "gn:feature_code":"PPL",
    "gn:name":"Mangu-dong",
    "gn:population":0,
    "gn:timezone":"Asia/Seoul",
    "iso:country":"KR",
    "name:ceb_x_preferred":[
        "Mangu-dong"
    ],
    "name:kor_x_preferred":[
        "\ub9dd\uc6b0\ub3d9"
    ],
    "name:msa_x_preferred":[
        "Mangu-dong"
    ],
    "name:swe_x_preferred":[
        "Mangu-dong"
    ],
    "name:tha_x_preferred":[
        "\u0e41\u0e02\u0e27\u0e07\u0e21\u0e31\u0e07\u0e2d\u0e39"
    ],
    "name:und_x_variant":[
        "H\u014fchiku-ri",
        "Pangch\u2019ung-ni",
        "Mangu-ri",
        "Mangu"
    ],
    "name:vie_x_preferred":[
        "Mangu-dong"
    ],
    "wof:name":"Mangu-dong",
    "wof:placetype":"locality"
},
  "geometry": {"coordinates":[127.10429999999999,37.5924],"type":"Point"}
}