{
  "type": "Feature",
  "properties": {
    "gn:admin1_code":"5.0",
    "gn:asciiname":"Chilgogae",
    "gn:country_code":"KR",
    "gn:dem":227,
    "gn:feature_class":"P",
    "gn:feature_code":"PPL",
    "gn:name":"Chilgogae",
    "gn:population":0,
    "gn:timezone":"Asia/Seoul",
    "iso:country":"KR",
    "name:kor_x_preferred":[
        "\uc9c8\uace0\uac1c"
    ],
    "wof:name":"Chilgogae",
    "wof:placetype":"locality"
},
  "geometry": {"coordinates":[128.02889999999999,37.1164],"type":"Point"}
}