{
  "type": "Feature",
  "properties": {
    "gn:admin1_code":"12.0",
    "gn:admin2_code":"Kanghwa-gun",
    "gn:asciiname":"Jeoundong",
    "gn:country_code":"KR",
    "gn:dem":31,
    "gn:feature_class":"P",
    "gn:feature_code":"PPL",
    "gn:name":"Jeoundong",
    "gn:population":0,
    "gn:timezone":"Asia/Seoul",
    "iso:country":"KR",
    "name:kor_x_preferred":[
        "\uc800\uc6b4\ub3d9"
    ],
    "name:und_x_variant":[
        "Ch\u014fund\u016dl",
        "Ch\u014fun-dong",
        "Jeoundong"
    ],
    "wof:name":"Jeoundong",
    "wof:placetype":"locality"
},
  "geometry": {"coordinates":[126.36928,37.78528],"type":"Point"}
}