{
  "type": "Feature",
  "properties": {
    "gn:admin1_code":"16.0",
    "gn:asciiname":"Chodong",
    "gn:country_code":"KR",
    "gn:dem":37,
    "gn:feature_class":"P",
    "gn:feature_code":"PPL",
    "gn:name":"Chodong",
    "gn:population":0,
    "gn:timezone":"Asia/Seoul",
    "iso:country":"KR",
    "name:kor_x_preferred":[
        "\ucd08\ub3d9"
    ],
    "wof:name":"Chodong",
    "wof:placetype":"locality"
},
  "geometry": {"coordinates":[126.86442,35.25365],"type":"Point"}
}