{
  "type": "Feature",
  "properties": {
    "gn:admin1_code":"0.0",
    "gn:asciiname":"Haktari",
    "gn:cc2":"KR",
    "gn:country_code":"KR",
    "gn:dem":21,
    "gn:feature_class":"P",
    "gn:feature_code":"PPL",
    "gn:name":"Haktari",
    "gn:population":0,
    "gn:timezone":"Asia/Seoul",
    "iso:country":"KR",
    "name:und_x_variant":[
        "Ssanggyo",
        "S\u014dky\u014d",
        "Hakkyo",
        "Haktari"
    ],
    "wof:name":"Haktari",
    "wof:placetype":"locality"
},
  "geometry": {"coordinates":[126.55,35.01667],"type":"Point"}
}