{
  "type": "Feature",
  "properties": {
    "gn:admin1_code":"15.0",
    "gn:asciiname":"Bakkatsujeom",
    "gn:country_code":"KR",
    "gn:dem":189,
    "gn:feature_class":"P",
    "gn:feature_code":"PPL",
    "gn:name":"Bakkatsujeom",
    "gn:population":0,
    "gn:timezone":"Asia/Seoul",
    "iso:country":"KR",
    "name:und_x_variant":[
        "\ubc14\uae65\uc218\uc810",
        "Pakkatsuj\u014fm",
        "Bakkatsujeom"
    ],
    "wof:name":"Bakkatsujeom",
    "wof:placetype":"locality"
},
  "geometry": {"coordinates":[128.65929,35.74186],"type":"Point"}
}