{
  "type": "Feature",
  "properties": {
    "gn:admin1_code":"14.0",
    "gn:asciiname":"Ot'ae",
    "gn:country_code":"KR",
    "gn:dem":111,
    "gn:feature_class":"P",
    "gn:feature_code":"PPL",
    "gn:name":"Ot\u2019ae",
    "gn:population":0,
    "gn:timezone":"Asia/Seoul",
    "iso:country":"KR",
    "name:und_x_variant":[
        "\uc624\ud0dc",
        "Ot\u2019ae"
    ],
    "wof:name":"Ot'ae",
    "wof:placetype":"locality"
},
  "geometry": {"coordinates":[128.11510000000001,36.4994],"type":"Point"}
}