{
  "type": "Feature",
  "properties": {
    "gn:admin1_code":"13.0",
    "gn:asciiname":"Cheonggye",
    "gn:country_code":"KR",
    "gn:dem":180,
    "gn:feature_class":"P",
    "gn:feature_code":"PPL",
    "gn:name":"Cheonggye",
    "gn:population":0,
    "gn:timezone":"Asia/Seoul",
    "iso:country":"KR",
    "name:kor_x_preferred":[
        "\uccad\uacc4"
    ],
    "name:kor_x_variant":[
        "Ch\u014fnggye"
    ],
    "wof:name":"Cheonggye",
    "wof:placetype":"locality"
},
  "geometry": {"coordinates":[127.3327,37.9486],"type":"Point"}
}