{
  "type": "Feature",
  "properties": {
    "gn:admin1_code":"14.0",
    "gn:asciiname":"Songjon",
    "gn:cc2":"KR",
    "gn:country_code":"KR",
    "gn:dem":46,
    "gn:feature_class":"P",
    "gn:feature_code":"PPL",
    "gn:name":"Songj\u014fn",
    "gn:population":0,
    "gn:timezone":"Asia/Seoul",
    "iso:country":"KR",
    "name:und_x_variant":[
        "Songj\u014fn-ni",
        "Songj\u014fl-li",
        "Songj\u014fn"
    ],
    "wof:name":"Songjon",
    "wof:placetype":"locality"
},
  "geometry": {"coordinates":[129.42833000000002,35.75972],"type":"Point"}
}