{
  "type": "Feature",
  "properties": {
    "gn:admin1_code":"20.0",
    "gn:asciiname":"Gyeongbin",
    "gn:country_code":"KR",
    "gn:dem":10,
    "gn:feature_class":"P",
    "gn:feature_code":"PPL",
    "gn:name":"Gyeongbin",
    "gn:population":0,
    "gn:timezone":"Asia/Seoul",
    "iso:country":"KR",
    "name:kor_x_preferred":[
        "\uacbd\ube48"
    ],
    "wof:name":"Gyeongbin",
    "wof:placetype":"locality"
},
  "geometry": {"coordinates":[128.81661,35.19663],"type":"Point"}
}