{
  "type": "Feature",
  "properties": {
    "gn:admin1_code":"15.0",
    "gn:asciiname":"Midae",
    "gn:country_code":"KR",
    "gn:dem":118,
    "gn:feature_class":"P",
    "gn:feature_code":"PPL",
    "gn:name":"Midae",
    "gn:population":0,
    "gn:timezone":"Asia/Seoul",
    "iso:country":"KR",
    "name:kor_x_preferred":[
        "\ubbf8\ub300"
    ],
    "name:und_x_variant":[
        "Midae-dong",
        "Midae"
    ],
    "wof:name":"Midae",
    "wof:placetype":"locality"
},
  "geometry": {"coordinates":[128.66865000000001,35.95950999999999],"type":"Point"}
}