{
  "type": "Feature",
  "properties": {
    "gn:admin1_code":"17.0",
    "gn:asciiname":"Changgong-ni",
    "gn:cc2":"KR",
    "gn:country_code":"KR",
    "gn:dem":11,
    "gn:feature_class":"P",
    "gn:feature_code":"PPL",
    "gn:name":"Changgong-ni",
    "gn:population":0,
    "gn:timezone":"Asia/Seoul",
    "iso:country":"KR",
    "name:und_x_variant":[
        "Changgok-ri",
        "Changgong-ni"
    ],
    "wof:name":"Changgong-ni",
    "wof:placetype":"locality"
},
  "geometry": {"coordinates":[126.36111,36.42417],"type":"Point"}
}