{
  "type": "Feature",
  "properties": {
    "gn:admin1_code":"13.0",
    "gn:asciiname":"Saemaeul",
    "gn:country_code":"KR",
    "gn:dem":63,
    "gn:feature_class":"P",
    "gn:feature_code":"PPL",
    "gn:name":"Saemaeul",
    "gn:population":0,
    "gn:timezone":"Asia/Seoul",
    "iso:country":"KR",
    "name:kor_x_preferred":[
        "\uc0c8\ub9c8\uc744"
    ],
    "name:kor_x_variant":[
        "Sae-ma\u016dl"
    ],
    "wof:name":"Saemaeul",
    "wof:placetype":"locality"
},
  "geometry": {"coordinates":[127.67927,37.2412],"type":"Point"}
}