{
  "type": "Feature",
  "properties": {
    "gn:admin1_code":"3.0",
    "gn:asciiname":"Kumdang",
    "gn:country_code":"KR",
    "gn:dem":265,
    "gn:feature_class":"P",
    "gn:feature_code":"PPL",
    "gn:name":"K\u016dmdang",
    "gn:population":0,
    "gn:timezone":"Asia/Seoul",
    "iso:country":"KR",
    "name:und_x_variant":[
        "\uae08\ub2f9",
        "K\u016dmdang"
    ],
    "wof:name":"Kumdang",
    "wof:placetype":"locality"
},
  "geometry": {"coordinates":[127.31126,35.64477],"type":"Point"}
}