{
  "type": "Feature",
  "properties": {
    "gn:admin1_code":"5.0",
    "gn:asciiname":"Samachi",
    "gn:country_code":"KR",
    "gn:dem":251,
    "gn:feature_class":"P",
    "gn:feature_code":"PPL",
    "gn:name":"Samachi",
    "gn:population":0,
    "gn:timezone":"Asia/Seoul",
    "iso:country":"KR",
    "name:kor_x_preferred":[
        "\uc0ac\ub9c8\uce58"
    ],
    "name:kor_x_variant":[
        "Samach\u2019i"
    ],
    "wof:name":"Samachi",
    "wof:placetype":"locality"
},
  "geometry": {"coordinates":[128.33421000000001,37.08184],"type":"Point"}
}