{
  "type": "Feature",
  "properties": {
    "gn:admin1_code":"3.0",
    "gn:asciiname":"Chunggum",
    "gn:country_code":"KR",
    "gn:dem":246,
    "gn:feature_class":"P",
    "gn:feature_code":"PPL",
    "gn:name":"Chungg\u016dm",
    "gn:population":0,
    "gn:timezone":"Asia/Seoul",
    "iso:country":"KR",
    "name:und_x_variant":[
        "\uc911\uae08",
        "Chungg\u016dm"
    ],
    "wof:name":"Chunggum",
    "wof:placetype":"locality"
},
  "geometry": {"coordinates":[127.30124000000001,35.64134],"type":"Point"}
}