{
  "type": "Feature",
  "properties": {
    "gn:admin1_code":"13.0",
    "gn:asciiname":"Utmal",
    "gn:country_code":"KR",
    "gn:dem":35,
    "gn:feature_class":"P",
    "gn:feature_code":"PPL",
    "gn:name":"Utmal",
    "gn:population":0,
    "gn:timezone":"Asia/Seoul",
    "iso:country":"KR",
    "name:kor_x_preferred":[
        "\uc6c3\ub9d0"
    ],
    "wof:name":"Utmal",
    "wof:placetype":"locality"
},
  "geometry": {"coordinates":[126.80722,37.25],"type":"Point"}
}