{
  "type": "Feature",
  "properties": {
    "gn:admin1_code":"20.0",
    "gn:asciiname":"P'unggye",
    "gn:country_code":"KR",
    "gn:dem":288,
    "gn:feature_class":"P",
    "gn:feature_code":"PPL",
    "gn:name":"P\u2019unggye",
    "gn:population":0,
    "gn:timezone":"Asia/Seoul",
    "iso:country":"KR",
    "name:und_x_variant":[
        "\ud48d\uacc4",
        "P\u2019unggye"
    ],
    "wof:name":"P'unggye",
    "wof:placetype":"locality"
},
  "geometry": {"coordinates":[127.85890000000001,35.73186],"type":"Point"}
}