{
  "type": "Feature",
  "properties": {
    "gn:admin1_code":"3.0",
    "gn:asciiname":"Sonamjong",
    "gn:country_code":"KR",
    "gn:dem":136,
    "gn:feature_class":"P",
    "gn:feature_code":"PPL",
    "gn:name":"Sonamj\u014fng",
    "gn:population":0,
    "gn:timezone":"Asia/Seoul",
    "iso:country":"KR",
    "name:und_x_variant":[
        "\uc18c\ub0a8\uc815",
        "Sonamj\u014fng",
        "Sonamjeong"
    ],
    "wof:name":"Sonamjong",
    "wof:placetype":"locality"
},
  "geometry": {"coordinates":[127.36136999999999,35.51862],"type":"Point"}
}