{
  "type": "Feature",
  "properties": {
    "gn:admin1_code":"6.0",
    "gn:asciiname":"Kwangsok",
    "gn:country_code":"KR",
    "gn:dem":288,
    "gn:feature_class":"P",
    "gn:feature_code":"PPL",
    "gn:name":"Kwangs\u014fk",
    "gn:population":0,
    "gn:timezone":"Asia/Seoul",
    "iso:country":"KR",
    "name:kor_x_preferred":[
        "\uad11\uc11d"
    ],
    "name:kor_x_variant":[
        "Kwangs\u014fk"
    ],
    "wof:name":"Kwangsok",
    "wof:placetype":"locality"
},
  "geometry": {"coordinates":[128.6206,37.3655],"type":"Point"}
}