{
  "type": "Feature",
  "properties": {
    "gn:admin1_code":"16.0",
    "gn:asciiname":"Yeocheon",
    "gn:country_code":"KR",
    "gn:dem":31,
    "gn:feature_class":"P",
    "gn:feature_code":"PPL",
    "gn:name":"Yeocheon",
    "gn:population":0,
    "gn:timezone":"Asia/Seoul",
    "iso:country":"KR",
    "name:und_x_variant":[
        "Y\u014fch\u2019\u014fn-dong",
        "Yeocheon",
        "Y\u014fch\u2019\u014fn"
    ],
    "wof:name":"Yeocheon",
    "wof:placetype":"locality"
},
  "geometry": {"coordinates":[127.75583,34.54944],"type":"Point"}
}