{
  "type": "Feature",
  "properties": {
    "gn:admin1_code":"6.0",
    "gn:asciiname":"Sangimok",
    "gn:country_code":"KR",
    "gn:dem":365,
    "gn:feature_class":"P",
    "gn:feature_code":"PPL",
    "gn:name":"Sangimok",
    "gn:population":0,
    "gn:timezone":"Asia/Seoul",
    "iso:country":"KR",
    "name:kor_x_preferred":[
        "\uc0c1\uc774\ubaa9"
    ],
    "wof:name":"Sangimok",
    "wof:placetype":"locality"
},
  "geometry": {"coordinates":[128.66929999999999,37.1688],"type":"Point"}
}