{
  "type": "Feature",
  "properties": {
    "gn:admin1_code":"17.0",
    "gn:asciiname":"Sinp'ungwon",
    "gn:country_code":"KR",
    "gn:dem":4,
    "gn:feature_class":"P",
    "gn:feature_code":"PPL",
    "gn:name":"Sinp\u2019ungw\u014fn",
    "gn:population":0,
    "gn:timezone":"Asia/Seoul",
    "iso:country":"KR",
    "name:und_x_variant":[
        "\uc2e0\ud48d\uc6d0",
        "Sinp\u2019ungw\u014fn"
    ],
    "wof:name":"Sinp'ungwon",
    "wof:placetype":"locality"
},
  "geometry": {"coordinates":[126.8267,36.7832],"type":"Point"}
}