{
  "type": "Feature",
  "properties": {
    "gn:admin1_code":"17.0",
    "gn:asciiname":"Chaun-gol",
    "gn:country_code":"KR",
    "gn:dem":23,
    "gn:feature_class":"P",
    "gn:feature_code":"PPL",
    "gn:name":"Cha\u016dn-gol",
    "gn:population":0,
    "gn:timezone":"Asia/Seoul",
    "iso:country":"KR",
    "name:und_x_variant":[
        "\uc790\uc740\uace8",
        "Cha\u016dn-gol"
    ],
    "wof:name":"Chaun-gol",
    "wof:placetype":"locality"
},
  "geometry": {"coordinates":[126.538,36.5682],"type":"Point"}
}