{
  "type": "Feature",
  "properties": {
    "gn:admin1_code":"6.0",
    "gn:asciiname":"Yaksu-ri",
    "gn:country_code":"KR",
    "gn:dem":297,
    "gn:feature_class":"P",
    "gn:feature_code":"PPL",
    "gn:name":"Yaksu-ri",
    "gn:population":0,
    "gn:timezone":"Asia/Seoul",
    "iso:country":"KR",
    "name:kor_x_preferred":[
        "\uc57d\uc218\ub9ac"
    ],
    "wof:name":"Yaksu-ri",
    "wof:placetype":"locality"
},
  "geometry": {"coordinates":[128.37119999999999,37.3493],"type":"Point"}
}