{
  "type": "Feature",
  "properties": {
    "gn:admin1_code":"10.0",
    "gn:asciiname":"Songsan",
    "gn:country_code":"KR",
    "gn:dem":4,
    "gn:feature_class":"P",
    "gn:feature_code":"PPL",
    "gn:name":"Songsan",
    "gn:population":0,
    "gn:timezone":"Asia/Seoul",
    "iso:country":"KR",
    "name:kor_x_preferred":[
        "\uc1a1\uc0b0"
    ],
    "wof:name":"Songsan",
    "wof:placetype":"locality"
},
  "geometry": {"coordinates":[128.89028999999999,35.20277],"type":"Point"}
}