{
  "type": "Feature",
  "properties": {
    "gn:admin1_code":"5.0",
    "gn:asciiname":"Witganggeori",
    "gn:country_code":"KR",
    "gn:dem":110,
    "gn:feature_class":"P",
    "gn:feature_code":"PPL",
    "gn:name":"Witganggeori",
    "gn:population":0,
    "gn:timezone":"Asia/Seoul",
    "iso:country":"KR",
    "name:kor_x_preferred":[
        "\uc717\uac15\uac70\ub9ac"
    ],
    "wof:name":"Witganggeori",
    "wof:placetype":"locality"
},
  "geometry": {"coordinates":[127.54227,37.00093],"type":"Point"}
}