{
  "type": "Feature",
  "properties": {
    "gn:admin1_code":"20.0",
    "gn:asciiname":"Oksan",
    "gn:country_code":"KR",
    "gn:dem":590,
    "gn:feature_class":"P",
    "gn:feature_code":"PPL",
    "gn:name":"Oksan",
    "gn:population":0,
    "gn:timezone":"Asia/Seoul",
    "iso:country":"KR",
    "name:und_x_variant":[
        "\uc625\uc0b0",
        "Oksan"
    ],
    "wof:name":"Oksan",
    "wof:placetype":"locality"
},
  "geometry": {"coordinates":[127.99236999999999,35.78537],"type":"Point"}
}