{
  "type": "Feature",
  "properties": {
    "gn:admin1_code":"13.0",
    "gn:asciiname":"Tongch'on",
    "gn:country_code":"KR",
    "gn:dem":8,
    "gn:feature_class":"P",
    "gn:feature_code":"PPL",
    "gn:name":"Tongch\u2019on",
    "gn:population":0,
    "gn:timezone":"Asia/Seoul",
    "iso:country":"KR",
    "name:kor_x_preferred":[
        "\ub3d9\ucd0c"
    ],
    "name:kor_x_variant":[
        "Tongch\u2019on"
    ],
    "wof:name":"Tongch'on",
    "wof:placetype":"locality"
},
  "geometry": {"coordinates":[126.72499999999999,37.66528],"type":"Point"}
}