{
  "type": "Feature",
  "properties": {
    "gn:admin1_code":"20.0",
    "gn:asciiname":"Yongjon",
    "gn:country_code":"KR",
    "gn:dem":471,
    "gn:feature_class":"P",
    "gn:feature_code":"PPL",
    "gn:name":"Yongj\u014fn",
    "gn:population":0,
    "gn:timezone":"Asia/Seoul",
    "iso:country":"KR",
    "name:und_x_variant":[
        "\uc6a9\uc804",
        "Yongj\u014fn"
    ],
    "wof:name":"Yongjon",
    "wof:placetype":"locality"
},
  "geometry": {"coordinates":[127.90956,35.83102],"type":"Point"}
}