{
  "type": "Feature",
  "properties": {
    "gn:admin1_code":"13.0",
    "gn:asciiname":"Heosani",
    "gn:country_code":"KR",
    "gn:dem":74,
    "gn:feature_class":"P",
    "gn:feature_code":"PPL",
    "gn:name":"Heosani",
    "gn:population":0,
    "gn:timezone":"Asia/Seoul",
    "iso:country":"KR",
    "name:und_x_variant":[
        "\ud5c8\uc0b0\uc774",
        "Heosani",
        "H\u014fsani"
    ],
    "wof:name":"Heosani",
    "wof:placetype":"locality"
},
  "geometry": {"coordinates":[127.23944,37.38111],"type":"Point"}
}