{
  "type": "Feature",
  "properties": {
    "gn:admin1_code":"5.0",
    "gn:asciiname":"Seokdonggol",
    "gn:country_code":"KR",
    "gn:dem":169,
    "gn:feature_class":"P",
    "gn:feature_code":"PPL",
    "gn:name":"Seokdonggol",
    "gn:population":0,
    "gn:timezone":"Asia/Seoul",
    "iso:country":"KR",
    "name:kor_x_preferred":[
        "\uc11d\ub3d9\uace8"
    ],
    "name:kor_x_variant":[
        "S\u014fktong-gol"
    ],
    "wof:name":"Seokdonggol",
    "wof:placetype":"locality"
},
  "geometry": {"coordinates":[128.15522000000001,37.05688],"type":"Point"}
}