{
  "type": "Feature",
  "properties": {
    "gn:admin1_code":"14.0",
    "gn:asciiname":"Baksil",
    "gn:country_code":"KR",
    "gn:dem":110,
    "gn:feature_class":"P",
    "gn:feature_code":"PPL",
    "gn:name":"Baksil",
    "gn:population":0,
    "gn:timezone":"Asia/Seoul",
    "iso:country":"KR",
    "name:kor_x_preferred":[
        "\ubc15\uc2e4"
    ],
    "wof:name":"Baksil",
    "wof:placetype":"locality"
},
  "geometry": {"coordinates":[129.09464,35.83352],"type":"Point"}
}