{
  "type": "Feature",
  "properties": {
    "gn:admin1_code":"6.0",
    "gn:asciiname":"Tokp'ung",
    "gn:country_code":"KR",
    "gn:dem":264,
    "gn:feature_class":"P",
    "gn:feature_code":"PPL",
    "gn:name":"T\u014fkp\u2019ung",
    "gn:population":0,
    "gn:timezone":"Asia/Seoul",
    "iso:country":"KR",
    "name:und_x_variant":[
        "\ub355\ud48d",
        "T\u014fkp\u2019ung"
    ],
    "wof:name":"Tokp'ung",
    "wof:placetype":"locality"
},
  "geometry": {"coordinates":[129.18491,37.09819],"type":"Point"}
}