{
  "type": "Feature",
  "properties": {
    "gn:admin1_code":"20.0",
    "gn:asciiname":"P'aso",
    "gn:country_code":"KR",
    "gn:dem":5,
    "gn:feature_class":"P",
    "gn:feature_code":"PPL",
    "gn:name":"P\u2019as\u014f",
    "gn:population":0,
    "gn:timezone":"Asia/Seoul",
    "iso:country":"KR",
    "name:und_x_variant":[
        "P\u2019as\u014f-ri",
        "P\u2019as\u014f"
    ],
    "wof:name":"P'aso",
    "wof:placetype":"locality"
},
  "geometry": {"coordinates":[128.75,35.38333],"type":"Point"}
}