{
  "type": "Feature",
  "properties": {
    "gn:admin1_code":"14.0",
    "gn:asciiname":"Tangni-ri",
    "gn:cc2":"KR",
    "gn:country_code":"KR",
    "gn:dem":85,
    "gn:feature_class":"P",
    "gn:feature_code":"PPL",
    "gn:name":"Tangni-ri",
    "gn:population":0,
    "gn:timezone":"Asia/Seoul",
    "iso:country":"KR",
    "name:und_x_variant":[
        "Tangni-dong",
        "Tangni-ri"
    ],
    "wof:name":"Tangni-ri",
    "wof:placetype":"locality"
},
  "geometry": {"coordinates":[128.87583000000001,35.79389000000001],"type":"Point"}
}