{
  "type": "Feature",
  "properties": {
    "gn:admin1_code":"13.0",
    "gn:asciiname":"Gungtteul",
    "gn:country_code":"KR",
    "gn:dem":101,
    "gn:feature_class":"P",
    "gn:feature_code":"PPL",
    "gn:name":"Gungtteul",
    "gn:population":0,
    "gn:timezone":"Asia/Seoul",
    "iso:country":"KR",
    "name:kor_x_preferred":[
        "\uad81\ub730"
    ],
    "wof:name":"Gungtteul",
    "wof:placetype":"locality"
},
  "geometry": {"coordinates":[127.11559,38.02007],"type":"Point"}
}