{
  "type": "Feature",
  "properties": {
    "gn:admin1_code":"6.0",
    "gn:asciiname":"Sojaegol",
    "gn:country_code":"KR",
    "gn:dem":354,
    "gn:feature_class":"P",
    "gn:feature_code":"PPL",
    "gn:name":"Sojaegol",
    "gn:population":0,
    "gn:timezone":"Asia/Seoul",
    "iso:country":"KR",
    "name:kor_x_preferred":[
        "\uc18c\uc7ac\uace8"
    ],
    "wof:name":"Sojaegol",
    "wof:placetype":"locality"
},
  "geometry": {"coordinates":[128.16673,38.16166],"type":"Point"}
}