{
  "type": "Feature",
  "properties": {
    "gn:admin1_code":"13.0",
    "gn:asciiname":"Beomuli",
    "gn:country_code":"KR",
    "gn:dem":67,
    "gn:feature_class":"P",
    "gn:feature_code":"PPL",
    "gn:name":"Beomuli",
    "gn:population":0,
    "gn:timezone":"Asia/Seoul",
    "iso:country":"KR",
    "name:kor_x_preferred":[
        "\ubc94\uc6b8\uc774"
    ],
    "wof:name":"Beomuli",
    "wof:placetype":"locality"
},
  "geometry": {"coordinates":[127.46099,37.71862],"type":"Point"}
}