{
  "type": "Feature",
  "properties": {
    "gn:admin1_code":"14.0",
    "gn:asciiname":"Chungmak",
    "gn:country_code":"KR",
    "gn:dem":191,
    "gn:feature_class":"P",
    "gn:feature_code":"PPL",
    "gn:name":"Chungmak",
    "gn:population":0,
    "gn:timezone":"Asia/Seoul",
    "iso:country":"KR",
    "name:und_x_variant":[
        "\uc8fd\ub9c9",
        "Chungmak"
    ],
    "wof:name":"Chungmak",
    "wof:placetype":"locality"
},
  "geometry": {"coordinates":[128.00630000000001,36.1965],"type":"Point"}
}