{
  "type": "Feature",
  "properties": {
    "gn:admin1_code":"14.0",
    "gn:asciiname":"Naemip'a-gol",
    "gn:country_code":"KR",
    "gn:dem":187,
    "gn:feature_class":"P",
    "gn:feature_code":"PPL",
    "gn:name":"Naemip\u2019a-gol",
    "gn:population":0,
    "gn:timezone":"Asia/Seoul",
    "iso:country":"KR",
    "name:und_x_variant":[
        "\ub0b4\ubbf8\ud30c\uace8",
        "Naemip\u2019a-gol"
    ],
    "wof:name":"Naemip'a-gol",
    "wof:placetype":"locality"
},
  "geometry": {"coordinates":[129.30959999999999,36.9901],"type":"Point"}
}