{
  "type": "Feature",
  "properties": {
    "gn:admin1_code":"13.0",
    "gn:asciiname":"Geongon",
    "gn:country_code":"KR",
    "gn:dem":13,
    "gn:feature_class":"P",
    "gn:feature_code":"PPL",
    "gn:name":"Geongon",
    "gn:population":0,
    "gn:timezone":"Asia/Seoul",
    "iso:country":"KR",
    "name:und_x_variant":[
        "\uac74\uace4",
        "Geongon",
        "K\u014fn\u2019gon"
    ],
    "wof:name":"Geongon",
    "wof:placetype":"locality"
},
  "geometry": {"coordinates":[127.03055999999999,37.01722],"type":"Point"}
}