{
  "type": "Feature",
  "properties": {
    "gn:admin1_code":"17.0",
    "gn:asciiname":"Kijisi-ri",
    "gn:cc2":"KR",
    "gn:country_code":"KR",
    "gn:dem":66,
    "gn:feature_class":"P",
    "gn:feature_code":"PPL",
    "gn:name":"Kijisi-ri",
    "gn:population":0,
    "gn:timezone":"Asia/Seoul",
    "iso:country":"KR",
    "name:und_x_variant":[
        "T\u2019ulmossi-ri",
        "Kijisi-ri",
        "\uae30\uc9c0\uc2dc\ub9ac"
    ],
    "wof:name":"Kijisi-ri",
    "wof:placetype":"locality"
},
  "geometry": {"coordinates":[126.68971999999999,36.90361],"type":"Point"}
}