{
  "type": "Feature",
  "properties": {
    "gn:admin1_code":"14.0",
    "gn:asciiname":"Yaguranggok",
    "gn:country_code":"KR",
    "gn:dem":398,
    "gn:feature_class":"P",
    "gn:feature_code":"PPL",
    "gn:name":"Yaguranggok",
    "gn:population":0,
    "gn:timezone":"Asia/Seoul",
    "iso:country":"KR",
    "name:und_x_variant":[
        "\uc57c\uad6c\ub791\uace1",
        "Yaguranggok"
    ],
    "wof:name":"Yaguranggok",
    "wof:placetype":"locality"
},
  "geometry": {"coordinates":[129.16829999999999,36.7803],"type":"Point"}
}