{
  "type": "Feature",
  "properties": {
    "gn:admin1_code":"3.0",
    "gn:asciiname":"Wang-ch'on",
    "gn:country_code":"KR",
    "gn:dem":176,
    "gn:feature_class":"P",
    "gn:feature_code":"PPL",
    "gn:name":"Wang-ch\u2019on",
    "gn:population":0,
    "gn:timezone":"Asia/Seoul",
    "iso:country":"KR",
    "name:und_x_variant":[
        "\uc655\ucd0c",
        "Wang-ch\u2019on",
        "Wangchon"
    ],
    "wof:name":"Wang-ch'on",
    "wof:placetype":"locality"
},
  "geometry": {"coordinates":[127.40922999999999,35.56487],"type":"Point"}
}