{
  "type": "Feature",
  "properties": {
    "gn:admin1_code":"13.0",
    "gn:asciiname":"Geodani",
    "gn:country_code":"KR",
    "gn:dem":178,
    "gn:feature_class":"P",
    "gn:feature_code":"PPL",
    "gn:name":"Geodani",
    "gn:population":0,
    "gn:timezone":"Asia/Seoul",
    "iso:country":"KR",
    "name:und_x_variant":[
        "K\u014fttani",
        "\uac70\ub2e8\uc774",
        "Geodani",
        "K\u014fdani"
    ],
    "wof:name":"Geodani",
    "wof:placetype":"locality"
},
  "geometry": {"coordinates":[127.71333,37.38722],"type":"Point"}
}