{
  "type": "Feature",
  "properties": {
    "gn:admin1_code":"20.0",
    "gn:asciiname":"Chinch'ang-ni",
    "gn:country_code":"KR",
    "gn:dem":20,
    "gn:feature_class":"P",
    "gn:feature_code":"PPL",
    "gn:name":"Chinch\u2019ang-ni",
    "gn:population":0,
    "gn:timezone":"Asia/Seoul",
    "iso:country":"KR",
    "name:und_x_variant":[
        "\uc9c4\ucc3d\ub9ac",
        "Chinch\u2019ang-ni"
    ],
    "wof:name":"Chinch'ang-ni",
    "wof:placetype":"locality"
},
  "geometry": {"coordinates":[128.42618999999999,35.49824],"type":"Point"}
}