{
  "type": "Feature",
  "properties": {
    "gn:admin1_code":"13.0",
    "gn:asciiname":"Komukkol",
    "gn:country_code":"KR",
    "gn:dem":29,
    "gn:feature_class":"P",
    "gn:feature_code":"PPL",
    "gn:name":"K\u014fmukkol",
    "gn:population":0,
    "gn:timezone":"Asia/Seoul",
    "iso:country":"KR",
    "name:kor_x_preferred":[
        "\uac70\ubb35\uace8"
    ],
    "name:kor_x_variant":[
        "K\u014fmukkol"
    ],
    "wof:name":"Komukkol",
    "wof:placetype":"locality"
},
  "geometry": {"coordinates":[126.8575,37.07833],"type":"Point"}
}