{
  "type": "Feature",
  "properties": {
    "gn:admin1_code":"16.0",
    "gn:asciiname":"Tuam",
    "gn:cc2":"KR",
    "gn:country_code":"KR",
    "gn:dem":4,
    "gn:feature_class":"P",
    "gn:feature_code":"PPL",
    "gn:name":"Tuam",
    "gn:population":0,
    "gn:timezone":"Asia/Seoul",
    "iso:country":"KR",
    "name:bre_x_preferred":[
        "Tuaim"
    ],
    "name:bul_x_preferred":[
        "\u0422\u0443\u044a\u043c"
    ],
    "name:cat_x_preferred":[
        "Tuam"
    ],
    "name:ceb_x_preferred":[
        "Tuam"
    ],
    "name:ces_x_preferred":[
        "Tuam"
    ],
    "name:dan_x_preferred":[
        "Tuam"
    ],
    "name:deu_x_preferred":[
        "Tuam"
    ],
    "name:eus_x_preferred":[
        "Tuam"
    ],
    "name:fra_x_preferred":[
        "Tuam"
    ],
    "name:gla_x_preferred":[
        "Tuaim"
    ],
    "name:gle_x_preferred":[
        "Tuaim"
    ],
    "name:glg_x_preferred":[
        "Tuam"
    ],
    "name:ind_x_preferred":[
        "Tuam"
    ],
    "name:ita_x_preferred":[
        "Tuam"
    ],
    "name:jpn_x_preferred":[
        "\u30c1\u30e5\u30a2\u30e0"
    ],
    "name:kat_x_preferred":[
        "\u10e9\u10e3\u10db\u10d8"
    ],
    "name:nld_x_preferred":[
        "Tuam"
    ],
    "name:pol_x_preferred":[
        "Tuam"
    ],
    "name:por_x_preferred":[
        "Tuam"
    ],
    "name:rus_x_preferred":[
        "\u0422\u0443\u0430\u043c"
    ],
    "name:spa_x_preferred":[
        "Tuam"
    ],
    "name:srp_x_preferred":[
        "\u0427\u0443\u043c"
    ],
    "name:swe_x_preferred":[
        "Tuam"
    ],
    "name:und_x_variant":[
        "Tuam-ni"
    ],
    "name:urd_x_preferred":[
        "\u0679\u06cc\u0648\u06cc\u0645"
    ],
    "wof:name":"Tuam",
    "wof:placetype":"locality"
},
  "geometry": {"coordinates":[126.51667,34.95],"type":"Point"}
}