{
  "type": "Feature",
  "properties": {
    "gn:admin1_code":"14.0",
    "gn:asciiname":"Komyong-dong",
    "gn:country_code":"KR",
    "gn:dem":60,
    "gn:feature_class":"P",
    "gn:feature_code":"PPL",
    "gn:name":"Komy\u014fng-dong",
    "gn:population":0,
    "gn:timezone":"Asia/Seoul",
    "iso:country":"KR",
    "name:und_x_variant":[
        "\uace0\uba85\ub3d9",
        "Komy\u014fng-dong"
    ],
    "wof:name":"Komyong-dong",
    "wof:placetype":"locality"
},
  "geometry": {"coordinates":[128.262,36.2266],"type":"Point"}
}