{
  "type": "Feature",
  "properties": {
    "gn:admin1_code":"13.0",
    "gn:asciiname":"Cheongdang-dong",
    "gn:country_code":"KR",
    "gn:dem":62,
    "gn:feature_class":"P",
    "gn:feature_code":"PPL",
    "gn:name":"Cheongdang-dong",
    "gn:population":0,
    "gn:timezone":"Asia/Seoul",
    "iso:country":"KR",
    "name:und_x_variant":[
        "\uccad\ub2f9\ub3d9",
        "Cheongdang-dong",
        "Ch\u2019\u014fngdang-dong"
    ],
    "wof:name":"Cheongdang-dong",
    "wof:placetype":"locality"
},
  "geometry": {"coordinates":[127.54111,37.31944],"type":"Point"}
}