{
  "type": "Feature",
  "properties": {
    "gn:admin1_code":"6.0",
    "gn:asciiname":"Wondanggol",
    "gn:country_code":"KR",
    "gn:dem":71,
    "gn:feature_class":"P",
    "gn:feature_code":"PPL",
    "gn:name":"Wondanggol",
    "gn:population":0,
    "gn:timezone":"Asia/Seoul",
    "iso:country":"KR",
    "name:kor_x_preferred":[
        "\uc6d0\ub2f9\uace8"
    ],
    "wof:name":"Wondanggol",
    "wof:placetype":"locality"
},
  "geometry": {"coordinates":[128.56939,38.06718],"type":"Point"}
}