{
  "type": "Feature",
  "properties": {
    "gn:admin1_code":"13.0",
    "gn:asciiname":"Jangseung",
    "gn:country_code":"KR",
    "gn:dem":60,
    "gn:feature_class":"P",
    "gn:feature_code":"PPL",
    "gn:name":"Jangseung",
    "gn:population":0,
    "gn:timezone":"Asia/Seoul",
    "iso:country":"KR",
    "name:fra_x_preferred":[
        "Jangseung"
    ],
    "name:ind_x_preferred":[
        "Jangseung"
    ],
    "name:jpn_x_preferred":[
        "\u5c06\u8ecd\u6a19"
    ],
    "name:kor_x_preferred":[
        "\uc7a5\uc2b9"
    ],
    "name:msa_x_preferred":[
        "Jangseung"
    ],
    "name:nld_x_preferred":[
        "Jangseung"
    ],
    "name:ukr_x_preferred":[
        "\u0427\u0430\u043d\u0441\u0438\u043d"
    ],
    "name:und_x_variant":[
        "Changs\u016dng"
    ],
    "wof:name":"Jangseung",
    "wof:placetype":"locality"
},
  "geometry": {"coordinates":[127.19293,37.73043],"type":"Point"}
}