{
  "type": "Feature",
  "properties": {
    "gn:admin1_code":"14.0",
    "gn:asciiname":"Kyo-ri",
    "gn:country_code":"KR",
    "gn:dem":45,
    "gn:feature_class":"P",
    "gn:feature_code":"PPLL",
    "gn:name":"Kyo-ri",
    "gn:population":0,
    "gn:timezone":"Asia/Seoul",
    "iso:country":"KR",
    "name:und_x_variant":[
        "\uad50\ub9ac",
        "Kyo-ri"
    ],
    "wof:name":"Kyo-ri",
    "wof:placetype":"locality"
},
  "geometry": {"coordinates":[128.3647,36.04926],"type":"Point"}
}