{
  "type": "Feature",
  "properties": {
    "gn:admin1_code":"16.0",
    "gn:asciiname":"Oksan",
    "gn:country_code":"KR",
    "gn:dem":23,
    "gn:feature_class":"P",
    "gn:feature_code":"PPL",
    "gn:name":"Oksan",
    "gn:population":0,
    "gn:timezone":"Asia/Seoul",
    "iso:country":"KR",
    "name:kor_x_preferred":[
        "\uc625\uc0b0"
    ],
    "wof:name":"Oksan",
    "wof:placetype":"locality"
},
  "geometry": {"coordinates":[126.74391,34.97806],"type":"Point"}
}