{
  "type": "Feature",
  "properties": {
    "gn:admin1_code":"5.0",
    "gn:asciiname":"Ganeungol",
    "gn:country_code":"KR",
    "gn:dem":301,
    "gn:feature_class":"P",
    "gn:feature_code":"PPL",
    "gn:name":"Ganeungol",
    "gn:population":0,
    "gn:timezone":"Asia/Seoul",
    "iso:country":"KR",
    "name:kor_x_preferred":[
        "\uac00\ub294\uace8"
    ],
    "name:kor_x_variant":[
        "Kan\u016dn-gol"
    ],
    "wof:name":"Ganeungol",
    "wof:placetype":"locality"
},
  "geometry": {"coordinates":[127.7649,37.1228],"type":"Point"}
}