{
  "type": "Feature",
  "properties": {
    "gn:admin1_code":"17.0",
    "gn:asciiname":"Oemaru",
    "gn:country_code":"KR",
    "gn:dem":55,
    "gn:feature_class":"P",
    "gn:feature_code":"PPL",
    "gn:name":"Oemaru",
    "gn:population":0,
    "gn:timezone":"Asia/Seoul",
    "iso:country":"KR",
    "name:kor_x_preferred":[
        "\uc65c\ub9c8\ub8e8"
    ],
    "wof:name":"Oemaru",
    "wof:placetype":"locality"
},
  "geometry": {"coordinates":[127.32246000000001,36.73585],"type":"Point"}
}