{
  "type": "Feature",
  "properties": {
    "gn:admin1_code":"3.0",
    "gn:asciiname":"Pallyong-ni",
    "gn:cc2":"KR",
    "gn:country_code":"KR",
    "gn:dem":82,
    "gn:feature_class":"P",
    "gn:feature_code":"PPL",
    "gn:name":"Pallyong-ni",
    "gn:population":0,
    "gn:timezone":"Asia/Seoul",
    "iso:country":"KR",
    "name:und_x_variant":[
        "Panyong-ni",
        "Pannyong-ni",
        "Pallyong-ni"
    ],
    "wof:name":"Pallyong-ni",
    "wof:placetype":"locality"
},
  "geometry": {"coordinates":[126.72221999999999,35.46694],"type":"Point"}
}