{
  "type": "Feature",
  "properties": {
    "gn:admin1_code":"13.0",
    "gn:asciiname":"Pamnamu-gol",
    "gn:country_code":"KR",
    "gn:dem":75,
    "gn:feature_class":"P",
    "gn:feature_code":"PPL",
    "gn:name":"Pamnamu-gol",
    "gn:population":0,
    "gn:timezone":"Asia/Seoul",
    "iso:country":"KR",
    "name:und_x_variant":[
        "\ubc24\ub098\ubb34\uace8",
        "Bamnamu-gol",
        "Pamnamu-gol"
    ],
    "wof:name":"Pamnamu-gol",
    "wof:placetype":"locality"
},
  "geometry": {"coordinates":[127.53278,37.27417],"type":"Point"}
}