{
  "type": "Feature",
  "properties": {
    "gn:admin1_code":"17.0",
    "gn:asciiname":"Hwangsae-gol",
    "gn:country_code":"KR",
    "gn:dem":36,
    "gn:feature_class":"P",
    "gn:feature_code":"PPL",
    "gn:name":"Hwangsae-gol",
    "gn:population":0,
    "gn:timezone":"Asia/Seoul",
    "iso:country":"KR",
    "name:und_x_variant":[
        "\ud669\uc0c8\uace8",
        "Hwangsae-gol"
    ],
    "wof:name":"Hwangsae-gol",
    "wof:placetype":"locality"
},
  "geometry": {"coordinates":[127.1121,36.4886],"type":"Point"}
}