{
  "type": "Feature",
  "properties": {
    "gn:admin1_code":"13.0",
    "gn:asciiname":"Yongso",
    "gn:country_code":"KR",
    "gn:dem":49,
    "gn:feature_class":"P",
    "gn:feature_code":"PPL",
    "gn:name":"Y\u014fngs\u014f",
    "gn:population":0,
    "gn:timezone":"Asia/Seoul",
    "iso:country":"KR",
    "name:kor_x_preferred":[
        "\uc601\uc11c"
    ],
    "name:und_x_variant":[
        "Y\u014fngs\u014f"
    ],
    "wof:name":"Yongso",
    "wof:placetype":"locality"
},
  "geometry": {"coordinates":[127.1557,37.6861],"type":"Point"}
}