{
  "type": "Feature",
  "properties": {
    "gn:admin1_code":"14.0",
    "gn:asciiname":"Sinhyeon",
    "gn:country_code":"KR",
    "gn:dem":506,
    "gn:feature_class":"P",
    "gn:feature_code":"PPL",
    "gn:name":"Sinhyeon",
    "gn:population":0,
    "gn:timezone":"Asia/Seoul",
    "iso:country":"KR",
    "name:kor_x_preferred":[
        "\uc2e0\ud604"
    ],
    "wof:name":"Sinhyeon",
    "wof:placetype":"locality"
},
  "geometry": {"coordinates":[128.81908000000001,37.0151],"type":"Point"}
}