{
  "type": "Feature",
  "properties": {
    "gn:admin1_code":"17.0",
    "gn:asciiname":"K'un-maul",
    "gn:country_code":"KR",
    "gn:dem":27,
    "gn:feature_class":"P",
    "gn:feature_code":"PPL",
    "gn:name":"K\u2019\u016dn-ma\u016dl",
    "gn:population":0,
    "gn:timezone":"Asia/Seoul",
    "iso:country":"KR",
    "name:und_x_variant":[
        "\ud070\ub9c8\uc744",
        "K\u2019\u016dn-ma\u016dl"
    ],
    "wof:name":"K'un-maul",
    "wof:placetype":"locality"
},
  "geometry": {"coordinates":[126.9228,36.3516],"type":"Point"}
}