{
  "type": "Feature",
  "properties": {
    "gn:admin1_code":"5.0",
    "gn:asciiname":"Yonggol",
    "gn:country_code":"KR",
    "gn:dem":143,
    "gn:feature_class":"P",
    "gn:feature_code":"PPL",
    "gn:name":"Yonggol",
    "gn:population":0,
    "gn:timezone":"Asia/Seoul",
    "iso:country":"KR",
    "name:und_x_variant":[
        "\uc6a9\uace8",
        "Yonggol"
    ],
    "wof:name":"Yonggol",
    "wof:placetype":"locality"
},
  "geometry": {"coordinates":[127.64543999999999,36.42512],"type":"Point"}
}