{
  "type": "Feature",
  "properties": {
    "gn:admin1_code":"5.0",
    "gn:asciiname":"Sanumul",
    "gn:country_code":"KR",
    "gn:dem":136,
    "gn:feature_class":"P",
    "gn:feature_code":"PPL",
    "gn:name":"Sanumul",
    "gn:population":0,
    "gn:timezone":"Asia/Seoul",
    "iso:country":"KR",
    "name:kor_x_preferred":[
        "\uc0b0\uc6b0\ubb3c"
    ],
    "wof:name":"Sanumul",
    "wof:placetype":"locality"
},
  "geometry": {"coordinates":[127.87415,36.95225],"type":"Point"}
}