{
  "type": "Feature",
  "properties": {
    "gn:admin1_code":"5.0",
    "gn:asciiname":"Dolmaraemi",
    "gn:country_code":"KR",
    "gn:dem":110,
    "gn:feature_class":"P",
    "gn:feature_code":"PPL",
    "gn:name":"Dolmaraemi",
    "gn:population":0,
    "gn:timezone":"Asia/Seoul",
    "iso:country":"KR",
    "name:kor_x_preferred":[
        "\ub3cc\ub9c8\ub798\ubbf8"
    ],
    "name:und_x_variant":[
        "Tolmaraemi"
    ],
    "wof:name":"Dolmaraemi",
    "wof:placetype":"locality"
},
  "geometry": {"coordinates":[127.67676000000002,37.12597],"type":"Point"}
}