{
  "type": "Feature",
  "properties": {
    "gn:admin1_code":"16.0",
    "gn:asciiname":"Sedung-ni",
    "gn:cc2":"KR",
    "gn:country_code":"KR",
    "gn:dem":25,
    "gn:feature_class":"P",
    "gn:feature_code":"PPL",
    "gn:name":"Sed\u016dng-ni",
    "gn:population":0,
    "gn:timezone":"Asia/Seoul",
    "iso:country":"KR",
    "name:eng_x_preferred":[
        "Sedung"
    ],
    "name:eng_x_variant":[
        "Sedung-ni"
    ],
    "name:und_x_variant":[
        "Sait\u014d-ri",
        "Sed\u016dng",
        "Sed\u016dng-ni"
    ],
    "wof:name":"Sedung",
    "wof:placetype":"locality"
},
  "geometry": {"coordinates":[126.31667,34.51667],"type":"Point"}
}