{
  "type": "Feature",
  "properties": {
    "gn:admin1_code":"17.0",
    "gn:asciiname":"Songji",
    "gn:country_code":"KR",
    "gn:dem":85,
    "gn:feature_class":"P",
    "gn:feature_code":"PPL",
    "gn:name":"S\u014fngji",
    "gn:population":0,
    "gn:timezone":"Asia/Seoul",
    "iso:country":"KR",
    "name:und_x_variant":[
        "\uc131\uc9c0",
        "S\u014fngji"
    ],
    "wof:name":"Songji",
    "wof:placetype":"locality"
},
  "geometry": {"coordinates":[126.65170000000001,36.7322],"type":"Point"}
}