{
  "type": "Feature",
  "properties": {
    "gn:admin1_code":"14.0",
    "gn:asciiname":"Kumam",
    "gn:country_code":"KR",
    "gn:dem":62,
    "gn:feature_class":"P",
    "gn:feature_code":"PPL",
    "gn:name":"K\u016dmam",
    "gn:population":0,
    "gn:timezone":"Asia/Seoul",
    "iso:country":"KR",
    "name:und_x_variant":[
        "\uae08\uc554",
        "K\u016dmam"
    ],
    "wof:name":"Kumam",
    "wof:placetype":"locality"
},
  "geometry": {"coordinates":[128.24045000000001,35.94058],"type":"Point"}
}