{
  "type": "Feature",
  "properties": {
    "gn:admin1_code":"14.0",
    "gn:asciiname":"Gaengbyeonma",
    "gn:country_code":"KR",
    "gn:dem":109,
    "gn:feature_class":"P",
    "gn:feature_code":"PPL",
    "gn:name":"Gaengbyeonma",
    "gn:population":0,
    "gn:timezone":"Asia/Seoul",
    "iso:country":"KR",
    "name:kor_x_preferred":[
        "\uac31\ubcc0\ub9c8"
    ],
    "wof:name":"Gaengbyeonma",
    "wof:placetype":"locality"
},
  "geometry": {"coordinates":[128.80624,36.01123],"type":"Point"}
}