{
  "type": "Feature",
  "properties": {
    "gn:admin1_code":"6.0",
    "gn:asciiname":"Saem-gol",
    "gn:country_code":"KR",
    "gn:dem":125,
    "gn:feature_class":"P",
    "gn:feature_code":"PPL",
    "gn:name":"Saem-gol",
    "gn:population":0,
    "gn:timezone":"Asia/Seoul",
    "iso:country":"KR",
    "name:und_x_variant":[
        "\uc0d8\uace8",
        "Saem-gol"
    ],
    "wof:name":"Saem-gol",
    "wof:placetype":"locality"
},
  "geometry": {"coordinates":[127.66840000000001,37.9102],"type":"Point"}
}