{
  "type": "Feature",
  "properties": {
    "gn:admin1_code":"14.0",
    "gn:asciiname":"Hwasan-dong",
    "gn:country_code":"KR",
    "gn:dem":59,
    "gn:feature_class":"P",
    "gn:feature_code":"PPL",
    "gn:name":"Hwasan-dong",
    "gn:population":0,
    "gn:timezone":"Asia/Seoul",
    "iso:country":"KR",
    "name:und_x_variant":[
        "\ud654\uc0b0\ub3d9",
        "Hwasan-dong"
    ],
    "wof:name":"Hwasan-dong",
    "wof:placetype":"locality"
},
  "geometry": {"coordinates":[128.17859999999999,36.4384],"type":"Point"}
}