{
  "type": "Feature",
  "properties": {
    "gn:admin1_code":"17.0",
    "gn:asciiname":"Hyeonam",
    "gn:country_code":"KR",
    "gn:dem":64,
    "gn:feature_class":"P",
    "gn:feature_code":"PPL",
    "gn:name":"Hyeonam",
    "gn:population":0,
    "gn:timezone":"Asia/Seoul",
    "iso:country":"KR",
    "name:kor_x_preferred":[
        "\ud604\uc554"
    ],
    "wof:name":"Hyeonam",
    "wof:placetype":"locality"
},
  "geometry": {"coordinates":[127.2611,36.72917],"type":"Point"}
}