{
  "type": "Feature",
  "properties": {
    "gn:admin1_code":"14.0",
    "gn:asciiname":"Mudong",
    "gn:country_code":"KR",
    "gn:dem":108,
    "gn:feature_class":"P",
    "gn:feature_code":"PPL",
    "gn:name":"Mudong",
    "gn:population":0,
    "gn:timezone":"Asia/Seoul",
    "iso:country":"KR",
    "name:kor_x_preferred":[
        "\ubb34\ub3d9"
    ],
    "wof:name":"Mudong",
    "wof:placetype":"locality"
},
  "geometry": {"coordinates":[128.30483000000001,36.60832],"type":"Point"}
}