{
  "type": "Feature",
  "properties": {
    "gn:admin1_code":"6.0",
    "gn:asciiname":"Kuragu",
    "gn:country_code":"KR",
    "gn:dem":482,
    "gn:feature_class":"P",
    "gn:feature_code":"PPL",
    "gn:name":"Kuragu",
    "gn:population":0,
    "gn:timezone":"Asia/Seoul",
    "iso:country":"KR",
    "name:kor_x_preferred":[
        "\uad74\uc544\uad6c"
    ],
    "wof:name":"Kuragu",
    "wof:placetype":"locality"
},
  "geometry": {"coordinates":[128.35120000000001,37.4097],"type":"Point"}
}