{
  "type": "Feature",
  "properties": {
    "gn:admin1_code":"17.0",
    "gn:asciiname":"Chagun-gol",
    "gn:country_code":"KR",
    "gn:dem":220,
    "gn:feature_class":"P",
    "gn:feature_code":"PPL",
    "gn:name":"Chag\u016dn-gol",
    "gn:population":0,
    "gn:timezone":"Asia/Seoul",
    "iso:country":"KR",
    "name:und_x_variant":[
        "\uc791\uc740\uace8",
        "Chag\u016dn-gol"
    ],
    "wof:name":"Chagun-gol",
    "wof:placetype":"locality"
},
  "geometry": {"coordinates":[126.75839999999999,36.4414],"type":"Point"}
}