{
  "type": "Feature",
  "properties": {
    "gn:admin1_code":"17.0",
    "gn:asciiname":"Amsam-ni",
    "gn:country_code":"KR",
    "gn:dem":240,
    "gn:feature_class":"P",
    "gn:feature_code":"PPL",
    "gn:name":"Amsam-ni",
    "gn:population":0,
    "gn:timezone":"Asia/Seoul",
    "iso:country":"KR",
    "name:und_x_variant":[
        "\uc554\uc0bc\ub9ac",
        "Amsam-ni"
    ],
    "wof:name":"Amsam-ni",
    "wof:placetype":"locality"
},
  "geometry": {"coordinates":[127.38330000000001,36.0682],"type":"Point"}
}