{
  "type": "Feature",
  "properties": {
    "gn:admin1_code":"5.0",
    "gn:asciiname":"Pangada-ri",
    "gn:country_code":"KR",
    "gn:dem":181,
    "gn:feature_class":"P",
    "gn:feature_code":"PPL",
    "gn:name":"Pangada-ri",
    "gn:population":0,
    "gn:timezone":"Asia/Seoul",
    "iso:country":"KR",
    "name:und_x_variant":[
        "\ubc29\uc544\ub2e4\ub9ac",
        "Pangada-ri"
    ],
    "wof:name":"Pangada-ri",
    "wof:placetype":"locality"
},
  "geometry": {"coordinates":[127.7706,36.4629],"type":"Point"}
}