{
  "type": "Feature",
  "properties": {
    "gn:admin1_code":"13.0",
    "gn:asciiname":"Yosul",
    "gn:country_code":"KR",
    "gn:dem":19,
    "gn:feature_class":"P",
    "gn:feature_code":"PPL",
    "gn:name":"Y\u014fsul",
    "gn:population":0,
    "gn:timezone":"Asia/Seoul",
    "iso:country":"KR",
    "name:kor_x_preferred":[
        "\uc5ec\uc220"
    ],
    "name:kor_x_variant":[
        "Y\u014fsul"
    ],
    "wof:name":"Yosul",
    "wof:placetype":"locality"
},
  "geometry": {"coordinates":[126.78861000000001,37.10611],"type":"Point"}
}