{
  "type": "Feature",
  "properties": {
    "gn:admin1_code":"5.0",
    "gn:asciiname":"Sang-ch'on",
    "gn:country_code":"KR",
    "gn:dem":168,
    "gn:feature_class":"P",
    "gn:feature_code":"PPL",
    "gn:name":"Sang-ch\u2019on",
    "gn:population":0,
    "gn:timezone":"Asia/Seoul",
    "iso:country":"KR",
    "name:und_x_variant":[
        "\uc0c1\ucd0c",
        "Sang-ch\u2019on"
    ],
    "wof:name":"Sang-ch'on",
    "wof:placetype":"locality"
},
  "geometry": {"coordinates":[127.78440000000001,36.4628],"type":"Point"}
}