{
  "type": "Feature",
  "properties": {
    "gn:admin1_code":"3.0",
    "gn:asciiname":"Ssangam",
    "gn:country_code":"KR",
    "gn:dem":305,
    "gn:feature_class":"P",
    "gn:feature_code":"PPL",
    "gn:name":"Ssangam",
    "gn:population":0,
    "gn:timezone":"Asia/Seoul",
    "iso:country":"KR",
    "name:und_x_variant":[
        "Sanam-ni",
        "Ssangam-ni",
        "\uc30d\uc554",
        "Ssangam"
    ],
    "wof:name":"Ssangam",
    "wof:placetype":"locality"
},
  "geometry": {"coordinates":[127.54599,35.78258],"type":"Point"}
}