{
  "type": "Feature",
  "properties": {
    "gn:admin1_code":"12.0",
    "gn:admin2_code":"Kanghwa-gun",
    "gn:asciiname":"Darimok",
    "gn:country_code":"KR",
    "gn:dem":16,
    "gn:feature_class":"P",
    "gn:feature_code":"PPL",
    "gn:name":"Darimok",
    "gn:population":0,
    "gn:timezone":"Asia/Seoul",
    "iso:country":"KR",
    "name:kor_x_preferred":[
        "\ub2e4\ub9ac\ubaa9"
    ],
    "name:und_x_variant":[
        "Tarimok"
    ],
    "wof:name":"Darimok",
    "wof:placetype":"locality"
},
  "geometry": {"coordinates":[126.39411,37.80596],"type":"Point"}
}