{
  "type": "Feature",
  "properties": {
    "gn:admin1_code":"3.0",
    "gn:asciiname":"Kungp'yong",
    "gn:country_code":"KR",
    "gn:dem":29,
    "gn:feature_class":"P",
    "gn:feature_code":"PPL",
    "gn:name":"Kungp\u2019y\u014fng",
    "gn:population":0,
    "gn:timezone":"Asia/Seoul",
    "iso:country":"KR",
    "name:und_x_variant":[
        "Kungp\u2019y\u014fng-ni",
        "\uad81\ud3c9",
        "Kungp\u2019y\u014fng"
    ],
    "wof:name":"Kungp'yong",
    "wof:placetype":"locality"
},
  "geometry": {"coordinates":[127.06968999999999,35.97398],"type":"Point"}
}