{
  "type": "Feature",
  "properties": {
    "gn:admin1_code":"13.0",
    "gn:asciiname":"Samongni",
    "gn:country_code":"KR",
    "gn:dem":15,
    "gn:feature_class":"P",
    "gn:feature_code":"PPL",
    "gn:name":"Samongni",
    "gn:population":0,
    "gn:timezone":"Asia/Seoul",
    "iso:country":"KR",
    "name:kor_x_preferred":[
        "\uc0ac\ubaa9\ub9ac"
    ],
    "wof:name":"Samongni",
    "wof:placetype":"locality"
},
  "geometry": {"coordinates":[126.75573,37.87094],"type":"Point"}
}