{
  "type": "Feature",
  "properties": {
    "gn:admin1_code":"14.0",
    "gn:asciiname":"Sopchae",
    "gn:country_code":"KR",
    "gn:dem":478,
    "gn:feature_class":"P",
    "gn:feature_code":"PPL",
    "gn:name":"S\u014fpchae",
    "gn:population":0,
    "gn:timezone":"Asia/Seoul",
    "iso:country":"KR",
    "name:und_x_variant":[
        "\uc12d\uc7ac",
        "S\u014fpchae"
    ],
    "wof:name":"Sopchae",
    "wof:placetype":"locality"
},
  "geometry": {"coordinates":[129.05260000000001,37.0425],"type":"Point"}
}