{
  "type": "Feature",
  "properties": {
    "gn:admin1_code":"5.0",
    "gn:asciiname":"Changam-ni",
    "gn:country_code":"KR",
    "gn:dem":327,
    "gn:feature_class":"P",
    "gn:feature_code":"PPL",
    "gn:name":"Changam-ni",
    "gn:population":0,
    "gn:timezone":"Asia/Seoul",
    "iso:country":"KR",
    "wof:name":"Changam-ni",
    "wof:placetype":"locality"
},
  "geometry": {"coordinates":[127.70999999999999,36.77056],"type":"Point"}
}