{
  "type": "Feature",
  "properties": {
    "gn:admin1_code":"20.0",
    "gn:asciiname":"Nonarae",
    "gn:country_code":"KR",
    "gn:dem":55,
    "gn:feature_class":"P",
    "gn:feature_code":"PPL",
    "gn:name":"Nonarae",
    "gn:population":0,
    "gn:timezone":"Asia/Seoul",
    "iso:country":"KR",
    "name:und_x_variant":[
        "\ub17c\uc544\ub798",
        "Nonarae"
    ],
    "wof:name":"Nonarae",
    "wof:placetype":"locality"
},
  "geometry": {"coordinates":[128.29199,34.9261],"type":"Point"}
}