{
  "type": "Feature",
  "properties": {
    "gn:admin1_code":"17.0",
    "gn:asciiname":"Huial-li",
    "gn:country_code":"KR",
    "gn:dem":36,
    "gn:feature_class":"P",
    "gn:feature_code":"PPL",
    "gn:name":"H\u016dial-li",
    "gn:population":0,
    "gn:timezone":"Asia/Seoul",
    "iso:country":"KR",
    "name:und_x_variant":[
        "\ud76c\uc548\ub9ac",
        "H\u016dial-li"
    ],
    "wof:name":"Huial-li",
    "wof:placetype":"locality"
},
  "geometry": {"coordinates":[126.98139999999999,36.7693],"type":"Point"}
}