{
  "type": "Feature",
  "properties": {
    "gn:admin1_code":"11.0",
    "gn:asciiname":"Yeogiso",
    "gn:country_code":"KR",
    "gn:dem":45,
    "gn:feature_class":"P",
    "gn:feature_code":"PPL",
    "gn:name":"Yeogiso",
    "gn:population":0,
    "gn:timezone":"Asia/Seoul",
    "iso:country":"KR",
    "name:und_x_variant":[
        "\uc5ec\uae30\uc18c",
        "Y\u014fgiso",
        "Yeogiso"
    ],
    "wof:name":"Yeogiso",
    "wof:placetype":"locality"
},
  "geometry": {"coordinates":[126.93988,37.65365],"type":"Point"}
}