{
  "type": "Feature",
  "properties": {
    "gn:admin1_code":"20.0",
    "gn:asciiname":"Yeongjunggol",
    "gn:country_code":"KR",
    "gn:dem":34,
    "gn:feature_class":"P",
    "gn:feature_code":"PPL",
    "gn:name":"Yeongjunggol",
    "gn:population":0,
    "gn:timezone":"Asia/Seoul",
    "iso:country":"KR",
    "name:kor_x_preferred":[
        "\uc601\uc911\uace8"
    ],
    "wof:name":"Yeongjunggol",
    "wof:placetype":"locality"
},
  "geometry": {"coordinates":[128.49421000000001,35.56595],"type":"Point"}
}