{
  "type": "Feature",
  "properties": {
    "gn:admin1_code":"14.0",
    "gn:asciiname":"Samgye",
    "gn:country_code":"KR",
    "gn:dem":423,
    "gn:feature_class":"P",
    "gn:feature_code":"PPL",
    "gn:name":"Samgye",
    "gn:population":0,
    "gn:timezone":"Asia/Seoul",
    "iso:country":"KR",
    "name:und_x_variant":[
        "\uc0bc\uacc4",
        "Samgye"
    ],
    "wof:name":"Samgye",
    "wof:placetype":"locality"
},
  "geometry": {"coordinates":[129.20310000000001,36.7427],"type":"Point"}
}