{
  "type": "Feature",
  "properties": {
    "gn:admin1_code":"14.0",
    "gn:asciiname":"Yetchangt'o",
    "gn:country_code":"KR",
    "gn:dem":204,
    "gn:feature_class":"P",
    "gn:feature_code":"PPL",
    "gn:name":"Yetchangt\u2019\u014f",
    "gn:population":0,
    "gn:timezone":"Asia/Seoul",
    "iso:country":"KR",
    "name:und_x_variant":[
        "\uc61b\uc7a5\ud130",
        "Yetchangt\u2019\u014f"
    ],
    "wof:name":"Yetchangt'o",
    "wof:placetype":"locality"
},
  "geometry": {"coordinates":[129.11420000000001,36.5603],"type":"Point"}
}