{
  "type": "Feature",
  "properties": {
    "gn:admin1_code":"20.0",
    "gn:asciiname":"Changch'ol-li",
    "gn:country_code":"KR",
    "gn:dem":26,
    "gn:feature_class":"P",
    "gn:feature_code":"PPL",
    "gn:name":"Changch\u2019\u014fl-li",
    "gn:population":0,
    "gn:timezone":"Asia/Seoul",
    "iso:country":"KR",
    "name:und_x_variant":[
        "\uc7a5\ucc9c\ub9ac",
        "Changch\u2019\u014fl-li"
    ],
    "wof:name":"Changch'ol-li",
    "wof:placetype":"locality"
},
  "geometry": {"coordinates":[128.37938,35.60225],"type":"Point"}
}