{
  "type": "Feature",
  "properties": {
    "gn:admin1_code":"17.0",
    "gn:asciiname":"Jeongdalli",
    "gn:country_code":"KR",
    "gn:dem":192,
    "gn:feature_class":"P",
    "gn:feature_code":"PPL",
    "gn:name":"Jeongdalli",
    "gn:population":0,
    "gn:timezone":"Asia/Seoul",
    "iso:country":"KR",
    "name:kor_x_preferred":[
        "\uc7a5\ub2e8\ub9ac"
    ],
    "wof:name":"Jeongdalli",
    "wof:placetype":"locality"
},
  "geometry": {"coordinates":[127.05488,36.66069],"type":"Point"}
}