{
  "type": "Feature",
  "properties": {
    "gn:admin1_code":"14.0",
    "gn:asciiname":"Saengdal",
    "gn:country_code":"KR",
    "gn:dem":419,
    "gn:feature_class":"P",
    "gn:feature_code":"PPL",
    "gn:name":"Saengdal",
    "gn:population":0,
    "gn:timezone":"Asia/Seoul",
    "iso:country":"KR",
    "name:kor_x_preferred":[
        "\uc0dd\ub2ec"
    ],
    "name:und_x_variant":[
        "S\u014fndal",
        "Saengdal"
    ],
    "wof:name":"Saengdal",
    "wof:placetype":"locality"
},
  "geometry": {"coordinates":[128.72794999999999,37.01326],"type":"Point"}
}