{
  "type": "Feature",
  "properties": {
    "gn:admin1_code":"14.0",
    "gn:asciiname":"Saejimnae",
    "gn:country_code":"KR",
    "gn:dem":82,
    "gn:feature_class":"P",
    "gn:feature_code":"PPL",
    "gn:name":"Saejimnae",
    "gn:population":0,
    "gn:timezone":"Asia/Seoul",
    "iso:country":"KR",
    "name:kor_x_preferred":[
        "\uc0c8\uc9d1\ub0b4"
    ],
    "wof:name":"Saejimnae",
    "wof:placetype":"locality"
},
  "geometry": {"coordinates":[128.19731999999999,36.57595],"type":"Point"}
}