{
  "type": "Feature",
  "properties": {
    "gn:admin1_code":"20.0",
    "gn:asciiname":"Moan",
    "gn:country_code":"KR",
    "gn:dem":29,
    "gn:feature_class":"P",
    "gn:feature_code":"PPL",
    "gn:name":"Moan",
    "gn:population":0,
    "gn:timezone":"Asia/Seoul",
    "iso:country":"KR",
    "name:und_x_variant":[
        "\ubaa8\uc548",
        "Moan"
    ],
    "wof:name":"Moan",
    "wof:placetype":"locality"
},
  "geometry": {"coordinates":[128.20913000000002,35.58597],"type":"Point"}
}