{
  "type": "Feature",
  "properties": {
    "gn:admin1_code":"17.0",
    "gn:asciiname":"Samjun",
    "gn:country_code":"KR",
    "gn:dem":101,
    "gn:feature_class":"P",
    "gn:feature_code":"PPL",
    "gn:name":"Samjun",
    "gn:population":0,
    "gn:timezone":"Asia/Seoul",
    "iso:country":"KR",
    "name:und_x_variant":[
        "\uc0bc\uc900",
        "Samjun"
    ],
    "wof:name":"Samjun",
    "wof:placetype":"locality"
},
  "geometry": {"coordinates":[126.58369999999999,36.6398],"type":"Point"}
}