{
  "type": "Feature",
  "properties": {
    "gn:admin1_code":"6.0",
    "gn:asciiname":"Chung-ch'on",
    "gn:country_code":"KR",
    "gn:dem":693,
    "gn:feature_class":"P",
    "gn:feature_code":"PPL",
    "gn:name":"Chung-ch\u2019on",
    "gn:population":0,
    "gn:timezone":"Asia/Seoul",
    "iso:country":"KR",
    "name:kor_x_preferred":[
        "\uc911\ucd0c"
    ],
    "name:kor_x_variant":[
        "Chung-ch\u2019on"
    ],
    "wof:name":"Chung-ch'on",
    "wof:placetype":"locality"
},
  "geometry": {"coordinates":[128.88390000000001,37.3065],"type":"Point"}
}