{
  "type": "Feature",
  "properties": {
    "gn:admin1_code":"14.0",
    "gn:asciiname":"Iro-ri",
    "gn:country_code":"KR",
    "gn:dem":103,
    "gn:feature_class":"P",
    "gn:feature_code":"PPL",
    "gn:name":"Iro-ri",
    "gn:population":0,
    "gn:timezone":"Asia/Seoul",
    "iso:country":"KR",
    "name:und_x_variant":[
        "\uc774\ub85c\ub9ac",
        "Iro-ri"
    ],
    "wof:name":"Iro-ri",
    "wof:placetype":"locality"
},
  "geometry": {"coordinates":[128.06104999999999,36.12262],"type":"Point"}
}