{
  "type": "Feature",
  "properties": {
    "gn:admin1_code":"17.0",
    "gn:asciiname":"Eoryong",
    "gn:country_code":"KR",
    "gn:dem":24,
    "gn:feature_class":"P",
    "gn:feature_code":"PPL",
    "gn:name":"Eoryong",
    "gn:population":0,
    "gn:timezone":"Asia/Seoul",
    "iso:country":"KR",
    "name:kor_x_preferred":[
        "\uc5b4\ub8e1"
    ],
    "name:und_x_variant":[
        "\uc5b4\ub8e1\ub9ac",
        "\u014eryong-ni",
        "Eoryong"
    ],
    "wof:name":"Eoryong",
    "wof:placetype":"locality"
},
  "geometry": {"coordinates":[127.12305000000001,36.93964],"type":"Point"}
}