{
  "type": "Feature",
  "properties": {
    "gn:admin1_code":"5.0",
    "gn:asciiname":"Gullyanggol",
    "gn:country_code":"KR",
    "gn:dem":68,
    "gn:feature_class":"P",
    "gn:feature_code":"PPL",
    "gn:name":"Gullyanggol",
    "gn:population":0,
    "gn:timezone":"Asia/Seoul",
    "iso:country":"KR",
    "name:kor_x_preferred":[
        "\uad70\ub7c9\uace8"
    ],
    "wof:name":"Gullyanggol",
    "wof:placetype":"locality"
},
  "geometry": {"coordinates":[127.52594000000001,36.71282],"type":"Point"}
}