{
  "type": "Feature",
  "properties": {
    "gn:admin1_code":"6.0",
    "gn:asciiname":"Saejaegol",
    "gn:country_code":"KR",
    "gn:dem":296,
    "gn:feature_class":"P",
    "gn:feature_code":"PPL",
    "gn:name":"Saejaegol",
    "gn:population":0,
    "gn:timezone":"Asia/Seoul",
    "iso:country":"KR",
    "name:kor_x_preferred":[
        "\uc0c8\uc7ac\uace8"
    ],
    "wof:name":"Saejaegol",
    "wof:placetype":"locality"
},
  "geometry": {"coordinates":[128.08068,37.95916],"type":"Point"}
}