{
  "type": "Feature",
  "properties": {
    "gn:admin1_code":"6.0",
    "gn:asciiname":"Tolt'omi",
    "gn:country_code":"KR",
    "gn:dem":259,
    "gn:feature_class":"P",
    "gn:feature_code":"PPL",
    "gn:name":"Tolt\u2019\u014fmi",
    "gn:population":0,
    "gn:timezone":"Asia/Seoul",
    "iso:country":"KR",
    "name:kor_x_preferred":[
        "\ub3cc\ud130\ubbf8"
    ],
    "name:kor_x_variant":[
        "Tolt\u2019\u014fmi"
    ],
    "wof:name":"Tolt'omi",
    "wof:placetype":"locality"
},
  "geometry": {"coordinates":[128.37289999999999,37.2432],"type":"Point"}
}