{
  "type": "Feature",
  "properties": {
    "gn:admin1_code":"5.0",
    "gn:asciiname":"Kurosimi",
    "gn:country_code":"KR",
    "gn:dem":197,
    "gn:feature_class":"P",
    "gn:feature_code":"PPL",
    "gn:name":"K\u016dr\u014fsimi",
    "gn:population":0,
    "gn:timezone":"Asia/Seoul",
    "iso:country":"KR",
    "name:kor_x_preferred":[
        "\uadf8\ub7ec\uc2ec\uc774"
    ],
    "name:kor_x_variant":[
        "K\u016dr\u014fsimi"
    ],
    "wof:name":"Kurosimi",
    "wof:placetype":"locality"
},
  "geometry": {"coordinates":[128.42439999999999,37.0895],"type":"Point"}
}