{
  "type": "Feature",
  "properties": {
    "gn:admin1_code":"5.0",
    "gn:asciiname":"Sanso",
    "gn:country_code":"KR",
    "gn:dem":104,
    "gn:feature_class":"P",
    "gn:feature_code":"PPL",
    "gn:name":"Sans\u014f",
    "gn:population":0,
    "gn:timezone":"Asia/Seoul",
    "iso:country":"KR",
    "name:fin_x_preferred":[
        "Sanso"
    ],
    "name:fra_x_preferred":[
        "Sanso"
    ],
    "name:ita_x_preferred":[
        "Sanso"
    ],
    "name:nld_x_preferred":[
        "Sanso"
    ],
    "name:spa_x_preferred":[
        "Sanso"
    ],
    "name:und_x_variant":[
        "\uc0b0\uc11c",
        "Sans\u014f"
    ],
    "wof:name":"Sanso",
    "wof:placetype":"locality"
},
  "geometry": {"coordinates":[127.5265,36.4561],"type":"Point"}
}