{
  "type": "Feature",
  "properties": {
    "gn:admin1_code":"13.0",
    "gn:asciiname":"Jangan",
    "gn:country_code":"KR",
    "gn:dem":58,
    "gn:feature_class":"P",
    "gn:feature_code":"PPL",
    "gn:name":"Jangan",
    "gn:population":0,
    "gn:timezone":"Asia/Seoul",
    "iso:country":"KR",
    "name:und_x_variant":[
        "\uc7a5\uc548",
        "Jangan",
        "Changan"
    ],
    "wof:name":"Jangan",
    "wof:placetype":"locality"
},
  "geometry": {"coordinates":[127.07812,37.05854],"type":"Point"}
}