{
  "type": "Feature",
  "properties": {
    "gn:admin1_code":"14.0",
    "gn:asciiname":"Nongjangdong",
    "gn:country_code":"KR",
    "gn:dem":33,
    "gn:feature_class":"P",
    "gn:feature_code":"PPL",
    "gn:name":"Nongjangdong",
    "gn:population":0,
    "gn:timezone":"Asia/Seoul",
    "iso:country":"KR",
    "name:kor_x_preferred":[
        "\ub18d\uc7a5\ub3d9"
    ],
    "wof:name":"Nongjangdong",
    "wof:placetype":"locality"
},
  "geometry": {"coordinates":[129.43216000000001,35.9814],"type":"Point"}
}