{
  "type": "Feature",
  "properties": {
    "gn:admin1_code":"14.0",
    "gn:asciiname":"Uisan",
    "gn:country_code":"KR",
    "gn:dem":247,
    "gn:feature_class":"P",
    "gn:feature_code":"PPL",
    "gn:name":"Uisan",
    "gn:population":0,
    "gn:timezone":"Asia/Seoul",
    "iso:country":"KR",
    "name:kor_x_preferred":[
        "\uc758\uc0b0"
    ],
    "wof:name":"Uisan",
    "wof:placetype":"locality"
},
  "geometry": {"coordinates":[128.52553999999998,36.77115],"type":"Point"}
}