{
  "type": "Feature",
  "properties": {
    "gn:admin1_code":"11.0",
    "gn:asciiname":"Pulgwangi-dong",
    "gn:country_code":"KR",
    "gn:dem":54,
    "gn:feature_class":"P",
    "gn:feature_code":"PPL",
    "gn:name":"Pulgwangi-dong",
    "gn:population":0,
    "gn:timezone":"Asia/Seoul",
    "iso:country":"KR",
    "name:und_x_variant":[
        "\ubd88\uad112\ub3d9",
        "Pulgwangi-dong"
    ],
    "wof:name":"Pulgwangi-dong",
    "wof:placetype":"locality"
},
  "geometry": {"coordinates":[126.93109,37.62146],"type":"Point"}
}