{
  "type": "Feature",
  "properties": {
    "gn:admin1_code":"6.0",
    "gn:asciiname":"Ko-ch'on",
    "gn:country_code":"KR",
    "gn:dem":133,
    "gn:feature_class":"P",
    "gn:feature_code":"PPL",
    "gn:name":"Ko-ch\u2019on",
    "gn:population":0,
    "gn:timezone":"Asia/Seoul",
    "iso:country":"KR",
    "name:kor_x_preferred":[
        "\uace0\ucd0c"
    ],
    "name:kor_x_variant":[
        "Ko-ch\u2019on"
    ],
    "wof:name":"Ko-ch'on",
    "wof:placetype":"locality"
},
  "geometry": {"coordinates":[127.97669999999999,37.4206],"type":"Point"}
}