{
  "type": "Feature",
  "properties": {
    "gn:admin1_code":"18.0",
    "gn:asciiname":"Guryong",
    "gn:country_code":"KR",
    "gn:dem":70,
    "gn:feature_class":"P",
    "gn:feature_code":"PPL",
    "gn:name":"Guryong",
    "gn:population":0,
    "gn:timezone":"Asia/Seoul",
    "iso:country":"KR",
    "name:kor_x_preferred":[
        "\uad6c\ub8e1"
    ],
    "wof:name":"Guryong",
    "wof:placetype":"locality"
},
  "geometry": {"coordinates":[126.69356999999999,35.20576],"type":"Point"}
}