{
  "type": "Feature",
  "properties": {
    "iso:country":"KR",
    "qs:name":"\ud30c\ub3d9",
    "qs:name_adm0":"\ud55c\uad6d",
    "qs:name_adm1":"\ub300\uad6c",
    "qs:photos":1,
    "qs:photos_1k":1,
    "qs:photos_9k":1,
    "qs:photos_9r":1,
    "qs:photos_all":1,
    "qs:photos_sr":1,
    "qs:placetype":"Suburb",
    "qs:pop_sr":"0",
    "wof:name":"\ud30c\ub3d9",
    "wof:placetype":"neighbourhood"
},
  "geometry": {"coordinates":[128.58472,35.08361],"type":"Point"}
}