{
  "type": "Feature",
  "properties": {
    "gn:admin1_code":"16.0",
    "gn:asciiname":"Chinmok",
    "gn:country_code":"KR",
    "gn:dem":45,
    "gn:feature_class":"P",
    "gn:feature_code":"PPL",
    "gn:name":"Chinmok",
    "gn:population":0,
    "gn:timezone":"Asia/Seoul",
    "iso:country":"KR",
    "name:kor_x_preferred":[
        "\uc9c4\ubaa9"
    ],
    "name:und_x_variant":[
        "Shimboku-ri",
        "Chinmong-ni",
        "Chinmok"
    ],
    "wof:name":"Chinmok",
    "wof:placetype":"locality"
},
  "geometry": {"coordinates":[126.92028000000001,34.47306],"type":"Point"}
}