{
  "type": "Feature",
  "properties": {
    "gn:admin1_code":"6.0",
    "gn:asciiname":"Utdumuri",
    "gn:country_code":"KR",
    "gn:dem":307,
    "gn:feature_class":"P",
    "gn:feature_code":"PPL",
    "gn:name":"Utdumuri",
    "gn:population":0,
    "gn:timezone":"Asia/Seoul",
    "iso:country":"KR",
    "name:kor_x_preferred":[
        "\uc717\ub450\ubb34\ub9ac"
    ],
    "name:kor_x_variant":[
        "Wit\u2019tumu-ri",
        "\uc6c3\ub450\ubb34\ub9ac"
    ],
    "name:und_x_variant":[
        "Witdumu-ri",
        "Utdumuri",
        "Wittumu-ri"
    ],
    "wof:name":"Utdumuri",
    "wof:placetype":"locality"
},
  "geometry": {"coordinates":[128.07516000000001,38.05629],"type":"Point"}
}