{
  "type": "Feature",
  "properties": {
    "gn:admin1_code":"6.0",
    "gn:asciiname":"Turi-gol",
    "gn:country_code":"KR",
    "gn:dem":592,
    "gn:feature_class":"P",
    "gn:feature_code":"PPL",
    "gn:name":"Turi-gol",
    "gn:population":0,
    "gn:timezone":"Asia/Seoul",
    "iso:country":"KR",
    "name:kor_x_preferred":[
        "\ub450\ub9ac\uace8"
    ],
    "wof:name":"Turi-gol",
    "wof:placetype":"locality"
},
  "geometry": {"coordinates":[128.67410000000001,37.2432],"type":"Point"}
}