{
  "type": "Feature",
  "properties": {
    "gn:admin1_code":"6.0",
    "gn:asciiname":"Malmudomi",
    "gn:country_code":"KR",
    "gn:dem":454,
    "gn:feature_class":"P",
    "gn:feature_code":"PPL",
    "gn:name":"Malmud\u014fmi",
    "gn:population":0,
    "gn:timezone":"Asia/Seoul",
    "iso:country":"KR",
    "name:kor_x_preferred":[
        "\ub9d0\ubb34\ub364\uc774"
    ],
    "name:kor_x_variant":[
        "Malmud\u014fmi"
    ],
    "wof:name":"Malmudomi",
    "wof:placetype":"locality"
},
  "geometry": {"coordinates":[128.15430000000001,37.4201],"type":"Point"}
}