{
  "type": "Feature",
  "properties": {
    "gn:admin1_code":"13.0",
    "gn:asciiname":"Beoreum",
    "gn:country_code":"KR",
    "gn:dem":35,
    "gn:feature_class":"P",
    "gn:feature_code":"PPL",
    "gn:name":"Beoreum",
    "gn:population":0,
    "gn:timezone":"Asia/Seoul",
    "iso:country":"KR",
    "name:und_x_variant":[
        "\ubc8c\uc74c",
        "Beoreum",
        "P\u014fr\u016dm"
    ],
    "wof:name":"Beoreum",
    "wof:placetype":"locality"
},
  "geometry": {"coordinates":[127.03888999999999,37.13917],"type":"Point"}
}