{
  "type": "Feature",
  "properties": {
    "gn:admin1_code":"13.0",
    "gn:asciiname":"Dodeokdong",
    "gn:country_code":"KR",
    "gn:dem":100,
    "gn:feature_class":"P",
    "gn:feature_code":"PPL",
    "gn:name":"Dodeokdong",
    "gn:population":0,
    "gn:timezone":"Asia/Seoul",
    "iso:country":"KR",
    "name:und_x_variant":[
        "\ub3c4\ub355\ub3d9",
        "Tod\u014fk-tong",
        "Dodeokdong"
    ],
    "wof:name":"Dodeokdong",
    "wof:placetype":"locality"
},
  "geometry": {"coordinates":[127.06010000000001,37.80684],"type":"Point"}
}