{
  "type": "Feature",
  "properties": {
    "gn:admin1_code":"17.0",
    "gn:asciiname":"Kojan",
    "gn:country_code":"KR",
    "gn:dem":13,
    "gn:feature_class":"P",
    "gn:feature_code":"PPL",
    "gn:name":"Kojan",
    "gn:population":0,
    "gn:timezone":"Asia/Seoul",
    "iso:country":"KR",
    "name:und_x_variant":[
        "\uace0\uc794",
        "Kojan"
    ],
    "wof:name":"Kojan",
    "wof:placetype":"locality"
},
  "geometry": {"coordinates":[126.7449,36.9715],"type":"Point"}
}