{
  "type": "Feature",
  "properties": {
    "gn:admin1_code":"13.0",
    "gn:asciiname":"Jeommal",
    "gn:country_code":"KR",
    "gn:dem":100,
    "gn:feature_class":"P",
    "gn:feature_code":"PPL",
    "gn:name":"Jeommal",
    "gn:population":0,
    "gn:timezone":"Asia/Seoul",
    "iso:country":"KR",
    "name:kor_x_preferred":[
        "\uc810\ub9d0"
    ],
    "name:kor_x_variant":[
        "Ch\u014fm-mal"
    ],
    "wof:name":"Jeommal",
    "wof:placetype":"locality"
},
  "geometry": {"coordinates":[127.51949,37.07279000000001],"type":"Point"}
}