{
  "type": "Feature",
  "properties": {
    "gn:admin1_code":"13.0",
    "gn:admin2_code":"P'aju-si",
    "gn:asciiname":"Yangjidong",
    "gn:country_code":"KR",
    "gn:dem":13,
    "gn:feature_class":"P",
    "gn:feature_code":"PPL",
    "gn:name":"Yangjidong",
    "gn:population":0,
    "gn:timezone":"Asia/Seoul",
    "iso:country":"KR",
    "name:kor_x_preferred":[
        "Yangji-ma\u016dl"
    ],
    "name:kor_x_variant":[
        "\uc591\uc9c0\ub3d9"
    ],
    "name:und_x_variant":[
        "Yangji-ma\u016dl",
        "Yangjidong"
    ],
    "wof:name":"Yangjidong",
    "wof:placetype":"locality"
},
  "geometry": {"coordinates":[126.68850999999999,37.81567],"type":"Point"}
}