{
  "type": "Feature",
  "properties": {
    "iso:country":"KR",
    "name:eng_x_preferred":[
        "Songwol-dong"
    ],
    "name:kor_x_preferred":[
        "\uc1a1\uc6d4\ub3d9"
    ],
    "name:kor_x_variant":[
        "\uc1a1\uc6d4\ub3d9"
    ],
    "qs:gn_adm0_cc":"KR",
    "qs:gn_local":1843564,
    "qs:local_max":2394,
    "qs:local_sum":10431,
    "qs:localhoods":47,
    "qs:name":"\uc1a1\uc6d4\ub3d9",
    "qs:name_adm0":"\ud55c\uad6d",
    "qs:name_adm1":"\uc778\ucc9c",
    "qs:name_adm2":"\uc911\uad6c",
    "qs:name_lau":"\uc1a1\uc6d4\ub3d9",
    "qs:name_local":"\uc778\ucc9c",
    "qs:photo_max":115,
    "qs:photo_sum":400,
    "qs:placetype":"Suburb",
    "qs:quad_count":13,
    "qs:woe_adm0":23424868,
    "qs:woe_adm1":20069922,
    "qs:woe_adm2":28289230,
    "qs:woe_lau":28806308,
    "qs:woe_local":1132496,
    "qs:woe_ver":"7.10.0",
    "wof:lang":[
        "kor"
    ],
    "wof:name":"Songwol-dong",
    "wof:placetype":"neighbourhood"
},
  "geometry": {"coordinates":[126.62018500000001,37.476031],"type":"Point"}
}