{
  "type": "Feature",
  "properties": {
    "gn:admin1_code":"3.0",
    "gn:asciiname":"Unamsan",
    "gn:country_code":"KR",
    "gn:dem":135,
    "gn:feature_class":"P",
    "gn:feature_code":"PPL",
    "gn:name":"Unamsan",
    "gn:population":0,
    "gn:timezone":"Asia/Seoul",
    "iso:country":"KR",
    "name:und_x_variant":[
        "\uc6b4\uc554\uc0b0",
        "Unamsan"
    ],
    "wof:name":"Unamsan",
    "wof:placetype":"locality"
},
  "geometry": {"coordinates":[127.27334,35.98329000000001],"type":"Point"}
}