{
  "type": "Feature",
  "properties": {
    "gn:admin1_code":"5.0",
    "gn:asciiname":"Hakgyomal",
    "gn:country_code":"KR",
    "gn:dem":59,
    "gn:feature_class":"P",
    "gn:feature_code":"PPL",
    "gn:name":"Hakgyomal",
    "gn:population":0,
    "gn:timezone":"Asia/Seoul",
    "iso:country":"KR",
    "name:kor_x_preferred":[
        "\ud559\uad50\ub9d0"
    ],
    "name:und_x_variant":[
        "Hakkyo-mal"
    ],
    "wof:name":"Hakgyomal",
    "wof:placetype":"locality"
},
  "geometry": {"coordinates":[127.75062,37.16086],"type":"Point"}
}