{
  "type": "Feature",
  "properties": {
    "gn:admin1_code":"6.0",
    "gn:asciiname":"Pangch'ungmaegi",
    "gn:country_code":"KR",
    "gn:dem":343,
    "gn:feature_class":"P",
    "gn:feature_code":"PPL",
    "gn:name":"Pangch\u2019ungmaegi",
    "gn:population":0,
    "gn:timezone":"Asia/Seoul",
    "iso:country":"KR",
    "name:kor_x_preferred":[
        "\ubc29\ucd95\ub9e5\uc774"
    ],
    "name:kor_x_variant":[
        "Pangch\u2019ungmaegi"
    ],
    "wof:name":"Pangch'ungmaegi",
    "wof:placetype":"locality"
},
  "geometry": {"coordinates":[128.35990000000001,37.3982],"type":"Point"}
}