{
  "type": "Feature",
  "properties": {
    "gn:admin1_code":"5.0",
    "gn:asciiname":"Duryeon",
    "gn:country_code":"KR",
    "gn:dem":84,
    "gn:feature_class":"P",
    "gn:feature_code":"PPL",
    "gn:name":"Duryeon",
    "gn:population":0,
    "gn:timezone":"Asia/Seoul",
    "iso:country":"KR",
    "name:kor_x_preferred":[
        "\ub450\ub828"
    ],
    "name:kor_x_variant":[
        "Tury\u014fn"
    ],
    "wof:name":"Duryeon",
    "wof:placetype":"locality"
},
  "geometry": {"coordinates":[127.85992,37.01123],"type":"Point"}
}