{
  "type": "Feature",
  "properties": {
    "gn:admin1_code":"5.0",
    "gn:asciiname":"Geoneomal",
    "gn:country_code":"KR",
    "gn:dem":285,
    "gn:feature_class":"P",
    "gn:feature_code":"PPL",
    "gn:name":"Geoneomal",
    "gn:population":0,
    "gn:timezone":"Asia/Seoul",
    "iso:country":"KR",
    "name:kor_x_preferred":[
        "\uac74\ub108\ub9d0"
    ],
    "wof:name":"Geoneomal",
    "wof:placetype":"locality"
},
  "geometry": {"coordinates":[127.70568,36.77248],"type":"Point"}
}