{
  "type": "Feature",
  "properties": {
    "gn:admin1_code":"17.0",
    "gn:asciiname":"Wanp'o-ri",
    "gn:country_code":"KR",
    "gn:dem":3,
    "gn:feature_class":"P",
    "gn:feature_code":"PPL",
    "gn:name":"Wanp\u2019o-ri",
    "gn:population":0,
    "gn:timezone":"Asia/Seoul",
    "iso:country":"KR",
    "wof:name":"Wanp'o-ri",
    "wof:placetype":"locality"
},
  "geometry": {"coordinates":[126.81667,36.05],"type":"Point"}
}