{
  "type": "Feature",
  "properties": {
    "gn:admin1_code":"13.0",
    "gn:asciiname":"Twikkol",
    "gn:country_code":"KR",
    "gn:dem":22,
    "gn:feature_class":"P",
    "gn:feature_code":"PPL",
    "gn:name":"Twikkol",
    "gn:population":0,
    "gn:timezone":"Asia/Seoul",
    "iso:country":"KR",
    "name:kor_x_preferred":[
        "\ub4b7\uace8"
    ],
    "wof:name":"Twikkol",
    "wof:placetype":"locality"
},
  "geometry": {"coordinates":[126.71333,37.225],"type":"Point"}
}