{
  "type": "Feature",
  "properties": {
    "gn:admin1_code":"14.0",
    "gn:asciiname":"Samgoejeong",
    "gn:country_code":"KR",
    "gn:dem":287,
    "gn:feature_class":"P",
    "gn:feature_code":"PPL",
    "gn:name":"Samgoejeong",
    "gn:population":0,
    "gn:timezone":"Asia/Seoul",
    "iso:country":"KR",
    "name:kor_x_preferred":[
        "\uc0bc\uad34\uc815"
    ],
    "wof:name":"Samgoejeong",
    "wof:placetype":"locality"
},
  "geometry": {"coordinates":[128.55615,36.93248],"type":"Point"}
}