{
  "type": "Feature",
  "properties": {
    "gn:admin1_code":"13.0",
    "gn:admin2_code":"Yongin-si",
    "gn:asciiname":"Yonghaegok",
    "gn:country_code":"KR",
    "gn:dem":184,
    "gn:feature_class":"P",
    "gn:feature_code":"PPL",
    "gn:name":"Yonghaegok",
    "gn:population":0,
    "gn:timezone":"Asia/Seoul",
    "iso:country":"KR",
    "name:kor_x_preferred":[
        "\uc6a9\ud574\uace1"
    ],
    "name:und_x_variant":[
        "Haegong-ni",
        "Yonghaeguk",
        "Yonghaegok"
    ],
    "wof:name":"Yonghaegok",
    "wof:placetype":"locality"
},
  "geometry": {"coordinates":[127.26972000000001,37.17833],"type":"Point"}
}