{
  "type": "Feature",
  "properties": {
    "gn:admin1_code":"16.0",
    "gn:asciiname":"Saetaegol",
    "gn:country_code":"KR",
    "gn:dem":29,
    "gn:feature_class":"P",
    "gn:feature_code":"PPL",
    "gn:name":"Saetaegol",
    "gn:population":0,
    "gn:timezone":"Asia/Seoul",
    "iso:country":"KR",
    "name:kor_x_preferred":[
        "\uc0c8\ud0dc\uace8"
    ],
    "wof:name":"Saetaegol",
    "wof:placetype":"locality"
},
  "geometry": {"coordinates":[126.71259000000001,35.06549],"type":"Point"}
}