{
  "type": "Feature",
  "properties": {
    "gn:admin1_code":"6.0",
    "gn:asciiname":"Kamjagok",
    "gn:cc2":"KR",
    "gn:country_code":"KR",
    "gn:dem":225,
    "gn:feature_class":"P",
    "gn:feature_code":"PPL",
    "gn:name":"Kamjagok",
    "gn:population":0,
    "gn:timezone":"Asia/Seoul",
    "iso:country":"KR",
    "name:und_x_variant":[
        "Kamjagol",
        "Kamjagok"
    ],
    "wof:name":"Kamjagok",
    "wof:placetype":"locality"
},
  "geometry": {"coordinates":[129.05000000000001,37.51667],"type":"Point"}
}