{
  "type": "Feature",
  "properties": {
    "gn:admin1_code":"13.0",
    "gn:asciiname":"Sinneung-dong",
    "gn:country_code":"KR",
    "gn:dem":56,
    "gn:feature_class":"P",
    "gn:feature_code":"PPL",
    "gn:name":"Sinneung-dong",
    "gn:population":0,
    "gn:timezone":"Asia/Seoul",
    "iso:country":"KR",
    "name:und_x_variant":[
        "\uc2e0\ub2a5\ub3d9",
        "Sinneung-dong",
        "Sinn\u016dng-dong"
    ],
    "wof:name":"Sinneung-dong",
    "wof:placetype":"locality"
},
  "geometry": {"coordinates":[127.6125,37.31222],"type":"Point"}
}