{
  "type": "Feature",
  "properties": {
    "gn:admin1_code":"14.0",
    "gn:asciiname":"Araettudae",
    "gn:country_code":"KR",
    "gn:dem":332,
    "gn:feature_class":"P",
    "gn:feature_code":"PPL",
    "gn:name":"Araettudae",
    "gn:population":0,
    "gn:timezone":"Asia/Seoul",
    "iso:country":"KR",
    "name:und_x_variant":[
        "\uc544\ub7ab\ub450\ub300",
        "Araettudae"
    ],
    "wof:name":"Araettudae",
    "wof:placetype":"locality"
},
  "geometry": {"coordinates":[127.92355999999999,36.00198],"type":"Point"}
}