{
  "type": "Feature",
  "properties": {
    "gn:admin1_code":"20.0",
    "gn:asciiname":"Changgi-ri",
    "gn:country_code":"KR",
    "gn:dem":277,
    "gn:feature_class":"P",
    "gn:feature_code":"PPL",
    "gn:name":"Changgi-ri",
    "gn:population":0,
    "gn:timezone":"Asia/Seoul",
    "iso:country":"KR",
    "name:und_x_variant":[
        "\uc7a5\uae30\ub9ac",
        "Changgi-ri"
    ],
    "wof:name":"Changgi-ri",
    "wof:placetype":"locality"
},
  "geometry": {"coordinates":[127.99994,35.71345],"type":"Point"}
}