{
  "type": "Feature",
  "properties": {
    "gn:admin1_code":"16.0",
    "gn:asciiname":"Guseokgul",
    "gn:country_code":"KR",
    "gn:dem":26,
    "gn:feature_class":"P",
    "gn:feature_code":"PPL",
    "gn:name":"Guseokgul",
    "gn:population":0,
    "gn:timezone":"Asia/Seoul",
    "iso:country":"KR",
    "name:kor_x_preferred":[
        "\uad6c\uc11d\uad74"
    ],
    "wof:name":"Guseokgul",
    "wof:placetype":"locality"
},
  "geometry": {"coordinates":[126.69396999999999,34.92917],"type":"Point"}
}