{
  "type": "Feature",
  "properties": {
    "gn:admin1_code":"13.0",
    "gn:admin2_code":"P'aju-si",
    "gn:asciiname":"Origol",
    "gn:country_code":"KR",
    "gn:dem":35,
    "gn:feature_class":"P",
    "gn:feature_code":"PPL",
    "gn:name":"Origol",
    "gn:population":0,
    "gn:timezone":"Asia/Seoul",
    "iso:country":"KR",
    "name:kor_x_preferred":[
        "\uc624\ub9ac\uace8"
    ],
    "wof:name":"Origol",
    "wof:placetype":"locality"
},
  "geometry": {"coordinates":[126.85993999999999,37.94928],"type":"Point"}
}