{
  "type": "Feature",
  "properties": {
    "gn:admin1_code":"17.0",
    "gn:asciiname":"Puch'odang",
    "gn:country_code":"KR",
    "gn:dem":267,
    "gn:feature_class":"P",
    "gn:feature_code":"PPL",
    "gn:name":"Puch\u2019\u014fdang",
    "gn:population":0,
    "gn:timezone":"Asia/Seoul",
    "iso:country":"KR",
    "name:und_x_variant":[
        "\ubd80\ucc98\ub2f9",
        "Puch\u2019\u014fdang"
    ],
    "wof:name":"Puch'odang",
    "wof:placetype":"locality"
},
  "geometry": {"coordinates":[127.5757,36.0301],"type":"Point"}
}