{
  "type": "Feature",
  "properties": {
    "gn:admin1_code":"16.0",
    "gn:asciiname":"Sanguigok",
    "gn:country_code":"KR",
    "gn:dem":159,
    "gn:feature_class":"P",
    "gn:feature_code":"PPL",
    "gn:name":"Sanguigok",
    "gn:population":0,
    "gn:timezone":"Asia/Seoul",
    "iso:country":"KR",
    "name:kor_x_preferred":[
        "\uc0c1\uc758\uace1"
    ],
    "name:und_x_variant":[
        "Sanggaemisil",
        "Sang\u016digok",
        "Sanguigok"
    ],
    "wof:name":"Sanguigok",
    "wof:placetype":"locality"
},
  "geometry": {"coordinates":[127.58695,34.82609],"type":"Point"}
}