{
  "type": "Feature",
  "properties": {
    "gn:admin1_code":"6.0",
    "gn:asciiname":"Tonghae",
    "gn:country_code":"KR",
    "gn:dem":8,
    "gn:feature_class":"P",
    "gn:feature_code":"PPL",
    "gn:name":"Tonghae",
    "gn:population":0,
    "gn:timezone":"Asia/Seoul",
    "iso:country":"KR",
    "name:und_x_variant":[
        "\ub3d9\ud574",
        "Tonghae"
    ],
    "wof:name":"Tonghae",
    "wof:placetype":"locality"
},
  "geometry": {"coordinates":[129.12739999999999,37.497],"type":"Point"}
}