{
  "type": "Feature",
  "properties": {
    "gn:admin1_code":"17.0",
    "gn:asciiname":"Kuman",
    "gn:country_code":"KR",
    "gn:dem":23,
    "gn:feature_class":"P",
    "gn:feature_code":"PPL",
    "gn:name":"K\u016dman",
    "gn:population":0,
    "gn:timezone":"Asia/Seoul",
    "iso:country":"KR",
    "name:und_x_variant":[
        "\uae08\uc548",
        "K\u016dman"
    ],
    "wof:name":"Kuman",
    "wof:placetype":"locality"
},
  "geometry": {"coordinates":[126.3075,36.7933],"type":"Point"}
}