{
  "type": "Feature",
  "properties": {
    "gn:admin1_code":"3.0",
    "gn:asciiname":"Un'gok",
    "gn:country_code":"KR",
    "gn:dem":80,
    "gn:feature_class":"P",
    "gn:feature_code":"PPL",
    "gn:name":"\u016cn\u2019gok",
    "gn:population":0,
    "gn:timezone":"Asia/Seoul",
    "iso:country":"KR",
    "name:und_x_variant":[
        "\uc740\uace1",
        "\u016cn\u2019gok"
    ],
    "wof:name":"Un'gok",
    "wof:placetype":"locality"
},
  "geometry": {"coordinates":[127.03048,35.70494],"type":"Point"}
}