{
  "type": "Feature",
  "properties": {
    "gn:admin1_code":"20.0",
    "gn:asciiname":"Tulma",
    "gn:country_code":"KR",
    "gn:dem":198,
    "gn:feature_class":"P",
    "gn:feature_code":"PPL",
    "gn:name":"T\u016dlma",
    "gn:population":0,
    "gn:timezone":"Asia/Seoul",
    "iso:country":"KR",
    "name:und_x_variant":[
        "\ub4e4\ub9c8",
        "T\u016dlma"
    ],
    "wof:name":"Tulma",
    "wof:placetype":"locality"
},
  "geometry": {"coordinates":[128.60128999999998,35.54886],"type":"Point"}
}