{
  "type": "Feature",
  "properties": {
    "gn:admin1_code":"14.0",
    "gn:asciiname":"Sinheungni",
    "gn:country_code":"KR",
    "gn:dem":34,
    "gn:feature_class":"P",
    "gn:feature_code":"PPL",
    "gn:name":"Sinheungni",
    "gn:population":0,
    "gn:timezone":"Asia/Seoul",
    "iso:country":"KR",
    "name:kor_x_preferred":[
        "\uc2e0\ud765\ub9ac"
    ],
    "wof:name":"Sinheungni",
    "wof:placetype":"locality"
},
  "geometry": {"coordinates":[129.42382000000001,35.96496],"type":"Point"}
}