{
  "type": "Feature",
  "properties": {
    "gn:admin1_code":"16.0",
    "gn:asciiname":"Geumdong",
    "gn:country_code":"KR",
    "gn:dem":145,
    "gn:feature_class":"P",
    "gn:feature_code":"PPL",
    "gn:name":"Geumdong",
    "gn:population":0,
    "gn:timezone":"Asia/Seoul",
    "iso:country":"KR",
    "name:kor_x_preferred":[
        "\uae08\ub3d9"
    ],
    "wof:name":"Geumdong",
    "wof:placetype":"locality"
},
  "geometry": {"coordinates":[126.72165,35.33419],"type":"Point"}
}