{
  "type": "Feature",
  "properties": {
    "gn:admin1_code":"14.0",
    "gn:asciiname":"T'o-gol",
    "gn:country_code":"KR",
    "gn:dem":101,
    "gn:feature_class":"P",
    "gn:feature_code":"PPL",
    "gn:name":"T\u2019\u014f-gol",
    "gn:population":0,
    "gn:timezone":"Asia/Seoul",
    "iso:country":"KR",
    "name:und_x_variant":[
        "\ud130\uace8",
        "T\u2019\u014f-gol"
    ],
    "wof:name":"T'o-gol",
    "wof:placetype":"locality"
},
  "geometry": {"coordinates":[128.2878,36.4751],"type":"Point"}
}