{
  "type": "Feature",
  "properties": {
    "gn:admin1_code":"17.0",
    "gn:asciiname":"Eumjipyeon",
    "gn:country_code":"KR",
    "gn:dem":64,
    "gn:feature_class":"P",
    "gn:feature_code":"PPL",
    "gn:name":"Eumjipyeon",
    "gn:population":0,
    "gn:timezone":"Asia/Seoul",
    "iso:country":"KR",
    "name:kor_x_preferred":[
        "\uc74c\uc9c0\ud3b8"
    ],
    "wof:name":"Eumjipyeon",
    "wof:placetype":"locality"
},
  "geometry": {"coordinates":[127.14478,36.42594],"type":"Point"}
}