{
  "type": "Feature",
  "properties": {
    "gn:admin1_code":"3.0",
    "gn:asciiname":"Such'ong",
    "gn:country_code":"KR",
    "gn:dem":24,
    "gn:feature_class":"P",
    "gn:feature_code":"PPL",
    "gn:name":"Such\u2019\u014fng",
    "gn:population":0,
    "gn:timezone":"Asia/Seoul",
    "iso:country":"KR",
    "name:und_x_variant":[
        "\uc218\uccad",
        "Such\u2019\u014fng"
    ],
    "wof:name":"Such'ong",
    "wof:placetype":"locality"
},
  "geometry": {"coordinates":[127.03595,35.84547],"type":"Point"}
}