{
  "type": "Feature",
  "properties": {
    "iso:country":"KR",
    "name:eng_x_preferred":[
        "Geomdan-dong"
    ],
    "name:kor_x_preferred":[
        "\uac80\ub2e8\ub3d9"
    ],
    "qs:gn_adm0_cc":"KR",
    "qs:gn_local":1843564,
    "qs:local_max":2394,
    "qs:local_sum":10431,
    "qs:localhoods":47,
    "qs:name":"\uac80\ub2e8\ub3d9",
    "qs:name_adm0":"\ud55c\uad6d",
    "qs:name_adm1":"\uc778\ucc9c",
    "qs:name_adm2":"\uc11c\uad6c",
    "qs:name_local":"\uc778\ucc9c",
    "qs:photo_max":100,
    "qs:photo_sum":319,
    "qs:placetype":"Suburb",
    "qs:quad_count":33,
    "qs:woe_adm0":23424868,
    "qs:woe_adm1":20069922,
    "qs:woe_adm2":28289279,
    "qs:woe_lau":0,
    "qs:woe_local":1132496,
    "qs:woe_ver":"7.10.0",
    "wof:lang":[
        "kor"
    ],
    "wof:name":"Geomdan-dong",
    "wof:placetype":"neighbourhood"
},
  "geometry": {"coordinates":[126.704194,37.607867],"type":"Point"}
}