{
  "type": "Feature",
  "properties": {
    "gn:admin1_code":"20.0",
    "gn:asciiname":"Sampo",
    "gn:country_code":"KR",
    "gn:dem":11,
    "gn:feature_class":"P",
    "gn:feature_code":"PPL",
    "gn:name":"Sampo",
    "gn:population":0,
    "gn:timezone":"Asia/Seoul",
    "iso:country":"KR",
    "name:deu_x_preferred":[
        "Sampo"
    ],
    "name:est_x_preferred":[
        "Sampo"
    ],
    "name:eus_x_preferred":[
        "Sampo"
    ],
    "name:fin_x_preferred":[
        "Sampo"
    ],
    "name:fra_x_preferred":[
        "Sampo"
    ],
    "name:glg_x_preferred":[
        "Sampo"
    ],
    "name:hun_x_preferred":[
        "Szamp\u00f3"
    ],
    "name:ita_x_preferred":[
        "Sampo"
    ],
    "name:jpn_x_preferred":[
        "\u30b5\u30f3\u30dd"
    ],
    "name:kor_x_preferred":[
        "\uc0bc\ud3ec"
    ],
    "name:lat_x_preferred":[
        "Sampo"
    ],
    "name:pol_x_preferred":[
        "Sampo"
    ],
    "name:por_x_preferred":[
        "Sampo"
    ],
    "name:rus_x_preferred":[
        "\u0421\u0430\u043c\u043f\u043e"
    ],
    "name:sco_x_preferred":[
        "Sampo"
    ],
    "name:spa_x_preferred":[
        "Sampo"
    ],
    "name:swe_x_preferred":[
        "Sampo"
    ],
    "name:zho_x_preferred":[
        "\u4e09\u5b9d\u78e8"
    ],
    "wof:name":"Sampo",
    "wof:placetype":"locality"
},
  "geometry": {"coordinates":[128.73214999999999,35.09198],"type":"Point"}
}