{
  "type": "Feature",
  "properties": {
    "gn:admin1_code":"17.0",
    "gn:asciiname":"Naedok",
    "gn:country_code":"KR",
    "gn:dem":140,
    "gn:feature_class":"P",
    "gn:feature_code":"PPL",
    "gn:name":"Naed\u014fk",
    "gn:population":0,
    "gn:timezone":"Asia/Seoul",
    "iso:country":"KR",
    "name:und_x_variant":[
        "Naed\u014fk",
        "\ub0b4\ub355"
    ],
    "wof:name":"Naedok",
    "wof:placetype":"locality"
},
  "geometry": {"coordinates":[126.81180000000001,36.493],"type":"Point"}
}