{
  "type": "Feature",
  "properties": {
    "gn:admin1_code":"13.0",
    "gn:asciiname":"Songmokchae",
    "gn:country_code":"KR",
    "gn:dem":19,
    "gn:feature_class":"P",
    "gn:feature_code":"PPL",
    "gn:name":"Songmokchae",
    "gn:population":0,
    "gn:timezone":"Asia/Seoul",
    "iso:country":"KR",
    "name:kor_x_preferred":[
        "\uc1a1\ubaa9\uc7ac"
    ],
    "wof:name":"Songmokchae",
    "wof:placetype":"locality"
},
  "geometry": {"coordinates":[126.76000000000001,37.1925],"type":"Point"}
}