{
  "type": "Feature",
  "properties": {
    "gn:admin1_code":"17.0",
    "gn:asciiname":"Sanjol-li",
    "gn:country_code":"KR",
    "gn:dem":23,
    "gn:feature_class":"P",
    "gn:feature_code":"PPL",
    "gn:name":"Sanj\u014fl-li",
    "gn:population":0,
    "gn:timezone":"Asia/Seoul",
    "iso:country":"KR",
    "name:und_x_variant":[
        "\uc0b0\uc804\ub9ac",
        "Sanj\u014fl-li"
    ],
    "wof:name":"Sanjol-li",
    "wof:placetype":"locality"
},
  "geometry": {"coordinates":[127.0419,36.8975],"type":"Point"}
}