{
  "type": "Feature",
  "properties": {
    "gn:admin1_code":"6.0",
    "gn:asciiname":"Wont'o",
    "gn:country_code":"KR",
    "gn:dem":219,
    "gn:feature_class":"P",
    "gn:feature_code":"PPL",
    "gn:name":"W\u014fnt\u2019\u014f",
    "gn:population":0,
    "gn:timezone":"Asia/Seoul",
    "iso:country":"KR",
    "name:kor_x_preferred":[
        "\uc6d0\ud130"
    ],
    "name:kor_x_variant":[
        "W\u014fnt\u2019\u014f"
    ],
    "wof:name":"Wont'o",
    "wof:placetype":"locality"
},
  "geometry": {"coordinates":[127.9246,37.5284],"type":"Point"}
}