{
  "type": "Feature",
  "properties": {
    "gn:admin1_code":"3.0",
    "gn:asciiname":"Songch'on",
    "gn:country_code":"KR",
    "gn:dem":212,
    "gn:feature_class":"P",
    "gn:feature_code":"PPL",
    "gn:name":"Songch\u2019\u014fn",
    "gn:population":0,
    "gn:timezone":"Asia/Seoul",
    "iso:country":"KR",
    "name:und_x_variant":[
        "Songch\u2019\u014fn-ni",
        "Songch\u2019\u014fn"
    ],
    "wof:name":"Songch'on",
    "wof:placetype":"locality"
},
  "geometry": {"coordinates":[126.90000000000001,36.06667],"type":"Point"}
}