{
  "type": "Feature",
  "properties": {
    "gn:admin1_code":"16.0",
    "gn:asciiname":"Tokch'on",
    "gn:country_code":"KR",
    "gn:dem":43,
    "gn:feature_class":"P",
    "gn:feature_code":"PPL",
    "gn:name":"T\u014fkch\u2019on",
    "gn:population":0,
    "gn:timezone":"Asia/Seoul",
    "iso:country":"KR",
    "name:kor_x_preferred":[
        "\ub355\ucd0c"
    ],
    "name:kor_x_variant":[
        "T\u014fkch\u2019on"
    ],
    "wof:name":"Tokch'on",
    "wof:placetype":"locality"
},
  "geometry": {"coordinates":[127.34650000000001,34.55275],"type":"Point"}
}