{
  "type": "Feature",
  "properties": {
    "gn:admin1_code":"11.0",
    "gn:asciiname":"Kumhoiga-dong",
    "gn:country_code":"KR",
    "gn:dem":78,
    "gn:feature_class":"P",
    "gn:feature_code":"PPL",
    "gn:name":"K\u016dmhoiga-dong",
    "gn:population":0,
    "gn:timezone":"Asia/Seoul",
    "iso:country":"KR",
    "name:und_x_variant":[
        "\uae08\ud6382\uac00\ub3d9",
        "K\u016dmhoiga-dong"
    ],
    "wof:name":"Kumhoiga-dong",
    "wof:placetype":"locality"
},
  "geometry": {"coordinates":[127.02058,37.55281],"type":"Point"}
}