{
  "type": "Feature",
  "properties": {
    "gn:admin1_code":"20.0",
    "gn:asciiname":"Ijong-gol",
    "gn:country_code":"KR",
    "gn:dem":244,
    "gn:feature_class":"P",
    "gn:feature_code":"PPL",
    "gn:name":"Ij\u014fng-gol",
    "gn:population":0,
    "gn:timezone":"Asia/Seoul",
    "iso:country":"KR",
    "name:und_x_variant":[
        "\uc774\uc815\uace8",
        "Ij\u014fng-gol"
    ],
    "wof:name":"Ijong-gol",
    "wof:placetype":"locality"
},
  "geometry": {"coordinates":[127.98586,35.53484],"type":"Point"}
}