{
  "type": "Feature",
  "properties": {
    "gn:admin1_code":"14.0",
    "gn:asciiname":"Solgyeongji",
    "gn:country_code":"KR",
    "gn:dem":136,
    "gn:feature_class":"P",
    "gn:feature_code":"PPL",
    "gn:name":"Solgyeongji",
    "gn:population":0,
    "gn:timezone":"Asia/Seoul",
    "iso:country":"KR",
    "name:kor_x_preferred":[
        "\uc194\uacbd\uc9c0"
    ],
    "wof:name":"Solgyeongji",
    "wof:placetype":"locality"
},
  "geometry": {"coordinates":[128.43702999999999,36.72445],"type":"Point"}
}