{
  "type": "Feature",
  "properties": {
    "gn:admin1_code":"16.0",
    "gn:asciiname":"Bomit",
    "gn:country_code":"KR",
    "gn:dem":12,
    "gn:feature_class":"P",
    "gn:feature_code":"PPL",
    "gn:name":"Bomit",
    "gn:population":0,
    "gn:timezone":"Asia/Seoul",
    "iso:country":"KR",
    "name:kor_x_preferred":[
        "\ubcf4\ubc11"
    ],
    "name:und_x_variant":[
        "Pomit",
        "Bomit"
    ],
    "wof:name":"Bomit",
    "wof:placetype":"locality"
},
  "geometry": {"coordinates":[127.465,34.92554000000001],"type":"Point"}
}