{
  "type": "Feature",
  "properties": {
    "gn:admin1_code":"17.0",
    "gn:asciiname":"Chung-ch'on",
    "gn:country_code":"KR",
    "gn:dem":35,
    "gn:feature_class":"P",
    "gn:feature_code":"PPL",
    "gn:name":"Chung-ch\u2019on",
    "gn:population":0,
    "gn:timezone":"Asia/Seoul",
    "iso:country":"KR",
    "name:und_x_variant":[
        "\uc911\ucd0c",
        "Chung-ch\u2019on"
    ],
    "wof:name":"Chung-ch'on",
    "wof:placetype":"locality"
},
  "geometry": {"coordinates":[126.9027,36.7807],"type":"Point"}
}