{
  "type": "Feature",
  "properties": {
    "gn:admin1_code":"17.0",
    "gn:asciiname":"Changson",
    "gn:country_code":"KR",
    "gn:dem":213,
    "gn:feature_class":"P",
    "gn:feature_code":"PPL",
    "gn:name":"Changs\u014fn",
    "gn:population":0,
    "gn:timezone":"Asia/Seoul",
    "iso:country":"KR",
    "name:und_x_variant":[
        "\uc7a5\uc120",
        "Changs\u014fn"
    ],
    "wof:name":"Changson",
    "wof:placetype":"locality"
},
  "geometry": {"coordinates":[126.7131,36.3584],"type":"Point"}
}