{
  "type": "Feature",
  "properties": {
    "gn:admin1_code":"5.0",
    "gn:asciiname":"Sangsongjong",
    "gn:country_code":"KR",
    "gn:dem":126,
    "gn:feature_class":"P",
    "gn:feature_code":"PPL",
    "gn:name":"Sangsongj\u014fng",
    "gn:population":0,
    "gn:timezone":"Asia/Seoul",
    "iso:country":"KR",
    "name:und_x_variant":[
        "\uc0c1\uc1a1\uc815",
        "Sangsongj\u014fng"
    ],
    "wof:name":"Sangsongjong",
    "wof:placetype":"locality"
},
  "geometry": {"coordinates":[127.68640000000001,36.3699],"type":"Point"}
}