{
  "type": "Feature",
  "properties": {
    "gn:admin1_code":"17.0",
    "gn:asciiname":"Hadae-ri",
    "gn:country_code":"KR",
    "gn:dem":6,
    "gn:feature_class":"P",
    "gn:feature_code":"PPL",
    "gn:name":"Hadae-ri",
    "gn:population":0,
    "gn:timezone":"Asia/Seoul",
    "iso:country":"KR",
    "name:und_x_variant":[
        "Tag\u016dn-ni"
    ],
    "wof:name":"Hadae-ri",
    "wof:placetype":"locality"
},
  "geometry": {"coordinates":[126.95,36.15],"type":"Point"}
}