{
  "type": "Feature",
  "properties": {
    "gn:admin1_code":"17.0",
    "gn:asciiname":"Changjaul",
    "gn:country_code":"KR",
    "gn:dem":48,
    "gn:feature_class":"P",
    "gn:feature_code":"PPL",
    "gn:name":"Changjaul",
    "gn:population":0,
    "gn:timezone":"Asia/Seoul",
    "iso:country":"KR",
    "name:und_x_variant":[
        "\uc7a5\uc790\uc6b8",
        "Changjaul"
    ],
    "wof:name":"Changjaul",
    "wof:placetype":"locality"
},
  "geometry": {"coordinates":[127.1067,36.414],"type":"Point"}
}