{
  "type": "Feature",
  "properties": {
    "gn:admin1_code":"20.0",
    "gn:asciiname":"Sirhak-kol",
    "gn:country_code":"KR",
    "gn:dem":322,
    "gn:feature_class":"P",
    "gn:feature_code":"PPL",
    "gn:name":"Sirhak-kol",
    "gn:population":0,
    "gn:timezone":"Asia/Seoul",
    "iso:country":"KR",
    "name:und_x_variant":[
        "\uc2e4\ud559\uace8",
        "Sirhak-kol"
    ],
    "wof:name":"Sirhak-kol",
    "wof:placetype":"locality"
},
  "geometry": {"coordinates":[127.94833,35.76776],"type":"Point"}
}