{
  "type": "Feature",
  "properties": {
    "gn:admin1_code":"20.0",
    "gn:asciiname":"Ulmun",
    "gn:country_code":"KR",
    "gn:dem":169,
    "gn:feature_class":"P",
    "gn:feature_code":"PPL",
    "gn:name":"\u016clmun",
    "gn:population":0,
    "gn:timezone":"Asia/Seoul",
    "iso:country":"KR",
    "name:und_x_variant":[
        "\uc744\ubb38",
        "\u016clmun"
    ],
    "wof:name":"Ulmun",
    "wof:placetype":"locality"
},
  "geometry": {"coordinates":[128.40037000000001,35.15056],"type":"Point"}
}