{
  "type": "Feature",
  "properties": {
    "gn:admin1_code":"17.0",
    "gn:asciiname":"Churae",
    "gn:country_code":"KR",
    "gn:dem":19,
    "gn:feature_class":"P",
    "gn:feature_code":"PPL",
    "gn:name":"Churae",
    "gn:population":0,
    "gn:timezone":"Asia/Seoul",
    "iso:country":"KR",
    "name:und_x_variant":[
        "\uc8fc\ub798",
        "Churae"
    ],
    "wof:name":"Churae",
    "wof:placetype":"locality"
},
  "geometry": {"coordinates":[126.7204,36.7021],"type":"Point"}
}