{
  "type": "Feature",
  "properties": {
    "gn:admin1_code":"14.0",
    "gn:asciiname":"Munon-gol",
    "gn:country_code":"KR",
    "gn:dem":55,
    "gn:feature_class":"P",
    "gn:feature_code":"PPL",
    "gn:name":"Munon-gol",
    "gn:population":0,
    "gn:timezone":"Asia/Seoul",
    "iso:country":"KR",
    "name:und_x_variant":[
        "\ubb34\ub17c\uace8",
        "Munon-gol"
    ],
    "wof:name":"Munon-gol",
    "wof:placetype":"locality"
},
  "geometry": {"coordinates":[129.42070000000001,36.6568],"type":"Point"}
}