{
  "type": "Feature",
  "properties": {
    "gn:admin1_code":"10.0",
    "gn:asciiname":"Hageun",
    "gn:country_code":"KR",
    "gn:dem":21,
    "gn:feature_class":"P",
    "gn:feature_code":"PPL",
    "gn:name":"Hageun",
    "gn:population":0,
    "gn:timezone":"Asia/Seoul",
    "iso:country":"KR",
    "name:kor_x_preferred":[
        "\ud558\uadfc"
    ],
    "name:und_x_variant":[
        "Hag\u016dn",
        "Hag\u014fn",
        "Hageun"
    ],
    "wof:name":"Hageun",
    "wof:placetype":"locality"
},
  "geometry": {"coordinates":[129.2544,35.34630999999999],"type":"Point"}
}