{
  "type": "Feature",
  "properties": {
    "gn:admin1_code":"16.0",
    "gn:asciiname":"Wolsong",
    "gn:country_code":"KR",
    "gn:dem":117,
    "gn:feature_class":"P",
    "gn:feature_code":"PPL",
    "gn:name":"Wolsong",
    "gn:population":0,
    "gn:timezone":"Asia/Seoul",
    "iso:country":"KR",
    "name:kor_x_preferred":[
        "W\u014flsong"
    ],
    "name:und_x_variant":[
        "\uc6d4\uc1a1",
        "Wolsong"
    ],
    "wof:name":"Wolsong",
    "wof:placetype":"locality"
},
  "geometry": {"coordinates":[126.69320999999999,34.71768],"type":"Point"}
}