{
  "type": "Feature",
  "properties": {
    "gn:admin1_code":"14.0",
    "gn:asciiname":"Uk-kol",
    "gn:country_code":"KR",
    "gn:dem":63,
    "gn:feature_class":"P",
    "gn:feature_code":"PPL",
    "gn:name":"Uk-kol",
    "gn:population":0,
    "gn:timezone":"Asia/Seoul",
    "iso:country":"KR",
    "name:und_x_variant":[
        "\uc6c3\uace8",
        "Uk-kol"
    ],
    "wof:name":"Uk-kol",
    "wof:placetype":"locality"
},
  "geometry": {"coordinates":[128.31047000000001,35.82953],"type":"Point"}
}