{
  "type": "Feature",
  "properties": {
    "gn:admin1_code":"14.0",
    "gn:asciiname":"Sangjongjong",
    "gn:country_code":"KR",
    "gn:dem":323,
    "gn:feature_class":"P",
    "gn:feature_code":"PPL",
    "gn:name":"Sangj\u014fngj\u014fng",
    "gn:population":0,
    "gn:timezone":"Asia/Seoul",
    "iso:country":"KR",
    "wof:name":"Sangjongjong",
    "wof:placetype":"locality"
},
  "geometry": {"coordinates":[128.86667,36.66667],"type":"Point"}
}