{
  "type": "Feature",
  "properties": {
    "gn:admin1_code":"5.0",
    "gn:asciiname":"Gyegol",
    "gn:country_code":"KR",
    "gn:dem":63,
    "gn:feature_class":"P",
    "gn:feature_code":"PPL",
    "gn:name":"Gyegol",
    "gn:population":0,
    "gn:timezone":"Asia/Seoul",
    "iso:country":"KR",
    "name:kor_x_preferred":[
        "\uacc4\uace8"
    ],
    "wof:name":"Gyegol",
    "wof:placetype":"locality"
},
  "geometry": {"coordinates":[127.5296,36.76],"type":"Point"}
}