{
  "type": "Feature",
  "properties": {
    "gn:admin1_code":"6.0",
    "gn:asciiname":"Humun",
    "gn:country_code":"KR",
    "gn:dem":291,
    "gn:feature_class":"P",
    "gn:feature_code":"PPL",
    "gn:name":"Humun",
    "gn:population":0,
    "gn:timezone":"Asia/Seoul",
    "iso:country":"KR",
    "name:kor_x_preferred":[
        "\ud6c4\ubb38"
    ],
    "wof:name":"Humun",
    "wof:placetype":"locality"
},
  "geometry": {"coordinates":[128.05278000000001,38.15806],"type":"Point"}
}