{
  "type": "Feature",
  "properties": {
    "gn:admin1_code":"14.0",
    "gn:asciiname":"Saejom",
    "gn:country_code":"KR",
    "gn:dem":295,
    "gn:feature_class":"P",
    "gn:feature_code":"PPL",
    "gn:name":"Saej\u014fm",
    "gn:population":0,
    "gn:timezone":"Asia/Seoul",
    "iso:country":"KR",
    "name:und_x_variant":[
        "\uc0c8\uc810",
        "Saej\u014fm"
    ],
    "wof:name":"Saejom",
    "wof:placetype":"locality"
},
  "geometry": {"coordinates":[129.22905,36.93786],"type":"Point"}
}