{
  "type": "Feature",
  "properties": {
    "gn:admin1_code":"16.0",
    "gn:asciiname":"Daepyeong",
    "gn:country_code":"KR",
    "gn:dem":102,
    "gn:feature_class":"P",
    "gn:feature_code":"PPL",
    "gn:name":"Daepyeong",
    "gn:population":0,
    "gn:timezone":"Asia/Seoul",
    "iso:country":"KR",
    "name:fra_x_preferred":[
        "Daepyeong"
    ],
    "name:kor_x_preferred":[
        "\ub300\ud3c9"
    ],
    "name:kor_x_variant":[
        "Taep\u2019y\u014fng"
    ],
    "wof:name":"Daepyeong",
    "wof:placetype":"locality"
},
  "geometry": {"coordinates":[127.40196,34.87589000000001],"type":"Point"}
}