{
  "type": "Feature",
  "properties": {
    "gn:admin1_code":"3.0",
    "gn:asciiname":"Taehang-ni",
    "gn:country_code":"KR",
    "gn:dem":88,
    "gn:feature_class":"P",
    "gn:feature_code":"PPL",
    "gn:name":"Taehang-ni",
    "gn:population":0,
    "gn:timezone":"Asia/Seoul",
    "iso:country":"KR",
    "name:und_x_variant":[
        "\ub300\ud5a5\ub9ac",
        "Taehang-ni"
    ],
    "wof:name":"Taehang-ni",
    "wof:placetype":"locality"
},
  "geometry": {"coordinates":[127.25879999999999,35.99416],"type":"Point"}
}