{
  "type": "Feature",
  "properties": {
    "gn:admin1_code":"6.0",
    "gn:asciiname":"Jangjagol",
    "gn:country_code":"KR",
    "gn:dem":88,
    "gn:feature_class":"P",
    "gn:feature_code":"PPL",
    "gn:name":"Jangjagol",
    "gn:population":0,
    "gn:timezone":"Asia/Seoul",
    "iso:country":"KR",
    "name:und_x_variant":[
        "\uc7a5\uc790\uace8",
        "Changja-gol",
        "Jangjagol"
    ],
    "wof:name":"Jangjagol",
    "wof:placetype":"locality"
},
  "geometry": {"coordinates":[127.53458000000001,37.82258],"type":"Point"}
}