{
  "type": "Feature",
  "properties": {
    "gn:admin1_code":"6.0",
    "gn:asciiname":"Sinyang",
    "gn:country_code":"KR",
    "gn:dem":182,
    "gn:feature_class":"P",
    "gn:feature_code":"PPL",
    "gn:name":"Sinyang",
    "gn:population":0,
    "gn:timezone":"Asia/Seoul",
    "iso:country":"KR",
    "name:kor_x_preferred":[
        "\uc2e0\uc591"
    ],
    "name:nor_x_preferred":[
        "Sinyang"
    ],
    "wof:name":"Sinyang",
    "wof:placetype":"locality"
},
  "geometry": {"coordinates":[127.9877,37.4132],"type":"Point"}
}