{
  "type": "Feature",
  "properties": {
    "gn:admin1_code":"20.0",
    "gn:asciiname":"Saeje-gol",
    "gn:country_code":"KR",
    "gn:dem":755,
    "gn:feature_class":"P",
    "gn:feature_code":"PPL",
    "gn:name":"Saeje-gol",
    "gn:population":0,
    "gn:timezone":"Asia/Seoul",
    "iso:country":"KR",
    "name:und_x_variant":[
        "\uc0c8\uc81c\uace8",
        "Saeje-gol"
    ],
    "wof:name":"Saeje-gol",
    "wof:placetype":"locality"
},
  "geometry": {"coordinates":[127.70822,35.58593],"type":"Point"}
}