{
  "type": "Feature",
  "properties": {
    "gn:admin1_code":"20.0",
    "gn:asciiname":"Songjon",
    "gn:country_code":"KR",
    "gn:dem":76,
    "gn:feature_class":"P",
    "gn:feature_code":"PPL",
    "gn:name":"S\u014fngj\u014fn",
    "gn:population":0,
    "gn:timezone":"Asia/Seoul",
    "iso:country":"KR",
    "name:und_x_variant":[
        "S\u014fngj\u014fn-ni",
        "\uc131\uc804",
        "S\u014fngj\u014fn"
    ],
    "wof:name":"Songjon",
    "wof:placetype":"locality"
},
  "geometry": {"coordinates":[128.31290000000001,35.06913],"type":"Point"}
}