{
  "type": "Feature",
  "properties": {
    "gn:admin1_code":"20.0",
    "gn:asciiname":"Sammun",
    "gn:cc2":"KR",
    "gn:country_code":"KR",
    "gn:dem":13,
    "gn:feature_class":"P",
    "gn:feature_code":"PPL",
    "gn:name":"Sammun",
    "gn:population":0,
    "gn:timezone":"Asia/Seoul",
    "iso:country":"KR",
    "name:und_x_variant":[
        "Sammon-ri",
        "Sammun-ni",
        "Sammul-li",
        "Samun-dong",
        "Sammun",
        "\uc0ac\ubb38\ub3d9"
    ],
    "wof:name":"Sammun",
    "wof:placetype":"locality"
},
  "geometry": {"coordinates":[128.75,35.48333],"type":"Point"}
}