{
  "type": "Feature",
  "properties": {
    "iso:country":"KR",
    "name:eng_x_preferred":[
        "Yonghwa-myeon"
    ],
    "name:kor_x_preferred":[
        "\uc6a9\ud654\uba74"
    ],
    "qs:name":"\uc6a9\ud654\uba74",
    "qs:name_adm0":"\ud55c\uad6d",
    "qs:name_adm1":"\ucda9\uccad\ubd81\ub3c4",
    "qs:photos":27,
    "qs:photos_1k":5,
    "qs:photos_9k":1,
    "qs:photos_9r":2,
    "qs:photos_all":27,
    "qs:photos_sr":2,
    "qs:placetype":"LocalAdmin",
    "qs:pop_sr":"0",
    "wof:name":"Yonghwa-myeon",
    "wof:placetype":"localadmin"
},
  "geometry": {"coordinates":[127.984542,36.12401],"type":"Point"}
}