{
  "type": "Feature",
  "properties": {
    "gn:admin1_code":"14.0",
    "gn:asciiname":"Chosil",
    "gn:country_code":"KR",
    "gn:dem":92,
    "gn:feature_class":"P",
    "gn:feature_code":"PPL",
    "gn:name":"Chosil",
    "gn:population":0,
    "gn:timezone":"Asia/Seoul",
    "iso:country":"KR",
    "name:und_x_variant":[
        "\uc870\uc2e4",
        "Chosil"
    ],
    "wof:name":"Chosil",
    "wof:placetype":"locality"
},
  "geometry": {"coordinates":[128.28763000000001,35.84323],"type":"Point"}
}