{
  "type": "Feature",
  "properties": {
    "gn:admin1_code":"5.0",
    "gn:asciiname":"Changsol-li",
    "gn:cc2":"KR",
    "gn:country_code":"KR",
    "gn:dem":273,
    "gn:feature_class":"P",
    "gn:feature_code":"PPL",
    "gn:name":"Changs\u014fl-li",
    "gn:population":0,
    "gn:timezone":"Asia/Seoul",
    "iso:country":"KR",
    "name:und_x_variant":[
        "Changs\u014fn-ri",
        "Changs\u014fl-li",
        "\uc7a5\uc120\ub9ac"
    ],
    "wof:name":"Changsol-li",
    "wof:placetype":"locality"
},
  "geometry": {"coordinates":[127.65000000000001,36.44694000000001],"type":"Point"}
}