{
  "type": "Feature",
  "properties": {
    "gn:admin1_code":"17.0",
    "gn:asciiname":"Chomsim-gol",
    "gn:country_code":"KR",
    "gn:dem":128,
    "gn:feature_class":"P",
    "gn:feature_code":"PPL",
    "gn:name":"Ch\u014fmsim-gol",
    "gn:population":0,
    "gn:timezone":"Asia/Seoul",
    "iso:country":"KR",
    "name:und_x_variant":[
        "Ch\u014fmsim-kol",
        "Ch\u014fmsim-dong",
        "Ch\u014fmsim-gol",
        "\uc810\uc2ec\uace8"
    ],
    "wof:name":"Chomsim-gol",
    "wof:placetype":"locality"
},
  "geometry": {"coordinates":[126.90989999999999,36.4252],"type":"Point"}
}