{
  "type": "Feature",
  "properties": {
    "gn:admin1_code":"17.0",
    "gn:asciiname":"Hansin",
    "gn:country_code":"KR",
    "gn:dem":99,
    "gn:feature_class":"P",
    "gn:feature_code":"PPL",
    "gn:name":"Hansin",
    "gn:population":0,
    "gn:timezone":"Asia/Seoul",
    "iso:country":"KR",
    "name:kor_x_preferred":[
        "\ud55c\uc2e0"
    ],
    "wof:name":"Hansin",
    "wof:placetype":"locality"
},
  "geometry": {"coordinates":[127.28515,36.70773],"type":"Point"}
}