{
  "type": "Feature",
  "properties": {
    "gn:admin1_code":"13.0",
    "gn:admin2_code":"Yongin-si",
    "gn:asciiname":"Jungneung-ri",
    "gn:country_code":"KR",
    "gn:dem":113,
    "gn:feature_class":"P",
    "gn:feature_code":"PPLL",
    "gn:name":"Jungneung-ri",
    "gn:population":0,
    "gn:timezone":"Asia/Seoul",
    "iso:country":"KR",
    "name:kor_x_preferred":[
        "\uc8fd\ub989\ub9ac"
    ],
    "name:kor_x_variant":[
        "Chungn\u016dng-ni"
    ],
    "wof:name":"Jungneung-ri",
    "wof:placetype":"locality"
},
  "geometry": {"coordinates":[127.30528,37.14722],"type":"Point"}
}