{
  "type": "Feature",
  "properties": {
    "gn:admin1_code":"16.0",
    "gn:asciiname":"Ch'okch'i",
    "gn:country_code":"KR",
    "gn:dem":87,
    "gn:feature_class":"P",
    "gn:feature_code":"PPL",
    "gn:name":"Ch\u2019\u014fkch\u2019i",
    "gn:population":0,
    "gn:timezone":"Asia/Seoul",
    "iso:country":"KR",
    "name:kor_x_preferred":[
        "\ucc99\uce58"
    ],
    "name:kor_x_variant":[
        "Ch\u2019\u014fkch\u2019i"
    ],
    "wof:name":"Ch'okch'i",
    "wof:placetype":"locality"
},
  "geometry": {"coordinates":[127.31001999999999,34.54734000000001],"type":"Point"}
}