{
  "type": "Feature",
  "properties": {
    "gn:admin1_code":"20.0",
    "gn:asciiname":"Deulma",
    "gn:country_code":"KR",
    "gn:dem":14,
    "gn:feature_class":"P",
    "gn:feature_code":"PPL",
    "gn:name":"Deulma",
    "gn:population":0,
    "gn:timezone":"Asia/Seoul",
    "iso:country":"KR",
    "name:und_x_variant":[
        "\ub4e4\ub9c8",
        "T\u016dlma",
        "Deulma"
    ],
    "wof:name":"Deulma",
    "wof:placetype":"locality"
},
  "geometry": {"coordinates":[128.38813000000002,35.60148],"type":"Point"}
}