{
  "type": "Feature",
  "properties": {
    "gn:admin1_code":"13.0",
    "gn:asciiname":"Hojuul",
    "gn:country_code":"KR",
    "gn:dem":67,
    "gn:feature_class":"P",
    "gn:feature_code":"PPL",
    "gn:name":"Hojuul",
    "gn:population":0,
    "gn:timezone":"Asia/Seoul",
    "iso:country":"KR",
    "name:kor_x_preferred":[
        "\ud638\uc8fc\uc6b8"
    ],
    "wof:name":"Hojuul",
    "wof:placetype":"locality"
},
  "geometry": {"coordinates":[126.86275999999999,37.85979],"type":"Point"}
}