{
  "type": "Feature",
  "properties": {
    "iso:country":"KR",
    "qs:name":"\ub2e8\uc6d4\uba74",
    "qs:name_adm0":"\ud55c\uad6d",
    "qs:name_adm1":"\uacbd\uae30\ub3c4",
    "qs:photos":80,
    "qs:photos_1k":16,
    "qs:photos_9k":1,
    "qs:photos_9r":3,
    "qs:photos_all":80,
    "qs:photos_sr":3,
    "qs:placetype":"LocalAdmin",
    "qs:pop_sr":"0",
    "wof:name":"\ub2e8\uc6d4\uba74",
    "wof:placetype":"localadmin"
},
  "geometry": {"coordinates":[127.621093,37.598499],"type":"Point"}
}