{
  "type": "Feature",
  "properties": {
    "iso:country":"KR",
    "name:kor_x_preferred":[
        "\uccad\ud559\ub3d9"
    ],
    "qs:gn_adm0_cc":"KR",
    "qs:gn_local":1838524,
    "qs:local_max":2765,
    "qs:local_sum":24552,
    "qs:localhoods":60,
    "qs:name":"\uccad\ud559\ub3d9",
    "qs:name_adm0":"\ud55c\uad6d",
    "qs:name_adm1":"\ubd80\uc0b0",
    "qs:name_adm2":"\uc601\ub3c4\uad6c",
    "qs:name_local":"\ubd80\uc0b0",
    "qs:photo_max":18,
    "qs:photo_sum":101,
    "qs:placetype":"Suburb",
    "qs:quad_count":19,
    "qs:woe_adm0":23424868,
    "qs:woe_adm1":2345968,
    "qs:woe_adm2":28289326,
    "qs:woe_lau":0,
    "qs:woe_local":1132447,
    "qs:woe_ver":"7.10.0",
    "wof:lang":[
        "kor"
    ],
    "wof:name":"\uccad\ud559\ub3d9",
    "wof:placetype":"neighbourhood"
},
  "geometry": {"coordinates":[129.067995,35.097767],"type":"Point"}
}