{
  "type": "Feature",
  "properties": {
    "gn:admin1_code":"6.0",
    "gn:asciiname":"Inheung-ri Igu",
    "gn:country_code":"KR",
    "gn:dem":16,
    "gn:feature_class":"P",
    "gn:feature_code":"PPL",
    "gn:name":"Inheung-ri Igu",
    "gn:population":0,
    "gn:timezone":"Asia/Seoul",
    "iso:country":"KR",
    "name:kor_x_preferred":[
        "\uc778\ud765\ub9ac\uc774\uad6c"
    ],
    "name:kor_x_variant":[
        "\uc778\ud765\ub9ac2\uad6c"
    ],
    "name:und_x_variant":[
        "Inheung-ri 2 Gu"
    ],
    "wof:name":"Inheung-ri Igu",
    "wof:placetype":"locality"
},
  "geometry": {"coordinates":[128.55266,38.23401],"type":"Point"}
}