{
  "type": "Feature",
  "properties": {
    "gn:admin1_code":"13.0",
    "gn:asciiname":"Jogok",
    "gn:country_code":"KR",
    "gn:dem":127,
    "gn:feature_class":"P",
    "gn:feature_code":"PPL",
    "gn:name":"Jogok",
    "gn:population":0,
    "gn:timezone":"Asia/Seoul",
    "iso:country":"KR",
    "name:kor_x_preferred":[
        "\uc870\uace1"
    ],
    "name:und_x_variant":[
        "\uc870\uace1",
        "Jogok"
    ],
    "wof:name":"Jogok",
    "wof:placetype":"locality"
},
  "geometry": {"coordinates":[127.28530000000001,37.5657],"type":"Point"}
}