{
  "type": "Feature",
  "properties": {
    "gn:admin1_code":"13.0",
    "gn:admin2_code":"Yongin-si",
    "gn:asciiname":"Hwangtojae",
    "gn:country_code":"KR",
    "gn:dem":119,
    "gn:feature_class":"P",
    "gn:feature_code":"PPL",
    "gn:name":"Hwangtojae",
    "gn:population":0,
    "gn:timezone":"Asia/Seoul",
    "iso:country":"KR",
    "name:kor_x_preferred":[
        "\ud669\ud1a0\uc7ac"
    ],
    "name:kor_x_variant":[
        "Hwangt\u2019ojae"
    ],
    "wof:name":"Hwangtojae",
    "wof:placetype":"locality"
},
  "geometry": {"coordinates":[127.33485,37.16465],"type":"Point"}
}