{
  "type": "Feature",
  "properties": {
    "gn:admin1_code":"12.0",
    "gn:asciiname":"Chigyong",
    "gn:country_code":"KR",
    "gn:dem":16,
    "gn:feature_class":"P",
    "gn:feature_code":"PPL",
    "gn:name":"Chigy\u014fng",
    "gn:population":0,
    "gn:timezone":"Asia/Seoul",
    "iso:country":"KR",
    "name:kor_x_preferred":[
        "\uc9c0\uacbd"
    ],
    "name:kor_x_variant":[
        "Chigy\u014fng"
    ],
    "wof:name":"Chigyong",
    "wof:placetype":"locality"
},
  "geometry": {"coordinates":[126.66916999999999,37.6525],"type":"Point"}
}