{
  "type": "Feature",
  "properties": {
    "gn:admin1_code":"17.0",
    "gn:asciiname":"Sungjimul",
    "gn:country_code":"KR",
    "gn:dem":29,
    "gn:feature_class":"P",
    "gn:feature_code":"PPL",
    "gn:name":"S\u016dngjimul",
    "gn:population":0,
    "gn:timezone":"Asia/Seoul",
    "iso:country":"KR",
    "name:und_x_variant":[
        "\uc2b9\uc9c0\ubb3c",
        "S\u016dngjimul"
    ],
    "wof:name":"Sungjimul",
    "wof:placetype":"locality"
},
  "geometry": {"coordinates":[126.8678,36.7971],"type":"Point"}
}