{
  "type": "Feature",
  "properties": {
    "gn:admin1_code":"14.0",
    "gn:asciiname":"Chukchong",
    "gn:country_code":"KR",
    "gn:dem":88,
    "gn:feature_class":"P",
    "gn:feature_code":"PPL",
    "gn:name":"Chukch\u014fng",
    "gn:population":0,
    "gn:timezone":"Asia/Seoul",
    "iso:country":"KR",
    "name:und_x_variant":[
        "\uc8fd\uc815",
        "Chukch\u014fng"
    ],
    "wof:name":"Chukchong",
    "wof:placetype":"locality"
},
  "geometry": {"coordinates":[128.10560000000001,36.0776],"type":"Point"}
}