{
  "type": "Feature",
  "properties": {
    "gn:admin1_code":"17.0",
    "gn:asciiname":"Kaundettum",
    "gn:country_code":"KR",
    "gn:dem":65,
    "gn:feature_class":"P",
    "gn:feature_code":"PPL",
    "gn:name":"Kaundett\u016dm",
    "gn:population":0,
    "gn:timezone":"Asia/Seoul",
    "iso:country":"KR",
    "name:und_x_variant":[
        "\uac00\uc6b4\ub370\ub738",
        "Kaundett\u016dm"
    ],
    "wof:name":"Kaundettum",
    "wof:placetype":"locality"
},
  "geometry": {"coordinates":[126.98180000000001,36.2809],"type":"Point"}
}