{
  "type": "Feature",
  "properties": {
    "gn:admin1_code":"13.0",
    "gn:asciiname":"Tap-gol",
    "gn:country_code":"KR",
    "gn:dem":66,
    "gn:feature_class":"P",
    "gn:feature_code":"PPL",
    "gn:name":"Tap-gol",
    "gn:population":0,
    "gn:timezone":"Asia/Seoul",
    "iso:country":"KR",
    "name:und_x_variant":[
        "\ud0d1\uace8",
        "Tap-gol",
        "T\u2019ap-kol"
    ],
    "wof:name":"Tap-gol",
    "wof:placetype":"locality"
},
  "geometry": {"coordinates":[127.53389,37.47639],"type":"Point"}
}