{
  "type": "Feature",
  "properties": {
    "gn:admin1_code":"17.0",
    "gn:asciiname":"Katchom",
    "gn:country_code":"KR",
    "gn:dem":71,
    "gn:feature_class":"P",
    "gn:feature_code":"PPL",
    "gn:name":"Katch\u014fm",
    "gn:population":0,
    "gn:timezone":"Asia/Seoul",
    "iso:country":"KR",
    "name:und_x_variant":[
        "\uac13\uc810",
        "Katch\u014fm"
    ],
    "wof:name":"Katchom",
    "wof:placetype":"locality"
},
  "geometry": {"coordinates":[127.10339999999999,36.3024],"type":"Point"}
}