{
  "type": "Feature",
  "properties": {
    "gn:admin1_code":"17.0",
    "gn:asciiname":"Taesum-maul",
    "gn:country_code":"KR",
    "gn:dem":35,
    "gn:feature_class":"P",
    "gn:feature_code":"PPL",
    "gn:name":"Taesum-ma\u016dl",
    "gn:population":0,
    "gn:timezone":"Asia/Seoul",
    "iso:country":"KR",
    "name:und_x_variant":[
        "\ub300\uc232\ub9c8\uc744",
        "Taesum-ma\u016dl"
    ],
    "wof:name":"Taesum-maul",
    "wof:placetype":"locality"
},
  "geometry": {"coordinates":[126.7855,36.2761],"type":"Point"}
}