{
  "type": "Feature",
  "properties": {
    "gn:admin1_code":"13.0",
    "gn:asciiname":"Chang-chon",
    "gn:country_code":"KR",
    "gn:dem":56,
    "gn:feature_class":"P",
    "gn:feature_code":"PPL",
    "gn:name":"Chang-chon",
    "gn:population":0,
    "gn:timezone":"Asia/Seoul",
    "iso:country":"KR",
    "name:und_x_variant":[
        "\ucc3d\ucd0c",
        "Chang-chon",
        "Ch\u2019ang-ch\u2019on"
    ],
    "wof:name":"Chang-chon",
    "wof:placetype":"locality"
},
  "geometry": {"coordinates":[127.38833,37.48056],"type":"Point"}
}