{
  "type": "Feature",
  "properties": {
    "gn:admin1_code":"17.0",
    "gn:asciiname":"Posanwol-li",
    "gn:cc2":"KR",
    "gn:country_code":"KR",
    "gn:dem":87,
    "gn:feature_class":"P",
    "gn:feature_code":"PPL",
    "gn:name":"Posanw\u014fl-li",
    "gn:population":0,
    "gn:timezone":"Asia/Seoul",
    "iso:country":"KR",
    "name:und_x_variant":[
        "Posanw\u014fn-ni",
        "Posanw\u014fl-li"
    ],
    "wof:name":"Posanwol-li",
    "wof:placetype":"locality"
},
  "geometry": {"coordinates":[127.07389000000001,36.68361],"type":"Point"}
}