{
  "type": "Feature",
  "properties": {
    "gn:admin1_code":"3.0",
    "gn:asciiname":"Pallyong",
    "gn:country_code":"KR",
    "gn:dem":243,
    "gn:feature_class":"P",
    "gn:feature_code":"PPL",
    "gn:name":"Pallyong",
    "gn:population":0,
    "gn:timezone":"Asia/Seoul",
    "iso:country":"KR",
    "name:und_x_variant":[
        "\ubc18\ub8e1",
        "Pallyong"
    ],
    "wof:name":"Pallyong",
    "wof:placetype":"locality"
},
  "geometry": {"coordinates":[127.30961000000001,35.71283],"type":"Point"}
}