{
  "type": "Feature",
  "properties": {
    "gn:admin1_code":"12.0",
    "gn:asciiname":"Suhae",
    "gn:country_code":"KR",
    "gn:dem":21,
    "gn:feature_class":"P",
    "gn:feature_code":"PPL",
    "gn:name":"Suhae",
    "gn:population":0,
    "gn:timezone":"Asia/Seoul",
    "iso:country":"KR",
    "name:kor_x_preferred":[
        "\uc218\ud574"
    ],
    "wof:name":"Suhae",
    "wof:placetype":"locality"
},
  "geometry": {"coordinates":[126.45735999999999,37.2815],"type":"Point"}
}