{
  "type": "Feature",
  "properties": {
    "gn:admin1_code":"16.0",
    "gn:asciiname":"Suchon",
    "gn:country_code":"KR",
    "gn:dem":51,
    "gn:feature_class":"P",
    "gn:feature_code":"PPL",
    "gn:name":"Suchon",
    "gn:population":0,
    "gn:timezone":"Asia/Seoul",
    "iso:country":"KR",
    "name:kor_x_preferred":[
        "\uc218\ucd0c"
    ],
    "name:und_x_variant":[
        "Such\u2019on"
    ],
    "wof:name":"Suchon",
    "wof:placetype":"locality"
},
  "geometry": {"coordinates":[126.81614,35.26005],"type":"Point"}
}