{
  "type": "Feature",
  "properties": {
    "gn:admin1_code":"17.0",
    "gn:asciiname":"Changbun",
    "gn:cc2":"KR",
    "gn:country_code":"KR",
    "gn:dem":6,
    "gn:feature_class":"P",
    "gn:feature_code":"PPL",
    "gn:name":"Changbun",
    "gn:population":0,
    "gn:timezone":"Asia/Seoul",
    "iso:country":"KR",
    "name:und_x_variant":[
        "Changmun-dong",
        "Changmun",
        "Changbun"
    ],
    "wof:name":"Changbun",
    "wof:placetype":"locality"
},
  "geometry": {"coordinates":[126.34999999999999,36.51667],"type":"Point"}
}