{
  "type": "Feature",
  "properties": {
    "gn:admin1_code":"13.0",
    "gn:asciiname":"Beombawi",
    "gn:country_code":"KR",
    "gn:dem":32,
    "gn:feature_class":"P",
    "gn:feature_code":"PPL",
    "gn:name":"Beombawi",
    "gn:population":0,
    "gn:timezone":"Asia/Seoul",
    "iso:country":"KR",
    "name:kor_x_preferred":[
        "\ubc94\ubc14\uc704"
    ],
    "wof:name":"Beombawi",
    "wof:placetype":"locality"
},
  "geometry": {"coordinates":[126.89809,37.96543],"type":"Point"}
}