{
  "type": "Feature",
  "properties": {
    "gn:admin1_code":"14.0",
    "gn:asciiname":"Dogyechon",
    "gn:country_code":"KR",
    "gn:dem":149,
    "gn:feature_class":"P",
    "gn:feature_code":"PPL",
    "gn:name":"Dogyechon",
    "gn:population":0,
    "gn:timezone":"Asia/Seoul",
    "iso:country":"KR",
    "name:kor_x_preferred":[
        "\ub3c4\uacc4\ucd0c"
    ],
    "wof:name":"Dogyechon",
    "wof:placetype":"locality"
},
  "geometry": {"coordinates":[128.69534999999999,36.66181],"type":"Point"}
}