{
  "type": "Feature",
  "properties": {
    "gn:admin1_code":"17.0",
    "gn:asciiname":"Pyeongtteum",
    "gn:country_code":"KR",
    "gn:dem":53,
    "gn:feature_class":"P",
    "gn:feature_code":"PPL",
    "gn:name":"Pyeongtteum",
    "gn:population":0,
    "gn:timezone":"Asia/Seoul",
    "iso:country":"KR",
    "name:und_x_variant":[
        "\ud3c9\ub738",
        "P\u2019y\u014fngtt\u016dm",
        "Pyeongtteum"
    ],
    "wof:name":"Pyeongtteum",
    "wof:placetype":"locality"
},
  "geometry": {"coordinates":[127.15689999999999,36.7672],"type":"Point"}
}