{
  "type": "Feature",
  "properties": {
    "gn:admin1_code":"16.0",
    "gn:asciiname":"Bakpo",
    "gn:country_code":"KR",
    "gn:dem":18,
    "gn:feature_class":"P",
    "gn:feature_code":"PPL",
    "gn:name":"Bakpo",
    "gn:population":0,
    "gn:timezone":"Asia/Seoul",
    "iso:country":"KR",
    "name:kor_x_preferred":[
        "\ubc15\ud3ec"
    ],
    "name:und_x_variant":[
        "Pakp\u2019o-ri",
        "Pakp\u2019o",
        "Bakpo"
    ],
    "wof:name":"Bakpo",
    "wof:placetype":"locality"
},
  "geometry": {"coordinates":[126.64549,34.95401],"type":"Point"}
}