{
  "type": "Feature",
  "properties": {
    "gn:admin1_code":"6.0",
    "gn:asciiname":"Min-gol",
    "gn:country_code":"KR",
    "gn:dem":871,
    "gn:feature_class":"P",
    "gn:feature_code":"PPL",
    "gn:name":"Min-gol",
    "gn:population":0,
    "gn:timezone":"Asia/Seoul",
    "iso:country":"KR",
    "name:kor_x_preferred":[
        "\ubbfc\uace8"
    ],
    "wof:name":"Min-gol",
    "wof:placetype":"locality"
},
  "geometry": {"coordinates":[128.81979999999999,37.1505],"type":"Point"}
}