{
  "type": "Feature",
  "properties": {
    "gn:admin1_code":"16.0",
    "gn:asciiname":"Yongbakgol",
    "gn:country_code":"KR",
    "gn:dem":55,
    "gn:feature_class":"P",
    "gn:feature_code":"PPL",
    "gn:name":"Yongbakgol",
    "gn:population":0,
    "gn:timezone":"Asia/Seoul",
    "iso:country":"KR",
    "name:kor_x_preferred":[
        "\uc6a9\ubc15\uace8"
    ],
    "name:und_x_variant":[
        "Yongbak-kol",
        "Yongbakgol"
    ],
    "wof:name":"Yongbakgol",
    "wof:placetype":"locality"
},
  "geometry": {"coordinates":[127.44208,34.92718],"type":"Point"}
}