{
  "type": "Feature",
  "properties": {
    "gn:admin1_code":"15.0",
    "gn:asciiname":"Gwangjeong",
    "gn:country_code":"KR",
    "gn:dem":231,
    "gn:feature_class":"P",
    "gn:feature_code":"PPL",
    "gn:name":"Gwangjeong",
    "gn:population":0,
    "gn:timezone":"Asia/Seoul",
    "iso:country":"KR",
    "name:kor_x_preferred":[
        "\uad11\uc815"
    ],
    "wof:name":"Gwangjeong",
    "wof:placetype":"locality"
},
  "geometry": {"coordinates":[128.67705000000001,35.76631],"type":"Point"}
}