{
  "type": "Feature",
  "properties": {
    "gn:admin1_code":"13.0",
    "gn:admin2_code":"Ans\u014fng-si",
    "gn:asciiname":"Sinyangbongni",
    "gn:country_code":"KR",
    "gn:dem":27,
    "gn:feature_class":"P",
    "gn:feature_code":"PPLL",
    "gn:name":"Sinyangbongni",
    "gn:population":0,
    "gn:timezone":"Asia/Seoul",
    "iso:country":"KR",
    "name:kor_x_preferred":[
        "\uc2e0\uc591\ubcf5\ub9ac"
    ],
    "name:und_x_variant":[
        "Sinyangbong-ni",
        "Sinyangbok-ri",
        "Sinyangbongni"
    ],
    "wof:name":"Sinyangbongni",
    "wof:placetype":"locality"
},
  "geometry": {"coordinates":[127.23917,37.00611],"type":"Point"}
}