{
  "type": "Feature",
  "properties": {
    "gn:admin1_code":"13.0",
    "gn:asciiname":"Jeoguni",
    "gn:country_code":"KR",
    "gn:dem":43,
    "gn:feature_class":"P",
    "gn:feature_code":"PPL",
    "gn:name":"Jeoguni",
    "gn:population":0,
    "gn:timezone":"Asia/Seoul",
    "iso:country":"KR",
    "name:kor_x_preferred":[
        "\uc801\uc6b4\uc774"
    ],
    "wof:name":"Jeoguni",
    "wof:placetype":"locality"
},
  "geometry": {"coordinates":[126.78373000000001,37.87331],"type":"Point"}
}