{
  "type": "Feature",
  "properties": {
    "gn:admin1_code":"5.0",
    "gn:asciiname":"Geomsi",
    "gn:country_code":"KR",
    "gn:dem":46,
    "gn:feature_class":"P",
    "gn:feature_code":"PPL",
    "gn:name":"Geomsi",
    "gn:population":0,
    "gn:timezone":"Asia/Seoul",
    "iso:country":"KR",
    "name:und_x_variant":[
        "\uac80\uc2dc",
        "K\u014fmsi",
        "Geomsi"
    ],
    "wof:name":"Geomsi",
    "wof:placetype":"locality"
},
  "geometry": {"coordinates":[127.37015,36.49491],"type":"Point"}
}