{
  "type": "Feature",
  "properties": {
    "gn:admin1_code":"16.0",
    "gn:asciiname":"Pyeongjang",
    "gn:country_code":"KR",
    "gn:dem":8,
    "gn:feature_class":"P",
    "gn:feature_code":"PPL",
    "gn:name":"Pyeongjang",
    "gn:population":0,
    "gn:timezone":"Asia/Seoul",
    "iso:country":"KR",
    "name:kor_x_preferred":[
        "\ud3c9\uc7a5"
    ],
    "name:und_x_variant":[
        "P\u2019y\u014fngjang-ni",
        "P\u2019y\u014fngjang",
        "Pyeongjang"
    ],
    "wof:name":"Pyeongjang",
    "wof:placetype":"locality"
},
  "geometry": {"coordinates":[126.67438,34.80662],"type":"Point"}
}