{
  "type": "Feature",
  "properties": {
    "gn:admin1_code":"14.0",
    "gn:asciiname":"Kumgok",
    "gn:country_code":"KR",
    "gn:dem":215,
    "gn:feature_class":"P",
    "gn:feature_code":"PPL",
    "gn:name":"K\u016dmgok",
    "gn:population":0,
    "gn:timezone":"Asia/Seoul",
    "iso:country":"KR",
    "name:und_x_variant":[
        "\uae08\uace1",
        "K\u016dmgok"
    ],
    "wof:name":"Kumgok",
    "wof:placetype":"locality"
},
  "geometry": {"coordinates":[128.06398000000002,36.00166],"type":"Point"}
}