{
  "type": "Feature",
  "properties": {
    "gn:admin1_code":"20.0",
    "gn:asciiname":"Numt'o",
    "gn:country_code":"KR",
    "gn:dem":399,
    "gn:feature_class":"P",
    "gn:feature_code":"PPL",
    "gn:name":"N\u016dmt\u2019\u014f",
    "gn:population":0,
    "gn:timezone":"Asia/Seoul",
    "iso:country":"KR",
    "name:und_x_variant":[
        "\ub2a0\ud130",
        "N\u016dmt\u2019\u014f"
    ],
    "wof:name":"Numt'o",
    "wof:placetype":"locality"
},
  "geometry": {"coordinates":[127.86660999999999,35.79019],"type":"Point"}
}