{
  "type": "Feature",
  "properties": {
    "gn:admin1_code":"17.0",
    "gn:asciiname":"Poktok",
    "gn:country_code":"KR",
    "gn:dem":49,
    "gn:feature_class":"P",
    "gn:feature_code":"PPL",
    "gn:name":"Pokt\u014fk",
    "gn:population":0,
    "gn:timezone":"Asia/Seoul",
    "iso:country":"KR",
    "name:und_x_variant":[
        "\ubcf5\ub355",
        "Pokt\u014fk"
    ],
    "wof:name":"Poktok",
    "wof:placetype":"locality"
},
  "geometry": {"coordinates":[127.18380000000001,36.8667],"type":"Point"}
}