{
  "type": "Feature",
  "properties": {
    "gn:admin1_code":"6.0",
    "gn:asciiname":"Sinheung Illi",
    "gn:country_code":"KR",
    "gn:dem":66,
    "gn:feature_class":"P",
    "gn:feature_code":"PPL",
    "gn:name":"Sinheung Illi",
    "gn:population":0,
    "gn:timezone":"Asia/Seoul",
    "iso:country":"KR",
    "name:kor_x_preferred":[
        "\uc2e0\ud765\uc77c\ub9ac"
    ],
    "name:kor_x_variant":[
        "\uc2e0\ud7651\ub9ac"
    ],
    "name:und_x_variant":[
        "Sinh\u016dngch\u2019on",
        "\uc2e0\ud765\ucd0c",
        "Sinheung Illi",
        "Sinheung 1 Ri"
    ],
    "wof:name":"Sinheung Illi",
    "wof:placetype":"locality"
},
  "geometry": {"coordinates":[128.53569999999999,38.20169],"type":"Point"}
}