{
  "type": "Feature",
  "properties": {
    "gn:admin1_code":"14.0",
    "gn:asciiname":"Non-gol",
    "gn:country_code":"KR",
    "gn:dem":41,
    "gn:feature_class":"P",
    "gn:feature_code":"PPL",
    "gn:name":"Non-gol",
    "gn:population":0,
    "gn:timezone":"Asia/Seoul",
    "iso:country":"KR",
    "name:und_x_variant":[
        "\ub17c\uace8",
        "Non-gol"
    ],
    "wof:name":"Non-gol",
    "wof:placetype":"locality"
},
  "geometry": {"coordinates":[128.35658999999998,35.64493],"type":"Point"}
}