{
  "type": "Feature",
  "properties": {
    "gn:admin1_code":"21.0",
    "gn:asciiname":"Chijeon",
    "gn:country_code":"KR",
    "gn:dem":11,
    "gn:feature_class":"P",
    "gn:feature_code":"PPL",
    "gn:name":"Chijeon",
    "gn:population":0,
    "gn:timezone":"Asia/Seoul",
    "iso:country":"KR",
    "name:kor_x_preferred":[
        "\uce58\uc804"
    ],
    "wof:name":"Chijeon",
    "wof:placetype":"locality"
},
  "geometry": {"coordinates":[129.38593,35.54352],"type":"Point"}
}