{
  "type": "Feature",
  "properties": {
    "gn:admin1_code":"14.0",
    "gn:asciiname":"Chik-tong",
    "gn:country_code":"KR",
    "gn:dem":134,
    "gn:feature_class":"P",
    "gn:feature_code":"PPL",
    "gn:name":"Chik-tong",
    "gn:population":0,
    "gn:timezone":"Asia/Seoul",
    "iso:country":"KR",
    "name:eng_x_preferred":[
        "Chik"
    ],
    "name:eng_x_variant":[
        "Chik-tong"
    ],
    "name:und_x_variant":[
        "\uc9c1\ub3d9"
    ],
    "wof:name":"Chik",
    "wof:placetype":"locality"
},
  "geometry": {"coordinates":[128.0694,36.1609],"type":"Point"}
}