{
  "type": "Feature",
  "properties": {
    "gn:admin1_code":"16.0",
    "gn:asciiname":"Haenggundong",
    "gn:country_code":"KR",
    "gn:dem":43,
    "gn:feature_class":"P",
    "gn:feature_code":"PPL",
    "gn:name":"Haenggundong",
    "gn:population":0,
    "gn:timezone":"Asia/Seoul",
    "iso:country":"KR",
    "name:kor_x_preferred":[
        "\ud589\uad70\ub3d9"
    ],
    "wof:name":"Haenggundong",
    "wof:placetype":"locality"
},
  "geometry": {"coordinates":[126.6968,34.86945],"type":"Point"}
}