{
  "type": "Feature",
  "properties": {
    "gn:admin1_code":"15.0",
    "gn:asciiname":"Naesan",
    "gn:country_code":"KR",
    "gn:dem":355,
    "gn:feature_class":"P",
    "gn:feature_code":"PPL",
    "gn:name":"Naesan",
    "gn:population":0,
    "gn:timezone":"Asia/Seoul",
    "iso:country":"KR",
    "name:und_x_variant":[
        "Naesan-dong",
        "\ub0b4\uc0b0",
        "Naesan"
    ],
    "wof:name":"Naesan",
    "wof:placetype":"locality"
},
  "geometry": {"coordinates":[128.50271999999998,35.71534000000001],"type":"Point"}
}