{
  "type": "Feature",
  "properties": {
    "gn:admin1_code":"16.0",
    "gn:asciiname":"Sil-li",
    "gn:country_code":"KR",
    "gn:dem":26,
    "gn:feature_class":"P",
    "gn:feature_code":"PPL",
    "gn:name":"Sil-li",
    "gn:population":0,
    "gn:timezone":"Asia/Seoul",
    "iso:country":"KR",
    "name:kor_x_preferred":[
        "\uc2e0\ub9ac"
    ],
    "name:und_x_variant":[
        "Sin-ni",
        "Sil-li"
    ],
    "wof:name":"Sil-li",
    "wof:placetype":"locality"
},
  "geometry": {"coordinates":[126.52333,34.54361],"type":"Point"}
}