{
  "type": "Feature",
  "properties": {
    "gn:admin1_code":"20.0",
    "gn:asciiname":"Sonso-ri",
    "gn:country_code":"KR",
    "gn:dem":19,
    "gn:feature_class":"P",
    "gn:feature_code":"PPL",
    "gn:name":"S\u014fnso-ri",
    "gn:population":0,
    "gn:timezone":"Asia/Seoul",
    "iso:country":"KR",
    "name:und_x_variant":[
        "\uc120\uc18c\ub9ac",
        "S\u014fnso",
        "S\u014fnso-ri"
    ],
    "wof:name":"Sonso-ri",
    "wof:placetype":"locality"
},
  "geometry": {"coordinates":[128.4229,35.51722],"type":"Point"}
}