{
  "type": "Feature",
  "properties": {
    "gn:admin1_code":"13.0",
    "gn:admin2_code":"P'aju-si",
    "gn:asciiname":"Sonoewol",
    "gn:country_code":"KR",
    "gn:dem":33,
    "gn:feature_class":"P",
    "gn:feature_code":"PPL",
    "gn:name":"Sonoewol",
    "gn:population":0,
    "gn:timezone":"Asia/Seoul",
    "iso:country":"KR",
    "name:kor_x_preferred":[
        "\uc18c\ub1cc\uc6d4"
    ],
    "name:und_x_variant":[
        "Sonoeul",
        "Sonoew\u014fl",
        "Sonoewol"
    ],
    "wof:name":"Sonoewol",
    "wof:placetype":"locality"
},
  "geometry": {"coordinates":[126.81629,37.77042],"type":"Point"}
}