{
  "type": "Feature",
  "properties": {
    "gn:admin1_code":"14.0",
    "gn:asciiname":"Araennabang",
    "gn:country_code":"KR",
    "gn:dem":417,
    "gn:feature_class":"P",
    "gn:feature_code":"PPL",
    "gn:name":"Araennabang",
    "gn:population":0,
    "gn:timezone":"Asia/Seoul",
    "iso:country":"KR",
    "name:und_x_variant":[
        "\uc544\ub7ab\ub098\ubc29",
        "Araennabang"
    ],
    "wof:name":"Araennabang",
    "wof:placetype":"locality"
},
  "geometry": {"coordinates":[129.0823,36.6869],"type":"Point"}
}