{
  "type": "Feature",
  "properties": {
    "gn:admin1_code":"17.0",
    "gn:asciiname":"Chongja-dong",
    "gn:country_code":"KR",
    "gn:dem":67,
    "gn:feature_class":"P",
    "gn:feature_code":"PPL",
    "gn:name":"Ch\u014fngja-dong",
    "gn:population":0,
    "gn:timezone":"Asia/Seoul",
    "iso:country":"KR",
    "name:und_x_variant":[
        "\uc815\uc790\ub3d9",
        "Ch\u014fngja-dong"
    ],
    "wof:name":"Chongja-dong",
    "wof:placetype":"locality"
},
  "geometry": {"coordinates":[126.3792,36.7968],"type":"Point"}
}