{
  "type": "Feature",
  "properties": {
    "gn:admin1_code":"20.0",
    "gn:asciiname":"Yulch'i-ri",
    "gn:country_code":"KR",
    "gn:dem":5,
    "gn:feature_class":"P",
    "gn:feature_code":"PPL",
    "gn:name":"Yulch\u2019i-ri",
    "gn:population":0,
    "gn:timezone":"Asia/Seoul",
    "iso:country":"KR",
    "name:und_x_variant":[
        "\uc728\uce58\ub9ac",
        "Yulch\u2019i-ri"
    ],
    "wof:name":"Yulch'i-ri",
    "wof:placetype":"locality"
},
  "geometry": {"coordinates":[128.46109999999999,35.10572],"type":"Point"}
}