{
  "type": "Feature",
  "properties": {
    "gn:admin1_code":"5.0",
    "gn:asciiname":"Eumdalmal",
    "gn:country_code":"KR",
    "gn:dem":95,
    "gn:feature_class":"P",
    "gn:feature_code":"PPL",
    "gn:name":"Eumdalmal",
    "gn:population":0,
    "gn:timezone":"Asia/Seoul",
    "iso:country":"KR",
    "name:kor_x_preferred":[
        "\uc74c\ub2ec\ub9d0"
    ],
    "wof:name":"Eumdalmal",
    "wof:placetype":"locality"
},
  "geometry": {"coordinates":[127.5628,36.94073],"type":"Point"}
}