{
  "type": "Feature",
  "properties": {
    "gn:admin1_code":"14.0",
    "gn:asciiname":"Jeongjigol",
    "gn:country_code":"KR",
    "gn:dem":296,
    "gn:feature_class":"P",
    "gn:feature_code":"PPL",
    "gn:name":"Jeongjigol",
    "gn:population":0,
    "gn:timezone":"Asia/Seoul",
    "iso:country":"KR",
    "name:kor_x_preferred":[
        "\uc815\uc9c0\uace8"
    ],
    "wof:name":"Jeongjigol",
    "wof:placetype":"locality"
},
  "geometry": {"coordinates":[128.94524999999999,36.75244],"type":"Point"}
}