{
  "type": "Feature",
  "properties": {
    "gn:admin1_code":"16.0",
    "gn:asciiname":"Mun'gwan",
    "gn:country_code":"KR",
    "gn:dem":10,
    "gn:feature_class":"P",
    "gn:feature_code":"PPL",
    "gn:name":"Mun\u2019gwan",
    "gn:population":0,
    "gn:timezone":"Asia/Seoul",
    "iso:country":"KR",
    "name:kor_x_preferred":[
        "\ubb38\uad00"
    ],
    "name:kor_x_variant":[
        "Mun\u2019gwan"
    ],
    "name:und_x_variant":[
        "Mun\u2019got",
        "Mun\u2019gwan-ni"
    ],
    "wof:name":"Mun'gwan",
    "wof:placetype":"locality"
},
  "geometry": {"coordinates":[127.19982,34.57767],"type":"Point"}
}