{
  "type": "Feature",
  "properties": {
    "gn:admin1_code":"17.0",
    "gn:asciiname":"Nopun'gogae",
    "gn:country_code":"KR",
    "gn:dem":34,
    "gn:feature_class":"P",
    "gn:feature_code":"PPL",
    "gn:name":"Nop\u016dn\u2019gogae",
    "gn:population":0,
    "gn:timezone":"Asia/Seoul",
    "iso:country":"KR",
    "name:und_x_variant":[
        "Kohy\u014fn-ni",
        "\ub192\uc740\uace0\uac1c",
        "Nop\u016dn\u2019gogae"
    ],
    "wof:name":"Nopun'gogae",
    "wof:placetype":"locality"
},
  "geometry": {"coordinates":[126.2433,36.7917],"type":"Point"}
}