{
  "type": "Feature",
  "properties": {
    "gn:admin1_code":"6.0",
    "gn:asciiname":"Dochon-ri",
    "gn:country_code":"KR",
    "gn:dem":215,
    "gn:feature_class":"P",
    "gn:feature_code":"PPL",
    "gn:name":"Dochon-ri",
    "gn:population":0,
    "gn:timezone":"Asia/Seoul",
    "iso:country":"KR",
    "name:kor_x_preferred":[
        "\ub3c4\ucd0c\ub9ac"
    ],
    "name:und_x_variant":[
        "Toch\u2019ol-li",
        "Dochon-ri"
    ],
    "wof:name":"Dochon-ri",
    "wof:placetype":"locality"
},
  "geometry": {"coordinates":[128.02167,38.07806],"type":"Point"}
}