{
  "type": "Feature",
  "properties": {
    "gn:admin1_code":"5.0",
    "gn:asciiname":"Changnae",
    "gn:country_code":"KR",
    "gn:dem":166,
    "gn:feature_class":"P",
    "gn:feature_code":"PPL",
    "gn:name":"Changnae",
    "gn:population":0,
    "gn:timezone":"Asia/Seoul",
    "iso:country":"KR",
    "name:und_x_variant":[
        "\uc7a5\ub0b4",
        "Changnae"
    ],
    "wof:name":"Changnae",
    "wof:placetype":"locality"
},
  "geometry": {"coordinates":[127.7873,36.4713],"type":"Point"}
}