{
  "type": "Feature",
  "properties": {
    "gn:admin1_code":"6.0",
    "gn:asciiname":"Hant'an",
    "gn:country_code":"KR",
    "gn:dem":276,
    "gn:feature_class":"P",
    "gn:feature_code":"PPL",
    "gn:name":"Hant\u2019an",
    "gn:population":0,
    "gn:timezone":"Asia/Seoul",
    "iso:country":"KR",
    "wof:name":"Hant'an",
    "wof:placetype":"locality"
},
  "geometry": {"coordinates":[128.51722000000001,37.31611],"type":"Point"}
}