{
  "type": "Feature",
  "properties": {
    "gn:admin1_code":"12.0",
    "gn:asciiname":"Jinchon",
    "gn:country_code":"KR",
    "gn:dem":20,
    "gn:feature_class":"P",
    "gn:feature_code":"PPL",
    "gn:name":"Jinchon",
    "gn:population":0,
    "gn:timezone":"Asia/Seoul",
    "iso:country":"KR",
    "name:und_x_variant":[
        "\uc9c4\ucd0c",
        "Jinchon",
        "Chin-ch\u2019on"
    ],
    "wof:name":"Jinchon",
    "wof:placetype":"locality"
},
  "geometry": {"coordinates":[126.33583,37.54533],"type":"Point"}
}