{
  "type": "Feature",
  "properties": {
    "gn:admin1_code":"16.0",
    "gn:asciiname":"Wonhwangnyong",
    "gn:country_code":"KR",
    "gn:dem":45,
    "gn:feature_class":"P",
    "gn:feature_code":"PPL",
    "gn:name":"Wonhwangnyong",
    "gn:population":0,
    "gn:timezone":"Asia/Seoul",
    "iso:country":"KR",
    "name:kor_x_preferred":[
        "\uc6d0\ud669\ub8e1"
    ],
    "wof:name":"Wonhwangnyong",
    "wof:placetype":"locality"
},
  "geometry": {"coordinates":[126.74652,35.27841],"type":"Point"}
}