{
  "type": "Feature",
  "properties": {
    "gn:admin1_code":"20.0",
    "gn:asciiname":"Tubang-dong",
    "gn:country_code":"KR",
    "gn:dem":83,
    "gn:feature_class":"P",
    "gn:feature_code":"PPL",
    "gn:name":"Tubang-dong",
    "gn:population":0,
    "gn:timezone":"Asia/Seoul",
    "iso:country":"KR",
    "name:und_x_variant":[
        "\ub450\ubc29\ub3d9",
        "Tubang-dong"
    ],
    "wof:name":"Tubang-dong",
    "wof:placetype":"locality"
},
  "geometry": {"coordinates":[128.29172,35.53258],"type":"Point"}
}