{
  "type": "Feature",
  "properties": {
    "gn:admin1_code":"3.0",
    "gn:asciiname":"Sindok",
    "gn:country_code":"KR",
    "gn:dem":35,
    "gn:feature_class":"P",
    "gn:feature_code":"PPL",
    "gn:name":"Sind\u014fk",
    "gn:population":0,
    "gn:timezone":"Asia/Seoul",
    "iso:country":"KR",
    "name:und_x_variant":[
        "\uc2e0\ub355",
        "Sind\u014fk"
    ],
    "wof:name":"Sindok",
    "wof:placetype":"locality"
},
  "geometry": {"coordinates":[127.1815,35.95330999999999],"type":"Point"}
}