{
  "type": "Feature",
  "properties": {
    "gn:admin1_code":"1.0",
    "gn:admin2_code":"Namjeju-gun",
    "gn:asciiname":"Sumang-ni",
    "gn:country_code":"KR",
    "gn:dem":156,
    "gn:feature_class":"P",
    "gn:feature_code":"PPL",
    "gn:name":"Sumang-ni",
    "gn:population":0,
    "gn:timezone":"Asia/Seoul",
    "iso:country":"KR",
    "wof:name":"Sumang-ni",
    "wof:placetype":"locality"
},
  "geometry": {"coordinates":[126.71278,33.32833],"type":"Point"}
}