{
  "type": "Feature",
  "properties": {
    "gn:admin1_code":"16.0",
    "gn:asciiname":"Jindeung",
    "gn:country_code":"KR",
    "gn:dem":14,
    "gn:feature_class":"P",
    "gn:feature_code":"PPL",
    "gn:name":"Jindeung",
    "gn:population":0,
    "gn:timezone":"Asia/Seoul",
    "iso:country":"KR",
    "name:kor_x_preferred":[
        "\uc9c4\ub4f1"
    ],
    "name:kor_x_variant":[
        "Chind\u016dng"
    ],
    "wof:name":"Jindeung",
    "wof:placetype":"locality"
},
  "geometry": {"coordinates":[127.32898,34.74712],"type":"Point"}
}