{
  "type": "Feature",
  "properties": {
    "gn:admin1_code":"16.0",
    "gn:asciiname":"Yongbo",
    "gn:country_code":"KR",
    "gn:dem":48,
    "gn:feature_class":"P",
    "gn:feature_code":"PPL",
    "gn:name":"Y\u014fngbo",
    "gn:population":0,
    "gn:timezone":"Asia/Seoul",
    "iso:country":"KR",
    "name:kor_x_preferred":[
        "\uc601\ubcf4"
    ],
    "name:kor_x_variant":[
        "Y\u014fngbo"
    ],
    "wof:name":"Yongbo",
    "wof:placetype":"locality"
},
  "geometry": {"coordinates":[126.90389,34.48806],"type":"Point"}
}