{
  "type": "Feature",
  "properties": {
    "gn:admin1_code":"6.0",
    "gn:asciiname":"Omu",
    "gn:country_code":"KR",
    "gn:dem":308,
    "gn:feature_class":"P",
    "gn:feature_code":"PPL",
    "gn:name":"Omu",
    "gn:population":0,
    "gn:timezone":"Asia/Seoul",
    "iso:country":"KR",
    "name:ceb_x_preferred":[
        "Omu"
    ],
    "name:kor_x_preferred":[
        "\uc624\ubb34"
    ],
    "name:swe_x_preferred":[
        "Omu"
    ],
    "wof:name":"Omu",
    "wof:placetype":"locality"
},
  "geometry": {"coordinates":[128.57759999999999,37.1952],"type":"Point"}
}