{
  "type": "Feature",
  "properties": {
    "gn:admin1_code":"6.0",
    "gn:asciiname":"T'aep'yong",
    "gn:country_code":"KR",
    "gn:dem":93,
    "gn:feature_class":"P",
    "gn:feature_code":"PPL",
    "gn:name":"T\u2019aep\u2019y\u014fng",
    "gn:population":0,
    "gn:timezone":"Asia/Seoul",
    "iso:country":"KR",
    "name:und_x_variant":[
        "\ud0dc\ud3c9",
        "T\u2019aep\u2019y\u014fng"
    ],
    "wof:name":"T'aep'yong",
    "wof:placetype":"locality"
},
  "geometry": {"coordinates":[127.70627,37.80951],"type":"Point"}
}