{
  "type": "Feature",
  "properties": {
    "gn:admin1_code":"13.0",
    "gn:asciiname":"Araethongjeok",
    "gn:country_code":"KR",
    "gn:dem":176,
    "gn:feature_class":"P",
    "gn:feature_code":"PPL",
    "gn:name":"Araethongjeok",
    "gn:population":0,
    "gn:timezone":"Asia/Seoul",
    "iso:country":"KR",
    "name:kor_x_preferred":[
        "\uc544\ub7ab\ud64d\uc801"
    ],
    "name:und_x_variant":[
        "\ud64d\uc801",
        "Hongj\u014fk",
        "Araethongjeok"
    ],
    "wof:name":"Araethongjeok",
    "wof:placetype":"locality"
},
  "geometry": {"coordinates":[127.57216,37.9394],"type":"Point"}
}