{
  "type": "Feature",
  "properties": {
    "gn:admin1_code":"16.0",
    "gn:asciiname":"Yongjon",
    "gn:country_code":"KR",
    "gn:dem":47,
    "gn:feature_class":"P",
    "gn:feature_code":"PPL",
    "gn:name":"Yongj\u014fn",
    "gn:population":0,
    "gn:timezone":"Asia/Seoul",
    "iso:country":"KR",
    "name:kor_x_preferred":[
        "\uc6a9\uc804"
    ],
    "name:kor_x_variant":[
        "Yongj\u014fn"
    ],
    "wof:name":"Yongjon",
    "wof:placetype":"locality"
},
  "geometry": {"coordinates":[126.62166999999999,34.50472],"type":"Point"}
}