{
  "type": "Feature",
  "properties": {
    "gn:admin1_code":"14.0",
    "gn:asciiname":"Saenggeumbiri",
    "gn:country_code":"KR",
    "gn:dem":463,
    "gn:feature_class":"P",
    "gn:feature_code":"PPL",
    "gn:name":"Saenggeumbiri",
    "gn:population":0,
    "gn:timezone":"Asia/Seoul",
    "iso:country":"KR",
    "name:kor_x_preferred":[
        "\uc0dd\uae08\ube44\ub9ac"
    ],
    "wof:name":"Saenggeumbiri",
    "wof:placetype":"locality"
},
  "geometry": {"coordinates":[129.02888999999999,35.65047],"type":"Point"}
}