{
  "type": "Feature",
  "properties": {
    "gn:admin1_code":"13.0",
    "gn:asciiname":"Ut-maeul",
    "gn:country_code":"KR",
    "gn:dem":169,
    "gn:feature_class":"P",
    "gn:feature_code":"PPL",
    "gn:name":"Ut-maeul",
    "gn:population":0,
    "gn:timezone":"Asia/Seoul",
    "iso:country":"KR",
    "name:und_x_variant":[
        "\uc6c3\ub9c8\uc744",
        "Ut-maeul",
        "Un-ma\u016dl"
    ],
    "wof:name":"Ut-maeul",
    "wof:placetype":"locality"
},
  "geometry": {"coordinates":[127.4725,37.40833],"type":"Point"}
}