{
  "type": "Feature",
  "properties": {
    "gn:admin1_code":"16.0",
    "gn:asciiname":"Ponghwang-ni",
    "gn:country_code":"KR",
    "gn:dem":103,
    "gn:feature_class":"P",
    "gn:feature_code":"PPL",
    "gn:name":"Ponghwang-ni",
    "gn:population":0,
    "gn:timezone":"Asia/Seoul",
    "iso:country":"KR",
    "name:kor_x_preferred":[
        "\ud48d\ud669\ub9ac"
    ],
    "name:und_x_variant":[
        "H\u014d\u014d-ri",
        "Ponghwang-ni"
    ],
    "wof:name":"Ponghwang-ni",
    "wof:placetype":"locality"
},
  "geometry": {"coordinates":[126.69611,34.55222],"type":"Point"}
}