{
  "type": "Feature",
  "properties": {
    "gn:admin1_code":"16.0",
    "gn:asciiname":"Tongam-ni",
    "gn:cc2":"KR",
    "gn:country_code":"KR",
    "gn:dem":15,
    "gn:feature_class":"P",
    "gn:feature_code":"PPL",
    "gn:name":"Tongam-ni",
    "gn:population":0,
    "gn:timezone":"Asia/Seoul",
    "iso:country":"KR",
    "name:und_x_variant":[
        "W\u014fndongam",
        "Tongam-ni"
    ],
    "wof:name":"Tongam-ni",
    "wof:placetype":"locality"
},
  "geometry": {"coordinates":[126.36639,35.00083],"type":"Point"}
}