{
  "type": "Feature",
  "properties": {
    "gn:admin1_code":"16.0",
    "gn:admin2_code":"Chindo-gun",
    "gn:asciiname":"Chindo",
    "gn:country_code":"KR",
    "gn:dem":12,
    "gn:feature_class":"P",
    "gn:feature_code":"PPL",
    "gn:name":"Chindo",
    "gn:population":0,
    "gn:timezone":"Asia/Seoul",
    "iso:country":"KR",
    "name:und_x_variant":[
        "Chint\u014d",
        "Chindo"
    ],
    "wof:name":"Chindo",
    "wof:placetype":"locality"
},
  "geometry": {"coordinates":[126.265,34.48389],"type":"Point"}
}