{
  "type": "Feature",
  "properties": {
    "gn:admin1_code":"16.0",
    "gn:admin2_code":"Chindo-gun",
    "gn:asciiname":"Chindo",
    "gn:country_code":"KR",
    "gn:dem":12,
    "gn:feature_class":"P",
    "gn:feature_code":"PPL",
    "gn:name":"Chindo",
    "gn:population":0,
    "gn:timezone":"Asia/Seoul",
    "iso:country":"KR",
    "name:ara_x_preferred":[
        "\u062c\u0646\u062f\u0648"
    ],
    "name:ceb_x_preferred":[
        "Jindo-gun"
    ],
    "name:deu_x_preferred":[
        "Jindo-gun"
    ],
    "name:fas_x_preferred":[
        "\u0634\u0647\u0631\u0633\u062a\u0627\u0646 \u062c\u06cc\u0646\u062f\u0648"
    ],
    "name:jpn_x_preferred":[
        "\u73cd\u5cf6\u90e1"
    ],
    "name:kor_x_preferred":[
        "\uc9c4\ub3c4\uad70"
    ],
    "name:mon_x_preferred":[
        "\u0427\u0438\u043d\u044c\u0434\u0443-\u0433\u04af\u043d\u044c"
    ],
    "name:spa_x_preferred":[
        "Jindo-gun"
    ],
    "name:swe_x_preferred":[
        "Jindo"
    ],
    "name:und_x_variant":[
        "Chint\u014d",
        "Chindo"
    ],
    "name:urd_x_preferred":[
        "\u062c\u0646\u062f\u0648 \u06a9\u0627\u0624\u0646\u0679\u06cc"
    ],
    "name:vie_x_preferred":[
        "Jindo"
    ],
    "name:zho_x_preferred":[
        "\u73cd\u5cf6\u90e1"
    ],
    "wof:name":"Chindo",
    "wof:placetype":"locality"
},
  "geometry": {"coordinates":[126.265,34.48389],"type":"Point"}
}