{
  "type": "Feature",
  "properties": {
    "gn:admin1_code":"13.0",
    "gn:asciiname":"Jumi-gol",
    "gn:country_code":"KR",
    "gn:dem":68,
    "gn:feature_class":"P",
    "gn:feature_code":"PPL",
    "gn:name":"Jumi-gol",
    "gn:population":0,
    "gn:timezone":"Asia/Seoul",
    "iso:country":"KR",
    "name:kor_x_preferred":[
        "\uc8fc\ubbf8\uace8"
    ],
    "wof:name":"Jumi-gol",
    "wof:placetype":"locality"
},
  "geometry": {"coordinates":[126.85472,37.20611],"type":"Point"}
}