{
  "type": "Feature",
  "properties": {
    "gn:admin1_code":"6.0",
    "gn:asciiname":"Mulgubi",
    "gn:country_code":"KR",
    "gn:dem":426,
    "gn:feature_class":"P",
    "gn:feature_code":"PPL",
    "gn:name":"Mulgubi",
    "gn:population":0,
    "gn:timezone":"Asia/Seoul",
    "iso:country":"KR",
    "name:kor_x_preferred":[
        "\ubb3c\uad6c\ube44"
    ],
    "wof:name":"Mulgubi",
    "wof:placetype":"locality"
},
  "geometry": {"coordinates":[128.19820000000001,37.3518],"type":"Point"}
}