{
  "type": "Feature",
  "properties": {
    "gn:admin1_code":"17.0",
    "gn:asciiname":"Kamamot",
    "gn:cc2":"KR",
    "gn:country_code":"KR",
    "gn:dem":13,
    "gn:feature_class":"P",
    "gn:feature_code":"PPL",
    "gn:name":"Kamamot",
    "gn:population":0,
    "gn:timezone":"Asia/Seoul",
    "iso:country":"KR",
    "name:und_x_variant":[
        "Puji-ri",
        "Kamamot"
    ],
    "wof:name":"Kamamot",
    "wof:placetype":"locality"
},
  "geometry": {"coordinates":[126.71666999999999,36.88333],"type":"Point"}
}