{
  "type": "Feature",
  "properties": {
    "gn:admin1_code":"3.0",
    "gn:asciiname":"Sunch'ang",
    "gn:country_code":"KR",
    "gn:dem":90,
    "gn:feature_class":"P",
    "gn:feature_code":"PPL",
    "gn:name":"Sunch\u2019ang",
    "gn:population":0,
    "gn:timezone":"Asia/Seoul",
    "iso:country":"KR",
    "name:kor_x_preferred":[
        "\uc21c\ucc3d\ucd08\ub4f1\ud559\uad50"
    ],
    "name:und_x_variant":[
        "Junsh\u014d",
        "Junch\u2019ang",
        "Sunch\u2019ang",
        "Sunchang-chodeunghakgyo"
    ],
    "wof:name":"Sunch'ang",
    "wof:placetype":"locality"
},
  "geometry": {"coordinates":[127.14278,35.37361],"type":"Point"}
}