{
  "type": "Feature",
  "properties": {
    "gn:admin1_code":"16.0",
    "gn:asciiname":"Sanjeong",
    "gn:country_code":"KR",
    "gn:dem":108,
    "gn:feature_class":"P",
    "gn:feature_code":"PPL",
    "gn:name":"Sanjeong",
    "gn:population":0,
    "gn:timezone":"Asia/Seoul",
    "iso:country":"KR",
    "name:kor_x_preferred":[
        "\uc0b0\uc815"
    ],
    "name:kor_x_variant":[
        "Sanj\u014fng"
    ],
    "wof:name":"Sanjeong",
    "wof:placetype":"locality"
},
  "geometry": {"coordinates":[126.94989,34.69725],"type":"Point"}
}