{
  "type": "Feature",
  "properties": {
    "gn:admin1_code":"6.0",
    "gn:asciiname":"Budong",
    "gn:country_code":"KR",
    "gn:dem":214,
    "gn:feature_class":"P",
    "gn:feature_code":"PPL",
    "gn:name":"Budong",
    "gn:population":0,
    "gn:timezone":"Asia/Seoul",
    "iso:country":"KR",
    "name:kor_x_preferred":[
        "\uac00\ub9c8\uace8"
    ],
    "name:kor_x_variant":[
        "\ubd80\ub3d9"
    ],
    "name:und_x_variant":[
        "Pu-dong",
        "Kama-gol",
        "Budong"
    ],
    "wof:name":"Budong",
    "wof:placetype":"locality"
},
  "geometry": {"coordinates":[128.79329999999999,37.72055],"type":"Point"}
}