{
  "type": "Feature",
  "properties": {
    "gn:admin1_code":"13.0",
    "gn:asciiname":"Sanghyeon",
    "gn:country_code":"KR",
    "gn:dem":16,
    "gn:feature_class":"P",
    "gn:feature_code":"PPL",
    "gn:name":"Sanghyeon",
    "gn:population":0,
    "gn:timezone":"Asia/Seoul",
    "iso:country":"KR",
    "name:und_x_variant":[
        "\uc0c1\ud604",
        "Sanghyeon",
        "Sanghy\u014fn"
    ],
    "wof:name":"Sanghyeon",
    "wof:placetype":"locality"
},
  "geometry": {"coordinates":[126.9828,37.0673],"type":"Point"}
}