{
  "type": "Feature",
  "properties": {
    "gn:admin1_code":"14.0",
    "gn:asciiname":"Omgogae",
    "gn:country_code":"KR",
    "gn:dem":181,
    "gn:feature_class":"P",
    "gn:feature_code":"PPL",
    "gn:name":"Omgogae",
    "gn:population":0,
    "gn:timezone":"Asia/Seoul",
    "iso:country":"KR",
    "name:und_x_variant":[
        "\u014emhy\u014fn"
    ],
    "wof:name":"Omgogae",
    "wof:placetype":"locality"
},
  "geometry": {"coordinates":[128.65000000000001,36.31667],"type":"Point"}
}