{
  "type": "Feature",
  "properties": {
    "gn:admin1_code":"21.0",
    "gn:asciiname":"Jukjeongok",
    "gn:country_code":"KR",
    "gn:dem":18,
    "gn:feature_class":"P",
    "gn:feature_code":"PPL",
    "gn:name":"Jukjeongok",
    "gn:population":0,
    "gn:timezone":"Asia/Seoul",
    "iso:country":"KR",
    "name:kor_x_preferred":[
        "\uc8fd\uc804\uace1"
    ],
    "wof:name":"Jukjeongok",
    "wof:placetype":"locality"
},
  "geometry": {"coordinates":[129.37203,35.56595],"type":"Point"}
}