{
  "type": "Feature",
  "properties": {
    "gn:admin1_code":"14.0",
    "gn:asciiname":"Jugan",
    "gn:country_code":"KR",
    "gn:dem":170,
    "gn:feature_class":"P",
    "gn:feature_code":"PPL",
    "gn:name":"Jugan",
    "gn:population":0,
    "gn:timezone":"Asia/Seoul",
    "iso:country":"KR",
    "name:kor_x_preferred":[
        "\uc8fd\uc548"
    ],
    "wof:name":"Jugan",
    "wof:placetype":"locality"
},
  "geometry": {"coordinates":[128.34518,36.66587],"type":"Point"}
}