{
  "type": "Feature",
  "properties": {
    "gn:admin1_code":"14.0",
    "gn:asciiname":"Sottong-gol",
    "gn:country_code":"KR",
    "gn:dem":311,
    "gn:feature_class":"P",
    "gn:feature_code":"PPL",
    "gn:name":"Sottong-gol",
    "gn:population":0,
    "gn:timezone":"Asia/Seoul",
    "iso:country":"KR",
    "name:und_x_variant":[
        "\uc18c\ub625\uace8",
        "Sottong-gol"
    ],
    "wof:name":"Sottong-gol",
    "wof:placetype":"locality"
},
  "geometry": {"coordinates":[129.1294,36.21784],"type":"Point"}
}