{
  "type": "Feature",
  "properties": {
    "gn:admin1_code":"14.0",
    "gn:asciiname":"Gungni",
    "gn:country_code":"KR",
    "gn:dem":126,
    "gn:feature_class":"P",
    "gn:feature_code":"PPL",
    "gn:name":"Gungni",
    "gn:population":0,
    "gn:timezone":"Asia/Seoul",
    "iso:country":"KR",
    "name:kor_x_preferred":[
        "\uad6d\ub9ac"
    ],
    "name:und_x_variant":[
        "Kung-ni"
    ],
    "wof:name":"Gungni",
    "wof:placetype":"locality"
},
  "geometry": {"coordinates":[128.52694,36.50761],"type":"Point"}
}