{
  "type": "Feature",
  "properties": {
    "gn:admin1_code":"13.0",
    "gn:asciiname":"Mejigol",
    "gn:country_code":"KR",
    "gn:dem":43,
    "gn:feature_class":"P",
    "gn:feature_code":"PPL",
    "gn:name":"Mejigol",
    "gn:population":0,
    "gn:timezone":"Asia/Seoul",
    "iso:country":"KR",
    "name:kor_x_preferred":[
        "\uba54\uc9c0\uace8"
    ],
    "wof:name":"Mejigol",
    "wof:placetype":"locality"
},
  "geometry": {"coordinates":[126.88903000000001,37.68327],"type":"Point"}
}