{
  "type": "Feature",
  "properties": {
    "gn:admin1_code":"20.0",
    "gn:asciiname":"Gumbawi",
    "gn:country_code":"KR",
    "gn:dem":113,
    "gn:feature_class":"P",
    "gn:feature_code":"PPL",
    "gn:name":"Gumbawi",
    "gn:population":0,
    "gn:timezone":"Asia/Seoul",
    "iso:country":"KR",
    "name:kor_x_preferred":[
        "\uad7c\ubc14\uc704"
    ],
    "wof:name":"Gumbawi",
    "wof:placetype":"locality"
},
  "geometry": {"coordinates":[129.15741,35.39144],"type":"Point"}
}