{
  "type": "Feature",
  "properties": {
    "gn:admin1_code":"6.0",
    "gn:asciiname":"Wolgol",
    "gn:country_code":"KR",
    "gn:dem":148,
    "gn:feature_class":"P",
    "gn:feature_code":"PPL",
    "gn:name":"Wolgol",
    "gn:population":0,
    "gn:timezone":"Asia/Seoul",
    "iso:country":"KR",
    "name:kor_x_preferred":[
        "\uc6d4\uace8"
    ],
    "name:und_x_variant":[
        "\uc6d4\uad74",
        "W\u014fl-gol",
        "W\u014flgul",
        "Wolgol"
    ],
    "wof:name":"Wolgol",
    "wof:placetype":"locality"
},
  "geometry": {"coordinates":[127.67316,37.92058],"type":"Point"}
}