{
  "type": "Feature",
  "properties": {
    "gn:admin1_code":"17.0",
    "gn:asciiname":"P'ungjol-li",
    "gn:country_code":"KR",
    "gn:dem":22,
    "gn:feature_class":"P",
    "gn:feature_code":"PPL",
    "gn:name":"P\u2019ungj\u014fl-li",
    "gn:population":0,
    "gn:timezone":"Asia/Seoul",
    "iso:country":"KR",
    "name:und_x_variant":[
        "\ud48d\uc804\ub9ac",
        "P\u2019ungj\u014fn-ni",
        "P\u2019ungj\u014fl-li"
    ],
    "wof:name":"P'ungjol-li",
    "wof:placetype":"locality"
},
  "geometry": {"coordinates":[126.4265,36.7724],"type":"Point"}
}