{
  "type": "Feature",
  "properties": {
    "gn:admin1_code":"13.0",
    "gn:asciiname":"Yulchon-ri",
    "gn:country_code":"KR",
    "gn:dem":68,
    "gn:feature_class":"P",
    "gn:feature_code":"PPLL",
    "gn:name":"Yulchon-ri",
    "gn:population":0,
    "gn:timezone":"Asia/Seoul",
    "iso:country":"KR",
    "name:und_x_variant":[
        "\uc728\ucd0c\ub9ac",
        "Yulchon-ri",
        "Yulch\u2019ol-li"
    ],
    "wof:name":"Yulchon-ri",
    "wof:placetype":"locality"
},
  "geometry": {"coordinates":[127.58028,37.38472],"type":"Point"}
}