{
  "type": "Feature",
  "properties": {
    "gn:country":"KR",
    "gn:fcode":"PPL",
    "gn:pop":59914,
    "iso:country":"KR",
    "name:kor_x_preferred":[
        "\ud654\uc21c"
    ],
    "name:rus_x_preferred":[
        "\u0425\u0432\u0430\u0441\u0443\u043d"
    ],
    "name:unk_x_variant":[
        "Wajun"
    ],
    "qs:name":"Hwasun",
    "qs:photos_9r":0,
    "qs:photos_sr":0,
    "qs:pop_sr":"8",
    "wd:wordcount":364,
    "wof:name":"Hwasun",
    "wof:placetype":"locality",
    "wof:population":59914
},
  "geometry": {"coordinates":[126.985,35.05944],"type":"Point"}
}