{
  "type": "Feature",
  "properties": {
    "gn:country":"KR",
    "gn:fcode":"PPL",
    "gn:pop":59914,
    "iso:country":"KR",
    "name:ceb_x_preferred":[
        "Hwasun"
    ],
    "name:deu_x_preferred":[
        "Hwasun"
    ],
    "name:eng_x_preferred":[
        "Hwasun County"
    ],
    "name:ita_x_preferred":[
        "Hwasun"
    ],
    "name:jpn_x_preferred":[
        "\u548c\u9806\u90e1"
    ],
    "name:kor_x_preferred":[
        "\ud654\uc21c"
    ],
    "name:kor_x_variant":[
        "\ud654\uc21c\uad70"
    ],
    "name:mon_x_preferred":[
        "\u0425\u0443\u0430\u0441\u04af\u043d\u044c-\u0433\u04af\u043d\u044c"
    ],
    "name:nan_x_preferred":[
        "Hwasun K\u016bn"
    ],
    "name:nld_x_preferred":[
        "Hwasun"
    ],
    "name:nob_x_preferred":[
        "Hwasun"
    ],
    "name:rus_x_preferred":[
        "\u0425\u0432\u0430\u0441\u0443\u043d"
    ],
    "name:spa_x_preferred":[
        "Hwasun"
    ],
    "name:swe_x_preferred":[
        "Hwasun"
    ],
    "name:unk_x_variant":[
        "Wajun"
    ],
    "name:urd_x_preferred":[
        "\u06c1\u0648\u0627\u0633\u0648\u0646 \u06a9\u0627\u0624\u0646\u0679\u06cc"
    ],
    "name:vie_x_preferred":[
        "Hwasun"
    ],
    "name:zho_x_preferred":[
        "\u548c\u9806\u90e1"
    ],
    "qs:name":"Hwasun",
    "qs:photos_9r":0,
    "qs:photos_sr":0,
    "qs:pop_sr":"8",
    "wd:wordcount":364,
    "wof:name":"Hwasun",
    "wof:placetype":"locality",
    "wof:population":59914
},
  "geometry": {"coordinates":[126.985,35.05944],"type":"Point"}
}