{
  "type": "Feature",
  "properties": {
    "iso:country":"KR",
    "name:eng_x_preferred":[
        "Bisan 3(sam)-dong"
    ],
    "name:kor_x_preferred":[
        "\ube44\uc0b03\ub3d9"
    ],
    "name:kor_x_variant":[
        "\ube44\uc0b03",
        "\ube44\uc0b03\ub3d9"
    ],
    "qs:gn_fcode":"PPL",
    "qs:gn_local":0,
    "qs:gn_namadm1":"13",
    "qs:gn_name":"Pisan-dong",
    "qs:local_max":474,
    "qs:local_sum":1333,
    "qs:localhoods":10,
    "qs:name":"\ube44\uc0b03\ub3d9",
    "qs:name_adm0":"\ud55c\uad6d",
    "qs:name_adm1":"\uacbd\uae30\ub3c4",
    "qs:name_adm2":"\uc548\uc591\uc2dc",
    "qs:name_lau":"\ub3d9\uc548\uad6c",
    "qs:name_local":"\ub3d9\uc548\uad6c",
    "qs:photo_max":58,
    "qs:photo_sum":94,
    "qs:placetype":"Suburb",
    "qs:quad_count":9,
    "qs:woe_adm0":23424868,
    "qs:woe_adm1":2345969,
    "qs:woe_adm2":28289110,
    "qs:woe_lau":28997203,
    "qs:woe_local":28997203,
    "qs:woe_ver":"7.10.0",
    "wof:lang":[
        "kor"
    ],
    "wof:name":"Bisan 3(sam)-dong",
    "wof:placetype":"neighbourhood"
},
  "geometry": {"coordinates":[126.96146899999999,37.428988],"type":"Point"}
}