{
  "type": "Feature",
  "properties": {
    "gn:admin1_code":"6.0",
    "gn:asciiname":"Sojae",
    "gn:country_code":"KR",
    "gn:dem":332,
    "gn:feature_class":"P",
    "gn:feature_code":"PPL",
    "gn:name":"Sojae",
    "gn:population":0,
    "gn:timezone":"Asia/Seoul",
    "iso:country":"KR",
    "name:kor_x_preferred":[
        "\uc18c\uc7ac"
    ],
    "wof:name":"Sojae",
    "wof:placetype":"locality"
},
  "geometry": {"coordinates":[128.13943999999998,37.95884],"type":"Point"}
}