{
  "type": "Feature",
  "properties": {
    "gn:admin1_code":"6.0",
    "gn:asciiname":"Eumjichon",
    "gn:country_code":"KR",
    "gn:dem":355,
    "gn:feature_class":"P",
    "gn:feature_code":"PPL",
    "gn:name":"Eumjichon",
    "gn:population":0,
    "gn:timezone":"Asia/Seoul",
    "iso:country":"KR",
    "name:kor_x_preferred":[
        "\uc74c\uc9c0\ucd0c"
    ],
    "wof:name":"Eumjichon",
    "wof:placetype":"locality"
},
  "geometry": {"coordinates":[128.21383,38.22367],"type":"Point"}
}