{
  "type": "Feature",
  "properties": {
    "gn:admin1_code":"6.0",
    "gn:asciiname":"Tohwadok",
    "gn:country_code":"KR",
    "gn:dem":605,
    "gn:feature_class":"P",
    "gn:feature_code":"PPL",
    "gn:name":"Tohwad\u014fk",
    "gn:population":0,
    "gn:timezone":"Asia/Seoul",
    "iso:country":"KR",
    "name:kor_x_preferred":[
        "\ub3c4\ud654\ub355"
    ],
    "name:kor_x_variant":[
        "Tohwad\u014fk"
    ],
    "wof:name":"Tohwadok",
    "wof:placetype":"locality"
},
  "geometry": {"coordinates":[128.4443,37.3961],"type":"Point"}
}