{
  "type": "Feature",
  "properties": {
    "gn:admin1_code":"14.0",
    "gn:asciiname":"Malbaemi",
    "gn:country_code":"KR",
    "gn:dem":52,
    "gn:feature_class":"P",
    "gn:feature_code":"PPL",
    "gn:name":"Malbaemi",
    "gn:population":0,
    "gn:timezone":"Asia/Seoul",
    "iso:country":"KR",
    "name:und_x_variant":[
        "\ub9d0\ubc40\uc774",
        "Malbaemi"
    ],
    "wof:name":"Malbaemi",
    "wof:placetype":"locality"
},
  "geometry": {"coordinates":[128.30001999999999,35.94175999999999],"type":"Point"}
}