{
  "type": "Feature",
  "properties": {
    "gn:admin1_code":"13.0",
    "gn:asciiname":"Araetgoeum",
    "gn:country_code":"KR",
    "gn:dem":111,
    "gn:feature_class":"P",
    "gn:feature_code":"PPL",
    "gn:name":"Araetgoeum",
    "gn:population":0,
    "gn:timezone":"Asia/Seoul",
    "iso:country":"KR",
    "name:kor_x_preferred":[
        "\uc544\ub7ab\uad34\uc6c0"
    ],
    "wof:name":"Araetgoeum",
    "wof:placetype":"locality"
},
  "geometry": {"coordinates":[126.9327,37.80575],"type":"Point"}
}