{
  "type": "Feature",
  "properties": {
    "gn:admin1_code":"16.0",
    "gn:asciiname":"Taman",
    "gn:country_code":"KR",
    "gn:dem":22,
    "gn:feature_class":"P",
    "gn:feature_code":"PPL",
    "gn:name":"Taman",
    "gn:population":0,
    "gn:timezone":"Asia/Seoul",
    "iso:country":"KR",
    "name:kor_x_preferred":[
        "\ub2f4\uc548"
    ],
    "wof:name":"Taman",
    "wof:placetype":"locality"
},
  "geometry": {"coordinates":[127.31589,34.86447],"type":"Point"}
}