{
  "type": "Feature",
  "properties": {
    "gn:admin1_code":"14.0",
    "gn:asciiname":"Kamul-li",
    "gn:country_code":"KR",
    "gn:dem":300,
    "gn:feature_class":"P",
    "gn:feature_code":"PPLL",
    "gn:name":"Kam\u016dl-li",
    "gn:population":0,
    "gn:timezone":"Asia/Seoul",
    "iso:country":"KR",
    "name:und_x_variant":[
        "\uac10\uc740\ub9ac",
        "Kam\u016dl-li"
    ],
    "wof:name":"Kamul-li",
    "wof:placetype":"locality"
},
  "geometry": {"coordinates":[128.93806000000001,36.29285],"type":"Point"}
}