{
  "type": "Feature",
  "properties": {
    "gn:admin1_code":"14.0",
    "gn:asciiname":"Sincheon",
    "gn:country_code":"KR",
    "gn:dem":98,
    "gn:feature_class":"P",
    "gn:feature_code":"PPL",
    "gn:name":"Sincheon",
    "gn:population":0,
    "gn:timezone":"Asia/Seoul",
    "iso:country":"KR",
    "name:kor_x_preferred":[
        "\uc2e0\ucc9c"
    ],
    "name:und_x_variant":[
        "Sinch\u2019on-dong",
        "Sinch\u2019\u014fn",
        "Sincheon"
    ],
    "wof:name":"Sincheon",
    "wof:placetype":"locality"
},
  "geometry": {"coordinates":[128.77789000000001,35.81895],"type":"Point"}
}