{
  "type": "Feature",
  "properties": {
    "gn:admin1_code":"14.0",
    "gn:asciiname":"Kojok-tong",
    "gn:country_code":"KR",
    "gn:dem":332,
    "gn:feature_class":"P",
    "gn:feature_code":"PPL",
    "gn:name":"Koj\u014fk-tong",
    "gn:population":0,
    "gn:timezone":"Asia/Seoul",
    "iso:country":"KR",
    "name:eng_x_preferred":[
        "Kojok"
    ],
    "name:eng_x_variant":[
        "Kojok-tong"
    ],
    "name:und_x_variant":[
        "\uace0\uc801\ub3d9",
        "Koj\u014fk-tong"
    ],
    "wof:name":"Kojok",
    "wof:placetype":"locality"
},
  "geometry": {"coordinates":[129.02301,36.23997],"type":"Point"}
}