{
  "type": "Feature",
  "properties": {
    "gn:admin1_code":"14.0",
    "gn:asciiname":"Wangha",
    "gn:country_code":"KR",
    "gn:dem":325,
    "gn:feature_class":"P",
    "gn:feature_code":"PPL",
    "gn:name":"Wangha",
    "gn:population":0,
    "gn:timezone":"Asia/Seoul",
    "iso:country":"KR",
    "name:und_x_variant":[
        "K\u2019\u016dnma",
        "\ud070\ub9c8"
    ],
    "wof:name":"Wangha",
    "wof:placetype":"locality"
},
  "geometry": {"coordinates":[128.03611000000001,36.32583],"type":"Point"}
}