{
  "type": "Feature",
  "properties": {
    "gn:admin1_code":"20.0",
    "gn:asciiname":"Holgok",
    "gn:country_code":"KR",
    "gn:dem":105,
    "gn:feature_class":"P",
    "gn:feature_code":"PPL",
    "gn:name":"Holgok",
    "gn:population":0,
    "gn:timezone":"Asia/Seoul",
    "iso:country":"KR",
    "wof:name":"Holgok",
    "wof:placetype":"locality"
},
  "geometry": {"coordinates":[128.13333,34.96667],"type":"Point"}
}