{
  "type": "Feature",
  "properties": {
    "gn:admin1_code":"6.0",
    "gn:asciiname":"Kokkyo-ri",
    "gn:country_code":"KR",
    "gn:dem":112,
    "gn:feature_class":"P",
    "gn:feature_code":"PPL",
    "gn:name":"Kokkyo-ri",
    "gn:population":0,
    "gn:timezone":"Asia/Seoul",
    "iso:country":"KR",
    "name:kor_x_preferred":[
        "\uace1\uad50\ub9ac"
    ],
    "wof:name":"Kokkyo-ri",
    "wof:placetype":"locality"
},
  "geometry": {"coordinates":[127.97580000000001,37.4605],"type":"Point"}
}