{
  "type": "Feature",
  "properties": {
    "gn:admin1_code":"13.0",
    "gn:admin2_code":"Ich'\u014fn-si",
    "gn:asciiname":"Deombawi",
    "gn:country_code":"KR",
    "gn:dem":91,
    "gn:feature_class":"P",
    "gn:feature_code":"PPL",
    "gn:name":"Deombawi",
    "gn:population":0,
    "gn:timezone":"Asia/Seoul",
    "iso:country":"KR",
    "name:kor_x_preferred":[
        "\ub364\ubc14\uc704"
    ],
    "name:kor_x_variant":[
        "T\u014fmbawi"
    ],
    "wof:name":"Deombawi",
    "wof:placetype":"locality"
},
  "geometry": {"coordinates":[127.45675,37.18449],"type":"Point"}
}