{
  "type": "Feature",
  "properties": {
    "gn:admin1_code":"14.0",
    "gn:asciiname":"Toma",
    "gn:country_code":"KR",
    "gn:dem":71,
    "gn:feature_class":"P",
    "gn:feature_code":"PPL",
    "gn:name":"Toma",
    "gn:population":0,
    "gn:timezone":"Asia/Seoul",
    "iso:country":"KR",
    "name:ceb_x_preferred":[
        "Toma"
    ],
    "name:deu_x_preferred":[
        "Toma"
    ],
    "name:fas_x_preferred":[
        "\u062a\u0648\u0645\u0627"
    ],
    "name:fra_x_preferred":[
        "Toma"
    ],
    "name:heb_x_preferred":[
        "\u05ea\u05d5\u05de\u05d0"
    ],
    "name:hun_x_preferred":[
        "Toma"
    ],
    "name:hye_x_preferred":[
        "\u054f\u0578\u0574\u0561"
    ],
    "name:ita_x_preferred":[
        "Toma"
    ],
    "name:kor_x_preferred":[
        "\ud1a0\ub9c8"
    ],
    "name:pol_x_preferred":[
        "Toma"
    ],
    "name:por_x_preferred":[
        "Toma"
    ],
    "name:ron_x_preferred":[
        "Toma"
    ],
    "name:rus_x_preferred":[
        "\u0422\u043e\u043c\u0430"
    ],
    "name:spa_x_preferred":[
        "Toma"
    ],
    "name:swe_x_preferred":[
        "Toma"
    ],
    "name:ukr_x_preferred":[
        "\u0422\u043e\u043c\u0430"
    ],
    "name:und_x_variant":[
        "\uc0c8\ub9c8",
        "Saema"
    ],
    "wof:name":"Toma",
    "wof:placetype":"locality"
},
  "geometry": {"coordinates":[128.20226,36.48499],"type":"Point"}
}