{
  "type": "Feature",
  "properties": {
    "gn:admin1_code":"20.0",
    "gn:asciiname":"Homi-dong",
    "gn:country_code":"KR",
    "gn:dem":24,
    "gn:feature_class":"P",
    "gn:feature_code":"PPL",
    "gn:name":"Homi-dong",
    "gn:population":0,
    "gn:timezone":"Asia/Seoul",
    "iso:country":"KR",
    "name:und_x_variant":[
        "\ud638\ubbf8\ub3d9",
        "Homi-dong"
    ],
    "wof:name":"Homi-dong",
    "wof:placetype":"locality"
},
  "geometry": {"coordinates":[128.33166,35.36287],"type":"Point"}
}