{
  "type": "Feature",
  "properties": {
    "gn:admin1_code":"13.0",
    "gn:admin2_code":"P'aju-si",
    "gn:asciiname":"Matgae",
    "gn:country_code":"KR",
    "gn:dem":12,
    "gn:feature_class":"P",
    "gn:feature_code":"PPL",
    "gn:name":"Matgae",
    "gn:population":0,
    "gn:timezone":"Asia/Seoul",
    "iso:country":"KR",
    "name:kor_x_preferred":[
        "\ub9db\uac1c"
    ],
    "name:und_x_variant":[
        "Makkae"
    ],
    "wof:name":"Matgae",
    "wof:placetype":"locality"
},
  "geometry": {"coordinates":[126.79313,37.89558],"type":"Point"}
}