{
  "type": "Feature",
  "properties": {
    "gn:admin1_code":"6.0",
    "gn:asciiname":"Songgaedong",
    "gn:country_code":"KR",
    "gn:dem":371,
    "gn:feature_class":"P",
    "gn:feature_code":"PPL",
    "gn:name":"Songgaedong",
    "gn:population":0,
    "gn:timezone":"Asia/Seoul",
    "iso:country":"KR",
    "name:kor_x_preferred":[
        "\uc194\uac1c\ub3d9"
    ],
    "name:kor_x_variant":[
        "\uc1a1\uac1c\ub3d9"
    ],
    "name:und_x_variant":[
        "Solgae-dong",
        "Songgaedong"
    ],
    "wof:name":"Songgaedong",
    "wof:placetype":"locality"
},
  "geometry": {"coordinates":[128.30823999999998,37.87304],"type":"Point"}
}