{
  "type": "Feature",
  "properties": {
    "gn:admin1_code":"16.0",
    "gn:asciiname":"Sakin-ri",
    "gn:country_code":"KR",
    "gn:dem":41,
    "gn:feature_class":"P",
    "gn:feature_code":"PPL",
    "gn:name":"Sakin-ri",
    "gn:population":0,
    "gn:timezone":"Asia/Seoul",
    "iso:country":"KR",
    "name:kor_x_preferred":[
        "\uc0ac\uae08"
    ],
    "name:kor_x_variant":[
        "Sag\u016dm"
    ],
    "name:und_x_variant":[
        "Sag\u016dm-ni"
    ],
    "wof:name":"Sakin-ri",
    "wof:placetype":"locality"
},
  "geometry": {"coordinates":[126.98333,34.54417],"type":"Point"}
}