{
  "type": "Feature",
  "properties": {
    "gn:admin1_code":"17.0",
    "gn:asciiname":"Hyonam-ni",
    "gn:country_code":"KR",
    "gn:dem":39,
    "gn:feature_class":"P",
    "gn:feature_code":"PPL",
    "gn:name":"Hy\u014fnam-ni",
    "gn:population":0,
    "gn:timezone":"Asia/Seoul",
    "iso:country":"KR",
    "name:eng_x_preferred":[
        "Hyonam"
    ],
    "name:eng_x_variant":[
        "Hyonam-ni"
    ],
    "wof:name":"Hyonam",
    "wof:placetype":"locality"
},
  "geometry": {"coordinates":[126.68861,36.15611],"type":"Point"}
}