{
  "type": "Feature",
  "properties": {
    "gn:admin1_code":"13.0",
    "gn:asciiname":"Dollae",
    "gn:country_code":"KR",
    "gn:dem":13,
    "gn:feature_class":"P",
    "gn:feature_code":"PPL",
    "gn:name":"Dollae",
    "gn:population":0,
    "gn:timezone":"Asia/Seoul",
    "iso:country":"KR",
    "name:und_x_variant":[
        "S\u014fkch\u2019\u014fn-ni",
        "\ub3cc\ub0b4",
        "Dollae",
        "Tollae"
    ],
    "wof:name":"Dollae",
    "wof:placetype":"locality"
},
  "geometry": {"coordinates":[126.90683,37.07663],"type":"Point"}
}