{
  "type": "Feature",
  "properties": {
    "gn:admin1_code":"16.0",
    "gn:asciiname":"Samsan",
    "gn:country_code":"KR",
    "gn:dem":41,
    "gn:feature_class":"P",
    "gn:feature_code":"PPL",
    "gn:name":"Samsan",
    "gn:population":0,
    "gn:timezone":"Asia/Seoul",
    "iso:country":"KR",
    "name:kor_x_preferred":[
        "\uc0bc\uc0b0"
    ],
    "wof:name":"Samsan",
    "wof:placetype":"locality"
},
  "geometry": {"coordinates":[127.55994,34.81415],"type":"Point"}
}