{
  "type": "Feature",
  "properties": {
    "gn:admin1_code":"14.0",
    "gn:asciiname":"Pugok",
    "gn:country_code":"KR",
    "gn:dem":278,
    "gn:feature_class":"P",
    "gn:feature_code":"PPL",
    "gn:name":"Pugok",
    "gn:population":0,
    "gn:timezone":"Asia/Seoul",
    "iso:country":"KR",
    "name:und_x_variant":[
        "\ubd80\uace1",
        "Pugok"
    ],
    "wof:name":"Pugok",
    "wof:placetype":"locality"
},
  "geometry": {"coordinates":[129.0087,36.3094],"type":"Point"}
}