{
  "type": "Feature",
  "properties": {
    "gn:admin1_code":"20.0",
    "gn:asciiname":"Naegok",
    "gn:country_code":"KR",
    "gn:dem":248,
    "gn:feature_class":"P",
    "gn:feature_code":"PPL",
    "gn:name":"Naegok",
    "gn:population":0,
    "gn:timezone":"Asia/Seoul",
    "iso:country":"KR",
    "name:und_x_variant":[
        "\ub0b4\uace1",
        "Naegok"
    ],
    "wof:name":"Naegok",
    "wof:placetype":"locality"
},
  "geometry": {"coordinates":[128.14917,35.64196],"type":"Point"}
}