{
  "type": "Feature",
  "properties": {
    "gn:admin1_code":"12.0",
    "gn:asciiname":"Bunori",
    "gn:country_code":"KR",
    "gn:dem":30,
    "gn:feature_class":"P",
    "gn:feature_code":"PPL",
    "gn:name":"Bunori",
    "gn:population":0,
    "gn:timezone":"Asia/Seoul",
    "iso:country":"KR",
    "name:und_x_variant":[
        "Punori",
        "\ubd84\uc624\ub9ac",
        "Punoridondae",
        "Bunori"
    ],
    "wof:name":"Bunori",
    "wof:placetype":"locality"
},
  "geometry": {"coordinates":[126.46193999999998,37.59573],"type":"Point"}
}