{
  "type": "Feature",
  "properties": {
    "gn:admin1_code":"14.0",
    "gn:asciiname":"Komsil",
    "gn:country_code":"KR",
    "gn:dem":162,
    "gn:feature_class":"P",
    "gn:feature_code":"PPL",
    "gn:name":"Komsil",
    "gn:population":0,
    "gn:timezone":"Asia/Seoul",
    "iso:country":"KR",
    "wof:name":"Komsil",
    "wof:placetype":"locality"
},
  "geometry": {"coordinates":[128.58888999999999,36.76722],"type":"Point"}
}