{
  "type": "Feature",
  "properties": {
    "gn:admin1_code":"16.0",
    "gn:asciiname":"Seountae",
    "gn:country_code":"KR",
    "gn:dem":228,
    "gn:feature_class":"P",
    "gn:feature_code":"PPL",
    "gn:name":"Seountae",
    "gn:population":0,
    "gn:timezone":"Asia/Seoul",
    "iso:country":"KR",
    "name:kor_x_preferred":[
        "\uc11c\uc6b4\ud0dc"
    ],
    "name:kor_x_variant":[
        "S\u014funt\u2019ae"
    ],
    "name:und_x_variant":[
        "S\u014fw\u014fn",
        "Seountae"
    ],
    "wof:name":"Seountae",
    "wof:placetype":"locality"
},
  "geometry": {"coordinates":[127.06847999999999,34.87821],"type":"Point"}
}