{
  "type": "Feature",
  "properties": {
    "gn:admin1_code":"16.0",
    "gn:asciiname":"Daeryeo",
    "gn:country_code":"KR",
    "gn:dem":41,
    "gn:feature_class":"P",
    "gn:feature_code":"PPL",
    "gn:name":"Daeryeo",
    "gn:population":0,
    "gn:timezone":"Asia/Seoul",
    "iso:country":"KR",
    "name:kor_x_preferred":[
        "\ub300\ub824"
    ],
    "name:kor_x_variant":[
        "Taery\u014f"
    ],
    "wof:name":"Daeryeo",
    "wof:placetype":"locality"
},
  "geometry": {"coordinates":[127.43488000000001,34.88195],"type":"Point"}
}