{
  "type": "Feature",
  "properties": {
    "gn:admin1_code":"13.0",
    "gn:asciiname":"Haegol",
    "gn:country_code":"KR",
    "gn:dem":117,
    "gn:feature_class":"P",
    "gn:feature_code":"PPL",
    "gn:name":"Haegol",
    "gn:population":0,
    "gn:timezone":"Asia/Seoul",
    "iso:country":"KR",
    "name:kor_x_preferred":[
        "\ud574\uace8"
    ],
    "name:und_x_variant":[
        "Haegol"
    ],
    "wof:name":"Haegol",
    "wof:placetype":"locality"
},
  "geometry": {"coordinates":[127.4956,37.7387],"type":"Point"}
}