{
  "type": "Feature",
  "properties": {
    "gn:admin1_code":"16.0",
    "gn:admin2_code":"Chindo-gun",
    "gn:asciiname":"Chogum-ni",
    "gn:country_code":"KR",
    "gn:dem":3,
    "gn:feature_class":"P",
    "gn:feature_code":"PPL",
    "gn:name":"Chog\u016dm-ni",
    "gn:population":0,
    "gn:timezone":"Asia/Seoul",
    "iso:country":"KR",
    "wof:name":"Chogum-ni",
    "wof:placetype":"locality"
},
  "geometry": {"coordinates":[126.25749999999999,34.48167],"type":"Point"}
}