{
  "type": "Feature",
  "properties": {
    "gn:admin1_code":"20.0",
    "gn:asciiname":"Makki",
    "gn:country_code":"KR",
    "gn:dem":254,
    "gn:feature_class":"P",
    "gn:feature_code":"PPL",
    "gn:name":"Makki",
    "gn:population":0,
    "gn:timezone":"Asia/Seoul",
    "iso:country":"KR",
    "name:und_x_variant":[
        "\ub9c9\uae30",
        "Makki"
    ],
    "wof:name":"Makki",
    "wof:placetype":"locality"
},
  "geometry": {"coordinates":[127.89870000000001,35.762],"type":"Point"}
}