{
  "type": "Feature",
  "properties": {
    "gn:admin1_code":"5.0",
    "gn:asciiname":"K'un-mal",
    "gn:country_code":"KR",
    "gn:dem":259,
    "gn:feature_class":"P",
    "gn:feature_code":"PPL",
    "gn:name":"K\u2019\u016dn-mal",
    "gn:population":0,
    "gn:timezone":"Asia/Seoul",
    "iso:country":"KR",
    "wof:name":"K'un-mal",
    "wof:placetype":"locality"
},
  "geometry": {"coordinates":[128.01611,36.8675],"type":"Point"}
}