{
  "type": "Feature",
  "properties": {
    "gn:admin1_code":"17.0",
    "gn:asciiname":"Kilgok",
    "gn:country_code":"KR",
    "gn:dem":213,
    "gn:feature_class":"P",
    "gn:feature_code":"PPL",
    "gn:name":"Kilgok",
    "gn:population":0,
    "gn:timezone":"Asia/Seoul",
    "iso:country":"KR",
    "name:und_x_variant":[
        "\uae38\uace1",
        "Kilgok"
    ],
    "wof:name":"Kilgok",
    "wof:placetype":"locality"
},
  "geometry": {"coordinates":[127.5638,36.1586],"type":"Point"}
}