{
  "type": "Feature",
  "properties": {
    "gn:admin1_code":"14.0",
    "gn:asciiname":"Hongjom",
    "gn:country_code":"KR",
    "gn:dem":503,
    "gn:feature_class":"P",
    "gn:feature_code":"PPL",
    "gn:name":"Hongj\u014fm",
    "gn:population":0,
    "gn:timezone":"Asia/Seoul",
    "iso:country":"KR",
    "name:und_x_variant":[
        "\ud64d\uc810",
        "Hongj\u014fm"
    ],
    "wof:name":"Hongjom",
    "wof:placetype":"locality"
},
  "geometry": {"coordinates":[129.0164,36.9867],"type":"Point"}
}