{
  "type": "Feature",
  "properties": {
    "gn:admin1_code":"6.0",
    "gn:asciiname":"Gasillakgol",
    "gn:country_code":"KR",
    "gn:dem":380,
    "gn:feature_class":"P",
    "gn:feature_code":"PPL",
    "gn:name":"Gasillakgol",
    "gn:population":0,
    "gn:timezone":"Asia/Seoul",
    "iso:country":"KR",
    "name:und_x_variant":[
        "Gasirag Gol",
        "Gasillakgol",
        "\uac00\uc2e4\ub77d\uace8",
        "Kasillak-kol"
    ],
    "wof:name":"Gasillakgol",
    "wof:placetype":"locality"
},
  "geometry": {"coordinates":[127.66446999999999,38.25612],"type":"Point"}
}