{
  "type": "Feature",
  "properties": {
    "gn:admin1_code":"20.0",
    "gn:asciiname":"Wongyenam",
    "gn:country_code":"KR",
    "gn:dem":252,
    "gn:feature_class":"P",
    "gn:feature_code":"PPL",
    "gn:name":"W\u014fngyenam",
    "gn:population":0,
    "gn:timezone":"Asia/Seoul",
    "iso:country":"KR",
    "name:und_x_variant":[
        "\uc6d0\uacc4\ub0a8",
        "W\u014fngyenam"
    ],
    "wof:name":"Wongyenam",
    "wof:placetype":"locality"
},
  "geometry": {"coordinates":[127.83816000000002,35.53683],"type":"Point"}
}