{
  "type": "Feature",
  "properties": {
    "gn:admin1_code":"14.0",
    "gn:asciiname":"Sageurei",
    "gn:country_code":"KR",
    "gn:dem":333,
    "gn:feature_class":"P",
    "gn:feature_code":"PPL",
    "gn:name":"Sageurei",
    "gn:population":0,
    "gn:timezone":"Asia/Seoul",
    "iso:country":"KR",
    "name:kor_x_preferred":[
        "\uc0ac\uadf8\ub808\uc774"
    ],
    "wof:name":"Sageurei",
    "wof:placetype":"locality"
},
  "geometry": {"coordinates":[128.64349999999999,36.98845],"type":"Point"}
}