{
  "type": "Feature",
  "properties": {
    "gn:admin1_code":"13.0",
    "gn:asciiname":"Udumul",
    "gn:country_code":"KR",
    "gn:dem":49,
    "gn:feature_class":"P",
    "gn:feature_code":"PPL",
    "gn:name":"Udumul",
    "gn:population":0,
    "gn:timezone":"Asia/Seoul",
    "iso:country":"KR",
    "name:und_x_variant":[
        "\uc6c3\uc6b0\ubb3c",
        "Usumul",
        "Udumul"
    ],
    "wof:name":"Udumul",
    "wof:placetype":"locality"
},
  "geometry": {"coordinates":[126.95972,37.36056],"type":"Point"}
}