{
  "type": "Feature",
  "properties": {
    "gn:admin1_code":"14.0",
    "gn:asciiname":"Chamsaemi",
    "gn:country_code":"KR",
    "gn:dem":29,
    "gn:feature_class":"P",
    "gn:feature_code":"PPL",
    "gn:name":"Chamsaemi",
    "gn:population":0,
    "gn:timezone":"Asia/Seoul",
    "iso:country":"KR",
    "name:kor_x_preferred":[
        "\ucc38\uc0d8\uc774"
    ],
    "name:und_x_variant":[
        "Ch\u2019amsaemi"
    ],
    "wof:name":"Chamsaemi",
    "wof:placetype":"locality"
},
  "geometry": {"coordinates":[129.34056000000001,36.08029000000001],"type":"Point"}
}