{
  "type": "Feature",
  "properties": {
    "gn:admin1_code":"14.0",
    "gn:asciiname":"Dwitteo",
    "gn:country_code":"KR",
    "gn:dem":472,
    "gn:feature_class":"P",
    "gn:feature_code":"PPL",
    "gn:name":"Dwitteo",
    "gn:population":0,
    "gn:timezone":"Asia/Seoul",
    "iso:country":"KR",
    "name:und_x_variant":[
        "\ub4b7\ud130",
        "Twitt\u2019\u014f",
        "Dwitteo"
    ],
    "wof:name":"Dwitteo",
    "wof:placetype":"locality"
},
  "geometry": {"coordinates":[129.27189999999999,36.29095],"type":"Point"}
}