{
  "type": "Feature",
  "properties": {
    "gn:admin1_code":"13.0",
    "gn:asciiname":"Dollae",
    "gn:country_code":"KR",
    "gn:dem":34,
    "gn:feature_class":"P",
    "gn:feature_code":"PPL",
    "gn:name":"Dollae",
    "gn:population":0,
    "gn:timezone":"Asia/Seoul",
    "iso:country":"KR",
    "name:kor_x_preferred":[
        "\ub3cc\ub0b4"
    ],
    "name:und_x_variant":[
        "Tollae",
        "Dollae"
    ],
    "wof:name":"Dollae",
    "wof:placetype":"locality"
},
  "geometry": {"coordinates":[126.70555,37.25457],"type":"Point"}
}