{
  "type": "Feature",
  "properties": {
    "gn:admin1_code":"17.0",
    "gn:asciiname":"Komundul",
    "gn:country_code":"KR",
    "gn:dem":26,
    "gn:feature_class":"P",
    "gn:feature_code":"PPL",
    "gn:name":"K\u014fm\u016dnd\u016dl",
    "gn:population":0,
    "gn:timezone":"Asia/Seoul",
    "iso:country":"KR",
    "name:und_x_variant":[
        "\uac80\uc740\ub4e4",
        "K\u014fm\u016dnd\u016dl"
    ],
    "wof:name":"Komundul",
    "wof:placetype":"locality"
},
  "geometry": {"coordinates":[126.37050000000001,36.5641],"type":"Point"}
}