{
  "type": "Feature",
  "properties": {
    "gn:admin1_code":"13.0",
    "gn:asciiname":"Jogaegol",
    "gn:country_code":"KR",
    "gn:dem":219,
    "gn:feature_class":"P",
    "gn:feature_code":"PPL",
    "gn:name":"Jogaegol",
    "gn:population":0,
    "gn:timezone":"Asia/Seoul",
    "iso:country":"KR",
    "name:kor_x_preferred":[
        "\uc870\uac1c\uace8"
    ],
    "name:und_x_variant":[
        "Chogae-gol",
        "Jogaegol"
    ],
    "wof:name":"Jogaegol",
    "wof:placetype":"locality"
},
  "geometry": {"coordinates":[127.58329999999999,37.5517],"type":"Point"}
}