{
  "type": "Feature",
  "properties": {
    "gn:admin1_code":"13.0",
    "gn:asciiname":"Buttanggol",
    "gn:country_code":"KR",
    "gn:dem":100,
    "gn:feature_class":"P",
    "gn:feature_code":"PPL",
    "gn:name":"Buttanggol",
    "gn:population":0,
    "gn:timezone":"Asia/Seoul",
    "iso:country":"KR",
    "name:kor_x_preferred":[
        "\ubd93\ub2f9\uace8"
    ],
    "wof:name":"Buttanggol",
    "wof:placetype":"locality"
},
  "geometry": {"coordinates":[127.03031,37.85545],"type":"Point"}
}