{
  "type": "Feature",
  "properties": {
    "gn:admin1_code":"13.0",
    "gn:admin2_code":"P'aju-si",
    "gn:asciiname":"Chiljeongmal",
    "gn:country_code":"KR",
    "gn:dem":19,
    "gn:feature_class":"P",
    "gn:feature_code":"PPL",
    "gn:name":"Chiljeongmal",
    "gn:population":0,
    "gn:timezone":"Asia/Seoul",
    "iso:country":"KR",
    "name:kor_x_preferred":[
        "\uce60\uc815\ub9d0"
    ],
    "name:und_x_variant":[
        "Ch\u2019ilch\u014fng-mal"
    ],
    "wof:name":"Chiljeongmal",
    "wof:placetype":"locality"
},
  "geometry": {"coordinates":[126.8159,37.86865],"type":"Point"}
}