{
  "type": "Feature",
  "properties": {
    "iso:country":"KR",
    "name:eng_x_preferred":[
        "Jipum-myeon"
    ],
    "name:kor_x_preferred":[
        "\uc9c0\ud488\uba74"
    ],
    "qs:name":"\uc9c0\ud488\uba74",
    "qs:name_adm0":"\ud55c\uad6d",
    "qs:name_adm1":"\uacbd\uc0c1\ubd81\ub3c4",
    "qs:photos":4,
    "qs:photos_1k":1,
    "qs:photos_9k":1,
    "qs:photos_9r":1,
    "qs:photos_all":4,
    "qs:photos_sr":1,
    "qs:placetype":"LocalAdmin",
    "qs:pop_sr":"0",
    "wof:name":"Jipum-myeon",
    "wof:placetype":"localadmin"
},
  "geometry": {"coordinates":[129.3516965,36.416309],"type":"Point"}
}