{
  "type": "Feature",
  "properties": {
    "gn:admin1_code":"16.0",
    "gn:asciiname":"Changdo-ri",
    "gn:country_code":"KR",
    "gn:dem":19,
    "gn:feature_class":"P",
    "gn:feature_code":"PPLL",
    "gn:name":"Changdo-ri",
    "gn:population":0,
    "gn:timezone":"Asia/Seoul",
    "iso:country":"KR",
    "name:kor_x_preferred":[
        "\uc7a5\ub3c4\ub9ac"
    ],
    "name:und_x_variant":[
        "Taech\u2019\u014fn-ni",
        "Nols\u014fm-ni",
        "Norus\u014fm-ni",
        "Changdo-ri"
    ],
    "wof:name":"Changdo-ri",
    "wof:placetype":"locality"
},
  "geometry": {"coordinates":[127.46201000000001,34.79229],"type":"Point"}
}