{
  "type": "Feature",
  "properties": {
    "iso:country":"KR",
    "qs:name":"\ub300\ud56d\uba74",
    "qs:name_adm0":"\ud55c\uad6d",
    "qs:name_adm1":"\uacbd\uc0c1\ubd81\ub3c4",
    "qs:photos":84,
    "qs:photos_1k":17,
    "qs:photos_9k":1,
    "qs:photos_9r":3,
    "qs:photos_all":84,
    "qs:photos_sr":3,
    "qs:placetype":"LocalAdmin",
    "qs:pop_sr":"0",
    "wof:name":"\ub300\ud56d\uba74",
    "wof:placetype":"localadmin"
},
  "geometry": {"coordinates":[128.014444,36.115277],"type":"Point"}
}