{
  "type": "Feature",
  "properties": {
    "gn:admin1_code":"17.0",
    "gn:asciiname":"Tongmak-kol",
    "gn:country_code":"KR",
    "gn:dem":113,
    "gn:feature_class":"P",
    "gn:feature_code":"PPL",
    "gn:name":"Tongmak-kol",
    "gn:population":0,
    "gn:timezone":"Asia/Seoul",
    "iso:country":"KR",
    "name:und_x_variant":[
        "\ub3d9\ub9c9\uace8",
        "Tongmak-kol"
    ],
    "wof:name":"Tongmak-kol",
    "wof:placetype":"locality"
},
  "geometry": {"coordinates":[126.6058,36.6597],"type":"Point"}
}