{
  "type": "Feature",
  "properties": {
    "gn:admin1_code":"13.0",
    "gn:admin2_code":"P'aju-si",
    "gn:asciiname":"Ullidong",
    "gn:country_code":"KR",
    "gn:dem":75,
    "gn:feature_class":"P",
    "gn:feature_code":"PPL",
    "gn:name":"Ullidong",
    "gn:population":0,
    "gn:timezone":"Asia/Seoul",
    "iso:country":"KR",
    "name:kor_x_preferred":[
        "\uc6b8\ub9ac\ub3d9"
    ],
    "wof:name":"Ullidong",
    "wof:placetype":"locality"
},
  "geometry": {"coordinates":[126.88328,37.77732],"type":"Point"}
}