{
  "type": "Feature",
  "properties": {
    "gn:admin1_code":"14.0",
    "gn:asciiname":"Monmin-maul",
    "gn:country_code":"KR",
    "gn:dem":201,
    "gn:feature_class":"P",
    "gn:feature_code":"PPL",
    "gn:name":"Monmin-ma\u016dl",
    "gn:population":0,
    "gn:timezone":"Asia/Seoul",
    "iso:country":"KR",
    "name:und_x_variant":[
        "\ubabb\ubc11\ub9c8\uc744",
        "Monmin-ma\u016dl"
    ],
    "wof:name":"Monmin-maul",
    "wof:placetype":"locality"
},
  "geometry": {"coordinates":[128.78710000000001,36.4386],"type":"Point"}
}