{
  "type": "Feature",
  "properties": {
    "gn:admin1_code":"17.0",
    "gn:asciiname":"Mongdae",
    "gn:country_code":"KR",
    "gn:dem":9,
    "gn:feature_class":"P",
    "gn:feature_code":"PPL",
    "gn:name":"Mongdae",
    "gn:population":0,
    "gn:timezone":"Asia/Seoul",
    "iso:country":"KR",
    "name:und_x_variant":[
        "\ubabd\ub300",
        "Mongdae"
    ],
    "wof:name":"Mongdae",
    "wof:placetype":"locality"
},
  "geometry": {"coordinates":[126.27290000000001,36.6735],"type":"Point"}
}