{
  "type": "Feature",
  "properties": {
    "gn:admin1_code":"6.0",
    "gn:asciiname":"Jeongjamun",
    "gn:country_code":"KR",
    "gn:dem":387,
    "gn:feature_class":"P",
    "gn:feature_code":"PPL",
    "gn:name":"Jeongjamun",
    "gn:population":0,
    "gn:timezone":"Asia/Seoul",
    "iso:country":"KR",
    "name:kor_x_preferred":[
        "\uc815\uc790\ubb38"
    ],
    "name:und_x_variant":[
        "Ch\u014fngjamun-ni",
        "Ch\u014fngjaun",
        "Ch\u014fngjamun",
        "Jeongjamun"
    ],
    "wof:name":"Jeongjamun",
    "wof:placetype":"locality"
},
  "geometry": {"coordinates":[128.27279999999999,38.1769],"type":"Point"}
}