{
  "type": "Feature",
  "properties": {
    "gn:admin1_code":"17.0",
    "gn:asciiname":"Chanda-ri",
    "gn:country_code":"KR",
    "gn:dem":30,
    "gn:feature_class":"P",
    "gn:feature_code":"PPL",
    "gn:name":"Chanda-ri",
    "gn:population":0,
    "gn:timezone":"Asia/Seoul",
    "iso:country":"KR",
    "name:und_x_variant":[
        "\uc794\ub2e4\ub9ac",
        "Chanda-ri"
    ],
    "wof:name":"Chanda-ri",
    "wof:placetype":"locality"
},
  "geometry": {"coordinates":[126.456,36.8328],"type":"Point"}
}