{
  "type": "Feature",
  "properties": {
    "gn:admin1_code":"17.0",
    "gn:asciiname":"Sowon-mal",
    "gn:country_code":"KR",
    "gn:dem":42,
    "gn:feature_class":"P",
    "gn:feature_code":"PPL",
    "gn:name":"S\u014fw\u014fn-mal",
    "gn:population":0,
    "gn:timezone":"Asia/Seoul",
    "iso:country":"KR",
    "name:und_x_variant":[
        "\uc11c\uc6d0\ub9d0",
        "S\u014fw\u014fn-mal"
    ],
    "wof:name":"Sowon-mal",
    "wof:placetype":"locality"
},
  "geometry": {"coordinates":[126.73350000000001,36.6444],"type":"Point"}
}