{
  "type": "Feature",
  "properties": {
    "gn:admin1_code":"5.0",
    "gn:asciiname":"Gangjeong",
    "gn:country_code":"KR",
    "gn:dem":62,
    "gn:feature_class":"P",
    "gn:feature_code":"PPL",
    "gn:name":"Gangjeong",
    "gn:population":0,
    "gn:timezone":"Asia/Seoul",
    "iso:country":"KR",
    "name:ind_x_preferred":[
        "Gangjeong"
    ],
    "name:jav_x_preferred":[
        "Gangjeong"
    ],
    "name:kor_x_preferred":[
        "\uac15\uc815"
    ],
    "name:kor_x_variant":[
        "Kangj\u014fng"
    ],
    "wof:name":"Gangjeong",
    "wof:placetype":"locality"
},
  "geometry": {"coordinates":[127.75342000000001,37.16958],"type":"Point"}
}