{
  "type": "Feature",
  "properties": {
    "gn:admin1_code":"6.0",
    "gn:asciiname":"Songjung-ni",
    "gn:country_code":"KR",
    "gn:dem":16,
    "gn:feature_class":"P",
    "gn:feature_code":"PPL",
    "gn:name":"Songjung-ni",
    "gn:population":0,
    "gn:timezone":"Asia/Seoul",
    "iso:country":"KR",
    "name:eng_x_preferred":[
        "Songjung"
    ],
    "name:eng_x_variant":[
        "Songjung-ni"
    ],
    "name:und_x_variant":[
        "\uc1a1\uc8fd\ub9ac"
    ],
    "wof:name":"Songjung",
    "wof:placetype":"locality"
},
  "geometry": {"coordinates":[128.46727999999999,38.40022],"type":"Point"}
}