{
  "type": "Feature",
  "properties": {
    "gn:admin1_code":"17.0",
    "gn:asciiname":"Pongam-ni",
    "gn:country_code":"KR",
    "gn:dem":53,
    "gn:feature_class":"P",
    "gn:feature_code":"PPL",
    "gn:name":"Pongam-ni",
    "gn:population":0,
    "gn:timezone":"Asia/Seoul",
    "iso:country":"KR",
    "name:und_x_variant":[
        "\ubd09\uc554\ub9ac",
        "Pongam-ni"
    ],
    "wof:name":"Pongam-ni",
    "wof:placetype":"locality"
},
  "geometry": {"coordinates":[127.27630000000001,36.4185],"type":"Point"}
}