{
  "type": "Feature",
  "properties": {
    "gn:admin1_code":"14.0",
    "gn:asciiname":"Sibugeori",
    "gn:country_code":"KR",
    "gn:dem":194,
    "gn:feature_class":"P",
    "gn:feature_code":"PPL",
    "gn:name":"Sibugeori",
    "gn:population":0,
    "gn:timezone":"Asia/Seoul",
    "iso:country":"KR",
    "name:kor_x_preferred":[
        "\uc2dc\ubd80\uac70\ub9ac"
    ],
    "wof:name":"Sibugeori",
    "wof:placetype":"locality"
},
  "geometry": {"coordinates":[129.33386999999999,35.82230999999999],"type":"Point"}
}