{
  "type": "Feature",
  "properties": {
    "gn:admin1_code":"13.0",
    "gn:asciiname":"Hogyesam-dong",
    "gn:country_code":"KR",
    "gn:dem":49,
    "gn:feature_class":"P",
    "gn:feature_code":"PPL",
    "gn:name":"Hogyesam-dong",
    "gn:population":0,
    "gn:timezone":"Asia/Seoul",
    "iso:country":"KR",
    "name:und_x_variant":[
        "\ud638\uacc43\ub3d9",
        "Hogyesam-dong"
    ],
    "wof:name":"Hogyesam-dong",
    "wof:placetype":"locality"
},
  "geometry": {"coordinates":[126.95833,37.36722],"type":"Point"}
}