{
  "type": "Feature",
  "properties": {
    "gn:admin1_code":"6.0",
    "gn:asciiname":"Songdan",
    "gn:country_code":"KR",
    "gn:dem":313,
    "gn:feature_class":"P",
    "gn:feature_code":"PPL",
    "gn:name":"Songdan",
    "gn:population":0,
    "gn:timezone":"Asia/Seoul",
    "iso:country":"KR",
    "name:kor_x_preferred":[
        "\uc1a1\ub2e8"
    ],
    "wof:name":"Songdan",
    "wof:placetype":"locality"
},
  "geometry": {"coordinates":[128.59899999999999,37.3626],"type":"Point"}
}