{
  "type": "Feature",
  "properties": {
    "gn:admin1_code":"17.0",
    "gn:asciiname":"Bakkatpami",
    "gn:country_code":"KR",
    "gn:dem":22,
    "gn:feature_class":"P",
    "gn:feature_code":"PPL",
    "gn:name":"Bakkatpami",
    "gn:population":0,
    "gn:timezone":"Asia/Seoul",
    "iso:country":"KR",
    "name:kor_x_preferred":[
        "\ubc14\uae65\ud30c\ubbf8"
    ],
    "wof:name":"Bakkatpami",
    "wof:placetype":"locality"
},
  "geometry": {"coordinates":[126.90559,36.76018],"type":"Point"}
}