{
  "type": "Feature",
  "properties": {
    "gn:admin1_code":"16.0",
    "gn:asciiname":"Sinbang",
    "gn:country_code":"KR",
    "gn:dem":193,
    "gn:feature_class":"P",
    "gn:feature_code":"PPL",
    "gn:name":"Sinbang",
    "gn:population":0,
    "gn:timezone":"Asia/Seoul",
    "iso:country":"KR",
    "name:kor_x_preferred":[
        "\uc2ec\ubc29\ub3d9"
    ],
    "name:kor_x_variant":[
        "\uc2e0\ubc29"
    ],
    "name:und_x_variant":[
        "Simbangdong",
        "Sinbang"
    ],
    "wof:name":"Sinbang",
    "wof:placetype":"locality"
},
  "geometry": {"coordinates":[127.09247000000001,34.96414],"type":"Point"}
}