{
  "type": "Feature",
  "properties": {
    "gn:admin1_code":"18.0",
    "gn:asciiname":"Baegoring",
    "gn:country_code":"KR",
    "gn:dem":29,
    "gn:feature_class":"P",
    "gn:feature_code":"PPL",
    "gn:name":"Baegoring",
    "gn:population":0,
    "gn:timezone":"Asia/Seoul",
    "iso:country":"KR",
    "name:kor_x_preferred":[
        "\ubc30\uace0\ub9c1"
    ],
    "wof:name":"Baegoring",
    "wof:placetype":"locality"
},
  "geometry": {"coordinates":[126.83944,35.12677],"type":"Point"}
}