{
  "type": "Feature",
  "properties": {
    "gn:admin1_code":"14.0",
    "gn:asciiname":"Oksal-li",
    "gn:country_code":"KR",
    "gn:dem":88,
    "gn:feature_class":"P",
    "gn:feature_code":"PPL",
    "gn:name":"Oksal-li",
    "gn:population":0,
    "gn:timezone":"Asia/Seoul",
    "iso:country":"KR",
    "name:und_x_variant":[
        "Gyokuzand\u014d",
        "Ogsan",
        "Gyokusan-d\u014d",
        "Oksan-dong",
        "Oksal-li",
        "\uc625\uc0b0\ub9ac",
        "Oksan"
    ],
    "wof:name":"Oksal-li",
    "wof:placetype":"locality"
},
  "geometry": {"coordinates":[128.0926,36.2834],"type":"Point"}
}