{
  "type": "Feature",
  "properties": {
    "gn:admin1_code":"14.0",
    "gn:asciiname":"Chuamni",
    "gn:country_code":"KR",
    "gn:dem":115,
    "gn:feature_class":"P",
    "gn:feature_code":"PPL",
    "gn:name":"Chuamni",
    "gn:population":0,
    "gn:timezone":"Asia/Seoul",
    "iso:country":"KR",
    "name:kor_x_preferred":[
        "\ucd94\uc554\ub9ac"
    ],
    "wof:name":"Chuamni",
    "wof:placetype":"locality"
},
  "geometry": {"coordinates":[128.23876000000001,36.62422],"type":"Point"}
}