{
  "type": "Feature",
  "properties": {
    "gn:admin1_code":"14.0",
    "gn:asciiname":"Songnae",
    "gn:country_code":"KR",
    "gn:dem":76,
    "gn:feature_class":"P",
    "gn:feature_code":"PPL",
    "gn:name":"S\u014fngnae",
    "gn:population":0,
    "gn:timezone":"Asia/Seoul",
    "iso:country":"KR",
    "name:und_x_variant":[
        "S\u014fngnae",
        "\uc131\ub0b4",
        "S\u014fngnae-dong"
    ],
    "wof:name":"Songnae",
    "wof:placetype":"locality"
},
  "geometry": {"coordinates":[129.38722000000001,37.0525],"type":"Point"}
}