{
  "type": "Feature",
  "properties": {
    "gn:admin1_code":"6.0",
    "gn:asciiname":"Sedaegi",
    "gn:country_code":"KR",
    "gn:dem":461,
    "gn:feature_class":"P",
    "gn:feature_code":"PPL",
    "gn:name":"Sedaegi",
    "gn:population":0,
    "gn:timezone":"Asia/Seoul",
    "iso:country":"KR",
    "name:kor_x_preferred":[
        "\uc138\ub300\uae30"
    ],
    "wof:name":"Sedaegi",
    "wof:placetype":"locality"
},
  "geometry": {"coordinates":[128.18790000000001,37.6632],"type":"Point"}
}