{
  "type": "Feature",
  "properties": {
    "gn:admin1_code":"20.0",
    "gn:asciiname":"Nopunt'o",
    "gn:country_code":"KR",
    "gn:dem":110,
    "gn:feature_class":"P",
    "gn:feature_code":"PPL",
    "gn:name":"Nop\u016dnt\u2019\u014f",
    "gn:population":0,
    "gn:timezone":"Asia/Seoul",
    "iso:country":"KR",
    "name:und_x_variant":[
        "\ub192\uc740\ud130",
        "Nop\u016dnt\u2019\u014f"
    ],
    "wof:name":"Nopunt'o",
    "wof:placetype":"locality"
},
  "geometry": {"coordinates":[128.10103999999998,35.50340999999999],"type":"Point"}
}