{
  "type": "Feature",
  "properties": {
    "gn:admin1_code":"13.0",
    "gn:asciiname":"T'okko-ri",
    "gn:country_code":"KR",
    "gn:dem":128,
    "gn:feature_class":"P",
    "gn:feature_code":"PPL",
    "gn:name":"T\u2019\u014fkk\u014f-ri",
    "gn:population":0,
    "gn:timezone":"Asia/Seoul",
    "iso:country":"KR",
    "name:und_x_variant":[
        "T\u014fkk\u014f-ri",
        "T\u2019\u014fkk\u014f-ri"
    ],
    "wof:name":"T'okko-ri",
    "wof:placetype":"locality"
},
  "geometry": {"coordinates":[127.08417,37.89528],"type":"Point"}
}