{
  "type": "Feature",
  "properties": {
    "gn:admin1_code":"13.0",
    "gn:asciiname":"Yongbawi",
    "gn:country_code":"KR",
    "gn:dem":112,
    "gn:feature_class":"P",
    "gn:feature_code":"PPL",
    "gn:name":"Yongbawi",
    "gn:population":0,
    "gn:timezone":"Asia/Seoul",
    "iso:country":"KR",
    "name:und_x_variant":[
        "\uc6a9\ubc14\uc704",
        "Yongbawi"
    ],
    "wof:name":"Yongbawi",
    "wof:placetype":"locality"
},
  "geometry": {"coordinates":[126.99679999999999,37.9125],"type":"Point"}
}