{
  "type": "Feature",
  "properties": {
    "gn:admin1_code":"5.0",
    "gn:asciiname":"Sagok",
    "gn:country_code":"KR",
    "gn:dem":194,
    "gn:feature_class":"P",
    "gn:feature_code":"PPL",
    "gn:name":"Sagok",
    "gn:population":0,
    "gn:timezone":"Asia/Seoul",
    "iso:country":"KR",
    "wof:name":"Sagok",
    "wof:placetype":"locality"
},
  "geometry": {"coordinates":[127.78333000000001,36.28333],"type":"Point"}
}