{
  "type": "Feature",
  "properties": {
    "gn:admin1_code":"13.0",
    "gn:admin2_code":"P'aju-si",
    "gn:asciiname":"Woreumsil",
    "gn:country_code":"KR",
    "gn:dem":36,
    "gn:feature_class":"P",
    "gn:feature_code":"PPL",
    "gn:name":"Woreumsil",
    "gn:population":0,
    "gn:timezone":"Asia/Seoul",
    "iso:country":"KR",
    "name:kor_x_preferred":[
        "\uc6d4\uc74c\uc2e4"
    ],
    "name:kor_x_variant":[
        "W\u014fr\u016dmsil"
    ],
    "wof:name":"Woreumsil",
    "wof:placetype":"locality"
},
  "geometry": {"coordinates":[126.69777999999999,37.79444],"type":"Point"}
}