{
  "type": "Feature",
  "properties": {
    "gn:admin1_code":"3.0",
    "gn:asciiname":"Changho-ri",
    "gn:cc2":"KR",
    "gn:country_code":"KR",
    "gn:dem":6,
    "gn:feature_class":"P",
    "gn:feature_code":"PPL",
    "gn:name":"Changho-ri",
    "gn:population":0,
    "gn:timezone":"Asia/Seoul",
    "iso:country":"KR",
    "name:und_x_variant":[
        "Changho",
        "Changho-ri"
    ],
    "wof:name":"Changho-ri",
    "wof:placetype":"locality"
},
  "geometry": {"coordinates":[126.46889,35.47194000000001],"type":"Point"}
}