{
  "type": "Feature",
  "properties": {
    "gn:admin1_code":"6.0",
    "gn:asciiname":"Andu-ri",
    "gn:country_code":"KR",
    "gn:dem":284,
    "gn:feature_class":"P",
    "gn:feature_code":"PPL",
    "gn:name":"Andu-ri",
    "gn:population":0,
    "gn:timezone":"Asia/Seoul",
    "iso:country":"KR",
    "name:kor_x_preferred":[
        "\uc548\ub450\ub9ac"
    ],
    "wof:name":"Andu-ri",
    "wof:placetype":"locality"
},
  "geometry": {"coordinates":[128.26439999999999,37.9961],"type":"Point"}
}