{
  "type": "Feature",
  "properties": {
    "gn:admin1_code":"11.0",
    "gn:asciiname":"P'il-tong",
    "gn:country_code":"KR",
    "gn:dem":67,
    "gn:feature_class":"P",
    "gn:feature_code":"PPL",
    "gn:name":"P\u2019il-tong",
    "gn:population":0,
    "gn:timezone":"Asia/Seoul",
    "iso:country":"KR",
    "name:und_x_variant":[
        "\ud544\ub3d9",
        "P\u2019il-tong"
    ],
    "wof:name":"P'il-tong",
    "wof:placetype":"locality"
},
  "geometry": {"coordinates":[126.99428,37.55667],"type":"Point"}
}