{
  "type": "Feature",
  "properties": {
    "gn:admin1_code":"17.0",
    "gn:asciiname":"Taeyagong-ni",
    "gn:country_code":"KR",
    "gn:dem":89,
    "gn:feature_class":"P",
    "gn:feature_code":"PPL",
    "gn:name":"Taeyagong-ni",
    "gn:population":0,
    "gn:timezone":"Asia/Seoul",
    "iso:country":"KR",
    "wof:name":"Taeyagong-ni",
    "wof:placetype":"locality"
},
  "geometry": {"coordinates":[126.58333,36.53333],"type":"Point"}
}