{
  "type": "Feature",
  "properties": {
    "gn:admin1_code":"17.0",
    "gn:asciiname":"Mahyangso",
    "gn:country_code":"KR",
    "gn:dem":88,
    "gn:feature_class":"P",
    "gn:feature_code":"PPL",
    "gn:name":"Mahyangs\u014f",
    "gn:population":0,
    "gn:timezone":"Asia/Seoul",
    "iso:country":"KR",
    "name:und_x_variant":[
        "\ub9c8\ud5a5\uc11c",
        "Mahyangs\u014f"
    ],
    "wof:name":"Mahyangso",
    "wof:placetype":"locality"
},
  "geometry": {"coordinates":[126.7968,36.4448],"type":"Point"}
}