{
  "type": "Feature",
  "properties": {
    "gn:admin1_code":"20.0",
    "gn:asciiname":"Kuman",
    "gn:country_code":"KR",
    "gn:dem":45,
    "gn:feature_class":"P",
    "gn:feature_code":"PPL",
    "gn:name":"Kuman",
    "gn:population":0,
    "gn:timezone":"Asia/Seoul",
    "iso:country":"KR",
    "name:und_x_variant":[
        "\uad6c\ub9cc",
        "Kuman"
    ],
    "wof:name":"Kuman",
    "wof:placetype":"locality"
},
  "geometry": {"coordinates":[128.33484999999999,35.08842],"type":"Point"}
}