{
  "type": "Feature",
  "properties": {
    "gn:admin1_code":"13.0",
    "gn:asciiname":"Eungdalmal",
    "gn:country_code":"KR",
    "gn:dem":88,
    "gn:feature_class":"P",
    "gn:feature_code":"PPL",
    "gn:name":"Eungdalmal",
    "gn:population":0,
    "gn:timezone":"Asia/Seoul",
    "iso:country":"KR",
    "name:und_x_variant":[
        "\uc751\ub2ec\ub9d0",
        "\u016cngdal-mal",
        "Eungdalmal"
    ],
    "wof:name":"Eungdalmal",
    "wof:placetype":"locality"
},
  "geometry": {"coordinates":[127.1289,37.70924],"type":"Point"}
}