{
  "type": "Feature",
  "properties": {
    "gn:admin1_code":"5.0",
    "gn:asciiname":"Wonsongjeol",
    "gn:country_code":"KR",
    "gn:dem":51,
    "gn:feature_class":"P",
    "gn:feature_code":"PPL",
    "gn:name":"Wonsongjeol",
    "gn:population":0,
    "gn:timezone":"Asia/Seoul",
    "iso:country":"KR",
    "name:kor_x_preferred":[
        "\uc6d0\uc1a1\uc808"
    ],
    "wof:name":"Wonsongjeol",
    "wof:placetype":"locality"
},
  "geometry": {"coordinates":[127.45059999999999,36.66162],"type":"Point"}
}