{
  "type": "Feature",
  "properties": {
    "gn:admin1_code":"13.0",
    "gn:asciiname":"Majol-li",
    "gn:cc2":"KR",
    "gn:country_code":"KR",
    "gn:dem":142,
    "gn:feature_class":"P",
    "gn:feature_code":"PPL",
    "gn:name":"Maj\u014fl-li",
    "gn:population":0,
    "gn:timezone":"Asia/Seoul",
    "iso:country":"KR",
    "name:und_x_variant":[
        "Maj\u014fn-ni",
        "Maj\u014fl-li"
    ],
    "wof:name":"Majol-li",
    "wof:placetype":"locality"
},
  "geometry": {"coordinates":[127.09139,38.22556],"type":"Point"}
}