{
  "type": "Feature",
  "properties": {
    "gn:admin1_code":"6.0",
    "gn:asciiname":"Ponburak",
    "gn:cc2":"KR",
    "gn:country_code":"KR",
    "gn:dem":226,
    "gn:feature_class":"P",
    "gn:feature_code":"PPL",
    "gn:name":"Ponburak",
    "gn:population":0,
    "gn:timezone":"Asia/Seoul",
    "iso:country":"KR",
    "name:und_x_variant":[
        "Naep\u2019y\u014fng-ni",
        "Naihyori",
        "Naihei-ri",
        "Ponburak"
    ],
    "wof:name":"Ponburak",
    "wof:placetype":"locality"
},
  "geometry": {"coordinates":[127.90000000000001,37.93333],"type":"Point"}
}