{
  "type": "Feature",
  "properties": {
    "gn:admin1_code":"0.0",
    "gn:asciiname":"Kwangsok",
    "gn:cc2":"KR",
    "gn:country_code":"KR",
    "gn:dem":27,
    "gn:feature_class":"P",
    "gn:feature_code":"PPL",
    "gn:name":"Kwangs\u014fk",
    "gn:population":0,
    "gn:timezone":"Asia/Seoul",
    "iso:country":"KR",
    "name:und_x_variant":[
        "Kwangs\u014fng-ni",
        "Kwangs\u014fk"
    ],
    "wof:name":"Kwangsok",
    "wof:placetype":"locality"
},
  "geometry": {"coordinates":[126.76667,35.01667],"type":"Point"}
}