{
  "type": "Feature",
  "properties": {
    "gn:admin1_code":"5.0",
    "gn:asciiname":"Sureneomi",
    "gn:country_code":"KR",
    "gn:dem":318,
    "gn:feature_class":"P",
    "gn:feature_code":"PPL",
    "gn:name":"Sureneomi",
    "gn:population":0,
    "gn:timezone":"Asia/Seoul",
    "iso:country":"KR",
    "name:kor_x_preferred":[
        "\uc218\ub808\ub108\ubbf8"
    ],
    "wof:name":"Sureneomi",
    "wof:placetype":"locality"
},
  "geometry": {"coordinates":[127.56059999999999,36.64418],"type":"Point"}
}