{
  "type": "Feature",
  "properties": {
    "gn:admin1_code":"13.0",
    "gn:asciiname":"Togok-tong",
    "gn:country_code":"KR",
    "gn:dem":70,
    "gn:feature_class":"P",
    "gn:feature_code":"PPL",
    "gn:name":"Togok-tong",
    "gn:population":0,
    "gn:timezone":"Asia/Seoul",
    "iso:country":"KR",
    "name:eng_x_preferred":[
        "Togok"
    ],
    "name:eng_x_variant":[
        "Togok-tong"
    ],
    "name:fas_x_preferred":[
        "\u062f\u0648\u06af\u0648\u06a9-\u062f\u0648\u0646\u06af"
    ],
    "name:kor_x_preferred":[
        "\ub3c4\uace1\ub3d9"
    ],
    "name:msa_x_preferred":[
        "Dogok-dong"
    ],
    "name:sco_x_preferred":[
        "Dogok-dong"
    ],
    "name:und_x_variant":[
        "Togok-tong"
    ],
    "name:vie_x_preferred":[
        "Dogok-dong"
    ],
    "wof:name":"Togok",
    "wof:placetype":"locality"
},
  "geometry": {"coordinates":[127.30249999999999,37.36833],"type":"Point"}
}