{
  "type": "Feature",
  "properties": {
    "gn:admin1_code":"3.0",
    "gn:asciiname":"Sagijom",
    "gn:country_code":"KR",
    "gn:dem":315,
    "gn:feature_class":"P",
    "gn:feature_code":"PPL",
    "gn:name":"Sagij\u014fm",
    "gn:population":0,
    "gn:timezone":"Asia/Seoul",
    "iso:country":"KR",
    "name:und_x_variant":[
        "\uc0ac\uae30\uc810",
        "Sagij\u014fm"
    ],
    "wof:name":"Sagijom",
    "wof:placetype":"locality"
},
  "geometry": {"coordinates":[127.29052,35.76231],"type":"Point"}
}