{
  "type": "Feature",
  "properties": {
    "gn:admin1_code":"13.0",
    "gn:asciiname":"Tammoraengi",
    "gn:country_code":"KR",
    "gn:dem":80,
    "gn:feature_class":"P",
    "gn:feature_code":"PPL",
    "gn:name":"Tammoraengi",
    "gn:population":0,
    "gn:timezone":"Asia/Seoul",
    "iso:country":"KR",
    "name:und_x_variant":[
        "\ub2f4\ubaa8\ub7ad\uc774",
        "Dammoraengi",
        "Tammoraengi"
    ],
    "wof:name":"Tammoraengi",
    "wof:placetype":"locality"
},
  "geometry": {"coordinates":[127.68333,37.38611],"type":"Point"}
}