{
  "type": "Feature",
  "properties": {
    "gn:admin1_code":"14.0",
    "gn:asciiname":"Bomagol",
    "gn:country_code":"KR",
    "gn:dem":174,
    "gn:feature_class":"P",
    "gn:feature_code":"PPL",
    "gn:name":"Bomagol",
    "gn:population":0,
    "gn:timezone":"Asia/Seoul",
    "iso:country":"KR",
    "name:kor_x_preferred":[
        "\ubcf4\ub9c8\uace8"
    ],
    "wof:name":"Bomagol",
    "wof:placetype":"locality"
},
  "geometry": {"coordinates":[128.90215000000001,36.61315],"type":"Point"}
}