{
  "type": "Feature",
  "properties": {
    "gn:admin1_code":"14.0",
    "gn:asciiname":"Sinhwa-ch'on",
    "gn:country_code":"KR",
    "gn:dem":121,
    "gn:feature_class":"P",
    "gn:feature_code":"PPL",
    "gn:name":"Sinhwa-ch\u2019on",
    "gn:population":0,
    "gn:timezone":"Asia/Seoul",
    "iso:country":"KR",
    "name:und_x_variant":[
        "\uc2e0\ud654\ucd0c",
        "Sinhwa-ch\u2019on"
    ],
    "wof:name":"Sinhwa-ch'on",
    "wof:placetype":"locality"
},
  "geometry": {"coordinates":[128.3937,36.2776],"type":"Point"}
}