{
  "type": "Feature",
  "properties": {
    "gn:admin1_code":"6.0",
    "gn:asciiname":"Mun'gaesil",
    "gn:country_code":"KR",
    "gn:dem":211,
    "gn:feature_class":"P",
    "gn:feature_code":"PPL",
    "gn:name":"Mun\u2019gaesil",
    "gn:population":0,
    "gn:timezone":"Asia/Seoul",
    "iso:country":"KR",
    "name:kor_x_preferred":[
        "\ubb38\uac1c\uc2e4"
    ],
    "name:kor_x_variant":[
        "Mun\u2019gaesil"
    ],
    "wof:name":"Mun'gaesil",
    "wof:placetype":"locality"
},
  "geometry": {"coordinates":[128.41669999999999,37.204],"type":"Point"}
}