{
  "type": "Feature",
  "properties": {
    "gn:admin1_code":"20.0",
    "gn:asciiname":"Al-li",
    "gn:country_code":"KR",
    "gn:dem":35,
    "gn:feature_class":"P",
    "gn:feature_code":"PPL",
    "gn:name":"Al-li",
    "gn:population":0,
    "gn:timezone":"Asia/Seoul",
    "iso:country":"KR",
    "name:und_x_variant":[
        "Am-ni",
        "An-ni",
        "\uc548\ub9ac",
        "Al-li"
    ],
    "wof:name":"Al-li",
    "wof:placetype":"locality"
},
  "geometry": {"coordinates":[128.38394,35.57818],"type":"Point"}
}