{
  "type": "Feature",
  "properties": {
    "gn:admin1_code":"6.0",
    "gn:asciiname":"Kaesui-ri",
    "gn:country_code":"KR",
    "gn:dem":443,
    "gn:feature_class":"P",
    "gn:feature_code":"PPL",
    "gn:name":"Kaesui-ri",
    "gn:population":0,
    "gn:timezone":"Asia/Seoul",
    "iso:country":"KR",
    "name:kor_x_preferred":[
        "\uac1c\uc218\uc774\ub9ac"
    ],
    "wof:name":"Kaesui-ri",
    "wof:placetype":"locality"
},
  "geometry": {"coordinates":[128.39230000000001,37.4995],"type":"Point"}
}