{
  "type": "Feature",
  "properties": {
    "gn:admin1_code":"0.0",
    "gn:asciiname":"Yongsin",
    "gn:cc2":"KR",
    "gn:country_code":"KR",
    "gn:dem":350,
    "gn:feature_class":"P",
    "gn:feature_code":"PPL",
    "gn:name":"Y\u014fngsin",
    "gn:population":0,
    "gn:timezone":"Asia/Seoul",
    "iso:country":"KR",
    "name:und_x_variant":[
        "Y\u014fngsin-ni",
        "Y\u014fngsin"
    ],
    "wof:name":"Yongsin",
    "wof:placetype":"locality"
},
  "geometry": {"coordinates":[127.03333000000001,35.11667],"type":"Point"}
}