{
  "type": "Feature",
  "properties": {
    "gn:admin1_code":"14.0",
    "gn:asciiname":"Sin-ch'on",
    "gn:country_code":"KR",
    "gn:dem":573,
    "gn:feature_class":"P",
    "gn:feature_code":"PPL",
    "gn:name":"Sin-ch\u2019on",
    "gn:population":0,
    "gn:timezone":"Asia/Seoul",
    "iso:country":"KR",
    "wof:name":"Sin-ch'on",
    "wof:placetype":"locality"
},
  "geometry": {"coordinates":[129.28638999999998,36.76417],"type":"Point"}
}