{
  "type": "Feature",
  "properties": {
    "gn:admin1_code":"12.0",
    "gn:admin2_code":"Kanghwa-gun",
    "gn:asciiname":"Sanipo",
    "gn:country_code":"KR",
    "gn:dem":11,
    "gn:feature_class":"P",
    "gn:feature_code":"PPL",
    "gn:name":"Sanipo",
    "gn:population":0,
    "gn:timezone":"Asia/Seoul",
    "iso:country":"KR",
    "name:kor_x_preferred":[
        "\uc0b0\uc774\ud3ec"
    ],
    "name:und_x_variant":[
        "Ch\u2019\u014flsal-li",
        "Ch\u2019\u014flsan-ni",
        "Sanip\u2019o",
        "Sanipo"
    ],
    "wof:name":"Sanipo",
    "wof:placetype":"locality"
},
  "geometry": {"coordinates":[126.44696,37.81597],"type":"Point"}
}