{
  "type": "Feature",
  "properties": {
    "gn:admin1_code":"6.0",
    "gn:asciiname":"Kurau",
    "gn:country_code":"KR",
    "gn:dem":298,
    "gn:feature_class":"P",
    "gn:feature_code":"PPL",
    "gn:name":"Kurau",
    "gn:population":0,
    "gn:timezone":"Asia/Seoul",
    "iso:country":"KR",
    "name:kor_x_preferred":[
        "\uad74\uc544\uc6b0"
    ],
    "name:und_x_variant":[
        "Kuram-ni",
        "Kurau"
    ],
    "wof:name":"Kurau",
    "wof:placetype":"locality"
},
  "geometry": {"coordinates":[128.14768999999998,37.6324],"type":"Point"}
}