{
  "type": "Feature",
  "properties": {
    "gn:admin1_code":"6.0",
    "gn:asciiname":"Yeokjeonmal",
    "gn:country_code":"KR",
    "gn:dem":79,
    "gn:feature_class":"P",
    "gn:feature_code":"PPL",
    "gn:name":"Yeokjeonmal",
    "gn:population":0,
    "gn:timezone":"Asia/Seoul",
    "iso:country":"KR",
    "name:und_x_variant":[
        "\uc5ed\uc804\ub9d0",
        "Y\u014fkch\u014fn-mal",
        "Yeokjeonmal"
    ],
    "wof:name":"Yeokjeonmal",
    "wof:placetype":"locality"
},
  "geometry": {"coordinates":[127.67921,37.82396],"type":"Point"}
}