{
  "type": "Feature",
  "properties": {
    "gn:admin1_code":"13.0",
    "gn:asciiname":"Anmaeul",
    "gn:country_code":"KR",
    "gn:dem":233,
    "gn:feature_class":"P",
    "gn:feature_code":"PPL",
    "gn:name":"Anmaeul",
    "gn:population":0,
    "gn:timezone":"Asia/Seoul",
    "iso:country":"KR",
    "name:kor_x_preferred":[
        "\uc548\ub9c8\uc744"
    ],
    "wof:name":"Anmaeul",
    "wof:placetype":"locality"
},
  "geometry": {"coordinates":[127.3875,37.84413],"type":"Point"}
}