{
  "type": "Feature",
  "properties": {
    "gn:admin1_code":"6.0",
    "gn:asciiname":"Naenamae",
    "gn:country_code":"KR",
    "gn:dem":24,
    "gn:feature_class":"P",
    "gn:feature_code":"PPL",
    "gn:name":"Naenamae",
    "gn:population":0,
    "gn:timezone":"Asia/Seoul",
    "iso:country":"KR",
    "name:kor_x_preferred":[
        "\ub0b4\ub0a8\uc560"
    ],
    "wof:name":"Naenamae",
    "wof:placetype":"locality"
},
  "geometry": {"coordinates":[128.78503999999998,37.94172],"type":"Point"}
}