{
  "type": "Feature",
  "properties": {
    "gn:admin1_code":"5.0",
    "gn:asciiname":"Sulmogi",
    "gn:country_code":"KR",
    "gn:dem":156,
    "gn:feature_class":"P",
    "gn:feature_code":"PPL",
    "gn:name":"Sulmogi",
    "gn:population":0,
    "gn:timezone":"Asia/Seoul",
    "iso:country":"KR",
    "name:kor_x_preferred":[
        "\uc220\ubaa8\uae30"
    ],
    "wof:name":"Sulmogi",
    "wof:placetype":"locality"
},
  "geometry": {"coordinates":[128.20275000000001,36.97919],"type":"Point"}
}