{
  "type": "Feature",
  "properties": {
    "gn:admin1_code":"17.0",
    "gn:asciiname":"Naejuk",
    "gn:country_code":"KR",
    "gn:dem":55,
    "gn:feature_class":"P",
    "gn:feature_code":"PPL",
    "gn:name":"Naejuk",
    "gn:population":0,
    "gn:timezone":"Asia/Seoul",
    "iso:country":"KR",
    "name:und_x_variant":[
        "\ub0b4\uc8fd",
        "Naejuk"
    ],
    "wof:name":"Naejuk",
    "wof:placetype":"locality"
},
  "geometry": {"coordinates":[126.8343,36.2991],"type":"Point"}
}