{
  "type": "Feature",
  "properties": {
    "gn:admin1_code":"13.0",
    "gn:asciiname":"Banggae",
    "gn:country_code":"KR",
    "gn:dem":10,
    "gn:feature_class":"P",
    "gn:feature_code":"PPL",
    "gn:name":"Banggae",
    "gn:population":0,
    "gn:timezone":"Asia/Seoul",
    "iso:country":"KR",
    "name:und_x_variant":[
        "\ubc29\uac1c",
        "Panggae",
        "Banggae"
    ],
    "wof:name":"Banggae",
    "wof:placetype":"locality"
},
  "geometry": {"coordinates":[126.95723,36.97505],"type":"Point"}
}