{
  "type": "Feature",
  "properties": {
    "gn:admin1_code":"17.0",
    "gn:asciiname":"Puksil",
    "gn:country_code":"KR",
    "gn:dem":84,
    "gn:feature_class":"P",
    "gn:feature_code":"PPL",
    "gn:name":"Puksil",
    "gn:population":0,
    "gn:timezone":"Asia/Seoul",
    "iso:country":"KR",
    "name:und_x_variant":[
        "\ubd81\uc2e4",
        "Puksil"
    ],
    "wof:name":"Puksil",
    "wof:placetype":"locality"
},
  "geometry": {"coordinates":[126.911,36.3819],"type":"Point"}
}