{
  "type": "Feature",
  "properties": {
    "gn:admin1_code":"20.0",
    "gn:asciiname":"Changgi",
    "gn:country_code":"KR",
    "gn:dem":12,
    "gn:feature_class":"P",
    "gn:feature_code":"PPL",
    "gn:name":"Changgi",
    "gn:population":0,
    "gn:timezone":"Asia/Seoul",
    "iso:country":"KR",
    "name:und_x_variant":[
        "Sh\u014dki-ri",
        "Changgi-ri",
        "\uc7a5\uae30",
        "Changgi"
    ],
    "wof:name":"Changgi",
    "wof:placetype":"locality"
},
  "geometry": {"coordinates":[128.42451,35.0418],"type":"Point"}
}