{
  "type": "Feature",
  "properties": {
    "gn:admin1_code":"20.0",
    "gn:asciiname":"Kaji-ri",
    "gn:country_code":"KR",
    "gn:dem":263,
    "gn:feature_class":"P",
    "gn:feature_code":"PPLL",
    "gn:name":"Kaji-ri",
    "gn:population":0,
    "gn:timezone":"Asia/Seoul",
    "iso:country":"KR",
    "name:und_x_variant":[
        "\uac00\uc9c0\ub9ac",
        "Kaji-ri"
    ],
    "wof:name":"Kaji-ri",
    "wof:placetype":"locality"
},
  "geometry": {"coordinates":[127.88986,35.70238],"type":"Point"}
}