{
  "type": "Feature",
  "properties": {
    "gn:admin1_code":"21.0",
    "gn:asciiname":"Duwang I Gu",
    "gn:country_code":"KR",
    "gn:dem":33,
    "gn:feature_class":"P",
    "gn:feature_code":"PPL",
    "gn:name":"Duwang I Gu",
    "gn:population":0,
    "gn:timezone":"Asia/Seoul",
    "iso:country":"KR",
    "name:kor_x_preferred":[
        "\ub450\uc6552\uad6c"
    ],
    "name:und_x_variant":[
        "Duwang 2 Gu"
    ],
    "wof:name":"Duwang I Gu",
    "wof:placetype":"locality"
},
  "geometry": {"coordinates":[129.30216999999999,35.50718],"type":"Point"}
}