{
  "type": "Feature",
  "properties": {
    "gn:admin1_code":"14.0",
    "gn:asciiname":"Koraesil",
    "gn:country_code":"KR",
    "gn:dem":96,
    "gn:feature_class":"P",
    "gn:feature_code":"PPL",
    "gn:name":"Koraesil",
    "gn:population":0,
    "gn:timezone":"Asia/Seoul",
    "iso:country":"KR",
    "name:und_x_variant":[
        "\uace0\ub798\uc2e4",
        "Koraesil"
    ],
    "wof:name":"Koraesil",
    "wof:placetype":"locality"
},
  "geometry": {"coordinates":[128.08189999999999,36.1225],"type":"Point"}
}