{
  "type": "Feature",
  "properties": {
    "gn:admin1_code":"10.0",
    "gn:asciiname":"Jeonggeo",
    "gn:country_code":"KR",
    "gn:dem":0,
    "gn:feature_class":"P",
    "gn:feature_code":"PPL",
    "gn:name":"Jeonggeo",
    "gn:population":0,
    "gn:timezone":"Asia/Seoul",
    "iso:country":"KR",
    "name:kor_x_preferred":[
        "\uc815\uac70"
    ],
    "name:und_x_variant":[
        "Teikyo-ri",
        "J\u014dkyo-ri",
        "Ch\u014fngg\u014f-ri",
        "Ch\u014fngg\u014f",
        "Jeonggeo"
    ],
    "wof:name":"Jeonggeo",
    "wof:placetype":"locality"
},
  "geometry": {"coordinates":[128.85395,35.06887],"type":"Point"}
}