{
  "type": "Feature",
  "properties": {
    "gn:admin1_code":"14.0",
    "gn:asciiname":"Sopsil-gol",
    "gn:country_code":"KR",
    "gn:dem":38,
    "gn:feature_class":"P",
    "gn:feature_code":"PPL",
    "gn:name":"S\u014fpsil-gol",
    "gn:population":0,
    "gn:timezone":"Asia/Seoul",
    "iso:country":"KR",
    "name:und_x_variant":[
        "\uc12d\uc2e4\uace8",
        "S\u014fpsil-gol"
    ],
    "wof:name":"Sopsil-gol",
    "wof:placetype":"locality"
},
  "geometry": {"coordinates":[129.44890000000001,36.7607],"type":"Point"}
}