{
  "type": "Feature",
  "properties": {
    "gn:admin1_code":"17.0",
    "gn:asciiname":"Sujori",
    "gn:country_code":"KR",
    "gn:dem":41,
    "gn:feature_class":"P",
    "gn:feature_code":"PPL",
    "gn:name":"Sujori",
    "gn:population":0,
    "gn:timezone":"Asia/Seoul",
    "iso:country":"KR",
    "name:kor_x_preferred":[
        "\uc218\uc870\ub9ac"
    ],
    "wof:name":"Sujori",
    "wof:placetype":"locality"
},
  "geometry": {"coordinates":[126.87811000000001,36.63857],"type":"Point"}
}