{
  "type": "Feature",
  "properties": {
    "gn:admin1_code":"20.0",
    "gn:asciiname":"Chindong-ni",
    "gn:country_code":"KR",
    "gn:dem":28,
    "gn:feature_class":"P",
    "gn:feature_code":"PPL",
    "gn:name":"Chindong-ni",
    "gn:population":0,
    "gn:timezone":"Asia/Seoul",
    "iso:country":"KR",
    "wof:name":"Chindong-ni",
    "wof:placetype":"locality"
},
  "geometry": {"coordinates":[128.05833000000001,34.8475],"type":"Point"}
}