{
  "type": "Feature",
  "properties": {
    "gn:admin1_code":"14.0",
    "gn:asciiname":"Nongmun",
    "gn:country_code":"KR",
    "gn:dem":84,
    "gn:feature_class":"P",
    "gn:feature_code":"PPL",
    "gn:name":"Nongmun",
    "gn:population":0,
    "gn:timezone":"Asia/Seoul",
    "iso:country":"KR",
    "name:kor_x_preferred":[
        "\ub179\ubb38"
    ],
    "wof:name":"Nongmun",
    "wof:placetype":"locality"
},
  "geometry": {"coordinates":[128.25623999999999,36.63003],"type":"Point"}
}