{
  "type": "Feature",
  "properties": {
    "gn:admin1_code":"12.0",
    "gn:asciiname":"So-yeonpyeong",
    "gn:country_code":"KR",
    "gn:dem":15,
    "gn:feature_class":"P",
    "gn:feature_code":"PPL",
    "gn:name":"So-yeonpyeong",
    "gn:population":0,
    "gn:timezone":"Asia/Seoul",
    "iso:country":"KR",
    "name:und_x_variant":[
        "Sany\u014fnp\u2019y\u014fng",
        "\uc18c\uc5f0\ud3c9",
        "So-yeonpyeong",
        "Soy\u014fnp\u2019y\u014fng"
    ],
    "wof:name":"So-yeonpyeong",
    "wof:placetype":"locality"
},
  "geometry": {"coordinates":[125.70833,37.61056],"type":"Point"}
}