{
  "type": "Feature",
  "properties": {
    "gn:admin1_code":"13.0",
    "gn:asciiname":"Nongok",
    "gn:country_code":"KR",
    "gn:dem":42,
    "gn:feature_class":"P",
    "gn:feature_code":"PPL",
    "gn:name":"Nongok",
    "gn:population":0,
    "gn:timezone":"Asia/Seoul",
    "iso:country":"KR",
    "name:kor_x_preferred":[
        "\ub17c\uace1"
    ],
    "wof:name":"Nongok",
    "wof:placetype":"locality"
},
  "geometry": {"coordinates":[126.85493,37.39362],"type":"Point"}
}