{
  "type": "Feature",
  "properties": {
    "iso:country":"KR",
    "qs:name":"\uc6d0\ub3d9\uba74",
    "qs:name_adm0":"\ud55c\uad6d",
    "qs:name_adm1":"\uacbd\uc0c1\ub0a8\ub3c4",
    "qs:photos":3,
    "qs:photos_1k":1,
    "qs:photos_9k":1,
    "qs:photos_9r":1,
    "qs:photos_all":3,
    "qs:photos_sr":1,
    "qs:placetype":"LocalAdmin",
    "qs:pop_sr":"0",
    "wof:name":"\uc6d0\ub3d9\uba74",
    "wof:placetype":"localadmin"
},
  "geometry": {"coordinates":[129.06120250000001,35.413256],"type":"Point"}
}