{
  "type": "Feature",
  "properties": {
    "gn:admin1_code":"17.0",
    "gn:asciiname":"Kuryong-gol",
    "gn:country_code":"KR",
    "gn:dem":22,
    "gn:feature_class":"P",
    "gn:feature_code":"PPL",
    "gn:name":"Kuryong-gol",
    "gn:population":0,
    "gn:timezone":"Asia/Seoul",
    "iso:country":"KR",
    "name:und_x_variant":[
        "\uad6c\ub8e1\uace8",
        "Kuryong-gol"
    ],
    "wof:name":"Kuryong-gol",
    "wof:placetype":"locality"
},
  "geometry": {"coordinates":[126.873,36.8427],"type":"Point"}
}