{
  "type": "Feature",
  "properties": {
    "gn:admin1_code":"12.0",
    "gn:asciiname":"Ogol",
    "gn:country_code":"KR",
    "gn:dem":27,
    "gn:feature_class":"P",
    "gn:feature_code":"PPL",
    "gn:name":"Ogol",
    "gn:population":0,
    "gn:timezone":"Asia/Seoul",
    "iso:country":"KR",
    "name:kor_x_preferred":[
        "\uc624\uace8"
    ],
    "name:kor_x_variant":[
        "\uae4c\uce58\uace8"
    ],
    "name:und_x_variant":[
        "Kkach\u2019i-gol",
        "Kkachi-gol"
    ],
    "wof:name":"Ogol",
    "wof:placetype":"locality"
},
  "geometry": {"coordinates":[126.48578000000001,37.67603],"type":"Point"}
}