{
  "type": "Feature",
  "properties": {
    "gn:admin1_code":"10.0",
    "gn:asciiname":"Ungch'ol-li",
    "gn:country_code":"KR",
    "gn:dem":170,
    "gn:feature_class":"P",
    "gn:feature_code":"PPL",
    "gn:name":"Ungch\u2019\u014fl-li",
    "gn:population":0,
    "gn:timezone":"Asia/Seoul",
    "iso:country":"KR",
    "name:und_x_variant":[
        "Ungch\u2019\u014fn-ni",
        "Ungch\u2019\u014fl-li"
    ],
    "wof:name":"Ungch'ol-li",
    "wof:placetype":"locality"
},
  "geometry": {"coordinates":[129.16361000000001,35.28917],"type":"Point"}
}