{
  "type": "Feature",
  "properties": {
    "gn:admin1_code":"17.0",
    "gn:asciiname":"Chuksan",
    "gn:country_code":"KR",
    "gn:dem":73,
    "gn:feature_class":"P",
    "gn:feature_code":"PPL",
    "gn:name":"Chuksan",
    "gn:population":0,
    "gn:timezone":"Asia/Seoul",
    "iso:country":"KR",
    "name:kor_x_preferred":[
        "\ucd95\uc0b0"
    ],
    "wof:name":"Chuksan",
    "wof:placetype":"locality"
},
  "geometry": {"coordinates":[127.304,36.44065],"type":"Point"}
}