{
  "type": "Feature",
  "properties": {
    "gn:admin1_code":"13.0",
    "gn:asciiname":"Giheung",
    "gn:country_code":"KR",
    "gn:dem":80,
    "gn:feature_class":"P",
    "gn:feature_code":"PPL",
    "gn:name":"Giheung",
    "gn:population":0,
    "gn:timezone":"Asia/Seoul",
    "iso:country":"KR",
    "name:und_x_variant":[
        "\uae30\ud765",
        "Giheung",
        "Kih\u016dng"
    ],
    "wof:name":"Giheung",
    "wof:placetype":"locality"
},
  "geometry": {"coordinates":[127.10833,37.27917],"type":"Point"}
}