{
  "type": "Feature",
  "properties": {
    "gn:admin1_code":"16.0",
    "gn:asciiname":"Dangsangol",
    "gn:country_code":"KR",
    "gn:dem":33,
    "gn:feature_class":"P",
    "gn:feature_code":"PPL",
    "gn:name":"Dangsangol",
    "gn:population":0,
    "gn:timezone":"Asia/Seoul",
    "iso:country":"KR",
    "name:kor_x_preferred":[
        "\ub2f9\uc0b0\uace8"
    ],
    "name:und_x_variant":[
        "Tangsan-gol",
        "Dangsangol"
    ],
    "wof:name":"Dangsangol",
    "wof:placetype":"locality"
},
  "geometry": {"coordinates":[126.64278,34.62417],"type":"Point"}
}