{
  "type": "Feature",
  "properties": {
    "gn:admin1_code":"1.0",
    "gn:asciiname":"Songdong-ni",
    "gn:country_code":"KR",
    "gn:dem":21,
    "gn:feature_class":"P",
    "gn:feature_code":"PPL",
    "gn:name":"S\u014fngd\u014fng-ni",
    "gn:population":0,
    "gn:timezone":"Asia/Seoul",
    "iso:country":"KR",
    "name:eng_x_preferred":[
        "Songdong"
    ],
    "name:eng_x_variant":[
        "Songdong-ni"
    ],
    "wof:name":"Songdong",
    "wof:placetype":"locality"
},
  "geometry": {"coordinates":[126.67417,33.535],"type":"Point"}
}