{
  "type": "Feature",
  "properties": {
    "gn:admin1_code":"5.0",
    "gn:asciiname":"Bakkatjangim",
    "gn:country_code":"KR",
    "gn:dem":247,
    "gn:feature_class":"P",
    "gn:feature_code":"PPL",
    "gn:name":"Bakkatjangim",
    "gn:population":0,
    "gn:timezone":"Asia/Seoul",
    "iso:country":"KR",
    "name:kor_x_preferred":[
        "\ubc14\uae65\uc7a5\uc784"
    ],
    "wof:name":"Bakkatjangim",
    "wof:placetype":"locality"
},
  "geometry": {"coordinates":[127.69423,36.73734],"type":"Point"}
}