{
  "type": "Feature",
  "properties": {
    "gn:admin1_code":"17.0",
    "gn:asciiname":"Kaeya-ri",
    "gn:cc2":"KR",
    "gn:country_code":"KR",
    "gn:dem":24,
    "gn:feature_class":"P",
    "gn:feature_code":"PPL",
    "gn:name":"Kaeya-ri",
    "gn:population":0,
    "gn:timezone":"Asia/Seoul",
    "iso:country":"KR",
    "name:und_x_variant":[
        "Keya-ri",
        "Kaeya-ri"
    ],
    "wof:name":"Kaeya-ri",
    "wof:placetype":"locality"
},
  "geometry": {"coordinates":[126.57056,36.17417],"type":"Point"}
}