{
  "type": "Feature",
  "properties": {
    "gn:admin1_code":"20.0",
    "gn:asciiname":"Sinan",
    "gn:country_code":"KR",
    "gn:dem":34,
    "gn:feature_class":"P",
    "gn:feature_code":"PPL",
    "gn:name":"Sinan",
    "gn:population":0,
    "gn:timezone":"Asia/Seoul",
    "iso:country":"KR",
    "name:ara_x_preferred":[
        "\u0633\u0646\u0627\u0646"
    ],
    "name:bul_x_preferred":[
        "\u0421\u0438\u043d\u0430\u043d \u043f\u0430\u0448\u0430"
    ],
    "name:ceb_x_preferred":[
        "Sinan"
    ],
    "name:deu_x_preferred":[
        "Sinan"
    ],
    "name:fra_x_preferred":[
        "Sinan"
    ],
    "name:heb_x_preferred":[
        "\u05e1\u05d9\u05e0\u05d0\u05df"
    ],
    "name:jpn_x_preferred":[
        "\u30b7\u30ca\u30f3"
    ],
    "name:nor_x_preferred":[
        "Sinan"
    ],
    "name:rus_x_preferred":[
        "\u0421\u0438\u043d\u0430\u043d"
    ],
    "name:slv_x_preferred":[
        "Sinan"
    ],
    "name:stq_x_preferred":[
        "Sinan"
    ],
    "name:swe_x_preferred":[
        "Sinan"
    ],
    "name:und_x_variant":[
        "\uc2e0\uc548"
    ],
    "wof:name":"Sinan",
    "wof:placetype":"locality"
},
  "geometry": {"coordinates":[128.45948999999999,35.60082],"type":"Point"}
}