{
  "type": "Feature",
  "properties": {
    "gn:admin1_code":"6.0",
    "gn:asciiname":"Orichon",
    "gn:country_code":"KR",
    "gn:dem":188,
    "gn:feature_class":"P",
    "gn:feature_code":"PPL",
    "gn:name":"Orichon",
    "gn:population":0,
    "gn:timezone":"Asia/Seoul",
    "iso:country":"KR",
    "name:kor_x_preferred":[
        "\uc624\ub9ac\ucd0c"
    ],
    "wof:name":"Orichon",
    "wof:placetype":"locality"
},
  "geometry": {"coordinates":[127.23260000000001,38.21131],"type":"Point"}
}