{
  "type": "Feature",
  "properties": {
    "gn:admin1_code":"13.0",
    "gn:asciiname":"Goeupdong",
    "gn:country_code":"KR",
    "gn:dem":42,
    "gn:feature_class":"P",
    "gn:feature_code":"PPL",
    "gn:name":"Goeupdong",
    "gn:population":0,
    "gn:timezone":"Asia/Seoul",
    "iso:country":"KR",
    "name:und_x_variant":[
        "\uace0\uc74d\ub3d9",
        "Goeupdong",
        "Ko\u016dp-tong"
    ],
    "wof:name":"Goeupdong",
    "wof:placetype":"locality"
},
  "geometry": {"coordinates":[126.55565,37.73195],"type":"Point"}
}