{
  "type": "Feature",
  "properties": {
    "gn:admin1_code":"16.0",
    "gn:asciiname":"Nobyeon",
    "gn:country_code":"KR",
    "gn:dem":117,
    "gn:feature_class":"P",
    "gn:feature_code":"PPL",
    "gn:name":"Nobyeon",
    "gn:population":0,
    "gn:timezone":"Asia/Seoul",
    "iso:country":"KR",
    "name:kor_x_preferred":[
        "\ub178\ub450"
    ],
    "name:kor_x_variant":[
        "\ub178\ubcc0"
    ],
    "name:und_x_variant":[
        "Nodu",
        "Nobyeon"
    ],
    "wof:name":"Nobyeon",
    "wof:placetype":"locality"
},
  "geometry": {"coordinates":[127.45987,34.95479],"type":"Point"}
}