{
  "type": "Feature",
  "properties": {
    "gn:admin1_code":"5.0",
    "gn:asciiname":"Mokpangi",
    "gn:country_code":"KR",
    "gn:dem":185,
    "gn:feature_class":"P",
    "gn:feature_code":"PPL",
    "gn:name":"M\u014fkpangi",
    "gn:population":0,
    "gn:timezone":"Asia/Seoul",
    "iso:country":"KR",
    "name:und_x_variant":[
        "\uba39\ubc29\uc774",
        "M\u014fkpangi"
    ],
    "wof:name":"Mokpangi",
    "wof:placetype":"locality"
},
  "geometry": {"coordinates":[127.64409999999999,36.1958],"type":"Point"}
}