{
  "type": "Feature",
  "properties": {
    "gn:admin1_code":"16.0",
    "gn:asciiname":"Saengdong",
    "gn:country_code":"KR",
    "gn:dem":42,
    "gn:feature_class":"P",
    "gn:feature_code":"PPL",
    "gn:name":"Saengdong",
    "gn:population":0,
    "gn:timezone":"Asia/Seoul",
    "iso:country":"KR",
    "name:kor_x_preferred":[
        "\uc0dd\ub3d9\ub9ac"
    ],
    "name:kor_x_variant":[
        "\uc0dd\ub3d9"
    ],
    "name:und_x_variant":[
        "Hasan-ri",
        "P\u2019asan",
        "P\u2019asan-ni",
        "P\u2019asal-li",
        "Saengdong-ni",
        "Saengdong"
    ],
    "wof:name":"Saengdong",
    "wof:placetype":"locality"
},
  "geometry": {"coordinates":[126.79694000000001,34.65611],"type":"Point"}
}