{
  "type": "Feature",
  "properties": {
    "gn:admin1_code":"16.0",
    "gn:asciiname":"Tason-ri",
    "gn:country_code":"KR",
    "gn:dem":-9999,
    "gn:feature_class":"P",
    "gn:feature_code":"PPL",
    "gn:name":"Tason-ri",
    "gn:population":0,
    "gn:timezone":"Asia/Seoul",
    "iso:country":"KR",
    "name:und_x_variant":[
        "Tason",
        "Tason-ri",
        "Tach\u2019on-ni"
    ],
    "wof:name":"Tason-ri",
    "wof:placetype":"locality"
},
  "geometry": {"coordinates":[125.45,34.73333],"type":"Point"}
}