{
  "type": "Feature",
  "properties": {
    "gn:admin1_code":"13.0",
    "gn:asciiname":"Gojamoe",
    "gn:country_code":"KR",
    "gn:dem":35,
    "gn:feature_class":"P",
    "gn:feature_code":"PPL",
    "gn:name":"Gojamoe",
    "gn:population":0,
    "gn:timezone":"Asia/Seoul",
    "iso:country":"KR",
    "name:und_x_variant":[
        "\uace0\uc790\ub9e4",
        "Gojamoe",
        "Kojamae"
    ],
    "wof:name":"Gojamoe",
    "wof:placetype":"locality"
},
  "geometry": {"coordinates":[126.59,37.71917],"type":"Point"}
}