{
  "type": "Feature",
  "properties": {
    "gn:admin1_code":"6.0",
    "gn:asciiname":"Si-dong",
    "gn:country_code":"KR",
    "gn:dem":336,
    "gn:feature_class":"P",
    "gn:feature_code":"PPL",
    "gn:name":"Si-dong",
    "gn:population":0,
    "gn:timezone":"Asia/Seoul",
    "iso:country":"KR",
    "name:kor_x_preferred":[
        "\uc2dc\ub3d9"
    ],
    "wof:name":"Si-dong",
    "wof:placetype":"locality"
},
  "geometry": {"coordinates":[128.39750000000001,37.3093],"type":"Point"}
}