{
  "type": "Feature",
  "properties": {
    "gn:admin1_code":"3.0",
    "gn:asciiname":"Changwon",
    "gn:country_code":"KR",
    "gn:dem":12,
    "gn:feature_class":"P",
    "gn:feature_code":"PPL",
    "gn:name":"Changw\u014fn",
    "gn:population":0,
    "gn:timezone":"Asia/Seoul",
    "iso:country":"KR",
    "wof:name":"Changwon",
    "wof:placetype":"locality"
},
  "geometry": {"coordinates":[126.63,35.92472],"type":"Point"}
}