{
  "type": "Feature",
  "properties": {
    "gn:admin1_code":"3.0",
    "gn:asciiname":"Changwon",
    "gn:country_code":"KR",
    "gn:dem":12,
    "gn:feature_class":"P",
    "gn:feature_code":"PPL",
    "gn:name":"Changw\u014fn",
    "gn:population":0,
    "gn:timezone":"Asia/Seoul",
    "iso:country":"KR",
    "name:afr_x_preferred":[
        "Changwon"
    ],
    "name:ara_x_preferred":[
        "\u062a\u0634\u0627\u0646\u063a\u0648\u0648\u0646"
    ],
    "name:ast_x_preferred":[
        "Changwon"
    ],
    "name:bul_x_preferred":[
        "\u0427\u0430\u043d\u0433\u0443\u043e\u043d"
    ],
    "name:cat_x_preferred":[
        "Changwon"
    ],
    "name:ceb_x_preferred":[
        "Changwon"
    ],
    "name:ces_x_preferred":[
        "\u010cchangwon"
    ],
    "name:che_x_preferred":[
        "\u0427\u0445\u0430\u043d\u0432\u043e\u043d"
    ],
    "name:deu_x_preferred":[
        "Changwon"
    ],
    "name:epo_x_preferred":[
        "\u0108angvon"
    ],
    "name:fas_x_preferred":[
        "\u0686\u0627\u0646\u06af\u200c\u0648\u0648\u0646"
    ],
    "name:fin_x_preferred":[
        "Changwon"
    ],
    "name:fra_x_preferred":[
        "Changwon"
    ],
    "name:heb_x_preferred":[
        "\u05e6'\u05e0\u05d2\u05d5\u05d5\u05df"
    ],
    "name:hun_x_preferred":[
        "Cshangvon"
    ],
    "name:ido_x_preferred":[
        "Changwon"
    ],
    "name:ind_x_preferred":[
        "Changwon"
    ],
    "name:ita_x_preferred":[
        "Changwon"
    ],
    "name:jav_x_preferred":[
        "Changwon"
    ],
    "name:jpn_x_preferred":[
        "\u660c\u539f\u5e02"
    ],
    "name:kal_x_preferred":[
        "Changwon"
    ],
    "name:kor_x_preferred":[
        "\ucc3d\uc6d0\uc2dc"
    ],
    "name:lit_x_preferred":[
        "\u010cangvonas"
    ],
    "name:lmo_x_preferred":[
        "Changwon"
    ],
    "name:mon_x_preferred":[
        "\u0427\u0430\u043d\u0432\u043e\u043d"
    ],
    "name:mri_x_preferred":[
        "Changwon"
    ],
    "name:nld_x_preferred":[
        "Changwon"
    ],
    "name:nor_x_preferred":[
        "Changwon"
    ],
    "name:oss_x_preferred":[
        "\u0427\u0445\u0430\u043d\u0432\u043e\u043d"
    ],
    "name:pnb_x_preferred":[
        "\u0686\u0627\u0646\u06af\u0648\u0646"
    ],
    "name:pol_x_preferred":[
        "Changwon"
    ],
    "name:por_x_preferred":[
        "Changwon"
    ],
    "name:rus_x_preferred":[
        "\u0427\u0445\u0430\u043d\u0432\u043e\u043d"
    ],
    "name:spa_x_preferred":[
        "Changwon"
    ],
    "name:swa_x_preferred":[
        "Changwon"
    ],
    "name:swe_x_preferred":[
        "Changwon"
    ],
    "name:tgl_x_preferred":[
        "Changwon"
    ],
    "name:tur_x_preferred":[
        "Changwon"
    ],
    "name:ukr_x_preferred":[
        "\u0427\u0445\u0430\u043d\u0432\u043e\u043d"
    ],
    "name:urd_x_preferred":[
        "\u0686\u0627\u0646\u06af\u0648\u0648\u0646"
    ],
    "name:vie_x_preferred":[
        "Changwon"
    ],
    "name:war_x_preferred":[
        "Changwon"
    ],
    "name:zho_x_preferred":[
        "\u660c\u539f\u5e02"
    ],
    "wof:name":"Changwon",
    "wof:placetype":"locality"
},
  "geometry": {"coordinates":[126.63,35.92472],"type":"Point"}
}