{
  "type": "Feature",
  "properties": {
    "gn:admin1_code":"5.0",
    "gn:asciiname":"Samjeongni",
    "gn:country_code":"KR",
    "gn:dem":123,
    "gn:feature_class":"P",
    "gn:feature_code":"PPL",
    "gn:name":"Samjeongni",
    "gn:population":0,
    "gn:timezone":"Asia/Seoul",
    "iso:country":"KR",
    "name:kor_x_preferred":[
        "\uc0bc\uc815\ub9ac"
    ],
    "wof:name":"Samjeongni",
    "wof:placetype":"locality"
},
  "geometry": {"coordinates":[127.84272,36.77332],"type":"Point"}
}