{
  "type": "Feature",
  "properties": {
    "gn:admin1_code":"6.0",
    "gn:asciiname":"Oryudong",
    "gn:country_code":"KR",
    "gn:dem":340,
    "gn:feature_class":"P",
    "gn:feature_code":"PPL",
    "gn:name":"Oryudong",
    "gn:population":0,
    "gn:timezone":"Asia/Seoul",
    "iso:country":"KR",
    "name:kor_x_preferred":[
        "\uc624\ub958\ub3d9"
    ],
    "wof:name":"Oryudong",
    "wof:placetype":"locality"
},
  "geometry": {"coordinates":[128.34975,37.95192],"type":"Point"}
}