{
  "type": "Feature",
  "properties": {
    "gn:admin1_code":"14.0",
    "gn:asciiname":"Hyanggyo",
    "gn:country_code":"KR",
    "gn:dem":73,
    "gn:feature_class":"P",
    "gn:feature_code":"PPL",
    "gn:name":"Hyanggyo",
    "gn:population":0,
    "gn:timezone":"Asia/Seoul",
    "iso:country":"KR",
    "name:und_x_variant":[
        "\ud5a5\uad50",
        "Hyanggyo"
    ],
    "wof:name":"Hyanggyo",
    "wof:placetype":"locality"
},
  "geometry": {"coordinates":[128.1576,36.4033],"type":"Point"}
}