{
  "type": "Feature",
  "properties": {
    "gn:admin1_code":"3.0",
    "gn:asciiname":"Sangsong",
    "gn:country_code":"KR",
    "gn:dem":260,
    "gn:feature_class":"P",
    "gn:feature_code":"PPL",
    "gn:name":"Sangs\u014fng",
    "gn:population":0,
    "gn:timezone":"Asia/Seoul",
    "iso:country":"KR",
    "name:und_x_variant":[
        "\uc0c1\uc131",
        "Sangs\u014fng"
    ],
    "wof:name":"Sangsong",
    "wof:placetype":"locality"
},
  "geometry": {"coordinates":[127.27330000000001,35.61152],"type":"Point"}
}