{
  "type": "Feature",
  "properties": {
    "gn:admin1_code":"14.0",
    "gn:asciiname":"Gaejeongni",
    "gn:country_code":"KR",
    "gn:dem":36,
    "gn:feature_class":"P",
    "gn:feature_code":"PPL",
    "gn:name":"Gaejeongni",
    "gn:population":0,
    "gn:timezone":"Asia/Seoul",
    "iso:country":"KR",
    "name:und_x_variant":[
        "\uac1c\uc815\ub9ac",
        "Kaej\u014fng-ni",
        "Gaejeongni"
    ],
    "wof:name":"Gaejeongni",
    "wof:placetype":"locality"
},
  "geometry": {"coordinates":[128.36348000000001,35.83971],"type":"Point"}
}