{
  "type": "Feature",
  "properties": {
    "gn:admin1_code":"6.0",
    "gn:asciiname":"Woltun-gol",
    "gn:country_code":"KR",
    "gn:dem":524,
    "gn:feature_class":"P",
    "gn:feature_code":"PPL",
    "gn:name":"W\u014fltun-gol",
    "gn:population":0,
    "gn:timezone":"Asia/Seoul",
    "iso:country":"KR",
    "name:kor_x_preferred":[
        "W\u014fltun-gol"
    ],
    "name:kor_x_variant":[
        "\uc6d4\ub454\uace8"
    ],
    "wof:name":"Woltun-gol",
    "wof:placetype":"locality"
},
  "geometry": {"coordinates":[128.41833,37.83528],"type":"Point"}
}