{
  "type": "Feature",
  "properties": {
    "gn:admin1_code":"13.0",
    "gn:asciiname":"Eungol",
    "gn:country_code":"KR",
    "gn:dem":42,
    "gn:feature_class":"P",
    "gn:feature_code":"PPL",
    "gn:name":"Eungol",
    "gn:population":0,
    "gn:timezone":"Asia/Seoul",
    "iso:country":"KR",
    "name:kor_x_preferred":[
        "\uc740\uace8"
    ],
    "name:kor_x_variant":[
        "\u016cn-gol"
    ],
    "wof:name":"Eungol",
    "wof:placetype":"locality"
},
  "geometry": {"coordinates":[126.84978999999998,37.74502],"type":"Point"}
}