{
  "type": "Feature",
  "properties": {
    "gn:admin1_code":"14.0",
    "gn:asciiname":"Yongha-dong",
    "gn:country_code":"KR",
    "gn:dem":183,
    "gn:feature_class":"P",
    "gn:feature_code":"PPL",
    "gn:name":"Y\u014fngha-dong",
    "gn:population":0,
    "gn:timezone":"Asia/Seoul",
    "iso:country":"KR",
    "name:und_x_variant":[
        "\uc601\ud558\ub3d9",
        "Y\u014fngha-dong"
    ],
    "wof:name":"Yongha-dong",
    "wof:placetype":"locality"
},
  "geometry": {"coordinates":[128.0625,36.3914],"type":"Point"}
}