{
  "type": "Feature",
  "properties": {
    "gn:admin1_code":"14.0",
    "gn:asciiname":"Kosaribadyangji",
    "gn:country_code":"KR",
    "gn:dem":365,
    "gn:feature_class":"P",
    "gn:feature_code":"PPL",
    "gn:name":"Kosaribadyangji",
    "gn:population":0,
    "gn:timezone":"Asia/Seoul",
    "iso:country":"KR",
    "name:und_x_variant":[
        "\uace0\uc0ac\ub9ac\ubc2d\uc591\uc9c0",
        "Kosaribadyangji"
    ],
    "wof:name":"Kosaribadyangji",
    "wof:placetype":"locality"
},
  "geometry": {"coordinates":[129.184,36.3633],"type":"Point"}
}