{
  "type": "Feature",
  "properties": {
    "gn:admin1_code":"1.0",
    "gn:asciiname":"Kaga-dong",
    "gn:country_code":"KR",
    "gn:dem":175,
    "gn:feature_class":"P",
    "gn:feature_code":"PPL",
    "gn:name":"Kaga-dong",
    "gn:population":0,
    "gn:timezone":"Asia/Seoul",
    "iso:country":"KR",
    "wof:name":"Kaga-dong",
    "wof:placetype":"locality"
},
  "geometry": {"coordinates":[126.37333,33.27167],"type":"Point"}
}