{
  "type": "Feature",
  "properties": {
    "gn:admin1_code":"17.0",
    "gn:asciiname":"Sin-ch'on",
    "gn:country_code":"KR",
    "gn:dem":12,
    "gn:feature_class":"P",
    "gn:feature_code":"PPL",
    "gn:name":"Sin-ch\u2019on",
    "gn:population":0,
    "gn:timezone":"Asia/Seoul",
    "iso:country":"KR",
    "name:und_x_variant":[
        "\uc2e0\ucd0c",
        "Sin-ch\u2019on"
    ],
    "wof:name":"Sin-ch'on",
    "wof:placetype":"locality"
},
  "geometry": {"coordinates":[126.7627,36.7037],"type":"Point"}
}