{
  "type": "Feature",
  "properties": {
    "gn:admin1_code":"13.0",
    "gn:asciiname":"Hoengsal-li",
    "gn:cc2":"KR",
    "gn:country_code":"KR",
    "gn:dem":79,
    "gn:feature_class":"P",
    "gn:feature_code":"PPL",
    "gn:name":"Hoengsal-li",
    "gn:population":0,
    "gn:timezone":"Asia/Seoul",
    "iso:country":"KR",
    "name:und_x_variant":[
        "Hoengsan-ni",
        "Hoengsal-li"
    ],
    "wof:name":"Hoengsal-li",
    "wof:placetype":"locality"
},
  "geometry": {"coordinates":[126.98166999999999,38.11306],"type":"Point"}
}