{
  "type": "Feature",
  "properties": {
    "gn:admin1_code":"17.0",
    "gn:asciiname":"Sumut'i",
    "gn:country_code":"KR",
    "gn:dem":116,
    "gn:feature_class":"P",
    "gn:feature_code":"PPL",
    "gn:name":"S\u016dm\u016dt\u2019i",
    "gn:population":0,
    "gn:timezone":"Asia/Seoul",
    "iso:country":"KR",
    "name:und_x_variant":[
        "\uc2a4\ubbc0\ud2f0",
        "S\u016dm\u016dt\u2019i"
    ],
    "wof:name":"Sumut'i",
    "wof:placetype":"locality"
},
  "geometry": {"coordinates":[126.69070000000001,36.4056],"type":"Point"}
}