{
  "type": "Feature",
  "properties": {
    "gn:admin1_code":"17.0",
    "gn:asciiname":"Naena-ri",
    "gn:country_code":"KR",
    "gn:dem":126,
    "gn:feature_class":"P",
    "gn:feature_code":"PPL",
    "gn:name":"Naena-ri",
    "gn:population":0,
    "gn:timezone":"Asia/Seoul",
    "iso:country":"KR",
    "name:und_x_variant":[
        "\ub0b4\ub098\ub9ac",
        "Naena-ri"
    ],
    "wof:name":"Naena-ri",
    "wof:placetype":"locality"
},
  "geometry": {"coordinates":[126.7788,36.3377],"type":"Point"}
}