{
  "type": "Feature",
  "properties": {
    "gn:admin1_code":"5.0",
    "gn:asciiname":"Bamti",
    "gn:country_code":"KR",
    "gn:dem":163,
    "gn:feature_class":"P",
    "gn:feature_code":"PPL",
    "gn:name":"Bamti",
    "gn:population":0,
    "gn:timezone":"Asia/Seoul",
    "iso:country":"KR",
    "name:kor_x_preferred":[
        "\ubc24\ud2f0"
    ],
    "wof:name":"Bamti",
    "wof:placetype":"locality"
},
  "geometry": {"coordinates":[127.63834,36.71694],"type":"Point"}
}