{
  "type": "Feature",
  "properties": {
    "gn:admin1_code":"5.0",
    "gn:asciiname":"Bangchugol",
    "gn:country_code":"KR",
    "gn:dem":126,
    "gn:feature_class":"P",
    "gn:feature_code":"PPL",
    "gn:name":"Bangchugol",
    "gn:population":0,
    "gn:timezone":"Asia/Seoul",
    "iso:country":"KR",
    "name:kor_x_preferred":[
        "\ubc29\ucd94\uace8"
    ],
    "name:kor_x_variant":[
        "Pangch\u2019u-gol"
    ],
    "wof:name":"Bangchugol",
    "wof:placetype":"locality"
},
  "geometry": {"coordinates":[127.71639999999999,37.00792],"type":"Point"}
}