{
  "type": "Feature",
  "properties": {
    "gn:admin1_code":"17.0",
    "gn:asciiname":"Sodang-gol",
    "gn:country_code":"KR",
    "gn:dem":76,
    "gn:feature_class":"P",
    "gn:feature_code":"PPL",
    "gn:name":"S\u014fdang-gol",
    "gn:population":0,
    "gn:timezone":"Asia/Seoul",
    "iso:country":"KR",
    "name:und_x_variant":[
        "\uc11c\ub2f9\uace8",
        "S\u014fdang-gol"
    ],
    "wof:name":"Sodang-gol",
    "wof:placetype":"locality"
},
  "geometry": {"coordinates":[127.2212,36.1823],"type":"Point"}
}