{
  "type": "Feature",
  "properties": {
    "gn:admin1_code":"3.0",
    "gn:asciiname":"Kumjong",
    "gn:country_code":"KR",
    "gn:dem":255,
    "gn:feature_class":"P",
    "gn:feature_code":"PPL",
    "gn:name":"K\u016dmj\u014fng",
    "gn:population":0,
    "gn:timezone":"Asia/Seoul",
    "iso:country":"KR",
    "name:und_x_variant":[
        "\uae08\uc815",
        "K\u016dmj\u014fng"
    ],
    "wof:name":"Kumjong",
    "wof:placetype":"locality"
},
  "geometry": {"coordinates":[127.31588000000001,35.6752],"type":"Point"}
}