{
  "type": "Feature",
  "properties": {
    "gn:admin1_code":"20.0",
    "gn:asciiname":"Yusang",
    "gn:country_code":"KR",
    "gn:dem":28,
    "gn:feature_class":"P",
    "gn:feature_code":"PPL",
    "gn:name":"Yusang",
    "gn:population":0,
    "gn:timezone":"Asia/Seoul",
    "iso:country":"KR",
    "name:und_x_variant":[
        "\uc720\uc0c1",
        "Yusang"
    ],
    "wof:name":"Yusang",
    "wof:placetype":"locality"
},
  "geometry": {"coordinates":[128.49411000000001,35.30019],"type":"Point"}
}