{
  "type": "Feature",
  "properties": {
    "gn:admin1_code":"6.0",
    "gn:asciiname":"Dudaeso",
    "gn:country_code":"KR",
    "gn:dem":423,
    "gn:feature_class":"P",
    "gn:feature_code":"PPL",
    "gn:name":"Dudaeso",
    "gn:population":0,
    "gn:timezone":"Asia/Seoul",
    "iso:country":"KR",
    "name:kor_x_preferred":[
        "\ub450\ub300\uc18c"
    ],
    "name:und_x_variant":[
        "Tut\u2019ay\u014fn",
        "Tut\u2019aeso",
        "Dudaeso"
    ],
    "wof:name":"Dudaeso",
    "wof:placetype":"locality"
},
  "geometry": {"coordinates":[127.99278,38.27417],"type":"Point"}
}