{
  "type": "Feature",
  "properties": {
    "iso:country":"KR",
    "qs:name":"\ud55c\ub9bc\uc74d",
    "qs:name_adm0":"\ud55c\uad6d",
    "qs:name_adm1":"\uc81c\uc8fc\ud2b9\ubcc4\uc790\uce58\ub3c4",
    "qs:photos":1,
    "qs:photos_1k":1,
    "qs:photos_9k":1,
    "qs:photos_9r":1,
    "qs:photos_all":1,
    "qs:photos_sr":1,
    "qs:placetype":"LocalAdmin",
    "qs:pop_sr":"0",
    "wof:name":"\ud55c\ub9bc\uc74d",
    "wof:placetype":"localadmin"
},
  "geometry": {"coordinates":[126.25659899999999,33.3890925],"type":"Point"}
}