{
  "type": "Feature",
  "properties": {
    "gn:admin1_code":"17.0",
    "gn:asciiname":"Sinp'yong",
    "gn:country_code":"KR",
    "gn:dem":41,
    "gn:feature_class":"P",
    "gn:feature_code":"PPL",
    "gn:name":"Sinp\u2019y\u014fng",
    "gn:population":0,
    "gn:timezone":"Asia/Seoul",
    "iso:country":"KR",
    "name:und_x_variant":[
        "\uc2e0\ud3c9",
        "Sinp\u2019y\u014fng"
    ],
    "wof:name":"Sinp'yong",
    "wof:placetype":"locality"
},
  "geometry": {"coordinates":[127.20780000000001,36.1805],"type":"Point"}
}