{
  "type": "Feature",
  "properties": {
    "gn:admin1_code":"20.0",
    "gn:asciiname":"Mosang",
    "gn:country_code":"KR",
    "gn:dem":34,
    "gn:feature_class":"P",
    "gn:feature_code":"PPL",
    "gn:name":"Mosang",
    "gn:population":0,
    "gn:timezone":"Asia/Seoul",
    "iso:country":"KR",
    "name:und_x_variant":[
        "\ubaa8\uc0c1",
        "Mosang"
    ],
    "wof:name":"Mosang",
    "wof:placetype":"locality"
},
  "geometry": {"coordinates":[128.35708,34.82652],"type":"Point"}
}