{
  "type": "Feature",
  "properties": {
    "gn:admin1_code":"13.0",
    "gn:asciiname":"Sataemal",
    "gn:country_code":"KR",
    "gn:dem":111,
    "gn:feature_class":"P",
    "gn:feature_code":"PPL",
    "gn:name":"Sataemal",
    "gn:population":0,
    "gn:timezone":"Asia/Seoul",
    "iso:country":"KR",
    "name:kor_x_preferred":[
        "\uc0ac\ud0dc\ub9d0"
    ],
    "wof:name":"Sataemal",
    "wof:placetype":"locality"
},
  "geometry": {"coordinates":[127.40866,37.05739000000001],"type":"Point"}
}