{
  "type": "Feature",
  "properties": {
    "gn:admin1_code":"20.0",
    "gn:asciiname":"Oyon'gum",
    "gn:country_code":"KR",
    "gn:dem":45,
    "gn:feature_class":"P",
    "gn:feature_code":"PPL",
    "gn:name":"\u014ey\u014fn\u2019g\u016dm",
    "gn:population":0,
    "gn:timezone":"Asia/Seoul",
    "iso:country":"KR",
    "name:und_x_variant":[
        "\uc5b4\uc5f0\uae08",
        "\u014ey\u014fn\u2019g\u016dm"
    ],
    "wof:name":"Oyon'gum",
    "wof:placetype":"locality"
},
  "geometry": {"coordinates":[128.24812,34.82454],"type":"Point"}
}