{
  "type": "Feature",
  "properties": {
    "gn:admin1_code":"11.0",
    "gn:asciiname":"Kirumsam-dong",
    "gn:country_code":"KR",
    "gn:dem":54,
    "gn:feature_class":"P",
    "gn:feature_code":"PPL",
    "gn:name":"Kir\u016dmsam-dong",
    "gn:population":0,
    "gn:timezone":"Asia/Seoul",
    "iso:country":"KR",
    "name:und_x_variant":[
        "\uae38\uc74c3\ub3d9",
        "Kir\u016dmsam-dong"
    ],
    "wof:name":"Kirumsam-dong",
    "wof:placetype":"locality"
},
  "geometry": {"coordinates":[127.02629,37.60844],"type":"Point"}
}