{
  "type": "Feature",
  "properties": {
    "gn:admin1_code":"20.0",
    "gn:asciiname":"Sungsan",
    "gn:country_code":"KR",
    "gn:dem":29,
    "gn:feature_class":"P",
    "gn:feature_code":"PPL",
    "gn:name":"S\u016dngsan",
    "gn:population":0,
    "gn:timezone":"Asia/Seoul",
    "iso:country":"KR",
    "name:und_x_variant":[
        "S\u016dngsan-dong",
        "\uc2b9\uc0b0",
        "S\u016dngsan"
    ],
    "wof:name":"Sungsan",
    "wof:placetype":"locality"
},
  "geometry": {"coordinates":[128.26806000000002,35.23512],"type":"Point"}
}