{
  "type": "Feature",
  "properties": {
    "gn:admin1_code":"20.0",
    "gn:asciiname":"Sogajong",
    "gn:cc2":"KR",
    "gn:country_code":"KR",
    "gn:dem":176,
    "gn:feature_class":"P",
    "gn:feature_code":"PPL",
    "gn:name":"S\u014fgaj\u014fng",
    "gn:population":0,
    "gn:timezone":"Asia/Seoul",
    "iso:country":"KR",
    "name:und_x_variant":[
        "S\u014fgaj\u014fng-dong",
        "S\u014fgaj\u014fng"
    ],
    "wof:name":"Sogajong",
    "wof:placetype":"locality"
},
  "geometry": {"coordinates":[128.58333000000002,35.48333],"type":"Point"}
}