{
  "type": "Feature",
  "properties": {
    "gn:admin1_code":"13.0",
    "gn:admin2_code":"Ans\u014fng-si",
    "gn:asciiname":"Juksan",
    "gn:country_code":"KR",
    "gn:dem":136,
    "gn:feature_class":"P",
    "gn:feature_code":"PPL",
    "gn:name":"Juksan",
    "gn:population":0,
    "gn:timezone":"Asia/Seoul",
    "iso:country":"KR",
    "name:kor_x_preferred":[
        "\uc8fd\uc0b0"
    ],
    "name:und_x_variant":[
        "Chuksan",
        "Juksan"
    ],
    "wof:name":"Juksan",
    "wof:placetype":"locality"
},
  "geometry": {"coordinates":[127.41433000000001,37.08033],"type":"Point"}
}