{
  "type": "Feature",
  "properties": {
    "gn:admin1_code":"10.0",
    "gn:asciiname":"Taihen-ri",
    "gn:country_code":"KR",
    "gn:dem":8,
    "gn:feature_class":"P",
    "gn:feature_code":"PPL",
    "gn:name":"Taihen-ri",
    "gn:population":0,
    "gn:timezone":"Asia/Seoul",
    "iso:country":"KR",
    "name:und_x_variant":[
        "Taeby\u014fn-ni",
        "Taeby\u014fn-ri",
        "Taeby\u014fn"
    ],
    "wof:name":"Taihen-ri",
    "wof:placetype":"locality"
},
  "geometry": {"coordinates":[129.22833,35.22611],"type":"Point"}
}