{
  "type": "Feature",
  "properties": {
    "gn:admin1_code":"14.0",
    "gn:asciiname":"Yongam",
    "gn:country_code":"KR",
    "gn:dem":86,
    "gn:feature_class":"P",
    "gn:feature_code":"PPL",
    "gn:name":"Yongam",
    "gn:population":0,
    "gn:timezone":"Asia/Seoul",
    "iso:country":"KR",
    "name:und_x_variant":[
        "\uc6a9\uc554",
        "Yongam"
    ],
    "wof:name":"Yongam",
    "wof:placetype":"locality"
},
  "geometry": {"coordinates":[128.37010000000001,36.3544],"type":"Point"}
}