{
  "type": "Feature",
  "properties": {
    "gn:admin1_code":"13.0",
    "gn:admin2_code":"Yongin-si",
    "gn:asciiname":"Jeomchon",
    "gn:country_code":"KR",
    "gn:dem":50,
    "gn:feature_class":"P",
    "gn:feature_code":"PPL",
    "gn:name":"Jeomchon",
    "gn:population":0,
    "gn:timezone":"Asia/Seoul",
    "iso:country":"KR",
    "name:kor_x_preferred":[
        "\uc810\ucd0c"
    ],
    "name:kor_x_variant":[
        "Ch\u014fmch\u2019on"
    ],
    "wof:name":"Jeomchon",
    "wof:placetype":"locality"
},
  "geometry": {"coordinates":[127.20885,37.11452],"type":"Point"}
}