{
  "type": "Feature",
  "properties": {
    "gn:admin1_code":"13.0",
    "gn:asciiname":"Hamjeong-ri",
    "gn:country_code":"KR",
    "gn:dem":4,
    "gn:feature_class":"P",
    "gn:feature_code":"PPL",
    "gn:name":"Hamjeong-ri",
    "gn:population":0,
    "gn:timezone":"Asia/Seoul",
    "iso:country":"KR",
    "name:und_x_variant":[
        "Ky\u014fngj\u014fng-ni",
        "\ud568\uc815\ub9ac",
        "Hamj\u014fng",
        "Hamj\u014fng-ni",
        "Hamjeong-ri"
    ],
    "wof:name":"Hamjeong-ri",
    "wof:placetype":"locality"
},
  "geometry": {"coordinates":[127.02043,36.95695],"type":"Point"}
}