{
  "type": "Feature",
  "properties": {
    "gn:admin1_code":"6.0",
    "gn:asciiname":"Araessadun",
    "gn:country_code":"KR",
    "gn:dem":30,
    "gn:feature_class":"P",
    "gn:feature_code":"PPL",
    "gn:name":"Araessadun",
    "gn:population":0,
    "gn:timezone":"Asia/Seoul",
    "iso:country":"KR",
    "name:und_x_variant":[
        "\uc544\ub7ab\uc0ac\ub454",
        "Araessadun"
    ],
    "wof:name":"Araessadun",
    "wof:placetype":"locality"
},
  "geometry": {"coordinates":[129.11259999999999,37.4241],"type":"Point"}
}