{
  "type": "Feature",
  "properties": {
    "gn:admin1_code":"17.0",
    "gn:asciiname":"Gwangseok",
    "gn:country_code":"KR",
    "gn:dem":72,
    "gn:feature_class":"P",
    "gn:feature_code":"PPL",
    "gn:name":"Gwangseok",
    "gn:population":0,
    "gn:timezone":"Asia/Seoul",
    "iso:country":"KR",
    "name:kor_x_preferred":[
        "\uad11\uc11d"
    ],
    "wof:name":"Gwangseok",
    "wof:placetype":"locality"
},
  "geometry": {"coordinates":[127.22271000000001,36.25082],"type":"Point"}
}