{
  "type": "Feature",
  "properties": {
    "gn:admin1_code":"14.0",
    "gn:asciiname":"P'yongp'an",
    "gn:country_code":"KR",
    "gn:dem":377,
    "gn:feature_class":"P",
    "gn:feature_code":"PPL",
    "gn:name":"P\u2019y\u014fngp\u2019an",
    "gn:population":0,
    "gn:timezone":"Asia/Seoul",
    "iso:country":"KR",
    "name:und_x_variant":[
        "\ud3c9\ud310",
        "P\u2019y\u014fngp\u2019an"
    ],
    "wof:name":"P'yongp'an",
    "wof:placetype":"locality"
},
  "geometry": {"coordinates":[129.1086,36.2542],"type":"Point"}
}