{
  "type": "Feature",
  "properties": {
    "gn:admin1_code":"13.0",
    "gn:asciiname":"Goyanggyo",
    "gn:country_code":"KR",
    "gn:dem":65,
    "gn:feature_class":"P",
    "gn:feature_code":"PPL",
    "gn:name":"Goyanggyo",
    "gn:population":0,
    "gn:timezone":"Asia/Seoul",
    "iso:country":"KR",
    "name:kor_x_preferred":[
        "\uace0\uc591\uad50"
    ],
    "wof:name":"Goyanggyo",
    "wof:placetype":"locality"
},
  "geometry": {"coordinates":[126.90375,37.70681],"type":"Point"}
}