{
  "type": "Feature",
  "properties": {
    "gn:admin1_code":"12.0",
    "gn:asciiname":"Meokjeol",
    "gn:country_code":"KR",
    "gn:dem":10,
    "gn:feature_class":"P",
    "gn:feature_code":"PPL",
    "gn:name":"Meokjeol",
    "gn:population":0,
    "gn:timezone":"Asia/Seoul",
    "iso:country":"KR",
    "name:und_x_variant":[
        "\uba39\uc808",
        "Meokjeol",
        "M\u014fkch\u014fl"
    ],
    "wof:name":"Meokjeol",
    "wof:placetype":"locality"
},
  "geometry": {"coordinates":[126.50912,37.73765],"type":"Point"}
}