{
  "type": "Feature",
  "properties": {
    "gn:admin1_code":"13.0",
    "gn:asciiname":"Solmoe",
    "gn:country_code":"KR",
    "gn:dem":8,
    "gn:feature_class":"P",
    "gn:feature_code":"PPL",
    "gn:name":"Solmoe",
    "gn:population":0,
    "gn:timezone":"Asia/Seoul",
    "iso:country":"KR",
    "name:kor_x_preferred":[
        "\uc194\ubafc"
    ],
    "wof:name":"Solmoe",
    "wof:placetype":"locality"
},
  "geometry": {"coordinates":[126.69972,37.21444],"type":"Point"}
}