{
  "type": "Feature",
  "properties": {
    "gn:admin1_code":"19.0",
    "gn:asciiname":"Biryong",
    "gn:country_code":"KR",
    "gn:dem":158,
    "gn:feature_class":"P",
    "gn:feature_code":"PPL",
    "gn:name":"Biryong",
    "gn:population":0,
    "gn:timezone":"Asia/Seoul",
    "iso:country":"KR",
    "name:und_x_variant":[
        "\ube44\ub8e1",
        "Piryong",
        "Biryong"
    ],
    "wof:name":"Biryong",
    "wof:placetype":"locality"
},
  "geometry": {"coordinates":[127.47195000000001,36.34889],"type":"Point"}
}