{
  "type": "Feature",
  "properties": {
    "gn:admin1_code":"16.0",
    "gn:asciiname":"Haewol",
    "gn:country_code":"KR",
    "gn:dem":34,
    "gn:feature_class":"P",
    "gn:feature_code":"PPL",
    "gn:name":"Haew\u014fl",
    "gn:population":0,
    "gn:timezone":"Asia/Seoul",
    "iso:country":"KR",
    "name:kor_x_preferred":[
        "\ud574\uc6d4"
    ],
    "name:kor_x_variant":[
        "Haew\u014fl"
    ],
    "wof:name":"Haewol",
    "wof:placetype":"locality"
},
  "geometry": {"coordinates":[126.67556,34.60444],"type":"Point"}
}