{
  "type": "Feature",
  "properties": {
    "gn:admin1_code":"13.0",
    "gn:asciiname":"Sagiso",
    "gn:country_code":"KR",
    "gn:dem":131,
    "gn:feature_class":"P",
    "gn:feature_code":"PPL",
    "gn:name":"Sagiso",
    "gn:population":0,
    "gn:timezone":"Asia/Seoul",
    "iso:country":"KR",
    "name:und_x_variant":[
        "\uc0ac\uae30\uc18c",
        "Sagiso"
    ],
    "wof:name":"Sagiso",
    "wof:placetype":"locality"
},
  "geometry": {"coordinates":[127.31999999999999,37.31028],"type":"Point"}
}