{
  "type": "Feature",
  "properties": {
    "gn:admin1_code":"17.0",
    "gn:asciiname":"Geoeunjeom",
    "gn:country_code":"KR",
    "gn:dem":69,
    "gn:feature_class":"P",
    "gn:feature_code":"PPL",
    "gn:name":"Geoeunjeom",
    "gn:population":0,
    "gn:timezone":"Asia/Seoul",
    "iso:country":"KR",
    "name:kor_x_preferred":[
        "\uac70\uc740\uc810"
    ],
    "name:und_x_variant":[
        "K\u014f\u016dnj\u014fm",
        "K\u014fmunj\u014fm",
        "\uac70\ubb38\uc810",
        "Geoeunjeom"
    ],
    "wof:name":"Geoeunjeom",
    "wof:placetype":"locality"
},
  "geometry": {"coordinates":[127.1884,36.3015],"type":"Point"}
}