{
  "type": "Feature",
  "properties": {
    "gn:admin1_code":"6.0",
    "gn:asciiname":"Takpak-kol",
    "gn:country_code":"KR",
    "gn:dem":204,
    "gn:feature_class":"P",
    "gn:feature_code":"PPL",
    "gn:name":"Takpak-kol",
    "gn:population":0,
    "gn:timezone":"Asia/Seoul",
    "iso:country":"KR",
    "name:kor_x_preferred":[
        "\ub2e5\ubc27\uace8"
    ],
    "wof:name":"Takpak-kol",
    "wof:placetype":"locality"
},
  "geometry": {"coordinates":[128.08420000000001,37.4878],"type":"Point"}
}