{
  "type": "Feature",
  "properties": {
    "gn:admin1_code":"17.0",
    "gn:asciiname":"Tambae-gol",
    "gn:country_code":"KR",
    "gn:dem":28,
    "gn:feature_class":"P",
    "gn:feature_code":"PPL",
    "gn:name":"Tambae-gol",
    "gn:population":0,
    "gn:timezone":"Asia/Seoul",
    "iso:country":"KR",
    "name:und_x_variant":[
        "\ub2f4\ubc30\uace8",
        "Tambae-gol"
    ],
    "wof:name":"Tambae-gol",
    "wof:placetype":"locality"
},
  "geometry": {"coordinates":[126.4196,36.6108],"type":"Point"}
}