{
  "type": "Feature",
  "properties": {
    "gn:admin1_code":"20.0",
    "gn:asciiname":"Somogok",
    "gn:country_code":"KR",
    "gn:dem":141,
    "gn:feature_class":"P",
    "gn:feature_code":"PPL",
    "gn:name":"Somogok",
    "gn:population":0,
    "gn:timezone":"Asia/Seoul",
    "iso:country":"KR",
    "name:und_x_variant":[
        "\uc18c\ubaa8\uace1",
        "Somogok"
    ],
    "wof:name":"Somogok",
    "wof:placetype":"locality"
},
  "geometry": {"coordinates":[128.45651999999998,35.20547],"type":"Point"}
}