{
  "type": "Feature",
  "properties": {
    "gn:admin1_code":"13.0",
    "gn:asciiname":"Seungjagol",
    "gn:country_code":"KR",
    "gn:dem":152,
    "gn:feature_class":"P",
    "gn:feature_code":"PPL",
    "gn:name":"Seungjagol",
    "gn:population":0,
    "gn:timezone":"Asia/Seoul",
    "iso:country":"KR",
    "name:kor_x_preferred":[
        "\uc548\uc11c\ub300"
    ],
    "name:kor_x_variant":[
        "Ans\u014fdae",
        "\uc2b9\uc790\uace8"
    ],
    "name:und_x_variant":[
        "Anseodae",
        "Seungjagol"
    ],
    "wof:name":"Seungjagol",
    "wof:placetype":"locality"
},
  "geometry": {"coordinates":[127.3814,37.776],"type":"Point"}
}