{
  "type": "Feature",
  "properties": {
    "gn:admin1_code":"5.0",
    "gn:asciiname":"Kkwongmal",
    "gn:country_code":"KR",
    "gn:dem":74,
    "gn:feature_class":"P",
    "gn:feature_code":"PPL",
    "gn:name":"Kkwongmal",
    "gn:population":0,
    "gn:timezone":"Asia/Seoul",
    "iso:country":"KR",
    "name:kor_x_preferred":[
        "\uafe9\ub9d0"
    ],
    "wof:name":"Kkwongmal",
    "wof:placetype":"locality"
},
  "geometry": {"coordinates":[127.51125999999999,36.93492],"type":"Point"}
}