{
  "type": "Feature",
  "properties": {
    "gn:admin1_code":"6.0",
    "gn:asciiname":"Soseonghwanggeori",
    "gn:country_code":"KR",
    "gn:dem":193,
    "gn:feature_class":"P",
    "gn:feature_code":"PPL",
    "gn:name":"Soseonghwanggeori",
    "gn:population":0,
    "gn:timezone":"Asia/Seoul",
    "iso:country":"KR",
    "name:kor_x_preferred":[
        "\uc18c\uc131\ud669\uac70\ub9ac"
    ],
    "name:kor_x_variant":[
        "Sos\u014fnghwangg\u014fri"
    ],
    "wof:name":"Soseonghwanggeori",
    "wof:placetype":"locality"
},
  "geometry": {"coordinates":[128.02071999999998,37.84078],"type":"Point"}
}