{
  "type": "Feature",
  "properties": {
    "gn:admin1_code":"13.0",
    "gn:asciiname":"Utga-maeul",
    "gn:country_code":"KR",
    "gn:dem":134,
    "gn:feature_class":"P",
    "gn:feature_code":"PPL",
    "gn:name":"Utga-maeul",
    "gn:population":0,
    "gn:timezone":"Asia/Seoul",
    "iso:country":"KR",
    "name:und_x_variant":[
        "\uc6c3\uac00\ub9c8\uc744",
        "Utga-maeul",
        "Ukka-ma\u016dl"
    ],
    "wof:name":"Utga-maeul",
    "wof:placetype":"locality"
},
  "geometry": {"coordinates":[127.39388999999998,37.35528],"type":"Point"}
}