{
  "type": "Feature",
  "properties": {
    "gn:admin1_code":"5.0",
    "gn:asciiname":"Solban-mal",
    "gn:country_code":"KR",
    "gn:dem":121,
    "gn:feature_class":"P",
    "gn:feature_code":"PPL",
    "gn:name":"Solban-mal",
    "gn:population":0,
    "gn:timezone":"Asia/Seoul",
    "iso:country":"KR",
    "name:und_x_variant":[
        "\uc194\ubc2d\ub9d0",
        "Solban-mal"
    ],
    "wof:name":"Solban-mal",
    "wof:placetype":"locality"
},
  "geometry": {"coordinates":[127.6356,36.287],"type":"Point"}
}