{
  "type": "Feature",
  "properties": {
    "gn:admin1_code":"14.0",
    "gn:asciiname":"Saebyeokgol",
    "gn:country_code":"KR",
    "gn:dem":160,
    "gn:feature_class":"P",
    "gn:feature_code":"PPL",
    "gn:name":"Saebyeokgol",
    "gn:population":0,
    "gn:timezone":"Asia/Seoul",
    "iso:country":"KR",
    "name:kor_x_preferred":[
        "\uc0c8\ubcbd\uace8"
    ],
    "wof:name":"Saebyeokgol",
    "wof:placetype":"locality"
},
  "geometry": {"coordinates":[128.43003999999999,36.66748],"type":"Point"}
}