{
  "type": "Feature",
  "properties": {
    "gn:admin1_code":"3.0",
    "gn:asciiname":"Chinso-ri",
    "gn:country_code":"KR",
    "gn:dem":5,
    "gn:feature_class":"P",
    "gn:feature_code":"PPL",
    "gn:name":"Chins\u014f-ri",
    "gn:population":0,
    "gn:timezone":"Asia/Seoul",
    "iso:country":"KR",
    "wof:name":"Chinso-ri",
    "wof:placetype":"locality"
},
  "geometry": {"coordinates":[126.61139,35.59305999999999],"type":"Point"}
}