{
  "type": "Feature",
  "properties": {
    "gn:admin1_code":"14.0",
    "gn:asciiname":"Ponggam",
    "gn:country_code":"KR",
    "gn:dem":195,
    "gn:feature_class":"P",
    "gn:feature_code":"PPL",
    "gn:name":"Ponggam",
    "gn:population":0,
    "gn:timezone":"Asia/Seoul",
    "iso:country":"KR",
    "name:und_x_variant":[
        "\ubd09\uac10",
        "Ponggam"
    ],
    "wof:name":"Ponggam",
    "wof:placetype":"locality"
},
  "geometry": {"coordinates":[129.07050000000001,36.5856],"type":"Point"}
}