{
  "type": "Feature",
  "properties": {
    "gn:admin1_code":"6.0",
    "gn:asciiname":"Hungjong-ni",
    "gn:country_code":"KR",
    "gn:dem":646,
    "gn:feature_class":"P",
    "gn:feature_code":"PPLL",
    "gn:name":"H\u016dngj\u014fng-ni",
    "gn:population":0,
    "gn:timezone":"Asia/Seoul",
    "iso:country":"KR",
    "name:kor_x_preferred":[
        "\ud765\uc815\ub9ac"
    ],
    "name:kor_x_variant":[
        "H\u016dngj\u014fng-ni"
    ],
    "name:und_x_variant":[
        "H\u016dngj\u014fng-dong"
    ],
    "wof:name":"Hungjong-ni",
    "wof:placetype":"locality"
},
  "geometry": {"coordinates":[128.33078,37.64555],"type":"Point"}
}