{
  "type": "Feature",
  "properties": {
    "gn:admin1_code":"6.0",
    "gn:asciiname":"Araetgalbeol",
    "gn:country_code":"KR",
    "gn:dem":6,
    "gn:feature_class":"P",
    "gn:feature_code":"PPL",
    "gn:name":"Araetgalbeol",
    "gn:population":0,
    "gn:timezone":"Asia/Seoul",
    "iso:country":"KR",
    "name:und_x_variant":[
        "Araetkalb\u014fl",
        "\uc544\ub7ab\uac08\ubc8c",
        "Araetgalbeol"
    ],
    "wof:name":"Araetgalbeol",
    "wof:placetype":"locality"
},
  "geometry": {"coordinates":[128.48706999999999,38.38959000000001],"type":"Point"}
}