{
  "type": "Feature",
  "properties": {
    "gn:admin1_code":"16.0",
    "gn:asciiname":"Mira",
    "gn:cc2":"KR",
    "gn:country_code":"KR",
    "gn:dem":22,
    "gn:feature_class":"P",
    "gn:feature_code":"PPL",
    "gn:name":"Mira",
    "gn:population":0,
    "gn:timezone":"Asia/Seoul",
    "iso:country":"KR",
    "name:kor_x_preferred":[
        "\ubbf8\ub77c"
    ],
    "name:und_x_variant":[
        "Bira-ri",
        "Mira-ri",
        "Mira"
    ],
    "wof:name":"Mira",
    "wof:placetype":"locality"
},
  "geometry": {"coordinates":[126.66694,34.14694],"type":"Point"}
}