{
  "type": "Feature",
  "properties": {
    "gn:admin1_code":"17.0",
    "gn:asciiname":"Ankkurongi",
    "gn:country_code":"KR",
    "gn:dem":14,
    "gn:feature_class":"P",
    "gn:feature_code":"PPL",
    "gn:name":"Ankkur\u014fngi",
    "gn:population":0,
    "gn:timezone":"Asia/Seoul",
    "iso:country":"KR",
    "name:und_x_variant":[
        "\uc548\uafb8\ub801\uc774",
        "Ankkur\u014fngi"
    ],
    "wof:name":"Ankkurongi",
    "wof:placetype":"locality"
},
  "geometry": {"coordinates":[126.2561,36.8703],"type":"Point"}
}