{
  "type": "Feature",
  "properties": {
    "gn:admin1_code":"16.0",
    "gn:asciiname":"Unjong",
    "gn:country_code":"KR",
    "gn:dem":12,
    "gn:feature_class":"P",
    "gn:feature_code":"PPL",
    "gn:name":"Unj\u014fng",
    "gn:population":0,
    "gn:timezone":"Asia/Seoul",
    "iso:country":"KR",
    "name:kor_x_preferred":[
        "\uc6b4\uc815"
    ],
    "name:kor_x_variant":[
        "Unj\u014fng"
    ],
    "name:und_x_variant":[
        "Unj\u014fng-ni"
    ],
    "wof:name":"Unjong",
    "wof:placetype":"locality"
},
  "geometry": {"coordinates":[126.97417,34.64889],"type":"Point"}
}