{
  "type": "Feature",
  "properties": {
    "gn:admin1_code":"20.0",
    "gn:asciiname":"Myonggong-ni",
    "gn:cc2":"KR",
    "gn:country_code":"KR",
    "gn:dem":128,
    "gn:feature_class":"P",
    "gn:feature_code":"PPL",
    "gn:name":"My\u014fnggong-ni",
    "gn:population":0,
    "gn:timezone":"Asia/Seoul",
    "iso:country":"KR",
    "name:und_x_variant":[
        "My\u014fnggok-ri",
        "My\u014fnggong-ni"
    ],
    "wof:name":"Myonggong-ni",
    "wof:placetype":"locality"
},
  "geometry": {"coordinates":[129.16806,35.39306],"type":"Point"}
}