{
  "type": "Feature",
  "properties": {
    "gn:admin1_code":"17.0",
    "gn:asciiname":"Unjok",
    "gn:cc2":"KR",
    "gn:country_code":"KR",
    "gn:dem":112,
    "gn:feature_class":"P",
    "gn:feature_code":"PPL",
    "gn:name":"\u016cnj\u014fk",
    "gn:population":0,
    "gn:timezone":"Asia/Seoul",
    "iso:country":"KR",
    "name:und_x_variant":[
        "\u016cnj\u014fng-ni",
        "\u016cnj\u014fk"
    ],
    "wof:name":"Unjok",
    "wof:placetype":"locality"
},
  "geometry": {"coordinates":[126.76667,36.18333],"type":"Point"}
}