{
  "type": "Feature",
  "properties": {
    "gn:admin1_code":"12.0",
    "gn:asciiname":"Tokku-ri",
    "gn:country_code":"KR",
    "gn:dem":19,
    "gn:feature_class":"P",
    "gn:feature_code":"PPL",
    "gn:name":"Tokku-ri",
    "gn:population":0,
    "gn:timezone":"Asia/Seoul",
    "iso:country":"KR",
    "name:kor_x_preferred":[
        "\ub3c5\uad6c\ub9ac"
    ],
    "wof:name":"Tokku-ri",
    "wof:placetype":"locality"
},
  "geometry": {"coordinates":[126.685,37.64833],"type":"Point"}
}