{
  "type": "Feature",
  "properties": {
    "gn:admin1_code":"15.0",
    "gn:asciiname":"Jungmoe",
    "gn:country_code":"KR",
    "gn:dem":231,
    "gn:feature_class":"P",
    "gn:feature_code":"PPL",
    "gn:name":"Jungmoe",
    "gn:population":0,
    "gn:timezone":"Asia/Seoul",
    "iso:country":"KR",
    "name:und_x_variant":[
        "\uc911\ubafc",
        "Chungmoe",
        "Jungmoe"
    ],
    "wof:name":"Jungmoe",
    "wof:placetype":"locality"
},
  "geometry": {"coordinates":[128.49594999999999,35.70333],"type":"Point"}
}