{
  "type": "Feature",
  "properties": {
    "gn:admin1_code":"13.0",
    "gn:asciiname":"Neuk-mal",
    "gn:country_code":"KR",
    "gn:dem":85,
    "gn:feature_class":"P",
    "gn:feature_code":"PPL",
    "gn:name":"Neuk-mal",
    "gn:population":0,
    "gn:timezone":"Asia/Seoul",
    "iso:country":"KR",
    "name:und_x_variant":[
        "\ub291\ub9d0",
        "Neuk-mal",
        "N\u016dng-mal"
    ],
    "wof:name":"Neuk-mal",
    "wof:placetype":"locality"
},
  "geometry": {"coordinates":[127.12528,37.19278],"type":"Point"}
}