{
  "type": "Feature",
  "properties": {
    "gn:admin1_code":"6.0",
    "gn:asciiname":"Jogateo",
    "gn:country_code":"KR",
    "gn:dem":186,
    "gn:feature_class":"P",
    "gn:feature_code":"PPL",
    "gn:name":"Jogateo",
    "gn:population":0,
    "gn:timezone":"Asia/Seoul",
    "iso:country":"KR",
    "name:kor_x_preferred":[
        "\uc870\uac00\ud130"
    ],
    "name:kor_x_variant":[
        "Chogat\u2019\u014f"
    ],
    "wof:name":"Jogateo",
    "wof:placetype":"locality"
},
  "geometry": {"coordinates":[127.95865000000001,37.73672],"type":"Point"}
}