{
  "type": "Feature",
  "properties": {
    "gn:admin1_code":"14.0",
    "gn:asciiname":"Komgu",
    "gn:country_code":"KR",
    "gn:dem":26,
    "gn:feature_class":"P",
    "gn:feature_code":"PPL",
    "gn:name":"K\u014fmgu",
    "gn:population":0,
    "gn:timezone":"Asia/Seoul",
    "iso:country":"KR",
    "name:und_x_variant":[
        "\uac80\uad6c",
        "K\u014fmgu"
    ],
    "wof:name":"Komgu",
    "wof:placetype":"locality"
},
  "geometry": {"coordinates":[129.45099999999999,36.712],"type":"Point"}
}