{
  "type": "Feature",
  "properties": {
    "gn:admin1_code":"6.0",
    "gn:asciiname":"Golmal",
    "gn:country_code":"KR",
    "gn:dem":63,
    "gn:feature_class":"P",
    "gn:feature_code":"PPL",
    "gn:name":"Golmal",
    "gn:population":0,
    "gn:timezone":"Asia/Seoul",
    "iso:country":"KR",
    "name:kor_x_preferred":[
        "\uace8\ub9d0"
    ],
    "name:und_x_variant":[
        "Kol-mal"
    ],
    "wof:name":"Golmal",
    "wof:placetype":"locality"
},
  "geometry": {"coordinates":[127.75783,37.20676],"type":"Point"}
}