{
  "type": "Feature",
  "properties": {
    "gn:admin1_code":"20.0",
    "gn:asciiname":"Yangjimaeul",
    "gn:country_code":"KR",
    "gn:dem":117,
    "gn:feature_class":"P",
    "gn:feature_code":"PPL",
    "gn:name":"Yangjimaeul",
    "gn:population":0,
    "gn:timezone":"Asia/Seoul",
    "iso:country":"KR",
    "name:und_x_variant":[
        "\uc591\uc9c0\ub9c8\uc744",
        "Yangji-ma\u016dl",
        "Yangjimaeul"
    ],
    "wof:name":"Yangjimaeul",
    "wof:placetype":"locality"
},
  "geometry": {"coordinates":[128.52521999999999,35.60136],"type":"Point"}
}