{
  "type": "Feature",
  "properties": {
    "gn:admin1_code":"14.0",
    "gn:asciiname":"Eonjeonggol",
    "gn:country_code":"KR",
    "gn:dem":83,
    "gn:feature_class":"P",
    "gn:feature_code":"PPL",
    "gn:name":"Eonjeonggol",
    "gn:population":0,
    "gn:timezone":"Asia/Seoul",
    "iso:country":"KR",
    "name:kor_x_preferred":[
        "\uc5b8\uc815\uace8"
    ],
    "wof:name":"Eonjeonggol",
    "wof:placetype":"locality"
},
  "geometry": {"coordinates":[129.40308999999999,35.91536],"type":"Point"}
}