{
  "type": "Feature",
  "properties": {
    "gn:admin1_code":"10.0",
    "gn:asciiname":"Hari",
    "gn:country_code":"KR",
    "gn:dem":4,
    "gn:feature_class":"P",
    "gn:feature_code":"PPL",
    "gn:name":"Hari",
    "gn:population":0,
    "gn:timezone":"Asia/Seoul",
    "iso:country":"KR",
    "name:deu_x_preferred":[
        "Hari"
    ],
    "name:ita_x_preferred":[
        "Hari"
    ],
    "name:kan_x_preferred":[
        "\u0cb9\u0cb0\u0cbf"
    ],
    "name:kaz_x_preferred":[
        "\u0425\u0430\u0440\u0438"
    ],
    "name:kor_x_preferred":[
        "\ud558\ub9ac"
    ],
    "name:pol_x_preferred":[
        "Hari"
    ],
    "name:por_x_preferred":[
        "Hari"
    ],
    "name:rus_x_preferred":[
        "\u0425\u0430\u0440\u0438"
    ],
    "name:tam_x_preferred":[
        "\u0bb9\u0bb0\u0bbf"
    ],
    "name:tel_x_preferred":[
        "\u0c39\u0c30\u0c3f"
    ],
    "name:ukr_x_preferred":[
        "\u0425\u0430\u0440\u0456"
    ],
    "wof:name":"Hari",
    "wof:placetype":"locality"
},
  "geometry": {"coordinates":[128.952,35.21507000000001],"type":"Point"}
}