{
  "type": "Feature",
  "properties": {
    "gn:admin1_code":"13.0",
    "gn:asciiname":"Yeoribiteo",
    "gn:country_code":"KR",
    "gn:dem":633,
    "gn:feature_class":"P",
    "gn:feature_code":"PPL",
    "gn:name":"Yeoribiteo",
    "gn:population":0,
    "gn:timezone":"Asia/Seoul",
    "iso:country":"KR",
    "name:kor_x_preferred":[
        "\uc5ec\ub9ac\ube44\ud130"
    ],
    "name:kor_x_variant":[
        "Y\u014fribit\u2019\u014f"
    ],
    "wof:name":"Yeoribiteo",
    "wof:placetype":"locality"
},
  "geometry": {"coordinates":[127.44076,37.88497],"type":"Point"}
}