{
  "type": "Feature",
  "properties": {
    "gn:admin1_code":"6.0",
    "gn:asciiname":"Ssaribak-kol",
    "gn:country_code":"KR",
    "gn:dem":826,
    "gn:feature_class":"P",
    "gn:feature_code":"PPL",
    "gn:name":"Ssaribak-kol",
    "gn:population":0,
    "gn:timezone":"Asia/Seoul",
    "iso:country":"KR",
    "name:kor_x_preferred":[
        "\uc2f8\ub9ac\ubc2d\uace8"
    ],
    "wof:name":"Ssaribak-kol",
    "wof:placetype":"locality"
},
  "geometry": {"coordinates":[128.947,37.2013],"type":"Point"}
}