{
  "type": "Feature",
  "properties": {
    "gn:admin1_code":"6.0",
    "gn:asciiname":"Chongja-gol",
    "gn:country_code":"KR",
    "gn:dem":564,
    "gn:feature_class":"P",
    "gn:feature_code":"PPL",
    "gn:name":"Ch\u014fngja-gol",
    "gn:population":0,
    "gn:timezone":"Asia/Seoul",
    "iso:country":"KR",
    "name:kor_x_preferred":[
        "\uc815\uc790\uace8"
    ],
    "name:kor_x_variant":[
        "Ch\u014fngja-gol"
    ],
    "wof:name":"Chongja-gol",
    "wof:placetype":"locality"
},
  "geometry": {"coordinates":[128.21029999999999,37.4066],"type":"Point"}
}