{
  "type": "Feature",
  "properties": {
    "gn:admin1_code":"17.0",
    "gn:asciiname":"Norumogi",
    "gn:country_code":"KR",
    "gn:dem":47,
    "gn:feature_class":"P",
    "gn:feature_code":"PPL",
    "gn:name":"Norumogi",
    "gn:population":0,
    "gn:timezone":"Asia/Seoul",
    "iso:country":"KR",
    "name:und_x_variant":[
        "\ub178\ub8e8\ubaa9\uc774",
        "Norumogi"
    ],
    "wof:name":"Norumogi",
    "wof:placetype":"locality"
},
  "geometry": {"coordinates":[126.85680000000001,36.6033],"type":"Point"}
}