{
  "type": "Feature",
  "properties": {
    "gn:admin1_code":"13.0",
    "gn:asciiname":"Namchon-dong",
    "gn:country_code":"KR",
    "gn:dem":23,
    "gn:feature_class":"P",
    "gn:feature_code":"PPL",
    "gn:name":"Namchon-dong",
    "gn:population":0,
    "gn:timezone":"Asia/Seoul",
    "iso:country":"KR",
    "name:und_x_variant":[
        "\ub0a8\ucd0c\ub3d9",
        "Namchon-dong",
        "Namch\u2019on-dong"
    ],
    "wof:name":"Namchon-dong",
    "wof:placetype":"locality"
},
  "geometry": {"coordinates":[127.05833,37.15083],"type":"Point"}
}