{
  "type": "Feature",
  "properties": {
    "gn:admin1_code":"17.0",
    "gn:asciiname":"Kwanp'o-ri",
    "gn:country_code":"KR",
    "gn:dem":82,
    "gn:feature_class":"P",
    "gn:feature_code":"PPL",
    "gn:name":"Kwanp\u2019o-ri",
    "gn:population":0,
    "gn:timezone":"Asia/Seoul",
    "iso:country":"KR",
    "wof:name":"Kwanp'o-ri",
    "wof:placetype":"locality"
},
  "geometry": {"coordinates":[126.78333000000001,36.16667],"type":"Point"}
}