{
  "type": "Feature",
  "properties": {
    "gn:admin1_code":"17.0",
    "gn:asciiname":"Chongmo-ri",
    "gn:country_code":"KR",
    "gn:dem":67,
    "gn:feature_class":"P",
    "gn:feature_code":"PPL",
    "gn:name":"Ch\u014fngm\u014f-ri",
    "gn:population":0,
    "gn:timezone":"Asia/Seoul",
    "iso:country":"KR",
    "name:und_x_variant":[
        "\uc815\uba38\ub9ac",
        "Ch\u014fngm\u014f-ri"
    ],
    "wof:name":"Chongmo-ri",
    "wof:placetype":"locality"
},
  "geometry": {"coordinates":[126.72799999999999,36.4716],"type":"Point"}
}