{
  "type": "Feature",
  "properties": {
    "gn:admin1_code":"17.0",
    "gn:asciiname":"Hant'oul",
    "gn:country_code":"KR",
    "gn:dem":30,
    "gn:feature_class":"P",
    "gn:feature_code":"PPL",
    "gn:name":"Hant\u2019\u014ful",
    "gn:population":0,
    "gn:timezone":"Asia/Seoul",
    "iso:country":"KR",
    "name:und_x_variant":[
        "\ud55c\ud130\uc6b8",
        "Hant\u2019\u014ful"
    ],
    "wof:name":"Hant'oul",
    "wof:placetype":"locality"
},
  "geometry": {"coordinates":[126.45189999999999,36.9009],"type":"Point"}
}