{
  "type": "Feature",
  "properties": {
    "gn:admin1_code":"12.0",
    "gn:asciiname":"Sanhwa",
    "gn:country_code":"KR",
    "gn:dem":37,
    "gn:feature_class":"P",
    "gn:feature_code":"PPL",
    "gn:name":"Sanhwa",
    "gn:population":0,
    "gn:timezone":"Asia/Seoul",
    "iso:country":"KR",
    "name:kor_x_preferred":[
        "\uc0b0\ud654"
    ],
    "wof:name":"Sanhwa",
    "wof:placetype":"locality"
},
  "geometry": {"coordinates":[126.39675,37.74935],"type":"Point"}
}