{
  "type": "Feature",
  "properties": {
    "gn:admin1_code":"14.0",
    "gn:asciiname":"Keunbamsil",
    "gn:country_code":"KR",
    "gn:dem":188,
    "gn:feature_class":"P",
    "gn:feature_code":"PPL",
    "gn:name":"Keunbamsil",
    "gn:population":0,
    "gn:timezone":"Asia/Seoul",
    "iso:country":"KR",
    "name:kor_x_preferred":[
        "\ud070\ubc24\uc2e4"
    ],
    "wof:name":"Keunbamsil",
    "wof:placetype":"locality"
},
  "geometry": {"coordinates":[128.42959999999999,36.72322],"type":"Point"}
}