{
  "type": "Feature",
  "properties": {
    "gn:admin1_code":"16.0",
    "gn:asciiname":"Yutangchon",
    "gn:country_code":"KR",
    "gn:dem":108,
    "gn:feature_class":"P",
    "gn:feature_code":"PPL",
    "gn:name":"Yutangchon",
    "gn:population":0,
    "gn:timezone":"Asia/Seoul",
    "iso:country":"KR",
    "name:kor_x_preferred":[
        "\uc720\ud0d5\ucd0c"
    ],
    "name:und_x_variant":[
        "Yut\u2019ang-ni",
        "Yut\u2019ang",
        "Yutangchon"
    ],
    "wof:name":"Yutangchon",
    "wof:placetype":"locality"
},
  "geometry": {"coordinates":[126.81793999999999,35.31564],"type":"Point"}
}