{
  "type": "Feature",
  "properties": {
    "gn:admin1_code":"14.0",
    "gn:asciiname":"Saraesil",
    "gn:country_code":"KR",
    "gn:dem":285,
    "gn:feature_class":"P",
    "gn:feature_code":"PPL",
    "gn:name":"Saraesil",
    "gn:population":0,
    "gn:timezone":"Asia/Seoul",
    "iso:country":"KR",
    "name:kor_x_preferred":[
        "\uc0ac\ub798\uc2e4"
    ],
    "wof:name":"Saraesil",
    "wof:placetype":"locality"
},
  "geometry": {"coordinates":[128.95296999999999,36.71923],"type":"Point"}
}