{
  "type": "Feature",
  "properties": {
    "gn:admin1_code":"6.0",
    "gn:asciiname":"Omija-gol",
    "gn:country_code":"KR",
    "gn:dem":796,
    "gn:feature_class":"P",
    "gn:feature_code":"PPL",
    "gn:name":"Omija-gol",
    "gn:population":0,
    "gn:timezone":"Asia/Seoul",
    "iso:country":"KR",
    "name:kor_x_preferred":[
        "\uc624\ubbf8\uc790\uace8"
    ],
    "wof:name":"Omija-gol",
    "wof:placetype":"locality"
},
  "geometry": {"coordinates":[128.15549999999999,37.9024],"type":"Point"}
}