{
  "type": "Feature",
  "properties": {
    "gn:admin1_code":"3.0",
    "gn:asciiname":"Toch'ol-li",
    "gn:country_code":"KR",
    "gn:dem":487,
    "gn:feature_class":"P",
    "gn:feature_code":"PPL",
    "gn:name":"Toch\u2019\u014fl-li",
    "gn:population":0,
    "gn:timezone":"Asia/Seoul",
    "iso:country":"KR",
    "name:und_x_variant":[
        "\ub3c4\ucc9c\ub9ac",
        "Toch\u2019\u014fl-li"
    ],
    "wof:name":"Toch'ol-li",
    "wof:placetype":"locality"
},
  "geometry": {"coordinates":[127.68847,35.8845],"type":"Point"}
}