{
  "type": "Feature",
  "properties": {
    "gn:admin1_code":"14.0",
    "gn:asciiname":"Up-tong",
    "gn:country_code":"KR",
    "gn:dem":166,
    "gn:feature_class":"P",
    "gn:feature_code":"PPL",
    "gn:name":"\u016cp-tong",
    "gn:population":0,
    "gn:timezone":"Asia/Seoul",
    "iso:country":"KR",
    "name:und_x_variant":[
        "\uc74d\ub3d9",
        "\u016cp-tong"
    ],
    "wof:name":"Up-tong",
    "wof:placetype":"locality"
},
  "geometry": {"coordinates":[129.04179999999999,36.5376],"type":"Point"}
}