{
  "type": "Feature",
  "properties": {
    "gn:admin1_code":"13.0",
    "gn:asciiname":"Eumdal-mal",
    "gn:country_code":"KR",
    "gn:dem":202,
    "gn:feature_class":"P",
    "gn:feature_code":"PPL",
    "gn:name":"Eumdal-mal",
    "gn:population":0,
    "gn:timezone":"Asia/Seoul",
    "iso:country":"KR",
    "name:und_x_variant":[
        "\uc74c\ub2ec\ub9d0",
        "Eumdal-mal",
        "\u016cmdal-mal"
    ],
    "wof:name":"Eumdal-mal",
    "wof:placetype":"locality"
},
  "geometry": {"coordinates":[127.71778,37.39028],"type":"Point"}
}