{
  "type": "Feature",
  "properties": {
    "gn:admin1_code":"6.0",
    "gn:asciiname":"Kalmagong-ni",
    "gn:country_code":"KR",
    "gn:dem":195,
    "gn:feature_class":"P",
    "gn:feature_code":"PPLL",
    "gn:name":"Kalmagong-ni",
    "gn:population":0,
    "gn:timezone":"Asia/Seoul",
    "iso:country":"KR",
    "name:kor_x_preferred":[
        "\uac08\ub9c8\uace1\ub9ac"
    ],
    "wof:name":"Kalmagong-ni",
    "wof:placetype":"locality"
},
  "geometry": {"coordinates":[127.90576,37.68923],"type":"Point"}
}