{
  "type": "Feature",
  "properties": {
    "gn:admin1_code":"3.0",
    "gn:asciiname":"Sanjong",
    "gn:country_code":"KR",
    "gn:dem":36,
    "gn:feature_class":"P",
    "gn:feature_code":"PPL",
    "gn:name":"Sanj\u014fng",
    "gn:population":0,
    "gn:timezone":"Asia/Seoul",
    "iso:country":"KR",
    "name:und_x_variant":[
        "\uc0b0\uc815",
        "Sanj\u014fng"
    ],
    "wof:name":"Sanjong",
    "wof:placetype":"locality"
},
  "geometry": {"coordinates":[127.11926,35.78967],"type":"Point"}
}