{
  "type": "Feature",
  "properties": {
    "gn:admin1_code":"14.0",
    "gn:asciiname":"Samjahyon",
    "gn:country_code":"KR",
    "gn:dem":529,
    "gn:feature_class":"P",
    "gn:feature_code":"PPL",
    "gn:name":"Samjahy\u014fn",
    "gn:population":0,
    "gn:timezone":"Asia/Seoul",
    "iso:country":"KR",
    "name:und_x_variant":[
        "\uc0bc\uc790\ud604",
        "Samjahy\u014fn"
    ],
    "wof:name":"Samjahyon",
    "wof:placetype":"locality"
},
  "geometry": {"coordinates":[129.04490000000001,36.3157],"type":"Point"}
}