{
  "type": "Feature",
  "properties": {
    "gn:admin1_code":"15.0",
    "gn:asciiname":"Bangmusan",
    "gn:country_code":"KR",
    "gn:dem":53,
    "gn:feature_class":"P",
    "gn:feature_code":"PPL",
    "gn:name":"Bangmusan",
    "gn:population":0,
    "gn:timezone":"Asia/Seoul",
    "iso:country":"KR",
    "name:kor_x_preferred":[
        "\ubc29\ubb34\uc0b0"
    ],
    "wof:name":"Bangmusan",
    "wof:placetype":"locality"
},
  "geometry": {"coordinates":[128.66783000000001,35.84602],"type":"Point"}
}