{
  "type": "Feature",
  "properties": {
    "gn:admin1_code":"20.0",
    "gn:asciiname":"Sinmyeong",
    "gn:country_code":"KR",
    "gn:dem":118,
    "gn:feature_class":"P",
    "gn:feature_code":"PPL",
    "gn:name":"Sinmyeong",
    "gn:population":0,
    "gn:timezone":"Asia/Seoul",
    "iso:country":"KR",
    "name:kor_x_preferred":[
        "\uc2e0\uba85"
    ],
    "wof:name":"Sinmyeong",
    "wof:placetype":"locality"
},
  "geometry": {"coordinates":[129.26300000000001,35.38443],"type":"Point"}
}