{
  "type": "Feature",
  "properties": {
    "gn:admin1_code":"3.0",
    "gn:asciiname":"Yon-dong",
    "gn:country_code":"KR",
    "gn:dem":28,
    "gn:feature_class":"P",
    "gn:feature_code":"PPL",
    "gn:name":"Y\u014fn-dong",
    "gn:population":0,
    "gn:timezone":"Asia/Seoul",
    "iso:country":"KR",
    "name:und_x_variant":[
        "\uc5f0\ub3d9",
        "Y\u014fn-dong"
    ],
    "wof:name":"Yon-dong",
    "wof:placetype":"locality"
},
  "geometry": {"coordinates":[127.0145,35.78955999999999],"type":"Point"}
}