{
  "type": "Feature",
  "properties": {
    "gn:admin1_code":"16.0",
    "gn:asciiname":"Kwayong-ni",
    "gn:country_code":"KR",
    "gn:dem":12,
    "gn:feature_class":"P",
    "gn:feature_code":"PPL",
    "gn:name":"Kway\u014fng-ni",
    "gn:population":0,
    "gn:timezone":"Asia/Seoul",
    "iso:country":"KR",
    "name:kor_x_preferred":[
        "\uacfc\uc5ed\ub9ac"
    ],
    "name:kor_x_variant":[
        "Kway\u014fng-ni"
    ],
    "name:und_x_variant":[
        "W\u014fnd\u016dng-ni"
    ],
    "wof:name":"Kwayong-ni",
    "wof:placetype":"locality"
},
  "geometry": {"coordinates":[127.36185999999999,34.67975999999999],"type":"Point"}
}