{
  "type": "Feature",
  "properties": {
    "gn:admin1_code":"6.0",
    "gn:asciiname":"Chung-gol",
    "gn:country_code":"KR",
    "gn:dem":119,
    "gn:feature_class":"P",
    "gn:feature_code":"PPL",
    "gn:name":"Ch\u016dng-gol",
    "gn:population":0,
    "gn:timezone":"Asia/Seoul",
    "iso:country":"KR",
    "name:kor_x_preferred":[
        "\uc99d\uace8"
    ],
    "name:kor_x_variant":[
        "Ch\u016dng-gol"
    ],
    "wof:name":"Chung-gol",
    "wof:placetype":"locality"
},
  "geometry": {"coordinates":[127.9328,37.4428],"type":"Point"}
}