{
  "type": "Feature",
  "properties": {
    "gn:admin1_code":"14.0",
    "gn:asciiname":"Cheoksi",
    "gn:country_code":"KR",
    "gn:dem":20,
    "gn:feature_class":"P",
    "gn:feature_code":"PPL",
    "gn:name":"Cheoksi",
    "gn:population":0,
    "gn:timezone":"Asia/Seoul",
    "iso:country":"KR",
    "name:kor_x_preferred":[
        "\ucc99\uc2dc"
    ],
    "wof:name":"Cheoksi",
    "wof:placetype":"locality"
},
  "geometry": {"coordinates":[129.51106999999999,35.81724000000001],"type":"Point"}
}