{
  "type": "Feature",
  "properties": {
    "gn:admin1_code":"15.0",
    "gn:asciiname":"Dongsanmaeul",
    "gn:country_code":"KR",
    "gn:dem":350,
    "gn:feature_class":"P",
    "gn:feature_code":"PPL",
    "gn:name":"Dongsanmaeul",
    "gn:population":0,
    "gn:timezone":"Asia/Seoul",
    "iso:country":"KR",
    "name:kor_x_preferred":[
        "\ub3d9\uc0b0\ub9c8\uc744"
    ],
    "wof:name":"Dongsanmaeul",
    "wof:placetype":"locality"
},
  "geometry": {"coordinates":[128.67479,35.98628],"type":"Point"}
}