{
  "type": "Feature",
  "properties": {
    "gn:admin1_code":"13.0",
    "gn:asciiname":"Masan",
    "gn:country_code":"KR",
    "gn:dem":41,
    "gn:feature_class":"P",
    "gn:feature_code":"PPL",
    "gn:name":"Masan",
    "gn:population":0,
    "gn:timezone":"Asia/Seoul",
    "iso:country":"KR",
    "name:kor_x_preferred":[
        "\ub9c8\uc0b0"
    ],
    "name:und_x_variant":[
        "\ub9c8\uc0b0",
        "Masan"
    ],
    "wof:name":"Masan",
    "wof:placetype":"locality"
},
  "geometry": {"coordinates":[127.1986,37.6118],"type":"Point"}
}