{
  "type": "Feature",
  "properties": {
    "gn:admin1_code":"13.0",
    "gn:asciiname":"Masan",
    "gn:country_code":"KR",
    "gn:dem":41,
    "gn:feature_class":"P",
    "gn:feature_code":"PPL",
    "gn:name":"Masan",
    "gn:population":0,
    "gn:timezone":"Asia/Seoul",
    "iso:country":"KR",
    "name:deu_x_preferred":[
        "Masan"
    ],
    "name:fas_x_preferred":[
        "\u0645\u0627\u0633\u0627\u0646"
    ],
    "name:fra_x_preferred":[
        "Masan"
    ],
    "name:ita_x_preferred":[
        "Masan"
    ],
    "name:jpn_x_preferred":[
        "\u99ac\u5c71\u5e02"
    ],
    "name:kor_x_preferred":[
        "\ub9c8\uc0b0"
    ],
    "name:kor_x_variant":[
        "\ub9c8\uc0b0\uc2dc"
    ],
    "name:lav_x_preferred":[
        "Masana"
    ],
    "name:lfn_x_preferred":[
        "Masan"
    ],
    "name:nno_x_preferred":[
        "Masan"
    ],
    "name:nor_x_preferred":[
        "Masan"
    ],
    "name:pol_x_preferred":[
        "Masan"
    ],
    "name:por_x_preferred":[
        "Masan"
    ],
    "name:rus_x_preferred":[
        "\u041c\u0430\u0441\u0430\u043d"
    ],
    "name:spa_x_preferred":[
        "Masan"
    ],
    "name:swe_x_preferred":[
        "Masan"
    ],
    "name:tgl_x_preferred":[
        "Masan"
    ],
    "name:und_x_variant":[
        "\ub9c8\uc0b0",
        "Masan"
    ],
    "name:uzb_x_preferred":[
        "Masan"
    ],
    "name:vie_x_preferred":[
        "Masan"
    ],
    "name:war_x_preferred":[
        "Masan"
    ],
    "name:zho_x_preferred":[
        "\u9a6c\u5c71\u5e02"
    ],
    "wof:name":"Masan",
    "wof:placetype":"locality"
},
  "geometry": {"coordinates":[127.1986,37.6118],"type":"Point"}
}