{
  "type": "Feature",
  "properties": {
    "gn:admin1_code":"14.0",
    "gn:asciiname":"Komurae",
    "gn:country_code":"KR",
    "gn:dem":45,
    "gn:feature_class":"P",
    "gn:feature_code":"PPL",
    "gn:name":"K\u014fmurae",
    "gn:population":0,
    "gn:timezone":"Asia/Seoul",
    "iso:country":"KR",
    "name:und_x_variant":[
        "\uac70\ubb34\ub798",
        "K\u014fmurae"
    ],
    "wof:name":"Komurae",
    "wof:placetype":"locality"
},
  "geometry": {"coordinates":[128.33709999999999,36.2384],"type":"Point"}
}