{
  "type": "Feature",
  "properties": {
    "gn:admin1_code":"17.0",
    "gn:asciiname":"Mo-ri",
    "gn:country_code":"KR",
    "gn:dem":21,
    "gn:feature_class":"P",
    "gn:feature_code":"PPL",
    "gn:name":"Mo-ri",
    "gn:population":0,
    "gn:timezone":"Asia/Seoul",
    "iso:country":"KR",
    "name:und_x_variant":[
        "\ubaa8\ub9ac",
        "Mo-ri"
    ],
    "wof:name":"Mo-ri",
    "wof:placetype":"locality"
},
  "geometry": {"coordinates":[126.86306999999999,36.29784],"type":"Point"}
}