{
  "type": "Feature",
  "properties": {
    "gn:admin1_code":"15.0",
    "gn:asciiname":"Joya",
    "gn:country_code":"KR",
    "gn:dem":32,
    "gn:feature_class":"P",
    "gn:feature_code":"PPL",
    "gn:name":"Joya",
    "gn:population":0,
    "gn:timezone":"Asia/Seoul",
    "iso:country":"KR",
    "name:kor_x_preferred":[
        "\uc870\uc57c"
    ],
    "name:und_x_variant":[
        "Choya"
    ],
    "wof:name":"Joya",
    "wof:placetype":"locality"
},
  "geometry": {"coordinates":[128.57657,35.91274],"type":"Point"}
}