{
  "type": "Feature",
  "properties": {
    "gn:admin1_code":"20.0",
    "gn:asciiname":"Naech'omak",
    "gn:country_code":"KR",
    "gn:dem":909,
    "gn:feature_class":"P",
    "gn:feature_code":"PPL",
    "gn:name":"Naech\u2019omak",
    "gn:population":0,
    "gn:timezone":"Asia/Seoul",
    "iso:country":"KR",
    "name:und_x_variant":[
        "\ub0b4\ucd08\ub9c9",
        "Naech\u2019omak"
    ],
    "wof:name":"Naech'omak",
    "wof:placetype":"locality"
},
  "geometry": {"coordinates":[128.04085000000001,35.78923],"type":"Point"}
}