{
  "type": "Feature",
  "properties": {
    "gn:admin1_code":"16.0",
    "gn:asciiname":"Kangjong",
    "gn:cc2":"KR",
    "gn:country_code":"KR",
    "gn:dem":36,
    "gn:feature_class":"P",
    "gn:feature_code":"PPL",
    "gn:name":"Kangj\u014fng",
    "gn:population":0,
    "gn:timezone":"Asia/Seoul",
    "iso:country":"KR",
    "name:und_x_variant":[
        "Kangj\u014fng-ni",
        "Kangj\u014fng"
    ],
    "wof:name":"Kangjong",
    "wof:placetype":"locality"
},
  "geometry": {"coordinates":[126.40000000000001,34.93333],"type":"Point"}
}