{
  "type": "Feature",
  "properties": {
    "gn:admin1_code":"13.0",
    "gn:asciiname":"Geumwoligu",
    "gn:country_code":"KR",
    "gn:dem":14,
    "gn:feature_class":"P",
    "gn:feature_code":"PPL",
    "gn:name":"Geumwoligu",
    "gn:population":0,
    "gn:timezone":"Asia/Seoul",
    "iso:country":"KR",
    "name:kor_x_preferred":[
        "\uae08\uc6d4 2\uad6c"
    ],
    "name:kor_x_variant":[
        "K\u016dmw\u014fli-gu"
    ],
    "wof:name":"Geumwoligu",
    "wof:placetype":"locality"
},
  "geometry": {"coordinates":[126.61418,37.74719],"type":"Point"}
}