{
  "type": "Feature",
  "properties": {
    "gn:admin1_code":"14.0",
    "gn:asciiname":"Taebang-ni",
    "gn:country_code":"KR",
    "gn:dem":85,
    "gn:feature_class":"P",
    "gn:feature_code":"PPL",
    "gn:name":"Taebang-ni",
    "gn:population":0,
    "gn:timezone":"Asia/Seoul",
    "iso:country":"KR",
    "name:und_x_variant":[
        "\ub300\ubc29\ub9ac",
        "Taebang-ni"
    ],
    "wof:name":"Taebang-ni",
    "wof:placetype":"locality"
},
  "geometry": {"coordinates":[128.13759999999999,36.0861],"type":"Point"}
}