{
  "type": "Feature",
  "properties": {
    "gn:admin1_code":"14.0",
    "gn:asciiname":"Tundogi",
    "gn:country_code":"KR",
    "gn:dem":152,
    "gn:feature_class":"P",
    "gn:feature_code":"PPL",
    "gn:name":"Tund\u014fgi",
    "gn:population":0,
    "gn:timezone":"Asia/Seoul",
    "iso:country":"KR",
    "name:und_x_variant":[
        "\ub454\ub355\uc774",
        "Tund\u014fgi"
    ],
    "wof:name":"Tundogi",
    "wof:placetype":"locality"
},
  "geometry": {"coordinates":[128.0429,36.4318],"type":"Point"}
}