{
  "type": "Feature",
  "properties": {
    "gn:admin1_code":"14.0",
    "gn:asciiname":"Wolsong",
    "gn:country_code":"KR",
    "gn:dem":9,
    "gn:feature_class":"P",
    "gn:feature_code":"PPL",
    "gn:name":"W\u014flsong",
    "gn:population":0,
    "gn:timezone":"Asia/Seoul",
    "iso:country":"KR",
    "name:und_x_variant":[
        "\uc6d4\uc1a1",
        "W\u014flsong"
    ],
    "wof:name":"Wolsong",
    "wof:placetype":"locality"
},
  "geometry": {"coordinates":[129.46059,36.74104000000001],"type":"Point"}
}