{
  "type": "Feature",
  "properties": {
    "iso:country":"KR",
    "name:eng_x_preferred":[
        "Donggwang-dong"
    ],
    "name:kor_x_preferred":[
        "\ub3d9\uad11\ub3d9"
    ],
    "qs:name":"\ub3d9\uad11\ub3d9",
    "qs:name_adm0":"\ud55c\uad6d",
    "qs:name_adm1":"\ubd80\uc0b0",
    "qs:photos":262,
    "qs:photos_1k":53,
    "qs:photos_9k":1,
    "qs:photos_9r":4,
    "qs:photos_all":262,
    "qs:photos_sr":5,
    "qs:placetype":"Suburb",
    "qs:pop_sr":"0",
    "wof:name":"Donggwang-dong",
    "wof:placetype":"neighbourhood"
},
  "geometry": {"coordinates":[129.034595,35.10081],"type":"Point"}
}