{
  "type": "Feature",
  "properties": {
    "gn:admin1_code":"20.0",
    "gn:asciiname":"Worhwa",
    "gn:country_code":"KR",
    "gn:dem":276,
    "gn:feature_class":"P",
    "gn:feature_code":"PPL",
    "gn:name":"W\u014frhwa",
    "gn:population":0,
    "gn:timezone":"Asia/Seoul",
    "iso:country":"KR",
    "name:und_x_variant":[
        "\uc6d4\ud654",
        "W\u014frhwa"
    ],
    "wof:name":"Worhwa",
    "wof:placetype":"locality"
},
  "geometry": {"coordinates":[127.84568,35.72042000000001],"type":"Point"}
}