{
  "type": "Feature",
  "properties": {
    "gn:admin1_code":"17.0",
    "gn:asciiname":"Turu-ni",
    "gn:cc2":"KR",
    "gn:country_code":"KR",
    "gn:dem":112,
    "gn:feature_class":"P",
    "gn:feature_code":"PPL",
    "gn:name":"Turu-ni",
    "gn:population":0,
    "gn:timezone":"Asia/Seoul",
    "iso:country":"KR",
    "name:eng_x_preferred":[
        "Turu"
    ],
    "name:eng_x_variant":[
        "Turu-ni"
    ],
    "name:und_x_variant":[
        "Ss\u016dmy\u014fng",
        "Tumy\u014fng",
        "Turu-ni"
    ],
    "wof:name":"Turu",
    "wof:placetype":"locality"
},
  "geometry": {"coordinates":[126.58333,36.26667],"type":"Point"}
}