{
  "type": "Feature",
  "properties": {
    "gn:admin1_code":"21.0",
    "gn:asciiname":"Soho-ri",
    "gn:country_code":"KR",
    "gn:dem":503,
    "gn:feature_class":"P",
    "gn:feature_code":"PPL",
    "gn:name":"Soho-ri",
    "gn:population":0,
    "gn:timezone":"Asia/Seoul",
    "iso:country":"KR",
    "name:kor_x_preferred":[
        "\uc18c\ud638\ub9ac"
    ],
    "wof:name":"Soho-ri",
    "wof:placetype":"locality"
},
  "geometry": {"coordinates":[129.08411999999998,35.66522],"type":"Point"}
}