{
  "type": "Feature",
  "properties": {
    "gn:admin1_code":"14.0",
    "gn:asciiname":"Doljeol",
    "gn:country_code":"KR",
    "gn:dem":135,
    "gn:feature_class":"P",
    "gn:feature_code":"PPL",
    "gn:name":"Doljeol",
    "gn:population":0,
    "gn:timezone":"Asia/Seoul",
    "iso:country":"KR",
    "name:kor_x_preferred":[
        "\ub3cc\uc808"
    ],
    "wof:name":"Doljeol",
    "wof:placetype":"locality"
},
  "geometry": {"coordinates":[128.63012000000001,36.74825],"type":"Point"}
}