{
  "type": "Feature",
  "properties": {
    "gn:admin1_code":"20.0",
    "gn:asciiname":"Wissup'twi",
    "gn:country_code":"KR",
    "gn:dem":38,
    "gn:feature_class":"P",
    "gn:feature_code":"PPL",
    "gn:name":"Wissup\u2019twi",
    "gn:population":0,
    "gn:timezone":"Asia/Seoul",
    "iso:country":"KR",
    "name:und_x_variant":[
        "\uc717\uc232\ub4a4",
        "Wissup\u2019twi"
    ],
    "wof:name":"Wissup'twi",
    "wof:placetype":"locality"
},
  "geometry": {"coordinates":[128.18549999999999,35.57718],"type":"Point"}
}