{
  "type": "Feature",
  "properties": {
    "gn:admin1_code":"20.0",
    "gn:asciiname":"Chomttam",
    "gn:country_code":"KR",
    "gn:dem":119,
    "gn:feature_class":"P",
    "gn:feature_code":"PPL",
    "gn:name":"Ch\u014fmttam",
    "gn:population":0,
    "gn:timezone":"Asia/Seoul",
    "iso:country":"KR",
    "name:und_x_variant":[
        "\uc810\ub540",
        "Ch\u014fmttam"
    ],
    "wof:name":"Chomttam",
    "wof:placetype":"locality"
},
  "geometry": {"coordinates":[128.34082000000001,35.10513],"type":"Point"}
}