{
  "type": "Feature",
  "properties": {
    "gn:admin1_code":"6.0",
    "gn:asciiname":"Chungbang",
    "gn:country_code":"KR",
    "gn:dem":269,
    "gn:feature_class":"P",
    "gn:feature_code":"PPL",
    "gn:name":"Chungbang",
    "gn:population":0,
    "gn:timezone":"Asia/Seoul",
    "iso:country":"KR",
    "name:kor_x_preferred":[
        "\uc911\ubc29"
    ],
    "name:und_x_variant":[
        "Chungbang-dong",
        "Chungbang"
    ],
    "wof:name":"Chungbang",
    "wof:placetype":"locality"
},
  "geometry": {"coordinates":[128.26840000000001,37.29],"type":"Point"}
}