{
  "type": "Feature",
  "properties": {
    "gn:admin1_code":"3.0",
    "gn:asciiname":"Kusu-ri",
    "gn:country_code":"KR",
    "gn:dem":224,
    "gn:feature_class":"P",
    "gn:feature_code":"PPL",
    "gn:name":"Kusu-ri",
    "gn:population":0,
    "gn:timezone":"Asia/Seoul",
    "iso:country":"KR",
    "name:und_x_variant":[
        "\uad6c\uc218\ub9ac",
        "Kusu-ri"
    ],
    "wof:name":"Kusu-ri",
    "wof:placetype":"locality"
},
  "geometry": {"coordinates":[127.32455,35.96102],"type":"Point"}
}