{
  "type": "Feature",
  "properties": {
    "gn:admin1_code":"14.0",
    "gn:asciiname":"Daebu",
    "gn:country_code":"KR",
    "gn:dem":19,
    "gn:feature_class":"P",
    "gn:feature_code":"PPL",
    "gn:name":"Daebu",
    "gn:population":0,
    "gn:timezone":"Asia/Seoul",
    "iso:country":"KR",
    "name:kor_x_preferred":[
        "\ub300\ubd80"
    ],
    "wof:name":"Daebu",
    "wof:placetype":"locality"
},
  "geometry": {"coordinates":[129.42098999999999,36.40052],"type":"Point"}
}