{
  "type": "Feature",
  "properties": {
    "gn:admin1_code":"17.0",
    "gn:asciiname":"Changhyol-li",
    "gn:country_code":"KR",
    "gn:dem":15,
    "gn:feature_class":"P",
    "gn:feature_code":"PPL",
    "gn:name":"Changhy\u014fl-li",
    "gn:population":0,
    "gn:timezone":"Asia/Seoul",
    "iso:country":"KR",
    "name:kor_x_preferred":[
        "\uc7a5\ud604\ub9ac"
    ],
    "name:und_x_variant":[
        "Changhy\u014fn-ni",
        "\uc7a5\ud604\ub9ac",
        "Kanghy\u014fn-ni",
        "Changhy\u014fl-li"
    ],
    "wof:name":"Changhyol-li",
    "wof:placetype":"locality"
},
  "geometry": {"coordinates":[126.4088,36.8572],"type":"Point"}
}