{
  "type": "Feature",
  "properties": {
    "gn:admin1_code":"13.0",
    "gn:asciiname":"Jageun-mal",
    "gn:country_code":"KR",
    "gn:dem":136,
    "gn:feature_class":"P",
    "gn:feature_code":"PPL",
    "gn:name":"Jageun-mal",
    "gn:population":0,
    "gn:timezone":"Asia/Seoul",
    "iso:country":"KR",
    "name:und_x_variant":[
        "\uc791\uc740\ub9d0",
        "Jageun-mal",
        "Chag\u016dn-mal"
    ],
    "wof:name":"Jageun-mal",
    "wof:placetype":"locality"
},
  "geometry": {"coordinates":[127.01361,37.32722],"type":"Point"}
}