{
  "type": "Feature",
  "properties": {
    "gn:admin1_code":"6.0",
    "gn:asciiname":"Pultunch'i",
    "gn:country_code":"KR",
    "gn:dem":551,
    "gn:feature_class":"P",
    "gn:feature_code":"PPL",
    "gn:name":"Pultunch\u2019i",
    "gn:population":0,
    "gn:timezone":"Asia/Seoul",
    "iso:country":"KR",
    "name:kor_x_preferred":[
        "\ubd88\ub454\uce58"
    ],
    "name:kor_x_variant":[
        "Pultunch\u2019i"
    ],
    "wof:name":"Pultunch'i",
    "wof:placetype":"locality"
},
  "geometry": {"coordinates":[128.22399999999999,37.3372],"type":"Point"}
}