{
  "type": "Feature",
  "properties": {
    "gn:admin1_code":"5.0",
    "gn:asciiname":"Kak-kol",
    "gn:country_code":"KR",
    "gn:dem":224,
    "gn:feature_class":"P",
    "gn:feature_code":"PPL",
    "gn:name":"Kak-kol",
    "gn:population":0,
    "gn:timezone":"Asia/Seoul",
    "iso:country":"KR",
    "name:kor_x_preferred":[
        "\uac01\uace8"
    ],
    "wof:name":"Kak-kol",
    "wof:placetype":"locality"
},
  "geometry": {"coordinates":[128.42259999999999,37.0963],"type":"Point"}
}