{
  "type": "Feature",
  "properties": {
    "gn:admin1_code":"11.0",
    "gn:asciiname":"Changansa-dong",
    "gn:country_code":"KR",
    "gn:dem":21,
    "gn:feature_class":"P",
    "gn:feature_code":"PPL",
    "gn:name":"Changansa-dong",
    "gn:population":0,
    "gn:timezone":"Asia/Seoul",
    "iso:country":"KR",
    "name:und_x_variant":[
        "\uc7a5\uc5484\ub3d9",
        "Changansa-dong"
    ],
    "wof:name":"Changansa-dong",
    "wof:placetype":"locality"
},
  "geometry": {"coordinates":[127.07182,37.57706],"type":"Point"}
}