{
  "type": "Feature",
  "properties": {
    "gn:admin1_code":"17.0",
    "gn:asciiname":"Tanjongi",
    "gn:country_code":"KR",
    "gn:dem":14,
    "gn:feature_class":"P",
    "gn:feature_code":"PPL",
    "gn:name":"Tanj\u014fngi",
    "gn:population":0,
    "gn:timezone":"Asia/Seoul",
    "iso:country":"KR",
    "name:und_x_variant":[
        "\ub2e8\uc815\uc774",
        "Tanj\u014fngi"
    ],
    "wof:name":"Tanjongi",
    "wof:placetype":"locality"
},
  "geometry": {"coordinates":[126.86320000000001,36.8121],"type":"Point"}
}