{
  "type": "Feature",
  "properties": {
    "gn:admin1_code":"17.0",
    "gn:asciiname":"Sajami",
    "gn:country_code":"KR",
    "gn:dem":218,
    "gn:feature_class":"P",
    "gn:feature_code":"PPL",
    "gn:name":"Sajami",
    "gn:population":0,
    "gn:timezone":"Asia/Seoul",
    "iso:country":"KR",
    "name:und_x_variant":[
        "\uc0ac\uc790\ubbf8",
        "Sajami"
    ],
    "wof:name":"Sajami",
    "wof:placetype":"locality"
},
  "geometry": {"coordinates":[126.8848,36.5274],"type":"Point"}
}