{
  "type": "Feature",
  "properties": {
    "gn:admin1_code":"20.0",
    "gn:asciiname":"Keunmaeul",
    "gn:country_code":"KR",
    "gn:dem":324,
    "gn:feature_class":"P",
    "gn:feature_code":"PPL",
    "gn:name":"Keunmaeul",
    "gn:population":0,
    "gn:timezone":"Asia/Seoul",
    "iso:country":"KR",
    "name:und_x_variant":[
        "\ud070\ub9c8\uc744",
        "K\u2019\u016dn-ma\u016dl",
        "Keunmaeul"
    ],
    "wof:name":"Keunmaeul",
    "wof:placetype":"locality"
},
  "geometry": {"coordinates":[128.52236000000002,35.6589],"type":"Point"}
}