{
  "type": "Feature",
  "properties": {
    "gn:admin1_code":"17.0",
    "gn:asciiname":"Ch'angam-ni",
    "gn:country_code":"KR",
    "gn:dem":16,
    "gn:feature_class":"P",
    "gn:feature_code":"PPL",
    "gn:name":"Ch\u2019angam-ni",
    "gn:population":0,
    "gn:timezone":"Asia/Seoul",
    "iso:country":"KR",
    "name:und_x_variant":[
        "\ucc3d\uc554\ub9ac",
        "Ch\u2019angam-ni"
    ],
    "wof:name":"Ch'angam-ni",
    "wof:placetype":"locality"
},
  "geometry": {"coordinates":[126.9958,36.3357],"type":"Point"}
}