{
  "type": "Feature",
  "properties": {
    "gn:admin1_code":"18.0",
    "gn:asciiname":"Dongha",
    "gn:country_code":"KR",
    "gn:dem":29,
    "gn:feature_class":"P",
    "gn:feature_code":"PPL",
    "gn:name":"Dongha",
    "gn:population":0,
    "gn:timezone":"Asia/Seoul",
    "iso:country":"KR",
    "name:kor_x_preferred":[
        "\ub3d9\ud558"
    ],
    "name:und_x_variant":[
        "Tongha"
    ],
    "wof:name":"Dongha",
    "wof:placetype":"locality"
},
  "geometry": {"coordinates":[126.83665000000001,35.11987],"type":"Point"}
}