{
  "type": "Feature",
  "properties": {
    "gn:admin1_code":"14.0",
    "gn:asciiname":"Kanun-gol",
    "gn:country_code":"KR",
    "gn:dem":209,
    "gn:feature_class":"P",
    "gn:feature_code":"PPL",
    "gn:name":"Kan\u016dn-gol",
    "gn:population":0,
    "gn:timezone":"Asia/Seoul",
    "iso:country":"KR",
    "name:und_x_variant":[
        "\uac00\ub294\uace8",
        "Kan\u016dn-gol"
    ],
    "wof:name":"Kanun-gol",
    "wof:placetype":"locality"
},
  "geometry": {"coordinates":[129.066,36.6287],"type":"Point"}
}