{
  "type": "Feature",
  "properties": {
    "gn:admin1_code":"16.0",
    "gn:asciiname":"Namjeon",
    "gn:country_code":"KR",
    "gn:dem":6,
    "gn:feature_class":"P",
    "gn:feature_code":"PPL",
    "gn:name":"Namjeon",
    "gn:population":0,
    "gn:timezone":"Asia/Seoul",
    "iso:country":"KR",
    "name:kor_x_preferred":[
        "Namj\u014fn"
    ],
    "name:kor_x_variant":[
        "\ub0a8\uc804"
    ],
    "wof:name":"Namjeon",
    "wof:placetype":"locality"
},
  "geometry": {"coordinates":[126.59972,34.33778],"type":"Point"}
}