{
  "type": "Feature",
  "properties": {
    "iso:country":"KR",
    "qs:name":"\ubd84\ub2f9\uad6c",
    "qs:name_adm0":"\ud55c\uad6d",
    "qs:name_adm1":"\uacbd\uae30\ub3c4",
    "qs:photos":20,
    "qs:photos_1k":4,
    "qs:photos_9k":30,
    "qs:photos_9r":15,
    "qs:photos_all":6704,
    "qs:photos_sr":1,
    "qs:placetype":"LocalAdmin",
    "qs:pop_sr":"0",
    "wof:name":"\ubd84\ub2f9\uad6c",
    "wof:placetype":"localadmin"
},
  "geometry": {"coordinates":[127.120666,37.379688],"type":"Point"}
}