{
  "type": "Feature",
  "properties": {
    "gn:admin1_code":"17.0",
    "gn:asciiname":"Samgong-ni",
    "gn:country_code":"KR",
    "gn:dem":31,
    "gn:feature_class":"P",
    "gn:feature_code":"PPL",
    "gn:name":"Samgong-ni",
    "gn:population":0,
    "gn:timezone":"Asia/Seoul",
    "iso:country":"KR",
    "name:eng_x_preferred":[
        "Samgong"
    ],
    "name:eng_x_variant":[
        "Samgong-ni"
    ],
    "name:und_x_variant":[
        "\uc0bc\uace1\ub9ac",
        "Samgong-ni"
    ],
    "wof:name":"Samgong",
    "wof:placetype":"locality"
},
  "geometry": {"coordinates":[127.1865,36.9004],"type":"Point"}
}