{
  "type": "Feature",
  "properties": {
    "gn:admin1_code":"16.0",
    "gn:asciiname":"Unggok",
    "gn:cc2":"KR",
    "gn:country_code":"KR",
    "gn:dem":9,
    "gn:feature_class":"P",
    "gn:feature_code":"PPL",
    "gn:name":"Unggok",
    "gn:population":0,
    "gn:timezone":"Asia/Seoul",
    "iso:country":"KR",
    "name:und_x_variant":[
        "Unggong-ni",
        "Unggok"
    ],
    "wof:name":"Unggok",
    "wof:placetype":"locality"
},
  "geometry": {"coordinates":[126.03610999999999,34.6025],"type":"Point"}
}