{
  "type": "Feature",
  "properties": {
    "gn:admin1_code":"6.0",
    "gn:asciiname":"Chakpaek-tong",
    "gn:country_code":"KR",
    "gn:dem":63,
    "gn:feature_class":"P",
    "gn:feature_code":"PPL",
    "gn:name":"Chakpaek-tong",
    "gn:population":0,
    "gn:timezone":"Asia/Seoul",
    "iso:country":"KR",
    "name:und_x_variant":[
        "\uc791\ubc31\ub3d9",
        "Jakbaek-dong",
        "Chakpaek-tong"
    ],
    "wof:name":"Chakpaek-tong",
    "wof:placetype":"locality"
},
  "geometry": {"coordinates":[127.79416999999999,37.29861],"type":"Point"}
}