{
  "type": "Feature",
  "properties": {
    "gn:admin1_code":"20.0",
    "gn:asciiname":"Sanggaemyong",
    "gn:country_code":"KR",
    "gn:dem":478,
    "gn:feature_class":"P",
    "gn:feature_code":"PPL",
    "gn:name":"Sanggaemy\u014fng",
    "gn:population":0,
    "gn:timezone":"Asia/Seoul",
    "iso:country":"KR",
    "name:und_x_variant":[
        "\uc0c1\uac1c\uba85",
        "Sanggaemy\u014fng"
    ],
    "wof:name":"Sanggaemyong",
    "wof:placetype":"locality"
},
  "geometry": {"coordinates":[127.85625,35.83607],"type":"Point"}
}