{
  "type": "Feature",
  "properties": {
    "gn:admin1_code":"14.0",
    "gn:asciiname":"Amnyang",
    "gn:country_code":"KR",
    "gn:dem":53,
    "gn:feature_class":"P",
    "gn:feature_code":"PPL",
    "gn:name":"Amnyang",
    "gn:population":0,
    "gn:timezone":"Asia/Seoul",
    "iso:country":"KR",
    "name:kor_x_preferred":[
        "\uc555\ub7c9"
    ],
    "wof:name":"Amnyang",
    "wof:placetype":"locality"
},
  "geometry": {"coordinates":[128.7706,35.84582],"type":"Point"}
}