{
  "type": "Feature",
  "properties": {
    "gn:admin1_code":"5.0",
    "gn:asciiname":"Uthanch'i",
    "gn:country_code":"KR",
    "gn:dem":275,
    "gn:feature_class":"P",
    "gn:feature_code":"PPL",
    "gn:name":"Uthanch\u2019i",
    "gn:population":0,
    "gn:timezone":"Asia/Seoul",
    "iso:country":"KR",
    "name:kor_x_preferred":[
        "\uc6c3\ud55c\uce58"
    ],
    "name:kor_x_variant":[
        "Uthanch\u2019i"
    ],
    "wof:name":"Uthanch'i",
    "wof:placetype":"locality"
},
  "geometry": {"coordinates":[128.06299999999999,37.105],"type":"Point"}
}