{
  "type": "Feature",
  "properties": {
    "gn:admin1_code":"17.0",
    "gn:asciiname":"Yomi-ri",
    "gn:country_code":"KR",
    "gn:dem":68,
    "gn:feature_class":"P",
    "gn:feature_code":"PPL",
    "gn:name":"Y\u014fmi-ri",
    "gn:population":0,
    "gn:timezone":"Asia/Seoul",
    "iso:country":"KR",
    "name:und_x_variant":[
        "\uc5ec\ubbf8\ub9ac",
        "Y\u014fmi-ri"
    ],
    "wof:name":"Yomi-ri",
    "wof:placetype":"locality"
},
  "geometry": {"coordinates":[126.56870000000001,36.8232],"type":"Point"}
}