{
  "type": "Feature",
  "properties": {
    "gn:admin1_code":"14.0",
    "gn:asciiname":"Masalli",
    "gn:country_code":"KR",
    "gn:dem":21,
    "gn:feature_class":"P",
    "gn:feature_code":"PPL",
    "gn:name":"Masalli",
    "gn:population":0,
    "gn:timezone":"Asia/Seoul",
    "iso:country":"KR",
    "name:kor_x_preferred":[
        "\ub9c8\uc0b0\ub9ac"
    ],
    "wof:name":"Masalli",
    "wof:placetype":"locality"
},
  "geometry": {"coordinates":[129.33811,36.11317],"type":"Point"}
}