{
  "type": "Feature",
  "properties": {
    "gn:admin1_code":"10.0",
    "gn:asciiname":"Taeryong",
    "gn:country_code":"KR",
    "gn:dem":78,
    "gn:feature_class":"P",
    "gn:feature_code":"PPL",
    "gn:name":"Taeryong",
    "gn:population":0,
    "gn:timezone":"Asia/Seoul",
    "iso:country":"KR",
    "name:kor_x_preferred":[
        "\ud0dc\ub8e1"
    ],
    "wof:name":"Taeryong",
    "wof:placetype":"locality"
},
  "geometry": {"coordinates":[129.26393000000002,35.37124],"type":"Point"}
}