{
  "type": "Feature",
  "properties": {
    "gn:admin1_code":"14.0",
    "gn:asciiname":"Keunumusil",
    "gn:country_code":"KR",
    "gn:dem":238,
    "gn:feature_class":"P",
    "gn:feature_code":"PPL",
    "gn:name":"Keunumusil",
    "gn:population":0,
    "gn:timezone":"Asia/Seoul",
    "iso:country":"KR",
    "name:kor_x_preferred":[
        "\ud070\uc6b0\ubb34\uc2e4"
    ],
    "wof:name":"Keunumusil",
    "wof:placetype":"locality"
},
  "geometry": {"coordinates":[128.66166000000001,36.76121],"type":"Point"}
}