{
  "type": "Feature",
  "properties": {
    "gn:admin1_code":"16.0",
    "gn:asciiname":"Orim",
    "gn:country_code":"KR",
    "gn:dem":46,
    "gn:feature_class":"P",
    "gn:feature_code":"PPL",
    "gn:name":"Orim",
    "gn:population":0,
    "gn:timezone":"Asia/Seoul",
    "iso:country":"KR",
    "name:kor_x_preferred":[
        "\uc624\ub9bc"
    ],
    "name:und_x_variant":[
        "Orim-ni",
        "Orim"
    ],
    "wof:name":"Orim",
    "wof:placetype":"locality"
},
  "geometry": {"coordinates":[126.7623,34.93657],"type":"Point"}
}