{
  "type": "Feature",
  "properties": {
    "gn:admin1_code":"15.0",
    "gn:asciiname":"Jangseongni",
    "gn:country_code":"KR",
    "gn:dem":37,
    "gn:feature_class":"P",
    "gn:feature_code":"PPL",
    "gn:name":"Jangseongni",
    "gn:population":0,
    "gn:timezone":"Asia/Seoul",
    "iso:country":"KR",
    "name:und_x_variant":[
        "\uc7a5\uc131\ub9ac",
        "Changs\u014fng-ni",
        "Jangseongni"
    ],
    "wof:name":"Jangseongni",
    "wof:placetype":"locality"
},
  "geometry": {"coordinates":[128.44099,35.93274],"type":"Point"}
}