{
  "type": "Feature",
  "properties": {
    "gn:admin1_code":"16.0",
    "gn:asciiname":"Sinjeong",
    "gn:country_code":"KR",
    "gn:dem":11,
    "gn:feature_class":"P",
    "gn:feature_code":"PPL",
    "gn:name":"Sinjeong",
    "gn:population":0,
    "gn:timezone":"Asia/Seoul",
    "iso:country":"KR",
    "name:kor_x_preferred":[
        "\uc2e0\uc815"
    ],
    "name:und_x_variant":[
        "Chinj\u014fng"
    ],
    "wof:name":"Sinjeong",
    "wof:placetype":"locality"
},
  "geometry": {"coordinates":[126.46666999999999,35.41667],"type":"Point"}
}