{
  "type": "Feature",
  "properties": {
    "gn:admin1_code":"16.0",
    "gn:asciiname":"Na-ri",
    "gn:cc2":"KR",
    "gn:country_code":"KR",
    "gn:dem":17,
    "gn:feature_class":"P",
    "gn:feature_code":"PPL",
    "gn:name":"Na-ri",
    "gn:population":0,
    "gn:timezone":"Asia/Seoul",
    "iso:country":"KR",
    "name:und_x_variant":[
        "Ra-ri",
        "Na-ri"
    ],
    "wof:name":"Na-ri",
    "wof:placetype":"locality"
},
  "geometry": {"coordinates":[126.25694,34.56722],"type":"Point"}
}