{
  "type": "Feature",
  "properties": {
    "gn:admin1_code":"13.0",
    "gn:asciiname":"Gujin",
    "gn:country_code":"KR",
    "gn:dem":19,
    "gn:feature_class":"P",
    "gn:feature_code":"PPL",
    "gn:name":"Gujin",
    "gn:population":0,
    "gn:timezone":"Asia/Seoul",
    "iso:country":"KR",
    "name:und_x_variant":[
        "Ch\u2019ijinp\u2019o",
        "Kujinp\u2019o",
        "\uad6c\uc9c4",
        "Kujin",
        "Gujin"
    ],
    "wof:name":"Gujin",
    "wof:placetype":"locality"
},
  "geometry": {"coordinates":[126.94289000000001,36.93151],"type":"Point"}
}