{
  "type": "Feature",
  "properties": {
    "gn:admin1_code":"17.0",
    "gn:asciiname":"Wonsal-li",
    "gn:cc2":"KR",
    "gn:country_code":"KR",
    "gn:dem":10,
    "gn:feature_class":"P",
    "gn:feature_code":"PPL",
    "gn:name":"W\u014fnsal-li",
    "gn:population":0,
    "gn:timezone":"Asia/Seoul",
    "iso:country":"KR",
    "name:und_x_variant":[
        "W\u014fnmoe",
        "W\u014fnsan-ni",
        "W\u014fnsal-li"
    ],
    "wof:name":"Wonsal-li",
    "wof:placetype":"locality"
},
  "geometry": {"coordinates":[126.83333,36.11694],"type":"Point"}
}