{
  "type": "Feature",
  "properties": {
    "gn:admin1_code":"20.0",
    "gn:asciiname":"Changji-dong",
    "gn:country_code":"KR",
    "gn:dem":124,
    "gn:feature_class":"P",
    "gn:feature_code":"PPL",
    "gn:name":"Changji-dong",
    "gn:population":0,
    "gn:timezone":"Asia/Seoul",
    "iso:country":"KR",
    "name:und_x_variant":[
        "\uc7a5\uc9c0\ub3d9",
        "Changji-dong"
    ],
    "wof:name":"Changji-dong",
    "wof:placetype":"locality"
},
  "geometry": {"coordinates":[128.25346999999999,35.45309],"type":"Point"}
}