{
  "type": "Feature",
  "properties": {
    "gn:admin1_code":"20.0",
    "gn:asciiname":"Pallye",
    "gn:cc2":"KR",
    "gn:country_code":"KR",
    "gn:dem":212,
    "gn:feature_class":"P",
    "gn:feature_code":"PPL",
    "gn:name":"Pallye",
    "gn:population":0,
    "gn:timezone":"Asia/Seoul",
    "iso:country":"KR",
    "name:und_x_variant":[
        "Pallae",
        "Pallye"
    ],
    "wof:name":"Pallye",
    "wof:placetype":"locality"
},
  "geometry": {"coordinates":[128.90000000000001,35.56667],"type":"Point"}
}