{
  "type": "Feature",
  "properties": {
    "gn:admin1_code":"20.0",
    "gn:asciiname":"Maeng-dong",
    "gn:country_code":"KR",
    "gn:dem":440,
    "gn:feature_class":"P",
    "gn:feature_code":"PPL",
    "gn:name":"Maeng-dong",
    "gn:population":0,
    "gn:timezone":"Asia/Seoul",
    "iso:country":"KR",
    "name:und_x_variant":[
        "\ub9f9\ub3d9",
        "Maeng-dong"
    ],
    "wof:name":"Maeng-dong",
    "wof:placetype":"locality"
},
  "geometry": {"coordinates":[127.68514,35.69264000000001],"type":"Point"}
}