{
  "type": "Feature",
  "properties": {
    "gn:admin1_code":"5.0",
    "gn:asciiname":"Gwangsangol",
    "gn:country_code":"KR",
    "gn:dem":82,
    "gn:feature_class":"P",
    "gn:feature_code":"PPL",
    "gn:name":"Gwangsangol",
    "gn:population":0,
    "gn:timezone":"Asia/Seoul",
    "iso:country":"KR",
    "name:kor_x_preferred":[
        "\uad11\uc0b0\uace8"
    ],
    "wof:name":"Gwangsangol",
    "wof:placetype":"locality"
},
  "geometry": {"coordinates":[127.86797,36.96049],"type":"Point"}
}