{
  "type": "Feature",
  "properties": {
    "gn:admin1_code":"16.0",
    "gn:asciiname":"Bakgok",
    "gn:country_code":"KR",
    "gn:dem":100,
    "gn:feature_class":"P",
    "gn:feature_code":"PPL",
    "gn:name":"Bakgok",
    "gn:population":0,
    "gn:timezone":"Asia/Seoul",
    "iso:country":"KR",
    "name:kor_x_preferred":[
        "\ubc15\uace1"
    ],
    "wof:name":"Bakgok",
    "wof:placetype":"locality"
},
  "geometry": {"coordinates":[126.81596,34.98741],"type":"Point"}
}