{
  "type": "Feature",
  "properties": {
    "gn:admin1_code":"6.0",
    "gn:asciiname":"Jangteo",
    "gn:country_code":"KR",
    "gn:dem":108,
    "gn:feature_class":"P",
    "gn:feature_code":"PPL",
    "gn:name":"Jangteo",
    "gn:population":0,
    "gn:timezone":"Asia/Seoul",
    "iso:country":"KR",
    "name:kor_x_preferred":[
        "\uc7a5\ud130"
    ],
    "wof:name":"Jangteo",
    "wof:placetype":"locality"
},
  "geometry": {"coordinates":[127.70916,37.73189],"type":"Point"}
}