{
  "type": "Feature",
  "properties": {
    "gn:admin1_code":"12.0",
    "gn:asciiname":"Ipkuji",
    "gn:country_code":"KR",
    "gn:dem":16,
    "gn:feature_class":"P",
    "gn:feature_code":"PPL",
    "gn:name":"Ipkuji",
    "gn:population":0,
    "gn:timezone":"Asia/Seoul",
    "iso:country":"KR",
    "name:und_x_variant":[
        "\uc785\uad6c\uc9c0",
        "Ipguji",
        "Ipkuji"
    ],
    "wof:name":"Ipkuji",
    "wof:placetype":"locality"
},
  "geometry": {"coordinates":[126.37860999999999,37.44333],"type":"Point"}
}