{
  "type": "Feature",
  "properties": {
    "gn:admin1_code":"17.0",
    "gn:asciiname":"T'aep'o",
    "gn:country_code":"KR",
    "gn:dem":24,
    "gn:feature_class":"P",
    "gn:feature_code":"PPL",
    "gn:name":"T\u2019aep\u2019o",
    "gn:population":0,
    "gn:timezone":"Asia/Seoul",
    "iso:country":"KR",
    "name:und_x_variant":[
        "\ud0dc\ud3ec",
        "T\u2019aep\u2019o"
    ],
    "wof:name":"T'aep'o",
    "wof:placetype":"locality"
},
  "geometry": {"coordinates":[126.2848,36.8372],"type":"Point"}
}