{
  "type": "Feature",
  "properties": {
    "gn:admin1_code":"17.0",
    "gn:asciiname":"T'an-dong",
    "gn:country_code":"KR",
    "gn:dem":131,
    "gn:feature_class":"P",
    "gn:feature_code":"PPL",
    "gn:name":"T\u2019an-dong",
    "gn:population":0,
    "gn:timezone":"Asia/Seoul",
    "iso:country":"KR",
    "name:und_x_variant":[
        "\ud0c4\ub3d9",
        "T\u2019an-dong"
    ],
    "wof:name":"T'an-dong",
    "wof:placetype":"locality"
},
  "geometry": {"coordinates":[126.657,36.7569],"type":"Point"}
}