{
  "type": "Feature",
  "properties": {
    "gn:admin1_code":"12.0",
    "gn:asciiname":"Dwitgol",
    "gn:country_code":"KR",
    "gn:dem":47,
    "gn:feature_class":"P",
    "gn:feature_code":"PPL",
    "gn:name":"Dwitgol",
    "gn:population":0,
    "gn:timezone":"Asia/Seoul",
    "iso:country":"KR",
    "name:kor_x_preferred":[
        "\ub4b7\uace8"
    ],
    "wof:name":"Dwitgol",
    "wof:placetype":"locality"
},
  "geometry": {"coordinates":[126.77124999999999,37.46018],"type":"Point"}
}