{
  "type": "Feature",
  "properties": {
    "gn:admin1_code":"6.0",
    "gn:asciiname":"Jaegungdong",
    "gn:country_code":"KR",
    "gn:dem":277,
    "gn:feature_class":"P",
    "gn:feature_code":"PPL",
    "gn:name":"Jaegungdong",
    "gn:population":0,
    "gn:timezone":"Asia/Seoul",
    "iso:country":"KR",
    "name:kor_x_preferred":[
        "\uc7ac\uad81\ub3d9"
    ],
    "name:und_x_variant":[
        "Chaeg\u014fnch\u2019on",
        "Jaegungdong",
        "Chaegung-dong"
    ],
    "wof:name":"Jaegungdong",
    "wof:placetype":"locality"
},
  "geometry": {"coordinates":[127.53653,38.27824],"type":"Point"}
}