{
  "type": "Feature",
  "properties": {
    "gn:admin1_code":"14.0",
    "gn:asciiname":"Pangbi",
    "gn:country_code":"KR",
    "gn:dem":154,
    "gn:feature_class":"P",
    "gn:feature_code":"PPL",
    "gn:name":"Pangbi",
    "gn:population":0,
    "gn:timezone":"Asia/Seoul",
    "iso:country":"KR",
    "name:und_x_variant":[
        "\ubc29\ube44",
        "Pangbi"
    ],
    "wof:name":"Pangbi",
    "wof:placetype":"locality"
},
  "geometry": {"coordinates":[129.37960000000001,36.8192],"type":"Point"}
}