{
  "type": "Feature",
  "properties": {
    "gn:admin1_code":"1.0",
    "gn:admin2_code":"Pukcheju-gun",
    "gn:asciiname":"Suryongdong",
    "gn:country_code":"KR",
    "gn:dem":80,
    "gn:feature_class":"P",
    "gn:feature_code":"PPL",
    "gn:name":"Suryongdong",
    "gn:population":0,
    "gn:timezone":"Asia/Seoul",
    "iso:country":"KR",
    "name:kor_x_preferred":[
        "\uc218\ub8e1\ub3d9"
    ],
    "name:und_x_variant":[
        "Suryong",
        "Suryongdong"
    ],
    "wof:name":"Suryongdong",
    "wof:placetype":"locality"
},
  "geometry": {"coordinates":[126.23956,33.30901],"type":"Point"}
}