{
  "type": "Feature",
  "properties": {
    "gn:admin1_code":"17.0",
    "gn:asciiname":"Sindu-ri",
    "gn:country_code":"KR",
    "gn:dem":61,
    "gn:feature_class":"P",
    "gn:feature_code":"PPLL",
    "gn:name":"Sindu-ri",
    "gn:population":0,
    "gn:timezone":"Asia/Seoul",
    "iso:country":"KR",
    "name:und_x_variant":[
        "\uc2e0\ub450\ub9ac",
        "Sindu-ri"
    ],
    "wof:name":"Sindu-ri",
    "wof:placetype":"locality"
},
  "geometry": {"coordinates":[126.2034,36.8308],"type":"Point"}
}