{
  "type": "Feature",
  "properties": {
    "gn:admin1_code":"14.0",
    "gn:asciiname":"Pultang-gol",
    "gn:country_code":"KR",
    "gn:dem":92,
    "gn:feature_class":"P",
    "gn:feature_code":"PPL",
    "gn:name":"Pultang-gol",
    "gn:population":0,
    "gn:timezone":"Asia/Seoul",
    "iso:country":"KR",
    "name:und_x_variant":[
        "\ubd88\ub2f9\uace8",
        "Pultang-gol"
    ],
    "wof:name":"Pultang-gol",
    "wof:placetype":"locality"
},
  "geometry": {"coordinates":[128.09389999999999,36.3084],"type":"Point"}
}