{
  "type": "Feature",
  "properties": {
    "gn:admin1_code":"6.0",
    "gn:asciiname":"Wonmudong",
    "gn:country_code":"KR",
    "gn:dem":231,
    "gn:feature_class":"P",
    "gn:feature_code":"PPL",
    "gn:name":"Wonmudong",
    "gn:population":0,
    "gn:timezone":"Asia/Seoul",
    "iso:country":"KR",
    "name:und_x_variant":[
        "\uc6d0\ubb34\ub3d9",
        "W\u014fnmu-dong",
        "Wonmudong"
    ],
    "wof:name":"Wonmudong",
    "wof:placetype":"locality"
},
  "geometry": {"coordinates":[127.78016,37.7645],"type":"Point"}
}