{
  "type": "Feature",
  "properties": {
    "gn:admin1_code":"14.0",
    "gn:asciiname":"Napsil",
    "gn:country_code":"KR",
    "gn:dem":33,
    "gn:feature_class":"P",
    "gn:feature_code":"PPL",
    "gn:name":"Napsil",
    "gn:population":0,
    "gn:timezone":"Asia/Seoul",
    "iso:country":"KR",
    "name:kor_x_preferred":[
        "\ub0a9\uc2e4"
    ],
    "wof:name":"Napsil",
    "wof:placetype":"locality"
},
  "geometry": {"coordinates":[128.50406000000001,35.9178],"type":"Point"}
}