{
  "type": "Feature",
  "properties": {
    "gn:admin1_code":"6.0",
    "gn:asciiname":"Chongson-ch'on",
    "gn:country_code":"KR",
    "gn:dem":722,
    "gn:feature_class":"P",
    "gn:feature_code":"PPL",
    "gn:name":"Ch\u014fngs\u014fn-ch\u2019on",
    "gn:population":0,
    "gn:timezone":"Asia/Seoul",
    "iso:country":"KR",
    "name:kor_x_preferred":[
        "\uc815\uc120\ucd0c"
    ],
    "name:kor_x_variant":[
        "Ch\u014fngs\u014fn-ch\u2019on"
    ],
    "wof:name":"Chongson-ch'on",
    "wof:placetype":"locality"
},
  "geometry": {"coordinates":[128.96680000000001,37.1821],"type":"Point"}
}