{
  "type": "Feature",
  "properties": {
    "gn:admin1_code":"3.0",
    "gn:asciiname":"Sinp'o",
    "gn:country_code":"KR",
    "gn:dem":51,
    "gn:feature_class":"P",
    "gn:feature_code":"PPL",
    "gn:name":"Sinp\u2019o",
    "gn:population":0,
    "gn:timezone":"Asia/Seoul",
    "iso:country":"KR",
    "name:und_x_variant":[
        "\uc2e0\ud3ec",
        "Sinp\u2019o"
    ],
    "wof:name":"Sinp'o",
    "wof:placetype":"locality"
},
  "geometry": {"coordinates":[127.12109,35.97677],"type":"Point"}
}