{
  "type": "Feature",
  "properties": {
    "gn:admin1_code":"6.0",
    "gn:asciiname":"Sangduwon",
    "gn:country_code":"KR",
    "gn:dem":627,
    "gn:feature_class":"P",
    "gn:feature_code":"PPL",
    "gn:name":"Sangduw\u014fn",
    "gn:population":0,
    "gn:timezone":"Asia/Seoul",
    "iso:country":"KR",
    "name:kor_x_preferred":[
        "\uc0c1\ub450\uc6d0"
    ],
    "name:kor_x_variant":[
        "Sangduw\u014fn"
    ],
    "wof:name":"Sangduwon",
    "wof:placetype":"locality"
},
  "geometry": {"coordinates":[128.25550000000001,37.4913],"type":"Point"}
}