{
  "type": "Feature",
  "properties": {
    "gn:admin1_code":"3.0",
    "gn:asciiname":"Tumusil",
    "gn:country_code":"KR",
    "gn:dem":263,
    "gn:feature_class":"P",
    "gn:feature_code":"PPL",
    "gn:name":"Tumusil",
    "gn:population":0,
    "gn:timezone":"Asia/Seoul",
    "iso:country":"KR",
    "name:und_x_variant":[
        "\ub450\ubb34\uc2e4",
        "Tumusil"
    ],
    "wof:name":"Tumusil",
    "wof:placetype":"locality"
},
  "geometry": {"coordinates":[127.26528999999999,35.70972000000001],"type":"Point"}
}