{
  "type": "Feature",
  "properties": {
    "gn:admin1_code":"16.0",
    "gn:asciiname":"Gyeyang",
    "gn:country_code":"KR",
    "gn:dem":53,
    "gn:feature_class":"P",
    "gn:feature_code":"PPL",
    "gn:name":"Gyeyang",
    "gn:population":0,
    "gn:timezone":"Asia/Seoul",
    "iso:country":"KR",
    "name:kor_x_preferred":[
        "\uacc4\uc591"
    ],
    "wof:name":"Gyeyang",
    "wof:placetype":"locality"
},
  "geometry": {"coordinates":[126.74059,34.93269],"type":"Point"}
}