{
  "type": "Feature",
  "properties": {
    "gn:admin1_code":"14.0",
    "gn:asciiname":"Ch'ilsongbong",
    "gn:country_code":"KR",
    "gn:dem":472,
    "gn:feature_class":"P",
    "gn:feature_code":"PPL",
    "gn:name":"Ch\u2019ils\u014fngbong",
    "gn:population":0,
    "gn:timezone":"Asia/Seoul",
    "iso:country":"KR",
    "name:und_x_variant":[
        "\uce60\uc131\ubd09",
        "Ch\u2019ils\u014fngbong"
    ],
    "wof:name":"Ch'ilsongbong",
    "wof:placetype":"locality"
},
  "geometry": {"coordinates":[129.20419999999999,36.5784],"type":"Point"}
}