{
  "type": "Feature",
  "properties": {
    "gn:admin1_code":"16.0",
    "gn:asciiname":"Seodongchon",
    "gn:country_code":"KR",
    "gn:dem":142,
    "gn:feature_class":"P",
    "gn:feature_code":"PPL",
    "gn:name":"Seodongchon",
    "gn:population":0,
    "gn:timezone":"Asia/Seoul",
    "iso:country":"KR",
    "name:kor_x_preferred":[
        "\uc11c\ub3d9\ucd0c"
    ],
    "wof:name":"Seodongchon",
    "wof:placetype":"locality"
},
  "geometry": {"coordinates":[126.83544999999999,35.31424000000001],"type":"Point"}
}