{
  "type": "Feature",
  "properties": {
    "gn:admin1_code":"13.0",
    "gn:asciiname":"Han-gak-ri",
    "gn:country_code":"KR",
    "gn:dem":14,
    "gn:feature_class":"P",
    "gn:feature_code":"PPL",
    "gn:name":"Han-gak-ri",
    "gn:population":0,
    "gn:timezone":"Asia/Seoul",
    "iso:country":"KR",
    "name:kor_x_preferred":[
        "\ud55c\uac01\ub9ac"
    ],
    "wof:name":"Han-gak-ri",
    "wof:placetype":"locality"
},
  "geometry": {"coordinates":[126.79778,37.095],"type":"Point"}
}