{
  "type": "Feature",
  "properties": {
    "gn:admin1_code":"20.0",
    "gn:asciiname":"Kwi-dong",
    "gn:country_code":"KR",
    "gn:dem":32,
    "gn:feature_class":"P",
    "gn:feature_code":"PPL",
    "gn:name":"Kwi-dong",
    "gn:population":0,
    "gn:timezone":"Asia/Seoul",
    "iso:country":"KR",
    "name:und_x_variant":[
        "\uadc0\ub3d9",
        "Kwi-dong"
    ],
    "wof:name":"Kwi-dong",
    "wof:placetype":"locality"
},
  "geometry": {"coordinates":[128.47087999999999,35.54565],"type":"Point"}
}