{
  "type": "Feature",
  "properties": {
    "gn:admin1_code":"16.0",
    "gn:asciiname":"Chukch'on",
    "gn:country_code":"KR",
    "gn:dem":13,
    "gn:feature_class":"P",
    "gn:feature_code":"PPL",
    "gn:name":"Chukch\u2019\u014fn",
    "gn:population":0,
    "gn:timezone":"Asia/Seoul",
    "iso:country":"KR",
    "name:kor_x_preferred":[
        "\uc8fd\ucc9c"
    ],
    "name:kor_x_variant":[
        "Chukch\u2019\u014fn"
    ],
    "wof:name":"Chukch'on",
    "wof:placetype":"locality"
},
  "geometry": {"coordinates":[127.23915,34.57938],"type":"Point"}
}