{
  "type": "Feature",
  "properties": {
    "gn:admin1_code":"14.0",
    "gn:asciiname":"T'aebong",
    "gn:country_code":"KR",
    "gn:dem":21,
    "gn:feature_class":"P",
    "gn:feature_code":"PPL",
    "gn:name":"T\u2019aebong",
    "gn:population":0,
    "gn:timezone":"Asia/Seoul",
    "iso:country":"KR",
    "name:und_x_variant":[
        "\ud0dc\ubd09",
        "T\u2019aebong-dong",
        "T\u2019aebong"
    ],
    "wof:name":"T'aebong",
    "wof:placetype":"locality"
},
  "geometry": {"coordinates":[129.3586,37.1314],"type":"Point"}
}