{
  "type": "Feature",
  "properties": {
    "gn:admin1_code":"5.0",
    "gn:asciiname":"Pyeongjeonmal",
    "gn:country_code":"KR",
    "gn:dem":40,
    "gn:feature_class":"P",
    "gn:feature_code":"PPL",
    "gn:name":"Pyeongjeonmal",
    "gn:population":0,
    "gn:timezone":"Asia/Seoul",
    "iso:country":"KR",
    "name:kor_x_preferred":[
        "\ud3c9\uc804\ub9d0"
    ],
    "wof:name":"Pyeongjeonmal",
    "wof:placetype":"locality"
},
  "geometry": {"coordinates":[127.44908999999998,36.45759],"type":"Point"}
}