{
  "type": "Feature",
  "properties": {
    "gn:admin1_code":"3.0",
    "gn:asciiname":"T'ongjong-ni",
    "gn:country_code":"KR",
    "gn:dem":14,
    "gn:feature_class":"P",
    "gn:feature_code":"PPL",
    "gn:name":"T\u2019ongj\u014fng-ni",
    "gn:population":0,
    "gn:timezone":"Asia/Seoul",
    "iso:country":"KR",
    "name:eng_x_preferred":[
        "T'ongjong"
    ],
    "name:eng_x_variant":[
        "T'ongjong-ni"
    ],
    "wof:name":"T'ongjong",
    "wof:placetype":"locality"
},
  "geometry": {"coordinates":[126.65582999999999,35.70694],"type":"Point"}
}