{
  "type": "Feature",
  "properties": {
    "gn:admin1_code":"17.0",
    "gn:asciiname":"Sinsol-tong",
    "gn:country_code":"KR",
    "gn:dem":17,
    "gn:feature_class":"P",
    "gn:feature_code":"PPL",
    "gn:name":"Sins\u014fl-tong",
    "gn:population":0,
    "gn:timezone":"Asia/Seoul",
    "iso:country":"KR",
    "name:und_x_variant":[
        "\uc2e0\uc124\ub3d9",
        "Sins\u014fl-tong"
    ],
    "wof:name":"Sinsol-tong",
    "wof:placetype":"locality"
},
  "geometry": {"coordinates":[126.3471,36.5816],"type":"Point"}
}