{
  "type": "Feature",
  "properties": {
    "gn:admin1_code":"11.0",
    "gn:asciiname":"Muak-tong",
    "gn:country_code":"KR",
    "gn:dem":139,
    "gn:feature_class":"P",
    "gn:feature_code":"PPL",
    "gn:name":"Muak-tong",
    "gn:population":0,
    "gn:timezone":"Asia/Seoul",
    "iso:country":"KR",
    "name:eng_x_preferred":[
        "Muak"
    ],
    "name:eng_x_variant":[
        "Muak-tong"
    ],
    "name:und_x_variant":[
        "\ubb34\uc545\ub3d9",
        "Muak-tong"
    ],
    "wof:name":"Muak",
    "wof:placetype":"locality"
},
  "geometry": {"coordinates":[126.95868,37.57816],"type":"Point"}
}