{
  "type": "Feature",
  "properties": {
    "gn:admin1_code":"6.0",
    "gn:asciiname":"Nuptunji",
    "gn:country_code":"KR",
    "gn:dem":92,
    "gn:feature_class":"P",
    "gn:feature_code":"PPL",
    "gn:name":"N\u016dptunji",
    "gn:population":0,
    "gn:timezone":"Asia/Seoul",
    "iso:country":"KR",
    "name:kor_x_preferred":[
        "\ub2aa\ub454\uc9c0"
    ],
    "name:kor_x_variant":[
        "N\u016dptunji"
    ],
    "wof:name":"Nuptunji",
    "wof:placetype":"locality"
},
  "geometry": {"coordinates":[127.6883,37.6888],"type":"Point"}
}