{
  "type": "Feature",
  "properties": {
    "iso:country":"KR",
    "name:eng_x_preferred":[
        "Jungmun-dong"
    ],
    "name:kor_x_preferred":[
        "\uc911\ubb38\ub3d9"
    ],
    "qs:name":"\uc911\ubb38\ub3d9",
    "qs:name_adm0":"\ud55c\uad6d",
    "qs:name_adm1":"\uc81c\uc8fc\ud2b9\ubcc4\uc790\uce58\ub3c4",
    "qs:photos":152,
    "qs:photos_1k":31,
    "qs:photos_9k":1,
    "qs:photos_9r":4,
    "qs:photos_all":152,
    "qs:photos_sr":4,
    "qs:placetype":"LocalAdmin",
    "qs:pop_sr":"0",
    "wof:name":"Jungmun-dong",
    "wof:placetype":"localadmin"
},
  "geometry": {"coordinates":[126.44989,33.249598],"type":"Point"}
}