{
  "type": "Feature",
  "properties": {
    "iso:country":"KR",
    "name:eng_x_preferred":[
        "Munsan-eup"
    ],
    "name:kor_x_preferred":[
        "\ubb38\uc0b0\uc74d"
    ],
    "qs:name":"\ubb38\uc0b0\uc74d",
    "qs:name_adm0":"\ud55c\uad6d",
    "qs:name_adm1":"\uacbd\uae30\ub3c4",
    "qs:photos":570,
    "qs:photos_1k":116,
    "qs:photos_9k":3,
    "qs:photos_9r":5,
    "qs:photos_all":570,
    "qs:photos_sr":8,
    "qs:placetype":"LocalAdmin",
    "qs:pop_sr":"0",
    "wof:name":"Munsan-eup",
    "wof:placetype":"localadmin"
},
  "geometry": {"coordinates":[126.740092,37.890149],"type":"Point"}
}