{
  "type": "Feature",
  "properties": {
    "iso:country":"KR",
    "qs:name":"\ubb38\uc0b0\uc74d",
    "qs:name_adm0":"\ud55c\uad6d",
    "qs:name_adm1":"\uacbd\uae30\ub3c4",
    "qs:photos":570,
    "qs:photos_1k":116,
    "qs:photos_9k":3,
    "qs:photos_9r":5,
    "qs:photos_all":570,
    "qs:photos_sr":8,
    "qs:placetype":"LocalAdmin",
    "qs:pop_sr":"0",
    "wof:name":"\ubb38\uc0b0\uc74d",
    "wof:placetype":"localadmin"
},
  "geometry": {"coordinates":[126.74009249999999,37.8901495],"type":"Point"}
}