{
  "type": "Feature",
  "properties": {
    "gn:country":"KR",
    "gn:fcode":"PPL",
    "gn:pop":0,
    "iso:country":"KR",
    "qs:name":"\ud0c4\ubc29\ub3d9",
    "qs:name_adm0":"\ud55c\uad6d",
    "qs:name_adm1":"\ub300\uc804",
    "qs:photos":47,
    "qs:photos_1k":10,
    "qs:photos_9k":1,
    "qs:photos_9r":2,
    "qs:photos_all":47,
    "qs:photos_sr":2,
    "qs:placetype":"Suburb",
    "qs:pop_sr":"0",
    "wof:name":"\ud0c4\ubc29\ub3d9",
    "wof:placetype":"neighbourhood",
    "wof:population":0
},
  "geometry": {"coordinates":[127.47028,35.92806],"type":"Point"}
}