{
  "type": "Feature",
  "properties": {
    "gn:admin1_code":"6.0",
    "gn:asciiname":"Hwadongp'o",
    "gn:country_code":"KR",
    "gn:dem":85,
    "gn:feature_class":"P",
    "gn:feature_code":"PPL",
    "gn:name":"Hwadongp\u2019o",
    "gn:population":0,
    "gn:timezone":"Asia/Seoul",
    "iso:country":"KR",
    "name:kor_x_preferred":[
        "\ud654\ub3d9\ud3ec"
    ],
    "name:kor_x_variant":[
        "Hwadongp\u2019o"
    ],
    "wof:name":"Hwadongp'o",
    "wof:placetype":"locality"
},
  "geometry": {"coordinates":[128.73169999999999,37.9261],"type":"Point"}
}