{
  "type": "Feature",
  "properties": {
    "gn:admin1_code":"6.0",
    "gn:asciiname":"Seongha",
    "gn:country_code":"KR",
    "gn:dem":104,
    "gn:feature_class":"P",
    "gn:feature_code":"PPL",
    "gn:name":"Seongha",
    "gn:population":0,
    "gn:timezone":"Asia/Seoul",
    "iso:country":"KR",
    "name:kor_x_preferred":[
        "\uc131\ud558"
    ],
    "name:kor_x_variant":[
        "S\u014fngha"
    ],
    "wof:name":"Seongha",
    "wof:placetype":"locality"
},
  "geometry": {"coordinates":[128.84963999999999,37.7483],"type":"Point"}
}