{
  "type": "Feature",
  "properties": {
    "gn:admin1_code":"17.0",
    "gn:asciiname":"Summit",
    "gn:country_code":"KR",
    "gn:dem":23,
    "gn:feature_class":"P",
    "gn:feature_code":"PPL",
    "gn:name":"Summit",
    "gn:population":0,
    "gn:timezone":"Asia/Seoul",
    "iso:country":"KR",
    "name:und_x_variant":[
        "\uc232\ubc11",
        "Summit"
    ],
    "wof:name":"Summit",
    "wof:placetype":"locality"
},
  "geometry": {"coordinates":[127.005,36.3498],"type":"Point"}
}