{
  "type": "Feature",
  "properties": {
    "gn:admin1_code":"6.0",
    "gn:asciiname":"Garogae",
    "gn:country_code":"KR",
    "gn:dem":273,
    "gn:feature_class":"P",
    "gn:feature_code":"PPL",
    "gn:name":"Garogae",
    "gn:population":0,
    "gn:timezone":"Asia/Seoul",
    "iso:country":"KR",
    "name:kor_x_preferred":[
        "\uac00\ub85c\uac1c"
    ],
    "name:und_x_variant":[
        "Karhy\u014f-dong",
        "Karugae",
        "Karogae",
        "Garogae"
    ],
    "wof:name":"Garogae",
    "wof:placetype":"locality"
},
  "geometry": {"coordinates":[127.33802,38.20206],"type":"Point"}
}