{
  "type": "Feature",
  "properties": {
    "gn:admin1_code":"19.0",
    "gn:asciiname":"Anjinbawi",
    "gn:country_code":"KR",
    "gn:dem":105,
    "gn:feature_class":"P",
    "gn:feature_code":"PPL",
    "gn:name":"Anjinbawi",
    "gn:population":0,
    "gn:timezone":"Asia/Seoul",
    "iso:country":"KR",
    "name:und_x_variant":[
        "\uc548\uc9c4\ubc14\uc704",
        "Anjinbawi"
    ],
    "wof:name":"Anjinbawi",
    "wof:placetype":"locality"
},
  "geometry": {"coordinates":[127.28904,36.36215],"type":"Point"}
}