{
  "type": "Feature",
  "properties": {
    "gn:admin1_code":"12.0",
    "gn:asciiname":"Boepjangdong",
    "gn:country_code":"KR",
    "gn:dem":12,
    "gn:feature_class":"P",
    "gn:feature_code":"PPL",
    "gn:name":"Boepjangdong",
    "gn:population":0,
    "gn:timezone":"Asia/Seoul",
    "iso:country":"KR",
    "name:kor_x_preferred":[
        "\ubc95\uc7a5\ub3d9"
    ],
    "wof:name":"Boepjangdong",
    "wof:placetype":"locality"
},
  "geometry": {"coordinates":[126.32407000000001,37.79077],"type":"Point"}
}