{
  "type": "Feature",
  "properties": {
    "gn:admin1_code":"17.0",
    "gn:asciiname":"Changmaru",
    "gn:country_code":"KR",
    "gn:dem":30,
    "gn:feature_class":"P",
    "gn:feature_code":"PPL",
    "gn:name":"Changmaru",
    "gn:population":0,
    "gn:timezone":"Asia/Seoul",
    "iso:country":"KR",
    "name:und_x_variant":[
        "\uc7a5\ub9c8\ub8e8",
        "Changmaru"
    ],
    "wof:name":"Changmaru",
    "wof:placetype":"locality"
},
  "geometry": {"coordinates":[127.0783,36.2984],"type":"Point"}
}