{
  "type": "Feature",
  "properties": {
    "gn:admin1_code":"3.0",
    "gn:asciiname":"T'apchon",
    "gn:country_code":"KR",
    "gn:dem":144,
    "gn:feature_class":"P",
    "gn:feature_code":"PPL",
    "gn:name":"T\u2019apch\u014fn",
    "gn:population":0,
    "gn:timezone":"Asia/Seoul",
    "iso:country":"KR",
    "name:und_x_variant":[
        "T\u2019apch\u014fn-ni",
        "\ud0d1\uc804",
        "T\u2019apch\u014fn",
        "Tapjeon"
    ],
    "wof:name":"T'apchon",
    "wof:placetype":"locality"
},
  "geometry": {"coordinates":[127.27641,35.50789],"type":"Point"}
}