{
  "type": "Feature",
  "properties": {
    "gn:admin1_code":"3.0",
    "gn:asciiname":"Tuhyon",
    "gn:country_code":"KR",
    "gn:dem":49,
    "gn:feature_class":"P",
    "gn:feature_code":"PPL",
    "gn:name":"Tuhy\u014fn",
    "gn:population":0,
    "gn:timezone":"Asia/Seoul",
    "iso:country":"KR",
    "name:und_x_variant":[
        "\ub450\ud604",
        "Tuhy\u014fn"
    ],
    "wof:name":"Tuhyon",
    "wof:placetype":"locality"
},
  "geometry": {"coordinates":[127.12264999999999,35.74444000000001],"type":"Point"}
}