{
  "type": "Feature",
  "properties": {
    "gn:admin1_code":"17.0",
    "gn:asciiname":"Dongmalgol",
    "gn:country_code":"KR",
    "gn:dem":142,
    "gn:feature_class":"P",
    "gn:feature_code":"PPL",
    "gn:name":"Dongmalgol",
    "gn:population":0,
    "gn:timezone":"Asia/Seoul",
    "iso:country":"KR",
    "name:kor_x_preferred":[
        "\ub3d9\ub9d0\uace8"
    ],
    "wof:name":"Dongmalgol",
    "wof:placetype":"locality"
},
  "geometry": {"coordinates":[127.0252,36.71456],"type":"Point"}
}