{
  "type": "Feature",
  "properties": {
    "gn:admin1_code":"5.0",
    "gn:asciiname":"Cheonyangchon",
    "gn:country_code":"KR",
    "gn:dem":131,
    "gn:feature_class":"P",
    "gn:feature_code":"PPL",
    "gn:name":"Cheonyangchon",
    "gn:population":0,
    "gn:timezone":"Asia/Seoul",
    "iso:country":"KR",
    "name:kor_x_preferred":[
        "\ucc9c\uc591\ucd0c"
    ],
    "wof:name":"Cheonyangchon",
    "wof:placetype":"locality"
},
  "geometry": {"coordinates":[127.59246,36.97569],"type":"Point"}
}