{
  "type": "Feature",
  "properties": {
    "gn:admin1_code":"17.0",
    "gn:asciiname":"Paron",
    "gn:country_code":"KR",
    "gn:dem":174,
    "gn:feature_class":"P",
    "gn:feature_code":"PPL",
    "gn:name":"Paron",
    "gn:population":0,
    "gn:timezone":"Asia/Seoul",
    "iso:country":"KR",
    "name:ceb_x_preferred":[
        "Paron"
    ],
    "name:fra_x_preferred":[
        "Paron"
    ],
    "name:ind_x_preferred":[
        "Paron"
    ],
    "name:nld_x_preferred":[
        "Paron"
    ],
    "name:oci_x_preferred":[
        "Paron"
    ],
    "name:pol_x_preferred":[
        "Paron"
    ],
    "name:swe_x_preferred":[
        "Paron"
    ],
    "name:und_x_variant":[
        "Paron-ni",
        "\ubc1c\uc628"
    ],
    "wof:name":"Paron",
    "wof:placetype":"locality"
},
  "geometry": {"coordinates":[126.78870000000001,36.3601],"type":"Point"}
}