{
  "type": "Feature",
  "properties": {
    "gn:admin1_code":"20.0",
    "gn:asciiname":"Sangdu",
    "gn:country_code":"KR",
    "gn:dem":30,
    "gn:feature_class":"P",
    "gn:feature_code":"PPL",
    "gn:name":"Sangdu",
    "gn:population":0,
    "gn:timezone":"Asia/Seoul",
    "iso:country":"KR",
    "name:und_x_variant":[
        "\uc0c1\ub450",
        "Sangdu"
    ],
    "wof:name":"Sangdu",
    "wof:placetype":"locality"
},
  "geometry": {"coordinates":[128.39986000000002,35.40255],"type":"Point"}
}