{
  "type": "Feature",
  "properties": {
    "gn:admin1_code":"18.0",
    "gn:asciiname":"Darimok",
    "gn:country_code":"KR",
    "gn:dem":136,
    "gn:feature_class":"P",
    "gn:feature_code":"PPL",
    "gn:name":"Darimok",
    "gn:population":0,
    "gn:timezone":"Asia/Seoul",
    "iso:country":"KR",
    "name:kor_x_preferred":[
        "\ub2e4\ub9ac\ubaa9"
    ],
    "wof:name":"Darimok",
    "wof:placetype":"locality"
},
  "geometry": {"coordinates":[126.95166,35.09056],"type":"Point"}
}