{
  "type": "Feature",
  "properties": {
    "gn:admin1_code":"13.0",
    "gn:asciiname":"Sangyeolmi",
    "gn:country_code":"KR",
    "gn:dem":245,
    "gn:feature_class":"P",
    "gn:feature_code":"PPL",
    "gn:name":"Sangyeolmi",
    "gn:population":0,
    "gn:timezone":"Asia/Seoul",
    "iso:country":"KR",
    "name:und_x_variant":[
        "\uc0c1\uc5f4\ubbf8",
        "Sangyeolmi",
        "Sangy\u014flmi"
    ],
    "wof:name":"Sangyeolmi",
    "wof:placetype":"locality"
},
  "geometry": {"coordinates":[127.35861,37.39389],"type":"Point"}
}