{
  "type": "Feature",
  "properties": {
    "gn:admin1_code":"16.0",
    "gn:asciiname":"Janggok",
    "gn:country_code":"KR",
    "gn:dem":92,
    "gn:feature_class":"P",
    "gn:feature_code":"PPL",
    "gn:name":"Janggok",
    "gn:population":0,
    "gn:timezone":"Asia/Seoul",
    "iso:country":"KR",
    "name:kor_x_preferred":[
        "\uc7a5\uace1"
    ],
    "wof:name":"Janggok",
    "wof:placetype":"locality"
},
  "geometry": {"coordinates":[126.92402,34.95718],"type":"Point"}
}