{
  "type": "Feature",
  "properties": {
    "gn:admin1_code":"13.0",
    "gn:asciiname":"Araejajingae",
    "gn:country_code":"KR",
    "gn:dem":48,
    "gn:feature_class":"P",
    "gn:feature_code":"PPL",
    "gn:name":"Araejajingae",
    "gn:population":0,
    "gn:timezone":"Asia/Seoul",
    "iso:country":"KR",
    "name:und_x_variant":[
        "\uc544\ub798\uc790\uc9c4\uac1c",
        "Araejajingae",
        "Araejajin\u2019gae"
    ],
    "wof:name":"Araejajingae",
    "wof:placetype":"locality"
},
  "geometry": {"coordinates":[127.54028,37.42833],"type":"Point"}
}