{
  "type": "Feature",
  "properties": {
    "gn:admin1_code":"21.0",
    "gn:asciiname":"Neunggol",
    "gn:country_code":"KR",
    "gn:dem":87,
    "gn:feature_class":"P",
    "gn:feature_code":"PPL",
    "gn:name":"Neunggol",
    "gn:population":0,
    "gn:timezone":"Asia/Seoul",
    "iso:country":"KR",
    "name:kor_x_preferred":[
        "\ub2a5\uace8"
    ],
    "wof:name":"Neunggol",
    "wof:placetype":"locality"
},
  "geometry": {"coordinates":[129.12228000000002,35.58094000000001],"type":"Point"}
}