{
  "type": "Feature",
  "properties": {
    "gn:admin1_code":"11.0",
    "gn:asciiname":"Pulgwang-dong",
    "gn:country_code":"KR",
    "gn:dem":75,
    "gn:feature_class":"P",
    "gn:feature_code":"PPL",
    "gn:name":"Pulgwang-dong",
    "gn:population":0,
    "gn:timezone":"Asia/Seoul",
    "iso:country":"KR",
    "name:und_x_variant":[
        "\ubd88\uad11\ub3d9",
        "Pulgwang-dong"
    ],
    "wof:name":"Pulgwang-dong",
    "wof:placetype":"locality"
},
  "geometry": {"coordinates":[126.92319999999999,37.6252],"type":"Point"}
}