{
  "type": "Feature",
  "properties": {
    "gn:admin1_code":"5.0",
    "gn:asciiname":"Deokdong",
    "gn:country_code":"KR",
    "gn:dem":129,
    "gn:feature_class":"P",
    "gn:feature_code":"PPL",
    "gn:name":"Deokdong",
    "gn:population":0,
    "gn:timezone":"Asia/Seoul",
    "iso:country":"KR",
    "name:kor_x_preferred":[
        "\ub355\ub3d9"
    ],
    "name:kor_x_variant":[
        "T\u014fk-tong"
    ],
    "wof:name":"Deokdong",
    "wof:placetype":"locality"
},
  "geometry": {"coordinates":[127.57205999999999,37.00777],"type":"Point"}
}