{
  "type": "Feature",
  "properties": {
    "gn:admin1_code":"19.0",
    "gn:asciiname":"Wonsajongi",
    "gn:cc2":"KR",
    "gn:country_code":"KR",
    "gn:dem":170,
    "gn:feature_class":"P",
    "gn:feature_code":"PPL",
    "gn:name":"W\u014fnsaj\u014fngi",
    "gn:population":0,
    "gn:timezone":"Asia/Seoul",
    "iso:country":"KR",
    "name:und_x_variant":[
        "Saj\u014fn-ni",
        "Saj\u014fng-ni",
        "W\u014fnsaj\u014fngi"
    ],
    "wof:name":"Wonsajongi",
    "wof:placetype":"locality"
},
  "geometry": {"coordinates":[127.40000000000001,36.28333],"type":"Point"}
}