{
  "type": "Feature",
  "properties": {
    "gn:admin1_code":"16.0",
    "gn:asciiname":"Chap'ung-ni",
    "gn:country_code":"KR",
    "gn:dem":34,
    "gn:feature_class":"P",
    "gn:feature_code":"PPL",
    "gn:name":"Chap\u2019ung-ni",
    "gn:population":0,
    "gn:timezone":"Asia/Seoul",
    "iso:country":"KR",
    "name:eng_x_preferred":[
        "Chap'ung"
    ],
    "name:eng_x_variant":[
        "Chap'ung-ni"
    ],
    "wof:name":"Chap'ung",
    "wof:placetype":"locality"
},
  "geometry": {"coordinates":[126.47638999999999,35.03556],"type":"Point"}
}