{
  "type": "Feature",
  "properties": {
    "gn:admin1_code":"3.0",
    "gn:asciiname":"Hayangam",
    "gn:country_code":"KR",
    "gn:dem":245,
    "gn:feature_class":"P",
    "gn:feature_code":"PPL",
    "gn:name":"Hayangam",
    "gn:population":0,
    "gn:timezone":"Asia/Seoul",
    "iso:country":"KR",
    "name:und_x_variant":[
        "\ud558\uc591\uc554",
        "Hayangam"
    ],
    "wof:name":"Hayangam",
    "wof:placetype":"locality"
},
  "geometry": {"coordinates":[127.35306,35.63732],"type":"Point"}
}