{
  "type": "Feature",
  "properties": {
    "gn:admin1_code":"10.0",
    "gn:asciiname":"Bolli",
    "gn:country_code":"KR",
    "gn:dem":2,
    "gn:feature_class":"P",
    "gn:feature_code":"PPL",
    "gn:name":"Bolli",
    "gn:population":0,
    "gn:timezone":"Asia/Seoul",
    "iso:country":"KR",
    "name:kor_x_preferred":[
        "\ubcf8\ub9ac"
    ],
    "wof:name":"Bolli",
    "wof:placetype":"locality"
},
  "geometry": {"coordinates":[128.95813000000001,35.17432],"type":"Point"}
}