{
  "type": "Feature",
  "properties": {
    "gn:admin1_code":"13.0",
    "gn:asciiname":"Solmi",
    "gn:country_code":"KR",
    "gn:dem":43,
    "gn:feature_class":"P",
    "gn:feature_code":"PPL",
    "gn:name":"Solmi",
    "gn:population":0,
    "gn:timezone":"Asia/Seoul",
    "iso:country":"KR",
    "name:und_x_variant":[
        "\uc194\ubbf8",
        "Solmi"
    ],
    "wof:name":"Solmi",
    "wof:placetype":"locality"
},
  "geometry": {"coordinates":[126.94889000000001,37.08833],"type":"Point"}
}