{
  "type": "Feature",
  "properties": {
    "gn:admin1_code":"11.0",
    "gn:asciiname":"Sinsu-dong",
    "gn:country_code":"KR",
    "gn:dem":19,
    "gn:feature_class":"P",
    "gn:feature_code":"PPL",
    "gn:name":"Sinsu-dong",
    "gn:population":0,
    "gn:timezone":"Asia/Seoul",
    "iso:country":"KR",
    "name:ceb_x_preferred":[
        "Sinsu-dong"
    ],
    "name:fas_x_preferred":[
        "\u0633\u06cc\u0646\u0633\u0648-\u062f\u0648\u0646\u06af"
    ],
    "name:kor_x_preferred":[
        "\uc2e0\uc218\ub3d9"
    ],
    "name:msa_x_preferred":[
        "Sinsu-dong"
    ],
    "name:swe_x_preferred":[
        "Sinsu-dong"
    ],
    "name:vie_x_preferred":[
        "Sinsu-dong"
    ],
    "wof:name":"Sinsu-dong",
    "wof:placetype":"locality"
},
  "geometry": {"coordinates":[126.93568,37.5447],"type":"Point"}
}