{
  "type": "Feature",
  "properties": {
    "gn:admin1_code":"11.0",
    "gn:asciiname":"Sinsu-dong",
    "gn:country_code":"KR",
    "gn:dem":19,
    "gn:feature_class":"P",
    "gn:feature_code":"PPL",
    "gn:name":"Sinsu-dong",
    "gn:population":0,
    "gn:timezone":"Asia/Seoul",
    "iso:country":"KR",
    "name:und_x_variant":[
        "\uc2e0\uc218\ub3d9",
        "Sinsu-dong"
    ],
    "wof:name":"Sinsu-dong",
    "wof:placetype":"locality"
},
  "geometry": {"coordinates":[126.93568,37.5447],"type":"Point"}
}