{
  "type": "Feature",
  "properties": {
    "gn:admin1_code":"14.0",
    "gn:asciiname":"Podulbaengi",
    "gn:country_code":"KR",
    "gn:dem":265,
    "gn:feature_class":"P",
    "gn:feature_code":"PPL",
    "gn:name":"P\u014fd\u016dlbaengi",
    "gn:population":0,
    "gn:timezone":"Asia/Seoul",
    "iso:country":"KR",
    "name:und_x_variant":[
        "\ubc84\ub4e4\ubc45\uc774",
        "P\u014fd\u016dlbaengi"
    ],
    "wof:name":"Podulbaengi",
    "wof:placetype":"locality"
},
  "geometry": {"coordinates":[127.8767,36.337],"type":"Point"}
}