{
  "type": "Feature",
  "properties": {
    "gn:country":"KR",
    "gn:fcode":"PPL",
    "gn:population":56006,
    "iso:country":"KR",
    "name:und_x_variant":[
        "Y\u014fngch\u2019\u014fn"
    ],
    "qs:name":"Eisen",
    "qs:photos_9r":0,
    "qs:photos_sr":0,
    "qs:pop_sr":"8",
    "wd:wordcount":119,
    "wof:name":"Eisen",
    "wof:placetype":"locality",
    "wof:population":56006
},
  "geometry": {"coordinates":[128.93082999999999,35.9675],"type":"Point"}
}