{
  "type": "Feature",
  "properties": {
    "gn:admin1_code":"14.0",
    "gn:asciiname":"Gatjae",
    "gn:country_code":"KR",
    "gn:dem":117,
    "gn:feature_class":"P",
    "gn:feature_code":"PPL",
    "gn:name":"Gatjae",
    "gn:population":0,
    "gn:timezone":"Asia/Seoul",
    "iso:country":"KR",
    "name:kor_x_preferred":[
        "\uac13\uc7ac"
    ],
    "wof:name":"Gatjae",
    "wof:placetype":"locality"
},
  "geometry": {"coordinates":[128.50828999999999,36.66075],"type":"Point"}
}