{
  "type": "Feature",
  "properties": {
    "gn:admin1_code":"17.0",
    "gn:asciiname":"Kulmi",
    "gn:country_code":"KR",
    "gn:dem":17,
    "gn:feature_class":"P",
    "gn:feature_code":"PPL",
    "gn:name":"Kulmi",
    "gn:population":0,
    "gn:timezone":"Asia/Seoul",
    "iso:country":"KR",
    "name:und_x_variant":[
        "\uad74\ubbf8",
        "Kulmi"
    ],
    "wof:name":"Kulmi",
    "wof:placetype":"locality"
},
  "geometry": {"coordinates":[126.6024,36.8485],"type":"Point"}
}