{
  "type": "Feature",
  "properties": {
    "gn:admin1_code":"14.0",
    "gn:asciiname":"Mottudul",
    "gn:country_code":"KR",
    "gn:dem":84,
    "gn:feature_class":"P",
    "gn:feature_code":"PPL",
    "gn:name":"Mottud\u016dl",
    "gn:population":0,
    "gn:timezone":"Asia/Seoul",
    "iso:country":"KR",
    "name:und_x_variant":[
        "\ubabb\ub450\ub4e4",
        "Mottud\u016dl"
    ],
    "wof:name":"Mottudul",
    "wof:placetype":"locality"
},
  "geometry": {"coordinates":[128.31620000000001,36.1865],"type":"Point"}
}