{
  "type": "Feature",
  "properties": {
    "gn:admin1_code":"14.0",
    "gn:asciiname":"Achidong",
    "gn:country_code":"KR",
    "gn:dem":34,
    "gn:feature_class":"P",
    "gn:feature_code":"PPL",
    "gn:name":"Achidong",
    "gn:population":0,
    "gn:timezone":"Asia/Seoul",
    "iso:country":"KR",
    "name:kor_x_preferred":[
        "\uc544\uce58\ub3d9"
    ],
    "wof:name":"Achidong",
    "wof:placetype":"locality"
},
  "geometry": {"coordinates":[128.34415000000001,35.66961],"type":"Point"}
}