{
  "type": "Feature",
  "properties": {
    "gn:admin1_code":"5.0",
    "gn:asciiname":"Jungmal",
    "gn:country_code":"KR",
    "gn:dem":167,
    "gn:feature_class":"P",
    "gn:feature_code":"PPL",
    "gn:name":"Jungmal",
    "gn:population":0,
    "gn:timezone":"Asia/Seoul",
    "iso:country":"KR",
    "name:kor_x_preferred":[
        "\uc911\ub9d0"
    ],
    "name:und_x_variant":[
        "Chung-mal",
        "Jungmal"
    ],
    "wof:name":"Jungmal",
    "wof:placetype":"locality"
},
  "geometry": {"coordinates":[128.18968999999998,37.05511],"type":"Point"}
}