{
  "type": "Feature",
  "properties": {
    "iso:country":"KR",
    "name:eng_x_preferred":[
        "Bugae-dong"
    ],
    "name:kor_x_preferred":[
        "\ubd80\uac1c\ub3d9"
    ],
    "qs:gn_adm0_cc":"KR",
    "qs:gn_local":1843564,
    "qs:local_max":2394,
    "qs:local_sum":10431,
    "qs:localhoods":47,
    "qs:name":"\ubd80\uac1c\ub3d9",
    "qs:name_adm0":"\ud55c\uad6d",
    "qs:name_adm1":"\uc778\ucc9c",
    "qs:name_adm2":"\ubd80\ud3c9\uad6c",
    "qs:name_local":"\uc778\ucc9c",
    "qs:photo_max":159,
    "qs:photo_sum":182,
    "qs:placetype":"Suburb",
    "qs:quad_count":6,
    "qs:woe_adm0":23424868,
    "qs:woe_adm1":20069922,
    "qs:woe_adm2":28808957,
    "qs:woe_lau":0,
    "qs:woe_local":1132496,
    "qs:woe_ver":"7.10.0",
    "wof:lang":[
        "kor"
    ],
    "wof:name":"Bugae-dong",
    "wof:placetype":"neighbourhood"
},
  "geometry": {"coordinates":[126.761121,37.487296],"type":"Point"}
}