{
  "type": "Feature",
  "properties": {
    "gn:admin1_code":"5.0",
    "gn:asciiname":"Neupsil",
    "gn:country_code":"KR",
    "gn:dem":165,
    "gn:feature_class":"P",
    "gn:feature_code":"PPL",
    "gn:name":"Neupsil",
    "gn:population":0,
    "gn:timezone":"Asia/Seoul",
    "iso:country":"KR",
    "name:kor_x_preferred":[
        "\ub2a1\uc2e4"
    ],
    "name:kor_x_variant":[
        "N\u016dpsil"
    ],
    "wof:name":"Neupsil",
    "wof:placetype":"locality"
},
  "geometry": {"coordinates":[128.42433,37.06131],"type":"Point"}
}