{
  "type": "Feature",
  "properties": {
    "gn:admin1_code":"20.0",
    "gn:asciiname":"Bamgol",
    "gn:country_code":"KR",
    "gn:dem":20,
    "gn:feature_class":"P",
    "gn:feature_code":"PPL",
    "gn:name":"Bamgol",
    "gn:population":0,
    "gn:timezone":"Asia/Seoul",
    "iso:country":"KR",
    "name:kor_x_preferred":[
        "\ubc24\uace8"
    ],
    "wof:name":"Bamgol",
    "wof:placetype":"locality"
},
  "geometry": {"coordinates":[128.41088999999999,35.57106],"type":"Point"}
}