{
  "type": "Feature",
  "properties": {
    "gn:admin1_code":"6.0",
    "gn:admin2_code":"Samch'\u014fk-si",
    "gn:asciiname":"Ori-dong",
    "gn:country_code":"KR",
    "gn:dem":13,
    "gn:feature_class":"P",
    "gn:feature_code":"PPL",
    "gn:name":"Ori-dong",
    "gn:population":0,
    "gn:timezone":"Asia/Seoul",
    "iso:country":"KR",
    "name:und_x_variant":[
        "\uc624\ub9ac\ub3d9",
        "Si-dong"
    ],
    "wof:name":"Ori-dong",
    "wof:placetype":"locality"
},
  "geometry": {"coordinates":[129.23306000000002,37.37444],"type":"Point"}
}