{
  "type": "Feature",
  "properties": {
    "gn:admin1_code":"0.0",
    "gn:asciiname":"Simch'on-ni",
    "gn:country_code":"KR",
    "gn:dem":16,
    "gn:feature_class":"P",
    "gn:feature_code":"PPL",
    "gn:name":"Simch\u2019\u014fn-ni",
    "gn:population":0,
    "gn:timezone":"Asia/Seoul",
    "iso:country":"KR",
    "name:eng_x_preferred":[
        "Simch'on"
    ],
    "name:eng_x_variant":[
        "Simch'on-ni"
    ],
    "wof:name":"Simch'on",
    "wof:placetype":"locality"
},
  "geometry": {"coordinates":[127.90000000000001,34.85],"type":"Point"}
}