{
  "type": "Feature",
  "properties": {
    "gn:admin1_code":"17.0",
    "gn:asciiname":"Chom-ch'on",
    "gn:country_code":"KR",
    "gn:dem":111,
    "gn:feature_class":"P",
    "gn:feature_code":"PPL",
    "gn:name":"Ch\u014fm-ch\u2019on",
    "gn:population":0,
    "gn:timezone":"Asia/Seoul",
    "iso:country":"KR",
    "name:und_x_variant":[
        "\uc810\ucd0c",
        "Ch\u014fm-ch\u2019on"
    ],
    "wof:name":"Chom-ch'on",
    "wof:placetype":"locality"
},
  "geometry": {"coordinates":[126.87690000000001,36.3783],"type":"Point"}
}