{
  "type": "Feature",
  "properties": {
    "gn:admin1_code":"15.0",
    "gn:asciiname":"Gacheon",
    "gn:country_code":"KR",
    "gn:dem":48,
    "gn:feature_class":"P",
    "gn:feature_code":"PPL",
    "gn:name":"Gacheon",
    "gn:population":0,
    "gn:timezone":"Asia/Seoul",
    "iso:country":"KR",
    "name:kor_x_preferred":[
        "\uac00\ucc9c"
    ],
    "wof:name":"Gacheon",
    "wof:placetype":"locality"
},
  "geometry": {"coordinates":[128.68638999999999,35.8522],"type":"Point"}
}