{
  "type": "Feature",
  "properties": {
    "gn:admin1_code":"14.0",
    "gn:asciiname":"Muul",
    "gn:country_code":"KR",
    "gn:dem":72,
    "gn:feature_class":"P",
    "gn:feature_code":"PPL",
    "gn:name":"Mu\u016dl",
    "gn:population":0,
    "gn:timezone":"Asia/Seoul",
    "iso:country":"KR",
    "name:und_x_variant":[
        "\ubb34\uc744",
        "Mu\u016dl"
    ],
    "wof:name":"Muul",
    "wof:placetype":"locality"
},
  "geometry": {"coordinates":[128.1961,36.2615],"type":"Point"}
}