{
  "type": "Feature",
  "properties": {
    "gn:admin1_code":"14.0",
    "gn:asciiname":"Sori-gol",
    "gn:country_code":"KR",
    "gn:dem":325,
    "gn:feature_class":"P",
    "gn:feature_code":"PPL",
    "gn:name":"S\u014fri-gol",
    "gn:population":0,
    "gn:timezone":"Asia/Seoul",
    "iso:country":"KR",
    "name:und_x_variant":[
        "\uc11c\ub9ac\uace8",
        "S\u014fri-gol"
    ],
    "wof:name":"Sori-gol",
    "wof:placetype":"locality"
},
  "geometry": {"coordinates":[129.13473999999999,36.15189],"type":"Point"}
}