{
  "type": "Feature",
  "properties": {
    "gn:admin1_code":"14.0",
    "gn:asciiname":"Omangga",
    "gn:country_code":"KR",
    "gn:dem":382,
    "gn:feature_class":"P",
    "gn:feature_code":"PPL",
    "gn:name":"Omangga",
    "gn:population":0,
    "gn:timezone":"Asia/Seoul",
    "iso:country":"KR",
    "name:und_x_variant":[
        "\uc624\ub9dd\uac00",
        "Omangga"
    ],
    "wof:name":"Omangga",
    "wof:placetype":"locality"
},
  "geometry": {"coordinates":[129.01528000000002,36.22101],"type":"Point"}
}