{
  "type": "Feature",
  "properties": {
    "gn:admin1_code":"15.0",
    "gn:asciiname":"Jangtaesil",
    "gn:country_code":"KR",
    "gn:dem":32,
    "gn:feature_class":"P",
    "gn:feature_code":"PPL",
    "gn:name":"Jangtaesil",
    "gn:population":0,
    "gn:timezone":"Asia/Seoul",
    "iso:country":"KR",
    "name:kor_x_preferred":[
        "\uc7a5\ud0dc\uc2e4"
    ],
    "wof:name":"Jangtaesil",
    "wof:placetype":"locality"
},
  "geometry": {"coordinates":[128.53661,35.89699],"type":"Point"}
}