{
  "type": "Feature",
  "properties": {
    "gn:admin1_code":"14.0",
    "gn:asciiname":"Hogungda-ri",
    "gn:country_code":"KR",
    "gn:dem":322,
    "gn:feature_class":"P",
    "gn:feature_code":"PPL",
    "gn:name":"H\u014fgungda-ri",
    "gn:population":0,
    "gn:timezone":"Asia/Seoul",
    "iso:country":"KR",
    "name:und_x_variant":[
        "\ud5c8\uad81\ub2e4\ub9ac",
        "H\u014fgungda-ri"
    ],
    "wof:name":"Hogungda-ri",
    "wof:placetype":"locality"
},
  "geometry": {"coordinates":[129.17349999999999,36.6856],"type":"Point"}
}