{
  "type": "Feature",
  "properties": {
    "gn:admin1_code":"16.0",
    "gn:asciiname":"Yongdong",
    "gn:country_code":"KR",
    "gn:dem":65,
    "gn:feature_class":"P",
    "gn:feature_code":"PPL",
    "gn:name":"Y\u014fngdong",
    "gn:population":0,
    "gn:timezone":"Asia/Seoul",
    "iso:country":"KR",
    "name:kor_x_preferred":[
        "\uc601\ub3d9"
    ],
    "name:kor_x_variant":[
        "Y\u014fngdong"
    ],
    "name:und_x_variant":[
        "Eit\u014d-ri",
        "Hy\u014dto"
    ],
    "wof:name":"Yongdong",
    "wof:placetype":"locality"
},
  "geometry": {"coordinates":[126.825,34.48639],"type":"Point"}
}