{
  "type": "Feature",
  "properties": {
    "gn:admin1_code":"14.0",
    "gn:asciiname":"Udwangsil",
    "gn:country_code":"KR",
    "gn:dem":342,
    "gn:feature_class":"P",
    "gn:feature_code":"PPL",
    "gn:name":"Udwangsil",
    "gn:population":0,
    "gn:timezone":"Asia/Seoul",
    "iso:country":"KR",
    "name:und_x_variant":[
        "\uc6c3\uc655\uc2e4",
        "Udwangsil"
    ],
    "wof:name":"Udwangsil",
    "wof:placetype":"locality"
},
  "geometry": {"coordinates":[128.04349999999999,36.3347],"type":"Point"}
}