{
  "type": "Feature",
  "properties": {
    "gn:admin1_code":"14.0",
    "gn:asciiname":"Nammunbak",
    "gn:country_code":"KR",
    "gn:dem":571,
    "gn:feature_class":"P",
    "gn:feature_code":"PPL",
    "gn:name":"Nammunbak",
    "gn:population":0,
    "gn:timezone":"Asia/Seoul",
    "iso:country":"KR",
    "name:kor_x_preferred":[
        "\ub0a8\ubb38\ubc16"
    ],
    "wof:name":"Nammunbak",
    "wof:placetype":"locality"
},
  "geometry": {"coordinates":[129.04953999999998,35.8336],"type":"Point"}
}