{
  "type": "Feature",
  "properties": {
    "gn:admin1_code":"13.0",
    "gn:asciiname":"Soekkoji",
    "gn:country_code":"KR",
    "gn:dem":85,
    "gn:feature_class":"P",
    "gn:feature_code":"PPL",
    "gn:name":"Soekkoji",
    "gn:population":0,
    "gn:timezone":"Asia/Seoul",
    "iso:country":"KR",
    "name:kor_x_preferred":[
        "\uc1e0\uaf2c\uc9c0"
    ],
    "wof:name":"Soekkoji",
    "wof:placetype":"locality"
},
  "geometry": {"coordinates":[127.6323,37.23234],"type":"Point"}
}