{
  "type": "Feature",
  "properties": {
    "iso:country":"KR",
    "name:ceb_x_preferred":[
        "Chunyang-myeon"
    ],
    "name:kor_x_preferred":[
        "\ucd98\uc591\uba74"
    ],
    "qs:name":"\ucd98\uc591\uba74",
    "qs:name_adm0":"\ud55c\uad6d",
    "qs:name_adm1":"\uc804\ub77c\ub0a8\ub3c4",
    "qs:photos":49,
    "qs:photos_1k":10,
    "qs:photos_9k":1,
    "qs:photos_9r":2,
    "qs:photos_all":49,
    "qs:photos_sr":2,
    "qs:placetype":"LocalAdmin",
    "qs:pop_sr":"0",
    "wd:wordcount":156,
    "wof:name":"\ucd98\uc591\uba74",
    "wof:placetype":"localadmin"
},
  "geometry": {"coordinates":[127.08435,35.086203],"type":"Point"}
}