{
  "type": "Feature",
  "properties": {
    "gn:admin1_code":"13.0",
    "gn:asciiname":"Chuja-ri",
    "gn:country_code":"KR",
    "gn:dem":110,
    "gn:feature_class":"P",
    "gn:feature_code":"PPLL",
    "gn:name":"Chuja-ri",
    "gn:population":0,
    "gn:timezone":"Asia/Seoul",
    "iso:country":"KR",
    "name:und_x_variant":[
        "Ch\u2019ujang-ni",
        "\ucd94\uc790\ub9ac",
        "Chuja-ri",
        "Ch\u2019uja-ri"
    ],
    "wof:name":"Chuja-ri",
    "wof:placetype":"locality"
},
  "geometry": {"coordinates":[127.21306,37.36194],"type":"Point"}
}