{
  "type": "Feature",
  "properties": {
    "gn:admin1_code":"17.0",
    "gn:asciiname":"Kwal-li",
    "gn:cc2":"KR",
    "gn:country_code":"KR",
    "gn:dem":32,
    "gn:feature_class":"P",
    "gn:feature_code":"PPL",
    "gn:name":"Kwal-li",
    "gn:population":0,
    "gn:timezone":"Asia/Seoul",
    "iso:country":"KR",
    "name:und_x_variant":[
        "Kwan-dong",
        "Kwan-ni",
        "Kwal-li"
    ],
    "wof:name":"Kwal-li",
    "wof:placetype":"locality"
},
  "geometry": {"coordinates":[126.62027999999999,36.105],"type":"Point"}
}