{
  "type": "Feature",
  "properties": {
    "gn:admin1_code":"17.0",
    "gn:asciiname":"Kkoppak-kol",
    "gn:country_code":"KR",
    "gn:dem":58,
    "gn:feature_class":"P",
    "gn:feature_code":"PPL",
    "gn:name":"Kkoppak-kol",
    "gn:population":0,
    "gn:timezone":"Asia/Seoul",
    "iso:country":"KR",
    "name:und_x_variant":[
        "\uaf43\ubc2d\uace8",
        "Kkoppak-kol"
    ],
    "wof:name":"Kkoppak-kol",
    "wof:placetype":"locality"
},
  "geometry": {"coordinates":[126.6801,36.4921],"type":"Point"}
}