{
  "type": "Feature",
  "properties": {
    "gn:admin1_code":"12.0",
    "gn:asciiname":"Anmal",
    "gn:country_code":"KR",
    "gn:dem":18,
    "gn:feature_class":"P",
    "gn:feature_code":"PPL",
    "gn:name":"Anmal",
    "gn:population":0,
    "gn:timezone":"Asia/Seoul",
    "iso:country":"KR",
    "name:und_x_variant":[
        "\u016cnhaeng-mal",
        "\u016cnhaeng-ni",
        "\uc548\ub9d0",
        "Anmal"
    ],
    "wof:name":"Anmal",
    "wof:placetype":"locality"
},
  "geometry": {"coordinates":[126.17722000000001,37.67417],"type":"Point"}
}