{
  "type": "Feature",
  "properties": {
    "gn:admin1_code":"16.0",
    "gn:asciiname":"Waryongdong",
    "gn:country_code":"KR",
    "gn:dem":93,
    "gn:feature_class":"P",
    "gn:feature_code":"PPL",
    "gn:name":"Waryongdong",
    "gn:population":0,
    "gn:timezone":"Asia/Seoul",
    "iso:country":"KR",
    "name:kor_x_preferred":[
        "\uc640\ub8e1\ub3d9"
    ],
    "wof:name":"Waryongdong",
    "wof:placetype":"locality"
},
  "geometry": {"coordinates":[126.91922,35.31248],"type":"Point"}
}