{
  "type": "Feature",
  "properties": {
    "gn:admin1_code":"17.0",
    "gn:asciiname":"Kun'gok",
    "gn:country_code":"KR",
    "gn:dem":37,
    "gn:feature_class":"P",
    "gn:feature_code":"PPL",
    "gn:name":"Kun\u2019gok",
    "gn:population":0,
    "gn:timezone":"Asia/Seoul",
    "iso:country":"KR",
    "name:und_x_variant":[
        "\uad70\uace1",
        "Kun\u2019gok"
    ],
    "wof:name":"Kun'gok",
    "wof:placetype":"locality"
},
  "geometry": {"coordinates":[126.6925,36.7478],"type":"Point"}
}