{
  "type": "Feature",
  "properties": {
    "gn:admin1_code":"14.0",
    "gn:asciiname":"Naesonmi",
    "gn:country_code":"KR",
    "gn:dem":134,
    "gn:feature_class":"P",
    "gn:feature_code":"PPL",
    "gn:name":"Naes\u014fnmi",
    "gn:population":0,
    "gn:timezone":"Asia/Seoul",
    "iso:country":"KR",
    "name:und_x_variant":[
        "\ub0b4\uc120\ubbf8",
        "Naes\u014fnmi"
    ],
    "wof:name":"Naesonmi",
    "wof:placetype":"locality"
},
  "geometry": {"coordinates":[129.33709999999999,36.7506],"type":"Point"}
}