{
  "type": "Feature",
  "properties": {
    "gn:admin1_code":"5.0",
    "gn:asciiname":"Jungteomal",
    "gn:country_code":"KR",
    "gn:dem":114,
    "gn:feature_class":"P",
    "gn:feature_code":"PPL",
    "gn:name":"Jungteomal",
    "gn:population":0,
    "gn:timezone":"Asia/Seoul",
    "iso:country":"KR",
    "name:kor_x_preferred":[
        "\uc911\ud130\ub9d0"
    ],
    "wof:name":"Jungteomal",
    "wof:placetype":"locality"
},
  "geometry": {"coordinates":[127.54512,37.00155],"type":"Point"}
}