{
  "type": "Feature",
  "properties": {
    "gn:admin1_code":"17.0",
    "gn:asciiname":"Hyanggyo-mal",
    "gn:country_code":"KR",
    "gn:dem":62,
    "gn:feature_class":"P",
    "gn:feature_code":"PPL",
    "gn:name":"Hyanggyo-mal",
    "gn:population":0,
    "gn:timezone":"Asia/Seoul",
    "iso:country":"KR",
    "name:und_x_variant":[
        "\ud5a5\uad50\ub9d0",
        "Hyanggyo-mal"
    ],
    "wof:name":"Hyanggyo-mal",
    "wof:placetype":"locality"
},
  "geometry": {"coordinates":[126.78230000000001,36.6099],"type":"Point"}
}