{
  "type": "Feature",
  "properties": {
    "gn:admin1_code":"14.0",
    "gn:asciiname":"Eumjima",
    "gn:country_code":"KR",
    "gn:dem":327,
    "gn:feature_class":"P",
    "gn:feature_code":"PPL",
    "gn:name":"Eumjima",
    "gn:population":0,
    "gn:timezone":"Asia/Seoul",
    "iso:country":"KR",
    "name:kor_x_preferred":[
        "\uc74c\uc9c0\ub9c8"
    ],
    "wof:name":"Eumjima",
    "wof:placetype":"locality"
},
  "geometry": {"coordinates":[128.71646000000001,36.97605],"type":"Point"}
}