{
  "type": "Feature",
  "properties": {
    "gn:admin1_code":"17.0",
    "gn:asciiname":"Daesil",
    "gn:country_code":"KR",
    "gn:dem":52,
    "gn:feature_class":"P",
    "gn:feature_code":"PPL",
    "gn:name":"Daesil",
    "gn:population":0,
    "gn:timezone":"Asia/Seoul",
    "iso:country":"KR",
    "name:und_x_variant":[
        "Sanj\u014fng-ni",
        "\ub300\uc2e4",
        "Taesil",
        "Daesil"
    ],
    "wof:name":"Daesil",
    "wof:placetype":"locality"
},
  "geometry": {"coordinates":[126.88081,36.65398],"type":"Point"}
}