{
  "type": "Feature",
  "properties": {
    "gn:admin1_code":"17.0",
    "gn:asciiname":"Chusil",
    "gn:country_code":"KR",
    "gn:dem":28,
    "gn:feature_class":"P",
    "gn:feature_code":"PPL",
    "gn:name":"Ch\u016dsil",
    "gn:population":0,
    "gn:timezone":"Asia/Seoul",
    "iso:country":"KR",
    "name:und_x_variant":[
        "\uc988\uc2e4",
        "Ch\u016dsil"
    ],
    "wof:name":"Chusil",
    "wof:placetype":"locality"
},
  "geometry": {"coordinates":[126.8451,36.3192],"type":"Point"}
}