{
  "type": "Feature",
  "properties": {
    "gn:admin1_code":"18.0",
    "gn:asciiname":"Dodeok",
    "gn:country_code":"KR",
    "gn:dem":29,
    "gn:feature_class":"P",
    "gn:feature_code":"PPL",
    "gn:name":"Dodeok",
    "gn:population":0,
    "gn:timezone":"Asia/Seoul",
    "iso:country":"KR",
    "name:kor_x_preferred":[
        "\ub3c4\ub355"
    ],
    "wof:name":"Dodeok",
    "wof:placetype":"locality"
},
  "geometry": {"coordinates":[126.70208,35.16252],"type":"Point"}
}