{
  "type": "Feature",
  "properties": {
    "gn:admin1_code":"14.0",
    "gn:asciiname":"Naesongsan",
    "gn:country_code":"KR",
    "gn:dem":46,
    "gn:feature_class":"P",
    "gn:feature_code":"PPL",
    "gn:name":"Naes\u014fngsan",
    "gn:population":0,
    "gn:timezone":"Asia/Seoul",
    "iso:country":"KR",
    "name:und_x_variant":[
        "\ub0b4\uc131\uc0b0",
        "Naes\u014fngsan"
    ],
    "wof:name":"Naesongsan",
    "wof:placetype":"locality"
},
  "geometry": {"coordinates":[129.36709999999999,36.9443],"type":"Point"}
}