{
  "type": "Feature",
  "properties": {
    "gn:admin1_code":"14.0",
    "gn:asciiname":"Muni",
    "gn:country_code":"KR",
    "gn:dem":539,
    "gn:feature_class":"P",
    "gn:feature_code":"PPL",
    "gn:name":"Muni",
    "gn:population":0,
    "gn:timezone":"Asia/Seoul",
    "iso:country":"KR",
    "name:ceb_x_preferred":[
        "Muni"
    ],
    "name:ces_x_preferred":[
        "Muni"
    ],
    "name:deu_x_preferred":[
        "Muni"
    ],
    "name:fra_x_preferred":[
        "Muni"
    ],
    "name:nld_x_preferred":[
        "Muni"
    ],
    "name:por_x_preferred":[
        "Muni"
    ],
    "name:spa_x_preferred":[
        "Muni"
    ],
    "name:swe_x_preferred":[
        "Muni"
    ],
    "name:tam_x_preferred":[
        "\u0bae\u0bc1\u0ba9\u0bbf"
    ],
    "name:und_x_variant":[
        "\ubb38\uc774",
        "Muni"
    ],
    "wof:name":"Muni",
    "wof:placetype":"locality"
},
  "geometry": {"coordinates":[128.04655,35.85669],"type":"Point"}
}