{
  "type": "Feature",
  "properties": {
    "gn:admin1_code":"14.0",
    "gn:asciiname":"Misan",
    "gn:country_code":"KR",
    "gn:dem":120,
    "gn:feature_class":"P",
    "gn:feature_code":"PPL",
    "gn:name":"Misan",
    "gn:population":0,
    "gn:timezone":"Asia/Seoul",
    "iso:country":"KR",
    "name:kor_x_preferred":[
        "\ubbf8\uc0b0"
    ],
    "wof:name":"Misan",
    "wof:placetype":"locality"
},
  "geometry": {"coordinates":[128.66524999999999,36.60345],"type":"Point"}
}