{
  "type": "Feature",
  "properties": {
    "gn:admin1_code":"6.0",
    "gn:asciiname":"Dueungdae",
    "gn:country_code":"KR",
    "gn:dem":484,
    "gn:feature_class":"P",
    "gn:feature_code":"PPL",
    "gn:name":"Dueungdae",
    "gn:population":0,
    "gn:timezone":"Asia/Seoul",
    "iso:country":"KR",
    "name:kor_x_preferred":[
        "\ub450\uc6c5\ub300"
    ],
    "name:kor_x_variant":[
        "\ub450\uc751\ub300"
    ],
    "name:und_x_variant":[
        "Tuungdae",
        "Dueungdae"
    ],
    "wof:name":"Dueungdae",
    "wof:placetype":"locality"
},
  "geometry": {"coordinates":[128.39134999999999,37.94463],"type":"Point"}
}