{
  "type": "Feature",
  "properties": {
    "gn:admin1_code":"16.0",
    "gn:asciiname":"Geogae",
    "gn:country_code":"KR",
    "gn:dem":116,
    "gn:feature_class":"P",
    "gn:feature_code":"PPL",
    "gn:name":"Geogae",
    "gn:population":0,
    "gn:timezone":"Asia/Seoul",
    "iso:country":"KR",
    "name:kor_x_preferred":[
        "K\u2019\u014fgae"
    ],
    "name:kor_x_variant":[
        "\uac70\uac1c"
    ],
    "wof:name":"Geogae",
    "wof:placetype":"locality"
},
  "geometry": {"coordinates":[126.95878,34.72894],"type":"Point"}
}