{
  "type": "Feature",
  "properties": {
    "gn:admin1_code":"13.0",
    "gn:asciiname":"Unmaeul",
    "gn:country_code":"KR",
    "gn:dem":46,
    "gn:feature_class":"P",
    "gn:feature_code":"PPL",
    "gn:name":"Unmaeul",
    "gn:population":0,
    "gn:timezone":"Asia/Seoul",
    "iso:country":"KR",
    "name:kor_x_preferred":[
        "\uc6c3\ub9c8\uc744"
    ],
    "wof:name":"Unmaeul",
    "wof:placetype":"locality"
},
  "geometry": {"coordinates":[126.70963,37.23494],"type":"Point"}
}