{
  "type": "Feature",
  "properties": {
    "gn:admin1_code":"6.0",
    "gn:asciiname":"Kwang-ch'on",
    "gn:country_code":"KR",
    "gn:dem":662,
    "gn:feature_class":"P",
    "gn:feature_code":"PPL",
    "gn:name":"Kwang-ch\u2019on",
    "gn:population":0,
    "gn:timezone":"Asia/Seoul",
    "iso:country":"KR",
    "name:kor_x_preferred":[
        "\uad11\ucc9c"
    ],
    "name:kor_x_variant":[
        "Kwang-ch\u2019on"
    ],
    "wof:name":"Kwang-ch'on",
    "wof:placetype":"locality"
},
  "geometry": {"coordinates":[128.64189999999999,37.6775],"type":"Point"}
}