{
  "type": "Feature",
  "properties": {
    "gn:admin1_code":"14.0",
    "gn:asciiname":"Jangseongbaengni",
    "gn:country_code":"KR",
    "gn:dem":170,
    "gn:feature_class":"P",
    "gn:feature_code":"PPL",
    "gn:name":"Jangseongbaengni",
    "gn:population":0,
    "gn:timezone":"Asia/Seoul",
    "iso:country":"KR",
    "name:kor_x_preferred":[
        "\uc7a5\uc131\ubc31\ub9ac"
    ],
    "wof:name":"Jangseongbaengni",
    "wof:placetype":"locality"
},
  "geometry": {"coordinates":[128.90186,36.64083],"type":"Point"}
}