{
  "type": "Feature",
  "properties": {
    "gn:admin1_code":"14.0",
    "gn:asciiname":"Saedudeul",
    "gn:country_code":"KR",
    "gn:dem":325,
    "gn:feature_class":"P",
    "gn:feature_code":"PPL",
    "gn:name":"Saedudeul",
    "gn:population":0,
    "gn:timezone":"Asia/Seoul",
    "iso:country":"KR",
    "name:kor_x_preferred":[
        "\uc0c8\ub450\ub4e4"
    ],
    "wof:name":"Saedudeul",
    "wof:placetype":"locality"
},
  "geometry": {"coordinates":[128.68617,36.97685],"type":"Point"}
}