{
  "type": "Feature",
  "properties": {
    "gn:admin1_code":"14.0",
    "gn:asciiname":"Gumidong",
    "gn:country_code":"KR",
    "gn:dem":30,
    "gn:feature_class":"P",
    "gn:feature_code":"PPL",
    "gn:name":"Gumidong",
    "gn:population":0,
    "gn:timezone":"Asia/Seoul",
    "iso:country":"KR",
    "name:kor_x_preferred":[
        "\uad6c\ubbf8\ub3d9"
    ],
    "wof:name":"Gumidong",
    "wof:placetype":"locality"
},
  "geometry": {"coordinates":[129.35366000000002,36.4344],"type":"Point"}
}