{
  "type": "Feature",
  "properties": {
    "gn:admin1_code":"17.0",
    "gn:asciiname":"Songmit",
    "gn:country_code":"KR",
    "gn:dem":45,
    "gn:feature_class":"P",
    "gn:feature_code":"PPL",
    "gn:name":"S\u014fngmit",
    "gn:population":0,
    "gn:timezone":"Asia/Seoul",
    "iso:country":"KR",
    "name:und_x_variant":[
        "\uc131\ubc11",
        "S\u014fngmit"
    ],
    "wof:name":"Songmit",
    "wof:placetype":"locality"
},
  "geometry": {"coordinates":[127.15560000000001,36.3211],"type":"Point"}
}