{
  "type": "Feature",
  "properties": {
    "gn:admin1_code":"17.0",
    "gn:asciiname":"Togong-ni",
    "gn:country_code":"KR",
    "gn:dem":178,
    "gn:feature_class":"P",
    "gn:feature_code":"PPLL",
    "gn:name":"Togong-ni",
    "gn:population":0,
    "gn:timezone":"Asia/Seoul",
    "iso:country":"KR",
    "name:eng_x_preferred":[
        "Togong"
    ],
    "name:eng_x_variant":[
        "Togong-ni"
    ],
    "name:und_x_variant":[
        "\ub3c4\uace1\ub9ac",
        "Togong-ni"
    ],
    "wof:name":"Togong",
    "wof:placetype":"locality"
},
  "geometry": {"coordinates":[127.47157,36.1144],"type":"Point"}
}