{
  "type": "Feature",
  "properties": {
    "gn:admin1_code":"13.0",
    "gn:asciiname":"Gaenodong",
    "gn:country_code":"KR",
    "gn:dem":203,
    "gn:feature_class":"P",
    "gn:feature_code":"PPL",
    "gn:name":"Gaenodong",
    "gn:population":0,
    "gn:timezone":"Asia/Seoul",
    "iso:country":"KR",
    "name:kor_x_preferred":[
        "\uac1c\ub178\ub3d9"
    ],
    "wof:name":"Gaenodong",
    "wof:placetype":"locality"
},
  "geometry": {"coordinates":[127.37345000000001,37.78147],"type":"Point"}
}