{
  "type": "Feature",
  "properties": {
    "gn:admin1_code":"12.0",
    "gn:asciiname":"Bak-chon",
    "gn:country_code":"KR",
    "gn:dem":25,
    "gn:feature_class":"P",
    "gn:feature_code":"PPL",
    "gn:name":"Bak-chon",
    "gn:population":0,
    "gn:timezone":"Asia/Seoul",
    "iso:country":"KR",
    "name:und_x_variant":[
        "\ubc15\ucd0c",
        "Bak-chon",
        "Pak-ch\u2019on"
    ],
    "wof:name":"Bak-chon",
    "wof:placetype":"locality"
},
  "geometry": {"coordinates":[126.50888999999999,37.52333],"type":"Point"}
}