{
  "type": "Feature",
  "properties": {
    "gn:admin1_code":"17.0",
    "gn:asciiname":"Wonanttuk",
    "gn:country_code":"KR",
    "gn:dem":16,
    "gn:feature_class":"P",
    "gn:feature_code":"PPL",
    "gn:name":"W\u014fnanttuk",
    "gn:population":0,
    "gn:timezone":"Asia/Seoul",
    "iso:country":"KR",
    "name:und_x_variant":[
        "\uc6d0\uc548\ub69d",
        "W\u014fnanttuk"
    ],
    "wof:name":"Wonanttuk",
    "wof:placetype":"locality"
},
  "geometry": {"coordinates":[126.53189999999999,36.5943],"type":"Point"}
}