{
  "type": "Feature",
  "properties": {
    "gn:admin1_code":"17.0",
    "gn:asciiname":"Mojong",
    "gn:country_code":"KR",
    "gn:dem":22,
    "gn:feature_class":"P",
    "gn:feature_code":"PPL",
    "gn:name":"Moj\u014fng",
    "gn:population":0,
    "gn:timezone":"Asia/Seoul",
    "iso:country":"KR",
    "name:und_x_variant":[
        "\ubaa8\uc815",
        "Moj\u014fng"
    ],
    "wof:name":"Mojong",
    "wof:placetype":"locality"
},
  "geometry": {"coordinates":[126.78360000000001,36.8356],"type":"Point"}
}