{
  "type": "Feature",
  "properties": {
    "iso:country":"KR",
    "name:kor_x_preferred":[
        "\uc740\ud589\uc120\ud654\ub3d9"
    ],
    "name:kor_x_variant":[
        "\uc740\ud589\uc120\ud654"
    ],
    "qs:gn_adm0_cc":"KR",
    "qs:gn_local":1835235,
    "qs:local_max":1052,
    "qs:local_sum":4707,
    "qs:localhoods":21,
    "qs:name":"\uc740\ud589\uc120\ud654\ub3d9",
    "qs:name_adm0":"\ud55c\uad6d",
    "qs:name_adm1":"\ub300\uc804",
    "qs:name_adm2":"\uc911\uad6c",
    "qs:name_lau":"\uc740\ud589\uc120\ud654\ub3d9",
    "qs:name_local":"\ub300\uc804",
    "qs:photo_max":38,
    "qs:photo_sum":95,
    "qs:placetype":"Suburb",
    "qs:quad_count":8,
    "qs:woe_adm0":23424868,
    "qs:woe_adm1":2345975,
    "qs:woe_adm2":28289231,
    "qs:woe_lau":28806543,
    "qs:woe_local":1132467,
    "qs:woe_ver":"7.10.0",
    "wof:lang":[
        "kor"
    ],
    "wof:name":"\uc740\ud589\uc120\ud654\ub3d9",
    "wof:placetype":"neighbourhood"
},
  "geometry": {"coordinates":[127.42635,36.324687],"type":"Point"}
}