{
  "type": "Feature",
  "properties": {
    "gn:admin1_code":"16.0",
    "gn:asciiname":"Jangmakdong",
    "gn:country_code":"KR",
    "gn:dem":11,
    "gn:feature_class":"P",
    "gn:feature_code":"PPL",
    "gn:name":"Jangmakdong",
    "gn:population":0,
    "gn:timezone":"Asia/Seoul",
    "iso:country":"KR",
    "name:kor_x_preferred":[
        "\uc7a5\ub9c9\ub3d9"
    ],
    "name:und_x_variant":[
        "Changmaktong",
        "Jangmakdong"
    ],
    "wof:name":"Jangmakdong",
    "wof:placetype":"locality"
},
  "geometry": {"coordinates":[127.27527000000001,34.68198],"type":"Point"}
}