{
  "type": "Feature",
  "properties": {
    "gn:admin1_code":"14.0",
    "gn:asciiname":"Kae-gol",
    "gn:country_code":"KR",
    "gn:dem":151,
    "gn:feature_class":"P",
    "gn:feature_code":"PPL",
    "gn:name":"Kae-gol",
    "gn:population":0,
    "gn:timezone":"Asia/Seoul",
    "iso:country":"KR",
    "name:und_x_variant":[
        "\uac1c\uace8",
        "Kae-gol"
    ],
    "wof:name":"Kae-gol",
    "wof:placetype":"locality"
},
  "geometry": {"coordinates":[128.7612,36.2589],"type":"Point"}
}