{
  "type": "Feature",
  "properties": {
    "gn:admin1_code":"17.0",
    "gn:asciiname":"Tolbo",
    "gn:country_code":"KR",
    "gn:dem":136,
    "gn:feature_class":"P",
    "gn:feature_code":"PPL",
    "gn:name":"Tolbo",
    "gn:population":0,
    "gn:timezone":"Asia/Seoul",
    "iso:country":"KR",
    "name:und_x_variant":[
        "Tolbong-ni",
        "Tolbo",
        "\ub3cc\ubcf4"
    ],
    "wof:name":"Tolbo",
    "wof:placetype":"locality"
},
  "geometry": {"coordinates":[126.7715,36.3659],"type":"Point"}
}