{
  "type": "Feature",
  "properties": {
    "gn:admin1_code":"17.0",
    "gn:asciiname":"Tolbo",
    "gn:country_code":"KR",
    "gn:dem":136,
    "gn:feature_class":"P",
    "gn:feature_code":"PPL",
    "gn:name":"Tolbo",
    "gn:population":0,
    "gn:timezone":"Asia/Seoul",
    "iso:country":"KR",
    "name:ceb_x_preferred":[
        "Tolbo"
    ],
    "name:fra_x_preferred":[
        "Tolbo"
    ],
    "name:hun_x_preferred":[
        "Tolbo j\u00e1r\u00e1s"
    ],
    "name:ita_x_preferred":[
        "Tolbo"
    ],
    "name:mkd_x_preferred":[
        "\u0422\u043e\u043b\u0431\u043e"
    ],
    "name:mon_x_preferred":[
        "\u0422\u043e\u043b\u0431\u043e \u0441\u0443\u043c"
    ],
    "name:rus_x_preferred":[
        "\u0422\u043e\u043b\u0431\u043e"
    ],
    "name:swe_x_preferred":[
        "Tolbo"
    ],
    "name:ukr_x_preferred":[
        "\u0422\u043e\u043b\u0431\u043e"
    ],
    "name:und_x_variant":[
        "Tolbong-ni",
        "Tolbo",
        "\ub3cc\ubcf4"
    ],
    "wof:name":"Tolbo",
    "wof:placetype":"locality"
},
  "geometry": {"coordinates":[126.7715,36.3659],"type":"Point"}
}