{
  "type": "Feature",
  "properties": {
    "gn:admin1_code":"16.0",
    "gn:asciiname":"Pukkon-mal",
    "gn:country_code":"KR",
    "gn:dem":31,
    "gn:feature_class":"P",
    "gn:feature_code":"PPL",
    "gn:name":"Pukkon-mal",
    "gn:population":0,
    "gn:timezone":"Asia/Seoul",
    "iso:country":"KR",
    "name:kor_x_preferred":[
        "\uad6c\ud3c9"
    ],
    "wof:name":"Pukkon-mal",
    "wof:placetype":"locality"
},
  "geometry": {"coordinates":[126.88667,34.51333],"type":"Point"}
}