{
  "type": "Feature",
  "properties": {
    "gn:admin1_code":"6.0",
    "gn:asciiname":"Maha",
    "gn:country_code":"KR",
    "gn:dem":241,
    "gn:feature_class":"P",
    "gn:feature_code":"PPL",
    "gn:name":"Maha",
    "gn:population":0,
    "gn:timezone":"Asia/Seoul",
    "iso:country":"KR",
    "name:ceb_x_preferred":[
        "Maha"
    ],
    "name:deu_x_preferred":[
        "Maha"
    ],
    "name:ita_x_preferred":[
        "Maha"
    ],
    "name:kor_x_preferred":[
        "\ub9c8\ud558"
    ],
    "name:mya_x_preferred":[
        "\u1019\u101f\u102c"
    ],
    "name:por_x_preferred":[
        "Maha"
    ],
    "name:swe_x_preferred":[
        "Maha"
    ],
    "name:tel_x_preferred":[
        "\u0c2e\u0c39\u0c3e"
    ],
    "wof:name":"Maha",
    "wof:placetype":"locality"
},
  "geometry": {"coordinates":[128.5403,37.2897],"type":"Point"}
}