{
  "type": "Feature",
  "properties": {
    "gn:admin1_code":"17.0",
    "gn:asciiname":"Hongch'on",
    "gn:country_code":"KR",
    "gn:dem":55,
    "gn:feature_class":"P",
    "gn:feature_code":"PPL",
    "gn:name":"Hongch\u2019\u014fn",
    "gn:population":0,
    "gn:timezone":"Asia/Seoul",
    "iso:country":"KR",
    "name:und_x_variant":[
        "\ud64d\ucc9c",
        "Hongch\u2019\u014fn"
    ],
    "wof:name":"Hongch'on",
    "wof:placetype":"locality"
},
  "geometry": {"coordinates":[126.63079999999999,36.6283],"type":"Point"}
}