{
  "type": "Feature",
  "properties": {
    "gn:admin1_code":"6.0",
    "gn:asciiname":"Nae-dong",
    "gn:country_code":"KR",
    "gn:dem":227,
    "gn:feature_class":"P",
    "gn:feature_code":"PPL",
    "gn:name":"Nae-dong",
    "gn:population":0,
    "gn:timezone":"Asia/Seoul",
    "iso:country":"KR",
    "name:kor_x_preferred":[
        "\ub0b4\ub3d9"
    ],
    "wof:name":"Nae-dong",
    "wof:placetype":"locality"
},
  "geometry": {"coordinates":[128.7062,37.8151],"type":"Point"}
}