{
  "type": "Feature",
  "properties": {
    "gn:admin1_code":"21.0",
    "gn:asciiname":"Gojeokbun",
    "gn:country_code":"KR",
    "gn:dem":72,
    "gn:feature_class":"P",
    "gn:feature_code":"PPL",
    "gn:name":"Gojeokbun",
    "gn:population":0,
    "gn:timezone":"Asia/Seoul",
    "iso:country":"KR",
    "name:kor_x_preferred":[
        "\uace0\uc801\ubd84"
    ],
    "wof:name":"Gojeokbun",
    "wof:placetype":"locality"
},
  "geometry": {"coordinates":[129.19236000000001,35.44105],"type":"Point"}
}