{
  "type": "Feature",
  "properties": {
    "gn:admin1_code":"14.0",
    "gn:asciiname":"Suseong",
    "gn:country_code":"KR",
    "gn:dem":18,
    "gn:feature_class":"P",
    "gn:feature_code":"PPL",
    "gn:name":"Suseong",
    "gn:population":0,
    "gn:timezone":"Asia/Seoul",
    "iso:country":"KR",
    "name:kor_x_preferred":[
        "\uc218\uc131"
    ],
    "wof:name":"Suseong",
    "wof:placetype":"locality"
},
  "geometry": {"coordinates":[129.50523999999999,35.88113],"type":"Point"}
}