{
  "type": "Feature",
  "properties": {
    "gn:admin1_code":"13.0",
    "gn:admin2_code":"Kimp'o-si",
    "gn:asciiname":"Huchondong",
    "gn:country_code":"KR",
    "gn:dem":26,
    "gn:feature_class":"P",
    "gn:feature_code":"PPL",
    "gn:name":"Huchondong",
    "gn:population":0,
    "gn:timezone":"Asia/Seoul",
    "iso:country":"KR",
    "name:kor_x_preferred":[
        "\ud6c4\ucd0c\ub3d9"
    ],
    "name:kor_x_variant":[
        "Huch\u2019on-dong"
    ],
    "wof:name":"Huchondong",
    "wof:placetype":"locality"
},
  "geometry": {"coordinates":[126.651,37.74721],"type":"Point"}
}