{
  "type": "Feature",
  "properties": {
    "gn:admin1_code":"10.0",
    "gn:asciiname":"Bangmo",
    "gn:country_code":"KR",
    "gn:dem":21,
    "gn:feature_class":"P",
    "gn:feature_code":"PPL",
    "gn:name":"Bangmo",
    "gn:population":0,
    "gn:timezone":"Asia/Seoul",
    "iso:country":"KR",
    "name:kor_x_preferred":[
        "\ubc29\ubaa8"
    ],
    "wof:name":"Bangmo",
    "wof:placetype":"locality"
},
  "geometry": {"coordinates":[129.25659999999999,35.3391],"type":"Point"}
}