{
  "type": "Feature",
  "properties": {
    "gn:admin1_code":"16.0",
    "gn:asciiname":"Munam",
    "gn:country_code":"KR",
    "gn:dem":255,
    "gn:feature_class":"P",
    "gn:feature_code":"PPL",
    "gn:name":"Munam",
    "gn:population":0,
    "gn:timezone":"Asia/Seoul",
    "iso:country":"KR",
    "name:kor_x_preferred":[
        "\ubb38\uc554"
    ],
    "wof:name":"Munam",
    "wof:placetype":"locality"
},
  "geometry": {"coordinates":[126.91083,34.88923],"type":"Point"}
}