{
  "type": "Feature",
  "properties": {
    "gn:admin1_code":"17.0",
    "gn:asciiname":"Ijok",
    "gn:country_code":"KR",
    "gn:dem":10,
    "gn:feature_class":"P",
    "gn:feature_code":"PPL",
    "gn:name":"Ij\u014fk",
    "gn:population":0,
    "gn:timezone":"Asia/Seoul",
    "iso:country":"KR",
    "name:msa_x_preferred":[
        "Ijok"
    ],
    "name:por_x_preferred":[
        "Ijok"
    ],
    "name:und_x_variant":[
        "\uc774\uc801",
        "Ij\u014fk"
    ],
    "wof:name":"Ijok",
    "wof:placetype":"locality"
},
  "geometry": {"coordinates":[126.2925,36.8258],"type":"Point"}
}