{
  "type": "Feature",
  "properties": {
    "gn:admin1_code":"17.0",
    "gn:asciiname":"Saet'o-mal",
    "gn:country_code":"KR",
    "gn:dem":88,
    "gn:feature_class":"P",
    "gn:feature_code":"PPL",
    "gn:name":"Saet\u2019\u014f-mal",
    "gn:population":0,
    "gn:timezone":"Asia/Seoul",
    "iso:country":"KR",
    "name:und_x_variant":[
        "\uc0c8\ud130\ub9d0",
        "Saet\u2019\u014f-mal"
    ],
    "wof:name":"Saet'o-mal",
    "wof:placetype":"locality"
},
  "geometry": {"coordinates":[127.1189,36.3575],"type":"Point"}
}