{
  "type": "Feature",
  "properties": {
    "gn:admin1_code":"13.0",
    "gn:asciiname":"Sangbanje",
    "gn:country_code":"KR",
    "gn:dem":65,
    "gn:feature_class":"P",
    "gn:feature_code":"PPL",
    "gn:name":"Sangbanje",
    "gn:population":0,
    "gn:timezone":"Asia/Seoul",
    "iso:country":"KR",
    "name:kor_x_preferred":[
        "\uc0c1\ubc18\uc81c"
    ],
    "name:und_x_variant":[
        "\uc6c3\ubc18\uc81c",
        "Utbanje",
        "Uppanje",
        "Sangbanje"
    ],
    "wof:name":"Sangbanje",
    "wof:placetype":"locality"
},
  "geometry": {"coordinates":[127.1617,37.03043],"type":"Point"}
}