{
  "type": "Feature",
  "properties": {
    "gn:admin1_code":"16.0",
    "gn:asciiname":"Yongju",
    "gn:country_code":"KR",
    "gn:dem":10,
    "gn:feature_class":"P",
    "gn:feature_code":"PPL",
    "gn:name":"Yongju",
    "gn:population":0,
    "gn:timezone":"Asia/Seoul",
    "iso:country":"KR",
    "name:kor_x_preferred":[
        "\uc6a9\uc8fc"
    ],
    "name:und_x_variant":[
        "Yongju-ri"
    ],
    "wof:name":"Yongju",
    "wof:placetype":"locality"
},
  "geometry": {"coordinates":[127.63033,34.71635999999999],"type":"Point"}
}