{
  "type": "Feature",
  "properties": {
    "gn:admin1_code":"16.0",
    "gn:asciiname":"janghwal",
    "gn:country_code":"KR",
    "gn:dem":19,
    "gn:feature_class":"P",
    "gn:feature_code":"PPL",
    "gn:name":"\uc7a5\ud65c",
    "gn:population":0,
    "gn:timezone":"Asia/Seoul",
    "iso:country":"KR",
    "wof:name":"janghwal",
    "wof:placetype":"locality"
},
  "geometry": {"coordinates":[126.52916999999999,34.54333],"type":"Point"}
}