{
  "type": "Feature",
  "properties": {
    "gn:admin1_code":"14.0",
    "gn:asciiname":"Kusowon",
    "gn:country_code":"KR",
    "gn:dem":94,
    "gn:feature_class":"P",
    "gn:feature_code":"PPL",
    "gn:name":"Kus\u014fw\u014fn",
    "gn:population":0,
    "gn:timezone":"Asia/Seoul",
    "iso:country":"KR",
    "name:und_x_variant":[
        "\uad6c\uc11c\uc6d0",
        "Kus\u014fw\u014fn"
    ],
    "wof:name":"Kusowon",
    "wof:placetype":"locality"
},
  "geometry": {"coordinates":[128.09389999999999,36.3398],"type":"Point"}
}