{
  "type": "Feature",
  "properties": {
    "gn:admin1_code":"14.0",
    "gn:asciiname":"Chukpang",
    "gn:country_code":"KR",
    "gn:dem":119,
    "gn:feature_class":"P",
    "gn:feature_code":"PPL",
    "gn:name":"Chukpang",
    "gn:population":0,
    "gn:timezone":"Asia/Seoul",
    "iso:country":"KR",
    "name:und_x_variant":[
        "\uc8fd\ubc29",
        "Chukpang"
    ],
    "wof:name":"Chukpang",
    "wof:placetype":"locality"
},
  "geometry": {"coordinates":[128.07897,36.05896],"type":"Point"}
}