{
  "type": "Feature",
  "properties": {
    "gn:admin1_code":"16.0",
    "gn:asciiname":"Kamdang",
    "gn:country_code":"KR",
    "gn:dem":74,
    "gn:feature_class":"P",
    "gn:feature_code":"PPL",
    "gn:name":"Kamdang",
    "gn:population":0,
    "gn:timezone":"Asia/Seoul",
    "iso:country":"KR",
    "name:und_x_variant":[
        "\uac10\ub2f9",
        "Kamdang"
    ],
    "wof:name":"Kamdang",
    "wof:placetype":"locality"
},
  "geometry": {"coordinates":[126.60805999999999,34.53778],"type":"Point"}
}