{
  "type": "Feature",
  "properties": {
    "iso:country":"KR",
    "qs:name":"\ubcd1\uc554\ub3d9",
    "qs:name_adm0":"\ud55c\uad6d",
    "qs:name_adm1":"\uacbd\uc0c1\ub0a8\ub3c4",
    "qs:photos":2,
    "qs:photos_1k":1,
    "qs:photos_9k":1,
    "qs:photos_9r":1,
    "qs:photos_all":2,
    "qs:photos_sr":1,
    "qs:placetype":"LocalAdmin",
    "qs:pop_sr":"0",
    "wof:name":"\ubcd1\uc554\ub3d9",
    "wof:placetype":"localadmin"
},
  "geometry": {"coordinates":[128.68726899999999,35.159219],"type":"Point"}
}