{
  "type": "Feature",
  "properties": {
    "gn:admin1_code":"16.0",
    "gn:asciiname":"Sinbokchon",
    "gn:country_code":"KR",
    "gn:dem":14,
    "gn:feature_class":"P",
    "gn:feature_code":"PPL",
    "gn:name":"Sinbokchon",
    "gn:population":0,
    "gn:timezone":"Asia/Seoul",
    "iso:country":"KR",
    "name:kor_x_preferred":[
        "\uc2e0\ubcf5\ucd0c"
    ],
    "name:und_x_variant":[
        "Sinsangchon",
        "Sinbok-ch\u2019on",
        "Sinbokchon"
    ],
    "wof:name":"Sinbokchon",
    "wof:placetype":"locality"
},
  "geometry": {"coordinates":[126.71767,34.80748],"type":"Point"}
}