{
  "type": "Feature",
  "properties": {
    "gn:admin1_code":"13.0",
    "gn:asciiname":"Gugwondong",
    "gn:country_code":"KR",
    "gn:dem":48,
    "gn:feature_class":"P",
    "gn:feature_code":"PPL",
    "gn:name":"Gugwondong",
    "gn:population":0,
    "gn:timezone":"Asia/Seoul",
    "iso:country":"KR",
    "name:kor_x_preferred":[
        "\uad6d\uc6d0\ub3d9"
    ],
    "wof:name":"Gugwondong",
    "wof:placetype":"locality"
},
  "geometry": {"coordinates":[126.71073,37.78329],"type":"Point"}
}