{
  "type": "Feature",
  "properties": {
    "gn:admin1_code":"14.0",
    "gn:asciiname":"Geondeokdong",
    "gn:country_code":"KR",
    "gn:dem":43,
    "gn:feature_class":"P",
    "gn:feature_code":"PPL",
    "gn:name":"Geondeokdong",
    "gn:population":0,
    "gn:timezone":"Asia/Seoul",
    "iso:country":"KR",
    "name:kor_x_preferred":[
        "\uac74\ub355\ub3d9"
    ],
    "wof:name":"Geondeokdong",
    "wof:placetype":"locality"
},
  "geometry": {"coordinates":[129.35575,35.95827],"type":"Point"}
}