{
  "type": "Feature",
  "properties": {
    "gn:admin1_code":"16.0",
    "gn:asciiname":"Naedaegok",
    "gn:country_code":"KR",
    "gn:dem":45,
    "gn:feature_class":"P",
    "gn:feature_code":"PPL",
    "gn:name":"Naedaegok",
    "gn:population":0,
    "gn:timezone":"Asia/Seoul",
    "iso:country":"KR",
    "name:kor_x_preferred":[
        "\ub0b4\ub300\uace1"
    ],
    "wof:name":"Naedaegok",
    "wof:placetype":"locality"
},
  "geometry": {"coordinates":[126.93648,34.99889],"type":"Point"}
}