{
  "type": "Feature",
  "properties": {
    "gn:admin1_code":"14.0",
    "gn:asciiname":"Cheil",
    "gn:country_code":"KR",
    "gn:dem":237,
    "gn:feature_class":"P",
    "gn:feature_code":"PPL",
    "gn:name":"Cheil",
    "gn:population":0,
    "gn:timezone":"Asia/Seoul",
    "iso:country":"KR",
    "name:und_x_variant":[
        "Cheilgok",
        "\uc81c\uc77c",
        "Cheil"
    ],
    "wof:name":"Cheil",
    "wof:placetype":"locality"
},
  "geometry": {"coordinates":[128.92240000000001,36.3408],"type":"Point"}
}