{
  "type": "Feature",
  "properties": {
    "gn:admin1_code":"13.0",
    "gn:asciiname":"Yeokgwiul",
    "gn:country_code":"KR",
    "gn:dem":87,
    "gn:feature_class":"P",
    "gn:feature_code":"PPL",
    "gn:name":"Yeokgwiul",
    "gn:population":0,
    "gn:timezone":"Asia/Seoul",
    "iso:country":"KR",
    "name:kor_x_preferred":[
        "\uc5ed\uadc0\uc6b8"
    ],
    "name:kor_x_variant":[
        "Y\u014fkkwiul"
    ],
    "wof:name":"Yeokgwiul",
    "wof:placetype":"locality"
},
  "geometry": {"coordinates":[127.54885,37.11232],"type":"Point"}
}