{
  "type": "Feature",
  "properties": {
    "gn:admin1_code":"17.0",
    "gn:asciiname":"Haemi",
    "gn:country_code":"KR",
    "gn:dem":28,
    "gn:feature_class":"P",
    "gn:feature_code":"PPL",
    "gn:name":"Haemi",
    "gn:population":0,
    "gn:timezone":"Asia/Seoul",
    "iso:country":"KR",
    "name:und_x_variant":[
        "Kaibi",
        "\ud574\ubbf8",
        "\u016cmnae-ri",
        "Haemi"
    ],
    "wof:name":"Haemi",
    "wof:placetype":"locality"
},
  "geometry": {"coordinates":[126.54667000000001,36.71667],"type":"Point"}
}