{
  "type": "Feature",
  "properties": {
    "gn:admin1_code":"6.0",
    "gn:asciiname":"Songhak",
    "gn:country_code":"KR",
    "gn:dem":266,
    "gn:feature_class":"P",
    "gn:feature_code":"PPL",
    "gn:name":"Songhak",
    "gn:population":0,
    "gn:timezone":"Asia/Seoul",
    "iso:country":"KR",
    "name:kor_x_preferred":[
        "\uc1a1\ud559\ub3d9"
    ],
    "name:kor_x_variant":[
        "\uc1a1\ud559"
    ],
    "name:und_x_variant":[
        "Songhak-tong",
        "Songhak"
    ],
    "wof:name":"Songhak",
    "wof:placetype":"locality"
},
  "geometry": {"coordinates":[128.20767000000001,38.17],"type":"Point"}
}