{
  "type": "Feature",
  "properties": {
    "gn:admin1_code":"6.0",
    "gn:asciiname":"Kalbak-kol",
    "gn:country_code":"KR",
    "gn:dem":730,
    "gn:feature_class":"P",
    "gn:feature_code":"PPL",
    "gn:name":"Kalbak-kol",
    "gn:population":0,
    "gn:timezone":"Asia/Seoul",
    "iso:country":"KR",
    "name:kor_x_preferred":[
        "\uac08\ubc2d\uace8"
    ],
    "wof:name":"Kalbak-kol",
    "wof:placetype":"locality"
},
  "geometry": {"coordinates":[128.7878,37.5748],"type":"Point"}
}