{
  "type": "Feature",
  "properties": {
    "gn:admin1_code":"13.0",
    "gn:asciiname":"Gwangmyeongni",
    "gn:country_code":"KR",
    "gn:dem":30,
    "gn:feature_class":"P",
    "gn:feature_code":"PPL",
    "gn:name":"Gwangmyeongni",
    "gn:population":0,
    "gn:timezone":"Asia/Seoul",
    "iso:country":"KR",
    "name:kor_x_preferred":[
        "\uad11\uba85\ub9ac"
    ],
    "wof:name":"Gwangmyeongni",
    "wof:placetype":"locality"
},
  "geometry": {"coordinates":[126.85208,37.46159],"type":"Point"}
}