{
  "type": "Feature",
  "properties": {
    "gn:admin1_code":"13.0",
    "gn:asciiname":"Ammal",
    "gn:country_code":"KR",
    "gn:dem":77,
    "gn:feature_class":"P",
    "gn:feature_code":"PPL",
    "gn:name":"Ammal",
    "gn:population":0,
    "gn:timezone":"Asia/Seoul",
    "iso:country":"KR",
    "name:ara_x_preferred":[
        "\u0639\u0645\u0627\u0644"
    ],
    "name:azb_x_preferred":[
        "\u0627\u0645\u0627\u0644"
    ],
    "name:fas_x_preferred":[
        "\u0627\u0645\u0627\u0644"
    ],
    "name:fra_x_preferred":[
        "Ammal"
    ],
    "name:ita_x_preferred":[
        "Ammal"
    ],
    "name:kab_x_preferred":[
        "\u0190emmal"
    ],
    "name:msa_x_preferred":[
        "Ammal"
    ],
    "name:por_x_preferred":[
        "Ammal"
    ],
    "name:ron_x_preferred":[
        "Ammal"
    ],
    "name:rus_x_preferred":[
        "\u0410\u043c\u043c\u0430\u043b"
    ],
    "name:spa_x_preferred":[
        "Ammal"
    ],
    "name:und_x_variant":[
        "\uc554\ub9d0",
        "Am-mal"
    ],
    "name:vie_x_preferred":[
        "Ammal"
    ],
    "name:zho_x_preferred":[
        "\u963f\u99ac\u52d2"
    ],
    "wof:name":"Ammal",
    "wof:placetype":"locality"
},
  "geometry": {"coordinates":[127.10556,37.05889000000001],"type":"Point"}
}