{
  "type": "Feature",
  "properties": {
    "gn:admin1_code":"13.0",
    "gn:asciiname":"Ammal",
    "gn:country_code":"KR",
    "gn:dem":77,
    "gn:feature_class":"P",
    "gn:feature_code":"PPL",
    "gn:name":"Ammal",
    "gn:population":0,
    "gn:timezone":"Asia/Seoul",
    "iso:country":"KR",
    "name:und_x_variant":[
        "\uc554\ub9d0",
        "Am-mal",
        "Ammal"
    ],
    "wof:name":"Ammal",
    "wof:placetype":"locality"
},
  "geometry": {"coordinates":[127.10556,37.05889000000001],"type":"Point"}
}