{
  "type": "Feature",
  "properties": {
    "gn:admin1_code":"15.0",
    "gn:asciiname":"Songchon",
    "gn:country_code":"KR",
    "gn:dem":126,
    "gn:feature_class":"P",
    "gn:feature_code":"PPL",
    "gn:name":"Songchon",
    "gn:population":0,
    "gn:timezone":"Asia/Seoul",
    "iso:country":"KR",
    "name:kor_x_preferred":[
        "\uc1a1\ucd0c"
    ],
    "wof:name":"Songchon",
    "wof:placetype":"locality"
},
  "geometry": {"coordinates":[128.47323,35.76503],"type":"Point"}
}