{
  "type": "Feature",
  "properties": {
    "gn:admin1_code":"11.0",
    "gn:asciiname":"Ponsam-dong",
    "gn:country_code":"KR",
    "gn:dem":73,
    "gn:feature_class":"P",
    "gn:feature_code":"PPL",
    "gn:name":"P\u014fnsam-dong",
    "gn:population":0,
    "gn:timezone":"Asia/Seoul",
    "iso:country":"KR",
    "name:und_x_variant":[
        "\ubc883\ub3d9",
        "P\u014fnsam-dong"
    ],
    "wof:name":"Ponsam-dong",
    "wof:placetype":"locality"
},
  "geometry": {"coordinates":[127.04331999999999,37.62345],"type":"Point"}
}