{
  "type": "Feature",
  "properties": {
    "gn:admin1_code":"13.0",
    "gn:asciiname":"Nongmak",
    "gn:country_code":"KR",
    "gn:dem":54,
    "gn:feature_class":"P",
    "gn:feature_code":"PPL",
    "gn:name":"Nongmak",
    "gn:population":0,
    "gn:timezone":"Asia/Seoul",
    "iso:country":"KR",
    "name:und_x_variant":[
        "\ub18d\ub9c9",
        "Nongmak"
    ],
    "wof:name":"Nongmak",
    "wof:placetype":"locality"
},
  "geometry": {"coordinates":[127.11528,37.40667],"type":"Point"}
}