{
  "type": "Feature",
  "properties": {
    "gn:admin1_code":"10.0",
    "gn:asciiname":"Ttokjagol",
    "gn:country_code":"KR",
    "gn:dem":50,
    "gn:feature_class":"P",
    "gn:feature_code":"PPL",
    "gn:name":"Ttokjagol",
    "gn:population":0,
    "gn:timezone":"Asia/Seoul",
    "iso:country":"KR",
    "name:kor_x_preferred":[
        "\ub611\uc790\uace8"
    ],
    "wof:name":"Ttokjagol",
    "wof:placetype":"locality"
},
  "geometry": {"coordinates":[129.21011999999999,35.27991],"type":"Point"}
}