{
  "type": "Feature",
  "properties": {
    "gn:admin1_code":"16.0",
    "gn:asciiname":"Hagui",
    "gn:country_code":"KR",
    "gn:dem":17,
    "gn:feature_class":"P",
    "gn:feature_code":"PPL",
    "gn:name":"Hagui",
    "gn:population":0,
    "gn:timezone":"Asia/Seoul",
    "iso:country":"KR",
    "name:kor_x_preferred":[
        "\ud559\uc758"
    ],
    "name:kor_x_variant":[
        "Hag\u016di"
    ],
    "name:und_x_variant":[
        "Hag\u016di-ri",
        "Hag\u016d-ri",
        "Hagui"
    ],
    "wof:name":"Hagui",
    "wof:placetype":"locality"
},
  "geometry": {"coordinates":[126.53556,34.46222],"type":"Point"}
}