{
  "type": "Feature",
  "properties": {
    "gn:admin1_code":"16.0",
    "gn:asciiname":"Hajanggok",
    "gn:country_code":"KR",
    "gn:dem":177,
    "gn:feature_class":"P",
    "gn:feature_code":"PPL",
    "gn:name":"Hajanggok",
    "gn:population":0,
    "gn:timezone":"Asia/Seoul",
    "iso:country":"KR",
    "name:kor_x_preferred":[
        "\ud558\uc7a5\uace1"
    ],
    "wof:name":"Hajanggok",
    "wof:placetype":"locality"
},
  "geometry": {"coordinates":[127.00132000000001,34.78468],"type":"Point"}
}