{
  "type": "Feature",
  "properties": {
    "gn:admin1_code":"14.0",
    "gn:asciiname":"Donguji",
    "gn:country_code":"KR",
    "gn:dem":106,
    "gn:feature_class":"P",
    "gn:feature_code":"PPL",
    "gn:name":"Donguji",
    "gn:population":0,
    "gn:timezone":"Asia/Seoul",
    "iso:country":"KR",
    "name:kor_x_preferred":[
        "\ub3d9\uc6b0\uc9c0"
    ],
    "wof:name":"Donguji",
    "wof:placetype":"locality"
},
  "geometry": {"coordinates":[128.23258999999999,36.55271],"type":"Point"}
}