{
  "type": "Feature",
  "properties": {
    "gn:admin1_code":"17.0",
    "gn:asciiname":"Puokto",
    "gn:country_code":"KR",
    "gn:dem":18,
    "gn:feature_class":"P",
    "gn:feature_code":"PPL",
    "gn:name":"Pu\u014fkto",
    "gn:population":0,
    "gn:timezone":"Asia/Seoul",
    "iso:country":"KR",
    "name:und_x_variant":[
        "\ubd80\uc5b5\ub3c4",
        "Pu\u014fkto"
    ],
    "wof:name":"Puokto",
    "wof:placetype":"locality"
},
  "geometry": {"coordinates":[126.1327,36.6728],"type":"Point"}
}