{
  "type": "Feature",
  "properties": {
    "gn:admin1_code":"17.0",
    "gn:asciiname":"Kaemul",
    "gn:country_code":"KR",
    "gn:dem":62,
    "gn:feature_class":"P",
    "gn:feature_code":"PPL",
    "gn:name":"Kaemul",
    "gn:population":0,
    "gn:timezone":"Asia/Seoul",
    "iso:country":"KR",
    "name:und_x_variant":[
        "\uac1c\ubb3c",
        "Kaemul"
    ],
    "wof:name":"Kaemul",
    "wof:placetype":"locality"
},
  "geometry": {"coordinates":[126.608,36.5677],"type":"Point"}
}