{
  "type": "Feature",
  "properties": {
    "gn:admin1_code":"17.0",
    "gn:asciiname":"Wonsong-ni",
    "gn:country_code":"KR",
    "gn:dem":28,
    "gn:feature_class":"P",
    "gn:feature_code":"PPL",
    "gn:name":"W\u014fns\u014fng-ni",
    "gn:population":0,
    "gn:timezone":"Asia/Seoul",
    "iso:country":"KR",
    "name:eng_x_preferred":[
        "Wonsong"
    ],
    "name:eng_x_variant":[
        "Wonsong-ni"
    ],
    "name:und_x_variant":[
        "\uc6d0\uc131\ub9ac",
        "W\u014fns\u014fng-ni"
    ],
    "wof:name":"Wonsong",
    "wof:placetype":"locality"
},
  "geometry": {"coordinates":[127.00149999999999,36.3308],"type":"Point"}
}