{
  "type": "Feature",
  "properties": {
    "gn:admin1_code":"20.0",
    "gn:asciiname":"Yorang-ni",
    "gn:country_code":"KR",
    "gn:dem":74,
    "gn:feature_class":"P",
    "gn:feature_code":"PPL",
    "gn:name":"Y\u014frang-ni",
    "gn:population":0,
    "gn:timezone":"Asia/Seoul",
    "iso:country":"KR",
    "wof:name":"Yorang-ni",
    "wof:placetype":"locality"
},
  "geometry": {"coordinates":[129.10556,35.30722],"type":"Point"}
}