{
  "type": "Feature",
  "properties": {
    "gn:admin1_code":"13.0",
    "gn:asciiname":"Kkotbongmal",
    "gn:country_code":"KR",
    "gn:dem":38,
    "gn:feature_class":"P",
    "gn:feature_code":"PPL",
    "gn:name":"Kkotbongmal",
    "gn:population":0,
    "gn:timezone":"Asia/Seoul",
    "iso:country":"KR",
    "name:kor_x_preferred":[
        "\uaf43\ubd09\ub9d0"
    ],
    "wof:name":"Kkotbongmal",
    "wof:placetype":"locality"
},
  "geometry": {"coordinates":[127.0256,37.99957],"type":"Point"}
}