{
  "type": "Feature",
  "properties": {
    "gn:admin1_code":"3.0",
    "gn:asciiname":"Samyu-ri",
    "gn:country_code":"KR",
    "gn:dem":358,
    "gn:feature_class":"P",
    "gn:feature_code":"PPLL",
    "gn:name":"Samyu-ri",
    "gn:population":0,
    "gn:timezone":"Asia/Seoul",
    "iso:country":"KR",
    "name:und_x_variant":[
        "\uc0bc\uc720\ub9ac",
        "Samyu-ri"
    ],
    "wof:name":"Samyu-ri",
    "wof:placetype":"locality"
},
  "geometry": {"coordinates":[127.61306999999999,35.91215],"type":"Point"}
}