{
  "type": "Feature",
  "properties": {
    "gn:admin1_code":"6.0",
    "gn:asciiname":"Mak-kol",
    "gn:country_code":"KR",
    "gn:dem":516,
    "gn:feature_class":"P",
    "gn:feature_code":"PPL",
    "gn:name":"Mak-kol",
    "gn:population":0,
    "gn:timezone":"Asia/Seoul",
    "iso:country":"KR",
    "name:kor_x_preferred":[
        "\ub9c9\uace8"
    ],
    "wof:name":"Mak-kol",
    "wof:placetype":"locality"
},
  "geometry": {"coordinates":[128.7388,37.186],"type":"Point"}
}