{
  "type": "Feature",
  "properties": {
    "gn:admin1_code":"16.0",
    "gn:asciiname":"Sosikp'o",
    "gn:country_code":"KR",
    "gn:dem":29,
    "gn:feature_class":"P",
    "gn:feature_code":"PPL",
    "gn:name":"Sosikp\u2019o",
    "gn:population":0,
    "gn:timezone":"Asia/Seoul",
    "iso:country":"KR",
    "name:kor_x_preferred":[
        "Sosikp\u2019o"
    ],
    "wof:name":"Sosikp'o",
    "wof:placetype":"locality"
},
  "geometry": {"coordinates":[126.67055999999999,34.32583],"type":"Point"}
}