{
  "type": "Feature",
  "properties": {
    "gn:admin1_code":"13.0",
    "gn:asciiname":"Yuldong",
    "gn:country_code":"KR",
    "gn:dem":64,
    "gn:feature_class":"P",
    "gn:feature_code":"PPL",
    "gn:name":"Yuldong",
    "gn:population":0,
    "gn:timezone":"Asia/Seoul",
    "iso:country":"KR",
    "name:kor_x_preferred":[
        "\uc728\ub3d9"
    ],
    "name:und_x_variant":[
        "\ubc30\ubbf8",
        "Baemi",
        "Paemi",
        "Yuldong"
    ],
    "wof:name":"Yuldong",
    "wof:placetype":"locality"
},
  "geometry": {"coordinates":[127.1825,37.03722],"type":"Point"}
}