{
  "type": "Feature",
  "properties": {
    "gn:admin1_code":"3.0",
    "gn:asciiname":"Chakso",
    "gn:country_code":"KR",
    "gn:dem":149,
    "gn:feature_class":"P",
    "gn:feature_code":"PPL",
    "gn:name":"Chakso",
    "gn:population":0,
    "gn:timezone":"Asia/Seoul",
    "iso:country":"KR",
    "name:und_x_variant":[
        "\uc791\uc18c",
        "Chakso",
        "Jakso"
    ],
    "wof:name":"Chakso",
    "wof:placetype":"locality"
},
  "geometry": {"coordinates":[127.39036000000002,35.51063],"type":"Point"}
}