{
  "type": "Feature",
  "properties": {
    "iso:country":"KR",
    "qs:name":"\ucd08\ub2f9\ub3d9",
    "qs:name_adm0":"\ud55c\uad6d",
    "qs:name_adm1":"\uac15\uc6d0\ub3c4",
    "qs:photos":120,
    "qs:photos_1k":24,
    "qs:photos_9k":1,
    "qs:photos_9r":3,
    "qs:photos_all":120,
    "qs:photos_sr":3,
    "qs:placetype":"LocalAdmin",
    "qs:pop_sr":"0",
    "wof:name":"\ucd08\ub2f9\ub3d9",
    "wof:placetype":"localadmin"
},
  "geometry": {"coordinates":[128.91316599999999,37.786166],"type":"Point"}
}