{
  "type": "Feature",
  "properties": {
    "gn:admin1_code":"13.0",
    "gn:asciiname":"Wolpa",
    "gn:country_code":"KR",
    "gn:dem":106,
    "gn:feature_class":"P",
    "gn:feature_code":"PPL",
    "gn:name":"Wolpa",
    "gn:population":0,
    "gn:timezone":"Asia/Seoul",
    "iso:country":"KR",
    "name:und_x_variant":[
        "\uc6d4\ud30c",
        "Wolpa",
        "W\u014flp\u2019a"
    ],
    "wof:name":"Wolpa",
    "wof:placetype":"locality"
},
  "geometry": {"coordinates":[127.64444,37.49583],"type":"Point"}
}