{
  "type": "Feature",
  "properties": {
    "gn:admin1_code":"20.0",
    "gn:asciiname":"Odun-gol",
    "gn:country_code":"KR",
    "gn:dem":51,
    "gn:feature_class":"P",
    "gn:feature_code":"PPL",
    "gn:name":"\u014edun-gol",
    "gn:population":0,
    "gn:timezone":"Asia/Seoul",
    "iso:country":"KR",
    "name:und_x_variant":[
        "\uc5b4\ub454\uace8",
        "\u014edun-gol"
    ],
    "wof:name":"Odun-gol",
    "wof:placetype":"locality"
},
  "geometry": {"coordinates":[128.29594,34.76035],"type":"Point"}
}