{
  "type": "Feature",
  "properties": {
    "gn:admin1_code":"14.0",
    "gn:asciiname":"Yongheung",
    "gn:country_code":"KR",
    "gn:dem":101,
    "gn:feature_class":"P",
    "gn:feature_code":"PPL",
    "gn:name":"Yongheung",
    "gn:population":0,
    "gn:timezone":"Asia/Seoul",
    "iso:country":"KR",
    "name:kor_x_preferred":[
        "\uc6a9\ud765"
    ],
    "wof:name":"Yongheung",
    "wof:placetype":"locality"
},
  "geometry": {"coordinates":[128.50364999999999,36.59514],"type":"Point"}
}