{
  "type": "Feature",
  "properties": {
    "gn:admin1_code":"17.0",
    "gn:asciiname":"Bamgye",
    "gn:country_code":"KR",
    "gn:dem":58,
    "gn:feature_class":"P",
    "gn:feature_code":"PPL",
    "gn:name":"Bamgye",
    "gn:population":0,
    "gn:timezone":"Asia/Seoul",
    "iso:country":"KR",
    "name:kor_x_preferred":[
        "\ubc24\uacc4"
    ],
    "wof:name":"Bamgye",
    "wof:placetype":"locality"
},
  "geometry": {"coordinates":[126.88500999999999,36.63536],"type":"Point"}
}