{
  "type": "Feature",
  "properties": {
    "gn:admin1_code":"6.0",
    "gn:asciiname":"Podong",
    "gn:country_code":"KR",
    "gn:dem":187,
    "gn:feature_class":"P",
    "gn:feature_code":"PPL",
    "gn:name":"P\u014fd\u014fng",
    "gn:population":0,
    "gn:timezone":"Asia/Seoul",
    "iso:country":"KR",
    "name:kor_x_preferred":[
        "\ubc84\ub369"
    ],
    "name:kor_x_variant":[
        "P\u014fd\u014fng"
    ],
    "wof:name":"Podong",
    "wof:placetype":"locality"
},
  "geometry": {"coordinates":[127.87739999999999,37.2211],"type":"Point"}
}