{
  "type": "Feature",
  "properties": {
    "gn:admin1_code":"17.0",
    "gn:asciiname":"Puhaejong",
    "gn:country_code":"KR",
    "gn:dem":14,
    "gn:feature_class":"P",
    "gn:feature_code":"PPL",
    "gn:name":"Puhaej\u014fng",
    "gn:population":0,
    "gn:timezone":"Asia/Seoul",
    "iso:country":"KR",
    "name:und_x_variant":[
        "\ubd80\ud574\uc815",
        "Puhaej\u014fng"
    ],
    "wof:name":"Puhaejong",
    "wof:placetype":"locality"
},
  "geometry": {"coordinates":[126.5269,36.5888],"type":"Point"}
}