{
  "type": "Feature",
  "properties": {
    "gn:country":"KR",
    "gn:fcode":"PPL",
    "gn:population":0,
    "iso:country":"KR",
    "name:eng_x_preferred":[
        "Sujin 2(i)-dong"
    ],
    "name:kor_x_preferred":[
        "\uc218\uc9c42\ub3d9"
    ],
    "name:und_x_variant":[
        "\uc218\uc9c4\ub3d9"
    ],
    "qs:name":"\uc218\uc9c42\ub3d9",
    "qs:name_adm0":"\ud55c\uad6d",
    "qs:name_adm1":"\uacbd\uae30\ub3c4",
    "qs:photos":184,
    "qs:photos_1k":37,
    "qs:photos_9k":1,
    "qs:photos_9r":4,
    "qs:photos_all":184,
    "qs:photos_sr":4,
    "qs:placetype":"Suburb",
    "qs:pop_sr":"0",
    "wof:name":"Sujin 2(i)-dong",
    "wof:placetype":"neighbourhood",
    "wof:population":0
},
  "geometry": {"coordinates":[127.13083,37.4375],"type":"Point"}
}