{
  "type": "Feature",
  "properties": {
    "gn:admin1_code":"13.0",
    "gn:asciiname":"Yaksan",
    "gn:country_code":"KR",
    "gn:dem":14,
    "gn:feature_class":"P",
    "gn:feature_code":"PPL",
    "gn:name":"Yaksan",
    "gn:population":0,
    "gn:timezone":"Asia/Seoul",
    "iso:country":"KR",
    "name:und_x_variant":[
        "\uc57d\uc0b0",
        "Yaksan"
    ],
    "wof:name":"Yaksan",
    "wof:placetype":"locality"
},
  "geometry": {"coordinates":[126.56871,37.62504000000001],"type":"Point"}
}