{
  "type": "Feature",
  "properties": {
    "gn:admin1_code":"13.0",
    "gn:asciiname":"Myongdong-ni",
    "gn:country_code":"KR",
    "gn:dem":167,
    "gn:feature_class":"P",
    "gn:feature_code":"PPLL",
    "gn:name":"My\u014fngd\u014fng-ni",
    "gn:population":0,
    "gn:timezone":"Asia/Seoul",
    "iso:country":"KR",
    "name:kor_x_preferred":[
        "\uba85\ub355\ub9ac"
    ],
    "name:kor_x_variant":[
        "My\u014fngd\u014fng-ni"
    ],
    "wof:name":"Myongdong-ni",
    "wof:placetype":"locality"
},
  "geometry": {"coordinates":[127.2792,37.88161],"type":"Point"}
}