{
  "type": "Feature",
  "properties": {
    "gn:admin1_code":"6.0",
    "gn:asciiname":"Songmul-li",
    "gn:country_code":"KR",
    "gn:dem":578,
    "gn:feature_class":"P",
    "gn:feature_code":"PPLL",
    "gn:name":"S\u014fngmul-li",
    "gn:population":0,
    "gn:timezone":"Asia/Seoul",
    "iso:country":"KR",
    "name:kor_x_preferred":[
        "\uc11d\ubb38\ub9ac"
    ],
    "name:kor_x_variant":[
        "S\u014fngmul-li"
    ],
    "wof:name":"Songmul-li",
    "wof:placetype":"locality"
},
  "geometry": {"coordinates":[128.23536999999999,37.54042000000001],"type":"Point"}
}