{
  "type": "Feature",
  "properties": {
    "gn:admin1_code":"13.0",
    "gn:asciiname":"Jeindong",
    "gn:country_code":"KR",
    "gn:dem":75,
    "gn:feature_class":"P",
    "gn:feature_code":"PPL",
    "gn:name":"Jeindong",
    "gn:population":0,
    "gn:timezone":"Asia/Seoul",
    "iso:country":"KR",
    "name:kor_x_preferred":[
        "\uc7ac\uc778\ub3d9"
    ],
    "wof:name":"Jeindong",
    "wof:placetype":"locality"
},
  "geometry": {"coordinates":[127.22938000000001,37.11196],"type":"Point"}
}