{
  "type": "Feature",
  "properties": {
    "gn:admin1_code":"3.0",
    "gn:asciiname":"Kombuk",
    "gn:country_code":"KR",
    "gn:dem":292,
    "gn:feature_class":"P",
    "gn:feature_code":"PPL",
    "gn:name":"K\u014fmbuk",
    "gn:population":0,
    "gn:timezone":"Asia/Seoul",
    "iso:country":"KR",
    "name:und_x_variant":[
        "\uac80\ubd81",
        "K\u014fmbuk"
    ],
    "wof:name":"Kombuk",
    "wof:placetype":"locality"
},
  "geometry": {"coordinates":[127.44516000000002,35.81237],"type":"Point"}
}