{
  "type": "Feature",
  "properties": {
    "gn:admin1_code":"0.0",
    "gn:asciiname":"Tonggye-ri",
    "gn:cc2":"KR",
    "gn:country_code":"KR",
    "gn:dem":5,
    "gn:feature_class":"P",
    "gn:feature_code":"PPL",
    "gn:name":"Tonggye-ri",
    "gn:population":0,
    "gn:timezone":"Asia/Seoul",
    "iso:country":"KR",
    "name:und_x_variant":[
        "Tongge-ri",
        "Tonggye-ri"
    ],
    "wof:name":"Tonggye-ri",
    "wof:placetype":"locality"
},
  "geometry": {"coordinates":[126.93333,35.88333],"type":"Point"}
}