{
  "type": "Feature",
  "properties": {
    "gn:admin1_code":"6.0",
    "gn:asciiname":"Saemaul",
    "gn:country_code":"KR",
    "gn:dem":160,
    "gn:feature_class":"P",
    "gn:feature_code":"PPL",
    "gn:name":"Saema\u016dl",
    "gn:population":0,
    "gn:timezone":"Asia/Seoul",
    "iso:country":"KR",
    "name:kor_x_preferred":[
        "\uc0c8\ub9c8\uc744"
    ],
    "name:kor_x_variant":[
        "Saema\u016dl"
    ],
    "wof:name":"Saemaul",
    "wof:placetype":"locality"
},
  "geometry": {"coordinates":[127.7683,37.6226],"type":"Point"}
}