{
  "type": "Feature",
  "properties": {
    "gn:admin1_code":"5.0",
    "gn:asciiname":"Saijiwon",
    "gn:country_code":"KR",
    "gn:dem":186,
    "gn:feature_class":"P",
    "gn:feature_code":"PPL",
    "gn:name":"Saijiwon",
    "gn:population":0,
    "gn:timezone":"Asia/Seoul",
    "iso:country":"KR",
    "name:kor_x_preferred":[
        "\uc0ac\uc9c0\uc6d0"
    ],
    "name:kor_x_variant":[
        "Sajiw\u014fn"
    ],
    "wof:name":"Saijiwon",
    "wof:placetype":"locality"
},
  "geometry": {"coordinates":[128.43301,37.08001],"type":"Point"}
}