{
  "type": "Feature",
  "properties": {
    "gn:admin1_code":"3.0",
    "gn:asciiname":"Geonneomul",
    "gn:country_code":"KR",
    "gn:dem":57,
    "gn:feature_class":"P",
    "gn:feature_code":"PPL",
    "gn:name":"Geonneomul",
    "gn:population":0,
    "gn:timezone":"Asia/Seoul",
    "iso:country":"KR",
    "name:kor_x_preferred":[
        "\uac74\ub108\ubb3c"
    ],
    "wof:name":"Geonneomul",
    "wof:placetype":"locality"
},
  "geometry": {"coordinates":[126.65055,35.36231],"type":"Point"}
}