{
  "type": "Feature",
  "properties": {
    "gn:admin1_code":"20.0",
    "gn:asciiname":"Saesaet'o",
    "gn:country_code":"KR",
    "gn:dem":280,
    "gn:feature_class":"P",
    "gn:feature_code":"PPL",
    "gn:name":"Saesaet\u2019\u014f",
    "gn:population":0,
    "gn:timezone":"Asia/Seoul",
    "iso:country":"KR",
    "name:und_x_variant":[
        "\uc0c8\uc0c8\ud130",
        "Saesaet\u2019\u014f"
    ],
    "wof:name":"Saesaet'o",
    "wof:placetype":"locality"
},
  "geometry": {"coordinates":[127.95218,35.57045],"type":"Point"}
}