{
  "type": "Feature",
  "properties": {
    "gn:admin1_code":"14.0",
    "gn:asciiname":"Seommasil",
    "gn:country_code":"KR",
    "gn:dem":122,
    "gn:feature_class":"P",
    "gn:feature_code":"PPL",
    "gn:name":"Seommasil",
    "gn:population":0,
    "gn:timezone":"Asia/Seoul",
    "iso:country":"KR",
    "name:kor_x_preferred":[
        "\uc12c\ub9c8\uc2e4"
    ],
    "wof:name":"Seommasil",
    "wof:placetype":"locality"
},
  "geometry": {"coordinates":[128.78797,36.0389],"type":"Point"}
}