{
  "type": "Feature",
  "properties": {
    "gn:admin1_code":"6.0",
    "gn:asciiname":"Chumakko-ri",
    "gn:country_code":"KR",
    "gn:dem":236,
    "gn:feature_class":"P",
    "gn:feature_code":"PPL",
    "gn:name":"Chumakk\u014f-ri",
    "gn:population":0,
    "gn:timezone":"Asia/Seoul",
    "iso:country":"KR",
    "name:kor_x_preferred":[
        "\uc8fc\ub9c9\uac70\ub9ac"
    ],
    "name:kor_x_variant":[
        "Chumakk\u014f-ri"
    ],
    "wof:name":"Chumakko-ri",
    "wof:placetype":"locality"
},
  "geometry": {"coordinates":[127.9462,37.5771],"type":"Point"}
}