{
  "type": "Feature",
  "properties": {
    "gn:admin1_code":"5.0",
    "gn:asciiname":"Hyol-li",
    "gn:country_code":"KR",
    "gn:dem":110,
    "gn:feature_class":"P",
    "gn:feature_code":"PPL",
    "gn:name":"Hy\u014fl-li",
    "gn:population":0,
    "gn:timezone":"Asia/Seoul",
    "iso:country":"KR",
    "name:und_x_variant":[
        "Hy\u014fl-li",
        "\ud604\ub9ac",
        "Hy\u014fn-ni"
    ],
    "wof:name":"Hyol-li",
    "wof:placetype":"locality"
},
  "geometry": {"coordinates":[127.6366,36.243],"type":"Point"}
}