{
  "type": "Feature",
  "properties": {
    "gn:admin1_code":"6.0",
    "gn:asciiname":"Almyon",
    "gn:country_code":"KR",
    "gn:dem":368,
    "gn:feature_class":"P",
    "gn:feature_code":"PPL",
    "gn:name":"Almy\u014fn",
    "gn:population":0,
    "gn:timezone":"Asia/Seoul",
    "iso:country":"KR",
    "name:kor_x_preferred":[
        "\uc54c\uba74"
    ],
    "name:kor_x_variant":[
        "Almy\u014fn"
    ],
    "wof:name":"Almyon",
    "wof:placetype":"locality"
},
  "geometry": {"coordinates":[128.26910000000001,37.329],"type":"Point"}
}