{
  "type": "Feature",
  "properties": {
    "gn:admin1_code":"14.0",
    "gn:asciiname":"Odang",
    "gn:country_code":"KR",
    "gn:dem":189,
    "gn:feature_class":"P",
    "gn:feature_code":"PPL",
    "gn:name":"Odang",
    "gn:population":0,
    "gn:timezone":"Asia/Seoul",
    "iso:country":"KR",
    "name:und_x_variant":[
        "\uc624\ub2f9",
        "Odang"
    ],
    "wof:name":"Odang",
    "wof:placetype":"locality"
},
  "geometry": {"coordinates":[128.17323999999999,35.91316],"type":"Point"}
}