{
  "type": "Feature",
  "properties": {
    "gn:admin1_code":"13.0",
    "gn:asciiname":"Salgae-gol",
    "gn:country_code":"KR",
    "gn:dem":87,
    "gn:feature_class":"P",
    "gn:feature_code":"PPL",
    "gn:name":"Salgae-gol",
    "gn:population":0,
    "gn:timezone":"Asia/Seoul",
    "iso:country":"KR",
    "name:kor_x_preferred":[
        "\uc0b4\uac1c\uace8"
    ],
    "wof:name":"Salgae-gol",
    "wof:placetype":"locality"
},
  "geometry": {"coordinates":[127.57810000000001,37.111],"type":"Point"}
}