{
  "type": "Feature",
  "properties": {
    "gn:admin1_code":"13.0",
    "gn:asciiname":"Godonggol",
    "gn:country_code":"KR",
    "gn:dem":47,
    "gn:feature_class":"P",
    "gn:feature_code":"PPL",
    "gn:name":"Godonggol",
    "gn:population":0,
    "gn:timezone":"Asia/Seoul",
    "iso:country":"KR",
    "name:kor_x_preferred":[
        "\uace0\ub3d9\uace8"
    ],
    "wof:name":"Godonggol",
    "wof:placetype":"locality"
},
  "geometry": {"coordinates":[126.98567,38.11687],"type":"Point"}
}