{
  "type": "Feature",
  "properties": {
    "gn:admin1_code":"17.0",
    "gn:asciiname":"Chonggyong",
    "gn:country_code":"KR",
    "gn:dem":25,
    "gn:feature_class":"P",
    "gn:feature_code":"PPL",
    "gn:name":"Chonggy\u014fng",
    "gn:population":0,
    "gn:timezone":"Asia/Seoul",
    "iso:country":"KR",
    "name:und_x_variant":[
        "\uc885\uacbd",
        "Chonggy\u014fng-ni",
        "Chonggy\u014fng"
    ],
    "wof:name":"Chonggyong",
    "wof:placetype":"locality"
},
  "geometry": {"coordinates":[126.822,36.7323],"type":"Point"}
}