{
  "type": "Feature",
  "properties": {
    "gn:admin1_code":"20.0",
    "gn:asciiname":"Sono-ri",
    "gn:country_code":"KR",
    "gn:dem":44,
    "gn:feature_class":"P",
    "gn:feature_code":"PPL",
    "gn:name":"Sono-ri",
    "gn:population":0,
    "gn:timezone":"Asia/Seoul",
    "iso:country":"KR",
    "name:und_x_variant":[
        "\uc190\uc624\ub9ac",
        "Sono-ri"
    ],
    "wof:name":"Sono-ri",
    "wof:placetype":"locality"
},
  "geometry": {"coordinates":[128.36321999999998,35.47445],"type":"Point"}
}