{
  "type": "Feature",
  "properties": {
    "gn:admin1_code":"14.0",
    "gn:asciiname":"Mojeong",
    "gn:country_code":"KR",
    "gn:dem":32,
    "gn:feature_class":"P",
    "gn:feature_code":"PPL",
    "gn:name":"Mojeong",
    "gn:population":0,
    "gn:timezone":"Asia/Seoul",
    "iso:country":"KR",
    "name:kor_x_preferred":[
        "\ubaa8\uc815"
    ],
    "wof:name":"Mojeong",
    "wof:placetype":"locality"
},
  "geometry": {"coordinates":[129.29622000000001,35.95986],"type":"Point"}
}