{
  "type": "Feature",
  "properties": {
    "gn:admin1_code":"14.0",
    "gn:asciiname":"Salt'i",
    "gn:country_code":"KR",
    "gn:dem":332,
    "gn:feature_class":"P",
    "gn:feature_code":"PPL",
    "gn:name":"Salt\u2019i",
    "gn:population":0,
    "gn:timezone":"Asia/Seoul",
    "iso:country":"KR",
    "name:und_x_variant":[
        "\uc0b4\ud2f0",
        "Salt\u2019i"
    ],
    "wof:name":"Salt'i",
    "wof:placetype":"locality"
},
  "geometry": {"coordinates":[128.15097,35.9557],"type":"Point"}
}