{
  "type": "Feature",
  "properties": {
    "gn:admin1_code":"6.0",
    "gn:asciiname":"Tokkaesu",
    "gn:country_code":"KR",
    "gn:dem":626,
    "gn:feature_class":"P",
    "gn:feature_code":"PPL",
    "gn:name":"T\u014fkkaesu",
    "gn:population":0,
    "gn:timezone":"Asia/Seoul",
    "iso:country":"KR",
    "name:kor_x_preferred":[
        "\ub355\uac1c\uc218"
    ],
    "name:kor_x_variant":[
        "T\u014fkkaesu"
    ],
    "wof:name":"Tokkaesu",
    "wof:placetype":"locality"
},
  "geometry": {"coordinates":[128.434,37.5056],"type":"Point"}
}