{
  "type": "Feature",
  "properties": {
    "gn:admin1_code":"14.0",
    "gn:asciiname":"Unnorumogi",
    "gn:country_code":"KR",
    "gn:dem":496,
    "gn:feature_class":"P",
    "gn:feature_code":"PPL",
    "gn:name":"Unnorumogi",
    "gn:population":0,
    "gn:timezone":"Asia/Seoul",
    "iso:country":"KR",
    "name:und_x_variant":[
        "\uc6c3\ub178\ub8e8\ubaa9\uc774",
        "Unnorumogi"
    ],
    "wof:name":"Unnorumogi",
    "wof:placetype":"locality"
},
  "geometry": {"coordinates":[129.11009999999999,36.7827],"type":"Point"}
}