{
  "type": "Feature",
  "properties": {
    "gn:admin1_code":"14.0",
    "gn:asciiname":"Araeiraesil",
    "gn:country_code":"KR",
    "gn:dem":29,
    "gn:feature_class":"P",
    "gn:feature_code":"PPL",
    "gn:name":"Araeiraesil",
    "gn:population":0,
    "gn:timezone":"Asia/Seoul",
    "iso:country":"KR",
    "name:und_x_variant":[
        "\uc544\ub798\uc774\ub798\uc2e4",
        "Araeiraesil"
    ],
    "wof:name":"Araeiraesil",
    "wof:placetype":"locality"
},
  "geometry": {"coordinates":[129.3802,36.5782],"type":"Point"}
}