{
  "type": "Feature",
  "properties": {
    "gn:admin1_code":"13.0",
    "gn:admin2_code":"Ans\u014fng-si",
    "gn:asciiname":"Pyeongchondong",
    "gn:country_code":"KR",
    "gn:dem":85,
    "gn:feature_class":"P",
    "gn:feature_code":"PPL",
    "gn:name":"Pyeongchondong",
    "gn:population":0,
    "gn:timezone":"Asia/Seoul",
    "iso:country":"KR",
    "name:kor_x_preferred":[
        "\ud3c9\ucd0c\ub3d9"
    ],
    "name:kor_x_variant":[
        "P\u2019y\u014fngch\u2019on-dong"
    ],
    "wof:name":"Pyeongchondong",
    "wof:placetype":"locality"
},
  "geometry": {"coordinates":[127.46361,37.1025],"type":"Point"}
}