{
  "type": "Feature",
  "properties": {
    "gn:admin1_code":"6.0",
    "gn:asciiname":"Widoman-dong",
    "gn:country_code":"KR",
    "gn:dem":329,
    "gn:feature_class":"P",
    "gn:feature_code":"PPL",
    "gn:name":"Widoman-dong",
    "gn:population":0,
    "gn:timezone":"Asia/Seoul",
    "iso:country":"KR",
    "name:kor_x_preferred":[
        "\uc717\uc624\ub9cc\ub3d9"
    ],
    "wof:name":"Widoman-dong",
    "wof:placetype":"locality"
},
  "geometry": {"coordinates":[128.4075,37.2511],"type":"Point"}
}