{
  "type": "Feature",
  "properties": {
    "gn:admin1_code":"16.0",
    "gn:asciiname":"Ipbidong",
    "gn:country_code":"KR",
    "gn:dem":37,
    "gn:feature_class":"P",
    "gn:feature_code":"PPL",
    "gn:name":"Ipbidong",
    "gn:population":0,
    "gn:timezone":"Asia/Seoul",
    "iso:country":"KR",
    "name:kor_x_preferred":[
        "\uc785\ube44\ub3d9"
    ],
    "name:und_x_variant":[
        "Ippi-dong"
    ],
    "wof:name":"Ipbidong",
    "wof:placetype":"locality"
},
  "geometry": {"coordinates":[126.68546000000001,34.85077],"type":"Point"}
}