{
  "type": "Feature",
  "properties": {
    "gn:admin1_code":"14.0",
    "gn:asciiname":"Saebattteul",
    "gn:country_code":"KR",
    "gn:dem":61,
    "gn:feature_class":"P",
    "gn:feature_code":"PPL",
    "gn:name":"Saebattteul",
    "gn:population":0,
    "gn:timezone":"Asia/Seoul",
    "iso:country":"KR",
    "name:kor_x_preferred":[
        "\uc0c8\ubc2d\ub730"
    ],
    "wof:name":"Saebattteul",
    "wof:placetype":"locality"
},
  "geometry": {"coordinates":[129.21003000000002,35.79998],"type":"Point"}
}