{
  "type": "Feature",
  "properties": {
    "gn:admin1_code":"6.0",
    "gn:asciiname":"Omi",
    "gn:country_code":"KR",
    "gn:dem":140,
    "gn:feature_class":"P",
    "gn:feature_code":"PPL",
    "gn:name":"Omi",
    "gn:population":0,
    "gn:timezone":"Asia/Seoul",
    "iso:country":"KR",
    "name:ita_x_preferred":[
        "Omi"
    ],
    "name:kor_x_preferred":[
        "\uc624\ubbf8"
    ],
    "name:por_x_preferred":[
        "Omi"
    ],
    "name:rus_x_preferred":[
        "\u041e\u043c\u0438"
    ],
    "name:ukr_x_preferred":[
        "\u041e\u043c\u0456"
    ],
    "name:zho_x_preferred":[
        "\u81e3"
    ],
    "wof:name":"Omi",
    "wof:placetype":"locality"
},
  "geometry": {"coordinates":[127.9888,37.519],"type":"Point"}
}