{
  "type": "Feature",
  "properties": {
    "gn:admin1_code":"20.0",
    "gn:asciiname":"Ttakpat",
    "gn:country_code":"KR",
    "gn:dem":327,
    "gn:feature_class":"P",
    "gn:feature_code":"PPL",
    "gn:name":"Ttakpat",
    "gn:population":0,
    "gn:timezone":"Asia/Seoul",
    "iso:country":"KR",
    "name:und_x_variant":[
        "\ub531\ubc2d",
        "Ttakpat"
    ],
    "wof:name":"Ttakpat",
    "wof:placetype":"locality"
},
  "geometry": {"coordinates":[128.00696000000002,35.58841],"type":"Point"}
}