{
  "type": "Feature",
  "properties": {
    "gn:admin1_code":"17.0",
    "gn:asciiname":"Moriul",
    "gn:country_code":"KR",
    "gn:dem":43,
    "gn:feature_class":"P",
    "gn:feature_code":"PPL",
    "gn:name":"Moriul",
    "gn:population":0,
    "gn:timezone":"Asia/Seoul",
    "iso:country":"KR",
    "name:und_x_variant":[
        "\ubaa8\ub9ac\uc6b8",
        "Moriul"
    ],
    "wof:name":"Moriul",
    "wof:placetype":"locality"
},
  "geometry": {"coordinates":[126.6187,36.4633],"type":"Point"}
}