{
  "type": "Feature",
  "properties": {
    "gn:admin1_code":"3.0",
    "gn:asciiname":"Hyoja-ch'on",
    "gn:country_code":"KR",
    "gn:dem":416,
    "gn:feature_class":"P",
    "gn:feature_code":"PPL",
    "gn:name":"Hyoja-ch\u2019on",
    "gn:population":0,
    "gn:timezone":"Asia/Seoul",
    "iso:country":"KR",
    "name:und_x_variant":[
        "\ud6a8\uc790\ucd0c",
        "Hyoja-ch\u2019on"
    ],
    "wof:name":"Hyoja-ch'on",
    "wof:placetype":"locality"
},
  "geometry": {"coordinates":[127.65295,35.87184],"type":"Point"}
}