{
  "type": "Feature",
  "properties": {
    "gn:admin1_code":"20.0",
    "gn:asciiname":"Um-ch'on",
    "gn:country_code":"KR",
    "gn:dem":17,
    "gn:feature_class":"P",
    "gn:feature_code":"PPL",
    "gn:name":"\u016cm-ch\u2019on",
    "gn:population":0,
    "gn:timezone":"Asia/Seoul",
    "iso:country":"KR",
    "name:und_x_variant":[
        "\uc74c\ucd0c",
        "\u016cm-ch\u2019on"
    ],
    "wof:name":"Um-ch'on",
    "wof:placetype":"locality"
},
  "geometry": {"coordinates":[128.44496000000001,34.88648],"type":"Point"}
}