{
  "type": "Feature",
  "properties": {
    "gn:admin1_code":"6.0",
    "gn:asciiname":"Maeunt'ang-gol",
    "gn:country_code":"KR",
    "gn:dem":103,
    "gn:feature_class":"P",
    "gn:feature_code":"PPL",
    "gn:name":"Maeunt\u2019ang-gol",
    "gn:population":0,
    "gn:timezone":"Asia/Seoul",
    "iso:country":"KR",
    "name:und_x_variant":[
        "\ub9e4\uc6b4\ud0d5\uace8",
        "Maeunt\u2019ang-gol"
    ],
    "wof:name":"Maeunt'ang-gol",
    "wof:placetype":"locality"
},
  "geometry": {"coordinates":[127.66379999999999,37.9666],"type":"Point"}
}