{
  "type": "Feature",
  "properties": {
    "gn:admin1_code":"10.0",
    "gn:asciiname":"Baenamugol",
    "gn:country_code":"KR",
    "gn:dem":94,
    "gn:feature_class":"P",
    "gn:feature_code":"PPL",
    "gn:name":"Baenamugol",
    "gn:population":0,
    "gn:timezone":"Asia/Seoul",
    "iso:country":"KR",
    "name:kor_x_preferred":[
        "\ubc30\ub098\ubb34\uace8"
    ],
    "wof:name":"Baenamugol",
    "wof:placetype":"locality"
},
  "geometry": {"coordinates":[129.11802,35.31115],"type":"Point"}
}