{
  "type": "Feature",
  "properties": {
    "gn:admin1_code":"14.0",
    "gn:asciiname":"Araech'amnamusil",
    "gn:country_code":"KR",
    "gn:dem":370,
    "gn:feature_class":"P",
    "gn:feature_code":"PPL",
    "gn:name":"Araech\u2019amnamusil",
    "gn:population":0,
    "gn:timezone":"Asia/Seoul",
    "iso:country":"KR",
    "name:und_x_variant":[
        "\uc544\ub798\ucc38\ub098\ubb34\uc2e4",
        "Araech\u2019amnamusil"
    ],
    "wof:name":"Araech'amnamusil",
    "wof:placetype":"locality"
},
  "geometry": {"coordinates":[128.85509999999999,36.3105],"type":"Point"}
}