{
  "type": "Feature",
  "properties": {
    "gn:country":"KR",
    "gn:fcode":"ADM3",
    "gn:pop":0,
    "iso:country":"KR",
    "name:eng_x_preferred":[
        "Okcheon-eup"
    ],
    "name:kor_x_preferred":[
        "\uc625\ucc9c\uc74d"
    ],
    "name:unk_x_variant":[
        "\uc625\ucc9c\uc74d"
    ],
    "qs:name":"Okch\u2019\u014fn-\u016dp",
    "qs:photos_9r":0,
    "qs:photos_sr":0,
    "qs:pop_sr":"0",
    "wof:name":"Okch\u2019\u014fn-\u016dp",
    "wof:placetype":"localadmin",
    "wof:population":0
},
  "geometry": {"coordinates":[127.5919,36.30363],"type":"Point"}
}