{
  "type": "Feature",
  "properties": {
    "gn:admin1_code":"17.0",
    "gn:asciiname":"Tokkosil",
    "gn:country_code":"KR",
    "gn:dem":205,
    "gn:feature_class":"P",
    "gn:feature_code":"PPL",
    "gn:name":"Tokkosil",
    "gn:population":0,
    "gn:timezone":"Asia/Seoul",
    "iso:country":"KR",
    "name:und_x_variant":[
        "\ub3c5\uace0\uc2e4",
        "Tokkosil"
    ],
    "wof:name":"Tokkosil",
    "wof:placetype":"locality"
},
  "geometry": {"coordinates":[126.86669999999999,36.4515],"type":"Point"}
}