{
  "type": "Feature",
  "properties": {
    "gn:admin1_code":"6.0",
    "gn:asciiname":"Yo-gol",
    "gn:country_code":"KR",
    "gn:dem":130,
    "gn:feature_class":"P",
    "gn:feature_code":"PPL",
    "gn:name":"Yo-gol",
    "gn:population":0,
    "gn:timezone":"Asia/Seoul",
    "iso:country":"KR",
    "name:kor_x_preferred":[
        "\uc694\uace8"
    ],
    "wof:name":"Yo-gol",
    "wof:placetype":"locality"
},
  "geometry": {"coordinates":[127.8879,37.3421],"type":"Point"}
}