{
  "type": "Feature",
  "properties": {
    "gn:admin1_code":"17.0",
    "gn:asciiname":"Mujong",
    "gn:cc2":"KR",
    "gn:country_code":"KR",
    "gn:dem":42,
    "gn:feature_class":"P",
    "gn:feature_code":"PPL",
    "gn:name":"Muj\u014fng",
    "gn:population":0,
    "gn:timezone":"Asia/Seoul",
    "iso:country":"KR",
    "name:und_x_variant":[
        "Muj\u014fng-ni",
        "Muj\u014fng"
    ],
    "wof:name":"Mujong",
    "wof:placetype":"locality"
},
  "geometry": {"coordinates":[126.78333000000001,36.23333],"type":"Point"}
}