{
  "type": "Feature",
  "properties": {
    "gn:admin1_code":"13.0",
    "gn:admin2_code":"P'aju-si",
    "gn:asciiname":"Garaeul",
    "gn:country_code":"KR",
    "gn:dem":14,
    "gn:feature_class":"P",
    "gn:feature_code":"PPL",
    "gn:name":"Garaeul",
    "gn:population":0,
    "gn:timezone":"Asia/Seoul",
    "iso:country":"KR",
    "name:kor_x_preferred":[
        "\uac00\ub798\uc6b8"
    ],
    "name:und_x_variant":[
        "Karaeul"
    ],
    "wof:name":"Garaeul",
    "wof:placetype":"locality"
},
  "geometry": {"coordinates":[126.75355,37.84262],"type":"Point"}
}