{
  "type": "Feature",
  "properties": {
    "gn:admin1_code":"16.0",
    "gn:asciiname":"Namgye",
    "gn:country_code":"KR",
    "gn:dem":121,
    "gn:feature_class":"P",
    "gn:feature_code":"PPL",
    "gn:name":"Namgye",
    "gn:population":0,
    "gn:timezone":"Asia/Seoul",
    "iso:country":"KR",
    "name:kor_x_preferred":[
        "\ub0a8\uacc4"
    ],
    "wof:name":"Namgye",
    "wof:placetype":"locality"
},
  "geometry": {"coordinates":[126.63536999999999,35.2761],"type":"Point"}
}