{
  "type": "Feature",
  "properties": {
    "gn:admin1_code":"17.0",
    "gn:asciiname":"Gomjigi",
    "gn:country_code":"KR",
    "gn:dem":39,
    "gn:feature_class":"P",
    "gn:feature_code":"PPL",
    "gn:name":"Gomjigi",
    "gn:population":0,
    "gn:timezone":"Asia/Seoul",
    "iso:country":"KR",
    "name:kor_x_preferred":[
        "\uacf0\uc9c1\uc774"
    ],
    "wof:name":"Gomjigi",
    "wof:placetype":"locality"
},
  "geometry": {"coordinates":[127.1524,36.73945],"type":"Point"}
}