{
  "type": "Feature",
  "properties": {
    "gn:admin1_code":"6.0",
    "gn:asciiname":"Sinhung-dong",
    "gn:country_code":"KR",
    "gn:dem":611,
    "gn:feature_class":"P",
    "gn:feature_code":"PPL",
    "gn:name":"Sinh\u016dng-dong",
    "gn:population":0,
    "gn:timezone":"Asia/Seoul",
    "iso:country":"KR",
    "name:und_x_variant":[
        "\uc2e0\ud765\ub3d9",
        "Sinh\u016dng-dong"
    ],
    "wof:name":"Sinhung-dong",
    "wof:placetype":"locality"
},
  "geometry": {"coordinates":[129.00319999999999,37.1109],"type":"Point"}
}