{
  "type": "Feature",
  "properties": {
    "gn:admin1_code":"17.0",
    "gn:asciiname":"Mongsonggul",
    "gn:country_code":"KR",
    "gn:dem":39,
    "gn:feature_class":"P",
    "gn:feature_code":"PPL",
    "gn:name":"M\u014fngs\u014fnggul",
    "gn:population":0,
    "gn:timezone":"Asia/Seoul",
    "iso:country":"KR",
    "name:und_x_variant":[
        "\uba4d\uc131\uad74",
        "M\u014fngs\u014fnggul"
    ],
    "wof:name":"Mongsonggul",
    "wof:placetype":"locality"
},
  "geometry": {"coordinates":[126.7004,36.9252],"type":"Point"}
}