{
  "type": "Feature",
  "properties": {
    "gn:admin1_code":"13.0",
    "gn:asciiname":"Saemgol",
    "gn:country_code":"KR",
    "gn:dem":79,
    "gn:feature_class":"P",
    "gn:feature_code":"PPL",
    "gn:name":"Saemgol",
    "gn:population":0,
    "gn:timezone":"Asia/Seoul",
    "iso:country":"KR",
    "name:kor_x_preferred":[
        "\uc0d8\uace8"
    ],
    "name:und_x_variant":[
        "Saemgol"
    ],
    "wof:name":"Saemgol",
    "wof:placetype":"locality"
},
  "geometry": {"coordinates":[127.37050000000001,37.5359],"type":"Point"}
}