{
  "type": "Feature",
  "properties": {
    "gn:admin1_code":"14.0",
    "gn:asciiname":"Goraemudeom",
    "gn:country_code":"KR",
    "gn:dem":127,
    "gn:feature_class":"P",
    "gn:feature_code":"PPL",
    "gn:name":"Goraemudeom",
    "gn:population":0,
    "gn:timezone":"Asia/Seoul",
    "iso:country":"KR",
    "name:kor_x_preferred":[
        "\uace0\ub798\ubb34\ub364"
    ],
    "wof:name":"Goraemudeom",
    "wof:placetype":"locality"
},
  "geometry": {"coordinates":[128.26425,36.65928],"type":"Point"}
}