{
  "type": "Feature",
  "properties": {
    "gn:admin1_code":"6.0",
    "gn:asciiname":"Gwanggandong",
    "gn:country_code":"KR",
    "gn:dem":495,
    "gn:feature_class":"P",
    "gn:feature_code":"PPL",
    "gn:name":"Gwanggandong",
    "gn:population":0,
    "gn:timezone":"Asia/Seoul",
    "iso:country":"KR",
    "name:kor_x_preferred":[
        "\ubc29\uac04\ub9c8\uc744"
    ],
    "name:kor_x_variant":[
        "Panggan-ma\u016dl",
        "\uad11\uac04\ub3d9"
    ],
    "wof:name":"Gwanggandong",
    "wof:placetype":"locality"
},
  "geometry": {"coordinates":[128.11081999999999,37.86396],"type":"Point"}
}