{
  "type": "Feature",
  "properties": {
    "gn:admin1_code":"17.0",
    "gn:asciiname":"Won'gumam",
    "gn:country_code":"KR",
    "gn:dem":17,
    "gn:feature_class":"P",
    "gn:feature_code":"PPL",
    "gn:name":"W\u014fn\u2019g\u016dmam",
    "gn:population":0,
    "gn:timezone":"Asia/Seoul",
    "iso:country":"KR",
    "name:und_x_variant":[
        "\uc6d0\uae08\uc554",
        "W\u014fn\u2019g\u016dmam"
    ],
    "wof:name":"Won'gumam",
    "wof:placetype":"locality"
},
  "geometry": {"coordinates":[126.6427,36.9227],"type":"Point"}
}