{
  "type": "Feature",
  "properties": {
    "gn:admin1_code":"6.0",
    "gn:asciiname":"Koet'ol",
    "gn:country_code":"KR",
    "gn:dem":560,
    "gn:feature_class":"P",
    "gn:feature_code":"PPL",
    "gn:name":"Koet\u2019ol",
    "gn:population":0,
    "gn:timezone":"Asia/Seoul",
    "iso:country":"KR",
    "name:kor_x_preferred":[
        "\uad34\ud1a8"
    ],
    "name:kor_x_variant":[
        "Koet\u2019ol"
    ],
    "wof:name":"Koet'ol",
    "wof:placetype":"locality"
},
  "geometry": {"coordinates":[128.46010000000001,37.549],"type":"Point"}
}