{
  "type": "Feature",
  "properties": {
    "gn:admin1_code":"11.0",
    "gn:asciiname":"Songnaei-dong",
    "gn:country_code":"KR",
    "gn:dem":24,
    "gn:feature_class":"P",
    "gn:feature_code":"PPL",
    "gn:name":"S\u014fngnaei-dong",
    "gn:population":0,
    "gn:timezone":"Asia/Seoul",
    "iso:country":"KR",
    "name:und_x_variant":[
        "\uc131\ub0b42\ub3d9",
        "S\u014fngnaei-dong"
    ],
    "wof:name":"Songnaei-dong",
    "wof:placetype":"locality"
},
  "geometry": {"coordinates":[127.12774,37.53432],"type":"Point"}
}