{
  "type": "Feature",
  "properties": {
    "gn:admin1_code":"3.0",
    "gn:asciiname":"Sainam",
    "gn:country_code":"KR",
    "gn:dem":337,
    "gn:feature_class":"P",
    "gn:feature_code":"PPL",
    "gn:name":"Sainam",
    "gn:population":0,
    "gn:timezone":"Asia/Seoul",
    "iso:country":"KR",
    "name:und_x_variant":[
        "\uc0ac\uc778\uc554",
        "Sainam"
    ],
    "wof:name":"Sainam",
    "wof:placetype":"locality"
},
  "geometry": {"coordinates":[127.35330999999999,35.83497],"type":"Point"}
}