{
  "type": "Feature",
  "properties": {
    "gn:admin1_code":"6.0",
    "gn:admin2_code":"Ch'\u014frw\u014fn-gun",
    "gn:asciiname":"Pori",
    "gn:country_code":"KR",
    "gn:dem":223,
    "gn:feature_class":"P",
    "gn:feature_code":"PPL",
    "gn:name":"Pori",
    "gn:population":0,
    "gn:timezone":"Asia/Seoul",
    "iso:country":"KR",
    "name:kor_x_preferred":[
        "\ud3ec\ub9ac"
    ],
    "name:und_x_variant":[
        "P\u2019o-ri"
    ],
    "wof:name":"Pori",
    "wof:placetype":"locality"
},
  "geometry": {"coordinates":[127.22313,38.26769],"type":"Point"}
}