{
  "type": "Feature",
  "properties": {
    "gn:admin1_code":"5.0",
    "gn:asciiname":"Saetcheoni",
    "gn:country_code":"KR",
    "gn:dem":93,
    "gn:feature_class":"P",
    "gn:feature_code":"PPL",
    "gn:name":"Saetcheoni",
    "gn:population":0,
    "gn:timezone":"Asia/Seoul",
    "iso:country":"KR",
    "name:kor_x_preferred":[
        "\uc0db\ucc9c\uc774"
    ],
    "name:kor_x_variant":[
        "Saetch\u2019\u014fni"
    ],
    "wof:name":"Saetcheoni",
    "wof:placetype":"locality"
},
  "geometry": {"coordinates":[127.61411,37.03477],"type":"Point"}
}