{
  "type": "Feature",
  "properties": {
    "gn:admin1_code":"10.0",
    "gn:asciiname":"Subongdo",
    "gn:country_code":"KR",
    "gn:dem":2,
    "gn:feature_class":"P",
    "gn:feature_code":"PPL",
    "gn:name":"Subongdo",
    "gn:population":0,
    "gn:timezone":"Asia/Seoul",
    "iso:country":"KR",
    "name:kor_x_preferred":[
        "\uc218\ubd09\ub3c4"
    ],
    "wof:name":"Subongdo",
    "wof:placetype":"locality"
},
  "geometry": {"coordinates":[128.9212,35.15132],"type":"Point"}
}