{
  "type": "Feature",
  "properties": {
    "gn:admin1_code":"5.0",
    "gn:asciiname":"Wonga",
    "gn:country_code":"KR",
    "gn:dem":93,
    "gn:feature_class":"P",
    "gn:feature_code":"PPL",
    "gn:name":"Wonga",
    "gn:population":0,
    "gn:timezone":"Asia/Seoul",
    "iso:country":"KR",
    "name:deu_x_preferred":[
        "Wonga"
    ],
    "name:kor_x_preferred":[
        "\uc6d0\uac00"
    ],
    "wof:name":"Wonga",
    "wof:placetype":"locality"
},
  "geometry": {"coordinates":[127.37829000000001,36.74063],"type":"Point"}
}