{
  "type": "Feature",
  "properties": {
    "gn:admin1_code":"6.0",
    "gn:asciiname":"Yudari-gol",
    "gn:country_code":"KR",
    "gn:dem":412,
    "gn:feature_class":"P",
    "gn:feature_code":"PPL",
    "gn:name":"Yudari-gol",
    "gn:population":0,
    "gn:timezone":"Asia/Seoul",
    "iso:country":"KR",
    "name:kor_x_preferred":[
        "\uc720\ub2e4\ub9ac\uace8"
    ],
    "wof:name":"Yudari-gol",
    "wof:placetype":"locality"
},
  "geometry": {"coordinates":[128.08067,37.24802],"type":"Point"}
}