{
  "type": "Feature",
  "properties": {
    "iso:country":"KR",
    "name:eng_x_preferred":[
        "Samsan-Myeon"
    ],
    "name:eng_x_variant":[
        "Samsanmyeon",
        "Samsan-Myeon"
    ],
    "name:kor_x_preferred":[
        "\uc0bc\uc0b0\uba74"
    ],
    "name:unk_x_variant":[
        "\uc0bc\uc0b0\uba74"
    ],
    "qs:gn_adm0_cc":"KR",
    "qs:gn_local":1843564,
    "qs:local_max":2394,
    "qs:local_sum":10431,
    "qs:localhoods":47,
    "qs:name":"\uc0bc\uc0b0\uba74",
    "qs:name_adm0":"\ud55c\uad6d",
    "qs:name_adm1":"\uc778\ucc9c",
    "qs:name_adm2":"\uac15\ud654\uad70",
    "qs:name_en":"Samsan-Myeon",
    "qs:name_lau":"\uc0bc\uc0b0\uba74",
    "qs:name_local":"\uc778\ucc9c",
    "qs:photo_max":49,
    "qs:photo_sum":132,
    "qs:placetype":"Suburb",
    "qs:quad_count":12,
    "qs:woe_adm0":23424868,
    "qs:woe_adm1":20069922,
    "qs:woe_adm2":28289161,
    "qs:woe_lau":28806429,
    "qs:woe_local":1132496,
    "qs:woe_ver":"7.10.0",
    "wof:lang":[
        "kor"
    ],
    "wof:name":"\uc0bc\uc0b0\uba74",
    "wof:placetype":"neighbourhood"
},
  "geometry": {"coordinates":[126.325451,37.689558],"type":"Point"}
}