{
  "type": "Feature",
  "properties": {
    "gn:admin1_code":"14.0",
    "gn:asciiname":"Seommaeul",
    "gn:country_code":"KR",
    "gn:dem":63,
    "gn:feature_class":"P",
    "gn:feature_code":"PPL",
    "gn:name":"Seommaeul",
    "gn:population":0,
    "gn:timezone":"Asia/Seoul",
    "iso:country":"KR",
    "name:kor_x_preferred":[
        "\uc12c\ub9c8\uc744"
    ],
    "wof:name":"Seommaeul",
    "wof:placetype":"locality"
},
  "geometry": {"coordinates":[128.83775,35.94244000000001],"type":"Point"}
}