{
  "type": "Feature",
  "properties": {
    "gn:admin1_code":"14.0",
    "gn:asciiname":"Kusal-li",
    "gn:country_code":"KR",
    "gn:dem":320,
    "gn:feature_class":"P",
    "gn:feature_code":"PPL",
    "gn:name":"Kusal-li",
    "gn:population":0,
    "gn:timezone":"Asia/Seoul",
    "iso:country":"KR",
    "name:und_x_variant":[
        "Ky\u016bsan-d\u014d",
        "Kusan-dong",
        "Kusan-ri",
        "Kusan",
        "\uad6c\uc0b0\ub9ac",
        "Kusal-li"
    ],
    "wof:name":"Kusal-li",
    "wof:placetype":"locality"
},
  "geometry": {"coordinates":[128.89641,36.27544],"type":"Point"}
}