{
  "type": "Feature",
  "properties": {
    "gn:admin1_code":"17.0",
    "gn:asciiname":"Jungnojang",
    "gn:country_code":"KR",
    "gn:dem":51,
    "gn:feature_class":"P",
    "gn:feature_code":"PPL",
    "gn:name":"Jungnojang",
    "gn:population":0,
    "gn:timezone":"Asia/Seoul",
    "iso:country":"KR",
    "name:kor_x_preferred":[
        "\uc911\ub178\uc7a5"
    ],
    "wof:name":"Jungnojang",
    "wof:placetype":"locality"
},
  "geometry": {"coordinates":[127.27427,36.65914],"type":"Point"}
}