{
  "type": "Feature",
  "properties": {
    "gn:admin1_code":"16.0",
    "gn:asciiname":"Jinsan",
    "gn:country_code":"KR",
    "gn:dem":146,
    "gn:feature_class":"P",
    "gn:feature_code":"PPL",
    "gn:name":"Jinsan",
    "gn:population":0,
    "gn:timezone":"Asia/Seoul",
    "iso:country":"KR",
    "name:kor_x_preferred":[
        "\uc9c4\uc0b0"
    ],
    "name:und_x_variant":[
        "Chinsan",
        "Jinsan"
    ],
    "wof:name":"Jinsan",
    "wof:placetype":"locality"
},
  "geometry": {"coordinates":[127.20739,34.91433],"type":"Point"}
}