{
  "type": "Feature",
  "properties": {
    "gn:admin1_code":"14.0",
    "gn:asciiname":"Goriseom",
    "gn:country_code":"KR",
    "gn:dem":6,
    "gn:feature_class":"P",
    "gn:feature_code":"PPL",
    "gn:name":"Goriseom",
    "gn:population":0,
    "gn:timezone":"Asia/Seoul",
    "iso:country":"KR",
    "name:kor_x_preferred":[
        "\uace0\ub9ac\uc12c"
    ],
    "wof:name":"Goriseom",
    "wof:placetype":"locality"
},
  "geometry": {"coordinates":[129.49254999999999,35.77922],"type":"Point"}
}