{
  "type": "Feature",
  "properties": {
    "gn:admin1_code":"14.0",
    "gn:asciiname":"Sanmaeul",
    "gn:country_code":"KR",
    "gn:dem":72,
    "gn:feature_class":"P",
    "gn:feature_code":"PPL",
    "gn:name":"Sanmaeul",
    "gn:population":0,
    "gn:timezone":"Asia/Seoul",
    "iso:country":"KR",
    "name:kor_x_preferred":[
        "\uc0b0\ub9c8\uc744"
    ],
    "wof:name":"Sanmaeul",
    "wof:placetype":"locality"
},
  "geometry": {"coordinates":[128.26627999999999,36.58745],"type":"Point"}
}