{
  "type": "Feature",
  "properties": {
    "gn:admin1_code":"17.0",
    "gn:asciiname":"Ch'anghyon",
    "gn:country_code":"KR",
    "gn:dem":13,
    "gn:feature_class":"P",
    "gn:feature_code":"PPL",
    "gn:name":"Ch\u2019anghy\u014fn",
    "gn:population":0,
    "gn:timezone":"Asia/Seoul",
    "iso:country":"KR",
    "name:und_x_variant":[
        "Ch\u2019anggogae",
        "Ch\u2019anghy\u014fn",
        "\ucc3d\ud604"
    ],
    "wof:name":"Ch'anghyon",
    "wof:placetype":"locality"
},
  "geometry": {"coordinates":[126.9385,36.3289],"type":"Point"}
}