{
  "type": "Feature",
  "properties": {
    "gn:admin1_code":"14.0",
    "gn:asciiname":"Songch'on",
    "gn:country_code":"KR",
    "gn:dem":53,
    "gn:feature_class":"P",
    "gn:feature_code":"PPL",
    "gn:name":"Songch\u2019\u014fn",
    "gn:population":0,
    "gn:timezone":"Asia/Seoul",
    "iso:country":"KR",
    "name:und_x_variant":[
        "Songch\u2019\u014fn-dong",
        "Songch\u2019\u014fn",
        "\uc1a1\ucc9c"
    ],
    "wof:name":"Songch'on",
    "wof:placetype":"locality"
},
  "geometry": {"coordinates":[128.36222000000001,36.28944],"type":"Point"}
}