{
  "type": "Feature",
  "properties": {
    "gn:admin1_code":"12.0",
    "gn:asciiname":"Dwinnamsangol",
    "gn:country_code":"KR",
    "gn:dem":32,
    "gn:feature_class":"P",
    "gn:feature_code":"PPL",
    "gn:name":"Dwinnamsangol",
    "gn:population":0,
    "gn:timezone":"Asia/Seoul",
    "iso:country":"KR",
    "name:kor_x_preferred":[
        "\ub4b7\ub0a8\uc0b0\uace8"
    ],
    "wof:name":"Dwinnamsangol",
    "wof:placetype":"locality"
},
  "geometry": {"coordinates":[126.47955,37.74511],"type":"Point"}
}