{
  "type": "Feature",
  "properties": {
    "gn:admin1_code":"13.0",
    "gn:asciiname":"Jonggok",
    "gn:country_code":"KR",
    "gn:dem":155,
    "gn:feature_class":"P",
    "gn:feature_code":"PPL",
    "gn:name":"Jonggok",
    "gn:population":0,
    "gn:timezone":"Asia/Seoul",
    "iso:country":"KR",
    "name:kor_x_preferred":[
        "\uc885\uace1"
    ],
    "name:und_x_variant":[
        "\uc885\uace1",
        "Jonggok"
    ],
    "wof:name":"Jonggok",
    "wof:placetype":"locality"
},
  "geometry": {"coordinates":[127.49838,37.71552],"type":"Point"}
}