{
  "type": "Feature",
  "properties": {
    "gn:admin1_code":"16.0",
    "gn:asciiname":"Sinwondong",
    "gn:country_code":"KR",
    "gn:dem":21,
    "gn:feature_class":"P",
    "gn:feature_code":"PPL",
    "gn:name":"Sinwondong",
    "gn:population":0,
    "gn:timezone":"Asia/Seoul",
    "iso:country":"KR",
    "name:kor_x_preferred":[
        "\uc2e0\uc6d0\ub3d9"
    ],
    "wof:name":"Sinwondong",
    "wof:placetype":"locality"
},
  "geometry": {"coordinates":[126.71198,34.94904],"type":"Point"}
}