{
  "type": "Feature",
  "properties": {
    "gn:admin1_code":"13.0",
    "gn:asciiname":"Yeossidong",
    "gn:country_code":"KR",
    "gn:dem":41,
    "gn:feature_class":"P",
    "gn:feature_code":"PPL",
    "gn:name":"Yeossidong",
    "gn:population":0,
    "gn:timezone":"Asia/Seoul",
    "iso:country":"KR",
    "name:kor_x_preferred":[
        "\uc5ec\uc528\ub3d9"
    ],
    "wof:name":"Yeossidong",
    "wof:placetype":"locality"
},
  "geometry": {"coordinates":[126.96359,38.02387],"type":"Point"}
}