{
  "type": "Feature",
  "properties": {
    "gn:admin1_code":"16.0",
    "gn:asciiname":"Ponggok",
    "gn:cc2":"KR",
    "gn:country_code":"KR",
    "gn:dem":4,
    "gn:feature_class":"P",
    "gn:feature_code":"PPL",
    "gn:name":"Ponggok",
    "gn:population":0,
    "gn:timezone":"Asia/Seoul",
    "iso:country":"KR",
    "name:und_x_variant":[
        "Ponggong-ni",
        "Ponggok"
    ],
    "wof:name":"Ponggok",
    "wof:placetype":"locality"
},
  "geometry": {"coordinates":[126.59999999999999,34.98333],"type":"Point"}
}