{
  "type": "Feature",
  "properties": {
    "gn:admin1_code":"13.0",
    "gn:asciiname":"Hasam",
    "gn:country_code":"KR",
    "gn:dem":93,
    "gn:feature_class":"P",
    "gn:feature_code":"PPL",
    "gn:name":"Hasam",
    "gn:population":0,
    "gn:timezone":"Asia/Seoul",
    "iso:country":"KR",
    "name:und_x_variant":[
        "\ud558\uc0bc",
        "Hasam"
    ],
    "wof:name":"Hasam",
    "wof:placetype":"locality"
},
  "geometry": {"coordinates":[127.0954,37.8112],"type":"Point"}
}