{
  "type": "Feature",
  "properties": {
    "gn:admin1_code":"20.0",
    "gn:asciiname":"Ch'ilsong",
    "gn:country_code":"KR",
    "gn:dem":65,
    "gn:feature_class":"P",
    "gn:feature_code":"PPL",
    "gn:name":"Ch\u2019ils\u014fng",
    "gn:population":0,
    "gn:timezone":"Asia/Seoul",
    "iso:country":"KR",
    "name:und_x_variant":[
        "\uce60\uc131",
        "Ch\u2019ils\u014fng"
    ],
    "wof:name":"Ch'ilsong",
    "wof:placetype":"locality"
},
  "geometry": {"coordinates":[128.32308,35.1454],"type":"Point"}
}