{
  "type": "Feature",
  "properties": {
    "gn:admin1_code":"12.0",
    "gn:asciiname":"Jeorarae",
    "gn:country_code":"KR",
    "gn:dem":39,
    "gn:feature_class":"P",
    "gn:feature_code":"PPL",
    "gn:name":"Jeorarae",
    "gn:population":0,
    "gn:timezone":"Asia/Seoul",
    "iso:country":"KR",
    "name:kor_x_preferred":[
        "\uc808\uc544\ub798"
    ],
    "name:kor_x_variant":[
        "Ch\u014frarae"
    ],
    "wof:name":"Jeorarae",
    "wof:placetype":"locality"
},
  "geometry": {"coordinates":[126.30096,37.77504],"type":"Point"}
}