{
  "type": "Feature",
  "properties": {
    "gn:admin1_code":"6.0",
    "gn:asciiname":"Eondeokgae",
    "gn:country_code":"KR",
    "gn:dem":125,
    "gn:feature_class":"P",
    "gn:feature_code":"PPL",
    "gn:name":"Eondeokgae",
    "gn:population":0,
    "gn:timezone":"Asia/Seoul",
    "iso:country":"KR",
    "name:kor_x_preferred":[
        "\uc5b8\ub355\uac1c"
    ],
    "wof:name":"Eondeokgae",
    "wof:placetype":"locality"
},
  "geometry": {"coordinates":[127.76253,37.96201],"type":"Point"}
}