{
  "type": "Feature",
  "properties": {
    "gn:admin1_code":"14.0",
    "gn:asciiname":"Jeongandong",
    "gn:country_code":"KR",
    "gn:dem":476,
    "gn:feature_class":"P",
    "gn:feature_code":"PPL",
    "gn:name":"Jeongandong",
    "gn:population":0,
    "gn:timezone":"Asia/Seoul",
    "iso:country":"KR",
    "name:kor_x_preferred":[
        "\uc815\uc548\ub3d9"
    ],
    "wof:name":"Jeongandong",
    "wof:placetype":"locality"
},
  "geometry": {"coordinates":[128.49511000000001,36.93171],"type":"Point"}
}