{
  "type": "Feature",
  "properties": {
    "gn:admin1_code":"17.0",
    "gn:asciiname":"Twigum-mal",
    "gn:country_code":"KR",
    "gn:dem":82,
    "gn:feature_class":"P",
    "gn:feature_code":"PPL",
    "gn:name":"Twigum-mal",
    "gn:population":0,
    "gn:timezone":"Asia/Seoul",
    "iso:country":"KR",
    "name:und_x_variant":[
        "\ub4a4\uad7d\ub9d0",
        "Twigum-mal"
    ],
    "wof:name":"Twigum-mal",
    "wof:placetype":"locality"
},
  "geometry": {"coordinates":[126.8532,36.6606],"type":"Point"}
}