{
  "type": "Feature",
  "properties": {
    "gn:admin1_code":"16.0",
    "gn:asciiname":"Eomsudong",
    "gn:country_code":"KR",
    "gn:dem":77,
    "gn:feature_class":"P",
    "gn:feature_code":"PPL",
    "gn:name":"Eomsudong",
    "gn:population":0,
    "gn:timezone":"Asia/Seoul",
    "iso:country":"KR",
    "name:kor_x_preferred":[
        "Y\u014fmsu"
    ],
    "name:kor_x_variant":[
        "\uc5c4\uc218\ub3d9"
    ],
    "wof:name":"Eomsudong",
    "wof:placetype":"locality"
},
  "geometry": {"coordinates":[126.72,34.32694],"type":"Point"}
}