{
  "type": "Feature",
  "properties": {
    "gn:country":"KR",
    "gn:fcode":"PPL",
    "gn:pop":0,
    "iso:country":"KR",
    "name:chi_x_preferred":[
        "\u76c6\u5510\u6d1e"
    ],
    "name:eng_x_preferred":[
        "Bundang-dong"
    ],
    "name:kor_x_preferred":[
        "\ubd84\ub2f9\ub3d9"
    ],
    "name:per_x_preferred":[
        "\u0628\u0648\u0646\u062f\u0627\u0646\u06af-\u062f\u0648\u0646\u06af"
    ],
    "name:unk_x_variant":[
        "Bundang-dong"
    ],
    "qs:name":"\ubd84\ub2f9\ub3d9",
    "qs:name_adm0":"\ud55c\uad6d",
    "qs:name_adm1":"\uacbd\uae30\ub3c4",
    "qs:photos":1,
    "qs:photos_1k":1,
    "qs:photos_9k":1,
    "qs:photos_9r":1,
    "qs:photos_all":1,
    "qs:photos_sr":1,
    "qs:placetype":"Suburb",
    "qs:pop_sr":"0",
    "wof:name":"\ubd84\ub2f9\ub3d9",
    "wof:placetype":"neighbourhood",
    "wof:population":0
},
  "geometry": {"coordinates":[127.14333000000001,37.36917],"type":"Point"}
}