{
  "type": "Feature",
  "properties": {
    "gn:admin1_code":"21.0",
    "gn:asciiname":"Pyeongcheon",
    "gn:country_code":"KR",
    "gn:dem":30,
    "gn:feature_class":"P",
    "gn:feature_code":"PPL",
    "gn:name":"Pyeongcheon",
    "gn:population":0,
    "gn:timezone":"Asia/Seoul",
    "iso:country":"KR",
    "name:kor_x_preferred":[
        "\ud3c9\ucc9c"
    ],
    "wof:name":"Pyeongcheon",
    "wof:placetype":"locality"
},
  "geometry": {"coordinates":[129.22024999999999,35.56208],"type":"Point"}
}