{
  "type": "Feature",
  "properties": {
    "gn:admin1_code":"6.0",
    "gn:asciiname":"Suri-gol",
    "gn:country_code":"KR",
    "gn:dem":37,
    "gn:feature_class":"P",
    "gn:feature_code":"PPL",
    "gn:name":"Suri-gol",
    "gn:population":0,
    "gn:timezone":"Asia/Seoul",
    "iso:country":"KR",
    "name:und_x_variant":[
        "\uc218\ub9ac\uace8",
        "Suri-gol"
    ],
    "wof:name":"Suri-gol",
    "wof:placetype":"locality"
},
  "geometry": {"coordinates":[129.21090000000001,37.3864],"type":"Point"}
}