{
  "type": "Feature",
  "properties": {
    "gn:admin1_code":"16.0",
    "gn:asciiname":"Wonma",
    "gn:country_code":"KR",
    "gn:dem":9,
    "gn:feature_class":"P",
    "gn:feature_code":"PPL",
    "gn:name":"Wonma",
    "gn:population":0,
    "gn:timezone":"Asia/Seoul",
    "iso:country":"KR",
    "name:kor_x_preferred":[
        "\uc6d0\ub9c8"
    ],
    "name:und_x_variant":[
        "W\u014fnma-ri",
        "W\u014fnma",
        "Wonma"
    ],
    "wof:name":"Wonma",
    "wof:placetype":"locality"
},
  "geometry": {"coordinates":[126.14230999999999,34.7742],"type":"Point"}
}