{
  "type": "Feature",
  "properties": {
    "gn:admin1_code":"13.0",
    "gn:asciiname":"Eoryongdong",
    "gn:country_code":"KR",
    "gn:dem":119,
    "gn:feature_class":"P",
    "gn:feature_code":"PPL",
    "gn:name":"Eoryongdong",
    "gn:population":0,
    "gn:timezone":"Asia/Seoul",
    "iso:country":"KR",
    "name:kor_x_preferred":[
        "\uc5b4\ub8e1\ub3d9"
    ],
    "wof:name":"Eoryongdong",
    "wof:placetype":"locality"
},
  "geometry": {"coordinates":[127.18145,37.88621],"type":"Point"}
}