{
  "type": "Feature",
  "properties": {
    "gn:admin1_code":"13.0",
    "gn:asciiname":"Anmal",
    "gn:country_code":"KR",
    "gn:dem":102,
    "gn:feature_class":"P",
    "gn:feature_code":"PPL",
    "gn:name":"Anmal",
    "gn:population":0,
    "gn:timezone":"Asia/Seoul",
    "iso:country":"KR",
    "name:und_x_variant":[
        "\uc548\ub9d0",
        "Anmal"
    ],
    "wof:name":"Anmal",
    "wof:placetype":"locality"
},
  "geometry": {"coordinates":[126.9936,37.8176],"type":"Point"}
}