{
  "type": "Feature",
  "properties": {
    "gn:admin1_code":"20.0",
    "gn:asciiname":"Pongchong",
    "gn:country_code":"KR",
    "gn:dem":106,
    "gn:feature_class":"P",
    "gn:feature_code":"PPL",
    "gn:name":"Pongchong",
    "gn:population":0,
    "gn:timezone":"Asia/Seoul",
    "iso:country":"KR",
    "name:und_x_variant":[
        "H\u014dson",
        "Pongchong",
        "Pongch\u2019on"
    ],
    "wof:name":"Pongchong",
    "wof:placetype":"locality"
},
  "geometry": {"coordinates":[128.01667,34.76667],"type":"Point"}
}