{
  "type": "Feature",
  "properties": {
    "gn:admin1_code":"5.0",
    "gn:asciiname":"Sokorani",
    "gn:country_code":"KR",
    "gn:dem":258,
    "gn:feature_class":"P",
    "gn:feature_code":"PPL",
    "gn:name":"Sokorani",
    "gn:population":0,
    "gn:timezone":"Asia/Seoul",
    "iso:country":"KR",
    "name:kor_x_preferred":[
        "\uc18c\ucf54\ub780\uc774"
    ],
    "name:kor_x_variant":[
        "Sok\u2019orani"
    ],
    "wof:name":"Sokorani",
    "wof:placetype":"locality"
},
  "geometry": {"coordinates":[128.25953000000001,37.054],"type":"Point"}
}