{
  "type": "Feature",
  "properties": {
    "gn:admin1_code":"17.0",
    "gn:asciiname":"Paet'ogo-ri",
    "gn:country_code":"KR",
    "gn:dem":14,
    "gn:feature_class":"P",
    "gn:feature_code":"PPL",
    "gn:name":"Paet\u2019\u014fg\u014f-ri",
    "gn:population":0,
    "gn:timezone":"Asia/Seoul",
    "iso:country":"KR",
    "name:und_x_variant":[
        "\ubc30\ud130\uac70\ub9ac",
        "Paet\u2019\u014fg\u014f-ri"
    ],
    "wof:name":"Paet'ogo-ri",
    "wof:placetype":"locality"
},
  "geometry": {"coordinates":[127.0134,36.8003],"type":"Point"}
}