{
  "type": "Feature",
  "properties": {
    "gn:admin1_code":"16.0",
    "gn:asciiname":"Gurim",
    "gn:country_code":"KR",
    "gn:dem":9,
    "gn:feature_class":"P",
    "gn:feature_code":"PPL",
    "gn:name":"Gurim",
    "gn:population":0,
    "gn:timezone":"Asia/Seoul",
    "iso:country":"KR",
    "name:kor_x_preferred":[
        "\uad6c\ub9bc"
    ],
    "name:und_x_variant":[
        "Gurim-ri",
        "Kurim-ni",
        "Gurim"
    ],
    "wof:name":"Gurim",
    "wof:placetype":"locality"
},
  "geometry": {"coordinates":[126.32805999999999,34.72944],"type":"Point"}
}