{
  "type": "Feature",
  "properties": {
    "gn:admin1_code":"20.0",
    "gn:asciiname":"Puch'ul-li",
    "gn:country_code":"KR",
    "gn:dem":191,
    "gn:feature_class":"P",
    "gn:feature_code":"PPL",
    "gn:name":"Puch\u2019ul-li",
    "gn:population":0,
    "gn:timezone":"Asia/Seoul",
    "iso:country":"KR",
    "wof:name":"Puch'ul-li",
    "wof:placetype":"locality"
},
  "geometry": {"coordinates":[127.65694000000001,35.17472],"type":"Point"}
}