{
  "type": "Feature",
  "properties": {
    "gn:admin1_code":"16.0",
    "gn:asciiname":"Chungdo-ri",
    "gn:country_code":"KR",
    "gn:dem":-9999,
    "gn:feature_class":"P",
    "gn:feature_code":"PPL",
    "gn:name":"Chungdo-ri",
    "gn:population":0,
    "gn:timezone":"Asia/Seoul",
    "iso:country":"KR",
    "name:und_x_variant":[
        "Kungt\u2019aedo-ri",
        "Chungdo-ri",
        "T\u2019aejungdo",
        "Chungt\u2019aedo-ri"
    ],
    "wof:name":"Chungdo-ri",
    "wof:placetype":"locality"
},
  "geometry": {"coordinates":[125.28333000000001,34.41667],"type":"Point"}
}