{
  "type": "Feature",
  "properties": {
    "gn:admin1_code":"16.0",
    "gn:asciiname":"Noktu",
    "gn:country_code":"KR",
    "gn:dem":15,
    "gn:feature_class":"P",
    "gn:feature_code":"PPL",
    "gn:name":"Noktu",
    "gn:population":0,
    "gn:timezone":"Asia/Seoul",
    "iso:country":"KR",
    "name:kor_x_preferred":[
        "\ub0a8\ucd0c"
    ],
    "name:kor_x_variant":[
        "Namch\u2019on"
    ],
    "name:und_x_variant":[
        "Rokut\u014d",
        "Namch\u2019on-ni",
        "Noktu"
    ],
    "wof:name":"Noktu",
    "wof:placetype":"locality"
},
  "geometry": {"coordinates":[127.14858,34.52899],"type":"Point"}
}