{
  "type": "Feature",
  "properties": {
    "gn:admin1_code":"14.0",
    "gn:asciiname":"Yakjeon",
    "gn:country_code":"KR",
    "gn:dem":22,
    "gn:feature_class":"P",
    "gn:feature_code":"PPL",
    "gn:name":"Yakjeon",
    "gn:population":0,
    "gn:timezone":"Asia/Seoul",
    "iso:country":"KR",
    "name:kor_x_preferred":[
        "\uc57d\uc804"
    ],
    "wof:name":"Yakjeon",
    "wof:placetype":"locality"
},
  "geometry": {"coordinates":[129.54748000000001,35.9877],"type":"Point"}
}