{
  "type": "Feature",
  "properties": {
    "gn:admin1_code":"14.0",
    "gn:asciiname":"Supt'o",
    "gn:country_code":"KR",
    "gn:dem":341,
    "gn:feature_class":"P",
    "gn:feature_code":"PPL",
    "gn:name":"Supt\u2019\u014f",
    "gn:population":0,
    "gn:timezone":"Asia/Seoul",
    "iso:country":"KR",
    "name:und_x_variant":[
        "\uc232\ud130",
        "Supt\u2019\u014f"
    ],
    "wof:name":"Supt'o",
    "wof:placetype":"locality"
},
  "geometry": {"coordinates":[128.99940000000001,36.9044],"type":"Point"}
}