{
  "type": "Feature",
  "properties": {
    "gn:admin1_code":"14.0",
    "gn:asciiname":"Yanggalbaegi",
    "gn:country_code":"KR",
    "gn:dem":206,
    "gn:feature_class":"P",
    "gn:feature_code":"PPL",
    "gn:name":"Yanggalbaegi",
    "gn:population":0,
    "gn:timezone":"Asia/Seoul",
    "iso:country":"KR",
    "name:kor_x_preferred":[
        "\uc591\uac08\ubc30\uae30"
    ],
    "wof:name":"Yanggalbaegi",
    "wof:placetype":"locality"
},
  "geometry": {"coordinates":[128.66848999999999,36.77046],"type":"Point"}
}