{
  "type": "Feature",
  "properties": {
    "gn:admin1_code":"3.0",
    "gn:asciiname":"Kahang",
    "gn:country_code":"KR",
    "gn:dem":511,
    "gn:feature_class":"P",
    "gn:feature_code":"PPL",
    "gn:name":"Kahang",
    "gn:population":0,
    "gn:timezone":"Asia/Seoul",
    "iso:country":"KR",
    "name:und_x_variant":[
        "\uac00\ud56d",
        "Kahang"
    ],
    "wof:name":"Kahang",
    "wof:placetype":"locality"
},
  "geometry": {"coordinates":[127.56468,35.76453],"type":"Point"}
}