{
  "type": "Feature",
  "properties": {
    "iso:country":"KR",
    "name:eng_x_preferred":[
        "Sangseo-myeon"
    ],
    "name:kor_x_preferred":[
        "\uc0c1\uc11c\uba74"
    ],
    "qs:name":"\uc0c1\uc11c\uba74",
    "qs:name_adm0":"\ud55c\uad6d",
    "qs:name_adm1":"\uac15\uc6d0\ub3c4",
    "qs:photos":1,
    "qs:photos_1k":1,
    "qs:photos_9k":1,
    "qs:photos_9r":1,
    "qs:photos_all":1,
    "qs:photos_sr":1,
    "qs:placetype":"LocalAdmin",
    "qs:pop_sr":"0",
    "wof:name":"Sangseo-myeon",
    "wof:placetype":"localadmin"
},
  "geometry": {"coordinates":[127.731685,38.095727],"type":"Point"}
}