{
  "type": "Feature",
  "properties": {
    "gn:admin1_code":"16.0",
    "gn:asciiname":"Bukjin",
    "gn:country_code":"KR",
    "gn:dem":-9999,
    "gn:feature_class":"P",
    "gn:feature_code":"PPL",
    "gn:name":"Bukjin",
    "gn:population":0,
    "gn:timezone":"Asia/Seoul",
    "iso:country":"KR",
    "name:kor_x_preferred":[
        "\ubd81\uc9c4"
    ],
    "name:und_x_variant":[
        "Hokushin-ri",
        "Pukchin-ni",
        "Pukchin",
        "Bukjin"
    ],
    "wof:name":"Bukjin",
    "wof:placetype":"locality"
},
  "geometry": {"coordinates":[126.1259,34.79524],"type":"Point"}
}