{
  "type": "Feature",
  "properties": {
    "gn:admin1_code":"6.0",
    "gn:asciiname":"Sangyangji",
    "gn:country_code":"KR",
    "gn:dem":187,
    "gn:feature_class":"P",
    "gn:feature_code":"PPL",
    "gn:name":"Sangyangji",
    "gn:population":0,
    "gn:timezone":"Asia/Seoul",
    "iso:country":"KR",
    "name:und_x_variant":[
        "\uc0c1\uc591\uc9c0",
        "Sangyangji"
    ],
    "wof:name":"Sangyangji",
    "wof:placetype":"locality"
},
  "geometry": {"coordinates":[127.64,38.16167],"type":"Point"}
}