{
  "type": "Feature",
  "properties": {
    "gn:admin1_code":"17.0",
    "gn:asciiname":"Chang-dong",
    "gn:country_code":"KR",
    "gn:dem":34,
    "gn:feature_class":"P",
    "gn:feature_code":"PPL",
    "gn:name":"Chang-dong",
    "gn:population":0,
    "gn:timezone":"Asia/Seoul",
    "iso:country":"KR",
    "name:fas_x_preferred":[
        "\u0686\u0627\u0646\u06af-\u062f\u0648\u0646\u06af"
    ],
    "name:kor_x_preferred":[
        "\ucc3d\ub3d9"
    ],
    "name:msa_x_preferred":[
        "Chang-dong"
    ],
    "name:tha_x_preferred":[
        "\u0e41\u0e02\u0e27\u0e07\u0e0a\u0e31\u0e07"
    ],
    "name:und_x_variant":[
        "\uc7a5\ub3d9"
    ],
    "name:vie_x_preferred":[
        "Chang-dong"
    ],
    "wof:name":"Chang-dong",
    "wof:placetype":"locality"
},
  "geometry": {"coordinates":[126.2512,36.7873],"type":"Point"}
}