{
  "type": "Feature",
  "properties": {
    "gn:admin1_code":"13.0",
    "gn:asciiname":"Sinjil-li",
    "gn:country_code":"KR",
    "gn:dem":63,
    "gn:feature_class":"P",
    "gn:feature_code":"PPLL",
    "gn:name":"Sinjil-li",
    "gn:population":0,
    "gn:timezone":"Asia/Seoul",
    "iso:country":"KR",
    "name:und_x_variant":[
        "\uc2e0\uc9c4\ub9ac",
        "Sinjin-ri",
        "Sinjil-li"
    ],
    "wof:name":"Sinjil-li",
    "wof:placetype":"locality"
},
  "geometry": {"coordinates":[127.66139,37.27639],"type":"Point"}
}