{
  "type": "Feature",
  "properties": {
    "gn:admin1_code":"6.0",
    "gn:asciiname":"Guamdong",
    "gn:country_code":"KR",
    "gn:dem":192,
    "gn:feature_class":"P",
    "gn:feature_code":"PPL",
    "gn:name":"Guamdong",
    "gn:population":0,
    "gn:timezone":"Asia/Seoul",
    "iso:country":"KR",
    "name:und_x_variant":[
        "\uad6c\uc554\ub3d9",
        "Kuam-dong",
        "Guamdong"
    ],
    "wof:name":"Guamdong",
    "wof:placetype":"locality"
},
  "geometry": {"coordinates":[127.75196,37.79161],"type":"Point"}
}