{
  "type": "Feature",
  "properties": {
    "gn:admin1_code":"3.0",
    "gn:asciiname":"Ch'ongok",
    "gn:country_code":"KR",
    "gn:dem":682,
    "gn:feature_class":"P",
    "gn:feature_code":"PPL",
    "gn:name":"Ch\u2019\u014fngok",
    "gn:population":0,
    "gn:timezone":"Asia/Seoul",
    "iso:country":"KR",
    "name:und_x_variant":[
        "\uccad\uc625",
        "Ch\u2019\u014fngok"
    ],
    "wof:name":"Ch'ongok",
    "wof:placetype":"locality"
},
  "geometry": {"coordinates":[127.61378000000001,35.62448],"type":"Point"}
}