{
  "type": "Feature",
  "properties": {
    "gn:admin1_code":"17.0",
    "gn:asciiname":"Oejik",
    "gn:country_code":"KR",
    "gn:dem":37,
    "gn:feature_class":"P",
    "gn:feature_code":"PPL",
    "gn:name":"Oejik",
    "gn:population":0,
    "gn:timezone":"Asia/Seoul",
    "iso:country":"KR",
    "name:und_x_variant":[
        "\uc678\uc9c1",
        "Oejik"
    ],
    "wof:name":"Oejik",
    "wof:placetype":"locality"
},
  "geometry": {"coordinates":[126.96299999999999,36.3701],"type":"Point"}
}