{
  "type": "Feature",
  "properties": {
    "gn:admin1_code":"13.0",
    "gn:asciiname":"Utdomachi",
    "gn:country_code":"KR",
    "gn:dem":56,
    "gn:feature_class":"P",
    "gn:feature_code":"PPL",
    "gn:name":"Utdomachi",
    "gn:population":0,
    "gn:timezone":"Asia/Seoul",
    "iso:country":"KR",
    "name:und_x_variant":[
        "\uc6c3\ub3c4\ub9c8\uce58",
        "Utdomachi",
        "Uttomach\u2019i"
    ],
    "wof:name":"Utdomachi",
    "wof:placetype":"locality"
},
  "geometry": {"coordinates":[127.27388999999999,37.46639],"type":"Point"}
}