{
  "type": "Feature",
  "properties": {
    "gn:admin1_code":"14.0",
    "gn:asciiname":"Araesungjang",
    "gn:country_code":"KR",
    "gn:dem":171,
    "gn:feature_class":"P",
    "gn:feature_code":"PPL",
    "gn:name":"Araes\u016dngjang",
    "gn:population":0,
    "gn:timezone":"Asia/Seoul",
    "iso:country":"KR",
    "name:und_x_variant":[
        "\uc544\ub798\uc2b9\uc7a5",
        "Araes\u016dngjang"
    ],
    "wof:name":"Araesungjang",
    "wof:placetype":"locality"
},
  "geometry": {"coordinates":[128.20750000000001,36.3624],"type":"Point"}
}