{
  "type": "Feature",
  "properties": {
    "gn:admin1_code":"13.0",
    "gn:asciiname":"Suyeok",
    "gn:country_code":"KR",
    "gn:dem":36,
    "gn:feature_class":"P",
    "gn:feature_code":"PPL",
    "gn:name":"Suyeok",
    "gn:population":0,
    "gn:timezone":"Asia/Seoul",
    "iso:country":"KR",
    "name:und_x_variant":[
        "\uc218\uc5ed",
        "Suyeok",
        "Suy\u014fk"
    ],
    "wof:name":"Suyeok",
    "wof:placetype":"locality"
},
  "geometry": {"coordinates":[127.18167,37.10639000000001],"type":"Point"}
}