{
  "type": "Feature",
  "properties": {
    "gn:admin1_code":"13.0",
    "gn:asciiname":"Yonam",
    "gn:country_code":"KR",
    "gn:dem":16,
    "gn:feature_class":"P",
    "gn:feature_code":"PPL",
    "gn:name":"Y\u014fnam",
    "gn:population":0,
    "gn:timezone":"Asia/Seoul",
    "iso:country":"KR",
    "name:und_x_variant":[
        "\uc5f0\uc554",
        "Y\u014fnam"
    ],
    "wof:name":"Yonam",
    "wof:placetype":"locality"
},
  "geometry": {"coordinates":[126.8481,36.9639],"type":"Point"}
}