{
  "type": "Feature",
  "properties": {
    "gn:admin1_code":"5.0",
    "gn:asciiname":"Yeonjeong",
    "gn:country_code":"KR",
    "gn:dem":93,
    "gn:feature_class":"P",
    "gn:feature_code":"PPL",
    "gn:name":"Yeonjeong",
    "gn:population":0,
    "gn:timezone":"Asia/Seoul",
    "iso:country":"KR",
    "name:kor_x_preferred":[
        "\uc5f0\uc815"
    ],
    "wof:name":"Yeonjeong",
    "wof:placetype":"locality"
},
  "geometry": {"coordinates":[127.61790000000001,36.74975],"type":"Point"}
}