{
  "type": "Feature",
  "properties": {
    "gn:admin1_code":"14.0",
    "gn:asciiname":"Subu-dong",
    "gn:country_code":"KR",
    "gn:dem":497,
    "gn:feature_class":"P",
    "gn:feature_code":"PPL",
    "gn:name":"Subu-dong",
    "gn:population":0,
    "gn:timezone":"Asia/Seoul",
    "iso:country":"KR",
    "name:und_x_variant":[
        "\uc218\ubd80\ub3d9",
        "Subu-dong"
    ],
    "wof:name":"Subu-dong",
    "wof:placetype":"locality"
},
  "geometry": {"coordinates":[127.95910000000001,36.0517],"type":"Point"}
}