{
  "type": "Feature",
  "properties": {
    "gn:admin1_code":"6.0",
    "gn:asciiname":"Komaru",
    "gn:country_code":"KR",
    "gn:dem":535,
    "gn:feature_class":"P",
    "gn:feature_code":"PPL",
    "gn:name":"Komaru",
    "gn:population":0,
    "gn:timezone":"Asia/Seoul",
    "iso:country":"KR",
    "name:kor_x_preferred":[
        "\uace0\ub9c8\ub8e8"
    ],
    "wof:name":"Komaru",
    "wof:placetype":"locality"
},
  "geometry": {"coordinates":[128.5256,37.2962],"type":"Point"}
}