{
  "type": "Feature",
  "properties": {
    "gn:admin1_code":"13.0",
    "gn:asciiname":"Pohoechon",
    "gn:country_code":"KR",
    "gn:dem":97,
    "gn:feature_class":"P",
    "gn:feature_code":"PPL",
    "gn:name":"Pohoechon",
    "gn:population":0,
    "gn:timezone":"Asia/Seoul",
    "iso:country":"KR",
    "name:kor_x_preferred":[
        "\ud3ec\ud68c\ucd0c"
    ],
    "name:kor_x_variant":[
        "P\u2019ohoe-ch\u2019on"
    ],
    "wof:name":"Pohoechon",
    "wof:placetype":"locality"
},
  "geometry": {"coordinates":[127.48506,37.80251],"type":"Point"}
}