{
  "type": "Feature",
  "properties": {
    "gn:admin1_code":"16.0",
    "gn:asciiname":"Jukpo",
    "gn:country_code":"KR",
    "gn:dem":173,
    "gn:feature_class":"P",
    "gn:feature_code":"PPL",
    "gn:name":"Jukpo",
    "gn:population":0,
    "gn:timezone":"Asia/Seoul",
    "iso:country":"KR",
    "name:kor_x_preferred":[
        "\uc8fd\ud3ec"
    ],
    "name:kor_x_variant":[
        "Chukp\u2019o"
    ],
    "wof:name":"Jukpo",
    "wof:placetype":"locality"
},
  "geometry": {"coordinates":[127.19378,34.88763],"type":"Point"}
}