{
  "type": "Feature",
  "properties": {
    "gn:admin1_code":"5.0",
    "gn:asciiname":"Taebongmil",
    "gn:country_code":"KR",
    "gn:dem":285,
    "gn:feature_class":"P",
    "gn:feature_code":"PPL",
    "gn:name":"Taebongmil",
    "gn:population":0,
    "gn:timezone":"Asia/Seoul",
    "iso:country":"KR",
    "name:kor_x_preferred":[
        "\ud0dc\ubd09\ubc00"
    ],
    "wof:name":"Taebongmil",
    "wof:placetype":"locality"
},
  "geometry": {"coordinates":[127.5796,36.652],"type":"Point"}
}