{
  "type": "Feature",
  "properties": {
    "gn:admin1_code":"14.0",
    "gn:asciiname":"Saeti",
    "gn:country_code":"KR",
    "gn:dem":214,
    "gn:feature_class":"P",
    "gn:feature_code":"PPL",
    "gn:name":"Saeti",
    "gn:population":0,
    "gn:timezone":"Asia/Seoul",
    "iso:country":"KR",
    "name:kor_x_preferred":[
        "\uc0c8\ud2f0"
    ],
    "wof:name":"Saeti",
    "wof:placetype":"locality"
},
  "geometry": {"coordinates":[128.81553,36.55776],"type":"Point"}
}