{
  "type": "Feature",
  "properties": {
    "gn:admin1_code":"17.0",
    "gn:asciiname":"Sin'gung-ni",
    "gn:country_code":"KR",
    "gn:dem":36,
    "gn:feature_class":"P",
    "gn:feature_code":"PPL",
    "gn:name":"Sin\u2019gung-ni",
    "gn:population":0,
    "gn:timezone":"Asia/Seoul",
    "iso:country":"KR",
    "name:eng_x_preferred":[
        "Sin'gung"
    ],
    "name:eng_x_variant":[
        "Sin'gung-ni"
    ],
    "name:und_x_variant":[
        "\uc2e0\uad81\ub9ac",
        "Sin\u2019gung-ni"
    ],
    "wof:name":"Sin'gung",
    "wof:placetype":"locality"
},
  "geometry": {"coordinates":[127.0904,36.9143],"type":"Point"}
}