{
  "type": "Feature",
  "properties": {
    "gn:admin1_code":"19.0",
    "gn:asciiname":"Win-mal",
    "gn:country_code":"KR",
    "gn:dem":87,
    "gn:feature_class":"P",
    "gn:feature_code":"PPL",
    "gn:name":"Win-mal",
    "gn:population":0,
    "gn:timezone":"Asia/Seoul",
    "iso:country":"KR",
    "name:und_x_variant":[
        "\uc717\ub9d0",
        "Win-mal"
    ],
    "wof:name":"Win-mal",
    "wof:placetype":"locality"
},
  "geometry": {"coordinates":[127.3749,36.2996],"type":"Point"}
}