{
  "type": "Feature",
  "properties": {
    "gn:admin1_code":"14.0",
    "gn:asciiname":"Araemoejae",
    "gn:country_code":"KR",
    "gn:dem":156,
    "gn:feature_class":"P",
    "gn:feature_code":"PPL",
    "gn:name":"Araemoejae",
    "gn:population":0,
    "gn:timezone":"Asia/Seoul",
    "iso:country":"KR",
    "name:und_x_variant":[
        "\uc544\ub798\ubafc\uc7ac",
        "Araemoejae"
    ],
    "wof:name":"Araemoejae",
    "wof:placetype":"locality"
},
  "geometry": {"coordinates":[128.21433999999999,35.89527000000001],"type":"Point"}
}