{
  "type": "Feature",
  "properties": {
    "gn:admin1_code":"14.0",
    "gn:asciiname":"Araeppaehae",
    "gn:cc2":"KR",
    "gn:country_code":"KR",
    "gn:dem":232,
    "gn:feature_class":"P",
    "gn:feature_code":"PPL",
    "gn:name":"Araeppaehae",
    "gn:population":0,
    "gn:timezone":"Asia/Seoul",
    "iso:country":"KR",
    "name:und_x_variant":[
        "Haso-ri",
        "Araet-paehae",
        "Araeppaehae"
    ],
    "wof:name":"Araeppaehae",
    "wof:placetype":"locality"
},
  "geometry": {"coordinates":[128.66666999999998,36.81667],"type":"Point"}
}