{
  "type": "Feature",
  "properties": {
    "gn:admin1_code":"5.0",
    "gn:asciiname":"Sonbawi",
    "gn:country_code":"KR",
    "gn:dem":244,
    "gn:feature_class":"P",
    "gn:feature_code":"PPL",
    "gn:name":"S\u014fnbawi",
    "gn:population":0,
    "gn:timezone":"Asia/Seoul",
    "iso:country":"KR",
    "name:und_x_variant":[
        "\uc120\ubc14\uc704",
        "S\u014fnbawi"
    ],
    "wof:name":"Sonbawi",
    "wof:placetype":"locality"
},
  "geometry": {"coordinates":[127.73690000000001,36.032],"type":"Point"}
}