{
  "type": "Feature",
  "properties": {
    "gn:admin1_code":"1.0",
    "gn:asciiname":"Donggareum",
    "gn:country_code":"KR",
    "gn:dem":64,
    "gn:feature_class":"P",
    "gn:feature_code":"PPL",
    "gn:name":"Donggareum",
    "gn:population":0,
    "gn:timezone":"Asia/Seoul",
    "iso:country":"KR",
    "name:kor_x_preferred":[
        "\ub3d9\uac00\ub984"
    ],
    "wof:name":"Donggareum",
    "wof:placetype":"locality"
},
  "geometry": {"coordinates":[126.3518,33.45749],"type":"Point"}
}