{
  "type": "Feature",
  "properties": {
    "gn:admin1_code":"17.0",
    "gn:asciiname":"Sogunt'o",
    "gn:country_code":"KR",
    "gn:dem":50,
    "gn:feature_class":"P",
    "gn:feature_code":"PPL",
    "gn:name":"S\u014fg\u016dnt\u2019\u014f",
    "gn:population":0,
    "gn:timezone":"Asia/Seoul",
    "iso:country":"KR",
    "name:und_x_variant":[
        "\uc11d\uc740\ud130",
        "S\u014fg\u016dnt\u2019\u014f"
    ],
    "wof:name":"Sogunt'o",
    "wof:placetype":"locality"
},
  "geometry": {"coordinates":[126.7054,36.5354],"type":"Point"}
}