{
  "type": "Feature",
  "properties": {
    "gn:admin1_code":"3.0",
    "gn:asciiname":"Suhan",
    "gn:country_code":"KR",
    "gn:dem":337,
    "gn:feature_class":"P",
    "gn:feature_code":"PPL",
    "gn:name":"Suhan",
    "gn:population":0,
    "gn:timezone":"Asia/Seoul",
    "iso:country":"KR",
    "name:und_x_variant":[
        "\uc218\ud55c",
        "Suhan"
    ],
    "wof:name":"Suhan",
    "wof:placetype":"locality"
},
  "geometry": {"coordinates":[127.81703,35.98970999999999],"type":"Point"}
}