{
  "type": "Feature",
  "properties": {
    "gn:admin1_code":"13.0",
    "gn:asciiname":"Oe-dong",
    "gn:country_code":"KR",
    "gn:dem":14,
    "gn:feature_class":"P",
    "gn:feature_code":"PPL",
    "gn:name":"Oe-dong",
    "gn:population":0,
    "gn:timezone":"Asia/Seoul",
    "iso:country":"KR",
    "wof:name":"Oe-dong",
    "wof:placetype":"locality"
},
  "geometry": {"coordinates":[126.81667,37.26667],"type":"Point"}
}