{
  "type": "Feature",
  "properties": {
    "gn:admin1_code":"13.0",
    "gn:asciiname":"Araenochae",
    "gn:country_code":"KR",
    "gn:dem":245,
    "gn:feature_class":"P",
    "gn:feature_code":"PPL",
    "gn:name":"Araenochae",
    "gn:population":0,
    "gn:timezone":"Asia/Seoul",
    "iso:country":"KR",
    "name:kor_x_preferred":[
        "\uc544\ub798\ub178\ucc44"
    ],
    "name:kor_x_variant":[
        "Araenoch\u2019ae"
    ],
    "wof:name":"Araenochae",
    "wof:placetype":"locality"
},
  "geometry": {"coordinates":[127.3503,37.8846],"type":"Point"}
}