{
  "type": "Feature",
  "properties": {
    "gn:admin1_code":"20.0",
    "gn:asciiname":"Sinch'on",
    "gn:country_code":"KR",
    "gn:dem":38,
    "gn:feature_class":"P",
    "gn:feature_code":"PPL",
    "gn:name":"Sinch\u2019\u014fn",
    "gn:population":0,
    "gn:timezone":"Asia/Seoul",
    "iso:country":"KR",
    "name:und_x_variant":[
        "\uc2e0\ucc9c",
        "Sinch\u2019\u014fn"
    ],
    "wof:name":"Sinch'on",
    "wof:placetype":"locality"
},
  "geometry": {"coordinates":[128.37644,35.07657],"type":"Point"}
}