{
  "type": "Feature",
  "properties": {
    "gn:admin1_code":"13.0",
    "gn:asciiname":"Oetdanmal",
    "gn:country_code":"KR",
    "gn:dem":74,
    "gn:feature_class":"P",
    "gn:feature_code":"PPL",
    "gn:name":"Oetdanmal",
    "gn:population":0,
    "gn:timezone":"Asia/Seoul",
    "iso:country":"KR",
    "name:kor_x_preferred":[
        "\uc68b\ub2e8\ub9d0"
    ],
    "wof:name":"Oetdanmal",
    "wof:placetype":"locality"
},
  "geometry": {"coordinates":[126.99925,38.03156],"type":"Point"}
}