{
  "type": "Feature",
  "properties": {
    "gn:admin1_code":"20.0",
    "gn:asciiname":"Tonae",
    "gn:country_code":"KR",
    "gn:dem":366,
    "gn:feature_class":"P",
    "gn:feature_code":"PPL",
    "gn:name":"T\u014fnae",
    "gn:population":0,
    "gn:timezone":"Asia/Seoul",
    "iso:country":"KR",
    "name:und_x_variant":[
        "\ub354\ub0b4",
        "T\u014fnae"
    ],
    "wof:name":"Tonae",
    "wof:placetype":"locality"
},
  "geometry": {"coordinates":[128.09058000000002,35.74701],"type":"Point"}
}