{
  "type": "Feature",
  "properties": {
    "gn:admin1_code":"3.0",
    "gn:asciiname":"Chinsang-dong",
    "gn:country_code":"KR",
    "gn:dem":352,
    "gn:feature_class":"P",
    "gn:feature_code":"PPL",
    "gn:name":"Chinsang-dong",
    "gn:population":0,
    "gn:timezone":"Asia/Seoul",
    "iso:country":"KR",
    "name:und_x_variant":[
        "\uc9c4\uc0c1\ub3d9",
        "Chinsang-dong"
    ],
    "wof:name":"Chinsang-dong",
    "wof:placetype":"locality"
},
  "geometry": {"coordinates":[127.39713999999999,35.86164],"type":"Point"}
}