{
  "type": "Feature",
  "properties": {
    "gn:admin1_code":"6.0",
    "gn:asciiname":"Seokgyo",
    "gn:country_code":"KR",
    "gn:dem":13,
    "gn:feature_class":"P",
    "gn:feature_code":"PPL",
    "gn:name":"Seokgyo",
    "gn:population":0,
    "gn:timezone":"Asia/Seoul",
    "iso:country":"KR",
    "name:kor_x_preferred":[
        "\uc11d\uad50"
    ],
    "name:und_x_variant":[
        "S\u014fkkyo",
        "Seokgyo"
    ],
    "wof:name":"Seokgyo",
    "wof:placetype":"locality"
},
  "geometry": {"coordinates":[128.51469,38.3284],"type":"Point"}
}