{
  "type": "Feature",
  "properties": {
    "gn:admin1_code":"6.0",
    "gn:asciiname":"Sangdaewol",
    "gn:country_code":"KR",
    "gn:dem":489,
    "gn:feature_class":"P",
    "gn:feature_code":"PPL",
    "gn:name":"Sangdaew\u014fl",
    "gn:population":0,
    "gn:timezone":"Asia/Seoul",
    "iso:country":"KR",
    "name:kor_x_preferred":[
        "\uc0c1\ub300\uc6d4"
    ],
    "name:kor_x_variant":[
        "Sangdaew\u014fl"
    ],
    "wof:name":"Sangdaewol",
    "wof:placetype":"locality"
},
  "geometry": {"coordinates":[128.29089999999999,37.7291],"type":"Point"}
}