{
  "type": "Feature",
  "properties": {
    "gn:admin1_code":"6.0",
    "gn:asciiname":"Sidong-ni",
    "gn:country_code":"KR",
    "gn:dem":270,
    "gn:feature_class":"P",
    "gn:feature_code":"PPLL",
    "gn:name":"Sidong-ni",
    "gn:population":0,
    "gn:timezone":"Asia/Seoul",
    "iso:country":"KR",
    "name:kor_x_preferred":[
        "\uc2dc\ub3d9\ub9ac"
    ],
    "wof:name":"Sidong-ni",
    "wof:placetype":"locality"
},
  "geometry": {"coordinates":[127.83132000000001,37.59845],"type":"Point"}
}