{
  "type": "Feature",
  "properties": {
    "gn:admin1_code":"6.0",
    "gn:asciiname":"Kogil",
    "gn:country_code":"KR",
    "gn:dem":463,
    "gn:feature_class":"P",
    "gn:feature_code":"PPL",
    "gn:name":"Kogil",
    "gn:population":0,
    "gn:timezone":"Asia/Seoul",
    "iso:country":"KR",
    "name:kor_x_preferred":[
        "\uace0\uae38"
    ],
    "wof:name":"Kogil",
    "wof:placetype":"locality"
},
  "geometry": {"coordinates":[128.45509999999999,37.4047],"type":"Point"}
}