{
  "type": "Feature",
  "properties": {
    "gn:admin1_code":"14.0",
    "gn:asciiname":"Wondang",
    "gn:country_code":"KR",
    "gn:dem":69,
    "gn:feature_class":"P",
    "gn:feature_code":"PPL",
    "gn:name":"W\u014fndang",
    "gn:population":0,
    "gn:timezone":"Asia/Seoul",
    "iso:country":"KR",
    "name:und_x_variant":[
        "\uc6d0\ub2f9",
        "W\u014fndang"
    ],
    "wof:name":"Wondang",
    "wof:placetype":"locality"
},
  "geometry": {"coordinates":[129.20931999999999,36.02643],"type":"Point"}
}