{
  "type": "Feature",
  "properties": {
    "gn:admin1_code":"3.0",
    "gn:asciiname":"Hoengsan",
    "gn:country_code":"KR",
    "gn:dem":241,
    "gn:feature_class":"P",
    "gn:feature_code":"PPL",
    "gn:name":"Hoengsan",
    "gn:population":0,
    "gn:timezone":"Asia/Seoul",
    "iso:country":"KR",
    "name:und_x_variant":[
        "Hoengam",
        "Kar\u016djinbawi",
        "Hoengsan"
    ],
    "wof:name":"Hoengsan",
    "wof:placetype":"locality"
},
  "geometry": {"coordinates":[127.29648,35.67858],"type":"Point"}
}