{
  "type": "Feature",
  "properties": {
    "gn:admin1_code":"3.0",
    "gn:asciiname":"Cheimp'yong",
    "gn:country_code":"KR",
    "gn:dem":203,
    "gn:feature_class":"P",
    "gn:feature_code":"PPL",
    "gn:name":"Cheimp\u2019y\u014fng",
    "gn:population":0,
    "gn:timezone":"Asia/Seoul",
    "iso:country":"KR",
    "name:und_x_variant":[
        "\uc81c\uc784\ud3c9",
        "Cheimp\u2019y\u014fng",
        "Jeimpyeong"
    ],
    "wof:name":"Cheimp'yong",
    "wof:placetype":"locality"
},
  "geometry": {"coordinates":[127.42316,35.52001],"type":"Point"}
}