{
  "type": "Feature",
  "properties": {
    "gn:admin1_code":"20.0",
    "gn:asciiname":"Chijong-ni",
    "gn:cc2":"KR",
    "gn:country_code":"KR",
    "gn:dem":5,
    "gn:feature_class":"P",
    "gn:feature_code":"PPL",
    "gn:name":"Chijong-ni",
    "gn:population":0,
    "gn:timezone":"Asia/Seoul",
    "iso:country":"KR",
    "name:und_x_variant":[
        "Chijok-ri",
        "Chijong-ni"
    ],
    "wof:name":"Chijong-ni",
    "wof:placetype":"locality"
},
  "geometry": {"coordinates":[128.00361000000001,34.83111],"type":"Point"}
}