{
  "type": "Feature",
  "properties": {
    "iso:country":"KR",
    "qs:name":"\uc911\uc559\ub3d9",
    "qs:name_adm0":"\ud55c\uad6d",
    "qs:name_adm1":"\uacbd\uc0c1\ub0a8\ub3c4",
    "qs:photos":49,
    "qs:photos_1k":10,
    "qs:photos_9k":1,
    "qs:photos_9r":2,
    "qs:photos_all":49,
    "qs:photos_sr":2,
    "qs:placetype":"LocalAdmin",
    "qs:pop_sr":"0",
    "wof:name":"\uc911\uc559\ub3d9",
    "wof:placetype":"localadmin"
},
  "geometry": {"coordinates":[129.06120250000001,35.413256],"type":"Point"}
}