{
  "type": "Feature",
  "properties": {
    "gn:admin1_code":"13.0",
    "gn:admin2_code":"Ans\u014fng-si",
    "gn:asciiname":"Eumdalmal",
    "gn:country_code":"KR",
    "gn:dem":151,
    "gn:feature_class":"P",
    "gn:feature_code":"PPL",
    "gn:name":"Eumdalmal",
    "gn:population":0,
    "gn:timezone":"Asia/Seoul",
    "iso:country":"KR",
    "name:kor_x_preferred":[
        "\uc74c\ucd0c\ub3d9"
    ],
    "name:kor_x_variant":[
        "\u016cmch\u2019on-dong",
        "\uc74c\ub2ec\ub9d0"
    ],
    "name:und_x_variant":[
        "Eumchon-dong",
        "Eumdalmal"
    ],
    "wof:name":"Eumdalmal",
    "wof:placetype":"locality"
},
  "geometry": {"coordinates":[127.35281999999999,37.08045],"type":"Point"}
}