{
  "type": "Feature",
  "properties": {
    "gn:admin1_code":"13.0",
    "gn:asciiname":"Beodeurachi",
    "gn:country_code":"KR",
    "gn:dem":237,
    "gn:feature_class":"P",
    "gn:feature_code":"PPL",
    "gn:name":"Beodeurachi",
    "gn:population":0,
    "gn:timezone":"Asia/Seoul",
    "iso:country":"KR",
    "name:und_x_variant":[
        "Yu-dong",
        "\ubc84\ub4e4\uc544\uce58",
        "P\u014fd\u016drach\u2019i",
        "Beodeurachi"
    ],
    "wof:name":"Beodeurachi",
    "wof:placetype":"locality"
},
  "geometry": {"coordinates":[127.53918,37.94064],"type":"Point"}
}