{
  "type": "Feature",
  "properties": {
    "gn:admin1_code":"6.0",
    "gn:asciiname":"Nongol",
    "gn:country_code":"KR",
    "gn:dem":555,
    "gn:feature_class":"P",
    "gn:feature_code":"PPL",
    "gn:name":"Nongol",
    "gn:population":0,
    "gn:timezone":"Asia/Seoul",
    "iso:country":"KR",
    "name:kor_x_preferred":[
        "\uc0c1\uc9c4\ubd80"
    ],
    "name:kor_x_variant":[
        "\ub17c\uace8"
    ],
    "name:und_x_variant":[
        "Sangjinbu",
        "Nongol"
    ],
    "wof:name":"Nongol",
    "wof:placetype":"locality"
},
  "geometry": {"coordinates":[128.5634,37.6543],"type":"Point"}
}