{
  "type": "Feature",
  "properties": {
    "gn:admin1_code":"17.0",
    "gn:asciiname":"Chak-kol",
    "gn:country_code":"KR",
    "gn:dem":54,
    "gn:feature_class":"P",
    "gn:feature_code":"PPL",
    "gn:name":"Chak-kol",
    "gn:population":0,
    "gn:timezone":"Asia/Seoul",
    "iso:country":"KR",
    "name:und_x_variant":[
        "\uc7a3\uace8",
        "Chak-kol"
    ],
    "wof:name":"Chak-kol",
    "wof:placetype":"locality"
},
  "geometry": {"coordinates":[127.0671,36.8715],"type":"Point"}
}