{
  "type": "Feature",
  "properties": {
    "gn:admin1_code":"5.0",
    "gn:asciiname":"Sin'gi",
    "gn:country_code":"KR",
    "gn:dem":165,
    "gn:feature_class":"P",
    "gn:feature_code":"PPL",
    "gn:name":"Sin\u2019gi",
    "gn:population":0,
    "gn:timezone":"Asia/Seoul",
    "iso:country":"KR",
    "name:und_x_variant":[
        "\uc2e0\uae30",
        "Sin\u2019gi"
    ],
    "wof:name":"Sin'gi",
    "wof:placetype":"locality"
},
  "geometry": {"coordinates":[127.73220000000001,36.1229],"type":"Point"}
}