{
  "type": "Feature",
  "properties": {
    "gn:admin1_code":"13.0",
    "gn:asciiname":"Seoguri",
    "gn:country_code":"KR",
    "gn:dem":69,
    "gn:feature_class":"P",
    "gn:feature_code":"PPL",
    "gn:name":"Seoguri",
    "gn:population":0,
    "gn:timezone":"Asia/Seoul",
    "iso:country":"KR",
    "name:kor_x_preferred":[
        "\uc11d\uc6b0\ub9ac"
    ],
    "wof:name":"Seoguri",
    "wof:placetype":"locality"
},
  "geometry": {"coordinates":[126.90992,38.06328],"type":"Point"}
}