{
  "type": "Feature",
  "properties": {
    "gn:admin1_code":"14.0",
    "gn:asciiname":"Araetgosari",
    "gn:country_code":"KR",
    "gn:dem":303,
    "gn:feature_class":"P",
    "gn:feature_code":"PPL",
    "gn:name":"Araetgosari",
    "gn:population":0,
    "gn:timezone":"Asia/Seoul",
    "iso:country":"KR",
    "name:kor_x_preferred":[
        "\uc544\ub7ab\uace0\uc0ac\ub9ac"
    ],
    "wof:name":"Araetgosari",
    "wof:placetype":"locality"
},
  "geometry": {"coordinates":[129.11977999999999,35.71177],"type":"Point"}
}