{
  "type": "Feature",
  "properties": {
    "gn:admin1_code":"6.0",
    "gn:asciiname":"Chonggori-gol",
    "gn:country_code":"KR",
    "gn:dem":443,
    "gn:feature_class":"P",
    "gn:feature_code":"PPL",
    "gn:name":"Ch\u014fngg\u014fri-gol",
    "gn:population":0,
    "gn:timezone":"Asia/Seoul",
    "iso:country":"KR",
    "name:und_x_variant":[
        "\uc815\uac70\ub9ac\uace8",
        "Ch\u014fngg\u014fri-gol"
    ],
    "wof:name":"Chonggori-gol",
    "wof:placetype":"locality"
},
  "geometry": {"coordinates":[129.0847,37.2042],"type":"Point"}
}