{
  "type": "Feature",
  "properties": {
    "gn:admin1_code":"6.0",
    "gn:asciiname":"Araettari-gol",
    "gn:country_code":"KR",
    "gn:dem":634,
    "gn:feature_class":"P",
    "gn:feature_code":"PPL",
    "gn:name":"Araettari-gol",
    "gn:population":0,
    "gn:timezone":"Asia/Seoul",
    "iso:country":"KR",
    "name:kor_x_preferred":[
        "\uc544\ub7ab\ub2e4\ub9ac\uace8"
    ],
    "name:und_x_variant":[
        "Araedari-gol",
        "Araettari-gol"
    ],
    "wof:name":"Araettari-gol",
    "wof:placetype":"locality"
},
  "geometry": {"coordinates":[128.83410000000001,37.5337],"type":"Point"}
}