{
  "type": "Feature",
  "properties": {
    "iso:country":"KR",
    "name:eng_x_preferred":[
        "Godae-myeon"
    ],
    "name:kor_x_preferred":[
        "\uace0\ub300\uba74"
    ],
    "qs:name":"\uace0\ub300\uba74",
    "qs:name_adm0":"\ud55c\uad6d",
    "qs:name_adm1":"\ucda9\uccad\ub0a8\ub3c4",
    "qs:photos":2,
    "qs:photos_1k":1,
    "qs:photos_9k":1,
    "qs:photos_9r":1,
    "qs:photos_all":2,
    "qs:photos_sr":1,
    "qs:placetype":"LocalAdmin",
    "qs:pop_sr":"0",
    "wof:name":"Godae-myeon",
    "wof:placetype":"localadmin"
},
  "geometry": {"coordinates":[126.58859200000001,36.907764],"type":"Point"}
}