{
  "type": "Feature",
  "properties": {
    "gn:admin1_code":"14.0",
    "gn:asciiname":"Sopsil",
    "gn:country_code":"KR",
    "gn:dem":49,
    "gn:feature_class":"P",
    "gn:feature_code":"PPL",
    "gn:name":"Sopsil",
    "gn:population":0,
    "gn:timezone":"Asia/Seoul",
    "iso:country":"KR",
    "name:und_x_variant":[
        "\uc19d\uc2e4"
    ],
    "wof:name":"Sopsil",
    "wof:placetype":"locality"
},
  "geometry": {"coordinates":[128.32686000000001,36.27199],"type":"Point"}
}