{
  "type": "Feature",
  "properties": {
    "gn:admin1_code":"14.0",
    "gn:asciiname":"Gumi",
    "gn:country_code":"KR",
    "gn:dem":158,
    "gn:feature_class":"P",
    "gn:feature_code":"PPL",
    "gn:name":"Gumi",
    "gn:population":0,
    "gn:timezone":"Asia/Seoul",
    "iso:country":"KR",
    "name:ceb_x_preferred":[
        "Gumi"
    ],
    "name:fra_x_preferred":[
        "Gumi"
    ],
    "name:jpn_x_preferred":[
        "\u30b0\u30df"
    ],
    "name:kor_x_preferred":[
        "\uad6c\ubbf8"
    ],
    "name:pol_x_preferred":[
        "Gumi"
    ],
    "name:swe_x_preferred":[
        "Gumi"
    ],
    "name:ukr_x_preferred":[
        "\u0413\u0443\u043c\u0456"
    ],
    "wof:name":"Gumi",
    "wof:placetype":"locality"
},
  "geometry": {"coordinates":[128.81398000000002,35.70263],"type":"Point"}
}