{
  "type": "Feature",
  "properties": {
    "gn:admin1_code":"6.0",
    "gn:asciiname":"Gwangjudong",
    "gn:country_code":"KR",
    "gn:dem":346,
    "gn:feature_class":"P",
    "gn:feature_code":"PPL",
    "gn:name":"Gwangjudong",
    "gn:population":0,
    "gn:timezone":"Asia/Seoul",
    "iso:country":"KR",
    "name:kor_x_preferred":[
        "\uad11\uc8fc\ub3d9"
    ],
    "name:und_x_variant":[
        "Kwangju-dong",
        "Gwangjudong"
    ],
    "wof:name":"Gwangjudong",
    "wof:placetype":"locality"
},
  "geometry": {"coordinates":[128.27635000000001,37.90173],"type":"Point"}
}