{
  "type": "Feature",
  "properties": {
    "gn:admin1_code":"6.0",
    "gn:asciiname":"Geumgwangdae",
    "gn:country_code":"KR",
    "gn:dem":101,
    "gn:feature_class":"P",
    "gn:feature_code":"PPL",
    "gn:name":"Geumgwangdae",
    "gn:population":0,
    "gn:timezone":"Asia/Seoul",
    "iso:country":"KR",
    "name:kor_x_preferred":[
        "\uae08\uad11\ub300"
    ],
    "name:und_x_variant":[
        "\uae08\uad11\ud130",
        "K\u016dmgwangt\u2019\u014f",
        "Geumgwangdae"
    ],
    "wof:name":"Geumgwangdae",
    "wof:placetype":"locality"
},
  "geometry": {"coordinates":[127.74352,37.95396],"type":"Point"}
}