{
  "type": "Feature",
  "properties": {
    "gn:admin1_code":"6.0",
    "gn:asciiname":"Sindeongni",
    "gn:country_code":"KR",
    "gn:dem":275,
    "gn:feature_class":"P",
    "gn:feature_code":"PPL",
    "gn:name":"Sindeongni",
    "gn:population":0,
    "gn:timezone":"Asia/Seoul",
    "iso:country":"KR",
    "name:kor_x_preferred":[
        "\uc2e0\ub355\ub9ac"
    ],
    "wof:name":"Sindeongni",
    "wof:placetype":"locality"
},
  "geometry": {"coordinates":[127.55443,38.05919],"type":"Point"}
}