{
  "type": "Feature",
  "properties": {
    "gn:admin1_code":"13.0",
    "gn:asciiname":"Solbat",
    "gn:country_code":"KR",
    "gn:dem":129,
    "gn:feature_class":"P",
    "gn:feature_code":"PPL",
    "gn:name":"Solbat",
    "gn:population":0,
    "gn:timezone":"Asia/Seoul",
    "iso:country":"KR",
    "name:kor_x_preferred":[
        "\uc194\ubc2d"
    ],
    "wof:name":"Solbat",
    "wof:placetype":"locality"
},
  "geometry": {"coordinates":[127.40908,37.04839000000001],"type":"Point"}
}