{
  "type": "Feature",
  "properties": {
    "gn:admin1_code":"13.0",
    "gn:asciiname":"Chilgoe",
    "gn:country_code":"KR",
    "gn:dem":23,
    "gn:feature_class":"P",
    "gn:feature_code":"PPL",
    "gn:name":"Chilgoe",
    "gn:population":0,
    "gn:timezone":"Asia/Seoul",
    "iso:country":"KR",
    "name:und_x_variant":[
        "\uce60\uad34",
        "Chilgoe",
        "Ch\u2019ilgoe"
    ],
    "wof:name":"Chilgoe",
    "wof:placetype":"locality"
},
  "geometry": {"coordinates":[127.08222000000001,37.02639],"type":"Point"}
}