{
  "type": "Feature",
  "properties": {
    "gn:admin1_code":"13.0",
    "gn:asciiname":"Wonseungdu",
    "gn:country_code":"KR",
    "gn:dem":30,
    "gn:feature_class":"P",
    "gn:feature_code":"PPL",
    "gn:name":"Wonseungdu",
    "gn:population":0,
    "gn:timezone":"Asia/Seoul",
    "iso:country":"KR",
    "name:und_x_variant":[
        "\uc6d0\uc2b9\ub450",
        "W\u014fns\u016dngdu",
        "Wonseungdu"
    ],
    "wof:name":"Wonseungdu",
    "wof:placetype":"locality"
},
  "geometry": {"coordinates":[127.15873000000001,36.99034],"type":"Point"}
}