{
  "type": "Feature",
  "properties": {
    "gn:admin1_code":"3.0",
    "gn:asciiname":"Taesongbang",
    "gn:country_code":"KR",
    "gn:dem":347,
    "gn:feature_class":"P",
    "gn:feature_code":"PPL",
    "gn:name":"Taes\u014fngbang",
    "gn:population":0,
    "gn:timezone":"Asia/Seoul",
    "iso:country":"KR",
    "name:und_x_variant":[
        "\ub300\uc131\ubc29",
        "Taes\u014fngbang"
    ],
    "wof:name":"Taesongbang",
    "wof:placetype":"locality"
},
  "geometry": {"coordinates":[127.49905,35.53995],"type":"Point"}
}