{
  "type": "Feature",
  "properties": {
    "gn:admin1_code":"13.0",
    "gn:asciiname":"Yusil",
    "gn:country_code":"KR",
    "gn:dem":80,
    "gn:feature_class":"P",
    "gn:feature_code":"PPL",
    "gn:name":"Yusil",
    "gn:population":0,
    "gn:timezone":"Asia/Seoul",
    "iso:country":"KR",
    "name:und_x_variant":[
        "Yusil-li",
        "\uc720\uc2e4",
        "Yusil"
    ],
    "wof:name":"Yusil",
    "wof:placetype":"locality"
},
  "geometry": {"coordinates":[127.22,37.30333],"type":"Point"}
}