{
  "type": "Feature",
  "properties": {
    "gn:admin1_code":"17.0",
    "gn:asciiname":"Chubang-gol",
    "gn:country_code":"KR",
    "gn:dem":10,
    "gn:feature_class":"P",
    "gn:feature_code":"PPL",
    "gn:name":"Chubang-gol",
    "gn:population":0,
    "gn:timezone":"Asia/Seoul",
    "iso:country":"KR",
    "name:und_x_variant":[
        "\uc8fc\ubc29\uace8",
        "Jubang-gol",
        "Chubang-gol"
    ],
    "wof:name":"Chubang-gol",
    "wof:placetype":"locality"
},
  "geometry": {"coordinates":[126.5025,37.05056],"type":"Point"}
}