{
  "type": "Feature",
  "properties": {
    "gn:admin1_code":"13.0",
    "gn:admin2_code":"Yongin-si",
    "gn:asciiname":"Yagwangi",
    "gn:country_code":"KR",
    "gn:dem":96,
    "gn:feature_class":"P",
    "gn:feature_code":"PPL",
    "gn:name":"Yagwangi",
    "gn:population":0,
    "gn:timezone":"Asia/Seoul",
    "iso:country":"KR",
    "name:kor_x_preferred":[
        "\uc57c\uad11\uc774"
    ],
    "wof:name":"Yagwangi",
    "wof:placetype":"locality"
},
  "geometry": {"coordinates":[127.30919,37.15657],"type":"Point"}
}