{
  "type": "Feature",
  "properties": {
    "gn:admin1_code":"5.0",
    "gn:asciiname":"Gyochon",
    "gn:country_code":"KR",
    "gn:dem":226,
    "gn:feature_class":"P",
    "gn:feature_code":"PPL",
    "gn:name":"Gyochon",
    "gn:population":0,
    "gn:timezone":"Asia/Seoul",
    "iso:country":"KR",
    "name:kor_x_preferred":[
        "\uad50\ucd0c"
    ],
    "wof:name":"Gyochon",
    "wof:placetype":"locality"
},
  "geometry": {"coordinates":[127.99683,36.76403],"type":"Point"}
}