{
  "type": "Feature",
  "properties": {
    "gn:admin1_code":"14.0",
    "gn:asciiname":"Olgol",
    "gn:country_code":"KR",
    "gn:dem":18,
    "gn:feature_class":"P",
    "gn:feature_code":"PPL",
    "gn:name":"Olgol",
    "gn:population":0,
    "gn:timezone":"Asia/Seoul",
    "iso:country":"KR",
    "name:kor_x_preferred":[
        "\uc62c\uace8"
    ],
    "wof:name":"Olgol",
    "wof:placetype":"locality"
},
  "geometry": {"coordinates":[129.45051000000001,35.68727],"type":"Point"}
}