{
  "type": "Feature",
  "properties": {
    "gn:admin1_code":"6.0",
    "gn:asciiname":"Pamja-gol",
    "gn:country_code":"KR",
    "gn:dem":132,
    "gn:feature_class":"P",
    "gn:feature_code":"PPL",
    "gn:name":"Pamja-gol",
    "gn:population":0,
    "gn:timezone":"Asia/Seoul",
    "iso:country":"KR",
    "name:und_x_variant":[
        "\ubc24\uc790\uace8",
        "Pamja-gol"
    ],
    "wof:name":"Pamja-gol",
    "wof:placetype":"locality"
},
  "geometry": {"coordinates":[127.68680000000001,37.914],"type":"Point"}
}