{
  "type": "Feature",
  "properties": {
    "gn:admin1_code":"6.0",
    "gn:asciiname":"Utchongam",
    "gn:country_code":"KR",
    "gn:dem":200,
    "gn:feature_class":"P",
    "gn:feature_code":"PPL",
    "gn:name":"Utch\u014fngam",
    "gn:population":0,
    "gn:timezone":"Asia/Seoul",
    "iso:country":"KR",
    "name:kor_x_preferred":[
        "\uc6c3\uc815\uc554"
    ],
    "name:kor_x_variant":[
        "Utch\u014fngam"
    ],
    "wof:name":"Utchongam",
    "wof:placetype":"locality"
},
  "geometry": {"coordinates":[128.01519999999999,37.4613],"type":"Point"}
}