{
  "type": "Feature",
  "properties": {
    "gn:admin1_code":"18.0",
    "gn:asciiname":"Chunghyo",
    "gn:country_code":"KR",
    "gn:dem":94,
    "gn:feature_class":"P",
    "gn:feature_code":"PPL",
    "gn:name":"Chunghyo",
    "gn:population":0,
    "gn:timezone":"Asia/Seoul",
    "iso:country":"KR",
    "name:kor_x_preferred":[
        "\ucda9\ud6a8"
    ],
    "wof:name":"Chunghyo",
    "wof:placetype":"locality"
},
  "geometry": {"coordinates":[127.00311000000001,35.1838],"type":"Point"}
}