{
  "type": "Feature",
  "properties": {
    "gn:admin1_code":"5.0",
    "gn:asciiname":"Sutonggeori",
    "gn:country_code":"KR",
    "gn:dem":211,
    "gn:feature_class":"P",
    "gn:feature_code":"PPL",
    "gn:name":"Sutonggeori",
    "gn:population":0,
    "gn:timezone":"Asia/Seoul",
    "iso:country":"KR",
    "name:kor_x_preferred":[
        "\uc218\ud1b5\uac70\ub9ac"
    ],
    "name:kor_x_variant":[
        "Sut\u2019ongg\u014f-ri"
    ],
    "wof:name":"Sutonggeori",
    "wof:placetype":"locality"
},
  "geometry": {"coordinates":[128.49121,37.05433],"type":"Point"}
}