{
  "type": "Feature",
  "properties": {
    "gn:admin1_code":"17.0",
    "gn:asciiname":"Hapkong-ni",
    "gn:country_code":"KR",
    "gn:dem":119,
    "gn:feature_class":"P",
    "gn:feature_code":"PPL",
    "gn:name":"Hapkong-ni",
    "gn:population":0,
    "gn:timezone":"Asia/Seoul",
    "iso:country":"KR",
    "name:eng_x_preferred":[
        "Hapkong"
    ],
    "name:eng_x_variant":[
        "Hapkong-ni"
    ],
    "wof:name":"Hapkong",
    "wof:placetype":"locality"
},
  "geometry": {"coordinates":[126.86667,36.21667],"type":"Point"}
}