{
  "type": "Feature",
  "properties": {
    "gn:admin1_code":"16.0",
    "gn:asciiname":"Guljeon",
    "gn:country_code":"KR",
    "gn:dem":8,
    "gn:feature_class":"P",
    "gn:feature_code":"PPL",
    "gn:name":"Guljeon",
    "gn:population":0,
    "gn:timezone":"Asia/Seoul",
    "iso:country":"KR",
    "name:kor_x_preferred":[
        "\uad74\uc804"
    ],
    "name:und_x_variant":[
        "Kulch\u014fn"
    ],
    "wof:name":"Guljeon",
    "wof:placetype":"locality"
},
  "geometry": {"coordinates":[127.76787,34.69272],"type":"Point"}
}