{
  "type": "Feature",
  "properties": {
    "gn:admin1_code":"14.0",
    "gn:asciiname":"Batanggol",
    "gn:country_code":"KR",
    "gn:dem":142,
    "gn:feature_class":"P",
    "gn:feature_code":"PPL",
    "gn:name":"Batanggol",
    "gn:population":0,
    "gn:timezone":"Asia/Seoul",
    "iso:country":"KR",
    "name:kor_x_preferred":[
        "\ubc14\ud0d5\uace8"
    ],
    "wof:name":"Batanggol",
    "wof:placetype":"locality"
},
  "geometry": {"coordinates":[129.25635,35.71546],"type":"Point"}
}