{
  "type": "Feature",
  "properties": {
    "gn:admin1_code":"13.0",
    "gn:asciiname":"Sangch'on",
    "gn:country_code":"KR",
    "gn:dem":123,
    "gn:feature_class":"P",
    "gn:feature_code":"PPL",
    "gn:name":"Sangch\u2019on",
    "gn:population":0,
    "gn:timezone":"Asia/Seoul",
    "iso:country":"KR",
    "name:und_x_variant":[
        "\uc0c1\ucd0c",
        "Sangch\u2019on"
    ],
    "wof:name":"Sangch'on",
    "wof:placetype":"locality"
},
  "geometry": {"coordinates":[127.5252,37.8994],"type":"Point"}
}