{
  "type": "Feature",
  "properties": {
    "gn:admin1_code":"3.0",
    "gn:asciiname":"Unda-ri",
    "gn:country_code":"KR",
    "gn:dem":33,
    "gn:feature_class":"P",
    "gn:feature_code":"PPL",
    "gn:name":"\u016cnda-ri",
    "gn:population":0,
    "gn:timezone":"Asia/Seoul",
    "iso:country":"KR",
    "name:und_x_variant":[
        "\uc740\ub2e4\ub9ac",
        "\u016cnda-ri"
    ],
    "wof:name":"Unda-ri",
    "wof:placetype":"locality"
},
  "geometry": {"coordinates":[127.00224,35.81862],"type":"Point"}
}