{
  "type": "Feature",
  "properties": {
    "gn:admin1_code":"16.0",
    "gn:asciiname":"Sindok",
    "gn:country_code":"KR",
    "gn:dem":12,
    "gn:feature_class":"P",
    "gn:feature_code":"PPL",
    "gn:name":"Sind\u014fk",
    "gn:population":0,
    "gn:timezone":"Asia/Seoul",
    "iso:country":"KR",
    "name:kor_x_preferred":[
        "Sind\u014fk"
    ],
    "wof:name":"Sindok",
    "wof:placetype":"locality"
},
  "geometry": {"coordinates":[126.81167000000001,34.56694],"type":"Point"}
}