{
  "type": "Feature",
  "properties": {
    "gn:admin1_code":"14.0",
    "gn:asciiname":"Chungdul",
    "gn:country_code":"KR",
    "gn:dem":195,
    "gn:feature_class":"P",
    "gn:feature_code":"PPL",
    "gn:name":"Chungd\u016dl",
    "gn:population":0,
    "gn:timezone":"Asia/Seoul",
    "iso:country":"KR",
    "wof:name":"Chungdul",
    "wof:placetype":"locality"
},
  "geometry": {"coordinates":[129.0213,36.4579],"type":"Point"}
}