{
  "type": "Feature",
  "properties": {
    "gn:admin1_code":"14.0",
    "gn:asciiname":"Okch'on",
    "gn:country_code":"KR",
    "gn:dem":109,
    "gn:feature_class":"P",
    "gn:feature_code":"PPL",
    "gn:name":"Okch\u2019\u014fn",
    "gn:population":0,
    "gn:timezone":"Asia/Seoul",
    "iso:country":"KR",
    "name:und_x_variant":[
        "\uc625\ucc9c",
        "Okch\u2019\u014fn"
    ],
    "wof:name":"Okch'on",
    "wof:placetype":"locality"
},
  "geometry": {"coordinates":[129.32040000000001,36.5974],"type":"Point"}
}