{
  "type": "Feature",
  "properties": {
    "gn:admin1_code":"11.0",
    "gn:asciiname":"Songsuilgail-tong",
    "gn:country_code":"KR",
    "gn:dem":22,
    "gn:feature_class":"P",
    "gn:feature_code":"PPL",
    "gn:name":"S\u014fngsuilgail-tong",
    "gn:population":0,
    "gn:timezone":"Asia/Seoul",
    "iso:country":"KR",
    "name:und_x_variant":[
        "\uc131\uc2181\uac001\ub3d9",
        "S\u014fngsuilgail-tong"
    ],
    "wof:name":"Songsuilgail-tong",
    "wof:placetype":"locality"
},
  "geometry": {"coordinates":[127.04012,37.54016],"type":"Point"}
}