{
  "type": "Feature",
  "properties": {
    "gn:admin1_code":"5.0",
    "gn:asciiname":"Hwangjom",
    "gn:country_code":"KR",
    "gn:dem":419,
    "gn:feature_class":"P",
    "gn:feature_code":"PPL",
    "gn:name":"Hwangj\u014fm",
    "gn:population":0,
    "gn:timezone":"Asia/Seoul",
    "iso:country":"KR",
    "name:und_x_variant":[
        "\ud669\uc810",
        "Hwangj\u014fm"
    ],
    "wof:name":"Hwangjom",
    "wof:placetype":"locality"
},
  "geometry": {"coordinates":[127.88,36.0963],"type":"Point"}
}