{
  "type": "Feature",
  "properties": {
    "gn:admin1_code":"17.0",
    "gn:asciiname":"Kasa-ri",
    "gn:country_code":"KR",
    "gn:dem":30,
    "gn:feature_class":"P",
    "gn:feature_code":"PPL",
    "gn:name":"Kasa-ri",
    "gn:population":0,
    "gn:timezone":"Asia/Seoul",
    "iso:country":"KR",
    "name:und_x_variant":[
        "\uac00\uc0ac\ub9ac",
        "Kasa-ri"
    ],
    "wof:name":"Kasa-ri",
    "wof:placetype":"locality"
},
  "geometry": {"coordinates":[126.3612,36.7571],"type":"Point"}
}