{
  "type": "Feature",
  "properties": {
    "gn:admin1_code":"16.0",
    "gn:asciiname":"Mannyeondong",
    "gn:country_code":"KR",
    "gn:dem":85,
    "gn:feature_class":"P",
    "gn:feature_code":"PPL",
    "gn:name":"Mannyeondong",
    "gn:population":0,
    "gn:timezone":"Asia/Seoul",
    "iso:country":"KR",
    "name:kor_x_preferred":[
        "\ub9cc\ub144\ub3d9"
    ],
    "name:und_x_variant":[
        "Manny\u014fn-ni",
        "Many\u014fn-ni",
        "Manny\u014fn-dong",
        "Mannyeondong"
    ],
    "wof:name":"Mannyeondong",
    "wof:placetype":"locality"
},
  "geometry": {"coordinates":[126.77643999999999,34.90116],"type":"Point"}
}