{
  "type": "Feature",
  "properties": {
    "gn:admin1_code":"6.0",
    "gn:asciiname":"Sodu-ri",
    "gn:country_code":"KR",
    "gn:dem":583,
    "gn:feature_class":"P",
    "gn:feature_code":"PPL",
    "gn:name":"Sodu-ri",
    "gn:population":0,
    "gn:timezone":"Asia/Seoul",
    "iso:country":"KR",
    "name:kor_x_preferred":[
        "\uc18c\ub450\ub9ac"
    ],
    "wof:name":"Sodu-ri",
    "wof:placetype":"locality"
},
  "geometry": {"coordinates":[128.89276999999998,37.39265],"type":"Point"}
}