{
  "type": "Feature",
  "properties": {
    "gn:admin1_code":"17.0",
    "gn:asciiname":"Chungsong",
    "gn:country_code":"KR",
    "gn:dem":49,
    "gn:feature_class":"P",
    "gn:feature_code":"PPL",
    "gn:name":"Chungsong",
    "gn:population":0,
    "gn:timezone":"Asia/Seoul",
    "iso:country":"KR",
    "name:und_x_variant":[
        "\uc911\uc1a1",
        "Chungsong"
    ],
    "wof:name":"Chungsong",
    "wof:placetype":"locality"
},
  "geometry": {"coordinates":[126.8398,36.6447],"type":"Point"}
}