{
  "type": "Feature",
  "properties": {
    "gn:admin1_code":"6.0",
    "gn:asciiname":"Ungjil-li",
    "gn:country_code":"KR",
    "gn:dem":288,
    "gn:feature_class":"P",
    "gn:feature_code":"PPL",
    "gn:name":"Ungjil-li",
    "gn:population":0,
    "gn:timezone":"Asia/Seoul",
    "iso:country":"KR",
    "name:kor_x_preferred":[
        "\uc6c5\uc9c4\ub9ac"
    ],
    "name:und_x_variant":[
        "Sumo-ni",
        "Ungjil-li",
        "Ungjin-ri"
    ],
    "wof:name":"Ungjil-li",
    "wof:placetype":"locality"
},
  "geometry": {"coordinates":[127.94194,38.06167],"type":"Point"}
}