{
  "type": "Feature",
  "properties": {
    "gn:admin1_code":"16.0",
    "gn:asciiname":"Guryedong",
    "gn:country_code":"KR",
    "gn:dem":145,
    "gn:feature_class":"P",
    "gn:feature_code":"PPL",
    "gn:name":"Guryedong",
    "gn:population":0,
    "gn:timezone":"Asia/Seoul",
    "iso:country":"KR",
    "name:kor_x_preferred":[
        "\uad6c\ub840\ub3d9"
    ],
    "name:und_x_variant":[
        "Kurye-dong",
        "Guryedong"
    ],
    "wof:name":"Guryedong",
    "wof:placetype":"locality"
},
  "geometry": {"coordinates":[127.02970999999999,34.85869],"type":"Point"}
}