{
  "type": "Feature",
  "properties": {
    "gn:admin1_code":"17.0",
    "gn:asciiname":"Parupchae",
    "gn:country_code":"KR",
    "gn:dem":52,
    "gn:feature_class":"P",
    "gn:feature_code":"PPL",
    "gn:name":"Par\u016dpchae",
    "gn:population":0,
    "gn:timezone":"Asia/Seoul",
    "iso:country":"KR",
    "name:und_x_variant":[
        "\ubc1c\uc74d\uc7ac",
        "Par\u016dpchae"
    ],
    "wof:name":"Parupchae",
    "wof:placetype":"locality"
},
  "geometry": {"coordinates":[126.60980000000001,36.5828],"type":"Point"}
}