{
  "type": "Feature",
  "properties": {
    "gn:admin1_code":"14.0",
    "gn:asciiname":"Sin-dong",
    "gn:country_code":"KR",
    "gn:dem":53,
    "gn:feature_class":"P",
    "gn:feature_code":"PPL",
    "gn:name":"Sin-dong",
    "gn:population":0,
    "gn:timezone":"Asia/Seoul",
    "iso:country":"KR",
    "name:und_x_variant":[
        "\uc2e0\ub3d9",
        "Sin-dong"
    ],
    "wof:name":"Sin-dong",
    "wof:placetype":"locality"
},
  "geometry": {"coordinates":[128.26310000000001,36.2008],"type":"Point"}
}