{
  "type": "Feature",
  "properties": {
    "gn:admin1_code":"16.0",
    "gn:asciiname":"Jangseungmul",
    "gn:country_code":"KR",
    "gn:dem":60,
    "gn:feature_class":"P",
    "gn:feature_code":"PPL",
    "gn:name":"Jangseungmul",
    "gn:population":0,
    "gn:timezone":"Asia/Seoul",
    "iso:country":"KR",
    "name:kor_x_preferred":[
        "\uc7a5\uc2b9\ubb3c"
    ],
    "wof:name":"Jangseungmul",
    "wof:placetype":"locality"
},
  "geometry": {"coordinates":[126.98475000000001,35.21995],"type":"Point"}
}