{
  "type": "Feature",
  "properties": {
    "gn:admin1_code":"17.0",
    "gn:asciiname":"Amnae",
    "gn:country_code":"KR",
    "gn:dem":147,
    "gn:feature_class":"P",
    "gn:feature_code":"PPL",
    "gn:name":"Amnae",
    "gn:population":0,
    "gn:timezone":"Asia/Seoul",
    "iso:country":"KR",
    "name:und_x_variant":[
        "\uc55e\ub0b4",
        "Amnae"
    ],
    "wof:name":"Amnae",
    "wof:placetype":"locality"
},
  "geometry": {"coordinates":[127.5714,36.1124],"type":"Point"}
}