{
  "type": "Feature",
  "properties": {
    "gn:admin1_code":"13.0",
    "gn:asciiname":"Songchonmal",
    "gn:country_code":"KR",
    "gn:dem":73,
    "gn:feature_class":"P",
    "gn:feature_code":"PPL",
    "gn:name":"Songchonmal",
    "gn:population":0,
    "gn:timezone":"Asia/Seoul",
    "iso:country":"KR",
    "name:kor_x_preferred":[
        "\uc1a1\ucd0c\ub9d0"
    ],
    "name:kor_x_variant":[
        "Songch\u2019on-mal"
    ],
    "wof:name":"Songchonmal",
    "wof:placetype":"locality"
},
  "geometry": {"coordinates":[127.57831000000002,37.21973],"type":"Point"}
}