{
  "type": "Feature",
  "properties": {
    "gn:admin1_code":"5.0",
    "gn:asciiname":"Byeolgok",
    "gn:country_code":"KR",
    "gn:dem":142,
    "gn:feature_class":"P",
    "gn:feature_code":"PPL",
    "gn:name":"Byeolgok",
    "gn:population":0,
    "gn:timezone":"Asia/Seoul",
    "iso:country":"KR",
    "name:kor_x_preferred":[
        "\ubcc4\uace1"
    ],
    "wof:name":"Byeolgok",
    "wof:placetype":"locality"
},
  "geometry": {"coordinates":[128.36188000000001,36.99198],"type":"Point"}
}