{
  "type": "Feature",
  "properties": {
    "gn:admin1_code":"17.0",
    "gn:asciiname":"Kiro",
    "gn:cc2":"KR",
    "gn:country_code":"KR",
    "gn:dem":8,
    "gn:feature_class":"P",
    "gn:feature_code":"PPL",
    "gn:name":"Kiro",
    "gn:population":0,
    "gn:timezone":"Asia/Seoul",
    "iso:country":"KR",
    "name:rus_x_preferred":[
        "\u041a\u0438\u0440\u043e"
    ],
    "name:und_x_variant":[
        "Kiro-ri",
        "Kiro"
    ],
    "wof:name":"Kiro",
    "wof:placetype":"locality"
},
  "geometry": {"coordinates":[126.61667,36.11667],"type":"Point"}
}