{
  "type": "Feature",
  "properties": {
    "gn:admin1_code":"14.0",
    "gn:asciiname":"Byeolgwan",
    "gn:country_code":"KR",
    "gn:dem":127,
    "gn:feature_class":"P",
    "gn:feature_code":"PPL",
    "gn:name":"Byeolgwan",
    "gn:population":0,
    "gn:timezone":"Asia/Seoul",
    "iso:country":"KR",
    "name:kor_x_preferred":[
        "\ubcc4\uad00"
    ],
    "wof:name":"Byeolgwan",
    "wof:placetype":"locality"
},
  "geometry": {"coordinates":[128.78126,36.04129],"type":"Point"}
}