{
  "type": "Feature",
  "properties": {
    "gn:admin1_code":"17.0",
    "gn:asciiname":"Taesan",
    "gn:country_code":"KR",
    "gn:dem":143,
    "gn:feature_class":"P",
    "gn:feature_code":"PPL",
    "gn:name":"Taesan",
    "gn:population":0,
    "gn:timezone":"Asia/Seoul",
    "iso:country":"KR",
    "name:und_x_variant":[
        "\ub300\uc0b0",
        "Taesan"
    ],
    "wof:name":"Taesan",
    "wof:placetype":"locality"
},
  "geometry": {"coordinates":[127.5534,36.1239],"type":"Point"}
}