{
  "type": "Feature",
  "properties": {
    "gn:admin1_code":"14.0",
    "gn:asciiname":"Uihung",
    "gn:cc2":"KR",
    "gn:country_code":"KR",
    "gn:dem":115,
    "gn:feature_class":"P",
    "gn:feature_code":"PPL",
    "gn:name":"\u016cih\u016dng",
    "gn:population":0,
    "gn:timezone":"Asia/Seoul",
    "iso:country":"KR",
    "name:und_x_variant":[
        "Gik\u014d",
        "\u016cih\u016dng"
    ],
    "wof:name":"Uihung",
    "wof:placetype":"locality"
},
  "geometry": {"coordinates":[128.70139,36.17861],"type":"Point"}
}