{
  "type": "Feature",
  "properties": {
    "gn:admin1_code":"6.0",
    "gn:asciiname":"Samwangdong",
    "gn:country_code":"KR",
    "gn:dem":286,
    "gn:feature_class":"P",
    "gn:feature_code":"PPL",
    "gn:name":"Samwangdong",
    "gn:population":0,
    "gn:timezone":"Asia/Seoul",
    "iso:country":"KR",
    "name:kor_x_preferred":[
        "\uc0bc\uc655\ub3d9"
    ],
    "name:und_x_variant":[
        "Samwang",
        "Samwangdong"
    ],
    "wof:name":"Samwangdong",
    "wof:placetype":"locality"
},
  "geometry": {"coordinates":[128.79560000000001,37.75778],"type":"Point"}
}