{
  "type": "Feature",
  "properties": {
    "gn:admin1_code":"3.0",
    "gn:asciiname":"Pup'yong",
    "gn:country_code":"KR",
    "gn:dem":571,
    "gn:feature_class":"P",
    "gn:feature_code":"PPL",
    "gn:name":"Pup\u2019y\u014fng",
    "gn:population":0,
    "gn:timezone":"Asia/Seoul",
    "iso:country":"KR",
    "name:und_x_variant":[
        "\ubd80\ud3c9",
        "Pup\u2019y\u014fng"
    ],
    "wof:name":"Pup'yong",
    "wof:placetype":"locality"
},
  "geometry": {"coordinates":[127.89854,35.9453],"type":"Point"}
}