{
  "type": "Feature",
  "properties": {
    "iso:country":"KR",
    "name:eng_x_preferred":[
        "Deungnyang-myeon"
    ],
    "name:kor_x_preferred":[
        "\ub4dd\ub7c9\uba74"
    ],
    "qs:name":"\ub4dd\ub7c9\uba74",
    "qs:name_adm0":"\ud55c\uad6d",
    "qs:name_adm1":"\uc804\ub77c\ub0a8\ub3c4",
    "qs:photos":187,
    "qs:photos_1k":38,
    "qs:photos_9k":1,
    "qs:photos_9r":4,
    "qs:photos_all":187,
    "qs:photos_sr":4,
    "qs:placetype":"LocalAdmin",
    "qs:pop_sr":"0",
    "wof:name":"Deungnyang-myeon",
    "wof:placetype":"localadmin"
},
  "geometry": {"coordinates":[127.16896800000001,34.761428],"type":"Point"}
}