{
  "type": "Feature",
  "properties": {
    "gn:admin1_code":"5.0",
    "gn:asciiname":"Motgol",
    "gn:country_code":"KR",
    "gn:dem":178,
    "gn:feature_class":"P",
    "gn:feature_code":"PPL",
    "gn:name":"Motgol",
    "gn:population":0,
    "gn:timezone":"Asia/Seoul",
    "iso:country":"KR",
    "name:kor_x_preferred":[
        "\ubabb\uace8"
    ],
    "name:und_x_variant":[
        "Mok-kol",
        "Motgol"
    ],
    "wof:name":"Motgol",
    "wof:placetype":"locality"
},
  "geometry": {"coordinates":[128.30587,37.05199],"type":"Point"}
}