{
  "type": "Feature",
  "properties": {
    "iso:country":"KR",
    "name:eng_x_preferred":[
        "Duryu-dong"
    ],
    "name:kor_x_preferred":[
        "\ub450\ub958\ub3d9"
    ],
    "qs:gn_adm0_cc":"KR",
    "qs:gn_local":1835329,
    "qs:local_max":1440,
    "qs:local_sum":5303,
    "qs:localhoods":33,
    "qs:name":"\ub450\ub958\ub3d9",
    "qs:name_adm0":"\ud55c\uad6d",
    "qs:name_adm1":"\ub300\uad6c",
    "qs:name_adm2":"\ub2ec\uc11c\uad6c",
    "qs:name_local":"\ub300\uad6c",
    "qs:photo_max":53,
    "qs:photo_sum":113,
    "qs:placetype":"Suburb",
    "qs:quad_count":6,
    "qs:woe_adm0":23424868,
    "qs:woe_adm1":2345971,
    "qs:woe_adm2":28289140,
    "qs:woe_lau":0,
    "qs:woe_local":1132466,
    "qs:woe_ver":"7.10.0",
    "wof:lang":[
        "kor"
    ],
    "wof:name":"Duryu-dong",
    "wof:placetype":"neighbourhood"
},
  "geometry": {"coordinates":[128.55999,35.849724],"type":"Point"}
}