{
  "type": "Feature",
  "properties": {
    "gn:admin1_code":"14.0",
    "gn:asciiname":"Ingak",
    "gn:country_code":"KR",
    "gn:dem":157,
    "gn:feature_class":"P",
    "gn:feature_code":"PPL",
    "gn:name":"Ingak",
    "gn:population":0,
    "gn:timezone":"Asia/Seoul",
    "iso:country":"KR",
    "name:kor_x_preferred":[
        "\uc778\uac01"
    ],
    "wof:name":"Ingak",
    "wof:placetype":"locality"
},
  "geometry": {"coordinates":[128.77257,36.12758],"type":"Point"}
}