{
  "type": "Feature",
  "properties": {
    "gn:admin1_code":"13.0",
    "gn:asciiname":"Gan-chon",
    "gn:country_code":"KR",
    "gn:dem":73,
    "gn:feature_class":"P",
    "gn:feature_code":"PPL",
    "gn:name":"Gan-chon",
    "gn:population":0,
    "gn:timezone":"Asia/Seoul",
    "iso:country":"KR",
    "name:und_x_variant":[
        "\uac04\ucd0c",
        "Gan-chon",
        "Kan-ch\u2019on"
    ],
    "wof:name":"Gan-chon",
    "wof:placetype":"locality"
},
  "geometry": {"coordinates":[127.39528,37.47],"type":"Point"}
}