{
  "type": "Feature",
  "properties": {
    "gn:admin1_code":"12.0",
    "gn:asciiname":"Andongpo",
    "gn:country_code":"KR",
    "gn:dem":19,
    "gn:feature_class":"P",
    "gn:feature_code":"PPL",
    "gn:name":"Andongpo",
    "gn:population":0,
    "gn:timezone":"Asia/Seoul",
    "iso:country":"KR",
    "name:kor_x_preferred":[
        "\uc548\ub3d9\ud3ec"
    ],
    "name:kor_x_variant":[
        "Andongp\u2019o"
    ],
    "wof:name":"Andongpo",
    "wof:placetype":"locality"
},
  "geometry": {"coordinates":[126.63766,37.58803],"type":"Point"}
}