{
  "type": "Feature",
  "properties": {
    "gn:admin1_code":"3.0",
    "gn:asciiname":"Sokkyo",
    "gn:country_code":"KR",
    "gn:dem":275,
    "gn:feature_class":"P",
    "gn:feature_code":"PPL",
    "gn:name":"S\u014fkkyo",
    "gn:population":0,
    "gn:timezone":"Asia/Seoul",
    "iso:country":"KR",
    "name:und_x_variant":[
        "\uc11d\uad50",
        "S\u014fkkyo"
    ],
    "wof:name":"Sokkyo",
    "wof:placetype":"locality"
},
  "geometry": {"coordinates":[127.36621,35.72883],"type":"Point"}
}