{
  "type": "Feature",
  "properties": {
    "gn:admin1_code":"5.0",
    "gn:asciiname":"Soek-kol",
    "gn:country_code":"KR",
    "gn:dem":509,
    "gn:feature_class":"P",
    "gn:feature_code":"PPL",
    "gn:name":"Soek-kol",
    "gn:population":0,
    "gn:timezone":"Asia/Seoul",
    "iso:country":"KR",
    "wof:name":"Soek-kol",
    "wof:placetype":"locality"
},
  "geometry": {"coordinates":[128.42139,36.90694000000001],"type":"Point"}
}