{
  "type": "Feature",
  "properties": {
    "gn:admin1_code":"14.0",
    "gn:asciiname":"Tarhyo",
    "gn:country_code":"KR",
    "gn:dem":6,
    "gn:feature_class":"P",
    "gn:feature_code":"PPL",
    "gn:name":"Tarhyo",
    "gn:population":0,
    "gn:timezone":"Asia/Seoul",
    "iso:country":"KR",
    "name:und_x_variant":[
        "\ub2ec\ud6a8",
        "Tarhyo"
    ],
    "wof:name":"Tarhyo",
    "wof:placetype":"locality"
},
  "geometry": {"coordinates":[129.4624,36.7371],"type":"Point"}
}