{
  "type": "Feature",
  "properties": {
    "gn:admin1_code":"17.0",
    "gn:asciiname":"Jakhyeon",
    "gn:country_code":"KR",
    "gn:dem":75,
    "gn:feature_class":"P",
    "gn:feature_code":"PPL",
    "gn:name":"Jakhyeon",
    "gn:population":0,
    "gn:timezone":"Asia/Seoul",
    "iso:country":"KR",
    "name:kor_x_preferred":[
        "\uc791\ud604"
    ],
    "wof:name":"Jakhyeon",
    "wof:placetype":"locality"
},
  "geometry": {"coordinates":[127.29716999999999,36.76521],"type":"Point"}
}