{
  "type": "Feature",
  "properties": {
    "gn:admin1_code":"6.0",
    "gn:asciiname":"Kumsal-li",
    "gn:country_code":"KR",
    "gn:dem":94,
    "gn:feature_class":"P",
    "gn:feature_code":"PPLL",
    "gn:name":"K\u016dmsal-li",
    "gn:population":0,
    "gn:timezone":"Asia/Seoul",
    "iso:country":"KR",
    "name:kor_x_preferred":[
        "\uae08\uc0b0\ub9ac"
    ],
    "name:kor_x_variant":[
        "K\u016dmsal-li"
    ],
    "wof:name":"Kumsal-li",
    "wof:placetype":"locality"
},
  "geometry": {"coordinates":[128.83213000000001,37.73932],"type":"Point"}
}