{
  "type": "Feature",
  "properties": {
    "gn:admin1_code":"6.0",
    "gn:asciiname":"Seomal",
    "gn:country_code":"KR",
    "gn:dem":140,
    "gn:feature_class":"P",
    "gn:feature_code":"PPL",
    "gn:name":"Seomal",
    "gn:population":0,
    "gn:timezone":"Asia/Seoul",
    "iso:country":"KR",
    "name:und_x_variant":[
        "\uc11c\ub9d0",
        "S\u014f-mal",
        "Seomal"
    ],
    "wof:name":"Seomal",
    "wof:placetype":"locality"
},
  "geometry": {"coordinates":[127.78358,37.84624],"type":"Point"}
}