{
  "type": "Feature",
  "properties": {
    "gn:admin1_code":"5.0",
    "gn:asciiname":"Witsalmi",
    "gn:country_code":"KR",
    "gn:dem":252,
    "gn:feature_class":"P",
    "gn:feature_code":"PPL",
    "gn:name":"Witsalmi",
    "gn:population":0,
    "gn:timezone":"Asia/Seoul",
    "iso:country":"KR",
    "name:kor_x_preferred":[
        "\uc717\uc0b4\ubbf8"
    ],
    "name:und_x_variant":[
        "Wissalmi",
        "Witsalmi"
    ],
    "wof:name":"Witsalmi",
    "wof:placetype":"locality"
},
  "geometry": {"coordinates":[128.13693999999998,37.05772],"type":"Point"}
}