{
  "type": "Feature",
  "properties": {
    "gn:admin1_code":"19.0",
    "gn:asciiname":"Bamsil",
    "gn:country_code":"KR",
    "gn:dem":87,
    "gn:feature_class":"P",
    "gn:feature_code":"PPL",
    "gn:name":"Bamsil",
    "gn:population":0,
    "gn:timezone":"Asia/Seoul",
    "iso:country":"KR",
    "name:kor_x_preferred":[
        "\ubc24\uc2e4"
    ],
    "name:und_x_variant":[
        "\uc2e0\ucd0c",
        "Sin-ch\u2019on",
        "Bamsil"
    ],
    "wof:name":"Bamsil",
    "wof:placetype":"locality"
},
  "geometry": {"coordinates":[127.50946,36.37313],"type":"Point"}
}