{
  "type": "Feature",
  "properties": {
    "gn:admin1_code":"13.0",
    "gn:asciiname":"Sujini-dong",
    "gn:country_code":"KR",
    "gn:dem":42,
    "gn:feature_class":"P",
    "gn:feature_code":"PPL",
    "gn:name":"Sujini-dong",
    "gn:population":0,
    "gn:timezone":"Asia/Seoul",
    "iso:country":"KR",
    "name:und_x_variant":[
        "\uc218\uc9c42\ub3d9",
        "Sujini-dong"
    ],
    "wof:name":"Sujini-dong",
    "wof:placetype":"locality"
},
  "geometry": {"coordinates":[127.12639,37.43667],"type":"Point"}
}