{
  "type": "Feature",
  "properties": {
    "gn:admin1_code":"14.0",
    "gn:asciiname":"Utchol-gol",
    "gn:country_code":"KR",
    "gn:dem":303,
    "gn:feature_class":"P",
    "gn:feature_code":"PPL",
    "gn:name":"Utch\u014fl-gol",
    "gn:population":0,
    "gn:timezone":"Asia/Seoul",
    "iso:country":"KR",
    "name:und_x_variant":[
        "\uc6c3\uc808\uace8",
        "Utch\u014fl-gol"
    ],
    "wof:name":"Utchol-gol",
    "wof:placetype":"locality"
},
  "geometry": {"coordinates":[129.19030000000001,36.5222],"type":"Point"}
}