{
  "type": "Feature",
  "properties": {
    "gn:admin1_code":"14.0",
    "gn:asciiname":"Chong-gol",
    "gn:country_code":"KR",
    "gn:dem":224,
    "gn:feature_class":"P",
    "gn:feature_code":"PPL",
    "gn:name":"Ch\u014fng-gol",
    "gn:population":0,
    "gn:timezone":"Asia/Seoul",
    "iso:country":"KR",
    "name:und_x_variant":[
        "\uc815\uace8",
        "Ch\u014fng-gol"
    ],
    "wof:name":"Chong-gol",
    "wof:placetype":"locality"
},
  "geometry": {"coordinates":[128.06209999999999,36.363],"type":"Point"}
}