{
  "type": "Feature",
  "properties": {
    "gn:admin1_code":"3.0",
    "gn:asciiname":"Kigong-ni",
    "gn:country_code":"KR",
    "gn:dem":240,
    "gn:feature_class":"P",
    "gn:feature_code":"PPL",
    "gn:name":"Kigong-ni",
    "gn:population":0,
    "gn:timezone":"Asia/Seoul",
    "iso:country":"KR",
    "name:und_x_variant":[
        "T\u2019\u014fil",
        "\ud130\uc77c"
    ],
    "wof:name":"Kigong-ni",
    "wof:placetype":"locality"
},
  "geometry": {"coordinates":[127.7171,36.0149],"type":"Point"}
}