{
  "type": "Feature",
  "properties": {
    "gn:admin1_code":"13.0",
    "gn:asciiname":"Hanteo",
    "gn:country_code":"KR",
    "gn:dem":83,
    "gn:feature_class":"P",
    "gn:feature_code":"PPL",
    "gn:name":"Hanteo",
    "gn:population":0,
    "gn:timezone":"Asia/Seoul",
    "iso:country":"KR",
    "name:kor_x_preferred":[
        "\uc194\uc885\uc9c0"
    ],
    "name:kor_x_variant":[
        "\ud55c\ud130"
    ],
    "name:und_x_variant":[
        "Solchongji",
        "Soljongji",
        "Hanteo"
    ],
    "wof:name":"Hanteo",
    "wof:placetype":"locality"
},
  "geometry": {"coordinates":[127.44193,37.77131],"type":"Point"}
}