{
  "type": "Feature",
  "properties": {
    "gn:admin1_code":"14.0",
    "gn:asciiname":"Witgalgol",
    "gn:country_code":"KR",
    "gn:dem":297,
    "gn:feature_class":"P",
    "gn:feature_code":"PPL",
    "gn:name":"Witgalgol",
    "gn:population":0,
    "gn:timezone":"Asia/Seoul",
    "iso:country":"KR",
    "name:kor_x_preferred":[
        "\uc717\uac08\uace8"
    ],
    "wof:name":"Witgalgol",
    "wof:placetype":"locality"
},
  "geometry": {"coordinates":[128.24158,36.76572],"type":"Point"}
}