{
  "type": "Feature",
  "properties": {
    "gn:admin1_code":"6.0",
    "gn:asciiname":"Pomaegi",
    "gn:country_code":"KR",
    "gn:dem":30,
    "gn:feature_class":"P",
    "gn:feature_code":"PPL",
    "gn:name":"Pomaegi",
    "gn:population":0,
    "gn:timezone":"Asia/Seoul",
    "iso:country":"KR",
    "name:kor_x_preferred":[
        "\ubcf4\ub9e4\uae30"
    ],
    "wof:name":"Pomaegi",
    "wof:placetype":"locality"
},
  "geometry": {"coordinates":[128.8578,37.8263],"type":"Point"}
}