{
  "type": "Feature",
  "properties": {
    "gn:admin1_code":"20.0",
    "gn:asciiname":"Kobi-dong",
    "gn:country_code":"KR",
    "gn:dem":720,
    "gn:feature_class":"P",
    "gn:feature_code":"PPL",
    "gn:name":"Kobi-dong",
    "gn:population":0,
    "gn:timezone":"Asia/Seoul",
    "iso:country":"KR",
    "name:und_x_variant":[
        "\uace0\ube44\ub3d9",
        "Kobi-dong"
    ],
    "wof:name":"Kobi-dong",
    "wof:placetype":"locality"
},
  "geometry": {"coordinates":[127.98463,35.82625],"type":"Point"}
}