{
  "type": "Feature",
  "properties": {
    "gn:admin1_code":"13.0",
    "gn:asciiname":"Tolsugye",
    "gn:country_code":"KR",
    "gn:dem":46,
    "gn:feature_class":"P",
    "gn:feature_code":"PPL",
    "gn:name":"Tolsugye",
    "gn:population":0,
    "gn:timezone":"Asia/Seoul",
    "iso:country":"KR",
    "name:und_x_variant":[
        "\ub3cc\uc218\uacc4",
        "Dolsugye",
        "Tolsugye"
    ],
    "wof:name":"Tolsugye",
    "wof:placetype":"locality"
},
  "geometry": {"coordinates":[127.11167,37.18389000000001],"type":"Point"}
}