{
  "type": "Feature",
  "properties": {
    "gn:admin1_code":"17.0",
    "gn:asciiname":"Makhyeon-ri",
    "gn:country_code":"KR",
    "gn:dem":171,
    "gn:feature_class":"P",
    "gn:feature_code":"PPLL",
    "gn:name":"Makhyeon-ri",
    "gn:population":0,
    "gn:timezone":"Asia/Seoul",
    "iso:country":"KR",
    "name:und_x_variant":[
        "\ub9c9\ud604\ub9ac",
        "Makhy\u014fl-li",
        "Makhyeon-ri"
    ],
    "wof:name":"Makhyeon-ri",
    "wof:placetype":"locality"
},
  "geometry": {"coordinates":[127.36317,36.19806],"type":"Point"}
}