{
  "type": "Feature",
  "properties": {
    "gn:admin1_code":"16.0",
    "gn:asciiname":"Hyojeong",
    "gn:country_code":"KR",
    "gn:dem":161,
    "gn:feature_class":"P",
    "gn:feature_code":"PPL",
    "gn:name":"Hyojeong",
    "gn:population":0,
    "gn:timezone":"Asia/Seoul",
    "iso:country":"KR",
    "name:kor_x_preferred":[
        "\ud6a8\uc815"
    ],
    "name:kor_x_variant":[
        "Hyoj\u014fng"
    ],
    "wof:name":"Hyojeong",
    "wof:placetype":"locality"
},
  "geometry": {"coordinates":[127.26685000000001,34.94138],"type":"Point"}
}