{
  "type": "Feature",
  "properties": {
    "gn:admin1_code":"16.0",
    "gn:asciiname":"Yulsan",
    "gn:country_code":"KR",
    "gn:dem":21,
    "gn:feature_class":"P",
    "gn:feature_code":"PPL",
    "gn:name":"Yulsan",
    "gn:population":0,
    "gn:timezone":"Asia/Seoul",
    "iso:country":"KR",
    "name:kor_x_preferred":[
        "\uc728\uc0b0"
    ],
    "wof:name":"Yulsan",
    "wof:placetype":"locality"
},
  "geometry": {"coordinates":[127.01569000000001,34.63174],"type":"Point"}
}