{
  "type": "Feature",
  "properties": {
    "gn:admin1_code":"16.0",
    "gn:asciiname":"Jeomchon",
    "gn:country_code":"KR",
    "gn:dem":49,
    "gn:feature_class":"P",
    "gn:feature_code":"PPL",
    "gn:name":"Jeomchon",
    "gn:population":0,
    "gn:timezone":"Asia/Seoul",
    "iso:country":"KR",
    "name:fas_x_preferred":[
        "\u062c\u0626\u0648\u0645\u0686\u0648\u0646"
    ],
    "name:kor_x_preferred":[
        "\uc810\ucd0c"
    ],
    "name:kor_x_variant":[
        "\uc810\ucd0c\ub3d9"
    ],
    "wof:name":"Jeomchon",
    "wof:placetype":"locality"
},
  "geometry": {"coordinates":[126.95434,35.02446],"type":"Point"}
}