{
  "type": "Feature",
  "properties": {
    "gn:admin1_code":"14.0",
    "gn:asciiname":"Byeolti",
    "gn:country_code":"KR",
    "gn:dem":173,
    "gn:feature_class":"P",
    "gn:feature_code":"PPL",
    "gn:name":"Byeolti",
    "gn:population":0,
    "gn:timezone":"Asia/Seoul",
    "iso:country":"KR",
    "name:kor_x_preferred":[
        "\ubcc4\ud2f0"
    ],
    "wof:name":"Byeolti",
    "wof:placetype":"locality"
},
  "geometry": {"coordinates":[128.91139999999999,36.60435],"type":"Point"}
}