{
  "type": "Feature",
  "properties": {
    "gn:admin1_code":"13.0",
    "gn:asciiname":"Jaraeul",
    "gn:country_code":"KR",
    "gn:dem":128,
    "gn:feature_class":"P",
    "gn:feature_code":"PPL",
    "gn:name":"Jaraeul",
    "gn:population":0,
    "gn:timezone":"Asia/Seoul",
    "iso:country":"KR",
    "name:kor_x_preferred":[
        "\uc790\ub798\uc6b8"
    ],
    "wof:name":"Jaraeul",
    "wof:placetype":"locality"
},
  "geometry": {"coordinates":[127.23275,37.9089],"type":"Point"}
}