{
  "type": "Feature",
  "properties": {
    "gn:admin1_code":"14.0",
    "gn:asciiname":"Tongmak",
    "gn:country_code":"KR",
    "gn:dem":138,
    "gn:feature_class":"P",
    "gn:feature_code":"PPL",
    "gn:name":"Tongmak",
    "gn:population":0,
    "gn:timezone":"Asia/Seoul",
    "iso:country":"KR",
    "name:und_x_variant":[
        "\ub3d9\ub9c9"
    ],
    "wof:name":"Tongmak",
    "wof:placetype":"locality"
},
  "geometry": {"coordinates":[129.36306000000002,37.05944],"type":"Point"}
}