{
  "type": "Feature",
  "properties": {
    "gn:admin1_code":"5.0",
    "gn:asciiname":"Suk-kol",
    "gn:country_code":"KR",
    "gn:dem":188,
    "gn:feature_class":"P",
    "gn:feature_code":"PPL",
    "gn:name":"Suk-kol",
    "gn:population":0,
    "gn:timezone":"Asia/Seoul",
    "iso:country":"KR",
    "name:und_x_variant":[
        "\uc22f\uace8",
        "Suk-kol"
    ],
    "wof:name":"Suk-kol",
    "wof:placetype":"locality"
},
  "geometry": {"coordinates":[127.87554,36.24716],"type":"Point"}
}