{
  "type": "Feature",
  "properties": {
    "gn:admin1_code":"3.0",
    "gn:asciiname":"Kal-gol",
    "gn:country_code":"KR",
    "gn:dem":444,
    "gn:feature_class":"P",
    "gn:feature_code":"PPL",
    "gn:name":"Kal-gol",
    "gn:population":0,
    "gn:timezone":"Asia/Seoul",
    "iso:country":"KR",
    "name:und_x_variant":[
        "\uac08\uace8",
        "Kal-gol"
    ],
    "wof:name":"Kal-gol",
    "wof:placetype":"locality"
},
  "geometry": {"coordinates":[127.57277000000001,35.87123],"type":"Point"}
}