{
  "type": "Feature",
  "properties": {
    "gn:admin1_code":"20.0",
    "gn:asciiname":"Chinae",
    "gn:country_code":"KR",
    "gn:dem":222,
    "gn:feature_class":"P",
    "gn:feature_code":"PPL",
    "gn:name":"Chinae",
    "gn:population":0,
    "gn:timezone":"Asia/Seoul",
    "iso:country":"KR",
    "name:und_x_variant":[
        "\uc9c0\ub0b4",
        "Chinae"
    ],
    "wof:name":"Chinae",
    "wof:placetype":"locality"
},
  "geometry": {"coordinates":[127.89702,35.70441],"type":"Point"}
}