{
  "type": "Feature",
  "properties": {
    "gn:admin1_code":"14.0",
    "gn:asciiname":"Mujigae",
    "gn:country_code":"KR",
    "gn:dem":408,
    "gn:feature_class":"P",
    "gn:feature_code":"PPL",
    "gn:name":"Mujigae",
    "gn:population":0,
    "gn:timezone":"Asia/Seoul",
    "iso:country":"KR",
    "wof:name":"Mujigae",
    "wof:placetype":"locality"
},
  "geometry": {"coordinates":[128.95889,36.22778],"type":"Point"}
}