{
  "type": "Feature",
  "properties": {
    "gn:admin1_code":"16.0",
    "gn:asciiname":"Mansu",
    "gn:country_code":"KR",
    "gn:dem":133,
    "gn:feature_class":"P",
    "gn:feature_code":"PPL",
    "gn:name":"Mansu",
    "gn:population":0,
    "gn:timezone":"Asia/Seoul",
    "iso:country":"KR",
    "name:kor_x_preferred":[
        "\ub9cc\uc218"
    ],
    "wof:name":"Mansu",
    "wof:placetype":"locality"
},
  "geometry": {"coordinates":[126.93992,34.74488],"type":"Point"}
}