{
  "type": "Feature",
  "properties": {
    "gn:admin1_code":"17.0",
    "gn:asciiname":"Dakjae",
    "gn:country_code":"KR",
    "gn:dem":63,
    "gn:feature_class":"P",
    "gn:feature_code":"PPL",
    "gn:name":"Dakjae",
    "gn:population":0,
    "gn:timezone":"Asia/Seoul",
    "iso:country":"KR",
    "name:kor_x_preferred":[
        "\ub2ed\uc7ac"
    ],
    "wof:name":"Dakjae",
    "wof:placetype":"locality"
},
  "geometry": {"coordinates":[127.34774,36.46251],"type":"Point"}
}