{
  "type": "Feature",
  "properties": {
    "gn:admin1_code":"0.0",
    "gn:asciiname":"Seongjeo",
    "gn:country_code":"KR",
    "gn:dem":119,
    "gn:feature_class":"P",
    "gn:feature_code":"PPL",
    "gn:name":"Seongjeo",
    "gn:population":0,
    "gn:timezone":"Asia/Seoul",
    "iso:country":"KR",
    "name:kor_x_preferred":[
        "\uc131\uc800"
    ],
    "wof:name":"Seongjeo",
    "wof:placetype":"locality"
},
  "geometry": {"coordinates":[129.28713999999999,35.65088],"type":"Point"}
}