{
  "type": "Feature",
  "properties": {
    "gn:admin1_code":"6.0",
    "gn:asciiname":"T'op'yong",
    "gn:country_code":"KR",
    "gn:dem":66,
    "gn:feature_class":"P",
    "gn:feature_code":"PPL",
    "gn:name":"T\u2019op\u2019y\u014fng",
    "gn:population":0,
    "gn:timezone":"Asia/Seoul",
    "iso:country":"KR",
    "wof:name":"T'op'yong",
    "wof:placetype":"locality"
},
  "geometry": {"coordinates":[127.81667,37.31667],"type":"Point"}
}