{
  "type": "Feature",
  "properties": {
    "gn:admin1_code":"20.0",
    "gn:asciiname":"Taep'yong",
    "gn:country_code":"KR",
    "gn:dem":248,
    "gn:feature_class":"P",
    "gn:feature_code":"PPL",
    "gn:name":"Taep\u2019y\u014fng",
    "gn:population":0,
    "gn:timezone":"Asia/Seoul",
    "iso:country":"KR",
    "name:und_x_variant":[
        "\ub300\ud3c9",
        "Taep\u2019y\u014fng"
    ],
    "wof:name":"Taep'yong",
    "wof:placetype":"locality"
},
  "geometry": {"coordinates":[127.66258000000001,35.53324],"type":"Point"}
}