{
  "type": "Feature",
  "properties": {
    "gn:country":"KR",
    "gn:fcode":"PPL",
    "gn:population":40423,
    "iso:country":"KR",
    "name:ceb_x_preferred":[
        "Hayang-eup"
    ],
    "name:eng_x_preferred":[
        "Hayang"
    ],
    "name:fas_x_preferred":[
        "\u0647\u0627\u06cc\u0627\u0646\u06af"
    ],
    "name:fra_x_preferred":[
        "Hayang"
    ],
    "name:jpn_x_preferred":[
        "\u6cb3\u967d\u9091"
    ],
    "name:kor_x_preferred":[
        "\ud558\uc591\uc74d"
    ],
    "name:swe_x_preferred":[
        "Hayang-eup"
    ],
    "name:und_x_variant":[
        "Kay\u014d"
    ],
    "name:zho_x_preferred":[
        "\u6cb3\u967d\u9091"
    ],
    "qs:name":"Hayang",
    "qs:photos_9r":0,
    "qs:photos_sr":0,
    "qs:pop_sr":"7",
    "wd:wordcount":77,
    "wof:name":"Hayang",
    "wof:placetype":"locality",
    "wof:population":40423
},
  "geometry": {"coordinates":[128.81999999999999,35.91333],"type":"Point"}
}