{
  "type": "Feature",
  "properties": {
    "gn:country":"KR",
    "gn:fcode":"PPL",
    "gn:pop":40423,
    "iso:country":"KR",
    "name:unk_x_variant":[
        "Kay\u014d"
    ],
    "qs:name":"Hayang",
    "qs:photos_9r":0,
    "qs:photos_sr":0,
    "qs:pop_sr":"7",
    "wd:wordcount":77,
    "wof:name":"Hayang",
    "wof:placetype":"locality",
    "wof:population":40423
},
  "geometry": {"coordinates":[128.81999999999999,35.91333],"type":"Point"}
}