{
  "type": "Feature",
  "properties": {
    "gn:admin1_code":"16.0",
    "gn:asciiname":"Malchi",
    "gn:country_code":"KR",
    "gn:dem":134,
    "gn:feature_class":"P",
    "gn:feature_code":"PPL",
    "gn:name":"Malchi",
    "gn:population":0,
    "gn:timezone":"Asia/Seoul",
    "iso:country":"KR",
    "name:kor_x_preferred":[
        "\ub9d0\uce58"
    ],
    "name:kor_x_variant":[
        "Malch\u2019i"
    ],
    "name:und_x_variant":[
        "Mach\u2019i",
        "Manch\u2019i",
        "Malchi"
    ],
    "wof:name":"Malchi",
    "wof:placetype":"locality"
},
  "geometry": {"coordinates":[127.17614,34.91987],"type":"Point"}
}