{
  "type": "Feature",
  "properties": {
    "gn:admin1_code":"5.0",
    "gn:asciiname":"Mara-gol",
    "gn:country_code":"KR",
    "gn:dem":312,
    "gn:feature_class":"P",
    "gn:feature_code":"PPL",
    "gn:name":"Mara-gol",
    "gn:population":0,
    "gn:timezone":"Asia/Seoul",
    "iso:country":"KR",
    "name:kor_x_preferred":[
        "\ub9c8\ub77c\uace8"
    ],
    "wof:name":"Mara-gol",
    "wof:placetype":"locality"
},
  "geometry": {"coordinates":[128.2011,37.1709],"type":"Point"}
}