{
  "type": "Feature",
  "properties": {
    "gn:admin1_code":"5.0",
    "gn:asciiname":"Taejol-li",
    "gn:country_code":"KR",
    "gn:dem":96,
    "gn:feature_class":"P",
    "gn:feature_code":"PPLL",
    "gn:name":"Taej\u014fl-li",
    "gn:population":0,
    "gn:timezone":"Asia/Seoul",
    "iso:country":"KR",
    "name:kor_x_preferred":[
        "\ub300\uc804\ub9ac"
    ],
    "name:kor_x_variant":[
        "Taej\u014fl-li"
    ],
    "wof:name":"Taejol-li",
    "wof:placetype":"locality"
},
  "geometry": {"coordinates":[127.93604000000001,37.04722],"type":"Point"}
}