{
  "type": "Feature",
  "properties": {
    "iso:country":"KR",
    "qs:name":"\ub355\uace1\uba74",
    "qs:name_adm0":"\ud55c\uad6d",
    "qs:name_adm1":"\uacbd\uc0c1\ubd81\ub3c4",
    "qs:photos":22,
    "qs:photos_1k":4,
    "qs:photos_9k":1,
    "qs:photos_9r":1,
    "qs:photos_all":22,
    "qs:photos_sr":1,
    "qs:placetype":"LocalAdmin",
    "qs:pop_sr":"0",
    "wof:name":"\ub355\uace1\uba74",
    "wof:placetype":"localadmin"
},
  "geometry": {"coordinates":[128.16650300000001,35.833401],"type":"Point"}
}