{
  "type": "Feature",
  "properties": {
    "gn:admin1_code":"5.0",
    "gn:asciiname":"Nosong-ni",
    "gn:country_code":"KR",
    "gn:dem":158,
    "gn:feature_class":"P",
    "gn:feature_code":"PPL",
    "gn:name":"Nosong-ni",
    "gn:population":0,
    "gn:timezone":"Asia/Seoul",
    "iso:country":"KR",
    "name:und_x_variant":[
        "\ub178\uc1a1\ub9ac",
        "Nodong",
        "Nosong-ni"
    ],
    "wof:name":"Nosong-ni",
    "wof:placetype":"locality"
},
  "geometry": {"coordinates":[127.65891999999999,36.84555],"type":"Point"}
}