{
  "type": "Feature",
  "properties": {
    "gn:admin1_code":"5.0",
    "gn:asciiname":"Jiseogol",
    "gn:country_code":"KR",
    "gn:dem":181,
    "gn:feature_class":"P",
    "gn:feature_code":"PPL",
    "gn:name":"Jiseogol",
    "gn:population":0,
    "gn:timezone":"Asia/Seoul",
    "iso:country":"KR",
    "name:kor_x_preferred":[
        "\uc9c0\uc18c\uace8"
    ],
    "name:kor_x_variant":[
        "\uc9c0\uc11c\uace8"
    ],
    "name:und_x_variant":[
        "Chiso-gol",
        "Jiseogol"
    ],
    "wof:name":"Jiseogol",
    "wof:placetype":"locality"
},
  "geometry": {"coordinates":[128.39375000000001,37.05409],"type":"Point"}
}