{
  "type": "Feature",
  "properties": {
    "gn:admin1_code":"12.0",
    "gn:asciiname":"Neungchon",
    "gn:country_code":"KR",
    "gn:dem":16,
    "gn:feature_class":"P",
    "gn:feature_code":"PPL",
    "gn:name":"Neungchon",
    "gn:population":0,
    "gn:timezone":"Asia/Seoul",
    "iso:country":"KR",
    "name:und_x_variant":[
        "\ub2a5\ucd0c",
        "Neungchon",
        "N\u016dng-ch\u2019on"
    ],
    "wof:name":"Neungchon",
    "wof:placetype":"locality"
},
  "geometry": {"coordinates":[126.49935000000001,37.68118],"type":"Point"}
}