{
  "type": "Feature",
  "properties": {
    "gn:admin1_code":"13.0",
    "gn:asciiname":"Chogam-ni",
    "gn:country_code":"KR",
    "gn:dem":42,
    "gn:feature_class":"P",
    "gn:feature_code":"PPL",
    "gn:name":"Ch\u014fgam-ni",
    "gn:population":0,
    "gn:timezone":"Asia/Seoul",
    "iso:country":"KR",
    "name:und_x_variant":[
        "\uc801\uc554\ub9ac",
        "Ch\u014fgam-ni"
    ],
    "wof:name":"Chogam-ni",
    "wof:placetype":"locality"
},
  "geometry": {"coordinates":[126.9952,37.9915],"type":"Point"}
}