{
  "type": "Feature",
  "properties": {
    "gn:admin1_code":"5.0",
    "gn:asciiname":"Dubyeong",
    "gn:country_code":"KR",
    "gn:dem":192,
    "gn:feature_class":"P",
    "gn:feature_code":"PPL",
    "gn:name":"Dubyeong",
    "gn:population":0,
    "gn:timezone":"Asia/Seoul",
    "iso:country":"KR",
    "name:kor_x_preferred":[
        "\ub450\ubcd1"
    ],
    "name:kor_x_variant":[
        "Tuby\u014fng"
    ],
    "wof:name":"Dubyeong",
    "wof:placetype":"locality"
},
  "geometry": {"coordinates":[128.36633999999998,37.05846],"type":"Point"}
}