{
  "type": "Feature",
  "properties": {
    "gn:admin1_code":"6.0",
    "gn:asciiname":"Saet'ogan",
    "gn:country_code":"KR",
    "gn:dem":252,
    "gn:feature_class":"P",
    "gn:feature_code":"PPL",
    "gn:name":"Saet\u2019\u014fgan",
    "gn:population":0,
    "gn:timezone":"Asia/Seoul",
    "iso:country":"KR",
    "name:kor_x_preferred":[
        "\uc0c8\ud130\uac04"
    ],
    "name:kor_x_variant":[
        "Saet\u2019\u014fgan"
    ],
    "wof:name":"Saet'ogan",
    "wof:placetype":"locality"
},
  "geometry": {"coordinates":[128.0806,37.6009],"type":"Point"}
}