{
  "type": "Feature",
  "properties": {
    "gn:admin1_code":"16.0",
    "gn:asciiname":"Seokgan",
    "gn:country_code":"KR",
    "gn:dem":5,
    "gn:feature_class":"P",
    "gn:feature_code":"PPL",
    "gn:name":"Seokgan",
    "gn:population":0,
    "gn:timezone":"Asia/Seoul",
    "iso:country":"KR",
    "name:kor_x_preferred":[
        "\uc11d\uac04"
    ],
    "name:kor_x_variant":[
        "S\u014fkkan"
    ],
    "wof:name":"Seokgan",
    "wof:placetype":"locality"
},
  "geometry": {"coordinates":[127.11592,34.69580999999999],"type":"Point"}
}