{
  "type": "Feature",
  "properties": {
    "gn:admin1_code":"20.0",
    "gn:asciiname":"Oe-ch'on",
    "gn:country_code":"KR",
    "gn:dem":35,
    "gn:feature_class":"P",
    "gn:feature_code":"PPL",
    "gn:name":"Oe-ch\u2019on",
    "gn:population":0,
    "gn:timezone":"Asia/Seoul",
    "iso:country":"KR",
    "name:und_x_variant":[
        "\uc678\ucd0c",
        "Oe-ch\u2019on"
    ],
    "wof:name":"Oe-ch'on",
    "wof:placetype":"locality"
},
  "geometry": {"coordinates":[128.19741000000002,35.61143],"type":"Point"}
}