{
  "type": "Feature",
  "properties": {
    "gn:admin1_code":"5.0",
    "gn:asciiname":"Gosijeonggol",
    "gn:country_code":"KR",
    "gn:dem":285,
    "gn:feature_class":"P",
    "gn:feature_code":"PPL",
    "gn:name":"Gosijeonggol",
    "gn:population":0,
    "gn:timezone":"Asia/Seoul",
    "iso:country":"KR",
    "name:kor_x_preferred":[
        "\uace0\uc2dc\uc815\uace8"
    ],
    "wof:name":"Gosijeonggol",
    "wof:placetype":"locality"
},
  "geometry": {"coordinates":[127.68893,36.73351],"type":"Point"}
}