{
  "type": "Feature",
  "properties": {
    "gn:admin1_code":"17.0",
    "gn:asciiname":"Kuonan",
    "gn:country_code":"KR",
    "gn:dem":16,
    "gn:feature_class":"P",
    "gn:feature_code":"PPL",
    "gn:name":"Ku\u014fnan",
    "gn:population":0,
    "gn:timezone":"Asia/Seoul",
    "iso:country":"KR",
    "name:und_x_variant":[
        "\uad6c\uc5b8\uc548",
        "Ku\u014fnan"
    ],
    "wof:name":"Kuonan",
    "wof:placetype":"locality"
},
  "geometry": {"coordinates":[126.4495,36.7356],"type":"Point"}
}