{
  "type": "Feature",
  "properties": {
    "gn:admin1_code":"16.0",
    "gn:asciiname":"Bangjugan",
    "gn:country_code":"KR",
    "gn:dem":35,
    "gn:feature_class":"P",
    "gn:feature_code":"PPL",
    "gn:name":"Bangjugan",
    "gn:population":0,
    "gn:timezone":"Asia/Seoul",
    "iso:country":"KR",
    "name:kor_x_preferred":[
        "\ubc29\uc8fd\uc548"
    ],
    "name:und_x_variant":[
        "Pangch\u2019ung-ni",
        "Pangch\u2019uk",
        "Bangjugan",
        "Naech\u2019uk"
    ],
    "wof:name":"Bangjugan",
    "wof:placetype":"locality"
},
  "geometry": {"coordinates":[126.83351999999999,35.02885999999999],"type":"Point"}
}