{
  "type": "Feature",
  "properties": {
    "gn:admin1_code":"16.0",
    "gn:asciiname":"Daman",
    "gn:country_code":"KR",
    "gn:dem":31,
    "gn:feature_class":"P",
    "gn:feature_code":"PPL",
    "gn:name":"Daman",
    "gn:population":0,
    "gn:timezone":"Asia/Seoul",
    "iso:country":"KR",
    "name:kor_x_preferred":[
        "\ub2e4\ub9cc"
    ],
    "wof:name":"Daman",
    "wof:placetype":"locality"
},
  "geometry": {"coordinates":[126.88002,35.0102],"type":"Point"}
}