{
  "type": "Feature",
  "properties": {
    "iso:country":"KR",
    "name:eng_x_preferred":[
        "Bodeok-dong"
    ],
    "name:kor_x_preferred":[
        "\ubcf4\ub355\ub3d9"
    ],
    "qs:name":"\ubcf4\ub355\ub3d9",
    "qs:name_adm0":"\ud55c\uad6d",
    "qs:name_adm1":"\uacbd\uc0c1\ubd81\ub3c4",
    "qs:photos":48,
    "qs:photos_1k":10,
    "qs:photos_9k":1,
    "qs:photos_9r":2,
    "qs:photos_all":48,
    "qs:photos_sr":2,
    "qs:placetype":"LocalAdmin",
    "qs:pop_sr":"0",
    "wof:name":"Bodeok-dong",
    "wof:placetype":"localadmin"
},
  "geometry": {"coordinates":[129.27741,35.841751],"type":"Point"}
}