{
  "type": "Feature",
  "properties": {
    "gn:admin1_code":"17.0",
    "gn:asciiname":"Notchong-gol",
    "gn:country_code":"KR",
    "gn:dem":190,
    "gn:feature_class":"P",
    "gn:feature_code":"PPL",
    "gn:name":"Notchong-gol",
    "gn:population":0,
    "gn:timezone":"Asia/Seoul",
    "iso:country":"KR",
    "name:und_x_variant":[
        "\ub18b\uc885\uace8",
        "Notchong-gol"
    ],
    "wof:name":"Notchong-gol",
    "wof:placetype":"locality"
},
  "geometry": {"coordinates":[127.4208,36.1467],"type":"Point"}
}