{
  "type": "Feature",
  "properties": {
    "gn:admin1_code":"20.0",
    "gn:asciiname":"Sinpo",
    "gn:country_code":"KR",
    "gn:dem":1,
    "gn:feature_class":"P",
    "gn:feature_code":"PPL",
    "gn:name":"Sinpo",
    "gn:population":0,
    "gn:timezone":"Asia/Seoul",
    "iso:country":"KR",
    "name:cat_x_preferred":[
        "Sinpo"
    ],
    "name:ces_x_preferred":[
        "Sinpcho"
    ],
    "name:deu_x_preferred":[
        "Sinpo"
    ],
    "name:fas_x_preferred":[
        "\u0633\u06cc\u0646\u067e\u0648"
    ],
    "name:fin_x_preferred":[
        "Sinpo"
    ],
    "name:fra_x_preferred":[
        "Sinpo"
    ],
    "name:ita_x_preferred":[
        "Sinpo"
    ],
    "name:jpn_x_preferred":[
        "\u65b0\u6d66\u5e02"
    ],
    "name:kor_x_preferred":[
        "\uc2e0\ud3ec"
    ],
    "name:kor_x_variant":[
        "\uc2e0\ud3ec\uc2dc"
    ],
    "name:nds_x_preferred":[
        "Sinpo"
    ],
    "name:nld_x_preferred":[
        "Sinp'o"
    ],
    "name:nor_x_preferred":[
        "Sinpo"
    ],
    "name:pol_x_preferred":[
        "Sinp'o"
    ],
    "name:por_x_preferred":[
        "Sinp'o"
    ],
    "name:rus_x_preferred":[
        "\u0421\u0438\u043d\u043f\u0445\u043e"
    ],
    "name:sco_x_preferred":[
        "Sinpo"
    ],
    "name:spa_x_preferred":[
        "Sinpo"
    ],
    "name:swe_x_preferred":[
        "Sinpo"
    ],
    "name:tur_x_preferred":[
        "Sinpo"
    ],
    "name:urd_x_preferred":[
        "\u0633\u0646\u067e\u0648"
    ],
    "name:vie_x_preferred":[
        "Sinpo"
    ],
    "name:zho_x_preferred":[
        "\u65b0\u6d66\u5e02"
    ],
    "wof:name":"Sinpo",
    "wof:placetype":"locality"
},
  "geometry": {"coordinates":[128.85572999999999,35.19295],"type":"Point"}
}