{
  "type": "Feature",
  "properties": {
    "gn:admin1_code":"5.0",
    "gn:asciiname":"Gureungmal",
    "gn:country_code":"KR",
    "gn:dem":106,
    "gn:feature_class":"P",
    "gn:feature_code":"PPL",
    "gn:name":"Gureungmal",
    "gn:population":0,
    "gn:timezone":"Asia/Seoul",
    "iso:country":"KR",
    "name:kor_x_preferred":[
        "\uad6c\ub989\ub9d0"
    ],
    "wof:name":"Gureungmal",
    "wof:placetype":"locality"
},
  "geometry": {"coordinates":[127.5484,36.9698],"type":"Point"}
}