{
  "type": "Feature",
  "properties": {
    "gn:admin1_code":"11.0",
    "gn:asciiname":"Yonhuii-dong",
    "gn:country_code":"KR",
    "gn:dem":88,
    "gn:feature_class":"P",
    "gn:feature_code":"PPL",
    "gn:name":"Y\u014fnh\u016dii-dong",
    "gn:population":0,
    "gn:timezone":"Asia/Seoul",
    "iso:country":"KR",
    "name:und_x_variant":[
        "\uc5f0\ud76c2\ub3d9",
        "Y\u014fnh\u016dii-dong"
    ],
    "wof:name":"Yonhuii-dong",
    "wof:placetype":"locality"
},
  "geometry": {"coordinates":[126.93125000000001,37.57422],"type":"Point"}
}