{
  "type": "Feature",
  "properties": {
    "gn:admin1_code":"17.0",
    "gn:asciiname":"Sandwi",
    "gn:country_code":"KR",
    "gn:dem":34,
    "gn:feature_class":"P",
    "gn:feature_code":"PPL",
    "gn:name":"Sandwi",
    "gn:population":0,
    "gn:timezone":"Asia/Seoul",
    "iso:country":"KR",
    "name:und_x_variant":[
        "Sanbung-ni",
        "\uc0b0\ub4a4",
        "Sandwi"
    ],
    "wof:name":"Sandwi",
    "wof:placetype":"locality"
},
  "geometry": {"coordinates":[126.4267,36.7885],"type":"Point"}
}