{
  "type": "Feature",
  "properties": {
    "gn:admin1_code":"14.0",
    "gn:asciiname":"Naewol",
    "gn:country_code":"KR",
    "gn:dem":83,
    "gn:feature_class":"P",
    "gn:feature_code":"PPL",
    "gn:name":"Naew\u014fl",
    "gn:population":0,
    "gn:timezone":"Asia/Seoul",
    "iso:country":"KR",
    "name:und_x_variant":[
        "\ub0b4\uc6d4",
        "Naew\u014fl"
    ],
    "wof:name":"Naewol",
    "wof:placetype":"locality"
},
  "geometry": {"coordinates":[128.2251,36.2416],"type":"Point"}
}