{
  "type": "Feature",
  "properties": {
    "gn:admin1_code":"5.0",
    "gn:asciiname":"Sumung-mal",
    "gn:country_code":"KR",
    "gn:dem":110,
    "gn:feature_class":"P",
    "gn:feature_code":"PPL",
    "gn:name":"Sumung-mal",
    "gn:population":0,
    "gn:timezone":"Asia/Seoul",
    "iso:country":"KR",
    "name:und_x_variant":[
        "\uc218\ubb35\ub9d0",
        "Sumung-mal"
    ],
    "wof:name":"Sumung-mal",
    "wof:placetype":"locality"
},
  "geometry": {"coordinates":[127.6263,36.227],"type":"Point"}
}