{
  "type": "Feature",
  "properties": {
    "gn:admin1_code":"13.0",
    "gn:asciiname":"Deurinbawi",
    "gn:country_code":"KR",
    "gn:dem":99,
    "gn:feature_class":"P",
    "gn:feature_code":"PPL",
    "gn:name":"Deurinbawi",
    "gn:population":0,
    "gn:timezone":"Asia/Seoul",
    "iso:country":"KR",
    "name:kor_x_preferred":[
        "\ub4dc\ub9b0\ubc14\uc704"
    ],
    "name:kor_x_variant":[
        "T\u016drinbawi"
    ],
    "wof:name":"Deurinbawi",
    "wof:placetype":"locality"
},
  "geometry": {"coordinates":[127.5437,37.16128],"type":"Point"}
}