{
  "type": "Feature",
  "properties": {
    "gn:admin1_code":"14.0",
    "gn:asciiname":"Dojin",
    "gn:country_code":"KR",
    "gn:dem":181,
    "gn:feature_class":"P",
    "gn:feature_code":"PPL",
    "gn:name":"Dojin",
    "gn:population":0,
    "gn:timezone":"Asia/Seoul",
    "iso:country":"KR",
    "name:kor_x_preferred":[
        "\ub3c4\uc9c4"
    ],
    "name:und_x_variant":[
        "Tojin"
    ],
    "wof:name":"Dojin",
    "wof:placetype":"locality"
},
  "geometry": {"coordinates":[129.11276999999998,35.73099000000001],"type":"Point"}
}