{
  "type": "Feature",
  "properties": {
    "gn:admin1_code":"17.0",
    "gn:asciiname":"Changsamok-kol",
    "gn:country_code":"KR",
    "gn:dem":100,
    "gn:feature_class":"P",
    "gn:feature_code":"PPL",
    "gn:name":"Changsamok-kol",
    "gn:population":0,
    "gn:timezone":"Asia/Seoul",
    "iso:country":"KR",
    "name:und_x_variant":[
        "\uc7a5\uc0ac\ubaa9\uace8",
        "Changsamok-kol"
    ],
    "wof:name":"Changsamok-kol",
    "wof:placetype":"locality"
},
  "geometry": {"coordinates":[126.6221,36.8089],"type":"Point"}
}