{
  "type": "Feature",
  "properties": {
    "gn:admin1_code":"20.0",
    "gn:asciiname":"Hopo",
    "gn:country_code":"KR",
    "gn:dem":19,
    "gn:feature_class":"P",
    "gn:feature_code":"PPL",
    "gn:name":"Hopo",
    "gn:population":0,
    "gn:timezone":"Asia/Seoul",
    "iso:country":"KR",
    "name:kor_x_preferred":[
        "\ud638\ud3ec"
    ],
    "name:und_x_variant":[
        "Koho-ri",
        "Hop\u2019o-ri",
        "Hop\u2019o",
        "Hopo"
    ],
    "wof:name":"Hopo",
    "wof:placetype":"locality"
},
  "geometry": {"coordinates":[129.01519999999999,35.28411],"type":"Point"}
}