{
  "type": "Feature",
  "properties": {
    "gn:admin1_code":"17.0",
    "gn:asciiname":"Mun'goji",
    "gn:country_code":"KR",
    "gn:dem":22,
    "gn:feature_class":"P",
    "gn:feature_code":"PPL",
    "gn:name":"Mun\u2019goji",
    "gn:population":0,
    "gn:timezone":"Asia/Seoul",
    "iso:country":"KR",
    "name:und_x_variant":[
        "Mun\u2019gon-ni",
        "\ubb38\uacf6\uc774",
        "Mun\u2019goji"
    ],
    "wof:name":"Mun'goji",
    "wof:placetype":"locality"
},
  "geometry": {"coordinates":[126.44410000000001,36.9007],"type":"Point"}
}