{
  "type": "Feature",
  "properties": {
    "gn:admin1_code":"6.0",
    "gn:asciiname":"Minamigol",
    "gn:country_code":"KR",
    "gn:dem":101,
    "gn:feature_class":"P",
    "gn:feature_code":"PPL",
    "gn:name":"Minamigol",
    "gn:population":0,
    "gn:timezone":"Asia/Seoul",
    "iso:country":"KR",
    "name:kor_x_preferred":[
        "\ubaa8\ub098\ubbf8\uace8"
    ],
    "name:kor_x_variant":[
        "\ubbf8\ub098\ubbf8\uace8"
    ],
    "name:und_x_variant":[
        "M\u014fnami-gol",
        "Minamigol"
    ],
    "wof:name":"Minamigol",
    "wof:placetype":"locality"
},
  "geometry": {"coordinates":[128.56010000000001,38.08593],"type":"Point"}
}