{
  "type": "Feature",
  "properties": {
    "gn:admin1_code":"20.0",
    "gn:asciiname":"Ganjeok",
    "gn:country_code":"KR",
    "gn:dem":101,
    "gn:feature_class":"P",
    "gn:feature_code":"PPL",
    "gn:name":"Ganjeok",
    "gn:population":0,
    "gn:timezone":"Asia/Seoul",
    "iso:country":"KR",
    "name:und_x_variant":[
        "\uac04\uc801",
        "Kanj\u014fk",
        "Ganjeok"
    ],
    "wof:name":"Ganjeok",
    "wof:placetype":"locality"
},
  "geometry": {"coordinates":[128.49413999999999,35.60025],"type":"Point"}
}