{
  "type": "Feature",
  "properties": {
    "gn:admin1_code":"14.0",
    "gn:asciiname":"Sinan",
    "gn:country_code":"KR",
    "gn:dem":30,
    "gn:feature_class":"P",
    "gn:feature_code":"PPL",
    "gn:name":"Sinan",
    "gn:population":0,
    "gn:timezone":"Asia/Seoul",
    "iso:country":"KR",
    "name:und_x_variant":[
        "\uc2e0\uc548",
        "Sinan"
    ],
    "wof:name":"Sinan",
    "wof:placetype":"locality"
},
  "geometry": {"coordinates":[129.25446000000002,36.02365],"type":"Point"}
}