{
  "type": "Feature",
  "properties": {
    "gn:admin1_code":"14.0",
    "gn:asciiname":"Wonje-dong",
    "gn:country_code":"KR",
    "gn:dem":77,
    "gn:feature_class":"P",
    "gn:feature_code":"PPL",
    "gn:name":"Wonje-dong",
    "gn:population":0,
    "gn:timezone":"Asia/Seoul",
    "iso:country":"KR",
    "name:und_x_variant":[
        "W\u014fnje-ri"
    ],
    "wof:name":"Wonje-dong",
    "wof:placetype":"locality"
},
  "geometry": {"coordinates":[128.89556000000002,35.94278],"type":"Point"}
}