{
  "type": "Feature",
  "properties": {
    "gn:admin1_code":"15.0",
    "gn:asciiname":"Sogyenae",
    "gn:country_code":"KR",
    "gn:dem":68,
    "gn:feature_class":"P",
    "gn:feature_code":"PPL",
    "gn:name":"Sogyenae",
    "gn:population":0,
    "gn:timezone":"Asia/Seoul",
    "iso:country":"KR",
    "name:kor_x_preferred":[
        "\uc18c\uacc4\ub0b4"
    ],
    "wof:name":"Sogyenae",
    "wof:placetype":"locality"
},
  "geometry": {"coordinates":[128.62545,35.84407],"type":"Point"}
}