{
  "type": "Feature",
  "properties": {
    "gn:admin1_code":"0.0",
    "gn:asciiname":"Yongdong-dong",
    "gn:country_code":"KR",
    "gn:dem":520,
    "gn:feature_class":"P",
    "gn:feature_code":"PPL",
    "gn:name":"Y\u014fngdong-dong",
    "gn:population":0,
    "gn:timezone":"Asia/Seoul",
    "iso:country":"KR",
    "wof:name":"Yongdong-dong",
    "wof:placetype":"locality"
},
  "geometry": {"coordinates":[127.68333,35.71667],"type":"Point"}
}