{
  "type": "Feature",
  "properties": {
    "gn:admin1_code":"17.0",
    "gn:asciiname":"Aera-ri",
    "gn:country_code":"KR",
    "gn:dem":75,
    "gn:feature_class":"P",
    "gn:feature_code":"PPL",
    "gn:name":"Aera-ri",
    "gn:population":0,
    "gn:timezone":"Asia/Seoul",
    "iso:country":"KR",
    "name:und_x_variant":[
        "\uc560\ub77c\ub9ac",
        "Aera-ri"
    ],
    "wof:name":"Aera-ri",
    "wof:placetype":"locality"
},
  "geometry": {"coordinates":[126.8552,36.5361],"type":"Point"}
}