{
  "type": "Feature",
  "properties": {
    "gn:admin1_code":"5.0",
    "gn:asciiname":"Ugyong",
    "gn:country_code":"KR",
    "gn:dem":267,
    "gn:feature_class":"P",
    "gn:feature_code":"PPL",
    "gn:name":"Ugy\u014fng",
    "gn:population":0,
    "gn:timezone":"Asia/Seoul",
    "iso:country":"KR",
    "name:kor_x_preferred":[
        "\uc6b0\uacbd"
    ],
    "name:kor_x_variant":[
        "Ugy\u014fng"
    ],
    "wof:name":"Ugyong",
    "wof:placetype":"locality"
},
  "geometry": {"coordinates":[128.00434999999999,37.1646],"type":"Point"}
}