{
  "type": "Feature",
  "properties": {
    "gn:admin1_code":"6.0",
    "gn:asciiname":"Chungmaup",
    "gn:country_code":"KR",
    "gn:dem":214,
    "gn:feature_class":"P",
    "gn:feature_code":"PPL",
    "gn:name":"Chungma\u016dp",
    "gn:population":0,
    "gn:timezone":"Asia/Seoul",
    "iso:country":"KR",
    "name:und_x_variant":[
        "\uc911\ub9c8\uc74d",
        "Chungma\u016dp"
    ],
    "wof:name":"Chungmaup",
    "wof:placetype":"locality"
},
  "geometry": {"coordinates":[129.17789999999999,37.2689],"type":"Point"}
}