{
  "type": "Feature",
  "properties": {
    "gn:admin1_code":"17.0",
    "gn:asciiname":"Won-gol",
    "gn:country_code":"KR",
    "gn:dem":40,
    "gn:feature_class":"P",
    "gn:feature_code":"PPL",
    "gn:name":"W\u014fn-gol",
    "gn:population":0,
    "gn:timezone":"Asia/Seoul",
    "iso:country":"KR",
    "name:und_x_variant":[
        "\uc6d0\uace8",
        "W\u014fn-gol"
    ],
    "wof:name":"Won-gol",
    "wof:placetype":"locality"
},
  "geometry": {"coordinates":[126.74469999999999,36.4957],"type":"Point"}
}