{
  "type": "Feature",
  "properties": {
    "gn:admin1_code":"5.0",
    "gn:asciiname":"Minp'an-dong",
    "gn:country_code":"KR",
    "gn:dem":436,
    "gn:feature_class":"P",
    "gn:feature_code":"PPL",
    "gn:name":"Minp\u2019an-dong",
    "gn:population":0,
    "gn:timezone":"Asia/Seoul",
    "iso:country":"KR",
    "wof:name":"Minp'an-dong",
    "wof:placetype":"locality"
},
  "geometry": {"coordinates":[127.82528000000001,36.55306],"type":"Point"}
}