{
  "type": "Feature",
  "properties": {
    "gn:admin1_code":"14.0",
    "gn:asciiname":"Modumi",
    "gn:country_code":"KR",
    "gn:dem":232,
    "gn:feature_class":"P",
    "gn:feature_code":"PPL",
    "gn:name":"Mod\u016dmi",
    "gn:population":0,
    "gn:timezone":"Asia/Seoul",
    "iso:country":"KR",
    "name:und_x_variant":[
        "\ubaa8\ub4ec\uc774",
        "Mod\u016dmi"
    ],
    "wof:name":"Modumi",
    "wof:placetype":"locality"
},
  "geometry": {"coordinates":[128.9616,36.4458],"type":"Point"}
}