{
  "type": "Feature",
  "properties": {
    "gn:admin1_code":"14.0",
    "gn:asciiname":"Toriwon",
    "gn:country_code":"KR",
    "gn:dem":260,
    "gn:feature_class":"P",
    "gn:feature_code":"PPL",
    "gn:name":"Toriw\u014fn",
    "gn:population":0,
    "gn:timezone":"Asia/Seoul",
    "iso:country":"KR",
    "name:und_x_variant":[
        "\ub3c4\ub9ac\uc6d0",
        "Toriw\u014fn"
    ],
    "wof:name":"Toriwon",
    "wof:placetype":"locality"
},
  "geometry": {"coordinates":[127.9529,36.2767],"type":"Point"}
}