{
  "type": "Feature",
  "properties": {
    "gn:admin1_code":"14.0",
    "gn:asciiname":"Susan",
    "gn:country_code":"KR",
    "gn:dem":86,
    "gn:feature_class":"P",
    "gn:feature_code":"PPL",
    "gn:name":"Susan",
    "gn:population":0,
    "gn:timezone":"Asia/Seoul",
    "iso:country":"KR",
    "name:und_x_variant":[
        "\uc218\uc0b0",
        "Susan"
    ],
    "wof:name":"Susan",
    "wof:placetype":"locality"
},
  "geometry": {"coordinates":[128.29148999999998,36.48025],"type":"Point"}
}