{
  "type": "Feature",
  "properties": {
    "gn:admin1_code":"14.0",
    "gn:asciiname":"Susan",
    "gn:country_code":"KR",
    "gn:dem":86,
    "gn:feature_class":"P",
    "gn:feature_code":"PPL",
    "gn:name":"Susan",
    "gn:population":0,
    "gn:timezone":"Asia/Seoul",
    "iso:country":"KR",
    "name:afr_x_preferred":[
        "Susan"
    ],
    "name:ara_x_preferred":[
        "\u0633\u0648\u0632\u0627\u0646"
    ],
    "name:bre_x_preferred":[
        "Susan"
    ],
    "name:deu_x_preferred":[
        "Susan"
    ],
    "name:epo_x_preferred":[
        "Susano"
    ],
    "name:fas_x_preferred":[
        "\u0633\u0648\u0632\u0627\u0646"
    ],
    "name:isl_x_preferred":[
        "Susan"
    ],
    "name:nld_x_preferred":[
        "Susan"
    ],
    "name:nor_x_preferred":[
        "Susan"
    ],
    "name:rus_x_preferred":[
        "\u0421\u044c\u044e\u0437\u0430\u043d"
    ],
    "name:und_x_variant":[
        "\uc218\uc0b0"
    ],
    "wof:name":"Susan",
    "wof:placetype":"locality"
},
  "geometry": {"coordinates":[128.29148999999998,36.48025],"type":"Point"}
}