{
  "type": "Feature",
  "properties": {
    "iso:country":"KR",
    "name:eng_x_preferred":[
        "Jinseong-myeon"
    ],
    "name:kor_x_preferred":[
        "\uc9c4\uc131\uba74"
    ],
    "qs:name":"\uc9c4\uc131\uba74",
    "qs:name_adm0":"\ud55c\uad6d",
    "qs:name_adm1":"\uacbd\uc0c1\ub0a8\ub3c4",
    "qs:photos":11,
    "qs:photos_1k":2,
    "qs:photos_9k":1,
    "qs:photos_9r":1,
    "qs:photos_all":11,
    "qs:photos_sr":1,
    "qs:placetype":"LocalAdmin",
    "qs:pop_sr":"0",
    "wof:name":"Jinseong-myeon",
    "wof:placetype":"localadmin"
},
  "geometry": {"coordinates":[128.04565400000001,35.200744],"type":"Point"}
}