{
  "type": "Feature",
  "properties": {
    "gn:admin1_code":"5.0",
    "gn:asciiname":"Witmal",
    "gn:country_code":"KR",
    "gn:dem":89,
    "gn:feature_class":"P",
    "gn:feature_code":"PPL",
    "gn:name":"Witmal",
    "gn:population":0,
    "gn:timezone":"Asia/Seoul",
    "iso:country":"KR",
    "name:kor_x_preferred":[
        "\uc717\ub9d0"
    ],
    "wof:name":"Witmal",
    "wof:placetype":"locality"
},
  "geometry": {"coordinates":[127.82076000000001,36.97283],"type":"Point"}
}