{
  "type": "Feature",
  "properties": {
    "gn:admin1_code":"20.0",
    "gn:asciiname":"Yombuni",
    "gn:cc2":"KR",
    "gn:country_code":"KR",
    "gn:dem":1,
    "gn:feature_class":"P",
    "gn:feature_code":"PPL",
    "gn:name":"Y\u014fmbuni",
    "gn:population":0,
    "gn:timezone":"Asia/Seoul",
    "iso:country":"KR",
    "name:und_x_variant":[
        "Y\u014fmbu-ri",
        "Y\u014fmbuni"
    ],
    "wof:name":"Yombuni",
    "wof:placetype":"locality"
},
  "geometry": {"coordinates":[128.40693999999999,35.05722],"type":"Point"}
}