{
  "type": "Feature",
  "properties": {
    "gn:admin1_code":"20.0",
    "gn:asciiname":"Soksal-li",
    "gn:country_code":"KR",
    "gn:dem":0,
    "gn:feature_class":"P",
    "gn:feature_code":"PPL",
    "gn:name":"S\u014fksal-li",
    "gn:population":0,
    "gn:timezone":"Asia/Seoul",
    "iso:country":"KR",
    "wof:name":"Soksal-li",
    "wof:placetype":"locality"
},
  "geometry": {"coordinates":[129.02583000000001,35.31694],"type":"Point"}
}