{
  "type": "Feature",
  "properties": {
    "gn:admin1_code":"6.0",
    "gn:asciiname":"Doenteo",
    "gn:country_code":"KR",
    "gn:dem":426,
    "gn:feature_class":"P",
    "gn:feature_code":"PPL",
    "gn:name":"Doenteo",
    "gn:population":0,
    "gn:timezone":"Asia/Seoul",
    "iso:country":"KR",
    "name:kor_x_preferred":[
        "\ub41c\ud130"
    ],
    "name:kor_x_variant":[
        "Toent\u2019\u014f"
    ],
    "wof:name":"Doenteo",
    "wof:placetype":"locality"
},
  "geometry": {"coordinates":[127.89361,38.05556],"type":"Point"}
}