{
  "type": "Feature",
  "properties": {
    "gn:admin1_code":"13.0",
    "gn:asciiname":"Dochon-dong",
    "gn:country_code":"KR",
    "gn:dem":64,
    "gn:feature_class":"P",
    "gn:feature_code":"PPLL",
    "gn:name":"Dochon-dong",
    "gn:population":0,
    "gn:timezone":"Asia/Seoul",
    "iso:country":"KR",
    "name:und_x_variant":[
        "\ub3c4\ucd0c\ub3d9",
        "Dochon-dong",
        "Toch\u2019on-dong"
    ],
    "wof:name":"Dochon-dong",
    "wof:placetype":"locality"
},
  "geometry": {"coordinates":[127.15694000000001,37.41917],"type":"Point"}
}