{
  "type": "Feature",
  "properties": {
    "gn:admin1_code":"3.0",
    "gn:asciiname":"Sujwa-dong",
    "gn:country_code":"KR",
    "gn:dem":274,
    "gn:feature_class":"P",
    "gn:feature_code":"PPL",
    "gn:name":"Sujwa-dong",
    "gn:population":0,
    "gn:timezone":"Asia/Seoul",
    "iso:country":"KR",
    "name:und_x_variant":[
        "\uc218\uc88c\ub3d9",
        "Sujwa-dong"
    ],
    "wof:name":"Sujwa-dong",
    "wof:placetype":"locality"
},
  "geometry": {"coordinates":[127.53452,35.92405],"type":"Point"}
}