{
  "type": "Feature",
  "properties": {
    "gn:admin1_code":"6.0",
    "gn:asciiname":"Omong-ni",
    "gn:country_code":"KR",
    "gn:dem":266,
    "gn:feature_class":"P",
    "gn:feature_code":"PPL",
    "gn:name":"Omong-ni",
    "gn:population":0,
    "gn:timezone":"Asia/Seoul",
    "iso:country":"KR",
    "name:eng_x_preferred":[
        "Omong"
    ],
    "name:eng_x_variant":[
        "Omong-ni"
    ],
    "name:kor_x_preferred":[
        "\uc624\ubaa9\ub9ac"
    ],
    "wof:name":"Omong",
    "wof:placetype":"locality"
},
  "geometry": {"coordinates":[128.27440000000001,37.273],"type":"Point"}
}