{
  "type": "Feature",
  "properties": {
    "gn:admin1_code":"14.0",
    "gn:asciiname":"Hakchon",
    "gn:country_code":"KR",
    "gn:dem":91,
    "gn:feature_class":"P",
    "gn:feature_code":"PPL",
    "gn:name":"Hakchon",
    "gn:population":0,
    "gn:timezone":"Asia/Seoul",
    "iso:country":"KR",
    "name:kor_x_preferred":[
        "\ud559\ucd0c"
    ],
    "wof:name":"Hakchon",
    "wof:placetype":"locality"
},
  "geometry": {"coordinates":[128.39188999999999,36.5257],"type":"Point"}
}