{
  "type": "Feature",
  "properties": {
    "gn:admin1_code":"13.0",
    "gn:asciiname":"Sunam-ni",
    "gn:country_code":"KR",
    "gn:dem":84,
    "gn:feature_class":"P",
    "gn:feature_code":"PPL",
    "gn:name":"Sunam-ni",
    "gn:population":0,
    "gn:timezone":"Asia/Seoul",
    "iso:country":"KR",
    "name:und_x_variant":[
        "\uc218\ub0a8\ub9ac",
        "Sunam-ri",
        "Sunam-ni"
    ],
    "wof:name":"Sunam-ni",
    "wof:placetype":"locality"
},
  "geometry": {"coordinates":[127.405,37.29389000000001],"type":"Point"}
}