{
  "type": "Feature",
  "properties": {
    "gn:admin1_code":"6.0",
    "gn:asciiname":"Wikkari-gol",
    "gn:country_code":"KR",
    "gn:dem":575,
    "gn:feature_class":"P",
    "gn:feature_code":"PPL",
    "gn:name":"Wikkari-gol",
    "gn:population":0,
    "gn:timezone":"Asia/Seoul",
    "iso:country":"KR",
    "name:kor_x_preferred":[
        "\uc717\uac00\ub9ac\uace8"
    ],
    "wof:name":"Wikkari-gol",
    "wof:placetype":"locality"
},
  "geometry": {"coordinates":[128.53700000000001,37.6413],"type":"Point"}
}