{
  "type": "Feature",
  "properties": {
    "gn:admin1_code":"17.0",
    "gn:asciiname":"Jeonggok",
    "gn:country_code":"KR",
    "gn:dem":103,
    "gn:feature_class":"P",
    "gn:feature_code":"PPL",
    "gn:name":"Jeonggok",
    "gn:population":0,
    "gn:timezone":"Asia/Seoul",
    "iso:country":"KR",
    "name:kor_x_preferred":[
        "\uc815\uace1"
    ],
    "wof:name":"Jeonggok",
    "wof:placetype":"locality"
},
  "geometry": {"coordinates":[127.22183,36.73353],"type":"Point"}
}