{
  "type": "Feature",
  "properties": {
    "gn:admin1_code":"15.0",
    "gn:asciiname":"Odongwon",
    "gn:country_code":"KR",
    "gn:dem":149,
    "gn:feature_class":"P",
    "gn:feature_code":"PPL",
    "gn:name":"Odongwon",
    "gn:population":0,
    "gn:timezone":"Asia/Seoul",
    "iso:country":"KR",
    "name:kor_x_preferred":[
        "\uc624\ub3d9\uc6d0"
    ],
    "wof:name":"Odongwon",
    "wof:placetype":"locality"
},
  "geometry": {"coordinates":[128.64741000000001,35.76967],"type":"Point"}
}