{
  "type": "Feature",
  "properties": {
    "gn:admin1_code":"16.0",
    "gn:asciiname":"Saeteo",
    "gn:country_code":"KR",
    "gn:dem":160,
    "gn:feature_class":"P",
    "gn:feature_code":"PPL",
    "gn:name":"Saeteo",
    "gn:population":0,
    "gn:timezone":"Asia/Seoul",
    "iso:country":"KR",
    "name:kor_x_preferred":[
        "\uc0c8\ud130"
    ],
    "name:kor_x_variant":[
        "Saet\u2019\u014f"
    ],
    "wof:name":"Saeteo",
    "wof:placetype":"locality"
},
  "geometry": {"coordinates":[127.10192000000001,34.76343],"type":"Point"}
}