{
  "type": "Feature",
  "properties": {
    "iso:country":"KR",
    "name:eng_x_preferred":[
        "Dongducheon-si"
    ],
    "name:kor_x_preferred":[
        "\ub3d9\ub450\ucc9c\uc2dc"
    ],
    "qs:name":"\ub3d9\ub450\ucc9c\uc2dc",
    "qs:name_adm0":"\ud55c\uad6d",
    "qs:name_adm1":"\uacbd\uae30\ub3c4",
    "qs:photos":439,
    "qs:photos_1k":89,
    "qs:photos_9k":2,
    "qs:photos_9r":5,
    "qs:photos_all":439,
    "qs:photos_sr":6,
    "qs:placetype":"Town",
    "qs:pop_sr":"0",
    "wof:name":"Dongducheon-si",
    "wof:placetype":"locality"
},
  "geometry": {"coordinates":[127.058944,37.922128],"type":"Point"}
}