{
  "type": "Feature",
  "properties": {
    "gn:admin1_code":"5.0",
    "gn:asciiname":"Boduri",
    "gn:country_code":"KR",
    "gn:dem":83,
    "gn:feature_class":"P",
    "gn:feature_code":"PPL",
    "gn:name":"Boduri",
    "gn:population":0,
    "gn:timezone":"Asia/Seoul",
    "iso:country":"KR",
    "name:kor_x_preferred":[
        "\ubcf4\ub450\ub9ac"
    ],
    "wof:name":"Boduri",
    "wof:placetype":"locality"
},
  "geometry": {"coordinates":[127.58519,36.72429],"type":"Point"}
}