{
  "type": "Feature",
  "properties": {
    "gn:admin1_code":"14.0",
    "gn:asciiname":"Habong",
    "gn:country_code":"KR",
    "gn:dem":250,
    "gn:feature_class":"P",
    "gn:feature_code":"PPL",
    "gn:name":"Habong",
    "gn:population":0,
    "gn:timezone":"Asia/Seoul",
    "iso:country":"KR",
    "name:kor_x_preferred":[
        "\ud558\ubd09"
    ],
    "wof:name":"Habong",
    "wof:placetype":"locality"
},
  "geometry": {"coordinates":[128.22743,36.62954000000001],"type":"Point"}
}