{
  "type": "Feature",
  "properties": {
    "gn:admin1_code":"6.0",
    "gn:asciiname":"Sinnae",
    "gn:country_code":"KR",
    "gn:dem":219,
    "gn:feature_class":"P",
    "gn:feature_code":"PPL",
    "gn:name":"Sinnae",
    "gn:population":0,
    "gn:timezone":"Asia/Seoul",
    "iso:country":"KR",
    "name:kor_x_preferred":[
        "\uc2e0\ub0b4"
    ],
    "wof:name":"Sinnae",
    "wof:placetype":"locality"
},
  "geometry": {"coordinates":[127.82417,38.10111],"type":"Point"}
}