{
  "type": "Feature",
  "properties": {
    "gn:admin1_code":"5.0",
    "gn:asciiname":"Saet'o-maul",
    "gn:country_code":"KR",
    "gn:dem":116,
    "gn:feature_class":"P",
    "gn:feature_code":"PPL",
    "gn:name":"Saet\u2019\u014f-ma\u016dl",
    "gn:population":0,
    "gn:timezone":"Asia/Seoul",
    "iso:country":"KR",
    "name:und_x_variant":[
        "\uc0c8\ud130\ub9c8\uc744",
        "Saet\u2019\u014f-ma\u016dl"
    ],
    "wof:name":"Saet'o-maul",
    "wof:placetype":"locality"
},
  "geometry": {"coordinates":[127.5971,36.5009],"type":"Point"}
}