{
  "type": "Feature",
  "properties": {
    "gn:admin1_code":"13.0",
    "gn:asciiname":"Sangsam",
    "gn:country_code":"KR",
    "gn:dem":101,
    "gn:feature_class":"P",
    "gn:feature_code":"PPL",
    "gn:name":"Sangsam",
    "gn:population":0,
    "gn:timezone":"Asia/Seoul",
    "iso:country":"KR",
    "name:und_x_variant":[
        "\uc0c1\uc0bc",
        "Sangsam"
    ],
    "wof:name":"Sangsam",
    "wof:placetype":"locality"
},
  "geometry": {"coordinates":[127.10732,37.81066],"type":"Point"}
}