{
  "type": "Feature",
  "properties": {
    "gn:admin1_code":"14.0",
    "gn:asciiname":"Tonggumit",
    "gn:country_code":"KR",
    "gn:dem":73,
    "gn:feature_class":"P",
    "gn:feature_code":"PPL",
    "gn:name":"Tonggumit",
    "gn:population":0,
    "gn:timezone":"Asia/Seoul",
    "iso:country":"KR",
    "name:und_x_variant":[
        "\ub3d9\uad6c\ubc11",
        "Tonggumit"
    ],
    "wof:name":"Tonggumit",
    "wof:placetype":"locality"
},
  "geometry": {"coordinates":[128.28380000000001,36.4279],"type":"Point"}
}