{
  "type": "Feature",
  "properties": {
    "gn:admin1_code":"13.0",
    "gn:asciiname":"Maryong-ni",
    "gn:country_code":"KR",
    "gn:dem":177,
    "gn:feature_class":"P",
    "gn:feature_code":"PPLL",
    "gn:name":"Maryong-ni",
    "gn:population":0,
    "gn:timezone":"Asia/Seoul",
    "iso:country":"KR",
    "name:eng_x_preferred":[
        "Maryong"
    ],
    "name:eng_x_variant":[
        "Maryong-ni"
    ],
    "name:und_x_variant":[
        "\ub9c8\ub8e1\ub9ac",
        "Maryong-ri",
        "Maryong-ni"
    ],
    "wof:name":"Maryong",
    "wof:placetype":"locality"
},
  "geometry": {"coordinates":[127.62444000000001,37.49556],"type":"Point"}
}