{
  "type": "Feature",
  "properties": {
    "gn:admin1_code":"6.0",
    "gn:asciiname":"Saenggong-ni",
    "gn:country_code":"KR",
    "gn:dem":377,
    "gn:feature_class":"P",
    "gn:feature_code":"PPLL",
    "gn:name":"Saenggong-ni",
    "gn:population":0,
    "gn:timezone":"Asia/Seoul",
    "iso:country":"KR",
    "name:eng_x_preferred":[
        "Saenggong"
    ],
    "name:eng_x_variant":[
        "Saenggong-ni"
    ],
    "name:kor_x_preferred":[
        "\uc0dd\uace1\ub9ac"
    ],
    "wof:name":"Saenggong",
    "wof:placetype":"locality"
},
  "geometry": {"coordinates":[128.23163,37.68441],"type":"Point"}
}