{
  "type": "Feature",
  "properties": {
    "gn:admin1_code":"14.0",
    "gn:asciiname":"Dansa",
    "gn:country_code":"KR",
    "gn:dem":172,
    "gn:feature_class":"P",
    "gn:feature_code":"PPL",
    "gn:name":"Dansa",
    "gn:population":0,
    "gn:timezone":"Asia/Seoul",
    "iso:country":"KR",
    "name:cat_x_preferred":[
        "Dansa"
    ],
    "name:ita_x_preferred":[
        "Dansa"
    ],
    "name:kor_x_preferred":[
        "\ub2e8\uc0ac"
    ],
    "wof:name":"Dansa",
    "wof:placetype":"locality"
},
  "geometry": {"coordinates":[128.88342,36.73954000000001],"type":"Point"}
}