{
  "type": "Feature",
  "properties": {
    "gn:admin1_code":"13.0",
    "gn:asciiname":"Sinmi",
    "gn:country_code":"KR",
    "gn:dem":120,
    "gn:feature_class":"P",
    "gn:feature_code":"PPL",
    "gn:name":"Sinmi",
    "gn:population":0,
    "gn:timezone":"Asia/Seoul",
    "iso:country":"KR",
    "name:und_x_variant":[
        "\uc2e0\ubbf8",
        "Sinmi"
    ],
    "wof:name":"Sinmi",
    "wof:placetype":"locality"
},
  "geometry": {"coordinates":[126.97920000000001,37.8973],"type":"Point"}
}