{
  "type": "Feature",
  "properties": {
    "gn:admin1_code":"13.0",
    "gn:asciiname":"Hoedeok-dong",
    "gn:country_code":"KR",
    "gn:dem":112,
    "gn:feature_class":"P",
    "gn:feature_code":"PPLL",
    "gn:name":"Hoedeok-dong",
    "gn:population":0,
    "gn:timezone":"Asia/Seoul",
    "iso:country":"KR",
    "name:und_x_variant":[
        "\ud68c\ub355\ub3d9",
        "Hoedeok-dong",
        "Hoed\u014fk-tong"
    ],
    "wof:name":"Hoedeok-dong",
    "wof:placetype":"locality"
},
  "geometry": {"coordinates":[127.24139,37.43917],"type":"Point"}
}