{
  "type": "Feature",
  "properties": {
    "gn:admin1_code":"13.0",
    "gn:asciiname":"Jeokhyeon",
    "gn:country_code":"KR",
    "gn:dem":130,
    "gn:feature_class":"P",
    "gn:feature_code":"PPL",
    "gn:name":"Jeokhyeon",
    "gn:population":0,
    "gn:timezone":"Asia/Seoul",
    "iso:country":"KR",
    "name:kor_x_preferred":[
        "\uc801\ud604"
    ],
    "name:kor_x_variant":[
        "Ch\u014fkhy\u014fn"
    ],
    "wof:name":"Jeokhyeon",
    "wof:placetype":"locality"
},
  "geometry": {"coordinates":[127.6168,37.5243],"type":"Point"}
}