{
  "type": "Feature",
  "properties": {
    "gn:admin1_code":"17.0",
    "gn:asciiname":"Un-gol",
    "gn:country_code":"KR",
    "gn:dem":69,
    "gn:feature_class":"P",
    "gn:feature_code":"PPL",
    "gn:name":"\u016cn-gol",
    "gn:population":0,
    "gn:timezone":"Asia/Seoul",
    "iso:country":"KR",
    "name:und_x_variant":[
        "\uc740\uace8",
        "\u016cn-gol"
    ],
    "wof:name":"Un-gol",
    "wof:placetype":"locality"
},
  "geometry": {"coordinates":[126.798,36.5207],"type":"Point"}
}