{
  "type": "Feature",
  "properties": {
    "gn:admin1_code":"13.0",
    "gn:asciiname":"Songjuk-tong",
    "gn:country_code":"KR",
    "gn:dem":70,
    "gn:feature_class":"P",
    "gn:feature_code":"PPL",
    "gn:name":"Songjuk-tong",
    "gn:population":0,
    "gn:timezone":"Asia/Seoul",
    "iso:country":"KR",
    "name:und_x_variant":[
        "\uc1a1\uc8fd\ub3d9",
        "Songjuk-dong",
        "Songjuk-tong"
    ],
    "wof:name":"Songjuk-tong",
    "wof:placetype":"locality"
},
  "geometry": {"coordinates":[127.00528,37.30694],"type":"Point"}
}