{
  "type": "Feature",
  "properties": {
    "gn:admin1_code":"17.0",
    "gn:asciiname":"Punich'i",
    "gn:country_code":"KR",
    "gn:dem":21,
    "gn:feature_class":"P",
    "gn:feature_code":"PPL",
    "gn:name":"Punich\u2019i",
    "gn:population":0,
    "gn:timezone":"Asia/Seoul",
    "iso:country":"KR",
    "name:und_x_variant":[
        "\ubd84\uc774\uce58",
        "Punich\u2019i"
    ],
    "wof:name":"Punich'i",
    "wof:placetype":"locality"
},
  "geometry": {"coordinates":[126.55240000000001,36.5382],"type":"Point"}
}