{
  "type": "Feature",
  "properties": {
    "gn:admin1_code":"14.0",
    "gn:asciiname":"Chumakko-ri",
    "gn:country_code":"KR",
    "gn:dem":122,
    "gn:feature_class":"P",
    "gn:feature_code":"PPL",
    "gn:name":"Chumakk\u014f-ri",
    "gn:population":0,
    "gn:timezone":"Asia/Seoul",
    "iso:country":"KR",
    "name:und_x_variant":[
        "\uc8fc\ub9c9\uac70\ub9ac",
        "Chumakk\u014f-ri"
    ],
    "wof:name":"Chumakko-ri",
    "wof:placetype":"locality"
},
  "geometry": {"coordinates":[128.05860000000001,36.4207],"type":"Point"}
}