{
  "type": "Feature",
  "properties": {
    "gn:admin1_code":"6.0",
    "gn:asciiname":"Saetgeonbae",
    "gn:country_code":"KR",
    "gn:dem":417,
    "gn:feature_class":"P",
    "gn:feature_code":"PPL",
    "gn:name":"Saetgeonbae",
    "gn:population":0,
    "gn:timezone":"Asia/Seoul",
    "iso:country":"KR",
    "name:kor_x_preferred":[
        "\uc0db\uac74\ubc30"
    ],
    "name:und_x_variant":[
        "Saeg\u014fnbae"
    ],
    "wof:name":"Saetgeonbae",
    "wof:placetype":"locality"
},
  "geometry": {"coordinates":[127.98497,38.27052],"type":"Point"}
}