{
  "type": "Feature",
  "properties": {
    "gn:admin1_code":"6.0",
    "gn:asciiname":"Hang-gol",
    "gn:country_code":"KR",
    "gn:dem":604,
    "gn:feature_class":"P",
    "gn:feature_code":"PPL",
    "gn:name":"Hang-gol",
    "gn:population":0,
    "gn:timezone":"Asia/Seoul",
    "iso:country":"KR",
    "name:kor_x_preferred":[
        "\ud070\ud56d\uace8"
    ],
    "name:kor_x_variant":[
        "K\u2019\u016dnhang-gol"
    ],
    "name:und_x_variant":[
        "Hang-dong"
    ],
    "wof:name":"Hang-gol",
    "wof:placetype":"locality"
},
  "geometry": {"coordinates":[128.36500000000001,37.5181],"type":"Point"}
}