{
  "type": "Feature",
  "properties": {
    "gn:admin1_code":"17.0",
    "gn:asciiname":"Chinmaru",
    "gn:country_code":"KR",
    "gn:dem":36,
    "gn:feature_class":"P",
    "gn:feature_code":"PPL",
    "gn:name":"Chinmaru",
    "gn:population":0,
    "gn:timezone":"Asia/Seoul",
    "iso:country":"KR",
    "name:und_x_variant":[
        "\uc9c4\ub9c8\ub8e8",
        "Chinmaru"
    ],
    "wof:name":"Chinmaru",
    "wof:placetype":"locality"
},
  "geometry": {"coordinates":[126.53333000000001,36.88333],"type":"Point"}
}