{
  "type": "Feature",
  "properties": {
    "gn:admin1_code":"5.0",
    "gn:asciiname":"Mageungol",
    "gn:country_code":"KR",
    "gn:dem":314,
    "gn:feature_class":"P",
    "gn:feature_code":"PPL",
    "gn:name":"Mageungol",
    "gn:population":0,
    "gn:timezone":"Asia/Seoul",
    "iso:country":"KR",
    "name:kor_x_preferred":[
        "\ub9c9\uc740\uace8"
    ],
    "wof:name":"Mageungol",
    "wof:placetype":"locality"
},
  "geometry": {"coordinates":[127.67274999999999,36.67126],"type":"Point"}
}