{
  "type": "Feature",
  "properties": {
    "gn:admin1_code":"5.0",
    "gn:asciiname":"Ch'ongnyong-ni",
    "gn:country_code":"KR",
    "gn:dem":116,
    "gn:feature_class":"P",
    "gn:feature_code":"PPL",
    "gn:name":"Ch\u2019\u014fngnyong-ni",
    "gn:population":0,
    "gn:timezone":"Asia/Seoul",
    "iso:country":"KR",
    "name:und_x_variant":[
        "Ch\u2019\u014fngyong-ni",
        "Ch\u2019\u014fng-yong-ri",
        "Ch\u2019\u014fngnyong-ni"
    ],
    "wof:name":"Ch'ongnyong-ni",
    "wof:placetype":"locality"
},
  "geometry": {"coordinates":[127.54722,36.5375],"type":"Point"}
}