{
  "type": "Feature",
  "properties": {
    "gn:admin1_code":"6.0",
    "gn:asciiname":"Sorani",
    "gn:country_code":"KR",
    "gn:dem":187,
    "gn:feature_class":"P",
    "gn:feature_code":"PPL",
    "gn:name":"Sorani",
    "gn:population":0,
    "gn:timezone":"Asia/Seoul",
    "iso:country":"KR",
    "name:kor_x_preferred":[
        "\uc18c\ub77c\ub2c8"
    ],
    "wof:name":"Sorani",
    "wof:placetype":"locality"
},
  "geometry": {"coordinates":[128.0498,37.4593],"type":"Point"}
}