{
  "type": "Feature",
  "properties": {
    "gn:admin1_code":"6.0",
    "gn:asciiname":"Sorani",
    "gn:country_code":"KR",
    "gn:dem":187,
    "gn:feature_class":"P",
    "gn:feature_code":"PPL",
    "gn:name":"Sorani",
    "gn:population":0,
    "gn:timezone":"Asia/Seoul",
    "iso:country":"KR",
    "name:amh_x_preferred":[
        "\u1236\u122b\u1292\u129b"
    ],
    "name:ara_x_preferred":[
        "\u0633\u0648\u0631\u0627\u0646\u064a\u0629 \u0643\u0631\u062f\u064a\u0629"
    ],
    "name:aze_x_preferred":[
        "Soran dili"
    ],
    "name:cat_x_preferred":[
        "Sorani"
    ],
    "name:ces_x_preferred":[
        "Sor\u00e1n\u00ed"
    ],
    "name:chv_x_preferred":[
        "\u0421\u043e\u0440\u0430\u043d\u0438"
    ],
    "name:ckb_x_preferred":[
        "\u06a9\u0648\u0631\u062f\u06cc\u06cc \u0646\u0627\u0648\u06d5\u0646\u062f\u06cc"
    ],
    "name:dan_x_preferred":[
        "Sorani"
    ],
    "name:deu_x_preferred":[
        "Sorani"
    ],
    "name:epo_x_preferred":[
        "Sorana lingvo"
    ],
    "name:est_x_preferred":[
        "Sorani keel"
    ],
    "name:eus_x_preferred":[
        "Sorani"
    ],
    "name:fas_x_preferred":[
        "\u0633\u0648\u0631\u0627\u0646\u06cc"
    ],
    "name:fin_x_preferred":[
        "Soran\u00ee"
    ],
    "name:fra_x_preferred":[
        "Sorani"
    ],
    "name:hak_x_preferred":[
        "Ch\u00fbng Kurd-ng\u00ee"
    ],
    "name:hrv_x_preferred":[
        "Centralnokurdski jezik"
    ],
    "name:jpn_x_preferred":[
        "\u30bd\u30e9\u30cb\u30fc"
    ],
    "name:kat_x_preferred":[
        "\u10e1\u10dd\u10e0\u10d0\u10dc\u10d8"
    ],
    "name:kor_x_preferred":[
        "\uc18c\ub77c\ub2c8"
    ],
    "name:kur_x_preferred":[
        "Soran\u00ee"
    ],
    "name:mzn_x_preferred":[
        "\u0633\u0648\u0631\u0627\u0646\u06cc"
    ],
    "name:nld_x_preferred":[
        "Soran\u00ee"
    ],
    "name:nov_x_preferred":[
        "Sorani"
    ],
    "name:pnb_x_preferred":[
        "\u0633\u0648\u0631\u0627\u0646\u06cc"
    ],
    "name:pol_x_preferred":[
        "J\u0119zyk sorani"
    ],
    "name:por_x_preferred":[
        "Sor\u00e2ni"
    ],
    "name:rus_x_preferred":[
        "\u0421\u043e\u0440\u0430\u043d\u0438"
    ],
    "name:swe_x_preferred":[
        "Sorani"
    ],
    "name:tam_x_preferred":[
        "\u0b9a\u0bca\u0bb0\u0bbe\u0ba9\u0bbf \u0bae\u0bca\u0bb4\u0bbf"
    ],
    "name:tha_x_preferred":[
        "\u0e20\u0e32\u0e29\u0e32\u0e40\u0e04\u0e34\u0e23\u0e4c\u0e14\u0e15\u0e2d\u0e19\u0e01\u0e25\u0e32\u0e07"
    ],
    "name:tur_x_preferred":[
        "Soranice"
    ],
    "name:ukr_x_preferred":[
        "\u0421\u043e\u0440\u0430\u043d\u0456"
    ],
    "name:urd_x_preferred":[
        "\u0633\u0648\u0631\u0627\u0646\u06cc"
    ],
    "name:zho_x_preferred":[
        "\u4e2d\u5e93\u5c14\u5fb7\u8bed"
    ],
    "wof:name":"Sorani",
    "wof:placetype":"locality"
},
  "geometry": {"coordinates":[128.0498,37.4593],"type":"Point"}
}