{
  "type": "Feature",
  "properties": {
    "gn:admin1_code":"14.0",
    "gn:asciiname":"Jichon",
    "gn:country_code":"KR",
    "gn:dem":182,
    "gn:feature_class":"P",
    "gn:feature_code":"PPL",
    "gn:name":"Jichon",
    "gn:population":0,
    "gn:timezone":"Asia/Seoul",
    "iso:country":"KR",
    "name:und_x_variant":[
        "\uc9c0\ucd0c",
        "Chi-ch\u2019on",
        "Jichon"
    ],
    "wof:name":"Jichon",
    "wof:placetype":"locality"
},
  "geometry": {"coordinates":[128.59553,35.69727],"type":"Point"}
}