{
  "type": "Feature",
  "properties": {
    "gn:admin1_code":"0.0",
    "gn:asciiname":"Kyech'on-ni",
    "gn:country_code":"KR",
    "gn:dem":4,
    "gn:feature_class":"P",
    "gn:feature_code":"PPL",
    "gn:name":"Kyech\u2019\u014fn-ni",
    "gn:population":0,
    "gn:timezone":"Asia/Seoul",
    "iso:country":"KR",
    "name:und_x_variant":[
        "Kech\u2019\u014f-ni",
        "Kyech\u2019\u014fn-ni"
    ],
    "wof:name":"Kyech'on-ni",
    "wof:placetype":"locality"
},
  "geometry": {"coordinates":[127.81667,34.98333],"type":"Point"}
}