{
  "type": "Feature",
  "properties": {
    "gn:admin1_code":"16.0",
    "gn:admin2_code":"Chindo-gun",
    "gn:asciiname":"Chimgye",
    "gn:country_code":"KR",
    "gn:dem":23,
    "gn:feature_class":"P",
    "gn:feature_code":"PPL",
    "gn:name":"Chimgye",
    "gn:population":0,
    "gn:timezone":"Asia/Seoul",
    "iso:country":"KR",
    "name:kor_x_preferred":[
        "\uce68\uacc4"
    ],
    "name:und_x_variant":[
        "Chinkei-ri",
        "Chin\u2019gye-ri",
        "Ch\u2019imgye",
        "Ch\u2019imgye-ri",
        "Chimgye"
    ],
    "wof:name":"Chimgye",
    "wof:placetype":"locality"
},
  "geometry": {"coordinates":[126.27167,34.44528],"type":"Point"}
}