{
  "type": "Feature",
  "properties": {
    "gn:admin1_code":"18.0",
    "gn:asciiname":"Jangseonggul",
    "gn:country_code":"KR",
    "gn:dem":97,
    "gn:feature_class":"P",
    "gn:feature_code":"PPL",
    "gn:name":"Jangseonggul",
    "gn:population":0,
    "gn:timezone":"Asia/Seoul",
    "iso:country":"KR",
    "name:kor_x_preferred":[
        "\uc7a5\uc131\uad74"
    ],
    "wof:name":"Jangseonggul",
    "wof:placetype":"locality"
},
  "geometry": {"coordinates":[126.73036,35.20099000000001],"type":"Point"}
}