{
  "type": "Feature",
  "properties": {
    "gn:admin1_code":"11.0",
    "gn:asciiname":"Changch'ung-dong",
    "gn:country_code":"KR",
    "gn:dem":57,
    "gn:feature_class":"P",
    "gn:feature_code":"PPL",
    "gn:name":"Changch\u2019ung-dong",
    "gn:population":0,
    "gn:timezone":"Asia/Seoul",
    "iso:country":"KR",
    "name:und_x_variant":[
        "\uc7a5\ucda9\ub3d9",
        "Changch\u2019ung-dong"
    ],
    "wof:name":"Changch'ung-dong",
    "wof:placetype":"locality"
},
  "geometry": {"coordinates":[127.00385,37.5555],"type":"Point"}
}