{
  "type": "Feature",
  "properties": {
    "gn:admin1_code":"6.0",
    "gn:asciiname":"Podong-mal",
    "gn:country_code":"KR",
    "gn:dem":550,
    "gn:feature_class":"P",
    "gn:feature_code":"PPL",
    "gn:name":"P\u014fd\u014fng-mal",
    "gn:population":0,
    "gn:timezone":"Asia/Seoul",
    "iso:country":"KR",
    "name:kor_x_preferred":[
        "\ubc84\ub369\ub9d0"
    ],
    "name:kor_x_variant":[
        "P\u014fd\u014fng-mal"
    ],
    "wof:name":"Podong-mal",
    "wof:placetype":"locality"
},
  "geometry": {"coordinates":[128.15289999999999,37.4639],"type":"Point"}
}