{
  "type": "Feature",
  "properties": {
    "gn:admin1_code":"5.0",
    "gn:asciiname":"Sin'guni",
    "gn:country_code":"KR",
    "gn:dem":152,
    "gn:feature_class":"P",
    "gn:feature_code":"PPL",
    "gn:name":"Sin\u2019g\u016dni",
    "gn:population":0,
    "gn:timezone":"Asia/Seoul",
    "iso:country":"KR",
    "name:und_x_variant":[
        "\uc2e0\uadfc\uc774",
        "Sin\u2019g\u016dni"
    ],
    "wof:name":"Sin'guni",
    "wof:placetype":"locality"
},
  "geometry": {"coordinates":[127.7445,36.4194],"type":"Point"}
}