{
  "type": "Feature",
  "properties": {
    "gn:admin1_code":"14.0",
    "gn:asciiname":"Hungmu-gol",
    "gn:country_code":"KR",
    "gn:dem":297,
    "gn:feature_class":"P",
    "gn:feature_code":"PPL",
    "gn:name":"H\u016dngmu-gol",
    "gn:population":0,
    "gn:timezone":"Asia/Seoul",
    "iso:country":"KR",
    "name:und_x_variant":[
        "\ud759\ubb34\uace8",
        "H\u016dngmu-gol"
    ],
    "wof:name":"Hungmu-gol",
    "wof:placetype":"locality"
},
  "geometry": {"coordinates":[129.1919,36.5097],"type":"Point"}
}