{
  "type": "Feature",
  "properties": {
    "gn:admin1_code":"13.0",
    "gn:asciiname":"Neunggok",
    "gn:country_code":"KR",
    "gn:dem":46,
    "gn:feature_class":"P",
    "gn:feature_code":"PPL",
    "gn:name":"Neunggok",
    "gn:population":0,
    "gn:timezone":"Asia/Seoul",
    "iso:country":"KR",
    "name:kor_x_preferred":[
        "\ub2a5\uace1"
    ],
    "name:und_x_variant":[
        "N\u016dng-gol",
        "N\u016dnggok",
        "Neunggok"
    ],
    "wof:name":"Neunggok",
    "wof:placetype":"locality"
},
  "geometry": {"coordinates":[127.3334,37.5284],"type":"Point"}
}