{
  "type": "Feature",
  "properties": {
    "gn:admin1_code":"20.0",
    "gn:asciiname":"Oho-ri",
    "gn:cc2":"KR",
    "gn:country_code":"KR",
    "gn:dem":29,
    "gn:feature_class":"P",
    "gn:feature_code":"PPL",
    "gn:name":"Oho-ri",
    "gn:population":0,
    "gn:timezone":"Asia/Seoul",
    "iso:country":"KR",
    "name:und_x_variant":[
        "Oeho-ri",
        "Oho-ri"
    ],
    "wof:name":"Oho-ri",
    "wof:placetype":"locality"
},
  "geometry": {"coordinates":[128.53556,35.40167],"type":"Point"}
}