{
  "type": "Feature",
  "properties": {
    "gn:admin1_code":"13.0",
    "gn:asciiname":"Naendeul",
    "gn:country_code":"KR",
    "gn:dem":41,
    "gn:feature_class":"P",
    "gn:feature_code":"PPL",
    "gn:name":"Naendeul",
    "gn:population":0,
    "gn:timezone":"Asia/Seoul",
    "iso:country":"KR",
    "name:und_x_variant":[
        "\ub0b8\ub4e4",
        "Naendeul",
        "Naend\u016dl"
    ],
    "wof:name":"Naendeul",
    "wof:placetype":"locality"
},
  "geometry": {"coordinates":[127.57277999999999,37.34861],"type":"Point"}
}