{
  "type": "Feature",
  "properties": {
    "gn:admin1_code":"20.0",
    "gn:asciiname":"Manggol",
    "gn:country_code":"KR",
    "gn:dem":109,
    "gn:feature_class":"P",
    "gn:feature_code":"PPL",
    "gn:name":"Manggol",
    "gn:population":0,
    "gn:timezone":"Asia/Seoul",
    "iso:country":"KR",
    "name:und_x_variant":[
        "Manggok",
        "Mangch\u2019on"
    ],
    "wof:name":"Manggol",
    "wof:placetype":"locality"
},
  "geometry": {"coordinates":[128.48694,34.77278],"type":"Point"}
}