{
  "type": "Feature",
  "properties": {
    "gn:admin1_code":"16.0",
    "gn:asciiname":"Jeongjang",
    "gn:country_code":"KR",
    "gn:dem":143,
    "gn:feature_class":"P",
    "gn:feature_code":"PPL",
    "gn:name":"Jeongjang",
    "gn:population":0,
    "gn:timezone":"Asia/Seoul",
    "iso:country":"KR",
    "name:kor_x_preferred":[
        "\uc815\uc7a5"
    ],
    "name:kor_x_variant":[
        "Ch\u014fngjang"
    ],
    "name:und_x_variant":[
        "Ch\u014fngjang-ni",
        "Jeongjang"
    ],
    "wof:name":"Jeongjang",
    "wof:placetype":"locality"
},
  "geometry": {"coordinates":[126.99337,34.85874],"type":"Point"}
}