{
  "type": "Feature",
  "properties": {
    "gn:admin1_code":"6.0",
    "gn:asciiname":"Kil-gol",
    "gn:country_code":"KR",
    "gn:dem":327,
    "gn:feature_class":"P",
    "gn:feature_code":"PPL",
    "gn:name":"Kil-gol",
    "gn:population":0,
    "gn:timezone":"Asia/Seoul",
    "iso:country":"KR",
    "name:kor_x_preferred":[
        "\uae38\uace8"
    ],
    "wof:name":"Kil-gol",
    "wof:placetype":"locality"
},
  "geometry": {"coordinates":[128.45660000000001,37.2395],"type":"Point"}
}