{
  "type": "Feature",
  "properties": {
    "gn:admin1_code":"13.0",
    "gn:admin2_code":"Yongin-si",
    "gn:asciiname":"Hasa",
    "gn:country_code":"KR",
    "gn:dem":110,
    "gn:feature_class":"P",
    "gn:feature_code":"PPL",
    "gn:name":"Hasa",
    "gn:population":0,
    "gn:timezone":"Asia/Seoul",
    "iso:country":"KR",
    "name:ceb_x_preferred":[
        "Hasa"
    ],
    "name:deu_x_preferred":[
        "Hasa"
    ],
    "name:fin_x_preferred":[
        "Hasa"
    ],
    "name:kor_x_preferred":[
        "\ud558\uc0ac"
    ],
    "wof:name":"Hasa",
    "wof:placetype":"locality"
},
  "geometry": {"coordinates":[127.32104,37.16586],"type":"Point"}
}