{
  "type": "Feature",
  "properties": {
    "gn:admin1_code":"14.0",
    "gn:asciiname":"Nounae",
    "gn:country_code":"KR",
    "gn:dem":41,
    "gn:feature_class":"P",
    "gn:feature_code":"PPL",
    "gn:name":"N\u014funae",
    "gn:population":0,
    "gn:timezone":"Asia/Seoul",
    "iso:country":"KR",
    "name:und_x_variant":[
        "\ub108\uc6b0\ub0b4",
        "N\u014funae"
    ],
    "wof:name":"Nounae",
    "wof:placetype":"locality"
},
  "geometry": {"coordinates":[129.34110000000001,36.5761],"type":"Point"}
}