{
  "type": "Feature",
  "properties": {
    "gn:admin1_code":"5.0",
    "gn:asciiname":"Neochuni",
    "gn:country_code":"KR",
    "gn:dem":99,
    "gn:feature_class":"P",
    "gn:feature_code":"PPL",
    "gn:name":"Neochuni",
    "gn:population":0,
    "gn:timezone":"Asia/Seoul",
    "iso:country":"KR",
    "name:kor_x_preferred":[
        "\ub108\ucd98\uc774"
    ],
    "wof:name":"Neochuni",
    "wof:placetype":"locality"
},
  "geometry": {"coordinates":[127.82789,37.05857],"type":"Point"}
}