{
  "type": "Feature",
  "properties": {
    "gn:admin1_code":"13.0",
    "gn:asciiname":"Yangchon",
    "gn:country_code":"KR",
    "gn:dem":45,
    "gn:feature_class":"P",
    "gn:feature_code":"PPL",
    "gn:name":"Yangchon",
    "gn:population":0,
    "gn:timezone":"Asia/Seoul",
    "iso:country":"KR",
    "name:und_x_variant":[
        "\uc591\ucd0c",
        "Yangchon",
        "Yangch\u2019on"
    ],
    "wof:name":"Yangchon",
    "wof:placetype":"locality"
},
  "geometry": {"coordinates":[126.91722,37.29722],"type":"Point"}
}