{
  "type": "Feature",
  "properties": {
    "gn:admin1_code":"5.0",
    "gn:asciiname":"Dojangbae",
    "gn:country_code":"KR",
    "gn:dem":54,
    "gn:feature_class":"P",
    "gn:feature_code":"PPL",
    "gn:name":"Dojangbae",
    "gn:population":0,
    "gn:timezone":"Asia/Seoul",
    "iso:country":"KR",
    "name:kor_x_preferred":[
        "\ub3c4\uc7a5\ubc30"
    ],
    "wof:name":"Dojangbae",
    "wof:placetype":"locality"
},
  "geometry": {"coordinates":[127.44493,36.75057],"type":"Point"}
}