{
  "type": "Feature",
  "properties": {
    "gn:admin1_code":"14.0",
    "gn:asciiname":"Somangsil",
    "gn:country_code":"KR",
    "gn:dem":116,
    "gn:feature_class":"P",
    "gn:feature_code":"PPL",
    "gn:name":"Somangsil",
    "gn:population":0,
    "gn:timezone":"Asia/Seoul",
    "iso:country":"KR",
    "name:kor_x_preferred":[
        "\uc18c\ub9dd\uc2e4"
    ],
    "wof:name":"Somangsil",
    "wof:placetype":"locality"
},
  "geometry": {"coordinates":[128.50496999999999,36.64526],"type":"Point"}
}