{
  "type": "Feature",
  "properties": {
    "gn:admin1_code":"13.0",
    "gn:asciiname":"Yongso",
    "gn:country_code":"KR",
    "gn:dem":80,
    "gn:feature_class":"P",
    "gn:feature_code":"PPL",
    "gn:name":"Yongso",
    "gn:population":0,
    "gn:timezone":"Asia/Seoul",
    "iso:country":"KR",
    "name:und_x_variant":[
        "\uc6a9\uc18c",
        "Yongso"
    ],
    "wof:name":"Yongso",
    "wof:placetype":"locality"
},
  "geometry": {"coordinates":[127.14865,37.0463],"type":"Point"}
}