{
  "type": "Feature",
  "properties": {
    "gn:admin1_code":"13.0",
    "gn:asciiname":"Saejanggeori",
    "gn:country_code":"KR",
    "gn:dem":23,
    "gn:feature_class":"P",
    "gn:feature_code":"PPL",
    "gn:name":"Saejanggeori",
    "gn:population":0,
    "gn:timezone":"Asia/Seoul",
    "iso:country":"KR",
    "name:kor_x_preferred":[
        "\uc0c8\uc7a5\uac70\ub9ac"
    ],
    "wof:name":"Saejanggeori",
    "wof:placetype":"locality"
},
  "geometry": {"coordinates":[126.91034999999999,37.96188],"type":"Point"}
}