{
  "type": "Feature",
  "properties": {
    "gn:admin1_code":"6.0",
    "gn:asciiname":"Saegogae",
    "gn:country_code":"KR",
    "gn:dem":132,
    "gn:feature_class":"P",
    "gn:feature_code":"PPL",
    "gn:name":"Saegogae",
    "gn:population":0,
    "gn:timezone":"Asia/Seoul",
    "iso:country":"KR",
    "name:und_x_variant":[
        "\uc0c8\uace0\uac1c",
        "Saegogae"
    ],
    "wof:name":"Saegogae",
    "wof:placetype":"locality"
},
  "geometry": {"coordinates":[127.72951999999999,37.79931],"type":"Point"}
}