{
  "type": "Feature",
  "properties": {
    "gn:admin1_code":"14.0",
    "gn:asciiname":"Yongyeon",
    "gn:country_code":"KR",
    "gn:dem":286,
    "gn:feature_class":"P",
    "gn:feature_code":"PPL",
    "gn:name":"Yongyeon",
    "gn:population":0,
    "gn:timezone":"Asia/Seoul",
    "iso:country":"KR",
    "name:kor_x_preferred":[
        "\uc6a9\uc5f0"
    ],
    "name:und_x_variant":[
        "Yongaen-ni",
        "Yongy\u014fn-ni",
        "Yongy\u014fn",
        "Yongyeon"
    ],
    "wof:name":"Yongyeon",
    "wof:placetype":"locality"
},
  "geometry": {"coordinates":[128.17482999999999,36.77672000000001],"type":"Point"}
}