{
  "type": "Feature",
  "properties": {
    "gn:admin1_code":"13.0",
    "gn:asciiname":"Pongsa-gol",
    "gn:country_code":"KR",
    "gn:dem":61,
    "gn:feature_class":"P",
    "gn:feature_code":"PPL",
    "gn:name":"Pongsa-gol",
    "gn:population":0,
    "gn:timezone":"Asia/Seoul",
    "iso:country":"KR",
    "name:kor_x_preferred":[
        "\ubd09\uc0ac\uace8"
    ],
    "name:und_x_variant":[
        "\ubd09\uc0ac\uace8",
        "Pongsa-gol"
    ],
    "wof:name":"Pongsa-gol",
    "wof:placetype":"locality"
},
  "geometry": {"coordinates":[127.1716,37.6281],"type":"Point"}
}