{
  "type": "Feature",
  "properties": {
    "gn:admin1_code":"13.0",
    "gn:asciiname":"Baemgol",
    "gn:country_code":"KR",
    "gn:dem":75,
    "gn:feature_class":"P",
    "gn:feature_code":"PPL",
    "gn:name":"Baemgol",
    "gn:population":0,
    "gn:timezone":"Asia/Seoul",
    "iso:country":"KR",
    "name:kor_x_preferred":[
        "\ubc40\uace8"
    ],
    "wof:name":"Baemgol",
    "wof:placetype":"locality"
},
  "geometry": {"coordinates":[127.11436999999999,37.73605],"type":"Point"}
}