{
  "type": "Feature",
  "properties": {
    "gn:admin1_code":"14.0",
    "gn:asciiname":"Sanmak-kol",
    "gn:country_code":"KR",
    "gn:dem":283,
    "gn:feature_class":"P",
    "gn:feature_code":"PPL",
    "gn:name":"Sanmak-kol",
    "gn:population":0,
    "gn:timezone":"Asia/Seoul",
    "iso:country":"KR",
    "name:und_x_variant":[
        "\uc0b0\ub9c9\uace8",
        "Sanmak-kol"
    ],
    "wof:name":"Sanmak-kol",
    "wof:placetype":"locality"
},
  "geometry": {"coordinates":[129.0179,36.6162],"type":"Point"}
}