{
  "type": "Feature",
  "properties": {
    "gn:admin1_code":"6.0",
    "gn:asciiname":"Kamdongji",
    "gn:country_code":"KR",
    "gn:dem":710,
    "gn:feature_class":"P",
    "gn:feature_code":"PPL",
    "gn:name":"Kamdongji",
    "gn:population":0,
    "gn:timezone":"Asia/Seoul",
    "iso:country":"KR",
    "name:kor_x_preferred":[
        "\uac10\ub3d9\uc9c0"
    ],
    "wof:name":"Kamdongji",
    "wof:placetype":"locality"
},
  "geometry": {"coordinates":[128.27350000000001,37.4882],"type":"Point"}
}