{
  "type": "Feature",
  "properties": {
    "gn:admin1_code":"17.0",
    "gn:asciiname":"P'unggyong-ni",
    "gn:country_code":"KR",
    "gn:dem":21,
    "gn:feature_class":"P",
    "gn:feature_code":"PPL",
    "gn:name":"P\u2019unggy\u014fng-ni",
    "gn:population":0,
    "gn:timezone":"Asia/Seoul",
    "iso:country":"KR",
    "name:und_x_variant":[
        "\ud48d\uacbd\ub9ac",
        "P\u2019unggy\u014fng-ni"
    ],
    "wof:name":"P'unggyong-ni",
    "wof:placetype":"locality"
},
  "geometry": {"coordinates":[126.6981,36.7206],"type":"Point"}
}