{
  "type": "Feature",
  "properties": {
    "gn:admin1_code":"19.0",
    "gn:asciiname":"Araetjulgol",
    "gn:country_code":"KR",
    "gn:dem":118,
    "gn:feature_class":"P",
    "gn:feature_code":"PPL",
    "gn:name":"Araetjulgol",
    "gn:population":0,
    "gn:timezone":"Asia/Seoul",
    "iso:country":"KR",
    "name:und_x_variant":[
        "\uc544\ub7ab\uc904\uace8",
        "Araetchul-gol",
        "Araetjulgol"
    ],
    "wof:name":"Araetjulgol",
    "wof:placetype":"locality"
},
  "geometry": {"coordinates":[127.47485,36.33138],"type":"Point"}
}