{
  "type": "Feature",
  "properties": {
    "gn:admin1_code":"5.0",
    "gn:asciiname":"Wonmoryongi",
    "gn:country_code":"KR",
    "gn:dem":111,
    "gn:feature_class":"P",
    "gn:feature_code":"PPL",
    "gn:name":"Wonmoryongi",
    "gn:population":0,
    "gn:timezone":"Asia/Seoul",
    "iso:country":"KR",
    "name:kor_x_preferred":[
        "\uc6d0\ubaa8\ub871\uc774"
    ],
    "name:kor_x_variant":[
        "W\u014fnmorongi",
        "\uc6d0\ubaa8\ub8e1\uc774"
    ],
    "wof:name":"Wonmoryongi",
    "wof:placetype":"locality"
},
  "geometry": {"coordinates":[127.80188,37.04641],"type":"Point"}
}