{
  "type": "Feature",
  "properties": {
    "gn:admin1_code":"5.0",
    "gn:asciiname":"Saetteo",
    "gn:country_code":"KR",
    "gn:dem":116,
    "gn:feature_class":"P",
    "gn:feature_code":"PPL",
    "gn:name":"Saetteo",
    "gn:population":0,
    "gn:timezone":"Asia/Seoul",
    "iso:country":"KR",
    "name:kor_x_preferred":[
        "\uc0c8\ud130"
    ],
    "name:kor_x_variant":[
        "Saet\u2019\u014f",
        "\uc0db\ud130"
    ],
    "name:und_x_variant":[
        "Saeteo",
        "Saetteo"
    ],
    "wof:name":"Saetteo",
    "wof:placetype":"locality"
},
  "geometry": {"coordinates":[127.49988999999999,37.0284],"type":"Point"}
}