{
  "type": "Feature",
  "properties": {
    "gn:admin1_code":"19.0",
    "gn:asciiname":"Wongeumgo",
    "gn:country_code":"KR",
    "gn:dem":66,
    "gn:feature_class":"P",
    "gn:feature_code":"PPL",
    "gn:name":"Wongeumgo",
    "gn:population":0,
    "gn:timezone":"Asia/Seoul",
    "iso:country":"KR",
    "name:kor_x_preferred":[
        "\uc6d0\uae08\uace0"
    ],
    "wof:name":"Wongeumgo",
    "wof:placetype":"locality"
},
  "geometry": {"coordinates":[127.3887,36.46498],"type":"Point"}
}