{
  "type": "Feature",
  "properties": {
    "gn:admin1_code":"15.0",
    "gn:asciiname":"Myogol",
    "gn:country_code":"KR",
    "gn:dem":48,
    "gn:feature_class":"P",
    "gn:feature_code":"PPL",
    "gn:name":"Myogol",
    "gn:population":0,
    "gn:timezone":"Asia/Seoul",
    "iso:country":"KR",
    "name:und_x_variant":[
        "Myo-ri",
        "\ubb18\uace8",
        "Myogol"
    ],
    "wof:name":"Myogol",
    "wof:placetype":"locality"
},
  "geometry": {"coordinates":[128.41609,35.91012],"type":"Point"}
}