{
  "type": "Feature",
  "properties": {
    "gn:admin1_code":"13.0",
    "gn:admin2_code":"Ans\u014fng-si",
    "gn:asciiname":"Gidong",
    "gn:country_code":"KR",
    "gn:dem":64,
    "gn:feature_class":"P",
    "gn:feature_code":"PPL",
    "gn:name":"Gidong",
    "gn:population":0,
    "gn:timezone":"Asia/Seoul",
    "iso:country":"KR",
    "name:kor_x_preferred":[
        "\uae30\ub3d9"
    ],
    "name:und_x_variant":[
        "Ki-dong",
        "Gidong"
    ],
    "wof:name":"Gidong",
    "wof:placetype":"locality"
},
  "geometry": {"coordinates":[127.27003999999999,37.07465],"type":"Point"}
}