{
  "type": "Feature",
  "properties": {
    "gn:admin1_code":"13.0",
    "gn:asciiname":"Eoryongdong",
    "gn:country_code":"KR",
    "gn:dem":64,
    "gn:feature_class":"P",
    "gn:feature_code":"PPL",
    "gn:name":"Eoryongdong",
    "gn:population":0,
    "gn:timezone":"Asia/Seoul",
    "iso:country":"KR",
    "name:und_x_variant":[
        "\uc5b4\ub8e1\ub3d9",
        "\u014eryong-dong",
        "Eoryongdong"
    ],
    "wof:name":"Eoryongdong",
    "wof:placetype":"locality"
},
  "geometry": {"coordinates":[127.0827,37.7458],"type":"Point"}
}