{
  "type": "Feature",
  "properties": {
    "gn:admin1_code":"16.0",
    "gn:asciiname":"Seochon",
    "gn:country_code":"KR",
    "gn:dem":23,
    "gn:feature_class":"P",
    "gn:feature_code":"PPL",
    "gn:name":"Seochon",
    "gn:population":0,
    "gn:timezone":"Asia/Seoul",
    "iso:country":"KR",
    "name:kor_x_preferred":[
        "\uc11c\ucd0c"
    ],
    "wof:name":"Seochon",
    "wof:placetype":"locality"
},
  "geometry": {"coordinates":[126.73390000000001,34.92735],"type":"Point"}
}