{
  "type": "Feature",
  "properties": {
    "gn:admin1_code":"16.0",
    "gn:asciiname":"Dongsin",
    "gn:country_code":"KR",
    "gn:dem":23,
    "gn:feature_class":"P",
    "gn:feature_code":"PPL",
    "gn:name":"Dongsin",
    "gn:population":0,
    "gn:timezone":"Asia/Seoul",
    "iso:country":"KR",
    "name:kor_x_preferred":[
        "\ub3d9\uc2e0"
    ],
    "name:und_x_variant":[
        "Tongsin-ni",
        "Tongsin",
        "Dongsin"
    ],
    "wof:name":"Dongsin",
    "wof:placetype":"locality"
},
  "geometry": {"coordinates":[126.72606,34.96501],"type":"Point"}
}