{
  "type": "Feature",
  "properties": {
    "gn:admin1_code":"19.0",
    "gn:asciiname":"Saeteo",
    "gn:country_code":"KR",
    "gn:dem":62,
    "gn:feature_class":"P",
    "gn:feature_code":"PPL",
    "gn:name":"Saeteo",
    "gn:population":0,
    "gn:timezone":"Asia/Seoul",
    "iso:country":"KR",
    "name:und_x_variant":[
        "\uc0c8\ud130",
        "Saet\u2019\u014f",
        "Saeteo"
    ],
    "wof:name":"Saeteo",
    "wof:placetype":"locality"
},
  "geometry": {"coordinates":[127.32471,36.33789],"type":"Point"}
}