{
  "type": "Feature",
  "properties": {
    "gn:admin1_code":"6.0",
    "gn:asciiname":"Sangtodong",
    "gn:country_code":"KR",
    "gn:dem":208,
    "gn:feature_class":"P",
    "gn:feature_code":"PPL",
    "gn:name":"Sangtodong",
    "gn:population":0,
    "gn:timezone":"Asia/Seoul",
    "iso:country":"KR",
    "name:kor_x_preferred":[
        "\uc0c1\ud1a0\ub3d9"
    ],
    "wof:name":"Sangtodong",
    "wof:placetype":"locality"
},
  "geometry": {"coordinates":[127.3425,38.2456],"type":"Point"}
}