{
  "type": "Feature",
  "properties": {
    "gn:admin1_code":"13.0",
    "gn:admin2_code":"Ans\u014fng-si",
    "gn:asciiname":"Beolmal",
    "gn:country_code":"KR",
    "gn:dem":41,
    "gn:feature_class":"P",
    "gn:feature_code":"PPL",
    "gn:name":"Beolmal",
    "gn:population":0,
    "gn:timezone":"Asia/Seoul",
    "iso:country":"KR",
    "name:kor_x_preferred":[
        "Taep\u2019y\u014fng-ni"
    ],
    "name:kor_x_variant":[
        "\ubc8c\ub9d0",
        "P\u014fl-mal"
    ],
    "wof:name":"Beolmal",
    "wof:placetype":"locality"
},
  "geometry": {"coordinates":[127.25718999999999,37.07376],"type":"Point"}
}