{
  "type": "Feature",
  "properties": {
    "gn:admin1_code":"14.0",
    "gn:asciiname":"Buldang",
    "gn:country_code":"KR",
    "gn:dem":355,
    "gn:feature_class":"P",
    "gn:feature_code":"PPL",
    "gn:name":"Buldang",
    "gn:population":0,
    "gn:timezone":"Asia/Seoul",
    "iso:country":"KR",
    "name:kor_x_preferred":[
        "\ubd88\ub2f9"
    ],
    "wof:name":"Buldang",
    "wof:placetype":"locality"
},
  "geometry": {"coordinates":[128.58420000000001,36.05655],"type":"Point"}
}