{
  "type": "Feature",
  "properties": {
    "gn:admin1_code":"19.0",
    "gn:asciiname":"Secheon",
    "gn:country_code":"KR",
    "gn:dem":94,
    "gn:feature_class":"P",
    "gn:feature_code":"PPL",
    "gn:name":"Secheon",
    "gn:population":0,
    "gn:timezone":"Asia/Seoul",
    "iso:country":"KR",
    "name:kor_x_preferred":[
        "\uc138\ucc9c"
    ],
    "name:und_x_variant":[
        "Sech\u014fn-ni",
        "Sech\u2019\u014fn",
        "\uc138\ucc9c\ub3d9",
        "Sech\u2019\u014fn-dong",
        "Secheon"
    ],
    "wof:name":"Secheon",
    "wof:placetype":"locality"
},
  "geometry": {"coordinates":[127.49279,36.33909],"type":"Point"}
}