{
  "type": "Feature",
  "properties": {
    "gn:admin1_code":"18.0",
    "gn:asciiname":"Doya",
    "gn:country_code":"KR",
    "gn:dem":36,
    "gn:feature_class":"P",
    "gn:feature_code":"PPL",
    "gn:name":"Doya",
    "gn:population":0,
    "gn:timezone":"Asia/Seoul",
    "iso:country":"KR",
    "name:kor_x_preferred":[
        "\ub3c4\uc57c"
    ],
    "wof:name":"Doya",
    "wof:placetype":"locality"
},
  "geometry": {"coordinates":[126.69288,35.12767],"type":"Point"}
}