{
  "type": "Feature",
  "properties": {
    "gn:admin1_code":"13.0",
    "gn:asciiname":"Oesandae",
    "gn:country_code":"KR",
    "gn:dem":88,
    "gn:feature_class":"P",
    "gn:feature_code":"PPL",
    "gn:name":"Oesandae",
    "gn:population":0,
    "gn:timezone":"Asia/Seoul",
    "iso:country":"KR",
    "name:kor_x_preferred":[
        "\uc678\uc0b0\ub300"
    ],
    "wof:name":"Oesandae",
    "wof:placetype":"locality"
},
  "geometry": {"coordinates":[127.50843999999999,37.09104],"type":"Point"}
}