{
  "type": "Feature",
  "properties": {
    "gn:admin1_code":"14.0",
    "gn:asciiname":"Simji",
    "gn:country_code":"KR",
    "gn:dem":58,
    "gn:feature_class":"P",
    "gn:feature_code":"PPL",
    "gn:name":"Simji",
    "gn:population":0,
    "gn:timezone":"Asia/Seoul",
    "iso:country":"KR",
    "name:kor_x_preferred":[
        "\uc2ec\uc9c0"
    ],
    "wof:name":"Simji",
    "wof:placetype":"locality"
},
  "geometry": {"coordinates":[128.50968999999998,35.9584],"type":"Point"}
}