{
  "type": "Feature",
  "properties": {
    "gn:admin1_code":"6.0",
    "gn:asciiname":"Koryongso",
    "gn:country_code":"KR",
    "gn:dem":483,
    "gn:feature_class":"P",
    "gn:feature_code":"PPL",
    "gn:name":"Koryongso",
    "gn:population":0,
    "gn:timezone":"Asia/Seoul",
    "iso:country":"KR",
    "name:kor_x_preferred":[
        "\uace0\ub8e1\uc18c"
    ],
    "wof:name":"Koryongso",
    "wof:placetype":"locality"
},
  "geometry": {"coordinates":[128.5634,37.5176],"type":"Point"}
}