{
  "type": "Feature",
  "properties": {
    "gn:admin1_code":"13.0",
    "gn:admin2_code":"P'aju-si",
    "gn:asciiname":"Seokpo",
    "gn:country_code":"KR",
    "gn:dem":20,
    "gn:feature_class":"P",
    "gn:feature_code":"PPL",
    "gn:name":"Seokpo",
    "gn:population":0,
    "gn:timezone":"Asia/Seoul",
    "iso:country":"KR",
    "name:kor_x_preferred":[
        "\uc11d\ud3ec"
    ],
    "name:und_x_variant":[
        "S\u014fkp\u2019o"
    ],
    "wof:name":"Seokpo",
    "wof:placetype":"locality"
},
  "geometry": {"coordinates":[126.83421,37.96567],"type":"Point"}
}