{
  "type": "Feature",
  "properties": {
    "gn:admin1_code":"5.0",
    "gn:asciiname":"Gonigol",
    "gn:country_code":"KR",
    "gn:dem":187,
    "gn:feature_class":"P",
    "gn:feature_code":"PPL",
    "gn:name":"Gonigol",
    "gn:population":0,
    "gn:timezone":"Asia/Seoul",
    "iso:country":"KR",
    "name:kor_x_preferred":[
        "\uace0\ub2c8\uace8"
    ],
    "name:und_x_variant":[
        "Koni-gol"
    ],
    "wof:name":"Gonigol",
    "wof:placetype":"locality"
},
  "geometry": {"coordinates":[127.67516999999999,37.05581],"type":"Point"}
}