{
  "type": "Feature",
  "properties": {
    "gn:admin1_code":"16.0",
    "gn:asciiname":"Jeongcheon",
    "gn:country_code":"KR",
    "gn:dem":52,
    "gn:feature_class":"P",
    "gn:feature_code":"PPL",
    "gn:name":"Jeongcheon",
    "gn:population":0,
    "gn:timezone":"Asia/Seoul",
    "iso:country":"KR",
    "name:kor_x_preferred":[
        "\uc815\ucc9c"
    ],
    "name:und_x_variant":[
        "Ch\u014fngch\u2019\u014fn-ni",
        "Ch\u014fngch\u2019\u014fn",
        "Jeongcheon"
    ],
    "wof:name":"Jeongcheon",
    "wof:placetype":"locality"
},
  "geometry": {"coordinates":[126.89233,34.9505],"type":"Point"}
}