{
  "type": "Feature",
  "properties": {
    "gn:admin1_code":"16.0",
    "gn:asciiname":"Sinheungchon",
    "gn:country_code":"KR",
    "gn:dem":2,
    "gn:feature_class":"P",
    "gn:feature_code":"PPL",
    "gn:name":"Sinheungchon",
    "gn:population":0,
    "gn:timezone":"Asia/Seoul",
    "iso:country":"KR",
    "name:kor_x_preferred":[
        "\uc0b0\ud765\ucd0c"
    ],
    "name:kor_x_variant":[
        "Sanh\u016dngch\u2019on",
        "\uc2e0\ud765\ucd0c"
    ],
    "wof:name":"Sinheungchon",
    "wof:placetype":"locality"
},
  "geometry": {"coordinates":[127.21695,34.76825],"type":"Point"}
}