{
  "type": "Feature",
  "properties": {
    "gn:admin1_code":"14.0",
    "gn:asciiname":"Guman",
    "gn:country_code":"KR",
    "gn:dem":28,
    "gn:feature_class":"P",
    "gn:feature_code":"PPL",
    "gn:name":"Guman",
    "gn:population":0,
    "gn:timezone":"Asia/Seoul",
    "iso:country":"KR",
    "name:kor_x_preferred":[
        "\uad6c\ub9cc"
    ],
    "wof:name":"Guman",
    "wof:placetype":"locality"
},
  "geometry": {"coordinates":[129.54952,36.08043],"type":"Point"}
}