{
  "type": "Feature",
  "properties": {
    "gn:admin1_code":"12.0",
    "gn:asciiname":"Changdo",
    "gn:country_code":"KR",
    "gn:dem":13,
    "gn:feature_class":"P",
    "gn:feature_code":"PPL",
    "gn:name":"Changdo",
    "gn:population":0,
    "gn:timezone":"Asia/Seoul",
    "iso:country":"KR",
    "name:kor_x_preferred":[
        "\uc7a5\ub3c4"
    ],
    "name:und_x_variant":[
        "Noru-y\u014fm",
        "Noru-s\u014fm",
        "Changdo"
    ],
    "wof:name":"Changdo",
    "wof:placetype":"locality"
},
  "geometry": {"coordinates":[126.60805999999999,37.55056],"type":"Point"}
}