{
  "type": "Feature",
  "properties": {
    "gn:admin1_code":"16.0",
    "gn:asciiname":"Sucheong",
    "gn:country_code":"KR",
    "gn:dem":23,
    "gn:feature_class":"P",
    "gn:feature_code":"PPL",
    "gn:name":"Sucheong",
    "gn:population":0,
    "gn:timezone":"Asia/Seoul",
    "iso:country":"KR",
    "name:kor_x_preferred":[
        "\uc218\uccad"
    ],
    "wof:name":"Sucheong",
    "wof:placetype":"locality"
},
  "geometry": {"coordinates":[126.85624,35.05240999999999],"type":"Point"}
}