{
  "type": "Feature",
  "properties": {
    "gn:admin1_code":"16.0",
    "gn:asciiname":"Heulsan",
    "gn:country_code":"KR",
    "gn:dem":26,
    "gn:feature_class":"P",
    "gn:feature_code":"PPL",
    "gn:name":"Heulsan",
    "gn:population":0,
    "gn:timezone":"Asia/Seoul",
    "iso:country":"KR",
    "name:kor_x_preferred":[
        "\ud758\uc0b0"
    ],
    "name:kor_x_variant":[
        "H\u016dlsan"
    ],
    "name:und_x_variant":[
        "Kalsan-ni",
        "H\u016dlsan-ni",
        "Heulsan"
    ],
    "wof:name":"Heulsan",
    "wof:placetype":"locality"
},
  "geometry": {"coordinates":[127.46416000000001,34.93139],"type":"Point"}
}