{
  "type": "Feature",
  "properties": {
    "gn:admin1_code":"3.0",
    "gn:asciiname":"Songga",
    "gn:country_code":"KR",
    "gn:dem":249,
    "gn:feature_class":"P",
    "gn:feature_code":"PPL",
    "gn:name":"S\u014fngga",
    "gn:population":0,
    "gn:timezone":"Asia/Seoul",
    "iso:country":"KR",
    "name:und_x_variant":[
        "\uc131\uac00",
        "S\u014fngga"
    ],
    "wof:name":"Songga",
    "wof:placetype":"locality"
},
  "geometry": {"coordinates":[127.26603,35.60286],"type":"Point"}
}