{
  "type": "Feature",
  "properties": {
    "gn:admin1_code":"14.0",
    "gn:asciiname":"Chigijae-dong",
    "gn:country_code":"KR",
    "gn:dem":273,
    "gn:feature_class":"P",
    "gn:feature_code":"PPL",
    "gn:name":"Chigijae-dong",
    "gn:population":0,
    "gn:timezone":"Asia/Seoul",
    "iso:country":"KR",
    "name:und_x_variant":[
        "\uc9c0\uae30\uc7ac\ub3d9",
        "Chigijae-dong"
    ],
    "wof:name":"Chigijae-dong",
    "wof:placetype":"locality"
},
  "geometry": {"coordinates":[127.9833,36.3667],"type":"Point"}
}