{
  "type": "Feature",
  "properties": {
    "gn:admin1_code":"17.0",
    "gn:asciiname":"Sach'ang",
    "gn:country_code":"KR",
    "gn:dem":27,
    "gn:feature_class":"P",
    "gn:feature_code":"PPL",
    "gn:name":"Sach\u2019ang",
    "gn:population":0,
    "gn:timezone":"Asia/Seoul",
    "iso:country":"KR",
    "name:und_x_variant":[
        "Sach\u2019ang-ni",
        "\uc0ac\ucc3d",
        "Sach\u2019ang"
    ],
    "wof:name":"Sach'ang",
    "wof:placetype":"locality"
},
  "geometry": {"coordinates":[126.2778,36.8488],"type":"Point"}
}