{
  "type": "Feature",
  "properties": {
    "gn:admin1_code":"14.0",
    "gn:asciiname":"Chaesilma",
    "gn:country_code":"KR",
    "gn:dem":141,
    "gn:feature_class":"P",
    "gn:feature_code":"PPL",
    "gn:name":"Chaesilma",
    "gn:population":0,
    "gn:timezone":"Asia/Seoul",
    "iso:country":"KR",
    "name:und_x_variant":[
        "\uc7ac\uc2e4\ub9c8",
        "Chaesilma"
    ],
    "wof:name":"Chaesilma",
    "wof:placetype":"locality"
},
  "geometry": {"coordinates":[128.15479999999999,36.0534],"type":"Point"}
}