{
  "type": "Feature",
  "properties": {
    "gn:admin1_code":"6.0",
    "gn:asciiname":"Cheoksalli",
    "gn:country_code":"KR",
    "gn:dem":25,
    "gn:feature_class":"P",
    "gn:feature_code":"PPL",
    "gn:name":"Cheoksalli",
    "gn:population":0,
    "gn:timezone":"Asia/Seoul",
    "iso:country":"KR",
    "name:kor_x_preferred":[
        "\ucc99\uc0b0\ub9ac"
    ],
    "name:und_x_variant":[
        "Ch\u2019\u014fksal-li",
        "Cheoksalli"
    ],
    "wof:name":"Cheoksalli",
    "wof:placetype":"locality"
},
  "geometry": {"coordinates":[128.54130000000001,38.18454000000001],"type":"Point"}
}