{
  "type": "Feature",
  "properties": {
    "gn:admin1_code":"13.0",
    "gn:asciiname":"Ajangdong",
    "gn:country_code":"KR",
    "gn:dem":75,
    "gn:feature_class":"P",
    "gn:feature_code":"PPL",
    "gn:name":"Ajangdong",
    "gn:population":0,
    "gn:timezone":"Asia/Seoul",
    "iso:country":"KR",
    "name:kor_x_preferred":[
        "\uc544\uc7a5\ub3d9"
    ],
    "wof:name":"Ajangdong",
    "wof:placetype":"locality"
},
  "geometry": {"coordinates":[127.10136,38.00473],"type":"Point"}
}