{
  "type": "Feature",
  "properties": {
    "gn:admin1_code":"13.0",
    "gn:asciiname":"Norumok",
    "gn:country_code":"KR",
    "gn:dem":146,
    "gn:feature_class":"P",
    "gn:feature_code":"PPL",
    "gn:name":"Norumok",
    "gn:population":0,
    "gn:timezone":"Asia/Seoul",
    "iso:country":"KR",
    "name:und_x_variant":[
        "\ub178\ub8e8\ubaa9",
        "Norumok"
    ],
    "wof:name":"Norumok",
    "wof:placetype":"locality"
},
  "geometry": {"coordinates":[127.33167,37.30278],"type":"Point"}
}