{
  "type": "Feature",
  "properties": {
    "gn:admin1_code":"5.0",
    "gn:asciiname":"Podusil",
    "gn:country_code":"KR",
    "gn:dem":229,
    "gn:feature_class":"P",
    "gn:feature_code":"PPL",
    "gn:name":"P\u014fd\u016dsil",
    "gn:population":0,
    "gn:timezone":"Asia/Seoul",
    "iso:country":"KR",
    "name:und_x_variant":[
        "\ubc84\ub4dc\uc2e4",
        "P\u014fd\u016dsil"
    ],
    "wof:name":"Podusil",
    "wof:placetype":"locality"
},
  "geometry": {"coordinates":[127.91289999999999,36.1425],"type":"Point"}
}