{
  "type": "Feature",
  "properties": {
    "gn:admin1_code":"17.0",
    "gn:asciiname":"Chojongi",
    "gn:country_code":"KR",
    "gn:dem":20,
    "gn:feature_class":"P",
    "gn:feature_code":"PPL",
    "gn:name":"Choj\u014fngi",
    "gn:population":0,
    "gn:timezone":"Asia/Seoul",
    "iso:country":"KR",
    "name:und_x_variant":[
        "\uc870\uc815\uc774",
        "Choj\u014fngi"
    ],
    "wof:name":"Chojongi",
    "wof:placetype":"locality"
},
  "geometry": {"coordinates":[126.7756,36.7967],"type":"Point"}
}