{
  "type": "Feature",
  "properties": {
    "gn:admin1_code":"6.0",
    "gn:asciiname":"Paegunjong",
    "gn:country_code":"KR",
    "gn:dem":197,
    "gn:feature_class":"P",
    "gn:feature_code":"PPL",
    "gn:name":"Paegunj\u014fng",
    "gn:population":0,
    "gn:timezone":"Asia/Seoul",
    "iso:country":"KR",
    "name:kor_x_preferred":[
        "\ubc31\uc6b4\uc815"
    ],
    "name:kor_x_variant":[
        "Paegunj\u014fng"
    ],
    "wof:name":"Paegunjong",
    "wof:placetype":"locality"
},
  "geometry": {"coordinates":[127.9385,37.296],"type":"Point"}
}