{
  "type": "Feature",
  "properties": {
    "gn:admin1_code":"6.0",
    "gn:asciiname":"Tteokgalmaegi",
    "gn:country_code":"KR",
    "gn:dem":356,
    "gn:feature_class":"P",
    "gn:feature_code":"PPL",
    "gn:name":"Tteokgalmaegi",
    "gn:population":0,
    "gn:timezone":"Asia/Seoul",
    "iso:country":"KR",
    "name:kor_x_preferred":[
        "\ub355\uac08\ub9e4\uae30"
    ],
    "name:kor_x_variant":[
        "T\u014fkkalmaegi",
        "\ub5a1\uac08\ub9e4\uae30"
    ],
    "name:und_x_variant":[
        "T\u014fkkalmegi",
        "Tteokgalmaegi"
    ],
    "wof:name":"Tteokgalmaegi",
    "wof:placetype":"locality"
},
  "geometry": {"coordinates":[127.89413,37.97398],"type":"Point"}
}