{
  "type": "Feature",
  "properties": {
    "gn:admin1_code":"16.0",
    "gn:asciiname":"Wonhyo",
    "gn:country_code":"KR",
    "gn:dem":107,
    "gn:feature_class":"P",
    "gn:feature_code":"PPL",
    "gn:name":"Wonhyo",
    "gn:population":0,
    "gn:timezone":"Asia/Seoul",
    "iso:country":"KR",
    "name:kor_x_preferred":[
        "\uc6d0\ud6a8"
    ],
    "wof:name":"Wonhyo",
    "wof:placetype":"locality"
},
  "geometry": {"coordinates":[127.01394000000001,35.26374000000001],"type":"Point"}
}