{
  "type": "Feature",
  "properties": {
    "gn:admin1_code":"16.0",
    "gn:asciiname":"Wonhyo",
    "gn:country_code":"KR",
    "gn:dem":107,
    "gn:feature_class":"P",
    "gn:feature_code":"PPL",
    "gn:name":"Wonhyo",
    "gn:population":0,
    "gn:timezone":"Asia/Seoul",
    "iso:country":"KR",
    "name:fra_x_preferred":[
        "Wonhyo"
    ],
    "name:ind_x_preferred":[
        "Wonhyo"
    ],
    "name:kor_x_preferred":[
        "\uc6d0\ud6a8"
    ],
    "name:nld_x_preferred":[
        "Wonhyo"
    ],
    "name:pol_x_preferred":[
        "W\u014fnhyo"
    ],
    "name:rus_x_preferred":[
        "\u0412\u043e\u043d\u0445\u0451"
    ],
    "name:spa_x_preferred":[
        "Wonhyo"
    ],
    "name:vie_x_preferred":[
        "Nguy\u00ean Hi\u1ec3u"
    ],
    "wof:name":"Wonhyo",
    "wof:placetype":"locality"
},
  "geometry": {"coordinates":[127.01394000000001,35.26374000000001],"type":"Point"}
}