{
  "type": "Feature",
  "properties": {
    "gn:admin1_code":"21.0",
    "gn:asciiname":"Hwarim",
    "gn:country_code":"KR",
    "gn:dem":47,
    "gn:feature_class":"P",
    "gn:feature_code":"PPL",
    "gn:name":"Hwarim",
    "gn:population":0,
    "gn:timezone":"Asia/Seoul",
    "iso:country":"KR",
    "name:kor_x_preferred":[
        "\ud654\ub9bc"
    ],
    "wof:name":"Hwarim",
    "wof:placetype":"locality"
},
  "geometry": {"coordinates":[129.27956,35.4813],"type":"Point"}
}