{
  "type": "Feature",
  "properties": {
    "gn:admin1_code":"14.0",
    "gn:asciiname":"Dokjeong",
    "gn:country_code":"KR",
    "gn:dem":98,
    "gn:feature_class":"P",
    "gn:feature_code":"PPL",
    "gn:name":"Dokjeong",
    "gn:population":0,
    "gn:timezone":"Asia/Seoul",
    "iso:country":"KR",
    "name:kor_x_preferred":[
        "\ub3c5\uc815"
    ],
    "wof:name":"Dokjeong",
    "wof:placetype":"locality"
},
  "geometry": {"coordinates":[128.49478999999999,36.65533],"type":"Point"}
}