{
  "type": "Feature",
  "properties": {
    "gn:admin1_code":"17.0",
    "gn:asciiname":"Hwa-ri",
    "gn:country_code":"KR",
    "gn:dem":44,
    "gn:feature_class":"P",
    "gn:feature_code":"PPL",
    "gn:name":"Hwa-ri",
    "gn:population":0,
    "gn:timezone":"Asia/Seoul",
    "iso:country":"KR",
    "name:und_x_variant":[
        "\ud654\ub9ac",
        "Hwa-ri"
    ],
    "wof:name":"Hwa-ri",
    "wof:placetype":"locality"
},
  "geometry": {"coordinates":[126.59229999999999,36.6027],"type":"Point"}
}