{
  "type": "Feature",
  "properties": {
    "gn:admin1_code":"13.0",
    "gn:admin2_code":"Ich'\u014fn-si",
    "gn:asciiname":"Angoni",
    "gn:country_code":"KR",
    "gn:dem":78,
    "gn:feature_class":"P",
    "gn:feature_code":"PPL",
    "gn:name":"Angoni",
    "gn:population":0,
    "gn:timezone":"Asia/Seoul",
    "iso:country":"KR",
    "name:kor_x_preferred":[
        "\uc548\uace0\ub2c8"
    ],
    "name:kor_x_variant":[
        "An\u2019goni"
    ],
    "wof:name":"Angoni",
    "wof:placetype":"locality"
},
  "geometry": {"coordinates":[127.42270000000001,37.23599],"type":"Point"}
}