{
  "type": "Feature",
  "properties": {
    "gn:admin1_code":"17.0",
    "gn:asciiname":"Yot'i",
    "gn:country_code":"KR",
    "gn:dem":151,
    "gn:feature_class":"P",
    "gn:feature_code":"PPL",
    "gn:name":"Y\u014ft\u2019i",
    "gn:population":0,
    "gn:timezone":"Asia/Seoul",
    "iso:country":"KR",
    "name:und_x_variant":[
        "Y\u014fch\u2019i-ri",
        "Y\u014ft\u2019i",
        "\uc5ec\ud2f0",
        "Y\u014ft\u2019oe"
    ],
    "wof:name":"Yot'i",
    "wof:placetype":"locality"
},
  "geometry": {"coordinates":[126.7574,36.4521],"type":"Point"}
}