{
  "type": "Feature",
  "properties": {
    "gn:admin1_code":"20.0",
    "gn:asciiname":"Kaekpang",
    "gn:cc2":"KR",
    "gn:country_code":"KR",
    "gn:dem":52,
    "gn:feature_class":"P",
    "gn:feature_code":"PPL",
    "gn:name":"Kaekpang",
    "gn:population":0,
    "gn:timezone":"Asia/Seoul",
    "iso:country":"KR",
    "name:und_x_variant":[
        "Kaekpang-ni",
        "Kaekpang"
    ],
    "wof:name":"Kaekpang",
    "wof:placetype":"locality"
},
  "geometry": {"coordinates":[128.16861,35.02444000000001],"type":"Point"}
}