{
  "type": "Feature",
  "properties": {
    "gn:admin1_code":"11.0",
    "gn:asciiname":"Huksoksam-dong",
    "gn:country_code":"KR",
    "gn:dem":29,
    "gn:feature_class":"P",
    "gn:feature_code":"PPL",
    "gn:name":"H\u016dks\u014fksam-dong",
    "gn:population":0,
    "gn:timezone":"Asia/Seoul",
    "iso:country":"KR",
    "name:und_x_variant":[
        "\ud751\uc11d3\ub3d9",
        "H\u016dks\u014fksam-dong"
    ],
    "wof:name":"Huksoksam-dong",
    "wof:placetype":"locality"
},
  "geometry": {"coordinates":[126.96366999999999,37.50387],"type":"Point"}
}