{
  "type": "Feature",
  "properties": {
    "gn:admin1_code":"13.0",
    "gn:asciiname":"Saen-mal",
    "gn:country_code":"KR",
    "gn:dem":59,
    "gn:feature_class":"P",
    "gn:feature_code":"PPL",
    "gn:name":"Saen-mal",
    "gn:population":0,
    "gn:timezone":"Asia/Seoul",
    "iso:country":"KR",
    "name:und_x_variant":[
        "\uc0db\ub9d0",
        "Saet-mal",
        "Saen-mal"
    ],
    "wof:name":"Saen-mal",
    "wof:placetype":"locality"
},
  "geometry": {"coordinates":[127.39639,37.46667],"type":"Point"}
}