{
  "type": "Feature",
  "properties": {
    "iso:country":"KR",
    "qs:name":"\ucd98\uad81\ub3d9",
    "qs:name_adm0":"\ud55c\uad6d",
    "qs:name_adm1":"\uacbd\uae30\ub3c4",
    "qs:photos":1,
    "qs:photos_1k":1,
    "qs:photos_9k":1,
    "qs:photos_9r":1,
    "qs:photos_all":1,
    "qs:photos_sr":1,
    "qs:placetype":"LocalAdmin",
    "qs:pop_sr":"0",
    "wof:name":"\ucd98\uad81\ub3d9",
    "wof:placetype":"localadmin"
},
  "geometry": {"coordinates":[127.24897350000001,37.552743],"type":"Point"}
}