{
  "type": "Feature",
  "properties": {
    "gn:admin1_code":"14.0",
    "gn:asciiname":"Imul-li",
    "gn:country_code":"KR",
    "gn:dem":58,
    "gn:feature_class":"P",
    "gn:feature_code":"PPLL",
    "gn:name":"Imul-li",
    "gn:population":0,
    "gn:timezone":"Asia/Seoul",
    "iso:country":"KR",
    "name:und_x_variant":[
        "\uc774\ubb38\ub9ac",
        "Imul-li"
    ],
    "wof:name":"Imul-li",
    "wof:placetype":"locality"
},
  "geometry": {"coordinates":[128.28673000000001,36.24123],"type":"Point"}
}