{
  "type": "Feature",
  "properties": {
    "gn:admin1_code":"13.0",
    "gn:asciiname":"Tura-ri",
    "gn:cc2":"KR",
    "gn:country_code":"KR",
    "gn:dem":59,
    "gn:feature_class":"P",
    "gn:feature_code":"PPL",
    "gn:name":"Tura-ri",
    "gn:population":0,
    "gn:timezone":"Asia/Seoul",
    "iso:country":"KR",
    "name:und_x_variant":[
        "Uttura-ri",
        "Tura-ri"
    ],
    "wof:name":"Tura-ri",
    "wof:placetype":"locality"
},
  "geometry": {"coordinates":[127.64278,37.35583],"type":"Point"}
}