{
  "type": "Feature",
  "properties": {
    "gn:admin1_code":"12.0",
    "gn:asciiname":"Soljeong",
    "gn:country_code":"KR",
    "gn:dem":13,
    "gn:feature_class":"P",
    "gn:feature_code":"PPL",
    "gn:name":"Soljeong",
    "gn:population":0,
    "gn:timezone":"Asia/Seoul",
    "iso:country":"KR",
    "name:und_x_variant":[
        "\uc194\uc815",
        "Soljeong",
        "Solch\u014fng"
    ],
    "wof:name":"Soljeong",
    "wof:placetype":"locality"
},
  "geometry": {"coordinates":[126.51282,37.64788],"type":"Point"}
}