{
  "type": "Feature",
  "properties": {
    "gn:admin1_code":"16.0",
    "gn:admin2_code":"Chindo-gun",
    "gn:asciiname":"Jangbalteo",
    "gn:country_code":"KR",
    "gn:dem":17,
    "gn:feature_class":"P",
    "gn:feature_code":"PPL",
    "gn:name":"Jangbalteo",
    "gn:population":0,
    "gn:timezone":"Asia/Seoul",
    "iso:country":"KR",
    "name:kor_x_preferred":[
        "\uc7a5\ubc1c\ud130"
    ],
    "name:und_x_variant":[
        "Changbalt\u2019\u014f"
    ],
    "wof:name":"Jangbalteo",
    "wof:placetype":"locality"
},
  "geometry": {"coordinates":[126.36196,34.44260999999999],"type":"Point"}
}