{
  "type": "Feature",
  "properties": {
    "gn:admin1_code":"16.0",
    "gn:asciiname":"Jangji",
    "gn:country_code":"KR",
    "gn:dem":4,
    "gn:feature_class":"P",
    "gn:feature_code":"PPL",
    "gn:name":"Jangji",
    "gn:population":0,
    "gn:timezone":"Asia/Seoul",
    "iso:country":"KR",
    "name:kor_x_preferred":[
        "\uc7a5\uc9c0"
    ],
    "name:und_x_variant":[
        "Changjwa",
        "Changja",
        "Jangji"
    ],
    "wof:name":"Jangji",
    "wof:placetype":"locality"
},
  "geometry": {"coordinates":[126.33645,34.78855],"type":"Point"}
}