{
  "type": "Feature",
  "properties": {
    "gn:admin1_code":"6.0",
    "gn:asciiname":"Chongbau",
    "gn:country_code":"KR",
    "gn:dem":402,
    "gn:feature_class":"P",
    "gn:feature_code":"PPL",
    "gn:name":"Ch\u014fngbau",
    "gn:population":0,
    "gn:timezone":"Asia/Seoul",
    "iso:country":"KR",
    "name:kor_x_preferred":[
        "\uc815\ubc14\uc6b0"
    ],
    "name:kor_x_variant":[
        "Ch\u014fngbau"
    ],
    "wof:name":"Chongbau",
    "wof:placetype":"locality"
},
  "geometry": {"coordinates":[128.1284,37.3594],"type":"Point"}
}