{
  "type": "Feature",
  "properties": {
    "gn:admin1_code":"15.0",
    "gn:asciiname":"Kkongji",
    "gn:country_code":"KR",
    "gn:dem":70,
    "gn:feature_class":"P",
    "gn:feature_code":"PPL",
    "gn:name":"Kkongji",
    "gn:population":0,
    "gn:timezone":"Asia/Seoul",
    "iso:country":"KR",
    "name:kor_x_preferred":[
        "\uaf41\uc9c0"
    ],
    "wof:name":"Kkongji",
    "wof:placetype":"locality"
},
  "geometry": {"coordinates":[128.68606,35.83869],"type":"Point"}
}