{
  "type": "Feature",
  "properties": {
    "gn:admin1_code":"18.0",
    "gn:asciiname":"Seochang",
    "gn:country_code":"KR",
    "gn:dem":20,
    "gn:feature_class":"P",
    "gn:feature_code":"PPL",
    "gn:name":"Seochang",
    "gn:population":0,
    "gn:timezone":"Asia/Seoul",
    "iso:country":"KR",
    "name:kor_x_preferred":[
        "\uc11c\ucc3d"
    ],
    "name:und_x_variant":[
        "S\u014fch\u2019ang"
    ],
    "wof:name":"Seochang",
    "wof:placetype":"locality"
},
  "geometry": {"coordinates":[126.82102,35.10869],"type":"Point"}
}