{
  "type": "Feature",
  "properties": {
    "gn:admin1_code":"5.0",
    "gn:asciiname":"Geomdeundol",
    "gn:country_code":"KR",
    "gn:dem":88,
    "gn:feature_class":"P",
    "gn:feature_code":"PPL",
    "gn:name":"Geomdeundol",
    "gn:population":0,
    "gn:timezone":"Asia/Seoul",
    "iso:country":"KR",
    "name:kor_x_preferred":[
        "\uac80\uc740\ub3cc"
    ],
    "wof:name":"Geomdeundol",
    "wof:placetype":"locality"
},
  "geometry": {"coordinates":[127.8372,36.97407000000001],"type":"Point"}
}