{
  "type": "Feature",
  "properties": {
    "gn:admin1_code":"20.0",
    "gn:asciiname":"Jungmaeul",
    "gn:country_code":"KR",
    "gn:dem":102,
    "gn:feature_class":"P",
    "gn:feature_code":"PPL",
    "gn:name":"Jungmaeul",
    "gn:population":0,
    "gn:timezone":"Asia/Seoul",
    "iso:country":"KR",
    "name:und_x_variant":[
        "\uc911\ub9c8\uc744",
        "Chung-ma\u016dl",
        "Jungmaeul"
    ],
    "wof:name":"Jungmaeul",
    "wof:placetype":"locality"
},
  "geometry": {"coordinates":[128.5001,35.60004],"type":"Point"}
}