{
  "type": "Feature",
  "properties": {
    "gn:admin1_code":"16.0",
    "gn:asciiname":"Hwacheon",
    "gn:country_code":"KR",
    "gn:dem":16,
    "gn:feature_class":"P",
    "gn:feature_code":"PPL",
    "gn:name":"Hwacheon",
    "gn:population":0,
    "gn:timezone":"Asia/Seoul",
    "iso:country":"KR",
    "name:kor_x_preferred":[
        "\ud654\ucc9c"
    ],
    "name:kor_x_variant":[
        "Hwach\u2019\u014fn"
    ],
    "wof:name":"Hwacheon",
    "wof:placetype":"locality"
},
  "geometry": {"coordinates":[127.26338,34.75097],"type":"Point"}
}