{
  "type": "Feature",
  "properties": {
    "gn:admin1_code":"17.0",
    "gn:asciiname":"Paguni-gol",
    "gn:country_code":"KR",
    "gn:dem":114,
    "gn:feature_class":"P",
    "gn:feature_code":"PPL",
    "gn:name":"Pag\u016dni-gol",
    "gn:population":0,
    "gn:timezone":"Asia/Seoul",
    "iso:country":"KR",
    "name:und_x_variant":[
        "\ubc15\uc740\uc774\uace8",
        "Pag\u016dni-gol"
    ],
    "wof:name":"Paguni-gol",
    "wof:placetype":"locality"
},
  "geometry": {"coordinates":[126.8349,36.4985],"type":"Point"}
}