{
  "type": "Feature",
  "properties": {
    "gn:admin1_code":"13.0",
    "gn:asciiname":"Seommal",
    "gn:country_code":"KR",
    "gn:dem":99,
    "gn:feature_class":"P",
    "gn:feature_code":"PPL",
    "gn:name":"Seommal",
    "gn:population":0,
    "gn:timezone":"Asia/Seoul",
    "iso:country":"KR",
    "name:und_x_variant":[
        "\uc12c\ub9d0",
        "S\u014fm-mal",
        "Seommal"
    ],
    "wof:name":"Seommal",
    "wof:placetype":"locality"
},
  "geometry": {"coordinates":[126.97318,37.83902],"type":"Point"}
}