{
  "type": "Feature",
  "properties": {
    "gn:admin1_code":"14.0",
    "gn:asciiname":"Saet'o",
    "gn:country_code":"KR",
    "gn:dem":303,
    "gn:feature_class":"P",
    "gn:feature_code":"PPL",
    "gn:name":"Saet\u2019\u014f",
    "gn:population":0,
    "gn:timezone":"Asia/Seoul",
    "iso:country":"KR",
    "wof:name":"Saet'o",
    "wof:placetype":"locality"
},
  "geometry": {"coordinates":[128.96583000000001,35.77389],"type":"Point"}
}