{
  "type": "Feature",
  "properties": {
    "gn:admin1_code":"15.0",
    "gn:asciiname":"Guam",
    "gn:country_code":"KR",
    "gn:dem":144,
    "gn:feature_class":"P",
    "gn:feature_code":"PPL",
    "gn:name":"Guam",
    "gn:population":0,
    "gn:timezone":"Asia/Seoul",
    "iso:country":"KR",
    "name:kor_x_preferred":[
        "\uad6c\uc554"
    ],
    "wof:name":"Guam",
    "wof:placetype":"locality"
},
  "geometry": {"coordinates":[128.67553000000001,35.9499],"type":"Point"}
}