{
  "type": "Feature",
  "properties": {
    "gn:admin1_code":"16.0",
    "gn:asciiname":"Dogo",
    "gn:country_code":"KR",
    "gn:dem":37,
    "gn:feature_class":"P",
    "gn:feature_code":"PPL",
    "gn:name":"Dogo",
    "gn:population":0,
    "gn:timezone":"Asia/Seoul",
    "iso:country":"KR",
    "name:ceb_x_preferred":[
        "Dogo"
    ],
    "name:deu_x_preferred":[
        "Dogo"
    ],
    "name:ita_x_preferred":[
        "Dogo"
    ],
    "name:kor_x_preferred":[
        "\ub3c4\uace0"
    ],
    "name:msa_x_preferred":[
        "Dogo"
    ],
    "name:ron_x_preferred":[
        "Dogo"
    ],
    "name:spa_x_preferred":[
        "Dogo"
    ],
    "name:swe_x_preferred":[
        "Dogo"
    ],
    "wof:name":"Dogo",
    "wof:placetype":"locality"
},
  "geometry": {"coordinates":[126.97048999999998,35.29235],"type":"Point"}
}