{
  "type": "Feature",
  "properties": {
    "gn:admin1_code":"0.0",
    "gn:asciiname":"Cheokchi",
    "gn:country_code":"KR",
    "gn:dem":13,
    "gn:feature_class":"P",
    "gn:feature_code":"PPL",
    "gn:name":"Cheokchi",
    "gn:population":0,
    "gn:timezone":"Asia/Seoul",
    "iso:country":"KR",
    "name:kor_x_preferred":[
        "\ucc99\uce58"
    ],
    "name:und_x_variant":[
        "Ch\u2019\u014fkch\u2019i-ri",
        "Ch\u2019\u014fkchae-ri",
        "Ch\u2019\u014fkch\u2019i",
        "Cheokchi"
    ],
    "wof:name":"Cheokchi",
    "wof:placetype":"locality"
},
  "geometry": {"coordinates":[127.02862,34.36167],"type":"Point"}
}