{
  "type": "Feature",
  "properties": {
    "gn:admin1_code":"20.0",
    "gn:asciiname":"Witunsan",
    "gn:cc2":"KR",
    "gn:country_code":"KR",
    "gn:dem":155,
    "gn:feature_class":"P",
    "gn:feature_code":"PPL",
    "gn:name":"Wit\u016dnsan",
    "gn:population":0,
    "gn:timezone":"Asia/Seoul",
    "iso:country":"KR",
    "name:und_x_variant":[
        "\u016cnsan",
        "Wit\u016dnsan"
    ],
    "wof:name":"Witunsan",
    "wof:placetype":"locality"
},
  "geometry": {"coordinates":[128.74056000000002,35.40306],"type":"Point"}
}