{
  "type": "Feature",
  "properties": {
    "gn:admin1_code":"17.0",
    "gn:asciiname":"Kalmaeji",
    "gn:country_code":"KR",
    "gn:dem":24,
    "gn:feature_class":"P",
    "gn:feature_code":"PPL",
    "gn:name":"Kalmaeji",
    "gn:population":0,
    "gn:timezone":"Asia/Seoul",
    "iso:country":"KR",
    "name:und_x_variant":[
        "\uac08\ub9e4\uc9c0",
        "Kalmaeji"
    ],
    "wof:name":"Kalmaeji",
    "wof:placetype":"locality"
},
  "geometry": {"coordinates":[126.95350000000001,36.8622],"type":"Point"}
}