{
  "type": "Feature",
  "properties": {
    "gn:admin1_code":"20.0",
    "gn:asciiname":"Ch'amyol-li",
    "gn:country_code":"KR",
    "gn:dem":41,
    "gn:feature_class":"P",
    "gn:feature_code":"PPL",
    "gn:name":"Ch\u2019amy\u014fl-li",
    "gn:population":0,
    "gn:timezone":"Asia/Seoul",
    "iso:country":"KR",
    "name:und_x_variant":[
        "Ch\u2019amy\u014fn-ni",
        "Ch\u2019amy\u014fl-li"
    ],
    "wof:name":"Ch'amyol-li",
    "wof:placetype":"locality"
},
  "geometry": {"coordinates":[127.85527999999999,34.9175],"type":"Point"}
}