{
  "type": "Feature",
  "properties": {
    "gn:admin1_code":"11.0",
    "gn:asciiname":"Puam-dong",
    "gn:country_code":"KR",
    "gn:dem":83,
    "gn:feature_class":"P",
    "gn:feature_code":"PPL",
    "gn:name":"Puam-dong",
    "gn:population":0,
    "gn:timezone":"Asia/Seoul",
    "iso:country":"KR",
    "name:und_x_variant":[
        "Puam-j\u014fng",
        "\ubd80\uc554\ub3d9",
        "Puam-dong"
    ],
    "wof:name":"Puam-dong",
    "wof:placetype":"locality"
},
  "geometry": {"coordinates":[126.96285,37.59835],"type":"Point"}
}