{
  "type": "Feature",
  "properties": {
    "gn:admin1_code":"16.0",
    "gn:asciiname":"Banghwa",
    "gn:country_code":"KR",
    "gn:dem":35,
    "gn:feature_class":"P",
    "gn:feature_code":"PPL",
    "gn:name":"Banghwa",
    "gn:population":0,
    "gn:timezone":"Asia/Seoul",
    "iso:country":"KR",
    "name:kor_x_preferred":[
        "\ubc29\ud654"
    ],
    "name:und_x_variant":[
        "Pangha-ri",
        "Pangha-dong",
        "Banghwa"
    ],
    "wof:name":"Banghwa",
    "wof:placetype":"locality"
},
  "geometry": {"coordinates":[126.60554999999999,35.20799],"type":"Point"}
}