{
  "type": "Feature",
  "properties": {
    "gn:admin1_code":"6.0",
    "gn:asciiname":"Beolchon",
    "gn:country_code":"KR",
    "gn:dem":226,
    "gn:feature_class":"P",
    "gn:feature_code":"PPL",
    "gn:name":"Beolchon",
    "gn:population":0,
    "gn:timezone":"Asia/Seoul",
    "iso:country":"KR",
    "name:kor_x_preferred":[
        "\ubc8c\ucd0c"
    ],
    "name:kor_x_variant":[
        "P\u014flch\u2019on"
    ],
    "wof:name":"Beolchon",
    "wof:placetype":"locality"
},
  "geometry": {"coordinates":[127.96559000000001,37.80267],"type":"Point"}
}