{
  "type": "Feature",
  "properties": {
    "gn:admin1_code":"5.0",
    "gn:asciiname":"Hageumgok",
    "gn:country_code":"KR",
    "gn:dem":97,
    "gn:feature_class":"P",
    "gn:feature_code":"PPL",
    "gn:name":"Hageumgok",
    "gn:population":0,
    "gn:timezone":"Asia/Seoul",
    "iso:country":"KR",
    "name:kor_x_preferred":[
        "\ud558\uae08\uace1"
    ],
    "wof:name":"Hageumgok",
    "wof:placetype":"locality"
},
  "geometry": {"coordinates":[127.82581999999999,36.96707],"type":"Point"}
}