{
  "type": "Feature",
  "properties": {
    "gn:admin1_code":"3.0",
    "gn:asciiname":"Onsu-dong",
    "gn:country_code":"KR",
    "gn:dem":33,
    "gn:feature_class":"P",
    "gn:feature_code":"PPL",
    "gn:name":"Onsu-dong",
    "gn:population":0,
    "gn:timezone":"Asia/Seoul",
    "iso:country":"KR",
    "name:msa_x_preferred":[
        "Onsu-dong"
    ],
    "name:sco_x_preferred":[
        "Onsu-dong"
    ],
    "name:und_x_variant":[
        "\uc628\uc218\ub3d9",
        "Onsu-dong"
    ],
    "name:vie_x_preferred":[
        "Onsu-dong"
    ],
    "wof:name":"Onsu-dong",
    "wof:placetype":"locality"
},
  "geometry": {"coordinates":[127.06737,35.93187],"type":"Point"}
}