{
  "type": "Feature",
  "properties": {
    "gn:admin1_code":"14.0",
    "gn:asciiname":"Suryom",
    "gn:cc2":"KR",
    "gn:country_code":"KR",
    "gn:dem":34,
    "gn:feature_class":"P",
    "gn:feature_code":"PPL",
    "gn:name":"Sury\u014fm",
    "gn:population":0,
    "gn:timezone":"Asia/Seoul",
    "iso:country":"KR",
    "name:und_x_variant":[
        "Suny\u014fmi-ni",
        "Sury\u014fm-ni",
        "Suny\u014fm",
        "Sury\u014fm"
    ],
    "wof:name":"Suryom",
    "wof:placetype":"locality"
},
  "geometry": {"coordinates":[129.45582999999999,35.66917],"type":"Point"}
}