{
  "type": "Feature",
  "properties": {
    "gn:admin1_code":"14.0",
    "gn:asciiname":"Bongnimi",
    "gn:country_code":"KR",
    "gn:dem":14,
    "gn:feature_class":"P",
    "gn:feature_code":"PPL",
    "gn:name":"Bongnimi",
    "gn:population":0,
    "gn:timezone":"Asia/Seoul",
    "iso:country":"KR",
    "name:kor_x_preferred":[
        "\ubd09\ub9bc\uc774"
    ],
    "wof:name":"Bongnimi",
    "wof:placetype":"locality"
},
  "geometry": {"coordinates":[129.39654999999999,36.1136],"type":"Point"}
}