{
  "type": "Feature",
  "properties": {
    "gn:admin1_code":"17.0",
    "gn:asciiname":"Ssangnyeong",
    "gn:country_code":"KR",
    "gn:dem":103,
    "gn:feature_class":"P",
    "gn:feature_code":"PPL",
    "gn:name":"Ssangnyeong",
    "gn:population":0,
    "gn:timezone":"Asia/Seoul",
    "iso:country":"KR",
    "name:kor_x_preferred":[
        "\uc30d\ub839"
    ],
    "wof:name":"Ssangnyeong",
    "wof:placetype":"locality"
},
  "geometry": {"coordinates":[127.12009999999999,36.68386],"type":"Point"}
}