{
  "type": "Feature",
  "properties": {
    "gn:admin1_code":"17.0",
    "gn:asciiname":"Uisil",
    "gn:country_code":"KR",
    "gn:dem":114,
    "gn:feature_class":"P",
    "gn:feature_code":"PPL",
    "gn:name":"Uisil",
    "gn:population":0,
    "gn:timezone":"Asia/Seoul",
    "iso:country":"KR",
    "name:kor_x_preferred":[
        "\uc758\uc2e4"
    ],
    "wof:name":"Uisil",
    "wof:placetype":"locality"
},
  "geometry": {"coordinates":[127.31043,36.21569],"type":"Point"}
}