{
  "type": "Feature",
  "properties": {
    "gn:admin1_code":"16.0",
    "gn:asciiname":"Kumgye-ri",
    "gn:country_code":"KR",
    "gn:dem":24,
    "gn:feature_class":"P",
    "gn:feature_code":"PPL",
    "gn:name":"K\u016dmgye-ri",
    "gn:population":0,
    "gn:timezone":"Asia/Seoul",
    "iso:country":"KR",
    "name:kor_x_preferred":[
        "\uae08\uacc4\ub9ac"
    ],
    "name:kor_x_variant":[
        "K\u016dmgye-ri"
    ],
    "name:und_x_variant":[
        "K\u016dmgyeri-ilgu",
        "K\u016dmge-ri"
    ],
    "wof:name":"Kumgye-ri",
    "wof:placetype":"locality"
},
  "geometry": {"coordinates":[126.59305999999999,34.72639],"type":"Point"}
}