{
  "type": "Feature",
  "properties": {
    "gn:admin1_code":"14.0",
    "gn:asciiname":"Iltu",
    "gn:country_code":"KR",
    "gn:dem":222,
    "gn:feature_class":"P",
    "gn:feature_code":"PPL",
    "gn:name":"Iltu",
    "gn:population":0,
    "gn:timezone":"Asia/Seoul",
    "iso:country":"KR",
    "name:und_x_variant":[
        "\uc77c\ub450",
        "Iltu"
    ],
    "wof:name":"Iltu",
    "wof:placetype":"locality"
},
  "geometry": {"coordinates":[129.06890000000001,36.3867],"type":"Point"}
}