{
  "type": "Feature",
  "properties": {
    "gn:admin1_code":"17.0",
    "gn:asciiname":"Mokchaeul",
    "gn:country_code":"KR",
    "gn:dem":19,
    "gn:feature_class":"P",
    "gn:feature_code":"PPL",
    "gn:name":"M\u014fkchaeul",
    "gn:population":0,
    "gn:timezone":"Asia/Seoul",
    "iso:country":"KR",
    "name:und_x_variant":[
        "\uba39\uc7ac\uc6b8",
        "M\u014fkchaeul"
    ],
    "wof:name":"Mokchaeul",
    "wof:placetype":"locality"
},
  "geometry": {"coordinates":[126.52760000000001,36.5752],"type":"Point"}
}