{
  "type": "Feature",
  "properties": {
    "gn:admin1_code":"17.0",
    "gn:asciiname":"Sojong-ni",
    "gn:country_code":"KR",
    "gn:dem":39,
    "gn:feature_class":"P",
    "gn:feature_code":"PPL",
    "gn:name":"Soj\u014fng-ni",
    "gn:population":0,
    "gn:timezone":"Asia/Seoul",
    "iso:country":"KR",
    "wof:name":"Sojong-ni",
    "wof:placetype":"locality"
},
  "geometry": {"coordinates":[127.15083,36.71083],"type":"Point"}
}