{
  "type": "Feature",
  "properties": {
    "gn:admin1_code":"6.0",
    "gn:asciiname":"Non'gae",
    "gn:country_code":"KR",
    "gn:dem":105,
    "gn:feature_class":"P",
    "gn:feature_code":"PPL",
    "gn:name":"Non\u2019gae",
    "gn:population":0,
    "gn:timezone":"Asia/Seoul",
    "iso:country":"KR",
    "name:und_x_variant":[
        "\ub17c\uac1c",
        "Non\u2019gae"
    ],
    "wof:name":"Non'gae",
    "wof:placetype":"locality"
},
  "geometry": {"coordinates":[129.12459999999999,37.3529],"type":"Point"}
}