{
  "type": "Feature",
  "properties": {
    "gn:admin1_code":"16.0",
    "gn:asciiname":"Usuiei",
    "gn:country_code":"KR",
    "gn:dem":24,
    "gn:feature_class":"P",
    "gn:feature_code":"PPL",
    "gn:name":"Usuiei",
    "gn:population":0,
    "gn:timezone":"Asia/Seoul",
    "iso:country":"KR",
    "name:und_x_variant":[
        "Suyon",
        "Usuiei",
        "Usuy\u014fng"
    ],
    "wof:name":"Usuiei",
    "wof:placetype":"locality"
},
  "geometry": {"coordinates":[126.31305999999999,34.59611],"type":"Point"}
}