{
  "type": "Feature",
  "properties": {
    "gn:admin1_code":"17.0",
    "gn:asciiname":"Yugumi",
    "gn:country_code":"KR",
    "gn:dem":16,
    "gn:feature_class":"P",
    "gn:feature_code":"PPL",
    "gn:name":"Yugumi",
    "gn:population":0,
    "gn:timezone":"Asia/Seoul",
    "iso:country":"KR",
    "name:und_x_variant":[
        "\uc720\uad6c\ubbf8",
        "Yugumi"
    ],
    "wof:name":"Yugumi",
    "wof:placetype":"locality"
},
  "geometry": {"coordinates":[126.3961,36.6519],"type":"Point"}
}