{
  "type": "Feature",
  "properties": {
    "gn:admin1_code":"6.0",
    "gn:asciiname":"Daepori",
    "gn:country_code":"KR",
    "gn:dem":16,
    "gn:feature_class":"P",
    "gn:feature_code":"PPL",
    "gn:name":"Daepori",
    "gn:population":0,
    "gn:timezone":"Asia/Seoul",
    "iso:country":"KR",
    "name:kor_x_preferred":[
        "\ub300\ud3ec"
    ],
    "name:kor_x_variant":[
        "\ub300\ud3ec\ub9ac"
    ],
    "name:und_x_variant":[
        "Taiho-ri",
        "Taep\u2019o-dong",
        "Taep\u2019o-ri",
        "Taep\u2019o",
        "Daepori"
    ],
    "wof:name":"Daepori",
    "wof:placetype":"locality"
},
  "geometry": {"coordinates":[128.60418999999999,38.17434],"type":"Point"}
}