{
  "type": "Feature",
  "properties": {
    "gn:admin1_code":"16.0",
    "gn:asciiname":"Gaundong",
    "gn:country_code":"KR",
    "gn:dem":101,
    "gn:feature_class":"P",
    "gn:feature_code":"PPL",
    "gn:name":"Gaundong",
    "gn:population":0,
    "gn:timezone":"Asia/Seoul",
    "iso:country":"KR",
    "name:kor_x_preferred":[
        "\uae30\uc6b4\ub3d9"
    ],
    "name:kor_x_variant":[
        "\uac00\uc6b4\ub3d9"
    ],
    "name:und_x_variant":[
        "Kiun-dong",
        "Giundong",
        "Gaundong"
    ],
    "wof:name":"Gaundong",
    "wof:placetype":"locality"
},
  "geometry": {"coordinates":[127.00611000000001,34.87066],"type":"Point"}
}