{
  "type": "Feature",
  "properties": {
    "gn:admin1_code":"11.0",
    "gn:asciiname":"Pangbaesa-dong",
    "gn:country_code":"KR",
    "gn:dem":21,
    "gn:feature_class":"P",
    "gn:feature_code":"PPL",
    "gn:name":"Pangbaesa-dong",
    "gn:population":0,
    "gn:timezone":"Asia/Seoul",
    "iso:country":"KR",
    "name:und_x_variant":[
        "\ubc29\ubc304\ub3d9",
        "Bangbaesa-dong",
        "Pangbaesa-dong"
    ],
    "wof:name":"Pangbaesa-dong",
    "wof:placetype":"locality"
},
  "geometry": {"coordinates":[126.99139,37.48972],"type":"Point"}
}