{
  "type": "Feature",
  "properties": {
    "gn:admin1_code":"17.0",
    "gn:asciiname":"Song-dong",
    "gn:country_code":"KR",
    "gn:dem":44,
    "gn:feature_class":"P",
    "gn:feature_code":"PPL",
    "gn:name":"S\u014fng-dong",
    "gn:population":0,
    "gn:timezone":"Asia/Seoul",
    "iso:country":"KR",
    "name:und_x_variant":[
        "\uc131\ub3d9",
        "S\u014fng-dong"
    ],
    "wof:name":"Song-dong",
    "wof:placetype":"locality"
},
  "geometry": {"coordinates":[126.3955,36.7804],"type":"Point"}
}