{
  "type": "Feature",
  "properties": {
    "gn:admin1_code":"13.0",
    "gn:asciiname":"Gueongmal",
    "gn:country_code":"KR",
    "gn:dem":13,
    "gn:feature_class":"P",
    "gn:feature_code":"PPL",
    "gn:name":"Gueongmal",
    "gn:population":0,
    "gn:timezone":"Asia/Seoul",
    "iso:country":"KR",
    "name:kor_x_preferred":[
        "\uad6c\uc5b5\ub9d0"
    ],
    "name:kor_x_variant":[
        "Ku\u014fngmal"
    ],
    "wof:name":"Gueongmal",
    "wof:placetype":"locality"
},
  "geometry": {"coordinates":[126.71835,37.24876],"type":"Point"}
}