{
  "type": "Feature",
  "properties": {
    "gn:admin1_code":"16.0",
    "gn:asciiname":"Gyochon",
    "gn:country_code":"KR",
    "gn:dem":96,
    "gn:feature_class":"P",
    "gn:feature_code":"PPL",
    "gn:name":"Gyochon",
    "gn:population":0,
    "gn:timezone":"Asia/Seoul",
    "iso:country":"KR",
    "name:kor_x_preferred":[
        "Kyoch\u2019on"
    ],
    "name:kor_x_variant":[
        "\uad50\ucd0c"
    ],
    "wof:name":"Gyochon",
    "wof:placetype":"locality"
},
  "geometry": {"coordinates":[126.9575,34.73778],"type":"Point"}
}