{
  "type": "Feature",
  "properties": {
    "gn:admin1_code":"14.0",
    "gn:asciiname":"Jaengam",
    "gn:country_code":"KR",
    "gn:dem":107,
    "gn:feature_class":"P",
    "gn:feature_code":"PPL",
    "gn:name":"Jaengam",
    "gn:population":0,
    "gn:timezone":"Asia/Seoul",
    "iso:country":"KR",
    "name:kor_x_preferred":[
        "\uc7c1\uc554"
    ],
    "name:und_x_variant":[
        "Chaengbau"
    ],
    "wof:name":"Jaengam",
    "wof:placetype":"locality"
},
  "geometry": {"coordinates":[129.32499999999999,36.30448],"type":"Point"}
}