{
  "type": "Feature",
  "properties": {
    "gn:admin1_code":"13.0",
    "gn:asciiname":"Mokgoljumak",
    "gn:country_code":"KR",
    "gn:dem":90,
    "gn:feature_class":"P",
    "gn:feature_code":"PPL",
    "gn:name":"Mokgoljumak",
    "gn:population":0,
    "gn:timezone":"Asia/Seoul",
    "iso:country":"KR",
    "name:kor_x_preferred":[
        "\ubaa9\uace8\uc8fc\ub9c9"
    ],
    "name:und_x_variant":[
        "Mokkolchumak"
    ],
    "wof:name":"Mokgoljumak",
    "wof:placetype":"locality"
},
  "geometry": {"coordinates":[127.60975999999999,37.11598],"type":"Point"}
}