{
  "type": "Feature",
  "properties": {
    "gn:admin1_code":"6.0",
    "gn:asciiname":"Sokkyo",
    "gn:country_code":"KR",
    "gn:dem":359,
    "gn:feature_class":"P",
    "gn:feature_code":"PPL",
    "gn:name":"S\u014fkkyo",
    "gn:population":0,
    "gn:timezone":"Asia/Seoul",
    "iso:country":"KR",
    "name:kor_x_preferred":[
        "\uc11d\uad50"
    ],
    "name:kor_x_variant":[
        "S\u014fkkyo"
    ],
    "wof:name":"Sokkyo",
    "wof:placetype":"locality"
},
  "geometry": {"coordinates":[128.66669999999999,37.3944],"type":"Point"}
}