{
  "type": "Feature",
  "properties": {
    "gn:admin1_code":"6.0",
    "gn:asciiname":"Hap'ohang",
    "gn:country_code":"KR",
    "gn:dem":573,
    "gn:feature_class":"P",
    "gn:feature_code":"PPL",
    "gn:name":"Hap\u2019ohang",
    "gn:population":0,
    "gn:timezone":"Asia/Seoul",
    "iso:country":"KR",
    "name:kor_x_preferred":[
        "\ud558\ud3ec\ud56d"
    ],
    "name:kor_x_variant":[
        "Hap\u2019ohang"
    ],
    "wof:name":"Hap'ohang",
    "wof:placetype":"locality"
},
  "geometry": {"coordinates":[128.36340000000001,37.6253],"type":"Point"}
}