{
  "type": "Feature",
  "properties": {
    "gn:admin1_code":"13.0",
    "gn:admin2_code":"Ich'\u014fn-si",
    "gn:asciiname":"Jumakgeori",
    "gn:country_code":"KR",
    "gn:dem":67,
    "gn:feature_class":"P",
    "gn:feature_code":"PPL",
    "gn:name":"Jumakgeori",
    "gn:population":0,
    "gn:timezone":"Asia/Seoul",
    "iso:country":"KR",
    "name:kor_x_preferred":[
        "\uc8fc\ub9c9\uac70\ub9ac"
    ],
    "name:kor_x_variant":[
        "Chumakk\u014fri"
    ],
    "wof:name":"Jumakgeori",
    "wof:placetype":"locality"
},
  "geometry": {"coordinates":[127.45045,37.22125],"type":"Point"}
}