{
  "type": "Feature",
  "properties": {
    "gn:admin1_code":"17.0",
    "gn:asciiname":"Sangbodul",
    "gn:country_code":"KR",
    "gn:dem":149,
    "gn:feature_class":"P",
    "gn:feature_code":"PPL",
    "gn:name":"Sangbod\u016dl",
    "gn:population":0,
    "gn:timezone":"Asia/Seoul",
    "iso:country":"KR",
    "name:und_x_variant":[
        "\uc0c1\ubcf4\ub4e4",
        "Sangbod\u016dl"
    ],
    "wof:name":"Sangbodul",
    "wof:placetype":"locality"
},
  "geometry": {"coordinates":[127.40430000000001,36.1614],"type":"Point"}
}