{
  "type": "Feature",
  "properties": {
    "gn:admin1_code":"16.0",
    "gn:asciiname":"Namjeong",
    "gn:country_code":"KR",
    "gn:dem":148,
    "gn:feature_class":"P",
    "gn:feature_code":"PPL",
    "gn:name":"Namjeong",
    "gn:population":0,
    "gn:timezone":"Asia/Seoul",
    "iso:country":"KR",
    "name:kor_x_preferred":[
        "\ub0a8\uc815"
    ],
    "name:kor_x_variant":[
        "Namj\u014fng"
    ],
    "name:und_x_variant":[
        "Namj\u014fn",
        "Namjeong"
    ],
    "wof:name":"Namjeong",
    "wof:placetype":"locality"
},
  "geometry": {"coordinates":[127.352,34.97187],"type":"Point"}
}