{
  "type": "Feature",
  "properties": {
    "gn:admin1_code":"14.0",
    "gn:asciiname":"Ttanggyeul",
    "gn:country_code":"KR",
    "gn:dem":150,
    "gn:feature_class":"P",
    "gn:feature_code":"PPL",
    "gn:name":"Ttanggyeul",
    "gn:population":0,
    "gn:timezone":"Asia/Seoul",
    "iso:country":"KR",
    "name:und_x_variant":[
        "\ub545\uacc4\uc6b8",
        "Ttanggyeul"
    ],
    "wof:name":"Ttanggyeul",
    "wof:placetype":"locality"
},
  "geometry": {"coordinates":[128.19333999999998,35.82116],"type":"Point"}
}