{
  "type": "Feature",
  "properties": {
    "gn:admin1_code":"14.0",
    "gn:asciiname":"Baekcheon",
    "gn:country_code":"KR",
    "gn:dem":635,
    "gn:feature_class":"P",
    "gn:feature_code":"PPL",
    "gn:name":"Baekcheon",
    "gn:population":0,
    "gn:timezone":"Asia/Seoul",
    "iso:country":"KR",
    "name:kor_x_preferred":[
        "\uc0c1\ubc31\ucc9c"
    ],
    "name:kor_x_variant":[
        "Sangbaekch\u2019\u014fn",
        "\ubc31\ucc9c"
    ],
    "wof:name":"Baekcheon",
    "wof:placetype":"locality"
},
  "geometry": {"coordinates":[128.98310000000001,37.0676],"type":"Point"}
}