{
  "type": "Feature",
  "properties": {
    "gn:admin1_code":"13.0",
    "gn:asciiname":"Kappawijangt'o",
    "gn:country_code":"KR",
    "gn:dem":81,
    "gn:feature_class":"P",
    "gn:feature_code":"PPL",
    "gn:name":"Kappawijangt\u2019\u014f",
    "gn:population":0,
    "gn:timezone":"Asia/Seoul",
    "iso:country":"KR",
    "name:und_x_variant":[
        "\uac13\ubc14\uc704\uc7a5\ud130",
        "Kappawijangt\u2019\u014f"
    ],
    "wof:name":"Kappawijangt'o",
    "wof:placetype":"locality"
},
  "geometry": {"coordinates":[126.99930000000001,37.8713],"type":"Point"}
}