{
  "type": "Feature",
  "properties": {
    "gn:admin1_code":"16.0",
    "gn:asciiname":"Pyeongjuk",
    "gn:country_code":"KR",
    "gn:dem":21,
    "gn:feature_class":"P",
    "gn:feature_code":"PPL",
    "gn:name":"Pyeongjuk",
    "gn:population":0,
    "gn:timezone":"Asia/Seoul",
    "iso:country":"KR",
    "name:kor_x_preferred":[
        "\ud3c9\uc8fd"
    ],
    "wof:name":"Pyeongjuk",
    "wof:placetype":"locality"
},
  "geometry": {"coordinates":[126.75709999999999,34.99802],"type":"Point"}
}