{
  "type": "Feature",
  "properties": {
    "gn:admin1_code":"16.0",
    "gn:asciiname":"Guam",
    "gn:country_code":"KR",
    "gn:dem":146,
    "gn:feature_class":"P",
    "gn:feature_code":"PPL",
    "gn:name":"Guam",
    "gn:population":0,
    "gn:timezone":"Asia/Seoul",
    "iso:country":"KR",
    "name:kor_x_preferred":[
        "\uad6c\uc554"
    ],
    "name:und_x_variant":[
        "Kuam-ni",
        "Kuam",
        "Guam"
    ],
    "wof:name":"Guam",
    "wof:placetype":"locality"
},
  "geometry": {"coordinates":[127.07838999999998,35.0353],"type":"Point"}
}