{
  "type": "Feature",
  "properties": {
    "gn:admin1_code":"16.0",
    "gn:asciiname":"Dunju",
    "gn:country_code":"KR",
    "gn:dem":7,
    "gn:feature_class":"P",
    "gn:feature_code":"PPL",
    "gn:name":"Dunju",
    "gn:population":0,
    "gn:timezone":"Asia/Seoul",
    "iso:country":"KR",
    "name:kor_x_preferred":[
        "\ub450\uc8fc"
    ],
    "name:und_x_variant":[
        "Tuju",
        "Dunju"
    ],
    "wof:name":"Dunju",
    "wof:placetype":"locality"
},
  "geometry": {"coordinates":[126.62761,34.63451],"type":"Point"}
}