{
  "type": "Feature",
  "properties": {
    "gn:admin1_code":"14.0",
    "gn:asciiname":"Meoso",
    "gn:country_code":"KR",
    "gn:dem":58,
    "gn:feature_class":"P",
    "gn:feature_code":"PPL",
    "gn:name":"Meoso",
    "gn:population":0,
    "gn:timezone":"Asia/Seoul",
    "iso:country":"KR",
    "name:kor_x_preferred":[
        "\uba38\uc18c"
    ],
    "wof:name":"Meoso",
    "wof:placetype":"locality"
},
  "geometry": {"coordinates":[129.19341,35.77309],"type":"Point"}
}