{
  "type": "Feature",
  "properties": {
    "gn:admin1_code":"17.0",
    "gn:asciiname":"Seungjeokgol",
    "gn:country_code":"KR",
    "gn:dem":68,
    "gn:feature_class":"P",
    "gn:feature_code":"PPL",
    "gn:name":"Seungjeokgol",
    "gn:population":0,
    "gn:timezone":"Asia/Seoul",
    "iso:country":"KR",
    "name:und_x_variant":[
        "\uc2b9\uc801\uace8",
        "S\u016dngj\u014fk-kol",
        "Seungjeokgol"
    ],
    "wof:name":"Seungjeokgol",
    "wof:placetype":"locality"
},
  "geometry": {"coordinates":[127.23299,36.16954000000001],"type":"Point"}
}