{
  "type": "Feature",
  "properties": {
    "gn:admin1_code":"1.0",
    "gn:asciiname":"Wittumunae",
    "gn:country_code":"KR",
    "gn:dem":207,
    "gn:feature_class":"P",
    "gn:feature_code":"PPL",
    "gn:name":"Wittumunae",
    "gn:population":0,
    "gn:timezone":"Asia/Seoul",
    "iso:country":"KR",
    "wof:name":"Wittumunae",
    "wof:placetype":"locality"
},
  "geometry": {"coordinates":[126.58611000000001,33.47833],"type":"Point"}
}