{
  "type": "Feature",
  "properties": {
    "gn:admin1_code":"17.0",
    "gn:asciiname":"Umnae",
    "gn:country_code":"KR",
    "gn:dem":45,
    "gn:feature_class":"P",
    "gn:feature_code":"PPL",
    "gn:name":"\u016cmnae",
    "gn:population":0,
    "gn:timezone":"Asia/Seoul",
    "iso:country":"KR",
    "name:und_x_variant":[
        "Shinsh\u014d",
        "Sinch\u2019ang",
        "\uc74d\ub0b4",
        "\u016cmnae-ri",
        "\u016cmnae"
    ],
    "wof:name":"Umnae",
    "wof:placetype":"locality"
},
  "geometry": {"coordinates":[126.9318,36.7783],"type":"Point"}
}