{
  "type": "Feature",
  "properties": {
    "gn:admin1_code":"16.0",
    "gn:asciiname":"Woljeolli",
    "gn:country_code":"KR",
    "gn:dem":80,
    "gn:feature_class":"P",
    "gn:feature_code":"PPL",
    "gn:name":"Woljeolli",
    "gn:population":0,
    "gn:timezone":"Asia/Seoul",
    "iso:country":"KR",
    "name:kor_x_preferred":[
        "\uc6d4\uc804\ub9ac"
    ],
    "wof:name":"Woljeolli",
    "wof:placetype":"locality"
},
  "geometry": {"coordinates":[126.89617,34.92673],"type":"Point"}
}