{
  "type": "Feature",
  "properties": {
    "gn:admin1_code":"17.0",
    "gn:asciiname":"Jiryang",
    "gn:country_code":"KR",
    "gn:dem":97,
    "gn:feature_class":"P",
    "gn:feature_code":"PPL",
    "gn:name":"Jiryang",
    "gn:population":0,
    "gn:timezone":"Asia/Seoul",
    "iso:country":"KR",
    "name:und_x_variant":[
        "\uc9c0\ub7c9",
        "Chiryang",
        "Jiryang"
    ],
    "wof:name":"Jiryang",
    "wof:placetype":"locality"
},
  "geometry": {"coordinates":[127.37005000000001,36.24692],"type":"Point"}
}