{
  "type": "Feature",
  "properties": {
    "gn:admin1_code":"18.0",
    "gn:asciiname":"Hosong",
    "gn:country_code":"KR",
    "gn:dem":30,
    "gn:feature_class":"P",
    "gn:feature_code":"PPL",
    "gn:name":"Hosong",
    "gn:population":0,
    "gn:timezone":"Asia/Seoul",
    "iso:country":"KR",
    "name:kor_x_preferred":[
        "\ud638\uc1a1"
    ],
    "wof:name":"Hosong",
    "wof:placetype":"locality"
},
  "geometry": {"coordinates":[126.74751000000001,35.17234000000001],"type":"Point"}
}