{
  "type": "Feature",
  "properties": {
    "gn:admin1_code":"16.0",
    "gn:asciiname":"Sinheungdong",
    "gn:country_code":"KR",
    "gn:dem":218,
    "gn:feature_class":"P",
    "gn:feature_code":"PPL",
    "gn:name":"Sinheungdong",
    "gn:population":0,
    "gn:timezone":"Asia/Seoul",
    "iso:country":"KR",
    "name:kor_x_preferred":[
        "\uc2e0\ud765"
    ],
    "name:kor_x_variant":[
        "Sinh\u016dng",
        "\uc2e0\ud765\ub3d9"
    ],
    "name:und_x_variant":[
        "Sinh\u016dng-dong",
        "Sinheungdong"
    ],
    "wof:name":"Sinheungdong",
    "wof:placetype":"locality"
},
  "geometry": {"coordinates":[127.05558000000001,34.83671],"type":"Point"}
}