{
  "type": "Feature",
  "properties": {
    "gn:admin1_code":"17.0",
    "gn:asciiname":"Sabong",
    "gn:country_code":"KR",
    "gn:dem":116,
    "gn:feature_class":"P",
    "gn:feature_code":"PPL",
    "gn:name":"Sabong",
    "gn:population":0,
    "gn:timezone":"Asia/Seoul",
    "iso:country":"KR",
    "name:und_x_variant":[
        "\uc0ac\ubd09",
        "Sabong"
    ],
    "wof:name":"Sabong",
    "wof:placetype":"locality"
},
  "geometry": {"coordinates":[127.2645,36.36653],"type":"Point"}
}