{
  "type": "Feature",
  "properties": {
    "gn:admin1_code":"17.0",
    "gn:asciiname":"Kaech'ugi",
    "gn:country_code":"KR",
    "gn:dem":122,
    "gn:feature_class":"P",
    "gn:feature_code":"PPL",
    "gn:name":"Kaech\u2019ugi",
    "gn:population":0,
    "gn:timezone":"Asia/Seoul",
    "iso:country":"KR",
    "name:und_x_variant":[
        "\uac1c\ucd95\uc774",
        "Kaech\u2019ugi"
    ],
    "wof:name":"Kaech'ugi",
    "wof:placetype":"locality"
},
  "geometry": {"coordinates":[126.7007,36.3048],"type":"Point"}
}