{
  "type": "Feature",
  "properties": {
    "gn:admin1_code":"20.0",
    "gn:asciiname":"Kajobang",
    "gn:country_code":"KR",
    "gn:dem":243,
    "gn:feature_class":"P",
    "gn:feature_code":"PPL",
    "gn:name":"Kajobang",
    "gn:population":0,
    "gn:timezone":"Asia/Seoul",
    "iso:country":"KR",
    "name:und_x_variant":[
        "\uac00\uc870\ubc29",
        "Kajobang"
    ],
    "wof:name":"Kajobang",
    "wof:placetype":"locality"
},
  "geometry": {"coordinates":[128.13345000000001,35.66275],"type":"Point"}
}