{
  "type": "Feature",
  "properties": {
    "gn:admin1_code":"6.0",
    "gn:asciiname":"Georimal",
    "gn:country_code":"KR",
    "gn:dem":115,
    "gn:feature_class":"P",
    "gn:feature_code":"PPL",
    "gn:name":"Georimal",
    "gn:population":0,
    "gn:timezone":"Asia/Seoul",
    "iso:country":"KR",
    "name:kor_x_preferred":[
        "\uac70\ub9ac\ub9d0"
    ],
    "wof:name":"Georimal",
    "wof:placetype":"locality"
},
  "geometry": {"coordinates":[127.65978,37.99167],"type":"Point"}
}