{
  "type": "Feature",
  "properties": {
    "gn:admin1_code":"17.0",
    "gn:asciiname":"Kolmoe",
    "gn:country_code":"KR",
    "gn:dem":15,
    "gn:feature_class":"P",
    "gn:feature_code":"PPL",
    "gn:name":"K\u014flmoe",
    "gn:population":0,
    "gn:timezone":"Asia/Seoul",
    "iso:country":"KR",
    "name:und_x_variant":[
        "\uac78\ubafc",
        "K\u014flmoe"
    ],
    "wof:name":"Kolmoe",
    "wof:placetype":"locality"
},
  "geometry": {"coordinates":[126.87739999999999,36.2785],"type":"Point"}
}