{
  "type": "Feature",
  "properties": {
    "gn:admin1_code":"13.0",
    "gn:asciiname":"Jiksanmal",
    "gn:country_code":"KR",
    "gn:dem":24,
    "gn:feature_class":"P",
    "gn:feature_code":"PPL",
    "gn:name":"Jiksanmal",
    "gn:population":0,
    "gn:timezone":"Asia/Seoul",
    "iso:country":"KR",
    "name:und_x_variant":[
        "Chiksan\u2019gok",
        "\uc9c1\uc0b0\ub9d0",
        "Chiksan-mal",
        "Jiksanmal"
    ],
    "wof:name":"Jiksanmal",
    "wof:placetype":"locality"
},
  "geometry": {"coordinates":[126.94256,36.97691],"type":"Point"}
}