{
  "type": "Feature",
  "properties": {
    "gn:admin1_code":"10.0",
    "gn:asciiname":"Jungni Il Gu",
    "gn:country_code":"KR",
    "gn:dem":6,
    "gn:feature_class":"P",
    "gn:feature_code":"PPL",
    "gn:name":"Jungni Il Gu",
    "gn:population":0,
    "gn:timezone":"Asia/Seoul",
    "iso:country":"KR",
    "name:eng_x_preferred":[
        "Jungni Il"
    ],
    "name:eng_x_variant":[
        "Jungni Il Gu"
    ],
    "name:kor_x_preferred":[
        "\uc911\ub9ac1\uad6c"
    ],
    "name:und_x_variant":[
        "Jungni 1 Gu"
    ],
    "wof:name":"Jungni Il",
    "wof:placetype":"locality"
},
  "geometry": {"coordinates":[128.95603,35.22095],"type":"Point"}
}