{
  "type": "Feature",
  "properties": {
    "gn:admin1_code":"16.0",
    "gn:asciiname":"Songchon",
    "gn:country_code":"KR",
    "gn:dem":33,
    "gn:feature_class":"P",
    "gn:feature_code":"PPL",
    "gn:name":"Songchon",
    "gn:population":0,
    "gn:timezone":"Asia/Seoul",
    "iso:country":"KR",
    "name:kor_x_preferred":[
        "\uc1a1\ucd0c"
    ],
    "name:kor_x_variant":[
        "Songch\u2019on"
    ],
    "name:und_x_variant":[
        "Songch\u2019on-ni",
        "Songchon"
    ],
    "wof:name":"Songchon",
    "wof:placetype":"locality"
},
  "geometry": {"coordinates":[126.58028,34.40555999999999],"type":"Point"}
}