{
  "type": "Feature",
  "properties": {
    "gn:admin1_code":"20.0",
    "gn:asciiname":"Tongnae",
    "gn:country_code":"KR",
    "gn:dem":16,
    "gn:feature_class":"P",
    "gn:feature_code":"PPL",
    "gn:name":"Tongnae",
    "gn:population":0,
    "gn:timezone":"Asia/Seoul",
    "iso:country":"KR",
    "name:und_x_variant":[
        "\ub3d9\ub798",
        "Tongnae"
    ],
    "wof:name":"Tongnae",
    "wof:placetype":"locality"
},
  "geometry": {"coordinates":[128.36816000000002,34.89032],"type":"Point"}
}