{
  "type": "Feature",
  "properties": {
    "gn:admin1_code":"16.0",
    "gn:asciiname":"Sinwol-li",
    "gn:country_code":"KR",
    "gn:dem":20,
    "gn:feature_class":"P",
    "gn:feature_code":"PPL",
    "gn:name":"Sinw\u014fl-li",
    "gn:population":0,
    "gn:timezone":"Asia/Seoul",
    "iso:country":"KR",
    "wof:name":"Sinwol-li",
    "wof:placetype":"locality"
},
  "geometry": {"coordinates":[126.70222,34.955],"type":"Point"}
}