{
  "type": "Feature",
  "properties": {
    "gn:admin1_code":"17.0",
    "gn:asciiname":"Songch'on",
    "gn:country_code":"KR",
    "gn:dem":38,
    "gn:feature_class":"P",
    "gn:feature_code":"PPL",
    "gn:name":"Songch\u2019\u014fn",
    "gn:population":0,
    "gn:timezone":"Asia/Seoul",
    "iso:country":"KR",
    "name:und_x_variant":[
        "\uc1a1\ucc9c",
        "Songch\u2019\u014fn"
    ],
    "wof:name":"Songch'on",
    "wof:placetype":"locality"
},
  "geometry": {"coordinates":[126.8532,36.5866],"type":"Point"}
}