{
  "type": "Feature",
  "properties": {
    "iso:country":"KR",
    "name:eng_x_preferred":[
        "Chopyeong-dong"
    ],
    "name:kor_x_preferred":[
        "\ucd08\ud3c9\ub3d9"
    ],
    "qs:name":"\ucd08\ud3c9\ub3d9",
    "qs:name_adm0":"\ud55c\uad6d",
    "qs:name_adm1":"\uacbd\uae30\ub3c4",
    "qs:photos":2,
    "qs:photos_1k":1,
    "qs:photos_9k":1,
    "qs:photos_9r":1,
    "qs:photos_all":2,
    "qs:photos_sr":1,
    "qs:placetype":"LocalAdmin",
    "qs:pop_sr":"0",
    "wof:name":"Chopyeong-dong",
    "wof:placetype":"localadmin"
},
  "geometry": {"coordinates":[127.056884,37.163599],"type":"Point"}
}