{
  "type": "Feature",
  "properties": {
    "gn:admin1_code":"6.0",
    "gn:asciiname":"Chongsung-gol",
    "gn:country_code":"KR",
    "gn:dem":638,
    "gn:feature_class":"P",
    "gn:feature_code":"PPL",
    "gn:name":"Ch\u014fngs\u016dng-gol",
    "gn:population":0,
    "gn:timezone":"Asia/Seoul",
    "iso:country":"KR",
    "name:kor_x_preferred":[
        "\uc815\uc2b9\uace8"
    ],
    "name:kor_x_variant":[
        "Ch\u014fngs\u016dng-gol"
    ],
    "wof:name":"Chongsung-gol",
    "wof:placetype":"locality"
},
  "geometry": {"coordinates":[128.85220000000001,37.2879],"type":"Point"}
}