{
  "type": "Feature",
  "properties": {
    "gn:admin1_code":"6.0",
    "gn:asciiname":"Hwajeolli",
    "gn:country_code":"KR",
    "gn:dem":237,
    "gn:feature_class":"P",
    "gn:feature_code":"PPL",
    "gn:name":"Hwajeolli",
    "gn:population":0,
    "gn:timezone":"Asia/Seoul",
    "iso:country":"KR",
    "name:kor_x_preferred":[
        "\ud654\uc804\ub9ac"
    ],
    "wof:name":"Hwajeolli",
    "wof:placetype":"locality"
},
  "geometry": {"coordinates":[127.20528,38.2428],"type":"Point"}
}