{
  "type": "Feature",
  "properties": {
    "gn:admin1_code":"16.0",
    "gn:asciiname":"Sansangak",
    "gn:country_code":"KR",
    "gn:dem":62,
    "gn:feature_class":"P",
    "gn:feature_code":"PPL",
    "gn:name":"Sansangak",
    "gn:population":0,
    "gn:timezone":"Asia/Seoul",
    "iso:country":"KR",
    "name:kor_x_preferred":[
        "\uc0b0\uc0b0\uac01"
    ],
    "wof:name":"Sansangak",
    "wof:placetype":"locality"
},
  "geometry": {"coordinates":[126.93235,35.03265],"type":"Point"}
}