{
  "type": "Feature",
  "properties": {
    "gn:admin1_code":"16.0",
    "gn:asciiname":"Sinun",
    "gn:country_code":"KR",
    "gn:dem":77,
    "gn:feature_class":"P",
    "gn:feature_code":"PPL",
    "gn:name":"Sinun",
    "gn:population":0,
    "gn:timezone":"Asia/Seoul",
    "iso:country":"KR",
    "name:ara_x_preferred":[
        "\u0633\u0646\u0648\u0646\u064a"
    ],
    "name:deu_x_preferred":[
        "Sinun"
    ],
    "name:kor_x_preferred":[
        "\uc2e0\uc6b4"
    ],
    "wof:name":"Sinun",
    "wof:placetype":"locality"
},
  "geometry": {"coordinates":[127.021,35.02579],"type":"Point"}
}