{
  "type": "Feature",
  "properties": {
    "gn:admin1_code":"20.0",
    "gn:asciiname":"Nosan",
    "gn:country_code":"KR",
    "gn:dem":9,
    "gn:feature_class":"P",
    "gn:feature_code":"PPL",
    "gn:name":"Nosan",
    "gn:population":0,
    "gn:timezone":"Asia/Seoul",
    "iso:country":"KR",
    "name:und_x_variant":[
        "Nosan-ni",
        "Nosan-ri",
        "\ub178\uc0b0",
        "Nosal-li",
        "Nosan"
    ],
    "wof:name":"Nosan",
    "wof:placetype":"locality"
},
  "geometry": {"coordinates":[128.40811000000002,34.89952],"type":"Point"}
}