{
  "type": "Feature",
  "properties": {
    "gn:admin1_code":"13.0",
    "gn:asciiname":"Kurumnae",
    "gn:country_code":"KR",
    "gn:dem":25,
    "gn:feature_class":"P",
    "gn:feature_code":"PPL",
    "gn:name":"Kur\u016dmnae",
    "gn:population":0,
    "gn:timezone":"Asia/Seoul",
    "iso:country":"KR",
    "name:kor_x_preferred":[
        "\uad6c\ub984\ub0b4"
    ],
    "name:kor_x_variant":[
        "Kur\u016dmnae"
    ],
    "wof:name":"Kurumnae",
    "wof:placetype":"locality"
},
  "geometry": {"coordinates":[126.69222000000001,37.19222],"type":"Point"}
}