{
  "type": "Feature",
  "properties": {
    "gn:admin1_code":"20.0",
    "gn:asciiname":"Kapsan",
    "gn:country_code":"KR",
    "gn:dem":31,
    "gn:feature_class":"P",
    "gn:feature_code":"PPL",
    "gn:name":"Kapsan",
    "gn:population":0,
    "gn:timezone":"Asia/Seoul",
    "iso:country":"KR",
    "name:und_x_variant":[
        "\uac11\uc0b0",
        "Kapsan"
    ],
    "wof:name":"Kapsan",
    "wof:placetype":"locality"
},
  "geometry": {"coordinates":[128.24578,35.59039],"type":"Point"}
}