{
  "type": "Feature",
  "properties": {
    "gn:admin1_code":"13.0",
    "gn:asciiname":"Maenggol",
    "gn:country_code":"KR",
    "gn:dem":109,
    "gn:feature_class":"P",
    "gn:feature_code":"PPL",
    "gn:name":"Maenggol",
    "gn:population":0,
    "gn:timezone":"Asia/Seoul",
    "iso:country":"KR",
    "name:kor_x_preferred":[
        "\ub9f9\uace8"
    ],
    "name:und_x_variant":[
        "\ub9f9\uace8",
        "Maenggol"
    ],
    "wof:name":"Maenggol",
    "wof:placetype":"locality"
},
  "geometry": {"coordinates":[127.3057,37.6197],"type":"Point"}
}