{
  "type": "Feature",
  "properties": {
    "iso:country":"KR",
    "name:eng_x_preferred":[
        "Milyang-si"
    ],
    "name:kor_x_preferred":[
        "\ubc00\uc591\uc2dc"
    ],
    "qs:name":"\ubc00\uc591\uc2dc",
    "qs:name_adm0":"\ud55c\uad6d",
    "qs:name_adm1":"\uacbd\uc0c1\ub0a8\ub3c4",
    "qs:photos":83,
    "qs:photos_1k":17,
    "qs:photos_9k":1,
    "qs:photos_9r":3,
    "qs:photos_all":83,
    "qs:photos_sr":3,
    "qs:placetype":"Town",
    "qs:pop_sr":"0",
    "wof:name":"Milyang-si",
    "wof:placetype":"locality"
},
  "geometry": {"coordinates":[128.764228,35.488629],"type":"Point"}
}