{
  "type": "Feature",
  "properties": {
    "gn:admin1_code":"3.0",
    "gn:asciiname":"Ch'ango-ri",
    "gn:country_code":"KR",
    "gn:dem":14,
    "gn:feature_class":"P",
    "gn:feature_code":"PPL",
    "gn:name":"Ch\u2019ango-ri",
    "gn:population":0,
    "gn:timezone":"Asia/Seoul",
    "iso:country":"KR",
    "name:und_x_variant":[
        "Ch\u2019ango",
        "Ch\u2019ango-ri"
    ],
    "wof:name":"Ch'ango-ri",
    "wof:placetype":"locality"
},
  "geometry": {"coordinates":[126.81833,35.98722],"type":"Point"}
}