{
  "type": "Feature",
  "properties": {
    "gn:admin1_code":"17.0",
    "gn:asciiname":"Yongdam-ni",
    "gn:country_code":"KR",
    "gn:dem":47,
    "gn:feature_class":"P",
    "gn:feature_code":"PPL",
    "gn:name":"Yongdam-ni",
    "gn:population":0,
    "gn:timezone":"Asia/Seoul",
    "iso:country":"KR",
    "name:eng_x_preferred":[
        "Yongdam"
    ],
    "name:eng_x_variant":[
        "Yongdam-ni"
    ],
    "wof:name":"Yongdam",
    "wof:placetype":"locality"
},
  "geometry": {"coordinates":[127.28417,36.4225],"type":"Point"}
}