{
  "type": "Feature",
  "properties": {
    "gn:admin1_code":"14.0",
    "gn:asciiname":"Nagye",
    "gn:country_code":"KR",
    "gn:dem":4,
    "gn:feature_class":"P",
    "gn:feature_code":"PPL",
    "gn:name":"Nagye",
    "gn:population":0,
    "gn:timezone":"Asia/Seoul",
    "iso:country":"KR",
    "name:kor_x_preferred":[
        "\ub098\uacc4"
    ],
    "wof:name":"Nagye",
    "wof:placetype":"locality"
},
  "geometry": {"coordinates":[129.37101999999999,36.20748],"type":"Point"}
}