{
  "type": "Feature",
  "properties": {
    "gn:admin1_code":"6.0",
    "gn:asciiname":"Madal-tong",
    "gn:country_code":"KR",
    "gn:dem":74,
    "gn:feature_class":"P",
    "gn:feature_code":"PPL",
    "gn:name":"Madal-tong",
    "gn:population":0,
    "gn:timezone":"Asia/Seoul",
    "iso:country":"KR",
    "name:und_x_variant":[
        "\ub9c8\ub2ec\ub3d9",
        "Madal-tong"
    ],
    "wof:name":"Madal-tong",
    "wof:placetype":"locality"
},
  "geometry": {"coordinates":[129.15369999999999,37.453],"type":"Point"}
}