{
  "type": "Feature",
  "properties": {
    "gn:admin1_code":"17.0",
    "gn:asciiname":"Changdae-ri",
    "gn:country_code":"KR",
    "gn:dem":66,
    "gn:feature_class":"P",
    "gn:feature_code":"PPLL",
    "gn:name":"Changdae-ri",
    "gn:population":0,
    "gn:timezone":"Asia/Seoul",
    "iso:country":"KR",
    "name:und_x_variant":[
        "\uc7a5\ub300\ub9ac",
        "Changdaemun",
        "Changdae-ri"
    ],
    "wof:name":"Changdae-ri",
    "wof:placetype":"locality"
},
  "geometry": {"coordinates":[126.2406,36.784],"type":"Point"}
}