{
  "type": "Feature",
  "properties": {
    "gn:admin1_code":"6.0",
    "gn:asciiname":"Yugok",
    "gn:country_code":"KR",
    "gn:dem":208,
    "gn:feature_class":"P",
    "gn:feature_code":"PPL",
    "gn:name":"Yugok",
    "gn:population":0,
    "gn:timezone":"Asia/Seoul",
    "iso:country":"KR",
    "name:und_x_variant":[
        "\uc720\uace1",
        "Yugok"
    ],
    "wof:name":"Yugok",
    "wof:placetype":"locality"
},
  "geometry": {"coordinates":[129.0986,37.3336],"type":"Point"}
}