{
  "type": "Feature",
  "properties": {
    "gn:admin1_code":"5.0",
    "gn:asciiname":"Motpat",
    "gn:country_code":"KR",
    "gn:dem":255,
    "gn:feature_class":"P",
    "gn:feature_code":"PPL",
    "gn:name":"Motpat",
    "gn:population":0,
    "gn:timezone":"Asia/Seoul",
    "iso:country":"KR",
    "name:kor_x_preferred":[
        "\ubabb\ubc2d"
    ],
    "name:und_x_variant":[
        "Moppat",
        "Motpat"
    ],
    "wof:name":"Motpat",
    "wof:placetype":"locality"
},
  "geometry": {"coordinates":[128.35897,37.02505],"type":"Point"}
}