{
  "type": "Feature",
  "properties": {
    "gn:admin1_code":"16.0",
    "gn:asciiname":"Senchi",
    "gn:country_code":"KR",
    "gn:dem":16,
    "gn:feature_class":"P",
    "gn:feature_code":"PPL",
    "gn:name":"Senchi",
    "gn:population":0,
    "gn:timezone":"Asia/Seoul",
    "iso:country":"KR",
    "name:frr_x_preferred":[
        "Senchi"
    ],
    "name:und_x_variant":[
        "S\u014fmji",
        "Ch\u016dng\u016di",
        "Ch\u016dng\u016di-ri"
    ],
    "wof:name":"Senchi",
    "wof:placetype":"locality"
},
  "geometry": {"coordinates":[126.45361,34.52583],"type":"Point"}
}