{
  "type": "Feature",
  "properties": {
    "gn:admin1_code":"6.0",
    "gn:asciiname":"Doeumdeul",
    "gn:country_code":"KR",
    "gn:dem":126,
    "gn:feature_class":"P",
    "gn:feature_code":"PPL",
    "gn:name":"Doeumdeul",
    "gn:population":0,
    "gn:timezone":"Asia/Seoul",
    "iso:country":"KR",
    "name:kor_x_preferred":[
        "\ub3c4\uc74c\ub4e4"
    ],
    "name:kor_x_variant":[
        "To\u016dmd\u016dl"
    ],
    "wof:name":"Doeumdeul",
    "wof:placetype":"locality"
},
  "geometry": {"coordinates":[128.6566,37.9625],"type":"Point"}
}