{
  "type": "Feature",
  "properties": {
    "gn:admin1_code":"16.0",
    "gn:asciiname":"Taeru-gol",
    "gn:country_code":"KR",
    "gn:dem":54,
    "gn:feature_class":"P",
    "gn:feature_code":"PPL",
    "gn:name":"Taeru-gol",
    "gn:population":0,
    "gn:timezone":"Asia/Seoul",
    "iso:country":"KR",
    "name:kor_x_preferred":[
        "\ub300\ub8e8\uace8"
    ],
    "wof:name":"Taeru-gol",
    "wof:placetype":"locality"
},
  "geometry": {"coordinates":[127.0025,34.64053],"type":"Point"}
}