{
  "type": "Feature",
  "properties": {
    "gn:admin1_code":"17.0",
    "gn:asciiname":"Yeongbangchuk",
    "gn:country_code":"KR",
    "gn:dem":19,
    "gn:feature_class":"P",
    "gn:feature_code":"PPL",
    "gn:name":"Yeongbangchuk",
    "gn:population":0,
    "gn:timezone":"Asia/Seoul",
    "iso:country":"KR",
    "name:und_x_variant":[
        "\uc601\ubc29\ucd95",
        "Yeongbangchuk",
        "Y\u014fngbangch\u2019uk"
    ],
    "wof:name":"Yeongbangchuk",
    "wof:placetype":"locality"
},
  "geometry": {"coordinates":[126.55417,37.02833],"type":"Point"}
}