{
  "type": "Feature",
  "properties": {
    "gn:admin1_code":"6.0",
    "gn:asciiname":"Kol-mal",
    "gn:country_code":"KR",
    "gn:dem":1074,
    "gn:feature_class":"P",
    "gn:feature_code":"PPL",
    "gn:name":"Kol-mal",
    "gn:population":0,
    "gn:timezone":"Asia/Seoul",
    "iso:country":"KR",
    "name:kor_x_preferred":[
        "\uace8\ub9d0"
    ],
    "wof:name":"Kol-mal",
    "wof:placetype":"locality"
},
  "geometry": {"coordinates":[128.81229999999999,37.1922],"type":"Point"}
}