{
  "type": "Feature",
  "properties": {
    "gn:admin1_code":"5.0",
    "gn:asciiname":"Gosireumteo",
    "gn:country_code":"KR",
    "gn:dem":79,
    "gn:feature_class":"P",
    "gn:feature_code":"PPL",
    "gn:name":"Gosireumteo",
    "gn:population":0,
    "gn:timezone":"Asia/Seoul",
    "iso:country":"KR",
    "name:kor_x_preferred":[
        "\uace0\uc2dc\ub984\ud130"
    ],
    "wof:name":"Gosireumteo",
    "wof:placetype":"locality"
},
  "geometry": {"coordinates":[127.53273,36.71607],"type":"Point"}
}