{
  "type": "Feature",
  "properties": {
    "gn:admin1_code":"16.0",
    "gn:asciiname":"Hodeok",
    "gn:country_code":"KR",
    "gn:dem":11,
    "gn:feature_class":"P",
    "gn:feature_code":"PPL",
    "gn:name":"Hodeok",
    "gn:population":0,
    "gn:timezone":"Asia/Seoul",
    "iso:country":"KR",
    "name:kor_x_preferred":[
        "\ud638\ub355"
    ],
    "name:kor_x_variant":[
        "Hod\u014fk"
    ],
    "name:und_x_variant":[
        "Hod\u014fng-ni",
        "Hodeok"
    ],
    "wof:name":"Hodeok",
    "wof:placetype":"locality"
},
  "geometry": {"coordinates":[127.39036000000002,34.68716],"type":"Point"}
}