{
  "type": "Feature",
  "properties": {
    "gn:admin1_code":"0.0",
    "gn:asciiname":"Hangdodong",
    "gn:country_code":"KR",
    "gn:dem":46,
    "gn:feature_class":"P",
    "gn:feature_code":"PPL",
    "gn:name":"Hangdodong",
    "gn:population":0,
    "gn:timezone":"Asia/Seoul",
    "iso:country":"KR",
    "name:kor_x_preferred":[
        "\ud56d\ub3c4\ub3d9"
    ],
    "name:und_x_variant":[
        "Moks\u014fm-dong",
        "Hangdo-dong",
        "Hangdodong"
    ],
    "wof:name":"Hangdodong",
    "wof:placetype":"locality"
},
  "geometry": {"coordinates":[127.01018999999999,34.3259],"type":"Point"}
}