{
  "type": "Feature",
  "properties": {
    "gn:admin1_code":"13.0",
    "gn:asciiname":"Malgaemi",
    "gn:country_code":"KR",
    "gn:dem":90,
    "gn:feature_class":"P",
    "gn:feature_code":"PPL",
    "gn:name":"Malgaemi",
    "gn:population":0,
    "gn:timezone":"Asia/Seoul",
    "iso:country":"KR",
    "name:und_x_variant":[
        "\ub9d0\uac1c\ubbf8",
        "Malgaemi"
    ],
    "wof:name":"Malgaemi",
    "wof:placetype":"locality"
},
  "geometry": {"coordinates":[127.71693999999999,37.29444],"type":"Point"}
}