{
  "type": "Feature",
  "properties": {
    "gn:admin1_code":"17.0",
    "gn:asciiname":"Hach'o",
    "gn:country_code":"KR",
    "gn:dem":9,
    "gn:feature_class":"P",
    "gn:feature_code":"PPL",
    "gn:name":"Hach\u2019o",
    "gn:population":0,
    "gn:timezone":"Asia/Seoul",
    "iso:country":"KR",
    "name:und_x_variant":[
        "\ud558\ucd08",
        "Hach\u2019o"
    ],
    "wof:name":"Hach'o",
    "wof:placetype":"locality"
},
  "geometry": {"coordinates":[126.7516,36.9018],"type":"Point"}
}