{
  "type": "Feature",
  "properties": {
    "gn:admin1_code":"20.0",
    "gn:asciiname":"Palsan",
    "gn:country_code":"KR",
    "gn:dem":50,
    "gn:feature_class":"P",
    "gn:feature_code":"PPL",
    "gn:name":"Palsan",
    "gn:population":0,
    "gn:timezone":"Asia/Seoul",
    "iso:country":"KR",
    "name:und_x_variant":[
        "\ubc1c\uc0b0",
        "Palsan"
    ],
    "wof:name":"Palsan",
    "wof:placetype":"locality"
},
  "geometry": {"coordinates":[128.31968999999998,35.06536],"type":"Point"}
}