{
  "type": "Feature",
  "properties": {
    "gn:admin1_code":"6.0",
    "gn:asciiname":"Jungganmal",
    "gn:country_code":"KR",
    "gn:dem":246,
    "gn:feature_class":"P",
    "gn:feature_code":"PPL",
    "gn:name":"Jungganmal",
    "gn:population":0,
    "gn:timezone":"Asia/Seoul",
    "iso:country":"KR",
    "name:kor_x_preferred":[
        "\uc911\uac04\ub9d0"
    ],
    "name:und_x_variant":[
        "Chungganch\u2019on",
        "Chungganmal",
        "Jungganmal"
    ],
    "wof:name":"Jungganmal",
    "wof:placetype":"locality"
},
  "geometry": {"coordinates":[127.9161,38.18631],"type":"Point"}
}