{
  "type": "Feature",
  "properties": {
    "gn:admin1_code":"14.0",
    "gn:asciiname":"Sunho",
    "gn:country_code":"KR",
    "gn:dem":135,
    "gn:feature_class":"P",
    "gn:feature_code":"PPL",
    "gn:name":"Sunho",
    "gn:population":0,
    "gn:timezone":"Asia/Seoul",
    "iso:country":"KR",
    "wof:name":"Sunho",
    "wof:placetype":"locality"
},
  "geometry": {"coordinates":[128.72943999999998,36.21194000000001],"type":"Point"}
}