{
  "type": "Feature",
  "properties": {
    "gn:admin1_code":"17.0",
    "gn:asciiname":"Tonghae-ri",
    "gn:country_code":"KR",
    "gn:dem":305,
    "gn:feature_class":"P",
    "gn:feature_code":"PPL",
    "gn:name":"Tonghae-ri",
    "gn:population":0,
    "gn:timezone":"Asia/Seoul",
    "iso:country":"KR",
    "wof:name":"Tonghae-ri",
    "wof:placetype":"locality"
},
  "geometry": {"coordinates":[127.02056,36.61278],"type":"Point"}
}