{
  "type": "Feature",
  "properties": {
    "gn:admin1_code":"20.0",
    "gn:asciiname":"Sibi-ri",
    "gn:country_code":"KR",
    "gn:dem":49,
    "gn:feature_class":"P",
    "gn:feature_code":"PPL",
    "gn:name":"Sibi-ri",
    "gn:population":0,
    "gn:timezone":"Asia/Seoul",
    "iso:country":"KR",
    "name:und_x_variant":[
        "\uc2ed\uc774\ub9ac",
        "Sibi-ri"
    ],
    "wof:name":"Sibi-ri",
    "wof:placetype":"locality"
},
  "geometry": {"coordinates":[128.47283000000002,35.6146],"type":"Point"}
}