{
  "type": "Feature",
  "properties": {
    "gn:admin1_code":"6.0",
    "gn:asciiname":"Yongsugol",
    "gn:country_code":"KR",
    "gn:dem":518,
    "gn:feature_class":"P",
    "gn:feature_code":"PPL",
    "gn:name":"Yongsugol",
    "gn:population":0,
    "gn:timezone":"Asia/Seoul",
    "iso:country":"KR",
    "name:und_x_variant":[
        "\uc6a9\uc218\uace8"
    ],
    "wof:name":"Yongsugol",
    "wof:placetype":"locality"
},
  "geometry": {"coordinates":[128.11141000000001,38.15831],"type":"Point"}
}