{
  "type": "Feature",
  "properties": {
    "gn:admin1_code":"13.0",
    "gn:asciiname":"Taebonggol",
    "gn:country_code":"KR",
    "gn:dem":149,
    "gn:feature_class":"P",
    "gn:feature_code":"PPL",
    "gn:name":"Taebonggol",
    "gn:population":0,
    "gn:timezone":"Asia/Seoul",
    "iso:country":"KR",
    "name:kor_x_preferred":[
        "\ud0dc\ubd09\uace8"
    ],
    "name:kor_x_variant":[
        "T\u2019aebong-gol"
    ],
    "wof:name":"Taebonggol",
    "wof:placetype":"locality"
},
  "geometry": {"coordinates":[127.33602999999999,37.80434],"type":"Point"}
}