{
  "type": "Feature",
  "properties": {
    "gn:admin1_code":"14.0",
    "gn:asciiname":"Hwangcheongni",
    "gn:country_code":"KR",
    "gn:dem":317,
    "gn:feature_class":"P",
    "gn:feature_code":"PPL",
    "gn:name":"Hwangcheongni",
    "gn:population":0,
    "gn:timezone":"Asia/Seoul",
    "iso:country":"KR",
    "name:kor_x_preferred":[
        "\ud669\uccad\ub9ac"
    ],
    "wof:name":"Hwangcheongni",
    "wof:placetype":"locality"
},
  "geometry": {"coordinates":[128.65371999999999,36.04601],"type":"Point"}
}