{
  "type": "Feature",
  "properties": {
    "gn:admin1_code":"13.0",
    "gn:admin2_code":"P'aju-si",
    "gn:asciiname":"Soepari",
    "gn:country_code":"KR",
    "gn:dem":37,
    "gn:feature_class":"P",
    "gn:feature_code":"PPL",
    "gn:name":"Soepari",
    "gn:population":0,
    "gn:timezone":"Asia/Seoul",
    "iso:country":"KR",
    "name:kor_x_preferred":[
        "\uc1e0\ud30c\ub9ac"
    ],
    "name:kor_x_variant":[
        "Soep\u2019ari"
    ],
    "wof:name":"Soepari",
    "wof:placetype":"locality"
},
  "geometry": {"coordinates":[126.75172000000001,37.82563],"type":"Point"}
}