{
  "type": "Feature",
  "properties": {
    "gn:admin1_code":"0.0",
    "gn:asciiname":"Hadae-ri",
    "gn:country_code":"KR",
    "gn:dem":5,
    "gn:feature_class":"P",
    "gn:feature_code":"PPL",
    "gn:name":"Hadae-ri",
    "gn:population":0,
    "gn:timezone":"Asia/Seoul",
    "iso:country":"KR",
    "name:kor_x_preferred":[
        "\ud558\ub300"
    ],
    "name:und_x_variant":[
        "Hadae",
        "Hadae-ri"
    ],
    "wof:name":"Hadae-ri",
    "wof:placetype":"locality"
},
  "geometry": {"coordinates":[126.43333,35.26667],"type":"Point"}
}