{
  "type": "Feature",
  "properties": {
    "gn:admin1_code":"13.0",
    "gn:asciiname":"Imaeil-tong",
    "gn:country_code":"KR",
    "gn:dem":73,
    "gn:feature_class":"P",
    "gn:feature_code":"PPL",
    "gn:name":"Imaeil-tong",
    "gn:population":0,
    "gn:timezone":"Asia/Seoul",
    "iso:country":"KR",
    "name:und_x_variant":[
        "\uc774\ub9e41\ub3d9",
        "Imaeil-dong",
        "Imaeil-tong"
    ],
    "wof:name":"Imaeil-tong",
    "wof:placetype":"locality"
},
  "geometry": {"coordinates":[127.13361,37.39556],"type":"Point"}
}