{
  "type": "Feature",
  "properties": {
    "gn:admin1_code":"6.0",
    "gn:asciiname":"Moteubak",
    "gn:country_code":"KR",
    "gn:dem":235,
    "gn:feature_class":"P",
    "gn:feature_code":"PPL",
    "gn:name":"Moteubak",
    "gn:population":0,
    "gn:timezone":"Asia/Seoul",
    "iso:country":"KR",
    "name:kor_x_preferred":[
        "\ubaa8\ub974\ubc15"
    ],
    "name:kor_x_variant":[
        "Mor\u016dbak",
        "\ubaa8\ud2b8\ubc15"
    ],
    "name:und_x_variant":[
        "Morumegi",
        "Molmegi",
        "Mor\u016dmak",
        "Moteubak"
    ],
    "wof:name":"Moteubak",
    "wof:placetype":"locality"
},
  "geometry": {"coordinates":[128.09951999999998,37.988],"type":"Point"}
}