{
  "type": "Feature",
  "properties": {
    "gn:admin1_code":"13.0",
    "gn:asciiname":"Sujakgol",
    "gn:country_code":"KR",
    "gn:dem":102,
    "gn:feature_class":"P",
    "gn:feature_code":"PPL",
    "gn:name":"Sujakgol",
    "gn:population":0,
    "gn:timezone":"Asia/Seoul",
    "iso:country":"KR",
    "name:und_x_variant":[
        "\uc218\uc791\uace8",
        "Sujak-kol",
        "Sujakgol"
    ],
    "wof:name":"Sujakgol",
    "wof:placetype":"locality"
},
  "geometry": {"coordinates":[126.90867,37.91503],"type":"Point"}
}