{
  "type": "Feature",
  "properties": {
    "gn:admin1_code":"13.0",
    "gn:asciiname":"Araeseongneup",
    "gn:country_code":"KR",
    "gn:dem":82,
    "gn:feature_class":"P",
    "gn:feature_code":"PPL",
    "gn:name":"Araeseongneup",
    "gn:population":0,
    "gn:timezone":"Asia/Seoul",
    "iso:country":"KR",
    "name:und_x_variant":[
        "\uc544\ub798\uc131\ub2aa",
        "Araeseongneup",
        "Araes\u014fngn\u016dp"
    ],
    "wof:name":"Araeseongneup",
    "wof:placetype":"locality"
},
  "geometry": {"coordinates":[127.65139000000001,37.26778],"type":"Point"}
}