{
  "type": "Feature",
  "properties": {
    "gn:admin1_code":"14.0",
    "gn:asciiname":"Myogok",
    "gn:country_code":"KR",
    "gn:dem":65,
    "gn:feature_class":"P",
    "gn:feature_code":"PPL",
    "gn:name":"Myogok",
    "gn:population":0,
    "gn:timezone":"Asia/Seoul",
    "iso:country":"KR",
    "name:und_x_variant":[
        "Myo-gol",
        "Myogok",
        "\ubb18\uace1"
    ],
    "wof:name":"Myogok",
    "wof:placetype":"locality"
},
  "geometry": {"coordinates":[128.3614,36.0745],"type":"Point"}
}