{
  "type": "Feature",
  "properties": {
    "gn:admin1_code":"16.0",
    "gn:asciiname":"Pidong-ni",
    "gn:country_code":"KR",
    "gn:dem":90,
    "gn:feature_class":"P",
    "gn:feature_code":"PPL",
    "gn:name":"Pidong-ni",
    "gn:population":0,
    "gn:timezone":"Asia/Seoul",
    "iso:country":"KR",
    "name:kor_x_preferred":[
        "\ube44\ub3d9\ub9ac"
    ],
    "name:und_x_variant":[
        "Pidongni-igu",
        "Pidong-ni"
    ],
    "wof:name":"Pidong-ni",
    "wof:placetype":"locality"
},
  "geometry": {"coordinates":[126.96250000000001,34.6725],"type":"Point"}
}