{
  "type": "Feature",
  "properties": {
    "gn:admin1_code":"5.0",
    "gn:asciiname":"Mantaedong",
    "gn:country_code":"KR",
    "gn:dem":156,
    "gn:feature_class":"P",
    "gn:feature_code":"PPL",
    "gn:name":"Mantaedong",
    "gn:population":0,
    "gn:timezone":"Asia/Seoul",
    "iso:country":"KR",
    "name:kor_x_preferred":[
        "\ub9cc\ud0dc\ub3d9"
    ],
    "name:kor_x_variant":[
        "Mant\u2019ae-dong"
    ],
    "wof:name":"Mantaedong",
    "wof:placetype":"locality"
},
  "geometry": {"coordinates":[127.63554999999999,37.03181],"type":"Point"}
}