{
  "type": "Feature",
  "properties": {
    "gn:admin1_code":"13.0",
    "gn:asciiname":"Dongmuteo",
    "gn:country_code":"KR",
    "gn:dem":88,
    "gn:feature_class":"P",
    "gn:feature_code":"PPL",
    "gn:name":"Dongmuteo",
    "gn:population":0,
    "gn:timezone":"Asia/Seoul",
    "iso:country":"KR",
    "name:kor_x_preferred":[
        "\ub3d9\ubb34\ud130"
    ],
    "name:und_x_variant":[
        "\ub4f1\ubb34\ub300",
        "T\u016dngmudae",
        "Dongmuteo"
    ],
    "wof:name":"Dongmuteo",
    "wof:placetype":"locality"
},
  "geometry": {"coordinates":[127.52302,37.87412],"type":"Point"}
}