{
  "type": "Feature",
  "properties": {
    "gn:admin1_code":"17.0",
    "gn:asciiname":"Kwonjaebol",
    "gn:country_code":"KR",
    "gn:dem":32,
    "gn:feature_class":"P",
    "gn:feature_code":"PPL",
    "gn:name":"Kw\u014fnjaeb\u014fl",
    "gn:population":0,
    "gn:timezone":"Asia/Seoul",
    "iso:country":"KR",
    "name:und_x_variant":[
        "\uad8c\uc7ac\ubc8c",
        "Kw\u014fnjaeb\u014fl"
    ],
    "wof:name":"Kwonjaebol",
    "wof:placetype":"locality"
},
  "geometry": {"coordinates":[126.4354,36.8592],"type":"Point"}
}