{
  "type": "Feature",
  "properties": {
    "gn:admin1_code":"12.0",
    "gn:asciiname":"Motungmal",
    "gn:country_code":"KR",
    "gn:dem":83,
    "gn:feature_class":"P",
    "gn:feature_code":"PPL",
    "gn:name":"Motungmal",
    "gn:population":0,
    "gn:timezone":"Asia/Seoul",
    "iso:country":"KR",
    "name:kor_x_preferred":[
        "\ubaa8\ud241\ub9d0"
    ],
    "wof:name":"Motungmal",
    "wof:placetype":"locality"
},
  "geometry": {"coordinates":[126.67948,37.53587],"type":"Point"}
}