{
  "type": "Feature",
  "properties": {
    "gn:admin1_code":"16.0",
    "gn:asciiname":"Banwol",
    "gn:country_code":"KR",
    "gn:dem":33,
    "gn:feature_class":"P",
    "gn:feature_code":"PPL",
    "gn:name":"Banwol",
    "gn:population":0,
    "gn:timezone":"Asia/Seoul",
    "iso:country":"KR",
    "name:kor_x_preferred":[
        "\ubc18\uc6d4"
    ],
    "wof:name":"Banwol",
    "wof:placetype":"locality"
},
  "geometry": {"coordinates":[126.73508,34.9316],"type":"Point"}
}