{
  "type": "Feature",
  "properties": {
    "gn:admin1_code":"20.0",
    "gn:asciiname":"Nammyong-ni",
    "gn:cc2":"KR",
    "gn:country_code":"KR",
    "gn:dem":455,
    "gn:feature_class":"P",
    "gn:feature_code":"PPL",
    "gn:name":"Nammy\u014fng-ni",
    "gn:population":0,
    "gn:timezone":"Asia/Seoul",
    "iso:country":"KR",
    "name:und_x_variant":[
        "Nammy\u014fng-dong",
        "Nammy\u014fng-ni"
    ],
    "wof:name":"Nammyong-ni",
    "wof:placetype":"locality"
},
  "geometry": {"coordinates":[128.94278,35.58389000000001],"type":"Point"}
}