{
  "type": "Feature",
  "properties": {
    "gn:admin1_code":"14.0",
    "gn:asciiname":"Kongsok",
    "gn:country_code":"KR",
    "gn:dem":30,
    "gn:feature_class":"P",
    "gn:feature_code":"PPL",
    "gn:name":"Kongs\u014fk",
    "gn:population":0,
    "gn:timezone":"Asia/Seoul",
    "iso:country":"KR",
    "name:und_x_variant":[
        "\uacf5\uc11d",
        "Kongs\u014fk"
    ],
    "wof:name":"Kongsok",
    "wof:placetype":"locality"
},
  "geometry": {"coordinates":[129.4102,36.9855],"type":"Point"}
}