{
  "type": "Feature",
  "properties": {
    "gn:admin1_code":"6.0",
    "gn:asciiname":"Saburang",
    "gn:country_code":"KR",
    "gn:dem":783,
    "gn:feature_class":"P",
    "gn:feature_code":"PPL",
    "gn:name":"Saburang",
    "gn:population":0,
    "gn:timezone":"Asia/Seoul",
    "iso:country":"KR",
    "name:kor_x_preferred":[
        "\uc0ac\ubd80\ub791"
    ],
    "wof:name":"Saburang",
    "wof:placetype":"locality"
},
  "geometry": {"coordinates":[128.82910000000001,37.2483],"type":"Point"}
}