{
  "type": "Feature",
  "properties": {
    "gn:admin1_code":"3.0",
    "gn:asciiname":"Kumak-tong",
    "gn:country_code":"KR",
    "gn:dem":237,
    "gn:feature_class":"P",
    "gn:feature_code":"PPL",
    "gn:name":"Kumak-tong",
    "gn:population":0,
    "gn:timezone":"Asia/Seoul",
    "iso:country":"KR",
    "name:und_x_variant":[
        "\uad6c\ub9c9\ub3d9",
        "Kumak-tong"
    ],
    "wof:name":"Kumak-tong",
    "wof:placetype":"locality"
},
  "geometry": {"coordinates":[127.28694,35.70382],"type":"Point"}
}