{
  "type": "Feature",
  "properties": {
    "gn:admin1_code":"16.0",
    "gn:asciiname":"Georyong",
    "gn:country_code":"KR",
    "gn:dem":13,
    "gn:feature_class":"P",
    "gn:feature_code":"PPL",
    "gn:name":"Georyong",
    "gn:population":0,
    "gn:timezone":"Asia/Seoul",
    "iso:country":"KR",
    "name:kor_x_preferred":[
        "\uac70\ub8e1"
    ],
    "name:und_x_variant":[
        "Komnyongch\u2019on",
        "K\u014fryongch\u2019on",
        "Georyong"
    ],
    "wof:name":"Georyong",
    "wof:placetype":"locality"
},
  "geometry": {"coordinates":[126.33808000000001,34.85028],"type":"Point"}
}