{
  "type": "Feature",
  "properties": {
    "gn:admin1_code":"11.0",
    "gn:asciiname":"Sillim 11-dong",
    "gn:country_code":"KR",
    "gn:dem":58,
    "gn:feature_class":"P",
    "gn:feature_code":"PPL",
    "gn:name":"Sillim 11-dong",
    "gn:population":0,
    "gn:timezone":"Asia/Seoul",
    "iso:country":"KR",
    "name:eng_x_preferred":[
        "Sillim 11-dong"
    ],
    "name:eng_x_variant":[
        "Sillim 11(sibil)-dong"
    ],
    "name:kor_x_preferred":[
        "\uc2e0\ub9bc11\ub3d9"
    ],
    "wof:name":"Sillim 11-dong",
    "wof:placetype":"locality"
},
  "geometry": {"coordinates":[126.91849999999999,37.4797],"type":"Point"}
}