{
  "type": "Feature",
  "properties": {
    "gn:admin1_code":"6.0",
    "gn:asciiname":"Sangch'uktok",
    "gn:country_code":"KR",
    "gn:dem":859,
    "gn:feature_class":"P",
    "gn:feature_code":"PPL",
    "gn:name":"Sangch\u2019ukt\u014fk",
    "gn:population":0,
    "gn:timezone":"Asia/Seoul",
    "iso:country":"KR",
    "name:kor_x_preferred":[
        "\uc0c1\ucd95\ub355"
    ],
    "name:kor_x_variant":[
        "Sangch\u2019ukt\u014fk"
    ],
    "wof:name":"Sangch'uktok",
    "wof:placetype":"locality"
},
  "geometry": {"coordinates":[128.3048,37.5282],"type":"Point"}
}