{
  "type": "Feature",
  "properties": {
    "gn:admin1_code":"20.0",
    "gn:asciiname":"Myoraedung",
    "gn:country_code":"KR",
    "gn:dem":5,
    "gn:feature_class":"P",
    "gn:feature_code":"PPL",
    "gn:name":"Myoraed\u016dng",
    "gn:population":0,
    "gn:timezone":"Asia/Seoul",
    "iso:country":"KR",
    "name:und_x_variant":[
        "Sad\u016dng-ni",
        "\ubaa8\ub7ab\ub4f1",
        "Myoraed\u016dng"
    ],
    "wof:name":"Myoraedung",
    "wof:placetype":"locality"
},
  "geometry": {"coordinates":[128.12256000000002,34.92296],"type":"Point"}
}