{
  "type": "Feature",
  "properties": {
    "gn:admin1_code":"17.0",
    "gn:asciiname":"Angol",
    "gn:country_code":"KR",
    "gn:dem":47,
    "gn:feature_class":"P",
    "gn:feature_code":"PPL",
    "gn:name":"Angol",
    "gn:population":0,
    "gn:timezone":"Asia/Seoul",
    "iso:country":"KR",
    "name:und_x_variant":[
        "\uc548\uace8",
        "Angol"
    ],
    "wof:name":"Angol",
    "wof:placetype":"locality"
},
  "geometry": {"coordinates":[127.15513,36.26928],"type":"Point"}
}