{
  "type": "Feature",
  "properties": {
    "gn:admin1_code":"6.0",
    "gn:asciiname":"Tongmae",
    "gn:country_code":"KR",
    "gn:dem":56,
    "gn:feature_class":"P",
    "gn:feature_code":"PPL",
    "gn:name":"Tongmae",
    "gn:population":0,
    "gn:timezone":"Asia/Seoul",
    "iso:country":"KR",
    "name:kor_x_preferred":[
        "\ud1b5\ub9e4"
    ],
    "wof:name":"Tongmae",
    "wof:placetype":"locality"
},
  "geometry": {"coordinates":[127.75064,37.23142],"type":"Point"}
}