{
  "type": "Feature",
  "properties": {
    "gn:admin1_code":"13.0",
    "gn:asciiname":"Poktae-ri",
    "gn:country_code":"KR",
    "gn:dem":46,
    "gn:feature_class":"P",
    "gn:feature_code":"PPLL",
    "gn:name":"Poktae-ri",
    "gn:population":0,
    "gn:timezone":"Asia/Seoul",
    "iso:country":"KR",
    "name:und_x_variant":[
        "\ubcf5\ub300\ub9ac",
        "Bokdae-ri",
        "Poktae-ri"
    ],
    "wof:name":"Poktae-ri",
    "wof:placetype":"locality"
},
  "geometry": {"coordinates":[127.53471999999999,37.35972],"type":"Point"}
}