{
  "type": "Feature",
  "properties": {
    "gn:admin1_code":"16.0",
    "gn:asciiname":"Kijom",
    "gn:cc2":"KR",
    "gn:country_code":"KR",
    "gn:dem":-9999,
    "gn:feature_class":"P",
    "gn:feature_code":"PPL",
    "gn:name":"Kij\u014fm",
    "gn:population":0,
    "gn:timezone":"Asia/Seoul",
    "iso:country":"KR",
    "name:und_x_variant":[
        "Kij\u014fm-ni",
        "Kij\u014fm"
    ],
    "wof:name":"Kijom",
    "wof:placetype":"locality"
},
  "geometry": {"coordinates":[126.21666999999999,34.95],"type":"Point"}
}