{
  "type": "Feature",
  "properties": {
    "gn:admin1_code":"6.0",
    "gn:asciiname":"Sangmun'gok",
    "gn:country_code":"KR",
    "gn:dem":645,
    "gn:feature_class":"P",
    "gn:feature_code":"PPL",
    "gn:name":"Sangmun\u2019gok",
    "gn:population":0,
    "gn:timezone":"Asia/Seoul",
    "iso:country":"KR",
    "name:kor_x_preferred":[
        "\uc0c1\ubb38\uace1"
    ],
    "name:kor_x_variant":[
        "Sangmun\u2019gok"
    ],
    "wof:name":"Sangmun'gok",
    "wof:placetype":"locality"
},
  "geometry": {"coordinates":[128.99590000000001,37.1248],"type":"Point"}
}