{
  "type": "Feature",
  "properties": {
    "gn:admin1_code":"13.0",
    "gn:asciiname":"Jeungil-dong",
    "gn:country_code":"KR",
    "gn:dem":98,
    "gn:feature_class":"P",
    "gn:feature_code":"PPLL",
    "gn:name":"Jeungil-dong",
    "gn:population":0,
    "gn:timezone":"Asia/Seoul",
    "iso:country":"KR",
    "name:und_x_variant":[
        "\uc99d\uc77c\ub3d9",
        "Jeungil-dong",
        "Ch\u016dngil-tong"
    ],
    "wof:name":"Jeungil-dong",
    "wof:placetype":"locality"
},
  "geometry": {"coordinates":[127.43028,37.26361],"type":"Point"}
}