{
  "type": "Feature",
  "properties": {
    "gn:admin1_code":"5.0",
    "gn:asciiname":"Samsandong",
    "gn:country_code":"KR",
    "gn:dem":348,
    "gn:feature_class":"P",
    "gn:feature_code":"PPL",
    "gn:name":"Samsandong",
    "gn:population":0,
    "gn:timezone":"Asia/Seoul",
    "iso:country":"KR",
    "name:kor_x_preferred":[
        "\uc0bc\uc0b0\ub3d9"
    ],
    "wof:name":"Samsandong",
    "wof:placetype":"locality"
},
  "geometry": {"coordinates":[128.32827,37.05639],"type":"Point"}
}