{
  "type": "Feature",
  "properties": {
    "gn:admin1_code":"11.0",
    "gn:asciiname":"Manguil-tong",
    "gn:country_code":"KR",
    "gn:dem":45,
    "gn:feature_class":"P",
    "gn:feature_code":"PPL",
    "gn:name":"Manguil-tong",
    "gn:population":0,
    "gn:timezone":"Asia/Seoul",
    "iso:country":"KR",
    "name:kor_x_preferred":[
        "\ub9dd\uc6b01\ub3d9"
    ],
    "name:und_x_variant":[
        "\ub9dd\uc6b01\ub3d9",
        "Manguil-tong"
    ],
    "wof:name":"Manguil-tong",
    "wof:placetype":"locality"
},
  "geometry": {"coordinates":[127.10921,37.60258],"type":"Point"}
}