{
  "type": "Feature",
  "properties": {
    "gn:admin1_code":"14.0",
    "gn:asciiname":"Godangsu",
    "gn:country_code":"KR",
    "gn:dem":76,
    "gn:feature_class":"P",
    "gn:feature_code":"PPL",
    "gn:name":"Godangsu",
    "gn:population":0,
    "gn:timezone":"Asia/Seoul",
    "iso:country":"KR",
    "name:kor_x_preferred":[
        "\uace0\ub2f9\uc218"
    ],
    "wof:name":"Godangsu",
    "wof:placetype":"locality"
},
  "geometry": {"coordinates":[129.17538000000002,35.74669],"type":"Point"}
}