{
  "type": "Feature",
  "properties": {
    "gn:admin1_code":"15.0",
    "gn:asciiname":"Jangsaemi",
    "gn:country_code":"KR",
    "gn:dem":35,
    "gn:feature_class":"P",
    "gn:feature_code":"PPL",
    "gn:name":"Jangsaemi",
    "gn:population":0,
    "gn:timezone":"Asia/Seoul",
    "iso:country":"KR",
    "name:und_x_variant":[
        "\uc7a5\uc0c8\ubbf8",
        "Changsaemi",
        "Jangsaemi"
    ],
    "wof:name":"Jangsaemi",
    "wof:placetype":"locality"
},
  "geometry": {"coordinates":[128.45723000000001,35.66512],"type":"Point"}
}