{
  "type": "Feature",
  "properties": {
    "gn:admin1_code":"20.0",
    "gn:asciiname":"Umch'on",
    "gn:country_code":"KR",
    "gn:dem":275,
    "gn:feature_class":"P",
    "gn:feature_code":"PPL",
    "gn:name":"\u016cmch\u2019\u014fn",
    "gn:population":0,
    "gn:timezone":"Asia/Seoul",
    "iso:country":"KR",
    "name:und_x_variant":[
        "\uc74c\ucc9c",
        "\u016cmch\u2019\u014fn"
    ],
    "wof:name":"Umch'on",
    "wof:placetype":"locality"
},
  "geometry": {"coordinates":[127.65237,35.52741],"type":"Point"}
}