{
  "type": "Feature",
  "properties": {
    "gn:admin1_code":"14.0",
    "gn:asciiname":"Namsil",
    "gn:cc2":"KR",
    "gn:country_code":"KR",
    "gn:dem":374,
    "gn:feature_class":"P",
    "gn:feature_code":"PPL",
    "gn:name":"Namsil",
    "gn:population":0,
    "gn:timezone":"Asia/Seoul",
    "iso:country":"KR",
    "name:und_x_variant":[
        "Namgok",
        "Namsil",
        "\ub0a8\uc2e4"
    ],
    "wof:name":"Namsil",
    "wof:placetype":"locality"
},
  "geometry": {"coordinates":[128.0325,36.27389],"type":"Point"}
}