{
  "type": "Feature",
  "properties": {
    "gn:admin1_code":"13.0",
    "gn:asciiname":"Georeun-ri",
    "gn:country_code":"KR",
    "gn:dem":71,
    "gn:feature_class":"P",
    "gn:feature_code":"PPLL",
    "gn:name":"Georeun-ri",
    "gn:population":0,
    "gn:timezone":"Asia/Seoul",
    "iso:country":"KR",
    "name:und_x_variant":[
        "K\u014fr\u016dn-ni",
        "\uac78\uc740\ub9ac",
        "Georeun-ri",
        "K\u014fr\u016dl-li"
    ],
    "wof:name":"Georeun-ri",
    "wof:placetype":"locality"
},
  "geometry": {"coordinates":[127.70139,37.29833],"type":"Point"}
}