{
  "type": "Feature",
  "properties": {
    "gn:admin1_code":"14.0",
    "gn:asciiname":"Jeolgol",
    "gn:country_code":"KR",
    "gn:dem":242,
    "gn:feature_class":"P",
    "gn:feature_code":"PPL",
    "gn:name":"Jeolgol",
    "gn:population":0,
    "gn:timezone":"Asia/Seoul",
    "iso:country":"KR",
    "name:kor_x_preferred":[
        "\uc808\uace8"
    ],
    "wof:name":"Jeolgol",
    "wof:placetype":"locality"
},
  "geometry": {"coordinates":[128.77748,35.70828],"type":"Point"}
}