{
  "type": "Feature",
  "properties": {
    "gn:admin1_code":"13.0",
    "gn:asciiname":"Channaebeol",
    "gn:country_code":"KR",
    "gn:dem":58,
    "gn:feature_class":"P",
    "gn:feature_code":"PPL",
    "gn:name":"Channaebeol",
    "gn:population":0,
    "gn:timezone":"Asia/Seoul",
    "iso:country":"KR",
    "name:kor_x_preferred":[
        "\ucc2c\ub0b4\ubc8c"
    ],
    "wof:name":"Channaebeol",
    "wof:placetype":"locality"
},
  "geometry": {"coordinates":[126.8852,37.80643],"type":"Point"}
}