{
  "type": "Feature",
  "properties": {
    "gn:admin1_code":"13.0",
    "gn:asciiname":"Dodangjae",
    "gn:country_code":"KR",
    "gn:dem":82,
    "gn:feature_class":"P",
    "gn:feature_code":"PPL",
    "gn:name":"Dodangjae",
    "gn:population":0,
    "gn:timezone":"Asia/Seoul",
    "iso:country":"KR",
    "name:kor_x_preferred":[
        "\ub3c4\ub2f9\uc7ac"
    ],
    "wof:name":"Dodangjae",
    "wof:placetype":"locality"
},
  "geometry": {"coordinates":[126.88997999999999,37.68718],"type":"Point"}
}