{
  "type": "Feature",
  "properties": {
    "gn:admin1_code":"6.0",
    "gn:asciiname":"Buheungchon",
    "gn:country_code":"KR",
    "gn:dem":236,
    "gn:feature_class":"P",
    "gn:feature_code":"PPL",
    "gn:name":"Buheungchon",
    "gn:population":0,
    "gn:timezone":"Asia/Seoul",
    "iso:country":"KR",
    "name:kor_x_preferred":[
        "\ubd80\ud765\ucd0c"
    ],
    "wof:name":"Buheungchon",
    "wof:placetype":"locality"
},
  "geometry": {"coordinates":[127.81185000000001,38.03525],"type":"Point"}
}