{
  "type": "Feature",
  "properties": {
    "gn:admin1_code":"14.0",
    "gn:asciiname":"Soran",
    "gn:country_code":"KR",
    "gn:dem":121,
    "gn:feature_class":"P",
    "gn:feature_code":"PPL",
    "gn:name":"Soran",
    "gn:population":0,
    "gn:timezone":"Asia/Seoul",
    "iso:country":"KR",
    "name:bul_x_preferred":[
        "\u0421\u043e\u0440\u0430\u043d"
    ],
    "name:ceb_x_preferred":[
        "Soran"
    ],
    "name:kur_x_preferred":[
        "Soran"
    ],
    "name:swe_x_preferred":[
        "Soran"
    ],
    "name:und_x_variant":[
        "\uc194\uc548"
    ],
    "wof:name":"Soran",
    "wof:placetype":"locality"
},
  "geometry": {"coordinates":[129.01051000000001,36.03415],"type":"Point"}
}