{
  "type": "Feature",
  "properties": {
    "gn:admin1_code":"14.0",
    "gn:asciiname":"Chongjit'o",
    "gn:country_code":"KR",
    "gn:dem":366,
    "gn:feature_class":"P",
    "gn:feature_code":"PPL",
    "gn:name":"Ch\u014fngjit\u2019\u014f",
    "gn:population":0,
    "gn:timezone":"Asia/Seoul",
    "iso:country":"KR",
    "name:und_x_variant":[
        "\uc815\uc9c0\ud130",
        "Ch\u014fngjit\u2019\u014f"
    ],
    "wof:name":"Chongjit'o",
    "wof:placetype":"locality"
},
  "geometry": {"coordinates":[129.17939999999999,36.5848],"type":"Point"}
}