{
  "type": "Feature",
  "properties": {
    "gn:admin1_code":"17.0",
    "gn:asciiname":"Soun",
    "gn:country_code":"KR",
    "gn:dem":53,
    "gn:feature_class":"P",
    "gn:feature_code":"PPL",
    "gn:name":"S\u014fun",
    "gn:population":0,
    "gn:timezone":"Asia/Seoul",
    "iso:country":"KR",
    "name:und_x_variant":[
        "S\u014fun-ni",
        "S\u014funae",
        "\uc11c\uc6b4",
        "S\u014fun"
    ],
    "wof:name":"Soun",
    "wof:placetype":"locality"
},
  "geometry": {"coordinates":[126.7794,36.2708],"type":"Point"}
}