{
  "type": "Feature",
  "properties": {
    "gn:admin1_code":"5.0",
    "gn:asciiname":"Umji-mal",
    "gn:country_code":"KR",
    "gn:dem":126,
    "gn:feature_class":"P",
    "gn:feature_code":"PPL",
    "gn:name":"\u016cmji-mal",
    "gn:population":0,
    "gn:timezone":"Asia/Seoul",
    "iso:country":"KR",
    "name:und_x_variant":[
        "\uc74c\uc9c0\ub9d0",
        "\u016cmji-mal"
    ],
    "wof:name":"Umji-mal",
    "wof:placetype":"locality"
},
  "geometry": {"coordinates":[127.78270000000001,36.3275],"type":"Point"}
}