{
  "type": "Feature",
  "properties": {
    "gn:admin1_code":"16.0",
    "gn:asciiname":"Wolchol-li",
    "gn:cc2":"KR",
    "gn:country_code":"KR",
    "gn:dem":41,
    "gn:feature_class":"P",
    "gn:feature_code":"PPL",
    "gn:name":"W\u014flch\u014fl-li",
    "gn:population":0,
    "gn:timezone":"Asia/Seoul",
    "iso:country":"KR",
    "name:und_x_variant":[
        "W\u014fnch\u2019\u014fn-dong",
        "W\u014fnch\u2019\u014fn",
        "W\u014flch\u014fl-li"
    ],
    "wof:name":"Wolchol-li",
    "wof:placetype":"locality"
},
  "geometry": {"coordinates":[127.48972000000001,35.19361],"type":"Point"}
}