{
  "type": "Feature",
  "properties": {
    "gn:admin1_code":"14.0",
    "gn:asciiname":"Saettom",
    "gn:country_code":"KR",
    "gn:dem":125,
    "gn:feature_class":"P",
    "gn:feature_code":"PPL",
    "gn:name":"Saett\u014fm",
    "gn:population":0,
    "gn:timezone":"Asia/Seoul",
    "iso:country":"KR",
    "name:und_x_variant":[
        "\uc0db\ub364",
        "Saett\u014fm"
    ],
    "wof:name":"Saettom",
    "wof:placetype":"locality"
},
  "geometry": {"coordinates":[128.31399999999999,36.0488],"type":"Point"}
}