{
  "type": "Feature",
  "properties": {
    "gn:admin1_code":"14.0",
    "gn:asciiname":"Andok",
    "gn:country_code":"KR",
    "gn:dem":277,
    "gn:feature_class":"P",
    "gn:feature_code":"PPL",
    "gn:name":"And\u014fk",
    "gn:population":0,
    "gn:timezone":"Asia/Seoul",
    "iso:country":"KR",
    "name:und_x_variant":[
        "\uc548\ub355",
        "And\u014fk"
    ],
    "wof:name":"Andok",
    "wof:placetype":"locality"
},
  "geometry": {"coordinates":[128.95959999999999,36.2887],"type":"Point"}
}