{
  "type": "Feature",
  "properties": {
    "gn:admin1_code":"14.0",
    "gn:asciiname":"Song-gol",
    "gn:country_code":"KR",
    "gn:dem":248,
    "gn:feature_class":"P",
    "gn:feature_code":"PPL",
    "gn:name":"S\u014fng-gol",
    "gn:population":0,
    "gn:timezone":"Asia/Seoul",
    "iso:country":"KR",
    "name:und_x_variant":[
        "\uc131\uace8",
        "S\u014fng-gol"
    ],
    "wof:name":"Song-gol",
    "wof:placetype":"locality"
},
  "geometry": {"coordinates":[129.13173999999998,36.01953],"type":"Point"}
}