{
  "type": "Feature",
  "properties": {
    "gn:admin1_code":"5.0",
    "gn:asciiname":"Geumwang",
    "gn:country_code":"KR",
    "gn:dem":102,
    "gn:feature_class":"P",
    "gn:feature_code":"PPL",
    "gn:name":"Geumwang",
    "gn:population":0,
    "gn:timezone":"Asia/Seoul",
    "iso:country":"KR",
    "name:kor_x_preferred":[
        "\uae08\uc655"
    ],
    "name:kor_x_variant":[
        "K\u016dmwang"
    ],
    "wof:name":"Geumwang",
    "wof:placetype":"locality"
},
  "geometry": {"coordinates":[127.59487,36.99246],"type":"Point"}
}