{
  "type": "Feature",
  "properties": {
    "gn:admin1_code":"13.0",
    "gn:asciiname":"Jangyeondong",
    "gn:country_code":"KR",
    "gn:dem":55,
    "gn:feature_class":"P",
    "gn:feature_code":"PPL",
    "gn:name":"Jangyeondong",
    "gn:population":0,
    "gn:timezone":"Asia/Seoul",
    "iso:country":"KR",
    "name:kor_x_preferred":[
        "\uc7a5\uc5f0\ub3d9"
    ],
    "wof:name":"Jangyeondong",
    "wof:placetype":"locality"
},
  "geometry": {"coordinates":[127.08432999999999,38.02596],"type":"Point"}
}