{
  "type": "Feature",
  "properties": {
    "gn:admin1_code":"13.0",
    "gn:asciiname":"Chunggansaeudae",
    "gn:country_code":"KR",
    "gn:dem":62,
    "gn:feature_class":"P",
    "gn:feature_code":"PPL",
    "gn:name":"Chunggansaeudae",
    "gn:population":0,
    "gn:timezone":"Asia/Seoul",
    "iso:country":"KR",
    "name:und_x_variant":[
        "\uc911\uac04\uc0c8\uc6b0\ub300",
        "Junggansaeudae",
        "Chunggansaeudae"
    ],
    "wof:name":"Chunggansaeudae",
    "wof:placetype":"locality"
},
  "geometry": {"coordinates":[126.93722,37.31083],"type":"Point"}
}