{
  "type": "Feature",
  "properties": {
    "gn:admin1_code":"16.0",
    "gn:asciiname":"Naepyeong",
    "gn:country_code":"KR",
    "gn:dem":42,
    "gn:feature_class":"P",
    "gn:feature_code":"PPL",
    "gn:name":"Naepyeong",
    "gn:population":0,
    "gn:timezone":"Asia/Seoul",
    "iso:country":"KR",
    "name:kor_x_preferred":[
        "Naep\u2019y\u014fng"
    ],
    "name:kor_x_variant":[
        "\ub0b4\ud3c9"
    ],
    "wof:name":"Naepyeong",
    "wof:placetype":"locality"
},
  "geometry": {"coordinates":[126.91623,34.66455999999999],"type":"Point"}
}