{
  "type": "Feature",
  "properties": {
    "gn:admin1_code":"17.0",
    "gn:asciiname":"Siwang",
    "gn:country_code":"KR",
    "gn:dem":65,
    "gn:feature_class":"P",
    "gn:feature_code":"PPL",
    "gn:name":"Siwang",
    "gn:population":0,
    "gn:timezone":"Asia/Seoul",
    "iso:country":"KR",
    "name:kor_x_preferred":[
        "\uc2dc\uc655"
    ],
    "wof:name":"Siwang",
    "wof:placetype":"locality"
},
  "geometry": {"coordinates":[126.89189,36.62515],"type":"Point"}
}