{
  "type": "Feature",
  "properties": {
    "gn:admin1_code":"17.0",
    "gn:asciiname":"Sinjon-ni",
    "gn:country_code":"KR",
    "gn:dem":170,
    "gn:feature_class":"P",
    "gn:feature_code":"PPL",
    "gn:name":"Sinj\u014fn-ni",
    "gn:population":0,
    "gn:timezone":"Asia/Seoul",
    "iso:country":"KR",
    "wof:name":"Sinjon-ni",
    "wof:placetype":"locality"
},
  "geometry": {"coordinates":[127.06667,36.63333],"type":"Point"}
}