{
  "type": "Feature",
  "properties": {
    "gn:admin1_code":"5.0",
    "gn:asciiname":"Hoenchi",
    "gn:country_code":"KR",
    "gn:dem":173,
    "gn:feature_class":"P",
    "gn:feature_code":"PPL",
    "gn:name":"Hoenchi",
    "gn:population":0,
    "gn:timezone":"Asia/Seoul",
    "iso:country":"KR",
    "name:kor_x_preferred":[
        "\ud770\uce58"
    ],
    "wof:name":"Hoenchi",
    "wof:placetype":"locality"
},
  "geometry": {"coordinates":[128.17066,36.96151],"type":"Point"}
}