{
  "type": "Feature",
  "properties": {
    "gn:admin1_code":"6.0",
    "gn:asciiname":"Nodongi-ri",
    "gn:country_code":"KR",
    "gn:dem":201,
    "gn:feature_class":"P",
    "gn:feature_code":"PPL",
    "gn:name":"Nodongi-ri",
    "gn:population":0,
    "gn:timezone":"Asia/Seoul",
    "iso:country":"KR",
    "name:und_x_variant":[
        "\ub178\ub3d92\ub9ac",
        "Nodongi-ri"
    ],
    "wof:name":"Nodongi-ri",
    "wof:placetype":"locality"
},
  "geometry": {"coordinates":[127.67417,38.16389],"type":"Point"}
}