{
  "type": "Feature",
  "properties": {
    "gn:admin1_code":"5.0",
    "gn:asciiname":"Silt'i",
    "gn:country_code":"KR",
    "gn:dem":194,
    "gn:feature_class":"P",
    "gn:feature_code":"PPL",
    "gn:name":"Silt\u2019i",
    "gn:population":0,
    "gn:timezone":"Asia/Seoul",
    "iso:country":"KR",
    "name:und_x_variant":[
        "\uc2e4\ud2f0",
        "Silt\u2019i"
    ],
    "wof:name":"Silt'i",
    "wof:placetype":"locality"
},
  "geometry": {"coordinates":[127.91889999999999,36.2523],"type":"Point"}
}