{
  "type": "Feature",
  "properties": {
    "gn:admin1_code":"13.0",
    "gn:asciiname":"Jageunmaegaegi",
    "gn:country_code":"KR",
    "gn:dem":51,
    "gn:feature_class":"P",
    "gn:feature_code":"PPL",
    "gn:name":"Jageunmaegaegi",
    "gn:population":0,
    "gn:timezone":"Asia/Seoul",
    "iso:country":"KR",
    "name:kor_x_preferred":[
        "\uc791\uc740\ub9e4\uac1c\uae30"
    ],
    "wof:name":"Jageunmaegaegi",
    "wof:placetype":"locality"
},
  "geometry": {"coordinates":[126.6814,37.24069],"type":"Point"}
}