{
  "type": "Feature",
  "properties": {
    "gn:admin1_code":"6.0",
    "gn:asciiname":"Toch'ul",
    "gn:country_code":"KR",
    "gn:dem":244,
    "gn:feature_class":"P",
    "gn:feature_code":"PPL",
    "gn:name":"Toch\u2019ul",
    "gn:population":0,
    "gn:timezone":"Asia/Seoul",
    "iso:country":"KR",
    "name:kor_x_preferred":[
        "\ub3c4\ucd9c"
    ],
    "name:kor_x_variant":[
        "Toch\u2019ul"
    ],
    "wof:name":"Toch'ul",
    "wof:placetype":"locality"
},
  "geometry": {"coordinates":[127.8395,37.5786],"type":"Point"}
}