{
  "type": "Feature",
  "properties": {
    "gn:admin1_code":"17.0",
    "gn:asciiname":"Anbol",
    "gn:country_code":"KR",
    "gn:dem":6,
    "gn:feature_class":"P",
    "gn:feature_code":"PPL",
    "gn:name":"Anb\u014fl",
    "gn:population":0,
    "gn:timezone":"Asia/Seoul",
    "iso:country":"KR",
    "name:und_x_variant":[
        "\uc548\ubc8c",
        "Anb\u014fl"
    ],
    "wof:name":"Anbol",
    "wof:placetype":"locality"
},
  "geometry": {"coordinates":[126.7428,36.729],"type":"Point"}
}