{
  "type": "Feature",
  "properties": {
    "gn:admin1_code":"3.0",
    "gn:asciiname":"Habuk",
    "gn:country_code":"KR",
    "gn:dem":317,
    "gn:feature_class":"P",
    "gn:feature_code":"PPL",
    "gn:name":"Habuk",
    "gn:population":0,
    "gn:timezone":"Asia/Seoul",
    "iso:country":"KR",
    "name:und_x_variant":[
        "Habung-ni",
        "\ud558\ubd81",
        "Habuk"
    ],
    "wof:name":"Habuk",
    "wof:placetype":"locality"
},
  "geometry": {"coordinates":[127.49363,35.54975],"type":"Point"}
}