{
  "type": "Feature",
  "properties": {
    "gn:admin1_code":"13.0",
    "gn:asciiname":"Yangchondong",
    "gn:country_code":"KR",
    "gn:dem":22,
    "gn:feature_class":"P",
    "gn:feature_code":"PPL",
    "gn:name":"Yangchondong",
    "gn:population":0,
    "gn:timezone":"Asia/Seoul",
    "iso:country":"KR",
    "name:kor_x_preferred":[
        "\uc591\ucd0c\ub3d9"
    ],
    "name:und_x_variant":[
        "Yangji-dong",
        "Yangjon-dong",
        "Yangchondong"
    ],
    "wof:name":"Yangchondong",
    "wof:placetype":"locality"
},
  "geometry": {"coordinates":[126.62487,37.73954000000001],"type":"Point"}
}