{
  "type": "Feature",
  "properties": {
    "gn:admin1_code":"17.0",
    "gn:asciiname":"Mageundaemi",
    "gn:country_code":"KR",
    "gn:dem":131,
    "gn:feature_class":"P",
    "gn:feature_code":"PPL",
    "gn:name":"Mageundaemi",
    "gn:population":0,
    "gn:timezone":"Asia/Seoul",
    "iso:country":"KR",
    "name:und_x_variant":[
        "Hamag\u016dn",
        "Mag\u016dndaemi",
        "\ub9c8\uadfc\ub300\ubbf8",
        "Mageundaemi"
    ],
    "wof:name":"Mageundaemi",
    "wof:placetype":"locality"
},
  "geometry": {"coordinates":[127.35312999999999,36.19409],"type":"Point"}
}