{
  "type": "Feature",
  "properties": {
    "gn:admin1_code":"5.0",
    "gn:asciiname":"Mokgye",
    "gn:country_code":"KR",
    "gn:dem":74,
    "gn:feature_class":"P",
    "gn:feature_code":"PPL",
    "gn:name":"Mokgye",
    "gn:population":0,
    "gn:timezone":"Asia/Seoul",
    "iso:country":"KR",
    "name:kor_x_preferred":[
        "\ubaa9\uacc4"
    ],
    "name:und_x_variant":[
        "Bokukei-d\u014d",
        "Mokkye-dong",
        "Bokkei",
        "Mokkye",
        "Mokgye"
    ],
    "wof:name":"Mokgye",
    "wof:placetype":"locality"
},
  "geometry": {"coordinates":[127.88858999999999,37.07907],"type":"Point"}
}