{
  "type": "Feature",
  "properties": {
    "gn:admin1_code":"17.0",
    "gn:asciiname":"Sop'yonmanghae",
    "gn:country_code":"KR",
    "gn:dem":54,
    "gn:feature_class":"P",
    "gn:feature_code":"PPL",
    "gn:name":"S\u014fp\u2019y\u014fnmanghae",
    "gn:population":0,
    "gn:timezone":"Asia/Seoul",
    "iso:country":"KR",
    "name:und_x_variant":[
        "Mangs\u014f-ri",
        "S\u014fp\u2019y\u014fnmanghae",
        "\uc11c\ud3b8\ub9dd\ud574"
    ],
    "wof:name":"Sop'yonmanghae",
    "wof:placetype":"locality"
},
  "geometry": {"coordinates":[126.80240000000001,36.2768],"type":"Point"}
}