{
  "type": "Feature",
  "properties": {
    "gn:admin1_code":"13.0",
    "gn:asciiname":"Onam",
    "gn:country_code":"KR",
    "gn:dem":78,
    "gn:feature_class":"P",
    "gn:feature_code":"PPLA3",
    "gn:name":"Onam",
    "gn:population":0,
    "gn:timezone":"Asia/Seoul",
    "iso:country":"KR",
    "name:kor_x_preferred":[
        "\uc624\ub0a8"
    ],
    "wof:name":"Onam",
    "wof:placetype":"locality"
},
  "geometry": {"coordinates":[127.20578999999999,37.69834],"type":"Point"}
}