{
  "type": "Feature",
  "properties": {
    "gn:admin1_code":"13.0",
    "gn:asciiname":"Onam",
    "gn:country_code":"KR",
    "gn:dem":78,
    "gn:feature_class":"P",
    "gn:feature_code":"PPLA3",
    "gn:name":"Onam",
    "gn:population":0,
    "gn:timezone":"Asia/Seoul",
    "iso:country":"KR",
    "name:ara_x_preferred":[
        "\u0623\u0648\u0646\u0627\u0645"
    ],
    "name:cat_x_preferred":[
        "Onam"
    ],
    "name:fin_x_preferred":[
        "Onam"
    ],
    "name:fra_x_preferred":[
        "Onam"
    ],
    "name:gom_x_preferred":[
        "Onam"
    ],
    "name:guj_x_preferred":[
        "\u0a93\u0aa3\u0aae"
    ],
    "name:hin_x_preferred":[
        "\u0913\u0923\u092e"
    ],
    "name:jpn_x_preferred":[
        "\u30aa\u30ca\u30e0"
    ],
    "name:kan_x_preferred":[
        "\u0c93\u0ca3\u0cae\u0ccd\u200c"
    ],
    "name:kor_x_preferred":[
        "\uc624\ub0a8"
    ],
    "name:lit_x_preferred":[
        "Onam"
    ],
    "name:mal_x_preferred":[
        "\u0d13\u0d23\u0d02"
    ],
    "name:mar_x_preferred":[
        "\u0913\u0923\u092e"
    ],
    "name:msa_x_preferred":[
        "Onam"
    ],
    "name:nno_x_preferred":[
        "Onam"
    ],
    "name:ori_x_preferred":[
        "\u0b13\u0b23\u0b2e"
    ],
    "name:pan_x_preferred":[
        "\u0a13\u0a23\u0a2e"
    ],
    "name:pol_x_preferred":[
        "Onam"
    ],
    "name:rus_x_preferred":[
        "\u041e\u043d\u0430\u043c"
    ],
    "name:san_x_preferred":[
        "\u0913\u0923\u092e\u094d"
    ],
    "name:slk_x_preferred":[
        "\u00d3nam"
    ],
    "name:spa_x_preferred":[
        "Onam"
    ],
    "name:tam_x_preferred":[
        "\u0b93\u0ba3\u0bae\u0bcd"
    ],
    "name:tcy_x_preferred":[
        "\u0c93\u0ca3\u0cae\u0ccd"
    ],
    "name:tel_x_preferred":[
        "\u0c13\u0c23\u0c02"
    ],
    "name:urd_x_preferred":[
        "\u0627\u0648\u0646\u0645"
    ],
    "wof:name":"Onam",
    "wof:placetype":"locality"
},
  "geometry": {"coordinates":[127.20578999999999,37.69834],"type":"Point"}
}