{
  "type": "Feature",
  "properties": {
    "gn:admin1_code":"0.0",
    "gn:asciiname":"Wont'ongjae",
    "gn:country_code":"KR",
    "gn:dem":461,
    "gn:feature_class":"P",
    "gn:feature_code":"PPL",
    "gn:name":"W\u014fnt\u2019ongjae",
    "gn:population":0,
    "gn:timezone":"Asia/Seoul",
    "iso:country":"KR",
    "name:und_x_variant":[
        "W\u014fnt\u2019ong-dong",
        "W\u014fnt\u2019ongjae"
    ],
    "wof:name":"Wont'ongjae",
    "wof:placetype":"locality"
},
  "geometry": {"coordinates":[127.68333,35.56667],"type":"Point"}
}