{
  "type": "Feature",
  "properties": {
    "gn:admin1_code":"14.0",
    "gn:asciiname":"Gangok",
    "gn:country_code":"KR",
    "gn:dem":17,
    "gn:feature_class":"P",
    "gn:feature_code":"PPL",
    "gn:name":"Gangok",
    "gn:population":0,
    "gn:timezone":"Asia/Seoul",
    "iso:country":"KR",
    "name:kor_x_preferred":[
        "\uac04\uace1"
    ],
    "wof:name":"Gangok",
    "wof:placetype":"locality"
},
  "geometry": {"coordinates":[129.28416999999999,35.97654],"type":"Point"}
}