{
  "type": "Feature",
  "properties": {
    "gn:admin1_code":"13.0",
    "gn:asciiname":"Neungudong",
    "gn:country_code":"KR",
    "gn:dem":91,
    "gn:feature_class":"P",
    "gn:feature_code":"PPL",
    "gn:name":"Neungudong",
    "gn:population":0,
    "gn:timezone":"Asia/Seoul",
    "iso:country":"KR",
    "name:kor_x_preferred":[
        "\ub2a5\uc6b0\ub3d9"
    ],
    "name:und_x_variant":[
        "\ub2a5\uc6b0",
        "N\u016dngu",
        "Neungudong"
    ],
    "wof:name":"Neungudong",
    "wof:placetype":"locality"
},
  "geometry": {"coordinates":[127.53754000000001,37.87071],"type":"Point"}
}