{
  "type": "Feature",
  "properties": {
    "gn:admin1_code":"14.0",
    "gn:asciiname":"Homi",
    "gn:country_code":"KR",
    "gn:dem":219,
    "gn:feature_class":"P",
    "gn:feature_code":"PPL",
    "gn:name":"Homi",
    "gn:population":0,
    "gn:timezone":"Asia/Seoul",
    "iso:country":"KR",
    "name:und_x_variant":[
        "\ud638\ubbf8",
        "Homi"
    ],
    "wof:name":"Homi",
    "wof:placetype":"locality"
},
  "geometry": {"coordinates":[127.97,35.92836],"type":"Point"}
}