{
  "type": "Feature",
  "properties": {
    "gn:admin1_code":"1.0",
    "gn:asciiname":"Sangmun-dong",
    "gn:country_code":"KR",
    "gn:dem":626,
    "gn:feature_class":"P",
    "gn:feature_code":"PPL",
    "gn:name":"Sangmun-dong",
    "gn:population":0,
    "gn:timezone":"Asia/Seoul",
    "iso:country":"KR",
    "wof:name":"Sangmun-dong",
    "wof:placetype":"locality"
},
  "geometry": {"coordinates":[126.43333,33.31667],"type":"Point"}
}