{
  "type": "Feature",
  "properties": {
    "gn:admin1_code":"3.0",
    "gn:asciiname":"Sangmangp'yo",
    "gn:country_code":"KR",
    "gn:dem":104,
    "gn:feature_class":"P",
    "gn:feature_code":"PPL",
    "gn:name":"Sangmangp\u2019yo",
    "gn:population":0,
    "gn:timezone":"Asia/Seoul",
    "iso:country":"KR",
    "name:und_x_variant":[
        "\uc0c1\ub9dd\ud45c",
        "Sangmangp\u2019yo"
    ],
    "wof:name":"Sangmangp'yo",
    "wof:placetype":"locality"
},
  "geometry": {"coordinates":[127.24057999999999,35.84233],"type":"Point"}
}