{
  "type": "Feature",
  "properties": {
    "gn:admin1_code":"14.0",
    "gn:asciiname":"Oeundae",
    "gn:country_code":"KR",
    "gn:dem":202,
    "gn:feature_class":"P",
    "gn:feature_code":"PPL",
    "gn:name":"Oeundae",
    "gn:population":0,
    "gn:timezone":"Asia/Seoul",
    "iso:country":"KR",
    "name:kor_x_preferred":[
        "\uc624\uc740\ub300"
    ],
    "wof:name":"Oeundae",
    "wof:placetype":"locality"
},
  "geometry": {"coordinates":[128.85856000000001,36.65574],"type":"Point"}
}