{
  "type": "Feature",
  "properties": {
    "gn:admin1_code":"14.0",
    "gn:asciiname":"Cheonnae",
    "gn:country_code":"KR",
    "gn:dem":128,
    "gn:feature_class":"P",
    "gn:feature_code":"PPL",
    "gn:name":"Cheonnae",
    "gn:population":0,
    "gn:timezone":"Asia/Seoul",
    "iso:country":"KR",
    "name:kor_x_preferred":[
        "\ucc9c\ub0b4"
    ],
    "wof:name":"Cheonnae",
    "wof:placetype":"locality"
},
  "geometry": {"coordinates":[128.41414,36.67954],"type":"Point"}
}