{
  "type": "Feature",
  "properties": {
    "gn:admin1_code":"5.0",
    "gn:asciiname":"Tongmi",
    "gn:country_code":"KR",
    "gn:dem":64,
    "gn:feature_class":"P",
    "gn:feature_code":"PPL",
    "gn:name":"Tongmi",
    "gn:population":0,
    "gn:timezone":"Asia/Seoul",
    "iso:country":"KR",
    "name:kor_x_preferred":[
        "\ud1b5\ubbf8"
    ],
    "wof:name":"Tongmi",
    "wof:placetype":"locality"
},
  "geometry": {"coordinates":[127.31433,36.64719],"type":"Point"}
}