{
  "type": "Feature",
  "properties": {
    "gn:admin1_code":"6.0",
    "gn:asciiname":"Hwangodae",
    "gn:country_code":"KR",
    "gn:dem":48,
    "gn:feature_class":"P",
    "gn:feature_code":"PPL",
    "gn:name":"Hwang\u014fdae",
    "gn:population":0,
    "gn:timezone":"Asia/Seoul",
    "iso:country":"KR",
    "name:kor_x_preferred":[
        "\ud669\uc5b4\ub300"
    ],
    "name:kor_x_variant":[
        "Hwang\u014fdae"
    ],
    "wof:name":"Hwangodae",
    "wof:placetype":"locality"
},
  "geometry": {"coordinates":[128.74879999999999,37.8496],"type":"Point"}
}