{
  "type": "Feature",
  "properties": {
    "gn:admin1_code":"12.0",
    "gn:asciiname":"Nolmal",
    "gn:country_code":"KR",
    "gn:dem":15,
    "gn:feature_class":"P",
    "gn:feature_code":"PPL",
    "gn:name":"N\u014flmal",
    "gn:population":0,
    "gn:timezone":"Asia/Seoul",
    "iso:country":"KR",
    "name:kor_x_preferred":[
        "\ub110\ub9d0"
    ],
    "name:kor_x_variant":[
        "N\u014flmal"
    ],
    "wof:name":"Nolmal",
    "wof:placetype":"locality"
},
  "geometry": {"coordinates":[126.77972,37.5425],"type":"Point"}
}