{
  "type": "Feature",
  "properties": {
    "gn:admin1_code":"17.0",
    "gn:asciiname":"Kumi-gol",
    "gn:country_code":"KR",
    "gn:dem":37,
    "gn:feature_class":"P",
    "gn:feature_code":"PPL",
    "gn:name":"Kumi-gol",
    "gn:population":0,
    "gn:timezone":"Asia/Seoul",
    "iso:country":"KR",
    "name:und_x_variant":[
        "Kumi-ri",
        "\uad6c\ubbf8\uace8",
        "Kumuk-kol",
        "Kumi-gol"
    ],
    "wof:name":"Kumi-gol",
    "wof:placetype":"locality"
},
  "geometry": {"coordinates":[127.0318,36.8044],"type":"Point"}
}