{
  "type": "Feature",
  "properties": {
    "gn:admin1_code":"13.0",
    "gn:admin2_code":"P'aju-si",
    "gn:asciiname":"Hwaseokdong",
    "gn:country_code":"KR",
    "gn:dem":45,
    "gn:feature_class":"P",
    "gn:feature_code":"PPL",
    "gn:name":"Hwaseokdong",
    "gn:population":0,
    "gn:timezone":"Asia/Seoul",
    "iso:country":"KR",
    "name:kor_x_preferred":[
        "\ud654\uc11d\ub3d9"
    ],
    "name:und_x_variant":[
        "Hwas\u014fk-tong"
    ],
    "wof:name":"Hwaseokdong",
    "wof:placetype":"locality"
},
  "geometry": {"coordinates":[126.80476000000002,37.88415],"type":"Point"}
}