{
  "type": "Feature",
  "properties": {
    "gn:admin1_code":"17.0",
    "gn:asciiname":"Munae",
    "gn:country_code":"KR",
    "gn:dem":32,
    "gn:feature_class":"P",
    "gn:feature_code":"PPL",
    "gn:name":"Munae",
    "gn:population":0,
    "gn:timezone":"Asia/Seoul",
    "iso:country":"KR",
    "name:und_x_variant":[
        "\ubb34\ub0b4",
        "Munae"
    ],
    "wof:name":"Munae",
    "wof:placetype":"locality"
},
  "geometry": {"coordinates":[126.2774,36.7829],"type":"Point"}
}