{
  "type": "Feature",
  "properties": {
    "gn:admin1_code":"3.0",
    "gn:asciiname":"Hasong",
    "gn:country_code":"KR",
    "gn:dem":276,
    "gn:feature_class":"P",
    "gn:feature_code":"PPL",
    "gn:name":"Has\u014fng",
    "gn:population":0,
    "gn:timezone":"Asia/Seoul",
    "iso:country":"KR",
    "name:und_x_variant":[
        "\ud558\uc131",
        "Has\u014fng"
    ],
    "wof:name":"Hasong",
    "wof:placetype":"locality"
},
  "geometry": {"coordinates":[127.2736,35.61539000000001],"type":"Point"}
}