{
  "type": "Feature",
  "properties": {
    "gn:admin1_code":"6.0",
    "gn:asciiname":"Kodulgogae",
    "gn:country_code":"KR",
    "gn:dem":488,
    "gn:feature_class":"P",
    "gn:feature_code":"PPL",
    "gn:name":"Kod\u016dlgogae",
    "gn:population":0,
    "gn:timezone":"Asia/Seoul",
    "iso:country":"KR",
    "name:kor_x_preferred":[
        "\uace0\ub4e4\uace0\uac1c"
    ],
    "name:kor_x_variant":[
        "Kod\u016dlgogae"
    ],
    "wof:name":"Kodulgogae",
    "wof:placetype":"locality"
},
  "geometry": {"coordinates":[128.1566,37.4873],"type":"Point"}
}