{
  "type": "Feature",
  "properties": {
    "gn:admin1_code":"16.0",
    "gn:asciiname":"Donsangjeong",
    "gn:country_code":"KR",
    "gn:dem":18,
    "gn:feature_class":"P",
    "gn:feature_code":"PPL",
    "gn:name":"Donsangjeong",
    "gn:population":0,
    "gn:timezone":"Asia/Seoul",
    "iso:country":"KR",
    "name:kor_x_preferred":[
        "\ub3c8\uc0b0\uc815"
    ],
    "name:kor_x_variant":[
        "Tonsanj\u014fng"
    ],
    "wof:name":"Donsangjeong",
    "wof:placetype":"locality"
},
  "geometry": {"coordinates":[127.29734000000001,34.76295],"type":"Point"}
}