{
  "type": "Feature",
  "properties": {
    "gn:admin1_code":"20.0",
    "gn:asciiname":"Myongwol",
    "gn:country_code":"KR",
    "gn:dem":27,
    "gn:feature_class":"P",
    "gn:feature_code":"PPL",
    "gn:name":"My\u014fngw\u014fl",
    "gn:population":0,
    "gn:timezone":"Asia/Seoul",
    "iso:country":"KR",
    "name:und_x_variant":[
        "\uba85\uc6d4",
        "My\u014fngw\u014fl"
    ],
    "wof:name":"Myongwol",
    "wof:placetype":"locality"
},
  "geometry": {"coordinates":[128.40326000000002,35.48515],"type":"Point"}
}