{
  "type": "Feature",
  "properties": {
    "gn:admin1_code":"19.0",
    "gn:asciiname":"Saetteum",
    "gn:country_code":"KR",
    "gn:dem":127,
    "gn:feature_class":"P",
    "gn:feature_code":"PPL",
    "gn:name":"Saetteum",
    "gn:population":0,
    "gn:timezone":"Asia/Seoul",
    "iso:country":"KR",
    "name:und_x_variant":[
        "\uc0c8\ub738",
        "Saett\u016dm",
        "Saetteum"
    ],
    "wof:name":"Saetteum",
    "wof:placetype":"locality"
},
  "geometry": {"coordinates":[127.43548,36.40255],"type":"Point"}
}