{
  "type": "Feature",
  "properties": {
    "gn:admin1_code":"6.0",
    "gn:asciiname":"Sajimok",
    "gn:country_code":"KR",
    "gn:dem":659,
    "gn:feature_class":"P",
    "gn:feature_code":"PPL",
    "gn:name":"Sajimok",
    "gn:population":0,
    "gn:timezone":"Asia/Seoul",
    "iso:country":"KR",
    "name:kor_x_preferred":[
        "\uc0ac\uc9c0\ubaa9"
    ],
    "wof:name":"Sajimok",
    "wof:placetype":"locality"
},
  "geometry": {"coordinates":[128.7456,37.5299],"type":"Point"}
}