{
  "type": "Feature",
  "properties": {
    "gn:admin1_code":"17.0",
    "gn:asciiname":"Songhyon",
    "gn:country_code":"KR",
    "gn:dem":29,
    "gn:feature_class":"P",
    "gn:feature_code":"PPL",
    "gn:name":"Songhy\u014fn",
    "gn:population":0,
    "gn:timezone":"Asia/Seoul",
    "iso:country":"KR",
    "name:und_x_variant":[
        "\uc1a1\ud604",
        "Songhy\u014fn"
    ],
    "wof:name":"Songhyon",
    "wof:placetype":"locality"
},
  "geometry": {"coordinates":[127.02979999999999,36.2699],"type":"Point"}
}