{
  "type": "Feature",
  "properties": {
    "gn:admin1_code":"14.0",
    "gn:asciiname":"Imsil",
    "gn:cc2":"KR",
    "gn:country_code":"KR",
    "gn:dem":128,
    "gn:feature_class":"P",
    "gn:feature_code":"PPL",
    "gn:name":"Imsil",
    "gn:population":0,
    "gn:timezone":"Asia/Seoul",
    "iso:country":"KR",
    "name:und_x_variant":[
        "Imgok",
        "Imsil"
    ],
    "wof:name":"Imsil",
    "wof:placetype":"locality"
},
  "geometry": {"coordinates":[128.89056000000002,35.64972],"type":"Point"}
}