{
  "type": "Feature",
  "properties": {
    "gn:admin1_code":"17.0",
    "gn:asciiname":"Hagwang",
    "gn:country_code":"KR",
    "gn:dem":126,
    "gn:feature_class":"P",
    "gn:feature_code":"PPL",
    "gn:name":"Hagwang",
    "gn:population":0,
    "gn:timezone":"Asia/Seoul",
    "iso:country":"KR",
    "name:und_x_variant":[
        "\ud558\uad11",
        "Hagwang"
    ],
    "wof:name":"Hagwang",
    "wof:placetype":"locality"
},
  "geometry": {"coordinates":[126.8415,36.4751],"type":"Point"}
}