{
  "type": "Feature",
  "properties": {
    "gn:admin1_code":"5.0",
    "gn:asciiname":"Saegogae",
    "gn:country_code":"KR",
    "gn:dem":60,
    "gn:feature_class":"P",
    "gn:feature_code":"PPL",
    "gn:name":"Saegogae",
    "gn:population":0,
    "gn:timezone":"Asia/Seoul",
    "iso:country":"KR",
    "name:kor_x_preferred":[
        "\uc0c8\uace0\uac1c"
    ],
    "wof:name":"Saegogae",
    "wof:placetype":"locality"
},
  "geometry": {"coordinates":[127.3732,36.595],"type":"Point"}
}