{
  "type": "Feature",
  "properties": {
    "gn:admin1_code":"14.0",
    "gn:asciiname":"Sangsa",
    "gn:country_code":"KR",
    "gn:dem":321,
    "gn:feature_class":"P",
    "gn:feature_code":"PPL",
    "gn:name":"Sangsa",
    "gn:population":0,
    "gn:timezone":"Asia/Seoul",
    "iso:country":"KR",
    "name:kor_x_preferred":[
        "\uc0c1\uc0ac"
    ],
    "wof:name":"Sangsa",
    "wof:placetype":"locality"
},
  "geometry": {"coordinates":[128.40932000000001,36.76942],"type":"Point"}
}