{
  "type": "Feature",
  "properties": {
    "gn:admin1_code":"13.0",
    "gn:asciiname":"Singidong",
    "gn:country_code":"KR",
    "gn:dem":21,
    "gn:feature_class":"P",
    "gn:feature_code":"PPL",
    "gn:name":"Singidong",
    "gn:population":0,
    "gn:timezone":"Asia/Seoul",
    "iso:country":"KR",
    "name:kor_x_preferred":[
        "\uc2e0\uae30"
    ],
    "name:kor_x_variant":[
        "Sin\u2019gi",
        "\uc2e0\uae30\ub3d9",
        "Sin\u2019gi-dong"
    ],
    "wof:name":"Singidong",
    "wof:placetype":"locality"
},
  "geometry": {"coordinates":[126.63684000000001,37.75054],"type":"Point"}
}