{
  "type": "Feature",
  "properties": {
    "gn:admin1_code":"14.0",
    "gn:asciiname":"Sangnyul",
    "gn:country_code":"KR",
    "gn:dem":18,
    "gn:feature_class":"P",
    "gn:feature_code":"PPL",
    "gn:name":"Sangnyul",
    "gn:population":0,
    "gn:timezone":"Asia/Seoul",
    "iso:country":"KR",
    "name:und_x_variant":[
        "\uc0c1\ubc24\ud22c",
        "Sangbamt\u2019u"
    ],
    "wof:name":"Sangnyul",
    "wof:placetype":"locality"
},
  "geometry": {"coordinates":[129.4357,36.6896],"type":"Point"}
}