{
  "type": "Feature",
  "properties": {
    "gn:admin1_code":"20.0",
    "gn:admin2_code":"K\u014fje-si",
    "gn:asciiname":"Sokp'o",
    "gn:country_code":"KR",
    "gn:dem":62,
    "gn:feature_class":"P",
    "gn:feature_code":"PPL",
    "gn:name":"S\u014fkp\u2019o",
    "gn:population":0,
    "gn:timezone":"Asia/Seoul",
    "iso:country":"KR",
    "name:und_x_variant":[
        "S\u014fkp\u2019o-ri",
        "S\u014fkp\u2019o"
    ],
    "wof:name":"Sokp'o",
    "wof:placetype":"locality"
},
  "geometry": {"coordinates":[128.59306000000001,34.9425],"type":"Point"}
}