{
  "type": "Feature",
  "properties": {
    "gn:admin1_code":"15.0",
    "gn:asciiname":"Gajae",
    "gn:country_code":"KR",
    "gn:dem":377,
    "gn:feature_class":"P",
    "gn:feature_code":"PPL",
    "gn:name":"Gajae",
    "gn:population":0,
    "gn:timezone":"Asia/Seoul",
    "iso:country":"KR",
    "name:und_x_variant":[
        "Kahy\u014fn-dong",
        "Kahy\u014fn",
        "Kajae-gol",
        "\uac00\uc7ac",
        "Kajae",
        "Gajae"
    ],
    "wof:name":"Gajae",
    "wof:placetype":"locality"
},
  "geometry": {"coordinates":[128.50191999999998,35.68998],"type":"Point"}
}