{
  "type": "Feature",
  "properties": {
    "gn:admin1_code":"16.0",
    "gn:asciiname":"P'yong-ni",
    "gn:country_code":"KR",
    "gn:dem":106,
    "gn:feature_class":"P",
    "gn:feature_code":"PPL",
    "gn:name":"P\u2019y\u014fng-ni",
    "gn:population":0,
    "gn:timezone":"Asia/Seoul",
    "iso:country":"KR",
    "name:eng_x_preferred":[
        "P'yong"
    ],
    "name:eng_x_variant":[
        "P'yong-ni"
    ],
    "wof:name":"P'yong",
    "wof:placetype":"locality"
},
  "geometry": {"coordinates":[127.29583,35.12611],"type":"Point"}
}