{
  "type": "Feature",
  "properties": {
    "gn:admin1_code":"17.0",
    "gn:asciiname":"Yeonhwadong",
    "gn:country_code":"KR",
    "gn:dem":118,
    "gn:feature_class":"P",
    "gn:feature_code":"PPL",
    "gn:name":"Yeonhwadong",
    "gn:population":0,
    "gn:timezone":"Asia/Seoul",
    "iso:country":"KR",
    "name:kor_x_preferred":[
        "\uc5f0\ud654\ub3d9"
    ],
    "wof:name":"Yeonhwadong",
    "wof:placetype":"locality"
},
  "geometry": {"coordinates":[127.24593,36.28352],"type":"Point"}
}