{
  "type": "Feature",
  "properties": {
    "gn:admin1_code":"13.0",
    "gn:asciiname":"Oesuip",
    "gn:country_code":"KR",
    "gn:dem":42,
    "gn:feature_class":"P",
    "gn:feature_code":"PPL",
    "gn:name":"Oesuip",
    "gn:population":0,
    "gn:timezone":"Asia/Seoul",
    "iso:country":"KR",
    "name:kor_x_preferred":[
        "\uc678\uc218\uc785"
    ],
    "name:und_x_variant":[
        "Oemud\u016dri",
        "Oemusu-ri",
        "Oesuim-ni",
        "\uc678\uc218\uc785",
        "Oesuip"
    ],
    "wof:name":"Oesuip",
    "wof:placetype":"locality"
},
  "geometry": {"coordinates":[127.376,37.646],"type":"Point"}
}