{
  "type": "Feature",
  "properties": {
    "gn:admin1_code":"11.0",
    "gn:asciiname":"Chonnongil-tong",
    "gn:country_code":"KR",
    "gn:dem":26,
    "gn:feature_class":"P",
    "gn:feature_code":"PPL",
    "gn:name":"Ch\u014fnnongil-tong",
    "gn:population":0,
    "gn:timezone":"Asia/Seoul",
    "iso:country":"KR",
    "name:und_x_variant":[
        "\uc804\ub18d1\ub3d9",
        "Ch\u014fnnongil-tong"
    ],
    "wof:name":"Chonnongil-tong",
    "wof:placetype":"locality"
},
  "geometry": {"coordinates":[127.04993,37.57582],"type":"Point"}
}