{
  "type": "Feature",
  "properties": {
    "gn:admin1_code":"15.0",
    "gn:asciiname":"Araetjanoe",
    "gn:country_code":"KR",
    "gn:dem":24,
    "gn:feature_class":"P",
    "gn:feature_code":"PPL",
    "gn:name":"Araetjanoe",
    "gn:population":0,
    "gn:timezone":"Asia/Seoul",
    "iso:country":"KR",
    "name:kor_x_preferred":[
        "\uc544\ub7ab\uc794\uc678"
    ],
    "wof:name":"Araetjanoe",
    "wof:placetype":"locality"
},
  "geometry": {"coordinates":[128.48121,35.80948],"type":"Point"}
}