{
  "type": "Feature",
  "properties": {
    "gn:admin1_code":"15.0",
    "gn:asciiname":"Nabisil",
    "gn:country_code":"KR",
    "gn:dem":47,
    "gn:feature_class":"P",
    "gn:feature_code":"PPL",
    "gn:name":"Nabisil",
    "gn:population":0,
    "gn:timezone":"Asia/Seoul",
    "iso:country":"KR",
    "name:kor_x_preferred":[
        "\ub098\ube44\uc2e4"
    ],
    "wof:name":"Nabisil",
    "wof:placetype":"locality"
},
  "geometry": {"coordinates":[128.40260000000001,35.66800999999999],"type":"Point"}
}