{
  "type": "Feature",
  "properties": {
    "gn:admin1_code":"14.0",
    "gn:asciiname":"Byeongsan",
    "gn:country_code":"KR",
    "gn:dem":205,
    "gn:feature_class":"P",
    "gn:feature_code":"PPL",
    "gn:name":"Byeongsan",
    "gn:population":0,
    "gn:timezone":"Asia/Seoul",
    "iso:country":"KR",
    "name:kor_x_preferred":[
        "\ubcd1\uc0b0"
    ],
    "name:kor_x_variant":[
        "Py\u014fngsan"
    ],
    "wof:name":"Byeongsan",
    "wof:placetype":"locality"
},
  "geometry": {"coordinates":[128.60813999999999,36.9256],"type":"Point"}
}