{
  "type": "Feature",
  "properties": {
    "gn:admin1_code":"12.0",
    "gn:asciiname":"Nammunbak",
    "gn:country_code":"KR",
    "gn:dem":21,
    "gn:feature_class":"P",
    "gn:feature_code":"PPL",
    "gn:name":"Nammunbak",
    "gn:population":0,
    "gn:timezone":"Asia/Seoul",
    "iso:country":"KR",
    "name:kor_x_preferred":[
        "\ub0a8\ubb38\ubc15"
    ],
    "name:und_x_variant":[
        "\ub0a8\ubb38\ubc16",
        "Nammunbakk",
        "Nammunbak"
    ],
    "wof:name":"Nammunbak",
    "wof:placetype":"locality"
},
  "geometry": {"coordinates":[126.48508,37.73989],"type":"Point"}
}