{
  "type": "Feature",
  "properties": {
    "gn:admin1_code":"20.0",
    "gn:asciiname":"Ch'oltuk",
    "gn:country_code":"KR",
    "gn:dem":5,
    "gn:feature_class":"P",
    "gn:feature_code":"PPL",
    "gn:name":"Ch\u2019\u014fltuk",
    "gn:population":0,
    "gn:timezone":"Asia/Seoul",
    "iso:country":"KR",
    "name:und_x_variant":[
        "\ucca0\ub451",
        "Ch\u2019\u014fltuk"
    ],
    "wof:name":"Ch'oltuk",
    "wof:placetype":"locality"
},
  "geometry": {"coordinates":[128.38682,34.81298],"type":"Point"}
}