{
  "type": "Feature",
  "properties": {
    "gn:admin1_code":"13.0",
    "gn:asciiname":"Withwangjeong",
    "gn:country_code":"KR",
    "gn:dem":82,
    "gn:feature_class":"P",
    "gn:feature_code":"PPL",
    "gn:name":"Withwangjeong",
    "gn:population":0,
    "gn:timezone":"Asia/Seoul",
    "iso:country":"KR",
    "name:kor_x_preferred":[
        "\uc717\ud669\uc815"
    ],
    "name:kor_x_variant":[
        "Withwangj\u014fng"
    ],
    "name:und_x_variant":[
        "Witwangjeong",
        "Withwangjeong"
    ],
    "wof:name":"Withwangjeong",
    "wof:placetype":"locality"
},
  "geometry": {"coordinates":[127.5926,37.1586],"type":"Point"}
}