{
  "type": "Feature",
  "properties": {
    "gn:admin1_code":"16.0",
    "gn:asciiname":"Wondung",
    "gn:country_code":"KR",
    "gn:dem":12,
    "gn:feature_class":"P",
    "gn:feature_code":"PPL",
    "gn:name":"W\u014fnd\u016dng",
    "gn:population":0,
    "gn:timezone":"Asia/Seoul",
    "iso:country":"KR",
    "name:kor_x_preferred":[
        "W\u014fnd\u016dng"
    ],
    "name:und_x_variant":[
        "\uc6d0\ub4f1"
    ],
    "wof:name":"Wondung",
    "wof:placetype":"locality"
},
  "geometry": {"coordinates":[126.56917,34.62333],"type":"Point"}
}