{
  "type": "Feature",
  "properties": {
    "gn:admin1_code":"17.0",
    "gn:asciiname":"Ch'onho-ri",
    "gn:country_code":"KR",
    "gn:dem":79,
    "gn:feature_class":"P",
    "gn:feature_code":"PPLL",
    "gn:name":"Ch\u2019\u014fnho-ri",
    "gn:population":0,
    "gn:timezone":"Asia/Seoul",
    "iso:country":"KR",
    "name:und_x_variant":[
        "\ucc9c\ud638\ub9ac",
        "Ch\u2019\u014fnho-ri"
    ],
    "wof:name":"Ch'onho-ri",
    "wof:placetype":"locality"
},
  "geometry": {"coordinates":[127.23039,36.24351],"type":"Point"}
}