{
  "type": "Feature",
  "properties": {
    "gn:admin1_code":"1.0",
    "gn:asciiname":"Haengwol-li",
    "gn:country_code":"KR",
    "gn:dem":3,
    "gn:feature_class":"P",
    "gn:feature_code":"PPL",
    "gn:name":"Haengw\u014fl-li",
    "gn:population":0,
    "gn:timezone":"Asia/Seoul",
    "iso:country":"KR",
    "name:und_x_variant":[
        "Haengw\u014fn-ni",
        "Haengw\u014fl-li"
    ],
    "wof:name":"Haengwol-li",
    "wof:placetype":"locality"
},
  "geometry": {"coordinates":[126.81194000000001,33.55361],"type":"Point"}
}