{
  "type": "Feature",
  "properties": {
    "gn:admin1_code":"16.0",
    "gn:asciiname":"Gyeoru",
    "gn:country_code":"KR",
    "gn:dem":98,
    "gn:feature_class":"P",
    "gn:feature_code":"PPL",
    "gn:name":"Gyeoru",
    "gn:population":0,
    "gn:timezone":"Asia/Seoul",
    "iso:country":"KR",
    "name:kor_x_preferred":[
        "\uacb0\uc6b0"
    ],
    "name:und_x_variant":[
        "Ky\u014fru-ri"
    ],
    "wof:name":"Gyeoru",
    "wof:placetype":"locality"
},
  "geometry": {"coordinates":[126.99853,34.98982],"type":"Point"}
}