{
  "type": "Feature",
  "properties": {
    "gn:admin1_code":"16.0",
    "gn:asciiname":"Jangpung",
    "gn:country_code":"KR",
    "gn:dem":13,
    "gn:feature_class":"P",
    "gn:feature_code":"PPL",
    "gn:name":"Jangpung",
    "gn:population":0,
    "gn:timezone":"Asia/Seoul",
    "iso:country":"KR",
    "name:kor_x_preferred":[
        "Changp\u2019ung"
    ],
    "name:kor_x_variant":[
        "\uc7a5\ud48d"
    ],
    "wof:name":"Jangpung",
    "wof:placetype":"locality"
},
  "geometry": {"coordinates":[126.80714,34.38619],"type":"Point"}
}