{
  "type": "Feature",
  "properties": {
    "gn:admin1_code":"13.0",
    "gn:asciiname":"Mokjeokgol",
    "gn:country_code":"KR",
    "gn:dem":71,
    "gn:feature_class":"P",
    "gn:feature_code":"PPL",
    "gn:name":"Mokjeokgol",
    "gn:population":0,
    "gn:timezone":"Asia/Seoul",
    "iso:country":"KR",
    "name:und_x_variant":[
        "\uba39\uc801\uace8",
        "M\u014fkch\u014fk-kol",
        "Mokjeokgol"
    ],
    "wof:name":"Mokjeokgol",
    "wof:placetype":"locality"
},
  "geometry": {"coordinates":[127.03352,37.77727],"type":"Point"}
}