{
  "type": "Feature",
  "properties": {
    "gn:admin1_code":"6.0",
    "gn:asciiname":"Sanggilseong",
    "gn:country_code":"KR",
    "gn:dem":195,
    "gn:feature_class":"P",
    "gn:feature_code":"PPL",
    "gn:name":"Sanggilseong",
    "gn:population":0,
    "gn:timezone":"Asia/Seoul",
    "iso:country":"KR",
    "name:kor_x_preferred":[
        "\uc0c1\uae38\uc131"
    ],
    "wof:name":"Sanggilseong",
    "wof:placetype":"locality"
},
  "geometry": {"coordinates":[127.22454999999999,38.15625],"type":"Point"}
}