{
  "type": "Feature",
  "properties": {
    "gn:admin1_code":"6.0",
    "gn:asciiname":"Supan",
    "gn:country_code":"KR",
    "gn:dem":637,
    "gn:feature_class":"P",
    "gn:feature_code":"PPL",
    "gn:name":"Supan",
    "gn:population":0,
    "gn:timezone":"Asia/Seoul",
    "iso:country":"KR",
    "name:kor_x_preferred":[
        "\uc232\uc548"
    ],
    "wof:name":"Supan",
    "wof:placetype":"locality"
},
  "geometry": {"coordinates":[128.92600000000002,37.3543],"type":"Point"}
}