{
  "type": "Feature",
  "properties": {
    "gn:admin1_code":"20.0",
    "gn:asciiname":"Panggye",
    "gn:country_code":"KR",
    "gn:dem":31,
    "gn:feature_class":"P",
    "gn:feature_code":"PPL",
    "gn:name":"Panggye",
    "gn:population":0,
    "gn:timezone":"Asia/Seoul",
    "iso:country":"KR",
    "name:und_x_variant":[
        "Panggye-ri",
        "\ubc29\uacc4",
        "Panggye"
    ],
    "wof:name":"Panggye",
    "wof:placetype":"locality"
},
  "geometry": {"coordinates":[128.37747999999999,35.48348],"type":"Point"}
}