{
  "type": "Feature",
  "properties": {
    "gn:admin1_code":"13.0",
    "gn:asciiname":"Son'gok",
    "gn:country_code":"KR",
    "gn:dem":15,
    "gn:feature_class":"P",
    "gn:feature_code":"PPL",
    "gn:name":"S\u014fn\u2019gok",
    "gn:population":0,
    "gn:timezone":"Asia/Seoul",
    "iso:country":"KR",
    "name:und_x_variant":[
        "S\u014fkkok",
        "S\u014fn\u2019gok"
    ],
    "wof:name":"Son'gok",
    "wof:placetype":"locality"
},
  "geometry": {"coordinates":[126.78417,37.33917],"type":"Point"}
}