{
  "type": "Feature",
  "properties": {
    "gn:admin1_code":"13.0",
    "gn:asciiname":"Yeonhwadong",
    "gn:country_code":"KR",
    "gn:dem":78,
    "gn:feature_class":"P",
    "gn:feature_code":"PPL",
    "gn:name":"Yeonhwadong",
    "gn:population":0,
    "gn:timezone":"Asia/Seoul",
    "iso:country":"KR",
    "name:kor_x_preferred":[
        "\uc5f0\ud654\ub3d9"
    ],
    "name:kor_x_variant":[
        "Y\u014fnhwa-dong"
    ],
    "wof:name":"Yeonhwadong",
    "wof:placetype":"locality"
},
  "geometry": {"coordinates":[127.545,37.0947],"type":"Point"}
}