{
  "type": "Feature",
  "properties": {
    "gn:admin1_code":"3.0",
    "gn:asciiname":"Hadu",
    "gn:country_code":"KR",
    "gn:dem":201,
    "gn:feature_class":"P",
    "gn:feature_code":"PPL",
    "gn:name":"Hadu",
    "gn:population":0,
    "gn:timezone":"Asia/Seoul",
    "iso:country":"KR",
    "name:und_x_variant":[
        "\ud558\ub450",
        "Hadu"
    ],
    "wof:name":"Hadu",
    "wof:placetype":"locality"
},
  "geometry": {"coordinates":[127.19784,35.52511],"type":"Point"}
}