{
  "type": "Feature",
  "properties": {
    "gn:admin1_code":"3.0",
    "gn:asciiname":"Wolp'o-ri",
    "gn:country_code":"KR",
    "gn:dem":275,
    "gn:feature_class":"P",
    "gn:feature_code":"PPLL",
    "gn:name":"W\u014flp\u2019o-ri",
    "gn:population":0,
    "gn:timezone":"Asia/Seoul",
    "iso:country":"KR",
    "name:und_x_variant":[
        "W\u014flp\u2019o",
        "\uc6d4\ud3ec\ub9ac",
        "W\u014flp\u2019o-ri"
    ],
    "wof:name":"Wolp'o-ri",
    "wof:placetype":"locality"
},
  "geometry": {"coordinates":[127.47711,35.86625],"type":"Point"}
}