{
  "type": "Feature",
  "properties": {
    "gn:admin1_code":"16.0",
    "gn:asciiname":"Gaesandong",
    "gn:country_code":"KR",
    "gn:dem":100,
    "gn:feature_class":"P",
    "gn:feature_code":"PPL",
    "gn:name":"Gaesandong",
    "gn:population":0,
    "gn:timezone":"Asia/Seoul",
    "iso:country":"KR",
    "name:kor_x_preferred":[
        "\uac1c\uc0b0\ub3d9"
    ],
    "name:und_x_variant":[
        "Kaesan",
        "Kyew\u014fn-ni",
        "Kyesan",
        "Kyew\u014fn",
        "Gaesandong"
    ],
    "wof:name":"Gaesandong",
    "wof:placetype":"locality"
},
  "geometry": {"coordinates":[126.79909000000001,34.74663],"type":"Point"}
}