{
  "type": "Feature",
  "properties": {
    "gn:admin1_code":"6.0",
    "gn:asciiname":"Chaen-mal",
    "gn:country_code":"KR",
    "gn:dem":565,
    "gn:feature_class":"P",
    "gn:feature_code":"PPL",
    "gn:name":"Chaen-mal",
    "gn:population":0,
    "gn:timezone":"Asia/Seoul",
    "iso:country":"KR",
    "name:kor_x_preferred":[
        "\uc7bf\ub9d0"
    ],
    "wof:name":"Chaen-mal",
    "wof:placetype":"locality"
},
  "geometry": {"coordinates":[128.6397,37.1758],"type":"Point"}
}