{
  "type": "Feature",
  "properties": {
    "gn:admin1_code":"5.0",
    "gn:asciiname":"Changt'ogo-ri",
    "gn:country_code":"KR",
    "gn:dem":202,
    "gn:feature_class":"P",
    "gn:feature_code":"PPL",
    "gn:name":"Changt\u2019\u014fg\u014f-ri",
    "gn:population":0,
    "gn:timezone":"Asia/Seoul",
    "iso:country":"KR",
    "name:kor_x_preferred":[
        "\uc7a5\ud130\uac70\ub9ac"
    ],
    "name:kor_x_variant":[
        "Changt\u2019\u014fg\u014f-ri"
    ],
    "wof:name":"Changt'ogo-ri",
    "wof:placetype":"locality"
},
  "geometry": {"coordinates":[128.41650000000001,37.0944],"type":"Point"}
}