{
  "type": "Feature",
  "properties": {
    "gn:admin1_code":"17.0",
    "gn:asciiname":"An'gojan",
    "gn:country_code":"KR",
    "gn:dem":18,
    "gn:feature_class":"P",
    "gn:feature_code":"PPL",
    "gn:name":"An\u2019gojan",
    "gn:population":0,
    "gn:timezone":"Asia/Seoul",
    "iso:country":"KR",
    "name:und_x_variant":[
        "\uc548\uace0\uc794",
        "An\u2019gojan"
    ],
    "wof:name":"An'gojan",
    "wof:placetype":"locality"
},
  "geometry": {"coordinates":[126.3685,36.7139],"type":"Point"}
}