{
  "type": "Feature",
  "properties": {
    "gn:admin1_code":"14.0",
    "gn:asciiname":"Simok",
    "gn:country_code":"KR",
    "gn:dem":202,
    "gn:feature_class":"P",
    "gn:feature_code":"PPL",
    "gn:name":"Simok",
    "gn:population":0,
    "gn:timezone":"Asia/Seoul",
    "iso:country":"KR",
    "name:und_x_variant":[
        "\uc2dc\ubaa9",
        "Simok"
    ],
    "wof:name":"Simok",
    "wof:placetype":"locality"
},
  "geometry": {"coordinates":[128.80882,36.38673],"type":"Point"}
}