{
  "type": "Feature",
  "properties": {
    "gn:admin1_code":"14.0",
    "gn:asciiname":"Munch'i-gol",
    "gn:country_code":"KR",
    "gn:dem":60,
    "gn:feature_class":"P",
    "gn:feature_code":"PPL",
    "gn:name":"Munch\u2019i-gol",
    "gn:population":0,
    "gn:timezone":"Asia/Seoul",
    "iso:country":"KR",
    "name:und_x_variant":[
        "\ubb38\uce58\uace8",
        "Munch\u2019i-gol"
    ],
    "wof:name":"Munch'i-gol",
    "wof:placetype":"locality"
},
  "geometry": {"coordinates":[128.27515,35.9592],"type":"Point"}
}