{
  "type": "Feature",
  "properties": {
    "gn:admin1_code":"6.0",
    "gn:asciiname":"Suppakke",
    "gn:country_code":"KR",
    "gn:dem":198,
    "gn:feature_class":"P",
    "gn:feature_code":"PPL",
    "gn:name":"Suppakke",
    "gn:population":0,
    "gn:timezone":"Asia/Seoul",
    "iso:country":"KR",
    "name:und_x_variant":[
        "Supbakke",
        "\uc232\ubc16\uc5d0",
        "Suppakke"
    ],
    "wof:name":"Suppakke",
    "wof:placetype":"locality"
},
  "geometry": {"coordinates":[127.79667000000001,38.06333],"type":"Point"}
}