{
  "type": "Feature",
  "properties": {
    "gn:admin1_code":"14.0",
    "gn:asciiname":"Malmudeom",
    "gn:country_code":"KR",
    "gn:dem":88,
    "gn:feature_class":"P",
    "gn:feature_code":"PPL",
    "gn:name":"Malmudeom",
    "gn:population":0,
    "gn:timezone":"Asia/Seoul",
    "iso:country":"KR",
    "name:kor_x_preferred":[
        "\ub9d0\ubb34\ub364"
    ],
    "wof:name":"Malmudeom",
    "wof:placetype":"locality"
},
  "geometry": {"coordinates":[129.28088,35.74507],"type":"Point"}
}