{
  "type": "Feature",
  "properties": {
    "gn:admin1_code":"13.0",
    "gn:asciiname":"Sum-mal",
    "gn:country_code":"KR",
    "gn:dem":74,
    "gn:feature_class":"P",
    "gn:feature_code":"PPL",
    "gn:name":"Sum-mal",
    "gn:population":0,
    "gn:timezone":"Asia/Seoul",
    "iso:country":"KR",
    "name:und_x_variant":[
        "\uc232\ub9d0",
        "Sum-mal"
    ],
    "wof:name":"Sum-mal",
    "wof:placetype":"locality"
},
  "geometry": {"coordinates":[127.71333,37.32806],"type":"Point"}
}