{
  "type": "Feature",
  "properties": {
    "gn:admin1_code":"17.0",
    "gn:asciiname":"Sukjingol",
    "gn:country_code":"KR",
    "gn:dem":20,
    "gn:feature_class":"P",
    "gn:feature_code":"PPL",
    "gn:name":"Sukjingol",
    "gn:population":0,
    "gn:timezone":"Asia/Seoul",
    "iso:country":"KR",
    "name:kor_x_preferred":[
        "\uc219\uc9c4\uace8"
    ],
    "wof:name":"Sukjingol",
    "wof:placetype":"locality"
},
  "geometry": {"coordinates":[127.14743,36.25476],"type":"Point"}
}