{
  "type": "Feature",
  "properties": {
    "gn:admin1_code":"6.0",
    "gn:asciiname":"Chanda-ri",
    "gn:country_code":"KR",
    "gn:dem":209,
    "gn:feature_class":"P",
    "gn:feature_code":"PPL",
    "gn:name":"Chanda-ri",
    "gn:population":0,
    "gn:timezone":"Asia/Seoul",
    "iso:country":"KR",
    "name:kor_x_preferred":[
        "\uc794\ub2e4\ub9ac"
    ],
    "wof:name":"Chanda-ri",
    "wof:placetype":"locality"
},
  "geometry": {"coordinates":[128.45009999999999,37.1859],"type":"Point"}
}