{
  "type": "Feature",
  "properties": {
    "gn:admin1_code":"14.0",
    "gn:asciiname":"Songgol",
    "gn:country_code":"KR",
    "gn:dem":172,
    "gn:feature_class":"P",
    "gn:feature_code":"PPL",
    "gn:name":"Songgol",
    "gn:population":0,
    "gn:timezone":"Asia/Seoul",
    "iso:country":"KR",
    "name:kor_x_preferred":[
        "\uc1a1\uace8"
    ],
    "wof:name":"Songgol",
    "wof:placetype":"locality"
},
  "geometry": {"coordinates":[128.96066999999999,36.58467],"type":"Point"}
}