{
  "type": "Feature",
  "properties": {
    "gn:admin1_code":"14.0",
    "gn:asciiname":"Yeji-ri",
    "gn:country_code":"KR",
    "gn:dem":103,
    "gn:feature_class":"P",
    "gn:feature_code":"PPLL",
    "gn:name":"Yeji-ri",
    "gn:population":0,
    "gn:timezone":"Asia/Seoul",
    "iso:country":"KR",
    "name:und_x_variant":[
        "\uc608\uc9c0\ub9ac",
        "Yeji-ri"
    ],
    "wof:name":"Yeji-ri",
    "wof:placetype":"locality"
},
  "geometry": {"coordinates":[128.04721999999998,36.14692],"type":"Point"}
}