{
  "type": "Feature",
  "properties": {
    "iso:country":"KR",
    "name:eng_x_preferred":[
        "Happo-dong"
    ],
    "name:kor_x_preferred":[
        "\ud569\ud3ec\ub3d9"
    ],
    "qs:name":"\ud569\ud3ec\ub3d9",
    "qs:name_adm0":"\ud55c\uad6d",
    "qs:name_adm1":"\uacbd\uc0c1\ub0a8\ub3c4",
    "qs:photos":39,
    "qs:photos_1k":8,
    "qs:photos_9k":1,
    "qs:photos_9r":2,
    "qs:photos_all":39,
    "qs:photos_sr":2,
    "qs:placetype":"LocalAdmin",
    "qs:pop_sr":"0",
    "wof:name":"Happo-dong",
    "wof:placetype":"localadmin"
},
  "geometry": {"coordinates":[128.57025100000001,35.251226],"type":"Point"}
}