{
  "type": "Feature",
  "properties": {
    "gn:admin1_code":"20.0",
    "gn:asciiname":"Kumsong",
    "gn:cc2":"KR",
    "gn:country_code":"KR",
    "gn:dem":96,
    "gn:feature_class":"P",
    "gn:feature_code":"PPL",
    "gn:name":"K\u016dmsong",
    "gn:population":0,
    "gn:timezone":"Asia/Seoul",
    "iso:country":"KR",
    "name:und_x_variant":[
        "K\u016dmsong-ni",
        "K\u016dmsong"
    ],
    "wof:name":"Kumsong",
    "wof:placetype":"locality"
},
  "geometry": {"coordinates":[128.01667,34.81667],"type":"Point"}
}