{
  "type": "Feature",
  "properties": {
    "gn:admin1_code":"3.0",
    "gn:asciiname":"Chong-dong",
    "gn:country_code":"KR",
    "gn:dem":547,
    "gn:feature_class":"P",
    "gn:feature_code":"PPL",
    "gn:name":"Ch\u014fng-dong",
    "gn:population":0,
    "gn:timezone":"Asia/Seoul",
    "iso:country":"KR",
    "name:und_x_variant":[
        "\uc815\ub3d9",
        "Ch\u014fng-dong"
    ],
    "wof:name":"Chong-dong",
    "wof:placetype":"locality"
},
  "geometry": {"coordinates":[127.49924,35.72739],"type":"Point"}
}