{
  "type": "Feature",
  "properties": {
    "gn:admin1_code":"5.0",
    "gn:asciiname":"Dalsin",
    "gn:country_code":"KR",
    "gn:dem":73,
    "gn:feature_class":"P",
    "gn:feature_code":"PPL",
    "gn:name":"Dalsin",
    "gn:population":0,
    "gn:timezone":"Asia/Seoul",
    "iso:country":"KR",
    "name:kor_x_preferred":[
        "\ub2ec\uc2e0"
    ],
    "wof:name":"Dalsin",
    "wof:placetype":"locality"
},
  "geometry": {"coordinates":[127.90441,36.96494000000001],"type":"Point"}
}