{
  "type": "Feature",
  "properties": {
    "gn:admin1_code":"5.0",
    "gn:asciiname":"Chamsaemgol",
    "gn:country_code":"KR",
    "gn:dem":91,
    "gn:feature_class":"P",
    "gn:feature_code":"PPL",
    "gn:name":"Chamsaemgol",
    "gn:population":0,
    "gn:timezone":"Asia/Seoul",
    "iso:country":"KR",
    "name:kor_x_preferred":[
        "\ucc38\uc0d8\uace8"
    ],
    "name:kor_x_variant":[
        "Ch\u2019amsaem-gol"
    ],
    "wof:name":"Chamsaemgol",
    "wof:placetype":"locality"
},
  "geometry": {"coordinates":[127.92983,37.07084],"type":"Point"}
}