{
  "type": "Feature",
  "properties": {
    "gn:admin1_code":"6.0",
    "gn:asciiname":"Gujindae",
    "gn:country_code":"KR",
    "gn:dem":242,
    "gn:feature_class":"P",
    "gn:feature_code":"PPL",
    "gn:name":"Gujindae",
    "gn:population":0,
    "gn:timezone":"Asia/Seoul",
    "iso:country":"KR",
    "name:kor_x_preferred":[
        "\uad6c\uc9c4\ub300"
    ],
    "wof:name":"Gujindae",
    "wof:placetype":"locality"
},
  "geometry": {"coordinates":[127.67173,37.87638],"type":"Point"}
}