{
  "type": "Feature",
  "properties": {
    "gn:admin1_code":"14.0",
    "gn:asciiname":"Gakseo",
    "gn:country_code":"KR",
    "gn:dem":233,
    "gn:feature_class":"P",
    "gn:feature_code":"PPL",
    "gn:name":"Gakseo",
    "gn:population":0,
    "gn:timezone":"Asia/Seoul",
    "iso:country":"KR",
    "name:kor_x_preferred":[
        "\uac01\uc11c"
    ],
    "name:und_x_variant":[
        "Kaks\u014f-ri",
        "Kaks\u014f",
        "Gakseo"
    ],
    "wof:name":"Gakseo",
    "wof:placetype":"locality"
},
  "geometry": {"coordinates":[128.06953999999999,36.74292],"type":"Point"}
}