{
  "type": "Feature",
  "properties": {
    "gn:admin1_code":"13.0",
    "gn:asciiname":"Gwangchon",
    "gn:country_code":"KR",
    "gn:dem":125,
    "gn:feature_class":"P",
    "gn:feature_code":"PPL",
    "gn:name":"Gwangchon",
    "gn:population":0,
    "gn:timezone":"Asia/Seoul",
    "iso:country":"KR",
    "name:und_x_variant":[
        "\uad11\ucd0c",
        "Kwang-ch\u2019on",
        "Gwangchon"
    ],
    "wof:name":"Gwangchon",
    "wof:placetype":"locality"
},
  "geometry": {"coordinates":[127.18917,37.82809],"type":"Point"}
}