{
  "type": "Feature",
  "properties": {
    "gn:admin1_code":"14.0",
    "gn:asciiname":"Myonggan",
    "gn:country_code":"KR",
    "gn:dem":60,
    "gn:feature_class":"P",
    "gn:feature_code":"PPL",
    "gn:name":"My\u014fnggan",
    "gn:population":0,
    "gn:timezone":"Asia/Seoul",
    "iso:country":"KR",
    "name:und_x_variant":[
        "\uba85\uac04",
        "My\u014fnggan"
    ],
    "wof:name":"Myonggan",
    "wof:placetype":"locality"
},
  "geometry": {"coordinates":[128.23036999999999,35.93194000000001],"type":"Point"}
}