{
  "type": "Feature",
  "properties": {
    "gn:admin1_code":"17.0",
    "gn:asciiname":"Hansongji",
    "gn:country_code":"KR",
    "gn:dem":17,
    "gn:feature_class":"P",
    "gn:feature_code":"PPL",
    "gn:name":"Hans\u014fngji",
    "gn:population":0,
    "gn:timezone":"Asia/Seoul",
    "iso:country":"KR",
    "name:und_x_variant":[
        "\ud55c\uc131\uc9c0",
        "Hans\u014fngji"
    ],
    "wof:name":"Hansongji",
    "wof:placetype":"locality"
},
  "geometry": {"coordinates":[126.4791,36.7641],"type":"Point"}
}