{
  "type": "Feature",
  "properties": {
    "gn:admin1_code":"6.0",
    "gn:asciiname":"Orimchon",
    "gn:country_code":"KR",
    "gn:dem":156,
    "gn:feature_class":"P",
    "gn:feature_code":"PPL",
    "gn:name":"Orimchon",
    "gn:population":0,
    "gn:timezone":"Asia/Seoul",
    "iso:country":"KR",
    "name:kor_x_preferred":[
        "\uc624\ub9bc\ucd0c"
    ],
    "wof:name":"Orimchon",
    "wof:placetype":"locality"
},
  "geometry": {"coordinates":[127.9438,37.76065],"type":"Point"}
}