{
  "type": "Feature",
  "properties": {
    "iso:country":"KR",
    "name:eng_x_preferred":[
        "Yongju-myeon"
    ],
    "name:kor_x_preferred":[
        "\uc6a9\uc8fc\uba74"
    ],
    "qs:name":"\uc6a9\uc8fc\uba74",
    "qs:name_adm0":"\ud55c\uad6d",
    "qs:name_adm1":"\uacbd\uc0c1\ub0a8\ub3c4",
    "qs:photos":8,
    "qs:photos_1k":2,
    "qs:photos_9k":1,
    "qs:photos_9r":1,
    "qs:photos_all":8,
    "qs:photos_sr":1,
    "qs:placetype":"LocalAdmin",
    "qs:pop_sr":"0",
    "wof:name":"Yongju-myeon",
    "wof:placetype":"localadmin"
},
  "geometry": {"coordinates":[128.07535100000001,35.634174],"type":"Point"}
}