{
  "type": "Feature",
  "properties": {
    "gn:admin1_code":"5.0",
    "gn:asciiname":"Josil",
    "gn:country_code":"KR",
    "gn:dem":248,
    "gn:feature_class":"P",
    "gn:feature_code":"PPL",
    "gn:name":"Josil",
    "gn:population":0,
    "gn:timezone":"Asia/Seoul",
    "iso:country":"KR",
    "name:kor_x_preferred":[
        "\uc870\uc2e4"
    ],
    "wof:name":"Josil",
    "wof:placetype":"locality"
},
  "geometry": {"coordinates":[127.61462,36.62056],"type":"Point"}
}