{
  "type": "Feature",
  "properties": {
    "iso:country":"KR",
    "name:kor_x_preferred":[
        "\uc74d\ub0b4\ub3d9"
    ],
    "name:kor_x_variant":[
        "\ub0b4\ub3d9"
    ],
    "name:und_x_variant":[
        "Naedong"
    ],
    "qs:gn_adm0_cc":"KR",
    "qs:gn_fcode":"PPL",
    "qs:gn_local":1835329,
    "qs:gn_namadm1":"10",
    "qs:gn_name":"Naedong",
    "qs:local_max":1440,
    "qs:local_sum":5303,
    "qs:localhoods":33,
    "qs:name":"\uc74d\ub0b4\ub3d9",
    "qs:name_adm0":"\ud55c\uad6d",
    "qs:name_adm1":"\ub300\uad6c",
    "qs:name_adm2":"\ubd81\uad6c",
    "qs:name_lau":"\uc74d\ub0b4\ub3d9",
    "qs:name_local":"\ub300\uad6c",
    "qs:photo_max":7,
    "qs:photo_sum":14,
    "qs:placetype":"Suburb",
    "qs:quad_count":4,
    "qs:woe_adm0":23424868,
    "qs:woe_adm1":2345971,
    "qs:woe_adm2":28289119,
    "qs:woe_lau":28806247,
    "qs:woe_local":1132466,
    "qs:woe_ver":"7.10.0",
    "wof:lang":[
        "kor"
    ],
    "wof:name":"\uc74d\ub0b4\ub3d9",
    "wof:placetype":"neighbourhood"
},
  "geometry": {"coordinates":[128.565934,35.953236],"type":"Point"}
}