{
  "type": "Feature",
  "properties": {
    "gn:admin1_code":"14.0",
    "gn:asciiname":"Taep'yong",
    "gn:country_code":"KR",
    "gn:dem":146,
    "gn:feature_class":"P",
    "gn:feature_code":"PPL",
    "gn:name":"Taep\u2019y\u014fng",
    "gn:population":0,
    "gn:timezone":"Asia/Seoul",
    "iso:country":"KR",
    "name:und_x_variant":[
        "Taep\u2019y\u014fng",
        "\ub300\ud3c9"
    ],
    "wof:name":"Taep'yong",
    "wof:placetype":"locality"
},
  "geometry": {"coordinates":[128.13052999999999,36.00628],"type":"Point"}
}