{
  "type": "Feature",
  "properties": {
    "gn:admin1_code":"20.0",
    "gn:asciiname":"Taech'i-ri",
    "gn:country_code":"KR",
    "gn:dem":100,
    "gn:feature_class":"P",
    "gn:feature_code":"PPL",
    "gn:name":"Taech\u2019i-ri",
    "gn:population":0,
    "gn:timezone":"Asia/Seoul",
    "iso:country":"KR",
    "name:und_x_variant":[
        "Taech\u2019i",
        "Taech\u2019i-ri"
    ],
    "wof:name":"Taech'i-ri",
    "wof:placetype":"locality"
},
  "geometry": {"coordinates":[127.88443999999998,34.97028],"type":"Point"}
}