{
  "type": "Feature",
  "properties": {
    "gn:admin1_code":"13.0",
    "gn:asciiname":"Beolmal",
    "gn:country_code":"KR",
    "gn:dem":80,
    "gn:feature_class":"P",
    "gn:feature_code":"PPL",
    "gn:name":"Beolmal",
    "gn:population":0,
    "gn:timezone":"Asia/Seoul",
    "iso:country":"KR",
    "name:kor_x_preferred":[
        "\ubc8c\ub9d0"
    ],
    "wof:name":"Beolmal",
    "wof:placetype":"locality"
},
  "geometry": {"coordinates":[127.61547,37.50754000000001],"type":"Point"}
}