{
  "type": "Feature",
  "properties": {
    "gn:admin1_code":"17.0",
    "gn:asciiname":"Ch'onan-gol",
    "gn:country_code":"KR",
    "gn:dem":15,
    "gn:feature_class":"P",
    "gn:feature_code":"PPL",
    "gn:name":"Ch\u2019\u014fnan-gol",
    "gn:population":0,
    "gn:timezone":"Asia/Seoul",
    "iso:country":"KR",
    "name:und_x_variant":[
        "\ucc9c\uc548\uace8",
        "Ch\u2019\u014fnan-gol"
    ],
    "wof:name":"Ch'onan-gol",
    "wof:placetype":"locality"
},
  "geometry": {"coordinates":[126.2334,36.7199],"type":"Point"}
}