{
  "type": "Feature",
  "properties": {
    "gn:admin1_code":"14.0",
    "gn:asciiname":"Mangdudul",
    "gn:country_code":"KR",
    "gn:dem":354,
    "gn:feature_class":"P",
    "gn:feature_code":"PPL",
    "gn:name":"Mangdud\u016dl",
    "gn:population":0,
    "gn:timezone":"Asia/Seoul",
    "iso:country":"KR",
    "name:und_x_variant":[
        "\ub9dd\ub450\ub4e4",
        "Mangdud\u016dl"
    ],
    "wof:name":"Mangdudul",
    "wof:placetype":"locality"
},
  "geometry": {"coordinates":[129.03280000000001,36.7567],"type":"Point"}
}