{
  "type": "Feature",
  "properties": {
    "gn:admin1_code":"13.0",
    "gn:asciiname":"Hadabu-ri",
    "gn:country_code":"KR",
    "gn:dem":57,
    "gn:feature_class":"P",
    "gn:feature_code":"PPL",
    "gn:name":"Hadabu-ri",
    "gn:population":0,
    "gn:timezone":"Asia/Seoul",
    "iso:country":"KR",
    "name:und_x_variant":[
        "\ud558\ub2e4\ubd80\ub9ac",
        "Hadabu-ri"
    ],
    "wof:name":"Hadabu-ri",
    "wof:placetype":"locality"
},
  "geometry": {"coordinates":[127.5325,37.34472],"type":"Point"}
}