{
  "type": "Feature",
  "properties": {
    "gn:admin1_code":"16.0",
    "gn:asciiname":"Mandong-ni",
    "gn:country_code":"KR",
    "gn:dem":44,
    "gn:feature_class":"P",
    "gn:feature_code":"PPL",
    "gn:name":"Mand\u014fng-ni",
    "gn:population":0,
    "gn:timezone":"Asia/Seoul",
    "iso:country":"KR",
    "name:kor_x_preferred":[
        "\uac74\ub108\ub3d9"
    ],
    "name:kor_x_variant":[
        "Mand\u014fng-ni"
    ],
    "wof:name":"Mandong-ni",
    "wof:placetype":"locality"
},
  "geometry": {"coordinates":[126.68694000000001,34.48944],"type":"Point"}
}