{
  "type": "Feature",
  "properties": {
    "gn:admin1_code":"13.0",
    "gn:asciiname":"Keunhwang-gol",
    "gn:country_code":"KR",
    "gn:dem":214,
    "gn:feature_class":"P",
    "gn:feature_code":"PPL",
    "gn:name":"Keunhwang-gol",
    "gn:population":0,
    "gn:timezone":"Asia/Seoul",
    "iso:country":"KR",
    "name:und_x_variant":[
        "\ud070\ud669\uace8",
        "Keunhwang-gol",
        "K\u016dnhwang-gol"
    ],
    "wof:name":"Keunhwang-gol",
    "wof:placetype":"locality"
},
  "geometry": {"coordinates":[127.74278,37.38917],"type":"Point"}
}