{
  "type": "Feature",
  "properties": {
    "gn:admin1_code":"1.0",
    "gn:asciiname":"Yonp'yong-ni",
    "gn:country_code":"KR",
    "gn:dem":22,
    "gn:feature_class":"P",
    "gn:feature_code":"PPL",
    "gn:name":"Y\u014fnp\u2019y\u014fng-ni",
    "gn:population":0,
    "gn:timezone":"Asia/Seoul",
    "iso:country":"KR",
    "name:eng_x_preferred":[
        "Yonp'yong"
    ],
    "name:eng_x_variant":[
        "Yonp'yong-ni"
    ],
    "wof:name":"Yonp'yong",
    "wof:placetype":"locality"
},
  "geometry": {"coordinates":[126.94861,33.50444],"type":"Point"}
}