{
  "type": "Feature",
  "properties": {
    "gn:admin1_code":"17.0",
    "gn:asciiname":"Haanyong",
    "gn:country_code":"KR",
    "gn:dem":27,
    "gn:feature_class":"P",
    "gn:feature_code":"PPL",
    "gn:name":"Haany\u014fng",
    "gn:population":0,
    "gn:timezone":"Asia/Seoul",
    "iso:country":"KR",
    "name:und_x_variant":[
        "\ud558\uc548\uc601",
        "Haany\u014fng"
    ],
    "wof:name":"Haanyong",
    "wof:placetype":"locality"
},
  "geometry": {"coordinates":[127.04089999999999,36.4724],"type":"Point"}
}