{
  "type": "Feature",
  "properties": {
    "gn:admin1_code":"5.0",
    "gn:asciiname":"Jingwiri",
    "gn:country_code":"KR",
    "gn:dem":182,
    "gn:feature_class":"P",
    "gn:feature_code":"PPL",
    "gn:name":"Jingwiri",
    "gn:population":0,
    "gn:timezone":"Asia/Seoul",
    "iso:country":"KR",
    "name:kor_x_preferred":[
        "\uc9c4\uac70\ub9ac"
    ],
    "name:kor_x_variant":[
        "Chin\u2019g\u014f-ri",
        "\uc9c4\uadc0\ub9ac"
    ],
    "wof:name":"Jingwiri",
    "wof:placetype":"locality"
},
  "geometry": {"coordinates":[128.51372000000001,37.07854],"type":"Point"}
}