{
  "type": "Feature",
  "properties": {
    "gn:admin1_code":"13.0",
    "gn:asciiname":"Sangseojae",
    "gn:country_code":"KR",
    "gn:dem":16,
    "gn:feature_class":"P",
    "gn:feature_code":"PPL",
    "gn:name":"Sangseojae",
    "gn:population":0,
    "gn:timezone":"Asia/Seoul",
    "iso:country":"KR",
    "name:und_x_variant":[
        "\uc0c1\uc11c\uc7ac",
        "Sangseojae",
        "Sangs\u014fjae"
    ],
    "wof:name":"Sangseojae",
    "wof:placetype":"locality"
},
  "geometry": {"coordinates":[127.10657999999999,37.01495],"type":"Point"}
}