{
  "type": "Feature",
  "properties": {
    "gn:admin1_code":"11.0",
    "gn:asciiname":"Ui-dong",
    "gn:country_code":"KR",
    "gn:dem":129,
    "gn:feature_class":"P",
    "gn:feature_code":"PPL",
    "gn:name":"Ui-dong",
    "gn:population":0,
    "gn:timezone":"Asia/Seoul",
    "iso:country":"KR",
    "name:ceb_x_preferred":[
        "Ui-dong"
    ],
    "name:fas_x_preferred":[
        "\u0627\u0648\u06cc-\u062f\u0648\u0646\u06af"
    ],
    "name:kor_x_preferred":[
        "\uc6b0\uc774\ub3d9"
    ],
    "name:msa_x_preferred":[
        "Ui-dong"
    ],
    "name:swe_x_preferred":[
        "Ui-dong"
    ],
    "name:tha_x_preferred":[
        "\u0e41\u0e02\u0e27\u0e07\u0e2d\u0e39\u0e2d\u0e35"
    ],
    "name:vie_x_preferred":[
        "Ui-dong"
    ],
    "wof:name":"Ui-dong",
    "wof:placetype":"locality"
},
  "geometry": {"coordinates":[127.01667,37.66667],"type":"Point"}
}