{
  "type": "Feature",
  "properties": {
    "gn:admin1_code":"11.0",
    "gn:asciiname":"Ui-dong",
    "gn:country_code":"KR",
    "gn:dem":129,
    "gn:feature_class":"P",
    "gn:feature_code":"PPL",
    "gn:name":"Ui-dong",
    "gn:population":0,
    "gn:timezone":"Asia/Seoul",
    "iso:country":"KR",
    "wof:name":"Ui-dong",
    "wof:placetype":"locality"
},
  "geometry": {"coordinates":[127.01667,37.66667],"type":"Point"}
}