{
  "type": "Feature",
  "properties": {
    "gn:admin1_code":"13.0",
    "gn:asciiname":"Deogwi",
    "gn:country_code":"KR",
    "gn:dem":46,
    "gn:feature_class":"P",
    "gn:feature_code":"PPL",
    "gn:name":"Deogwi",
    "gn:population":0,
    "gn:timezone":"Asia/Seoul",
    "iso:country":"KR",
    "name:und_x_variant":[
        "\ub355\uc704",
        "Deogwi",
        "T\u014fgwi"
    ],
    "wof:name":"Deogwi",
    "wof:placetype":"locality"
},
  "geometry": {"coordinates":[126.92,37.16528],"type":"Point"}
}