{
  "type": "Feature",
  "properties": {
    "gn:admin1_code":"11.0",
    "gn:asciiname":"Kuuisam-dong",
    "gn:country_code":"KR",
    "gn:dem":58,
    "gn:feature_class":"P",
    "gn:feature_code":"PPL",
    "gn:name":"Ku\u016disam-dong",
    "gn:population":0,
    "gn:timezone":"Asia/Seoul",
    "iso:country":"KR",
    "name:und_x_variant":[
        "\uad6c\uc7583\ub3d9",
        "Ku\u016disam-dong"
    ],
    "wof:name":"Kuuisam-dong",
    "wof:placetype":"locality"
},
  "geometry": {"coordinates":[127.09610000000001,37.53572],"type":"Point"}
}