{
  "type": "Feature",
  "properties": {
    "gn:admin1_code":"11.0",
    "gn:asciiname":"Sin'gilch'il-tong",
    "gn:country_code":"KR",
    "gn:dem":43,
    "gn:feature_class":"P",
    "gn:feature_code":"PPL",
    "gn:name":"Sin\u2019gilch\u2019il-tong",
    "gn:population":0,
    "gn:timezone":"Asia/Seoul",
    "iso:country":"KR",
    "name:eng_x_preferred":[
        "Sin'gilch'il"
    ],
    "name:eng_x_variant":[
        "Sin'gilch'il-tong"
    ],
    "name:und_x_variant":[
        "\uc2e0\uae387\ub3d9",
        "Sin\u2019gilch\u2019il-tong"
    ],
    "wof:name":"Sin'gilch'il",
    "wof:placetype":"locality"
},
  "geometry": {"coordinates":[126.91946,37.50751],"type":"Point"}
}