{
  "type": "Feature",
  "properties": {
    "gn:admin1_code":"13.0",
    "gn:admin2_code":"Yongin-si",
    "gn:asciiname":"Geumhyeon",
    "gn:country_code":"KR",
    "gn:dem":77,
    "gn:feature_class":"P",
    "gn:feature_code":"PPL",
    "gn:name":"Geumhyeon",
    "gn:population":0,
    "gn:timezone":"Asia/Seoul",
    "iso:country":"KR",
    "name:kor_x_preferred":[
        "\uae08\ud604"
    ],
    "name:kor_x_variant":[
        "K\u016dmhy\u014fn"
    ],
    "wof:name":"Geumhyeon",
    "wof:placetype":"locality"
},
  "geometry": {"coordinates":[127.21205999999999,37.1655],"type":"Point"}
}