{
  "type": "Feature",
  "properties": {
    "gn:admin1_code":"20.0",
    "gn:asciiname":"Shinki-ri",
    "gn:country_code":"KR",
    "gn:dem":9,
    "gn:feature_class":"P",
    "gn:feature_code":"PPL",
    "gn:name":"Shinki-ri",
    "gn:population":0,
    "gn:timezone":"Asia/Seoul",
    "iso:country":"KR",
    "name:und_x_variant":[
        "\uc2e0\uae30\ub9ac",
        "Sin\u2019gi-ri"
    ],
    "wof:name":"Shinki-ri",
    "wof:placetype":"locality"
},
  "geometry": {"coordinates":[128.47538,35.1116],"type":"Point"}
}