{
  "type": "Feature",
  "properties": {
    "gn:admin1_code":"13.0",
    "gn:asciiname":"Yongmugol",
    "gn:country_code":"KR",
    "gn:dem":250,
    "gn:feature_class":"P",
    "gn:feature_code":"PPL",
    "gn:name":"Yongmugol",
    "gn:population":0,
    "gn:timezone":"Asia/Seoul",
    "iso:country":"KR",
    "name:und_x_variant":[
        "\uc6a9\ubb34\uace8",
        "Yongmugol"
    ],
    "wof:name":"Yongmugol",
    "wof:placetype":"locality"
},
  "geometry": {"coordinates":[126.9978,37.7415],"type":"Point"}
}