{
  "type": "Feature",
  "properties": {
    "gn:admin1_code":"16.0",
    "gn:asciiname":"Yangjibangchukp'o",
    "gn:country_code":"KR",
    "gn:dem":11,
    "gn:feature_class":"P",
    "gn:feature_code":"PPL",
    "gn:name":"Yangjibangchukp\u2019o",
    "gn:population":0,
    "gn:timezone":"Asia/Seoul",
    "iso:country":"KR",
    "name:kor_x_preferred":[
        "Yangjibangchukp\u2019o"
    ],
    "wof:name":"Yangjibangchukp'o",
    "wof:placetype":"locality"
},
  "geometry": {"coordinates":[126.85306,34.30778],"type":"Point"}
}