{
  "type": "Feature",
  "properties": {
    "gn:admin1_code":"5.0",
    "gn:asciiname":"Samsang-gol",
    "gn:country_code":"KR",
    "gn:dem":367,
    "gn:feature_class":"P",
    "gn:feature_code":"PPL",
    "gn:name":"Samsang-gol",
    "gn:population":0,
    "gn:timezone":"Asia/Seoul",
    "iso:country":"KR",
    "name:kor_x_preferred":[
        "\uc0bc\uc0c1\uace8"
    ],
    "wof:name":"Samsang-gol",
    "wof:placetype":"locality"
},
  "geometry": {"coordinates":[128.0685,37.1294],"type":"Point"}
}