{
  "type": "Feature",
  "properties": {
    "gn:admin1_code":"16.0",
    "gn:asciiname":"Songjon",
    "gn:country_code":"KR",
    "gn:dem":13,
    "gn:feature_class":"P",
    "gn:feature_code":"PPL",
    "gn:name":"Songj\u014fn",
    "gn:population":0,
    "gn:timezone":"Asia/Seoul",
    "iso:country":"KR",
    "name:kor_x_preferred":[
        "Songj\u014fn"
    ],
    "wof:name":"Songjon",
    "wof:placetype":"locality"
},
  "geometry": {"coordinates":[126.93528000000001,34.56944],"type":"Point"}
}