{
  "type": "Feature",
  "properties": {
    "gn:admin1_code":"5.0",
    "gn:asciiname":"Tunggong-ni",
    "gn:country_code":"KR",
    "gn:dem":82,
    "gn:feature_class":"P",
    "gn:feature_code":"PPL",
    "gn:name":"T\u016dnggong-ni",
    "gn:population":0,
    "gn:timezone":"Asia/Seoul",
    "iso:country":"KR",
    "name:und_x_variant":[
        "\ub4f1\uace1\ub9ac",
        "T\u016dnggong-ni"
    ],
    "wof:name":"Tunggong-ni",
    "wof:placetype":"locality"
},
  "geometry": {"coordinates":[127.40730000000001,36.5021],"type":"Point"}
}