{
  "type": "Feature",
  "properties": {
    "gn:admin1_code":"14.0",
    "gn:asciiname":"Sinbong",
    "gn:country_code":"KR",
    "gn:dem":299,
    "gn:feature_class":"P",
    "gn:feature_code":"PPL",
    "gn:name":"Sinbong",
    "gn:population":0,
    "gn:timezone":"Asia/Seoul",
    "iso:country":"KR",
    "name:und_x_variant":[
        "Hwary\u014fngjang-Pongj\u014fng-ni",
        "Pongj\u014fng-ni",
        "Hay\u014fngjang",
        "Hwany\u014fngjang",
        "Hwany\u014fngjang-Pongj\u014fng-ni",
        "Hwary\u014fngjang",
        "\ud654\ub839\uc7a5"
    ],
    "wof:name":"Sinbong",
    "wof:placetype":"locality"
},
  "geometry": {"coordinates":[127.95139,36.44667000000001],"type":"Point"}
}