{
  "type": "Feature",
  "properties": {
    "gn:admin1_code":"16.0",
    "gn:asciiname":"Singeun",
    "gn:country_code":"KR",
    "gn:dem":27,
    "gn:feature_class":"P",
    "gn:feature_code":"PPL",
    "gn:name":"Singeun",
    "gn:population":0,
    "gn:timezone":"Asia/Seoul",
    "iso:country":"KR",
    "name:kor_x_preferred":[
        "\uc2e0\uadfc"
    ],
    "name:kor_x_variant":[
        "Sin\u2019g\u016dn"
    ],
    "wof:name":"Singeun",
    "wof:placetype":"locality"
},
  "geometry": {"coordinates":[127.05198,34.66621],"type":"Point"}
}