{
  "type": "Feature",
  "properties": {
    "gn:admin1_code":"17.0",
    "gn:asciiname":"Songjong",
    "gn:country_code":"KR",
    "gn:dem":39,
    "gn:feature_class":"P",
    "gn:feature_code":"PPL",
    "gn:name":"Songj\u014fng",
    "gn:population":0,
    "gn:timezone":"Asia/Seoul",
    "iso:country":"KR",
    "name:und_x_variant":[
        "\u014ejigok",
        "\u014ejigol",
        "\uc1a1\uc815",
        "Songj\u014fng"
    ],
    "wof:name":"Songjong",
    "wof:placetype":"locality"
},
  "geometry": {"coordinates":[126.63460000000001,36.874],"type":"Point"}
}