{
  "type": "Feature",
  "properties": {
    "gn:admin1_code":"14.0",
    "gn:asciiname":"Pusi-gol",
    "gn:country_code":"KR",
    "gn:dem":225,
    "gn:feature_class":"P",
    "gn:feature_code":"PPL",
    "gn:name":"Pusi-gol",
    "gn:population":0,
    "gn:timezone":"Asia/Seoul",
    "iso:country":"KR",
    "name:und_x_variant":[
        "\ubd80\uc2dc\uace8",
        "Pusi-gol"
    ],
    "wof:name":"Pusi-gol",
    "wof:placetype":"locality"
},
  "geometry": {"coordinates":[129.0966,36.3749],"type":"Point"}
}