{
  "type": "Feature",
  "properties": {
    "gn:country":"KR",
    "gn:fcode":"ADMD",
    "gn:pop":0,
    "iso:country":"KR",
    "name:eng_x_preferred":[
        "Chungju-si"
    ],
    "name:eng_x_variant":[
        "Chungju"
    ],
    "name:kor_x_preferred":[
        "\ucda9\uc8fc\uc2dc"
    ],
    "name:kor_x_variant":[
        "\ucda9\uc8fc",
        "Ch\u2019ungju-si"
    ],
    "name:unk_x_variant":[
        "Chungju-si"
    ],
    "qs:name":"Chungju City",
    "qs:photos_9r":0,
    "qs:photos_sr":0,
    "qs:pop_sr":"0",
    "wof:name":"Chungju City",
    "wof:placetype":"localadmin",
    "wof:population":0
},
  "geometry": {"coordinates":[127.95,36.96667],"type":"Point"}
}