{
  "type": "Feature",
  "properties": {
    "gn:admin1_code":"13.0",
    "gn:asciiname":"Seokjeong",
    "gn:country_code":"KR",
    "gn:dem":15,
    "gn:feature_class":"P",
    "gn:feature_code":"PPL",
    "gn:name":"Seokjeong",
    "gn:population":0,
    "gn:timezone":"Asia/Seoul",
    "iso:country":"KR",
    "name:und_x_variant":[
        "S\u014fkch\u014fng-ni",
        "\uc11d\uc815",
        "Seokjeong",
        "S\u014fkch\u014fng"
    ],
    "wof:name":"Seokjeong",
    "wof:placetype":"locality"
},
  "geometry": {"coordinates":[126.55546,37.6731],"type":"Point"}
}