{
  "type": "Feature",
  "properties": {
    "gn:admin1_code":"11.0",
    "gn:asciiname":"Panghak-tong",
    "gn:country_code":"KR",
    "gn:dem":37,
    "gn:feature_class":"P",
    "gn:feature_code":"PPL",
    "gn:name":"Panghak-tong",
    "gn:population":0,
    "gn:timezone":"Asia/Seoul",
    "iso:country":"KR",
    "name:und_x_variant":[
        "\ubc29\ud559\ub3d9",
        "Panghak-tong"
    ],
    "wof:name":"Panghak-tong",
    "wof:placetype":"locality"
},
  "geometry": {"coordinates":[127.0372,37.6665],"type":"Point"}
}