{
  "type": "Feature",
  "properties": {
    "gn:admin1_code":"6.0",
    "gn:asciiname":"P'yonghwa-ch'on",
    "gn:country_code":"KR",
    "gn:dem":1041,
    "gn:feature_class":"P",
    "gn:feature_code":"PPL",
    "gn:name":"P\u2019y\u014fnghwa-ch\u2019on",
    "gn:population":0,
    "gn:timezone":"Asia/Seoul",
    "iso:country":"KR",
    "name:kor_x_preferred":[
        "\ud3c9\ud654\ucd0c"
    ],
    "name:kor_x_variant":[
        "P\u2019y\u014fnghwa-ch\u2019on"
    ],
    "wof:name":"P'yonghwa-ch'on",
    "wof:placetype":"locality"
},
  "geometry": {"coordinates":[128.90049999999999,37.1658],"type":"Point"}
}