{
  "type": "Feature",
  "properties": {
    "gn:admin1_code":"15.0",
    "gn:asciiname":"Wolsongjeong",
    "gn:country_code":"KR",
    "gn:dem":331,
    "gn:feature_class":"P",
    "gn:feature_code":"PPL",
    "gn:name":"Wolsongjeong",
    "gn:population":0,
    "gn:timezone":"Asia/Seoul",
    "iso:country":"KR",
    "name:kor_x_preferred":[
        "\uc6d4\uc131\uc815"
    ],
    "wof:name":"Wolsongjeong",
    "wof:placetype":"locality"
},
  "geometry": {"coordinates":[128.73871,35.9651],"type":"Point"}
}