{
  "type": "Feature",
  "properties": {
    "gn:admin1_code":"14.0",
    "gn:asciiname":"Choryonggogae",
    "gn:country_code":"KR",
    "gn:dem":273,
    "gn:feature_class":"P",
    "gn:feature_code":"PPL",
    "gn:name":"Choryonggogae",
    "gn:population":0,
    "gn:timezone":"Asia/Seoul",
    "iso:country":"KR",
    "name:und_x_variant":[
        "\uc870\ub8e1\uace0\uac1c",
        "Choryonggogae"
    ],
    "wof:name":"Choryonggogae",
    "wof:placetype":"locality"
},
  "geometry": {"coordinates":[129.3254,36.9972],"type":"Point"}
}