{
  "type": "Feature",
  "properties": {
    "gn:admin1_code":"17.0",
    "gn:asciiname":"Ha-ri",
    "gn:country_code":"KR",
    "gn:dem":46,
    "gn:feature_class":"P",
    "gn:feature_code":"PPL",
    "gn:name":"Ha-ri",
    "gn:population":0,
    "gn:timezone":"Asia/Seoul",
    "iso:country":"KR",
    "name:und_x_variant":[
        "Chukha-ri",
        "\ud558\ub9ac",
        "Ha-ri"
    ],
    "wof:name":"Ha-ri",
    "wof:placetype":"locality"
},
  "geometry": {"coordinates":[126.676,36.4983],"type":"Point"}
}