{
  "type": "Feature",
  "properties": {
    "gn:admin1_code":"14.0",
    "gn:asciiname":"Yulmok",
    "gn:country_code":"KR",
    "gn:dem":533,
    "gn:feature_class":"P",
    "gn:feature_code":"PPL",
    "gn:name":"Yulmok",
    "gn:population":0,
    "gn:timezone":"Asia/Seoul",
    "iso:country":"KR",
    "name:und_x_variant":[
        "\uc728\ubaa9",
        "Yulmok"
    ],
    "wof:name":"Yulmok",
    "wof:placetype":"locality"
},
  "geometry": {"coordinates":[129.2133,36.6791],"type":"Point"}
}