{
  "type": "Feature",
  "properties": {
    "gn:admin1_code":"16.0",
    "gn:asciiname":"P'yongsado",
    "gn:country_code":"KR",
    "gn:dem":50,
    "gn:feature_class":"P",
    "gn:feature_code":"PPL",
    "gn:name":"P\u2019y\u014fngsado",
    "gn:population":0,
    "gn:timezone":"Asia/Seoul",
    "iso:country":"KR",
    "name:und_x_variant":[
        "P\u2019y\u014fngsa",
        "P\u2019y\u014fngsado"
    ],
    "wof:name":"P'yongsado",
    "wof:placetype":"locality"
},
  "geometry": {"coordinates":[126.15000000000001,34.56667],"type":"Point"}
}