{
  "type": "Feature",
  "properties": {
    "gn:admin1_code":"17.0",
    "gn:asciiname":"Tut'o-gol",
    "gn:country_code":"KR",
    "gn:dem":90,
    "gn:feature_class":"P",
    "gn:feature_code":"PPL",
    "gn:name":"Tut\u2019\u014f-gol",
    "gn:population":0,
    "gn:timezone":"Asia/Seoul",
    "iso:country":"KR",
    "name:und_x_variant":[
        "\ub450\ud130\uace8",
        "Tut\u2019\u014f-gol"
    ],
    "wof:name":"Tut'o-gol",
    "wof:placetype":"locality"
},
  "geometry": {"coordinates":[126.8305,36.3073],"type":"Point"}
}