{
  "type": "Feature",
  "properties": {
    "gn:admin1_code":"5.0",
    "gn:asciiname":"Gomsil",
    "gn:country_code":"KR",
    "gn:dem":108,
    "gn:feature_class":"P",
    "gn:feature_code":"PPL",
    "gn:name":"Gomsil",
    "gn:population":0,
    "gn:timezone":"Asia/Seoul",
    "iso:country":"KR",
    "name:kor_x_preferred":[
        "\uacf0\uc2e4"
    ],
    "wof:name":"Gomsil",
    "wof:placetype":"locality"
},
  "geometry": {"coordinates":[127.81079,36.99179],"type":"Point"}
}