{
  "type": "Feature",
  "properties": {
    "gn:admin1_code":"14.0",
    "gn:asciiname":"Manusil",
    "gn:country_code":"KR",
    "gn:dem":97,
    "gn:feature_class":"P",
    "gn:feature_code":"PPL",
    "gn:name":"Man\u016dsil",
    "gn:population":0,
    "gn:timezone":"Asia/Seoul",
    "iso:country":"KR",
    "name:und_x_variant":[
        "\ub9c8\ub290\uc2e4",
        "Man\u016dsil"
    ],
    "wof:name":"Manusil",
    "wof:placetype":"locality"
},
  "geometry": {"coordinates":[128.23920000000001,36.3555],"type":"Point"}
}