{
  "type": "Feature",
  "properties": {
    "gn:admin1_code":"16.0",
    "gn:asciiname":"Yedong",
    "gn:country_code":"KR",
    "gn:dem":70,
    "gn:feature_class":"P",
    "gn:feature_code":"PPL",
    "gn:name":"Yedong",
    "gn:population":0,
    "gn:timezone":"Asia/Seoul",
    "iso:country":"KR",
    "name:und_x_variant":[
        "\uc608\ub3d9",
        "Yedong"
    ],
    "wof:name":"Yedong",
    "wof:placetype":"locality"
},
  "geometry": {"coordinates":[126.73051,34.6661],"type":"Point"}
}