{
  "type": "Feature",
  "properties": {
    "gn:admin1_code":"12.0",
    "gn:asciiname":"Nongjangmal",
    "gn:country_code":"KR",
    "gn:dem":12,
    "gn:feature_class":"P",
    "gn:feature_code":"PPL",
    "gn:name":"Nongjangmal",
    "gn:population":0,
    "gn:timezone":"Asia/Seoul",
    "iso:country":"KR",
    "name:kor_x_preferred":[
        "\ub18d\uc7a5\ub9d0"
    ],
    "wof:name":"Nongjangmal",
    "wof:placetype":"locality"
},
  "geometry": {"coordinates":[126.22235000000001,37.79532],"type":"Point"}
}