{
  "type": "Feature",
  "properties": {
    "gn:admin1_code":"6.0",
    "gn:asciiname":"Mich'onipku",
    "gn:country_code":"KR",
    "gn:dem":242,
    "gn:feature_class":"P",
    "gn:feature_code":"PPL",
    "gn:name":"Mich\u2019\u014fnipku",
    "gn:population":0,
    "gn:timezone":"Asia/Seoul",
    "iso:country":"KR",
    "name:kor_x_preferred":[
        "\ubbf8\ucc9c\uc785\uad6c"
    ],
    "name:kor_x_variant":[
        "Mich\u2019\u014fnipku"
    ],
    "wof:name":"Mich'onipku",
    "wof:placetype":"locality"
},
  "geometry": {"coordinates":[128.5034,37.952],"type":"Point"}
}