{
  "type": "Feature",
  "properties": {
    "gn:admin1_code":"5.0",
    "gn:asciiname":"Saett'o",
    "gn:country_code":"KR",
    "gn:dem":564,
    "gn:feature_class":"P",
    "gn:feature_code":"PPL",
    "gn:name":"Saett\u2019\u014f",
    "gn:population":0,
    "gn:timezone":"Asia/Seoul",
    "iso:country":"KR",
    "wof:name":"Saett'o",
    "wof:placetype":"locality"
},
  "geometry": {"coordinates":[128.36972,36.83444],"type":"Point"}
}