{
  "type": "Feature",
  "properties": {
    "gn:admin1_code":"13.0",
    "gn:asciiname":"Sanmit",
    "gn:country_code":"KR",
    "gn:dem":47,
    "gn:feature_class":"P",
    "gn:feature_code":"PPL",
    "gn:name":"Sanmit",
    "gn:population":0,
    "gn:timezone":"Asia/Seoul",
    "iso:country":"KR",
    "name:kor_x_preferred":[
        "\uc0b0\ubc11"
    ],
    "name:und_x_variant":[
        "Sanmit"
    ],
    "wof:name":"Sanmit",
    "wof:placetype":"locality"
},
  "geometry": {"coordinates":[127.17789999999999,37.5318],"type":"Point"}
}