{
  "type": "Feature",
  "properties": {
    "gn:admin1_code":"5.0",
    "gn:asciiname":"Ch'oksal-li",
    "gn:country_code":"KR",
    "gn:dem":104,
    "gn:feature_class":"P",
    "gn:feature_code":"PPLL",
    "gn:name":"Ch\u2019\u014fksal-li",
    "gn:population":0,
    "gn:timezone":"Asia/Seoul",
    "iso:country":"KR",
    "wof:name":"Ch'oksal-li",
    "wof:placetype":"locality"
},
  "geometry": {"coordinates":[127.43583,36.56389],"type":"Point"}
}