{
  "type": "Feature",
  "properties": {
    "gn:admin1_code":"13.0",
    "gn:asciiname":"Posipkae",
    "gn:country_code":"KR",
    "gn:dem":216,
    "gn:feature_class":"P",
    "gn:feature_code":"PPL",
    "gn:name":"Posipkae",
    "gn:population":0,
    "gn:timezone":"Asia/Seoul",
    "iso:country":"KR",
    "name:kor_x_preferred":[
        "\ubcf4\uc2ed\uac1c"
    ],
    "wof:name":"Posipkae",
    "wof:placetype":"locality"
},
  "geometry": {"coordinates":[127.52,37.6115],"type":"Point"}
}