{
  "type": "Feature",
  "properties": {
    "gn:admin1_code":"6.0",
    "gn:asciiname":"Jingogae",
    "gn:country_code":"KR",
    "gn:dem":268,
    "gn:feature_class":"P",
    "gn:feature_code":"PPL",
    "gn:name":"Jingogae",
    "gn:population":0,
    "gn:timezone":"Asia/Seoul",
    "iso:country":"KR",
    "name:kor_x_preferred":[
        "\uc9c4\uace0\uac1c"
    ],
    "name:kor_x_variant":[
        "Chin\u2019gogae"
    ],
    "wof:name":"Jingogae",
    "wof:placetype":"locality"
},
  "geometry": {"coordinates":[128.15308000000002,37.76706],"type":"Point"}
}