{
  "type": "Feature",
  "properties": {
    "gn:admin1_code":"0.0",
    "gn:asciiname":"Wonch'ongnyang",
    "gn:country_code":"KR",
    "gn:dem":14,
    "gn:feature_class":"P",
    "gn:feature_code":"PPL",
    "gn:name":"W\u014fnch\u2019ongnyang",
    "gn:population":0,
    "gn:timezone":"Asia/Seoul",
    "iso:country":"KR",
    "name:und_x_variant":[
        "Ch\u2019\u014fngnyang-ni",
        "Ch\u2019\u014fngyang-ni",
        "W\u014fnch\u2019ongnyang"
    ],
    "wof:name":"Wonch'ongnyang",
    "wof:placetype":"locality"
},
  "geometry": {"coordinates":[126.78333000000001,35.66667],"type":"Point"}
}