{
  "type": "Feature",
  "properties": {
    "gn:admin1_code":"13.0",
    "gn:asciiname":"Byeokgye",
    "gn:country_code":"KR",
    "gn:dem":110,
    "gn:feature_class":"P",
    "gn:feature_code":"PPL",
    "gn:name":"Byeokgye",
    "gn:population":0,
    "gn:timezone":"Asia/Seoul",
    "iso:country":"KR",
    "name:kor_x_preferred":[
        "\ubcbd\uacc4"
    ],
    "name:und_x_variant":[
        "Byeokgye"
    ],
    "wof:name":"Byeokgye",
    "wof:placetype":"locality"
},
  "geometry": {"coordinates":[127.4271,37.6402],"type":"Point"}
}