{
  "type": "Feature",
  "properties": {
    "gn:admin1_code":"6.0",
    "gn:asciiname":"Kangp'o-ri",
    "gn:country_code":"KR",
    "gn:dem":147,
    "gn:feature_class":"P",
    "gn:feature_code":"PPL",
    "gn:name":"Kangp\u2019o-ri",
    "gn:population":0,
    "gn:timezone":"Asia/Seoul",
    "iso:country":"KR",
    "wof:name":"Kangp'o-ri",
    "wof:placetype":"locality"
},
  "geometry": {"coordinates":[127.2925,38.11778],"type":"Point"}
}