{
  "type": "Feature",
  "properties": {
    "gn:admin1_code":"13.0",
    "gn:asciiname":"Osang-gol",
    "gn:country_code":"KR",
    "gn:dem":48,
    "gn:feature_class":"P",
    "gn:feature_code":"PPL",
    "gn:name":"Osang-gol",
    "gn:population":0,
    "gn:timezone":"Asia/Seoul",
    "iso:country":"KR",
    "name:und_x_variant":[
        "\uc624\uc0c1\uace8",
        "Osang-gol"
    ],
    "wof:name":"Osang-gol",
    "wof:placetype":"locality"
},
  "geometry": {"coordinates":[126.96666999999999,37.1475],"type":"Point"}
}