{
  "type": "Feature",
  "properties": {
    "gn:admin1_code":"5.0",
    "gn:asciiname":"Hoegok",
    "gn:country_code":"KR",
    "gn:dem":267,
    "gn:feature_class":"P",
    "gn:feature_code":"PPL",
    "gn:name":"Hoegok",
    "gn:population":0,
    "gn:timezone":"Asia/Seoul",
    "iso:country":"KR",
    "name:und_x_variant":[
        "\ud68c\uace1",
        "Hoegok"
    ],
    "wof:name":"Hoegok",
    "wof:placetype":"locality"
},
  "geometry": {"coordinates":[127.9628,36.2008],"type":"Point"}
}