{
  "type": "Feature",
  "properties": {
    "gn:admin1_code":"6.0",
    "gn:asciiname":"Buheungdong",
    "gn:country_code":"KR",
    "gn:dem":180,
    "gn:feature_class":"P",
    "gn:feature_code":"PPL",
    "gn:name":"Buheungdong",
    "gn:population":0,
    "gn:timezone":"Asia/Seoul",
    "iso:country":"KR",
    "name:kor_x_preferred":[
        "\ubd80\ud765\ub3d9"
    ],
    "wof:name":"Buheungdong",
    "wof:placetype":"locality"
},
  "geometry": {"coordinates":[127.25933000000001,38.20317],"type":"Point"}
}