{
  "type": "Feature",
  "properties": {
    "gn:admin1_code":"11.0",
    "gn:asciiname":"Chegiil-tong",
    "gn:country_code":"KR",
    "gn:dem":22,
    "gn:feature_class":"P",
    "gn:feature_code":"PPL",
    "gn:name":"Chegiil-tong",
    "gn:population":0,
    "gn:timezone":"Asia/Seoul",
    "iso:country":"KR",
    "name:eng_x_preferred":[
        "Chegiil"
    ],
    "name:eng_x_variant":[
        "Chegiil-tong"
    ],
    "name:und_x_variant":[
        "\uc81c\uae301\ub3d9",
        "Chegiil-tong"
    ],
    "wof:name":"Chegiil",
    "wof:placetype":"locality"
},
  "geometry": {"coordinates":[127.04017,37.58472],"type":"Point"}
}