{
  "type": "Feature",
  "properties": {
    "gn:admin1_code":"17.0",
    "gn:asciiname":"Summal",
    "gn:country_code":"KR",
    "gn:dem":33,
    "gn:feature_class":"P",
    "gn:feature_code":"PPL",
    "gn:name":"Summal",
    "gn:population":0,
    "gn:timezone":"Asia/Seoul",
    "iso:country":"KR",
    "name:kor_x_preferred":[
        "\uc228\ub9d0"
    ],
    "wof:name":"Summal",
    "wof:placetype":"locality"
},
  "geometry": {"coordinates":[127.16556,36.22151],"type":"Point"}
}