{
  "type": "Feature",
  "properties": {
    "gn:admin1_code":"5.0",
    "gn:asciiname":"Maehwa-ri",
    "gn:country_code":"KR",
    "gn:dem":120,
    "gn:feature_class":"P",
    "gn:feature_code":"PPL",
    "gn:name":"Maehwa-ri",
    "gn:population":0,
    "gn:timezone":"Asia/Seoul",
    "iso:country":"KR",
    "name:und_x_variant":[
        "\ub9e4\ud654\ub9ac",
        "Maehwa-ri"
    ],
    "wof:name":"Maehwa-ri",
    "wof:placetype":"locality"
},
  "geometry": {"coordinates":[127.5929,36.3058],"type":"Point"}
}