{
  "type": "Feature",
  "properties": {
    "gn:admin1_code":"13.0",
    "gn:asciiname":"Yongjimeori",
    "gn:country_code":"KR",
    "gn:dem":73,
    "gn:feature_class":"P",
    "gn:feature_code":"PPL",
    "gn:name":"Yongjimeori",
    "gn:population":0,
    "gn:timezone":"Asia/Seoul",
    "iso:country":"KR",
    "name:kor_x_preferred":[
        "\uc6a9\uc9c0\uba38\ub9ac"
    ],
    "name:kor_x_variant":[
        "Yongjim\u014f-ri"
    ],
    "wof:name":"Yongjimeori",
    "wof:placetype":"locality"
},
  "geometry": {"coordinates":[127.5014,37.2018],"type":"Point"}
}