{
  "type": "Feature",
  "properties": {
    "gn:admin1_code":"14.0",
    "gn:asciiname":"Namhoe",
    "gn:country_code":"KR",
    "gn:dem":557,
    "gn:feature_class":"P",
    "gn:feature_code":"PPL",
    "gn:name":"Namhoe",
    "gn:population":0,
    "gn:timezone":"Asia/Seoul",
    "iso:country":"KR",
    "name:und_x_variant":[
        "\ub0a8\ud68c",
        "Namhoe"
    ],
    "wof:name":"Namhoe",
    "wof:placetype":"locality"
},
  "geometry": {"coordinates":[129.15119999999999,36.8883],"type":"Point"}
}