{
  "type": "Feature",
  "properties": {
    "gn:admin1_code":"13.0",
    "gn:asciiname":"Tongmyeong",
    "gn:country_code":"KR",
    "gn:dem":178,
    "gn:feature_class":"P",
    "gn:feature_code":"PPL",
    "gn:name":"Tongmyeong",
    "gn:population":0,
    "gn:timezone":"Asia/Seoul",
    "iso:country":"KR",
    "name:und_x_variant":[
        "\ud1b5\uba85",
        "Tongmyeong",
        "T\u2019ongmy\u014fng"
    ],
    "wof:name":"Tongmyeong",
    "wof:placetype":"locality"
},
  "geometry": {"coordinates":[127.74194,37.30083],"type":"Point"}
}