{
  "type": "Feature",
  "properties": {
    "gn:admin1_code":"14.0",
    "gn:asciiname":"Mojimi",
    "gn:country_code":"KR",
    "gn:dem":159,
    "gn:feature_class":"P",
    "gn:feature_code":"PPL",
    "gn:name":"M\u014fjimi",
    "gn:population":0,
    "gn:timezone":"Asia/Seoul",
    "iso:country":"KR",
    "name:und_x_variant":[
        "\uba38\uc9c0\ubbf8",
        "M\u014fjimi"
    ],
    "wof:name":"Mojimi",
    "wof:placetype":"locality"
},
  "geometry": {"coordinates":[128.15565000000001,35.90319],"type":"Point"}
}