{
  "type": "Feature",
  "properties": {
    "gn:admin1_code":"6.0",
    "gn:asciiname":"Paubaegi",
    "gn:country_code":"KR",
    "gn:dem":324,
    "gn:feature_class":"P",
    "gn:feature_code":"PPL",
    "gn:name":"Paubaegi",
    "gn:population":0,
    "gn:timezone":"Asia/Seoul",
    "iso:country":"KR",
    "name:und_x_variant":[
        "\ubc14\uc6b0\ubc31\uc774"
    ],
    "wof:name":"Paubaegi",
    "wof:placetype":"locality"
},
  "geometry": {"coordinates":[128.19336999999999,38.26345],"type":"Point"}
}