{
  "type": "Feature",
  "properties": {
    "gn:admin1_code":"14.0",
    "gn:asciiname":"Araen-mal",
    "gn:country_code":"KR",
    "gn:dem":69,
    "gn:feature_class":"P",
    "gn:feature_code":"PPL",
    "gn:name":"Araen-mal",
    "gn:population":0,
    "gn:timezone":"Asia/Seoul",
    "iso:country":"KR",
    "name:und_x_variant":[
        "\uc544\ub7ab\ub9d0",
        "Araen-mal"
    ],
    "wof:name":"Araen-mal",
    "wof:placetype":"locality"
},
  "geometry": {"coordinates":[128.17509999999999,36.3881],"type":"Point"}
}