{
  "type": "Feature",
  "properties": {
    "gn:admin1_code":"14.0",
    "gn:asciiname":"Araetchidul",
    "gn:country_code":"KR",
    "gn:dem":191,
    "gn:feature_class":"P",
    "gn:feature_code":"PPL",
    "gn:name":"Araetchid\u016dl",
    "gn:population":0,
    "gn:timezone":"Asia/Seoul",
    "iso:country":"KR",
    "name:und_x_variant":[
        "\uc544\ub7ab\uc9c0\ub4e4",
        "Araetchid\u016dl"
    ],
    "wof:name":"Araetchidul",
    "wof:placetype":"locality"
},
  "geometry": {"coordinates":[129.07911999999999,36.11852],"type":"Point"}
}