{
  "type": "Feature",
  "properties": {
    "gn:admin1_code":"17.0",
    "gn:asciiname":"Anae-ri",
    "gn:country_code":"KR",
    "gn:dem":60,
    "gn:feature_class":"P",
    "gn:feature_code":"PPL",
    "gn:name":"Anae-ri",
    "gn:population":0,
    "gn:timezone":"Asia/Seoul",
    "iso:country":"KR",
    "name:und_x_variant":[
        "Py\u014fngch\u2019\u014fn-ni",
        "Py\u014fngch\u2019\u014fl-li"
    ],
    "wof:name":"Anae-ri",
    "wof:placetype":"locality"
},
  "geometry": {"coordinates":[127.29971999999999,36.76056],"type":"Point"}
}