{
  "type": "Feature",
  "properties": {
    "gn:admin1_code":"17.0",
    "gn:asciiname":"Chinho-ri",
    "gn:country_code":"KR",
    "gn:dem":26,
    "gn:feature_class":"P",
    "gn:feature_code":"PPL",
    "gn:name":"Chinho-ri",
    "gn:population":0,
    "gn:timezone":"Asia/Seoul",
    "iso:country":"KR",
    "name:und_x_variant":[
        "\uc9c4\ud638\ub9ac",
        "Chinho-ri"
    ],
    "wof:name":"Chinho-ri",
    "wof:placetype":"locality"
},
  "geometry": {"coordinates":[127.0538,36.2747],"type":"Point"}
}