{
  "type": "Feature",
  "properties": {
    "gn:admin1_code":"14.0",
    "gn:asciiname":"Saenaru",
    "gn:country_code":"KR",
    "gn:dem":75,
    "gn:feature_class":"P",
    "gn:feature_code":"PPL",
    "gn:name":"Saenaru",
    "gn:population":0,
    "gn:timezone":"Asia/Seoul",
    "iso:country":"KR",
    "name:und_x_variant":[
        "\uc0c8\ub098\ub8e8",
        "Saenaru"
    ],
    "wof:name":"Saenaru",
    "wof:placetype":"locality"
},
  "geometry": {"coordinates":[128.18556000000001,35.67066],"type":"Point"}
}