{
  "type": "Feature",
  "properties": {
    "gn:admin1_code":"17.0",
    "gn:asciiname":"Sanso-mal",
    "gn:country_code":"KR",
    "gn:dem":64,
    "gn:feature_class":"P",
    "gn:feature_code":"PPL",
    "gn:name":"Sanso-mal",
    "gn:population":0,
    "gn:timezone":"Asia/Seoul",
    "iso:country":"KR",
    "name:und_x_variant":[
        "\uc0b0\uc18c\ub9d0",
        "Sanso-mal"
    ],
    "wof:name":"Sanso-mal",
    "wof:placetype":"locality"
},
  "geometry": {"coordinates":[127.004,36.8556],"type":"Point"}
}