{
  "type": "Feature",
  "properties": {
    "gn:admin1_code":"12.0",
    "gn:asciiname":"Cheonjjae",
    "gn:country_code":"KR",
    "gn:dem":6,
    "gn:feature_class":"P",
    "gn:feature_code":"PPL",
    "gn:name":"Cheonjjae",
    "gn:population":0,
    "gn:timezone":"Asia/Seoul",
    "iso:country":"KR",
    "name:kor_x_preferred":[
        "\ucc9c\uc9f8"
    ],
    "wof:name":"Cheonjjae",
    "wof:placetype":"locality"
},
  "geometry": {"coordinates":[126.31559,37.73492],"type":"Point"}
}