{
  "type": "Feature",
  "properties": {
    "gn:admin1_code":"5.0",
    "gn:asciiname":"Pon-dong",
    "gn:country_code":"KR",
    "gn:dem":269,
    "gn:feature_class":"P",
    "gn:feature_code":"PPL",
    "gn:name":"Pon-dong",
    "gn:population":0,
    "gn:timezone":"Asia/Seoul",
    "iso:country":"KR",
    "name:kor_x_preferred":[
        "\ubcf8\ub3d9"
    ],
    "wof:name":"Pon-dong",
    "wof:placetype":"locality"
},
  "geometry": {"coordinates":[128.13919999999999,37.1572],"type":"Point"}
}