{
  "type": "Feature",
  "properties": {
    "gn:admin1_code":"14.0",
    "gn:asciiname":"Anhuksu",
    "gn:country_code":"KR",
    "gn:dem":65,
    "gn:feature_class":"P",
    "gn:feature_code":"PPL",
    "gn:name":"Anh\u016dksu",
    "gn:population":0,
    "gn:timezone":"Asia/Seoul",
    "iso:country":"KR",
    "name:und_x_variant":[
        "\uc548\ud751\uc218",
        "Anh\u016dksu"
    ],
    "wof:name":"Anhuksu",
    "wof:placetype":"locality"
},
  "geometry": {"coordinates":[128.28963000000002,35.80181],"type":"Point"}
}