{
  "type": "Feature",
  "properties": {
    "gn:admin1_code":"14.0",
    "gn:asciiname":"Namgok",
    "gn:country_code":"KR",
    "gn:dem":85,
    "gn:feature_class":"P",
    "gn:feature_code":"PPL",
    "gn:name":"Namgok",
    "gn:population":0,
    "gn:timezone":"Asia/Seoul",
    "iso:country":"KR",
    "name:und_x_variant":[
        "\ub0a8\uace1",
        "Namgok"
    ],
    "wof:name":"Namgok",
    "wof:placetype":"locality"
},
  "geometry": {"coordinates":[128.15989999999999,36.1124],"type":"Point"}
}