{
  "type": "Feature",
  "properties": {
    "gn:admin1_code":"13.0",
    "gn:asciiname":"Danghyeon-ri",
    "gn:country_code":"KR",
    "gn:dem":29,
    "gn:feature_class":"P",
    "gn:feature_code":"PPL",
    "gn:name":"Danghyeon-ri",
    "gn:population":0,
    "gn:timezone":"Asia/Seoul",
    "iso:country":"KR",
    "name:und_x_variant":[
        "\ub2f9\ud604\ub9ac",
        "Danghyeon-ri",
        "Tanghy\u014fl-li"
    ],
    "wof:name":"Danghyeon-ri",
    "wof:placetype":"locality"
},
  "geometry": {"coordinates":[127.0325,37.06556],"type":"Point"}
}