{
  "type": "Feature",
  "properties": {
    "gn:admin1_code":"14.0",
    "gn:asciiname":"Samgeori",
    "gn:country_code":"KR",
    "gn:dem":248,
    "gn:feature_class":"P",
    "gn:feature_code":"PPL",
    "gn:name":"Samgeori",
    "gn:population":0,
    "gn:timezone":"Asia/Seoul",
    "iso:country":"KR",
    "name:kor_x_preferred":[
        "\uc0bc\uac70\ub9ac"
    ],
    "wof:name":"Samgeori",
    "wof:placetype":"locality"
},
  "geometry": {"coordinates":[128.71281000000002,36.74919000000001],"type":"Point"}
}