{
  "type": "Feature",
  "properties": {
    "gn:admin1_code":"14.0",
    "gn:asciiname":"Tomok",
    "gn:cc2":"KR",
    "gn:country_code":"KR",
    "gn:dem":154,
    "gn:feature_class":"P",
    "gn:feature_code":"PPL",
    "gn:name":"Tomok",
    "gn:population":0,
    "gn:timezone":"Asia/Seoul",
    "iso:country":"KR",
    "name:und_x_variant":[
        "Sangdomok",
        "Tomok"
    ],
    "wof:name":"Tomok",
    "wof:placetype":"locality"
},
  "geometry": {"coordinates":[128.84999999999999,36.61667],"type":"Point"}
}