{
  "type": "Feature",
  "properties": {
    "gn:admin1_code":"12.0",
    "gn:asciiname":"Changgi-dong",
    "gn:country_code":"KR",
    "gn:dem":24,
    "gn:feature_class":"P",
    "gn:feature_code":"PPL",
    "gn:name":"Changgi-dong",
    "gn:population":0,
    "gn:timezone":"Asia/Seoul",
    "iso:country":"KR",
    "name:kor_x_preferred":[
        "\uc7a5\uae30\ub3d9"
    ],
    "name:und_x_variant":[
        "Changgi-ri",
        "Changgi-dong"
    ],
    "wof:name":"Changgi-dong",
    "wof:placetype":"locality"
},
  "geometry": {"coordinates":[126.73444000000001,37.57917],"type":"Point"}
}