{
  "type": "Feature",
  "properties": {
    "gn:admin1_code":"13.0",
    "gn:asciiname":"Changsim-ni",
    "gn:country_code":"KR",
    "gn:dem":195,
    "gn:feature_class":"P",
    "gn:feature_code":"PPLL",
    "gn:name":"Changsim-ni",
    "gn:population":0,
    "gn:timezone":"Asia/Seoul",
    "iso:country":"KR",
    "name:eng_x_preferred":[
        "Changsim"
    ],
    "name:eng_x_variant":[
        "Changsim-ni"
    ],
    "name:und_x_variant":[
        "\uc7a5\uc2ec\ub9ac",
        "Jangsim-ri",
        "Changsim-ni"
    ],
    "wof:name":"Changsim",
    "wof:placetype":"locality"
},
  "geometry": {"coordinates":[127.39028,37.38278],"type":"Point"}
}