{
  "type": "Feature",
  "properties": {
    "gn:admin1_code":"16.0",
    "gn:asciiname":"Sinhung",
    "gn:country_code":"KR",
    "gn:dem":19,
    "gn:feature_class":"P",
    "gn:feature_code":"PPL",
    "gn:name":"Sinh\u016dng",
    "gn:population":0,
    "gn:timezone":"Asia/Seoul",
    "iso:country":"KR",
    "name:kor_x_preferred":[
        "\uc2e0\ud765"
    ],
    "name:und_x_variant":[
        "Shinh\u016dng",
        "Sinh\u016dng-ni"
    ],
    "wof:name":"Sinhung",
    "wof:placetype":"locality"
},
  "geometry": {"coordinates":[127.14532,34.59073],"type":"Point"}
}