{
  "type": "Feature",
  "properties": {
    "gn:admin1_code":"17.0",
    "gn:asciiname":"Pae-mal",
    "gn:country_code":"KR",
    "gn:dem":10,
    "gn:feature_class":"P",
    "gn:feature_code":"PPL",
    "gn:name":"Pae-mal",
    "gn:population":0,
    "gn:timezone":"Asia/Seoul",
    "iso:country":"KR",
    "name:und_x_variant":[
        "\ubc30\ub9d0",
        "Paeil",
        "Pae-mal"
    ],
    "wof:name":"Pae-mal",
    "wof:placetype":"locality"
},
  "geometry": {"coordinates":[126.36879999999999,36.8736],"type":"Point"}
}