{
  "type": "Feature",
  "properties": {
    "gn:admin1_code":"5.0",
    "gn:asciiname":"Witchanggol",
    "gn:country_code":"KR",
    "gn:dem":189,
    "gn:feature_class":"P",
    "gn:feature_code":"PPL",
    "gn:name":"Witchanggol",
    "gn:population":0,
    "gn:timezone":"Asia/Seoul",
    "iso:country":"KR",
    "name:kor_x_preferred":[
        "\uc717\ucc3d\uace8"
    ],
    "wof:name":"Witchanggol",
    "wof:placetype":"locality"
},
  "geometry": {"coordinates":[127.6191,36.94097],"type":"Point"}
}