{
  "type": "Feature",
  "properties": {
    "gn:admin1_code":"13.0",
    "gn:asciiname":"Baemi",
    "gn:country_code":"KR",
    "gn:dem":17,
    "gn:feature_class":"P",
    "gn:feature_code":"PPL",
    "gn:name":"Baemi",
    "gn:population":0,
    "gn:timezone":"Asia/Seoul",
    "iso:country":"KR",
    "name:kor_x_preferred":[
        "\ubc30\ubbf8"
    ],
    "name:nld_x_preferred":[
        "Baemi"
    ],
    "wof:name":"Baemi",
    "wof:placetype":"locality"
},
  "geometry": {"coordinates":[126.75958,37.89276],"type":"Point"}
}