{
  "type": "Feature",
  "properties": {
    "gn:admin1_code":"14.0",
    "gn:asciiname":"Oecheong",
    "gn:country_code":"KR",
    "gn:dem":61,
    "gn:feature_class":"P",
    "gn:feature_code":"PPL",
    "gn:name":"Oecheong",
    "gn:population":0,
    "gn:timezone":"Asia/Seoul",
    "iso:country":"KR",
    "name:kor_x_preferred":[
        "\uc678\uccad"
    ],
    "wof:name":"Oecheong",
    "wof:placetype":"locality"
},
  "geometry": {"coordinates":[129.32494,36.21195],"type":"Point"}
}