{
  "type": "Feature",
  "properties": {
    "gn:admin1_code":"6.0",
    "gn:asciiname":"Tunji-mal",
    "gn:country_code":"KR",
    "gn:dem":245,
    "gn:feature_class":"P",
    "gn:feature_code":"PPL",
    "gn:name":"Tunji-mal",
    "gn:population":0,
    "gn:timezone":"Asia/Seoul",
    "iso:country":"KR",
    "name:kor_x_preferred":[
        "\ub454\uc9c0\ub9d0"
    ],
    "wof:name":"Tunji-mal",
    "wof:placetype":"locality"
},
  "geometry": {"coordinates":[128.00716,37.63572],"type":"Point"}
}