{
  "type": "Feature",
  "properties": {
    "gn:admin1_code":"14.0",
    "gn:asciiname":"Myeongmok",
    "gn:country_code":"KR",
    "gn:dem":139,
    "gn:feature_class":"P",
    "gn:feature_code":"PPL",
    "gn:name":"Myeongmok",
    "gn:population":0,
    "gn:timezone":"Asia/Seoul",
    "iso:country":"KR",
    "name:kor_x_preferred":[
        "\uba85\ubaa9"
    ],
    "wof:name":"Myeongmok",
    "wof:placetype":"locality"
},
  "geometry": {"coordinates":[128.44468000000001,36.71382],"type":"Point"}
}