{
  "type": "Feature",
  "properties": {
    "gn:admin1_code":"14.0",
    "gn:asciiname":"Tongsanma",
    "gn:country_code":"KR",
    "gn:dem":74,
    "gn:feature_class":"P",
    "gn:feature_code":"PPL",
    "gn:name":"Tongsanma",
    "gn:population":0,
    "gn:timezone":"Asia/Seoul",
    "iso:country":"KR",
    "name:und_x_variant":[
        "\ub3d9\uc0b0\ub9c8"
    ],
    "wof:name":"Tongsanma",
    "wof:placetype":"locality"
},
  "geometry": {"coordinates":[128.11660000000001,36.4126],"type":"Point"}
}