{
  "type": "Feature",
  "properties": {
    "gn:admin1_code":"20.0",
    "gn:asciiname":"Sang-ch'on",
    "gn:country_code":"KR",
    "gn:dem":147,
    "gn:feature_class":"P",
    "gn:feature_code":"PPL",
    "gn:name":"Sang-ch\u2019on",
    "gn:population":0,
    "gn:timezone":"Asia/Seoul",
    "iso:country":"KR",
    "name:und_x_variant":[
        "\uc0c1\ucd0c",
        "Sang-ch\u2019on"
    ],
    "wof:name":"Sang-ch'on",
    "wof:placetype":"locality"
},
  "geometry": {"coordinates":[128.39082999999999,35.13525],"type":"Point"}
}