{
  "type": "Feature",
  "properties": {
    "gn:admin1_code":"15.0",
    "gn:asciiname":"Josangeol",
    "gn:country_code":"KR",
    "gn:dem":167,
    "gn:feature_class":"P",
    "gn:feature_code":"PPL",
    "gn:name":"Josangeol",
    "gn:population":0,
    "gn:timezone":"Asia/Seoul",
    "iso:country":"KR",
    "name:kor_x_preferred":[
        "\uc870\uc0b0\uac78"
    ],
    "wof:name":"Josangeol",
    "wof:placetype":"locality"
},
  "geometry": {"coordinates":[128.65007,35.76067000000001],"type":"Point"}
}