{
  "type": "Feature",
  "properties": {
    "gn:admin1_code":"14.0",
    "gn:asciiname":"Chidangttum",
    "gn:country_code":"KR",
    "gn:dem":97,
    "gn:feature_class":"P",
    "gn:feature_code":"PPL",
    "gn:name":"Chidangtt\u016dm",
    "gn:population":0,
    "gn:timezone":"Asia/Seoul",
    "iso:country":"KR",
    "name:und_x_variant":[
        "\uc9c0\ub2f9\ub738",
        "Chidangtt\u016dm"
    ],
    "wof:name":"Chidangttum",
    "wof:placetype":"locality"
},
  "geometry": {"coordinates":[128.1122,36.4182],"type":"Point"}
}