{
  "type": "Feature",
  "properties": {
    "gn:admin1_code":"11.0",
    "gn:asciiname":"Taerimil-tong",
    "gn:country_code":"KR",
    "gn:dem":22,
    "gn:feature_class":"P",
    "gn:feature_code":"PPL",
    "gn:name":"Taerimil-tong",
    "gn:population":0,
    "gn:timezone":"Asia/Seoul",
    "iso:country":"KR",
    "name:eng_x_preferred":[
        "Taerimil"
    ],
    "name:eng_x_variant":[
        "Taerimil-tong"
    ],
    "name:und_x_variant":[
        "\ub300\ub9bc1\ub3d9",
        "Daerimil-dong",
        "Taerimil-tong"
    ],
    "wof:name":"Taerimil",
    "wof:placetype":"locality"
},
  "geometry": {"coordinates":[126.90472,37.49333],"type":"Point"}
}