{
  "type": "Feature",
  "properties": {
    "gn:admin1_code":"6.0",
    "gn:asciiname":"Changjadul",
    "gn:country_code":"KR",
    "gn:dem":288,
    "gn:feature_class":"P",
    "gn:feature_code":"PPL",
    "gn:name":"Changjad\u016dl",
    "gn:population":0,
    "gn:timezone":"Asia/Seoul",
    "iso:country":"KR",
    "name:kor_x_preferred":[
        "\uc7a5\uc790\ub4e4"
    ],
    "name:kor_x_variant":[
        "Changjad\u016dl"
    ],
    "wof:name":"Changjadul",
    "wof:placetype":"locality"
},
  "geometry": {"coordinates":[128.26070000000001,37.3109],"type":"Point"}
}