{
  "type": "Feature",
  "properties": {
    "iso:country":"KR",
    "qs:name":"\uc77c\uc0b0\uc11c\uad6c",
    "qs:name_adm0":"\ud55c\uad6d",
    "qs:name_adm1":"\uacbd\uae30\ub3c4",
    "qs:photos":184,
    "qs:photos_1k":37,
    "qs:photos_9k":11,
    "qs:photos_9r":10,
    "qs:photos_all":2429,
    "qs:photos_sr":4,
    "qs:placetype":"LocalAdmin",
    "qs:pop_sr":"0",
    "wof:name":"\uc77c\uc0b0\uc11c\uad6c",
    "wof:placetype":"localadmin"
},
  "geometry": {"coordinates":[126.759653,37.668456],"type":"Point"}
}