{
  "type": "Feature",
  "properties": {
    "gn:admin1_code":"3.0",
    "gn:asciiname":"Soch'ang",
    "gn:country_code":"KR",
    "gn:dem":345,
    "gn:feature_class":"P",
    "gn:feature_code":"PPL",
    "gn:name":"S\u014fch\u2019ang",
    "gn:population":0,
    "gn:timezone":"Asia/Seoul",
    "iso:country":"KR",
    "name:und_x_variant":[
        "\uc11c\ucc3d",
        "S\u014fch\u2019ang"
    ],
    "wof:name":"Soch'ang",
    "wof:placetype":"locality"
},
  "geometry": {"coordinates":[127.67273,35.94918],"type":"Point"}
}