{
  "type": "Feature",
  "properties": {
    "gn:admin1_code":"20.0",
    "gn:asciiname":"Kusa",
    "gn:country_code":"KR",
    "gn:dem":31,
    "gn:feature_class":"P",
    "gn:feature_code":"PPL",
    "gn:name":"Kusa",
    "gn:population":0,
    "gn:timezone":"Asia/Seoul",
    "iso:country":"KR",
    "name:ceb_x_preferred":[
        "Kusa"
    ],
    "name:deu_x_preferred":[
        "Kusa"
    ],
    "name:nld_x_preferred":[
        "Kusa"
    ],
    "name:rus_x_preferred":[
        "\u041a\u0443\u0441\u0430"
    ],
    "name:swe_x_preferred":[
        "Kusa"
    ],
    "name:und_x_variant":[
        "\uad6c\uc0ac",
        "Kusa"
    ],
    "wof:name":"Kusa",
    "wof:placetype":"locality"
},
  "geometry": {"coordinates":[128.43476999999999,35.33207],"type":"Point"}
}