{
  "type": "Feature",
  "properties": {
    "gn:admin1_code":"6.0",
    "gn:asciiname":"Jungbaeyang",
    "gn:country_code":"KR",
    "gn:dem":430,
    "gn:feature_class":"P",
    "gn:feature_code":"PPL",
    "gn:name":"Jungbaeyang",
    "gn:population":0,
    "gn:timezone":"Asia/Seoul",
    "iso:country":"KR",
    "name:kor_x_preferred":[
        "\uc911\ubc30\uc591"
    ],
    "wof:name":"Jungbaeyang",
    "wof:placetype":"locality"
},
  "geometry": {"coordinates":[128.20595,38.29242],"type":"Point"}
}