{
  "type": "Feature",
  "properties": {
    "gn:admin1_code":"17.0",
    "gn:asciiname":"Jangteo",
    "gn:country_code":"KR",
    "gn:dem":29,
    "gn:feature_class":"P",
    "gn:feature_code":"PPL",
    "gn:name":"Jangteo",
    "gn:population":0,
    "gn:timezone":"Asia/Seoul",
    "iso:country":"KR",
    "name:und_x_variant":[
        "\uc7a5\ud130",
        "Changt\u2019\u014f",
        "Jangteo"
    ],
    "wof:name":"Jangteo",
    "wof:placetype":"locality"
},
  "geometry": {"coordinates":[127.28115,36.46647],"type":"Point"}
}