{
  "type": "Feature",
  "properties": {
    "gn:admin1_code":"13.0",
    "gn:asciiname":"Jaeneomeo",
    "gn:country_code":"KR",
    "gn:dem":57,
    "gn:feature_class":"P",
    "gn:feature_code":"PPL",
    "gn:name":"Jaeneomeo",
    "gn:population":0,
    "gn:timezone":"Asia/Seoul",
    "iso:country":"KR",
    "name:und_x_variant":[
        "\uc7ac\ub118\uc5b4",
        "Jaeneomeo",
        "Chaen\u014fm\u014f"
    ],
    "wof:name":"Jaeneomeo",
    "wof:placetype":"locality"
},
  "geometry": {"coordinates":[127.10944000000001,37.38444000000001],"type":"Point"}
}