{
  "type": "Feature",
  "properties": {
    "gn:admin1_code":"13.0",
    "gn:asciiname":"Kach'ae-ri",
    "gn:country_code":"KR",
    "gn:dem":114,
    "gn:feature_class":"P",
    "gn:feature_code":"PPLL",
    "gn:name":"Kach\u2019ae-ri",
    "gn:population":0,
    "gn:timezone":"Asia/Seoul",
    "iso:country":"KR",
    "name:kor_x_preferred":[
        "\uac00\ucc44\ub9ac"
    ],
    "name:kor_x_variant":[
        "Kach\u2019ae-ri"
    ],
    "wof:name":"Kach'ae-ri",
    "wof:placetype":"locality"
},
  "geometry": {"coordinates":[127.21184,37.92166],"type":"Point"}
}