{
  "type": "Feature",
  "properties": {
    "gn:admin1_code":"12.0",
    "gn:asciiname":"Sammok-tong",
    "gn:country_code":"KR",
    "gn:dem":14,
    "gn:feature_class":"P",
    "gn:feature_code":"PPL",
    "gn:name":"Sammok-tong",
    "gn:population":0,
    "gn:timezone":"Asia/Seoul",
    "iso:country":"KR",
    "name:und_x_variant":[
        "Sammong-ni",
        "\uc0bc\ubaa9\ub3d9",
        "Sammok",
        "Sammok-dong",
        "Sammok-tong"
    ],
    "wof:name":"Sammok-tong",
    "wof:placetype":"locality"
},
  "geometry": {"coordinates":[126.46583,37.48333],"type":"Point"}
}