{
  "type": "Feature",
  "properties": {
    "gn:admin1_code":"16.0",
    "gn:asciiname":"Namseong",
    "gn:country_code":"KR",
    "gn:dem":29,
    "gn:feature_class":"P",
    "gn:feature_code":"PPL",
    "gn:name":"Namseong",
    "gn:population":0,
    "gn:timezone":"Asia/Seoul",
    "iso:country":"KR",
    "name:kor_x_preferred":[
        "\ub0a8\uc131"
    ],
    "name:und_x_variant":[
        "Nams\u014fng-ni",
        "Nams\u014fng",
        "Namseong"
    ],
    "wof:name":"Namseong",
    "wof:placetype":"locality"
},
  "geometry": {"coordinates":[126.41828,34.91293],"type":"Point"}
}