{
  "type": "Feature",
  "properties": {
    "gn:admin1_code":"3.0",
    "gn:asciiname":"Kaech'i",
    "gn:country_code":"KR",
    "gn:dem":249,
    "gn:feature_class":"P",
    "gn:feature_code":"PPL",
    "gn:name":"Kaech\u2019i",
    "gn:population":0,
    "gn:timezone":"Asia/Seoul",
    "iso:country":"KR",
    "name:und_x_variant":[
        "\uac1c\uce58",
        "Kaech\u2019i",
        "Gaechi"
    ],
    "wof:name":"Kaech'i",
    "wof:placetype":"locality"
},
  "geometry": {"coordinates":[127.43367000000001,35.57725],"type":"Point"}
}