{
  "type": "Feature",
  "properties": {
    "gn:admin1_code":"5.0",
    "gn:asciiname":"Sanjo-gol",
    "gn:country_code":"KR",
    "gn:dem":235,
    "gn:feature_class":"P",
    "gn:feature_code":"PPL",
    "gn:name":"Sanj\u014f-gol",
    "gn:population":0,
    "gn:timezone":"Asia/Seoul",
    "iso:country":"KR",
    "name:und_x_variant":[
        "\uc0b0\uc800\uace8",
        "Sanj\u014f-gol"
    ],
    "wof:name":"Sanjo-gol",
    "wof:placetype":"locality"
},
  "geometry": {"coordinates":[127.65300000000001,36.4876],"type":"Point"}
}