{
  "type": "Feature",
  "properties": {
    "gn:admin1_code":"14.0",
    "gn:asciiname":"Wonmundeok",
    "gn:country_code":"KR",
    "gn:dem":38,
    "gn:feature_class":"P",
    "gn:feature_code":"PPL",
    "gn:name":"Wonmundeok",
    "gn:population":0,
    "gn:timezone":"Asia/Seoul",
    "iso:country":"KR",
    "name:kor_x_preferred":[
        "\uc6d0\ubb38\ub355"
    ],
    "wof:name":"Wonmundeok",
    "wof:placetype":"locality"
},
  "geometry": {"coordinates":[129.404,35.95348],"type":"Point"}
}