{
  "type": "Feature",
  "properties": {
    "gn:admin1_code":"17.0",
    "gn:asciiname":"Haipsok",
    "gn:country_code":"KR",
    "gn:dem":39,
    "gn:feature_class":"P",
    "gn:feature_code":"PPL",
    "gn:name":"Haips\u014fk",
    "gn:population":0,
    "gn:timezone":"Asia/Seoul",
    "iso:country":"KR",
    "name:und_x_variant":[
        "\ud558\uc785\uc11d",
        "Haips\u014fk"
    ],
    "wof:name":"Haipsok",
    "wof:placetype":"locality"
},
  "geometry": {"coordinates":[126.4699,36.7915],"type":"Point"}
}