{
  "type": "Feature",
  "properties": {
    "gn:admin1_code":"3.0",
    "gn:asciiname":"Choch'on-dong",
    "gn:country_code":"KR",
    "gn:dem":20,
    "gn:feature_class":"P",
    "gn:feature_code":"PPL",
    "gn:name":"Choch\u2019on-dong",
    "gn:population":0,
    "gn:timezone":"Asia/Seoul",
    "iso:country":"KR",
    "name:und_x_variant":[
        "\uc870\ucd0c\ub3d9",
        "Choch\u2019on-dong"
    ],
    "wof:name":"Choch'on-dong",
    "wof:placetype":"locality"
},
  "geometry": {"coordinates":[127.03727000000001,35.87487],"type":"Point"}
}