{
  "type": "Feature",
  "properties": {
    "gn:admin1_code":"16.0",
    "gn:asciiname":"Yongp'yong-dong",
    "gn:country_code":"KR",
    "gn:dem":31,
    "gn:feature_class":"P",
    "gn:feature_code":"PPL",
    "gn:name":"Y\u014fngp\u2019y\u014fng-dong",
    "gn:population":0,
    "gn:timezone":"Asia/Seoul",
    "iso:country":"KR",
    "name:kor_x_preferred":[
        "Y\u014fngp\u2019y\u014fng-dong"
    ],
    "wof:name":"Yongp'yong-dong",
    "wof:placetype":"locality"
},
  "geometry": {"coordinates":[126.81917,34.57556],"type":"Point"}
}