{
  "type": "Feature",
  "properties": {
    "gn:admin1_code":"5.0",
    "gn:asciiname":"Neommal",
    "gn:country_code":"KR",
    "gn:dem":97,
    "gn:feature_class":"P",
    "gn:feature_code":"PPL",
    "gn:name":"Neommal",
    "gn:population":0,
    "gn:timezone":"Asia/Seoul",
    "iso:country":"KR",
    "name:kor_x_preferred":[
        "\ub118\ub9d0"
    ],
    "wof:name":"Neommal",
    "wof:placetype":"locality"
},
  "geometry": {"coordinates":[127.36190000000001,36.74084000000001],"type":"Point"}
}