{
  "type": "Feature",
  "properties": {
    "gn:admin1_code":"12.0",
    "gn:asciiname":"Yeochagol",
    "gn:country_code":"KR",
    "gn:dem":21,
    "gn:feature_class":"P",
    "gn:feature_code":"PPL",
    "gn:name":"Yeochagol",
    "gn:population":0,
    "gn:timezone":"Asia/Seoul",
    "iso:country":"KR",
    "name:kor_x_preferred":[
        "\uc5ec\ucc28\uace8"
    ],
    "name:und_x_variant":[
        "Y\u014fja-gol"
    ],
    "wof:name":"Yeochagol",
    "wof:placetype":"locality"
},
  "geometry": {"coordinates":[126.39587,37.60778],"type":"Point"}
}