{
  "type": "Feature",
  "properties": {
    "gn:admin1_code":"16.0",
    "gn:asciiname":"Daechi",
    "gn:country_code":"KR",
    "gn:dem":71,
    "gn:feature_class":"P",
    "gn:feature_code":"PPL",
    "gn:name":"Daechi",
    "gn:population":0,
    "gn:timezone":"Asia/Seoul",
    "iso:country":"KR",
    "name:kor_x_preferred":[
        "\ub300\uce58"
    ],
    "name:kor_x_variant":[
        "Taech\u2019i"
    ],
    "name:und_x_variant":[
        "Taeji",
        "Daechi"
    ],
    "wof:name":"Daechi",
    "wof:placetype":"locality"
},
  "geometry": {"coordinates":[127.38373,34.85570999999999],"type":"Point"}
}