{
  "type": "Feature",
  "properties": {
    "gn:admin1_code":"6.0",
    "gn:asciiname":"Daewol",
    "gn:country_code":"KR",
    "gn:dem":200,
    "gn:feature_class":"P",
    "gn:feature_code":"PPL",
    "gn:name":"Daewol",
    "gn:population":0,
    "gn:timezone":"Asia/Seoul",
    "iso:country":"KR",
    "name:kor_x_preferred":[
        "\ub300\uc6d4"
    ],
    "name:kor_x_variant":[
        "Taew\u014fl"
    ],
    "wof:name":"Daewol",
    "wof:placetype":"locality"
},
  "geometry": {"coordinates":[127.99167,38.07472],"type":"Point"}
}