{
  "type": "Feature",
  "properties": {
    "iso:country":"KR",
    "name:eng_x_preferred":[
        "Sangnok"
    ],
    "name:eng_x_variant":[
        "Sangnok-gu"
    ],
    "name:kor_x_preferred":[
        "\uc0c1\ub85d\uad6c"
    ],
    "qs:name":"\uc0c1\ub85d\uad6c",
    "qs:name_adm0":"\ud55c\uad6d",
    "qs:name_adm1":"\uacbd\uae30\ub3c4",
    "qs:photos":3,
    "qs:photos_1k":1,
    "qs:photos_9k":4,
    "qs:photos_9r":6,
    "qs:photos_all":822,
    "qs:photos_sr":1,
    "qs:placetype":"LocalAdmin",
    "qs:pop_sr":"0",
    "wof:name":"Sangnok",
    "wof:placetype":"localadmin"
},
  "geometry": {"coordinates":[126.855469,37.3065],"type":"Point"}
}