{
  "type": "Feature",
  "properties": {
    "gn:admin1_code":"6.0",
    "gn:asciiname":"Baengmachon",
    "gn:country_code":"KR",
    "gn:dem":390,
    "gn:feature_class":"P",
    "gn:feature_code":"PPL",
    "gn:name":"Baengmachon",
    "gn:population":0,
    "gn:timezone":"Asia/Seoul",
    "iso:country":"KR",
    "name:und_x_variant":[
        "\ubc31\ub9c8\ucd0c",
        "Paengmach\u2019on",
        "Baengmachon"
    ],
    "wof:name":"Baengmachon",
    "wof:placetype":"locality"
},
  "geometry": {"coordinates":[127.53180999999999,38.11549],"type":"Point"}
}