{
  "type": "Feature",
  "properties": {
    "gn:admin1_code":"20.0",
    "gn:admin2_code":"Masan-si",
    "gn:asciiname":"Araekkae",
    "gn:country_code":"KR",
    "gn:dem":106,
    "gn:feature_class":"P",
    "gn:feature_code":"PPL",
    "gn:name":"Araekkae",
    "gn:population":0,
    "gn:timezone":"Asia/Seoul",
    "iso:country":"KR",
    "wof:name":"Araekkae",
    "wof:placetype":"locality"
},
  "geometry": {"coordinates":[128.5575,35.05472],"type":"Point"}
}