{
  "type": "Feature",
  "properties": {
    "gn:admin1_code":"15.0",
    "gn:asciiname":"Jigyeong",
    "gn:country_code":"KR",
    "gn:dem":349,
    "gn:feature_class":"P",
    "gn:feature_code":"PPL",
    "gn:name":"Jigyeong",
    "gn:population":0,
    "gn:timezone":"Asia/Seoul",
    "iso:country":"KR",
    "name:kor_x_preferred":[
        "\uc9c0\uacbd"
    ],
    "name:und_x_variant":[
        "Chigy\u014fng"
    ],
    "wof:name":"Jigyeong",
    "wof:placetype":"locality"
},
  "geometry": {"coordinates":[128.74411000000001,35.96581],"type":"Point"}
}