{
  "type": "Feature",
  "properties": {
    "gn:admin1_code":"1.0",
    "gn:asciiname":"Wolsan",
    "gn:country_code":"KR",
    "gn:dem":86,
    "gn:feature_class":"P",
    "gn:feature_code":"PPL",
    "gn:name":"Wolsan",
    "gn:population":0,
    "gn:timezone":"Asia/Seoul",
    "iso:country":"KR",
    "name:kor_x_preferred":[
        "\uc6d4\uc0b0"
    ],
    "name:und_x_variant":[
        "W\u014flsan-dong",
        "W\u014flsan",
        "Wolsan"
    ],
    "wof:name":"Wolsan",
    "wof:placetype":"locality"
},
  "geometry": {"coordinates":[126.46151999999999,33.47409],"type":"Point"}
}