{
  "type": "Feature",
  "properties": {
    "iso:country":"KR",
    "qs:name":"\uc6d0\ub355\uc74d",
    "qs:name_adm0":"\ud55c\uad6d",
    "qs:name_adm1":"\uac15\uc6d0\ub3c4",
    "qs:photos":7,
    "qs:photos_1k":1,
    "qs:photos_9k":1,
    "qs:photos_9r":1,
    "qs:photos_all":7,
    "qs:photos_sr":1,
    "qs:placetype":"LocalAdmin",
    "qs:pop_sr":"0",
    "wof:name":"\uc6d0\ub355\uc74d",
    "wof:placetype":"localadmin"
},
  "geometry": {"coordinates":[129.32650000000001,37.2692],"type":"Point"}
}