{
  "type": "Feature",
  "properties": {
    "gn:country":"KR",
    "gn:fcode":"PPL",
    "gn:population":0,
    "iso:country":"KR",
    "name:und_x_variant":[
        "\uc6a9\uc0b0\ub3d9"
    ],
    "qs:name":"\ub3d9\uc0b0\ub3d9",
    "qs:name_adm0":"\ud55c\uad6d",
    "qs:name_adm1":"\uc804\ub77c\ubd81\ub3c4",
    "qs:photos":13,
    "qs:photos_1k":3,
    "qs:photos_9k":1,
    "qs:photos_9r":1,
    "qs:photos_all":13,
    "qs:photos_sr":1,
    "qs:placetype":"Suburb",
    "qs:pop_sr":"0",
    "wof:name":"\ub3d9\uc0b0\ub3d9",
    "wof:placetype":"neighbourhood",
    "wof:population":0
},
  "geometry": {"coordinates":[127.4023,36.4204],"type":"Point"}
}