{
  "type": "Feature",
  "properties": {
    "iso:country":"KR",
    "qs:name":"\uc644\uc0b0\uad6c",
    "qs:name_adm0":"\ud55c\uad6d",
    "qs:name_adm1":"\uc804\ub77c\ubd81\ub3c4",
    "qs:photos":1,
    "qs:photos_1k":1,
    "qs:photos_9k":9,
    "qs:photos_9r":9,
    "qs:photos_all":2063,
    "qs:photos_sr":1,
    "qs:placetype":"LocalAdmin",
    "qs:pop_sr":"0",
    "wof:name":"\uc644\uc0b0\uad6c",
    "wof:placetype":"localadmin"
},
  "geometry": {"coordinates":[127.149753,35.814841],"type":"Point"}
}