{
  "type": "Feature",
  "properties": {
    "gn:admin1_code":"20.0",
    "gn:asciiname":"Sadong-ni",
    "gn:country_code":"KR",
    "gn:dem":25,
    "gn:feature_class":"P",
    "gn:feature_code":"PPL",
    "gn:name":"Sadong-ni",
    "gn:population":0,
    "gn:timezone":"Asia/Seoul",
    "iso:country":"KR",
    "name:eng_x_preferred":[
        "Sadong"
    ],
    "name:eng_x_variant":[
        "Sadong-ni"
    ],
    "name:und_x_variant":[
        "\uc0ac\ub3d9\ub9ac",
        "Sadong-ni"
    ],
    "wof:name":"Sadong",
    "wof:placetype":"locality"
},
  "geometry": {"coordinates":[128.48093,35.11995],"type":"Point"}
}