{
  "type": "Feature",
  "properties": {
    "gn:admin1_code":"6.0",
    "gn:asciiname":"Geomyul-ri",
    "gn:country_code":"KR",
    "gn:dem":293,
    "gn:feature_class":"P",
    "gn:feature_code":"PPL",
    "gn:name":"Geomyul-ri",
    "gn:population":0,
    "gn:timezone":"Asia/Seoul",
    "iso:country":"KR",
    "name:kor_x_preferred":[
        "\uac80\ub960\ub9ac"
    ],
    "name:kor_x_variant":[
        "K\u014fmnyul-li",
        "\uac80\uc728\ub9ac"
    ],
    "wof:name":"Geomyul-ri",
    "wof:placetype":"locality"
},
  "geometry": {"coordinates":[127.91878,37.6901],"type":"Point"}
}