{
  "type": "Feature",
  "properties": {
    "gn:admin1_code":"17.0",
    "gn:asciiname":"Yongdu",
    "gn:country_code":"KR",
    "gn:dem":26,
    "gn:feature_class":"P",
    "gn:feature_code":"PPL",
    "gn:name":"Yongdu",
    "gn:population":0,
    "gn:timezone":"Asia/Seoul",
    "iso:country":"KR",
    "name:und_x_variant":[
        "\uc6a9\ub450",
        "Yongdu"
    ],
    "wof:name":"Yongdu",
    "wof:placetype":"locality"
},
  "geometry": {"coordinates":[126.6267,36.5097],"type":"Point"}
}