{
  "type": "Feature",
  "properties": {
    "gn:admin1_code":"17.0",
    "gn:asciiname":"Hambagi",
    "gn:country_code":"KR",
    "gn:dem":47,
    "gn:feature_class":"P",
    "gn:feature_code":"PPL",
    "gn:name":"Hambagi",
    "gn:population":0,
    "gn:timezone":"Asia/Seoul",
    "iso:country":"KR",
    "name:und_x_variant":[
        "\ud568\ubc15\uc774",
        "Hambagi"
    ],
    "wof:name":"Hambagi",
    "wof:placetype":"locality"
},
  "geometry": {"coordinates":[126.6591,36.5198],"type":"Point"}
}