{
  "type": "Feature",
  "properties": {
    "gn:admin1_code":"5.0",
    "gn:asciiname":"Goseong",
    "gn:country_code":"KR",
    "gn:dem":122,
    "gn:feature_class":"P",
    "gn:feature_code":"PPL",
    "gn:name":"Goseong",
    "gn:population":0,
    "gn:timezone":"Asia/Seoul",
    "iso:country":"KR",
    "name:und_x_variant":[
        "Y\u014fn\u2019go",
        "Kos\u014fng",
        "\uace0\uc131",
        "Goseong"
    ],
    "wof:name":"Goseong",
    "wof:placetype":"locality"
},
  "geometry": {"coordinates":[127.6546,36.3365],"type":"Point"}
}