{
  "type": "Feature",
  "properties": {
    "gn:admin1_code":"5.0",
    "gn:asciiname":"Goseong",
    "gn:country_code":"KR",
    "gn:dem":122,
    "gn:feature_class":"P",
    "gn:feature_code":"PPL",
    "gn:name":"Goseong",
    "gn:population":0,
    "gn:timezone":"Asia/Seoul",
    "iso:country":"KR",
    "name:ara_x_preferred":[
        "\u063a\u0648\u0633\u0648\u0646\u063a"
    ],
    "name:ceb_x_preferred":[
        "Goseong"
    ],
    "name:jpn_x_preferred":[
        "\u30b3\u30bd\u30f3"
    ],
    "name:mon_x_preferred":[
        "\u041a\u0443\u0441\u043e\u043d-\u0433\u04af\u043d\u044c"
    ],
    "name:swe_x_preferred":[
        "Goseong"
    ],
    "name:und_x_variant":[
        "Y\u014fn\u2019go",
        "Kos\u014fng",
        "\uace0\uc131"
    ],
    "name:vie_x_preferred":[
        "Goseong"
    ],
    "wof:name":"Goseong",
    "wof:placetype":"locality"
},
  "geometry": {"coordinates":[127.6546,36.3365],"type":"Point"}
}