{
  "type": "Feature",
  "properties": {
    "gn:admin1_code":"14.0",
    "gn:asciiname":"Jigyeong",
    "gn:country_code":"KR",
    "gn:dem":207,
    "gn:feature_class":"P",
    "gn:feature_code":"PPL",
    "gn:name":"Jigyeong",
    "gn:population":0,
    "gn:timezone":"Asia/Seoul",
    "iso:country":"KR",
    "name:kor_x_preferred":[
        "\uc9c0\uacbd"
    ],
    "wof:name":"Jigyeong",
    "wof:placetype":"locality"
},
  "geometry": {"coordinates":[128.81406999999999,36.15014],"type":"Point"}
}