{
  "type": "Feature",
  "properties": {
    "gn:admin1_code":"16.0",
    "gn:asciiname":"Koyo",
    "gn:country_code":"KR",
    "gn:dem":34,
    "gn:feature_class":"P",
    "gn:feature_code":"PPL",
    "gn:name":"Koyo",
    "gn:population":0,
    "gn:timezone":"Asia/Seoul",
    "iso:country":"KR",
    "name:ceb_x_preferred":[
        "Goheung-gun"
    ],
    "name:jpn_x_preferred":[
        "\u9ad8\u8208\u90e1"
    ],
    "name:kor_x_preferred":[
        "\uace0\ud765"
    ],
    "name:kor_x_variant":[
        "Koh\u016dng",
        "\uace0\ud765\uad70"
    ],
    "name:mon_x_preferred":[
        "\u041a\u0443\u0445\u04e9\u043d-\u0433\u04af\u043d\u044c"
    ],
    "name:nor_x_preferred":[
        "Goheung"
    ],
    "name:por_x_preferred":[
        "Goheung"
    ],
    "name:rus_x_preferred":[
        "\u041a\u043e\u0445\u044b\u043d"
    ],
    "name:spa_x_preferred":[
        "Goheung-gun"
    ],
    "name:swe_x_preferred":[
        "Goheung"
    ],
    "name:und_x_variant":[
        "Funyan",
        "K\u014dk\u014d",
        "Goheung",
        "Koyo"
    ],
    "name:urd_x_preferred":[
        "\u06af\u0648\u06c1\u0626\u0648\u0646\u06af \u06a9\u0627\u0624\u0646\u0679\u06cc"
    ],
    "name:vie_x_preferred":[
        "Goheung"
    ],
    "name:zho_x_preferred":[
        "\u9ad8\u8208\u90e1"
    ],
    "wof:name":"Koyo",
    "wof:placetype":"locality"
},
  "geometry": {"coordinates":[127.28446,34.61008],"type":"Point"}
}