{
  "type": "Feature",
  "properties": {
    "gn:admin1_code":"5.0",
    "gn:asciiname":"Yongdam",
    "gn:country_code":"KR",
    "gn:dem":63,
    "gn:feature_class":"P",
    "gn:feature_code":"PPL",
    "gn:name":"Yongdam",
    "gn:population":0,
    "gn:timezone":"Asia/Seoul",
    "iso:country":"KR",
    "name:kor_x_preferred":[
        "\uc6a9\ub2f4"
    ],
    "wof:name":"Yongdam",
    "wof:placetype":"locality"
},
  "geometry": {"coordinates":[127.52143999999998,36.74877],"type":"Point"}
}