{
  "type": "Feature",
  "properties": {
    "gn:admin1_code":"3.0",
    "gn:asciiname":"Pangok",
    "gn:country_code":"KR",
    "gn:dem":216,
    "gn:feature_class":"P",
    "gn:feature_code":"PPL",
    "gn:name":"Pangok",
    "gn:population":0,
    "gn:timezone":"Asia/Seoul",
    "iso:country":"KR",
    "name:und_x_variant":[
        "\ubc18\uace1",
        "Pangok",
        "Bangok"
    ],
    "wof:name":"Pangok",
    "wof:placetype":"locality"
},
  "geometry": {"coordinates":[127.41646,35.55967000000001],"type":"Point"}
}