{
  "type": "Feature",
  "properties": {
    "gn:admin1_code":"16.0",
    "gn:asciiname":"Juksan",
    "gn:country_code":"KR",
    "gn:dem":60,
    "gn:feature_class":"P",
    "gn:feature_code":"PPL",
    "gn:name":"Juksan",
    "gn:population":0,
    "gn:timezone":"Asia/Seoul",
    "iso:country":"KR",
    "name:kor_x_preferred":[
        "\uc8fd\uc0b0"
    ],
    "name:und_x_variant":[
        "Chuksan-ni",
        "Chuksan",
        "Juksan"
    ],
    "wof:name":"Juksan",
    "wof:placetype":"locality"
},
  "geometry": {"coordinates":[126.77083,34.72139],"type":"Point"}
}