{
  "type": "Feature",
  "properties": {
    "gn:admin1_code":"13.0",
    "gn:asciiname":"Seonseok",
    "gn:country_code":"KR",
    "gn:dem":83,
    "gn:feature_class":"P",
    "gn:feature_code":"PPL",
    "gn:name":"Seonseok",
    "gn:population":0,
    "gn:timezone":"Asia/Seoul",
    "iso:country":"KR",
    "name:kor_x_preferred":[
        "\uc120\uc11d"
    ],
    "wof:name":"Seonseok",
    "wof:placetype":"locality"
},
  "geometry": {"coordinates":[127.01927999999999,37.75878],"type":"Point"}
}