{
  "type": "Feature",
  "properties": {
    "gn:admin1_code":"20.0",
    "gn:asciiname":"Kye-dong",
    "gn:country_code":"KR",
    "gn:dem":248,
    "gn:feature_class":"P",
    "gn:feature_code":"PPL",
    "gn:name":"Kye-dong",
    "gn:population":0,
    "gn:timezone":"Asia/Seoul",
    "iso:country":"KR",
    "name:und_x_variant":[
        "\uacc4\ub3d9",
        "Kye-dong"
    ],
    "wof:name":"Kye-dong",
    "wof:placetype":"locality"
},
  "geometry": {"coordinates":[127.86414000000001,35.70346],"type":"Point"}
}