{
  "type": "Feature",
  "properties": {
    "gn:admin1_code":"6.0",
    "gn:asciiname":"Ibam-ni",
    "gn:country_code":"KR",
    "gn:dem":20,
    "gn:feature_class":"P",
    "gn:feature_code":"PPLL",
    "gn:name":"Ibam-ni",
    "gn:population":0,
    "gn:timezone":"Asia/Seoul",
    "iso:country":"KR",
    "name:kor_x_preferred":[
        "\uc785\uc554\ub9ac"
    ],
    "wof:name":"Ibam-ni",
    "wof:placetype":"locality"
},
  "geometry": {"coordinates":[128.77395000000001,37.93011],"type":"Point"}
}