{
  "type": "Feature",
  "properties": {
    "gn:admin1_code":"14.0",
    "gn:asciiname":"Pombawi",
    "gn:country_code":"KR",
    "gn:dem":15,
    "gn:feature_class":"P",
    "gn:feature_code":"PPL",
    "gn:name":"P\u014fmbawi",
    "gn:population":0,
    "gn:timezone":"Asia/Seoul",
    "iso:country":"KR",
    "name:und_x_variant":[
        "\ubc94\ubc14\uc704",
        "P\u014fmbawi"
    ],
    "wof:name":"Pombawi",
    "wof:placetype":"locality"
},
  "geometry": {"coordinates":[129.40180000000001,36.6055],"type":"Point"}
}