{
  "type": "Feature",
  "properties": {
    "gn:admin1_code":"17.0",
    "gn:asciiname":"Hwangsan-ni",
    "gn:country_code":"KR",
    "gn:dem":4,
    "gn:feature_class":"P",
    "gn:feature_code":"PPL",
    "gn:name":"Hwangsan-ni",
    "gn:population":0,
    "gn:timezone":"Asia/Seoul",
    "iso:country":"KR",
    "name:eng_x_preferred":[
        "Hwangsan"
    ],
    "name:eng_x_variant":[
        "Hwangsan-ni"
    ],
    "wof:name":"Hwangsan",
    "wof:placetype":"locality"
},
  "geometry": {"coordinates":[126.71666999999999,36.06667],"type":"Point"}
}