{
  "type": "Feature",
  "properties": {
    "gn:admin1_code":"5.0",
    "gn:asciiname":"Chung-mal",
    "gn:country_code":"KR",
    "gn:dem":461,
    "gn:feature_class":"P",
    "gn:feature_code":"PPL",
    "gn:name":"Chung-mal",
    "gn:population":0,
    "gn:timezone":"Asia/Seoul",
    "iso:country":"KR",
    "name:und_x_variant":[
        "\uc911\ub9d0",
        "Chung-mal"
    ],
    "wof:name":"Chung-mal",
    "wof:placetype":"locality"
},
  "geometry": {"coordinates":[127.87690000000001,36.0687],"type":"Point"}
}