{
  "type": "Feature",
  "properties": {
    "gn:admin1_code":"5.0",
    "gn:asciiname":"Bakkatseongmaru",
    "gn:country_code":"KR",
    "gn:dem":89,
    "gn:feature_class":"P",
    "gn:feature_code":"PPL",
    "gn:name":"Bakkatseongmaru",
    "gn:population":0,
    "gn:timezone":"Asia/Seoul",
    "iso:country":"KR",
    "name:kor_x_preferred":[
        "\ubc14\uae65\uc131\ub9c8\ub8e8"
    ],
    "wof:name":"Bakkatseongmaru",
    "wof:placetype":"locality"
},
  "geometry": {"coordinates":[127.83595,36.96458],"type":"Point"}
}