{
  "type": "Feature",
  "properties": {
    "gn:admin1_code":"17.0",
    "gn:asciiname":"Yugye-ri",
    "gn:country_code":"KR",
    "gn:dem":31,
    "gn:feature_class":"P",
    "gn:feature_code":"PPL",
    "gn:name":"Yugye-ri",
    "gn:population":0,
    "gn:timezone":"Asia/Seoul",
    "iso:country":"KR",
    "name:und_x_variant":[
        "\uc720\uacc4\ub9ac",
        "Yugye-ri"
    ],
    "wof:name":"Yugye-ri",
    "wof:placetype":"locality"
},
  "geometry": {"coordinates":[126.52500000000001,36.7617],"type":"Point"}
}