{
  "type": "Feature",
  "properties": {
    "gn:admin1_code":"14.0",
    "gn:asciiname":"Chammok",
    "gn:country_code":"KR",
    "gn:dem":198,
    "gn:feature_class":"P",
    "gn:feature_code":"PPL",
    "gn:name":"Chammok",
    "gn:population":0,
    "gn:timezone":"Asia/Seoul",
    "iso:country":"KR",
    "name:und_x_variant":[
        "\uc7a0\ubaa9",
        "Chammok"
    ],
    "wof:name":"Chammok",
    "wof:placetype":"locality"
},
  "geometry": {"coordinates":[129.08420000000001,36.5423],"type":"Point"}
}