{
  "type": "Feature",
  "properties": {
    "gn:admin1_code":"14.0",
    "gn:asciiname":"Godo",
    "gn:country_code":"KR",
    "gn:dem":227,
    "gn:feature_class":"P",
    "gn:feature_code":"PPL",
    "gn:name":"Godo",
    "gn:population":0,
    "gn:timezone":"Asia/Seoul",
    "iso:country":"KR",
    "name:ceb_x_preferred":[
        "Godo"
    ],
    "name:deu_x_preferred":[
        "Godo"
    ],
    "name:fra_x_preferred":[
        "Godo"
    ],
    "name:kor_x_preferred":[
        "\uace0\ub3c4"
    ],
    "name:spa_x_preferred":[
        "Godo"
    ],
    "name:swe_x_preferred":[
        "Godo"
    ],
    "name:ukr_x_preferred":[
        "\u0490\u043e\u0434\u043e"
    ],
    "wof:name":"Godo",
    "wof:placetype":"locality"
},
  "geometry": {"coordinates":[128.97256999999999,36.64379],"type":"Point"}
}