{
  "type": "Feature",
  "properties": {
    "gn:admin1_code":"6.0",
    "gn:asciiname":"Chumakkori",
    "gn:country_code":"KR",
    "gn:dem":301,
    "gn:feature_class":"P",
    "gn:feature_code":"PPL",
    "gn:name":"Chumakk\u014fri",
    "gn:population":0,
    "gn:timezone":"Asia/Seoul",
    "iso:country":"KR",
    "name:kor_x_preferred":[
        "\uc8fc\ub9c9\uac70\ub9ac"
    ],
    "name:kor_x_variant":[
        "Chumakk\u014fri"
    ],
    "wof:name":"Chumakkori",
    "wof:placetype":"locality"
},
  "geometry": {"coordinates":[128.14019999999999,37.6157],"type":"Point"}
}