{
  "type": "Feature",
  "properties": {
    "gn:admin1_code":"20.0",
    "gn:asciiname":"Ch'onnae",
    "gn:country_code":"KR",
    "gn:dem":190,
    "gn:feature_class":"P",
    "gn:feature_code":"PPL",
    "gn:name":"Ch\u2019\u014fnnae",
    "gn:population":0,
    "gn:timezone":"Asia/Seoul",
    "iso:country":"KR",
    "name:und_x_variant":[
        "\ucc9c\ub0b4",
        "Ch\u2019\u014fnnae"
    ],
    "wof:name":"Ch'onnae",
    "wof:placetype":"locality"
},
  "geometry": {"coordinates":[128.02619000000001,35.53804],"type":"Point"}
}