{
  "type": "Feature",
  "properties": {
    "gn:admin1_code":"20.0",
    "gn:asciiname":"Hasin-ch'on",
    "gn:country_code":"KR",
    "gn:dem":31,
    "gn:feature_class":"P",
    "gn:feature_code":"PPL",
    "gn:name":"Hasin-ch\u2019on",
    "gn:population":0,
    "gn:timezone":"Asia/Seoul",
    "iso:country":"KR",
    "name:und_x_variant":[
        "\ud558\uc2e0\ucd0c",
        "Hasin-ch\u2019on"
    ],
    "wof:name":"Hasin-ch'on",
    "wof:placetype":"locality"
},
  "geometry": {"coordinates":[128.45698999999999,35.47215999999999],"type":"Point"}
}