{
  "type": "Feature",
  "properties": {
    "gn:admin1_code":"16.0",
    "gn:asciiname":"Tongsal-li",
    "gn:cc2":"KR",
    "gn:country_code":"KR",
    "gn:dem":15,
    "gn:feature_class":"P",
    "gn:feature_code":"PPL",
    "gn:name":"Tongsal-li",
    "gn:population":0,
    "gn:timezone":"Asia/Seoul",
    "iso:country":"KR",
    "name:und_x_variant":[
        "Tongsan-ni",
        "Tongsal-li"
    ],
    "wof:name":"Tongsal-li",
    "wof:placetype":"locality"
},
  "geometry": {"coordinates":[126.42,35.00028],"type":"Point"}
}