{
  "type": "Feature",
  "properties": {
    "gn:admin1_code":"13.0",
    "gn:asciiname":"Saemsil",
    "gn:country_code":"KR",
    "gn:dem":21,
    "gn:feature_class":"P",
    "gn:feature_code":"PPL",
    "gn:name":"Saemsil",
    "gn:population":0,
    "gn:timezone":"Asia/Seoul",
    "iso:country":"KR",
    "name:kor_x_preferred":[
        "\uc0d8\uc2e4"
    ],
    "wof:name":"Saemsil",
    "wof:placetype":"locality"
},
  "geometry": {"coordinates":[126.80306000000002,37.22417],"type":"Point"}
}