{
  "type": "Feature",
  "properties": {
    "gn:admin1_code":"14.0",
    "gn:asciiname":"Tungi",
    "gn:country_code":"KR",
    "gn:dem":120,
    "gn:feature_class":"P",
    "gn:feature_code":"PPL",
    "gn:name":"T\u016dngi",
    "gn:population":0,
    "gn:timezone":"Asia/Seoul",
    "iso:country":"KR",
    "name:ceb_x_preferred":[
        "Tungi"
    ],
    "name:swe_x_preferred":[
        "Tungi"
    ],
    "name:und_x_variant":[
        "\ub4f1\uc774",
        "T\u016dngi"
    ],
    "wof:name":"Tungi",
    "wof:placetype":"locality"
},
  "geometry": {"coordinates":[128.11089999999999,36.3804],"type":"Point"}
}