{
  "type": "Feature",
  "properties": {
    "gn:admin1_code":"6.0",
    "gn:asciiname":"Sucheonggol",
    "gn:country_code":"KR",
    "gn:dem":262,
    "gn:feature_class":"P",
    "gn:feature_code":"PPL",
    "gn:name":"Sucheonggol",
    "gn:population":0,
    "gn:timezone":"Asia/Seoul",
    "iso:country":"KR",
    "name:kor_x_preferred":[
        "\uc218\uccad\uace8"
    ],
    "name:kor_x_variant":[
        "Such\u2019\u014fng-gol"
    ],
    "wof:name":"Sucheonggol",
    "wof:placetype":"locality"
},
  "geometry": {"coordinates":[127.88737999999999,37.9785],"type":"Point"}
}