{
  "type": "Feature",
  "properties": {
    "gn:admin1_code":"14.0",
    "gn:asciiname":"Nurimi",
    "gn:country_code":"KR",
    "gn:dem":251,
    "gn:feature_class":"P",
    "gn:feature_code":"PPL",
    "gn:name":"N\u016drimi",
    "gn:population":0,
    "gn:timezone":"Asia/Seoul",
    "iso:country":"KR",
    "name:und_x_variant":[
        "\ub290\ub9ac\ubbf8",
        "N\u016drimi"
    ],
    "wof:name":"Nurimi",
    "wof:placetype":"locality"
},
  "geometry": {"coordinates":[128.8389,36.3699],"type":"Point"}
}