{
  "type": "Feature",
  "properties": {
    "gn:admin1_code":"14.0",
    "gn:asciiname":"Ppeoldigi",
    "gn:country_code":"KR",
    "gn:dem":176,
    "gn:feature_class":"P",
    "gn:feature_code":"PPL",
    "gn:name":"Ppeoldigi",
    "gn:population":0,
    "gn:timezone":"Asia/Seoul",
    "iso:country":"KR",
    "name:kor_x_preferred":[
        "\ubed8\ub514\uae30"
    ],
    "wof:name":"Ppeoldigi",
    "wof:placetype":"locality"
},
  "geometry": {"coordinates":[128.14569,36.69488],"type":"Point"}
}