{
  "type": "Feature",
  "properties": {
    "gn:admin1_code":"20.0",
    "gn:asciiname":"An-maul",
    "gn:country_code":"KR",
    "gn:dem":19,
    "gn:feature_class":"P",
    "gn:feature_code":"PPL",
    "gn:name":"An-ma\u016dl",
    "gn:population":0,
    "gn:timezone":"Asia/Seoul",
    "iso:country":"KR",
    "name:und_x_variant":[
        "\uc548\ub9c8\uc744",
        "An-ma\u016dl"
    ],
    "wof:name":"An-maul",
    "wof:placetype":"locality"
},
  "geometry": {"coordinates":[128.31127000000001,35.26951],"type":"Point"}
}