{
  "type": "Feature",
  "properties": {
    "gn:admin1_code":"1.0",
    "gn:admin2_code":"Namjeju-gun",
    "gn:asciiname":"Kwanjon-dong",
    "gn:country_code":"KR",
    "gn:dem":179,
    "gn:feature_class":"P",
    "gn:feature_code":"PPL",
    "gn:name":"Kwanj\u014fn-dong",
    "gn:population":0,
    "gn:timezone":"Asia/Seoul",
    "iso:country":"KR",
    "wof:name":"Kwanjon-dong",
    "wof:placetype":"locality"
},
  "geometry": {"coordinates":[126.31722000000001,33.29111],"type":"Point"}
}