{
  "type": "Feature",
  "properties": {
    "gn:admin1_code":"14.0",
    "gn:asciiname":"Pojeon",
    "gn:country_code":"KR",
    "gn:dem":11,
    "gn:feature_class":"P",
    "gn:feature_code":"PPL",
    "gn:name":"Pojeon",
    "gn:population":0,
    "gn:timezone":"Asia/Seoul",
    "iso:country":"KR",
    "name:kor_x_preferred":[
        "\ud3ec\uc804"
    ],
    "wof:name":"Pojeon",
    "wof:placetype":"locality"
},
  "geometry": {"coordinates":[129.23881,35.9529],"type":"Point"}
}