{
  "type": "Feature",
  "properties": {
    "gn:admin1_code":"12.0",
    "gn:asciiname":"Yangdalmal",
    "gn:country_code":"KR",
    "gn:dem":17,
    "gn:feature_class":"P",
    "gn:feature_code":"PPL",
    "gn:name":"Yangdalmal",
    "gn:population":0,
    "gn:timezone":"Asia/Seoul",
    "iso:country":"KR",
    "name:kor_x_preferred":[
        "\uc591\ub2ec\ub9d0"
    ],
    "wof:name":"Yangdalmal",
    "wof:placetype":"locality"
},
  "geometry": {"coordinates":[126.45205,37.62698],"type":"Point"}
}