{
  "type": "Feature",
  "properties": {
    "gn:admin1_code":"13.0",
    "gn:asciiname":"Gulpani",
    "gn:country_code":"KR",
    "gn:dem":14,
    "gn:feature_class":"P",
    "gn:feature_code":"PPL",
    "gn:name":"Gulpani",
    "gn:population":0,
    "gn:timezone":"Asia/Seoul",
    "iso:country":"KR",
    "name:kor_x_preferred":[
        "\uad74\ud310\uc774"
    ],
    "wof:name":"Gulpani",
    "wof:placetype":"locality"
},
  "geometry": {"coordinates":[126.80138999999998,37.20556],"type":"Point"}
}