{
  "type": "Feature",
  "properties": {
    "gn:admin1_code":"5.0",
    "gn:asciiname":"Bakkatandong",
    "gn:country_code":"KR",
    "gn:dem":153,
    "gn:feature_class":"P",
    "gn:feature_code":"PPL",
    "gn:name":"Bakkatandong",
    "gn:population":0,
    "gn:timezone":"Asia/Seoul",
    "iso:country":"KR",
    "name:kor_x_preferred":[
        "\ubc14\uae65\uc548\ub3d9"
    ],
    "wof:name":"Bakkatandong",
    "wof:placetype":"locality"
},
  "geometry": {"coordinates":[128.31585000000001,37.03122000000001],"type":"Point"}
}