{
  "type": "Feature",
  "properties": {
    "gn:admin1_code":"14.0",
    "gn:asciiname":"Somi",
    "gn:country_code":"KR",
    "gn:dem":398,
    "gn:feature_class":"P",
    "gn:feature_code":"PPL",
    "gn:name":"Somi",
    "gn:population":0,
    "gn:timezone":"Asia/Seoul",
    "iso:country":"KR",
    "name:deu_x_preferred":[
        "Somi"
    ],
    "name:und_x_variant":[
        "\uc18c\ubbf8"
    ],
    "wof:name":"Somi",
    "wof:placetype":"locality"
},
  "geometry": {"coordinates":[128.9796,36.3483],"type":"Point"}
}