{
  "type": "Feature",
  "properties": {
    "gn:admin1_code":"14.0",
    "gn:asciiname":"Yangjimaeul",
    "gn:country_code":"KR",
    "gn:dem":291,
    "gn:feature_class":"P",
    "gn:feature_code":"PPL",
    "gn:name":"Yangjimaeul",
    "gn:population":0,
    "gn:timezone":"Asia/Seoul",
    "iso:country":"KR",
    "name:kor_x_preferred":[
        "\uc591\uc9c0\ub9c8\uc744"
    ],
    "wof:name":"Yangjimaeul",
    "wof:placetype":"locality"
},
  "geometry": {"coordinates":[128.63385,36.9811],"type":"Point"}
}