{
  "type": "Feature",
  "properties": {
    "gn:admin1_code":"5.0",
    "gn:asciiname":"Map'osil",
    "gn:country_code":"KR",
    "gn:dem":161,
    "gn:feature_class":"P",
    "gn:feature_code":"PPL",
    "gn:name":"Map\u2019osil",
    "gn:population":0,
    "gn:timezone":"Asia/Seoul",
    "iso:country":"KR",
    "name:und_x_variant":[
        "\ub9c8\ud3ec\uc2e4",
        "Map\u2019osil"
    ],
    "wof:name":"Map'osil",
    "wof:placetype":"locality"
},
  "geometry": {"coordinates":[127.8436,36.235],"type":"Point"}
}