{
  "type": "Feature",
  "properties": {
    "gn:admin1_code":"14.0",
    "gn:asciiname":"P'yong-ch'on",
    "gn:country_code":"KR",
    "gn:dem":100,
    "gn:feature_class":"P",
    "gn:feature_code":"PPL",
    "gn:name":"P\u2019y\u014fng-ch\u2019on",
    "gn:population":0,
    "gn:timezone":"Asia/Seoul",
    "iso:country":"KR",
    "name:und_x_variant":[
        "\ud3c9\ucd0c",
        "P\u2019y\u014fng-ch\u2019on"
    ],
    "wof:name":"P'yong-ch'on",
    "wof:placetype":"locality"
},
  "geometry": {"coordinates":[128.31569999999999,36.0538],"type":"Point"}
}