{
  "type": "Feature",
  "properties": {
    "gn:admin1_code":"21.0",
    "gn:asciiname":"Duwang Il Gu",
    "gn:country_code":"KR",
    "gn:dem":17,
    "gn:feature_class":"P",
    "gn:feature_code":"PPL",
    "gn:name":"Duwang Il Gu",
    "gn:population":0,
    "gn:timezone":"Asia/Seoul",
    "iso:country":"KR",
    "name:eng_x_preferred":[
        "Duwang Il"
    ],
    "name:eng_x_variant":[
        "Duwang Il Gu"
    ],
    "name:kor_x_preferred":[
        "\ub450\uc6551\uad6c"
    ],
    "name:und_x_variant":[
        "Duwang 1 Gu"
    ],
    "wof:name":"Duwang Il",
    "wof:placetype":"locality"
},
  "geometry": {"coordinates":[129.30242999999999,35.50306],"type":"Point"}
}