{
  "type": "Feature",
  "properties": {
    "gn:admin1_code":"3.0",
    "gn:asciiname":"Pongun-dong",
    "gn:country_code":"KR",
    "gn:dem":51,
    "gn:feature_class":"P",
    "gn:feature_code":"PPL",
    "gn:name":"Pong\u016dn-dong",
    "gn:population":0,
    "gn:timezone":"Asia/Seoul",
    "iso:country":"KR",
    "name:und_x_variant":[
        "\ubd09\uc740\ub3d9",
        "Pong\u016dn-dong"
    ],
    "wof:name":"Pongun-dong",
    "wof:placetype":"locality"
},
  "geometry": {"coordinates":[127.00675,35.73837],"type":"Point"}
}