{
  "type": "Feature",
  "properties": {
    "gn:admin1_code":"6.0",
    "gn:asciiname":"Changyol",
    "gn:country_code":"KR",
    "gn:dem":359,
    "gn:feature_class":"P",
    "gn:feature_code":"PPL",
    "gn:name":"Changy\u014fl",
    "gn:population":0,
    "gn:timezone":"Asia/Seoul",
    "iso:country":"KR",
    "name:kor_x_preferred":[
        "\uc7a5\uc5f4"
    ],
    "name:kor_x_variant":[
        "Changy\u014fl"
    ],
    "wof:name":"Changyol",
    "wof:placetype":"locality"
},
  "geometry": {"coordinates":[128.6823,37.4585],"type":"Point"}
}