{
  "type": "Feature",
  "properties": {
    "gn:admin1_code":"6.0",
    "gn:asciiname":"Deombau",
    "gn:country_code":"KR",
    "gn:dem":261,
    "gn:feature_class":"P",
    "gn:feature_code":"PPL",
    "gn:name":"Deombau",
    "gn:population":0,
    "gn:timezone":"Asia/Seoul",
    "iso:country":"KR",
    "name:kor_x_preferred":[
        "\ub364\ubc14\uc6b0"
    ],
    "name:und_x_variant":[
        "\ub364\ubc14\uc704",
        "T\u014fmbawi",
        "Deombau"
    ],
    "wof:name":"Deombau",
    "wof:placetype":"locality"
},
  "geometry": {"coordinates":[127.76906,37.77757],"type":"Point"}
}