{
  "type": "Feature",
  "properties": {
    "gn:admin1_code":"14.0",
    "gn:asciiname":"Yangjong",
    "gn:country_code":"KR",
    "gn:dem":20,
    "gn:feature_class":"P",
    "gn:feature_code":"PPL",
    "gn:name":"Yangj\u014fng",
    "gn:population":0,
    "gn:timezone":"Asia/Seoul",
    "iso:country":"KR",
    "name:und_x_variant":[
        "\uc591\uc815",
        "Yangj\u014fng-dong",
        "Yangj\u014fng"
    ],
    "wof:name":"Yangjong",
    "wof:placetype":"locality"
},
  "geometry": {"coordinates":[129.4118,37.0151],"type":"Point"}
}