{
  "type": "Feature",
  "properties": {
    "gn:admin1_code":"13.0",
    "gn:asciiname":"Ilsin",
    "gn:country_code":"KR",
    "gn:dem":90,
    "gn:feature_class":"P",
    "gn:feature_code":"PPL",
    "gn:name":"Ilsin",
    "gn:population":0,
    "gn:timezone":"Asia/Seoul",
    "iso:country":"KR",
    "name:kor_x_preferred":[
        "\uc77c\uc2e0"
    ],
    "name:und_x_variant":[
        "\uc77c\uc2e0",
        "Ilsin"
    ],
    "wof:name":"Ilsin",
    "wof:placetype":"locality"
},
  "geometry": {"coordinates":[127.2996,37.628],"type":"Point"}
}