{
  "type": "Feature",
  "properties": {
    "gn:admin1_code":"14.0",
    "gn:asciiname":"Kokhae",
    "gn:country_code":"KR",
    "gn:dem":30,
    "gn:feature_class":"P",
    "gn:feature_code":"PPL",
    "gn:name":"Kokhae",
    "gn:population":0,
    "gn:timezone":"Asia/Seoul",
    "iso:country":"KR",
    "name:und_x_variant":[
        "Umhae-dong",
        "Kunbal",
        "Kongmae-dong",
        "\uace1\ud574",
        "Kokhae-dong",
        "Kokhae"
    ],
    "wof:name":"Kokhae",
    "wof:placetype":"locality"
},
  "geometry": {"coordinates":[129.40790000000001,37.027],"type":"Point"}
}