{
  "type": "Feature",
  "properties": {
    "gn:admin1_code":"16.0",
    "gn:asciiname":"Sangdong-ni",
    "gn:country_code":"KR",
    "gn:dem":42,
    "gn:feature_class":"P",
    "gn:feature_code":"PPL",
    "gn:name":"Sangdong-ni",
    "gn:population":0,
    "gn:timezone":"Asia/Seoul",
    "iso:country":"KR",
    "name:kor_x_preferred":[
        "\uc6d0\ub3d9"
    ],
    "name:kor_x_variant":[
        "\uc2e0\ud765\ub9ac",
        "W\u014fndong"
    ],
    "name:und_x_variant":[
        "J\u014dd\u014d-ri",
        "W\u014fndong-ni"
    ],
    "wof:name":"Sangdong-ni",
    "wof:placetype":"locality"
},
  "geometry": {"coordinates":[126.90639,34.17667],"type":"Point"}
}