{
  "type": "Feature",
  "properties": {
    "gn:admin1_code":"16.0",
    "gn:admin2_code":"Chindo-gun",
    "gn:asciiname":"Osang",
    "gn:country_code":"KR",
    "gn:dem":30,
    "gn:feature_class":"P",
    "gn:feature_code":"PPL",
    "gn:name":"Osang",
    "gn:population":0,
    "gn:timezone":"Asia/Seoul",
    "iso:country":"KR",
    "name:und_x_variant":[
        "Gosan-ri",
        "Osan-ni",
        "Osang-ni",
        "Osan",
        "Osal-li",
        "Osang"
    ],
    "wof:name":"Osang",
    "wof:placetype":"locality"
},
  "geometry": {"coordinates":[126.34111,34.49639000000001],"type":"Point"}
}