{
  "type": "Feature",
  "properties": {
    "gn:admin1_code":"14.0",
    "gn:asciiname":"Hudong",
    "gn:country_code":"KR",
    "gn:dem":12,
    "gn:feature_class":"P",
    "gn:feature_code":"PPL",
    "gn:name":"Hudong",
    "gn:population":0,
    "gn:timezone":"Asia/Seoul",
    "iso:country":"KR",
    "name:kor_x_preferred":[
        "\ud6c4\ub3d9"
    ],
    "wof:name":"Hudong",
    "wof:placetype":"locality"
},
  "geometry": {"coordinates":[129.53187,35.9877],"type":"Point"}
}