{
  "type": "Feature",
  "properties": {
    "gn:admin1_code":"15.0",
    "gn:asciiname":"Jintteumgol",
    "gn:country_code":"KR",
    "gn:dem":28,
    "gn:feature_class":"P",
    "gn:feature_code":"PPL",
    "gn:name":"Jintteumgol",
    "gn:population":0,
    "gn:timezone":"Asia/Seoul",
    "iso:country":"KR",
    "name:kor_x_preferred":[
        "\uc9c4\ub738\uace8"
    ],
    "wof:name":"Jintteumgol",
    "wof:placetype":"locality"
},
  "geometry": {"coordinates":[128.42242999999999,35.88459],"type":"Point"}
}