{
  "type": "Feature",
  "properties": {
    "gn:admin1_code":"13.0",
    "gn:asciiname":"Baegi",
    "gn:country_code":"KR",
    "gn:dem":98,
    "gn:feature_class":"P",
    "gn:feature_code":"PPL",
    "gn:name":"Baegi",
    "gn:population":0,
    "gn:timezone":"Asia/Seoul",
    "iso:country":"KR",
    "name:kor_x_preferred":[
        "\ubc30\uae30"
    ],
    "name:und_x_variant":[
        "Baegi"
    ],
    "wof:name":"Baegi",
    "wof:placetype":"locality"
},
  "geometry": {"coordinates":[127.2992,37.626],"type":"Point"}
}