{
  "type": "Feature",
  "properties": {
    "gn:admin1_code":"13.0",
    "gn:asciiname":"Manseokdong",
    "gn:country_code":"KR",
    "gn:dem":16,
    "gn:feature_class":"P",
    "gn:feature_code":"PPL",
    "gn:name":"Manseokdong",
    "gn:population":0,
    "gn:timezone":"Asia/Seoul",
    "iso:country":"KR",
    "name:kor_x_preferred":[
        "\ub9cc\uc11d\ub3d9"
    ],
    "name:kor_x_variant":[
        "Mans\u014fktong"
    ],
    "wof:name":"Manseokdong",
    "wof:placetype":"locality"
},
  "geometry": {"coordinates":[126.87551000000001,37.02309],"type":"Point"}
}