{
  "type": "Feature",
  "properties": {
    "gn:admin1_code":"5.0",
    "gn:asciiname":"Yongsudong",
    "gn:country_code":"KR",
    "gn:dem":202,
    "gn:feature_class":"P",
    "gn:feature_code":"PPL",
    "gn:name":"Yongsudong",
    "gn:population":0,
    "gn:timezone":"Asia/Seoul",
    "iso:country":"KR",
    "name:kor_x_preferred":[
        "\uc6a9\uc218\uae68"
    ],
    "name:kor_x_variant":[
        "\uc6a9\uc218\ub3d9"
    ],
    "name:und_x_variant":[
        "Yongsukkae",
        "Yongsudong"
    ],
    "wof:name":"Yongsudong",
    "wof:placetype":"locality"
},
  "geometry": {"coordinates":[128.27095,37.08063],"type":"Point"}
}