{
  "type": "Feature",
  "properties": {
    "gn:admin1_code":"20.0",
    "gn:asciiname":"Ssangam",
    "gn:country_code":"KR",
    "gn:dem":282,
    "gn:feature_class":"P",
    "gn:feature_code":"PPL",
    "gn:name":"Ssangam",
    "gn:population":0,
    "gn:timezone":"Asia/Seoul",
    "iso:country":"KR",
    "name:und_x_variant":[
        "\uc30d\uc554",
        "Ssangam"
    ],
    "wof:name":"Ssangam",
    "wof:placetype":"locality"
},
  "geometry": {"coordinates":[128.0386,35.50804],"type":"Point"}
}