{
  "type": "Feature",
  "properties": {
    "gn:admin1_code":"6.0",
    "gn:asciiname":"Ch'atkol",
    "gn:country_code":"KR",
    "gn:dem":24,
    "gn:feature_class":"P",
    "gn:feature_code":"PPL",
    "gn:name":"Ch\u2019atkol",
    "gn:population":0,
    "gn:timezone":"Asia/Seoul",
    "iso:country":"KR",
    "name:und_x_variant":[
        "Ch\u2019atkol",
        "\ucc3b\uace8"
    ],
    "wof:name":"Ch'atkol",
    "wof:placetype":"locality"
},
  "geometry": {"coordinates":[128.43382,38.45797],"type":"Point"}
}