{
  "type": "Feature",
  "properties": {
    "gn:admin1_code":"17.0",
    "gn:asciiname":"Yomsong-ni",
    "gn:country_code":"KR",
    "gn:dem":-9999,
    "gn:feature_class":"P",
    "gn:feature_code":"PPL",
    "gn:name":"Y\u014fms\u014fng-ni",
    "gn:population":0,
    "gn:timezone":"Asia/Seoul",
    "iso:country":"KR",
    "wof:name":"Yomsong-ni",
    "wof:placetype":"locality"
},
  "geometry": {"coordinates":[126.48333,36.45],"type":"Point"}
}