{
  "type": "Feature",
  "properties": {
    "gn:admin1_code":"14.0",
    "gn:asciiname":"Jjagol",
    "gn:country_code":"KR",
    "gn:dem":203,
    "gn:feature_class":"P",
    "gn:feature_code":"PPL",
    "gn:name":"Jjagol",
    "gn:population":0,
    "gn:timezone":"Asia/Seoul",
    "iso:country":"KR",
    "name:kor_x_preferred":[
        "\uc9dc\uace8"
    ],
    "wof:name":"Jjagol",
    "wof:placetype":"locality"
},
  "geometry": {"coordinates":[128.70583999999999,35.72519000000001],"type":"Point"}
}