{
  "type": "Feature",
  "properties": {
    "gn:admin1_code":"6.0",
    "gn:asciiname":"Mun'gok",
    "gn:country_code":"KR",
    "gn:dem":656,
    "gn:feature_class":"P",
    "gn:feature_code":"PPL",
    "gn:name":"Mun\u2019gok",
    "gn:population":0,
    "gn:timezone":"Asia/Seoul",
    "iso:country":"KR",
    "name:kor_x_preferred":[
        "\ubb38\uace1"
    ],
    "name:kor_x_variant":[
        "Mun\u2019gok"
    ],
    "wof:name":"Mun'gok",
    "wof:placetype":"locality"
},
  "geometry": {"coordinates":[128.99029999999999,37.1477],"type":"Point"}
}