{
  "type": "Feature",
  "properties": {
    "gn:admin1_code":"17.0",
    "gn:asciiname":"Wisyangsimni",
    "gn:country_code":"KR",
    "gn:dem":126,
    "gn:feature_class":"P",
    "gn:feature_code":"PPL",
    "gn:name":"Wisyangsimni",
    "gn:population":0,
    "gn:timezone":"Asia/Seoul",
    "iso:country":"KR",
    "name:kor_x_preferred":[
        "\uc717\uc591\uc2ec\ub9ac"
    ],
    "wof:name":"Wisyangsimni",
    "wof:placetype":"locality"
},
  "geometry": {"coordinates":[127.51549,36.26496],"type":"Point"}
}