{
  "type": "Feature",
  "properties": {
    "gn:admin1_code":"14.0",
    "gn:asciiname":"Utchaek-kol",
    "gn:country_code":"KR",
    "gn:dem":624,
    "gn:feature_class":"P",
    "gn:feature_code":"PPL",
    "gn:name":"Utchaek-kol",
    "gn:population":0,
    "gn:timezone":"Asia/Seoul",
    "iso:country":"KR",
    "name:und_x_variant":[
        "\uc6c3\uc7bf\uace8",
        "Utchaek-kol"
    ],
    "wof:name":"Utchaek-kol",
    "wof:placetype":"locality"
},
  "geometry": {"coordinates":[129.23500000000001,36.6278],"type":"Point"}
}