{
  "type": "Feature",
  "properties": {
    "gn:admin1_code":"16.0",
    "gn:asciiname":"Nae-ri",
    "gn:country_code":"KR",
    "gn:dem":19,
    "gn:feature_class":"P",
    "gn:feature_code":"PPL",
    "gn:name":"Nae-ri",
    "gn:population":0,
    "gn:timezone":"Asia/Seoul",
    "iso:country":"KR",
    "name:kor_x_preferred":[
        "\ub0b4\ub9ac"
    ],
    "name:und_x_variant":[
        "Nai-ri",
        "Nae-ri"
    ],
    "wof:name":"Nae-ri",
    "wof:placetype":"locality"
},
  "geometry": {"coordinates":[126.50806,34.19611],"type":"Point"}
}