{
  "type": "Feature",
  "properties": {
    "gn:admin1_code":"14.0",
    "gn:asciiname":"Mogol",
    "gn:country_code":"KR",
    "gn:dem":264,
    "gn:feature_class":"P",
    "gn:feature_code":"PPL",
    "gn:name":"Mogol",
    "gn:population":0,
    "gn:timezone":"Asia/Seoul",
    "iso:country":"KR",
    "name:ceb_x_preferred":[
        "Mogol"
    ],
    "name:kor_x_preferred":[
        "\ubaa8\uace8"
    ],
    "wof:name":"Mogol",
    "wof:placetype":"locality"
},
  "geometry": {"coordinates":[128.7842,36.59729],"type":"Point"}
}