{
  "type": "Feature",
  "properties": {
    "gn:admin1_code":"17.0",
    "gn:asciiname":"Ojip'yong",
    "gn:country_code":"KR",
    "gn:dem":19,
    "gn:feature_class":"P",
    "gn:feature_code":"PPL",
    "gn:name":"Ojip\u2019y\u014fng",
    "gn:population":0,
    "gn:timezone":"Asia/Seoul",
    "iso:country":"KR",
    "name:und_x_variant":[
        "\uc624\uc9c0\ud3c9",
        "Ojip\u2019y\u014fng"
    ],
    "wof:name":"Ojip'yong",
    "wof:placetype":"locality"
},
  "geometry": {"coordinates":[126.443,36.8327],"type":"Point"}
}