{
  "type": "Feature",
  "properties": {
    "gn:admin1_code":"16.0",
    "gn:asciiname":"Wollam-ni",
    "gn:country_code":"KR",
    "gn:dem":133,
    "gn:feature_class":"P",
    "gn:feature_code":"PPL",
    "gn:name":"W\u014fllam-ni",
    "gn:population":0,
    "gn:timezone":"Asia/Seoul",
    "iso:country":"KR",
    "name:kor_x_preferred":[
        "\uc6d4\ub0a8\ub9ac"
    ],
    "name:kor_x_variant":[
        "W\u014fllam-ni"
    ],
    "wof:name":"Wollam-ni",
    "wof:placetype":"locality"
},
  "geometry": {"coordinates":[126.71333,34.74056],"type":"Point"}
}