{
  "type": "Feature",
  "properties": {
    "gn:admin1_code":"5.0",
    "gn:asciiname":"Korim",
    "gn:country_code":"KR",
    "gn:dem":201,
    "gn:feature_class":"P",
    "gn:feature_code":"PPL",
    "gn:name":"Korim",
    "gn:population":0,
    "gn:timezone":"Asia/Seoul",
    "iso:country":"KR",
    "name:und_x_variant":[
        "\uace0\ub9bc",
        "Korim"
    ],
    "wof:name":"Korim",
    "wof:placetype":"locality"
},
  "geometry": {"coordinates":[127.77030000000001,36.1284],"type":"Point"}
}