{
  "type": "Feature",
  "properties": {
    "gn:admin1_code":"3.0",
    "gn:asciiname":"Tongsan",
    "gn:country_code":"KR",
    "gn:dem":354,
    "gn:feature_class":"P",
    "gn:feature_code":"PPL",
    "gn:name":"Tongsan",
    "gn:population":0,
    "gn:timezone":"Asia/Seoul",
    "iso:country":"KR",
    "name:und_x_variant":[
        "\ub3d9\uc0b0",
        "Tongsan"
    ],
    "wof:name":"Tongsan",
    "wof:placetype":"locality"
},
  "geometry": {"coordinates":[127.38132,35.68640999999999],"type":"Point"}
}