{
  "type": "Feature",
  "properties": {
    "gn:admin1_code":"6.0",
    "gn:asciiname":"Hungyang",
    "gn:country_code":"KR",
    "gn:dem":206,
    "gn:feature_class":"P",
    "gn:feature_code":"PPL",
    "gn:name":"H\u016dngyang",
    "gn:population":0,
    "gn:timezone":"Asia/Seoul",
    "iso:country":"KR",
    "name:kor_x_preferred":[
        "\ud765\uc591"
    ],
    "name:kor_x_variant":[
        "H\u016dngyang"
    ],
    "wof:name":"Hungyang",
    "wof:placetype":"locality"
},
  "geometry": {"coordinates":[127.9978,37.3748],"type":"Point"}
}