{
  "type": "Feature",
  "properties": {
    "gn:admin1_code":"12.0",
    "gn:asciiname":"Tolp'akchae",
    "gn:country_code":"KR",
    "gn:dem":12,
    "gn:feature_class":"P",
    "gn:feature_code":"PPL",
    "gn:name":"Tolp\u2019akchae",
    "gn:population":0,
    "gn:timezone":"Asia/Seoul",
    "iso:country":"KR",
    "name:und_x_variant":[
        "\ub3cc\ud30d\uc7ac",
        "Tolp\u2019akchae"
    ],
    "wof:name":"Tolp'akchae",
    "wof:placetype":"locality"
},
  "geometry": {"coordinates":[126.56417,37.50083],"type":"Point"}
}