{
  "type": "Feature",
  "properties": {
    "gn:admin1_code":"17.0",
    "gn:asciiname":"Garaeul",
    "gn:country_code":"KR",
    "gn:dem":213,
    "gn:feature_class":"P",
    "gn:feature_code":"PPL",
    "gn:name":"Garaeul",
    "gn:population":0,
    "gn:timezone":"Asia/Seoul",
    "iso:country":"KR",
    "name:und_x_variant":[
        "\uac00\ub798\uc6b8",
        "Karaeul",
        "Garaeul"
    ],
    "wof:name":"Garaeul",
    "wof:placetype":"locality"
},
  "geometry": {"coordinates":[127.47181999999999,36.17602],"type":"Point"}
}