{
  "type": "Feature",
  "properties": {
    "gn:admin1_code":"13.0",
    "gn:asciiname":"Otgomgi",
    "gn:country_code":"KR",
    "gn:dem":141,
    "gn:feature_class":"P",
    "gn:feature_code":"PPL",
    "gn:name":"Otgomgi",
    "gn:population":0,
    "gn:timezone":"Asia/Seoul",
    "iso:country":"KR",
    "name:kor_x_preferred":[
        "\uc637\uacf0\uae30"
    ],
    "wof:name":"Otgomgi",
    "wof:placetype":"locality"
},
  "geometry": {"coordinates":[127.12258,38.21863],"type":"Point"}
}