{
  "type": "Feature",
  "properties": {
    "gn:admin1_code":"6.0",
    "gn:asciiname":"Jeongjagol",
    "gn:country_code":"KR",
    "gn:dem":275,
    "gn:feature_class":"P",
    "gn:feature_code":"PPL",
    "gn:name":"Jeongjagol",
    "gn:population":0,
    "gn:timezone":"Asia/Seoul",
    "iso:country":"KR",
    "name:kor_x_preferred":[
        "\uc815\uc790\uace8"
    ],
    "name:kor_x_variant":[
        "Ch\u014fngja-gol"
    ],
    "name:und_x_variant":[
        "Ch\u014fngji-gol",
        "Jeongjagol"
    ],
    "wof:name":"Jeongjagol",
    "wof:placetype":"locality"
},
  "geometry": {"coordinates":[128.02375000000001,37.98218],"type":"Point"}
}