{
  "type": "Feature",
  "properties": {
    "gn:admin1_code":"16.0",
    "gn:asciiname":"Pongnim",
    "gn:country_code":"KR",
    "gn:dem":42,
    "gn:feature_class":"P",
    "gn:feature_code":"PPL",
    "gn:name":"Pongnim",
    "gn:population":0,
    "gn:timezone":"Asia/Seoul",
    "iso:country":"KR",
    "name:kor_x_preferred":[
        "\ubd09\ub9bc"
    ],
    "name:und_x_variant":[
        "H\u014drin-ri",
        "Pongnim-ni",
        "Pongnim"
    ],
    "wof:name":"Pongnim",
    "wof:placetype":"locality"
},
  "geometry": {"coordinates":[126.57167,34.47361],"type":"Point"}
}