{
  "type": "Feature",
  "properties": {
    "gn:admin1_code":"1.0",
    "gn:asciiname":"Sanji",
    "gn:cc2":"KR",
    "gn:country_code":"KR",
    "gn:dem":25,
    "gn:feature_class":"P",
    "gn:feature_code":"PPL",
    "gn:name":"Sanji",
    "gn:population":0,
    "gn:timezone":"Asia/Seoul",
    "iso:country":"KR",
    "name:ceb_x_preferred":[
        "Sanji"
    ],
    "name:swe_x_preferred":[
        "Sanji"
    ],
    "name:und_x_variant":[
        "Sanchi",
        "Sanji"
    ],
    "wof:name":"Sanji",
    "wof:placetype":"locality"
},
  "geometry": {"coordinates":[126.53333000000001,33.51667],"type":"Point"}
}