{
  "type": "Feature",
  "properties": {
    "gn:admin1_code":"13.0",
    "gn:asciiname":"Nonggae",
    "gn:country_code":"KR",
    "gn:dem":16,
    "gn:feature_class":"P",
    "gn:feature_code":"PPL",
    "gn:name":"Nonggae",
    "gn:population":0,
    "gn:timezone":"Asia/Seoul",
    "iso:country":"KR",
    "name:kor_x_preferred":[
        "\ub18d\uac1c"
    ],
    "wof:name":"Nonggae",
    "wof:placetype":"locality"
},
  "geometry": {"coordinates":[126.87027999999999,37.02],"type":"Point"}
}