{
  "type": "Feature",
  "properties": {
    "gn:admin1_code":"6.0",
    "gn:asciiname":"Kurul-li",
    "gn:country_code":"KR",
    "gn:dem":179,
    "gn:feature_class":"P",
    "gn:feature_code":"PPLL",
    "gn:name":"Kurul-li",
    "gn:population":0,
    "gn:timezone":"Asia/Seoul",
    "iso:country":"KR",
    "name:kor_x_preferred":[
        "\uad74\uc6b4\ub9ac"
    ],
    "wof:name":"Kurul-li",
    "wof:placetype":"locality"
},
  "geometry": {"coordinates":[127.95976,37.73468],"type":"Point"}
}