{
  "type": "Feature",
  "properties": {
    "gn:admin1_code":"3.0",
    "gn:asciiname":"Chiram",
    "gn:country_code":"KR",
    "gn:dem":59,
    "gn:feature_class":"P",
    "gn:feature_code":"PPL",
    "gn:name":"Chiram",
    "gn:population":0,
    "gn:timezone":"Asia/Seoul",
    "iso:country":"KR",
    "name:kor_x_preferred":[
        "\uce60\uc554"
    ],
    "wof:name":"Chiram",
    "wof:placetype":"locality"
},
  "geometry": {"coordinates":[126.66316,35.37834],"type":"Point"}
}