{
  "type": "Feature",
  "properties": {
    "gn:admin1_code":"19.0",
    "gn:asciiname":"Baekgol",
    "gn:country_code":"KR",
    "gn:dem":98,
    "gn:feature_class":"P",
    "gn:feature_code":"PPL",
    "gn:name":"Baekgol",
    "gn:population":0,
    "gn:timezone":"Asia/Seoul",
    "iso:country":"KR",
    "name:und_x_variant":[
        "\ubc31\uace8",
        "Paek-kol",
        "Baekgol"
    ],
    "wof:name":"Baekgol",
    "wof:placetype":"locality"
},
  "geometry": {"coordinates":[127.39483,36.299],"type":"Point"}
}