{
  "type": "Feature",
  "properties": {
    "gn:admin1_code":"6.0",
    "gn:asciiname":"Hwangcheoldong",
    "gn:country_code":"KR",
    "gn:dem":660,
    "gn:feature_class":"P",
    "gn:feature_code":"PPL",
    "gn:name":"Hwangcheoldong",
    "gn:population":0,
    "gn:timezone":"Asia/Seoul",
    "iso:country":"KR",
    "name:kor_x_preferred":[
        "\ud669\ucca0\ub3d9"
    ],
    "name:kor_x_variant":[
        "Hwangch\u2019\u014fl-tong"
    ],
    "name:und_x_variant":[
        "Hwangch\u2019\u014fl-gol",
        "Hwangch\u2019\u014fl-dong",
        "Hwangcheoldong"
    ],
    "wof:name":"Hwangcheoldong",
    "wof:placetype":"locality"
},
  "geometry": {"coordinates":[128.14151000000001,37.85446],"type":"Point"}
}