{
  "type": "Feature",
  "properties": {
    "gn:admin1_code":"20.0",
    "gn:asciiname":"Sondu",
    "gn:country_code":"KR",
    "gn:dem":8,
    "gn:feature_class":"P",
    "gn:feature_code":"PPL",
    "gn:name":"S\u014fndu",
    "gn:population":0,
    "gn:timezone":"Asia/Seoul",
    "iso:country":"KR",
    "name:und_x_variant":[
        "S\u014fn\u2019gi",
        "\uc120\ub450",
        "S\u014fndu"
    ],
    "wof:name":"Sondu",
    "wof:placetype":"locality"
},
  "geometry": {"coordinates":[128.46788999999998,35.10103],"type":"Point"}
}