{
  "type": "Feature",
  "properties": {
    "gn:admin1_code":"13.0",
    "gn:asciiname":"Toe-gol",
    "gn:country_code":"KR",
    "gn:dem":97,
    "gn:feature_class":"P",
    "gn:feature_code":"PPL",
    "gn:name":"Toe-gol",
    "gn:population":0,
    "gn:timezone":"Asia/Seoul",
    "iso:country":"KR",
    "name:und_x_variant":[
        "\ud1f4\uace8",
        "Toe-gol",
        "T\u2019oe-gol"
    ],
    "wof:name":"Toe-gol",
    "wof:placetype":"locality"
},
  "geometry": {"coordinates":[127.76582999999999,37.30333],"type":"Point"}
}