{
  "type": "Feature",
  "properties": {
    "gn:admin1_code":"14.0",
    "gn:asciiname":"Jageunyeok",
    "gn:country_code":"KR",
    "gn:dem":65,
    "gn:feature_class":"P",
    "gn:feature_code":"PPL",
    "gn:name":"Jageunyeok",
    "gn:population":0,
    "gn:timezone":"Asia/Seoul",
    "iso:country":"KR",
    "name:kor_x_preferred":[
        "\uc791\uc740\uc5ed"
    ],
    "wof:name":"Jageunyeok",
    "wof:placetype":"locality"
},
  "geometry": {"coordinates":[128.30476000000002,36.48548],"type":"Point"}
}