{
  "type": "Feature",
  "properties": {
    "gn:admin1_code":"3.0",
    "gn:asciiname":"Sip'yong",
    "gn:country_code":"KR",
    "gn:dem":226,
    "gn:feature_class":"P",
    "gn:feature_code":"PPL",
    "gn:name":"Sip\u2019y\u014fng",
    "gn:population":0,
    "gn:timezone":"Asia/Seoul",
    "iso:country":"KR",
    "name:und_x_variant":[
        "\uc2dc\ud3c9",
        "Sip\u2019y\u014fng"
    ],
    "wof:name":"Sip'yong",
    "wof:placetype":"locality"
},
  "geometry": {"coordinates":[127.31309,35.89062],"type":"Point"}
}