{
  "type": "Feature",
  "properties": {
    "gn:admin1_code":"13.0",
    "gn:asciiname":"Jeongnim",
    "gn:country_code":"KR",
    "gn:dem":48,
    "gn:feature_class":"P",
    "gn:feature_code":"PPL",
    "gn:name":"Jeongnim",
    "gn:population":0,
    "gn:timezone":"Asia/Seoul",
    "iso:country":"KR",
    "name:und_x_variant":[
        "\uc815\ub9bc",
        "Ch\u014fngnim",
        "Jeongnim"
    ],
    "wof:name":"Jeongnim",
    "wof:placetype":"locality"
},
  "geometry": {"coordinates":[127.16070000000001,37.5064],"type":"Point"}
}