{
  "type": "Feature",
  "properties": {
    "gn:admin1_code":"16.0",
    "gn:asciiname":"Jangwol",
    "gn:country_code":"KR",
    "gn:dem":78,
    "gn:feature_class":"P",
    "gn:feature_code":"PPL",
    "gn:name":"Jangwol",
    "gn:population":0,
    "gn:timezone":"Asia/Seoul",
    "iso:country":"KR",
    "name:kor_x_preferred":[
        "\uc7a5\uc6d4"
    ],
    "wof:name":"Jangwol",
    "wof:placetype":"locality"
},
  "geometry": {"coordinates":[126.98436,35.33687000000001],"type":"Point"}
}