{
  "type": "Feature",
  "properties": {
    "gn:admin1_code":"13.0",
    "gn:admin2_code":"P'aju-si",
    "gn:asciiname":"Jeokseongmal",
    "gn:country_code":"KR",
    "gn:dem":55,
    "gn:feature_class":"P",
    "gn:feature_code":"PPL",
    "gn:name":"Jeokseongmal",
    "gn:population":0,
    "gn:timezone":"Asia/Seoul",
    "iso:country":"KR",
    "name:kor_x_preferred":[
        "\uc801\uc131\ub9d0"
    ],
    "name:und_x_variant":[
        "Ch\u014fks\u014fng-mal"
    ],
    "wof:name":"Jeokseongmal",
    "wof:placetype":"locality"
},
  "geometry": {"coordinates":[126.86108,37.94517000000001],"type":"Point"}
}