{
  "type": "Feature",
  "properties": {
    "gn:admin1_code":"13.0",
    "gn:asciiname":"Simgyo",
    "gn:country_code":"KR",
    "gn:dem":55,
    "gn:feature_class":"P",
    "gn:feature_code":"PPL",
    "gn:name":"Simgyo",
    "gn:population":0,
    "gn:timezone":"Asia/Seoul",
    "iso:country":"KR",
    "name:und_x_variant":[
        "\uc2ec\uad50",
        "Simgyo"
    ],
    "wof:name":"Simgyo",
    "wof:placetype":"locality"
},
  "geometry": {"coordinates":[127.17471999999999,37.02889],"type":"Point"}
}