{
  "type": "Feature",
  "properties": {
    "gn:admin1_code":"3.0",
    "gn:asciiname":"Hwawol-li",
    "gn:country_code":"KR",
    "gn:dem":98,
    "gn:feature_class":"P",
    "gn:feature_code":"PPLL",
    "gn:name":"Hwaw\u014fl-li",
    "gn:population":0,
    "gn:timezone":"Asia/Seoul",
    "iso:country":"KR",
    "name:und_x_variant":[
        "\ud654\uc6d4\ub9ac",
        "Hwaw\u014fl-li"
    ],
    "wof:name":"Hwawol-li",
    "wof:placetype":"locality"
},
  "geometry": {"coordinates":[127.20892000000001,36.02177000000001],"type":"Point"}
}