{
  "type": "Feature",
  "properties": {
    "gn:admin1_code":"0.0",
    "gn:asciiname":"Pongnae",
    "gn:cc2":"KR",
    "gn:country_code":"KR",
    "gn:dem":197,
    "gn:feature_class":"P",
    "gn:feature_code":"PPL",
    "gn:name":"Pongnae",
    "gn:population":0,
    "gn:timezone":"Asia/Seoul",
    "iso:country":"KR",
    "name:und_x_variant":[
        "Pongnaejang",
        "Pongnae"
    ],
    "wof:name":"Pongnae",
    "wof:placetype":"locality"
},
  "geometry": {"coordinates":[127.11667,34.88333],"type":"Point"}
}