{
  "type": "Feature",
  "properties": {
    "gn:admin1_code":"15.0",
    "gn:asciiname":"Baenae",
    "gn:country_code":"KR",
    "gn:dem":72,
    "gn:feature_class":"P",
    "gn:feature_code":"PPL",
    "gn:name":"Baenae",
    "gn:population":0,
    "gn:timezone":"Asia/Seoul",
    "iso:country":"KR",
    "name:kor_x_preferred":[
        "\ubc30\ub0b4"
    ],
    "name:und_x_variant":[
        "Paenae"
    ],
    "wof:name":"Baenae",
    "wof:placetype":"locality"
},
  "geometry": {"coordinates":[128.65541000000002,35.83880999999999],"type":"Point"}
}