{
  "type": "Feature",
  "properties": {
    "gn:admin1_code":"13.0",
    "gn:asciiname":"Saeteo",
    "gn:country_code":"KR",
    "gn:dem":93,
    "gn:feature_class":"P",
    "gn:feature_code":"PPL",
    "gn:name":"Saeteo",
    "gn:population":0,
    "gn:timezone":"Asia/Seoul",
    "iso:country":"KR",
    "name:und_x_variant":[
        "\uc0c8\ud130",
        "Saeteo",
        "Saet\u2019\u014f"
    ],
    "wof:name":"Saeteo",
    "wof:placetype":"locality"
},
  "geometry": {"coordinates":[127.19638999999999,37.40028],"type":"Point"}
}