{
  "type": "Feature",
  "properties": {
    "gn:admin1_code":"11.0",
    "gn:asciiname":"Karagi-dong",
    "gn:country_code":"KR",
    "gn:dem":45,
    "gn:feature_class":"P",
    "gn:feature_code":"PPL",
    "gn:name":"Karagi-dong",
    "gn:population":0,
    "gn:timezone":"Asia/Seoul",
    "iso:country":"KR",
    "name:und_x_variant":[
        "\uac00\ub77d2\ub3d9",
        "Garagi-dong",
        "Karagi-dong"
    ],
    "wof:name":"Karagi-dong",
    "wof:placetype":"locality"
},
  "geometry": {"coordinates":[127.13139,37.49639000000001],"type":"Point"}
}