{
  "type": "Feature",
  "properties": {
    "gn:admin1_code":"14.0",
    "gn:asciiname":"Kwansin",
    "gn:country_code":"KR",
    "gn:dem":125,
    "gn:feature_class":"P",
    "gn:feature_code":"PPL",
    "gn:name":"Kwansin",
    "gn:population":0,
    "gn:timezone":"Asia/Seoul",
    "iso:country":"KR",
    "name:und_x_variant":[
        "Kallyang",
        "Karyang",
        "\uac08\ub839",
        "Kally\u014fng"
    ],
    "wof:name":"Kwansin",
    "wof:placetype":"locality"
},
  "geometry": {"coordinates":[128.0712,36.489],"type":"Point"}
}