{
  "type": "Feature",
  "properties": {
    "gn:admin1_code":"13.0",
    "gn:asciiname":"Jeonmal",
    "gn:country_code":"KR",
    "gn:dem":91,
    "gn:feature_class":"P",
    "gn:feature_code":"PPL",
    "gn:name":"Jeonmal",
    "gn:population":0,
    "gn:timezone":"Asia/Seoul",
    "iso:country":"KR",
    "name:kor_x_preferred":[
        "\uc804\ub9d0"
    ],
    "wof:name":"Jeonmal",
    "wof:placetype":"locality"
},
  "geometry": {"coordinates":[127.48699999999999,37.84295],"type":"Point"}
}