{
  "type": "Feature",
  "properties": {
    "gn:admin1_code":"5.0",
    "gn:asciiname":"Galgol",
    "gn:country_code":"KR",
    "gn:dem":79,
    "gn:feature_class":"P",
    "gn:feature_code":"PPL",
    "gn:name":"Galgol",
    "gn:population":0,
    "gn:timezone":"Asia/Seoul",
    "iso:country":"KR",
    "name:kor_x_preferred":[
        "\uac08\uace8"
    ],
    "name:und_x_variant":[
        "Kal-gol",
        "Galgol"
    ],
    "wof:name":"Galgol",
    "wof:placetype":"locality"
},
  "geometry": {"coordinates":[127.84481,37.02081],"type":"Point"}
}