{
  "type": "Feature",
  "properties": {
    "gn:admin1_code":"17.0",
    "gn:asciiname":"Chisa",
    "gn:country_code":"KR",
    "gn:dem":17,
    "gn:feature_class":"P",
    "gn:feature_code":"PPL",
    "gn:name":"Chisa",
    "gn:population":0,
    "gn:timezone":"Asia/Seoul",
    "iso:country":"KR",
    "name:und_x_variant":[
        "\uc9c0\uc0ac",
        "Chisa"
    ],
    "wof:name":"Chisa",
    "wof:placetype":"locality"
},
  "geometry": {"coordinates":[126.4516,36.9566],"type":"Point"}
}