{
  "type": "Feature",
  "properties": {
    "gn:admin1_code":"17.0",
    "gn:asciiname":"Chisa",
    "gn:country_code":"KR",
    "gn:dem":17,
    "gn:feature_class":"P",
    "gn:feature_code":"PPL",
    "gn:name":"Chisa",
    "gn:population":0,
    "gn:timezone":"Asia/Seoul",
    "iso:country":"KR",
    "name:cat_x_preferred":[
        "Chisa"
    ],
    "name:ceb_x_preferred":[
        "Chisa"
    ],
    "name:cos_x_preferred":[
        "Chis\u00e0"
    ],
    "name:deu_x_preferred":[
        "Chisa"
    ],
    "name:eus_x_preferred":[
        "Chisa"
    ],
    "name:fra_x_preferred":[
        "Chisa"
    ],
    "name:hun_x_preferred":[
        "Chisa"
    ],
    "name:ita_x_preferred":[
        "Chisa"
    ],
    "name:kaz_x_preferred":[
        "\u041a\u0438\u0437\u0430"
    ],
    "name:lat_x_preferred":[
        "Chisa"
    ],
    "name:lmo_x_preferred":[
        "Chisa"
    ],
    "name:mlg_x_preferred":[
        "Chisa"
    ],
    "name:msa_x_preferred":[
        "Chisa"
    ],
    "name:nld_x_preferred":[
        "Chisa"
    ],
    "name:oci_x_preferred":[
        "Chisa"
    ],
    "name:pol_x_preferred":[
        "Chisa"
    ],
    "name:por_x_preferred":[
        "Chisa"
    ],
    "name:rus_x_preferred":[
        "\u041a\u0438\u0437\u0430"
    ],
    "name:slk_x_preferred":[
        "Chisa"
    ],
    "name:slv_x_preferred":[
        "Chisa"
    ],
    "name:spa_x_preferred":[
        "Chisa"
    ],
    "name:srp_x_preferred":[
        "\u041a\u0438\u0437\u0430"
    ],
    "name:swe_x_preferred":[
        "Chisa"
    ],
    "name:ukr_x_preferred":[
        "\u041a\u0456\u0437\u0430"
    ],
    "name:und_x_variant":[
        "\uc9c0\uc0ac"
    ],
    "name:vie_x_preferred":[
        "Chisa"
    ],
    "name:vol_x_preferred":[
        "Chisa"
    ],
    "name:war_x_preferred":[
        "Chisa"
    ],
    "wof:name":"Chisa",
    "wof:placetype":"locality"
},
  "geometry": {"coordinates":[126.4516,36.9566],"type":"Point"}
}