{
  "type": "Feature",
  "properties": {
    "gn:admin1_code":"5.0",
    "gn:asciiname":"Gamagol",
    "gn:country_code":"KR",
    "gn:dem":75,
    "gn:feature_class":"P",
    "gn:feature_code":"PPL",
    "gn:name":"Gamagol",
    "gn:population":0,
    "gn:timezone":"Asia/Seoul",
    "iso:country":"KR",
    "name:kor_x_preferred":[
        "\uac00\ub9c8\uace8"
    ],
    "wof:name":"Gamagol",
    "wof:placetype":"locality"
},
  "geometry": {"coordinates":[127.38525,36.61913],"type":"Point"}
}