{
  "type": "Feature",
  "properties": {
    "gn:admin1_code":"6.0",
    "gn:asciiname":"Seokdonggeori",
    "gn:country_code":"KR",
    "gn:dem":154,
    "gn:feature_class":"P",
    "gn:feature_code":"PPL",
    "gn:name":"Seokdonggeori",
    "gn:population":0,
    "gn:timezone":"Asia/Seoul",
    "iso:country":"KR",
    "name:und_x_variant":[
        "\uc11d\ub3d9\uac70\ub9ac",
        "S\u014fktongg\u014fri",
        "Seokdonggeori"
    ],
    "wof:name":"Seokdonggeori",
    "wof:placetype":"locality"
},
  "geometry": {"coordinates":[127.63976,38.03793],"type":"Point"}
}