{
  "type": "Feature",
  "properties": {
    "gn:admin1_code":"13.0",
    "gn:asciiname":"Paemaru",
    "gn:country_code":"KR",
    "gn:dem":49,
    "gn:feature_class":"P",
    "gn:feature_code":"PPL",
    "gn:name":"Paemaru",
    "gn:population":0,
    "gn:timezone":"Asia/Seoul",
    "iso:country":"KR",
    "name:und_x_variant":[
        "\ubc30\ub9c8\ub8e8",
        "Baemaru",
        "Paemaru"
    ],
    "wof:name":"Paemaru",
    "wof:placetype":"locality"
},
  "geometry": {"coordinates":[127.10222,37.17556],"type":"Point"}
}