{
  "type": "Feature",
  "properties": {
    "gn:admin1_code":"5.0",
    "gn:asciiname":"Hangoraengi",
    "gn:country_code":"KR",
    "gn:dem":253,
    "gn:feature_class":"P",
    "gn:feature_code":"PPL",
    "gn:name":"Hangoraengi",
    "gn:population":0,
    "gn:timezone":"Asia/Seoul",
    "iso:country":"KR",
    "name:kor_x_preferred":[
        "\ud55c\uace0\ub7ad\uc774"
    ],
    "name:kor_x_variant":[
        "Han\u2019goraengi"
    ],
    "wof:name":"Hangoraengi",
    "wof:placetype":"locality"
},
  "geometry": {"coordinates":[128.49795,37.07145],"type":"Point"}
}