{
  "type": "Feature",
  "properties": {
    "gn:admin1_code":"20.0",
    "gn:asciiname":"Yongsong-ni",
    "gn:country_code":"KR",
    "gn:dem":36,
    "gn:feature_class":"P",
    "gn:feature_code":"PPL",
    "gn:name":"Yongs\u014fng-ni",
    "gn:population":0,
    "gn:timezone":"Asia/Seoul",
    "iso:country":"KR",
    "name:und_x_variant":[
        "\uc6a9\uc11d\ub9ac",
        "Yongs\u014fng-ni"
    ],
    "wof:name":"Yongsong-ni",
    "wof:placetype":"locality"
},
  "geometry": {"coordinates":[128.48356999999999,35.5109],"type":"Point"}
}