{
  "type": "Feature",
  "properties": {
    "gn:admin1_code":"16.0",
    "gn:asciiname":"Geumgu",
    "gn:country_code":"KR",
    "gn:dem":19,
    "gn:feature_class":"P",
    "gn:feature_code":"PPL",
    "gn:name":"Geumgu",
    "gn:population":0,
    "gn:timezone":"Asia/Seoul",
    "iso:country":"KR",
    "name:kor_x_preferred":[
        "\uae08\uad6c"
    ],
    "wof:name":"Geumgu",
    "wof:placetype":"locality"
},
  "geometry": {"coordinates":[126.75395,35.03208],"type":"Point"}
}