{
  "type": "Feature",
  "properties": {
    "gn:admin1_code":"14.0",
    "gn:asciiname":"Taengdaengi-gol",
    "gn:country_code":"KR",
    "gn:dem":209,
    "gn:feature_class":"P",
    "gn:feature_code":"PPL",
    "gn:name":"Taengdaengi-gol",
    "gn:population":0,
    "gn:timezone":"Asia/Seoul",
    "iso:country":"KR",
    "name:und_x_variant":[
        "\ub315\ub315\uc774\uace8",
        "Taengdaengi-gol"
    ],
    "wof:name":"Taengdaengi-gol",
    "wof:placetype":"locality"
},
  "geometry": {"coordinates":[129.38040000000001,36.6326],"type":"Point"}
}