{
  "type": "Feature",
  "properties": {
    "gn:admin1_code":"17.0",
    "gn:asciiname":"Nundo-ri",
    "gn:country_code":"KR",
    "gn:dem":22,
    "gn:feature_class":"P",
    "gn:feature_code":"PPL",
    "gn:name":"Nund\u014f-ri",
    "gn:population":0,
    "gn:timezone":"Asia/Seoul",
    "iso:country":"KR",
    "name:und_x_variant":[
        "\ub208\ub354\ub9ac",
        "Nund\u014f-ri"
    ],
    "wof:name":"Nundo-ri",
    "wof:placetype":"locality"
},
  "geometry": {"coordinates":[126.3064,36.6612],"type":"Point"}
}