{
  "type": "Feature",
  "properties": {
    "gn:admin1_code":"13.0",
    "gn:asciiname":"Jinmal",
    "gn:country_code":"KR",
    "gn:dem":16,
    "gn:feature_class":"P",
    "gn:feature_code":"PPL",
    "gn:name":"Jinmal",
    "gn:population":0,
    "gn:timezone":"Asia/Seoul",
    "iso:country":"KR",
    "name:kor_x_preferred":[
        "\uc9c4\ub9d0"
    ],
    "wof:name":"Jinmal",
    "wof:placetype":"locality"
},
  "geometry": {"coordinates":[126.82411999999999,37.39177],"type":"Point"}
}