{
  "type": "Feature",
  "properties": {
    "gn:admin1_code":"17.0",
    "gn:asciiname":"Hanmo-ri",
    "gn:country_code":"KR",
    "gn:dem":21,
    "gn:feature_class":"P",
    "gn:feature_code":"PPL",
    "gn:name":"Hanm\u014f-ri",
    "gn:population":0,
    "gn:timezone":"Asia/Seoul",
    "iso:country":"KR",
    "name:und_x_variant":[
        "\ud55c\uba38\ub9ac",
        "Hanm\u014f-ri"
    ],
    "wof:name":"Hanmo-ri",
    "wof:placetype":"locality"
},
  "geometry": {"coordinates":[126.3849,36.7071],"type":"Point"}
}