{
  "type": "Feature",
  "properties": {
    "gn:admin1_code":"5.0",
    "gn:asciiname":"Jiwang",
    "gn:country_code":"KR",
    "gn:dem":228,
    "gn:feature_class":"P",
    "gn:feature_code":"PPL",
    "gn:name":"Jiwang",
    "gn:population":0,
    "gn:timezone":"Asia/Seoul",
    "iso:country":"KR",
    "name:kor_x_preferred":[
        "\uc9c0\uc655"
    ],
    "wof:name":"Jiwang",
    "wof:placetype":"locality"
},
  "geometry": {"coordinates":[127.73927999999999,36.62087],"type":"Point"}
}