{
  "type": "Feature",
  "properties": {
    "gn:admin1_code":"5.0",
    "gn:asciiname":"Seokhwa",
    "gn:country_code":"KR",
    "gn:dem":40,
    "gn:feature_class":"P",
    "gn:feature_code":"PPL",
    "gn:name":"Seokhwa",
    "gn:population":0,
    "gn:timezone":"Asia/Seoul",
    "iso:country":"KR",
    "name:kor_x_preferred":[
        "\uc11d\ud654"
    ],
    "wof:name":"Seokhwa",
    "wof:placetype":"locality"
},
  "geometry": {"coordinates":[127.36037,36.63078],"type":"Point"}
}