{
  "type": "Feature",
  "properties": {
    "gn:admin1_code":"13.0",
    "gn:asciiname":"Sangha-ri",
    "gn:country_code":"KR",
    "gn:dem":103,
    "gn:feature_class":"P",
    "gn:feature_code":"PPLL",
    "gn:name":"Sangha-ri",
    "gn:population":0,
    "gn:timezone":"Asia/Seoul",
    "iso:country":"KR",
    "name:und_x_variant":[
        "\uc0c1\ud558\ub9ac",
        "Sangha-ri"
    ],
    "wof:name":"Sangha-ri",
    "wof:placetype":"locality"
},
  "geometry": {"coordinates":[127.14583,37.27417],"type":"Point"}
}