{
  "type": "Feature",
  "properties": {
    "gn:admin1_code":"6.0",
    "gn:asciiname":"Sangp'anmun",
    "gn:country_code":"KR",
    "gn:dem":716,
    "gn:feature_class":"P",
    "gn:feature_code":"PPL",
    "gn:name":"Sangp\u2019anmun",
    "gn:population":0,
    "gn:timezone":"Asia/Seoul",
    "iso:country":"KR",
    "name:kor_x_preferred":[
        "\uc0c1\ud310\ubb38"
    ],
    "name:kor_x_variant":[
        "Sangp\u2019anmun"
    ],
    "wof:name":"Sangp'anmun",
    "wof:placetype":"locality"
},
  "geometry": {"coordinates":[128.90360000000001,37.2628],"type":"Point"}
}