{
  "type": "Feature",
  "properties": {
    "gn:admin1_code":"16.0",
    "gn:asciiname":"Ikgeumni",
    "gn:country_code":"KR",
    "gn:dem":10,
    "gn:feature_class":"P",
    "gn:feature_code":"PPL",
    "gn:name":"Ikgeumni",
    "gn:population":0,
    "gn:timezone":"Asia/Seoul",
    "iso:country":"KR",
    "name:kor_x_preferred":[
        "\uc775\uae08\ub9ac"
    ],
    "name:und_x_variant":[
        "Ikk\u016dm-ni"
    ],
    "wof:name":"Ikgeumni",
    "wof:placetype":"locality"
},
  "geometry": {"coordinates":[126.12303,34.87407],"type":"Point"}
}