{
  "type": "Feature",
  "properties": {
    "gn:admin1_code":"6.0",
    "gn:asciiname":"Yaksugol",
    "gn:country_code":"KR",
    "gn:dem":264,
    "gn:feature_class":"P",
    "gn:feature_code":"PPL",
    "gn:name":"Yaksugol",
    "gn:population":0,
    "gn:timezone":"Asia/Seoul",
    "iso:country":"KR",
    "name:kor_x_preferred":[
        "\uc57d\uc218\uace8"
    ],
    "wof:name":"Yaksugol",
    "wof:placetype":"locality"
},
  "geometry": {"coordinates":[127.88800999999999,38.03642],"type":"Point"}
}