{
  "type": "Feature",
  "properties": {
    "gn:admin1_code":"20.0",
    "gn:asciiname":"Mosin",
    "gn:cc2":"KR",
    "gn:country_code":"KR",
    "gn:dem":101,
    "gn:feature_class":"P",
    "gn:feature_code":"PPL",
    "gn:name":"Mosin",
    "gn:population":0,
    "gn:timezone":"Asia/Seoul",
    "iso:country":"KR",
    "name:und_x_variant":[
        "Mosan",
        "Mosin"
    ],
    "wof:name":"Mosin",
    "wof:placetype":"locality"
},
  "geometry": {"coordinates":[128.05528000000001,35.13667],"type":"Point"}
}