{
  "type": "Feature",
  "properties": {
    "gn:admin1_code":"14.0",
    "gn:asciiname":"Monogol",
    "gn:country_code":"KR",
    "gn:dem":175,
    "gn:feature_class":"P",
    "gn:feature_code":"PPL",
    "gn:name":"Monogol",
    "gn:population":0,
    "gn:timezone":"Asia/Seoul",
    "iso:country":"KR",
    "name:kor_x_preferred":[
        "\ubaa8\ub178\uace8"
    ],
    "wof:name":"Monogol",
    "wof:placetype":"locality"
},
  "geometry": {"coordinates":[128.62431999999998,36.59795],"type":"Point"}
}