{
  "type": "Feature",
  "properties": {
    "gn:admin1_code":"16.0",
    "gn:asciiname":"Bajae",
    "gn:country_code":"KR",
    "gn:dem":36,
    "gn:feature_class":"P",
    "gn:feature_code":"PPL",
    "gn:name":"Bajae",
    "gn:population":0,
    "gn:timezone":"Asia/Seoul",
    "iso:country":"KR",
    "name:kor_x_preferred":[
        "\ubc14\uc7ac"
    ],
    "wof:name":"Bajae",
    "wof:placetype":"locality"
},
  "geometry": {"coordinates":[126.79067000000001,34.96542],"type":"Point"}
}