{
  "type": "Feature",
  "properties": {
    "gn:admin1_code":"19.0",
    "gn:asciiname":"Agam",
    "gn:country_code":"KR",
    "gn:dem":127,
    "gn:feature_class":"P",
    "gn:feature_code":"PPL",
    "gn:name":"Agam",
    "gn:population":0,
    "gn:timezone":"Asia/Seoul",
    "iso:country":"KR",
    "name:und_x_variant":[
        "\uc544\uac10",
        "Agam"
    ],
    "wof:name":"Agam",
    "wof:placetype":"locality"
},
  "geometry": {"coordinates":[127.51761999999999,36.3549],"type":"Point"}
}