{
  "type": "Feature",
  "properties": {
    "gn:admin1_code":"17.0",
    "gn:asciiname":"Yangjittum",
    "gn:country_code":"KR",
    "gn:dem":45,
    "gn:feature_class":"P",
    "gn:feature_code":"PPL",
    "gn:name":"Yangjitt\u016dm",
    "gn:population":0,
    "gn:timezone":"Asia/Seoul",
    "iso:country":"KR",
    "name:und_x_variant":[
        "\uc591\uc9c0\ub738",
        "Yangjitt\u016dm"
    ],
    "wof:name":"Yangjittum",
    "wof:placetype":"locality"
},
  "geometry": {"coordinates":[126.8466,36.3289],"type":"Point"}
}