{
  "type": "Feature",
  "properties": {
    "gn:admin1_code":"0.0",
    "gn:asciiname":"Songgong-ni",
    "gn:country_code":"KR",
    "gn:dem":2,
    "gn:feature_class":"P",
    "gn:feature_code":"PPL",
    "gn:name":"Songgong-ni",
    "gn:population":0,
    "gn:timezone":"Asia/Seoul",
    "iso:country":"KR",
    "wof:name":"Songgong-ni",
    "wof:placetype":"locality"
},
  "geometry": {"coordinates":[126.68333,35.98333],"type":"Point"}
}