{
  "type": "Feature",
  "properties": {
    "gn:admin1_code":"17.0",
    "gn:asciiname":"Hagyodong",
    "gn:country_code":"KR",
    "gn:dem":72,
    "gn:feature_class":"P",
    "gn:feature_code":"PPL",
    "gn:name":"Hagyodong",
    "gn:population":0,
    "gn:timezone":"Asia/Seoul",
    "iso:country":"KR",
    "name:kor_x_preferred":[
        "\ud558\uad50\ub3d9"
    ],
    "wof:name":"Hagyodong",
    "wof:placetype":"locality"
},
  "geometry": {"coordinates":[127.20605999999999,36.68141],"type":"Point"}
}