{
  "type": "Feature",
  "properties": {
    "gn:admin1_code":"17.0",
    "gn:asciiname":"Deodeokgol",
    "gn:country_code":"KR",
    "gn:dem":137,
    "gn:feature_class":"P",
    "gn:feature_code":"PPL",
    "gn:name":"Deodeokgol",
    "gn:population":0,
    "gn:timezone":"Asia/Seoul",
    "iso:country":"KR",
    "name:kor_x_preferred":[
        "\ub354\ub355\uace8"
    ],
    "name:und_x_variant":[
        "T\u014fk-tong",
        "Tad\u014fk-tong",
        "Tad\u014fk-kol",
        "T\u2019\u014fd\u014fk-kol",
        "Deodeokgol"
    ],
    "wof:name":"Deodeokgol",
    "wof:placetype":"locality"
},
  "geometry": {"coordinates":[127.15309999999999,36.66144],"type":"Point"}
}