{
  "type": "Feature",
  "properties": {
    "gn:admin1_code":"17.0",
    "gn:asciiname":"Taesuk-kol",
    "gn:country_code":"KR",
    "gn:dem":29,
    "gn:feature_class":"P",
    "gn:feature_code":"PPL",
    "gn:name":"Taesuk-kol",
    "gn:population":0,
    "gn:timezone":"Asia/Seoul",
    "iso:country":"KR",
    "name:und_x_variant":[
        "\ub300\uc232\uace8",
        "Taesuk-kol"
    ],
    "wof:name":"Taesuk-kol",
    "wof:placetype":"locality"
},
  "geometry": {"coordinates":[126.8193,36.6529],"type":"Point"}
}