{
  "type": "Feature",
  "properties": {
    "gn:admin1_code":"17.0",
    "gn:asciiname":"Chungnim-ni",
    "gn:country_code":"KR",
    "gn:dem":12,
    "gn:feature_class":"P",
    "gn:feature_code":"PPLL",
    "gn:name":"Chungnim-ni",
    "gn:population":0,
    "gn:timezone":"Asia/Seoul",
    "iso:country":"KR",
    "name:und_x_variant":[
        "\uc8fd\ub9bc\ub9ac",
        "Chungnim-ni"
    ],
    "wof:name":"Chungnim-ni",
    "wof:placetype":"locality"
},
  "geometry": {"coordinates":[126.60927,36.46811],"type":"Point"}
}