{
  "type": "Feature",
  "properties": {
    "gn:admin1_code":"17.0",
    "gn:asciiname":"Wonhaktang",
    "gn:country_code":"KR",
    "gn:dem":110,
    "gn:feature_class":"P",
    "gn:feature_code":"PPL",
    "gn:name":"W\u014fnhaktang",
    "gn:population":0,
    "gn:timezone":"Asia/Seoul",
    "iso:country":"KR",
    "name:und_x_variant":[
        "\uc6d0\ud559\ub2f9",
        "W\u014fnhaktang"
    ],
    "wof:name":"Wonhaktang",
    "wof:placetype":"locality"
},
  "geometry": {"coordinates":[126.80159999999999,36.471],"type":"Point"}
}