{
  "type": "Feature",
  "properties": {
    "gn:admin1_code":"19.0",
    "gn:asciiname":"Madalchon",
    "gn:country_code":"KR",
    "gn:dem":141,
    "gn:feature_class":"P",
    "gn:feature_code":"PPL",
    "gn:name":"Madalchon",
    "gn:population":0,
    "gn:timezone":"Asia/Seoul",
    "iso:country":"KR",
    "name:und_x_variant":[
        "\ub9c8\ub2ec\ucd0c",
        "Madal-ch\u2019on",
        "Madalchon"
    ],
    "wof:name":"Madalchon",
    "wof:placetype":"locality"
},
  "geometry": {"coordinates":[127.47698,36.24062],"type":"Point"}
}