{
  "type": "Feature",
  "properties": {
    "gn:admin1_code":"13.0",
    "gn:asciiname":"Polmal",
    "gn:country_code":"KR",
    "gn:dem":19,
    "gn:feature_class":"P",
    "gn:feature_code":"PPL",
    "gn:name":"P\u014flmal",
    "gn:population":0,
    "gn:timezone":"Asia/Seoul",
    "iso:country":"KR",
    "name:kor_x_preferred":[
        "\ubc8c\ub9d0"
    ],
    "name:kor_x_variant":[
        "P\u014flmal"
    ],
    "wof:name":"Polmal",
    "wof:placetype":"locality"
},
  "geometry": {"coordinates":[126.89583,37.11111],"type":"Point"}
}