{
  "type": "Feature",
  "properties": {
    "gn:admin1_code":"5.0",
    "gn:asciiname":"Dukkeopbawi",
    "gn:country_code":"KR",
    "gn:dem":102,
    "gn:feature_class":"P",
    "gn:feature_code":"PPL",
    "gn:name":"Dukkeopbawi",
    "gn:population":0,
    "gn:timezone":"Asia/Seoul",
    "iso:country":"KR",
    "name:kor_x_preferred":[
        "\ub450\uaecd\ubc14\uc704"
    ],
    "wof:name":"Dukkeopbawi",
    "wof:placetype":"locality"
},
  "geometry": {"coordinates":[127.62017,37.02999000000001],"type":"Point"}
}