{
  "type": "Feature",
  "properties": {
    "gn:admin1_code":"6.0",
    "gn:asciiname":"Juranmal",
    "gn:country_code":"KR",
    "gn:dem":358,
    "gn:feature_class":"P",
    "gn:feature_code":"PPL",
    "gn:name":"Juranmal",
    "gn:population":0,
    "gn:timezone":"Asia/Seoul",
    "iso:country":"KR",
    "name:kor_x_preferred":[
        "\uc8fc\ub78f\ub9d0"
    ],
    "wof:name":"Juranmal",
    "wof:placetype":"locality"
},
  "geometry": {"coordinates":[127.98702,38.15532],"type":"Point"}
}