{
  "type": "Feature",
  "properties": {
    "gn:admin1_code":"16.0",
    "gn:asciiname":"Haep'yong-ni",
    "gn:country_code":"KR",
    "gn:dem":2,
    "gn:feature_class":"P",
    "gn:feature_code":"PPL",
    "gn:name":"Haep\u2019y\u014fng-ni",
    "gn:population":0,
    "gn:timezone":"Asia/Seoul",
    "iso:country":"KR",
    "name:kor_x_preferred":[
        "\ud574\ud3c9\ub9ac"
    ],
    "name:kor_x_variant":[
        "Haep\u2019y\u014fng-ni"
    ],
    "wof:name":"Haep'yong-ni",
    "wof:placetype":"locality"
},
  "geometry": {"coordinates":[127.19992999999999,34.75305],"type":"Point"}
}