{
  "type": "Feature",
  "properties": {
    "gn:admin1_code":"3.0",
    "gn:asciiname":"Chinbatsil",
    "gn:country_code":"KR",
    "gn:dem":83,
    "gn:feature_class":"P",
    "gn:feature_code":"PPL",
    "gn:name":"Chinbatsil",
    "gn:population":0,
    "gn:timezone":"Asia/Seoul",
    "iso:country":"KR",
    "name:und_x_variant":[
        "\uc9c4\ubc2d\uc2e4",
        "Chinbatsil"
    ],
    "wof:name":"Chinbatsil",
    "wof:placetype":"locality"
},
  "geometry": {"coordinates":[127.18814999999999,36.00194000000001],"type":"Point"}
}