{
  "type": "Feature",
  "properties": {
    "gn:admin1_code":"14.0",
    "gn:asciiname":"Myosan",
    "gn:country_code":"KR",
    "gn:dem":87,
    "gn:feature_class":"P",
    "gn:feature_code":"PPL",
    "gn:name":"Myosan",
    "gn:population":0,
    "gn:timezone":"Asia/Seoul",
    "iso:country":"KR",
    "name:und_x_variant":[
        "\ubb18\uc0b0",
        "Myosan"
    ],
    "wof:name":"Myosan",
    "wof:placetype":"locality"
},
  "geometry": {"coordinates":[128.14349999999999,36.3452],"type":"Point"}
}