{
  "type": "Feature",
  "properties": {
    "gn:admin1_code":"17.0",
    "gn:asciiname":"Wondaljeon",
    "gn:country_code":"KR",
    "gn:dem":51,
    "gn:feature_class":"P",
    "gn:feature_code":"PPL",
    "gn:name":"Wondaljeon",
    "gn:population":0,
    "gn:timezone":"Asia/Seoul",
    "iso:country":"KR",
    "name:kor_x_preferred":[
        "\uc6d0\ub2ec\uc804"
    ],
    "wof:name":"Wondaljeon",
    "wof:placetype":"locality"
},
  "geometry": {"coordinates":[127.34899,36.46551],"type":"Point"}
}