{
  "type": "Feature",
  "properties": {
    "gn:admin1_code":"20.0",
    "gn:asciiname":"Sagong-ni",
    "gn:country_code":"KR",
    "gn:dem":226,
    "gn:feature_class":"P",
    "gn:feature_code":"PPL",
    "gn:name":"Sagong-ni",
    "gn:population":0,
    "gn:timezone":"Asia/Seoul",
    "iso:country":"KR",
    "name:eng_x_preferred":[
        "Sagong"
    ],
    "name:eng_x_variant":[
        "Sagong-ni"
    ],
    "wof:name":"Sagong",
    "wof:placetype":"locality"
},
  "geometry": {"coordinates":[127.90917,35.23778],"type":"Point"}
}