{
  "type": "Feature",
  "properties": {
    "gn:admin1_code":"14.0",
    "gn:asciiname":"Hyobugol",
    "gn:country_code":"KR",
    "gn:dem":88,
    "gn:feature_class":"P",
    "gn:feature_code":"PPL",
    "gn:name":"Hyobugol",
    "gn:population":0,
    "gn:timezone":"Asia/Seoul",
    "iso:country":"KR",
    "name:kor_x_preferred":[
        "\ud6a8\ubd80\uace8"
    ],
    "wof:name":"Hyobugol",
    "wof:placetype":"locality"
},
  "geometry": {"coordinates":[128.53774999999999,36.55482],"type":"Point"}
}