{
  "type": "Feature",
  "properties": {
    "gn:admin1_code":"14.0",
    "gn:asciiname":"Pallae",
    "gn:country_code":"KR",
    "gn:dem":64,
    "gn:feature_class":"P",
    "gn:feature_code":"PPL",
    "gn:name":"Pallae",
    "gn:population":0,
    "gn:timezone":"Asia/Seoul",
    "iso:country":"KR",
    "name:und_x_variant":[
        "\ubc1c\ub798",
        "Pallae"
    ],
    "wof:name":"Pallae",
    "wof:placetype":"locality"
},
  "geometry": {"coordinates":[128.26480000000001,36.4184],"type":"Point"}
}