{
  "type": "Feature",
  "properties": {
    "gn:admin1_code":"6.0",
    "gn:asciiname":"Hach'unjon",
    "gn:country_code":"KR",
    "gn:dem":304,
    "gn:feature_class":"P",
    "gn:feature_code":"PPL",
    "gn:name":"Hach\u2019unj\u014fn",
    "gn:population":0,
    "gn:timezone":"Asia/Seoul",
    "iso:country":"KR",
    "name:und_x_variant":[
        "Hach\u2019ungj\u014fn",
        "\ud558\ucda9\uc804",
        "Hach\u2019unj\u014fn"
    ],
    "wof:name":"Hach'unjon",
    "wof:placetype":"locality"
},
  "geometry": {"coordinates":[129.14089999999999,37.1532],"type":"Point"}
}