{
  "type": "Feature",
  "properties": {
    "gn:admin1_code":"14.0",
    "gn:asciiname":"Geomureongni",
    "gn:country_code":"KR",
    "gn:dem":201,
    "gn:feature_class":"P",
    "gn:feature_code":"PPL",
    "gn:name":"Geomureongni",
    "gn:population":0,
    "gn:timezone":"Asia/Seoul",
    "iso:country":"KR",
    "name:kor_x_preferred":[
        "\uac70\ubb3c\uc5b5\ub9ac"
    ],
    "wof:name":"Geomureongni",
    "wof:placetype":"locality"
},
  "geometry": {"coordinates":[128.57181,36.47149],"type":"Point"}
}