{
  "type": "Feature",
  "properties": {
    "gn:admin1_code":"16.0",
    "gn:asciiname":"Gagok",
    "gn:country_code":"KR",
    "gn:dem":219,
    "gn:feature_class":"P",
    "gn:feature_code":"PPL",
    "gn:name":"Gagok",
    "gn:population":0,
    "gn:timezone":"Asia/Seoul",
    "iso:country":"KR",
    "name:deu_x_preferred":[
        "Gagok"
    ],
    "name:ind_x_preferred":[
        "Gagok"
    ],
    "name:jav_x_preferred":[
        "Gagok"
    ],
    "name:kor_x_preferred":[
        "\uac00\uace1"
    ],
    "name:pol_x_preferred":[
        "Gagok"
    ],
    "wof:name":"Gagok",
    "wof:placetype":"locality"
},
  "geometry": {"coordinates":[126.90215000000001,35.35667],"type":"Point"}
}