{
  "type": "Feature",
  "properties": {
    "gn:admin1_code":"6.0",
    "gn:asciiname":"Sinbaegol",
    "gn:country_code":"KR",
    "gn:dem":253,
    "gn:feature_class":"P",
    "gn:feature_code":"PPL",
    "gn:name":"Sinbaegol",
    "gn:population":0,
    "gn:timezone":"Asia/Seoul",
    "iso:country":"KR",
    "name:kor_x_preferred":[
        "\uc2e0\ubc30\uace8"
    ],
    "wof:name":"Sinbaegol",
    "wof:placetype":"locality"
},
  "geometry": {"coordinates":[127.84707,37.88567000000001],"type":"Point"}
}