{
  "type": "Feature",
  "properties": {
    "gn:admin1_code":"16.0",
    "gn:asciiname":"Jangjeon",
    "gn:country_code":"KR",
    "gn:dem":11,
    "gn:feature_class":"P",
    "gn:feature_code":"PPL",
    "gn:name":"Jangjeon",
    "gn:population":0,
    "gn:timezone":"Asia/Seoul",
    "iso:country":"KR",
    "name:kor_x_preferred":[
        "\uc7a5\uc804"
    ],
    "name:und_x_variant":[
        "Changj\u014fn"
    ],
    "wof:name":"Jangjeon",
    "wof:placetype":"locality"
},
  "geometry": {"coordinates":[127.61143,34.82602],"type":"Point"}
}