{
  "type": "Feature",
  "properties": {
    "gn:admin1_code":"17.0",
    "gn:asciiname":"Hasungam",
    "gn:country_code":"KR",
    "gn:dem":245,
    "gn:feature_class":"P",
    "gn:feature_code":"PPL",
    "gn:name":"Hasungam",
    "gn:population":0,
    "gn:timezone":"Asia/Seoul",
    "iso:country":"KR",
    "name:und_x_variant":[
        "\ud558\uc22d\uc554",
        "Hasungam"
    ],
    "wof:name":"Hasungam",
    "wof:placetype":"locality"
},
  "geometry": {"coordinates":[127.49936,36.18626],"type":"Point"}
}