{
  "type": "Feature",
  "properties": {
    "iso:country":"KR",
    "name:kor_x_preferred":[
        "\uc6d4\ud53c\ub3d9"
    ],
    "name:kor_x_variant":[
        "\ubd80\uace1\ub3d9",
        "\uc591\uc0c1\ub3d9",
        "\uc6d4\uae30\ub3d9"
    ],
    "name:und_x_variant":[
        "Wolgi-dong"
    ],
    "qs:gn_fcode":"PPL",
    "qs:gn_local":0,
    "qs:gn_namadm1":"13",
    "qs:gn_name":"Wolgi-dong",
    "qs:local_max":244,
    "qs:local_sum":708,
    "qs:localhoods":8,
    "qs:name":"\uc6d4\ud53c\ub3d9",
    "qs:name_adm0":"\ud55c\uad6d",
    "qs:name_adm1":"\uacbd\uae30\ub3c4",
    "qs:name_adm2":"\uc548\uc0b0\uc2dc",
    "qs:name_lau":"\uc0c1\ub85d\uad6c",
    "qs:name_local":"\uc0c1\ub85d\uad6c",
    "qs:photo_max":40,
    "qs:photo_sum":63,
    "qs:placetype":"Suburb",
    "qs:quad_count":4,
    "qs:woe_adm0":23424868,
    "qs:woe_adm1":2345969,
    "qs:woe_adm2":28289108,
    "qs:woe_lau":28997207,
    "qs:woe_local":28997207,
    "qs:woe_ver":"7.10.0",
    "wof:lang":[
        "kor"
    ],
    "wof:name":"\uc6d4\ud53c\ub3d9",
    "wof:placetype":"neighbourhood"
},
  "geometry": {"coordinates":[126.851934,37.336578],"type":"Point"}
}