{
  "type": "Feature",
  "properties": {
    "gn:admin1_code":"14.0",
    "gn:asciiname":"Sudong",
    "gn:country_code":"KR",
    "gn:dem":87,
    "gn:feature_class":"P",
    "gn:feature_code":"PPL",
    "gn:name":"Sudong",
    "gn:population":0,
    "gn:timezone":"Asia/Seoul",
    "iso:country":"KR",
    "name:fas_x_preferred":[
        "\u0633\u0648\u062f\u0648\u0646\u06af"
    ],
    "name:jpn_x_preferred":[
        "\u6c34\u6d1e\u533a"
    ],
    "name:kor_x_preferred":[
        "\uc218\ub3d9"
    ],
    "name:kor_x_variant":[
        "\uc218\ub3d9\uad6c"
    ],
    "name:nor_x_preferred":[
        "Sudong"
    ],
    "name:pol_x_preferred":[
        "Sudong"
    ],
    "name:por_x_preferred":[
        "Sudong-ku"
    ],
    "name:tur_x_preferred":[
        "Sudong"
    ],
    "name:vie_x_preferred":[
        "Sudong"
    ],
    "name:zho_x_preferred":[
        "\u6c34\u6d1e\u5340"
    ],
    "wof:name":"Sudong",
    "wof:placetype":"locality"
},
  "geometry": {"coordinates":[128.39818,36.58425],"type":"Point"}
}