{
  "type": "Feature",
  "properties": {
    "gn:admin1_code":"17.0",
    "gn:asciiname":"Araegonch'on",
    "gn:country_code":"KR",
    "gn:dem":118,
    "gn:feature_class":"P",
    "gn:feature_code":"PPL",
    "gn:name":"Araeg\u014fnch\u2019\u014fn",
    "gn:population":0,
    "gn:timezone":"Asia/Seoul",
    "iso:country":"KR",
    "name:und_x_variant":[
        "\uc544\ub798\uac74\ucc9c",
        "Araeg\u014fnch\u2019\u014fn"
    ],
    "wof:name":"Araegonch'on",
    "wof:placetype":"locality"
},
  "geometry": {"coordinates":[126.6802,36.4269],"type":"Point"}
}