{
  "type": "Feature",
  "properties": {
    "gn:admin1_code":"17.0",
    "gn:asciiname":"Taeho",
    "gn:country_code":"KR",
    "gn:dem":18,
    "gn:feature_class":"P",
    "gn:feature_code":"PPL",
    "gn:name":"Taeho",
    "gn:population":0,
    "gn:timezone":"Asia/Seoul",
    "iso:country":"KR",
    "name:und_x_variant":[
        "\ub300\ud638",
        "Taeho"
    ],
    "wof:name":"Taeho",
    "wof:placetype":"locality"
},
  "geometry": {"coordinates":[126.7722,36.7835],"type":"Point"}
}