{
  "type": "Feature",
  "properties": {
    "gn:admin1_code":"3.0",
    "gn:asciiname":"Yongsal-li",
    "gn:cc2":"KR",
    "gn:country_code":"KR",
    "gn:dem":95,
    "gn:feature_class":"P",
    "gn:feature_code":"PPL",
    "gn:name":"Yongsal-li",
    "gn:population":0,
    "gn:timezone":"Asia/Seoul",
    "iso:country":"KR",
    "name:und_x_variant":[
        "Yongsan-ni",
        "Yongsan-dong",
        "Yongsal-li"
    ],
    "wof:name":"Yongsal-li",
    "wof:placetype":"locality"
},
  "geometry": {"coordinates":[126.63833,35.50611],"type":"Point"}
}