{
  "type": "Feature",
  "properties": {
    "gn:admin1_code":"5.0",
    "gn:asciiname":"Hanti",
    "gn:country_code":"KR",
    "gn:dem":306,
    "gn:feature_class":"P",
    "gn:feature_code":"PPL",
    "gn:name":"Hanti",
    "gn:population":0,
    "gn:timezone":"Asia/Seoul",
    "iso:country":"KR",
    "name:kor_x_preferred":[
        "\ud55c\ud2f0"
    ],
    "wof:name":"Hanti",
    "wof:placetype":"locality"
},
  "geometry": {"coordinates":[127.59730999999999,36.6579],"type":"Point"}
}