{
  "type": "Feature",
  "properties": {
    "gn:admin1_code":"14.0",
    "gn:asciiname":"Oksong",
    "gn:country_code":"KR",
    "gn:dem":289,
    "gn:feature_class":"P",
    "gn:feature_code":"PPL",
    "gn:name":"Oks\u014fng",
    "gn:population":0,
    "gn:timezone":"Asia/Seoul",
    "iso:country":"KR",
    "name:und_x_variant":[
        "\uc625\uc131",
        "Oks\u014fng"
    ],
    "wof:name":"Oksong",
    "wof:placetype":"locality"
},
  "geometry": {"coordinates":[127.9281,36.4355],"type":"Point"}
}