{
  "type": "Feature",
  "properties": {
    "gn:admin1_code":"6.0",
    "gn:asciiname":"Moran",
    "gn:country_code":"KR",
    "gn:dem":221,
    "gn:feature_class":"P",
    "gn:feature_code":"PPL",
    "gn:name":"Moran",
    "gn:population":0,
    "gn:timezone":"Asia/Seoul",
    "iso:country":"KR",
    "name:ara_x_preferred":[
        "\u0645\u0648\u0631\u0627\u0646"
    ],
    "name:asm_x_preferred":[
        "\u09ae\u09f0\u09be\u09a3"
    ],
    "name:bre_x_preferred":[
        "Moran"
    ],
    "name:cat_x_preferred":[
        "Moran"
    ],
    "name:ceb_x_preferred":[
        "Moran"
    ],
    "name:ces_x_preferred":[
        "Moran"
    ],
    "name:deu_x_preferred":[
        "Moran"
    ],
    "name:fas_x_preferred":[
        "\u0645\u0648\u0631\u0627\u0646"
    ],
    "name:fin_x_preferred":[
        "Moran"
    ],
    "name:fra_x_preferred":[
        "Moran"
    ],
    "name:ita_x_preferred":[
        "Moran"
    ],
    "name:kor_x_preferred":[
        "\ubaa8\ub780"
    ],
    "name:nds_x_preferred":[
        "Moran"
    ],
    "name:nld_x_preferred":[
        "Moran"
    ],
    "name:pol_x_preferred":[
        "Moran"
    ],
    "name:rus_x_preferred":[
        "\u041c\u043e\u0440\u0430\u043d"
    ],
    "name:spa_x_preferred":[
        "Moran"
    ],
    "name:srp_x_preferred":[
        "\u041c\u043e\u0440\u0430\u043d"
    ],
    "name:swe_x_preferred":[
        "Moran"
    ],
    "name:vol_x_preferred":[
        "Moran"
    ],
    "wof:name":"Moran",
    "wof:placetype":"locality"
},
  "geometry": {"coordinates":[128.0823,37.45],"type":"Point"}
}