{
  "type": "Feature",
  "properties": {
    "iso:country":"KR",
    "name:eng_x_preferred":[
        "Sang 1(il)-dong"
    ],
    "name:kor_x_preferred":[
        "\uc0c11\ub3d9"
    ],
    "name:und_x_variant":[
        "\uc0c1\ub3d9"
    ],
    "qs:gn_fcode":"PPL",
    "qs:gn_local":0,
    "qs:gn_namadm1":"13",
    "qs:gn_name":"Sang-dong",
    "qs:local_max":241,
    "qs:local_sum":869,
    "qs:localhoods":8,
    "qs:name":"\uc0c11\ub3d9",
    "qs:name_adm0":"\ud55c\uad6d",
    "qs:name_adm1":"\uacbd\uae30\ub3c4",
    "qs:name_adm2":"\ubd80\ucc9c\uc2dc",
    "qs:name_lau":"\uc6d0\ubbf8\uad6c",
    "qs:name_local":"\uc6d0\ubbf8\uad6c",
    "qs:photo_max":27,
    "qs:photo_sum":72,
    "qs:placetype":"Suburb",
    "qs:quad_count":5,
    "qs:woe_adm0":23424868,
    "qs:woe_adm1":2345969,
    "qs:woe_adm2":28289117,
    "qs:woe_lau":28997204,
    "qs:woe_local":28997204,
    "qs:woe_ver":"7.10.0",
    "wof:lang":[
        "kor"
    ],
    "wof:name":"Sang 1(il)-dong",
    "wof:placetype":"neighbourhood"
},
  "geometry": {"coordinates":[126.758543,37.50442],"type":"Point"}
}