{
  "type": "Feature",
  "properties": {
    "gn:admin1_code":"19.0",
    "gn:asciiname":"Araennapjakgol",
    "gn:country_code":"KR",
    "gn:dem":55,
    "gn:feature_class":"P",
    "gn:feature_code":"PPL",
    "gn:name":"Araennapjakgol",
    "gn:population":0,
    "gn:timezone":"Asia/Seoul",
    "iso:country":"KR",
    "name:kor_x_preferred":[
        "\uc544\ub7ab\ub0a9\uc791\uace8"
    ],
    "wof:name":"Araennapjakgol",
    "wof:placetype":"locality"
},
  "geometry": {"coordinates":[127.33794,36.37475],"type":"Point"}
}