{
  "type": "Feature",
  "properties": {
    "gn:admin1_code":"6.0",
    "gn:asciiname":"Dohwadong",
    "gn:country_code":"KR",
    "gn:dem":209,
    "gn:feature_class":"P",
    "gn:feature_code":"PPL",
    "gn:name":"Dohwadong",
    "gn:population":0,
    "gn:timezone":"Asia/Seoul",
    "iso:country":"KR",
    "name:kor_x_preferred":[
        "\ub3c4\ud654\ub3d9"
    ],
    "name:und_x_variant":[
        "Tohwa-dong",
        "Dohwadong"
    ],
    "wof:name":"Dohwadong",
    "wof:placetype":"locality"
},
  "geometry": {"coordinates":[127.81112,37.77266],"type":"Point"}
}