{
  "type": "Feature",
  "properties": {
    "gn:admin1_code":"6.0",
    "gn:asciiname":"Saemalteo",
    "gn:country_code":"KR",
    "gn:dem":278,
    "gn:feature_class":"P",
    "gn:feature_code":"PPL",
    "gn:name":"Saemalteo",
    "gn:population":0,
    "gn:timezone":"Asia/Seoul",
    "iso:country":"KR",
    "name:kor_x_preferred":[
        "\uc0c8\ub9c8\uc744\ud130"
    ],
    "name:kor_x_variant":[
        "Saema\u016dlt\u2019\u014f",
        "\uc0c8\ub9d0\ud130"
    ],
    "name:und_x_variant":[
        "Saemaeulteo",
        "Saemalteo"
    ],
    "wof:name":"Saemalteo",
    "wof:placetype":"locality"
},
  "geometry": {"coordinates":[127.88120000000001,38.00872],"type":"Point"}
}