{
  "type": "Feature",
  "properties": {
    "gn:admin1_code":"13.0",
    "gn:asciiname":"Taegam",
    "gn:country_code":"KR",
    "gn:dem":68,
    "gn:feature_class":"P",
    "gn:feature_code":"PPL",
    "gn:name":"Taegam",
    "gn:population":0,
    "gn:timezone":"Asia/Seoul",
    "iso:country":"KR",
    "name:und_x_variant":[
        "Han\u2019gam-ni",
        "Taegam-ni",
        "\ub300\uac10",
        "Daegam",
        "Taegam"
    ],
    "wof:name":"Taegam",
    "wof:placetype":"locality"
},
  "geometry": {"coordinates":[127.47722,37.43111],"type":"Point"}
}