{
  "type": "Feature",
  "properties": {
    "gn:admin1_code":"20.0",
    "gn:asciiname":"Byeongbaedong",
    "gn:country_code":"KR",
    "gn:dem":26,
    "gn:feature_class":"P",
    "gn:feature_code":"PPL",
    "gn:name":"Byeongbaedong",
    "gn:population":0,
    "gn:timezone":"Asia/Seoul",
    "iso:country":"KR",
    "name:kor_x_preferred":[
        "\ubcd1\ubc30\ub3d9"
    ],
    "name:und_x_variant":[
        "\ubcd1\ubc30",
        "Py\u014fngbae",
        "Byeongbaedong"
    ],
    "wof:name":"Byeongbaedong",
    "wof:placetype":"locality"
},
  "geometry": {"coordinates":[128.34017,35.62553],"type":"Point"}
}