{
  "type": "Feature",
  "properties": {
    "gn:admin1_code":"3.0",
    "gn:asciiname":"Ch'angje-ri",
    "gn:country_code":"KR",
    "gn:dem":6,
    "gn:feature_class":"P",
    "gn:feature_code":"PPL",
    "gn:name":"Ch\u2019angje-ri",
    "gn:population":0,
    "gn:timezone":"Asia/Seoul",
    "iso:country":"KR",
    "wof:name":"Ch'angje-ri",
    "wof:placetype":"locality"
},
  "geometry": {"coordinates":[126.72083000000001,35.84083],"type":"Point"}
}