{
  "type": "Feature",
  "properties": {
    "gn:admin1_code":"16.0",
    "gn:asciiname":"Soseoho",
    "gn:country_code":"KR",
    "gn:dem":15,
    "gn:feature_class":"P",
    "gn:feature_code":"PPL",
    "gn:name":"Soseoho",
    "gn:population":0,
    "gn:timezone":"Asia/Seoul",
    "iso:country":"KR",
    "name:kor_x_preferred":[
        "\uc18c\uc11c\ud638"
    ],
    "name:und_x_variant":[
        "Sos\u014fho",
        "Soseoho"
    ],
    "wof:name":"Soseoho",
    "wof:placetype":"locality"
},
  "geometry": {"coordinates":[126.50917,34.73944],"type":"Point"}
}