{
  "type": "Feature",
  "properties": {
    "gn:admin1_code":"13.0",
    "gn:asciiname":"Sogari",
    "gn:country_code":"KR",
    "gn:dem":109,
    "gn:feature_class":"P",
    "gn:feature_code":"PPL",
    "gn:name":"Sogari",
    "gn:population":0,
    "gn:timezone":"Asia/Seoul",
    "iso:country":"KR",
    "name:und_x_variant":[
        "\uc18c\uac00\ub9ac",
        "Soga-ri",
        "Sogari"
    ],
    "wof:name":"Sogari",
    "wof:placetype":"locality"
},
  "geometry": {"coordinates":[126.96647,37.81759],"type":"Point"}
}