{
  "type": "Feature",
  "properties": {
    "gn:admin1_code":"16.0",
    "gn:asciiname":"Geumsan",
    "gn:country_code":"KR",
    "gn:dem":199,
    "gn:feature_class":"P",
    "gn:feature_code":"PPL",
    "gn:name":"Geumsan",
    "gn:population":0,
    "gn:timezone":"Asia/Seoul",
    "iso:country":"KR",
    "name:kor_x_preferred":[
        "\uae08\uc0b0"
    ],
    "name:kor_x_variant":[
        "K\u016dmsan"
    ],
    "name:und_x_variant":[
        "K\u016dms\u014fng-ni",
        "K\u016dmsan-ni",
        "K\u016dmsal-li",
        "Geumsan"
    ],
    "wof:name":"Geumsan",
    "wof:placetype":"locality"
},
  "geometry": {"coordinates":[127.35462,34.9406],"type":"Point"}
}