{
  "type": "Feature",
  "properties": {
    "gn:admin1_code":"6.0",
    "gn:asciiname":"Munael-gol",
    "gn:country_code":"KR",
    "gn:dem":677,
    "gn:feature_class":"P",
    "gn:feature_code":"PPL",
    "gn:name":"Munael-gol",
    "gn:population":0,
    "gn:timezone":"Asia/Seoul",
    "iso:country":"KR",
    "name:kor_x_preferred":[
        "\ubb34\ub0bc\uace8"
    ],
    "name:und_x_variant":[
        "Munel",
        "Munael-gol"
    ],
    "wof:name":"Munael-gol",
    "wof:placetype":"locality"
},
  "geometry": {"coordinates":[128.83860000000001,37.3774],"type":"Point"}
}