{
  "type": "Feature",
  "properties": {
    "gn:admin1_code":"13.0",
    "gn:asciiname":"Tomakpo",
    "gn:country_code":"KR",
    "gn:dem":37,
    "gn:feature_class":"P",
    "gn:feature_code":"PPL",
    "gn:name":"Tomakpo",
    "gn:population":0,
    "gn:timezone":"Asia/Seoul",
    "iso:country":"KR",
    "name:kor_x_preferred":[
        "\ud1a0\ub9c9\ud3ec"
    ],
    "wof:name":"Tomakpo",
    "wof:placetype":"locality"
},
  "geometry": {"coordinates":[126.96004000000001,38.0064],"type":"Point"}
}