{
  "type": "Feature",
  "properties": {
    "gn:admin1_code":"6.0",
    "gn:asciiname":"Witdamuri",
    "gn:country_code":"KR",
    "gn:dem":525,
    "gn:feature_class":"P",
    "gn:feature_code":"PPL",
    "gn:name":"Witdamuri",
    "gn:population":0,
    "gn:timezone":"Asia/Seoul",
    "iso:country":"KR",
    "name:kor_x_preferred":[
        "\uc6c3\ub2e4\ubb34\ub9ac"
    ],
    "name:kor_x_variant":[
        "\uc717\ub2e4\ubb34\ub9ac"
    ],
    "name:und_x_variant":[
        "Uttamu-ri",
        "Witdamuri"
    ],
    "wof:name":"Witdamuri",
    "wof:placetype":"locality"
},
  "geometry": {"coordinates":[128.09962999999999,37.94111],"type":"Point"}
}