{
  "type": "Feature",
  "properties": {
    "gn:admin1_code":"20.0",
    "gn:asciiname":"Oe-dong",
    "gn:country_code":"KR",
    "gn:dem":35,
    "gn:feature_class":"P",
    "gn:feature_code":"PPL",
    "gn:name":"Oe-dong",
    "gn:population":0,
    "gn:timezone":"Asia/Seoul",
    "iso:country":"KR",
    "name:und_x_variant":[
        "\uc678\ub3d9",
        "Oe-dong"
    ],
    "wof:name":"Oe-dong",
    "wof:placetype":"locality"
},
  "geometry": {"coordinates":[128.43584999999999,35.29147000000001],"type":"Point"}
}