{
  "type": "Feature",
  "properties": {
    "gn:admin1_code":"5.0",
    "gn:asciiname":"Sotdaeul",
    "gn:country_code":"KR",
    "gn:dem":122,
    "gn:feature_class":"P",
    "gn:feature_code":"PPL",
    "gn:name":"Sotdaeul",
    "gn:population":0,
    "gn:timezone":"Asia/Seoul",
    "iso:country":"KR",
    "name:kor_x_preferred":[
        "\uc19f\ub300\uc6b8"
    ],
    "name:und_x_variant":[
        "Sottaeul"
    ],
    "wof:name":"Sotdaeul",
    "wof:placetype":"locality"
},
  "geometry": {"coordinates":[127.78309,37.04355],"type":"Point"}
}