{
  "type": "Feature",
  "properties": {
    "gn:admin1_code":"6.0",
    "gn:asciiname":"Janggeori",
    "gn:country_code":"KR",
    "gn:dem":289,
    "gn:feature_class":"P",
    "gn:feature_code":"PPL",
    "gn:name":"Janggeori",
    "gn:population":0,
    "gn:timezone":"Asia/Seoul",
    "iso:country":"KR",
    "name:kor_x_preferred":[
        "\uc7a5\uac70\ub9ac"
    ],
    "name:kor_x_variant":[
        "Changg\u014f-ri"
    ],
    "wof:name":"Janggeori",
    "wof:placetype":"locality"
},
  "geometry": {"coordinates":[128.04443999999998,38.20194],"type":"Point"}
}