{
  "type": "Feature",
  "properties": {
    "gn:admin1_code":"16.0",
    "gn:asciiname":"Singyeong",
    "gn:country_code":"KR",
    "gn:dem":1,
    "gn:feature_class":"P",
    "gn:feature_code":"PPL",
    "gn:name":"Singyeong",
    "gn:population":0,
    "gn:timezone":"Asia/Seoul",
    "iso:country":"KR",
    "name:kor_x_preferred":[
        "\uc2e0\uacbd"
    ],
    "name:kor_x_variant":[
        "Sin\u2019gy\u014fng"
    ],
    "wof:name":"Singyeong",
    "wof:placetype":"locality"
},
  "geometry": {"coordinates":[127.44333,34.77981],"type":"Point"}
}