{
  "type": "Feature",
  "properties": {
    "gn:admin1_code":"20.0",
    "gn:asciiname":"Igye",
    "gn:country_code":"KR",
    "gn:dem":60,
    "gn:feature_class":"P",
    "gn:feature_code":"PPL",
    "gn:name":"Igye",
    "gn:population":0,
    "gn:timezone":"Asia/Seoul",
    "iso:country":"KR",
    "name:und_x_variant":[
        "\uc774\uacc4",
        "Igye"
    ],
    "wof:name":"Igye",
    "wof:placetype":"locality"
},
  "geometry": {"coordinates":[128.16,35.51809],"type":"Point"}
}