{
  "type": "Feature",
  "properties": {
    "gn:admin1_code":"14.0",
    "gn:asciiname":"Paenadu-ri",
    "gn:country_code":"KR",
    "gn:dem":301,
    "gn:feature_class":"P",
    "gn:feature_code":"PPL",
    "gn:name":"Paenad\u016d-ri",
    "gn:population":0,
    "gn:timezone":"Asia/Seoul",
    "iso:country":"KR",
    "name:und_x_variant":[
        "\ubc30\ub098\ub4dc\ub9ac",
        "Paenad\u016d-ri"
    ],
    "wof:name":"Paenadu-ri",
    "wof:placetype":"locality"
},
  "geometry": {"coordinates":[129.02359999999999,36.9289],"type":"Point"}
}