{
  "type": "Feature",
  "properties": {
    "gn:admin1_code":"14.0",
    "gn:asciiname":"Sangt'o",
    "gn:country_code":"KR",
    "gn:dem":40,
    "gn:feature_class":"P",
    "gn:feature_code":"PPL",
    "gn:name":"Sangt\u2019o",
    "gn:population":0,
    "gn:timezone":"Asia/Seoul",
    "iso:country":"KR",
    "name:und_x_variant":[
        "\uc0c1\ud1a0",
        "Sangt\u2019o"
    ],
    "wof:name":"Sangt'o",
    "wof:placetype":"locality"
},
  "geometry": {"coordinates":[129.37860000000001,36.986],"type":"Point"}
}