{
  "type": "Feature",
  "properties": {
    "gn:admin1_code":"20.0",
    "gn:asciiname":"Pujae",
    "gn:country_code":"KR",
    "gn:dem":347,
    "gn:feature_class":"P",
    "gn:feature_code":"PPL",
    "gn:name":"Pujae",
    "gn:population":0,
    "gn:timezone":"Asia/Seoul",
    "iso:country":"KR",
    "name:und_x_variant":[
        "\ubd80\uc7ac",
        "Pujae"
    ],
    "wof:name":"Pujae",
    "wof:placetype":"locality"
},
  "geometry": {"coordinates":[128.41686000000001,35.15331],"type":"Point"}
}