{
  "type": "Feature",
  "properties": {
    "gn:admin1_code":"17.0",
    "gn:asciiname":"Gwandong",
    "gn:country_code":"KR",
    "gn:dem":69,
    "gn:feature_class":"P",
    "gn:feature_code":"PPL",
    "gn:name":"Gwandong",
    "gn:population":0,
    "gn:timezone":"Asia/Seoul",
    "iso:country":"KR",
    "name:und_x_variant":[
        "\uad00\ub3d9",
        "Kwan-dong",
        "Gwandong"
    ],
    "wof:name":"Gwandong",
    "wof:placetype":"locality"
},
  "geometry": {"coordinates":[127.21081,36.22974],"type":"Point"}
}