{
  "type": "Feature",
  "properties": {
    "gn:admin1_code":"13.0",
    "gn:asciiname":"Noksu-gol",
    "gn:country_code":"KR",
    "gn:dem":118,
    "gn:feature_class":"P",
    "gn:feature_code":"PPL",
    "gn:name":"Noksu-gol",
    "gn:population":0,
    "gn:timezone":"Asia/Seoul",
    "iso:country":"KR",
    "name:und_x_variant":[
        "\ub179\uc218\uace8",
        "Noksu-gol"
    ],
    "wof:name":"Noksu-gol",
    "wof:placetype":"locality"
},
  "geometry": {"coordinates":[127.72139,37.35111],"type":"Point"}
}