{
  "type": "Feature",
  "properties": {
    "gn:admin1_code":"6.0",
    "gn:asciiname":"Su-gol",
    "gn:country_code":"KR",
    "gn:dem":189,
    "gn:feature_class":"P",
    "gn:feature_code":"PPL",
    "gn:name":"Su-gol",
    "gn:population":0,
    "gn:timezone":"Asia/Seoul",
    "iso:country":"KR",
    "name:kor_x_preferred":[
        "\uc218\uace8"
    ],
    "wof:name":"Su-gol",
    "wof:placetype":"locality"
},
  "geometry": {"coordinates":[128.0033,37.3989],"type":"Point"}
}