{
  "type": "Feature",
  "properties": {
    "gn:admin1_code":"3.0",
    "gn:asciiname":"Andongne",
    "gn:country_code":"KR",
    "gn:dem":150,
    "gn:feature_class":"P",
    "gn:feature_code":"PPL",
    "gn:name":"Andongne",
    "gn:population":0,
    "gn:timezone":"Asia/Seoul",
    "iso:country":"KR",
    "name:und_x_variant":[
        "\uc548\ub3d9\ub124",
        "Andongne"
    ],
    "wof:name":"Andongne",
    "wof:placetype":"locality"
},
  "geometry": {"coordinates":[127.39385,35.5049],"type":"Point"}
}