{
  "type": "Feature",
  "properties": {
    "gn:admin1_code":"6.0",
    "gn:asciiname":"Dangsuban",
    "gn:country_code":"KR",
    "gn:dem":132,
    "gn:feature_class":"P",
    "gn:feature_code":"PPL",
    "gn:name":"Dangsuban",
    "gn:population":0,
    "gn:timezone":"Asia/Seoul",
    "iso:country":"KR",
    "name:kor_x_preferred":[
        "\ub2f9\uc218\ubc18"
    ],
    "name:und_x_variant":[
        "\ub2f9\uc232\uc548",
        "Tangsup\u2019an",
        "Dangsuban"
    ],
    "wof:name":"Dangsuban",
    "wof:placetype":"locality"
},
  "geometry": {"coordinates":[127.60243,37.85935],"type":"Point"}
}