{
  "type": "Feature",
  "properties": {
    "gn:admin1_code":"6.0",
    "gn:asciiname":"Sindae-ri",
    "gn:country_code":"KR",
    "gn:dem":142,
    "gn:feature_class":"P",
    "gn:feature_code":"PPL",
    "gn:name":"Sindae-ri",
    "gn:population":0,
    "gn:timezone":"Asia/Seoul",
    "iso:country":"KR",
    "name:und_x_variant":[
        "\uc2e0\ub300\ub9ac",
        "Sindae-ri"
    ],
    "wof:name":"Sindae-ri",
    "wof:placetype":"locality"
},
  "geometry": {"coordinates":[127.67833,38.13444000000001],"type":"Point"}
}