{
  "type": "Feature",
  "properties": {
    "gn:admin1_code":"3.0",
    "gn:asciiname":"Tapjeong",
    "gn:country_code":"KR",
    "gn:dem":29,
    "gn:feature_class":"P",
    "gn:feature_code":"PPL",
    "gn:name":"Tapjeong",
    "gn:population":0,
    "gn:timezone":"Asia/Seoul",
    "iso:country":"KR",
    "name:kor_x_preferred":[
        "\ud0d1\uc815"
    ],
    "name:und_x_variant":[
        "Sangt\u2019ap",
        "T\u2019apch\u014fng",
        "Tapjeong"
    ],
    "wof:name":"Tapjeong",
    "wof:placetype":"locality"
},
  "geometry": {"coordinates":[126.61957,35.49259],"type":"Point"}
}