{
  "type": "Feature",
  "properties": {
    "gn:admin1_code":"16.0",
    "gn:asciiname":"Goran",
    "gn:country_code":"KR",
    "gn:dem":29,
    "gn:feature_class":"P",
    "gn:feature_code":"PPL",
    "gn:name":"Goran",
    "gn:population":0,
    "gn:timezone":"Asia/Seoul",
    "iso:country":"KR",
    "name:kor_x_preferred":[
        "\uace8\uc548"
    ],
    "name:und_x_variant":[
        "Koran",
        "Goran"
    ],
    "wof:name":"Goran",
    "wof:placetype":"locality"
},
  "geometry": {"coordinates":[127.35244,34.72867],"type":"Point"}
}