{
  "type": "Feature",
  "properties": {
    "gn:admin1_code":"14.0",
    "gn:asciiname":"Ich'ol-li",
    "gn:country_code":"KR",
    "gn:dem":82,
    "gn:feature_class":"P",
    "gn:feature_code":"PPLL",
    "gn:name":"Ich\u2019\u014fl-li",
    "gn:population":0,
    "gn:timezone":"Asia/Seoul",
    "iso:country":"KR",
    "name:und_x_variant":[
        "\uc774\ucc9c\ub9ac",
        "Ich\u2019\u014fl-li"
    ],
    "wof:name":"Ich'ol-li",
    "wof:placetype":"locality"
},
  "geometry": {"coordinates":[128.12861000000001,36.47668],"type":"Point"}
}