{
  "type": "Feature",
  "properties": {
    "gn:admin1_code":"20.0",
    "gn:asciiname":"Oech'u",
    "gn:country_code":"KR",
    "gn:dem":66,
    "gn:feature_class":"P",
    "gn:feature_code":"PPL",
    "gn:name":"Oech\u2019u",
    "gn:population":0,
    "gn:timezone":"Asia/Seoul",
    "iso:country":"KR",
    "name:und_x_variant":[
        "\uc678\ucd94",
        "Oech\u2019u"
    ],
    "wof:name":"Oech'u",
    "wof:placetype":"locality"
},
  "geometry": {"coordinates":[128.47808000000001,35.15746],"type":"Point"}
}