{
  "type": "Feature",
  "properties": {
    "gn:admin1_code":"13.0",
    "gn:asciiname":"Wondanghyeon",
    "gn:country_code":"KR",
    "gn:dem":57,
    "gn:feature_class":"P",
    "gn:feature_code":"PPL",
    "gn:name":"Wondanghyeon",
    "gn:population":0,
    "gn:timezone":"Asia/Seoul",
    "iso:country":"KR",
    "name:und_x_variant":[
        "\uc6d0\ub2f9\ud604",
        "Wondanghyeon",
        "W\u014fndanghy\u014fn"
    ],
    "wof:name":"Wondanghyeon",
    "wof:placetype":"locality"
},
  "geometry": {"coordinates":[127.03343,37.06863],"type":"Point"}
}