{
  "type": "Feature",
  "properties": {
    "gn:admin1_code":"16.0",
    "gn:asciiname":"Togyang-ni",
    "gn:cc2":"KR",
    "gn:country_code":"KR",
    "gn:dem":20,
    "gn:feature_class":"P",
    "gn:feature_code":"PPL",
    "gn:name":"T\u014fgyang-ni",
    "gn:population":0,
    "gn:timezone":"Asia/Seoul",
    "iso:country":"KR",
    "name:und_x_variant":[
        "Tokuy\u014d-ri",
        "T\u014fngyang-ni",
        "T\u014fgyang-ni"
    ],
    "wof:name":"Togyang-ni",
    "wof:placetype":"locality"
},
  "geometry": {"coordinates":[127.63443999999998,34.79028],"type":"Point"}
}