{
  "type": "Feature",
  "properties": {
    "gn:admin1_code":"6.0",
    "gn:asciiname":"Odu-ch'on",
    "gn:country_code":"KR",
    "gn:dem":811,
    "gn:feature_class":"P",
    "gn:feature_code":"PPL",
    "gn:name":"Odu-ch\u2019on",
    "gn:population":0,
    "gn:timezone":"Asia/Seoul",
    "iso:country":"KR",
    "name:kor_x_preferred":[
        "\uc624\ub450\ucd0c"
    ],
    "name:kor_x_variant":[
        "Odu-ch\u2019on"
    ],
    "wof:name":"Odu-ch'on",
    "wof:placetype":"locality"
},
  "geometry": {"coordinates":[128.8903,37.3234],"type":"Point"}
}