{
  "type": "Feature",
  "properties": {
    "gn:admin1_code":"17.0",
    "gn:asciiname":"Kumam-ni",
    "gn:country_code":"KR",
    "gn:dem":50,
    "gn:feature_class":"P",
    "gn:feature_code":"PPL",
    "gn:name":"K\u016dmam-ni",
    "gn:population":0,
    "gn:timezone":"Asia/Seoul",
    "iso:country":"KR",
    "name:und_x_variant":[
        "\uae08\uc554\ub9ac",
        "K\u016dmam-ni"
    ],
    "wof:name":"Kumam-ni",
    "wof:placetype":"locality"
},
  "geometry": {"coordinates":[126.6448,36.9255],"type":"Point"}
}