{
  "type": "Feature",
  "properties": {
    "gn:admin1_code":"1.0",
    "gn:asciiname":"Ch'onsong-dong",
    "gn:country_code":"KR",
    "gn:dem":223,
    "gn:feature_class":"P",
    "gn:feature_code":"PPL",
    "gn:name":"Ch\u2019\u014fns\u014fng-dong",
    "gn:population":0,
    "gn:timezone":"Asia/Seoul",
    "iso:country":"KR",
    "wof:name":"Ch'onsong-dong",
    "wof:placetype":"locality"
},
  "geometry": {"coordinates":[126.69889000000001,33.48556],"type":"Point"}
}