{
  "type": "Feature",
  "properties": {
    "gn:admin1_code":"17.0",
    "gn:asciiname":"Taegi-ri",
    "gn:country_code":"KR",
    "gn:dem":21,
    "gn:feature_class":"P",
    "gn:feature_code":"PPL",
    "gn:name":"Taegi-ri",
    "gn:population":0,
    "gn:timezone":"Asia/Seoul",
    "iso:country":"KR",
    "name:und_x_variant":[
        "\ud070\ud130\uace8",
        "K\u2019\u016dnt\u2019\u014f-gol"
    ],
    "wof:name":"Taegi-ri",
    "wof:placetype":"locality"
},
  "geometry": {"coordinates":[126.23009999999999,36.8038],"type":"Point"}
}