{
  "type": "Feature",
  "properties": {
    "gn:admin1_code":"14.0",
    "gn:asciiname":"Namha",
    "gn:country_code":"KR",
    "gn:dem":54,
    "gn:feature_class":"P",
    "gn:feature_code":"PPL",
    "gn:name":"Namha",
    "gn:population":0,
    "gn:timezone":"Asia/Seoul",
    "iso:country":"KR",
    "name:kor_x_preferred":[
        "\ub0a8\ud558"
    ],
    "name:und_x_variant":[
        "Namha-dong",
        "Namha"
    ],
    "wof:name":"Namha",
    "wof:placetype":"locality"
},
  "geometry": {"coordinates":[128.77303000000001,35.88588],"type":"Point"}
}