{
  "type": "Feature",
  "properties": {
    "gn:admin1_code":"6.0",
    "gn:asciiname":"Pan'gok-tong",
    "gn:country_code":"KR",
    "gn:dem":179,
    "gn:feature_class":"P",
    "gn:feature_code":"PPLL",
    "gn:name":"Pan\u2019gok-tong",
    "gn:population":0,
    "gn:timezone":"Asia/Seoul",
    "iso:country":"KR",
    "name:eng_x_preferred":[
        "Pan'gok"
    ],
    "name:eng_x_variant":[
        "Pan'gok-tong"
    ],
    "name:kor_x_preferred":[
        "\ubc18\uace1\ub3d9"
    ],
    "name:kor_x_variant":[
        "Pan\u2019gok-tong"
    ],
    "wof:name":"Pan'gok",
    "wof:placetype":"locality"
},
  "geometry": {"coordinates":[127.98777,37.32415],"type":"Point"}
}