{
  "type": "Feature",
  "properties": {
    "gn:admin1_code":"5.0",
    "gn:asciiname":"Munam",
    "gn:country_code":"KR",
    "gn:dem":170,
    "gn:feature_class":"P",
    "gn:feature_code":"PPL",
    "gn:name":"Munam",
    "gn:population":0,
    "gn:timezone":"Asia/Seoul",
    "iso:country":"KR",
    "name:und_x_variant":[
        "\ubb38\uc554",
        "Munam"
    ],
    "wof:name":"Munam",
    "wof:placetype":"locality"
},
  "geometry": {"coordinates":[127.68640000000001,36.4973],"type":"Point"}
}