{
  "type": "Feature",
  "properties": {
    "gn:admin1_code":"16.0",
    "gn:asciiname":"Naedong-ni",
    "gn:cc2":"KR",
    "gn:country_code":"KR",
    "gn:dem":7,
    "gn:feature_class":"P",
    "gn:feature_code":"PPL",
    "gn:name":"Naedong-ni",
    "gn:population":0,
    "gn:timezone":"Asia/Seoul",
    "iso:country":"KR",
    "name:eng_x_preferred":[
        "Naedong"
    ],
    "name:eng_x_variant":[
        "Naedong-ni"
    ],
    "name:und_x_variant":[
        "W\u014fnnaedong",
        "Naedong-ni"
    ],
    "wof:name":"Naedong",
    "wof:placetype":"locality"
},
  "geometry": {"coordinates":[126.60917000000001,34.86639],"type":"Point"}
}