{
  "type": "Feature",
  "properties": {
    "gn:admin1_code":"6.0",
    "gn:asciiname":"Mach'i-gol",
    "gn:country_code":"KR",
    "gn:dem":507,
    "gn:feature_class":"P",
    "gn:feature_code":"PPL",
    "gn:name":"Mach\u2019i-gol",
    "gn:population":0,
    "gn:timezone":"Asia/Seoul",
    "iso:country":"KR",
    "name:kor_x_preferred":[
        "\ub9c8\uce58\uace8"
    ],
    "name:kor_x_variant":[
        "Mach\u2019i-gol"
    ],
    "wof:name":"Mach'i-gol",
    "wof:placetype":"locality"
},
  "geometry": {"coordinates":[128.1232,37.3368],"type":"Point"}
}