{
  "type": "Feature",
  "properties": {
    "gn:admin1_code":"14.0",
    "gn:asciiname":"Kugong-ni",
    "gn:country_code":"KR",
    "gn:dem":63,
    "gn:feature_class":"P",
    "gn:feature_code":"PPL",
    "gn:name":"Kugong-ni",
    "gn:population":0,
    "gn:timezone":"Asia/Seoul",
    "iso:country":"KR",
    "name:und_x_variant":[
        "\uad6c\uace1\ub9ac",
        "Kugong-ni"
    ],
    "wof:name":"Kugong-ni",
    "wof:placetype":"locality"
},
  "geometry": {"coordinates":[128.20813999999999,35.67752],"type":"Point"}
}