{
  "type": "Feature",
  "properties": {
    "gn:admin1_code":"6.0",
    "gn:asciiname":"Munam",
    "gn:country_code":"KR",
    "gn:dem":8,
    "gn:feature_class":"P",
    "gn:feature_code":"PPL",
    "gn:name":"Munam",
    "gn:population":0,
    "gn:timezone":"Asia/Seoul",
    "iso:country":"KR",
    "name:und_x_variant":[
        "\ubb38\uc554",
        "Munam-dong"
    ],
    "wof:name":"Munam",
    "wof:placetype":"locality"
},
  "geometry": {"coordinates":[129.28693999999999,37.30889000000001],"type":"Point"}
}