{
  "type": "Feature",
  "properties": {
    "gn:admin1_code":"6.0",
    "gn:asciiname":"Changsu-gol",
    "gn:cc2":"KR",
    "gn:country_code":"KR",
    "gn:dem":717,
    "gn:feature_class":"P",
    "gn:feature_code":"PPL",
    "gn:name":"Changsu-gol",
    "gn:population":0,
    "gn:timezone":"Asia/Seoul",
    "iso:country":"KR",
    "name:kor_x_preferred":[
        "\uc7a5\uc218\uace8"
    ],
    "name:und_x_variant":[
        "Changsu-dong",
        "Changsu-kol",
        "Changsu-gol"
    ],
    "wof:name":"Changsu-gol",
    "wof:placetype":"locality"
},
  "geometry": {"coordinates":[128.47471999999999,37.66306],"type":"Point"}
}