{
  "type": "Feature",
  "properties": {
    "gn:admin1_code":"17.0",
    "gn:asciiname":"Gaengchi",
    "gn:country_code":"KR",
    "gn:dem":54,
    "gn:feature_class":"P",
    "gn:feature_code":"PPL",
    "gn:name":"Gaengchi",
    "gn:population":0,
    "gn:timezone":"Asia/Seoul",
    "iso:country":"KR",
    "name:kor_x_preferred":[
        "\uac31\uce58"
    ],
    "wof:name":"Gaengchi",
    "wof:placetype":"locality"
},
  "geometry": {"coordinates":[126.97081,36.74409],"type":"Point"}
}