{
  "type": "Feature",
  "properties": {
    "iso:country":"KR",
    "name:kor_x_preferred":[
        "\ud654\uc218\ub3d9"
    ],
    "name:und_x_variant":[
        "Hwasu-ri"
    ],
    "qs:gn_adm0_cc":"KR",
    "qs:gn_fcode":"PPL",
    "qs:gn_local":1843564,
    "qs:gn_namadm1":"13",
    "qs:gn_name":"Hwasu-dong",
    "qs:local_max":2394,
    "qs:local_sum":10431,
    "qs:localhoods":47,
    "qs:name":"\ud654\uc218\ub3d9",
    "qs:name_adm0":"\ud55c\uad6d",
    "qs:name_adm1":"\uc778\ucc9c",
    "qs:name_adm2":"\ub3d9\uad6c",
    "qs:name_lau":"\ud654\uc2182\ub3d9",
    "qs:name_local":"\uc778\ucc9c",
    "qs:photo_max":50,
    "qs:photo_sum":185,
    "qs:placetype":"Suburb",
    "qs:quad_count":14,
    "qs:woe_adm0":23424868,
    "qs:woe_adm1":20069922,
    "qs:woe_adm2":28289150,
    "qs:woe_lau":28806313,
    "qs:woe_local":1132496,
    "qs:woe_ver":"7.10.0",
    "wof:lang":[
        "kor"
    ],
    "wof:name":"\ud654\uc218\ub3d9",
    "wof:placetype":"neighbourhood"
},
  "geometry": {"coordinates":[126.630043,37.483776],"type":"Point"}
}