{
  "type": "Feature",
  "properties": {
    "gn:admin1_code":"14.0",
    "gn:asciiname":"Danggol",
    "gn:country_code":"KR",
    "gn:dem":106,
    "gn:feature_class":"P",
    "gn:feature_code":"PPL",
    "gn:name":"Danggol",
    "gn:population":0,
    "gn:timezone":"Asia/Seoul",
    "iso:country":"KR",
    "name:kor_x_preferred":[
        "\ub2f9\uace8"
    ],
    "wof:name":"Danggol",
    "wof:placetype":"locality"
},
  "geometry": {"coordinates":[128.66678999999999,36.54037],"type":"Point"}
}