{
  "type": "Feature",
  "properties": {
    "gn:admin1_code":"14.0",
    "gn:asciiname":"Haan",
    "gn:country_code":"KR",
    "gn:dem":61,
    "gn:feature_class":"P",
    "gn:feature_code":"PPL",
    "gn:name":"Haan",
    "gn:population":0,
    "gn:timezone":"Asia/Seoul",
    "iso:country":"KR",
    "name:bel_x_preferred":[
        "\u0413\u0430\u043d"
    ],
    "name:ceb_x_preferred":[
        "Haan"
    ],
    "name:deu_x_preferred":[
        "Haan"
    ],
    "name:epo_x_preferred":[
        "Haan"
    ],
    "name:eus_x_preferred":[
        "Haan"
    ],
    "name:fra_x_preferred":[
        "Haan"
    ],
    "name:hun_x_preferred":[
        "Haan"
    ],
    "name:ita_x_preferred":[
        "Haan"
    ],
    "name:kaz_x_preferred":[
        "\u0425\u0430\u043d"
    ],
    "name:ksh_x_preferred":[
        "Haan"
    ],
    "name:lim_x_preferred":[
        "Haan"
    ],
    "name:msa_x_preferred":[
        "Haan"
    ],
    "name:nld_x_preferred":[
        "Haan"
    ],
    "name:pol_x_preferred":[
        "Haan"
    ],
    "name:por_x_preferred":[
        "Haan"
    ],
    "name:ron_x_preferred":[
        "Haan"
    ],
    "name:rus_x_preferred":[
        "\u0425\u0430\u043d"
    ],
    "name:sco_x_preferred":[
        "Haan"
    ],
    "name:spa_x_preferred":[
        "Haan"
    ],
    "name:srp_x_preferred":[
        "\u0425\u0430\u043d"
    ],
    "name:swe_x_preferred":[
        "Haan"
    ],
    "name:tur_x_preferred":[
        "Haan"
    ],
    "name:ukr_x_preferred":[
        "\u0413\u0430\u043d"
    ],
    "name:vol_x_preferred":[
        "Haan"
    ],
    "name:war_x_preferred":[
        "Haan"
    ],
    "wof:name":"Haan",
    "wof:placetype":"locality"
},
  "geometry": {"coordinates":[128.42167000000001,36.40444],"type":"Point"}
}