{
  "type": "Feature",
  "properties": {
    "gn:admin1_code":"12.0",
    "gn:asciiname":"Keunmal",
    "gn:country_code":"KR",
    "gn:dem":8,
    "gn:feature_class":"P",
    "gn:feature_code":"PPL",
    "gn:name":"Keunmal",
    "gn:population":0,
    "gn:timezone":"Asia/Seoul",
    "iso:country":"KR",
    "name:und_x_variant":[
        "\ud070\ub9d0",
        "Keunmal",
        "Tae-ch\u2019on",
        "K\u2019unmal"
    ],
    "wof:name":"Keunmal",
    "wof:placetype":"locality"
},
  "geometry": {"coordinates":[125.94667,37.07889],"type":"Point"}
}