{
  "type": "Feature",
  "properties": {
    "gn:admin1_code":"14.0",
    "gn:asciiname":"Usseom",
    "gn:country_code":"KR",
    "gn:dem":68,
    "gn:feature_class":"P",
    "gn:feature_code":"PPL",
    "gn:name":"Usseom",
    "gn:population":0,
    "gn:timezone":"Asia/Seoul",
    "iso:country":"KR",
    "name:kor_x_preferred":[
        "\uc6c3\uc12c"
    ],
    "wof:name":"Usseom",
    "wof:placetype":"locality"
},
  "geometry": {"coordinates":[128.47701999999998,36.53552],"type":"Point"}
}