{
  "type": "Feature",
  "properties": {
    "gn:admin1_code":"16.0",
    "gn:admin2_code":"Haenam-gun",
    "gn:asciiname":"Muhak",
    "gn:country_code":"KR",
    "gn:dem":18,
    "gn:feature_class":"P",
    "gn:feature_code":"PPL",
    "gn:name":"Muhak",
    "gn:population":0,
    "gn:timezone":"Asia/Seoul",
    "iso:country":"KR",
    "wof:name":"Muhak",
    "wof:placetype":"locality"
},
  "geometry": {"coordinates":[126.47638999999999,34.49333],"type":"Point"}
}