{
  "type": "Feature",
  "properties": {
    "gn:admin1_code":"17.0",
    "gn:asciiname":"Sansu-gol",
    "gn:country_code":"KR",
    "gn:dem":107,
    "gn:feature_class":"P",
    "gn:feature_code":"PPL",
    "gn:name":"Sansu-gol",
    "gn:population":0,
    "gn:timezone":"Asia/Seoul",
    "iso:country":"KR",
    "name:und_x_variant":[
        "\uc0b0\uc218\uace8",
        "Sansu-gol"
    ],
    "wof:name":"Sansu-gol",
    "wof:placetype":"locality"
},
  "geometry": {"coordinates":[126.771,36.4048],"type":"Point"}
}