{
  "type": "Feature",
  "properties": {
    "gn:admin1_code":"14.0",
    "gn:asciiname":"Yongdang",
    "gn:cc2":"KR",
    "gn:country_code":"KR",
    "gn:dem":58,
    "gn:feature_class":"P",
    "gn:feature_code":"PPL",
    "gn:name":"Yongdang",
    "gn:population":0,
    "gn:timezone":"Asia/Seoul",
    "iso:country":"KR",
    "name:und_x_variant":[
        "Hao-ri",
        "Yongdang"
    ],
    "wof:name":"Yongdang",
    "wof:placetype":"locality"
},
  "geometry": {"coordinates":[129.26667,35.96667],"type":"Point"}
}