{
  "type": "Feature",
  "properties": {
    "gn:admin1_code":"16.0",
    "gn:asciiname":"Changpyeong",
    "gn:country_code":"KR",
    "gn:dem":73,
    "gn:feature_class":"P",
    "gn:feature_code":"PPLA3",
    "gn:name":"Changpyeong",
    "gn:population":0,
    "gn:timezone":"Asia/Seoul",
    "iso:country":"KR",
    "name:kor_x_preferred":[
        "\ucc3d\ud3c9"
    ],
    "name:und_x_variant":[
        "Sh\u014dhei",
        "Ch\u2019angp\u2019y\u014fng",
        "Ch\u2019angp\u2019y\u014fng-ni",
        "Changpyeong"
    ],
    "wof:name":"Changpyeong",
    "wof:placetype":"locality"
},
  "geometry": {"coordinates":[127.01792,35.23904],"type":"Point"}
}