{
  "type": "Feature",
  "properties": {
    "gn:admin1_code":"3.0",
    "gn:asciiname":"Sokchong-ni",
    "gn:country_code":"KR",
    "gn:dem":114,
    "gn:feature_class":"P",
    "gn:feature_code":"PPL",
    "gn:name":"S\u014fkch\u014fng-ni",
    "gn:population":0,
    "gn:timezone":"Asia/Seoul",
    "iso:country":"KR",
    "name:eng_x_preferred":[
        "Sokchong"
    ],
    "name:eng_x_variant":[
        "Sokchong-ni"
    ],
    "wof:name":"Sokchong",
    "wof:placetype":"locality"
},
  "geometry": {"coordinates":[126.73944,35.42722],"type":"Point"}
}