{
  "type": "Feature",
  "properties": {
    "gn:admin1_code":"20.0",
    "gn:asciiname":"Tungdae",
    "gn:country_code":"KR",
    "gn:dem":56,
    "gn:feature_class":"P",
    "gn:feature_code":"PPL",
    "gn:name":"T\u016dngdae",
    "gn:population":0,
    "gn:timezone":"Asia/Seoul",
    "iso:country":"KR",
    "name:und_x_variant":[
        "T\u016dngdae-ri",
        "T\u016dngdae-dong",
        "\ub4f1\ub300",
        "T\u016dngdae"
    ],
    "wof:name":"Tungdae",
    "wof:placetype":"locality"
},
  "geometry": {"coordinates":[128.31278999999998,35.43238],"type":"Point"}
}