{
  "type": "Feature",
  "properties": {
    "gn:admin1_code":"14.0",
    "gn:asciiname":"Deokcheon",
    "gn:country_code":"KR",
    "gn:dem":48,
    "gn:feature_class":"P",
    "gn:feature_code":"PPL",
    "gn:name":"Deokcheon",
    "gn:population":0,
    "gn:timezone":"Asia/Seoul",
    "iso:country":"KR",
    "name:und_x_variant":[
        "\ub355\ucc9c",
        "T\u014fkch\u2019\u014fn",
        "Doekcheon",
        "Deokcheon"
    ],
    "wof:name":"Deokcheon",
    "wof:placetype":"locality"
},
  "geometry": {"coordinates":[128.48599999999999,35.9371],"type":"Point"}
}