{
  "type": "Feature",
  "properties": {
    "gn:admin1_code":"13.0",
    "gn:admin2_code":"Ans\u014fng-si",
    "gn:asciiname":"Wolhyang-ri",
    "gn:country_code":"KR",
    "gn:dem":103,
    "gn:feature_class":"P",
    "gn:feature_code":"PPLL",
    "gn:name":"Wolhyang-ri",
    "gn:population":0,
    "gn:timezone":"Asia/Seoul",
    "iso:country":"KR",
    "name:kor_x_preferred":[
        "\uc6d4\ud5a5\ub9ac"
    ],
    "name:kor_x_variant":[
        "W\u014frhyang-ni"
    ],
    "wof:name":"Wolhyang-ri",
    "wof:placetype":"locality"
},
  "geometry": {"coordinates":[127.28389,37.09694],"type":"Point"}
}