{
  "type": "Feature",
  "properties": {
    "gn:admin1_code":"17.0",
    "gn:asciiname":"Jeumgol",
    "gn:country_code":"KR",
    "gn:dem":125,
    "gn:feature_class":"P",
    "gn:feature_code":"PPL",
    "gn:name":"Jeumgol",
    "gn:population":0,
    "gn:timezone":"Asia/Seoul",
    "iso:country":"KR",
    "name:kor_x_preferred":[
        "\uc998\uace8"
    ],
    "wof:name":"Jeumgol",
    "wof:placetype":"locality"
},
  "geometry": {"coordinates":[127.11100999999999,36.68284],"type":"Point"}
}