{
  "type": "Feature",
  "properties": {
    "gn:admin1_code":"6.0",
    "gn:asciiname":"Chose",
    "gn:country_code":"KR",
    "gn:dem":226,
    "gn:feature_class":"P",
    "gn:feature_code":"PPL",
    "gn:name":"Ch\u014fse",
    "gn:population":0,
    "gn:timezone":"Asia/Seoul",
    "iso:country":"KR",
    "name:kor_x_preferred":[
        "\uc800\uc138"
    ],
    "name:kor_x_variant":[
        "Ch\u014fse"
    ],
    "wof:name":"Chose",
    "wof:placetype":"locality"
},
  "geometry": {"coordinates":[128.4957,37.1906],"type":"Point"}
}