{
  "type": "Feature",
  "properties": {
    "gn:admin1_code":"16.0",
    "gn:asciiname":"Mui",
    "gn:country_code":"KR",
    "gn:dem":51,
    "gn:feature_class":"P",
    "gn:feature_code":"PPL",
    "gn:name":"Mui",
    "gn:population":0,
    "gn:timezone":"Asia/Seoul",
    "iso:country":"KR",
    "name:und_x_variant":[
        "Bui-ri",
        "\ubb34\uc774",
        "Mui-ri",
        "Mui"
    ],
    "wof:name":"Mui",
    "wof:placetype":"locality"
},
  "geometry": {"coordinates":[126.65971999999999,34.63861],"type":"Point"}
}