{
  "type": "Feature",
  "properties": {
    "gn:admin1_code":"6.0",
    "gn:asciiname":"Samgeori",
    "gn:country_code":"KR",
    "gn:dem":381,
    "gn:feature_class":"P",
    "gn:feature_code":"PPL",
    "gn:name":"Samgeori",
    "gn:population":0,
    "gn:timezone":"Asia/Seoul",
    "iso:country":"KR",
    "name:und_x_variant":[
        "\uc0bc\uac70\ub9ac",
        "Samg\u014fri",
        "Samgeori"
    ],
    "wof:name":"Samgeori",
    "wof:placetype":"locality"
},
  "geometry": {"coordinates":[127.52467,38.10134],"type":"Point"}
}