{
  "type": "Feature",
  "properties": {
    "gn:admin1_code":"13.0",
    "gn:asciiname":"Seoneomni",
    "gn:country_code":"KR",
    "gn:dem":72,
    "gn:feature_class":"P",
    "gn:feature_code":"PPL",
    "gn:name":"Seoneomni",
    "gn:population":0,
    "gn:timezone":"Asia/Seoul",
    "iso:country":"KR",
    "name:kor_x_preferred":[
        "\uc120\uc5c5\ub9ac"
    ],
    "name:und_x_variant":[
        "\uc120\uc5c5\ub3d9",
        "S\u014fn\u014fp-tong",
        "Seoneomni"
    ],
    "wof:name":"Seoneomni",
    "wof:placetype":"locality"
},
  "geometry": {"coordinates":[127.04009000000001,37.88754],"type":"Point"}
}