{
  "type": "Feature",
  "properties": {
    "gn:admin1_code":"16.0",
    "gn:asciiname":"Keunjaegol",
    "gn:country_code":"KR",
    "gn:dem":210,
    "gn:feature_class":"P",
    "gn:feature_code":"PPL",
    "gn:name":"Keunjaegol",
    "gn:population":0,
    "gn:timezone":"Asia/Seoul",
    "iso:country":"KR",
    "name:kor_x_preferred":[
        "\ud070\uc7ac\uace8"
    ],
    "name:kor_x_variant":[
        "K\u2019\u016dnjaegol"
    ],
    "wof:name":"Keunjaegol",
    "wof:placetype":"locality"
},
  "geometry": {"coordinates":[127.04543,34.75747],"type":"Point"}
}