{
  "type": "Feature",
  "properties": {
    "gn:admin1_code":"17.0",
    "gn:asciiname":"Omang-dong",
    "gn:country_code":"KR",
    "gn:dem":12,
    "gn:feature_class":"P",
    "gn:feature_code":"PPL",
    "gn:name":"\u014emang-dong",
    "gn:population":0,
    "gn:timezone":"Asia/Seoul",
    "iso:country":"KR",
    "name:und_x_variant":[
        "\uc5b4\ub9dd\ub3d9",
        "\u014emang-dong"
    ],
    "wof:name":"Omang-dong",
    "wof:placetype":"locality"
},
  "geometry": {"coordinates":[126.4836,36.5069],"type":"Point"}
}