{
  "type": "Feature",
  "properties": {
    "gn:admin1_code":"20.0",
    "gn:asciiname":"Chongjang-ni",
    "gn:country_code":"KR",
    "gn:dem":208,
    "gn:feature_class":"P",
    "gn:feature_code":"PPL",
    "gn:name":"Ch\u014fngjang-ni",
    "gn:population":0,
    "gn:timezone":"Asia/Seoul",
    "iso:country":"KR",
    "name:und_x_variant":[
        "\uc815\uc7a5\ub9ac",
        "Ch\u014fngjang-ni"
    ],
    "wof:name":"Chongjang-ni",
    "wof:placetype":"locality"
},
  "geometry": {"coordinates":[127.91703,35.6711],"type":"Point"}
}