{
  "type": "Feature",
  "properties": {
    "gn:admin1_code":"16.0",
    "gn:asciiname":"Bukchang",
    "gn:country_code":"KR",
    "gn:dem":7,
    "gn:feature_class":"P",
    "gn:feature_code":"PPL",
    "gn:name":"Bukchang",
    "gn:population":0,
    "gn:timezone":"Asia/Seoul",
    "iso:country":"KR",
    "name:kor_x_preferred":[
        "\ubcf5\ucc3d"
    ],
    "name:kor_x_variant":[
        "Pokch\u2019ang",
        "\ubd81\ucc3d"
    ],
    "wof:name":"Bukchang",
    "wof:placetype":"locality"
},
  "geometry": {"coordinates":[126.61292,34.62885],"type":"Point"}
}