{
  "type": "Feature",
  "properties": {
    "gn:admin1_code":"3.0",
    "gn:asciiname":"Haeryong-ni",
    "gn:cc2":"KR",
    "gn:country_code":"KR",
    "gn:dem":17,
    "gn:feature_class":"P",
    "gn:feature_code":"PPL",
    "gn:name":"Haeryong-ni",
    "gn:population":0,
    "gn:timezone":"Asia/Seoul",
    "iso:country":"KR",
    "name:und_x_variant":[
        "Hoeryong-ni",
        "Haeryong-ni"
    ],
    "wof:name":"Haeryong-ni",
    "wof:placetype":"locality"
},
  "geometry": {"coordinates":[126.53556,35.31639000000001],"type":"Point"}
}