{
  "type": "Feature",
  "properties": {
    "gn:admin1_code":"6.0",
    "gn:asciiname":"Deotgol",
    "gn:country_code":"KR",
    "gn:dem":440,
    "gn:feature_class":"P",
    "gn:feature_code":"PPL",
    "gn:name":"Deotgol",
    "gn:population":0,
    "gn:timezone":"Asia/Seoul",
    "iso:country":"KR",
    "name:kor_x_preferred":[
        "\ub367\uace8"
    ],
    "wof:name":"Deotgol",
    "wof:placetype":"locality"
},
  "geometry": {"coordinates":[127.99303999999999,37.92126],"type":"Point"}
}