{
  "type": "Feature",
  "properties": {
    "gn:admin1_code":"17.0",
    "gn:asciiname":"Naeho-ri",
    "gn:country_code":"KR",
    "gn:dem":18,
    "gn:feature_class":"P",
    "gn:feature_code":"PPL",
    "gn:name":"Naeho-ri",
    "gn:population":0,
    "gn:timezone":"Asia/Seoul",
    "iso:country":"KR",
    "name:und_x_variant":[
        "\ubc94\uba38\ub9ac",
        "P\u014fmm\u014f-ri"
    ],
    "wof:name":"Naeho-ri",
    "wof:placetype":"locality"
},
  "geometry": {"coordinates":[126.33369999999999,36.8598],"type":"Point"}
}