{
  "type": "Feature",
  "properties": {
    "gn:admin1_code":"13.0",
    "gn:asciiname":"Seonjang-gol",
    "gn:country_code":"KR",
    "gn:dem":134,
    "gn:feature_class":"P",
    "gn:feature_code":"PPL",
    "gn:name":"Seonjang-gol",
    "gn:population":0,
    "gn:timezone":"Asia/Seoul",
    "iso:country":"KR",
    "name:und_x_variant":[
        "\uc120\uc7a5\uace8",
        "Seonjang-gol",
        "S\u014fnjang-gol"
    ],
    "wof:name":"Seonjang-gol",
    "wof:placetype":"locality"
},
  "geometry": {"coordinates":[127.32193999999998,37.39083],"type":"Point"}
}