{
  "type": "Feature",
  "properties": {
    "gn:admin1_code":"5.0",
    "gn:asciiname":"Chungbong",
    "gn:country_code":"KR",
    "gn:dem":251,
    "gn:feature_class":"P",
    "gn:feature_code":"PPL",
    "gn:name":"Chungbong",
    "gn:population":0,
    "gn:timezone":"Asia/Seoul",
    "iso:country":"KR",
    "name:kor_x_preferred":[
        "\uc911\ubd09"
    ],
    "wof:name":"Chungbong",
    "wof:placetype":"locality"
},
  "geometry": {"coordinates":[127.9268,37.1458],"type":"Point"}
}