{
  "type": "Feature",
  "properties": {
    "gn:admin1_code":"5.0",
    "gn:asciiname":"Midang-ni",
    "gn:country_code":"KR",
    "gn:dem":302,
    "gn:feature_class":"P",
    "gn:feature_code":"PPLL",
    "gn:name":"Midang-ni",
    "gn:population":0,
    "gn:timezone":"Asia/Seoul",
    "iso:country":"KR",
    "name:kor_x_preferred":[
        "\ubbf8\ub2f9\ub9ac"
    ],
    "wof:name":"Midang-ni",
    "wof:placetype":"locality"
},
  "geometry": {"coordinates":[128.15937,37.16164000000001],"type":"Point"}
}