{
  "type": "Feature",
  "properties": {
    "gn:admin1_code":"14.0",
    "gn:asciiname":"Nurha",
    "gn:country_code":"KR",
    "gn:dem":175,
    "gn:feature_class":"P",
    "gn:feature_code":"PPL",
    "gn:name":"Nurha",
    "gn:population":0,
    "gn:timezone":"Asia/Seoul",
    "iso:country":"KR",
    "name:und_x_variant":[
        "\ub20c\ud558",
        "Nurha"
    ],
    "wof:name":"Nurha",
    "wof:placetype":"locality"
},
  "geometry": {"coordinates":[127.876,36.3985],"type":"Point"}
}