{
  "type": "Feature",
  "properties": {
    "gn:admin1_code":"13.0",
    "gn:asciiname":"Sagimak",
    "gn:country_code":"KR",
    "gn:dem":95,
    "gn:feature_class":"P",
    "gn:feature_code":"PPL",
    "gn:name":"Sagimak",
    "gn:population":0,
    "gn:timezone":"Asia/Seoul",
    "iso:country":"KR",
    "name:und_x_variant":[
        "\uc0ac\uae30\ub9c9",
        "Sagimak"
    ],
    "wof:name":"Sagimak",
    "wof:placetype":"locality"
},
  "geometry": {"coordinates":[127.17278,37.08722],"type":"Point"}
}