{
  "type": "Feature",
  "properties": {
    "gn:admin1_code":"14.0",
    "gn:asciiname":"Chondae",
    "gn:country_code":"KR",
    "gn:dem":240,
    "gn:feature_class":"P",
    "gn:feature_code":"PPL",
    "gn:name":"Ch\u014fndae",
    "gn:population":0,
    "gn:timezone":"Asia/Seoul",
    "iso:country":"KR",
    "name:und_x_variant":[
        "\uc804\ub300",
        "Ch\u014fndae"
    ],
    "wof:name":"Chondae",
    "wof:placetype":"locality"
},
  "geometry": {"coordinates":[128.83160000000001,36.379],"type":"Point"}
}