{
  "type": "Feature",
  "properties": {
    "gn:admin1_code":"5.0",
    "gn:asciiname":"Twittul",
    "gn:country_code":"KR",
    "gn:dem":278,
    "gn:feature_class":"P",
    "gn:feature_code":"PPL",
    "gn:name":"Twitt\u016dl",
    "gn:population":0,
    "gn:timezone":"Asia/Seoul",
    "iso:country":"KR",
    "name:kor_x_preferred":[
        "\ub4a4\ub730"
    ],
    "name:kor_x_variant":[
        "Twitt\u016dl"
    ],
    "wof:name":"Twittul",
    "wof:placetype":"locality"
},
  "geometry": {"coordinates":[128.1962,37.1554],"type":"Point"}
}