{
  "type": "Feature",
  "properties": {
    "gn:admin1_code":"6.0",
    "gn:asciiname":"Mul-gol",
    "gn:country_code":"KR",
    "gn:dem":214,
    "gn:feature_class":"P",
    "gn:feature_code":"PPL",
    "gn:name":"Mul-gol",
    "gn:population":0,
    "gn:timezone":"Asia/Seoul",
    "iso:country":"KR",
    "name:kor_x_preferred":[
        "\ubb3c\uace8"
    ],
    "wof:name":"Mul-gol",
    "wof:placetype":"locality"
},
  "geometry": {"coordinates":[127.90179999999999,37.4805],"type":"Point"}
}