{
  "type": "Feature",
  "properties": {
    "gn:admin1_code":"6.0",
    "gn:asciiname":"Uirimgil",
    "gn:country_code":"KR",
    "gn:dem":486,
    "gn:feature_class":"P",
    "gn:feature_code":"PPL",
    "gn:name":"\u016cirimgil",
    "gn:population":0,
    "gn:timezone":"Asia/Seoul",
    "iso:country":"KR",
    "wof:name":"Uirimgil",
    "wof:placetype":"locality"
},
  "geometry": {"coordinates":[128.65000000000001,37.21667],"type":"Point"}
}