{
  "type": "Feature",
  "properties": {
    "gn:admin1_code":"13.0",
    "gn:asciiname":"Beolteo",
    "gn:country_code":"KR",
    "gn:dem":142,
    "gn:feature_class":"P",
    "gn:feature_code":"PPL",
    "gn:name":"Beolteo",
    "gn:population":0,
    "gn:timezone":"Asia/Seoul",
    "iso:country":"KR",
    "name:kor_x_preferred":[
        "\ubc8c\ud130"
    ],
    "name:kor_x_variant":[
        "P\u014flt\u2019\u014f"
    ],
    "wof:name":"Beolteo",
    "wof:placetype":"locality"
},
  "geometry": {"coordinates":[127.59141,37.52116],"type":"Point"}
}