{
  "type": "Feature",
  "properties": {
    "gn:admin1_code":"6.0",
    "gn:asciiname":"Gajakgol",
    "gn:country_code":"KR",
    "gn:dem":179,
    "gn:feature_class":"P",
    "gn:feature_code":"PPL",
    "gn:name":"Gajakgol",
    "gn:population":0,
    "gn:timezone":"Asia/Seoul",
    "iso:country":"KR",
    "name:kor_x_preferred":[
        "\uac00\uc7ac\uace8"
    ],
    "name:kor_x_variant":[
        "\uac00\uc791\uace8"
    ],
    "name:und_x_variant":[
        "Kajae-gol",
        "Gajakgol"
    ],
    "wof:name":"Gajakgol",
    "wof:placetype":"locality"
},
  "geometry": {"coordinates":[127.77460000000001,37.6229],"type":"Point"}
}