{
  "type": "Feature",
  "properties": {
    "gn:admin1_code":"16.0",
    "gn:asciiname":"Saetjeom",
    "gn:country_code":"KR",
    "gn:dem":276,
    "gn:feature_class":"P",
    "gn:feature_code":"PPL",
    "gn:name":"Saetjeom",
    "gn:population":0,
    "gn:timezone":"Asia/Seoul",
    "iso:country":"KR",
    "name:kor_x_preferred":[
        "\uc0db\uc810"
    ],
    "name:kor_x_variant":[
        "Saetch\u014fm"
    ],
    "wof:name":"Saetjeom",
    "wof:placetype":"locality"
},
  "geometry": {"coordinates":[127.04832,34.94526],"type":"Point"}
}