{
  "type": "Feature",
  "properties": {
    "iso:country":"KR",
    "name:kor_x_preferred":[
        "\uc815\ubc1c\uc0b0\ub3d9"
    ],
    "name:kor_x_variant":[
        "\uc815\ubc1c\uc0b0"
    ],
    "name:und_x_variant":[
        "\uc815\uc7903\ub3d9"
    ],
    "qs:gn_fcode":"PPL",
    "qs:gn_local":0,
    "qs:gn_namadm1":"13",
    "qs:gn_name":"Jeongjasam-dong",
    "qs:local_max":852,
    "qs:local_sum":1203,
    "qs:localhoods":6,
    "qs:name":"\uc815\ubc1c\uc0b0\ub3d9",
    "qs:name_adm0":"\ud55c\uad6d",
    "qs:name_adm1":"\uacbd\uae30\ub3c4",
    "qs:name_adm2":"\uace0\uc591\uc2dc",
    "qs:name_lau":"\uc77c\uc0b0\ub3d9\uad6c",
    "qs:name_local":"\uc77c\uc0b0\ub3d9\uad6c",
    "qs:photo_max":28,
    "qs:photo_sum":47,
    "qs:placetype":"Suburb",
    "qs:quad_count":8,
    "qs:woe_adm0":23424868,
    "qs:woe_adm1":2345969,
    "qs:woe_adm2":28289179,
    "qs:woe_lau":28997210,
    "qs:woe_local":28997210,
    "qs:woe_ver":"7.10.0",
    "wof:lang":[
        "kor"
    ],
    "wof:name":"\uc815\ubc1c\uc0b0\ub3d9",
    "wof:placetype":"neighbourhood"
},
  "geometry": {"coordinates":[126.784971,37.664993],"type":"Point"}
}