{
  "type": "Feature",
  "properties": {
    "gn:admin1_code":"14.0",
    "gn:asciiname":"Utjima",
    "gn:country_code":"KR",
    "gn:dem":104,
    "gn:feature_class":"P",
    "gn:feature_code":"PPL",
    "gn:name":"Utjima",
    "gn:population":0,
    "gn:timezone":"Asia/Seoul",
    "iso:country":"KR",
    "name:kor_x_preferred":[
        "\uc6c3\uc9c0\ub9c8"
    ],
    "wof:name":"Utjima",
    "wof:placetype":"locality"
},
  "geometry": {"coordinates":[128.37145000000001,36.6124],"type":"Point"}
}