{
  "type": "Feature",
  "properties": {
    "gn:admin1_code":"16.0",
    "gn:asciiname":"Cheonggangni",
    "gn:country_code":"KR",
    "gn:dem":42,
    "gn:feature_class":"P",
    "gn:feature_code":"PPL",
    "gn:name":"Cheonggangni",
    "gn:population":0,
    "gn:timezone":"Asia/Seoul",
    "iso:country":"KR",
    "name:kor_x_preferred":[
        "\uccad\uac15\ub9ac"
    ],
    "name:und_x_variant":[
        "Ch\u2019anggang-ni"
    ],
    "wof:name":"Cheonggangni",
    "wof:placetype":"locality"
},
  "geometry": {"coordinates":[126.96603,35.25088],"type":"Point"}
}