{
  "type": "Feature",
  "properties": {
    "gn:admin1_code":"13.0",
    "gn:asciiname":"Musugomi",
    "gn:country_code":"KR",
    "gn:dem":134,
    "gn:feature_class":"P",
    "gn:feature_code":"PPL",
    "gn:name":"Musug\u014fmi",
    "gn:population":0,
    "gn:timezone":"Asia/Seoul",
    "iso:country":"KR",
    "wof:name":"Musugomi",
    "wof:placetype":"locality"
},
  "geometry": {"coordinates":[127.06889,37.88556],"type":"Point"}
}