{
  "type": "Feature",
  "properties": {
    "gn:admin1_code":"13.0",
    "gn:asciiname":"Galmun",
    "gn:country_code":"KR",
    "gn:dem":122,
    "gn:feature_class":"P",
    "gn:feature_code":"PPL",
    "gn:name":"Galmun",
    "gn:population":0,
    "gn:timezone":"Asia/Seoul",
    "iso:country":"KR",
    "name:kor_x_preferred":[
        "\uac08\ubb38"
    ],
    "name:und_x_variant":[
        "\uac08\ubb38",
        "Galmun"
    ],
    "wof:name":"Galmun",
    "wof:placetype":"locality"
},
  "geometry": {"coordinates":[127.4324,37.6473],"type":"Point"}
}