{
  "type": "Feature",
  "properties": {
    "gn:admin1_code":"17.0",
    "gn:asciiname":"Umji-ri",
    "gn:country_code":"KR",
    "gn:dem":187,
    "gn:feature_class":"P",
    "gn:feature_code":"PPLL",
    "gn:name":"\u016cmji-ri",
    "gn:population":0,
    "gn:timezone":"Asia/Seoul",
    "iso:country":"KR",
    "name:und_x_variant":[
        "\uc74c\uc9c0\ub9ac",
        "\u016cmji-ri"
    ],
    "wof:name":"Umji-ri",
    "wof:placetype":"locality"
},
  "geometry": {"coordinates":[127.46235,36.09938],"type":"Point"}
}