{
  "type": "Feature",
  "properties": {
    "gn:admin1_code":"14.0",
    "gn:asciiname":"Hyeongcheon",
    "gn:country_code":"KR",
    "gn:dem":112,
    "gn:feature_class":"P",
    "gn:feature_code":"PPL",
    "gn:name":"Hyeongcheon",
    "gn:population":0,
    "gn:timezone":"Asia/Seoul",
    "iso:country":"KR",
    "name:kor_x_preferred":[
        "\ud615\ucc9c"
    ],
    "wof:name":"Hyeongcheon",
    "wof:placetype":"locality"
},
  "geometry": {"coordinates":[128.28989000000001,36.64542],"type":"Point"}
}