{
  "type": "Feature",
  "properties": {
    "gn:admin1_code":"6.0",
    "gn:asciiname":"Tunbak-kol",
    "gn:country_code":"KR",
    "gn:dem":568,
    "gn:feature_class":"P",
    "gn:feature_code":"PPL",
    "gn:name":"Tunbak-kol",
    "gn:population":0,
    "gn:timezone":"Asia/Seoul",
    "iso:country":"KR",
    "name:kor_x_preferred":[
        "\ub454\ubc15\uace8"
    ],
    "wof:name":"Tunbak-kol",
    "wof:placetype":"locality"
},
  "geometry": {"coordinates":[128.70140000000001,37.2269],"type":"Point"}
}