{
  "type": "Feature",
  "properties": {
    "gn:admin1_code":"16.0",
    "gn:asciiname":"Maesil",
    "gn:country_code":"KR",
    "gn:dem":105,
    "gn:feature_class":"P",
    "gn:feature_code":"PPL",
    "gn:name":"Maesil",
    "gn:population":0,
    "gn:timezone":"Asia/Seoul",
    "iso:country":"KR",
    "name:kor_x_preferred":[
        "\ub9e4\uc2e4"
    ],
    "wof:name":"Maesil",
    "wof:placetype":"locality"
},
  "geometry": {"coordinates":[126.7204,35.31174],"type":"Point"}
}