{
  "type": "Feature",
  "properties": {
    "iso:country":"KR",
    "name:eng_x_preferred":[
        "Nokyang-dong"
    ],
    "name:kor_x_preferred":[
        "\ub179\uc591\ub3d9"
    ],
    "qs:name":"\ub179\uc591\ub3d9",
    "qs:name_adm0":"\ud55c\uad6d",
    "qs:name_adm1":"\uacbd\uae30\ub3c4",
    "qs:photos":1,
    "qs:photos_1k":1,
    "qs:photos_9k":1,
    "qs:photos_9r":1,
    "qs:photos_all":1,
    "qs:photos_sr":1,
    "qs:placetype":"LocalAdmin",
    "qs:pop_sr":"0",
    "wof:name":"Nokyang-dong",
    "wof:placetype":"localadmin"
},
  "geometry": {"coordinates":[127.040233,37.741399],"type":"Point"}
}