{
  "type": "Feature",
  "properties": {
    "gn:admin1_code":"13.0",
    "gn:admin2_code":"Ans\u014fng-si",
    "gn:asciiname":"Sohyeon-ri",
    "gn:country_code":"KR",
    "gn:dem":49,
    "gn:feature_class":"P",
    "gn:feature_code":"PPLL",
    "gn:name":"Sohyeon-ri",
    "gn:population":0,
    "gn:timezone":"Asia/Seoul",
    "iso:country":"KR",
    "name:kor_x_preferred":[
        "\uc18c\ud604\ub9ac"
    ],
    "name:kor_x_variant":[
        "Sohy\u014fl-li"
    ],
    "wof:name":"Sohyeon-ri",
    "wof:placetype":"locality"
},
  "geometry": {"coordinates":[127.25583,37.03222],"type":"Point"}
}