{
  "type": "Feature",
  "properties": {
    "gn:admin1_code":"3.0",
    "gn:asciiname":"Kumgwang",
    "gn:country_code":"KR",
    "gn:dem":62,
    "gn:feature_class":"P",
    "gn:feature_code":"PPL",
    "gn:name":"K\u016dmgwang",
    "gn:population":0,
    "gn:timezone":"Asia/Seoul",
    "iso:country":"KR",
    "name:und_x_variant":[
        "K\u016dmgwang-ni",
        "\uae08\uad11",
        "K\u016dmgwang"
    ],
    "wof:name":"Kumgwang",
    "wof:placetype":"locality"
},
  "geometry": {"coordinates":[127.10626999999999,35.99225999999999],"type":"Point"}
}