{
  "type": "Feature",
  "properties": {
    "iso:country":"KR",
    "qs:name":"\uc2e0\uc0ac\uc6b0\ub3d9",
    "qs:name_adm0":"\ud55c\uad6d",
    "qs:name_adm1":"\uac15\uc6d0\ub3c4",
    "qs:photos":644,
    "qs:photos_1k":130,
    "qs:photos_9k":3,
    "qs:photos_9r":5,
    "qs:photos_all":644,
    "qs:photos_sr":8,
    "qs:placetype":"LocalAdmin",
    "qs:pop_sr":"0",
    "wof:name":"\uc2e0\uc0ac\uc6b0\ub3d9",
    "wof:placetype":"localadmin"
},
  "geometry": {"coordinates":[127.75675,37.925236],"type":"Point"}
}