{
  "type": "Feature",
  "properties": {
    "gn:admin1_code":"13.0",
    "gn:asciiname":"Geoncheon",
    "gn:country_code":"KR",
    "gn:dem":14,
    "gn:feature_class":"P",
    "gn:feature_code":"PPL",
    "gn:name":"Geoncheon",
    "gn:population":0,
    "gn:timezone":"Asia/Seoul",
    "iso:country":"KR",
    "name:und_x_variant":[
        "\uac74\ucc9c",
        "K\u014fnch\u2019\u014fn",
        "Geoncheon"
    ],
    "wof:name":"Geoncheon",
    "wof:placetype":"locality"
},
  "geometry": {"coordinates":[127.1382,36.9782],"type":"Point"}
}