{
  "type": "Feature",
  "properties": {
    "gn:admin1_code":"13.0",
    "gn:asciiname":"Seureuremi",
    "gn:country_code":"KR",
    "gn:dem":200,
    "gn:feature_class":"P",
    "gn:feature_code":"PPL",
    "gn:name":"Seureuremi",
    "gn:population":0,
    "gn:timezone":"Asia/Seoul",
    "iso:country":"KR",
    "name:kor_x_preferred":[
        "\uc2a4\ub974\ub808\ubbf8"
    ],
    "name:und_x_variant":[
        "\uc2a4\ub8e8\ub0b4\ubbf8",
        "S\u016drunaemi",
        "Seureuremi",
        "Seurunaemi"
    ],
    "wof:name":"Seureuremi",
    "wof:placetype":"locality"
},
  "geometry": {"coordinates":[126.93358000000001,37.85555],"type":"Point"}
}