{
  "type": "Feature",
  "properties": {
    "gn:admin1_code":"11.0",
    "gn:asciiname":"Wolgogil-tong",
    "gn:country_code":"KR",
    "gn:dem":36,
    "gn:feature_class":"P",
    "gn:feature_code":"PPL",
    "gn:name":"W\u014flgogil-tong",
    "gn:population":0,
    "gn:timezone":"Asia/Seoul",
    "iso:country":"KR",
    "name:und_x_variant":[
        "\uc6d4\uace11\ub3d9",
        "W\u014flgogil-tong"
    ],
    "wof:name":"Wolgogil-tong",
    "wof:placetype":"locality"
},
  "geometry": {"coordinates":[127.03178,37.60703],"type":"Point"}
}