{
  "type": "Feature",
  "properties": {
    "gn:admin1_code":"14.0",
    "gn:asciiname":"Haeyangji",
    "gn:country_code":"KR",
    "gn:dem":424,
    "gn:feature_class":"P",
    "gn:feature_code":"PPL",
    "gn:name":"Haeyangji",
    "gn:population":0,
    "gn:timezone":"Asia/Seoul",
    "iso:country":"KR",
    "name:und_x_variant":[
        "\ud574\uc591\uc9c0",
        "Haeyangji"
    ],
    "wof:name":"Haeyangji",
    "wof:placetype":"locality"
},
  "geometry": {"coordinates":[129.10290000000001,36.675],"type":"Point"}
}