{
  "type": "Feature",
  "properties": {
    "gn:admin1_code":"6.0",
    "gn:asciiname":"Pulmusil-gol",
    "gn:country_code":"KR",
    "gn:dem":749,
    "gn:feature_class":"P",
    "gn:feature_code":"PPL",
    "gn:name":"Pulmusil-gol",
    "gn:population":0,
    "gn:timezone":"Asia/Seoul",
    "iso:country":"KR",
    "name:kor_x_preferred":[
        "\ubd88\ubb34\uc2e4\uace8"
    ],
    "wof:name":"Pulmusil-gol",
    "wof:placetype":"locality"
},
  "geometry": {"coordinates":[128.9776,37.0862],"type":"Point"}
}