{
  "type": "Feature",
  "properties": {
    "gn:admin1_code":"17.0",
    "gn:asciiname":"Yonggyeong",
    "gn:country_code":"KR",
    "gn:dem":106,
    "gn:feature_class":"P",
    "gn:feature_code":"PPL",
    "gn:name":"Yonggyeong",
    "gn:population":0,
    "gn:timezone":"Asia/Seoul",
    "iso:country":"KR",
    "name:kor_x_preferred":[
        "\uc6a9\uacbd"
    ],
    "wof:name":"Yonggyeong",
    "wof:placetype":"locality"
},
  "geometry": {"coordinates":[127.08642,36.68472],"type":"Point"}
}