{
  "type": "Feature",
  "properties": {
    "gn:admin1_code":"16.0",
    "gn:asciiname":"Gwangyangdo",
    "gn:country_code":"KR",
    "gn:dem":97,
    "gn:feature_class":"P",
    "gn:feature_code":"PPL",
    "gn:name":"Gwangyangdo",
    "gn:population":0,
    "gn:timezone":"Asia/Seoul",
    "iso:country":"KR",
    "name:kor_x_preferred":[
        "\uad11\uc591\ub3c4"
    ],
    "name:und_x_variant":[
        "K\u014dy\u014dho",
        "Kwangyanggae",
        "Kwangyangp\u2019o",
        "Kwangyangdo",
        "Gwangyangdo"
    ],
    "wof:name":"Gwangyangdo",
    "wof:placetype":"locality"
},
  "geometry": {"coordinates":[127.70058,34.88854],"type":"Point"}
}