{
  "type": "Feature",
  "properties": {
    "gn:admin1_code":"16.0",
    "gn:asciiname":"Wolgang",
    "gn:country_code":"KR",
    "gn:dem":11,
    "gn:feature_class":"P",
    "gn:feature_code":"PPL",
    "gn:name":"Wolgang",
    "gn:population":0,
    "gn:timezone":"Asia/Seoul",
    "iso:country":"KR",
    "name:kor_x_preferred":[
        "W\u014flgang"
    ],
    "name:kor_x_variant":[
        "\uc6d4\uac15"
    ],
    "wof:name":"Wolgang",
    "wof:placetype":"locality"
},
  "geometry": {"coordinates":[126.54667000000001,34.41972],"type":"Point"}
}