{
  "type": "Feature",
  "properties": {
    "gn:admin1_code":"17.0",
    "gn:asciiname":"Gamabong",
    "gn:country_code":"KR",
    "gn:dem":102,
    "gn:feature_class":"P",
    "gn:feature_code":"PPL",
    "gn:name":"Gamabong",
    "gn:population":0,
    "gn:timezone":"Asia/Seoul",
    "iso:country":"KR",
    "name:und_x_variant":[
        "\uac00\ub9c8\ubd09",
        "Kamabong",
        "Gamabong"
    ],
    "wof:name":"Gamabong",
    "wof:placetype":"locality"
},
  "geometry": {"coordinates":[127.23291,36.39808],"type":"Point"}
}