{
  "type": "Feature",
  "properties": {
    "gn:admin1_code":"3.0",
    "gn:asciiname":"Wonoegung",
    "gn:country_code":"KR",
    "gn:dem":284,
    "gn:feature_class":"P",
    "gn:feature_code":"PPL",
    "gn:name":"W\u014fnoegung",
    "gn:population":0,
    "gn:timezone":"Asia/Seoul",
    "iso:country":"KR",
    "name:und_x_variant":[
        "\uc6d0\uc678\uad81",
        "W\u014fnoegung"
    ],
    "wof:name":"Wonoegung",
    "wof:placetype":"locality"
},
  "geometry": {"coordinates":[127.32922000000001,35.70532],"type":"Point"}
}