{
  "type": "Feature",
  "properties": {
    "iso:country":"KR",
    "name:eng_x_preferred":[
        "Seryu 1(il)-dong"
    ],
    "name:kor_x_preferred":[
        "\uc138\ub9581\ub3d9"
    ],
    "qs:gn_fcode":"PPL",
    "qs:gn_local":0,
    "qs:gn_namadm1":"13",
    "qs:gn_name":"Seryu-dong",
    "qs:local_max":553,
    "qs:local_sum":1093,
    "qs:localhoods":4,
    "qs:name":"\uc138\ub9581\ub3d9",
    "qs:name_adm0":"\ud55c\uad6d",
    "qs:name_adm1":"\uacbd\uae30\ub3c4",
    "qs:name_adm2":"\uc218\uc6d0\uc2dc",
    "qs:name_lau":"\uad8c\uc120\uad6c",
    "qs:name_local":"\uad8c\uc120\uad6c",
    "qs:photo_max":134,
    "qs:photo_sum":553,
    "qs:placetype":"Suburb",
    "qs:quad_count":18,
    "qs:woe_adm0":23424868,
    "qs:woe_adm1":2345969,
    "qs:woe_adm2":28289297,
    "qs:woe_lau":28997196,
    "qs:woe_local":28997196,
    "qs:woe_ver":"7.10.0",
    "wof:lang":[
        "kor"
    ],
    "wof:name":"Seryu 1(il)-dong",
    "wof:placetype":"neighbourhood"
},
  "geometry": {"coordinates":[127.01164300000001,37.25639],"type":"Point"}
}