{
  "type": "Feature",
  "properties": {
    "gn:admin1_code":"6.0",
    "gn:asciiname":"Dangang",
    "gn:country_code":"KR",
    "gn:dem":61,
    "gn:feature_class":"P",
    "gn:feature_code":"PPL",
    "gn:name":"Dangang",
    "gn:population":0,
    "gn:timezone":"Asia/Seoul",
    "iso:country":"KR",
    "name:kor_x_preferred":[
        "\ub2e8\uc815"
    ],
    "name:kor_x_variant":[
        "Tanj\u014fng",
        "\ub2e8\uac15"
    ],
    "name:und_x_variant":[
        "Danjeong",
        "Dangang"
    ],
    "wof:name":"Dangang",
    "wof:placetype":"locality"
},
  "geometry": {"coordinates":[127.78745000000001,37.15271],"type":"Point"}
}