{
  "type": "Feature",
  "properties": {
    "gn:admin1_code":"13.0",
    "gn:asciiname":"Jeolgol",
    "gn:country_code":"KR",
    "gn:dem":173,
    "gn:feature_class":"P",
    "gn:feature_code":"PPL",
    "gn:name":"Jeolgol",
    "gn:population":0,
    "gn:timezone":"Asia/Seoul",
    "iso:country":"KR",
    "name:und_x_variant":[
        "\uc808\uace8",
        "Ch\u014fl-gol",
        "Jeolgol"
    ],
    "wof:name":"Jeolgol",
    "wof:placetype":"locality"
},
  "geometry": {"coordinates":[127.14662,37.79067],"type":"Point"}
}