{
  "type": "Feature",
  "properties": {
    "gn:admin1_code":"17.0",
    "gn:asciiname":"Gwongmal",
    "gn:country_code":"KR",
    "gn:dem":40,
    "gn:feature_class":"P",
    "gn:feature_code":"PPL",
    "gn:name":"Gwongmal",
    "gn:population":0,
    "gn:timezone":"Asia/Seoul",
    "iso:country":"KR",
    "name:kor_x_preferred":[
        "\uad9d\ub9d0"
    ],
    "wof:name":"Gwongmal",
    "wof:placetype":"locality"
},
  "geometry": {"coordinates":[127.17224,36.21625],"type":"Point"}
}