{
  "type": "Feature",
  "properties": {
    "gn:admin1_code":"10.0",
    "gn:asciiname":"Imseok",
    "gn:country_code":"KR",
    "gn:dem":56,
    "gn:feature_class":"P",
    "gn:feature_code":"PPL",
    "gn:name":"Imseok",
    "gn:population":0,
    "gn:timezone":"Asia/Seoul",
    "iso:country":"KR",
    "name:kor_x_preferred":[
        "\uc784\uc11d"
    ],
    "wof:name":"Imseok",
    "wof:placetype":"locality"
},
  "geometry": {"coordinates":[129.11048,35.28817],"type":"Point"}
}