{
  "type": "Feature",
  "properties": {
    "gn:admin1_code":"17.0",
    "gn:asciiname":"Changt'o",
    "gn:country_code":"KR",
    "gn:dem":13,
    "gn:feature_class":"P",
    "gn:feature_code":"PPL",
    "gn:name":"Changt\u2019\u014f",
    "gn:population":0,
    "gn:timezone":"Asia/Seoul",
    "iso:country":"KR",
    "name:und_x_variant":[
        "\uc7a5\ud130",
        "Changt\u2019\u014f"
    ],
    "wof:name":"Changt'o",
    "wof:placetype":"locality"
},
  "geometry": {"coordinates":[126.7894,36.7539],"type":"Point"}
}