{
  "type": "Feature",
  "properties": {
    "gn:admin1_code":"16.0",
    "gn:asciiname":"Wolpyeong",
    "gn:country_code":"KR",
    "gn:dem":7,
    "gn:feature_class":"P",
    "gn:feature_code":"PPL",
    "gn:name":"Wolpyeong",
    "gn:population":0,
    "gn:timezone":"Asia/Seoul",
    "iso:country":"KR",
    "name:kor_x_preferred":[
        "\uc6d4\ud3c9"
    ],
    "name:kor_x_variant":[
        "W\u014flp\u2019y\u014fng"
    ],
    "wof:name":"Wolpyeong",
    "wof:placetype":"locality"
},
  "geometry": {"coordinates":[127.18599,34.75386],"type":"Point"}
}