{
  "type": "Feature",
  "properties": {
    "gn:admin1_code":"16.0",
    "gn:admin2_code":"Chindo-gun",
    "gn:asciiname":"Hagujado",
    "gn:country_code":"KR",
    "gn:dem":22,
    "gn:feature_class":"P",
    "gn:feature_code":"PPL",
    "gn:name":"Hagujado",
    "gn:population":0,
    "gn:timezone":"Asia/Seoul",
    "iso:country":"KR",
    "name:kor_x_preferred":[
        "\ud558\uad6c\uc790\ub3c4"
    ],
    "wof:name":"Hagujado",
    "wof:placetype":"locality"
},
  "geometry": {"coordinates":[126.30028,34.32194],"type":"Point"}
}