{
  "type": "Feature",
  "properties": {
    "gn:admin1_code":"13.0",
    "gn:asciiname":"Sangbonch'on-ni",
    "gn:country_code":"KR",
    "gn:dem":72,
    "gn:feature_class":"P",
    "gn:feature_code":"PPL",
    "gn:name":"Sangb\u014fnch\u2019\u014fn-ni",
    "gn:population":0,
    "gn:timezone":"Asia/Seoul",
    "iso:country":"KR",
    "name:und_x_variant":[
        "Sang-p\u014fnch\u014fn-ni",
        "Sangb\u014fnch\u2019\u014fn-ni"
    ],
    "wof:name":"Sangbonch'on-ni",
    "wof:placetype":"locality"
},
  "geometry": {"coordinates":[127.26667,37.45],"type":"Point"}
}