{
  "type": "Feature",
  "properties": {
    "gn:admin1_code":"6.0",
    "gn:asciiname":"Doil",
    "gn:country_code":"KR",
    "gn:dem":104,
    "gn:feature_class":"P",
    "gn:feature_code":"PPL",
    "gn:name":"Doil",
    "gn:population":0,
    "gn:timezone":"Asia/Seoul",
    "iso:country":"KR",
    "name:und_x_variant":[
        "\ub3c4\uc77c",
        "Toil",
        "Doil"
    ],
    "wof:name":"Doil",
    "wof:placetype":"locality"
},
  "geometry": {"coordinates":[127.76560000000001,37.88381],"type":"Point"}
}