{
  "type": "Feature",
  "properties": {
    "gn:admin1_code":"0.0",
    "gn:asciiname":"Kwanson",
    "gn:cc2":"KR",
    "gn:country_code":"KR",
    "gn:dem":-9999,
    "gn:feature_class":"P",
    "gn:feature_code":"PPL",
    "gn:name":"Kwans\u014fn",
    "gn:population":0,
    "gn:timezone":"Asia/Seoul",
    "iso:country":"KR",
    "name:und_x_variant":[
        "Kwans\u014fn-ni",
        "Kwans\u014fn"
    ],
    "wof:name":"Kwanson",
    "wof:placetype":"locality"
},
  "geometry": {"coordinates":[126.56667,35.58333],"type":"Point"}
}