{
  "type": "Feature",
  "properties": {
    "gn:admin1_code":"6.0",
    "gn:asciiname":"Eungmakdong",
    "gn:country_code":"KR",
    "gn:dem":13,
    "gn:feature_class":"P",
    "gn:feature_code":"PPL",
    "gn:name":"Eungmakdong",
    "gn:population":0,
    "gn:timezone":"Asia/Seoul",
    "iso:country":"KR",
    "name:kor_x_preferred":[
        "\uc751\ub9c9\ub3d9"
    ],
    "name:kor_x_variant":[
        "\u016cngmak-tong"
    ],
    "wof:name":"Eungmakdong",
    "wof:placetype":"locality"
},
  "geometry": {"coordinates":[128.82366000000002,37.87422],"type":"Point"}
}