{
  "type": "Feature",
  "properties": {
    "gn:admin1_code":"17.0",
    "gn:asciiname":"Tabak-kol",
    "gn:country_code":"KR",
    "gn:dem":46,
    "gn:feature_class":"P",
    "gn:feature_code":"PPL",
    "gn:name":"Tabak-kol",
    "gn:population":0,
    "gn:timezone":"Asia/Seoul",
    "iso:country":"KR",
    "name:und_x_variant":[
        "\ub2e4\ubc15\uace8",
        "Tabak-kol"
    ],
    "wof:name":"Tabak-kol",
    "wof:placetype":"locality"
},
  "geometry": {"coordinates":[126.83450000000001,36.5979],"type":"Point"}
}