{
  "type": "Feature",
  "properties": {
    "gn:admin1_code":"16.0",
    "gn:asciiname":"Oksan",
    "gn:country_code":"KR",
    "gn:dem":32,
    "gn:feature_class":"P",
    "gn:feature_code":"PPL",
    "gn:name":"Oksan",
    "gn:population":0,
    "gn:timezone":"Asia/Seoul",
    "iso:country":"KR",
    "name:kor_x_preferred":[
        "S\u014fdong"
    ],
    "name:kor_x_variant":[
        "\uc11c\ub3d9",
        "\uc625\uc0b0"
    ],
    "wof:name":"Oksan",
    "wof:placetype":"locality"
},
  "geometry": {"coordinates":[127.33261,34.89343],"type":"Point"}
}