{
  "type": "Feature",
  "properties": {
    "gn:admin1_code":"1.0",
    "gn:asciiname":"Bondong",
    "gn:country_code":"KR",
    "gn:dem":66,
    "gn:feature_class":"P",
    "gn:feature_code":"PPL",
    "gn:name":"Bondong",
    "gn:population":0,
    "gn:timezone":"Asia/Seoul",
    "iso:country":"KR",
    "name:kor_x_preferred":[
        "\ubcf8\ub3d9"
    ],
    "name:und_x_variant":[
        "Pon-dong"
    ],
    "wof:name":"Bondong",
    "wof:placetype":"locality"
},
  "geometry": {"coordinates":[126.39256,33.46843],"type":"Point"}
}