{
  "type": "Feature",
  "properties": {
    "gn:admin1_code":"6.0",
    "gn:asciiname":"Heurigol",
    "gn:country_code":"KR",
    "gn:dem":306,
    "gn:feature_class":"P",
    "gn:feature_code":"PPL",
    "gn:name":"Heurigol",
    "gn:population":0,
    "gn:timezone":"Asia/Seoul",
    "iso:country":"KR",
    "name:kor_x_preferred":[
        "\ud750\ub9bf\uace8"
    ],
    "name:kor_x_variant":[
        "H\u016drik-kol",
        "\ud750\ub9ac\uace8"
    ],
    "name:und_x_variant":[
        "Heurit-gol",
        "Heurigol"
    ],
    "wof:name":"Heurigol",
    "wof:placetype":"locality"
},
  "geometry": {"coordinates":[128.02813,38.06266],"type":"Point"}
}