{
  "type": "Feature",
  "properties": {
    "gn:admin1_code":"17.0",
    "gn:asciiname":"Ch'wijangbolgae",
    "gn:country_code":"KR",
    "gn:dem":47,
    "gn:feature_class":"P",
    "gn:feature_code":"PPL",
    "gn:name":"Ch\u2019wijangb\u014flgae",
    "gn:population":0,
    "gn:timezone":"Asia/Seoul",
    "iso:country":"KR",
    "name:und_x_variant":[
        "\ucde8\uc7a5\ubc8c\uac1c",
        "Ch\u2019wijangb\u014flgae"
    ],
    "wof:name":"Ch'wijangbolgae",
    "wof:placetype":"locality"
},
  "geometry": {"coordinates":[126.40170000000001,36.7205],"type":"Point"}
}