{
  "type": "Feature",
  "properties": {
    "gn:admin1_code":"6.0",
    "gn:asciiname":"Koal-li",
    "gn:country_code":"KR",
    "gn:dem":238,
    "gn:feature_class":"P",
    "gn:feature_code":"PPL",
    "gn:name":"K\u014fal-li",
    "gn:population":0,
    "gn:timezone":"Asia/Seoul",
    "iso:country":"KR",
    "name:kor_x_preferred":[
        "K\u014fal-li"
    ],
    "name:kor_x_variant":[
        "\uac70\uc548\ub9ac"
    ],
    "wof:name":"Koal-li",
    "wof:placetype":"locality"
},
  "geometry": {"coordinates":[128.29721999999998,37.24333],"type":"Point"}
}