{
  "type": "Feature",
  "properties": {
    "gn:admin1_code":"6.0",
    "gn:asciiname":"Hansamoru",
    "gn:country_code":"KR",
    "gn:dem":133,
    "gn:feature_class":"P",
    "gn:feature_code":"PPL",
    "gn:name":"Hansamoru",
    "gn:population":0,
    "gn:timezone":"Asia/Seoul",
    "iso:country":"KR",
    "name:und_x_variant":[
        "\ud55c\uc0ac\ubaa8\ub8e8",
        "Hansamoru"
    ],
    "wof:name":"Hansamoru",
    "wof:placetype":"locality"
},
  "geometry": {"coordinates":[127.66763,38.05064],"type":"Point"}
}