{
  "type": "Feature",
  "properties": {
    "gn:admin1_code":"6.0",
    "gn:asciiname":"Woltu-dong",
    "gn:country_code":"KR",
    "gn:dem":378,
    "gn:feature_class":"P",
    "gn:feature_code":"PPL",
    "gn:name":"W\u014fltu-dong",
    "gn:population":0,
    "gn:timezone":"Asia/Seoul",
    "iso:country":"KR",
    "name:kor_x_preferred":[
        "\uc6d4\ub450\ub3d9"
    ],
    "name:kor_x_variant":[
        "W\u014fltu-dong"
    ],
    "wof:name":"Woltu-dong",
    "wof:placetype":"locality"
},
  "geometry": {"coordinates":[128.43690000000001,37.4482],"type":"Point"}
}