{
  "type": "Feature",
  "properties": {
    "gn:admin1_code":"20.0",
    "gn:asciiname":"Tonggu",
    "gn:country_code":"KR",
    "gn:dem":175,
    "gn:feature_class":"P",
    "gn:feature_code":"PPL",
    "gn:name":"Tonggu",
    "gn:population":0,
    "gn:timezone":"Asia/Seoul",
    "iso:country":"KR",
    "name:und_x_variant":[
        "\ub3d9\uad6c",
        "Tonggu"
    ],
    "wof:name":"Tonggu",
    "wof:placetype":"locality"
},
  "geometry": {"coordinates":[127.78979,35.58094000000001],"type":"Point"}
}