{
  "type": "Feature",
  "properties": {
    "gn:admin1_code":"15.0",
    "gn:asciiname":"Gamasil",
    "gn:country_code":"KR",
    "gn:dem":30,
    "gn:feature_class":"P",
    "gn:feature_code":"PPL",
    "gn:name":"Gamasil",
    "gn:population":0,
    "gn:timezone":"Asia/Seoul",
    "iso:country":"KR",
    "name:kor_x_preferred":[
        "\uac00\ub9c8\uc2e4"
    ],
    "wof:name":"Gamasil",
    "wof:placetype":"locality"
},
  "geometry": {"coordinates":[128.44138000000001,35.85859],"type":"Point"}
}