{
  "type": "Feature",
  "properties": {
    "gn:admin1_code":"5.0",
    "gn:asciiname":"Jungteokmaeul",
    "gn:country_code":"KR",
    "gn:dem":198,
    "gn:feature_class":"P",
    "gn:feature_code":"PPL",
    "gn:name":"Jungteokmaeul",
    "gn:population":0,
    "gn:timezone":"Asia/Seoul",
    "iso:country":"KR",
    "name:kor_x_preferred":[
        "\uc911\ud131\ub9c8\uc744"
    ],
    "wof:name":"Jungteokmaeul",
    "wof:placetype":"locality"
},
  "geometry": {"coordinates":[127.64758999999999,37.02122],"type":"Point"}
}