{
  "type": "Feature",
  "properties": {
    "gn:admin1_code":"12.0",
    "gn:admin2_code":"Kanghwa-gun",
    "gn:asciiname":"Seonmeol",
    "gn:country_code":"KR",
    "gn:dem":14,
    "gn:feature_class":"P",
    "gn:feature_code":"PPL",
    "gn:name":"Seonmeol",
    "gn:population":0,
    "gn:timezone":"Asia/Seoul",
    "iso:country":"KR",
    "name:kor_x_preferred":[
        "\uc120\uba40"
    ],
    "name:kor_x_variant":[
        "S\u014fnm\u014fl"
    ],
    "wof:name":"Seonmeol",
    "wof:placetype":"locality"
},
  "geometry": {"coordinates":[126.31291,37.77832],"type":"Point"}
}