{
  "type": "Feature",
  "properties": {
    "gn:admin1_code":"20.0",
    "gn:asciiname":"Sangmae",
    "gn:country_code":"KR",
    "gn:dem":223,
    "gn:feature_class":"P",
    "gn:feature_code":"PPL",
    "gn:name":"Sangmae",
    "gn:population":0,
    "gn:timezone":"Asia/Seoul",
    "iso:country":"KR",
    "name:und_x_variant":[
        "\uc0c1\ub9e4",
        "Sangmae"
    ],
    "wof:name":"Sangmae",
    "wof:placetype":"locality"
},
  "geometry": {"coordinates":[128.10363999999998,35.73138],"type":"Point"}
}