{
  "type": "Feature",
  "properties": {
    "gn:admin1_code":"17.0",
    "gn:asciiname":"Chibang-ni",
    "gn:country_code":"KR",
    "gn:dem":176,
    "gn:feature_class":"P",
    "gn:feature_code":"PPLL",
    "gn:name":"Chibang-ni",
    "gn:population":0,
    "gn:timezone":"Asia/Seoul",
    "iso:country":"KR",
    "name:und_x_variant":[
        "\uc9c0\ubc29\ub9ac",
        "Chibang-ni"
    ],
    "wof:name":"Chibang-ni",
    "wof:placetype":"locality"
},
  "geometry": {"coordinates":[127.35939999999999,36.1842],"type":"Point"}
}