{
  "type": "Feature",
  "properties": {
    "gn:admin1_code":"17.0",
    "gn:asciiname":"Songgi",
    "gn:country_code":"KR",
    "gn:dem":56,
    "gn:feature_class":"P",
    "gn:feature_code":"PPL",
    "gn:name":"Songgi",
    "gn:population":0,
    "gn:timezone":"Asia/Seoul",
    "iso:country":"KR",
    "name:und_x_variant":[
        "\uc1a1\uae30",
        "Songgi"
    ],
    "wof:name":"Songgi",
    "wof:placetype":"locality"
},
  "geometry": {"coordinates":[127.134,36.8726],"type":"Point"}
}