{
  "type": "Feature",
  "properties": {
    "gn:admin1_code":"20.0",
    "gn:asciiname":"Seam",
    "gn:country_code":"KR",
    "gn:dem":20,
    "gn:feature_class":"P",
    "gn:feature_code":"PPL",
    "gn:name":"Seam",
    "gn:population":0,
    "gn:timezone":"Asia/Seoul",
    "iso:country":"KR",
    "name:rus_x_preferred":[
        "\u0428\u043e\u0432"
    ],
    "name:ukr_x_preferred":[
        "\u0428\u043e\u0432"
    ],
    "name:und_x_variant":[
        "\uc138\uc554",
        "Saeam",
        "Seam"
    ],
    "wof:name":"Seam",
    "wof:placetype":"locality"
},
  "geometry": {"coordinates":[128.29611,34.93803],"type":"Point"}
}