{
  "type": "Feature",
  "properties": {
    "gn:admin1_code":"20.0",
    "gn:asciiname":"Changgye-ri",
    "gn:country_code":"KR",
    "gn:dem":8,
    "gn:feature_class":"P",
    "gn:feature_code":"PPL",
    "gn:name":"Changgye-ri",
    "gn:population":0,
    "gn:timezone":"Asia/Seoul",
    "iso:country":"KR",
    "name:und_x_variant":[
        "\uc7a5\uacc4\ub9ac",
        "Changgye-ri"
    ],
    "wof:name":"Changgye-ri",
    "wof:placetype":"locality"
},
  "geometry": {"coordinates":[128.33736000000002,34.9945],"type":"Point"}
}