{
  "type": "Feature",
  "properties": {
    "gn:admin1_code":"16.0",
    "gn:asciiname":"Konno-dong",
    "gn:country_code":"KR",
    "gn:dem":44,
    "gn:feature_class":"P",
    "gn:feature_code":"PPL",
    "gn:name":"K\u014fnn\u014f-dong",
    "gn:population":0,
    "gn:timezone":"Asia/Seoul",
    "iso:country":"KR",
    "name:kor_x_preferred":[
        "K\u014fnn\u014f-dong"
    ],
    "wof:name":"Konno-dong",
    "wof:placetype":"locality"
},
  "geometry": {"coordinates":[126.68694000000001,34.48944],"type":"Point"}
}