{
  "type": "Feature",
  "properties": {
    "gn:admin1_code":"17.0",
    "gn:asciiname":"Gajaeul",
    "gn:country_code":"KR",
    "gn:dem":45,
    "gn:feature_class":"P",
    "gn:feature_code":"PPL",
    "gn:name":"Gajaeul",
    "gn:population":0,
    "gn:timezone":"Asia/Seoul",
    "iso:country":"KR",
    "name:und_x_variant":[
        "\uac00\uc7ac\uc6b8",
        "Kajaeul",
        "Gajaeul"
    ],
    "wof:name":"Gajaeul",
    "wof:placetype":"locality"
},
  "geometry": {"coordinates":[127.1671,36.3161],"type":"Point"}
}