{
  "type": "Feature",
  "properties": {
    "gn:admin1_code":"20.0",
    "gn:asciiname":"Nalgaji",
    "gn:country_code":"KR",
    "gn:dem":82,
    "gn:feature_class":"P",
    "gn:feature_code":"PPL",
    "gn:name":"Nalgaji",
    "gn:population":0,
    "gn:timezone":"Asia/Seoul",
    "iso:country":"KR",
    "name:und_x_variant":[
        "\ub0a0\uac00\uc9c0",
        "Nalgaji"
    ],
    "wof:name":"Nalgaji",
    "wof:placetype":"locality"
},
  "geometry": {"coordinates":[128.40861000000001,35.23441],"type":"Point"}
}