{
  "type": "Feature",
  "properties": {
    "gn:admin1_code":"13.0",
    "gn:asciiname":"Jageunakkul",
    "gn:country_code":"KR",
    "gn:dem":158,
    "gn:feature_class":"P",
    "gn:feature_code":"PPL",
    "gn:name":"Jageunakkul",
    "gn:population":0,
    "gn:timezone":"Asia/Seoul",
    "iso:country":"KR",
    "name:und_x_variant":[
        "\uc791\uc740\uc544\uace8",
        "Chag\u016dna-gol",
        "Jageunakkul"
    ],
    "wof:name":"Jageunakkul",
    "wof:placetype":"locality"
},
  "geometry": {"coordinates":[126.94201,37.73479],"type":"Point"}
}