{
  "type": "Feature",
  "properties": {
    "gn:admin1_code":"13.0",
    "gn:asciiname":"Sagimakgol",
    "gn:country_code":"KR",
    "gn:dem":83,
    "gn:feature_class":"P",
    "gn:feature_code":"PPL",
    "gn:name":"Sagimakgol",
    "gn:population":0,
    "gn:timezone":"Asia/Seoul",
    "iso:country":"KR",
    "name:und_x_variant":[
        "\uc0ac\uae30\ub9c9\uace8",
        "Sagimak-kol",
        "Sagimakgol"
    ],
    "wof:name":"Sagimakgol",
    "wof:placetype":"locality"
},
  "geometry": {"coordinates":[126.95878,37.67992],"type":"Point"}
}