{
  "type": "Feature",
  "properties": {
    "gn:admin1_code":"13.0",
    "gn:asciiname":"Wondokchong",
    "gn:country_code":"KR",
    "gn:dem":26,
    "gn:feature_class":"P",
    "gn:feature_code":"PPL",
    "gn:name":"W\u014fndokch\u014fng",
    "gn:population":0,
    "gn:timezone":"Asia/Seoul",
    "iso:country":"KR",
    "name:kor_x_preferred":[
        "\uc6d0\ub3c5\uc815"
    ],
    "name:kor_x_variant":[
        "W\u014fndokch\u014fng"
    ],
    "wof:name":"Wondokchong",
    "wof:placetype":"locality"
},
  "geometry": {"coordinates":[126.845,37.06722],"type":"Point"}
}