{
  "type": "Feature",
  "properties": {
    "gn:admin1_code":"17.0",
    "gn:asciiname":"Nayul",
    "gn:cc2":"KR",
    "gn:country_code":"KR",
    "gn:dem":13,
    "gn:feature_class":"P",
    "gn:feature_code":"PPL",
    "gn:name":"Nayul",
    "gn:population":0,
    "gn:timezone":"Asia/Seoul",
    "iso:country":"KR",
    "name:und_x_variant":[
        "W\u014flsan-ni",
        "Nayul"
    ],
    "wof:name":"Nayul",
    "wof:placetype":"locality"
},
  "geometry": {"coordinates":[126.81667,36.06667],"type":"Point"}
}