{
  "type": "Feature",
  "properties": {
    "gn:admin1_code":"5.0",
    "gn:asciiname":"Koji-gol",
    "gn:country_code":"KR",
    "gn:dem":248,
    "gn:feature_class":"P",
    "gn:feature_code":"PPL",
    "gn:name":"Koji-gol",
    "gn:population":0,
    "gn:timezone":"Asia/Seoul",
    "iso:country":"KR",
    "name:kor_x_preferred":[
        "\uace0\uc9c0\uace8"
    ],
    "wof:name":"Koji-gol",
    "wof:placetype":"locality"
},
  "geometry": {"coordinates":[128.1925,37.1236],"type":"Point"}
}