{
  "type": "Feature",
  "properties": {
    "gn:admin1_code":"13.0",
    "gn:asciiname":"Saesam",
    "gn:country_code":"KR",
    "gn:dem":52,
    "gn:feature_class":"P",
    "gn:feature_code":"PPL",
    "gn:name":"Saesam",
    "gn:population":0,
    "gn:timezone":"Asia/Seoul",
    "iso:country":"KR",
    "name:und_x_variant":[
        "\uc0c8\uc0bc",
        "Saesam"
    ],
    "wof:name":"Saesam",
    "wof:placetype":"locality"
},
  "geometry": {"coordinates":[127.51861,37.45833],"type":"Point"}
}