{
  "type": "Feature",
  "properties": {
    "gn:admin1_code":"17.0",
    "gn:asciiname":"Yongsu-mal",
    "gn:country_code":"KR",
    "gn:dem":15,
    "gn:feature_class":"P",
    "gn:feature_code":"PPL",
    "gn:name":"Yongsu-mal",
    "gn:population":0,
    "gn:timezone":"Asia/Seoul",
    "iso:country":"KR",
    "name:und_x_variant":[
        "\uc6a9\uc218\ub9d0",
        "Yongsu-mal"
    ],
    "wof:name":"Yongsu-mal",
    "wof:placetype":"locality"
},
  "geometry": {"coordinates":[126.7247,36.7227],"type":"Point"}
}