{
  "type": "Feature",
  "properties": {
    "gn:admin1_code":"20.0",
    "gn:asciiname":"Sil-li",
    "gn:country_code":"KR",
    "gn:dem":9,
    "gn:feature_class":"P",
    "gn:feature_code":"PPL",
    "gn:name":"Sil-li",
    "gn:population":0,
    "gn:timezone":"Asia/Seoul",
    "iso:country":"KR",
    "name:und_x_variant":[
        "\uc2e0\ub9ac",
        "Sin-ni",
        "Sil-li"
    ],
    "wof:name":"Sil-li",
    "wof:placetype":"locality"
},
  "geometry": {"coordinates":[128.43639999999999,34.88562],"type":"Point"}
}