{
  "type": "Feature",
  "properties": {
    "gn:admin1_code":"13.0",
    "gn:asciiname":"Napsangol",
    "gn:country_code":"KR",
    "gn:dem":34,
    "gn:feature_class":"P",
    "gn:feature_code":"PPL",
    "gn:name":"Napsangol",
    "gn:population":0,
    "gn:timezone":"Asia/Seoul",
    "iso:country":"KR",
    "name:kor_x_preferred":[
        "\ub0a9\uc0b0\uace8"
    ],
    "wof:name":"Napsangol",
    "wof:placetype":"locality"
},
  "geometry": {"coordinates":[126.55422,37.72793],"type":"Point"}
}