{
  "type": "Feature",
  "properties": {
    "gn:admin1_code":"13.0",
    "gn:admin2_code":"Ans\u014fng-si",
    "gn:asciiname":"Tangmong-ni",
    "gn:country_code":"KR",
    "gn:dem":155,
    "gn:feature_class":"P",
    "gn:feature_code":"PPLL",
    "gn:name":"Tangmong-ni",
    "gn:population":0,
    "gn:timezone":"Asia/Seoul",
    "iso:country":"KR",
    "name:kor_x_preferred":[
        "\ub2f9\ubaa9\ub9ac"
    ],
    "name:und_x_variant":[
        "Dangmok-ri"
    ],
    "wof:name":"Tangmong-ni",
    "wof:placetype":"locality"
},
  "geometry": {"coordinates":[127.42972,37.02861],"type":"Point"}
}