{
  "type": "Feature",
  "properties": {
    "gn:admin1_code":"13.0",
    "gn:admin2_code":"Ans\u014fng-si",
    "gn:asciiname":"Sinchang-ri",
    "gn:country_code":"KR",
    "gn:dem":60,
    "gn:feature_class":"P",
    "gn:feature_code":"PPLL",
    "gn:name":"Sinchang-ri",
    "gn:population":0,
    "gn:timezone":"Asia/Seoul",
    "iso:country":"KR",
    "name:kor_x_preferred":[
        "\uc2e0\ucc3d\ub9ac"
    ],
    "name:kor_x_variant":[
        "Sinch\u2019ang-ni"
    ],
    "wof:name":"Sinchang-ri",
    "wof:placetype":"locality"
},
  "geometry": {"coordinates":[127.2475,37.0825],"type":"Point"}
}