{
  "type": "Feature",
  "properties": {
    "gn:admin1_code":"16.0",
    "gn:asciiname":"Mun-ch'on",
    "gn:country_code":"KR",
    "gn:dem":28,
    "gn:feature_class":"P",
    "gn:feature_code":"PPL",
    "gn:name":"Mun-ch\u2019on",
    "gn:population":0,
    "gn:timezone":"Asia/Seoul",
    "iso:country":"KR",
    "name:kor_x_preferred":[
        "\ubb38\ucd0c"
    ],
    "name:kor_x_variant":[
        "Mun-ch\u2019on"
    ],
    "wof:name":"Mun-ch'on",
    "wof:placetype":"locality"
},
  "geometry": {"coordinates":[126.66388999999999,34.58528],"type":"Point"}
}