{
  "type": "Feature",
  "properties": {
    "gn:admin1_code":"5.0",
    "gn:asciiname":"Taeal-li",
    "gn:cc2":"KR",
    "gn:country_code":"KR",
    "gn:dem":283,
    "gn:feature_class":"P",
    "gn:feature_code":"PPL",
    "gn:name":"Taeal-li",
    "gn:population":0,
    "gn:timezone":"Asia/Seoul",
    "iso:country":"KR",
    "name:und_x_variant":[
        "Taean-ri",
        "Taeal-li"
    ],
    "wof:name":"Taeal-li",
    "wof:placetype":"locality"
},
  "geometry": {"coordinates":[127.65139000000001,36.56],"type":"Point"}
}