{
  "type": "Feature",
  "properties": {
    "gn:admin1_code":"20.0",
    "gn:asciiname":"Chungjang",
    "gn:country_code":"KR",
    "gn:dem":70,
    "gn:feature_class":"P",
    "gn:feature_code":"PPL",
    "gn:name":"Chungjang",
    "gn:population":0,
    "gn:timezone":"Asia/Seoul",
    "iso:country":"KR",
    "name:und_x_variant":[
        "\uc911\uc7a5",
        "Chungjang"
    ],
    "wof:name":"Chungjang",
    "wof:placetype":"locality"
},
  "geometry": {"coordinates":[128.28792000000001,35.42406],"type":"Point"}
}