{
  "type": "Feature",
  "properties": {
    "gn:admin1_code":"13.0",
    "gn:asciiname":"Toksani",
    "gn:country_code":"KR",
    "gn:dem":54,
    "gn:feature_class":"P",
    "gn:feature_code":"PPL",
    "gn:name":"Toksani",
    "gn:population":0,
    "gn:timezone":"Asia/Seoul",
    "iso:country":"KR",
    "name:und_x_variant":[
        "\ub3c5\uc0b0\uc774",
        "Doksani",
        "Toksani"
    ],
    "wof:name":"Toksani",
    "wof:placetype":"locality"
},
  "geometry": {"coordinates":[127.24139,37.35694],"type":"Point"}
}