{
  "type": "Feature",
  "properties": {
    "gn:admin1_code":"13.0",
    "gn:asciiname":"Geumdong",
    "gn:country_code":"KR",
    "gn:dem":162,
    "gn:feature_class":"P",
    "gn:feature_code":"PPL",
    "gn:name":"Geumdong",
    "gn:population":0,
    "gn:timezone":"Asia/Seoul",
    "iso:country":"KR",
    "name:und_x_variant":[
        "\uae08\ub3d9",
        "K\u016dm-dong",
        "Geumdong"
    ],
    "wof:name":"Geumdong",
    "wof:placetype":"locality"
},
  "geometry": {"coordinates":[127.12681000000001,37.94246],"type":"Point"}
}