{
  "type": "Feature",
  "properties": {
    "gn:admin1_code":"17.0",
    "gn:asciiname":"Poch'i",
    "gn:country_code":"KR",
    "gn:dem":311,
    "gn:feature_class":"P",
    "gn:feature_code":"PPL",
    "gn:name":"Poch\u2019i",
    "gn:population":0,
    "gn:timezone":"Asia/Seoul",
    "iso:country":"KR",
    "name:und_x_variant":[
        "\ubcf4\uce58",
        "Poch\u2019i"
    ],
    "wof:name":"Poch'i",
    "wof:placetype":"locality"
},
  "geometry": {"coordinates":[127.42619999999999,36.0858],"type":"Point"}
}