{
  "type": "Feature",
  "properties": {
    "gn:admin1_code":"17.0",
    "gn:asciiname":"Harogok",
    "gn:country_code":"KR",
    "gn:dem":142,
    "gn:feature_class":"P",
    "gn:feature_code":"PPL",
    "gn:name":"Harogok",
    "gn:population":0,
    "gn:timezone":"Asia/Seoul",
    "iso:country":"KR",
    "name:kor_x_preferred":[
        "\ud558\ub85c\uace1"
    ],
    "name:und_x_variant":[
        "Hanogol",
        "Ha-nogok",
        "Harogok"
    ],
    "wof:name":"Harogok",
    "wof:placetype":"locality"
},
  "geometry": {"coordinates":[127.22799000000001,36.7027],"type":"Point"}
}