{
  "type": "Feature",
  "properties": {
    "gn:admin1_code":"14.0",
    "gn:asciiname":"Kump'o",
    "gn:country_code":"KR",
    "gn:dem":370,
    "gn:feature_class":"P",
    "gn:feature_code":"PPL",
    "gn:name":"K\u016dmp\u2019o",
    "gn:population":0,
    "gn:timezone":"Asia/Seoul",
    "iso:country":"KR",
    "name:und_x_variant":[
        "\uae08\ud3ec",
        "K\u016dmp\u2019o"
    ],
    "wof:name":"Kump'o",
    "wof:placetype":"locality"
},
  "geometry": {"coordinates":[128.02513000000002,35.90992],"type":"Point"}
}