{
  "type": "Feature",
  "properties": {
    "gn:admin1_code":"20.0",
    "gn:asciiname":"Mullim-ni",
    "gn:country_code":"KR",
    "gn:dem":33,
    "gn:feature_class":"P",
    "gn:feature_code":"PPL",
    "gn:name":"Mullim-ni",
    "gn:population":0,
    "gn:timezone":"Asia/Seoul",
    "iso:country":"KR",
    "name:und_x_variant":[
        "\ubb38\ub9bc\ub9ac",
        "Mullim-ni"
    ],
    "wof:name":"Mullim-ni",
    "wof:placetype":"locality"
},
  "geometry": {"coordinates":[128.19155000000001,35.56991],"type":"Point"}
}