{
  "type": "Feature",
  "properties": {
    "gn:admin1_code":"3.0",
    "gn:asciiname":"Eungamchon",
    "gn:country_code":"KR",
    "gn:dem":52,
    "gn:feature_class":"P",
    "gn:feature_code":"PPL",
    "gn:name":"Eungamchon",
    "gn:population":0,
    "gn:timezone":"Asia/Seoul",
    "iso:country":"KR",
    "name:kor_x_preferred":[
        "\uc751\uc554\ucd0c"
    ],
    "wof:name":"Eungamchon",
    "wof:placetype":"locality"
},
  "geometry": {"coordinates":[126.63618,35.35612000000001],"type":"Point"}
}