{
  "type": "Feature",
  "properties": {
    "gn:admin1_code":"6.0",
    "gn:asciiname":"Sin'gi-ri",
    "gn:country_code":"KR",
    "gn:dem":91,
    "gn:feature_class":"P",
    "gn:feature_code":"PPL",
    "gn:name":"Sin\u2019gi-ri",
    "gn:population":0,
    "gn:timezone":"Asia/Seoul",
    "iso:country":"KR",
    "name:und_x_variant":[
        "\uc2e0\uae30\ub9ac",
        "Saet\u2019\u014f",
        "Sin\u2019gi-ri"
    ],
    "wof:name":"Sin'gi-ri",
    "wof:placetype":"locality"
},
  "geometry": {"coordinates":[129.0829,37.349],"type":"Point"}
}