{
  "type": "Feature",
  "properties": {
    "gn:admin1_code":"16.0",
    "gn:asciiname":"Wolsongjeong",
    "gn:country_code":"KR",
    "gn:dem":175,
    "gn:feature_class":"P",
    "gn:feature_code":"PPL",
    "gn:name":"Wolsongjeong",
    "gn:population":0,
    "gn:timezone":"Asia/Seoul",
    "iso:country":"KR",
    "name:kor_x_preferred":[
        "\uc6d4\uc1a1\uc815"
    ],
    "wof:name":"Wolsongjeong",
    "wof:placetype":"locality"
},
  "geometry": {"coordinates":[126.92024000000001,35.35988],"type":"Point"}
}