{
  "type": "Feature",
  "properties": {
    "gn:admin1_code":"16.0",
    "gn:asciiname":"Nakp'o-dong",
    "gn:country_code":"KR",
    "gn:dem":33,
    "gn:feature_class":"P",
    "gn:feature_code":"PPL",
    "gn:name":"Nakp\u2019o-dong",
    "gn:population":0,
    "gn:timezone":"Asia/Seoul",
    "iso:country":"KR",
    "name:und_x_variant":[
        "Nakp\u2019o-ri",
        "Nakp\u2019o-dong"
    ],
    "wof:name":"Nakp'o-dong",
    "wof:placetype":"locality"
},
  "geometry": {"coordinates":[127.75360999999999,34.84722],"type":"Point"}
}