{
  "type": "Feature",
  "properties": {
    "gn:admin1_code":"14.0",
    "gn:asciiname":"Miryong",
    "gn:country_code":"KR",
    "gn:dem":229,
    "gn:feature_class":"P",
    "gn:feature_code":"PPL",
    "gn:name":"Miryong",
    "gn:population":0,
    "gn:timezone":"Asia/Seoul",
    "iso:country":"KR",
    "name:und_x_variant":[
        "\ubbf8\ub8e1",
        "Miryong"
    ],
    "wof:name":"Miryong",
    "wof:placetype":"locality"
},
  "geometry": {"coordinates":[129.125,36.02274],"type":"Point"}
}