{
  "type": "Feature",
  "properties": {
    "gn:admin1_code":"15.0",
    "gn:asciiname":"Daedeok",
    "gn:country_code":"KR",
    "gn:dem":117,
    "gn:feature_class":"P",
    "gn:feature_code":"PPL",
    "gn:name":"Daedeok",
    "gn:population":0,
    "gn:timezone":"Asia/Seoul",
    "iso:country":"KR",
    "name:kor_x_preferred":[
        "\ub300\ub355"
    ],
    "name:und_x_variant":[
        "Taed\u014fk"
    ],
    "wof:name":"Daedeok",
    "wof:placetype":"locality"
},
  "geometry": {"coordinates":[128.66701,35.82715],"type":"Point"}
}