{
  "type": "Feature",
  "properties": {
    "gn:admin1_code":"14.0",
    "gn:asciiname":"Sapsil",
    "gn:country_code":"KR",
    "gn:dem":133,
    "gn:feature_class":"P",
    "gn:feature_code":"PPL",
    "gn:name":"Sapsil",
    "gn:population":0,
    "gn:timezone":"Asia/Seoul",
    "iso:country":"KR",
    "name:und_x_variant":[
        "\uc0bd\uc2e4",
        "Sapsil"
    ],
    "wof:name":"Sapsil",
    "wof:placetype":"locality"
},
  "geometry": {"coordinates":[128.88149999999999,36.4601],"type":"Point"}
}