{
  "type": "Feature",
  "properties": {
    "gn:admin1_code":"13.0",
    "gn:asciiname":"Toksal-li",
    "gn:country_code":"KR",
    "gn:dem":83,
    "gn:feature_class":"P",
    "gn:feature_code":"PPL",
    "gn:name":"Toksal-li",
    "gn:population":0,
    "gn:timezone":"Asia/Seoul",
    "iso:country":"KR",
    "name:kor_x_preferred":[
        "\ub3c5\uc0b0\ub9ac"
    ],
    "wof:name":"Toksal-li",
    "wof:placetype":"locality"
},
  "geometry": {"coordinates":[127.5072,37.6703],"type":"Point"}
}