{
  "type": "Feature",
  "properties": {
    "gn:admin1_code":"6.0",
    "gn:asciiname":"Koch'on",
    "gn:country_code":"KR",
    "gn:dem":85,
    "gn:feature_class":"P",
    "gn:feature_code":"PPL",
    "gn:name":"Koch\u2019\u014fn",
    "gn:population":0,
    "gn:timezone":"Asia/Seoul",
    "iso:country":"KR",
    "name:und_x_variant":[
        "\uace0\ucc9c",
        "Koch\u2019\u014fn"
    ],
    "wof:name":"Koch'on",
    "wof:placetype":"locality"
},
  "geometry": {"coordinates":[129.0616,37.4181],"type":"Point"}
}