{
  "type": "Feature",
  "properties": {
    "gn:admin1_code":"14.0",
    "gn:asciiname":"Maekkeut",
    "gn:country_code":"KR",
    "gn:dem":85,
    "gn:feature_class":"P",
    "gn:feature_code":"PPL",
    "gn:name":"Maekkeut",
    "gn:population":0,
    "gn:timezone":"Asia/Seoul",
    "iso:country":"KR",
    "name:kor_x_preferred":[
        "\ub9e4\ub05d"
    ],
    "wof:name":"Maekkeut",
    "wof:placetype":"locality"
},
  "geometry": {"coordinates":[129.25682,35.79469],"type":"Point"}
}