{
  "type": "Feature",
  "properties": {
    "gn:admin1_code":"16.0",
    "gn:asciiname":"Sesan",
    "gn:country_code":"KR",
    "gn:dem":16,
    "gn:feature_class":"P",
    "gn:feature_code":"PPL",
    "gn:name":"Sesan",
    "gn:population":0,
    "gn:timezone":"Asia/Seoul",
    "iso:country":"KR",
    "name:kor_x_preferred":[
        "\uc138\uc0b0"
    ],
    "wof:name":"Sesan",
    "wof:placetype":"locality"
},
  "geometry": {"coordinates":[126.65562,34.96847],"type":"Point"}
}