{
  "type": "Feature",
  "properties": {
    "gn:admin1_code":"21.0",
    "gn:asciiname":"Hwadong",
    "gn:country_code":"KR",
    "gn:dem":76,
    "gn:feature_class":"P",
    "gn:feature_code":"PPL",
    "gn:name":"Hwadong",
    "gn:population":0,
    "gn:timezone":"Asia/Seoul",
    "iso:country":"KR",
    "name:kor_x_preferred":[
        "\ud654\ub3d9"
    ],
    "wof:name":"Hwadong",
    "wof:placetype":"locality"
},
  "geometry": {"coordinates":[129.37379000000001,35.58897],"type":"Point"}
}