{
  "type": "Feature",
  "properties": {
    "gn:admin1_code":"14.0",
    "gn:asciiname":"Jungjigol",
    "gn:country_code":"KR",
    "gn:dem":79,
    "gn:feature_class":"P",
    "gn:feature_code":"PPL",
    "gn:name":"Jungjigol",
    "gn:population":0,
    "gn:timezone":"Asia/Seoul",
    "iso:country":"KR",
    "name:kor_x_preferred":[
        "\uc911\uc9c0\uace8"
    ],
    "wof:name":"Jungjigol",
    "wof:placetype":"locality"
},
  "geometry": {"coordinates":[129.44978999999998,35.89578],"type":"Point"}
}