{
  "type": "Feature",
  "properties": {
    "gn:admin1_code":"14.0",
    "gn:asciiname":"Dokjeom",
    "gn:country_code":"KR",
    "gn:dem":209,
    "gn:feature_class":"P",
    "gn:feature_code":"PPL",
    "gn:name":"Dokjeom",
    "gn:population":0,
    "gn:timezone":"Asia/Seoul",
    "iso:country":"KR",
    "name:kor_x_preferred":[
        "\ub3c5\uc810"
    ],
    "wof:name":"Dokjeom",
    "wof:placetype":"locality"
},
  "geometry": {"coordinates":[128.63121000000001,36.6087],"type":"Point"}
}