{
  "type": "Feature",
  "properties": {
    "gn:admin1_code":"14.0",
    "gn:asciiname":"Sin'gong-ni",
    "gn:country_code":"KR",
    "gn:dem":68,
    "gn:feature_class":"P",
    "gn:feature_code":"PPL",
    "gn:name":"Sin\u2019gong-ni",
    "gn:population":0,
    "gn:timezone":"Asia/Seoul",
    "iso:country":"KR",
    "name:eng_x_preferred":[
        "Sin'gong"
    ],
    "name:eng_x_variant":[
        "Sin'gong-ni"
    ],
    "name:und_x_variant":[
        "Sin\u2019gong-ni",
        "\uc2e0\uace1\ub9ac",
        "Sin\u2019gok-tong"
    ],
    "wof:name":"Sin'gong",
    "wof:placetype":"locality"
},
  "geometry": {"coordinates":[128.35028,36.3175],"type":"Point"}
}