{
  "type": "Feature",
  "properties": {
    "gn:admin1_code":"16.0",
    "gn:asciiname":"Jeomchon",
    "gn:country_code":"KR",
    "gn:dem":69,
    "gn:feature_class":"P",
    "gn:feature_code":"PPL",
    "gn:name":"Jeomchon",
    "gn:population":0,
    "gn:timezone":"Asia/Seoul",
    "iso:country":"KR",
    "name:kor_x_preferred":[
        "\uc810\ucd0c"
    ],
    "wof:name":"Jeomchon",
    "wof:placetype":"locality"
},
  "geometry": {"coordinates":[126.81028000000001,35.27148],"type":"Point"}
}