{
  "type": "Feature",
  "properties": {
    "gn:admin1_code":"10.0",
    "gn:asciiname":"Deunggu",
    "gn:country_code":"KR",
    "gn:dem":4,
    "gn:feature_class":"P",
    "gn:feature_code":"PPL",
    "gn:name":"Deunggu",
    "gn:population":0,
    "gn:timezone":"Asia/Seoul",
    "iso:country":"KR",
    "name:kor_x_preferred":[
        "\ub4f1\uad6c"
    ],
    "name:und_x_variant":[
        "Tunggu"
    ],
    "wof:name":"Deunggu",
    "wof:placetype":"locality"
},
  "geometry": {"coordinates":[128.96131,35.19378],"type":"Point"}
}