{
  "type": "Feature",
  "properties": {
    "gn:admin1_code":"5.0",
    "gn:asciiname":"Hayuam",
    "gn:country_code":"KR",
    "gn:dem":288,
    "gn:feature_class":"P",
    "gn:feature_code":"PPL",
    "gn:name":"Hayuam",
    "gn:population":0,
    "gn:timezone":"Asia/Seoul",
    "iso:country":"KR",
    "name:kor_x_preferred":[
        "\ud558\uc720\uc554"
    ],
    "wof:name":"Hayuam",
    "wof:placetype":"locality"
},
  "geometry": {"coordinates":[128.39230000000001,37.1476],"type":"Point"}
}