{
  "type": "Feature",
  "properties": {
    "gn:admin1_code":"14.0",
    "gn:asciiname":"Soe-gol",
    "gn:country_code":"KR",
    "gn:dem":351,
    "gn:feature_class":"P",
    "gn:feature_code":"PPL",
    "gn:name":"Soe-gol",
    "gn:population":0,
    "gn:timezone":"Asia/Seoul",
    "iso:country":"KR",
    "name:und_x_variant":[
        "\uc1e0\uace8",
        "Soe-gol"
    ],
    "wof:name":"Soe-gol",
    "wof:placetype":"locality"
},
  "geometry": {"coordinates":[128.876,36.3192],"type":"Point"}
}