{
  "type": "Feature",
  "properties": {
    "gn:admin1_code":"6.0",
    "gn:asciiname":"Saenmal",
    "gn:country_code":"KR",
    "gn:dem":532,
    "gn:feature_class":"P",
    "gn:feature_code":"PPL",
    "gn:name":"Saenmal",
    "gn:population":0,
    "gn:timezone":"Asia/Seoul",
    "iso:country":"KR",
    "name:kor_x_preferred":[
        "\uc0db\ub9d0"
    ],
    "wof:name":"Saenmal",
    "wof:placetype":"locality"
},
  "geometry": {"coordinates":[128.19051999999999,37.9512],"type":"Point"}
}