{
  "type": "Feature",
  "properties": {
    "gn:admin1_code":"6.0",
    "gn:asciiname":"Chonnam-gol",
    "gn:country_code":"KR",
    "gn:dem":401,
    "gn:feature_class":"P",
    "gn:feature_code":"PPL",
    "gn:name":"Ch\u014fnnam-gol",
    "gn:population":0,
    "gn:timezone":"Asia/Seoul",
    "iso:country":"KR",
    "name:kor_x_preferred":[
        "\uc804\ub0a8\uace8"
    ],
    "name:kor_x_variant":[
        "Ch\u014fnnam-gol"
    ],
    "wof:name":"Chonnam-gol",
    "wof:placetype":"locality"
},
  "geometry": {"coordinates":[128.65719999999999,37.17],"type":"Point"}
}