{
  "type": "Feature",
  "properties": {
    "gn:admin1_code":"14.0",
    "gn:asciiname":"Geumdan",
    "gn:country_code":"KR",
    "gn:dem":37,
    "gn:feature_class":"P",
    "gn:feature_code":"PPL",
    "gn:name":"Geumdan",
    "gn:population":0,
    "gn:timezone":"Asia/Seoul",
    "iso:country":"KR",
    "name:kor_x_preferred":[
        "\uae08\ub2e8"
    ],
    "name:und_x_variant":[
        "K\u016dmdan-dong",
        "K\u016dmdan",
        "Geumdan"
    ],
    "wof:name":"Geumdan",
    "wof:placetype":"locality"
},
  "geometry": {"coordinates":[129.39476000000002,36.1634],"type":"Point"}
}