{
  "type": "Feature",
  "properties": {
    "gn:admin1_code":"14.0",
    "gn:asciiname":"Hung-dong",
    "gn:country_code":"KR",
    "gn:dem":404,
    "gn:feature_class":"P",
    "gn:feature_code":"PPL",
    "gn:name":"H\u016dng-dong",
    "gn:population":0,
    "gn:timezone":"Asia/Seoul",
    "iso:country":"KR",
    "wof:name":"Hung-dong",
    "wof:placetype":"locality"
},
  "geometry": {"coordinates":[128.84999999999999,36.36667],"type":"Point"}
}