{
  "type": "Feature",
  "properties": {
    "gn:admin1_code":"5.0",
    "gn:asciiname":"Hahyonch'on",
    "gn:country_code":"KR",
    "gn:dem":375,
    "gn:feature_class":"P",
    "gn:feature_code":"PPL",
    "gn:name":"Hahy\u014fnch\u2019\u014fn",
    "gn:population":0,
    "gn:timezone":"Asia/Seoul",
    "iso:country":"KR",
    "wof:name":"Hahyonch'on",
    "wof:placetype":"locality"
},
  "geometry": {"coordinates":[128.33888999999999,36.95361],"type":"Point"}
}