{
  "type": "Feature",
  "properties": {
    "gn:admin1_code":"6.0",
    "gn:asciiname":"Hambawi",
    "gn:country_code":"KR",
    "gn:dem":551,
    "gn:feature_class":"P",
    "gn:feature_code":"PPL",
    "gn:name":"Hambawi",
    "gn:population":0,
    "gn:timezone":"Asia/Seoul",
    "iso:country":"KR",
    "name:kor_x_preferred":[
        "\ud568\ubc14\uc704"
    ],
    "name:und_x_variant":[
        "Paekpau",
        "Hambawi"
    ],
    "wof:name":"Hambawi",
    "wof:placetype":"locality"
},
  "geometry": {"coordinates":[128.76990000000001,37.3981],"type":"Point"}
}