{
  "type": "Feature",
  "properties": {
    "gn:admin1_code":"20.0",
    "gn:asciiname":"Chunghwa-ri",
    "gn:country_code":"KR",
    "gn:dem":10,
    "gn:feature_class":"P",
    "gn:feature_code":"PPL",
    "gn:name":"Chunghwa-ri",
    "gn:population":0,
    "gn:timezone":"Asia/Seoul",
    "iso:country":"KR",
    "name:und_x_variant":[
        "Chunghwa-dong",
        "\uc911\ud654\ub9ac",
        "Chunghwa",
        "Chunghwa-ri"
    ],
    "wof:name":"Chunghwa-ri",
    "wof:placetype":"locality"
},
  "geometry": {"coordinates":[128.39104,34.78999],"type":"Point"}
}