{
  "type": "Feature",
  "properties": {
    "gn:admin1_code":"6.0",
    "gn:asciiname":"Hannae-ri",
    "gn:country_code":"KR",
    "gn:dem":547,
    "gn:feature_class":"P",
    "gn:feature_code":"PPL",
    "gn:name":"Hannae-ri",
    "gn:population":0,
    "gn:timezone":"Asia/Seoul",
    "iso:country":"KR",
    "name:und_x_variant":[
        "Kannai-ri",
        "Hamtae",
        "\ud55c\ub0b4\ub9ac",
        "Hannae-ri"
    ],
    "wof:name":"Hannae-ri",
    "wof:placetype":"locality"
},
  "geometry": {"coordinates":[129.01769999999999,37.2881],"type":"Point"}
}