{
  "type": "Feature",
  "properties": {
    "gn:admin1_code":"20.0",
    "gn:asciiname":"Segal-li",
    "gn:country_code":"KR",
    "gn:dem":31,
    "gn:feature_class":"P",
    "gn:feature_code":"PPL",
    "gn:name":"Segal-li",
    "gn:population":0,
    "gn:timezone":"Asia/Seoul",
    "iso:country":"KR",
    "name:und_x_variant":[
        "\uc138\uac04\ub9ac",
        "Segal-li"
    ],
    "wof:name":"Segal-li",
    "wof:placetype":"locality"
},
  "geometry": {"coordinates":[128.34434999999999,35.43751],"type":"Point"}
}