{
  "type": "Feature",
  "properties": {
    "gn:admin1_code":"16.0",
    "gn:asciiname":"Fundo-ri",
    "gn:country_code":"KR",
    "gn:dem":89,
    "gn:feature_class":"P",
    "gn:feature_code":"PPL",
    "gn:name":"Fundo-ri",
    "gn:population":0,
    "gn:timezone":"Asia/Seoul",
    "iso:country":"KR",
    "name:und_x_variant":[
        "Punt\u2019o",
        "Punt\u2019o-ri"
    ],
    "wof:name":"Fundo-ri",
    "wof:placetype":"locality"
},
  "geometry": {"coordinates":[126.28333000000001,34.51667],"type":"Point"}
}