{
  "type": "Feature",
  "properties": {
    "gn:admin1_code":"6.0",
    "gn:asciiname":"Tangmuk-kol",
    "gn:country_code":"KR",
    "gn:dem":529,
    "gn:feature_class":"P",
    "gn:feature_code":"PPL",
    "gn:name":"Tangmuk-kol",
    "gn:population":0,
    "gn:timezone":"Asia/Seoul",
    "iso:country":"KR",
    "name:kor_x_preferred":[
        "\ub2f9\ubb35\uace8"
    ],
    "wof:name":"Tangmuk-kol",
    "wof:placetype":"locality"
},
  "geometry": {"coordinates":[128.77850000000001,37.6342],"type":"Point"}
}