{
  "type": "Feature",
  "properties": {
    "gn:admin1_code":"5.0",
    "gn:asciiname":"Mareumgol",
    "gn:country_code":"KR",
    "gn:dem":88,
    "gn:feature_class":"P",
    "gn:feature_code":"PPL",
    "gn:name":"Mareumgol",
    "gn:population":0,
    "gn:timezone":"Asia/Seoul",
    "iso:country":"KR",
    "name:und_x_variant":[
        "\ub9c8\ub984\uace8",
        "Mar\u016dm-gol",
        "Mareumgol"
    ],
    "wof:name":"Mareumgol",
    "wof:placetype":"locality"
},
  "geometry": {"coordinates":[127.54649000000001,36.4352],"type":"Point"}
}