{
  "type": "Feature",
  "properties": {
    "gn:admin1_code":"5.0",
    "gn:asciiname":"Gaeoji",
    "gn:country_code":"KR",
    "gn:dem":127,
    "gn:feature_class":"P",
    "gn:feature_code":"PPL",
    "gn:name":"Gaeoji",
    "gn:population":0,
    "gn:timezone":"Asia/Seoul",
    "iso:country":"KR",
    "name:kor_x_preferred":[
        "\uac1c\uc624\uc9c0"
    ],
    "wof:name":"Gaeoji",
    "wof:placetype":"locality"
},
  "geometry": {"coordinates":[127.56878,36.97964],"type":"Point"}
}