{
  "type": "Feature",
  "properties": {
    "gn:admin1_code":"11.0",
    "gn:asciiname":"Seorim-dong",
    "gn:country_code":"KR",
    "gn:dem":53,
    "gn:feature_class":"P",
    "gn:feature_code":"PPL",
    "gn:name":"Seorim-dong",
    "gn:population":0,
    "gn:timezone":"Asia/Seoul",
    "iso:country":"KR",
    "name:eng_x_preferred":[
        "Seorim-dong"
    ],
    "name:kor_x_preferred":[
        "\uc11c\ub9bc\ub3d9"
    ],
    "wof:name":"Seorim-dong",
    "wof:placetype":"locality"
},
  "geometry": {"coordinates":[126.93805999999999,37.47389],"type":"Point"}
}