{
  "type": "Feature",
  "properties": {
    "gn:admin1_code":"20.0",
    "gn:asciiname":"Mae-ch'on",
    "gn:country_code":"KR",
    "gn:dem":165,
    "gn:feature_class":"P",
    "gn:feature_code":"PPL",
    "gn:name":"Mae-ch\u2019on",
    "gn:population":0,
    "gn:timezone":"Asia/Seoul",
    "iso:country":"KR",
    "name:und_x_variant":[
        "\ub9e4\ucd0c",
        "Mae-ch\u2019on"
    ],
    "wof:name":"Mae-ch'on",
    "wof:placetype":"locality"
},
  "geometry": {"coordinates":[127.75913,35.51598],"type":"Point"}
}