{
  "type": "Feature",
  "properties": {
    "gn:admin1_code":"6.0",
    "gn:asciiname":"Wippodung",
    "gn:country_code":"KR",
    "gn:dem":181,
    "gn:feature_class":"P",
    "gn:feature_code":"PPL",
    "gn:name":"Wipp\u014fd\u016dng",
    "gn:population":0,
    "gn:timezone":"Asia/Seoul",
    "iso:country":"KR",
    "name:und_x_variant":[
        "\uc717\ubc84\ub4f1",
        "Wipp\u014fd\u016dng"
    ],
    "wof:name":"Wippodung",
    "wof:placetype":"locality"
},
  "geometry": {"coordinates":[127.59869999999999,37.9745],"type":"Point"}
}