{
  "type": "Feature",
  "properties": {
    "gn:admin1_code":"21.0",
    "gn:asciiname":"Saegakdan",
    "gn:country_code":"KR",
    "gn:dem":37,
    "gn:feature_class":"P",
    "gn:feature_code":"PPL",
    "gn:name":"Saegakdan",
    "gn:population":0,
    "gn:timezone":"Asia/Seoul",
    "iso:country":"KR",
    "name:kor_x_preferred":[
        "\uc0c8\uac01\ub2e8"
    ],
    "wof:name":"Saegakdan",
    "wof:placetype":"locality"
},
  "geometry": {"coordinates":[129.24549999999999,35.43615],"type":"Point"}
}