{
  "type": "Feature",
  "properties": {
    "gn:admin1_code":"6.0",
    "gn:asciiname":"Bonguiteogol",
    "gn:country_code":"KR",
    "gn:dem":298,
    "gn:feature_class":"P",
    "gn:feature_code":"PPL",
    "gn:name":"Bonguiteogol",
    "gn:population":0,
    "gn:timezone":"Asia/Seoul",
    "iso:country":"KR",
    "name:kor_x_preferred":[
        "\ubd09\uc758\ud130\uace8"
    ],
    "name:und_x_variant":[
        "\ubd09\uc5d0\ud130\uace8",
        "Ponget\u2019\u014f-gol",
        "Bonguiteogol"
    ],
    "wof:name":"Bonguiteogol",
    "wof:placetype":"locality"
},
  "geometry": {"coordinates":[127.6998,37.77193],"type":"Point"}
}