{
  "type": "Feature",
  "properties": {
    "gn:admin1_code":"13.0",
    "gn:asciiname":"Keuncheongtan",
    "gn:country_code":"KR",
    "gn:dem":50,
    "gn:feature_class":"P",
    "gn:feature_code":"PPL",
    "gn:name":"Keuncheongtan",
    "gn:population":0,
    "gn:timezone":"Asia/Seoul",
    "iso:country":"KR",
    "name:kor_x_preferred":[
        "\ud070\uccad\ud0c4"
    ],
    "name:und_x_variant":[
        "Taech\u014fngt\u2019an",
        "\ud070\uccad\ud0c4",
        "Keuncheongtan",
        "K\u2019\u016dnch\u2019\u014fngt\u2019an"
    ],
    "wof:name":"Keuncheongtan",
    "wof:placetype":"locality"
},
  "geometry": {"coordinates":[127.37139000000001,37.5025],"type":"Point"}
}