{
  "type": "Feature",
  "properties": {
    "gn:admin1_code":"3.0",
    "gn:asciiname":"Taech'ang",
    "gn:country_code":"KR",
    "gn:dem":146,
    "gn:feature_class":"P",
    "gn:feature_code":"PPL",
    "gn:name":"Taech\u2019ang",
    "gn:population":0,
    "gn:timezone":"Asia/Seoul",
    "iso:country":"KR",
    "name:und_x_variant":[
        "\ub300\ucc3d",
        "Taech\u2019ang"
    ],
    "wof:name":"Taech'ang",
    "wof:placetype":"locality"
},
  "geometry": {"coordinates":[127.38624,35.58105],"type":"Point"}
}