{
  "type": "Feature",
  "properties": {
    "gn:admin1_code":"17.0",
    "gn:asciiname":"Ilsingi",
    "gn:country_code":"KR",
    "gn:dem":68,
    "gn:feature_class":"P",
    "gn:feature_code":"PPL",
    "gn:name":"Ilsingi",
    "gn:population":0,
    "gn:timezone":"Asia/Seoul",
    "iso:country":"KR",
    "name:kor_x_preferred":[
        "\uc77c\uc2e0\uae30"
    ],
    "wof:name":"Ilsingi",
    "wof:placetype":"locality"
},
  "geometry": {"coordinates":[127.23921,36.74101],"type":"Point"}
}