{
  "type": "Feature",
  "properties": {
    "gn:admin1_code":"14.0",
    "gn:asciiname":"Jangdari",
    "gn:country_code":"KR",
    "gn:dem":41,
    "gn:feature_class":"P",
    "gn:feature_code":"PPL",
    "gn:name":"Jangdari",
    "gn:population":0,
    "gn:timezone":"Asia/Seoul",
    "iso:country":"KR",
    "name:kor_x_preferred":[
        "\uc7a5\ub2ec\uc774"
    ],
    "name:und_x_variant":[
        "\uc7a5\ub2e4\ub9ac",
        "Changda-ri",
        "Jangdari"
    ],
    "wof:name":"Jangdari",
    "wof:placetype":"locality"
},
  "geometry": {"coordinates":[128.42775,35.98219],"type":"Point"}
}