{
  "type": "Feature",
  "properties": {
    "gn:admin1_code":"6.0",
    "gn:asciiname":"Wongol",
    "gn:country_code":"KR",
    "gn:dem":177,
    "gn:feature_class":"P",
    "gn:feature_code":"PPL",
    "gn:name":"Wongol",
    "gn:population":0,
    "gn:timezone":"Asia/Seoul",
    "iso:country":"KR",
    "name:kor_x_preferred":[
        "\uc6d0\uace8"
    ],
    "name:kor_x_variant":[
        "W\u014fn-gol"
    ],
    "wof:name":"Wongol",
    "wof:placetype":"locality"
},
  "geometry": {"coordinates":[127.8374,37.7271],"type":"Point"}
}