{
  "type": "Feature",
  "properties": {
    "gn:admin1_code":"16.0",
    "gn:asciiname":"Samgo-ri",
    "gn:country_code":"KR",
    "gn:dem":72,
    "gn:feature_class":"P",
    "gn:feature_code":"PPL",
    "gn:name":"Samg\u014f-ri",
    "gn:population":0,
    "gn:timezone":"Asia/Seoul",
    "iso:country":"KR",
    "name:kor_x_preferred":[
        "Samg\u014f-ri"
    ],
    "wof:name":"Samgo-ri",
    "wof:placetype":"locality"
},
  "geometry": {"coordinates":[126.64306000000001,34.49556],"type":"Point"}
}