{
  "type": "Feature",
  "properties": {
    "gn:admin1_code":"3.0",
    "gn:asciiname":"Yongch'u-ri",
    "gn:country_code":"KR",
    "gn:dem":491,
    "gn:feature_class":"P",
    "gn:feature_code":"PPL",
    "gn:name":"Yongch\u2019u-ri",
    "gn:population":0,
    "gn:timezone":"Asia/Seoul",
    "iso:country":"KR",
    "name:und_x_variant":[
        "\uc6a9\ucd94\ub9ac",
        "Yongch\u2019u-ri"
    ],
    "wof:name":"Yongch'u-ri",
    "wof:placetype":"locality"
},
  "geometry": {"coordinates":[127.68137,35.84433],"type":"Point"}
}