{
  "type": "Feature",
  "properties": {
    "gn:admin1_code":"13.0",
    "gn:asciiname":"Seomi-gol",
    "gn:country_code":"KR",
    "gn:dem":216,
    "gn:feature_class":"P",
    "gn:feature_code":"PPL",
    "gn:name":"Seomi-gol",
    "gn:population":0,
    "gn:timezone":"Asia/Seoul",
    "iso:country":"KR",
    "name:und_x_variant":[
        "\uc11c\ubbf8\uace8",
        "Seomi-gol",
        "S\u014fmi-gol"
    ],
    "wof:name":"Seomi-gol",
    "wof:placetype":"locality"
},
  "geometry": {"coordinates":[127.39722,37.40056],"type":"Point"}
}