{
  "type": "Feature",
  "properties": {
    "gn:admin1_code":"17.0",
    "gn:asciiname":"Sahyeon",
    "gn:country_code":"KR",
    "gn:dem":77,
    "gn:feature_class":"P",
    "gn:feature_code":"PPL",
    "gn:name":"Sahyeon",
    "gn:population":0,
    "gn:timezone":"Asia/Seoul",
    "iso:country":"KR",
    "name:und_x_variant":[
        "\uc0ac\ud604",
        "Sahy\u014fn",
        "Sahyeon"
    ],
    "wof:name":"Sahyeon",
    "wof:placetype":"locality"
},
  "geometry": {"coordinates":[127.16938,36.26849],"type":"Point"}
}