{
  "type": "Feature",
  "properties": {
    "gn:admin1_code":"14.0",
    "gn:asciiname":"Sanggong-ni",
    "gn:country_code":"KR",
    "gn:dem":37,
    "gn:feature_class":"P",
    "gn:feature_code":"PPL",
    "gn:name":"Sanggong-ni",
    "gn:population":0,
    "gn:timezone":"Asia/Seoul",
    "iso:country":"KR",
    "name:eng_x_preferred":[
        "Sanggong"
    ],
    "name:eng_x_variant":[
        "Sanggong-ni"
    ],
    "name:und_x_variant":[
        "\uc0c1\uace1\ub9ac",
        "Sanggong-ni"
    ],
    "wof:name":"Sanggong",
    "wof:placetype":"locality"
},
  "geometry": {"coordinates":[128.44512,35.82851],"type":"Point"}
}