{
  "type": "Feature",
  "properties": {
    "gn:admin1_code":"16.0",
    "gn:asciiname":"Seongjeon",
    "gn:country_code":"KR",
    "gn:dem":27,
    "gn:feature_class":"P",
    "gn:feature_code":"PPL",
    "gn:name":"Seongjeon",
    "gn:population":0,
    "gn:timezone":"Asia/Seoul",
    "iso:country":"KR",
    "name:kor_x_preferred":[
        "\uc131\uc804"
    ],
    "name:kor_x_variant":[
        "S\u014fngj\u014fn"
    ],
    "wof:name":"Seongjeon",
    "wof:placetype":"locality"
},
  "geometry": {"coordinates":[126.65472,34.6475],"type":"Point"}
}