{
  "type": "Feature",
  "properties": {
    "gn:admin1_code":"17.0",
    "gn:asciiname":"Kap-kol",
    "gn:country_code":"KR",
    "gn:dem":88,
    "gn:feature_class":"P",
    "gn:feature_code":"PPL",
    "gn:name":"Kap-kol",
    "gn:population":0,
    "gn:timezone":"Asia/Seoul",
    "iso:country":"KR",
    "name:und_x_variant":[
        "\uac11\uace8",
        "Kap-kol"
    ],
    "wof:name":"Kap-kol",
    "wof:placetype":"locality"
},
  "geometry": {"coordinates":[126.63979999999999,36.8177],"type":"Point"}
}