{
  "type": "Feature",
  "properties": {
    "gn:admin1_code":"17.0",
    "gn:asciiname":"Soenaegol",
    "gn:country_code":"KR",
    "gn:dem":230,
    "gn:feature_class":"P",
    "gn:feature_code":"PPL",
    "gn:name":"Soenaegol",
    "gn:population":0,
    "gn:timezone":"Asia/Seoul",
    "iso:country":"KR",
    "name:kor_x_preferred":[
        "\uc1e0\ub0b4\uace8"
    ],
    "wof:name":"Soenaegol",
    "wof:placetype":"locality"
},
  "geometry": {"coordinates":[127.15038,36.63533],"type":"Point"}
}