{
  "type": "Feature",
  "properties": {
    "gn:admin1_code":"6.0",
    "gn:asciiname":"Noksu-gol",
    "gn:country_code":"KR",
    "gn:dem":555,
    "gn:feature_class":"P",
    "gn:feature_code":"PPL",
    "gn:name":"Noksu-gol",
    "gn:population":0,
    "gn:timezone":"Asia/Seoul",
    "iso:country":"KR",
    "name:kor_x_preferred":[
        "\ub179\uc218\uace8"
    ],
    "wof:name":"Noksu-gol",
    "wof:placetype":"locality"
},
  "geometry": {"coordinates":[128.27070000000001,37.7906],"type":"Point"}
}