{
  "type": "Feature",
  "properties": {
    "gn:admin1_code":"17.0",
    "gn:asciiname":"Maeap-kol",
    "gn:country_code":"KR",
    "gn:dem":8,
    "gn:feature_class":"P",
    "gn:feature_code":"PPL",
    "gn:name":"Maeap-kol",
    "gn:population":0,
    "gn:timezone":"Asia/Seoul",
    "iso:country":"KR",
    "name:und_x_variant":[
        "\ub9e4\uc55e\uace8",
        "Maeap-kol"
    ],
    "wof:name":"Maeap-kol",
    "wof:placetype":"locality"
},
  "geometry": {"coordinates":[126.31019999999999,36.6251],"type":"Point"}
}