{
  "type": "Feature",
  "properties": {
    "gn:admin1_code":"6.0",
    "gn:asciiname":"Chumul-li",
    "gn:country_code":"KR",
    "gn:dem":25,
    "gn:feature_class":"P",
    "gn:feature_code":"PPLL",
    "gn:name":"Chumul-li",
    "gn:population":0,
    "gn:timezone":"Asia/Seoul",
    "iso:country":"KR",
    "name:kor_x_preferred":[
        "\uc8fc\ubb38\ub9ac"
    ],
    "wof:name":"Chumul-li",
    "wof:placetype":"locality"
},
  "geometry": {"coordinates":[128.81501,37.89437],"type":"Point"}
}