{
  "type": "Feature",
  "properties": {
    "gn:admin1_code":"6.0",
    "gn:asciiname":"Dangnim",
    "gn:country_code":"KR",
    "gn:dem":62,
    "gn:feature_class":"P",
    "gn:feature_code":"PPL",
    "gn:name":"Dangnim",
    "gn:population":0,
    "gn:timezone":"Asia/Seoul",
    "iso:country":"KR",
    "name:und_x_variant":[
        "\ub2f9\ub9bc",
        "Tangnim",
        "Dangnim"
    ],
    "wof:name":"Dangnim",
    "wof:placetype":"locality"
},
  "geometry": {"coordinates":[127.63122,37.81908],"type":"Point"}
}