{
  "type": "Feature",
  "properties": {
    "gn:admin1_code":"16.0",
    "gn:asciiname":"Jachagol",
    "gn:country_code":"KR",
    "gn:dem":110,
    "gn:feature_class":"P",
    "gn:feature_code":"PPL",
    "gn:name":"Jachagol",
    "gn:population":0,
    "gn:timezone":"Asia/Seoul",
    "iso:country":"KR",
    "name:kor_x_preferred":[
        "\uc790\ucc28\uace8"
    ],
    "wof:name":"Jachagol",
    "wof:placetype":"locality"
},
  "geometry": {"coordinates":[126.78941,35.34133],"type":"Point"}
}