{
  "type": "Feature",
  "properties": {
    "gn:admin1_code":"15.0",
    "gn:asciiname":"Hansil",
    "gn:country_code":"KR",
    "gn:dem":92,
    "gn:feature_class":"P",
    "gn:feature_code":"PPL",
    "gn:name":"Hansil",
    "gn:population":0,
    "gn:timezone":"Asia/Seoul",
    "iso:country":"KR",
    "name:kor_x_preferred":[
        "\ud55c\uc2e4"
    ],
    "wof:name":"Hansil",
    "wof:placetype":"locality"
},
  "geometry": {"coordinates":[128.52948000000001,35.79356],"type":"Point"}
}