{
  "type": "Feature",
  "properties": {
    "gn:admin1_code":"18.0",
    "gn:asciiname":"Seungchon",
    "gn:country_code":"KR",
    "gn:dem":13,
    "gn:feature_class":"P",
    "gn:feature_code":"PPL",
    "gn:name":"Seungchon",
    "gn:population":0,
    "gn:timezone":"Asia/Seoul",
    "iso:country":"KR",
    "name:kor_x_preferred":[
        "\uc2b9\ucd0c"
    ],
    "name:und_x_variant":[
        "S\u016dngch\u2019on-ni",
        "S\u016dngch\u2019on",
        "Seungchon"
    ],
    "wof:name":"Seungchon",
    "wof:placetype":"locality"
},
  "geometry": {"coordinates":[126.78694,35.05848],"type":"Point"}
}