{
  "type": "Feature",
  "properties": {
    "gn:admin1_code":"13.0",
    "gn:asciiname":"Paegun-dong",
    "gn:country_code":"KR",
    "gn:dem":113,
    "gn:feature_class":"P",
    "gn:feature_code":"PPL",
    "gn:name":"Paegun-dong",
    "gn:population":0,
    "gn:timezone":"Asia/Seoul",
    "iso:country":"KR",
    "name:und_x_variant":[
        "\ubc31\uc6b4\ub3d9",
        "Baegun-dong",
        "Paegun-dong"
    ],
    "wof:name":"Paegun-dong",
    "wof:placetype":"locality"
},
  "geometry": {"coordinates":[126.99694,37.35667],"type":"Point"}
}