{
  "type": "Feature",
  "properties": {
    "gn:admin1_code":"14.0",
    "gn:asciiname":"Yeonggak",
    "gn:country_code":"KR",
    "gn:dem":116,
    "gn:feature_class":"P",
    "gn:feature_code":"PPL",
    "gn:name":"Yeonggak",
    "gn:population":0,
    "gn:timezone":"Asia/Seoul",
    "iso:country":"KR",
    "name:kor_x_preferred":[
        "\uc601\uac01"
    ],
    "wof:name":"Yeonggak",
    "wof:placetype":"locality"
},
  "geometry": {"coordinates":[128.26973000000001,36.66981],"type":"Point"}
}