{
  "type": "Feature",
  "properties": {
    "gn:admin1_code":"6.0",
    "gn:asciiname":"Simugae",
    "gn:country_code":"KR",
    "gn:dem":129,
    "gn:feature_class":"P",
    "gn:feature_code":"PPL",
    "gn:name":"Simugae",
    "gn:population":0,
    "gn:timezone":"Asia/Seoul",
    "iso:country":"KR",
    "name:kor_x_preferred":[
        "\uc2dc\ubb34\uac1c"
    ],
    "wof:name":"Simugae",
    "wof:placetype":"locality"
},
  "geometry": {"coordinates":[127.80287,37.72117],"type":"Point"}
}