{
  "type": "Feature",
  "properties": {
    "gn:admin1_code":"16.0",
    "gn:asciiname":"Nodu",
    "gn:country_code":"KR",
    "gn:dem":173,
    "gn:feature_class":"P",
    "gn:feature_code":"PPL",
    "gn:name":"Nodu",
    "gn:population":0,
    "gn:timezone":"Asia/Seoul",
    "iso:country":"KR",
    "name:kor_x_preferred":[
        "\ub178\ubcc0"
    ],
    "name:kor_x_variant":[
        "Noby\u014fn",
        "\ub178\ub450"
    ],
    "wof:name":"Nodu",
    "wof:placetype":"locality"
},
  "geometry": {"coordinates":[127.44168000000001,34.97095],"type":"Point"}
}