{
  "type": "Feature",
  "properties": {
    "gn:admin1_code":"3.0",
    "gn:asciiname":"Yangson",
    "gn:country_code":"KR",
    "gn:dem":420,
    "gn:feature_class":"P",
    "gn:feature_code":"PPL",
    "gn:name":"Yangs\u014fn",
    "gn:population":0,
    "gn:timezone":"Asia/Seoul",
    "iso:country":"KR",
    "name:und_x_variant":[
        "\uc591\uc120",
        "Yangs\u014fn"
    ],
    "wof:name":"Yangson",
    "wof:placetype":"locality"
},
  "geometry": {"coordinates":[127.52211,35.66365],"type":"Point"}
}