{
  "type": "Feature",
  "properties": {
    "gn:admin1_code":"16.0",
    "gn:asciiname":"Pyeongjeon",
    "gn:country_code":"KR",
    "gn:dem":84,
    "gn:feature_class":"P",
    "gn:feature_code":"PPL",
    "gn:name":"Pyeongjeon",
    "gn:population":0,
    "gn:timezone":"Asia/Seoul",
    "iso:country":"KR",
    "name:kor_x_preferred":[
        "\ud3c9\uc804"
    ],
    "wof:name":"Pyeongjeon",
    "wof:placetype":"locality"
},
  "geometry": {"coordinates":[126.65300000000001,35.09246],"type":"Point"}
}