{
  "type": "Feature",
  "properties": {
    "gn:admin1_code":"14.0",
    "gn:asciiname":"Seondumal",
    "gn:country_code":"KR",
    "gn:dem":39,
    "gn:feature_class":"P",
    "gn:feature_code":"PPL",
    "gn:name":"Seondumal",
    "gn:population":0,
    "gn:timezone":"Asia/Seoul",
    "iso:country":"KR",
    "name:kor_x_preferred":[
        "\uc120\ub450\ub9d0"
    ],
    "wof:name":"Seondumal",
    "wof:placetype":"locality"
},
  "geometry": {"coordinates":[129.19030000000001,35.81282],"type":"Point"}
}