{
  "type": "Feature",
  "properties": {
    "gn:admin1_code":"13.0",
    "gn:asciiname":"Kojal-li",
    "gn:country_code":"KR",
    "gn:dem":32,
    "gn:feature_class":"P",
    "gn:feature_code":"PPLL",
    "gn:name":"Kojal-li",
    "gn:population":0,
    "gn:timezone":"Asia/Seoul",
    "iso:country":"KR",
    "name:und_x_variant":[
        "\uace0\uc794\ub9ac",
        "Gojan-ri",
        "Kojal-li"
    ],
    "wof:name":"Kojal-li",
    "wof:placetype":"locality"
},
  "geometry": {"coordinates":[126.90889,37.06083],"type":"Point"}
}