{
  "type": "Feature",
  "properties": {
    "gn:admin1_code":"16.0",
    "gn:asciiname":"Mangnam",
    "gn:country_code":"KR",
    "gn:dem":73,
    "gn:feature_class":"P",
    "gn:feature_code":"PPL",
    "gn:name":"Mangnam",
    "gn:population":0,
    "gn:timezone":"Asia/Seoul",
    "iso:country":"KR",
    "name:kor_x_preferred":[
        "\ub9dd\ub0a8"
    ],
    "name:und_x_variant":[
        "Mangnam-ni",
        "Mangnam"
    ],
    "wof:name":"Mangnam",
    "wof:placetype":"locality"
},
  "geometry": {"coordinates":[126.75943999999998,34.29667],"type":"Point"}
}