{
  "type": "Feature",
  "properties": {
    "gn:admin1_code":"14.0",
    "gn:asciiname":"Tungp'yong",
    "gn:country_code":"KR",
    "gn:dem":258,
    "gn:feature_class":"P",
    "gn:feature_code":"PPL",
    "gn:name":"T\u016dngp\u2019y\u014fng",
    "gn:population":0,
    "gn:timezone":"Asia/Seoul",
    "iso:country":"KR",
    "wof:name":"Tungp'yong",
    "wof:placetype":"locality"
},
  "geometry": {"coordinates":[128.81056000000001,36.24056],"type":"Point"}
}