{
  "type": "Feature",
  "properties": {
    "gn:admin1_code":"5.0",
    "gn:asciiname":"Anbaraemi",
    "gn:country_code":"KR",
    "gn:dem":107,
    "gn:feature_class":"P",
    "gn:feature_code":"PPL",
    "gn:name":"Anbaraemi",
    "gn:population":0,
    "gn:timezone":"Asia/Seoul",
    "iso:country":"KR",
    "name:kor_x_preferred":[
        "\uc548\ubc14\ub798\ubbf8"
    ],
    "wof:name":"Anbaraemi",
    "wof:placetype":"locality"
},
  "geometry": {"coordinates":[127.59099000000001,36.99312000000001],"type":"Point"}
}