{
  "type": "Feature",
  "properties": {
    "gn:admin1_code":"6.0",
    "gn:asciiname":"Maesang-gol",
    "gn:country_code":"KR",
    "gn:dem":723,
    "gn:feature_class":"P",
    "gn:feature_code":"PPL",
    "gn:name":"Maesang-gol",
    "gn:population":0,
    "gn:timezone":"Asia/Seoul",
    "iso:country":"KR",
    "name:und_x_variant":[
        "\ub9e4\uc0c1\uace8",
        "Maesang-gol"
    ],
    "wof:name":"Maesang-gol",
    "wof:placetype":"locality"
},
  "geometry": {"coordinates":[129.07560000000001,37.1166],"type":"Point"}
}