{
  "type": "Feature",
  "properties": {
    "gn:admin1_code":"17.0",
    "gn:asciiname":"Chebijae",
    "gn:country_code":"KR",
    "gn:dem":93,
    "gn:feature_class":"P",
    "gn:feature_code":"PPL",
    "gn:name":"Chebijae",
    "gn:population":0,
    "gn:timezone":"Asia/Seoul",
    "iso:country":"KR",
    "name:und_x_variant":[
        "\uc81c\ube44\uc7ac",
        "Chebijae"
    ],
    "wof:name":"Chebijae",
    "wof:placetype":"locality"
},
  "geometry": {"coordinates":[126.7971,36.4367],"type":"Point"}
}