{
  "type": "Feature",
  "properties": {
    "gn:admin1_code":"16.0",
    "gn:asciiname":"Ongnyong",
    "gn:country_code":"KR",
    "gn:dem":20,
    "gn:feature_class":"P",
    "gn:feature_code":"PPL",
    "gn:name":"Ongnyong",
    "gn:population":0,
    "gn:timezone":"Asia/Seoul",
    "iso:country":"KR",
    "name:kor_x_preferred":[
        "\uc625\ub8e1"
    ],
    "name:und_x_variant":[
        "Chinmakk\u016dm",
        "Ongnyong-ni",
        "Ongnyong"
    ],
    "wof:name":"Ongnyong",
    "wof:placetype":"locality"
},
  "geometry": {"coordinates":[127.12586,34.43687],"type":"Point"}
}