{
  "type": "Feature",
  "properties": {
    "gn:admin1_code":"6.0",
    "gn:asciiname":"Bonmal",
    "gn:country_code":"KR",
    "gn:dem":248,
    "gn:feature_class":"P",
    "gn:feature_code":"PPL",
    "gn:name":"Bonmal",
    "gn:population":0,
    "gn:timezone":"Asia/Seoul",
    "iso:country":"KR",
    "name:kor_x_preferred":[
        "\ubcf8\ub9d0"
    ],
    "name:und_x_variant":[
        "Pon-mal",
        "Bonmal"
    ],
    "wof:name":"Bonmal",
    "wof:placetype":"locality"
},
  "geometry": {"coordinates":[128.61903000000001,37.91348],"type":"Point"}
}