{
  "type": "Feature",
  "properties": {
    "gn:admin1_code":"20.0",
    "gn:asciiname":"Daegyeon",
    "gn:country_code":"KR",
    "gn:dem":46,
    "gn:feature_class":"P",
    "gn:feature_code":"PPL",
    "gn:name":"Daegyeon",
    "gn:population":0,
    "gn:timezone":"Asia/Seoul",
    "iso:country":"KR",
    "name:kor_x_preferred":[
        "\ub300\uacac"
    ],
    "wof:name":"Daegyeon",
    "wof:placetype":"locality"
},
  "geometry": {"coordinates":[128.45991999999998,35.63787],"type":"Point"}
}