{
  "type": "Feature",
  "properties": {
    "gn:admin1_code":"17.0",
    "gn:asciiname":"Twittul",
    "gn:country_code":"KR",
    "gn:dem":5,
    "gn:feature_class":"P",
    "gn:feature_code":"PPL",
    "gn:name":"Twitt\u016dl",
    "gn:population":0,
    "gn:timezone":"Asia/Seoul",
    "iso:country":"KR",
    "name:und_x_variant":[
        "\ub4b7\ub730",
        "Twitt\u016dl"
    ],
    "wof:name":"Twittul",
    "wof:placetype":"locality"
},
  "geometry": {"coordinates":[126.3462,36.5066],"type":"Point"}
}