{
  "type": "Feature",
  "properties": {
    "gn:admin1_code":"14.0",
    "gn:asciiname":"Kwinaegi",
    "gn:country_code":"KR",
    "gn:dem":566,
    "gn:feature_class":"P",
    "gn:feature_code":"PPL",
    "gn:name":"Kwinaegi",
    "gn:population":0,
    "gn:timezone":"Asia/Seoul",
    "iso:country":"KR",
    "wof:name":"Kwinaegi",
    "wof:placetype":"locality"
},
  "geometry": {"coordinates":[128.36722,36.77472],"type":"Point"}
}