{
  "type": "Feature",
  "properties": {
    "gn:admin1_code":"5.0",
    "gn:asciiname":"Surinnae",
    "gn:country_code":"KR",
    "gn:dem":228,
    "gn:feature_class":"P",
    "gn:feature_code":"PPL",
    "gn:name":"Surinnae",
    "gn:population":0,
    "gn:timezone":"Asia/Seoul",
    "iso:country":"KR",
    "name:kor_x_preferred":[
        "\uc218\ub9bf\ub0b4"
    ],
    "wof:name":"Surinnae",
    "wof:placetype":"locality"
},
  "geometry": {"coordinates":[127.66046,36.94843],"type":"Point"}
}