{
  "type": "Feature",
  "properties": {
    "gn:admin1_code":"20.0",
    "gn:asciiname":"Changyu",
    "gn:country_code":"KR",
    "gn:dem":105,
    "gn:feature_class":"P",
    "gn:feature_code":"PPL",
    "gn:name":"Changyu",
    "gn:population":0,
    "gn:timezone":"Asia/Seoul",
    "iso:country":"KR",
    "name:fra_x_preferred":[
        "Changyu"
    ],
    "name:und_x_variant":[
        "\uc7a5\uc720",
        "Changyu"
    ],
    "name:zho_x_preferred":[
        "\u5f20\u88d5\u8461\u8404\u9152"
    ],
    "wof:name":"Changyu",
    "wof:placetype":"locality"
},
  "geometry": {"coordinates":[128.24889999999999,35.47734000000001],"type":"Point"}
}