{
  "type": "Feature",
  "properties": {
    "gn:admin1_code":"6.0",
    "gn:asciiname":"Gumbengi",
    "gn:country_code":"KR",
    "gn:dem":135,
    "gn:feature_class":"P",
    "gn:feature_code":"PPL",
    "gn:name":"Gumbengi",
    "gn:population":0,
    "gn:timezone":"Asia/Seoul",
    "iso:country":"KR",
    "name:und_x_variant":[
        "\uad7c\ubcb5\uc774",
        "Kumbengi",
        "Gumbengi"
    ],
    "wof:name":"Gumbengi",
    "wof:placetype":"locality"
},
  "geometry": {"coordinates":[127.78673000000001,37.87664],"type":"Point"}
}