{
  "type": "Feature",
  "properties": {
    "gn:admin1_code":"17.0",
    "gn:asciiname":"Song-am",
    "gn:country_code":"KR",
    "gn:dem":47,
    "gn:feature_class":"P",
    "gn:feature_code":"PPL",
    "gn:name":"Song-am",
    "gn:population":0,
    "gn:timezone":"Asia/Seoul",
    "iso:country":"KR",
    "name:und_x_variant":[
        "\uc1a1\uc554",
        "Song-am"
    ],
    "wof:name":"Song-am",
    "wof:placetype":"locality"
},
  "geometry": {"coordinates":[126.84739999999999,36.6119],"type":"Point"}
}