{
  "type": "Feature",
  "properties": {
    "gn:admin1_code":"16.0",
    "gn:asciiname":"Noryeok",
    "gn:country_code":"KR",
    "gn:dem":20,
    "gn:feature_class":"P",
    "gn:feature_code":"PPL",
    "gn:name":"Noryeok",
    "gn:population":0,
    "gn:timezone":"Asia/Seoul",
    "iso:country":"KR",
    "name:kor_x_preferred":[
        "Nory\u014fk"
    ],
    "name:kor_x_variant":[
        "\ub178\ub825"
    ],
    "wof:name":"Noryeok",
    "wof:placetype":"locality"
},
  "geometry": {"coordinates":[126.96643,34.46273],"type":"Point"}
}