{
  "type": "Feature",
  "properties": {
    "gn:admin1_code":"18.0",
    "gn:asciiname":"Bongnim",
    "gn:country_code":"KR",
    "gn:dem":55,
    "gn:feature_class":"P",
    "gn:feature_code":"PPL",
    "gn:name":"Bongnim",
    "gn:population":0,
    "gn:timezone":"Asia/Seoul",
    "iso:country":"KR",
    "name:kor_x_preferred":[
        "\ubcf5\ub9bc"
    ],
    "wof:name":"Bongnim",
    "wof:placetype":"locality"
},
  "geometry": {"coordinates":[126.68955,35.14832],"type":"Point"}
}