{
  "type": "Feature",
  "properties": {
    "gn:admin1_code":"14.0",
    "gn:asciiname":"Hansilgok",
    "gn:country_code":"KR",
    "gn:dem":240,
    "gn:feature_class":"P",
    "gn:feature_code":"PPL",
    "gn:name":"Hansilgok",
    "gn:population":0,
    "gn:timezone":"Asia/Seoul",
    "iso:country":"KR",
    "name:kor_x_preferred":[
        "\ud55c\uc2e4\uace1"
    ],
    "name:und_x_variant":[
        "Hansil",
        "Han\u2019gok",
        "Hansilgok"
    ],
    "wof:name":"Hansilgok",
    "wof:placetype":"locality"
},
  "geometry": {"coordinates":[128.06086000000002,36.68511],"type":"Point"}
}