{
  "type": "Feature",
  "properties": {
    "gn:admin1_code":"5.0",
    "gn:asciiname":"Kujom",
    "gn:country_code":"KR",
    "gn:dem":169,
    "gn:feature_class":"P",
    "gn:feature_code":"PPL",
    "gn:name":"Kuj\u014fm",
    "gn:population":0,
    "gn:timezone":"Asia/Seoul",
    "iso:country":"KR",
    "wof:name":"Kujom",
    "wof:placetype":"locality"
},
  "geometry": {"coordinates":[127.90333,36.78278],"type":"Point"}
}