{
  "type": "Feature",
  "properties": {
    "gn:admin1_code":"21.0",
    "gn:asciiname":"Sinchon",
    "gn:country_code":"KR",
    "gn:dem":30,
    "gn:feature_class":"P",
    "gn:feature_code":"PPL",
    "gn:name":"Sinchon",
    "gn:population":0,
    "gn:timezone":"Asia/Seoul",
    "iso:country":"KR",
    "name:kor_x_preferred":[
        "\uc2e0\ucd0c"
    ],
    "name:und_x_variant":[
        "Shinch\u2019\u014fn",
        "Sinch\u2019\u014fn",
        "Sinchon"
    ],
    "name:zho_x_preferred":[
        "\u65b0\u6751"
    ],
    "wof:name":"Sinchon",
    "wof:placetype":"locality"
},
  "geometry": {"coordinates":[129.31676000000002,35.46742000000001],"type":"Point"}
}