{
  "type": "Feature",
  "properties": {
    "gn:admin1_code":"16.0",
    "gn:asciiname":"Ganaehang",
    "gn:country_code":"KR",
    "gn:dem":7,
    "gn:feature_class":"P",
    "gn:feature_code":"PPL",
    "gn:name":"Ganaehang",
    "gn:population":0,
    "gn:timezone":"Asia/Seoul",
    "iso:country":"KR",
    "name:kor_x_preferred":[
        "\uac00\ub0b4\ud56d"
    ],
    "name:und_x_variant":[
        "Kanaemogi",
        "Kannaemok",
        "Kannaehang",
        "Ganaehang"
    ],
    "wof:name":"Ganaehang",
    "wof:placetype":"locality"
},
  "geometry": {"coordinates":[126.41041,34.75053],"type":"Point"}
}