{
  "type": "Feature",
  "properties": {
    "gn:admin1_code":"14.0",
    "gn:asciiname":"Anduksu-gol",
    "gn:country_code":"KR",
    "gn:dem":248,
    "gn:feature_class":"P",
    "gn:feature_code":"PPL",
    "gn:name":"And\u016dksu-gol",
    "gn:population":0,
    "gn:timezone":"Asia/Seoul",
    "iso:country":"KR",
    "name:und_x_variant":[
        "\uc548\ub4dd\uc218\uace8",
        "And\u016dksu-gol"
    ],
    "wof:name":"Anduksu-gol",
    "wof:placetype":"locality"
},
  "geometry": {"coordinates":[127.8973,36.3357],"type":"Point"}
}