{
  "type": "Feature",
  "properties": {
    "gn:admin1_code":"13.0",
    "gn:asciiname":"Nangyu-dong",
    "gn:cc2":"KR",
    "gn:country_code":"KR",
    "gn:dem":152,
    "gn:feature_class":"P",
    "gn:feature_code":"PPL",
    "gn:name":"Nangyu-dong",
    "gn:population":0,
    "gn:timezone":"Asia/Seoul",
    "iso:country":"KR",
    "name:und_x_variant":[
        "Nangyu-ri",
        "Nangyu-dong"
    ],
    "wof:name":"Nangyu-dong",
    "wof:placetype":"locality"
},
  "geometry": {"coordinates":[127.33333,38.01667],"type":"Point"}
}