{
  "type": "Feature",
  "properties": {
    "gn:admin1_code":"13.0",
    "gn:asciiname":"Sangmakgeum",
    "gn:country_code":"KR",
    "gn:dem":57,
    "gn:feature_class":"P",
    "gn:feature_code":"PPL",
    "gn:name":"Sangmakgeum",
    "gn:population":0,
    "gn:timezone":"Asia/Seoul",
    "iso:country":"KR",
    "name:und_x_variant":[
        "\uc0c1\ub9c9\uae08",
        "Sangmakgeum",
        "Sangmakk\u016dm"
    ],
    "wof:name":"Sangmakgeum",
    "wof:placetype":"locality"
},
  "geometry": {"coordinates":[127.03784,37.07524],"type":"Point"}
}