{
  "type": "Feature",
  "properties": {
    "gn:admin1_code":"6.0",
    "gn:asciiname":"Nop'un'gi",
    "gn:country_code":"KR",
    "gn:dem":698,
    "gn:feature_class":"P",
    "gn:feature_code":"PPL",
    "gn:name":"Nop\u2019un\u2019gi",
    "gn:population":0,
    "gn:timezone":"Asia/Seoul",
    "iso:country":"KR",
    "name:und_x_variant":[
        "\ub178\ud47c\uae30",
        "Nop\u2019un\u2019gi"
    ],
    "wof:name":"Nop'un'gi",
    "wof:placetype":"locality"
},
  "geometry": {"coordinates":[129.04816,37.18493],"type":"Point"}
}