{
  "type": "Feature",
  "properties": {
    "gn:admin1_code":"14.0",
    "gn:asciiname":"Noejeongsan",
    "gn:country_code":"KR",
    "gn:dem":965,
    "gn:feature_class":"P",
    "gn:feature_code":"PPL",
    "gn:name":"Noejeongsan",
    "gn:population":0,
    "gn:timezone":"Asia/Seoul",
    "iso:country":"KR",
    "name:kor_x_preferred":[
        "\ub1cc\uc815\uc0b0"
    ],
    "wof:name":"Noejeongsan",
    "wof:placetype":"locality"
},
  "geometry": {"coordinates":[128.03832,36.68891],"type":"Point"}
}