{
  "type": "Feature",
  "properties": {
    "gn:admin1_code":"16.0",
    "gn:asciiname":"Oech'o-ri",
    "gn:country_code":"KR",
    "gn:dem":34,
    "gn:feature_class":"P",
    "gn:feature_code":"PPL",
    "gn:name":"Oech\u2019o-ri",
    "gn:population":0,
    "gn:timezone":"Asia/Seoul",
    "iso:country":"KR",
    "name:und_x_variant":[
        "Aech\u2019o-ri",
        "Oech\u2019o-ri"
    ],
    "wof:name":"Oech'o-ri",
    "wof:placetype":"locality"
},
  "geometry": {"coordinates":[127.48917,34.4425],"type":"Point"}
}