{
  "type": "Feature",
  "properties": {
    "gn:admin1_code":"16.0",
    "gn:asciiname":"Pook",
    "gn:country_code":"KR",
    "gn:dem":33,
    "gn:feature_class":"P",
    "gn:feature_code":"PPL",
    "gn:name":"Pook",
    "gn:population":0,
    "gn:timezone":"Asia/Seoul",
    "iso:country":"KR",
    "name:kor_x_preferred":[
        "\ubcf4\uc625"
    ],
    "name:und_x_variant":[
        "Puong-ni",
        "Poong-ni",
        "Pook"
    ],
    "wof:name":"Pook",
    "wof:placetype":"locality"
},
  "geometry": {"coordinates":[126.51611,34.12972],"type":"Point"}
}