{
  "type": "Feature",
  "properties": {
    "gn:admin1_code":"16.0",
    "gn:asciiname":"Nogodu",
    "gn:country_code":"KR",
    "gn:dem":26,
    "gn:feature_class":"P",
    "gn:feature_code":"PPL",
    "gn:name":"Nogodu",
    "gn:population":0,
    "gn:timezone":"Asia/Seoul",
    "iso:country":"KR",
    "name:kor_x_preferred":[
        "\ub178\uace0\ub450"
    ],
    "wof:name":"Nogodu",
    "wof:placetype":"locality"
},
  "geometry": {"coordinates":[126.88906,35.00117],"type":"Point"}
}