{
  "type": "Feature",
  "properties": {
    "gn:admin1_code":"14.0",
    "gn:asciiname":"Tansan",
    "gn:country_code":"KR",
    "gn:dem":250,
    "gn:feature_class":"P",
    "gn:feature_code":"PPL",
    "gn:name":"Tansan",
    "gn:population":0,
    "gn:timezone":"Asia/Seoul",
    "iso:country":"KR",
    "name:und_x_variant":[
        "\ub2e8\uc0b0",
        "Tansan"
    ],
    "wof:name":"Tansan",
    "wof:placetype":"locality"
},
  "geometry": {"coordinates":[127.96644999999999,35.97642000000001],"type":"Point"}
}