{
  "type": "Feature",
  "properties": {
    "gn:admin1_code":"16.0",
    "gn:asciiname":"Saebaldul",
    "gn:country_code":"KR",
    "gn:dem":16,
    "gn:feature_class":"P",
    "gn:feature_code":"PPL",
    "gn:name":"Saebald\u016dl",
    "gn:population":0,
    "gn:timezone":"Asia/Seoul",
    "iso:country":"KR",
    "name:kor_x_preferred":[
        "Saebald\u016dl"
    ],
    "wof:name":"Saebaldul",
    "wof:placetype":"locality"
},
  "geometry": {"coordinates":[126.82138999999999,34.56944],"type":"Point"}
}