{
  "type": "Feature",
  "properties": {
    "gn:admin1_code":"17.0",
    "gn:asciiname":"Chidan",
    "gn:country_code":"KR",
    "gn:dem":233,
    "gn:feature_class":"P",
    "gn:feature_code":"PPL",
    "gn:name":"Chidan",
    "gn:population":0,
    "gn:timezone":"Asia/Seoul",
    "iso:country":"KR",
    "name:und_x_variant":[
        "\uc9c0\ub2e8",
        "Chidan"
    ],
    "wof:name":"Chidan",
    "wof:placetype":"locality"
},
  "geometry": {"coordinates":[126.7093,36.3573],"type":"Point"}
}