{
  "type": "Feature",
  "properties": {
    "gn:admin1_code":"20.0",
    "gn:asciiname":"Chojeon",
    "gn:country_code":"KR",
    "gn:dem":12,
    "gn:feature_class":"P",
    "gn:feature_code":"PPL",
    "gn:name":"Chojeon",
    "gn:population":0,
    "gn:timezone":"Asia/Seoul",
    "iso:country":"KR",
    "name:kor_x_preferred":[
        "\ucd08\uc804"
    ],
    "name:und_x_variant":[
        "Saebakk\u016dm"
    ],
    "wof:name":"Chojeon",
    "wof:placetype":"locality"
},
  "geometry": {"coordinates":[128.03288999999998,34.72898],"type":"Point"}
}