{
  "type": "Feature",
  "properties": {
    "gn:admin1_code":"20.0",
    "gn:asciiname":"Osinaraettam",
    "gn:country_code":"KR",
    "gn:dem":10,
    "gn:feature_class":"P",
    "gn:feature_code":"PPL",
    "gn:name":"\u014esinaraettam",
    "gn:population":0,
    "gn:timezone":"Asia/Seoul",
    "iso:country":"KR",
    "name:und_x_variant":[
        "\uc5b4\uc2e0\uc544\ub7ab\ub540",
        "\u014esinaraettam"
    ],
    "wof:name":"Osinaraettam",
    "wof:placetype":"locality"
},
  "geometry": {"coordinates":[128.42025000000001,35.05937],"type":"Point"}
}