{
  "type": "Feature",
  "properties": {
    "iso:country":"KR",
    "qs:name":"\uad11\uc591\uc74d",
    "qs:name_adm0":"\ud55c\uad6d",
    "qs:name_adm1":"\uc804\ub77c\ub0a8\ub3c4",
    "qs:photos":3,
    "qs:photos_1k":1,
    "qs:photos_9k":1,
    "qs:photos_9r":1,
    "qs:photos_all":3,
    "qs:photos_sr":1,
    "qs:placetype":"LocalAdmin",
    "qs:pop_sr":"0",
    "wof:name":"\uad11\uc591\uc74d",
    "wof:placetype":"localadmin"
},
  "geometry": {"coordinates":[127.584228,34.990628],"type":"Point"}
}