{
  "type": "Feature",
  "properties": {
    "gn:admin1_code":"14.0",
    "gn:asciiname":"Sonhang-ni",
    "gn:country_code":"KR",
    "gn:dem":172,
    "gn:feature_class":"P",
    "gn:feature_code":"PPL",
    "gn:name":"S\u014fnhang-ni",
    "gn:population":0,
    "gn:timezone":"Asia/Seoul",
    "iso:country":"KR",
    "name:und_x_variant":[
        "\uc120\ud56d\ub9ac",
        "S\u014fnhang-ni"
    ],
    "wof:name":"Sonhang-ni",
    "wof:placetype":"locality"
},
  "geometry": {"coordinates":[128.91630000000001,36.4169],"type":"Point"}
}