{
  "type": "Feature",
  "properties": {
    "gn:admin1_code":"13.0",
    "gn:asciiname":"Chohyeon",
    "gn:country_code":"KR",
    "gn:dem":72,
    "gn:feature_class":"P",
    "gn:feature_code":"PPL",
    "gn:name":"Chohyeon",
    "gn:population":0,
    "gn:timezone":"Asia/Seoul",
    "iso:country":"KR",
    "name:und_x_variant":[
        "\ucd08\ud604",
        "Chohyeon",
        "Ch\u2019ohy\u014fn"
    ],
    "wof:name":"Chohyeon",
    "wof:placetype":"locality"
},
  "geometry": {"coordinates":[127.23860999999999,37.30278],"type":"Point"}
}