{
  "type": "Feature",
  "properties": {
    "gn:admin1_code":"13.0",
    "gn:admin2_code":"P'alu-si",
    "gn:asciiname":"Dumulli",
    "gn:country_code":"KR",
    "gn:dem":24,
    "gn:feature_class":"P",
    "gn:feature_code":"PPL",
    "gn:name":"Dumulli",
    "gn:population":0,
    "gn:timezone":"Asia/Seoul",
    "iso:country":"KR",
    "name:kor_x_preferred":[
        "\ub450\ubb38\ub9ac"
    ],
    "name:und_x_variant":[
        "Tumun-dong",
        "Tumul-li",
        "Dumulli"
    ],
    "wof:name":"Dumulli",
    "wof:placetype":"locality"
},
  "geometry": {"coordinates":[126.77222999999999,37.78154],"type":"Point"}
}