{
  "type": "Feature",
  "properties": {
    "gn:admin1_code":"14.0",
    "gn:asciiname":"Sojaeji",
    "gn:country_code":"KR",
    "gn:dem":134,
    "gn:feature_class":"P",
    "gn:feature_code":"PPL",
    "gn:name":"Sojaeji",
    "gn:population":0,
    "gn:timezone":"Asia/Seoul",
    "iso:country":"KR",
    "name:kor_x_preferred":[
        "\uc18c\uc7ac\uc9c0"
    ],
    "wof:name":"Sojaeji",
    "wof:placetype":"locality"
},
  "geometry": {"coordinates":[128.76393999999999,36.52649],"type":"Point"}
}