{
  "type": "Feature",
  "properties": {
    "gn:admin1_code":"11.0",
    "gn:asciiname":"Karagil-tong",
    "gn:country_code":"KR",
    "gn:dem":20,
    "gn:feature_class":"P",
    "gn:feature_code":"PPL",
    "gn:name":"Karagil-tong",
    "gn:population":0,
    "gn:timezone":"Asia/Seoul",
    "iso:country":"KR",
    "name:und_x_variant":[
        "\uac00\ub77d1\ub3d9",
        "Garagil-dong",
        "Karagil-tong"
    ],
    "wof:name":"Karagil-tong",
    "wof:placetype":"locality"
},
  "geometry": {"coordinates":[127.10778000000001,37.49528],"type":"Point"}
}