{
  "type": "Feature",
  "properties": {
    "gn:admin1_code":"17.0",
    "gn:asciiname":"Wolgok",
    "gn:country_code":"KR",
    "gn:dem":186,
    "gn:feature_class":"P",
    "gn:feature_code":"PPL",
    "gn:name":"W\u014flgok",
    "gn:population":0,
    "gn:timezone":"Asia/Seoul",
    "iso:country":"KR",
    "name:und_x_variant":[
        "\uc6d4\uace1",
        "W\u014flgok"
    ],
    "wof:name":"Wolgok",
    "wof:placetype":"locality"
},
  "geometry": {"coordinates":[127.44199999999999,36.1214],"type":"Point"}
}