{
  "type": "Feature",
  "properties": {
    "gn:admin1_code":"20.0",
    "gn:asciiname":"T'ongp'o",
    "gn:country_code":"KR",
    "gn:dem":43,
    "gn:feature_class":"P",
    "gn:feature_code":"PPL",
    "gn:name":"T\u2019ongp\u2019o",
    "gn:population":0,
    "gn:timezone":"Asia/Seoul",
    "iso:country":"KR",
    "name:und_x_variant":[
        "\ud1b5\ud3ec",
        "T\u2019ongp\u2019o"
    ],
    "wof:name":"T'ongp'o",
    "wof:placetype":"locality"
},
  "geometry": {"coordinates":[128.25453999999999,34.80994],"type":"Point"}
}