{
  "type": "Feature",
  "properties": {
    "gn:admin1_code":"3.0",
    "gn:asciiname":"Mach'i",
    "gn:country_code":"KR",
    "gn:dem":414,
    "gn:feature_class":"P",
    "gn:feature_code":"PPL",
    "gn:name":"Mach\u2019i",
    "gn:population":0,
    "gn:timezone":"Asia/Seoul",
    "iso:country":"KR",
    "name:und_x_variant":[
        "\ub9c8\uce58",
        "Mach\u2019i"
    ],
    "wof:name":"Mach'i",
    "wof:placetype":"locality"
},
  "geometry": {"coordinates":[127.43635999999999,35.72356],"type":"Point"}
}