{
  "type": "Feature",
  "properties": {
    "gn:admin1_code":"16.0",
    "gn:asciiname":"Soyu-ri",
    "gn:country_code":"KR",
    "gn:dem":208,
    "gn:feature_class":"P",
    "gn:feature_code":"PPL",
    "gn:name":"S\u014fyu-ri",
    "gn:population":0,
    "gn:timezone":"Asia/Seoul",
    "iso:country":"KR",
    "wof:name":"Soyu-ri",
    "wof:placetype":"locality"
},
  "geometry": {"coordinates":[127.08944,35.17417],"type":"Point"}
}