{
  "type": "Feature",
  "properties": {
    "gn:admin1_code":"13.0",
    "gn:asciiname":"Pyeonjeon",
    "gn:country_code":"KR",
    "gn:dem":105,
    "gn:feature_class":"P",
    "gn:feature_code":"PPL",
    "gn:name":"Pyeonjeon",
    "gn:population":0,
    "gn:timezone":"Asia/Seoul",
    "iso:country":"KR",
    "name:kor_x_preferred":[
        "\ud3b8\uc804"
    ],
    "name:und_x_variant":[
        "Pyeonjeon"
    ],
    "wof:name":"Pyeonjeon",
    "wof:placetype":"locality"
},
  "geometry": {"coordinates":[127.48820000000001,37.5369],"type":"Point"}
}