{
  "type": "Feature",
  "properties": {
    "gn:admin1_code":"6.0",
    "gn:asciiname":"P'yongch'onbon-dong",
    "gn:country_code":"KR",
    "gn:dem":549,
    "gn:feature_class":"P",
    "gn:feature_code":"PPL",
    "gn:name":"P\u2019y\u014fngch\u2019onbon-dong",
    "gn:population":0,
    "gn:timezone":"Asia/Seoul",
    "iso:country":"KR",
    "name:kor_x_preferred":[
        "\ud3c9\ucd0c\ubcf8\ub3d9"
    ],
    "name:kor_x_variant":[
        "P\u2019y\u014fngch\u2019onbon-dong"
    ],
    "wof:name":"P'yongch'onbon-dong",
    "wof:placetype":"locality"
},
  "geometry": {"coordinates":[128.38299999999998,37.5986],"type":"Point"}
}