{
  "type": "Feature",
  "properties": {
    "gn:admin1_code":"6.0",
    "gn:asciiname":"Yeohonae",
    "gn:country_code":"KR",
    "gn:dem":108,
    "gn:feature_class":"P",
    "gn:feature_code":"PPL",
    "gn:name":"Yeohonae",
    "gn:population":0,
    "gn:timezone":"Asia/Seoul",
    "iso:country":"KR",
    "name:kor_x_preferred":[
        "\uc5ec\ud638\ub0b4"
    ],
    "wof:name":"Yeohonae",
    "wof:placetype":"locality"
},
  "geometry": {"coordinates":[127.7735,37.6742],"type":"Point"}
}