{
  "type": "Feature",
  "properties": {
    "gn:admin1_code":"12.0",
    "gn:asciiname":"Oryugol",
    "gn:country_code":"KR",
    "gn:dem":23,
    "gn:feature_class":"P",
    "gn:feature_code":"PPL",
    "gn:name":"Oryugol",
    "gn:population":0,
    "gn:timezone":"Asia/Seoul",
    "iso:country":"KR",
    "name:und_x_variant":[
        "\uc624\ub958\uace8",
        "Oryugol"
    ],
    "wof:name":"Oryugol",
    "wof:placetype":"locality"
},
  "geometry": {"coordinates":[126.50471,37.63442],"type":"Point"}
}