{
  "type": "Feature",
  "properties": {
    "gn:admin1_code":"0.0",
    "gn:asciiname":"Wolgye",
    "gn:cc2":"KR",
    "gn:country_code":"KR",
    "gn:dem":325,
    "gn:feature_class":"P",
    "gn:feature_code":"PPL",
    "gn:name":"W\u014flgye",
    "gn:population":0,
    "gn:timezone":"Asia/Seoul",
    "iso:country":"KR",
    "name:und_x_variant":[
        "W\u014fge",
        "W\u014flgye"
    ],
    "wof:name":"Wolgye",
    "wof:placetype":"locality"
},
  "geometry": {"coordinates":[127.48333,35.33333],"type":"Point"}
}