{
  "type": "Feature",
  "properties": {
    "gn:admin1_code":"13.0",
    "gn:asciiname":"Saetomal",
    "gn:country_code":"KR",
    "gn:dem":27,
    "gn:feature_class":"P",
    "gn:feature_code":"PPL",
    "gn:name":"Saetomal",
    "gn:population":0,
    "gn:timezone":"Asia/Seoul",
    "iso:country":"KR",
    "name:kor_x_preferred":[
        "\uc0c8\ud130\ub9d0"
    ],
    "name:kor_x_variant":[
        "Saet\u2019\u014fmal"
    ],
    "wof:name":"Saetomal",
    "wof:placetype":"locality"
},
  "geometry": {"coordinates":[126.788,37.72131],"type":"Point"}
}