{
  "type": "Feature",
  "properties": {
    "gn:admin1_code":"6.0",
    "gn:asciiname":"Pusawol-li",
    "gn:country_code":"KR",
    "gn:dem":207,
    "gn:feature_class":"P",
    "gn:feature_code":"PPLL",
    "gn:name":"Pusaw\u014fl-li",
    "gn:population":0,
    "gn:timezone":"Asia/Seoul",
    "iso:country":"KR",
    "name:kor_x_preferred":[
        "\ubd80\uc0ac\uc6d0\ub9ac"
    ],
    "name:kor_x_variant":[
        "Pusaw\u014fl-li"
    ],
    "wof:name":"Pusawol-li",
    "wof:placetype":"locality"
},
  "geometry": {"coordinates":[127.83329999999999,37.74012000000001],"type":"Point"}
}