{
  "type": "Feature",
  "properties": {
    "gn:admin1_code":"17.0",
    "gn:asciiname":"Tokchongi",
    "gn:country_code":"KR",
    "gn:dem":175,
    "gn:feature_class":"P",
    "gn:feature_code":"PPL",
    "gn:name":"Tokch\u014fngi",
    "gn:population":0,
    "gn:timezone":"Asia/Seoul",
    "iso:country":"KR",
    "name:und_x_variant":[
        "\ub3c5\uc815\uc774",
        "Tokch\u014fngi"
    ],
    "wof:name":"Tokchongi",
    "wof:placetype":"locality"
},
  "geometry": {"coordinates":[126.8467,36.4529],"type":"Point"}
}