{
  "type": "Feature",
  "properties": {
    "gn:admin1_code":"17.0",
    "gn:asciiname":"Hagalsin",
    "gn:country_code":"KR",
    "gn:dem":68,
    "gn:feature_class":"P",
    "gn:feature_code":"PPL",
    "gn:name":"Hagalsin",
    "gn:population":0,
    "gn:timezone":"Asia/Seoul",
    "iso:country":"KR",
    "name:und_x_variant":[
        "\ud558\uac08\uc2e0",
        "Hagalsin"
    ],
    "wof:name":"Hagalsin",
    "wof:placetype":"locality"
},
  "geometry": {"coordinates":[126.85299999999999,36.6541],"type":"Point"}
}