{
  "type": "Feature",
  "properties": {
    "gn:admin1_code":"16.0",
    "gn:asciiname":"Todong-ni",
    "gn:cc2":"KR",
    "gn:country_code":"KR",
    "gn:dem":10,
    "gn:feature_class":"P",
    "gn:feature_code":"PPL",
    "gn:name":"Tod\u014fng-ni",
    "gn:population":0,
    "gn:timezone":"Asia/Seoul",
    "iso:country":"KR",
    "name:und_x_variant":[
        "Pan\u2019gol-tong",
        "Pan\u2019gok-tong",
        "Tod\u014fng-ni"
    ],
    "wof:name":"Todong-ni",
    "wof:placetype":"locality"
},
  "geometry": {"coordinates":[126.51667,34.86667],"type":"Point"}
}