{
  "type": "Feature",
  "properties": {
    "gn:admin1_code":"12.0",
    "gn:asciiname":"Yucheonmal",
    "gn:country_code":"KR",
    "gn:dem":13,
    "gn:feature_class":"P",
    "gn:feature_code":"PPL",
    "gn:name":"Yucheonmal",
    "gn:population":0,
    "gn:timezone":"Asia/Seoul",
    "iso:country":"KR",
    "name:und_x_variant":[
        "\uc720\ucc9c\ub9d0",
        "Yucheonmal",
        "Yuch\u2019\u014fn-mal"
    ],
    "wof:name":"Yucheonmal",
    "wof:placetype":"locality"
},
  "geometry": {"coordinates":[126.47865,37.61028],"type":"Point"}
}