{
  "type": "Feature",
  "properties": {
    "iso:country":"KR",
    "qs:name":"\ud3c9\uc548\ub3d9",
    "qs:name_adm0":"\ud55c\uad6d",
    "qs:name_adm1":"\uacbd\uae30\ub3c4",
    "qs:photos":10,
    "qs:photos_1k":2,
    "qs:photos_9k":1,
    "qs:photos_9r":1,
    "qs:photos_all":10,
    "qs:photos_sr":1,
    "qs:placetype":"Suburb",
    "qs:pop_sr":"0",
    "wof:name":"\ud3c9\uc548\ub3d9",
    "wof:placetype":"neighbourhood"
},
  "geometry": {"coordinates":[126.967878,37.383286],"type":"Point"}
}