{
  "type": "Feature",
  "properties": {
    "gn:admin1_code":"16.0",
    "gn:asciiname":"Ammaeul",
    "gn:country_code":"KR",
    "gn:dem":163,
    "gn:feature_class":"P",
    "gn:feature_code":"PPL",
    "gn:name":"Ammaeul",
    "gn:population":0,
    "gn:timezone":"Asia/Seoul",
    "iso:country":"KR",
    "name:kor_x_preferred":[
        "\uc55e\ub9c8\uc744"
    ],
    "wof:name":"Ammaeul",
    "wof:placetype":"locality"
},
  "geometry": {"coordinates":[126.74172,35.33944],"type":"Point"}
}