{
  "type": "Feature",
  "properties": {
    "gn:admin1_code":"13.0",
    "gn:asciiname":"Taegwal-li",
    "gn:country_code":"KR",
    "gn:dem":58,
    "gn:feature_class":"P",
    "gn:feature_code":"PPLL",
    "gn:name":"Taegwal-li",
    "gn:population":0,
    "gn:timezone":"Asia/Seoul",
    "iso:country":"KR",
    "name:und_x_variant":[
        "\ub300\uad00\ub9ac",
        "Daegwan-ri",
        "Taegwal-li"
    ],
    "wof:name":"Taegwal-li",
    "wof:placetype":"locality"
},
  "geometry": {"coordinates":[127.535,37.31056],"type":"Point"}
}