{
  "type": "Feature",
  "properties": {
    "gn:admin1_code":"5.0",
    "gn:admin2_code":"\u016cms\u014fng-gun",
    "gn:asciiname":"Saetteomal",
    "gn:country_code":"KR",
    "gn:dem":108,
    "gn:feature_class":"P",
    "gn:feature_code":"PPL",
    "gn:name":"Saetteomal",
    "gn:population":0,
    "gn:timezone":"Asia/Seoul",
    "iso:country":"KR",
    "name:kor_x_preferred":[
        "\uc0c8\ud130\ub9d0"
    ],
    "name:kor_x_variant":[
        "Saet\u014f-mal",
        "\uc0db\ud130\ub9d0"
    ],
    "wof:name":"Saetteomal",
    "wof:placetype":"locality"
},
  "geometry": {"coordinates":[127.4598,37.00543],"type":"Point"}
}