{
  "type": "Feature",
  "properties": {
    "gn:admin1_code":"3.0",
    "gn:asciiname":"Yusang-ni",
    "gn:country_code":"KR",
    "gn:dem":102,
    "gn:feature_class":"P",
    "gn:feature_code":"PPL",
    "gn:name":"Yusang-ni",
    "gn:population":0,
    "gn:timezone":"Asia/Seoul",
    "iso:country":"KR",
    "name:und_x_variant":[
        "\uc720\uc0c1\ub9ac",
        "Yusang-ni"
    ],
    "wof:name":"Yusang-ni",
    "wof:placetype":"locality"
},
  "geometry": {"coordinates":[127.26965,35.83434000000001],"type":"Point"}
}