{
  "type": "Feature",
  "properties": {
    "gn:admin1_code":"14.0",
    "gn:asciiname":"Anyusinae",
    "gn:country_code":"KR",
    "gn:dem":341,
    "gn:feature_class":"P",
    "gn:feature_code":"PPL",
    "gn:name":"Anyusinae",
    "gn:population":0,
    "gn:timezone":"Asia/Seoul",
    "iso:country":"KR",
    "name:und_x_variant":[
        "\uc548\uc720\uc2dc\ub0b4",
        "Anyusinae"
    ],
    "wof:name":"Anyusinae",
    "wof:placetype":"locality"
},
  "geometry": {"coordinates":[129.05471,36.24318],"type":"Point"}
}