{
  "type": "Feature",
  "properties": {
    "gn:admin1_code":"20.0",
    "gn:asciiname":"Agul-li",
    "gn:country_code":"KR",
    "gn:dem":32,
    "gn:feature_class":"P",
    "gn:feature_code":"PPL",
    "gn:name":"Ag\u016dl-li",
    "gn:population":0,
    "gn:timezone":"Asia/Seoul",
    "iso:country":"KR",
    "name:und_x_variant":[
        "\uc544\uadfc\ub9ac",
        "Ag\u016dl-li"
    ],
    "wof:name":"Agul-li",
    "wof:placetype":"locality"
},
  "geometry": {"coordinates":[128.37949,35.50561],"type":"Point"}
}