{
  "type": "Feature",
  "properties": {
    "gn:admin1_code":"14.0",
    "gn:asciiname":"Yek-kol",
    "gn:country_code":"KR",
    "gn:dem":323,
    "gn:feature_class":"P",
    "gn:feature_code":"PPL",
    "gn:name":"Yek-kol",
    "gn:population":0,
    "gn:timezone":"Asia/Seoul",
    "iso:country":"KR",
    "name:und_x_variant":[
        "\uc61b\uace8",
        "Yek-kol"
    ],
    "wof:name":"Yek-kol",
    "wof:placetype":"locality"
},
  "geometry": {"coordinates":[129.01750000000001,36.6022],"type":"Point"}
}