{
  "type": "Feature",
  "properties": {
    "gn:admin1_code":"16.0",
    "gn:asciiname":"Yeondongni",
    "gn:country_code":"KR",
    "gn:dem":14,
    "gn:feature_class":"P",
    "gn:feature_code":"PPL",
    "gn:name":"Yeondongni",
    "gn:population":0,
    "gn:timezone":"Asia/Seoul",
    "iso:country":"KR",
    "name:kor_x_preferred":[
        "Y\u014fn-dong"
    ],
    "name:kor_x_variant":[
        "\uc5f0\ub3d9\ub9ac"
    ],
    "wof:name":"Yeondongni",
    "wof:placetype":"locality"
},
  "geometry": {"coordinates":[126.8075,34.38432],"type":"Point"}
}