{
  "type": "Feature",
  "properties": {
    "gn:admin1_code":"14.0",
    "gn:asciiname":"Gyochon",
    "gn:country_code":"KR",
    "gn:dem":161,
    "gn:feature_class":"P",
    "gn:feature_code":"PPL",
    "gn:name":"Gyochon",
    "gn:population":0,
    "gn:timezone":"Asia/Seoul",
    "iso:country":"KR",
    "name:kor_x_preferred":[
        "\uad50\ucd0c"
    ],
    "wof:name":"Gyochon",
    "wof:placetype":"locality"
},
  "geometry": {"coordinates":[128.48915,36.73302],"type":"Point"}
}