{
  "type": "Feature",
  "properties": {
    "gn:admin1_code":"14.0",
    "gn:asciiname":"Pamsil",
    "gn:country_code":"KR",
    "gn:dem":59,
    "gn:feature_class":"P",
    "gn:feature_code":"PPL",
    "gn:name":"Pamsil",
    "gn:population":0,
    "gn:timezone":"Asia/Seoul",
    "iso:country":"KR",
    "name:und_x_variant":[
        "\ubc24\uc2e4",
        "Pamsil"
    ],
    "wof:name":"Pamsil",
    "wof:placetype":"locality"
},
  "geometry": {"coordinates":[128.33619999999999,36.1433],"type":"Point"}
}