{
  "type": "Feature",
  "properties": {
    "gn:admin1_code":"3.0",
    "gn:asciiname":"Hwasim",
    "gn:country_code":"KR",
    "gn:dem":102,
    "gn:feature_class":"P",
    "gn:feature_code":"PPL",
    "gn:name":"Hwasim",
    "gn:population":0,
    "gn:timezone":"Asia/Seoul",
    "iso:country":"KR",
    "name:und_x_variant":[
        "\ud654\uc2ec",
        "Hwasim"
    ],
    "wof:name":"Hwasim",
    "wof:placetype":"locality"
},
  "geometry": {"coordinates":[127.26694000000001,35.83600999999999],"type":"Point"}
}