{
  "type": "Feature",
  "properties": {
    "gn:admin1_code":"16.0",
    "gn:asciiname":"Sok-tong",
    "gn:country_code":"KR",
    "gn:dem":38,
    "gn:feature_class":"P",
    "gn:feature_code":"PPL",
    "gn:name":"S\u014fk-tong",
    "gn:population":0,
    "gn:timezone":"Asia/Seoul",
    "iso:country":"KR",
    "name:kor_x_preferred":[
        "S\u014fk-tong"
    ],
    "wof:name":"Sok-tong",
    "wof:placetype":"locality"
},
  "geometry": {"coordinates":[126.91056,34.62917],"type":"Point"}
}