{
  "type": "Feature",
  "properties": {
    "iso:country":"KR",
    "name:eng_x_preferred":[
        "Yonghyeon-myeon"
    ],
    "name:kor_x_preferred":[
        "\uc6a9\ud604\uba74"
    ],
    "qs:name":"\uc6a9\ud604\uba74",
    "qs:name_adm0":"\ud55c\uad6d",
    "qs:name_adm1":"\uacbd\uc0c1\ub0a8\ub3c4",
    "qs:photos":24,
    "qs:photos_1k":5,
    "qs:photos_9k":1,
    "qs:photos_9r":1,
    "qs:photos_all":24,
    "qs:photos_sr":1,
    "qs:placetype":"LocalAdmin",
    "qs:pop_sr":"0",
    "wof:name":"Yonghyeon-myeon",
    "wof:placetype":"localadmin"
},
  "geometry": {"coordinates":[128.06367800000001,35.092734],"type":"Point"}
}