{
  "type": "Feature",
  "properties": {
    "gn:admin1_code":"6.0",
    "gn:asciiname":"Taemi-dong",
    "gn:country_code":"KR",
    "gn:dem":651,
    "gn:feature_class":"P",
    "gn:feature_code":"PPL",
    "gn:name":"Taemi-dong",
    "gn:population":0,
    "gn:timezone":"Asia/Seoul",
    "iso:country":"KR",
    "wof:name":"Taemi-dong",
    "wof:placetype":"locality"
},
  "geometry": {"coordinates":[128.30528000000001,37.48917],"type":"Point"}
}