{
  "type": "Feature",
  "properties": {
    "gn:admin1_code":"16.0",
    "gn:asciiname":"Kobun-dong",
    "gn:country_code":"KR",
    "gn:dem":24,
    "gn:feature_class":"P",
    "gn:feature_code":"PPL",
    "gn:name":"Kobun-dong",
    "gn:population":0,
    "gn:timezone":"Asia/Seoul",
    "iso:country":"KR",
    "name:und_x_variant":[
        "\uace0\ubd84\ub3d9",
        "Kobun-dong"
    ],
    "wof:name":"Kobun-dong",
    "wof:placetype":"locality"
},
  "geometry": {"coordinates":[126.73056,34.50472],"type":"Point"}
}