{
  "type": "Feature",
  "properties": {
    "gn:admin1_code":"11.0",
    "gn:asciiname":"Miasa-dong",
    "gn:country_code":"KR",
    "gn:dem":40,
    "gn:feature_class":"P",
    "gn:feature_code":"PPL",
    "gn:name":"Miasa-dong",
    "gn:population":0,
    "gn:timezone":"Asia/Seoul",
    "iso:country":"KR",
    "name:und_x_variant":[
        "\ubbf8\uc5444\ub3d9",
        "Miasa-dong"
    ],
    "wof:name":"Miasa-dong",
    "wof:placetype":"locality"
},
  "geometry": {"coordinates":[127.0348,37.61446],"type":"Point"}
}