{
  "type": "Feature",
  "properties": {
    "gn:admin1_code":"20.0",
    "gn:asciiname":"Supch'on",
    "gn:country_code":"KR",
    "gn:dem":126,
    "gn:feature_class":"P",
    "gn:feature_code":"PPL",
    "gn:name":"Supch\u2019on",
    "gn:population":0,
    "gn:timezone":"Asia/Seoul",
    "iso:country":"KR",
    "name:und_x_variant":[
        "Supch\u2019ol-li",
        "Supch\u2019on"
    ],
    "wof:name":"Supch'on",
    "wof:placetype":"locality"
},
  "geometry": {"coordinates":[128.79193999999998,35.5225],"type":"Point"}
}