{
  "type": "Feature",
  "properties": {
    "gn:admin1_code":"3.0",
    "gn:asciiname":"Hanodan",
    "gn:country_code":"KR",
    "gn:dem":284,
    "gn:feature_class":"P",
    "gn:feature_code":"PPL",
    "gn:name":"Hanodan",
    "gn:population":0,
    "gn:timezone":"Asia/Seoul",
    "iso:country":"KR",
    "name:und_x_variant":[
        "\ud558\ub178\ub2e8",
        "Hanodan"
    ],
    "wof:name":"Hanodan",
    "wof:placetype":"locality"
},
  "geometry": {"coordinates":[127.53357,35.52217],"type":"Point"}
}