{
  "type": "Feature",
  "properties": {
    "gn:admin1_code":"14.0",
    "gn:asciiname":"Ha-dong",
    "gn:country_code":"KR",
    "gn:dem":105,
    "gn:feature_class":"P",
    "gn:feature_code":"PPL",
    "gn:name":"Ha-dong",
    "gn:population":0,
    "gn:timezone":"Asia/Seoul",
    "iso:country":"KR",
    "name:und_x_variant":[
        "Hwa-dong",
        "\ud558\ub3d9",
        "Ha-dong"
    ],
    "wof:name":"Ha-dong",
    "wof:placetype":"locality"
},
  "geometry": {"coordinates":[129.3638,37.084],"type":"Point"}
}