{
  "type": "Feature",
  "properties": {
    "gn:admin1_code":"17.0",
    "gn:asciiname":"Junggunmoraengi",
    "gn:country_code":"KR",
    "gn:dem":60,
    "gn:feature_class":"P",
    "gn:feature_code":"PPL",
    "gn:name":"Junggunmoraengi",
    "gn:population":0,
    "gn:timezone":"Asia/Seoul",
    "iso:country":"KR",
    "name:kor_x_preferred":[
        "\uc911\uad70\ubaa8\ub7ad\uc774"
    ],
    "wof:name":"Junggunmoraengi",
    "wof:placetype":"locality"
},
  "geometry": {"coordinates":[127.30058,36.76372],"type":"Point"}
}