{
  "type": "Feature",
  "properties": {
    "gn:admin1_code":"16.0",
    "gn:asciiname":"Naejang",
    "gn:country_code":"KR",
    "gn:dem":13,
    "gn:feature_class":"P",
    "gn:feature_code":"PPL",
    "gn:name":"Naejang",
    "gn:population":0,
    "gn:timezone":"Asia/Seoul",
    "iso:country":"KR",
    "name:kor_x_preferred":[
        "\ub0b4\uc7a5"
    ],
    "name:und_x_variant":[
        "Naich\u014d",
        "Naejang-ni",
        "Naejang"
    ],
    "wof:name":"Naejang",
    "wof:placetype":"locality"
},
  "geometry": {"coordinates":[126.4875,34.3825],"type":"Point"}
}