{
  "type": "Feature",
  "properties": {
    "gn:admin1_code":"11.0",
    "gn:asciiname":"Miail-tong",
    "gn:country_code":"KR",
    "gn:dem":82,
    "gn:feature_class":"P",
    "gn:feature_code":"PPL",
    "gn:name":"Miail-tong",
    "gn:population":0,
    "gn:timezone":"Asia/Seoul",
    "iso:country":"KR",
    "name:eng_x_preferred":[
        "Miail"
    ],
    "name:eng_x_variant":[
        "Miail-tong"
    ],
    "name:und_x_variant":[
        "\ubbf8\uc5441\ub3d9",
        "Miail-tong"
    ],
    "wof:name":"Miail",
    "wof:placetype":"locality"
},
  "geometry": {"coordinates":[127.01416999999999,37.62123],"type":"Point"}
}