{
  "type": "Feature",
  "properties": {
    "gn:admin1_code":"14.0",
    "gn:asciiname":"Nodal",
    "gn:country_code":"KR",
    "gn:dem":190,
    "gn:feature_class":"P",
    "gn:feature_code":"PPL",
    "gn:name":"Nodal",
    "gn:population":0,
    "gn:timezone":"Asia/Seoul",
    "iso:country":"KR",
    "name:deu_x_preferred":[
        "Nodal"
    ],
    "name:und_x_variant":[
        "Nodal-tong",
        "\ub178\ub2ec",
        "Kolnodal"
    ],
    "wof:name":"Nodal",
    "wof:placetype":"locality"
},
  "geometry": {"coordinates":[129.09110000000001,36.5737],"type":"Point"}
}