{
  "type": "Feature",
  "properties": {
    "gn:admin1_code":"16.0",
    "gn:asciiname":"An'gong-ni",
    "gn:country_code":"KR",
    "gn:dem":13,
    "gn:feature_class":"P",
    "gn:feature_code":"PPL",
    "gn:name":"An\u2019gong-ni",
    "gn:population":0,
    "gn:timezone":"Asia/Seoul",
    "iso:country":"KR",
    "name:eng_x_preferred":[
        "An'gong"
    ],
    "name:eng_x_variant":[
        "An'gong-ni"
    ],
    "wof:name":"An'gong",
    "wof:placetype":"locality"
},
  "geometry": {"coordinates":[126.60056,35.05444],"type":"Point"}
}