{
  "type": "Feature",
  "properties": {
    "gn:admin1_code":"5.0",
    "gn:asciiname":"Wontaebi",
    "gn:country_code":"KR",
    "gn:dem":300,
    "gn:feature_class":"P",
    "gn:feature_code":"PPL",
    "gn:name":"Wontaebi",
    "gn:population":0,
    "gn:timezone":"Asia/Seoul",
    "iso:country":"KR",
    "name:kor_x_preferred":[
        "\uc6d0\ud0dc\ube44"
    ],
    "wof:name":"Wontaebi",
    "wof:placetype":"locality"
},
  "geometry": {"coordinates":[127.84111,36.67496],"type":"Point"}
}