{
  "type": "Feature",
  "properties": {
    "iso:country":"KR",
    "name:eng_x_preferred":[
        "Hoenam-myeon"
    ],
    "name:kor_x_preferred":[
        "\ud68c\ub0a8\uba74"
    ],
    "qs:name":"\ud68c\ub0a8\uba74",
    "qs:name_adm0":"\ud55c\uad6d",
    "qs:name_adm1":"\ucda9\uccad\ubd81\ub3c4",
    "qs:photos":29,
    "qs:photos_1k":6,
    "qs:photos_9k":1,
    "qs:photos_9r":2,
    "qs:photos_all":29,
    "qs:photos_sr":2,
    "qs:placetype":"LocalAdmin",
    "qs:pop_sr":"0",
    "wof:name":"Hoenam-myeon",
    "wof:placetype":"localadmin"
},
  "geometry": {"coordinates":[127.711944,36.472098],"type":"Point"}
}