{
  "type": "Feature",
  "properties": {
    "gn:admin1_code":"5.0",
    "gn:asciiname":"Tondae",
    "gn:country_code":"KR",
    "gn:dem":217,
    "gn:feature_class":"P",
    "gn:feature_code":"PPL",
    "gn:name":"Tondae",
    "gn:population":0,
    "gn:timezone":"Asia/Seoul",
    "iso:country":"KR",
    "name:und_x_variant":[
        "\ub3c8\ub300",
        "Tondae"
    ],
    "wof:name":"Tondae",
    "wof:placetype":"locality"
},
  "geometry": {"coordinates":[127.9182,36.1574],"type":"Point"}
}