{
  "type": "Feature",
  "properties": {
    "gn:admin1_code":"11.0",
    "gn:asciiname":"Kongnungi-dong",
    "gn:country_code":"KR",
    "gn:dem":59,
    "gn:feature_class":"P",
    "gn:feature_code":"PPL",
    "gn:name":"Kongn\u016dngi-dong",
    "gn:population":0,
    "gn:timezone":"Asia/Seoul",
    "iso:country":"KR",
    "name:und_x_variant":[
        "\uacf5\ub9892\ub3d9",
        "Kongn\u016dngi-dong"
    ],
    "wof:name":"Kongnungi-dong",
    "wof:placetype":"locality"
},
  "geometry": {"coordinates":[127.09181,37.63139],"type":"Point"}
}