{
  "type": "Feature",
  "properties": {
    "gn:admin1_code":"16.0",
    "gn:asciiname":"Hwalmok",
    "gn:country_code":"KR",
    "gn:dem":14,
    "gn:feature_class":"P",
    "gn:feature_code":"PPL",
    "gn:name":"Hwalmok",
    "gn:population":0,
    "gn:timezone":"Asia/Seoul",
    "iso:country":"KR",
    "wof:name":"Hwalmok",
    "wof:placetype":"locality"
},
  "geometry": {"coordinates":[126.59444000000001,34.19944],"type":"Point"}
}