{
  "type": "Feature",
  "properties": {
    "gn:admin1_code":"16.0",
    "gn:asciiname":"Saeteo",
    "gn:country_code":"KR",
    "gn:dem":31,
    "gn:feature_class":"P",
    "gn:feature_code":"PPL",
    "gn:name":"Saeteo",
    "gn:population":0,
    "gn:timezone":"Asia/Seoul",
    "iso:country":"KR",
    "name:kor_x_preferred":[
        "\uc0c8\ud130"
    ],
    "name:und_x_variant":[
        "Sin\u2019gi",
        "Saet\u2019\u014f",
        "Saeteo"
    ],
    "wof:name":"Saeteo",
    "wof:placetype":"locality"
},
  "geometry": {"coordinates":[126.77287,34.9723],"type":"Point"}
}