{
  "type": "Feature",
  "properties": {
    "gn:admin1_code":"20.0",
    "gn:asciiname":"Maehwa-gol",
    "gn:country_code":"KR",
    "gn:dem":70,
    "gn:feature_class":"P",
    "gn:feature_code":"PPL",
    "gn:name":"Maehwa-gol",
    "gn:population":0,
    "gn:timezone":"Asia/Seoul",
    "iso:country":"KR",
    "name:und_x_variant":[
        "\ub9e4\ud654\uace8",
        "Maehwa-gol"
    ],
    "wof:name":"Maehwa-gol",
    "wof:placetype":"locality"
},
  "geometry": {"coordinates":[128.32831000000002,35.19319],"type":"Point"}
}