{
  "type": "Feature",
  "properties": {
    "gn:admin1_code":"17.0",
    "gn:asciiname":"Chungwajong",
    "gn:country_code":"KR",
    "gn:dem":233,
    "gn:feature_class":"P",
    "gn:feature_code":"PPL",
    "gn:name":"Chungwaj\u014fng",
    "gn:population":0,
    "gn:timezone":"Asia/Seoul",
    "iso:country":"KR",
    "name:und_x_variant":[
        "\uc911\uc640\uc815",
        "Chungwaj\u014fng"
    ],
    "wof:name":"Chungwajong",
    "wof:placetype":"locality"
},
  "geometry": {"coordinates":[127.4444,36.0982],"type":"Point"}
}