{
  "type": "Feature",
  "properties": {
    "gn:admin1_code":"14.0",
    "gn:asciiname":"Seodanggol",
    "gn:country_code":"KR",
    "gn:dem":207,
    "gn:feature_class":"P",
    "gn:feature_code":"PPL",
    "gn:name":"Seodanggol",
    "gn:population":0,
    "gn:timezone":"Asia/Seoul",
    "iso:country":"KR",
    "name:kor_x_preferred":[
        "\uc11c\ub2f9\uace8"
    ],
    "wof:name":"Seodanggol",
    "wof:placetype":"locality"
},
  "geometry": {"coordinates":[128.86777000000001,36.64769],"type":"Point"}
}