{
  "type": "Feature",
  "properties": {
    "gn:admin1_code":"13.0",
    "gn:asciiname":"Oemani",
    "gn:country_code":"KR",
    "gn:dem":35,
    "gn:feature_class":"P",
    "gn:feature_code":"PPL",
    "gn:name":"Oemani",
    "gn:population":0,
    "gn:timezone":"Asia/Seoul",
    "iso:country":"KR",
    "name:kor_x_preferred":[
        "\uc678\ub9c8\ub2c8"
    ],
    "wof:name":"Oemani",
    "wof:placetype":"locality"
},
  "geometry": {"coordinates":[126.82250000000001,37.18417],"type":"Point"}
}