{
  "type": "Feature",
  "properties": {
    "gn:admin1_code":"13.0",
    "gn:asciiname":"Sindaechon",
    "gn:country_code":"KR",
    "gn:dem":58,
    "gn:feature_class":"P",
    "gn:feature_code":"PPL",
    "gn:name":"Sindaechon",
    "gn:population":0,
    "gn:timezone":"Asia/Seoul",
    "iso:country":"KR",
    "name:kor_x_preferred":[
        "\uc2e0\ub300\ucd0c"
    ],
    "name:kor_x_variant":[
        "Sindae-ch\u2019on"
    ],
    "name:und_x_variant":[
        "Sandae-ch\u2019on",
        "Sindaechon"
    ],
    "wof:name":"Sindaechon",
    "wof:placetype":"locality"
},
  "geometry": {"coordinates":[127.69268,37.25089000000001],"type":"Point"}
}