{
  "type": "Feature",
  "properties": {
    "gn:admin1_code":"17.0",
    "gn:asciiname":"Pulgundaengi",
    "gn:country_code":"KR",
    "gn:dem":45,
    "gn:feature_class":"P",
    "gn:feature_code":"PPL",
    "gn:name":"Pulg\u016dndaengi",
    "gn:population":0,
    "gn:timezone":"Asia/Seoul",
    "iso:country":"KR",
    "name:und_x_variant":[
        "\ubd89\uc740\ub315\uc774",
        "Pulg\u016dndaengi"
    ],
    "wof:name":"Pulgundaengi",
    "wof:placetype":"locality"
},
  "geometry": {"coordinates":[126.6157,36.2644],"type":"Point"}
}