{
  "type": "Feature",
  "properties": {
    "gn:admin1_code":"5.0",
    "gn:asciiname":"Imiseol",
    "gn:country_code":"KR",
    "gn:dem":97,
    "gn:feature_class":"P",
    "gn:feature_code":"PPL",
    "gn:name":"Imiseol",
    "gn:population":0,
    "gn:timezone":"Asia/Seoul",
    "iso:country":"KR",
    "name:kor_x_preferred":[
        "\uc784\uc774\uc124"
    ],
    "wof:name":"Imiseol",
    "wof:placetype":"locality"
},
  "geometry": {"coordinates":[127.51913999999999,36.95482],"type":"Point"}
}