{
  "type": "Feature",
  "properties": {
    "gn:admin1_code":"13.0",
    "gn:asciiname":"Sut'aegil-tong",
    "gn:country_code":"KR",
    "gn:dem":45,
    "gn:feature_class":"P",
    "gn:feature_code":"PPL",
    "gn:name":"Sut\u2019aegil-tong",
    "gn:population":0,
    "gn:timezone":"Asia/Seoul",
    "iso:country":"KR",
    "name:eng_x_preferred":[
        "Sut'aegil"
    ],
    "name:eng_x_variant":[
        "Sut'aegil-tong"
    ],
    "name:kor_x_preferred":[
        "\uc218\ud0dd1\ub3d9"
    ],
    "name:und_x_variant":[
        "Sut\u2019aegil-tong"
    ],
    "wof:name":"Sut'aegil",
    "wof:placetype":"locality"
},
  "geometry": {"coordinates":[127.14935,37.59871],"type":"Point"}
}