{
  "type": "Feature",
  "properties": {
    "gn:admin1_code":"5.0",
    "gn:asciiname":"Chamae",
    "gn:country_code":"KR",
    "gn:dem":111,
    "gn:feature_class":"P",
    "gn:feature_code":"PPL",
    "gn:name":"Chamae",
    "gn:population":0,
    "gn:timezone":"Asia/Seoul",
    "iso:country":"KR",
    "name:und_x_variant":[
        "\uc790\ub9e4"
    ],
    "wof:name":"Chamae",
    "wof:placetype":"locality"
},
  "geometry": {"coordinates":[127.7723,36.3202],"type":"Point"}
}