{
  "type": "Feature",
  "properties": {
    "gn:admin1_code":"16.0",
    "gn:asciiname":"Jigye",
    "gn:country_code":"KR",
    "gn:dem":211,
    "gn:feature_class":"P",
    "gn:feature_code":"PPL",
    "gn:name":"Jigye",
    "gn:population":0,
    "gn:timezone":"Asia/Seoul",
    "iso:country":"KR",
    "name:kor_x_preferred":[
        "\uc9c0\uacc4"
    ],
    "name:und_x_variant":[
        "Chigae",
        "Chige",
        "Chigye",
        "Jigye"
    ],
    "wof:name":"Jigye",
    "wof:placetype":"locality"
},
  "geometry": {"coordinates":[127.68039,35.07983],"type":"Point"}
}