{
  "type": "Feature",
  "properties": {
    "gn:admin1_code":"5.0",
    "gn:asciiname":"Ansan",
    "gn:country_code":"KR",
    "gn:dem":71,
    "gn:feature_class":"P",
    "gn:feature_code":"PPL",
    "gn:name":"Ansan",
    "gn:population":0,
    "gn:timezone":"Asia/Seoul",
    "iso:country":"KR",
    "name:kor_x_preferred":[
        "\uc548\uc0b0"
    ],
    "wof:name":"Ansan",
    "wof:placetype":"locality"
},
  "geometry": {"coordinates":[127.6437,37.1126],"type":"Point"}
}