{
  "type": "Feature",
  "properties": {
    "gn:admin1_code":"20.0",
    "gn:asciiname":"Chiritt'o",
    "gn:country_code":"KR",
    "gn:dem":85,
    "gn:feature_class":"P",
    "gn:feature_code":"PPL",
    "gn:name":"Chiritt\u2019\u014f",
    "gn:population":0,
    "gn:timezone":"Asia/Seoul",
    "iso:country":"KR",
    "name:und_x_variant":[
        "\uc9c0\ub9bf\ud130",
        "Chiritt\u2019\u014f"
    ],
    "wof:name":"Chiritt'o",
    "wof:placetype":"locality"
},
  "geometry": {"coordinates":[128.20614,35.63641],"type":"Point"}
}