{
  "type": "Feature",
  "properties": {
    "gn:admin1_code":"5.0",
    "gn:asciiname":"Yangji-mal",
    "gn:country_code":"KR",
    "gn:dem":242,
    "gn:feature_class":"P",
    "gn:feature_code":"PPL",
    "gn:name":"Yangji-mal",
    "gn:population":0,
    "gn:timezone":"Asia/Seoul",
    "iso:country":"KR",
    "wof:name":"Yangji-mal",
    "wof:placetype":"locality"
},
  "geometry": {"coordinates":[127.94889000000001,36.81806],"type":"Point"}
}