{
  "type": "Feature",
  "properties": {
    "gn:admin1_code":"17.0",
    "gn:asciiname":"Ch'ongnyang-ni",
    "gn:country_code":"KR",
    "gn:dem":16,
    "gn:feature_class":"P",
    "gn:feature_code":"PPL",
    "gn:name":"Ch\u2019\u014fngnyang-ni",
    "gn:population":0,
    "gn:timezone":"Asia/Seoul",
    "iso:country":"KR",
    "name:eng_x_preferred":[
        "Ch'ongnyang"
    ],
    "name:eng_x_variant":[
        "Ch'ongnyang-ni"
    ],
    "name:und_x_variant":[
        "\uccad\ub7c9\ub9ac",
        "Ch\u2019\u014fngnyang-ni"
    ],
    "wof:name":"Ch'ongnyang",
    "wof:placetype":"locality"
},
  "geometry": {"coordinates":[126.46129999999999,36.9494],"type":"Point"}
}