{
  "type": "Feature",
  "properties": {
    "gn:admin1_code":"13.0",
    "gn:asciiname":"Segok",
    "gn:country_code":"KR",
    "gn:dem":119,
    "gn:feature_class":"P",
    "gn:feature_code":"PPL",
    "gn:name":"Segok",
    "gn:population":0,
    "gn:timezone":"Asia/Seoul",
    "iso:country":"KR",
    "name:und_x_variant":[
        "\uc138\uace1",
        "Segok"
    ],
    "wof:name":"Segok",
    "wof:placetype":"locality"
},
  "geometry": {"coordinates":[127.0086,37.9535],"type":"Point"}
}