{
  "type": "Feature",
  "properties": {
    "gn:admin1_code":"13.0",
    "gn:asciiname":"Chansaemgol",
    "gn:country_code":"KR",
    "gn:dem":97,
    "gn:feature_class":"P",
    "gn:feature_code":"PPL",
    "gn:name":"Chansaemgol",
    "gn:population":0,
    "gn:timezone":"Asia/Seoul",
    "iso:country":"KR",
    "name:kor_x_preferred":[
        "\ucc2c\uc0d8\uace8"
    ],
    "name:kor_x_variant":[
        "Ch\u2019ansaem-gol"
    ],
    "wof:name":"Chansaemgol",
    "wof:placetype":"locality"
},
  "geometry": {"coordinates":[127.53149000000001,37.14698],"type":"Point"}
}