{
  "type": "Feature",
  "properties": {
    "gn:admin1_code":"14.0",
    "gn:asciiname":"Sunamugol",
    "gn:country_code":"KR",
    "gn:dem":136,
    "gn:feature_class":"P",
    "gn:feature_code":"PPL",
    "gn:name":"Sunamugol",
    "gn:population":0,
    "gn:timezone":"Asia/Seoul",
    "iso:country":"KR",
    "name:kor_x_preferred":[
        "\uc218\ub098\ubb34\uace8"
    ],
    "wof:name":"Sunamugol",
    "wof:placetype":"locality"
},
  "geometry": {"coordinates":[128.47512,36.68664],"type":"Point"}
}