{
  "type": "Feature",
  "properties": {
    "iso:country":"KR",
    "name:eng_x_preferred":[
        "Changpyeong-myeon"
    ],
    "name:kor_x_preferred":[
        "\ucc3d\ud3c9\uba74"
    ],
    "qs:name":"\ucc3d\ud3c9\uba74",
    "qs:name_adm0":"\ud55c\uad6d",
    "qs:name_adm1":"\uc804\ub77c\ub0a8\ub3c4",
    "qs:photos":6,
    "qs:photos_1k":1,
    "qs:photos_9k":1,
    "qs:photos_9r":1,
    "qs:photos_all":6,
    "qs:photos_sr":1,
    "qs:placetype":"LocalAdmin",
    "qs:pop_sr":"0",
    "wof:name":"Changpyeong-myeon",
    "wof:placetype":"localadmin"
},
  "geometry": {"coordinates":[127.025581,35.3271105],"type":"Point"}
}