{
  "type": "Feature",
  "properties": {
    "gn:admin1_code":"17.0",
    "gn:asciiname":"Puktumo-ri",
    "gn:country_code":"KR",
    "gn:dem":112,
    "gn:feature_class":"P",
    "gn:feature_code":"PPL",
    "gn:name":"Puktum\u014f-ri",
    "gn:population":0,
    "gn:timezone":"Asia/Seoul",
    "iso:country":"KR",
    "name:und_x_variant":[
        "\ubd81\ub450\uba38\ub9ac",
        "Puktum\u014f-ri"
    ],
    "wof:name":"Puktumo-ri",
    "wof:placetype":"locality"
},
  "geometry": {"coordinates":[126.70189999999999,36.2995],"type":"Point"}
}