{
  "type": "Feature",
  "properties": {
    "gn:admin1_code":"16.0",
    "gn:asciiname":"Chikusei-ri",
    "gn:country_code":"KR",
    "gn:dem":13,
    "gn:feature_class":"P",
    "gn:feature_code":"PPL",
    "gn:name":"Chikusei-ri",
    "gn:population":0,
    "gn:timezone":"Asia/Seoul",
    "iso:country":"KR",
    "name:kor_x_preferred":[
        "\uc8fd\uccad\ub9ac"
    ],
    "name:kor_x_variant":[
        "Chukch\u2019\u014fng-ni"
    ],
    "name:und_x_variant":[
        "Chukch\u2019\u014fng"
    ],
    "wof:name":"Chikusei-ri",
    "wof:placetype":"locality"
},
  "geometry": {"coordinates":[126.97638999999999,34.58222],"type":"Point"}
}