{
  "type": "Feature",
  "properties": {
    "gn:admin1_code":"13.0",
    "gn:asciiname":"Anteo",
    "gn:country_code":"KR",
    "gn:dem":78,
    "gn:feature_class":"P",
    "gn:feature_code":"PPL",
    "gn:name":"Anteo",
    "gn:population":0,
    "gn:timezone":"Asia/Seoul",
    "iso:country":"KR",
    "name:kor_x_preferred":[
        "\uc548\ud130"
    ],
    "name:kor_x_variant":[
        "Ant\u2019\u014f"
    ],
    "wof:name":"Anteo",
    "wof:placetype":"locality"
},
  "geometry": {"coordinates":[127.61321,37.15107],"type":"Point"}
}