{
  "type": "Feature",
  "properties": {
    "gn:admin1_code":"16.0",
    "gn:asciiname":"Komam-ni",
    "gn:country_code":"KR",
    "gn:dem":78,
    "gn:feature_class":"P",
    "gn:feature_code":"PPL",
    "gn:name":"K\u014fmam-ni",
    "gn:population":0,
    "gn:timezone":"Asia/Seoul",
    "iso:country":"KR",
    "name:kor_x_preferred":[
        "\uac80\uc554\ub9ac"
    ],
    "name:kor_x_variant":[
        "K\u014fmam-ni"
    ],
    "wof:name":"Komam-ni",
    "wof:placetype":"locality"
},
  "geometry": {"coordinates":[127.32449,34.90367],"type":"Point"}
}