{
  "type": "Feature",
  "properties": {
    "gn:admin1_code":"14.0",
    "gn:asciiname":"Kwon-ch'on",
    "gn:country_code":"KR",
    "gn:dem":80,
    "gn:feature_class":"P",
    "gn:feature_code":"PPL",
    "gn:name":"Kw\u014fn-ch\u2019on",
    "gn:population":0,
    "gn:timezone":"Asia/Seoul",
    "iso:country":"KR",
    "name:und_x_variant":[
        "\uad8c\ucd0c",
        "Kw\u014fn-ch\u2019on"
    ],
    "wof:name":"Kwon-ch'on",
    "wof:placetype":"locality"
},
  "geometry": {"coordinates":[129.3724,36.5158],"type":"Point"}
}