{
  "type": "Feature",
  "properties": {
    "gn:admin1_code":"5.0",
    "gn:asciiname":"Beomui",
    "gn:country_code":"KR",
    "gn:dem":159,
    "gn:feature_class":"P",
    "gn:feature_code":"PPL",
    "gn:name":"Beomui",
    "gn:population":0,
    "gn:timezone":"Asia/Seoul",
    "iso:country":"KR",
    "name:kor_x_preferred":[
        "\ubc94\uc758"
    ],
    "name:kor_x_variant":[
        "P\u014fm\u016di"
    ],
    "wof:name":"Beomui",
    "wof:placetype":"locality"
},
  "geometry": {"coordinates":[127.96468,36.97478],"type":"Point"}
}