{
  "type": "Feature",
  "properties": {
    "gn:admin1_code":"13.0",
    "gn:asciiname":"Sasa-dong",
    "gn:country_code":"KR",
    "gn:dem":56,
    "gn:feature_class":"P",
    "gn:feature_code":"PPLL",
    "gn:name":"Sasa-dong",
    "gn:population":0,
    "gn:timezone":"Asia/Seoul",
    "iso:country":"KR",
    "name:und_x_variant":[
        "\uc0ac\uc0ac\ub3d9",
        "Sasa-ni",
        "Sasa-dong"
    ],
    "wof:name":"Sasa-dong",
    "wof:placetype":"locality"
},
  "geometry": {"coordinates":[126.92556,37.29222],"type":"Point"}
}