{
  "type": "Feature",
  "properties": {
    "gn:admin1_code":"20.0",
    "gn:asciiname":"Taech'o-ri",
    "gn:country_code":"KR",
    "gn:dem":255,
    "gn:feature_class":"P",
    "gn:feature_code":"PPL",
    "gn:name":"Taech\u2019o-ri",
    "gn:population":0,
    "gn:timezone":"Asia/Seoul",
    "iso:country":"KR",
    "name:und_x_variant":[
        "\ub300\ucd08\ub9ac",
        "Taech\u2019o-ri"
    ],
    "wof:name":"Taech'o-ri",
    "wof:placetype":"locality"
},
  "geometry": {"coordinates":[128.01486,35.69132000000001],"type":"Point"}
}