{
  "type": "Feature",
  "properties": {
    "gn:admin1_code":"5.0",
    "gn:asciiname":"Chungung",
    "gn:country_code":"KR",
    "gn:dem":390,
    "gn:feature_class":"P",
    "gn:feature_code":"PPL",
    "gn:name":"Chungung",
    "gn:population":0,
    "gn:timezone":"Asia/Seoul",
    "iso:country":"KR",
    "name:und_x_variant":[
        "\uc911\uc6c5",
        "Chungung"
    ],
    "wof:name":"Chungung",
    "wof:placetype":"locality"
},
  "geometry": {"coordinates":[128.03018,36.25756],"type":"Point"}
}