{
  "type": "Feature",
  "properties": {
    "gn:admin1_code":"20.0",
    "gn:asciiname":"T'ap-tong",
    "gn:country_code":"KR",
    "gn:dem":48,
    "gn:feature_class":"P",
    "gn:feature_code":"PPL",
    "gn:name":"T\u2019ap-tong",
    "gn:population":0,
    "gn:timezone":"Asia/Seoul",
    "iso:country":"KR",
    "name:eng_x_preferred":[
        "T'ap"
    ],
    "name:eng_x_variant":[
        "T'ap-tong"
    ],
    "name:und_x_variant":[
        "T\u2019ap-kol",
        "\ud0d1\ub3d9",
        "T\u2019ap-tong"
    ],
    "wof:name":"T'ap",
    "wof:placetype":"locality"
},
  "geometry": {"coordinates":[128.39815999999999,35.09607],"type":"Point"}
}