{
  "type": "Feature",
  "properties": {
    "gn:admin1_code":"14.0",
    "gn:asciiname":"Chunggach'on",
    "gn:country_code":"KR",
    "gn:dem":312,
    "gn:feature_class":"P",
    "gn:feature_code":"PPL",
    "gn:name":"Chunggach\u2019\u014fn",
    "gn:population":0,
    "gn:timezone":"Asia/Seoul",
    "iso:country":"KR",
    "name:und_x_variant":[
        "\uc911\uac00\ucc9c",
        "Chunggach\u2019\u014fn"
    ],
    "wof:name":"Chunggach'on",
    "wof:placetype":"locality"
},
  "geometry": {"coordinates":[129.15979999999999,36.7141],"type":"Point"}
}