{
  "type": "Feature",
  "properties": {
    "gn:admin1_code":"3.0",
    "gn:asciiname":"Mansu-dong",
    "gn:country_code":"KR",
    "gn:dem":120,
    "gn:feature_class":"P",
    "gn:feature_code":"PPL",
    "gn:name":"Mansu-dong",
    "gn:population":0,
    "gn:timezone":"Asia/Seoul",
    "iso:country":"KR",
    "name:und_x_variant":[
        "\ub9cc\uc218\ub3d9",
        "Mansu-dong"
    ],
    "wof:name":"Mansu-dong",
    "wof:placetype":"locality"
},
  "geometry": {"coordinates":[127.2534,36.0446],"type":"Point"}
}