{
  "type": "Feature",
  "properties": {
    "gn:admin1_code":"17.0",
    "gn:asciiname":"Hagogae",
    "gn:country_code":"KR",
    "gn:dem":61,
    "gn:feature_class":"P",
    "gn:feature_code":"PPL",
    "gn:name":"Hagogae",
    "gn:population":0,
    "gn:timezone":"Asia/Seoul",
    "iso:country":"KR",
    "name:und_x_variant":[
        "\ud558\uace0\uac1c",
        "Hagogae"
    ],
    "wof:name":"Hagogae",
    "wof:placetype":"locality"
},
  "geometry": {"coordinates":[126.6384,36.589],"type":"Point"}
}