{
  "type": "Feature",
  "properties": {
    "gn:admin1_code":"19.0",
    "gn:asciiname":"Gilgok",
    "gn:country_code":"KR",
    "gn:dem":199,
    "gn:feature_class":"P",
    "gn:feature_code":"PPL",
    "gn:name":"Gilgok",
    "gn:population":0,
    "gn:timezone":"Asia/Seoul",
    "iso:country":"KR",
    "name:und_x_variant":[
        "\uae38\uace1",
        "Kilgok",
        "Gilgok"
    ],
    "wof:name":"Gilgok",
    "wof:placetype":"locality"
},
  "geometry": {"coordinates":[127.35351,36.21429000000001],"type":"Point"}
}