{
  "type": "Feature",
  "properties": {
    "gn:admin1_code":"0.0",
    "gn:asciiname":"Woram",
    "gn:country_code":"KR",
    "gn:dem":49,
    "gn:feature_class":"P",
    "gn:feature_code":"PPL",
    "gn:name":"Woram",
    "gn:population":0,
    "gn:timezone":"Asia/Seoul",
    "iso:country":"KR",
    "name:kor_x_preferred":[
        "\uc6d4\uc554"
    ],
    "name:und_x_variant":[
        "W\u014fram"
    ],
    "wof:name":"Woram",
    "wof:placetype":"locality"
},
  "geometry": {"coordinates":[127.77572000000001,34.66817],"type":"Point"}
}