{
  "type": "Feature",
  "properties": {
    "gn:admin1_code":"18.0",
    "gn:asciiname":"Geumdang",
    "gn:country_code":"KR",
    "gn:dem":39,
    "gn:feature_class":"P",
    "gn:feature_code":"PPL",
    "gn:name":"Geumdang",
    "gn:population":0,
    "gn:timezone":"Asia/Seoul",
    "iso:country":"KR",
    "name:kor_x_preferred":[
        "\uae08\ub2f9"
    ],
    "wof:name":"Geumdang",
    "wof:placetype":"locality"
},
  "geometry": {"coordinates":[126.87045000000001,35.24213],"type":"Point"}
}