{
  "type": "Feature",
  "properties": {
    "gn:admin1_code":"6.0",
    "gn:asciiname":"Bangtong",
    "gn:country_code":"KR",
    "gn:dem":281,
    "gn:feature_class":"P",
    "gn:feature_code":"PPL",
    "gn:name":"Bangtong",
    "gn:population":0,
    "gn:timezone":"Asia/Seoul",
    "iso:country":"KR",
    "name:und_x_variant":[
        "Pangt\u2019ong"
    ],
    "wof:name":"Bangtong",
    "wof:placetype":"locality"
},
  "geometry": {"coordinates":[127.54333,38.31306],"type":"Point"}
}