{
  "type": "Feature",
  "properties": {
    "gn:admin1_code":"16.0",
    "gn:asciiname":"Am-dong",
    "gn:cc2":"KR",
    "gn:country_code":"KR",
    "gn:dem":45,
    "gn:feature_class":"P",
    "gn:feature_code":"PPL",
    "gn:name":"Am-dong",
    "gn:population":0,
    "gn:timezone":"Asia/Seoul",
    "iso:country":"KR",
    "name:und_x_variant":[
        "Amch\u2019on",
        "Am-dong"
    ],
    "wof:name":"Am-dong",
    "wof:placetype":"locality"
},
  "geometry": {"coordinates":[125.39639,34.64361],"type":"Point"}
}