{
  "type": "Feature",
  "properties": {
    "gn:admin1_code":"13.0",
    "gn:asciiname":"Sungbangteo",
    "gn:country_code":"KR",
    "gn:dem":176,
    "gn:feature_class":"P",
    "gn:feature_code":"PPL",
    "gn:name":"Sungbangteo",
    "gn:population":0,
    "gn:timezone":"Asia/Seoul",
    "iso:country":"KR",
    "name:und_x_variant":[
        "\uc22d\ubc29\ud130",
        "Sungbangteo",
        "Sungbangt\u2019\u014f"
    ],
    "wof:name":"Sungbangteo",
    "wof:placetype":"locality"
},
  "geometry": {"coordinates":[127.29555999999999,37.31806],"type":"Point"}
}