{
  "type": "Feature",
  "properties": {
    "gn:admin1_code":"6.0",
    "gn:asciiname":"Chinp'o-ri",
    "gn:country_code":"KR",
    "gn:dem":372,
    "gn:feature_class":"P",
    "gn:feature_code":"PPL",
    "gn:name":"Chinp\u2019o-ri",
    "gn:population":0,
    "gn:timezone":"Asia/Seoul",
    "iso:country":"KR",
    "name:kor_x_preferred":[
        "\uc9c4\ud3ec\ub9ac"
    ],
    "name:kor_x_variant":[
        "Chinp\u2019o-ri"
    ],
    "wof:name":"Chinp'o-ri",
    "wof:placetype":"locality"
},
  "geometry": {"coordinates":[128.63829999999999,37.3911],"type":"Point"}
}