{
  "type": "Feature",
  "properties": {
    "gn:admin1_code":"17.0",
    "gn:asciiname":"Sonsa",
    "gn:country_code":"KR",
    "gn:dem":186,
    "gn:feature_class":"P",
    "gn:feature_code":"PPL",
    "gn:name":"Sonsa",
    "gn:population":0,
    "gn:timezone":"Asia/Seoul",
    "iso:country":"KR",
    "name:und_x_variant":[
        "\uc190\uc0ac",
        "Sonsa"
    ],
    "wof:name":"Sonsa",
    "wof:placetype":"locality"
},
  "geometry": {"coordinates":[126.7133,36.2702],"type":"Point"}
}