{
  "type": "Feature",
  "properties": {
    "gn:admin1_code":"14.0",
    "gn:asciiname":"Gaebang",
    "gn:country_code":"KR",
    "gn:dem":183,
    "gn:feature_class":"P",
    "gn:feature_code":"PPL",
    "gn:name":"Gaebang",
    "gn:population":0,
    "gn:timezone":"Asia/Seoul",
    "iso:country":"KR",
    "name:kor_x_preferred":[
        "\uac1c\ubc29"
    ],
    "wof:name":"Gaebang",
    "wof:placetype":"locality"
},
  "geometry": {"coordinates":[128.38931000000002,36.68174000000001],"type":"Point"}
}