{
  "type": "Feature",
  "properties": {
    "gn:admin1_code":"14.0",
    "gn:asciiname":"Obae",
    "gn:country_code":"KR",
    "gn:dem":181,
    "gn:feature_class":"P",
    "gn:feature_code":"PPL",
    "gn:name":"Obae",
    "gn:population":0,
    "gn:timezone":"Asia/Seoul",
    "iso:country":"KR",
    "name:und_x_variant":[
        "\uc624\ubc30",
        "Obae"
    ],
    "wof:name":"Obae",
    "wof:placetype":"locality"
},
  "geometry": {"coordinates":[129.13272000000001,36.01415],"type":"Point"}
}