{
  "type": "Feature",
  "properties": {
    "gn:admin1_code":"20.0",
    "gn:asciiname":"Sanch'on",
    "gn:country_code":"KR",
    "gn:dem":13,
    "gn:feature_class":"P",
    "gn:feature_code":"PPL",
    "gn:name":"Sanch\u2019on",
    "gn:population":0,
    "gn:timezone":"Asia/Seoul",
    "iso:country":"KR",
    "name:und_x_variant":[
        "Sanch\u2019on-ni",
        "Sanch\u2019on"
    ],
    "wof:name":"Sanch'on",
    "wof:placetype":"locality"
},
  "geometry": {"coordinates":[128.60471999999999,34.83111],"type":"Point"}
}