{
  "type": "Feature",
  "properties": {
    "gn:admin1_code":"14.0",
    "gn:asciiname":"Wisateumsil",
    "gn:country_code":"KR",
    "gn:dem":118,
    "gn:feature_class":"P",
    "gn:feature_code":"PPL",
    "gn:name":"Wisateumsil",
    "gn:population":0,
    "gn:timezone":"Asia/Seoul",
    "iso:country":"KR",
    "name:kor_x_preferred":[
        "\uc717\uc544\ud2c8\uc2e4"
    ],
    "name:und_x_variant":[
        "Sanga-dong",
        "Udat\u2019\u016dmsil",
        "Widar\u016dmsil",
        "Widat\u2019\u016dmsil",
        "Wisateumsil"
    ],
    "wof:name":"Wisateumsil",
    "wof:placetype":"locality"
},
  "geometry": {"coordinates":[128.58476000000002,36.51786],"type":"Point"}
}