{
  "type": "Feature",
  "properties": {
    "gn:admin1_code":"16.0",
    "gn:asciiname":"Namsong-ni",
    "gn:country_code":"KR",
    "gn:dem":16,
    "gn:feature_class":"P",
    "gn:feature_code":"PPL",
    "gn:name":"Nams\u014fng-ni",
    "gn:population":0,
    "gn:timezone":"Asia/Seoul",
    "iso:country":"KR",
    "name:kor_x_preferred":[
        "\ub0a8\uc131\ub9ac"
    ],
    "name:kor_x_variant":[
        "Nams\u014fng-ni"
    ],
    "wof:name":"Namsong-ni",
    "wof:placetype":"locality"
},
  "geometry": {"coordinates":[127.40521,34.52543],"type":"Point"}
}