{
  "type": "Feature",
  "properties": {
    "gn:admin1_code":"16.0",
    "gn:asciiname":"Noppau",
    "gn:country_code":"KR",
    "gn:dem":19,
    "gn:feature_class":"P",
    "gn:feature_code":"PPL",
    "gn:name":"N\u014fppau",
    "gn:population":0,
    "gn:timezone":"Asia/Seoul",
    "iso:country":"KR",
    "name:kor_x_preferred":[
        "N\u014fppau"
    ],
    "wof:name":"Noppau",
    "wof:placetype":"locality"
},
  "geometry": {"coordinates":[126.97611000000001,34.48722],"type":"Point"}
}