{
  "type": "Feature",
  "properties": {
    "gn:admin1_code":"16.0",
    "gn:asciiname":"Hwangok",
    "gn:country_code":"KR",
    "gn:dem":34,
    "gn:feature_class":"P",
    "gn:feature_code":"PPL",
    "gn:name":"Hwangok",
    "gn:population":0,
    "gn:timezone":"Asia/Seoul",
    "iso:country":"KR",
    "name:kor_x_preferred":[
        "\ud658\uace1"
    ],
    "name:und_x_variant":[
        "Hwan\u2019gong-ni"
    ],
    "wof:name":"Hwangok",
    "wof:placetype":"locality"
},
  "geometry": {"coordinates":[126.60647,35.13392],"type":"Point"}
}