{
  "type": "Feature",
  "properties": {
    "gn:admin1_code":"17.0",
    "gn:asciiname":"Yukkong-ni",
    "gn:country_code":"KR",
    "gn:dem":52,
    "gn:feature_class":"P",
    "gn:feature_code":"PPL",
    "gn:name":"Yukkong-ni",
    "gn:population":0,
    "gn:timezone":"Asia/Seoul",
    "iso:country":"KR",
    "wof:name":"Yukkong-ni",
    "wof:placetype":"locality"
},
  "geometry": {"coordinates":[127.15944,36.1325],"type":"Point"}
}