{
  "type": "Feature",
  "properties": {
    "gn:admin1_code":"14.0",
    "gn:asciiname":"Sandaebatgol",
    "gn:country_code":"KR",
    "gn:dem":134,
    "gn:feature_class":"P",
    "gn:feature_code":"PPL",
    "gn:name":"Sandaebatgol",
    "gn:population":0,
    "gn:timezone":"Asia/Seoul",
    "iso:country":"KR",
    "name:kor_x_preferred":[
        "\uc0b0\ub300\ubc2d\uace8"
    ],
    "wof:name":"Sandaebatgol",
    "wof:placetype":"locality"
},
  "geometry": {"coordinates":[128.52081000000001,36.7045],"type":"Point"}
}