{
  "type": "Feature",
  "properties": {
    "gn:admin1_code":"13.0",
    "gn:asciiname":"Weongu-ri",
    "gn:country_code":"KR",
    "gn:dem":95,
    "gn:feature_class":"P",
    "gn:feature_code":"PPL",
    "gn:name":"Weongu-ri",
    "gn:population":0,
    "gn:timezone":"Asia/Seoul",
    "iso:country":"KR",
    "name:und_x_variant":[
        "\uc6d0\uad6c\ub9ac",
        "Weongu-ri",
        "W\u014fn\u2019gu-ri"
    ],
    "wof:name":"Weongu-ri",
    "wof:placetype":"locality"
},
  "geometry": {"coordinates":[127.71028,37.30778],"type":"Point"}
}