{
  "type": "Feature",
  "properties": {
    "gn:admin1_code":"11.0",
    "gn:asciiname":"Eunhaengdong",
    "gn:country_code":"KR",
    "gn:dem":51,
    "gn:feature_class":"P",
    "gn:feature_code":"PPL",
    "gn:name":"Eunhaengdong",
    "gn:population":0,
    "gn:timezone":"Asia/Seoul",
    "iso:country":"KR",
    "name:und_x_variant":[
        "\uc740\ud589\ub3d9",
        "\u016cnhaeng-dong",
        "Eunhaengdong"
    ],
    "wof:name":"Eunhaengdong",
    "wof:placetype":"locality"
},
  "geometry": {"coordinates":[127.0834,37.6484],"type":"Point"}
}