{
  "type": "Feature",
  "properties": {
    "gn:admin1_code":"5.0",
    "gn:asciiname":"Kongbung-ni",
    "gn:country_code":"KR",
    "gn:dem":51,
    "gn:feature_class":"P",
    "gn:feature_code":"PPL",
    "gn:name":"Kongbung-ni",
    "gn:population":0,
    "gn:timezone":"Asia/Seoul",
    "iso:country":"KR",
    "name:eng_x_preferred":[
        "Kongbung"
    ],
    "name:eng_x_variant":[
        "Kongbung-ni"
    ],
    "wof:name":"Kongbung",
    "wof:placetype":"locality"
},
  "geometry": {"coordinates":[127.31917,36.64806],"type":"Point"}
}