{
  "type": "Feature",
  "properties": {
    "gn:admin1_code":"11.0",
    "gn:asciiname":"Yonhui-dong",
    "gn:country_code":"KR",
    "gn:dem":47,
    "gn:feature_class":"P",
    "gn:feature_code":"PPL",
    "gn:name":"Y\u014fnh\u016di-dong",
    "gn:population":0,
    "gn:timezone":"Asia/Seoul",
    "iso:country":"KR",
    "name:und_x_variant":[
        "\uc5f0\ud76c\ub3d9",
        "Y\u014fnh\u016di-dong"
    ],
    "wof:name":"Yonhui-dong",
    "wof:placetype":"locality"
},
  "geometry": {"coordinates":[126.93559999999999,37.5738],"type":"Point"}
}