{
  "type": "Feature",
  "properties": {
    "gn:admin1_code":"16.0",
    "gn:asciiname":"Jangsa",
    "gn:country_code":"KR",
    "gn:dem":287,
    "gn:feature_class":"P",
    "gn:feature_code":"PPL",
    "gn:name":"Jangsa",
    "gn:population":0,
    "gn:timezone":"Asia/Seoul",
    "iso:country":"KR",
    "name:kor_x_preferred":[
        "\uc7a5\uc0ac"
    ],
    "name:und_x_variant":[
        "Changsa-ri",
        "Changsa",
        "Jangsa"
    ],
    "wof:name":"Jangsa",
    "wof:placetype":"locality"
},
  "geometry": {"coordinates":[126.84999999999999,35.38333],"type":"Point"}
}