{
  "type": "Feature",
  "properties": {
    "gn:admin1_code":"11.0",
    "gn:asciiname":"Chayang-dong",
    "gn:country_code":"KR",
    "gn:dem":23,
    "gn:feature_class":"P",
    "gn:feature_code":"PPL",
    "gn:name":"Chayang-dong",
    "gn:population":0,
    "gn:timezone":"Asia/Seoul",
    "iso:country":"KR",
    "name:und_x_variant":[
        "Sinyang",
        "Chamajang-ni",
        "Sinyang-dong",
        "\uc790\uc591\ub3d9",
        "Chayang-dong"
    ],
    "wof:name":"Chayang-dong",
    "wof:placetype":"locality"
},
  "geometry": {"coordinates":[127.0765,37.5316],"type":"Point"}
}