{
  "type": "Feature",
  "properties": {
    "gn:admin1_code":"17.0",
    "gn:asciiname":"Oesong",
    "gn:country_code":"KR",
    "gn:dem":18,
    "gn:feature_class":"P",
    "gn:feature_code":"PPL",
    "gn:name":"Oes\u014fng",
    "gn:population":0,
    "gn:timezone":"Asia/Seoul",
    "iso:country":"KR",
    "name:und_x_variant":[
        "Oes\u014fng-ni",
        "\uc678\uc131",
        "Oes\u014fng"
    ],
    "wof:name":"Oesong",
    "wof:placetype":"locality"
},
  "geometry": {"coordinates":[126.48284,36.8572],"type":"Point"}
}