{
  "type": "Feature",
  "properties": {
    "gn:admin1_code":"3.0",
    "gn:asciiname":"Kumgu",
    "gn:country_code":"KR",
    "gn:dem":42,
    "gn:feature_class":"P",
    "gn:feature_code":"PPL",
    "gn:name":"K\u016dmgu",
    "gn:population":0,
    "gn:timezone":"Asia/Seoul",
    "iso:country":"KR",
    "name:und_x_variant":[
        "Kink\u014d-ri",
        "K\u016dmgu",
        "K\u016dmgang",
        "\uae08\uad6c",
        "K\u016dmgu-ri"
    ],
    "wof:name":"Kumgu",
    "wof:placetype":"locality"
},
  "geometry": {"coordinates":[127.01027999999999,35.77389],"type":"Point"}
}