{
  "type": "Feature",
  "properties": {
    "gn:admin1_code":"14.0",
    "gn:asciiname":"Anyangji",
    "gn:country_code":"KR",
    "gn:dem":144,
    "gn:feature_class":"P",
    "gn:feature_code":"PPL",
    "gn:name":"Anyangji",
    "gn:population":0,
    "gn:timezone":"Asia/Seoul",
    "iso:country":"KR",
    "name:und_x_variant":[
        "\uc548\uc591\uc9c0",
        "Anyangji"
    ],
    "wof:name":"Anyangji",
    "wof:placetype":"locality"
},
  "geometry": {"coordinates":[128.73526000000001,35.59287],"type":"Point"}
}