{
  "type": "Feature",
  "properties": {
    "gn:admin1_code":"16.0",
    "gn:asciiname":"Buyeon",
    "gn:country_code":"KR",
    "gn:dem":56,
    "gn:feature_class":"P",
    "gn:feature_code":"PPL",
    "gn:name":"Buyeon",
    "gn:population":0,
    "gn:timezone":"Asia/Seoul",
    "iso:country":"KR",
    "name:kor_x_preferred":[
        "\ubd80\uc5f0"
    ],
    "wof:name":"Buyeon",
    "wof:placetype":"locality"
},
  "geometry": {"coordinates":[126.66534,35.24841],"type":"Point"}
}