{
  "type": "Feature",
  "properties": {
    "gn:admin1_code":"21.0",
    "gn:asciiname":"Malmi",
    "gn:country_code":"KR",
    "gn:dem":31,
    "gn:feature_class":"P",
    "gn:feature_code":"PPL",
    "gn:name":"Malmi",
    "gn:population":0,
    "gn:timezone":"Asia/Seoul",
    "iso:country":"KR",
    "name:fin_x_preferred":[
        "Malmi"
    ],
    "name:kor_x_preferred":[
        "\ub9d0\ubbf8"
    ],
    "name:swe_x_preferred":[
        "Malmi"
    ],
    "wof:name":"Malmi",
    "wof:placetype":"locality"
},
  "geometry": {"coordinates":[129.26830000000001,35.58469],"type":"Point"}
}