{
  "type": "Feature",
  "properties": {
    "gn:admin1_code":"6.0",
    "gn:asciiname":"Sinp'oi-ri",
    "gn:country_code":"KR",
    "gn:dem":139,
    "gn:feature_class":"P",
    "gn:feature_code":"PPL",
    "gn:name":"Sinp\u2019oi-ri",
    "gn:population":0,
    "gn:timezone":"Asia/Seoul",
    "iso:country":"KR",
    "name:und_x_variant":[
        "\uc2e0\ud3ec2\ub9ac",
        "Sinp\u2019oi-ri"
    ],
    "wof:name":"Sinp'oi-ri",
    "wof:placetype":"locality"
},
  "geometry": {"coordinates":[127.63443999999998,38.01833],"type":"Point"}
}