{
  "type": "Feature",
  "properties": {
    "gn:admin1_code":"14.0",
    "gn:asciiname":"Chamnamujeong",
    "gn:country_code":"KR",
    "gn:dem":246,
    "gn:feature_class":"P",
    "gn:feature_code":"PPL",
    "gn:name":"Chamnamujeong",
    "gn:population":0,
    "gn:timezone":"Asia/Seoul",
    "iso:country":"KR",
    "name:kor_x_preferred":[
        "\ucc38\ub098\ubb34\uc815"
    ],
    "wof:name":"Chamnamujeong",
    "wof:placetype":"locality"
},
  "geometry": {"coordinates":[129.35203999999999,35.83572],"type":"Point"}
}