{
  "type": "Feature",
  "properties": {
    "gn:admin1_code":"16.0",
    "gn:asciiname":"Hyogong-ni",
    "gn:cc2":"KR",
    "gn:country_code":"KR",
    "gn:dem":107,
    "gn:feature_class":"P",
    "gn:feature_code":"PPL",
    "gn:name":"Hyogong-ni",
    "gn:population":0,
    "gn:timezone":"Asia/Seoul",
    "iso:country":"KR",
    "name:und_x_variant":[
        "Hyojung-ni",
        "Hyogong-ni"
    ],
    "wof:name":"Hyogong-ni",
    "wof:placetype":"locality"
},
  "geometry": {"coordinates":[127.54333,35.14056],"type":"Point"}
}