{
  "type": "Feature",
  "properties": {
    "gn:admin1_code":"14.0",
    "gn:asciiname":"Sangpyeong",
    "gn:country_code":"KR",
    "gn:dem":165,
    "gn:feature_class":"P",
    "gn:feature_code":"PPL",
    "gn:name":"Sangpyeong",
    "gn:population":0,
    "gn:timezone":"Asia/Seoul",
    "iso:country":"KR",
    "name:kor_x_preferred":[
        "\uc0c1\ud3c9"
    ],
    "wof:name":"Sangpyeong",
    "wof:placetype":"locality"
},
  "geometry": {"coordinates":[128.59001999999998,36.08785],"type":"Point"}
}