{
  "type": "Feature",
  "properties": {
    "gn:admin1_code":"0.0",
    "gn:asciiname":"Muson",
    "gn:country_code":"KR",
    "gn:dem":114,
    "gn:feature_class":"P",
    "gn:feature_code":"PPL",
    "gn:name":"Mus\u014fn",
    "gn:population":0,
    "gn:timezone":"Asia/Seoul",
    "iso:country":"KR",
    "wof:name":"Muson",
    "wof:placetype":"locality"
},
  "geometry": {"coordinates":[127.65000000000001,34.76667],"type":"Point"}
}