{
  "type": "Feature",
  "properties": {
    "gn:admin1_code":"13.0",
    "gn:asciiname":"Sanghajo",
    "gn:country_code":"KR",
    "gn:dem":47,
    "gn:feature_class":"P",
    "gn:feature_code":"PPL",
    "gn:name":"Sanghaj\u014f",
    "gn:population":0,
    "gn:timezone":"Asia/Seoul",
    "iso:country":"KR",
    "name:kor_x_preferred":[
        "\uc0c1\ud558\uc800"
    ],
    "name:kor_x_variant":[
        "Sanghaj\u014f"
    ],
    "wof:name":"Sanghajo",
    "wof:placetype":"locality"
},
  "geometry": {"coordinates":[126.86583,37.19056],"type":"Point"}
}