{
  "type": "Feature",
  "properties": {
    "gn:admin1_code":"16.0",
    "gn:asciiname":"Sinwol",
    "gn:country_code":"KR",
    "gn:dem":18,
    "gn:feature_class":"P",
    "gn:feature_code":"PPL",
    "gn:name":"Sinwol",
    "gn:population":0,
    "gn:timezone":"Asia/Seoul",
    "iso:country":"KR",
    "name:kor_x_preferred":[
        "\uc2e0\uc6d4"
    ],
    "name:und_x_variant":[
        "Sinw\u014fl",
        "Sinw\u014fl-li",
        "Shinwol-dong",
        "Sinw\u014fl-tong",
        "Sinwol"
    ],
    "wof:name":"Sinwol",
    "wof:placetype":"locality"
},
  "geometry": {"coordinates":[127.69866,34.72774],"type":"Point"}
}