{
  "type": "Feature",
  "properties": {
    "gn:admin1_code":"1.0",
    "gn:asciiname":"Sindo il-li",
    "gn:country_code":"KR",
    "gn:dem":30,
    "gn:feature_class":"P",
    "gn:feature_code":"PPL",
    "gn:name":"Sindo il-li",
    "gn:population":0,
    "gn:timezone":"Asia/Seoul",
    "iso:country":"KR",
    "name:und_x_variant":[
        "Sindo 1-li",
        "Sindo il-li"
    ],
    "wof:name":"Sindo il-li",
    "wof:placetype":"locality"
},
  "geometry": {"coordinates":[126.19110999999999,33.27694],"type":"Point"}
}