{
  "type": "Feature",
  "properties": {
    "gn:admin1_code":"6.0",
    "gn:asciiname":"Kaegonno",
    "gn:country_code":"KR",
    "gn:dem":213,
    "gn:feature_class":"P",
    "gn:feature_code":"PPL",
    "gn:name":"Kaeg\u014fnn\u014f",
    "gn:population":0,
    "gn:timezone":"Asia/Seoul",
    "iso:country":"KR",
    "name:kor_x_preferred":[
        "\uac1c\uac74\ub108"
    ],
    "name:kor_x_variant":[
        "Kaeg\u014fnn\u014f"
    ],
    "wof:name":"Kaegonno",
    "wof:placetype":"locality"
},
  "geometry": {"coordinates":[127.9432,37.5703],"type":"Point"}
}