{
  "type": "Feature",
  "properties": {
    "gn:admin1_code":"10.0",
    "gn:asciiname":"Ch'oup-tong",
    "gn:country_code":"KR",
    "gn:dem":102,
    "gn:feature_class":"P",
    "gn:feature_code":"PPL",
    "gn:name":"Ch\u2019o\u016dp-tong",
    "gn:population":0,
    "gn:timezone":"Asia/Seoul",
    "iso:country":"KR",
    "name:und_x_variant":[
        "Ch\u2019os\u014f",
        "Ch\u2019o\u016dp-tong"
    ],
    "wof:name":"Ch'oup-tong",
    "wof:placetype":"locality"
},
  "geometry": {"coordinates":[129.05000000000001,35.18333],"type":"Point"}
}