{
  "type": "Feature",
  "properties": {
    "gn:admin1_code":"14.0",
    "gn:asciiname":"Ugakdan",
    "gn:country_code":"KR",
    "gn:dem":62,
    "gn:feature_class":"P",
    "gn:feature_code":"PPL",
    "gn:name":"Ugakdan",
    "gn:population":0,
    "gn:timezone":"Asia/Seoul",
    "iso:country":"KR",
    "name:kor_x_preferred":[
        "\uc6b0\uac01\ub2e8"
    ],
    "wof:name":"Ugakdan",
    "wof:placetype":"locality"
},
  "geometry": {"coordinates":[129.26111,35.88544],"type":"Point"}
}