{
  "type": "Feature",
  "properties": {
    "gn:admin1_code":"20.0",
    "gn:asciiname":"Taesa-ri",
    "gn:cc2":"KR",
    "gn:country_code":"KR",
    "gn:dem":11,
    "gn:feature_class":"P",
    "gn:feature_code":"PPL",
    "gn:name":"Taesa-ri",
    "gn:population":0,
    "gn:timezone":"Asia/Seoul",
    "iso:country":"KR",
    "name:und_x_variant":[
        "Daiji-ri",
        "Taiji-ri",
        "Taesa-ri"
    ],
    "wof:name":"Taesa-ri",
    "wof:placetype":"locality"
},
  "geometry": {"coordinates":[127.87056,34.8925],"type":"Point"}
}