{
  "type": "Feature",
  "properties": {
    "gn:admin1_code":"14.0",
    "gn:asciiname":"Chisan",
    "gn:country_code":"KR",
    "gn:dem":124,
    "gn:feature_class":"P",
    "gn:feature_code":"PPL",
    "gn:name":"Chisan",
    "gn:population":0,
    "gn:timezone":"Asia/Seoul",
    "iso:country":"KR",
    "name:und_x_variant":[
        "\uc9c0\uc0b0",
        "Chisan"
    ],
    "wof:name":"Chisan",
    "wof:placetype":"locality"
},
  "geometry": {"coordinates":[128.11680000000001,36.1652],"type":"Point"}
}