{
  "type": "Feature",
  "properties": {
    "gn:admin1_code":"17.0",
    "gn:asciiname":"Haengp'aengi",
    "gn:country_code":"KR",
    "gn:dem":12,
    "gn:feature_class":"P",
    "gn:feature_code":"PPL",
    "gn:name":"Haengp\u2019aengi",
    "gn:population":0,
    "gn:timezone":"Asia/Seoul",
    "iso:country":"KR",
    "name:und_x_variant":[
        "\ud589\ud33d\uc774",
        "Haengp\u2019aengi"
    ],
    "wof:name":"Haengp'aengi",
    "wof:placetype":"locality"
},
  "geometry": {"coordinates":[126.1756,36.8007],"type":"Point"}
}