{
  "type": "Feature",
  "properties": {
    "gn:admin1_code":"14.0",
    "gn:asciiname":"Wik-kol",
    "gn:country_code":"KR",
    "gn:dem":64,
    "gn:feature_class":"P",
    "gn:feature_code":"PPL",
    "gn:name":"Wik-kol",
    "gn:population":0,
    "gn:timezone":"Asia/Seoul",
    "iso:country":"KR",
    "name:und_x_variant":[
        "\uc717\uace8",
        "Wik-kol"
    ],
    "wof:name":"Wik-kol",
    "wof:placetype":"locality"
},
  "geometry": {"coordinates":[128.3424,36.163],"type":"Point"}
}