{
  "type": "Feature",
  "properties": {
    "gn:admin1_code":"11.0",
    "gn:asciiname":"Chegang-mal",
    "gn:country_code":"KR",
    "gn:dem":57,
    "gn:feature_class":"P",
    "gn:feature_code":"PPL",
    "gn:name":"Chegang-mal",
    "gn:population":0,
    "gn:timezone":"Asia/Seoul",
    "iso:country":"KR",
    "name:und_x_variant":[
        "\uc81c\uac01\ub9d0",
        "Chegang-mal"
    ],
    "wof:name":"Chegang-mal",
    "wof:placetype":"locality"
},
  "geometry": {"coordinates":[126.9254,37.6359],"type":"Point"}
}