{
  "type": "Feature",
  "properties": {
    "iso:country":"KR",
    "name:eng_x_preferred":[
        "Guseo-dong"
    ],
    "name:kor_x_preferred":[
        "\uad6c\uc11c\ub3d9"
    ],
    "name:kor_x_variant":[
        "\uad6c\uc11c\ub3d9"
    ],
    "qs:gn_adm0_cc":"KR",
    "qs:gn_local":1838524,
    "qs:local_max":2765,
    "qs:local_sum":24552,
    "qs:localhoods":60,
    "qs:name":"\uad6c\uc11c\ub3d9",
    "qs:name_adm0":"\ud55c\uad6d",
    "qs:name_adm1":"\ubd80\uc0b0",
    "qs:name_adm2":"\uae08\uc815\uad6c",
    "qs:name_local":"\ubd80\uc0b0",
    "qs:photo_max":173,
    "qs:photo_sum":216,
    "qs:placetype":"Suburb",
    "qs:quad_count":9,
    "qs:woe_adm0":23424868,
    "qs:woe_adm1":2345968,
    "qs:woe_adm2":28289169,
    "qs:woe_lau":0,
    "qs:woe_local":1132447,
    "qs:woe_ver":"7.10.0",
    "wof:lang":[
        "kor"
    ],
    "wof:name":"Guseo-dong",
    "wof:placetype":"neighbourhood"
},
  "geometry": {"coordinates":[129.08228299999999,35.251618],"type":"Point"}
}