{
  "type": "Feature",
  "properties": {
    "gn:admin1_code":"16.0",
    "gn:asciiname":"Tongbaekto",
    "gn:country_code":"KR",
    "gn:dem":8,
    "gn:feature_class":"P",
    "gn:feature_code":"PPL",
    "gn:name":"Tongbaekto",
    "gn:population":0,
    "gn:timezone":"Asia/Seoul",
    "iso:country":"KR",
    "name:kor_x_preferred":[
        "\ub3d9\ubc31\ub3c4"
    ],
    "wof:name":"Tongbaekto",
    "wof:placetype":"locality"
},
  "geometry": {"coordinates":[127.28711,34.75743],"type":"Point"}
}