{
  "type": "Feature",
  "properties": {
    "gn:admin1_code":"16.0",
    "gn:asciiname":"Chongsin",
    "gn:country_code":"KR",
    "gn:dem":34,
    "gn:feature_class":"P",
    "gn:feature_code":"PPL",
    "gn:name":"Ch\u014fngsin",
    "gn:population":0,
    "gn:timezone":"Asia/Seoul",
    "iso:country":"KR",
    "name:kor_x_preferred":[
        "Ch\u014fngsin"
    ],
    "name:und_x_variant":[
        "\uccad\uc2e0"
    ],
    "wof:name":"Chongsin",
    "wof:placetype":"locality"
},
  "geometry": {"coordinates":[126.67361,34.55860999999999],"type":"Point"}
}