{
  "type": "Feature",
  "properties": {
    "gn:admin1_code":"16.0",
    "gn:admin2_code":"Chindo-gun",
    "gn:asciiname":"Songcheon",
    "gn:country_code":"KR",
    "gn:dem":8,
    "gn:feature_class":"P",
    "gn:feature_code":"PPL",
    "gn:name":"Songcheon",
    "gn:population":0,
    "gn:timezone":"Asia/Seoul",
    "iso:country":"KR",
    "name:kor_x_preferred":[
        "\uc1a1\ucc9c"
    ],
    "name:und_x_variant":[
        "Sh\u014dsen-ri",
        "Songgul-li",
        "Songgun-ni",
        "Songch\u2019\u014fn-ni",
        "Songch\u2019on",
        "Songgun",
        "Songcheon"
    ],
    "wof:name":"Songcheon",
    "wof:placetype":"locality"
},
  "geometry": {"coordinates":[126.32805999999999,34.405],"type":"Point"}
}