{
  "type": "Feature",
  "properties": {
    "gn:admin1_code":"16.0",
    "gn:asciiname":"Yomsan",
    "gn:cc2":"KR",
    "gn:country_code":"KR",
    "gn:dem":49,
    "gn:feature_class":"P",
    "gn:feature_code":"PPL",
    "gn:name":"Y\u014fmsan",
    "gn:population":0,
    "gn:timezone":"Asia/Seoul",
    "iso:country":"KR",
    "name:und_x_variant":[
        "Y\u014fmsan-ni",
        "Y\u014fmsal-li",
        "Y\u014fmsan"
    ],
    "wof:name":"Yomsan",
    "wof:placetype":"locality"
},
  "geometry": {"coordinates":[126.13583,35.01611],"type":"Point"}
}