{
  "type": "Feature",
  "properties": {
    "gn:admin1_code":"13.0",
    "gn:admin2_code":"Ans\u014fng-si",
    "gn:asciiname":"Sangchon",
    "gn:country_code":"KR",
    "gn:dem":134,
    "gn:feature_class":"P",
    "gn:feature_code":"PPL",
    "gn:name":"Sangchon",
    "gn:population":0,
    "gn:timezone":"Asia/Seoul",
    "iso:country":"KR",
    "name:kor_x_preferred":[
        "Sanch\u2019on"
    ],
    "name:kor_x_variant":[
        "\uc0c1\ucd0c",
        "Sangch\u2019on"
    ],
    "wof:name":"Sangchon",
    "wof:placetype":"locality"
},
  "geometry": {"coordinates":[127.25815,37.13808],"type":"Point"}
}