{
  "type": "Feature",
  "properties": {
    "gn:admin1_code":"13.0",
    "gn:asciiname":"K'unt'ogol",
    "gn:country_code":"KR",
    "gn:dem":19,
    "gn:feature_class":"P",
    "gn:feature_code":"PPL",
    "gn:name":"K\u2019\u016dnt\u2019\u014fgol",
    "gn:population":0,
    "gn:timezone":"Asia/Seoul",
    "iso:country":"KR",
    "name:kor_x_preferred":[
        "\ud070\ud130\uace8"
    ],
    "name:kor_x_variant":[
        "K\u2019\u016dnt\u2019\u014fgol"
    ],
    "wof:name":"K'unt'ogol",
    "wof:placetype":"locality"
},
  "geometry": {"coordinates":[126.85193999999998,37.05611],"type":"Point"}
}