{
  "type": "Feature",
  "properties": {
    "gn:admin1_code":"16.0",
    "gn:asciiname":"Worho",
    "gn:cc2":"KR",
    "gn:country_code":"KR",
    "gn:dem":39,
    "gn:feature_class":"P",
    "gn:feature_code":"PPL",
    "gn:name":"W\u014frho",
    "gn:population":0,
    "gn:timezone":"Asia/Seoul",
    "iso:country":"KR",
    "name:und_x_variant":[
        "W\u014frho-ri",
        "W\u014frho"
    ],
    "wof:name":"Worho",
    "wof:placetype":"locality"
},
  "geometry": {"coordinates":[126.61667,34.95],"type":"Point"}
}