{
  "type": "Feature",
  "properties": {
    "gn:admin1_code":"13.0",
    "gn:asciiname":"Galmoe",
    "gn:country_code":"KR",
    "gn:dem":115,
    "gn:feature_class":"P",
    "gn:feature_code":"PPL",
    "gn:name":"Galmoe",
    "gn:population":0,
    "gn:timezone":"Asia/Seoul",
    "iso:country":"KR",
    "name:und_x_variant":[
        "\uac08\ubafc",
        "Kalmoe",
        "Galmoe"
    ],
    "wof:name":"Galmoe",
    "wof:placetype":"locality"
},
  "geometry": {"coordinates":[127.14700000000001,37.8243],"type":"Point"}
}