{
  "type": "Feature",
  "properties": {
    "gn:admin1_code":"14.0",
    "gn:asciiname":"Sangdaemun",
    "gn:country_code":"KR",
    "gn:dem":278,
    "gn:feature_class":"P",
    "gn:feature_code":"PPL",
    "gn:name":"Sangdaemun",
    "gn:population":0,
    "gn:timezone":"Asia/Seoul",
    "iso:country":"KR",
    "name:kor_x_preferred":[
        "\uc0c1\ub300\ubb38"
    ],
    "wof:name":"Sangdaemun",
    "wof:placetype":"locality"
},
  "geometry": {"coordinates":[127.98976,36.64921],"type":"Point"}
}