{
  "type": "Feature",
  "properties": {
    "gn:admin1_code":"13.0",
    "gn:asciiname":"Jujeongdong",
    "gn:country_code":"KR",
    "gn:dem":77,
    "gn:feature_class":"P",
    "gn:feature_code":"PPL",
    "gn:name":"Jujeongdong",
    "gn:population":0,
    "gn:timezone":"Asia/Seoul",
    "iso:country":"KR",
    "name:kor_x_preferred":[
        "\uc8fc\uc815\ub3d9"
    ],
    "name:und_x_variant":[
        "\uc8fc\uc815",
        "Jujeong",
        "Chuj\u014fng",
        "Jujeongdong"
    ],
    "wof:name":"Jujeongdong",
    "wof:placetype":"locality"
},
  "geometry": {"coordinates":[127.15863,37.02213],"type":"Point"}
}