{
  "type": "Feature",
  "properties": {
    "gn:admin1_code":"14.0",
    "gn:asciiname":"Taep'yong-dong",
    "gn:country_code":"KR",
    "gn:dem":620,
    "gn:feature_class":"P",
    "gn:feature_code":"PPL",
    "gn:name":"Taep\u2019y\u014fng-dong",
    "gn:population":0,
    "gn:timezone":"Asia/Seoul",
    "iso:country":"KR",
    "name:und_x_variant":[
        "\ub300\ud3c9\ub3d9",
        "Taep\u2019y\u014fng-dong"
    ],
    "wof:name":"Taep'yong-dong",
    "wof:placetype":"locality"
},
  "geometry": {"coordinates":[127.9508,36.0387],"type":"Point"}
}