{
  "type": "Feature",
  "properties": {
    "gn:country":"KR",
    "iso:country":"KR",
    "name:eng_x_preferred":[
        "Daegyo-dong"
    ],
    "name:kor_x_preferred":[
        "\ub300\uad50\ub3d9"
    ],
    "qs:name":"\ub300\uad50\ub3d9",
    "qs:name_adm0":"\ud55c\uad6d",
    "qs:name_adm1":"\uc804\ub77c\ub0a8\ub3c4",
    "qs:photos":4,
    "qs:photos_1k":1,
    "qs:photos_9k":1,
    "qs:photos_9r":1,
    "qs:photos_all":4,
    "qs:photos_sr":1,
    "qs:placetype":"LocalAdmin",
    "qs:pop_sr":"0",
    "wof:name":"Daegyo-dong",
    "wof:placetype":"localadmin"
},
  "geometry": {"coordinates":[127.722072,34.726747],"type":"Point"}
}