{
  "type": "Feature",
  "properties": {
    "gn:admin1_code":"5.0",
    "gn:asciiname":"Bugwisil",
    "gn:country_code":"KR",
    "gn:dem":208,
    "gn:feature_class":"P",
    "gn:feature_code":"PPL",
    "gn:name":"Bugwisil",
    "gn:population":0,
    "gn:timezone":"Asia/Seoul",
    "iso:country":"KR",
    "name:kor_x_preferred":[
        "\ubd80\uadc0\uc2e4"
    ],
    "wof:name":"Bugwisil",
    "wof:placetype":"locality"
},
  "geometry": {"coordinates":[127.73108999999999,36.70288],"type":"Point"}
}