{
  "type": "Feature",
  "properties": {
    "gn:admin1_code":"6.0",
    "gn:asciiname":"Bongnamdae",
    "gn:country_code":"KR",
    "gn:dem":561,
    "gn:feature_class":"P",
    "gn:feature_code":"PPL",
    "gn:name":"Bongnamdae",
    "gn:population":0,
    "gn:timezone":"Asia/Seoul",
    "iso:country":"KR",
    "name:kor_x_preferred":[
        "\ubd09\ub0a8\ub300"
    ],
    "name:und_x_variant":[
        "Pongnamdae",
        "Bongnamdae"
    ],
    "wof:name":"Bongnamdae",
    "wof:placetype":"locality"
},
  "geometry": {"coordinates":[128.21527,37.88649],"type":"Point"}
}