{
  "type": "Feature",
  "properties": {
    "iso:country":"KR",
    "name:kor_x_preferred":[
        "\uc131\ub0a8\ub3d9"
    ],
    "name:und_x_variant":[
        "J\u014dsanri"
    ],
    "qs:gn_adm0_cc":"KR",
    "qs:gn_fcode":"PPLX",
    "qs:gn_local":1833747,
    "qs:gn_nam_loc":"Ulsan",
    "qs:gn_namadm1":"20",
    "qs:gn_name":"Sangnam-dong",
    "qs:local_max":1081,
    "qs:local_sum":1745,
    "qs:localhoods":9,
    "qs:name":"\uc131\ub0a8\ub3d9",
    "qs:name_adm0":"\ud55c\uad6d",
    "qs:name_adm1":"\uc6b8\uc0b0",
    "qs:name_adm2":"\uc911\uad6c",
    "qs:name_lau":"\uc131\ub0a8\ub3d9",
    "qs:name_local":"\uc6b8\uc0b0",
    "qs:photo_max":671,
    "qs:photo_sum":1081,
    "qs:placetype":"Suburb",
    "qs:quad_count":23,
    "qs:woe_adm0":23424868,
    "qs:woe_adm1":23701285,
    "qs:woe_adm2":28289226,
    "qs:woe_lau":28806605,
    "qs:woe_local":1132578,
    "qs:woe_ver":"7.10.0",
    "wof:lang":[
        "kor"
    ],
    "wof:name":"\uc131\ub0a8\ub3d9",
    "wof:placetype":"neighbourhood"
},
  "geometry": {"coordinates":[129.31455600000001,35.550925],"type":"Point"}
}