{
  "type": "Feature",
  "properties": {
    "gn:admin1_code":"6.0",
    "gn:asciiname":"Samgori",
    "gn:country_code":"KR",
    "gn:dem":129,
    "gn:feature_class":"P",
    "gn:feature_code":"PPL",
    "gn:name":"Samg\u014fri",
    "gn:population":0,
    "gn:timezone":"Asia/Seoul",
    "iso:country":"KR",
    "name:und_x_variant":[
        "\uc0bc\uac70\ub9ac",
        "Samg\u014fri"
    ],
    "wof:name":"Samgori",
    "wof:placetype":"locality"
},
  "geometry": {"coordinates":[127.68680000000001,37.9955],"type":"Point"}
}