{
  "type": "Feature",
  "properties": {
    "gn:admin1_code":"0.0",
    "gn:asciiname":"Pigo",
    "gn:cc2":"KR",
    "gn:country_code":"KR",
    "gn:dem":283,
    "gn:feature_class":"P",
    "gn:feature_code":"PPL",
    "gn:name":"Pig\u014f",
    "gn:population":0,
    "gn:timezone":"Asia/Seoul",
    "iso:country":"KR",
    "name:als_x_preferred":[
        "Pigo"
    ],
    "name:cat_x_preferred":[
        "Rutilus pigus"
    ],
    "name:deu_x_preferred":[
        "Frauennerfling"
    ],
    "name:eus_x_preferred":[
        "Rutilus pigus"
    ],
    "name:fra_x_preferred":[
        "Gardon galant"
    ],
    "name:hun_x_preferred":[
        "Rutilus pigus"
    ],
    "name:ita_x_preferred":[
        "Rutilus pigus"
    ],
    "name:kor_x_preferred":[
        "\ube44\uac70"
    ],
    "name:nld_x_preferred":[
        "Rutilus pigus"
    ],
    "name:pol_x_preferred":[
        "P\u0142o\u0107 alpejska"
    ],
    "name:por_x_preferred":[
        "Rutilus pigus"
    ],
    "name:spa_x_preferred":[
        "Rutilus pigus"
    ],
    "name:ukr_x_preferred":[
        "Rutilus pigus"
    ],
    "name:und_x_variant":[
        "Pig\u014f-ri",
        "Pig\u014f",
        "Bigeo"
    ],
    "name:vie_x_preferred":[
        "Rutilus pigus"
    ],
    "wof:name":"Pigo",
    "wof:placetype":"locality"
},
  "geometry": {"coordinates":[126.93333,35.43333],"type":"Point"}
}