{
  "type": "Feature",
  "properties": {
    "gn:admin1_code":"6.0",
    "gn:asciiname":"Madok",
    "gn:country_code":"KR",
    "gn:dem":697,
    "gn:feature_class":"P",
    "gn:feature_code":"PPL",
    "gn:name":"Mad\u014fk",
    "gn:population":0,
    "gn:timezone":"Asia/Seoul",
    "iso:country":"KR",
    "name:kor_x_preferred":[
        "\ub9c8\ub355"
    ],
    "name:kor_x_variant":[
        "Mad\u014fk"
    ],
    "wof:name":"Madok",
    "wof:placetype":"locality"
},
  "geometry": {"coordinates":[128.7611,37.3272],"type":"Point"}
}