{
  "type": "Feature",
  "properties": {
    "gn:admin1_code":"6.0",
    "gn:asciiname":"Sanghyeonam",
    "gn:country_code":"KR",
    "gn:dem":79,
    "gn:feature_class":"P",
    "gn:feature_code":"PPL",
    "gn:name":"Sanghyeonam",
    "gn:population":0,
    "gn:timezone":"Asia/Seoul",
    "iso:country":"KR",
    "name:kor_x_preferred":[
        "\uc0c1\ud604\uc554"
    ],
    "wof:name":"Sanghyeonam",
    "wof:placetype":"locality"
},
  "geometry": {"coordinates":[127.68591000000001,37.88846],"type":"Point"}
}