{
  "type": "Feature",
  "properties": {
    "gn:admin1_code":"6.0",
    "gn:asciiname":"Solchigol",
    "gn:country_code":"KR",
    "gn:dem":330,
    "gn:feature_class":"P",
    "gn:feature_code":"PPL",
    "gn:name":"Solchigol",
    "gn:population":0,
    "gn:timezone":"Asia/Seoul",
    "iso:country":"KR",
    "name:kor_x_preferred":[
        "\uc194\uce58\uace8"
    ],
    "name:kor_x_variant":[
        "Solch\u2019i-gol"
    ],
    "wof:name":"Solchigol",
    "wof:placetype":"locality"
},
  "geometry": {"coordinates":[128.14667,37.73062],"type":"Point"}
}