{
  "type": "Feature",
  "properties": {
    "gn:admin1_code":"17.0",
    "gn:asciiname":"Sojangdol",
    "gn:country_code":"KR",
    "gn:dem":6,
    "gn:feature_class":"P",
    "gn:feature_code":"PPL",
    "gn:name":"Sojangdol",
    "gn:population":0,
    "gn:timezone":"Asia/Seoul",
    "iso:country":"KR",
    "name:und_x_variant":[
        "Sojangs\u014fk",
        "Chag\u016dn-changdol",
        "Sojangdol",
        "Chag\u016dnjangdol"
    ],
    "wof:name":"Sojangdol",
    "wof:placetype":"locality"
},
  "geometry": {"coordinates":[126.36667,36.43333],"type":"Point"}
}