{
  "type": "Feature",
  "properties": {
    "gn:admin1_code":"20.0",
    "gn:asciiname":"Mojol-li",
    "gn:country_code":"KR",
    "gn:dem":31,
    "gn:feature_class":"P",
    "gn:feature_code":"PPL",
    "gn:name":"Moj\u014fl-li",
    "gn:population":0,
    "gn:timezone":"Asia/Seoul",
    "iso:country":"KR",
    "name:und_x_variant":[
        "\ubaa8\uc804\ub9ac",
        "Moj\u014fl-li"
    ],
    "wof:name":"Mojol-li",
    "wof:placetype":"locality"
},
  "geometry": {"coordinates":[128.46018000000001,35.57678],"type":"Point"}
}