{
  "type": "Feature",
  "properties": {
    "gn:admin1_code":"6.0",
    "gn:asciiname":"Kyesan-dong",
    "gn:country_code":"KR",
    "gn:dem":610,
    "gn:feature_class":"P",
    "gn:feature_code":"PPL",
    "gn:name":"Kyesan-dong",
    "gn:population":0,
    "gn:timezone":"Asia/Seoul",
    "iso:country":"KR",
    "name:und_x_variant":[
        "Kesan-mal",
        "Kyesanmai",
        "Kyesanmal",
        "Kyesan-ni",
        "\uacc4\uc0b0\ub3d9",
        "Kyesan-dong"
    ],
    "wof:name":"Kyesan-dong",
    "wof:placetype":"locality"
},
  "geometry": {"coordinates":[129.00299999999999,37.1081],"type":"Point"}
}