{
  "type": "Feature",
  "properties": {
    "gn:admin1_code":"13.0",
    "gn:asciiname":"Samga-ri",
    "gn:country_code":"KR",
    "gn:dem":45,
    "gn:feature_class":"P",
    "gn:feature_code":"PPL",
    "gn:name":"Samga-ri",
    "gn:population":0,
    "gn:timezone":"Asia/Seoul",
    "iso:country":"KR",
    "name:und_x_variant":[
        "\uc0bc\uac70\ub9ac",
        "Samgeo-ri",
        "Samg\u014f-ri"
    ],
    "wof:name":"Samga-ri",
    "wof:placetype":"locality"
},
  "geometry": {"coordinates":[127.10583,37.39444],"type":"Point"}
}