{
  "type": "Feature",
  "properties": {
    "gn:admin1_code":"16.0",
    "gn:asciiname":"Bangok",
    "gn:country_code":"KR",
    "gn:dem":133,
    "gn:feature_class":"P",
    "gn:feature_code":"PPL",
    "gn:name":"Bangok",
    "gn:population":0,
    "gn:timezone":"Asia/Seoul",
    "iso:country":"KR",
    "name:kor_x_preferred":[
        "\ubc18\uace1"
    ],
    "name:kor_x_variant":[
        "Pan\u2019gok"
    ],
    "wof:name":"Bangok",
    "wof:placetype":"locality"
},
  "geometry": {"coordinates":[127.12519,34.90222],"type":"Point"}
}