{
  "type": "Feature",
  "properties": {
    "gn:admin1_code":"20.0",
    "gn:asciiname":"Kosim-gol",
    "gn:country_code":"KR",
    "gn:dem":104,
    "gn:feature_class":"P",
    "gn:feature_code":"PPL",
    "gn:name":"Kosim-gol",
    "gn:population":0,
    "gn:timezone":"Asia/Seoul",
    "iso:country":"KR",
    "name:und_x_variant":[
        "\uace0\uc2ec\uace8",
        "Kosim-gol"
    ],
    "wof:name":"Kosim-gol",
    "wof:placetype":"locality"
},
  "geometry": {"coordinates":[128.39837,35.22655],"type":"Point"}
}