{
  "type": "Feature",
  "properties": {
    "gn:admin1_code":"17.0",
    "gn:asciiname":"Chang-gol",
    "gn:country_code":"KR",
    "gn:dem":31,
    "gn:feature_class":"P",
    "gn:feature_code":"PPL",
    "gn:name":"Chang-gol",
    "gn:population":0,
    "gn:timezone":"Asia/Seoul",
    "iso:country":"KR",
    "name:und_x_variant":[
        "\uc7a5\uace8",
        "Chang-gol"
    ],
    "wof:name":"Chang-gol",
    "wof:placetype":"locality"
},
  "geometry": {"coordinates":[127.15000000000001,36.4844],"type":"Point"}
}