{
  "type": "Feature",
  "properties": {
    "gn:admin1_code":"5.0",
    "gn:asciiname":"Ijidang",
    "gn:country_code":"KR",
    "gn:dem":95,
    "gn:feature_class":"P",
    "gn:feature_code":"PPL",
    "gn:name":"Ijidang",
    "gn:population":0,
    "gn:timezone":"Asia/Seoul",
    "iso:country":"KR",
    "name:und_x_variant":[
        "\uc774\uc9c0\ub2f9",
        "Ijidang"
    ],
    "wof:name":"Ijidang",
    "wof:placetype":"locality"
},
  "geometry": {"coordinates":[127.55257,36.33014],"type":"Point"}
}