{
  "type": "Feature",
  "properties": {
    "gn:admin1_code":"17.0",
    "gn:asciiname":"Nolbunbae",
    "gn:country_code":"KR",
    "gn:dem":72,
    "gn:feature_class":"P",
    "gn:feature_code":"PPL",
    "gn:name":"N\u014flb\u016dnbae",
    "gn:population":0,
    "gn:timezone":"Asia/Seoul",
    "iso:country":"KR",
    "name:und_x_variant":[
        "\ub113\uc740\ubc30",
        "N\u014flb\u016dnbae"
    ],
    "wof:name":"Nolbunbae",
    "wof:placetype":"locality"
},
  "geometry": {"coordinates":[126.736,36.5633],"type":"Point"}
}