{
  "type": "Feature",
  "properties": {
    "gn:admin1_code":"6.0",
    "gn:asciiname":"Maehwa-dong",
    "gn:country_code":"KR",
    "gn:dem":731,
    "gn:feature_class":"P",
    "gn:feature_code":"PPL",
    "gn:name":"Maehwa-dong",
    "gn:population":0,
    "gn:timezone":"Asia/Seoul",
    "iso:country":"KR",
    "name:kor_x_preferred":[
        "\ub9e4\ud654\ub3d9"
    ],
    "wof:name":"Maehwa-dong",
    "wof:placetype":"locality"
},
  "geometry": {"coordinates":[128.70230000000001,37.25],"type":"Point"}
}