{
  "type": "Feature",
  "properties": {
    "iso:country":"KR",
    "name:eng_x_preferred":[
        "Yeosu-si"
    ],
    "name:kor_x_preferred":[
        "\uc5ec\uc218\uc2dc"
    ],
    "qs:name":"\uc5ec\uc218\uc2dc",
    "qs:name_adm0":"\ud55c\uad6d",
    "qs:name_adm1":"\uc804\ub77c\ub0a8\ub3c4",
    "qs:photos":305,
    "qs:photos_1k":62,
    "qs:photos_9k":1,
    "qs:photos_9r":5,
    "qs:photos_all":305,
    "qs:photos_sr":5,
    "qs:placetype":"Town",
    "qs:pop_sr":"0",
    "wof:name":"Yeosu-si",
    "wof:placetype":"locality"
},
  "geometry": {"coordinates":[127.65335399999999,34.75127],"type":"Point"}
}