{
  "type": "Feature",
  "properties": {
    "gn:admin1_code":"17.0",
    "gn:asciiname":"Beomheori",
    "gn:country_code":"KR",
    "gn:dem":59,
    "gn:feature_class":"P",
    "gn:feature_code":"PPL",
    "gn:name":"Beomheori",
    "gn:population":0,
    "gn:timezone":"Asia/Seoul",
    "iso:country":"KR",
    "name:und_x_variant":[
        "\ubc94\ud5c8\ub9ac",
        "P\u014fmh\u014f-ri",
        "Beomheori"
    ],
    "wof:name":"Beomheori",
    "wof:placetype":"locality"
},
  "geometry": {"coordinates":[127.25816,36.41602],"type":"Point"}
}