{
  "type": "Feature",
  "properties": {
    "gn:admin1_code":"5.0",
    "gn:asciiname":"Chungsam",
    "gn:country_code":"KR",
    "gn:dem":150,
    "gn:feature_class":"P",
    "gn:feature_code":"PPL",
    "gn:name":"Chungsam",
    "gn:population":0,
    "gn:timezone":"Asia/Seoul",
    "iso:country":"KR",
    "name:und_x_variant":[
        "\uc911\uc0bc",
        "Chungsam"
    ],
    "wof:name":"Chungsam",
    "wof:placetype":"locality"
},
  "geometry": {"coordinates":[127.5754,36.2674],"type":"Point"}
}