{
  "type": "Feature",
  "properties": {
    "gn:admin1_code":"6.0",
    "gn:asciiname":"Chongji-gol",
    "gn:country_code":"KR",
    "gn:dem":428,
    "gn:feature_class":"P",
    "gn:feature_code":"PPL",
    "gn:name":"Ch\u014fngji-gol",
    "gn:population":0,
    "gn:timezone":"Asia/Seoul",
    "iso:country":"KR",
    "name:kor_x_preferred":[
        "\uc815\uc9c0\uace8"
    ],
    "name:kor_x_variant":[
        "Ch\u014fngji-gol"
    ],
    "wof:name":"Chongji-gol",
    "wof:placetype":"locality"
},
  "geometry": {"coordinates":[128.5188,37.3469],"type":"Point"}
}