{
  "type": "Feature",
  "properties": {
    "gn:admin1_code":"17.0",
    "gn:asciiname":"Nokto-ri",
    "gn:cc2":"KR",
    "gn:country_code":"KR",
    "gn:dem":59,
    "gn:feature_class":"P",
    "gn:feature_code":"PPL",
    "gn:name":"Nokto-ri",
    "gn:population":0,
    "gn:timezone":"Asia/Seoul",
    "iso:country":"KR",
    "name:und_x_variant":[
        "Nokto",
        "Nokto-ri"
    ],
    "wof:name":"Nokto-ri",
    "wof:placetype":"locality"
},
  "geometry": {"coordinates":[126.26306,36.26972],"type":"Point"}
}