{
  "type": "Feature",
  "properties": {
    "iso:country":"KR",
    "name:eng_x_preferred":[
        "Seoksa-dong"
    ],
    "name:kor_x_preferred":[
        "\uc11d\uc0ac\ub3d9"
    ],
    "qs:name":"\uc11d\uc0ac\ub3d9",
    "qs:name_adm0":"\ud55c\uad6d",
    "qs:name_adm1":"\uac15\uc6d0\ub3c4",
    "qs:photos":383,
    "qs:photos_1k":78,
    "qs:photos_9k":2,
    "qs:photos_9r":5,
    "qs:photos_all":383,
    "qs:photos_sr":6,
    "qs:placetype":"LocalAdmin",
    "qs:pop_sr":"0",
    "wof:name":"Seoksa-dong",
    "wof:placetype":"localadmin"
},
  "geometry": {"coordinates":[127.74803900000001,37.853984],"type":"Point"}
}