{
  "type": "Feature",
  "properties": {
    "gn:admin1_code":"6.0",
    "gn:asciiname":"Hyojai-dong",
    "gn:country_code":"KR",
    "gn:dem":111,
    "gn:feature_class":"P",
    "gn:feature_code":"PPL",
    "gn:name":"Hyojai-dong",
    "gn:population":0,
    "gn:timezone":"Asia/Seoul",
    "iso:country":"KR",
    "name:und_x_variant":[
        "\ud6a8\uc7902\ub3d9",
        "Hyojai-dong"
    ],
    "wof:name":"Hyojai-dong",
    "wof:placetype":"locality"
},
  "geometry": {"coordinates":[127.73806999999999,37.86925],"type":"Point"}
}