{
  "type": "Feature",
  "properties": {
    "gn:admin1_code":"17.0",
    "gn:asciiname":"Araeyongmo-ri",
    "gn:country_code":"KR",
    "gn:dem":60,
    "gn:feature_class":"P",
    "gn:feature_code":"PPL",
    "gn:name":"Araeyongm\u014f-ri",
    "gn:population":0,
    "gn:timezone":"Asia/Seoul",
    "iso:country":"KR",
    "name:und_x_variant":[
        "\uc544\ub798\uc6a9\uba38\ub9ac",
        "Araeyongm\u014f-ri"
    ],
    "wof:name":"Araeyongmo-ri",
    "wof:placetype":"locality"
},
  "geometry": {"coordinates":[126.6493,36.4126],"type":"Point"}
}