{
  "type": "Feature",
  "properties": {
    "gn:admin1_code":"20.0",
    "gn:asciiname":"Mok-kol",
    "gn:country_code":"KR",
    "gn:dem":254,
    "gn:feature_class":"P",
    "gn:feature_code":"PPL",
    "gn:name":"Mok-kol",
    "gn:population":0,
    "gn:timezone":"Asia/Seoul",
    "iso:country":"KR",
    "name:und_x_variant":[
        "\ubabb\uace8",
        "Mok-kol"
    ],
    "wof:name":"Mok-kol",
    "wof:placetype":"locality"
},
  "geometry": {"coordinates":[128.0591,35.52083],"type":"Point"}
}