{
  "type": "Feature",
  "properties": {
    "gn:admin1_code":"13.0",
    "gn:asciiname":"Sasong-dong",
    "gn:country_code":"KR",
    "gn:dem":63,
    "gn:feature_class":"P",
    "gn:feature_code":"PPL",
    "gn:name":"Sasong-dong",
    "gn:population":0,
    "gn:timezone":"Asia/Seoul",
    "iso:country":"KR",
    "name:und_x_variant":[
        "\uc0ac\uc1a1\ub3d9",
        "Sasong-dong"
    ],
    "wof:name":"Sasong-dong",
    "wof:placetype":"locality"
},
  "geometry": {"coordinates":[127.09860999999999,37.41306],"type":"Point"}
}