{
  "type": "Feature",
  "properties": {
    "gn:admin1_code":"0.0",
    "gn:asciiname":"Bongyang",
    "gn:country_code":"KR",
    "gn:dem":139,
    "gn:feature_class":"P",
    "gn:feature_code":"PPL",
    "gn:name":"Bongyang",
    "gn:population":0,
    "gn:timezone":"Asia/Seoul",
    "iso:country":"KR",
    "name:kor_x_preferred":[
        "\ubd09\uc591"
    ],
    "name:und_x_variant":[
        "Pongyang-ni",
        "Pongyang",
        "Bongyang"
    ],
    "wof:name":"Bongyang",
    "wof:placetype":"locality"
},
  "geometry": {"coordinates":[127.75024000000001,34.64082],"type":"Point"}
}