{
  "type": "Feature",
  "properties": {
    "gn:admin1_code":"16.0",
    "gn:asciiname":"Taesin",
    "gn:country_code":"KR",
    "gn:dem":32,
    "gn:feature_class":"P",
    "gn:feature_code":"PPL",
    "gn:name":"Taesin",
    "gn:population":0,
    "gn:timezone":"Asia/Seoul",
    "iso:country":"KR",
    "name:kor_x_preferred":[
        "\ud0dc\uc2e0"
    ],
    "wof:name":"Taesin",
    "wof:placetype":"locality"
},
  "geometry": {"coordinates":[126.75882,34.98489],"type":"Point"}
}