{
  "type": "Feature",
  "properties": {
    "gn:admin1_code":"17.0",
    "gn:asciiname":"Sogunjin",
    "gn:country_code":"KR",
    "gn:dem":21,
    "gn:feature_class":"P",
    "gn:feature_code":"PPL",
    "gn:name":"Sog\u016dnjin",
    "gn:population":0,
    "gn:timezone":"Asia/Seoul",
    "iso:country":"KR",
    "name:und_x_variant":[
        "Sog\u016dn-ni",
        "\uc18c\uadfc\uc9c4",
        "Sog\u016dl-li",
        "Sog\u016dnjin"
    ],
    "wof:name":"Sogunjin",
    "wof:placetype":"locality"
},
  "geometry": {"coordinates":[126.1841,36.8188],"type":"Point"}
}