{
  "type": "Feature",
  "properties": {
    "gn:admin1_code":"16.0",
    "gn:asciiname":"Yeompo",
    "gn:country_code":"KR",
    "gn:dem":44,
    "gn:feature_class":"P",
    "gn:feature_code":"PPL",
    "gn:name":"Yeompo",
    "gn:population":0,
    "gn:timezone":"Asia/Seoul",
    "iso:country":"KR",
    "name:kor_x_preferred":[
        "\uc5fc\ud3ec"
    ],
    "name:und_x_variant":[
        "Y\u014fmp\u2019o"
    ],
    "wof:name":"Yeompo",
    "wof:placetype":"locality"
},
  "geometry": {"coordinates":[127.49333,34.42197],"type":"Point"}
}