{
  "type": "Feature",
  "properties": {
    "gn:admin1_code":"6.0",
    "gn:asciiname":"Sangjap'o",
    "gn:country_code":"KR",
    "gn:dem":535,
    "gn:feature_class":"P",
    "gn:feature_code":"PPL",
    "gn:name":"Sangjap\u2019o",
    "gn:population":0,
    "gn:timezone":"Asia/Seoul",
    "iso:country":"KR",
    "name:kor_x_preferred":[
        "\uc0c1\uc790\ud3ec"
    ],
    "name:kor_x_variant":[
        "Sangjap\u2019o"
    ],
    "wof:name":"Sangjap'o",
    "wof:placetype":"locality"
},
  "geometry": {"coordinates":[128.2363,37.5224],"type":"Point"}
}