{
  "type": "Feature",
  "properties": {
    "gn:admin1_code":"20.0",
    "gn:asciiname":"Sowon",
    "gn:country_code":"KR",
    "gn:dem":205,
    "gn:feature_class":"P",
    "gn:feature_code":"PPL",
    "gn:name":"S\u014fw\u014fn",
    "gn:population":0,
    "gn:timezone":"Asia/Seoul",
    "iso:country":"KR",
    "name:und_x_variant":[
        "\uc11c\uc6d0",
        "S\u014fw\u014fn"
    ],
    "wof:name":"Sowon",
    "wof:placetype":"locality"
},
  "geometry": {"coordinates":[127.82214999999999,35.63604],"type":"Point"}
}