{
  "type": "Feature",
  "properties": {
    "gn:admin1_code":"21.0",
    "gn:asciiname":"Banmadang",
    "gn:country_code":"KR",
    "gn:dem":91,
    "gn:feature_class":"P",
    "gn:feature_code":"PPL",
    "gn:name":"Banmadang",
    "gn:population":0,
    "gn:timezone":"Asia/Seoul",
    "iso:country":"KR",
    "name:kor_x_preferred":[
        "\ubc18\ub9c8\ub2f9"
    ],
    "wof:name":"Banmadang",
    "wof:placetype":"locality"
},
  "geometry": {"coordinates":[129.17275000000001,35.44512],"type":"Point"}
}