{
  "type": "Feature",
  "properties": {
    "gn:admin1_code":"6.0",
    "gn:asciiname":"Jodeokgol",
    "gn:country_code":"KR",
    "gn:dem":300,
    "gn:feature_class":"P",
    "gn:feature_code":"PPL",
    "gn:name":"Jodeokgol",
    "gn:population":0,
    "gn:timezone":"Asia/Seoul",
    "iso:country":"KR",
    "name:kor_x_preferred":[
        "\uc870\ub355\uace8"
    ],
    "name:kor_x_variant":[
        "Chod\u014fk-kol"
    ],
    "wof:name":"Jodeokgol",
    "wof:placetype":"locality"
},
  "geometry": {"coordinates":[128.0051,37.90713],"type":"Point"}
}