{
  "type": "Feature",
  "properties": {
    "gn:admin1_code":"17.0",
    "gn:asciiname":"Kunbuk",
    "gn:country_code":"KR",
    "gn:dem":179,
    "gn:feature_class":"P",
    "gn:feature_code":"PPL",
    "gn:name":"Kunbuk",
    "gn:population":0,
    "gn:timezone":"Asia/Seoul",
    "iso:country":"KR",
    "name:und_x_variant":[
        "\uad70\ubd81",
        "Kunbuk"
    ],
    "wof:name":"Kunbuk",
    "wof:placetype":"locality"
},
  "geometry": {"coordinates":[127.5274,36.1678],"type":"Point"}
}