{
  "type": "Feature",
  "properties": {
    "gn:admin1_code":"13.0",
    "gn:asciiname":"Sindae",
    "gn:country_code":"KR",
    "gn:dem":47,
    "gn:feature_class":"P",
    "gn:feature_code":"PPL",
    "gn:name":"Sindae",
    "gn:population":0,
    "gn:timezone":"Asia/Seoul",
    "iso:country":"KR",
    "name:und_x_variant":[
        "\uc2e0\ub300",
        "Sindae"
    ],
    "wof:name":"Sindae",
    "wof:placetype":"locality"
},
  "geometry": {"coordinates":[127.50417,37.48556],"type":"Point"}
}