{
  "type": "Feature",
  "properties": {
    "gn:admin1_code":"14.0",
    "gn:asciiname":"Saenajeong",
    "gn:country_code":"KR",
    "gn:dem":29,
    "gn:feature_class":"P",
    "gn:feature_code":"PPL",
    "gn:name":"Saenajeong",
    "gn:population":0,
    "gn:timezone":"Asia/Seoul",
    "iso:country":"KR",
    "name:und_x_variant":[
        "\uc0c8\ub098\uc815",
        "Saenaj\u014fng",
        "Saenajeong"
    ],
    "wof:name":"Saenajeong",
    "wof:placetype":"locality"
},
  "geometry": {"coordinates":[128.39963999999998,35.82176],"type":"Point"}
}