{
  "type": "Feature",
  "properties": {
    "gn:admin1_code":"20.0",
    "gn:asciiname":"Maegok",
    "gn:country_code":"KR",
    "gn:dem":162,
    "gn:feature_class":"P",
    "gn:feature_code":"PPL",
    "gn:name":"Maegok",
    "gn:population":0,
    "gn:timezone":"Asia/Seoul",
    "iso:country":"KR",
    "name:kor_x_preferred":[
        "\ub9e4\uace1"
    ],
    "name:und_x_variant":[
        "Maegong-ni",
        "Maegok-ri",
        "Maegok"
    ],
    "wof:name":"Maegok",
    "wof:placetype":"locality"
},
  "geometry": {"coordinates":[129.17625000000001,35.36809],"type":"Point"}
}