{
  "type": "Feature",
  "properties": {
    "iso:country":"KR",
    "name:ceb_x_preferred":[
        "Bugok-dong"
    ],
    "name:eng_x_preferred":[
        "Bugok-dong"
    ],
    "name:kor_x_preferred":[
        "\ubd80\uace1\ub3d9"
    ],
    "name:slk_x_preferred":[
        "Pugok-dong"
    ],
    "name:swe_x_preferred":[
        "Bugok-dong"
    ],
    "wof:lang":[
        "kor"
    ],
    "wof:name":"\ubd80\uace1\ub3d9",
    "wof:placetype":"neighbourhood"
},
  "geometry": {"coordinates":[126.88684499999999,37.32629],"type":"Point"}
}