{
  "type": "Feature",
  "properties": {
    "gn:admin1_code":"5.0",
    "gn:asciiname":"T'ap-tong",
    "gn:country_code":"KR",
    "gn:dem":295,
    "gn:feature_class":"P",
    "gn:feature_code":"PPL",
    "gn:name":"T\u2019ap-tong",
    "gn:population":0,
    "gn:timezone":"Asia/Seoul",
    "iso:country":"KR",
    "name:eng_x_preferred":[
        "T'ap"
    ],
    "name:eng_x_variant":[
        "T'ap-tong"
    ],
    "name:kor_x_preferred":[
        "\ud0d1\ub3d9"
    ],
    "name:kor_x_variant":[
        "T\u2019ap-tong"
    ],
    "wof:name":"T'ap",
    "wof:placetype":"locality"
},
  "geometry": {"coordinates":[128.09870000000001,37.1718],"type":"Point"}
}