{
  "type": "Feature",
  "properties": {
    "gn:admin1_code":"11.0",
    "gn:asciiname":"Sageun",
    "gn:country_code":"KR",
    "gn:dem":57,
    "gn:feature_class":"P",
    "gn:feature_code":"PPL",
    "gn:name":"Sageun",
    "gn:population":0,
    "gn:timezone":"Asia/Seoul",
    "iso:country":"KR",
    "name:und_x_variant":[
        "\uc0ac\uadfc\ub3d9",
        "Sag\u016dn-dong"
    ],
    "wof:name":"Sageun",
    "wof:placetype":"locality"
},
  "geometry": {"coordinates":[127.04531,37.55896],"type":"Point"}
}