{
  "type": "Feature",
  "properties": {
    "gn:admin1_code":"17.0",
    "gn:asciiname":"Kao-ri",
    "gn:country_code":"KR",
    "gn:dem":316,
    "gn:feature_class":"P",
    "gn:feature_code":"PPL",
    "gn:name":"Kao-ri",
    "gn:population":0,
    "gn:timezone":"Asia/Seoul",
    "iso:country":"KR",
    "name:und_x_variant":[
        "\uac00\uc624\ub9ac",
        "Kao-ri"
    ],
    "wof:name":"Kao-ri",
    "wof:placetype":"locality"
},
  "geometry": {"coordinates":[127.4037,36.0714],"type":"Point"}
}