{
  "type": "Feature",
  "properties": {
    "gn:admin1_code":"6.0",
    "gn:asciiname":"Han'gi",
    "gn:country_code":"KR",
    "gn:dem":26,
    "gn:feature_class":"P",
    "gn:feature_code":"PPL",
    "gn:name":"Han\u2019gi",
    "gn:population":0,
    "gn:timezone":"Asia/Seoul",
    "iso:country":"KR",
    "name:und_x_variant":[
        "Hant\u2019ae",
        "Han\u2019gi",
        "\ud55c\uae30"
    ],
    "wof:name":"Han'gi",
    "wof:placetype":"locality"
},
  "geometry": {"coordinates":[129.30667,37.14861],"type":"Point"}
}