{
  "type": "Feature",
  "properties": {
    "gn:admin1_code":"6.0",
    "gn:asciiname":"Tulgogae",
    "gn:country_code":"KR",
    "gn:dem":538,
    "gn:feature_class":"P",
    "gn:feature_code":"PPL",
    "gn:name":"T\u016dlgogae",
    "gn:population":0,
    "gn:timezone":"Asia/Seoul",
    "iso:country":"KR",
    "name:kor_x_preferred":[
        "\ub4e4\uace0\uac1c"
    ],
    "name:kor_x_variant":[
        "T\u016dlgogae"
    ],
    "wof:name":"Tulgogae",
    "wof:placetype":"locality"
},
  "geometry": {"coordinates":[128.2259,37.5424],"type":"Point"}
}