{
  "type": "Feature",
  "properties": {
    "gn:admin1_code":"14.0",
    "gn:asciiname":"Doldanggol",
    "gn:country_code":"KR",
    "gn:dem":273,
    "gn:feature_class":"P",
    "gn:feature_code":"PPL",
    "gn:name":"Doldanggol",
    "gn:population":0,
    "gn:timezone":"Asia/Seoul",
    "iso:country":"KR",
    "name:kor_x_preferred":[
        "\ub3cc\ub2f9\uace8"
    ],
    "wof:name":"Doldanggol",
    "wof:placetype":"locality"
},
  "geometry": {"coordinates":[128.22114999999999,36.71473],"type":"Point"}
}