{
  "type": "Feature",
  "properties": {
    "gn:admin1_code":"20.0",
    "gn:asciiname":"Gupdari",
    "gn:country_code":"KR",
    "gn:dem":34,
    "gn:feature_class":"P",
    "gn:feature_code":"PPL",
    "gn:name":"Gupdari",
    "gn:population":0,
    "gn:timezone":"Asia/Seoul",
    "iso:country":"KR",
    "name:und_x_variant":[
        "\uad7d\ub2e4\ub9ac",
        "Kupta-ri",
        "Gupdari"
    ],
    "wof:name":"Gupdari",
    "wof:placetype":"locality"
},
  "geometry": {"coordinates":[128.38011,35.60587],"type":"Point"}
}