{
  "type": "Feature",
  "properties": {
    "gn:admin1_code":"13.0",
    "gn:asciiname":"Witjawori",
    "gn:country_code":"KR",
    "gn:dem":101,
    "gn:feature_class":"P",
    "gn:feature_code":"PPL",
    "gn:name":"Witjawori",
    "gn:population":0,
    "gn:timezone":"Asia/Seoul",
    "iso:country":"KR",
    "name:kor_x_preferred":[
        "\uc6c3\uc790\uc704\ub9ac"
    ],
    "name:kor_x_variant":[
        "\uc717\uc790\uc6cc\ub9ac"
    ],
    "name:und_x_variant":[
        "Utjawi-ri",
        "Utchawi-ri",
        "Witjawori"
    ],
    "wof:name":"Witjawori",
    "wof:placetype":"locality"
},
  "geometry": {"coordinates":[127.55332,37.06929],"type":"Point"}
}