{
  "type": "Feature",
  "properties": {
    "gn:admin1_code":"12.0",
    "gn:asciiname":"Nongjang",
    "gn:country_code":"KR",
    "gn:dem":6,
    "gn:feature_class":"P",
    "gn:feature_code":"PPL",
    "gn:name":"Nongjang",
    "gn:population":0,
    "gn:timezone":"Asia/Seoul",
    "iso:country":"KR",
    "name:kor_x_preferred":[
        "\ub18d\uc7a5"
    ],
    "wof:name":"Nongjang",
    "wof:placetype":"locality"
},
  "geometry": {"coordinates":[126.22459000000001,37.8024],"type":"Point"}
}