{
  "type": "Feature",
  "properties": {
    "gn:admin1_code":"14.0",
    "gn:asciiname":"Ch'anmulmaegi",
    "gn:country_code":"KR",
    "gn:dem":326,
    "gn:feature_class":"P",
    "gn:feature_code":"PPL",
    "gn:name":"Ch\u2019anmulmaegi",
    "gn:population":0,
    "gn:timezone":"Asia/Seoul",
    "iso:country":"KR",
    "name:und_x_variant":[
        "\ucc2c\ubb3c\ub9e4\uae30",
        "Ch\u2019anmulmaegi"
    ],
    "wof:name":"Ch'anmulmaegi",
    "wof:placetype":"locality"
},
  "geometry": {"coordinates":[129.3126,36.9474],"type":"Point"}
}