{
  "type": "Feature",
  "properties": {
    "gn:admin1_code":"15.0",
    "gn:asciiname":"Oedong",
    "gn:country_code":"KR",
    "gn:dem":28,
    "gn:feature_class":"P",
    "gn:feature_code":"PPL",
    "gn:name":"Oedong",
    "gn:population":0,
    "gn:timezone":"Asia/Seoul",
    "iso:country":"KR",
    "name:und_x_variant":[
        "\uc678\ub3d9",
        "Oedong"
    ],
    "wof:name":"Oedong",
    "wof:placetype":"locality"
},
  "geometry": {"coordinates":[128.40313999999998,35.6912],"type":"Point"}
}