{
  "type": "Feature",
  "properties": {
    "gn:admin1_code":"20.0",
    "gn:asciiname":"Kumch'ol-li",
    "gn:country_code":"KR",
    "gn:dem":203,
    "gn:feature_class":"P",
    "gn:feature_code":"PPL",
    "gn:name":"K\u016dmch\u2019\u014fl-li",
    "gn:population":0,
    "gn:timezone":"Asia/Seoul",
    "iso:country":"KR",
    "name:und_x_variant":[
        "\uae08\ucc9c\ub9ac",
        "K\u016dmch\u2019\u014fl-li"
    ],
    "wof:name":"Kumch'ol-li",
    "wof:placetype":"locality"
},
  "geometry": {"coordinates":[127.91092999999999,35.67894000000001],"type":"Point"}
}