{
  "type": "Feature",
  "properties": {
    "gn:admin1_code":"13.0",
    "gn:admin2_code":"Ans\u014fng-si",
    "gn:asciiname":"Chungnim-ni",
    "gn:country_code":"KR",
    "gn:dem":109,
    "gn:feature_class":"P",
    "gn:feature_code":"PPLL",
    "gn:name":"Chungnim-ni",
    "gn:population":0,
    "gn:timezone":"Asia/Seoul",
    "iso:country":"KR",
    "name:kor_x_preferred":[
        "\uc8fd\ub9bc\ub9ac"
    ],
    "name:und_x_variant":[
        "Jungnim-ri"
    ],
    "wof:name":"Chungnim-ni",
    "wof:placetype":"locality"
},
  "geometry": {"coordinates":[127.4525,37.06722],"type":"Point"}
}