{
  "type": "Feature",
  "properties": {
    "gn:admin1_code":"16.0",
    "gn:asciiname":"Ch'ongyong",
    "gn:country_code":"KR",
    "gn:dem":94,
    "gn:feature_class":"P",
    "gn:feature_code":"PPL",
    "gn:name":"Ch\u2019\u014fngyong",
    "gn:population":0,
    "gn:timezone":"Asia/Seoul",
    "iso:country":"KR",
    "name:kor_x_preferred":[
        "Ch\u2019\u014fngyong"
    ],
    "name:und_x_variant":[
        "\uccad\uc6a9"
    ],
    "wof:name":"Ch'ongyong",
    "wof:placetype":"locality"
},
  "geometry": {"coordinates":[126.72167,34.59361],"type":"Point"}
}