{
  "type": "Feature",
  "properties": {
    "gn:admin1_code":"19.0",
    "gn:asciiname":"Sinpyeong",
    "gn:country_code":"KR",
    "gn:dem":103,
    "gn:feature_class":"P",
    "gn:feature_code":"PPL",
    "gn:name":"Sinpyeong",
    "gn:population":0,
    "gn:timezone":"Asia/Seoul",
    "iso:country":"KR",
    "name:kor_x_preferred":[
        "\uc2e0\ud3c9"
    ],
    "name:und_x_variant":[
        "\uc9c4\ud3c9",
        "Chinp\u2019y\u014fng",
        "Sinpyeong"
    ],
    "wof:name":"Sinpyeong",
    "wof:placetype":"locality"
},
  "geometry": {"coordinates":[127.32040000000001,36.23934000000001],"type":"Point"}
}