{
  "type": "Feature",
  "properties": {
    "gn:admin1_code":"3.0",
    "gn:asciiname":"Poksongi",
    "gn:country_code":"KR",
    "gn:dem":451,
    "gn:feature_class":"P",
    "gn:feature_code":"PPL",
    "gn:name":"Poks\u014fngi",
    "gn:population":0,
    "gn:timezone":"Asia/Seoul",
    "iso:country":"KR",
    "name:und_x_variant":[
        "\ubcf5\uc131\uc774",
        "Poks\u014fngi"
    ],
    "wof:name":"Poksongi",
    "wof:placetype":"locality"
},
  "geometry": {"coordinates":[127.56738,35.51542],"type":"Point"}
}