{
  "type": "Feature",
  "properties": {
    "gn:admin1_code":"13.0",
    "gn:asciiname":"Neunggol",
    "gn:country_code":"KR",
    "gn:dem":96,
    "gn:feature_class":"P",
    "gn:feature_code":"PPL",
    "gn:name":"Neunggol",
    "gn:population":0,
    "gn:timezone":"Asia/Seoul",
    "iso:country":"KR",
    "name:und_x_variant":[
        "\ub2a5\uace8",
        "N\u016dng-gol",
        "Neunggol"
    ],
    "wof:name":"Neunggol",
    "wof:placetype":"locality"
},
  "geometry": {"coordinates":[127.0886,37.9092],"type":"Point"}
}