{
  "type": "Feature",
  "properties": {
    "gn:admin1_code":"1.0",
    "gn:asciiname":"Hwasul-li",
    "gn:cc2":"KR",
    "gn:country_code":"KR",
    "gn:dem":40,
    "gn:feature_class":"P",
    "gn:feature_code":"PPL",
    "gn:name":"Hwasul-li",
    "gn:population":0,
    "gn:timezone":"Asia/Seoul",
    "iso:country":"KR",
    "name:und_x_variant":[
        "Wajun-ri",
        "Hwasun-ni",
        "Kajun-ri",
        "Hwasul-li"
    ],
    "wof:name":"Hwasul-li",
    "wof:placetype":"locality"
},
  "geometry": {"coordinates":[126.33444,33.24639000000001],"type":"Point"}
}