{
  "type": "Feature",
  "properties": {
    "gn:admin1_code":"16.0",
    "gn:admin2_code":"Chindo-gun",
    "gn:asciiname":"Dohang",
    "gn:country_code":"KR",
    "gn:dem":6,
    "gn:feature_class":"P",
    "gn:feature_code":"PPL",
    "gn:name":"Dohang",
    "gn:population":0,
    "gn:timezone":"Asia/Seoul",
    "iso:country":"KR",
    "name:kor_x_preferred":[
        "\ub3c4\ud56d"
    ],
    "name:und_x_variant":[
        "Chag\u016dndomok",
        "Sodomok"
    ],
    "wof:name":"Dohang",
    "wof:placetype":"locality"
},
  "geometry": {"coordinates":[126.30788,34.4102],"type":"Point"}
}