{
  "type": "Feature",
  "properties": {
    "gn:admin1_code":"16.0",
    "gn:asciiname":"Ssukjeongi",
    "gn:country_code":"KR",
    "gn:dem":103,
    "gn:feature_class":"P",
    "gn:feature_code":"PPL",
    "gn:name":"Ssukjeongi",
    "gn:population":0,
    "gn:timezone":"Asia/Seoul",
    "iso:country":"KR",
    "name:kor_x_preferred":[
        "\uc465\uc815\uc774"
    ],
    "wof:name":"Ssukjeongi",
    "wof:placetype":"locality"
},
  "geometry": {"coordinates":[126.73257,35.31795],"type":"Point"}
}