{
  "type": "Feature",
  "properties": {
    "gn:admin1_code":"12.0",
    "gn:admin2_code":"Kanghwa-gun",
    "gn:asciiname":"Ochondong",
    "gn:country_code":"KR",
    "gn:dem":29,
    "gn:feature_class":"P",
    "gn:feature_code":"PPL",
    "gn:name":"Ochondong",
    "gn:population":0,
    "gn:timezone":"Asia/Seoul",
    "iso:country":"KR",
    "name:kor_x_preferred":[
        "\uc624\ucd0c\ub3d9"
    ],
    "name:und_x_variant":[
        "Och\u2019on-dong"
    ],
    "wof:name":"Ochondong",
    "wof:placetype":"locality"
},
  "geometry": {"coordinates":[126.42415,37.80737],"type":"Point"}
}