{
  "type": "Feature",
  "properties": {
    "gn:admin1_code":"17.0",
    "gn:asciiname":"Soeseong",
    "gn:country_code":"KR",
    "gn:dem":197,
    "gn:feature_class":"P",
    "gn:feature_code":"PPL",
    "gn:name":"Soeseong",
    "gn:population":0,
    "gn:timezone":"Asia/Seoul",
    "iso:country":"KR",
    "name:kor_x_preferred":[
        "\uc1e0\uc131"
    ],
    "wof:name":"Soeseong",
    "wof:placetype":"locality"
},
  "geometry": {"coordinates":[127.19817,36.62398],"type":"Point"}
}