{
  "type": "Feature",
  "properties": {
    "gn:admin1_code":"6.0",
    "gn:asciiname":"Mangbaek",
    "gn:country_code":"KR",
    "gn:dem":145,
    "gn:feature_class":"P",
    "gn:feature_code":"PPL",
    "gn:name":"Mangbaek",
    "gn:population":0,
    "gn:timezone":"Asia/Seoul",
    "iso:country":"KR",
    "name:kor_x_preferred":[
        "\ub9dd\ubc31"
    ],
    "wof:name":"Mangbaek",
    "wof:placetype":"locality"
},
  "geometry": {"coordinates":[128.02070000000001,37.4689],"type":"Point"}
}