{
  "type": "Feature",
  "properties": {
    "gn:admin1_code":"6.0",
    "gn:asciiname":"Godungol",
    "gn:country_code":"KR",
    "gn:dem":378,
    "gn:feature_class":"P",
    "gn:feature_code":"PPL",
    "gn:name":"Godungol",
    "gn:population":0,
    "gn:timezone":"Asia/Seoul",
    "iso:country":"KR",
    "name:kor_x_preferred":[
        "\uace0\ub454\uace8"
    ],
    "name:und_x_variant":[
        "Kodun-gol"
    ],
    "wof:name":"Godungol",
    "wof:placetype":"locality"
},
  "geometry": {"coordinates":[127.74078,38.25962],"type":"Point"}
}