{
  "type": "Feature",
  "properties": {
    "gn:admin1_code":"20.0",
    "gn:asciiname":"Ch'angp'yong-ni",
    "gn:country_code":"KR",
    "gn:dem":183,
    "gn:feature_class":"P",
    "gn:feature_code":"PPL",
    "gn:name":"Ch\u2019angp\u2019y\u014fng-ni",
    "gn:population":0,
    "gn:timezone":"Asia/Seoul",
    "iso:country":"KR",
    "name:und_x_variant":[
        "\ucc3d\ud3c9\ub9ac",
        "Ch\u2019angp\u2019y\u014fng-ni"
    ],
    "wof:name":"Ch'angp'yong-ni",
    "wof:placetype":"locality"
},
  "geometry": {"coordinates":[127.7715,35.57273],"type":"Point"}
}