{
  "type": "Feature",
  "properties": {
    "gn:admin1_code":"16.0",
    "gn:asciiname":"Songji",
    "gn:country_code":"KR",
    "gn:dem":27,
    "gn:feature_class":"P",
    "gn:feature_code":"PPL",
    "gn:name":"S\u014fngji",
    "gn:population":0,
    "gn:timezone":"Asia/Seoul",
    "iso:country":"KR",
    "name:kor_x_preferred":[
        "S\u014fngji"
    ],
    "name:und_x_variant":[
        "\uc131\uc9c0"
    ],
    "wof:name":"Songji",
    "wof:placetype":"locality"
},
  "geometry": {"coordinates":[126.73027999999999,34.55694],"type":"Point"}
}