{
  "type": "Feature",
  "properties": {
    "gn:admin1_code":"13.0",
    "gn:asciiname":"Sokgol",
    "gn:country_code":"KR",
    "gn:dem":158,
    "gn:feature_class":"P",
    "gn:feature_code":"PPL",
    "gn:name":"Sokgol",
    "gn:population":0,
    "gn:timezone":"Asia/Seoul",
    "iso:country":"KR",
    "name:kor_x_preferred":[
        "\uc18d\uace8"
    ],
    "name:und_x_variant":[
        "\uc18d\uace8",
        "Sok-kol",
        "Sokgol"
    ],
    "wof:name":"Sokgol",
    "wof:placetype":"locality"
},
  "geometry": {"coordinates":[127.48099999999999,37.6487],"type":"Point"}
}