{
  "type": "Feature",
  "properties": {
    "iso:country":"KR",
    "qs:name":"\uc775\uc0b0\uc2dc",
    "qs:name_adm0":"\ud55c\uad6d",
    "qs:name_adm1":"\uc804\ub77c\ubd81\ub3c4",
    "qs:photos":39,
    "qs:photos_1k":8,
    "qs:photos_9k":1,
    "qs:photos_9r":2,
    "qs:photos_all":39,
    "qs:photos_sr":2,
    "qs:placetype":"Town",
    "qs:pop_sr":"0",
    "wof:name":"\uc775\uc0b0\uc2dc",
    "wof:placetype":"locality"
},
  "geometry": {"coordinates":[126.998588,36.012357],"type":"Point"}
}