{
  "type": "Feature",
  "properties": {
    "gn:admin1_code":"3.0",
    "gn:asciiname":"Chungwa",
    "gn:country_code":"KR",
    "gn:dem":16,
    "gn:feature_class":"P",
    "gn:feature_code":"PPL",
    "gn:name":"Chungwa",
    "gn:population":0,
    "gn:timezone":"Asia/Seoul",
    "iso:country":"KR",
    "name:und_x_variant":[
        "\uc911\uc640",
        "Chungwa"
    ],
    "wof:name":"Chungwa",
    "wof:placetype":"locality"
},
  "geometry": {"coordinates":[127.11045,35.91101],"type":"Point"}
}