{
  "type": "Feature",
  "properties": {
    "gn:admin1_code":"17.0",
    "gn:asciiname":"Saewon",
    "gn:country_code":"KR",
    "gn:dem":11,
    "gn:feature_class":"P",
    "gn:feature_code":"PPL",
    "gn:name":"Saew\u014fn",
    "gn:population":0,
    "gn:timezone":"Asia/Seoul",
    "iso:country":"KR",
    "name:und_x_variant":[
        "\uc0c8\uc6d0",
        "Saew\u014fn"
    ],
    "wof:name":"Saewon",
    "wof:placetype":"locality"
},
  "geometry": {"coordinates":[126.91459999999999,36.8858],"type":"Point"}
}