{
  "type": "Feature",
  "properties": {
    "gn:admin1_code":"6.0",
    "gn:asciiname":"Taraenomi",
    "gn:country_code":"KR",
    "gn:dem":556,
    "gn:feature_class":"P",
    "gn:feature_code":"PPL",
    "gn:name":"Taraen\u014fmi",
    "gn:population":0,
    "gn:timezone":"Asia/Seoul",
    "iso:country":"KR",
    "name:kor_x_preferred":[
        "\ub2e4\ub798\ub118\uc774"
    ],
    "name:kor_x_variant":[
        "Taraen\u014fmi"
    ],
    "wof:name":"Taraenomi",
    "wof:placetype":"locality"
},
  "geometry": {"coordinates":[128.4718,37.3511],"type":"Point"}
}