{
  "type": "Feature",
  "properties": {
    "gn:admin1_code":"16.0",
    "gn:asciiname":"Gugichon",
    "gn:country_code":"KR",
    "gn:dem":17,
    "gn:feature_class":"P",
    "gn:feature_code":"PPL",
    "gn:name":"Gugichon",
    "gn:population":0,
    "gn:timezone":"Asia/Seoul",
    "iso:country":"KR",
    "name:kor_x_preferred":[
        "\uad6c\uae30\ucd0c"
    ],
    "wof:name":"Gugichon",
    "wof:placetype":"locality"
},
  "geometry": {"coordinates":[126.69161,34.97223],"type":"Point"}
}