{
  "type": "Feature",
  "properties": {
    "gn:admin1_code":"13.0",
    "gn:asciiname":"Gwandong",
    "gn:country_code":"KR",
    "gn:dem":54,
    "gn:feature_class":"P",
    "gn:feature_code":"PPL",
    "gn:name":"Gwandong",
    "gn:population":0,
    "gn:timezone":"Asia/Seoul",
    "iso:country":"KR",
    "name:ara_x_preferred":[
        "\u063a\u0648\u0627\u0646\u062f\u0648\u0646\u063a"
    ],
    "name:hun_x_preferred":[
        "Kvandong"
    ],
    "name:ind_x_preferred":[
        "Gwandong"
    ],
    "name:kor_x_preferred":[
        "\uad00\ub3d9 \uc9c0\ubc29"
    ],
    "name:spa_x_preferred":[
        "Gwandong"
    ],
    "name:tha_x_preferred":[
        "\u0e04\u0e27\u0e31\u0e19\u0e14\u0e07"
    ],
    "name:und_x_variant":[
        "\uad00\ub3d9",
        "Kwan-dong"
    ],
    "name:urd_x_preferred":[
        "\u06af\u0648\u0627\u0646\u0688\u0648\u0646\u06af"
    ],
    "wof:name":"Gwandong",
    "wof:placetype":"locality"
},
  "geometry": {"coordinates":[127.13784,37.02798],"type":"Point"}
}