{
  "type": "Feature",
  "properties": {
    "gn:admin1_code":"16.0",
    "gn:asciiname":"Suda-ri",
    "gn:cc2":"KR",
    "gn:country_code":"KR",
    "gn:dem":2,
    "gn:feature_class":"P",
    "gn:feature_code":"PPL",
    "gn:name":"Suda-ri",
    "gn:population":0,
    "gn:timezone":"Asia/Seoul",
    "iso:country":"KR",
    "name:und_x_variant":[
        "Suda",
        "Suita-ri",
        "Suda-ri"
    ],
    "wof:name":"Suda-ri",
    "wof:placetype":"locality"
},
  "geometry": {"coordinates":[125.96111000000001,34.71944000000001],"type":"Point"}
}