{
  "type": "Feature",
  "properties": {
    "iso:country":"KR",
    "name:eng_x_preferred":[
        "Bugok-myeon"
    ],
    "name:kor_x_preferred":[
        "\ubd80\uace1\uba74"
    ],
    "qs:name":"\ubd80\uace1\uba74",
    "qs:name_adm0":"\ud55c\uad6d",
    "qs:name_adm1":"\uacbd\uc0c1\ub0a8\ub3c4",
    "qs:photos":1,
    "qs:photos_1k":1,
    "qs:photos_9k":1,
    "qs:photos_9r":1,
    "qs:photos_all":1,
    "qs:photos_sr":1,
    "qs:placetype":"LocalAdmin",
    "qs:pop_sr":"0",
    "wof:name":"Bugok-myeon",
    "wof:placetype":"localadmin"
},
  "geometry": {"coordinates":[128.63999899999999,35.375061],"type":"Point"}
}