{
  "type": "Feature",
  "properties": {
    "gn:admin1_code":"20.0",
    "gn:asciiname":"Sagye",
    "gn:country_code":"KR",
    "gn:dem":104,
    "gn:feature_class":"P",
    "gn:feature_code":"PPL",
    "gn:name":"Sagye",
    "gn:population":0,
    "gn:timezone":"Asia/Seoul",
    "iso:country":"KR",
    "name:und_x_variant":[
        "\uc0ac\uacc4",
        "Sagye"
    ],
    "wof:name":"Sagye",
    "wof:placetype":"locality"
},
  "geometry": {"coordinates":[128.37179,34.93744],"type":"Point"}
}