{
  "type": "Feature",
  "properties": {
    "gn:admin1_code":"16.0",
    "gn:asciiname":"Sangsurak",
    "gn:country_code":"KR",
    "gn:dem":387,
    "gn:feature_class":"P",
    "gn:feature_code":"PPL",
    "gn:name":"Sangsurak",
    "gn:population":0,
    "gn:timezone":"Asia/Seoul",
    "iso:country":"KR",
    "name:kor_x_preferred":[
        "\uc0c1\uc218\ub77d"
    ],
    "name:und_x_variant":[
        "Sansurak",
        "Sangsurak"
    ],
    "wof:name":"Sangsurak",
    "wof:placetype":"locality"
},
  "geometry": {"coordinates":[126.86622,34.87351],"type":"Point"}
}