{
  "type": "Feature",
  "properties": {
    "gn:admin1_code":"1.0",
    "gn:admin2_code":"Pukcheju-gun",
    "gn:asciiname":"Pulmittang",
    "gn:country_code":"KR",
    "gn:dem":18,
    "gn:feature_class":"P",
    "gn:feature_code":"PPL",
    "gn:name":"Pulmittang",
    "gn:population":0,
    "gn:timezone":"Asia/Seoul",
    "iso:country":"KR",
    "wof:name":"Pulmittang",
    "wof:placetype":"locality"
},
  "geometry": {"coordinates":[126.20917,33.36861],"type":"Point"}
}