{
  "type": "Feature",
  "properties": {
    "gn:admin1_code":"6.0",
    "gn:asciiname":"Komun-gol",
    "gn:country_code":"KR",
    "gn:dem":576,
    "gn:feature_class":"P",
    "gn:feature_code":"PPL",
    "gn:name":"K\u014fm\u016dn-gol",
    "gn:population":0,
    "gn:timezone":"Asia/Seoul",
    "iso:country":"KR",
    "name:und_x_variant":[
        "\uac80\uc740\uace8",
        "K\u014fm\u016dn-gol"
    ],
    "wof:name":"Komun-gol",
    "wof:placetype":"locality"
},
  "geometry": {"coordinates":[129.16669999999999,37.1592],"type":"Point"}
}