{
  "type": "Feature",
  "properties": {
    "gn:admin1_code":"17.0",
    "gn:asciiname":"Seobongdong",
    "gn:country_code":"KR",
    "gn:dem":127,
    "gn:feature_class":"P",
    "gn:feature_code":"PPL",
    "gn:name":"Seobongdong",
    "gn:population":0,
    "gn:timezone":"Asia/Seoul",
    "iso:country":"KR",
    "name:kor_x_preferred":[
        "\uc11c\ubd09\ub3d9"
    ],
    "wof:name":"Seobongdong",
    "wof:placetype":"locality"
},
  "geometry": {"coordinates":[127.25982,36.68878],"type":"Point"}
}