{
  "type": "Feature",
  "properties": {
    "gn:admin1_code":"15.0",
    "gn:asciiname":"Towon-dong",
    "gn:country_code":"KR",
    "gn:dem":163,
    "gn:feature_class":"P",
    "gn:feature_code":"PPLL",
    "gn:name":"Tow\u014fn-dong",
    "gn:population":0,
    "gn:timezone":"Asia/Seoul",
    "iso:country":"KR",
    "wof:name":"Towon-dong",
    "wof:placetype":"locality"
},
  "geometry": {"coordinates":[128.55389,35.80444],"type":"Point"}
}