{
  "type": "Feature",
  "properties": {
    "gn:admin1_code":"1.0",
    "gn:asciiname":"Odoburak",
    "gn:country_code":"KR",
    "gn:dem":38,
    "gn:feature_class":"P",
    "gn:feature_code":"PPL",
    "gn:name":"Odoburak",
    "gn:population":0,
    "gn:timezone":"Asia/Seoul",
    "iso:country":"KR",
    "name:kor_x_preferred":[
        "\uc624\ub3c4\ubd80\ub77d"
    ],
    "name:und_x_variant":[
        "Odo-dong"
    ],
    "wof:name":"Odoburak",
    "wof:placetype":"locality"
},
  "geometry": {"coordinates":[126.45943,33.49159],"type":"Point"}
}