{
  "type": "Feature",
  "properties": {
    "gn:admin1_code":"6.0",
    "gn:asciiname":"Haenginnadeuri",
    "gn:country_code":"KR",
    "gn:dem":188,
    "gn:feature_class":"P",
    "gn:feature_code":"PPL",
    "gn:name":"Haenginnadeuri",
    "gn:population":0,
    "gn:timezone":"Asia/Seoul",
    "iso:country":"KR",
    "name:kor_x_preferred":[
        "\ud589\uc778\ub098\ub4dc\ub9ac"
    ],
    "name:kor_x_variant":[
        "Haenginnad\u016d-ri"
    ],
    "wof:name":"Haenginnadeuri",
    "wof:placetype":"locality"
},
  "geometry": {"coordinates":[127.97248,37.78949],"type":"Point"}
}