{
  "type": "Feature",
  "properties": {
    "gn:admin1_code":"5.0",
    "gn:asciiname":"Yeongchon",
    "gn:country_code":"KR",
    "gn:dem":177,
    "gn:feature_class":"P",
    "gn:feature_code":"PPL",
    "gn:name":"Yeongchon",
    "gn:population":0,
    "gn:timezone":"Asia/Seoul",
    "iso:country":"KR",
    "name:kor_x_preferred":[
        "\uc601\ucd0c"
    ],
    "wof:name":"Yeongchon",
    "wof:placetype":"locality"
},
  "geometry": {"coordinates":[127.81542,36.93375],"type":"Point"}
}