{
  "type": "Feature",
  "properties": {
    "gn:admin1_code":"3.0",
    "gn:asciiname":"Hasal-li",
    "gn:country_code":"KR",
    "gn:dem":418,
    "gn:feature_class":"P",
    "gn:feature_code":"PPL",
    "gn:name":"Hasal-li",
    "gn:population":0,
    "gn:timezone":"Asia/Seoul",
    "iso:country":"KR",
    "name:und_x_variant":[
        "\ud558\uc0b0\ub9ac",
        "Hasan-ni",
        "Hasal-li"
    ],
    "wof:name":"Hasal-li",
    "wof:placetype":"locality"
},
  "geometry": {"coordinates":[127.65925,35.86779],"type":"Point"}
}