{
  "type": "Feature",
  "properties": {
    "gn:admin1_code":"14.0",
    "gn:asciiname":"Deonmeori",
    "gn:country_code":"KR",
    "gn:dem":63,
    "gn:feature_class":"P",
    "gn:feature_code":"PPL",
    "gn:name":"Deonmeori",
    "gn:population":0,
    "gn:timezone":"Asia/Seoul",
    "iso:country":"KR",
    "name:kor_x_preferred":[
        "\ub367\uba38\ub9ac"
    ],
    "wof:name":"Deonmeori",
    "wof:placetype":"locality"
},
  "geometry": {"coordinates":[129.28136000000001,35.89835],"type":"Point"}
}