{
  "type": "Feature",
  "properties": {
    "gn:admin1_code":"6.0",
    "gn:asciiname":"Kajol-li",
    "gn:country_code":"KR",
    "gn:dem":176,
    "gn:feature_class":"P",
    "gn:feature_code":"PPL",
    "gn:name":"Kaj\u014fl-li",
    "gn:population":0,
    "gn:timezone":"Asia/Seoul",
    "iso:country":"KR",
    "name:kor_x_preferred":[
        "\uac00\uc804\ub9ac"
    ],
    "name:kor_x_variant":[
        "Kaj\u014fl-li"
    ],
    "wof:name":"Kajol-li",
    "wof:placetype":"locality"
},
  "geometry": {"coordinates":[127.9858,37.5714],"type":"Point"}
}