{
  "type": "Feature",
  "properties": {
    "gn:admin1_code":"5.0",
    "gn:asciiname":"Koch'oni",
    "gn:country_code":"KR",
    "gn:dem":276,
    "gn:feature_class":"P",
    "gn:feature_code":"PPL",
    "gn:name":"K\u014fch\u2019\u014fni",
    "gn:population":0,
    "gn:timezone":"Asia/Seoul",
    "iso:country":"KR",
    "name:kor_x_preferred":[
        "\uac70\ucc98\ub2c8"
    ],
    "name:kor_x_variant":[
        "K\u014fch\u2019\u014fni"
    ],
    "wof:name":"Koch'oni",
    "wof:placetype":"locality"
},
  "geometry": {"coordinates":[128.18559999999999,37.148],"type":"Point"}
}