{
  "type": "Feature",
  "properties": {
    "gn:admin1_code":"6.0",
    "gn:asciiname":"Hach'amyon",
    "gn:country_code":"KR",
    "gn:dem":144,
    "gn:feature_class":"P",
    "gn:feature_code":"PPL",
    "gn:name":"Hach\u2019amy\u014fn",
    "gn:population":0,
    "gn:timezone":"Asia/Seoul",
    "iso:country":"KR",
    "name:kor_x_preferred":[
        "\ud558\ucc28\uba74"
    ],
    "name:kor_x_variant":[
        "Hach\u2019amy\u014fn"
    ],
    "wof:name":"Hach'amyon",
    "wof:placetype":"locality"
},
  "geometry": {"coordinates":[127.8951,37.361],"type":"Point"}
}