{
  "type": "Feature",
  "properties": {
    "gn:admin1_code":"14.0",
    "gn:asciiname":"Gyeonggok",
    "gn:country_code":"KR",
    "gn:dem":211,
    "gn:feature_class":"P",
    "gn:feature_code":"PPL",
    "gn:name":"Gyeonggok",
    "gn:population":0,
    "gn:timezone":"Asia/Seoul",
    "iso:country":"KR",
    "name:kor_x_preferred":[
        "\uacbd\uace1"
    ],
    "wof:name":"Gyeonggok",
    "wof:placetype":"locality"
},
  "geometry": {"coordinates":[128.98106000000001,36.59893],"type":"Point"}
}