{
  "type": "Feature",
  "properties": {
    "gn:admin1_code":"20.0",
    "gn:asciiname":"Ogu-ri",
    "gn:cc2":"KR",
    "gn:country_code":"KR",
    "gn:dem":1,
    "gn:feature_class":"P",
    "gn:feature_code":"PPL",
    "gn:name":"\u014egu-ri",
    "gn:population":0,
    "gn:timezone":"Asia/Seoul",
    "iso:country":"KR",
    "name:und_x_variant":[
        "\u014egu",
        "\u014egu-ri"
    ],
    "wof:name":"Ogu-ri",
    "wof:placetype":"locality"
},
  "geometry": {"coordinates":[128.50667000000001,34.81944],"type":"Point"}
}