{
  "type": "Feature",
  "properties": {
    "gn:admin1_code":"14.0",
    "gn:asciiname":"Pidae-dong",
    "gn:country_code":"KR",
    "gn:dem":219,
    "gn:feature_class":"P",
    "gn:feature_code":"PPL",
    "gn:name":"Pidae-dong",
    "gn:population":0,
    "gn:timezone":"Asia/Seoul",
    "iso:country":"KR",
    "name:und_x_variant":[
        "Pidae-gol",
        "\ube44\ub300\ub3d9",
        "Pidae-dong"
    ],
    "wof:name":"Pidae-dong",
    "wof:placetype":"locality"
},
  "geometry": {"coordinates":[128.76294999999999,36.45048],"type":"Point"}
}