{
  "type": "Feature",
  "properties": {
    "gn:admin1_code":"6.0",
    "gn:asciiname":"Gulbawi",
    "gn:country_code":"KR",
    "gn:dem":13,
    "gn:feature_class":"P",
    "gn:feature_code":"PPL",
    "gn:name":"Gulbawi",
    "gn:population":0,
    "gn:timezone":"Asia/Seoul",
    "iso:country":"KR",
    "name:kor_x_preferred":[
        "\uad74\ubc14\uc704"
    ],
    "wof:name":"Gulbawi",
    "wof:placetype":"locality"
},
  "geometry": {"coordinates":[128.76048,37.965],"type":"Point"}
}