{
  "type": "Feature",
  "properties": {
    "gn:admin1_code":"20.0",
    "gn:asciiname":"Pongnam-dong",
    "gn:country_code":"KR",
    "gn:dem":12,
    "gn:feature_class":"P",
    "gn:feature_code":"PPL",
    "gn:name":"Pongnam-dong",
    "gn:population":0,
    "gn:timezone":"Asia/Seoul",
    "iso:country":"KR",
    "name:und_x_variant":[
        "Pongj\u014fn",
        "Pongnam-dong",
        "Pongg\u014fn"
    ],
    "wof:name":"Pongnam-dong",
    "wof:placetype":"locality"
},
  "geometry": {"coordinates":[128.11667,34.93333],"type":"Point"}
}