{
  "type": "Feature",
  "properties": {
    "gn:admin1_code":"14.0",
    "gn:asciiname":"Araetgamasil",
    "gn:country_code":"KR",
    "gn:dem":60,
    "gn:feature_class":"P",
    "gn:feature_code":"PPL",
    "gn:name":"Araetgamasil",
    "gn:population":0,
    "gn:timezone":"Asia/Seoul",
    "iso:country":"KR",
    "name:kor_x_preferred":[
        "\uc544\ub7ab\uac00\ub9c8\uc2e4"
    ],
    "wof:name":"Araetgamasil",
    "wof:placetype":"locality"
},
  "geometry": {"coordinates":[128.80073000000002,35.90421],"type":"Point"}
}