{
  "type": "Feature",
  "properties": {
    "gn:admin1_code":"17.0",
    "gn:asciiname":"Siuch'i",
    "gn:country_code":"KR",
    "gn:dem":17,
    "gn:feature_class":"P",
    "gn:feature_code":"PPL",
    "gn:name":"Siuch\u2019i",
    "gn:population":0,
    "gn:timezone":"Asia/Seoul",
    "iso:country":"KR",
    "name:und_x_variant":[
        "\uc2dc\uc6b0\uce58",
        "Siuch\u2019i"
    ],
    "wof:name":"Siuch'i",
    "wof:placetype":"locality"
},
  "geometry": {"coordinates":[126.2811,36.8321],"type":"Point"}
}