{
  "type": "Feature",
  "properties": {
    "gn:admin1_code":"14.0",
    "gn:asciiname":"Wonbyeongsan",
    "gn:country_code":"KR",
    "gn:dem":85,
    "gn:feature_class":"P",
    "gn:feature_code":"PPL",
    "gn:name":"Wonbyeongsan",
    "gn:population":0,
    "gn:timezone":"Asia/Seoul",
    "iso:country":"KR",
    "name:kor_x_preferred":[
        "\uc6d0\ubcd1\uc0b0"
    ],
    "wof:name":"Wonbyeongsan",
    "wof:placetype":"locality"
},
  "geometry": {"coordinates":[128.55343999999999,36.54067],"type":"Point"}
}