{
  "type": "Feature",
  "properties": {
    "gn:country":"KR",
    "gn:fcode":"ADMD",
    "gn:pop":0,
    "iso:country":"KR",
    "name:eng_x_preferred":[
        "Andong-si"
    ],
    "name:eng_x_variant":[
        "Andong"
    ],
    "name:kor_x_preferred":[
        "\uc548\ub3d9\uc2dc"
    ],
    "name:kor_x_variant":[
        "\uc548\ub3d9",
        "Andong-\u016dp"
    ],
    "name:unk_x_variant":[
        "Andong"
    ],
    "qs:name":"Andong-si",
    "qs:photos_9r":0,
    "qs:photos_sr":0,
    "qs:pop_sr":"0",
    "wd:elevation":139.0,
    "wd:wordcount":1314,
    "wof:name":"Andong-si",
    "wof:placetype":"localadmin",
    "wof:population":0
},
  "geometry": {"coordinates":[128.71666999999999,36.56667],"type":"Point"}
}