{
  "type": "Feature",
  "properties": {
    "gn:admin1_code":"16.0",
    "gn:asciiname":"Julsa",
    "gn:country_code":"KR",
    "gn:dem":55,
    "gn:feature_class":"P",
    "gn:feature_code":"PPL",
    "gn:name":"Julsa",
    "gn:population":0,
    "gn:timezone":"Asia/Seoul",
    "iso:country":"KR",
    "name:kor_x_preferred":[
        "\uc904\uc0ac"
    ],
    "wof:name":"Julsa",
    "wof:placetype":"locality"
},
  "geometry": {"coordinates":[126.63743999999998,35.10918],"type":"Point"}
}