{
  "type": "Feature",
  "properties": {
    "gn:admin1_code":"3.0",
    "gn:asciiname":"Ujong",
    "gn:country_code":"KR",
    "gn:dem":339,
    "gn:feature_class":"P",
    "gn:feature_code":"PPL",
    "gn:name":"Uj\u014fng",
    "gn:population":0,
    "gn:timezone":"Asia/Seoul",
    "iso:country":"KR",
    "name:und_x_variant":[
        "\uc6b0\uc815",
        "Uj\u014fng"
    ],
    "wof:name":"Ujong",
    "wof:placetype":"locality"
},
  "geometry": {"coordinates":[127.32496999999999,35.79593],"type":"Point"}
}