{
  "type": "Feature",
  "properties": {
    "gn:admin1_code":"16.0",
    "gn:asciiname":"Seokgeundeokbyeok",
    "gn:country_code":"KR",
    "gn:dem":47,
    "gn:feature_class":"P",
    "gn:feature_code":"PPL",
    "gn:name":"Seokgeundeokbyeok",
    "gn:population":0,
    "gn:timezone":"Asia/Seoul",
    "iso:country":"KR",
    "name:kor_x_preferred":[
        "\uc11d\uadfc\ub355\ubcbd"
    ],
    "wof:name":"Seokgeundeokbyeok",
    "wof:placetype":"locality"
},
  "geometry": {"coordinates":[126.75232,34.93306],"type":"Point"}
}