{
  "type": "Feature",
  "properties": {
    "gn:admin1_code":"17.0",
    "gn:asciiname":"Haenggyeong",
    "gn:country_code":"KR",
    "gn:dem":63,
    "gn:feature_class":"P",
    "gn:feature_code":"PPL",
    "gn:name":"Haenggyeong",
    "gn:population":0,
    "gn:timezone":"Asia/Seoul",
    "iso:country":"KR",
    "name:kor_x_preferred":[
        "\ud589\uacbd"
    ],
    "wof:name":"Haenggyeong",
    "wof:placetype":"locality"
},
  "geometry": {"coordinates":[127.18859,36.23703],"type":"Point"}
}