{
  "type": "Feature",
  "properties": {
    "gn:admin1_code":"5.0",
    "gn:asciiname":"Sangwon",
    "gn:country_code":"KR",
    "gn:dem":119,
    "gn:feature_class":"P",
    "gn:feature_code":"PPL",
    "gn:name":"Sangw\u014fn",
    "gn:population":0,
    "gn:timezone":"Asia/Seoul",
    "iso:country":"KR",
    "name:und_x_variant":[
        "\uc0c1\uc6d0",
        "Sangw\u014fn"
    ],
    "wof:name":"Sangwon",
    "wof:placetype":"locality"
},
  "geometry": {"coordinates":[127.6563,36.2419],"type":"Point"}
}