{
  "type": "Feature",
  "properties": {
    "gn:admin1_code":"16.0",
    "gn:asciiname":"Yongsan",
    "gn:country_code":"KR",
    "gn:dem":130,
    "gn:feature_class":"P",
    "gn:feature_code":"PPL",
    "gn:name":"Yongsan",
    "gn:population":0,
    "gn:timezone":"Asia/Seoul",
    "iso:country":"KR",
    "name:kor_x_preferred":[
        "\uc6a9\uc0b0"
    ],
    "wof:name":"Yongsan",
    "wof:placetype":"locality"
},
  "geometry": {"coordinates":[126.91681,35.3807],"type":"Point"}
}