{
  "type": "Feature",
  "properties": {
    "gn:admin1_code":"16.0",
    "gn:asciiname":"Galma",
    "gn:country_code":"KR",
    "gn:dem":96,
    "gn:feature_class":"P",
    "gn:feature_code":"PPL",
    "gn:name":"Galma",
    "gn:population":0,
    "gn:timezone":"Asia/Seoul",
    "iso:country":"KR",
    "name:kor_x_preferred":[
        "\uac08\ub9c8"
    ],
    "name:und_x_variant":[
        "Kalma-ri",
        "Kalma",
        "Galma"
    ],
    "wof:name":"Galma",
    "wof:placetype":"locality"
},
  "geometry": {"coordinates":[126.84729,34.92303],"type":"Point"}
}