{
  "type": "Feature",
  "properties": {
    "gn:admin1_code":"16.0",
    "gn:asciiname":"Ye-ri",
    "gn:cc2":"KR",
    "gn:country_code":"KR",
    "gn:dem":-9999,
    "gn:feature_class":"P",
    "gn:feature_code":"PPL",
    "gn:name":"Ye-ri",
    "gn:population":0,
    "gn:timezone":"Asia/Seoul",
    "iso:country":"KR",
    "name:und_x_variant":[
        "Ei-ri",
        "Ye-ri"
    ],
    "wof:name":"Ye-ri",
    "wof:placetype":"locality"
},
  "geometry": {"coordinates":[125.45,34.68333],"type":"Point"}
}