{
  "type": "Feature",
  "properties": {
    "gn:admin1_code":"13.0",
    "gn:asciiname":"Soenae",
    "gn:country_code":"KR",
    "gn:dem":73,
    "gn:feature_class":"P",
    "gn:feature_code":"PPL",
    "gn:name":"Soenae",
    "gn:population":0,
    "gn:timezone":"Asia/Seoul",
    "iso:country":"KR",
    "name:kor_x_preferred":[
        "\uc1e0\ub0b4"
    ],
    "wof:name":"Soenae",
    "wof:placetype":"locality"
},
  "geometry": {"coordinates":[127.52462,37.74958],"type":"Point"}
}