{
  "type": "Feature",
  "properties": {
    "gn:admin1_code":"6.0",
    "gn:asciiname":"Eomdalgol",
    "gn:country_code":"KR",
    "gn:dem":423,
    "gn:feature_class":"P",
    "gn:feature_code":"PPL",
    "gn:name":"Eomdalgol",
    "gn:population":0,
    "gn:timezone":"Asia/Seoul",
    "iso:country":"KR",
    "name:kor_x_preferred":[
        "\uc5c4\ub2ec\uace8"
    ],
    "name:kor_x_variant":[
        "\u014emdal-gol"
    ],
    "wof:name":"Eomdalgol",
    "wof:placetype":"locality"
},
  "geometry": {"coordinates":[128.25158999999999,37.86607],"type":"Point"}
}