{
  "type": "Feature",
  "properties": {
    "gn:admin1_code":"6.0",
    "gn:asciiname":"Manji-dong",
    "gn:country_code":"KR",
    "gn:dem":216,
    "gn:feature_class":"P",
    "gn:feature_code":"PPL",
    "gn:name":"Manji-dong",
    "gn:population":0,
    "gn:timezone":"Asia/Seoul",
    "iso:country":"KR",
    "name:kor_x_preferred":[
        "\ub9cc\uc9c0\ub3d9"
    ],
    "wof:name":"Manji-dong",
    "wof:placetype":"locality"
},
  "geometry": {"coordinates":[128.53739999999999,37.2343],"type":"Point"}
}