{
  "type": "Feature",
  "properties": {
    "gn:admin1_code":"6.0",
    "gn:asciiname":"Aoraji",
    "gn:country_code":"KR",
    "gn:dem":392,
    "gn:feature_class":"P",
    "gn:feature_code":"PPL",
    "gn:name":"Aoraji",
    "gn:population":0,
    "gn:timezone":"Asia/Seoul",
    "iso:country":"KR",
    "name:kor_x_preferred":[
        "\uc544\uc624\ub77c\uc9c0"
    ],
    "wof:name":"Aoraji",
    "wof:placetype":"locality"
},
  "geometry": {"coordinates":[128.2347,37.7274],"type":"Point"}
}