{
  "type": "Feature",
  "properties": {
    "gn:admin1_code":"6.0",
    "gn:asciiname":"K'un-gol",
    "gn:country_code":"KR",
    "gn:dem":126,
    "gn:feature_class":"P",
    "gn:feature_code":"PPL",
    "gn:name":"K\u2019\u016dn-gol",
    "gn:population":0,
    "gn:timezone":"Asia/Seoul",
    "iso:country":"KR",
    "name:und_x_variant":[
        "\ud070\uace8",
        "K\u2019\u016dn-gol"
    ],
    "wof:name":"K'un-gol",
    "wof:placetype":"locality"
},
  "geometry": {"coordinates":[127.75472000000001,38.085],"type":"Point"}
}