{
  "type": "Feature",
  "properties": {
    "gn:admin1_code":"20.0",
    "gn:asciiname":"Chisu",
    "gn:country_code":"KR",
    "gn:dem":64,
    "gn:feature_class":"P",
    "gn:feature_code":"PPL",
    "gn:name":"Chisu",
    "gn:population":0,
    "gn:timezone":"Asia/Seoul",
    "iso:country":"KR",
    "name:und_x_variant":[
        "\uc9c0\uc218",
        "Chisu"
    ],
    "wof:name":"Chisu",
    "wof:placetype":"locality"
},
  "geometry": {"coordinates":[128.63697999999999,35.54939],"type":"Point"}
}