{
  "type": "Feature",
  "properties": {
    "gn:admin1_code":"3.0",
    "gn:asciiname":"Wonjonggok",
    "gn:country_code":"KR",
    "gn:dem":325,
    "gn:feature_class":"P",
    "gn:feature_code":"PPL",
    "gn:name":"W\u014fnj\u014fnggok",
    "gn:population":0,
    "gn:timezone":"Asia/Seoul",
    "iso:country":"KR",
    "name:und_x_variant":[
        "\uc6d0\uc815\uace1",
        "W\u014fnj\u014fnggok"
    ],
    "wof:name":"Wonjonggok",
    "wof:placetype":"locality"
},
  "geometry": {"coordinates":[127.38988999999999,35.79228],"type":"Point"}
}