{
  "type": "Feature",
  "properties": {
    "gn:admin1_code":"5.0",
    "gn:asciiname":"Chonggok",
    "gn:country_code":"KR",
    "gn:dem":107,
    "gn:feature_class":"P",
    "gn:feature_code":"PPL",
    "gn:name":"Ch\u014fnggok",
    "gn:population":0,
    "gn:timezone":"Asia/Seoul",
    "iso:country":"KR",
    "name:und_x_variant":[
        "\uc815\uace1",
        "Ch\u014fnggok"
    ],
    "wof:name":"Chonggok",
    "wof:placetype":"locality"
},
  "geometry": {"coordinates":[127.6713,36.3979],"type":"Point"}
}