{
  "type": "Feature",
  "properties": {
    "gn:admin1_code":"5.0",
    "gn:asciiname":"Yongso-mal",
    "gn:country_code":"KR",
    "gn:dem":105,
    "gn:feature_class":"P",
    "gn:feature_code":"PPL",
    "gn:name":"Yongso-mal",
    "gn:population":0,
    "gn:timezone":"Asia/Seoul",
    "iso:country":"KR",
    "name:und_x_variant":[
        "\uc6a9\uc18c\ub9d0",
        "Yongso-mal"
    ],
    "wof:name":"Yongso-mal",
    "wof:placetype":"locality"
},
  "geometry": {"coordinates":[127.6384,36.2714],"type":"Point"}
}