{
  "type": "Feature",
  "properties": {
    "gn:admin1_code":"17.0",
    "gn:asciiname":"Wonmoe",
    "gn:country_code":"KR",
    "gn:dem":20,
    "gn:feature_class":"P",
    "gn:feature_code":"PPL",
    "gn:name":"W\u014fnmoe",
    "gn:population":0,
    "gn:timezone":"Asia/Seoul",
    "iso:country":"KR",
    "name:und_x_variant":[
        "\uc6d0\ubafc",
        "W\u014fnmoe"
    ],
    "wof:name":"Wonmoe",
    "wof:placetype":"locality"
},
  "geometry": {"coordinates":[126.49160000000001,36.8809],"type":"Point"}
}