{
  "type": "Feature",
  "properties": {
    "gn:admin1_code":"14.0",
    "gn:asciiname":"Sijangt'o",
    "gn:country_code":"KR",
    "gn:dem":193,
    "gn:feature_class":"P",
    "gn:feature_code":"PPL",
    "gn:name":"Sijangt\u2019\u014f",
    "gn:population":0,
    "gn:timezone":"Asia/Seoul",
    "iso:country":"KR",
    "name:und_x_variant":[
        "\uc2dc\uc7a5\ud130",
        "Sijangt\u2019\u014f"
    ],
    "wof:name":"Sijangt'o",
    "wof:placetype":"locality"
},
  "geometry": {"coordinates":[128.80240000000001,36.401],"type":"Point"}
}