{
  "type": "Feature",
  "properties": {
    "gn:admin1_code":"14.0",
    "gn:asciiname":"Sojang-ni",
    "gn:country_code":"KR",
    "gn:dem":209,
    "gn:feature_class":"P",
    "gn:feature_code":"PPL",
    "gn:name":"Sojang-ni",
    "gn:population":0,
    "gn:timezone":"Asia/Seoul",
    "iso:country":"KR",
    "name:und_x_variant":[
        "\uc74c\uc9c0\ub9d0",
        "\u016cmji-mal"
    ],
    "wof:name":"Sojang-ni",
    "wof:placetype":"locality"
},
  "geometry": {"coordinates":[127.97293000000001,35.95176],"type":"Point"}
}