{
  "type": "Feature",
  "properties": {
    "gn:admin1_code":"13.0",
    "gn:asciiname":"Keun-mal",
    "gn:country_code":"KR",
    "gn:dem":64,
    "gn:feature_class":"P",
    "gn:feature_code":"PPL",
    "gn:name":"Keun-mal",
    "gn:population":0,
    "gn:timezone":"Asia/Seoul",
    "iso:country":"KR",
    "name:und_x_variant":[
        "\ud070\ub9d0",
        "Keun-mal",
        "K\u2019\u016dn-mal"
    ],
    "wof:name":"Keun-mal",
    "wof:placetype":"locality"
},
  "geometry": {"coordinates":[127.58472,37.31889],"type":"Point"}
}