{
  "type": "Feature",
  "properties": {
    "gn:admin1_code":"17.0",
    "gn:asciiname":"Taesu-gol",
    "gn:country_code":"KR",
    "gn:dem":176,
    "gn:feature_class":"P",
    "gn:feature_code":"PPL",
    "gn:name":"Taesu-gol",
    "gn:population":0,
    "gn:timezone":"Asia/Seoul",
    "iso:country":"KR",
    "name:und_x_variant":[
        "\ub300\uc218\uace8",
        "Taesu-gol"
    ],
    "wof:name":"Taesu-gol",
    "wof:placetype":"locality"
},
  "geometry": {"coordinates":[126.7427,36.3689],"type":"Point"}
}