{
  "type": "Feature",
  "properties": {
    "gn:admin1_code":"14.0",
    "gn:asciiname":"Bokgogae",
    "gn:country_code":"KR",
    "gn:dem":207,
    "gn:feature_class":"P",
    "gn:feature_code":"PPL",
    "gn:name":"Bokgogae",
    "gn:population":0,
    "gn:timezone":"Asia/Seoul",
    "iso:country":"KR",
    "name:kor_x_preferred":[
        "\ubcf5\uace0\uac1c"
    ],
    "name:und_x_variant":[
        "Pokkogae"
    ],
    "wof:name":"Bokgogae",
    "wof:placetype":"locality"
},
  "geometry": {"coordinates":[128.60482999999999,36.07409000000001],"type":"Point"}
}