{
  "type": "Feature",
  "properties": {
    "gn:admin1_code":"19.0",
    "gn:asciiname":"Haun-ni",
    "gn:country_code":"KR",
    "gn:dem":121,
    "gn:feature_class":"P",
    "gn:feature_code":"PPL",
    "gn:name":"Ha\u016dn-ni",
    "gn:population":0,
    "gn:timezone":"Asia/Seoul",
    "iso:country":"KR",
    "name:eng_x_preferred":[
        "Haun"
    ],
    "name:eng_x_variant":[
        "Haun-ni"
    ],
    "wof:name":"Haun",
    "wof:placetype":"locality"
},
  "geometry": {"coordinates":[127.51667,36.26667],"type":"Point"}
}