{
  "type": "Feature",
  "properties": {
    "gn:admin1_code":"16.0",
    "gn:asciiname":"Nogam",
    "gn:country_code":"KR",
    "gn:dem":22,
    "gn:feature_class":"P",
    "gn:feature_code":"PPL",
    "gn:name":"Nogam",
    "gn:population":0,
    "gn:timezone":"Asia/Seoul",
    "iso:country":"KR",
    "name:kor_x_preferred":[
        "\ub179\uc554"
    ],
    "name:und_x_variant":[
        "Nongmun-ni",
        "Nogam"
    ],
    "wof:name":"Nogam",
    "wof:placetype":"locality"
},
  "geometry": {"coordinates":[126.67895,34.79048],"type":"Point"}
}