{
  "type": "Feature",
  "properties": {
    "iso:country":"KR",
    "name:eng_x_preferred":[
        "Onyang 3(sam)-dong"
    ],
    "name:kor_x_preferred":[
        "\uc628\uc5913\ub3d9"
    ],
    "qs:name":"\uc628\uc5913\ub3d9",
    "qs:name_adm0":"\ud55c\uad6d",
    "qs:name_adm1":"\ucda9\uccad\ub0a8\ub3c4",
    "qs:photos":69,
    "qs:photos_1k":14,
    "qs:photos_9k":1,
    "qs:photos_9r":2,
    "qs:photos_all":69,
    "qs:photos_sr":2,
    "qs:placetype":"LocalAdmin",
    "qs:pop_sr":"0",
    "wof:name":"Onyang 3(sam)-dong",
    "wof:placetype":"localadmin"
},
  "geometry": {"coordinates":[127.03304199999999,36.808732],"type":"Point"}
}