{
  "type": "Feature",
  "properties": {
    "gn:admin1_code":"5.0",
    "gn:asciiname":"Goran",
    "gn:country_code":"KR",
    "gn:dem":248,
    "gn:feature_class":"P",
    "gn:feature_code":"PPL",
    "gn:name":"Goran",
    "gn:population":0,
    "gn:timezone":"Asia/Seoul",
    "iso:country":"KR",
    "name:kor_x_preferred":[
        "\ub204\ub8e8\uc2e4"
    ],
    "name:kor_x_variant":[
        "\uace0\ub780"
    ],
    "name:und_x_variant":[
        "Nurusil",
        "Goran"
    ],
    "wof:name":"Goran",
    "wof:placetype":"locality"
},
  "geometry": {"coordinates":[128.24913999999998,37.03717],"type":"Point"}
}