{
  "type": "Feature",
  "properties": {
    "gn:admin1_code":"5.0",
    "gn:asciiname":"Goran",
    "gn:country_code":"KR",
    "gn:dem":248,
    "gn:feature_class":"P",
    "gn:feature_code":"PPL",
    "gn:name":"Goran",
    "gn:population":0,
    "gn:timezone":"Asia/Seoul",
    "iso:country":"KR",
    "name:aze_x_preferred":[
        "Goran"
    ],
    "name:bul_x_preferred":[
        "\u0413\u043e\u0440\u0430\u043d"
    ],
    "name:ceb_x_preferred":[
        "Goran"
    ],
    "name:ckb_x_preferred":[
        "\u06af\u06c6\u0631\u0627\u0646"
    ],
    "name:deu_x_preferred":[
        "Goran"
    ],
    "name:fas_x_preferred":[
        "\u06af\u0648\u0631\u0627\u0646"
    ],
    "name:fra_x_preferred":[
        "Goran"
    ],
    "name:hye_x_preferred":[
        "\u0533\u0578\u0580\u0561\u0576"
    ],
    "name:kat_x_preferred":[
        "\u10d2\u10dd\u10e0\u10d0\u10dc\u10d8"
    ],
    "name:kor_x_preferred":[
        "\ub204\ub8e8\uc2e4"
    ],
    "name:kor_x_variant":[
        "\uace0\ub780"
    ],
    "name:kur_x_preferred":[
        "Goran"
    ],
    "name:pol_x_preferred":[
        "Goran"
    ],
    "name:ron_x_preferred":[
        "Goran"
    ],
    "name:rus_x_preferred":[
        "\u0413\u043e\u0440\u0430\u043d"
    ],
    "name:srp_x_preferred":[
        "\u0413\u043e\u0440\u0430\u043d"
    ],
    "name:swe_x_preferred":[
        "Goran"
    ],
    "name:und_x_variant":[
        "Nurusil",
        "Goran"
    ],
    "wof:name":"Goran",
    "wof:placetype":"locality"
},
  "geometry": {"coordinates":[128.24913999999998,37.03717],"type":"Point"}
}