{
  "type": "Feature",
  "properties": {
    "iso:country":"KR",
    "name:eng_x_preferred":[
        "Gobong-dong"
    ],
    "name:kor_x_preferred":[
        "\uace0\ubd09\ub3d9"
    ],
    "name:und_x_variant":[
        "\ub3c4\ubd09\ub3d9"
    ],
    "qs:gn_fcode":"PPL",
    "qs:gn_local":0,
    "qs:gn_namadm1":"11",
    "qs:gn_name":"Tobong-dong",
    "qs:local_max":852,
    "qs:local_sum":1203,
    "qs:localhoods":6,
    "qs:name":"\uace0\ubd09\ub3d9",
    "qs:name_adm0":"\ud55c\uad6d",
    "qs:name_adm1":"\uacbd\uae30\ub3c4",
    "qs:name_adm2":"\uace0\uc591\uc2dc",
    "qs:name_lau":"\uc77c\uc0b0\ub3d9\uad6c",
    "qs:name_local":"\uc77c\uc0b0\ub3d9\uad6c",
    "qs:photo_max":87,
    "qs:photo_sum":115,
    "qs:placetype":"Suburb",
    "qs:quad_count":10,
    "qs:woe_adm0":23424868,
    "qs:woe_adm1":2345969,
    "qs:woe_adm2":28289179,
    "qs:woe_lau":28997210,
    "qs:woe_local":28997210,
    "qs:woe_ver":"7.10.0",
    "wof:lang":[
        "kor"
    ],
    "wof:name":"Gobong-dong",
    "wof:placetype":"neighbourhood"
},
  "geometry": {"coordinates":[126.8343,37.731125],"type":"Point"}
}