{
  "type": "Feature",
  "properties": {
    "gn:admin1_code":"16.0",
    "gn:asciiname":"Todae-ri",
    "gn:cc2":"KR",
    "gn:country_code":"KR",
    "gn:dem":13,
    "gn:feature_class":"P",
    "gn:feature_code":"PPL",
    "gn:name":"Todae-ri",
    "gn:population":0,
    "gn:timezone":"Asia/Seoul",
    "iso:country":"KR",
    "name:und_x_variant":[
        "Todae",
        "Todae-ri"
    ],
    "wof:name":"Todae-ri",
    "wof:placetype":"locality"
},
  "geometry": {"coordinates":[126.40611,34.95056],"type":"Point"}
}