{
  "type": "Feature",
  "properties": {
    "iso:country":"KR",
    "name:ceb_x_preferred":[
        "Is\u014f-my\u014fn"
    ],
    "name:eng_x_preferred":[
        "Iseo-myeon"
    ],
    "name:kor_x_preferred":[
        "\uc774\uc11c\uba74"
    ],
    "name:nld_x_preferred":[
        "Iseo-myeon"
    ],
    "name:swe_x_preferred":[
        "Is\u014f-my\u014fn"
    ],
    "name:swe_x_variant":[
        "Iseo-myeon"
    ],
    "name:zho_x_preferred":[
        "\u4f0a\u897f\u9762"
    ],
    "qs:name":"\uc774\uc11c\uba74",
    "qs:name_adm0":"\ud55c\uad6d",
    "qs:name_adm1":"\uc804\ub77c\ubd81\ub3c4",
    "qs:photos":3,
    "qs:photos_1k":1,
    "qs:photos_9k":1,
    "qs:photos_9r":1,
    "qs:photos_all":3,
    "qs:photos_sr":1,
    "qs:placetype":"LocalAdmin",
    "qs:pop_sr":"0",
    "wd:wordcount":242,
    "wof:name":"\uc774\uc11c\uba74",
    "wof:placetype":"localadmin"
},
  "geometry": {"coordinates":[127.238159,35.806676],"type":"Point"}
}