{
  "type": "Feature",
  "properties": {
    "gn:admin1_code":"14.0",
    "gn:asciiname":"Gwigye",
    "gn:country_code":"KR",
    "gn:dem":87,
    "gn:feature_class":"P",
    "gn:feature_code":"PPL",
    "gn:name":"Gwigye",
    "gn:population":0,
    "gn:timezone":"Asia/Seoul",
    "iso:country":"KR",
    "name:kor_x_preferred":[
        "\uadc0\uacc4"
    ],
    "wof:name":"Gwigye",
    "wof:placetype":"locality"
},
  "geometry": {"coordinates":[129.16262,35.7508],"type":"Point"}
}