{
  "type": "Feature",
  "properties": {
    "gn:country":"KR",
    "gn:fcode":"ADM3",
    "gn:population":0,
    "iso:country":"KR",
    "name:eng_x_preferred":[
        "Samnye"
    ],
    "name:eng_x_variant":[
        "Samnye-\u016dp",
        "Samnye-eup"
    ],
    "name:kor_x_preferred":[
        "\uc0bc\ub840\uc74d"
    ],
    "qs:name":"Samnye-\u016dp",
    "qs:photos_9r":0,
    "qs:photos_sr":0,
    "qs:pop_sr":"0",
    "wof:name":"Samnye",
    "wof:placetype":"localadmin",
    "wof:population":0
},
  "geometry": {"coordinates":[127.08174,35.91557],"type":"Point"}
}