{
  "type": "Feature",
  "properties": {
    "gn:admin1_code":"13.0",
    "gn:asciiname":"Mulguri",
    "gn:country_code":"KR",
    "gn:dem":27,
    "gn:feature_class":"P",
    "gn:feature_code":"PPL",
    "gn:name":"Mulguri",
    "gn:population":0,
    "gn:timezone":"Asia/Seoul",
    "iso:country":"KR",
    "name:kor_x_preferred":[
        "\ubb3c\uad6c\ub9ac"
    ],
    "wof:name":"Mulguri",
    "wof:placetype":"locality"
},
  "geometry": {"coordinates":[126.86639,37.05222],"type":"Point"}
}