{
  "type": "Feature",
  "properties": {
    "gn:admin1_code":"13.0",
    "gn:asciiname":"Sangbeoncheon-ri",
    "gn:country_code":"KR",
    "gn:dem":97,
    "gn:feature_class":"P",
    "gn:feature_code":"PPLL",
    "gn:name":"Sangbeoncheon-ri",
    "gn:population":0,
    "gn:timezone":"Asia/Seoul",
    "iso:country":"KR",
    "name:und_x_variant":[
        "\uc0c1\ubc88\ucc9c\ub9ac",
        "Sangbeoncheon-ri",
        "Sangb\u014fnch\u2019\u014fl-li"
    ],
    "wof:name":"Sangbeoncheon-ri",
    "wof:placetype":"locality"
},
  "geometry": {"coordinates":[127.26000000000001,37.445],"type":"Point"}
}