{
  "type": "Feature",
  "properties": {
    "gn:admin1_code":"15.0",
    "gn:asciiname":"Yeobudong",
    "gn:country_code":"KR",
    "gn:dem":39,
    "gn:feature_class":"P",
    "gn:feature_code":"PPL",
    "gn:name":"Yeobudong",
    "gn:population":0,
    "gn:timezone":"Asia/Seoul",
    "iso:country":"KR",
    "name:kor_x_preferred":[
        "\uc5ec\ubd80\ub3d9"
    ],
    "wof:name":"Yeobudong",
    "wof:placetype":"locality"
},
  "geometry": {"coordinates":[128.43236000000002,35.65991],"type":"Point"}
}