{
  "type": "Feature",
  "properties": {
    "gn:admin1_code":"13.0",
    "gn:asciiname":"Seju-gol",
    "gn:country_code":"KR",
    "gn:dem":132,
    "gn:feature_class":"P",
    "gn:feature_code":"PPL",
    "gn:name":"Seju-gol",
    "gn:population":0,
    "gn:timezone":"Asia/Seoul",
    "iso:country":"KR",
    "name:und_x_variant":[
        "\uc138\uc8fc\uace8",
        "Seju-gol"
    ],
    "wof:name":"Seju-gol",
    "wof:placetype":"locality"
},
  "geometry": {"coordinates":[127.57889,37.445],"type":"Point"}
}