{
  "type": "Feature",
  "properties": {
    "gn:admin1_code":"13.0",
    "gn:asciiname":"Oesamjong-ni",
    "gn:country_code":"KR",
    "gn:dem":5,
    "gn:feature_class":"P",
    "gn:feature_code":"PPL",
    "gn:name":"Oesamj\u014fng-ni",
    "gn:population":0,
    "gn:timezone":"Asia/Seoul",
    "iso:country":"KR",
    "name:eng_x_preferred":[
        "Oesamjong"
    ],
    "name:eng_x_variant":[
        "Oesamjong-ni"
    ],
    "wof:name":"Oesamjong",
    "wof:placetype":"locality"
},
  "geometry": {"coordinates":[126.96666999999999,36.96667],"type":"Point"}
}