{
  "type": "Feature",
  "properties": {
    "gn:admin1_code":"14.0",
    "gn:asciiname":"Towon",
    "gn:country_code":"KR",
    "gn:dem":63,
    "gn:feature_class":"P",
    "gn:feature_code":"PPL",
    "gn:name":"Tow\u014fn",
    "gn:population":0,
    "gn:timezone":"Asia/Seoul",
    "iso:country":"KR",
    "name:und_x_variant":[
        "\ub3c4\uc6d0",
        "Tow\u014fn"
    ],
    "wof:name":"Towon",
    "wof:placetype":"locality"
},
  "geometry": {"coordinates":[128.27408,35.97542],"type":"Point"}
}