{
  "type": "Feature",
  "properties": {
    "gn:admin1_code":"16.0",
    "gn:asciiname":"Hajangam",
    "gn:country_code":"KR",
    "gn:dem":24,
    "gn:feature_class":"P",
    "gn:feature_code":"PPL",
    "gn:name":"Hajangam",
    "gn:population":0,
    "gn:timezone":"Asia/Seoul",
    "iso:country":"KR",
    "name:kor_x_preferred":[
        "\ud558\uc7a5"
    ],
    "name:kor_x_variant":[
        "\ud558\uc7a5\uc554"
    ],
    "name:und_x_variant":[
        "Hajang",
        "Hajangam"
    ],
    "wof:name":"Hajangam",
    "wof:placetype":"locality"
},
  "geometry": {"coordinates":[127.40631,34.80852],"type":"Point"}
}