{
  "type": "Feature",
  "properties": {
    "gn:admin1_code":"13.0",
    "gn:asciiname":"Sinchon",
    "gn:country_code":"KR",
    "gn:dem":183,
    "gn:feature_class":"P",
    "gn:feature_code":"PPL",
    "gn:name":"Sinchon",
    "gn:population":0,
    "gn:timezone":"Asia/Seoul",
    "iso:country":"KR",
    "name:kor_x_preferred":[
        "\uc2e0\ucd0c"
    ],
    "name:kor_x_variant":[
        "Sin-ch\u2019on"
    ],
    "wof:name":"Sinchon",
    "wof:placetype":"locality"
},
  "geometry": {"coordinates":[127.25318,37.81102],"type":"Point"}
}