{
  "type": "Feature",
  "properties": {
    "gn:admin1_code":"20.0",
    "gn:asciiname":"Changch'ang-gol",
    "gn:country_code":"KR",
    "gn:dem":29,
    "gn:feature_class":"P",
    "gn:feature_code":"PPL",
    "gn:name":"Changch\u2019ang-gol",
    "gn:population":0,
    "gn:timezone":"Asia/Seoul",
    "iso:country":"KR",
    "name:und_x_variant":[
        "\uc7a5\ucc3d\uace8",
        "Changch\u2019ang-gol"
    ],
    "wof:name":"Changch'ang-gol",
    "wof:placetype":"locality"
},
  "geometry": {"coordinates":[128.45713000000001,35.53296],"type":"Point"}
}