{
  "type": "Feature",
  "properties": {
    "gn:admin1_code":"13.0",
    "gn:asciiname":"Tongjin",
    "gn:country_code":"KR",
    "gn:dem":147,
    "gn:feature_class":"P",
    "gn:feature_code":"PPL",
    "gn:name":"Tongjin",
    "gn:population":0,
    "gn:timezone":"Asia/Seoul",
    "iso:country":"KR",
    "name:und_x_variant":[
        "\ub3d9\uc9c4",
        "Dongjin",
        "Tongjin"
    ],
    "wof:name":"Tongjin",
    "wof:placetype":"locality"
},
  "geometry": {"coordinates":[127.18861,37.22694],"type":"Point"}
}