{
  "type": "Feature",
  "properties": {
    "gn:admin1_code":"17.0",
    "gn:asciiname":"Sodaengi",
    "gn:country_code":"KR",
    "gn:dem":27,
    "gn:feature_class":"P",
    "gn:feature_code":"PPL",
    "gn:name":"Sodaengi",
    "gn:population":0,
    "gn:timezone":"Asia/Seoul",
    "iso:country":"KR",
    "name:und_x_variant":[
        "\uc18c\ub315\uc774",
        "Sodaengi"
    ],
    "wof:name":"Sodaengi",
    "wof:placetype":"locality"
},
  "geometry": {"coordinates":[126.4722,36.7447],"type":"Point"}
}