{
  "type": "Feature",
  "properties": {
    "gn:admin1_code":"14.0",
    "gn:asciiname":"Beomsil",
    "gn:country_code":"KR",
    "gn:dem":29,
    "gn:feature_class":"P",
    "gn:feature_code":"PPL",
    "gn:name":"Beomsil",
    "gn:population":0,
    "gn:timezone":"Asia/Seoul",
    "iso:country":"KR",
    "name:kor_x_preferred":[
        "\ubc94\uc2e4"
    ],
    "wof:name":"Beomsil",
    "wof:placetype":"locality"
},
  "geometry": {"coordinates":[129.43788000000001,35.66907],"type":"Point"}
}