{
  "type": "Feature",
  "properties": {
    "gn:admin1_code":"14.0",
    "gn:asciiname":"Chungp'yong",
    "gn:country_code":"KR",
    "gn:dem":159,
    "gn:feature_class":"P",
    "gn:feature_code":"PPL",
    "gn:name":"Chungp\u2019y\u014fng",
    "gn:population":0,
    "gn:timezone":"Asia/Seoul",
    "iso:country":"KR",
    "wof:name":"Chungp'yong",
    "wof:placetype":"locality"
},
  "geometry": {"coordinates":[128.52361000000002,36.17167],"type":"Point"}
}