{
  "type": "Feature",
  "properties": {
    "gn:admin1_code":"17.0",
    "gn:asciiname":"Sangdong-ni",
    "gn:country_code":"KR",
    "gn:dem":43,
    "gn:feature_class":"P",
    "gn:feature_code":"PPLL",
    "gn:name":"Sangd\u014fng-ni",
    "gn:population":0,
    "gn:timezone":"Asia/Seoul",
    "iso:country":"KR",
    "name:eng_x_preferred":[
        "Sangdong"
    ],
    "name:eng_x_variant":[
        "Sangdong-ni"
    ],
    "name:und_x_variant":[
        "\uc0c1\ub355\ub9ac",
        "Sangd\u014fng-ni"
    ],
    "wof:name":"Sangdong",
    "wof:placetype":"locality"
},
  "geometry": {"coordinates":[127.11324999999999,36.88957],"type":"Point"}
}