{
  "type": "Feature",
  "properties": {
    "gn:admin1_code":"17.0",
    "gn:asciiname":"Ihwa-ri",
    "gn:country_code":"KR",
    "gn:dem":174,
    "gn:feature_class":"P",
    "gn:feature_code":"PPL",
    "gn:name":"Ihwa-ri",
    "gn:population":0,
    "gn:timezone":"Asia/Seoul",
    "iso:country":"KR",
    "name:und_x_variant":[
        "Ihwaj\u014fng",
        "\uc774\ud654\uc815"
    ],
    "wof:name":"Ihwa-ri",
    "wof:placetype":"locality"
},
  "geometry": {"coordinates":[126.88760000000001,36.4641],"type":"Point"}
}