{
  "type": "Feature",
  "properties": {
    "gn:admin1_code":"17.0",
    "gn:asciiname":"Doenjeori",
    "gn:country_code":"KR",
    "gn:dem":74,
    "gn:feature_class":"P",
    "gn:feature_code":"PPL",
    "gn:name":"Doenjeori",
    "gn:population":0,
    "gn:timezone":"Asia/Seoul",
    "iso:country":"KR",
    "name:kor_x_preferred":[
        "\ub41c\uc808\uc774"
    ],
    "wof:name":"Doenjeori",
    "wof:placetype":"locality"
},
  "geometry": {"coordinates":[126.90188999999999,36.66271],"type":"Point"}
}