{
  "type": "Feature",
  "properties": {
    "gn:admin1_code":"18.0",
    "gn:asciiname":"Hwasan",
    "gn:country_code":"KR",
    "gn:dem":93,
    "gn:feature_class":"P",
    "gn:feature_code":"PPL",
    "gn:name":"Hwasan",
    "gn:population":0,
    "gn:timezone":"Asia/Seoul",
    "iso:country":"KR",
    "name:kor_x_preferred":[
        "\ud654\uc0b0"
    ],
    "wof:name":"Hwasan",
    "wof:placetype":"locality"
},
  "geometry": {"coordinates":[126.92167000000001,35.11507],"type":"Point"}
}