{
  "type": "Feature",
  "properties": {
    "gn:admin1_code":"17.0",
    "gn:asciiname":"Huch'ong-dong",
    "gn:country_code":"KR",
    "gn:dem":32,
    "gn:feature_class":"P",
    "gn:feature_code":"PPL",
    "gn:name":"Huch\u2019\u014fng-dong",
    "gn:population":0,
    "gn:timezone":"Asia/Seoul",
    "iso:country":"KR",
    "name:und_x_variant":[
        "\ud6c4\uccad\ub3d9",
        "Huch\u2019\u014fng-dong"
    ],
    "wof:name":"Huch'ong-dong",
    "wof:placetype":"locality"
},
  "geometry": {"coordinates":[126.5316,36.5345],"type":"Point"}
}