{
  "type": "Feature",
  "properties": {
    "gn:admin1_code":"17.0",
    "gn:asciiname":"Nung-dong",
    "gn:country_code":"KR",
    "gn:dem":38,
    "gn:feature_class":"P",
    "gn:feature_code":"PPL",
    "gn:name":"N\u016dng-dong",
    "gn:population":0,
    "gn:timezone":"Asia/Seoul",
    "iso:country":"KR",
    "name:und_x_variant":[
        "\ub2a5\ub3d9",
        "N\u016dng-dong"
    ],
    "wof:name":"Nung-dong",
    "wof:placetype":"locality"
},
  "geometry": {"coordinates":[126.5193,36.5648],"type":"Point"}
}