{
  "type": "Feature",
  "properties": {
    "gn:admin1_code":"16.0",
    "gn:asciiname":"Yedong",
    "gn:country_code":"KR",
    "gn:dem":29,
    "gn:feature_class":"P",
    "gn:feature_code":"PPL",
    "gn:name":"Yedong",
    "gn:population":0,
    "gn:timezone":"Asia/Seoul",
    "iso:country":"KR",
    "name:kor_x_preferred":[
        "\uc608\ub3d9"
    ],
    "wof:name":"Yedong",
    "wof:placetype":"locality"
},
  "geometry": {"coordinates":[126.74141000000002,34.95311],"type":"Point"}
}