{
  "type": "Feature",
  "properties": {
    "gn:admin1_code":"13.0",
    "gn:asciiname":"Sinchon",
    "gn:country_code":"KR",
    "gn:dem":11,
    "gn:feature_class":"P",
    "gn:feature_code":"PPL",
    "gn:name":"Sinchon",
    "gn:population":0,
    "gn:timezone":"Asia/Seoul",
    "iso:country":"KR",
    "name:und_x_variant":[
        "\uc2e0\ucd0c",
        "Sinchon",
        "Sinch\u2019on"
    ],
    "wof:name":"Sinchon",
    "wof:placetype":"locality"
},
  "geometry": {"coordinates":[126.91522000000001,37.04371],"type":"Point"}
}