{
  "type": "Feature",
  "properties": {
    "gn:admin1_code":"20.0",
    "gn:asciiname":"Kwang-ni",
    "gn:country_code":"KR",
    "gn:dem":14,
    "gn:feature_class":"P",
    "gn:feature_code":"PPL",
    "gn:name":"Kwang-ni",
    "gn:population":0,
    "gn:timezone":"Asia/Seoul",
    "iso:country":"KR",
    "name:eng_x_preferred":[
        "Kwang"
    ],
    "name:eng_x_variant":[
        "Kwang-ni"
    ],
    "name:und_x_variant":[
        "\uad11\ub9ac",
        "Kwang-ni"
    ],
    "wof:name":"Kwang",
    "wof:placetype":"locality"
},
  "geometry": {"coordinates":[128.47502,34.87418],"type":"Point"}
}