{
  "type": "Feature",
  "properties": {
    "gn:admin1_code":"14.0",
    "gn:asciiname":"Cheongdomal",
    "gn:country_code":"KR",
    "gn:dem":198,
    "gn:feature_class":"P",
    "gn:feature_code":"PPL",
    "gn:name":"Cheongdomal",
    "gn:population":0,
    "gn:timezone":"Asia/Seoul",
    "iso:country":"KR",
    "name:kor_x_preferred":[
        "\uccad\ub3c4\ub9d0"
    ],
    "wof:name":"Cheongdomal",
    "wof:placetype":"locality"
},
  "geometry": {"coordinates":[129.14292,35.73735],"type":"Point"}
}