{
  "type": "Feature",
  "properties": {
    "gn:admin1_code":"6.0",
    "gn:asciiname":"Komjari",
    "gn:country_code":"KR",
    "gn:dem":668,
    "gn:feature_class":"P",
    "gn:feature_code":"PPL",
    "gn:name":"Komjari",
    "gn:population":0,
    "gn:timezone":"Asia/Seoul",
    "iso:country":"KR",
    "name:kor_x_preferred":[
        "\uacf0\uc790\ub9ac"
    ],
    "wof:name":"Komjari",
    "wof:placetype":"locality"
},
  "geometry": {"coordinates":[128.75970000000001,37.5906],"type":"Point"}
}