{
  "type": "Feature",
  "properties": {
    "gn:admin1_code":"18.0",
    "gn:asciiname":"Daeya",
    "gn:country_code":"KR",
    "gn:dem":50,
    "gn:feature_class":"P",
    "gn:feature_code":"PPL",
    "gn:name":"Daeya",
    "gn:population":0,
    "gn:timezone":"Asia/Seoul",
    "iso:country":"KR",
    "name:kor_x_preferred":[
        "\ub300\uc57c"
    ],
    "wof:name":"Daeya",
    "wof:placetype":"locality"
},
  "geometry": {"coordinates":[126.67298,35.13865999999999],"type":"Point"}
}