{
  "type": "Feature",
  "properties": {
    "gn:admin1_code":"6.0",
    "gn:asciiname":"Nambeorwon",
    "gn:country_code":"KR",
    "gn:dem":366,
    "gn:feature_class":"P",
    "gn:feature_code":"PPL",
    "gn:name":"Nambeorwon",
    "gn:population":0,
    "gn:timezone":"Asia/Seoul",
    "iso:country":"KR",
    "name:kor_x_preferred":[
        "\ub0a8\ubc8c\uc6d0"
    ],
    "name:und_x_variant":[
        "\ub0a8\ubd88\uc6d0",
        "Namburw\u014fn",
        "Nambeorwon"
    ],
    "wof:name":"Nambeorwon",
    "wof:placetype":"locality"
},
  "geometry": {"coordinates":[127.70278999999999,38.16969],"type":"Point"}
}