{
  "type": "Feature",
  "properties": {
    "gn:admin1_code":"6.0",
    "gn:asciiname":"Saoranggol",
    "gn:country_code":"KR",
    "gn:dem":253,
    "gn:feature_class":"P",
    "gn:feature_code":"PPL",
    "gn:name":"Saoranggol",
    "gn:population":0,
    "gn:timezone":"Asia/Seoul",
    "iso:country":"KR",
    "name:kor_x_preferred":[
        "\uc0ac\uc624\ub791"
    ],
    "name:kor_x_variant":[
        "\uc0ac\uc624\ub791\uace8"
    ],
    "name:und_x_variant":[
        "Saorang",
        "Saoranggol"
    ],
    "wof:name":"Saoranggol",
    "wof:placetype":"locality"
},
  "geometry": {"coordinates":[127.89134,37.87637],"type":"Point"}
}