{
  "type": "Feature",
  "properties": {
    "gn:admin1_code":"13.0",
    "gn:asciiname":"Kyesil-li",
    "gn:country_code":"KR",
    "gn:dem":49,
    "gn:feature_class":"P",
    "gn:feature_code":"PPLL",
    "gn:name":"Kyesil-li",
    "gn:population":0,
    "gn:timezone":"Asia/Seoul",
    "iso:country":"KR",
    "name:und_x_variant":[
        "\uacc4\uc2e0\ub9ac",
        "Gyesil-li",
        "Kyesil-li"
    ],
    "wof:name":"Kyesil-li",
    "wof:placetype":"locality"
},
  "geometry": {"coordinates":[127.52388999999999,37.37917],"type":"Point"}
}