{
  "type": "Feature",
  "properties": {
    "gn:admin1_code":"13.0",
    "gn:asciiname":"Nongpyeonmal",
    "gn:country_code":"KR",
    "gn:dem":37,
    "gn:feature_class":"P",
    "gn:feature_code":"PPL",
    "gn:name":"Nongpyeonmal",
    "gn:population":0,
    "gn:timezone":"Asia/Seoul",
    "iso:country":"KR",
    "name:kor_x_preferred":[
        "\ub18d\ud3b8\ub9d0"
    ],
    "wof:name":"Nongpyeonmal",
    "wof:placetype":"locality"
},
  "geometry": {"coordinates":[126.74131,37.75541],"type":"Point"}
}