{
  "type": "Feature",
  "properties": {
    "gn:admin1_code":"17.0",
    "gn:asciiname":"Oyatgoji",
    "gn:country_code":"KR",
    "gn:dem":70,
    "gn:feature_class":"P",
    "gn:feature_code":"PPL",
    "gn:name":"Oyatgoji",
    "gn:population":0,
    "gn:timezone":"Asia/Seoul",
    "iso:country":"KR",
    "name:kor_x_preferred":[
        "\uc624\uc58f\uace0\uc9c0"
    ],
    "wof:name":"Oyatgoji",
    "wof:placetype":"locality"
},
  "geometry": {"coordinates":[127.20211999999999,36.67365],"type":"Point"}
}