{
  "type": "Feature",
  "properties": {
    "gn:admin1_code":"14.0",
    "gn:asciiname":"Araennult'i",
    "gn:country_code":"KR",
    "gn:dem":369,
    "gn:feature_class":"P",
    "gn:feature_code":"PPL",
    "gn:name":"Araenn\u016dlt\u2019i",
    "gn:population":0,
    "gn:timezone":"Asia/Seoul",
    "iso:country":"KR",
    "wof:name":"Araennult'i",
    "wof:placetype":"locality"
},
  "geometry": {"coordinates":[127.90111,36.58639],"type":"Point"}
}