{
  "type": "Feature",
  "properties": {
    "gn:admin1_code":"20.0",
    "gn:asciiname":"Jifuho",
    "gn:country_code":"KR",
    "gn:dem":-9999,
    "gn:feature_class":"P",
    "gn:feature_code":"PPL",
    "gn:name":"Jifuho",
    "gn:population":0,
    "gn:timezone":"Asia/Seoul",
    "iso:country":"KR",
    "name:und_x_variant":[
        "Chabup\u2019o"
    ],
    "wof:name":"Jifuho",
    "wof:placetype":"locality"
},
  "geometry": {"coordinates":[128.26667,34.63333],"type":"Point"}
}