{
  "type": "Feature",
  "properties": {
    "gn:admin1_code":"16.0",
    "gn:asciiname":"Jukdong",
    "gn:country_code":"KR",
    "gn:dem":89,
    "gn:feature_class":"P",
    "gn:feature_code":"PPL",
    "gn:name":"Jukdong",
    "gn:population":0,
    "gn:timezone":"Asia/Seoul",
    "iso:country":"KR",
    "name:kor_x_preferred":[
        "\uc8fd\ub3d9"
    ],
    "name:und_x_variant":[
        "Chuk-tong"
    ],
    "wof:name":"Jukdong",
    "wof:placetype":"locality"
},
  "geometry": {"coordinates":[126.90937,34.95341],"type":"Point"}
}