{
  "type": "Feature",
  "properties": {
    "gn:admin1_code":"16.0",
    "gn:asciiname":"Juryeong",
    "gn:country_code":"KR",
    "gn:dem":135,
    "gn:feature_class":"P",
    "gn:feature_code":"PPL",
    "gn:name":"Juryeong",
    "gn:population":0,
    "gn:timezone":"Asia/Seoul",
    "iso:country":"KR",
    "name:kor_x_preferred":[
        "\uc8fc\ub839"
    ],
    "name:und_x_variant":[
        "Chury\u014fng"
    ],
    "wof:name":"Juryeong",
    "wof:placetype":"locality"
},
  "geometry": {"coordinates":[127.55141999999999,34.96823],"type":"Point"}
}