{
  "type": "Feature",
  "properties": {
    "gn:admin1_code":"5.0",
    "gn:asciiname":"Witbanjeong",
    "gn:country_code":"KR",
    "gn:dem":175,
    "gn:feature_class":"P",
    "gn:feature_code":"PPL",
    "gn:name":"Witbanjeong",
    "gn:population":0,
    "gn:timezone":"Asia/Seoul",
    "iso:country":"KR",
    "name:kor_x_preferred":[
        "\uc717\ubc18\uc815"
    ],
    "wof:name":"Witbanjeong",
    "wof:placetype":"locality"
},
  "geometry": {"coordinates":[128.17740000000001,37.07678],"type":"Point"}
}