{
  "type": "Feature",
  "properties": {
    "gn:admin1_code":"6.0",
    "gn:asciiname":"Eoyeong-gol",
    "gn:country_code":"KR",
    "gn:dem":245,
    "gn:feature_class":"P",
    "gn:feature_code":"PPL",
    "gn:name":"Eoyeong-gol",
    "gn:population":0,
    "gn:timezone":"Asia/Seoul",
    "iso:country":"KR",
    "name:kor_x_preferred":[
        "\uc5b4\uc601\uace8"
    ],
    "name:kor_x_variant":[
        "\u014ey\u014fng-gol"
    ],
    "wof:name":"Eoyeong-gol",
    "wof:placetype":"locality"
},
  "geometry": {"coordinates":[127.82138999999999,38.04139],"type":"Point"}
}