{
  "type": "Feature",
  "properties": {
    "gn:admin1_code":"6.0",
    "gn:asciiname":"Chagun'gal-gol",
    "gn:country_code":"KR",
    "gn:dem":325,
    "gn:feature_class":"P",
    "gn:feature_code":"PPL",
    "gn:name":"Chag\u016dn\u2019gal-gol",
    "gn:population":0,
    "gn:timezone":"Asia/Seoul",
    "iso:country":"KR",
    "name:kor_x_preferred":[
        "\uc791\uc740\uac08\uace8"
    ],
    "name:kor_x_variant":[
        "Chag\u016dn\u2019gal-gol"
    ],
    "wof:name":"Chagun'gal-gol",
    "wof:placetype":"locality"
},
  "geometry": {"coordinates":[128.38919999999999,37.2809],"type":"Point"}
}