{
  "type": "Feature",
  "properties": {
    "gn:admin1_code":"17.0",
    "gn:asciiname":"Tolmok",
    "gn:country_code":"KR",
    "gn:dem":171,
    "gn:feature_class":"P",
    "gn:feature_code":"PPL",
    "gn:name":"Tolmok",
    "gn:population":0,
    "gn:timezone":"Asia/Seoul",
    "iso:country":"KR",
    "name:und_x_variant":[
        "S\u014fkhang"
    ],
    "wof:name":"Tolmok",
    "wof:placetype":"locality"
},
  "geometry": {"coordinates":[127.31667,36.85],"type":"Point"}
}