{
  "type": "Feature",
  "properties": {
    "gn:admin1_code":"16.0",
    "gn:asciiname":"Yeongjeon",
    "gn:country_code":"KR",
    "gn:dem":8,
    "gn:feature_class":"P",
    "gn:feature_code":"PPL",
    "gn:name":"Yeongjeon",
    "gn:population":0,
    "gn:timezone":"Asia/Seoul",
    "iso:country":"KR",
    "name:kor_x_preferred":[
        "Y\u014fngj\u014fn"
    ],
    "name:kor_x_variant":[
        "\uc601\uc804"
    ],
    "wof:name":"Yeongjeon",
    "wof:placetype":"locality"
},
  "geometry": {"coordinates":[126.59332999999999,34.33944],"type":"Point"}
}