{
  "type": "Feature",
  "properties": {
    "gn:admin1_code":"6.0",
    "gn:asciiname":"Nonsal-li",
    "gn:cc2":"KR",
    "gn:country_code":"KR",
    "gn:dem":34,
    "gn:feature_class":"P",
    "gn:feature_code":"PPL",
    "gn:name":"Nonsal-li",
    "gn:population":0,
    "gn:timezone":"Asia/Seoul",
    "iso:country":"KR",
    "name:kor_x_preferred":[
        "\ub17c\uc0b0\ub9ac"
    ],
    "name:und_x_variant":[
        "Nonsan-ni",
        "Nonsal-li"
    ],
    "wof:name":"Nonsal-li",
    "wof:placetype":"locality"
},
  "geometry": {"coordinates":[128.58250000000001,38.18694],"type":"Point"}
}