{
  "type": "Feature",
  "properties": {
    "gn:admin1_code":"6.0",
    "gn:asciiname":"Hagya-ri",
    "gn:country_code":"KR",
    "gn:dem":61,
    "gn:feature_class":"P",
    "gn:feature_code":"PPL",
    "gn:name":"Hagya-ri",
    "gn:population":0,
    "gn:timezone":"Asia/Seoul",
    "iso:country":"KR",
    "name:kor_x_preferred":[
        "\ud559\uc57c\ub9ac"
    ],
    "wof:name":"Hagya-ri",
    "wof:placetype":"locality"
},
  "geometry": {"coordinates":[128.50056000000001,38.28556],"type":"Point"}
}