{
  "type": "Feature",
  "properties": {
    "gn:admin1_code":"12.0",
    "gn:admin2_code":"Kanghwa-gun",
    "gn:asciiname":"Kosong-dong",
    "gn:country_code":"KR",
    "gn:dem":27,
    "gn:feature_class":"P",
    "gn:feature_code":"PPL",
    "gn:name":"Kos\u014fng-dong",
    "gn:population":0,
    "gn:timezone":"Asia/Seoul",
    "iso:country":"KR",
    "wof:name":"Kosong-dong",
    "wof:placetype":"locality"
},
  "geometry": {"coordinates":[126.50388999999998,37.77111],"type":"Point"}
}