{
  "type": "Feature",
  "properties": {
    "gn:admin1_code":"17.0",
    "gn:asciiname":"Karijong-gol",
    "gn:country_code":"KR",
    "gn:dem":173,
    "gn:feature_class":"P",
    "gn:feature_code":"PPL",
    "gn:name":"Karij\u014fng-gol",
    "gn:population":0,
    "gn:timezone":"Asia/Seoul",
    "iso:country":"KR",
    "name:und_x_variant":[
        "\uac00\ub9ac\uc815\uace8",
        "Karij\u014fng-gol"
    ],
    "wof:name":"Karijong-gol",
    "wof:placetype":"locality"
},
  "geometry": {"coordinates":[126.71769999999999,36.2699],"type":"Point"}
}