{
  "type": "Feature",
  "properties": {
    "gn:admin1_code":"14.0",
    "gn:asciiname":"Beombawi",
    "gn:country_code":"KR",
    "gn:dem":201,
    "gn:feature_class":"P",
    "gn:feature_code":"PPL",
    "gn:name":"Beombawi",
    "gn:population":0,
    "gn:timezone":"Asia/Seoul",
    "iso:country":"KR",
    "name:kor_x_preferred":[
        "\ubc94\ubc14\uc704"
    ],
    "wof:name":"Beombawi",
    "wof:placetype":"locality"
},
  "geometry": {"coordinates":[128.78246999999999,36.73869000000001],"type":"Point"}
}