{
  "type": "Feature",
  "properties": {
    "gn:admin1_code":"13.0",
    "gn:asciiname":"Song-ni",
    "gn:country_code":"KR",
    "gn:dem":46,
    "gn:feature_class":"P",
    "gn:feature_code":"PPLL",
    "gn:name":"Song-ni",
    "gn:population":0,
    "gn:timezone":"Asia/Seoul",
    "iso:country":"KR",
    "name:und_x_variant":[
        "\uc1a1\ub9ac",
        "Song-ri",
        "Song-ni"
    ],
    "wof:name":"Song-ni",
    "wof:placetype":"locality"
},
  "geometry": {"coordinates":[127.10193999999998,37.16194],"type":"Point"}
}