{
  "type": "Feature",
  "properties": {
    "gn:admin1_code":"17.0",
    "gn:asciiname":"Osa",
    "gn:country_code":"KR",
    "gn:dem":42,
    "gn:feature_class":"P",
    "gn:feature_code":"PPL",
    "gn:name":"Osa",
    "gn:population":0,
    "gn:timezone":"Asia/Seoul",
    "iso:country":"KR",
    "name:bul_x_preferred":[
        "\u041e\u0441\u0430"
    ],
    "name:ceb_x_preferred":[
        "Osa"
    ],
    "name:ces_x_preferred":[
        "Osa"
    ],
    "name:est_x_preferred":[
        "Osa"
    ],
    "name:hrv_x_preferred":[
        "Osa"
    ],
    "name:hun_x_preferred":[
        "Osza"
    ],
    "name:hye_x_preferred":[
        "\u0555\u057d\u0561"
    ],
    "name:nld_x_preferred":[
        "Osa"
    ],
    "name:nno_x_preferred":[
        "Osa"
    ],
    "name:nor_x_preferred":[
        "Osa"
    ],
    "name:pol_x_preferred":[
        "Osa"
    ],
    "name:por_x_preferred":[
        "Osa"
    ],
    "name:rus_x_preferred":[
        "\u041e\u0441\u0430"
    ],
    "name:slk_x_preferred":[
        "Osa"
    ],
    "name:spa_x_preferred":[
        "Osa"
    ],
    "name:srp_x_preferred":[
        "\u041e\u0441\u0430"
    ],
    "name:ukr_x_preferred":[
        "\u041e\u0441\u0430"
    ],
    "name:und_x_variant":[
        "Osa-ri",
        "\uc624\uc0ac"
    ],
    "wof:name":"Osa",
    "wof:placetype":"locality"
},
  "geometry": {"coordinates":[126.7518,36.9463],"type":"Point"}
}