{
  "type": "Feature",
  "properties": {
    "gn:admin1_code":"17.0",
    "gn:asciiname":"Osa",
    "gn:country_code":"KR",
    "gn:dem":42,
    "gn:feature_class":"P",
    "gn:feature_code":"PPL",
    "gn:name":"Osa",
    "gn:population":0,
    "gn:timezone":"Asia/Seoul",
    "iso:country":"KR",
    "name:und_x_variant":[
        "Osa-ri",
        "\uc624\uc0ac",
        "Osa"
    ],
    "wof:name":"Osa",
    "wof:placetype":"locality"
},
  "geometry": {"coordinates":[126.7518,36.9463],"type":"Point"}
}