{
  "type": "Feature",
  "properties": {
    "gn:admin1_code":"5.0",
    "gn:asciiname":"Sinyeoul",
    "gn:country_code":"KR",
    "gn:dem":40,
    "gn:feature_class":"P",
    "gn:feature_code":"PPL",
    "gn:name":"Sinyeoul",
    "gn:population":0,
    "gn:timezone":"Asia/Seoul",
    "iso:country":"KR",
    "name:kor_x_preferred":[
        "\uc2e0\uc5ec\uc6b8"
    ],
    "wof:name":"Sinyeoul",
    "wof:placetype":"locality"
},
  "geometry": {"coordinates":[127.48436,36.7282],"type":"Point"}
}