{
  "type": "Feature",
  "properties": {
    "gn:admin1_code":"13.0",
    "gn:admin2_code":"P'aju-si",
    "gn:asciiname":"Yaksangol",
    "gn:country_code":"KR",
    "gn:dem":26,
    "gn:feature_class":"P",
    "gn:feature_code":"PPL",
    "gn:name":"Yaksangol",
    "gn:population":0,
    "gn:timezone":"Asia/Seoul",
    "iso:country":"KR",
    "name:kor_x_preferred":[
        "\uc57d\uc0b0\uace8"
    ],
    "name:und_x_variant":[
        "Aksang-gol"
    ],
    "wof:name":"Yaksangol",
    "wof:placetype":"locality"
},
  "geometry": {"coordinates":[126.69811,37.77169],"type":"Point"}
}