{
  "type": "Feature",
  "properties": {
    "gn:admin1_code":"0.0",
    "gn:asciiname":"Sumundong",
    "gn:country_code":"KR",
    "gn:dem":30,
    "gn:feature_class":"P",
    "gn:feature_code":"PPL",
    "gn:name":"Sumundong",
    "gn:population":0,
    "gn:timezone":"Asia/Seoul",
    "iso:country":"KR",
    "name:kor_x_preferred":[
        "\uc218\ubb38\ub3d9"
    ],
    "wof:name":"Sumundong",
    "wof:placetype":"locality"
},
  "geometry": {"coordinates":[127.59229999999999,34.65264000000001],"type":"Point"}
}