{
  "type": "Feature",
  "properties": {
    "gn:admin1_code":"17.0",
    "gn:asciiname":"Tolgogae",
    "gn:country_code":"KR",
    "gn:dem":188,
    "gn:feature_class":"P",
    "gn:feature_code":"PPL",
    "gn:name":"Tolgogae",
    "gn:population":0,
    "gn:timezone":"Asia/Seoul",
    "iso:country":"KR",
    "name:und_x_variant":[
        "\ub3cc\uace0\uac1c",
        "Tolgogae"
    ],
    "wof:name":"Tolgogae",
    "wof:placetype":"locality"
},
  "geometry": {"coordinates":[127.46339999999999,36.1467],"type":"Point"}
}