{
  "type": "Feature",
  "properties": {
    "gn:admin1_code":"20.0",
    "gn:asciiname":"Chogyang",
    "gn:cc2":"KR",
    "gn:country_code":"KR",
    "gn:dem":14,
    "gn:feature_class":"P",
    "gn:feature_code":"PPL",
    "gn:name":"Ch\u014fgyang",
    "gn:population":0,
    "gn:timezone":"Asia/Seoul",
    "iso:country":"KR",
    "name:und_x_variant":[
        "Ch\u014fngyang",
        "Ch\u014fngnyang",
        "Ch\u014fngyang-ni",
        "Ch\u014fgyang"
    ],
    "wof:name":"Chogyang",
    "wof:placetype":"locality"
},
  "geometry": {"coordinates":[128.06,34.86111],"type":"Point"}
}