{
  "type": "Feature",
  "properties": {
    "gn:admin1_code":"16.0",
    "gn:asciiname":"Piha",
    "gn:country_code":"KR",
    "gn:dem":11,
    "gn:feature_class":"P",
    "gn:feature_code":"PPL",
    "gn:name":"Piha",
    "gn:population":0,
    "gn:timezone":"Asia/Seoul",
    "iso:country":"KR",
    "name:deu_x_preferred":[
        "Piha"
    ],
    "name:fin_x_preferred":[
        "Piha"
    ],
    "name:nld_x_preferred":[
        "Piha"
    ],
    "name:nor_x_preferred":[
        "Piha"
    ],
    "name:rus_x_preferred":[
        "\u041f\u0438\u0445\u0430"
    ],
    "wof:name":"Piha",
    "wof:placetype":"locality"
},
  "geometry": {"coordinates":[126.88611000000002,34.45722],"type":"Point"}
}