{
  "type": "Feature",
  "properties": {
    "gn:admin1_code":"17.0",
    "gn:asciiname":"Pamgalmi",
    "gn:country_code":"KR",
    "gn:dem":20,
    "gn:feature_class":"P",
    "gn:feature_code":"PPL",
    "gn:name":"Pamgalmi",
    "gn:population":0,
    "gn:timezone":"Asia/Seoul",
    "iso:country":"KR",
    "name:und_x_variant":[
        "\ubc24\uac08\ubbf8",
        "Pamgalmi"
    ],
    "wof:name":"Pamgalmi",
    "wof:placetype":"locality"
},
  "geometry": {"coordinates":[126.8591,36.3481],"type":"Point"}
}