{
  "type": "Feature",
  "properties": {
    "gn:admin1_code":"6.0",
    "gn:asciiname":"Parigogae",
    "gn:country_code":"KR",
    "gn:dem":158,
    "gn:feature_class":"P",
    "gn:feature_code":"PPL",
    "gn:name":"Parigogae",
    "gn:population":0,
    "gn:timezone":"Asia/Seoul",
    "iso:country":"KR",
    "name:und_x_variant":[
        "\ubc1c\uc774\uace0\uac1c",
        "Parigogae"
    ],
    "wof:name":"Parigogae",
    "wof:placetype":"locality"
},
  "geometry": {"coordinates":[129.06710000000001,37.2901],"type":"Point"}
}