{
  "type": "Feature",
  "properties": {
    "gn:admin1_code":"14.0",
    "gn:asciiname":"Ch'onbei",
    "gn:country_code":"KR",
    "gn:dem":128,
    "gn:feature_class":"P",
    "gn:feature_code":"PPL",
    "gn:name":"Ch\u2019\u014fnbei",
    "gn:population":0,
    "gn:timezone":"Asia/Seoul",
    "iso:country":"KR",
    "name:und_x_variant":[
        "\ucc9c\ubca0\uc774",
        "Ch\u2019\u014fnbei"
    ],
    "wof:name":"Ch'onbei",
    "wof:placetype":"locality"
},
  "geometry": {"coordinates":[128.18823999999998,35.82842],"type":"Point"}
}