{
  "type": "Feature",
  "properties": {
    "gn:admin1_code":"13.0",
    "gn:asciiname":"Bangogae",
    "gn:country_code":"KR",
    "gn:dem":32,
    "gn:feature_class":"P",
    "gn:feature_code":"PPL",
    "gn:name":"Bangogae",
    "gn:population":0,
    "gn:timezone":"Asia/Seoul",
    "iso:country":"KR",
    "name:und_x_variant":[
        "\ubc18\uace0\uac1c",
        "Bangogae",
        "Pan\u2019gogae"
    ],
    "wof:name":"Bangogae",
    "wof:placetype":"locality"
},
  "geometry": {"coordinates":[126.95361,37.22361],"type":"Point"}
}