{
  "type": "Feature",
  "properties": {
    "gn:admin1_code":"20.0",
    "gn:asciiname":"Sinun",
    "gn:country_code":"KR",
    "gn:dem":25,
    "gn:feature_class":"P",
    "gn:feature_code":"PPL",
    "gn:name":"Sin\u016dn",
    "gn:population":0,
    "gn:timezone":"Asia/Seoul",
    "iso:country":"KR",
    "name:ara_x_preferred":[
        "\u0633\u0646\u0648\u0646\u064a"
    ],
    "name:deu_x_preferred":[
        "Sinun"
    ],
    "name:und_x_variant":[
        "\uc2e0\uc740",
        "Sin\u016dn"
    ],
    "wof:name":"Sinun",
    "wof:placetype":"locality"
},
  "geometry": {"coordinates":[128.36098999999999,34.97408],"type":"Point"}
}