{
  "type": "Feature",
  "properties": {
    "gn:admin1_code":"13.0",
    "gn:asciiname":"Sirat",
    "gn:country_code":"KR",
    "gn:dem":113,
    "gn:feature_class":"P",
    "gn:feature_code":"PPL",
    "gn:name":"Sirat",
    "gn:population":0,
    "gn:timezone":"Asia/Seoul",
    "iso:country":"KR",
    "name:ara_x_preferred":[
        "\u0633\u064a\u0631\u0627\u062a"
    ],
    "name:azb_x_preferred":[
        "\u0633\u06cc\u0631\u0627\u062a"
    ],
    "name:fas_x_preferred":[
        "\u0633\u06cc\u0631\u0627\u062a"
    ],
    "name:fra_x_preferred":[
        "Sirat"
    ],
    "name:ita_x_preferred":[
        "Sirat"
    ],
    "name:msa_x_preferred":[
        "Sirat"
    ],
    "name:por_x_preferred":[
        "Sirat"
    ],
    "name:ron_x_preferred":[
        "Sirat"
    ],
    "name:spa_x_preferred":[
        "Sirat"
    ],
    "name:und_x_variant":[
        "\uc2dc\ub78f",
        "Sirat"
    ],
    "name:vie_x_preferred":[
        "Sirat"
    ],
    "wof:name":"Sirat",
    "wof:placetype":"locality"
},
  "geometry": {"coordinates":[127.49083,37.36528],"type":"Point"}
}