{
  "type": "Feature",
  "properties": {
    "iso:country":"KR",
    "name:eng_x_preferred":[
        "Osan-myeon"
    ],
    "name:kor_x_preferred":[
        "\uc624\uc0b0\uba74"
    ],
    "qs:name":"\uc624\uc0b0\uba74",
    "qs:name_adm0":"\ud55c\uad6d",
    "qs:name_adm1":"\uc804\ub77c\ubd81\ub3c4",
    "qs:photos":1,
    "qs:photos_1k":1,
    "qs:photos_9k":1,
    "qs:photos_9r":1,
    "qs:photos_all":1,
    "qs:photos_sr":1,
    "qs:placetype":"LocalAdmin",
    "qs:pop_sr":"0",
    "wof:name":"Osan-myeon",
    "wof:placetype":"localadmin"
},
  "geometry": {"coordinates":[126.933288,35.959111],"type":"Point"}
}