{
  "type": "Feature",
  "properties": {
    "gn:admin1_code":"13.0",
    "gn:asciiname":"Punggok",
    "gn:country_code":"KR",
    "gn:dem":28,
    "gn:feature_class":"P",
    "gn:feature_code":"PPL",
    "gn:name":"Punggok",
    "gn:population":0,
    "gn:timezone":"Asia/Seoul",
    "iso:country":"KR",
    "name:kor_x_preferred":[
        "\ud48d\uace1"
    ],
    "name:kor_x_variant":[
        "P\u2019unggok"
    ],
    "wof:name":"Punggok",
    "wof:placetype":"locality"
},
  "geometry": {"coordinates":[126.75803000000001,37.60888],"type":"Point"}
}