{
  "type": "Feature",
  "properties": {
    "gn:admin1_code":"14.0",
    "gn:asciiname":"Chidong-gol",
    "gn:country_code":"KR",
    "gn:dem":153,
    "gn:feature_class":"P",
    "gn:feature_code":"PPL",
    "gn:name":"Chidong-gol",
    "gn:population":0,
    "gn:timezone":"Asia/Seoul",
    "iso:country":"KR",
    "name:und_x_variant":[
        "\uc9c0\ub3d9\uace8",
        "Chidong-gol"
    ],
    "wof:name":"Chidong-gol",
    "wof:placetype":"locality"
},
  "geometry": {"coordinates":[128.7157,36.4598],"type":"Point"}
}