{
  "type": "Feature",
  "properties": {
    "gn:admin1_code":"14.0",
    "gn:asciiname":"Opyeong",
    "gn:country_code":"KR",
    "gn:dem":210,
    "gn:feature_class":"P",
    "gn:feature_code":"PPL",
    "gn:name":"Opyeong",
    "gn:population":0,
    "gn:timezone":"Asia/Seoul",
    "iso:country":"KR",
    "name:kor_x_preferred":[
        "\uc624\ud3c9"
    ],
    "wof:name":"Opyeong",
    "wof:placetype":"locality"
},
  "geometry": {"coordinates":[128.9288,36.71701],"type":"Point"}
}