{
  "type": "Feature",
  "properties": {
    "gn:admin1_code":"14.0",
    "gn:asciiname":"Deokhyeon",
    "gn:country_code":"KR",
    "gn:dem":386,
    "gn:feature_class":"P",
    "gn:feature_code":"PPL",
    "gn:name":"Deokhyeon",
    "gn:population":0,
    "gn:timezone":"Asia/Seoul",
    "iso:country":"KR",
    "name:kor_x_preferred":[
        "\ub355\ud604"
    ],
    "wof:name":"Deokhyeon",
    "wof:placetype":"locality"
},
  "geometry": {"coordinates":[128.55496000000002,36.94966],"type":"Point"}
}