{
  "type": "Feature",
  "properties": {
    "gn:admin1_code":"5.0",
    "gn:asciiname":"Saemgol",
    "gn:country_code":"KR",
    "gn:dem":255,
    "gn:feature_class":"P",
    "gn:feature_code":"PPL",
    "gn:name":"Saemgol",
    "gn:population":0,
    "gn:timezone":"Asia/Seoul",
    "iso:country":"KR",
    "name:kor_x_preferred":[
        "\uc0d8\uace8"
    ],
    "wof:name":"Saemgol",
    "wof:placetype":"locality"
},
  "geometry": {"coordinates":[127.65226,36.65065],"type":"Point"}
}