{
  "type": "Feature",
  "properties": {
    "gn:admin1_code":"17.0",
    "gn:asciiname":"Paksalmoe",
    "gn:country_code":"KR",
    "gn:dem":136,
    "gn:feature_class":"P",
    "gn:feature_code":"PPL",
    "gn:name":"Paksalmoe",
    "gn:population":0,
    "gn:timezone":"Asia/Seoul",
    "iso:country":"KR",
    "name:und_x_variant":[
        "\ubc15\uc0b4\ubafc",
        "Paksalmoe"
    ],
    "wof:name":"Paksalmoe",
    "wof:placetype":"locality"
},
  "geometry": {"coordinates":[126.68899999999999,36.4226],"type":"Point"}
}