{
  "type": "Feature",
  "properties": {
    "gn:admin1_code":"16.0",
    "gn:asciiname":"Daechun",
    "gn:country_code":"KR",
    "gn:dem":24,
    "gn:feature_class":"P",
    "gn:feature_code":"PPL",
    "gn:name":"Daechun",
    "gn:population":0,
    "gn:timezone":"Asia/Seoul",
    "iso:country":"KR",
    "name:kor_x_preferred":[
        "\ub300\ucd98"
    ],
    "name:kor_x_variant":[
        "Taech\u2019un"
    ],
    "wof:name":"Daechun",
    "wof:placetype":"locality"
},
  "geometry": {"coordinates":[127.37411000000002,34.65753],"type":"Point"}
}