{
  "type": "Feature",
  "properties": {
    "gn:admin1_code":"14.0",
    "gn:asciiname":"Gwasangol",
    "gn:country_code":"KR",
    "gn:dem":182,
    "gn:feature_class":"P",
    "gn:feature_code":"PPL",
    "gn:name":"Gwasangol",
    "gn:population":0,
    "gn:timezone":"Asia/Seoul",
    "iso:country":"KR",
    "name:kor_x_preferred":[
        "\uacfc\uc0b0\uace8"
    ],
    "wof:name":"Gwasangol",
    "wof:placetype":"locality"
},
  "geometry": {"coordinates":[128.43582000000001,36.74312000000001],"type":"Point"}
}