{
  "type": "Feature",
  "properties": {
    "gn:admin1_code":"20.0",
    "gn:asciiname":"Yangjeonggol",
    "gn:country_code":"KR",
    "gn:dem":4,
    "gn:feature_class":"P",
    "gn:feature_code":"PPL",
    "gn:name":"Yangjeonggol",
    "gn:population":0,
    "gn:timezone":"Asia/Seoul",
    "iso:country":"KR",
    "name:kor_x_preferred":[
        "\uc591\uc815\uace8"
    ],
    "wof:name":"Yangjeonggol",
    "wof:placetype":"locality"
},
  "geometry": {"coordinates":[128.92896999999999,35.22261],"type":"Point"}
}