{
  "type": "Feature",
  "properties": {
    "gn:admin1_code":"17.0",
    "gn:asciiname":"Sonyu-gol",
    "gn:country_code":"KR",
    "gn:dem":94,
    "gn:feature_class":"P",
    "gn:feature_code":"PPL",
    "gn:name":"S\u014fnyu-gol",
    "gn:population":0,
    "gn:timezone":"Asia/Seoul",
    "iso:country":"KR",
    "name:und_x_variant":[
        "\uc120\uc720\uace8",
        "S\u014fnyu-gol"
    ],
    "wof:name":"Sonyu-gol",
    "wof:placetype":"locality"
},
  "geometry": {"coordinates":[126.67829999999999,36.4048],"type":"Point"}
}