{
  "type": "Feature",
  "properties": {
    "gn:admin1_code":"3.0",
    "gn:asciiname":"Sungch'irimokpang",
    "gn:country_code":"KR",
    "gn:dem":148,
    "gn:feature_class":"P",
    "gn:feature_code":"PPL",
    "gn:name":"S\u016dngch\u2019irim\u014fkpang",
    "gn:population":0,
    "gn:timezone":"Asia/Seoul",
    "iso:country":"KR",
    "name:und_x_variant":[
        "\uc2b9\uce58\ub9ac\uba39\ubc29",
        "S\u016dngch\u2019irim\u014fkpang"
    ],
    "wof:name":"Sungch'irimokpang",
    "wof:placetype":"locality"
},
  "geometry": {"coordinates":[127.2204,36.0759],"type":"Point"}
}