{
  "type": "Feature",
  "properties": {
    "gn:admin1_code":"16.0",
    "gn:asciiname":"Gureumtteok",
    "gn:country_code":"KR",
    "gn:dem":44,
    "gn:feature_class":"P",
    "gn:feature_code":"PPL",
    "gn:name":"Gureumtteok",
    "gn:population":0,
    "gn:timezone":"Asia/Seoul",
    "iso:country":"KR",
    "name:kor_x_preferred":[
        "\uad6c\ub984\ub5a1"
    ],
    "wof:name":"Gureumtteok",
    "wof:placetype":"locality"
},
  "geometry": {"coordinates":[126.73574000000001,35.26064],"type":"Point"}
}