{
  "type": "Feature",
  "properties": {
    "gn:admin1_code":"6.0",
    "gn:asciiname":"Saem-gol",
    "gn:country_code":"KR",
    "gn:dem":670,
    "gn:feature_class":"P",
    "gn:feature_code":"PPL",
    "gn:name":"Saem-gol",
    "gn:population":0,
    "gn:timezone":"Asia/Seoul",
    "iso:country":"KR",
    "wof:name":"Saem-gol",
    "wof:placetype":"locality"
},
  "geometry": {"coordinates":[128.47971999999999,37.83361],"type":"Point"}
}