{
  "type": "Feature",
  "properties": {
    "gn:admin1_code":"20.0",
    "gn:asciiname":"Iyangji",
    "gn:country_code":"KR",
    "gn:dem":3,
    "gn:feature_class":"P",
    "gn:feature_code":"PPL",
    "gn:name":"Iyangji",
    "gn:population":0,
    "gn:timezone":"Asia/Seoul",
    "iso:country":"KR",
    "name:kor_x_preferred":[
        "\uc774\uc591\uc9c0"
    ],
    "wof:name":"Iyangji",
    "wof:placetype":"locality"
},
  "geometry": {"coordinates":[128.85881000000001,35.19017],"type":"Point"}
}