{
  "type": "Feature",
  "properties": {
    "gn:admin1_code":"13.0",
    "gn:asciiname":"Paseong",
    "gn:country_code":"KR",
    "gn:dem":66,
    "gn:feature_class":"P",
    "gn:feature_code":"PPL",
    "gn:name":"Paseong",
    "gn:population":0,
    "gn:timezone":"Asia/Seoul",
    "iso:country":"KR",
    "name:und_x_variant":[
        "\ud30c\uc131",
        "Paseong",
        "P\u2019as\u014fng"
    ],
    "wof:name":"Paseong",
    "wof:placetype":"locality"
},
  "geometry": {"coordinates":[127.55361000000001,37.40722],"type":"Point"}
}