{
  "type": "Feature",
  "properties": {
    "gn:admin1_code":"17.0",
    "gn:asciiname":"Witsanmakgol",
    "gn:country_code":"KR",
    "gn:dem":62,
    "gn:feature_class":"P",
    "gn:feature_code":"PPL",
    "gn:name":"Witsanmakgol",
    "gn:population":0,
    "gn:timezone":"Asia/Seoul",
    "iso:country":"KR",
    "name:kor_x_preferred":[
        "\uc717\uc0b0\ub9c9\uace8"
    ],
    "wof:name":"Witsanmakgol",
    "wof:placetype":"locality"
},
  "geometry": {"coordinates":[127.01658999999999,36.73635],"type":"Point"}
}