{
  "type": "Feature",
  "properties": {
    "gn:admin1_code":"13.0",
    "gn:asciiname":"Keungail",
    "gn:country_code":"KR",
    "gn:dem":26,
    "gn:feature_class":"P",
    "gn:feature_code":"PPL",
    "gn:name":"Keungail",
    "gn:population":0,
    "gn:timezone":"Asia/Seoul",
    "iso:country":"KR",
    "name:kor_x_preferred":[
        "\ud070\uac00\uc77c"
    ],
    "wof:name":"Keungail",
    "wof:placetype":"locality"
},
  "geometry": {"coordinates":[126.81249,37.44346],"type":"Point"}
}