{
  "type": "Feature",
  "properties": {
    "gn:admin1_code":"17.0",
    "gn:asciiname":"Taegong-ni",
    "gn:country_code":"KR",
    "gn:dem":166,
    "gn:feature_class":"P",
    "gn:feature_code":"PPL",
    "gn:name":"Taegong-ni",
    "gn:population":0,
    "gn:timezone":"Asia/Seoul",
    "iso:country":"KR",
    "wof:name":"Taegong-ni",
    "wof:placetype":"locality"
},
  "geometry": {"coordinates":[126.91667,36.66667],"type":"Point"}
}