{
  "type": "Feature",
  "properties": {
    "gn:admin1_code":"14.0",
    "gn:asciiname":"Minori",
    "gn:country_code":"KR",
    "gn:dem":329,
    "gn:feature_class":"P",
    "gn:feature_code":"PPL",
    "gn:name":"Minori",
    "gn:population":0,
    "gn:timezone":"Asia/Seoul",
    "iso:country":"KR",
    "name:kor_x_preferred":[
        "\ubbf8\ub178\ub9ac"
    ],
    "name:und_x_variant":[
        "Miro-ri"
    ],
    "wof:name":"Minori",
    "wof:placetype":"locality"
},
  "geometry": {"coordinates":[128.04706999999999,36.67218],"type":"Point"}
}