{
  "type": "Feature",
  "properties": {
    "gn:admin1_code":"14.0",
    "gn:asciiname":"Muduru",
    "gn:country_code":"KR",
    "gn:dem":145,
    "gn:feature_class":"P",
    "gn:feature_code":"PPL",
    "gn:name":"Muduru",
    "gn:population":0,
    "gn:timezone":"Asia/Seoul",
    "iso:country":"KR",
    "name:und_x_variant":[
        "Mud\u016dl-li",
        "\ubb34\ub4dc\ub9ac",
        "Mud\u016d-ri"
    ],
    "wof:name":"Muduru",
    "wof:placetype":"locality"
},
  "geometry": {"coordinates":[128.04660000000001,36.4688],"type":"Point"}
}