{
  "type": "Feature",
  "properties": {
    "gn:admin1_code":"21.0",
    "gn:asciiname":"Hahoe",
    "gn:country_code":"KR",
    "gn:dem":7,
    "gn:feature_class":"P",
    "gn:feature_code":"PPL",
    "gn:name":"Hahoe",
    "gn:population":0,
    "gn:timezone":"Asia/Seoul",
    "iso:country":"KR",
    "name:kor_x_preferred":[
        "\ud558\ud68c"
    ],
    "wof:name":"Hahoe",
    "wof:placetype":"locality"
},
  "geometry": {"coordinates":[129.33322999999999,35.3992],"type":"Point"}
}