{
  "type": "Feature",
  "properties": {
    "gn:admin1_code":"16.0",
    "gn:asciiname":"Geomdan",
    "gn:country_code":"KR",
    "gn:dem":66,
    "gn:feature_class":"P",
    "gn:feature_code":"PPL",
    "gn:name":"Geomdan",
    "gn:population":0,
    "gn:timezone":"Asia/Seoul",
    "iso:country":"KR",
    "name:kor_x_preferred":[
        "\uac80\ub2e8"
    ],
    "wof:name":"Geomdan",
    "wof:placetype":"locality"
},
  "geometry": {"coordinates":[126.96966999999999,35.21411],"type":"Point"}
}