{
  "type": "Feature",
  "properties": {
    "gn:admin1_code":"5.0",
    "gn:asciiname":"Chaktu-gol",
    "gn:country_code":"KR",
    "gn:dem":132,
    "gn:feature_class":"P",
    "gn:feature_code":"PPL",
    "gn:name":"Chaktu-gol",
    "gn:population":0,
    "gn:timezone":"Asia/Seoul",
    "iso:country":"KR",
    "name:und_x_variant":[
        "\uc791\ub450\uace8",
        "Chaktu-gol"
    ],
    "wof:name":"Chaktu-gol",
    "wof:placetype":"locality"
},
  "geometry": {"coordinates":[127.6341,36.1274],"type":"Point"}
}