{
  "type": "Feature",
  "properties": {
    "gn:admin1_code":"15.0",
    "gn:asciiname":"Inae",
    "gn:country_code":"KR",
    "gn:dem":34,
    "gn:feature_class":"P",
    "gn:feature_code":"PPL",
    "gn:name":"Inae",
    "gn:population":0,
    "gn:timezone":"Asia/Seoul",
    "iso:country":"KR",
    "name:und_x_variant":[
        "\uc774\ub0b4",
        "Inae"
    ],
    "wof:name":"Inae",
    "wof:placetype":"locality"
},
  "geometry": {"coordinates":[128.46610999999999,35.89138],"type":"Point"}
}