{
  "type": "Feature",
  "properties": {
    "gn:admin1_code":"17.0",
    "gn:asciiname":"Unam",
    "gn:country_code":"KR",
    "gn:dem":64,
    "gn:feature_class":"P",
    "gn:feature_code":"PPL",
    "gn:name":"\u016cnam",
    "gn:population":0,
    "gn:timezone":"Asia/Seoul",
    "iso:country":"KR",
    "wof:name":"Unam",
    "wof:placetype":"locality"
},
  "geometry": {"coordinates":[127.23333,36.55],"type":"Point"}
}