{
  "type": "Feature",
  "properties": {
    "gn:admin1_code":"17.0",
    "gn:asciiname":"Pun-gol",
    "gn:country_code":"KR",
    "gn:dem":155,
    "gn:feature_class":"P",
    "gn:feature_code":"PPL",
    "gn:name":"Pun-gol",
    "gn:population":0,
    "gn:timezone":"Asia/Seoul",
    "iso:country":"KR",
    "name:und_x_variant":[
        "\ubd84\uace8",
        "Pun-gol"
    ],
    "wof:name":"Pun-gol",
    "wof:placetype":"locality"
},
  "geometry": {"coordinates":[126.8361,36.4907],"type":"Point"}
}