{
  "type": "Feature",
  "properties": {
    "gn:admin1_code":"17.0",
    "gn:asciiname":"Yong-mal",
    "gn:country_code":"KR",
    "gn:dem":44,
    "gn:feature_class":"P",
    "gn:feature_code":"PPL",
    "gn:name":"Y\u014fng-mal",
    "gn:population":0,
    "gn:timezone":"Asia/Seoul",
    "iso:country":"KR",
    "name:und_x_variant":[
        "Y\u014fng-ni",
        "\uc5ed\ub9d0",
        "Y\u014fng-mal"
    ],
    "wof:name":"Yong-mal",
    "wof:placetype":"locality"
},
  "geometry": {"coordinates":[126.4299,36.7705],"type":"Point"}
}