{
  "type": "Feature",
  "properties": {
    "gn:admin1_code":"5.0",
    "gn:asciiname":"Gangdangmal",
    "gn:country_code":"KR",
    "gn:dem":48,
    "gn:feature_class":"P",
    "gn:feature_code":"PPL",
    "gn:name":"Gangdangmal",
    "gn:population":0,
    "gn:timezone":"Asia/Seoul",
    "iso:country":"KR",
    "name:kor_x_preferred":[
        "\uac15\ub2f9\ub9d0"
    ],
    "wof:name":"Gangdangmal",
    "wof:placetype":"locality"
},
  "geometry": {"coordinates":[127.4515,36.71205],"type":"Point"}
}