{
  "type": "Feature",
  "properties": {
    "gn:admin1_code":"1.0",
    "gn:admin2_code":"Namjeju-gun",
    "gn:asciiname":"Jongjeongdong",
    "gn:country_code":"KR",
    "gn:dem":30,
    "gn:feature_class":"P",
    "gn:feature_code":"PPL",
    "gn:name":"Jongjeongdong",
    "gn:population":0,
    "gn:timezone":"Asia/Seoul",
    "iso:country":"KR",
    "name:kor_x_preferred":[
        "\uc885\uc815\ub3d9"
    ],
    "name:und_x_variant":[
        "Chongj\u014fng-dong"
    ],
    "wof:name":"Jongjeongdong",
    "wof:placetype":"locality"
},
  "geometry": {"coordinates":[126.68792999999999,33.27531],"type":"Point"}
}