{
  "type": "Feature",
  "properties": {
    "gn:admin1_code":"20.0",
    "gn:asciiname":"Saemsil",
    "gn:country_code":"KR",
    "gn:dem":32,
    "gn:feature_class":"P",
    "gn:feature_code":"PPL",
    "gn:name":"Saemsil",
    "gn:population":0,
    "gn:timezone":"Asia/Seoul",
    "iso:country":"KR",
    "name:und_x_variant":[
        "\uc0d8\uc2e4",
        "Saemsil"
    ],
    "wof:name":"Saemsil",
    "wof:placetype":"locality"
},
  "geometry": {"coordinates":[128.19141999999999,35.55668],"type":"Point"}
}