{
  "type": "Feature",
  "properties": {
    "gn:admin1_code":"20.0",
    "gn:asciiname":"Ori-dong",
    "gn:country_code":"KR",
    "gn:dem":299,
    "gn:feature_class":"P",
    "gn:feature_code":"PPL",
    "gn:name":"Ori-dong",
    "gn:population":0,
    "gn:timezone":"Asia/Seoul",
    "iso:country":"KR",
    "name:und_x_variant":[
        "\uc624\ub9ac\ub3d9",
        "Ori-dong"
    ],
    "wof:name":"Ori-dong",
    "wof:placetype":"locality"
},
  "geometry": {"coordinates":[127.76414,35.61991],"type":"Point"}
}