{
  "type": "Feature",
  "properties": {
    "gn:admin1_code":"16.0",
    "gn:asciiname":"Nohae",
    "gn:country_code":"KR",
    "gn:dem":24,
    "gn:feature_class":"P",
    "gn:feature_code":"PPL",
    "gn:name":"Nohae",
    "gn:population":0,
    "gn:timezone":"Asia/Seoul",
    "iso:country":"KR",
    "name:kor_x_preferred":[
        "\ub178\ud574"
    ],
    "name:und_x_variant":[
        "Nohea-ri",
        "Nohae"
    ],
    "wof:name":"Nohae",
    "wof:placetype":"locality"
},
  "geometry": {"coordinates":[126.72028,34.51278],"type":"Point"}
}