{
  "type": "Feature",
  "properties": {
    "gn:admin1_code":"10.0",
    "gn:asciiname":"Wolpo",
    "gn:country_code":"KR",
    "gn:dem":3,
    "gn:feature_class":"P",
    "gn:feature_code":"PPL",
    "gn:name":"Wolpo",
    "gn:population":0,
    "gn:timezone":"Asia/Seoul",
    "iso:country":"KR",
    "name:kor_x_preferred":[
        "\uc6d4\ud3ec"
    ],
    "wof:name":"Wolpo",
    "wof:placetype":"locality"
},
  "geometry": {"coordinates":[128.93735000000001,35.15497],"type":"Point"}
}