{
  "type": "Feature",
  "properties": {
    "gn:admin1_code":"14.0",
    "gn:asciiname":"Jikgok",
    "gn:country_code":"KR",
    "gn:dem":132,
    "gn:feature_class":"P",
    "gn:feature_code":"PPL",
    "gn:name":"Jikgok",
    "gn:population":0,
    "gn:timezone":"Asia/Seoul",
    "iso:country":"KR",
    "name:kor_x_preferred":[
        "\uc9c1\uace1"
    ],
    "wof:name":"Jikgok",
    "wof:placetype":"locality"
},
  "geometry": {"coordinates":[128.69363999999999,36.59445],"type":"Point"}
}