{
  "type": "Feature",
  "properties": {
    "gn:admin1_code":"17.0",
    "gn:asciiname":"Sinal-li",
    "gn:country_code":"KR",
    "gn:dem":50,
    "gn:feature_class":"P",
    "gn:feature_code":"PPL",
    "gn:name":"Sinal-li",
    "gn:population":0,
    "gn:timezone":"Asia/Seoul",
    "iso:country":"KR",
    "name:und_x_variant":[
        "Ch\u014fngjung-ni"
    ],
    "wof:name":"Sinal-li",
    "wof:placetype":"locality"
},
  "geometry": {"coordinates":[127.28417,36.62833],"type":"Point"}
}