{
  "type": "Feature",
  "properties": {
    "gn:admin1_code":"17.0",
    "gn:asciiname":"Wondae",
    "gn:country_code":"KR",
    "gn:dem":45,
    "gn:feature_class":"P",
    "gn:feature_code":"PPL",
    "gn:name":"Wondae",
    "gn:population":0,
    "gn:timezone":"Asia/Seoul",
    "iso:country":"KR",
    "name:und_x_variant":[
        "\uc6d0\ub300",
        "W\u014fndae",
        "Wondae"
    ],
    "wof:name":"Wondae",
    "wof:placetype":"locality"
},
  "geometry": {"coordinates":[127.21339999999999,36.4226],"type":"Point"}
}