{
  "type": "Feature",
  "properties": {
    "gn:admin1_code":"6.0",
    "gn:asciiname":"Noelbeunae",
    "gn:country_code":"KR",
    "gn:dem":149,
    "gn:feature_class":"P",
    "gn:feature_code":"PPL",
    "gn:name":"Noelbeunae",
    "gn:population":0,
    "gn:timezone":"Asia/Seoul",
    "iso:country":"KR",
    "name:kor_x_preferred":[
        "\ub113\uc73c\ub0b4"
    ],
    "name:kor_x_variant":[
        "N\u014flb\u016dnae",
        "\ub108\ube0c\ub124"
    ],
    "name:und_x_variant":[
        "Neobune"
    ],
    "wof:name":"Noelbeunae",
    "wof:placetype":"locality"
},
  "geometry": {"coordinates":[127.86020000000001,37.7188],"type":"Point"}
}