{
  "type": "Feature",
  "properties": {
    "gn:admin1_code":"13.0",
    "gn:asciiname":"Sasilgol",
    "gn:country_code":"KR",
    "gn:dem":443,
    "gn:feature_class":"P",
    "gn:feature_code":"PPL",
    "gn:name":"Sasilgol",
    "gn:population":0,
    "gn:timezone":"Asia/Seoul",
    "iso:country":"KR",
    "name:kor_x_preferred":[
        "\uc0ac\uc2e4\uace8"
    ],
    "wof:name":"Sasilgol",
    "wof:placetype":"locality"
},
  "geometry": {"coordinates":[127.34665,38.05065],"type":"Point"}
}