{
  "type": "Feature",
  "properties": {
    "gn:admin1_code":"14.0",
    "gn:asciiname":"Jabong",
    "gn:country_code":"KR",
    "gn:dem":180,
    "gn:feature_class":"P",
    "gn:feature_code":"PPL",
    "gn:name":"Jabong",
    "gn:population":0,
    "gn:timezone":"Asia/Seoul",
    "iso:country":"KR",
    "name:kor_x_preferred":[
        "\uc790\ubd09"
    ],
    "wof:name":"Jabong",
    "wof:placetype":"locality"
},
  "geometry": {"coordinates":[128.49446,36.75162],"type":"Point"}
}