{
  "type": "Feature",
  "properties": {
    "gn:admin1_code":"16.0",
    "gn:asciiname":"Chogok",
    "gn:country_code":"KR",
    "gn:dem":147,
    "gn:feature_class":"P",
    "gn:feature_code":"PPL",
    "gn:name":"Chogok",
    "gn:population":0,
    "gn:timezone":"Asia/Seoul",
    "iso:country":"KR",
    "name:kor_x_preferred":[
        "\ucd08\uace1"
    ],
    "name:kor_x_variant":[
        "Ch\u2019ogok"
    ],
    "name:und_x_variant":[
        "Ch\u2019ogong-ni",
        "Chogok"
    ],
    "wof:name":"Chogok",
    "wof:placetype":"locality"
},
  "geometry": {"coordinates":[127.40604999999999,34.91559],"type":"Point"}
}