{
  "type": "Feature",
  "properties": {
    "gn:admin1_code":"17.0",
    "gn:asciiname":"Sambasilgol",
    "gn:country_code":"KR",
    "gn:dem":95,
    "gn:feature_class":"P",
    "gn:feature_code":"PPL",
    "gn:name":"Sambasilgol",
    "gn:population":0,
    "gn:timezone":"Asia/Seoul",
    "iso:country":"KR",
    "name:kor_x_preferred":[
        "\uc0bc\ubc14\uc2e4\uace8"
    ],
    "wof:name":"Sambasilgol",
    "wof:placetype":"locality"
},
  "geometry": {"coordinates":[126.9179,36.62942],"type":"Point"}
}