{
  "type": "Feature",
  "properties": {
    "gn:admin1_code":"18.0",
    "gn:asciiname":"Gungnyong",
    "gn:country_code":"KR",
    "gn:dem":46,
    "gn:feature_class":"P",
    "gn:feature_code":"PPL",
    "gn:name":"Gungnyong",
    "gn:population":0,
    "gn:timezone":"Asia/Seoul",
    "iso:country":"KR",
    "name:kor_x_preferred":[
        "\uad6d\ub8e1"
    ],
    "wof:name":"Gungnyong",
    "wof:placetype":"locality"
},
  "geometry": {"coordinates":[126.67735999999999,35.11637],"type":"Point"}
}