{
  "type": "Feature",
  "properties": {
    "gn:admin1_code":"14.0",
    "gn:asciiname":"OImijae",
    "gn:country_code":"KR",
    "gn:dem":196,
    "gn:feature_class":"P",
    "gn:feature_code":"PPL",
    "gn:name":"OImijae",
    "gn:population":0,
    "gn:timezone":"Asia/Seoul",
    "iso:country":"KR",
    "name:kor_x_preferred":[
        "\uc62c\ubbf8\uc7ac"
    ],
    "wof:name":"OImijae",
    "wof:placetype":"locality"
},
  "geometry": {"coordinates":[128.88628,36.76253],"type":"Point"}
}