{
  "type": "Feature",
  "properties": {
    "gn:admin1_code":"14.0",
    "gn:asciiname":"Yongmo-ri",
    "gn:country_code":"KR",
    "gn:dem":90,
    "gn:feature_class":"P",
    "gn:feature_code":"PPL",
    "gn:name":"Yongm\u014f-ri",
    "gn:population":0,
    "gn:timezone":"Asia/Seoul",
    "iso:country":"KR",
    "name:und_x_variant":[
        "\uc6a9\uba38\ub9ac",
        "Yongm\u014f-ri"
    ],
    "wof:name":"Yongmo-ri",
    "wof:placetype":"locality"
},
  "geometry": {"coordinates":[128.12129999999999,36.494],"type":"Point"}
}