{
  "type": "Feature",
  "properties": {
    "gn:admin1_code":"16.0",
    "gn:admin2_code":"Chindo-gun",
    "gn:asciiname":"Wondagol",
    "gn:country_code":"KR",
    "gn:dem":12,
    "gn:feature_class":"P",
    "gn:feature_code":"PPL",
    "gn:name":"Wondagol",
    "gn:population":0,
    "gn:timezone":"Asia/Seoul",
    "iso:country":"KR",
    "name:kor_x_preferred":[
        "\uc6d0\ub2e4\uace8"
    ],
    "name:und_x_variant":[
        "Genta-d\u014d",
        "W\u014fnda-dong",
        "W\u014fnda-gol",
        "W\u014fnda",
        "Wondagol"
    ],
    "wof:name":"Wondagol",
    "wof:placetype":"locality"
},
  "geometry": {"coordinates":[126.28742,34.38799],"type":"Point"}
}