{
  "type": "Feature",
  "properties": {
    "gn:admin1_code":"6.0",
    "gn:asciiname":"Jeotdonggae",
    "gn:country_code":"KR",
    "gn:dem":755,
    "gn:feature_class":"P",
    "gn:feature_code":"PPL",
    "gn:name":"Jeotdonggae",
    "gn:population":0,
    "gn:timezone":"Asia/Seoul",
    "iso:country":"KR",
    "name:kor_x_preferred":[
        "\uc816\ub3d9\uac1c"
    ],
    "name:kor_x_variant":[
        "Ch\u014fttonggae",
        "\uc813\ub3d9\uac1c"
    ],
    "wof:name":"Jeotdonggae",
    "wof:placetype":"locality"
},
  "geometry": {"coordinates":[128.65000000000001,37.0734],"type":"Point"}
}