{
  "type": "Feature",
  "properties": {
    "gn:admin1_code":"20.0",
    "gn:asciiname":"An'gok",
    "gn:country_code":"KR",
    "gn:dem":95,
    "gn:feature_class":"P",
    "gn:feature_code":"PPL",
    "gn:name":"An\u2019gok",
    "gn:population":0,
    "gn:timezone":"Asia/Seoul",
    "iso:country":"KR",
    "name:und_x_variant":[
        "\uc548\uace1",
        "An\u2019gok"
    ],
    "wof:name":"An'gok",
    "wof:placetype":"locality"
},
  "geometry": {"coordinates":[128.65311,35.56688],"type":"Point"}
}