{
  "type": "Feature",
  "properties": {
    "gn:admin1_code":"12.0",
    "gn:asciiname":"Pibijae",
    "gn:country_code":"KR",
    "gn:dem":32,
    "gn:feature_class":"P",
    "gn:feature_code":"PPL",
    "gn:name":"Pibijae",
    "gn:population":0,
    "gn:timezone":"Asia/Seoul",
    "iso:country":"KR",
    "name:und_x_variant":[
        "\ube44\ube44\uc7ac",
        "Bibijae",
        "Pibijae"
    ],
    "wof:name":"Pibijae",
    "wof:placetype":"locality"
},
  "geometry": {"coordinates":[126.44361000000001,37.63667],"type":"Point"}
}