{
  "type": "Feature",
  "properties": {
    "gn:admin1_code":"14.0",
    "gn:asciiname":"Oro-gol",
    "gn:country_code":"KR",
    "gn:dem":82,
    "gn:feature_class":"P",
    "gn:feature_code":"PPL",
    "gn:name":"Oro-gol",
    "gn:population":0,
    "gn:timezone":"Asia/Seoul",
    "iso:country":"KR",
    "name:und_x_variant":[
        "\uc624\ub85c\uace8",
        "Oro-gol"
    ],
    "wof:name":"Oro-gol",
    "wof:placetype":"locality"
},
  "geometry": {"coordinates":[128.2921,36.1395],"type":"Point"}
}