{
  "type": "Feature",
  "properties": {
    "gn:admin1_code":"20.0",
    "gn:asciiname":"Sohwa",
    "gn:country_code":"KR",
    "gn:dem":40,
    "gn:feature_class":"P",
    "gn:feature_code":"PPL",
    "gn:name":"S\u014fhwa",
    "gn:population":0,
    "gn:timezone":"Asia/Seoul",
    "iso:country":"KR",
    "name:und_x_variant":[
        "\uc11c\ud654",
        "S\u014fhwa"
    ],
    "wof:name":"Sohwa",
    "wof:placetype":"locality"
},
  "geometry": {"coordinates":[128.34146000000001,35.06131],"type":"Point"}
}