{
  "type": "Feature",
  "properties": {
    "gn:admin1_code":"16.0",
    "gn:asciiname":"Jeomsu",
    "gn:country_code":"KR",
    "gn:dem":20,
    "gn:feature_class":"P",
    "gn:feature_code":"PPL",
    "gn:name":"Jeomsu",
    "gn:population":0,
    "gn:timezone":"Asia/Seoul",
    "iso:country":"KR",
    "name:kor_x_preferred":[
        "\uc810\uc218"
    ],
    "name:kor_x_variant":[
        "Sinw\u014fn"
    ],
    "wof:name":"Jeomsu",
    "wof:placetype":"locality"
},
  "geometry": {"coordinates":[126.77813,34.64675],"type":"Point"}
}