{
  "type": "Feature",
  "properties": {
    "gn:admin1_code":"6.0",
    "gn:asciiname":"Mudomsil",
    "gn:country_code":"KR",
    "gn:dem":144,
    "gn:feature_class":"P",
    "gn:feature_code":"PPL",
    "gn:name":"Mud\u014fmsil",
    "gn:population":0,
    "gn:timezone":"Asia/Seoul",
    "iso:country":"KR",
    "name:kor_x_preferred":[
        "\ubb34\ub364\uc2e4"
    ],
    "name:kor_x_variant":[
        "Mud\u014fmsil"
    ],
    "wof:name":"Mudomsil",
    "wof:placetype":"locality"
},
  "geometry": {"coordinates":[128.02029999999999,37.5074],"type":"Point"}
}