{
  "type": "Feature",
  "properties": {
    "gn:admin1_code":"14.0",
    "gn:asciiname":"Nari",
    "gn:country_code":"KR",
    "gn:dem":95,
    "gn:feature_class":"P",
    "gn:feature_code":"PPL",
    "gn:name":"Nari",
    "gn:population":0,
    "gn:timezone":"Asia/Seoul",
    "iso:country":"KR",
    "name:ceb_x_preferred":[
        "Nari"
    ],
    "name:deu_x_preferred":[
        "Nari"
    ],
    "name:kor_x_preferred":[
        "\ub098\ub9ac"
    ],
    "name:swe_x_preferred":[
        "Nari"
    ],
    "name:ukr_x_preferred":[
        "\u041d\u0430\u0440\u0456"
    ],
    "wof:name":"Nari",
    "wof:placetype":"locality"
},
  "geometry": {"coordinates":[129.27701999999999,35.92279],"type":"Point"}
}