{
  "type": "Feature",
  "properties": {
    "gn:admin1_code":"3.0",
    "gn:asciiname":"Nae-dong",
    "gn:country_code":"KR",
    "gn:dem":211,
    "gn:feature_class":"P",
    "gn:feature_code":"PPL",
    "gn:name":"Nae-dong",
    "gn:population":0,
    "gn:timezone":"Asia/Seoul",
    "iso:country":"KR",
    "name:und_x_variant":[
        "\ub0b4\ub3d9",
        "Nae-dong"
    ],
    "wof:name":"Nae-dong",
    "wof:placetype":"locality"
},
  "geometry": {"coordinates":[127.6486,36.0475],"type":"Point"}
}