{
  "type": "Feature",
  "properties": {
    "gn:admin1_code":"11.0",
    "gn:asciiname":"Unhaengjong",
    "gn:country_code":"KR",
    "gn:dem":13,
    "gn:feature_class":"P",
    "gn:feature_code":"PPL",
    "gn:name":"\u016cnhaengj\u014fng",
    "gn:population":0,
    "gn:timezone":"Asia/Seoul",
    "iso:country":"KR",
    "name:kor_x_preferred":[
        "\uc740\ud589\uc815"
    ],
    "name:kor_x_variant":[
        "\u016cnhaengj\u014fng"
    ],
    "wof:name":"Unhaengjong",
    "wof:placetype":"locality"
},
  "geometry": {"coordinates":[126.84361,37.60361],"type":"Point"}
}