{
  "type": "Feature",
  "properties": {
    "gn:admin1_code":"17.0",
    "gn:asciiname":"Kok-ch'on",
    "gn:country_code":"KR",
    "gn:dem":15,
    "gn:feature_class":"P",
    "gn:feature_code":"PPL",
    "gn:name":"Kok-ch\u2019on",
    "gn:population":0,
    "gn:timezone":"Asia/Seoul",
    "iso:country":"KR",
    "name:und_x_variant":[
        "\uace1\ucd0c",
        "Kok-ch\u2019on"
    ],
    "wof:name":"Kok-ch'on",
    "wof:placetype":"locality"
},
  "geometry": {"coordinates":[126.45610000000001,36.7521],"type":"Point"}
}