{
  "type": "Feature",
  "properties": {
    "gn:admin1_code":"5.0",
    "gn:asciiname":"Byeongmugwan",
    "gn:country_code":"KR",
    "gn:dem":125,
    "gn:feature_class":"P",
    "gn:feature_code":"PPL",
    "gn:name":"Byeongmugwan",
    "gn:population":0,
    "gn:timezone":"Asia/Seoul",
    "iso:country":"KR",
    "name:kor_x_preferred":[
        "\ubcd1\ubb34\uad00"
    ],
    "wof:name":"Byeongmugwan",
    "wof:placetype":"locality"
},
  "geometry": {"coordinates":[127.42229,36.98341],"type":"Point"}
}