{
  "type": "Feature",
  "properties": {
    "gn:admin1_code":"13.0",
    "gn:asciiname":"Bangchuk-gol",
    "gn:country_code":"KR",
    "gn:dem":79,
    "gn:feature_class":"P",
    "gn:feature_code":"PPL",
    "gn:name":"Bangchuk-gol",
    "gn:population":0,
    "gn:timezone":"Asia/Seoul",
    "iso:country":"KR",
    "name:und_x_variant":[
        "\ubc29\ucd95\uace8",
        "Bangchuk-gol",
        "Pangch\u2019uk-kol"
    ],
    "wof:name":"Bangchuk-gol",
    "wof:placetype":"locality"
},
  "geometry": {"coordinates":[127.53333000000001,37.44389],"type":"Point"}
}