{
  "type": "Feature",
  "properties": {
    "gn:admin1_code":"14.0",
    "gn:asciiname":"Chulmaendung",
    "gn:country_code":"KR",
    "gn:dem":360,
    "gn:feature_class":"P",
    "gn:feature_code":"PPL",
    "gn:name":"Chulmaend\u016dng",
    "gn:population":0,
    "gn:timezone":"Asia/Seoul",
    "iso:country":"KR",
    "name:kor_x_preferred":[
        "\uc904\ub9e8\ub4f1"
    ],
    "name:kor_x_variant":[
        "Chulmaend\u016dng"
    ],
    "wof:name":"Chulmaendung",
    "wof:placetype":"locality"
},
  "geometry": {"coordinates":[130.8954,37.5013],"type":"Point"}
}