{
  "type": "Feature",
  "properties": {
    "gn:admin1_code":"20.0",
    "gn:asciiname":"Yurwol-li",
    "gn:country_code":"KR",
    "gn:dem":58,
    "gn:feature_class":"P",
    "gn:feature_code":"PPL",
    "gn:name":"Yurw\u014fl-li",
    "gn:population":0,
    "gn:timezone":"Asia/Seoul",
    "iso:country":"KR",
    "name:und_x_variant":[
        "Yurw\u014fn-ni",
        "Yurw\u014fn",
        "\uc728\uc6d0\ub9ac",
        "Yurw\u014fn-dong",
        "Yurw\u014fl-li"
    ],
    "wof:name":"Yurwol-li",
    "wof:placetype":"locality"
},
  "geometry": {"coordinates":[128.29061999999999,35.64001],"type":"Point"}
}