{
  "type": "Feature",
  "properties": {
    "gn:admin1_code":"6.0",
    "gn:asciiname":"Dareumjae",
    "gn:country_code":"KR",
    "gn:dem":664,
    "gn:feature_class":"P",
    "gn:feature_code":"PPL",
    "gn:name":"Dareumjae",
    "gn:population":0,
    "gn:timezone":"Asia/Seoul",
    "iso:country":"KR",
    "name:kor_x_preferred":[
        "\ub2e4\ub984\uc7ac"
    ],
    "name:kor_x_variant":[
        "Tar\u016dmjae",
        "\ub2ec\uc74c\uc7ac"
    ],
    "wof:name":"Dareumjae",
    "wof:placetype":"locality"
},
  "geometry": {"coordinates":[128.09963999999999,37.886],"type":"Point"}
}