{
  "type": "Feature",
  "properties": {
    "gn:admin1_code":"16.0",
    "gn:asciiname":"Dalli",
    "gn:country_code":"KR",
    "gn:dem":22,
    "gn:feature_class":"P",
    "gn:feature_code":"PPL",
    "gn:name":"Dalli",
    "gn:population":0,
    "gn:timezone":"Asia/Seoul",
    "iso:country":"KR",
    "name:kor_x_preferred":[
        "\ub2ec\ub9ac"
    ],
    "name:und_x_variant":[
        "Tal-li"
    ],
    "wof:name":"Dalli",
    "wof:placetype":"locality"
},
  "geometry": {"coordinates":[126.31278,34.76919],"type":"Point"}
}