{
  "type": "Feature",
  "properties": {
    "gn:admin1_code":"17.0",
    "gn:asciiname":"Madae",
    "gn:country_code":"KR",
    "gn:dem":43,
    "gn:feature_class":"P",
    "gn:feature_code":"PPL",
    "gn:name":"Madae",
    "gn:population":0,
    "gn:timezone":"Asia/Seoul",
    "iso:country":"KR",
    "name:kor_x_preferred":[
        "\ub9c8\ub300"
    ],
    "name:und_x_variant":[
        "\ud0d1\uace8",
        "T\u2019ap-kol",
        "Madae",
        "Tapgol"
    ],
    "wof:name":"Madae",
    "wof:placetype":"locality"
},
  "geometry": {"coordinates":[127.072,36.7536],"type":"Point"}
}