{
  "type": "Feature",
  "properties": {
    "gn:admin1_code":"5.0",
    "gn:asciiname":"Sin'gidul",
    "gn:country_code":"KR",
    "gn:dem":221,
    "gn:feature_class":"P",
    "gn:feature_code":"PPL",
    "gn:name":"Sin\u2019gid\u016dl",
    "gn:population":0,
    "gn:timezone":"Asia/Seoul",
    "iso:country":"KR",
    "name:kor_x_preferred":[
        "\uc2e0\uae30\ub4e4"
    ],
    "name:kor_x_variant":[
        "Sin\u2019gid\u016dl"
    ],
    "wof:name":"Sin'gidul",
    "wof:placetype":"locality"
},
  "geometry": {"coordinates":[128.36789999999999,37.0969],"type":"Point"}
}