{
  "type": "Feature",
  "properties": {
    "gn:admin1_code":"20.0",
    "gn:asciiname":"Hak-ri",
    "gn:country_code":"KR",
    "gn:dem":40,
    "gn:feature_class":"P",
    "gn:feature_code":"PPL",
    "gn:name":"Hak-ri",
    "gn:population":0,
    "gn:timezone":"Asia/Seoul",
    "iso:country":"KR",
    "name:und_x_variant":[
        "\ud559\ub9ac",
        "Hang-ni",
        "Hak-ri"
    ],
    "wof:name":"Hak-ri",
    "wof:placetype":"locality"
},
  "geometry": {"coordinates":[128.35220000000001,35.62302000000001],"type":"Point"}
}