{
  "type": "Feature",
  "properties": {
    "gn:admin1_code":"5.0",
    "gn:asciiname":"Bondeung",
    "gn:country_code":"KR",
    "gn:dem":212,
    "gn:feature_class":"P",
    "gn:feature_code":"PPL",
    "gn:name":"Bondeung",
    "gn:population":0,
    "gn:timezone":"Asia/Seoul",
    "iso:country":"KR",
    "name:kor_x_preferred":[
        "\ubcf8\ub4f1"
    ],
    "wof:name":"Bondeung",
    "wof:placetype":"locality"
},
  "geometry": {"coordinates":[128.28328999999999,37.01344],"type":"Point"}
}