{
  "type": "Feature",
  "properties": {
    "gn:admin1_code":"6.0",
    "gn:asciiname":"Takpawi",
    "gn:country_code":"KR",
    "gn:dem":149,
    "gn:feature_class":"P",
    "gn:feature_code":"PPL",
    "gn:name":"Takpawi",
    "gn:population":0,
    "gn:timezone":"Asia/Seoul",
    "iso:country":"KR",
    "name:kor_x_preferred":[
        "\ub2ed\ubc14\uc704"
    ],
    "wof:name":"Takpawi",
    "wof:placetype":"locality"
},
  "geometry": {"coordinates":[127.899,37.692],"type":"Point"}
}