{
  "type": "Feature",
  "properties": {
    "gn:admin1_code":"16.0",
    "gn:asciiname":"Junghyeon",
    "gn:country_code":"KR",
    "gn:dem":211,
    "gn:feature_class":"P",
    "gn:feature_code":"PPL",
    "gn:name":"Junghyeon",
    "gn:population":0,
    "gn:timezone":"Asia/Seoul",
    "iso:country":"KR",
    "name:kor_x_preferred":[
        "\uc911\ud604"
    ],
    "name:kor_x_variant":[
        "Chunghy\u014fn"
    ],
    "wof:name":"Junghyeon",
    "wof:placetype":"locality"
},
  "geometry": {"coordinates":[127.41672,34.90282],"type":"Point"}
}