{
  "type": "Feature",
  "properties": {
    "gn:admin1_code":"14.0",
    "gn:asciiname":"Gwangeori",
    "gn:country_code":"KR",
    "gn:dem":76,
    "gn:feature_class":"P",
    "gn:feature_code":"PPL",
    "gn:name":"Gwangeori",
    "gn:population":0,
    "gn:timezone":"Asia/Seoul",
    "iso:country":"KR",
    "name:kor_x_preferred":[
        "\uad00\uac70\ub9ac"
    ],
    "wof:name":"Gwangeori",
    "wof:placetype":"locality"
},
  "geometry": {"coordinates":[129.31988000000001,35.71089],"type":"Point"}
}