{
  "type": "Feature",
  "properties": {
    "gn:admin1_code":"5.0",
    "gn:asciiname":"Chunggan-mal",
    "gn:country_code":"KR",
    "gn:dem":239,
    "gn:feature_class":"P",
    "gn:feature_code":"PPL",
    "gn:name":"Chunggan-mal",
    "gn:population":0,
    "gn:timezone":"Asia/Seoul",
    "iso:country":"KR",
    "name:kor_x_preferred":[
        "\uc911\uac04\ub9d0"
    ],
    "wof:name":"Chunggan-mal",
    "wof:placetype":"locality"
},
  "geometry": {"coordinates":[128.01159999999999,37.1523],"type":"Point"}
}