{
  "type": "Feature",
  "properties": {
    "gn:admin1_code":"14.0",
    "gn:asciiname":"Sangoksan",
    "gn:country_code":"KR",
    "gn:dem":141,
    "gn:feature_class":"P",
    "gn:feature_code":"PPL",
    "gn:name":"Sangoksan",
    "gn:population":0,
    "gn:timezone":"Asia/Seoul",
    "iso:country":"KR",
    "name:und_x_variant":[
        "\uc0c1\uc625\uc0b0",
        "Sangoksan"
    ],
    "wof:name":"Sangoksan",
    "wof:placetype":"locality"
},
  "geometry": {"coordinates":[128.62476999999998,35.60554000000001],"type":"Point"}
}