{
  "type": "Feature",
  "properties": {
    "gn:admin1_code":"14.0",
    "gn:asciiname":"Pae-gol",
    "gn:country_code":"KR",
    "gn:dem":186,
    "gn:feature_class":"P",
    "gn:feature_code":"PPL",
    "gn:name":"Pae-gol",
    "gn:population":0,
    "gn:timezone":"Asia/Seoul",
    "iso:country":"KR",
    "name:und_x_variant":[
        "\ubc30\uace8",
        "Pae-gol"
    ],
    "wof:name":"Pae-gol",
    "wof:placetype":"locality"
},
  "geometry": {"coordinates":[128.74340000000001,36.2534],"type":"Point"}
}