{
  "type": "Feature",
  "properties": {
    "gn:admin1_code":"13.0",
    "gn:asciiname":"Wolchon",
    "gn:country_code":"KR",
    "gn:dem":87,
    "gn:feature_class":"P",
    "gn:feature_code":"PPL",
    "gn:name":"Wolchon",
    "gn:population":0,
    "gn:timezone":"Asia/Seoul",
    "iso:country":"KR",
    "name:und_x_variant":[
        "\uc6d4\ucd0c",
        "W\u014flch\u2019on",
        "Wolchon"
    ],
    "wof:name":"Wolchon",
    "wof:placetype":"locality"
},
  "geometry": {"coordinates":[127.1122,37.7085],"type":"Point"}
}