{
  "type": "Feature",
  "properties": {
    "gn:admin1_code":"17.0",
    "gn:asciiname":"Soch'on-mal",
    "gn:country_code":"KR",
    "gn:dem":13,
    "gn:feature_class":"P",
    "gn:feature_code":"PPL",
    "gn:name":"S\u014fch\u2019on-mal",
    "gn:population":0,
    "gn:timezone":"Asia/Seoul",
    "iso:country":"KR",
    "name:und_x_variant":[
        "\uc11c\ucd0c\ub9d0",
        "S\u014fch\u2019on-mal"
    ],
    "wof:name":"Soch'on-mal",
    "wof:placetype":"locality"
},
  "geometry": {"coordinates":[126.5266,36.7532],"type":"Point"}
}