{
  "type": "Feature",
  "properties": {
    "gn:admin1_code":"13.0",
    "gn:admin2_code":"Ans\u014fng-si",
    "gn:asciiname":"Nogong-ni",
    "gn:country_code":"KR",
    "gn:dem":98,
    "gn:feature_class":"P",
    "gn:feature_code":"PPLL",
    "gn:name":"Nogong-ni",
    "gn:population":0,
    "gn:timezone":"Asia/Seoul",
    "iso:country":"KR",
    "name:kor_x_preferred":[
        "\ub178\uace1\ub9ac"
    ],
    "name:und_x_variant":[
        "Nogok-ri"
    ],
    "wof:name":"Nogong-ni",
    "wof:placetype":"locality"
},
  "geometry": {"coordinates":[127.23778,37.11167],"type":"Point"}
}