{
  "type": "Feature",
  "properties": {
    "gn:admin1_code":"16.0",
    "gn:asciiname":"Kumgong-ni",
    "gn:cc2":"KR",
    "gn:country_code":"KR",
    "gn:dem":14,
    "gn:feature_class":"P",
    "gn:feature_code":"PPL",
    "gn:name":"K\u016dmgong-ni",
    "gn:population":0,
    "gn:timezone":"Asia/Seoul",
    "iso:country":"KR",
    "name:und_x_variant":[
        "W\u014fn\u2019g\u016dmgok",
        "K\u016dmgong-ni"
    ],
    "wof:name":"Kumgong-ni",
    "wof:placetype":"locality"
},
  "geometry": {"coordinates":[126.60972,34.94278],"type":"Point"}
}