{
  "type": "Feature",
  "properties": {
    "gn:admin1_code":"17.0",
    "gn:asciiname":"Ansut'o",
    "gn:country_code":"KR",
    "gn:dem":22,
    "gn:feature_class":"P",
    "gn:feature_code":"PPL",
    "gn:name":"Ansut\u2019\u014f",
    "gn:population":0,
    "gn:timezone":"Asia/Seoul",
    "iso:country":"KR",
    "name:und_x_variant":[
        "\uc548\uc218\ud130",
        "Ansut\u2019\u014f"
    ],
    "wof:name":"Ansut'o",
    "wof:placetype":"locality"
},
  "geometry": {"coordinates":[126.3616,36.5213],"type":"Point"}
}