{
  "type": "Feature",
  "properties": {
    "gn:admin1_code":"13.0",
    "gn:asciiname":"Maejiul",
    "gn:country_code":"KR",
    "gn:dem":78,
    "gn:feature_class":"P",
    "gn:feature_code":"PPL",
    "gn:name":"Maejiul",
    "gn:population":0,
    "gn:timezone":"Asia/Seoul",
    "iso:country":"KR",
    "name:und_x_variant":[
        "\ub9e4\uc9c0\uc6b8",
        "Maejiul"
    ],
    "wof:name":"Maejiul",
    "wof:placetype":"locality"
},
  "geometry": {"coordinates":[127.48472,37.26333],"type":"Point"}
}