{
  "type": "Feature",
  "properties": {
    "gn:admin1_code":"13.0",
    "gn:admin2_code":"P'aju-si",
    "gn:asciiname":"Bogwoldong",
    "gn:country_code":"KR",
    "gn:dem":47,
    "gn:feature_class":"P",
    "gn:feature_code":"PPL",
    "gn:name":"Bogwoldong",
    "gn:population":0,
    "gn:timezone":"Asia/Seoul",
    "iso:country":"KR",
    "name:kor_x_preferred":[
        "\ubcf5\uc6d4\ub3d9"
    ],
    "name:kor_x_variant":[
        "Pogw\u014fl-tong"
    ],
    "wof:name":"Bogwoldong",
    "wof:placetype":"locality"
},
  "geometry": {"coordinates":[126.87437,37.79112],"type":"Point"}
}