{
  "type": "Feature",
  "properties": {
    "gn:admin1_code":"14.0",
    "gn:asciiname":"Wandam",
    "gn:country_code":"KR",
    "gn:dem":72,
    "gn:feature_class":"P",
    "gn:feature_code":"PPL",
    "gn:name":"Wandam",
    "gn:population":0,
    "gn:timezone":"Asia/Seoul",
    "iso:country":"KR",
    "name:kor_x_preferred":[
        "\uc644\ub2f4"
    ],
    "wof:name":"Wandam",
    "wof:placetype":"locality"
},
  "geometry": {"coordinates":[128.32557,36.55059],"type":"Point"}
}