{
  "type": "Feature",
  "properties": {
    "gn:admin1_code":"6.0",
    "gn:asciiname":"Keungol",
    "gn:country_code":"KR",
    "gn:dem":173,
    "gn:feature_class":"P",
    "gn:feature_code":"PPL",
    "gn:name":"Keungol",
    "gn:population":0,
    "gn:timezone":"Asia/Seoul",
    "iso:country":"KR",
    "name:kor_x_preferred":[
        "\ud070\uace8"
    ],
    "name:kor_x_variant":[
        "K\u2019\u016dn-gol"
    ],
    "wof:name":"Keungol",
    "wof:placetype":"locality"
},
  "geometry": {"coordinates":[127.89418999999999,37.71127],"type":"Point"}
}