{
  "type": "Feature",
  "properties": {
    "gn:admin1_code":"17.0",
    "gn:asciiname":"Saemaeul",
    "gn:country_code":"KR",
    "gn:dem":69,
    "gn:feature_class":"P",
    "gn:feature_code":"PPL",
    "gn:name":"Saemaeul",
    "gn:population":0,
    "gn:timezone":"Asia/Seoul",
    "iso:country":"KR",
    "name:kor_x_preferred":[
        "\uc0c8\ub9c8\uc744"
    ],
    "wof:name":"Saemaeul",
    "wof:placetype":"locality"
},
  "geometry": {"coordinates":[126.99661,36.70608],"type":"Point"}
}