{
  "type": "Feature",
  "properties": {
    "gn:admin1_code":"14.0",
    "gn:asciiname":"Witdeul",
    "gn:country_code":"KR",
    "gn:dem":94,
    "gn:feature_class":"P",
    "gn:feature_code":"PPL",
    "gn:name":"Witdeul",
    "gn:population":0,
    "gn:timezone":"Asia/Seoul",
    "iso:country":"KR",
    "name:kor_x_preferred":[
        "\uc717\ub4e4"
    ],
    "wof:name":"Witdeul",
    "wof:placetype":"locality"
},
  "geometry": {"coordinates":[128.6403,36.55454],"type":"Point"}
}