{
  "type": "Feature",
  "properties": {
    "gn:admin1_code":"17.0",
    "gn:asciiname":"Yugong-ni",
    "gn:country_code":"KR",
    "gn:dem":31,
    "gn:feature_class":"P",
    "gn:feature_code":"PPL",
    "gn:name":"Yugong-ni",
    "gn:population":0,
    "gn:timezone":"Asia/Seoul",
    "iso:country":"KR",
    "name:und_x_variant":[
        "W\u014fnyugok"
    ],
    "wof:name":"Yugong-ni",
    "wof:placetype":"locality"
},
  "geometry": {"coordinates":[126.59999999999999,36.18333],"type":"Point"}
}