{
  "type": "Feature",
  "properties": {
    "gn:admin1_code":"5.0",
    "gn:asciiname":"Doldarimot",
    "gn:country_code":"KR",
    "gn:dem":36,
    "gn:feature_class":"P",
    "gn:feature_code":"PPL",
    "gn:name":"Doldarimot",
    "gn:population":0,
    "gn:timezone":"Asia/Seoul",
    "iso:country":"KR",
    "name:kor_x_preferred":[
        "\ub3cc\ub2e4\ub9ac\ubabb"
    ],
    "wof:name":"Doldarimot",
    "wof:placetype":"locality"
},
  "geometry": {"coordinates":[127.32174999999999,36.62893],"type":"Point"}
}