{
  "type": "Feature",
  "properties": {
    "gn:admin1_code":"6.0",
    "gn:asciiname":"Keunsolgol",
    "gn:country_code":"KR",
    "gn:dem":363,
    "gn:feature_class":"P",
    "gn:feature_code":"PPL",
    "gn:name":"Keunsolgol",
    "gn:population":0,
    "gn:timezone":"Asia/Seoul",
    "iso:country":"KR",
    "name:kor_x_preferred":[
        "\ud070\uc194\uace8"
    ],
    "name:kor_x_variant":[
        "K\u2019\u016dnsol-gol"
    ],
    "wof:name":"Keunsolgol",
    "wof:placetype":"locality"
},
  "geometry": {"coordinates":[128.03139999999999,37.8177],"type":"Point"}
}