{
  "type": "Feature",
  "properties": {
    "gn:admin1_code":"14.0",
    "gn:asciiname":"Unmak",
    "gn:country_code":"KR",
    "gn:dem":122,
    "gn:feature_class":"P",
    "gn:feature_code":"PPL",
    "gn:name":"Unmak",
    "gn:population":0,
    "gn:timezone":"Asia/Seoul",
    "iso:country":"KR",
    "name:und_x_variant":[
        "\uc6c3\ub9c9",
        "Unmak"
    ],
    "wof:name":"Unmak",
    "wof:placetype":"locality"
},
  "geometry": {"coordinates":[128.67383999999998,35.63334000000001],"type":"Point"}
}