{
  "type": "Feature",
  "properties": {
    "gn:admin1_code":"14.0",
    "gn:asciiname":"Soran",
    "gn:country_code":"KR",
    "gn:dem":92,
    "gn:feature_class":"P",
    "gn:feature_code":"PPL",
    "gn:name":"Soran",
    "gn:population":0,
    "gn:timezone":"Asia/Seoul",
    "iso:country":"KR",
    "name:kor_x_preferred":[
        "\uc194\uc548"
    ],
    "wof:name":"Soran",
    "wof:placetype":"locality"
},
  "geometry": {"coordinates":[128.8287,35.78338],"type":"Point"}
}