{
  "type": "Feature",
  "properties": {
    "gn:admin1_code":"11.0",
    "gn:asciiname":"Kijach'on",
    "gn:country_code":"KR",
    "gn:dem":101,
    "gn:feature_class":"P",
    "gn:feature_code":"PPL",
    "gn:name":"Kijach\u2019on",
    "gn:population":0,
    "gn:timezone":"Asia/Seoul",
    "iso:country":"KR",
    "name:und_x_variant":[
        "\uae30\uc790\ucd0c",
        "Kijach\u2019on"
    ],
    "wof:name":"Kijach'on",
    "wof:placetype":"locality"
},
  "geometry": {"coordinates":[126.9344,37.6331],"type":"Point"}
}