{
  "type": "Feature",
  "properties": {
    "gn:admin1_code":"13.0",
    "gn:asciiname":"Dangap",
    "gn:country_code":"KR",
    "gn:dem":103,
    "gn:feature_class":"P",
    "gn:feature_code":"PPL",
    "gn:name":"Dangap",
    "gn:population":0,
    "gn:timezone":"Asia/Seoul",
    "iso:country":"KR",
    "name:kor_x_preferred":[
        "\ub2f9\uc55e"
    ],
    "name:und_x_variant":[
        "Tangap"
    ],
    "wof:name":"Dangap",
    "wof:placetype":"locality"
},
  "geometry": {"coordinates":[127.52263000000001,37.12956],"type":"Point"}
}