{
  "type": "Feature",
  "properties": {
    "gn:admin1_code":"3.0",
    "gn:asciiname":"P'yongda-ri",
    "gn:country_code":"KR",
    "gn:dem":241,
    "gn:feature_class":"P",
    "gn:feature_code":"PPL",
    "gn:name":"P\u2019y\u014fngda-ri",
    "gn:population":0,
    "gn:timezone":"Asia/Seoul",
    "iso:country":"KR",
    "name:und_x_variant":[
        "\ud3c9\ub2e4\ub9ac",
        "P\u2019y\u014fngda-ri"
    ],
    "wof:name":"P'yongda-ri",
    "wof:placetype":"locality"
},
  "geometry": {"coordinates":[127.29482,35.60901],"type":"Point"}
}