{
  "type": "Feature",
  "properties": {
    "gn:admin1_code":"20.0",
    "gn:asciiname":"Oryong-gol",
    "gn:country_code":"KR",
    "gn:dem":318,
    "gn:feature_class":"P",
    "gn:feature_code":"PPL",
    "gn:name":"Oryong-gol",
    "gn:population":0,
    "gn:timezone":"Asia/Seoul",
    "iso:country":"KR",
    "wof:name":"Oryong-gol",
    "wof:placetype":"locality"
},
  "geometry": {"coordinates":[129.02222,35.45944],"type":"Point"}
}