{
  "type": "Feature",
  "properties": {
    "gn:admin1_code":"6.0",
    "gn:asciiname":"Jangjaeul",
    "gn:country_code":"KR",
    "gn:dem":348,
    "gn:feature_class":"P",
    "gn:feature_code":"PPL",
    "gn:name":"Jangjaeul",
    "gn:population":0,
    "gn:timezone":"Asia/Seoul",
    "iso:country":"KR",
    "name:kor_x_preferred":[
        "\uc7a5\uc7ac\uc6b8"
    ],
    "name:und_x_variant":[
        "Changjaeul",
        "Jangjaeul"
    ],
    "wof:name":"Jangjaeul",
    "wof:placetype":"locality"
},
  "geometry": {"coordinates":[127.89521999999999,37.82603],"type":"Point"}
}