{
  "type": "Feature",
  "properties": {
    "gn:admin1_code":"14.0",
    "gn:asciiname":"Ansinyang",
    "gn:country_code":"KR",
    "gn:dem":137,
    "gn:feature_class":"P",
    "gn:feature_code":"PPL",
    "gn:name":"Ansinyang",
    "gn:population":0,
    "gn:timezone":"Asia/Seoul",
    "iso:country":"KR",
    "name:kor_x_preferred":[
        "\uc548\uc2e0\uc591"
    ],
    "wof:name":"Ansinyang",
    "wof:placetype":"locality"
},
  "geometry": {"coordinates":[128.55063999999999,36.61783],"type":"Point"}
}