{
  "type": "Feature",
  "properties": {
    "gn:admin1_code":"3.0",
    "gn:asciiname":"Wonbanwol",
    "gn:country_code":"KR",
    "gn:dem":347,
    "gn:feature_class":"P",
    "gn:feature_code":"PPL",
    "gn:name":"W\u014fnbanw\u014fl",
    "gn:population":0,
    "gn:timezone":"Asia/Seoul",
    "iso:country":"KR",
    "name:und_x_variant":[
        "Panw\u014fl-li",
        "\uc6d0\ubc18\uc6d4",
        "W\u014fnbanw\u014fl"
    ],
    "wof:name":"Wonbanwol",
    "wof:placetype":"locality"
},
  "geometry": {"coordinates":[127.43978,35.76217000000001],"type":"Point"}
}