{
  "type": "Feature",
  "properties": {
    "gn:admin1_code":"12.0",
    "gn:asciiname":"Gaegeonneo",
    "gn:country_code":"KR",
    "gn:dem":7,
    "gn:feature_class":"P",
    "gn:feature_code":"PPL",
    "gn:name":"Gaegeonneo",
    "gn:population":0,
    "gn:timezone":"Asia/Seoul",
    "iso:country":"KR",
    "name:kor_x_preferred":[
        "\uac1c\uac74\ub108"
    ],
    "wof:name":"Gaegeonneo",
    "wof:placetype":"locality"
},
  "geometry": {"coordinates":[126.29912,37.7217],"type":"Point"}
}