{
  "type": "Feature",
  "properties": {
    "gn:admin1_code":"6.0",
    "gn:asciiname":"Sinch'ol-li",
    "gn:country_code":"KR",
    "gn:dem":282,
    "gn:feature_class":"P",
    "gn:feature_code":"PPLL",
    "gn:name":"Sinch\u2019ol-li",
    "gn:population":0,
    "gn:timezone":"Asia/Seoul",
    "iso:country":"KR",
    "name:kor_x_preferred":[
        "\uc2e0\ucd0c\ub9ac"
    ],
    "name:kor_x_variant":[
        "Sinch\u2019ol-li"
    ],
    "wof:name":"Sinch'ol-li",
    "wof:placetype":"locality"
},
  "geometry": {"coordinates":[127.96877000000001,37.28927],"type":"Point"}
}