{
  "type": "Feature",
  "properties": {
    "gn:admin1_code":"6.0",
    "gn:asciiname":"Soch'on",
    "gn:country_code":"KR",
    "gn:dem":670,
    "gn:feature_class":"P",
    "gn:feature_code":"PPL",
    "gn:name":"S\u014fch\u2019\u014fn",
    "gn:population":0,
    "gn:timezone":"Asia/Seoul",
    "iso:country":"KR",
    "name:kor_x_preferred":[
        "\uc11c\ucc9c"
    ],
    "name:kor_x_variant":[
        "S\u014fch\u2019\u014fn"
    ],
    "wof:name":"Soch'on",
    "wof:placetype":"locality"
},
  "geometry": {"coordinates":[128.32650000000001,37.5371],"type":"Point"}
}