{
  "type": "Feature",
  "properties": {
    "gn:admin1_code":"6.0",
    "gn:asciiname":"Eumdalmal",
    "gn:country_code":"KR",
    "gn:dem":107,
    "gn:feature_class":"P",
    "gn:feature_code":"PPL",
    "gn:name":"Eumdalmal",
    "gn:population":0,
    "gn:timezone":"Asia/Seoul",
    "iso:country":"KR",
    "name:kor_x_preferred":[
        "\uc74c\ub2ec\ub9d0"
    ],
    "name:kor_x_variant":[
        "\u016cmdal-mal"
    ],
    "wof:name":"Eumdalmal",
    "wof:placetype":"locality"
},
  "geometry": {"coordinates":[128.6566,37.97838],"type":"Point"}
}