{
  "type": "Feature",
  "properties": {
    "gn:admin1_code":"13.0",
    "gn:asciiname":"Wonam-ri",
    "gn:country_code":"KR",
    "gn:dem":50,
    "gn:feature_class":"P",
    "gn:feature_code":"PPLL",
    "gn:name":"Wonam-ri",
    "gn:population":0,
    "gn:timezone":"Asia/Seoul",
    "iso:country":"KR",
    "name:und_x_variant":[
        "\uc6d0\uc554\ub9ac",
        "Wonam-ri",
        "W\u014fnam-ni"
    ],
    "wof:name":"Wonam-ri",
    "wof:placetype":"locality"
},
  "geometry": {"coordinates":[127.15528,37.09944],"type":"Point"}
}