{
  "type": "Feature",
  "properties": {
    "gn:admin1_code":"14.0",
    "gn:asciiname":"Pommorae",
    "gn:country_code":"KR",
    "gn:dem":17,
    "gn:feature_class":"P",
    "gn:feature_code":"PPL",
    "gn:name":"P\u014fmmorae",
    "gn:population":0,
    "gn:timezone":"Asia/Seoul",
    "iso:country":"KR",
    "name:und_x_variant":[
        "\ubc94\ubaa8\ub798",
        "P\u014fmmorae"
    ],
    "wof:name":"Pommorae",
    "wof:placetype":"locality"
},
  "geometry": {"coordinates":[129.42250000000001,36.722],"type":"Point"}
}