{
  "type": "Feature",
  "properties": {
    "gn:admin1_code":"6.0",
    "gn:asciiname":"Saemaeul",
    "gn:country_code":"KR",
    "gn:dem":212,
    "gn:feature_class":"P",
    "gn:feature_code":"PPL",
    "gn:name":"Saemaeul",
    "gn:population":0,
    "gn:timezone":"Asia/Seoul",
    "iso:country":"KR",
    "name:jpn_x_preferred":[
        "\u30bb\u30de\u30a6\u30eb"
    ],
    "name:kor_x_preferred":[
        "\uc0c8\ub9c8\uc744"
    ],
    "name:kor_x_variant":[
        "Saema\u016dl"
    ],
    "wof:name":"Saemaeul",
    "wof:placetype":"locality"
},
  "geometry": {"coordinates":[128.06721999999999,38.02722],"type":"Point"}
}