{
  "type": "Feature",
  "properties": {
    "gn:admin1_code":"5.0",
    "gn:asciiname":"T'aeso",
    "gn:country_code":"KR",
    "gn:dem":123,
    "gn:feature_class":"P",
    "gn:feature_code":"PPL",
    "gn:name":"T\u2019aeso",
    "gn:population":0,
    "gn:timezone":"Asia/Seoul",
    "iso:country":"KR",
    "name:und_x_variant":[
        "\ud0dc\uc18c",
        "T\u2019aeso"
    ],
    "wof:name":"T'aeso",
    "wof:placetype":"locality"
},
  "geometry": {"coordinates":[127.6878,36.1727],"type":"Point"}
}