{
  "type": "Feature",
  "properties": {
    "gn:admin1_code":"6.0",
    "gn:asciiname":"Hoek-kol",
    "gn:country_code":"KR",
    "gn:dem":373,
    "gn:feature_class":"P",
    "gn:feature_code":"PPL",
    "gn:name":"Hoek-kol",
    "gn:population":0,
    "gn:timezone":"Asia/Seoul",
    "iso:country":"KR",
    "wof:name":"Hoek-kol",
    "wof:placetype":"locality"
},
  "geometry": {"coordinates":[128.09138999999999,38.05056],"type":"Point"}
}