{
  "type": "Feature",
  "properties": {
    "gn:admin1_code":"5.0",
    "gn:asciiname":"Sinpyeong",
    "gn:country_code":"KR",
    "gn:dem":39,
    "gn:feature_class":"P",
    "gn:feature_code":"PPL",
    "gn:name":"Sinpyeong",
    "gn:population":0,
    "gn:timezone":"Asia/Seoul",
    "iso:country":"KR",
    "name:kor_x_preferred":[
        "\uc2e0\ud3c9"
    ],
    "wof:name":"Sinpyeong",
    "wof:placetype":"locality"
},
  "geometry": {"coordinates":[127.36902000000001,36.66478],"type":"Point"}
}