{
  "type": "Feature",
  "properties": {
    "gn:admin1_code":"20.0",
    "gn:asciiname":"Kosan",
    "gn:country_code":"KR",
    "gn:dem":8,
    "gn:feature_class":"P",
    "gn:feature_code":"PPL",
    "gn:name":"K\u014fsan",
    "gn:population":0,
    "gn:timezone":"Asia/Seoul",
    "iso:country":"KR",
    "name:ceb_x_preferred":[
        "Kosan"
    ],
    "name:swe_x_preferred":[
        "Kosan"
    ],
    "name:und_x_variant":[
        "K\u014fsan-ni",
        "\uac70\uc0b0",
        "K\u014fsan"
    ],
    "wof:name":"Kosan",
    "wof:placetype":"locality"
},
  "geometry": {"coordinates":[128.36596,35.0125],"type":"Point"}
}