{
  "type": "Feature",
  "properties": {
    "iso:country":"KR",
    "qs:name":"\ud314\ub8e1\ub3d9",
    "qs:name_adm0":"\ud55c\uad6d",
    "qs:name_adm1":"\uacbd\uc0c1\ub0a8\ub3c4",
    "qs:photos":5,
    "qs:photos_1k":1,
    "qs:photos_9k":1,
    "qs:photos_9r":1,
    "qs:photos_all":5,
    "qs:photos_sr":1,
    "qs:placetype":"LocalAdmin",
    "qs:pop_sr":"0",
    "wof:name":"\ud314\ub8e1\ub3d9",
    "wof:placetype":"localadmin"
},
  "geometry": {"coordinates":[128.63968800000001,35.232167],"type":"Point"}
}