{
  "type": "Feature",
  "properties": {
    "gn:admin1_code":"20.0",
    "gn:asciiname":"Usil",
    "gn:country_code":"KR",
    "gn:dem":57,
    "gn:feature_class":"P",
    "gn:feature_code":"PPL",
    "gn:name":"Usil",
    "gn:population":0,
    "gn:timezone":"Asia/Seoul",
    "iso:country":"KR",
    "name:fra_x_preferred":[
        "Usil"
    ],
    "name:und_x_variant":[
        "\uc6b0\uc2e4"
    ],
    "wof:name":"Usil",
    "wof:placetype":"locality"
},
  "geometry": {"coordinates":[128.27098999999998,34.97725],"type":"Point"}
}