{
  "type": "Feature",
  "properties": {
    "gn:admin1_code":"16.0",
    "gn:asciiname":"Jangdong",
    "gn:country_code":"KR",
    "gn:dem":66,
    "gn:feature_class":"P",
    "gn:feature_code":"PPL",
    "gn:name":"Jangdong",
    "gn:population":0,
    "gn:timezone":"Asia/Seoul",
    "iso:country":"KR",
    "name:kor_x_preferred":[
        "\uc7a5\ub3d9"
    ],
    "name:und_x_variant":[
        "Sh\u014dd\u014d-ri",
        "Changd\u014fng-ni",
        "Changdong",
        "Jangdong"
    ],
    "wof:name":"Jangdong",
    "wof:placetype":"locality"
},
  "geometry": {"coordinates":[127.35053000000001,34.80704],"type":"Point"}
}