{
  "type": "Feature",
  "properties": {
    "gn:admin1_code":"16.0",
    "gn:asciiname":"Shitei-ri",
    "gn:country_code":"KR",
    "gn:dem":31,
    "gn:feature_class":"P",
    "gn:feature_code":"PPL",
    "gn:name":"Shitei-ri",
    "gn:population":0,
    "gn:timezone":"Asia/Seoul",
    "iso:country":"KR",
    "name:und_x_variant":[
        "Chij\u014fngilgu",
        "Chij\u014fng",
        "Chij\u014fng-ni"
    ],
    "wof:name":"Shitei-ri",
    "wof:placetype":"locality"
},
  "geometry": {"coordinates":[126.88667,34.51306],"type":"Point"}
}