{
  "type": "Feature",
  "properties": {
    "gn:admin1_code":"14.0",
    "gn:asciiname":"Yongnak",
    "gn:country_code":"KR",
    "gn:dem":56,
    "gn:feature_class":"P",
    "gn:feature_code":"PPL",
    "gn:name":"Yongnak",
    "gn:population":0,
    "gn:timezone":"Asia/Seoul",
    "iso:country":"KR",
    "name:kor_x_preferred":[
        "\uc6a9\ub77d"
    ],
    "wof:name":"Yongnak",
    "wof:placetype":"locality"
},
  "geometry": {"coordinates":[129.27688000000001,35.86686],"type":"Point"}
}