{
  "type": "Feature",
  "properties": {
    "gn:admin1_code":"13.0",
    "gn:asciiname":"Ssangjong-ri",
    "gn:country_code":"KR",
    "gn:dem":12,
    "gn:feature_class":"P",
    "gn:feature_code":"PPL",
    "gn:name":"Ssangj\u014fng-ri",
    "gn:population":0,
    "gn:timezone":"Asia/Seoul",
    "iso:country":"KR",
    "name:kor_x_preferred":[
        "\uc30d\uc815\ub9ac"
    ],
    "name:kor_x_variant":[
        "Ssangj\u014fng-ri"
    ],
    "wof:name":"Ssangjong-ri",
    "wof:placetype":"locality"
},
  "geometry": {"coordinates":[126.73694,37.23111],"type":"Point"}
}