{
  "type": "Feature",
  "properties": {
    "gn:admin1_code":"20.0",
    "gn:asciiname":"Songsansaettam",
    "gn:country_code":"KR",
    "gn:dem":462,
    "gn:feature_class":"P",
    "gn:feature_code":"PPL",
    "gn:name":"Songsansaettam",
    "gn:population":0,
    "gn:timezone":"Asia/Seoul",
    "iso:country":"KR",
    "name:und_x_variant":[
        "\uc1a1\uc0b0\uc0db\ub2f4",
        "Songsansaettam"
    ],
    "wof:name":"Songsansaettam",
    "wof:placetype":"locality"
},
  "geometry": {"coordinates":[127.90873000000001,35.85406],"type":"Point"}
}