{
  "type": "Feature",
  "properties": {
    "gn:admin1_code":"17.0",
    "gn:asciiname":"Soktu-ri",
    "gn:country_code":"KR",
    "gn:dem":20,
    "gn:feature_class":"P",
    "gn:feature_code":"PPL",
    "gn:name":"S\u014fktu-ri",
    "gn:population":0,
    "gn:timezone":"Asia/Seoul",
    "iso:country":"KR",
    "name:und_x_variant":[
        "\uc11d\ub450\ub9ac",
        "S\u014fktu-ri"
    ],
    "wof:name":"Soktu-ri",
    "wof:placetype":"locality"
},
  "geometry": {"coordinates":[126.99464999999999,36.81442],"type":"Point"}
}