{
  "type": "Feature",
  "properties": {
    "gn:admin1_code":"15.0",
    "gn:asciiname":"Moran",
    "gn:country_code":"KR",
    "gn:dem":25,
    "gn:feature_class":"P",
    "gn:feature_code":"PPL",
    "gn:name":"Moran",
    "gn:population":0,
    "gn:timezone":"Asia/Seoul",
    "iso:country":"KR",
    "name:und_x_variant":[
        "\ubaa8\ub780",
        "Moran"
    ],
    "wof:name":"Moran",
    "wof:placetype":"locality"
},
  "geometry": {"coordinates":[128.41808,35.62355],"type":"Point"}
}