{
  "type": "Feature",
  "properties": {
    "gn:admin1_code":"17.0",
    "gn:asciiname":"Todok-kol",
    "gn:country_code":"KR",
    "gn:dem":96,
    "gn:feature_class":"P",
    "gn:feature_code":"PPL",
    "gn:name":"Tod\u014fk-kol",
    "gn:population":0,
    "gn:timezone":"Asia/Seoul",
    "iso:country":"KR",
    "name:und_x_variant":[
        "\ub3c4\ub355\uace8",
        "Tod\u014fk-kol"
    ],
    "wof:name":"Todok-kol",
    "wof:placetype":"locality"
},
  "geometry": {"coordinates":[126.8811,36.5695],"type":"Point"}
}