{
  "type": "Feature",
  "properties": {
    "gn:admin1_code":"13.0",
    "gn:asciiname":"Baekhyeon",
    "gn:country_code":"KR",
    "gn:dem":66,
    "gn:feature_class":"P",
    "gn:feature_code":"PPL",
    "gn:name":"Baekhyeon",
    "gn:population":0,
    "gn:timezone":"Asia/Seoul",
    "iso:country":"KR",
    "name:kor_x_preferred":[
        "\ubc31\ud604"
    ],
    "name:und_x_variant":[
        "\ubc31\ud604",
        "Baekhyeon"
    ],
    "wof:name":"Baekhyeon",
    "wof:placetype":"locality"
},
  "geometry": {"coordinates":[127.4756,37.5277],"type":"Point"}
}