{
  "type": "Feature",
  "properties": {
    "gn:admin1_code":"17.0",
    "gn:asciiname":"Unch'ol-li",
    "gn:country_code":"KR",
    "gn:dem":29,
    "gn:feature_class":"P",
    "gn:feature_code":"PPL",
    "gn:name":"Unch\u2019\u014fl-li",
    "gn:population":0,
    "gn:timezone":"Asia/Seoul",
    "iso:country":"KR",
    "name:und_x_variant":[
        "\uc6b4\ucc9c\ub9ac",
        "Unch\u2019\u014fl-li"
    ],
    "wof:name":"Unch'ol-li",
    "wof:placetype":"locality"
},
  "geometry": {"coordinates":[127.0625,36.3997],"type":"Point"}
}