{
  "type": "Feature",
  "properties": {
    "gn:admin1_code":"16.0",
    "gn:asciiname":"Sindong",
    "gn:country_code":"KR",
    "gn:dem":49,
    "gn:feature_class":"P",
    "gn:feature_code":"PPL",
    "gn:name":"Sindong",
    "gn:population":0,
    "gn:timezone":"Asia/Seoul",
    "iso:country":"KR",
    "name:kor_x_preferred":[
        "\uc2e0\ub3d9"
    ],
    "wof:name":"Sindong",
    "wof:placetype":"locality"
},
  "geometry": {"coordinates":[126.77451000000001,34.71850999999999],"type":"Point"}
}