{
  "type": "Feature",
  "properties": {
    "gn:admin1_code":"12.0",
    "gn:admin2_code":"Kanghwa-gun",
    "gn:asciiname":"Yangchon",
    "gn:country_code":"KR",
    "gn:dem":19,
    "gn:feature_class":"P",
    "gn:feature_code":"PPL",
    "gn:name":"Yangchon",
    "gn:population":0,
    "gn:timezone":"Asia/Seoul",
    "iso:country":"KR",
    "name:kor_x_preferred":[
        "\uc591\ucd0c"
    ],
    "name:und_x_variant":[
        "Soyang-ch\u2019on",
        "Yang-ch\u2019on",
        "Yangchon"
    ],
    "wof:name":"Yangchon",
    "wof:placetype":"locality"
},
  "geometry": {"coordinates":[126.42943,37.81119],"type":"Point"}
}