{
  "type": "Feature",
  "properties": {
    "gn:admin1_code":"12.0",
    "gn:asciiname":"Gonggae",
    "gn:country_code":"KR",
    "gn:dem":22,
    "gn:feature_class":"P",
    "gn:feature_code":"PPL",
    "gn:name":"Gonggae",
    "gn:population":0,
    "gn:timezone":"Asia/Seoul",
    "iso:country":"KR",
    "name:und_x_variant":[
        "\uacf5\uac1c",
        "Gonggae",
        "Konggae"
    ],
    "wof:name":"Gonggae",
    "wof:placetype":"locality"
},
  "geometry": {"coordinates":[126.35389000000001,37.68778],"type":"Point"}
}