{
  "type": "Feature",
  "properties": {
    "gn:admin1_code":"5.0",
    "gn:asciiname":"Balteo",
    "gn:country_code":"KR",
    "gn:dem":51,
    "gn:feature_class":"P",
    "gn:feature_code":"PPL",
    "gn:name":"Balteo",
    "gn:population":0,
    "gn:timezone":"Asia/Seoul",
    "iso:country":"KR",
    "name:kor_x_preferred":[
        "\ubc2d\ud130"
    ],
    "name:und_x_variant":[
        "Patt\u2019\u014f"
    ],
    "wof:name":"Balteo",
    "wof:placetype":"locality"
},
  "geometry": {"coordinates":[127.49056000000002,36.68306],"type":"Point"}
}