{
  "type": "Feature",
  "properties": {
    "gn:admin1_code":"6.0",
    "gn:asciiname":"Naruttuduk",
    "gn:country_code":"KR",
    "gn:dem":188,
    "gn:feature_class":"P",
    "gn:feature_code":"PPL",
    "gn:name":"Naruttuduk",
    "gn:population":0,
    "gn:timezone":"Asia/Seoul",
    "iso:country":"KR",
    "name:kor_x_preferred":[
        "\ub098\ub8e8\ub69c\ub451"
    ],
    "wof:name":"Naruttuduk",
    "wof:placetype":"locality"
},
  "geometry": {"coordinates":[128.53569999999999,37.131],"type":"Point"}
}