{
  "type": "Feature",
  "properties": {
    "gn:admin1_code":"3.0",
    "gn:asciiname":"Kusang",
    "gn:country_code":"KR",
    "gn:dem":297,
    "gn:feature_class":"P",
    "gn:feature_code":"PPL",
    "gn:name":"Kusang",
    "gn:population":0,
    "gn:timezone":"Asia/Seoul",
    "iso:country":"KR",
    "name:und_x_variant":[
        "\uad6c\uc0c1",
        "Kusang"
    ],
    "wof:name":"Kusang",
    "wof:placetype":"locality"
},
  "geometry": {"coordinates":[127.54459,35.78947],"type":"Point"}
}