{
  "type": "Feature",
  "properties": {
    "gn:admin1_code":"14.0",
    "gn:asciiname":"Ijon",
    "gn:country_code":"KR",
    "gn:dem":298,
    "gn:feature_class":"P",
    "gn:feature_code":"PPL",
    "gn:name":"Ij\u014fn",
    "gn:population":0,
    "gn:timezone":"Asia/Seoul",
    "iso:country":"KR",
    "name:und_x_variant":[
        "Ij\u014fn-dong",
        "Ij\u014fn"
    ],
    "wof:name":"Ijon",
    "wof:placetype":"locality"
},
  "geometry": {"coordinates":[129.16040000000001,36.3575],"type":"Point"}
}