{
  "type": "Feature",
  "properties": {
    "gn:admin1_code":"13.0",
    "gn:asciiname":"Chigot",
    "gn:country_code":"KR",
    "gn:dem":52,
    "gn:feature_class":"P",
    "gn:feature_code":"PPL",
    "gn:name":"Chigot",
    "gn:population":0,
    "gn:timezone":"Asia/Seoul",
    "iso:country":"KR",
    "name:und_x_variant":[
        "\uc9c0\uacf6",
        "Jigot",
        "Chigot"
    ],
    "wof:name":"Chigot",
    "wof:placetype":"locality"
},
  "geometry": {"coordinates":[127.02333,37.17833],"type":"Point"}
}