{
  "type": "Feature",
  "properties": {
    "gn:admin1_code":"16.0",
    "gn:asciiname":"Hyorye",
    "gn:country_code":"KR",
    "gn:dem":32,
    "gn:feature_class":"P",
    "gn:feature_code":"PPL",
    "gn:name":"Hyorye",
    "gn:population":0,
    "gn:timezone":"Asia/Seoul",
    "iso:country":"KR",
    "name:kor_x_preferred":[
        "\ud6a8\ub840"
    ],
    "wof:name":"Hyorye",
    "wof:placetype":"locality"
},
  "geometry": {"coordinates":[126.75154999999999,35.09113],"type":"Point"}
}