{
  "type": "Feature",
  "properties": {
    "gn:admin1_code":"19.0",
    "gn:asciiname":"Hanch'ol-li",
    "gn:country_code":"KR",
    "gn:dem":96,
    "gn:feature_class":"P",
    "gn:feature_code":"PPL",
    "gn:name":"Hanch\u2019\u014fl-li",
    "gn:population":0,
    "gn:timezone":"Asia/Seoul",
    "iso:country":"KR",
    "name:und_x_variant":[
        "\ud55c\ucc9c\ub9ac",
        "Hanch\u2019\u014fl-li"
    ],
    "wof:name":"Hanch'ol-li",
    "wof:placetype":"locality"
},
  "geometry": {"coordinates":[127.3222,36.2849],"type":"Point"}
}