{
  "type": "Feature",
  "properties": {
    "gn:admin1_code":"14.0",
    "gn:asciiname":"Sopbanmit",
    "gn:country_code":"KR",
    "gn:dem":10,
    "gn:feature_class":"P",
    "gn:feature_code":"PPL",
    "gn:name":"S\u014fpbanmit",
    "gn:population":0,
    "gn:timezone":"Asia/Seoul",
    "iso:country":"KR",
    "name:und_x_variant":[
        "\uc136\ubc2d\ubc11",
        "S\u014fppatmit",
        "S\u014fpbanmit"
    ],
    "wof:name":"Sopbanmit",
    "wof:placetype":"locality"
},
  "geometry": {"coordinates":[129.43289999999999,36.6674],"type":"Point"}
}