{
  "type": "Feature",
  "properties": {
    "iso:country":"KR",
    "name:ara_x_preferred":[
        "\u062a\u0627\u064a\u0622\u0646"
    ],
    "name:ceb_x_preferred":[
        "Taean-gun"
    ],
    "name:ces_x_preferred":[
        "Tch\u00e4an"
    ],
    "name:eng_x_preferred":[
        "Taean County"
    ],
    "name:fas_x_preferred":[
        "\u0634\u0647\u0631\u0633\u062a\u0627\u0646 \u062a\u0627\u0627\u0646"
    ],
    "name:hak_x_preferred":[
        "Thai-\u00f4n-khi\u00f9n"
    ],
    "name:ind_x_preferred":[
        "Daerah Taean"
    ],
    "name:jpn_x_preferred":[
        "\u6cf0\u5b89\u90e1"
    ],
    "name:kor_x_preferred":[
        "\ud0dc\uc548\uad70"
    ],
    "name:mon_x_preferred":[
        "\u0422\u044d\u0430\u043d\u044c-\u0433\u04af\u043d\u044c"
    ],
    "name:nan_x_preferred":[
        "Taean K\u016bn"
    ],
    "name:nld_x_preferred":[
        "Taean County"
    ],
    "name:nob_x_preferred":[
        "Taean"
    ],
    "name:rus_x_preferred":[
        "\u0422\u0445\u044d\u0430\u043d"
    ],
    "name:slk_x_preferred":[
        "Tch\u00e4an"
    ],
    "name:spa_x_preferred":[
        "Taean"
    ],
    "name:swe_x_preferred":[
        "Taean"
    ],
    "name:urd_x_preferred":[
        "\u062a\u0627\u0626\u0627\u0646 \u06a9\u0627\u0624\u0646\u0679\u06cc"
    ],
    "name:vie_x_preferred":[
        "Taean"
    ],
    "name:zho_x_preferred":[
        "\u6cf0\u5b89\u90e1"
    ],
    "qs:name":"\ub0a8\uba74",
    "qs:name_adm0":"\ud55c\uad6d",
    "qs:name_adm1":"\ucda9\uccad\ub0a8\ub3c4",
    "qs:photos":105,
    "qs:photos_1k":21,
    "qs:photos_9k":1,
    "qs:photos_9r":3,
    "qs:photos_all":105,
    "qs:photos_sr":3,
    "qs:placetype":"LocalAdmin",
    "qs:pop_sr":"0",
    "wd:wordcount":354,
    "wof:name":"\ub0a8\uba74",
    "wof:placetype":"localadmin"
},
  "geometry": {"coordinates":[126.284408,36.670808],"type":"Point"}
}