{
  "type": "Feature",
  "properties": {
    "iso:country":"KR",
    "qs:name":"\ub0a8\uba74",
    "qs:name_adm0":"\ud55c\uad6d",
    "qs:name_adm1":"\ucda9\uccad\ub0a8\ub3c4",
    "qs:photos":105,
    "qs:photos_1k":21,
    "qs:photos_9k":1,
    "qs:photos_9r":3,
    "qs:photos_all":105,
    "qs:photos_sr":3,
    "qs:placetype":"LocalAdmin",
    "qs:pop_sr":"0",
    "wd:wordcount":354,
    "wof:name":"\ub0a8\uba74",
    "wof:placetype":"localadmin"
},
  "geometry": {"coordinates":[126.284408,36.670808],"type":"Point"}
}