{
  "type": "Feature",
  "properties": {
    "gn:admin1_code":"13.0",
    "gn:admin2_code":"Ans\u014fng-si",
    "gn:asciiname":"Gahyeon",
    "gn:country_code":"KR",
    "gn:dem":34,
    "gn:feature_class":"P",
    "gn:feature_code":"PPL",
    "gn:name":"Gahyeon",
    "gn:population":0,
    "gn:timezone":"Asia/Seoul",
    "iso:country":"KR",
    "name:kor_x_preferred":[
        "\uac00\ud604"
    ],
    "name:kor_x_variant":[
        "Kahy\u014fn"
    ],
    "wof:name":"Gahyeon",
    "wof:placetype":"locality"
},
  "geometry": {"coordinates":[127.28767999999999,37.0079],"type":"Point"}
}