{
  "type": "Feature",
  "properties": {
    "gn:admin1_code":"16.0",
    "gn:asciiname":"Geonseoljigol",
    "gn:country_code":"KR",
    "gn:dem":18,
    "gn:feature_class":"P",
    "gn:feature_code":"PPL",
    "gn:name":"Geonseoljigol",
    "gn:population":0,
    "gn:timezone":"Asia/Seoul",
    "iso:country":"KR",
    "name:kor_x_preferred":[
        "\uac74\uc124\uc9c0\uace8"
    ],
    "wof:name":"Geonseoljigol",
    "wof:placetype":"locality"
},
  "geometry": {"coordinates":[126.76858,34.98453],"type":"Point"}
}