{
  "type": "Feature",
  "properties": {
    "gn:admin1_code":"21.0",
    "gn:asciiname":"Sindang",
    "gn:cc2":"KR",
    "gn:country_code":"KR",
    "gn:dem":120,
    "gn:feature_class":"P",
    "gn:feature_code":"PPL",
    "gn:name":"Sindang",
    "gn:population":0,
    "gn:timezone":"Asia/Seoul",
    "iso:country":"KR",
    "name:und_x_variant":[
        "Shindang",
        "Sindang"
    ],
    "wof:name":"Sindang",
    "wof:placetype":"locality"
},
  "geometry": {"coordinates":[129.14250000000001,35.61722],"type":"Point"}
}