{
  "type": "Feature",
  "properties": {
    "gn:admin1_code":"3.0",
    "gn:asciiname":"Turak",
    "gn:country_code":"KR",
    "gn:dem":443,
    "gn:feature_class":"P",
    "gn:feature_code":"PPL",
    "gn:name":"Turak",
    "gn:population":0,
    "gn:timezone":"Asia/Seoul",
    "iso:country":"KR",
    "name:und_x_variant":[
        "\ub450\ub77d",
        "Turak"
    ],
    "wof:name":"Turak",
    "wof:placetype":"locality"
},
  "geometry": {"coordinates":[127.62213,35.51809],"type":"Point"}
}