{
  "type": "Feature",
  "properties": {
    "gn:admin1_code":"18.0",
    "gn:asciiname":"Sinch'ang-dong",
    "gn:country_code":"KR",
    "gn:dem":19,
    "gn:feature_class":"P",
    "gn:feature_code":"PPLL",
    "gn:name":"Sinch\u2019ang-dong",
    "gn:population":0,
    "gn:timezone":"Asia/Seoul",
    "iso:country":"KR",
    "name:und_x_variant":[
        "Sinch\u2019ang-ni",
        "Sinch\u2019ang-dong"
    ],
    "wof:name":"Sinch'ang-dong",
    "wof:placetype":"locality"
},
  "geometry": {"coordinates":[126.85083,35.18778],"type":"Point"}
}