{
  "type": "Feature",
  "properties": {
    "gn:admin1_code":"14.0",
    "gn:asciiname":"Angoil",
    "gn:country_code":"KR",
    "gn:dem":210,
    "gn:feature_class":"P",
    "gn:feature_code":"PPL",
    "gn:name":"Angoil",
    "gn:population":0,
    "gn:timezone":"Asia/Seoul",
    "iso:country":"KR",
    "name:und_x_variant":[
        "\uc548\uace0\uc77c",
        "An\u2019goil",
        "Angoil"
    ],
    "wof:name":"Angoil",
    "wof:placetype":"locality"
},
  "geometry": {"coordinates":[128.82991000000001,36.46714],"type":"Point"}
}