{
  "type": "Feature",
  "properties": {
    "iso:country":"KR",
    "name:eng_x_preferred":[
        "Hoecheon 4(sa)-dong"
    ],
    "name:kor_x_preferred":[
        "\ud68c\ucc9c4\ub3d9"
    ],
    "qs:name":"\ud68c\ucc9c4\ub3d9",
    "qs:name_adm0":"\ud55c\uad6d",
    "qs:name_adm1":"\uacbd\uae30\ub3c4",
    "qs:photos":1,
    "qs:photos_1k":1,
    "qs:photos_9k":1,
    "qs:photos_9r":1,
    "qs:photos_all":1,
    "qs:photos_sr":1,
    "qs:placetype":"LocalAdmin",
    "qs:pop_sr":"0",
    "wof:name":"Hoecheon 4(sa)-dong",
    "wof:placetype":"localadmin"
},
  "geometry": {"coordinates":[126.96693399999999,37.71859],"type":"Point"}
}