{
  "type": "Feature",
  "properties": {
    "gn:admin1_code":"16.0",
    "gn:asciiname":"Seojeong",
    "gn:country_code":"KR",
    "gn:dem":51,
    "gn:feature_class":"P",
    "gn:feature_code":"PPL",
    "gn:name":"Seojeong",
    "gn:population":0,
    "gn:timezone":"Asia/Seoul",
    "iso:country":"KR",
    "name:kor_x_preferred":[
        "\uc6b4\ubcf8"
    ],
    "name:kor_x_variant":[
        "Songj\u014fng",
        "\uc11c\uc815"
    ],
    "name:und_x_variant":[
        "Unbon"
    ],
    "wof:name":"Seojeong",
    "wof:placetype":"locality"
},
  "geometry": {"coordinates":[126.55174,34.38612],"type":"Point"}
}