{
  "type": "Feature",
  "properties": {
    "gn:admin1_code":"13.0",
    "gn:asciiname":"Onjae-mal",
    "gn:country_code":"KR",
    "gn:dem":43,
    "gn:feature_class":"P",
    "gn:feature_code":"PPL",
    "gn:name":"\u014enjae-mal",
    "gn:population":0,
    "gn:timezone":"Asia/Seoul",
    "iso:country":"KR",
    "name:kor_x_preferred":[
        "\uc5b8\uc7ac\ub9d0"
    ],
    "name:und_x_variant":[
        "\uc5b8\uc7ac\ub9d0",
        "\u014enjae-mal"
    ],
    "wof:name":"Onjae-mal",
    "wof:placetype":"locality"
},
  "geometry": {"coordinates":[127.1444,37.6379],"type":"Point"}
}