{
  "type": "Feature",
  "properties": {
    "gn:admin1_code":"14.0",
    "gn:asciiname":"Somma",
    "gn:country_code":"KR",
    "gn:dem":88,
    "gn:feature_class":"P",
    "gn:feature_code":"PPL",
    "gn:name":"S\u014fmma",
    "gn:population":0,
    "gn:timezone":"Asia/Seoul",
    "iso:country":"KR",
    "name:und_x_variant":[
        "\uc12c\ub9c8",
        "S\u014fmma"
    ],
    "wof:name":"Somma",
    "wof:placetype":"locality"
},
  "geometry": {"coordinates":[128.23057,35.75761],"type":"Point"}
}