{
  "type": "Feature",
  "properties": {
    "gn:admin1_code":"12.0",
    "gn:asciiname":"Ichonmal",
    "gn:country_code":"KR",
    "gn:dem":24,
    "gn:feature_class":"P",
    "gn:feature_code":"PPL",
    "gn:name":"Ichonmal",
    "gn:population":0,
    "gn:timezone":"Asia/Seoul",
    "iso:country":"KR",
    "name:und_x_variant":[
        "\uc774\ucd0c\ub9d0",
        "Ich\u2019onmal",
        "Ichonmal"
    ],
    "wof:name":"Ichonmal",
    "wof:placetype":"locality"
},
  "geometry": {"coordinates":[126.29604999999999,37.70373],"type":"Point"}
}