{
  "type": "Feature",
  "properties": {
    "gn:admin1_code":"13.0",
    "gn:asciiname":"Burodong",
    "gn:country_code":"KR",
    "gn:dem":88,
    "gn:feature_class":"P",
    "gn:feature_code":"PPL",
    "gn:name":"Burodong",
    "gn:population":0,
    "gn:timezone":"Asia/Seoul",
    "iso:country":"KR",
    "name:kor_x_preferred":[
        "\ubd80\ub85c\ub3d9"
    ],
    "name:und_x_variant":[
        "Puro-dong"
    ],
    "wof:name":"Burodong",
    "wof:placetype":"locality"
},
  "geometry": {"coordinates":[127.52885000000001,37.08695],"type":"Point"}
}