{
  "type": "Feature",
  "properties": {
    "gn:admin1_code":"15.0",
    "gn:asciiname":"Jangseongbak",
    "gn:country_code":"KR",
    "gn:dem":41,
    "gn:feature_class":"P",
    "gn:feature_code":"PPL",
    "gn:name":"Jangseongbak",
    "gn:population":0,
    "gn:timezone":"Asia/Seoul",
    "iso:country":"KR",
    "name:kor_x_preferred":[
        "\uc7a5\uc131\ubc15"
    ],
    "wof:name":"Jangseongbak",
    "wof:placetype":"locality"
},
  "geometry": {"coordinates":[128.45311999999998,35.64295999999999],"type":"Point"}
}