{
  "type": "Feature",
  "properties": {
    "gn:admin1_code":"17.0",
    "gn:asciiname":"Dukkeommal",
    "gn:country_code":"KR",
    "gn:dem":56,
    "gn:feature_class":"P",
    "gn:feature_code":"PPL",
    "gn:name":"Dukkeommal",
    "gn:population":0,
    "gn:timezone":"Asia/Seoul",
    "iso:country":"KR",
    "name:kor_x_preferred":[
        "\ub450\uaecc\ub9d0"
    ],
    "wof:name":"Dukkeommal",
    "wof:placetype":"locality"
},
  "geometry": {"coordinates":[127.16160000000001,36.31837],"type":"Point"}
}