{
  "type": "Feature",
  "properties": {
    "gn:admin1_code":"18.0",
    "gn:asciiname":"Gujangteo",
    "gn:country_code":"KR",
    "gn:dem":18,
    "gn:feature_class":"P",
    "gn:feature_code":"PPL",
    "gn:name":"Gujangteo",
    "gn:population":0,
    "gn:timezone":"Asia/Seoul",
    "iso:country":"KR",
    "name:kor_x_preferred":[
        "\uad6c\uc7a5\ud130"
    ],
    "name:und_x_variant":[
        "Kujangt\u2019\u014f"
    ],
    "wof:name":"Gujangteo",
    "wof:placetype":"locality"
},
  "geometry": {"coordinates":[126.78264,35.14548],"type":"Point"}
}