{
  "type": "Feature",
  "properties": {
    "gn:admin1_code":"1.0",
    "gn:admin2_code":"S\u014fgwip'o-si",
    "gn:asciiname":"Hawon-dong",
    "gn:country_code":"KR",
    "gn:dem":108,
    "gn:feature_class":"P",
    "gn:feature_code":"PPL",
    "gn:name":"Haw\u014fn-dong",
    "gn:population":0,
    "gn:timezone":"Asia/Seoul",
    "iso:country":"KR",
    "name:und_x_variant":[
        "Haw\u014fn-ni",
        "Haw\u014fn-dong"
    ],
    "wof:name":"Hawon-dong",
    "wof:placetype":"locality"
},
  "geometry": {"coordinates":[126.45944,33.25583],"type":"Point"}
}