{
  "type": "Feature",
  "properties": {
    "gn:admin1_code":"3.0",
    "gn:asciiname":"Sin'gyewol",
    "gn:country_code":"KR",
    "gn:dem":194,
    "gn:feature_class":"P",
    "gn:feature_code":"PPL",
    "gn:name":"Sin\u2019gyew\u014fl",
    "gn:population":0,
    "gn:timezone":"Asia/Seoul",
    "iso:country":"KR",
    "name:und_x_variant":[
        "\uc2e0\uacc4\uc6d4",
        "Sin\u2019gyew\u014fl"
    ],
    "wof:name":"Sin'gyewol",
    "wof:placetype":"locality"
},
  "geometry": {"coordinates":[127.33116,35.60295],"type":"Point"}
}