{
  "type": "Feature",
  "properties": {
    "gn:admin1_code":"14.0",
    "gn:asciiname":"Deungneomeo",
    "gn:country_code":"KR",
    "gn:dem":102,
    "gn:feature_class":"P",
    "gn:feature_code":"PPL",
    "gn:name":"Deungneomeo",
    "gn:population":0,
    "gn:timezone":"Asia/Seoul",
    "iso:country":"KR",
    "name:kor_x_preferred":[
        "\ub4f1\ub118\uc5b4"
    ],
    "wof:name":"Deungneomeo",
    "wof:placetype":"locality"
},
  "geometry": {"coordinates":[128.39258999999998,36.61436],"type":"Point"}
}