{
  "type": "Feature",
  "properties": {
    "iso:country":"KR",
    "name:eng_x_preferred":[
        "Jwa-dong"
    ],
    "name:kor_x_preferred":[
        "\uc88c\ub3d9"
    ],
    "name:kor_x_variant":[
        "\uc88c\ub3d9"
    ],
    "qs:gn_adm0_cc":"KR",
    "qs:gn_local":1838524,
    "qs:local_max":2765,
    "qs:local_sum":24552,
    "qs:localhoods":60,
    "qs:name":"\uc88c\ub3d9",
    "qs:name_adm0":"\ud55c\uad6d",
    "qs:name_adm1":"\ubd80\uc0b0",
    "qs:name_adm2":"\ud574\uc6b4\ub300\uad6c",
    "qs:name_local":"\ubd80\uc0b0",
    "qs:photo_max":285,
    "qs:photo_sum":1439,
    "qs:placetype":"Suburb",
    "qs:quad_count":46,
    "qs:woe_adm0":23424868,
    "qs:woe_adm1":2345968,
    "qs:woe_adm2":28289197,
    "qs:woe_lau":0,
    "qs:woe_local":1132447,
    "qs:woe_ver":"7.10.0",
    "wof:lang":[
        "kor"
    ],
    "wof:name":"Jwa-dong",
    "wof:placetype":"neighbourhood"
},
  "geometry": {"coordinates":[129.15709100000001,35.158866],"type":"Point"}
}