{
  "type": "Feature",
  "properties": {
    "gn:admin1_code":"20.0",
    "gn:asciiname":"Sanp'o",
    "gn:country_code":"KR",
    "gn:dem":517,
    "gn:feature_class":"P",
    "gn:feature_code":"PPL",
    "gn:name":"Sanp\u2019o",
    "gn:population":0,
    "gn:timezone":"Asia/Seoul",
    "iso:country":"KR",
    "name:und_x_variant":[
        "\uc0b0\ud3ec",
        "Sanp\u2019o"
    ],
    "wof:name":"Sanp'o",
    "wof:placetype":"locality"
},
  "geometry": {"coordinates":[127.83777000000001,35.84484000000001],"type":"Point"}
}