{
  "type": "Feature",
  "properties": {
    "gn:admin1_code":"20.0",
    "gn:asciiname":"Hadok",
    "gn:cc2":"KR",
    "gn:country_code":"KR",
    "gn:dem":57,
    "gn:feature_class":"P",
    "gn:feature_code":"PPL",
    "gn:name":"Had\u014fk",
    "gn:population":0,
    "gn:timezone":"Asia/Seoul",
    "iso:country":"KR",
    "name:und_x_variant":[
        "Had\u014fng-ni",
        "Had\u014fk"
    ],
    "wof:name":"Hadok",
    "wof:placetype":"locality"
},
  "geometry": {"coordinates":[128.70639,34.90778],"type":"Point"}
}