{
  "type": "Feature",
  "properties": {
    "gn:admin1_code":"14.0",
    "gn:asciiname":"Hacho",
    "gn:country_code":"KR",
    "gn:dem":229,
    "gn:feature_class":"P",
    "gn:feature_code":"PPL",
    "gn:name":"Hacho",
    "gn:population":0,
    "gn:timezone":"Asia/Seoul",
    "iso:country":"KR",
    "name:kor_x_preferred":[
        "\ud558\ucd08"
    ],
    "wof:name":"Hacho",
    "wof:placetype":"locality"
},
  "geometry": {"coordinates":[128.08653000000001,36.75197],"type":"Point"}
}