{
  "type": "Feature",
  "properties": {
    "gn:admin1_code":"14.0",
    "gn:asciiname":"Musil",
    "gn:country_code":"KR",
    "gn:dem":86,
    "gn:feature_class":"P",
    "gn:feature_code":"PPL",
    "gn:name":"Musil",
    "gn:population":0,
    "gn:timezone":"Asia/Seoul",
    "iso:country":"KR",
    "name:slk_x_preferred":[
        "Musil"
    ],
    "name:und_x_variant":[
        "\ubb34\uc2e4",
        "Musil"
    ],
    "wof:name":"Musil",
    "wof:placetype":"locality"
},
  "geometry": {"coordinates":[128.1542,36.1151],"type":"Point"}
}