{
  "type": "Feature",
  "properties": {
    "gn:admin1_code":"5.0",
    "gn:asciiname":"Bakdaesil",
    "gn:country_code":"KR",
    "gn:dem":208,
    "gn:feature_class":"P",
    "gn:feature_code":"PPL",
    "gn:name":"Bakdaesil",
    "gn:population":0,
    "gn:timezone":"Asia/Seoul",
    "iso:country":"KR",
    "name:kor_x_preferred":[
        "\ubc15\ub300\uc2e4"
    ],
    "name:und_x_variant":[
        "Paktaesil",
        "Bakdaesil"
    ],
    "wof:name":"Bakdaesil",
    "wof:placetype":"locality"
},
  "geometry": {"coordinates":[128.35693999999998,37.05153],"type":"Point"}
}