{
  "type": "Feature",
  "properties": {
    "gn:admin1_code":"13.0",
    "gn:asciiname":"Jigaeul",
    "gn:country_code":"KR",
    "gn:dem":123,
    "gn:feature_class":"P",
    "gn:feature_code":"PPL",
    "gn:name":"Jigaeul",
    "gn:population":0,
    "gn:timezone":"Asia/Seoul",
    "iso:country":"KR",
    "name:und_x_variant":[
        "\uc9c0\uac1c\uc6b8",
        "Chigaeul",
        "Jigaeul"
    ],
    "wof:name":"Jigaeul",
    "wof:placetype":"locality"
},
  "geometry": {"coordinates":[126.95195,37.7345],"type":"Point"}
}