{
  "type": "Feature",
  "properties": {
    "gn:admin1_code":"20.0",
    "gn:asciiname":"Ungam",
    "gn:country_code":"KR",
    "gn:dem":364,
    "gn:feature_class":"P",
    "gn:feature_code":"PPL",
    "gn:name":"Ungam",
    "gn:population":0,
    "gn:timezone":"Asia/Seoul",
    "iso:country":"KR",
    "name:und_x_variant":[
        "\uc6c5\uc554",
        "Ungam"
    ],
    "wof:name":"Ungam",
    "wof:placetype":"locality"
},
  "geometry": {"coordinates":[127.78449000000001,35.67387],"type":"Point"}
}