{
  "type": "Feature",
  "properties": {
    "gn:admin1_code":"20.0",
    "gn:asciiname":"Seobu",
    "gn:country_code":"KR",
    "gn:dem":85,
    "gn:feature_class":"P",
    "gn:feature_code":"PPL",
    "gn:name":"Seobu",
    "gn:population":0,
    "gn:timezone":"Asia/Seoul",
    "iso:country":"KR",
    "name:kor_x_preferred":[
        "\uc11c\ubd80"
    ],
    "wof:name":"Seobu",
    "wof:placetype":"locality"
},
  "geometry": {"coordinates":[129.17355000000001,35.41777000000001],"type":"Point"}
}