{
  "type": "Feature",
  "properties": {
    "gn:admin1_code":"20.0",
    "gn:asciiname":"Kimnyong",
    "gn:country_code":"KR",
    "gn:dem":199,
    "gn:feature_class":"P",
    "gn:feature_code":"PPL",
    "gn:name":"Kimnyong",
    "gn:population":0,
    "gn:timezone":"Asia/Seoul",
    "iso:country":"KR",
    "name:und_x_variant":[
        "\uae40\ub8e1",
        "Kimnyong"
    ],
    "wof:name":"Kimnyong",
    "wof:placetype":"locality"
},
  "geometry": {"coordinates":[127.93902,35.68812],"type":"Point"}
}