{
  "type": "Feature",
  "properties": {
    "gn:admin1_code":"17.0",
    "gn:asciiname":"Witchung-mal",
    "gn:country_code":"KR",
    "gn:dem":271,
    "gn:feature_class":"P",
    "gn:feature_code":"PPL",
    "gn:name":"Witchung-mal",
    "gn:population":0,
    "gn:timezone":"Asia/Seoul",
    "iso:country":"KR",
    "name:und_x_variant":[
        "\uc717\uc8fd\ub9d0",
        "Witchung-mal"
    ],
    "wof:name":"Witchung-mal",
    "wof:placetype":"locality"
},
  "geometry": {"coordinates":[127.5796,36.2054],"type":"Point"}
}