{
  "type": "Feature",
  "properties": {
    "gn:admin1_code":"6.0",
    "gn:asciiname":"Och'on",
    "gn:country_code":"KR",
    "gn:dem":316,
    "gn:feature_class":"P",
    "gn:feature_code":"PPL",
    "gn:name":"\u014ech\u2019\u014fn",
    "gn:population":0,
    "gn:timezone":"Asia/Seoul",
    "iso:country":"KR",
    "name:kor_x_preferred":[
        "\uc5b4\ucc9c"
    ],
    "name:kor_x_variant":[
        "\u014ech\u2019\u014fn"
    ],
    "wof:name":"Och'on",
    "wof:placetype":"locality"
},
  "geometry": {"coordinates":[128.67150000000001,37.3718],"type":"Point"}
}