{
  "type": "Feature",
  "properties": {
    "gn:admin1_code":"3.0",
    "gn:asciiname":"Kalgye-ri",
    "gn:country_code":"KR",
    "gn:dem":431,
    "gn:feature_class":"P",
    "gn:feature_code":"PPL",
    "gn:name":"Kalgye-ri",
    "gn:population":0,
    "gn:timezone":"Asia/Seoul",
    "iso:country":"KR",
    "wof:name":"Kalgye-ri",
    "wof:placetype":"locality"
},
  "geometry": {"coordinates":[127.61111,35.50639],"type":"Point"}
}