{
  "type": "Feature",
  "properties": {
    "gn:admin1_code":"5.0",
    "gn:asciiname":"Tapjeon",
    "gn:country_code":"KR",
    "gn:dem":82,
    "gn:feature_class":"P",
    "gn:feature_code":"PPL",
    "gn:name":"Tapjeon",
    "gn:population":0,
    "gn:timezone":"Asia/Seoul",
    "iso:country":"KR",
    "name:kor_x_preferred":[
        "\ud0d1\uc804"
    ],
    "wof:name":"Tapjeon",
    "wof:placetype":"locality"
},
  "geometry": {"coordinates":[127.52813,36.6906],"type":"Point"}
}