{
  "type": "Feature",
  "properties": {
    "gn:admin1_code":"17.0",
    "gn:asciiname":"Kosa-ri",
    "gn:country_code":"KR",
    "gn:dem":28,
    "gn:feature_class":"P",
    "gn:feature_code":"PPL",
    "gn:name":"K\u014fsa-ri",
    "gn:population":0,
    "gn:timezone":"Asia/Seoul",
    "iso:country":"KR",
    "name:und_x_variant":[
        "\uac70\uc0ac\ub9ac",
        "K\u014fsa-ri"
    ],
    "wof:name":"Kosa-ri",
    "wof:placetype":"locality"
},
  "geometry": {"coordinates":[126.89615999999999,36.77414],"type":"Point"}
}