{
  "type": "Feature",
  "properties": {
    "gn:admin1_code":"16.0",
    "gn:asciiname":"Songgok",
    "gn:country_code":"KR",
    "gn:dem":25,
    "gn:feature_class":"P",
    "gn:feature_code":"PPL",
    "gn:name":"Songgok",
    "gn:population":0,
    "gn:timezone":"Asia/Seoul",
    "iso:country":"KR",
    "name:kor_x_preferred":[
        "\uc1a1\uace1"
    ],
    "name:und_x_variant":[
        "Songgong-ni"
    ],
    "wof:name":"Songgok",
    "wof:placetype":"locality"
},
  "geometry": {"coordinates":[126.12799,34.8419],"type":"Point"}
}