{
  "type": "Feature",
  "properties": {
    "iso:country":"KR",
    "name:eng_x_preferred":[
        "Jowon-dong"
    ],
    "name:fas_x_preferred":[
        "\u062c\u0648\u0648\u0648\u0646-\u062f\u0648\u0646\u06af"
    ],
    "name:kor_x_preferred":[
        "\uc870\uc6d02\ub3d9"
    ],
    "name:kor_x_variant":[
        "\uc870\uc6d0\ub3d9"
    ],
    "name:zho_x_preferred":[
        "\u68d7\u5712\u6d1e"
    ],
    "qs:gn_fcode":"PPL",
    "qs:gn_local":0,
    "qs:gn_namadm1":"13",
    "qs:gn_name":"Jowon-dong",
    "qs:local_max":599,
    "qs:local_sum":2052,
    "qs:localhoods":9,
    "qs:name":"\uc870\uc6d02\ub3d9",
    "qs:name_adm0":"\ud55c\uad6d",
    "qs:name_adm1":"\uacbd\uae30\ub3c4",
    "qs:name_adm2":"\uc218\uc6d0\uc2dc",
    "qs:name_lau":"\uc7a5\uc548\uad6c",
    "qs:name_local":"\uc7a5\uc548\uad6c",
    "qs:photo_max":39,
    "qs:photo_sum":144,
    "qs:placetype":"Suburb",
    "qs:quad_count":10,
    "qs:woe_adm0":23424868,
    "qs:woe_adm1":2345969,
    "qs:woe_adm2":28289297,
    "qs:woe_lau":28997195,
    "qs:woe_local":28997195,
    "qs:woe_ver":"7.10.0",
    "wof:lang":[
        "kor"
    ],
    "wof:name":"\uc870\uc6d02\ub3d9",
    "wof:placetype":"neighbourhood"
},
  "geometry": {"coordinates":[127.02834300000001,37.291452],"type":"Point"}
}