{
  "type": "Feature",
  "properties": {
    "gn:admin1_code":"0.0",
    "gn:asciiname":"Samyang-ni",
    "gn:country_code":"KR",
    "gn:dem":511,
    "gn:feature_class":"P",
    "gn:feature_code":"PPL",
    "gn:name":"Samyang-ni",
    "gn:population":0,
    "gn:timezone":"Asia/Seoul",
    "iso:country":"KR",
    "wof:name":"Samyang-ni",
    "wof:placetype":"locality"
},
  "geometry": {"coordinates":[128.78333000000001,37.11667],"type":"Point"}
}