{
  "type": "Feature",
  "properties": {
    "gn:admin1_code":"20.0",
    "gn:asciiname":"Taehyon",
    "gn:country_code":"KR",
    "gn:dem":116,
    "gn:feature_class":"P",
    "gn:feature_code":"PPL",
    "gn:name":"Taehy\u014fn",
    "gn:population":0,
    "gn:timezone":"Asia/Seoul",
    "iso:country":"KR",
    "name:und_x_variant":[
        "\ub300\ud604",
        "Taehy\u014fn"
    ],
    "wof:name":"Taehyon",
    "wof:placetype":"locality"
},
  "geometry": {"coordinates":[128.46881000000002,35.17524],"type":"Point"}
}