{
  "type": "Feature",
  "properties": {
    "gn:admin1_code":"0.0",
    "gn:asciiname":"Chigyong-ni",
    "gn:cc2":"KR",
    "gn:country_code":"KR",
    "gn:dem":8,
    "gn:feature_class":"P",
    "gn:feature_code":"PPL",
    "gn:name":"Chigy\u014fng-ni",
    "gn:population":0,
    "gn:timezone":"Asia/Seoul",
    "iso:country":"KR",
    "name:und_x_variant":[
        "Chiky\u014d-ri",
        "Chigy\u014fng-ni"
    ],
    "wof:name":"Chigyong-ni",
    "wof:placetype":"locality"
},
  "geometry": {"coordinates":[126.81667,35.95],"type":"Point"}
}