{
  "type": "Feature",
  "properties": {
    "gn:admin1_code":"5.0",
    "gn:asciiname":"Majo",
    "gn:country_code":"KR",
    "gn:dem":362,
    "gn:feature_class":"P",
    "gn:feature_code":"PPL",
    "gn:name":"Majo",
    "gn:population":0,
    "gn:timezone":"Asia/Seoul",
    "iso:country":"KR",
    "name:bre_x_preferred":[
        "Majo"
    ],
    "name:bul_x_preferred":[
        "\u041c\u0430\u0445\u0430"
    ],
    "name:ell_x_preferred":[
        "\u039c\u03ac\u03c7\u03b1"
    ],
    "name:fra_x_preferred":[
        "Majo"
    ],
    "name:kor_x_preferred":[
        "\ub9c8\uc870"
    ],
    "name:nor_x_preferred":[
        "Majo"
    ],
    "name:por_x_preferred":[
        "Majo"
    ],
    "name:rus_x_preferred":[
        "\u041c\u0430\u0445\u043e"
    ],
    "name:spa_x_preferred":[
        "Manolo"
    ],
    "name:swe_x_preferred":[
        "Majo"
    ],
    "name:tur_x_preferred":[
        "Manolo"
    ],
    "wof:name":"Majo",
    "wof:placetype":"locality"
},
  "geometry": {"coordinates":[128.39192,36.94477],"type":"Point"}
}