{
  "type": "Feature",
  "properties": {
    "gn:admin1_code":"5.0",
    "gn:asciiname":"Majo",
    "gn:country_code":"KR",
    "gn:dem":362,
    "gn:feature_class":"P",
    "gn:feature_code":"PPL",
    "gn:name":"Majo",
    "gn:population":0,
    "gn:timezone":"Asia/Seoul",
    "iso:country":"KR",
    "name:kor_x_preferred":[
        "\ub9c8\uc870"
    ],
    "wof:name":"Majo",
    "wof:placetype":"locality"
},
  "geometry": {"coordinates":[128.39192,36.94477],"type":"Point"}
}