{
  "type": "Feature",
  "properties": {
    "gn:admin1_code":"1.0",
    "gn:asciiname":"Hagwi-ri",
    "gn:country_code":"KR",
    "gn:dem":23,
    "gn:feature_class":"P",
    "gn:feature_code":"PPL",
    "gn:name":"Hagwi-ri",
    "gn:population":0,
    "gn:timezone":"Asia/Seoul",
    "iso:country":"KR",
    "name:und_x_variant":[
        "Kwiil-li",
        "Hagwi-ri"
    ],
    "wof:name":"Hagwi-ri",
    "wof:placetype":"locality"
},
  "geometry": {"coordinates":[126.40167,33.48],"type":"Point"}
}