{
  "type": "Feature",
  "properties": {
    "gn:admin1_code":"17.0",
    "gn:asciiname":"Tokchi",
    "gn:country_code":"KR",
    "gn:dem":26,
    "gn:feature_class":"P",
    "gn:feature_code":"PPL",
    "gn:name":"Tokchi",
    "gn:population":0,
    "gn:timezone":"Asia/Seoul",
    "iso:country":"KR",
    "name:und_x_variant":[
        "\ub3c5\uc9c0",
        "Tokchi-ri",
        "Tokchi"
    ],
    "wof:name":"Tokchi",
    "wof:placetype":"locality"
},
  "geometry": {"coordinates":[126.5235,36.7028],"type":"Point"}
}