{
  "type": "Feature",
  "properties": {
    "gn:admin1_code":"20.0",
    "gn:asciiname":"To-dong",
    "gn:country_code":"KR",
    "gn:dem":79,
    "gn:feature_class":"P",
    "gn:feature_code":"PPL",
    "gn:name":"To-dong",
    "gn:population":0,
    "gn:timezone":"Asia/Seoul",
    "iso:country":"KR",
    "name:und_x_variant":[
        "\uc5f0\ub3d9",
        "Y\u014fn-dong"
    ],
    "wof:name":"To-dong",
    "wof:placetype":"locality"
},
  "geometry": {"coordinates":[128.32093,35.10135],"type":"Point"}
}