{
  "type": "Feature",
  "properties": {
    "gn:admin1_code":"15.0",
    "gn:asciiname":"Garatgol",
    "gn:country_code":"KR",
    "gn:dem":316,
    "gn:feature_class":"P",
    "gn:feature_code":"PPL",
    "gn:name":"Garatgol",
    "gn:population":0,
    "gn:timezone":"Asia/Seoul",
    "iso:country":"KR",
    "name:kor_x_preferred":[
        "\uac00\ub78f\uace8"
    ],
    "wof:name":"Garatgol",
    "wof:placetype":"locality"
},
  "geometry": {"coordinates":[128.66130999999999,35.8064],"type":"Point"}
}