{
  "type": "Feature",
  "properties": {
    "gn:admin1_code":"17.0",
    "gn:asciiname":"Hap'yong",
    "gn:country_code":"KR",
    "gn:dem":145,
    "gn:feature_class":"P",
    "gn:feature_code":"PPL",
    "gn:name":"Hap\u2019y\u014fng",
    "gn:population":0,
    "gn:timezone":"Asia/Seoul",
    "iso:country":"KR",
    "name:und_x_variant":[
        "\ud558\ud3c9",
        "Hap\u2019y\u014fng"
    ],
    "wof:name":"Hap'yong",
    "wof:placetype":"locality"
},
  "geometry": {"coordinates":[127.56319999999999,36.0789],"type":"Point"}
}