{
  "type": "Feature",
  "properties": {
    "gn:admin1_code":"6.0",
    "gn:asciiname":"Sajong",
    "gn:country_code":"KR",
    "gn:dem":226,
    "gn:feature_class":"P",
    "gn:feature_code":"PPL",
    "gn:name":"Saj\u014fng",
    "gn:population":0,
    "gn:timezone":"Asia/Seoul",
    "iso:country":"KR",
    "name:kor_x_preferred":[
        "\uc0ac\uc815"
    ],
    "name:kor_x_variant":[
        "Saj\u014fng"
    ],
    "wof:name":"Sajong",
    "wof:placetype":"locality"
},
  "geometry": {"coordinates":[128.37100000000001,37.218],"type":"Point"}
}