{
  "type": "Feature",
  "properties": {
    "gn:admin1_code":"13.0",
    "gn:asciiname":"Polt'o",
    "gn:country_code":"KR",
    "gn:dem":48,
    "gn:feature_class":"P",
    "gn:feature_code":"PPL",
    "gn:name":"P\u014flt\u2019\u014f",
    "gn:population":0,
    "gn:timezone":"Asia/Seoul",
    "iso:country":"KR",
    "wof:name":"Polt'o",
    "wof:placetype":"locality"
},
  "geometry": {"coordinates":[127.0575,37.23917],"type":"Point"}
}