{
  "type": "Feature",
  "properties": {
    "gn:admin1_code":"3.0",
    "gn:asciiname":"Yu-ch'on",
    "gn:country_code":"KR",
    "gn:dem":372,
    "gn:feature_class":"P",
    "gn:feature_code":"PPL",
    "gn:name":"Yu-ch\u2019on",
    "gn:population":0,
    "gn:timezone":"Asia/Seoul",
    "iso:country":"KR",
    "name:und_x_variant":[
        "\uc720\ucd0c",
        "Yu-ch\u2019on"
    ],
    "wof:name":"Yu-ch'on",
    "wof:placetype":"locality"
},
  "geometry": {"coordinates":[127.57649000000001,35.70551],"type":"Point"}
}