{
  "type": "Feature",
  "properties": {
    "gn:admin1_code":"13.0",
    "gn:asciiname":"Chigari",
    "gn:country_code":"KR",
    "gn:dem":10,
    "gn:feature_class":"P",
    "gn:feature_code":"PPL",
    "gn:name":"Chigari",
    "gn:population":0,
    "gn:timezone":"Asia/Seoul",
    "iso:country":"KR",
    "name:kor_x_preferred":[
        "\uce58\uac00\ub9ac"
    ],
    "wof:name":"Chigari",
    "wof:placetype":"locality"
},
  "geometry": {"coordinates":[126.72535000000001,37.25235],"type":"Point"}
}