{
  "type": "Feature",
  "properties": {
    "gn:admin1_code":"20.0",
    "gn:asciiname":"Sok-tong",
    "gn:country_code":"KR",
    "gn:dem":366,
    "gn:feature_class":"P",
    "gn:feature_code":"PPL",
    "gn:name":"S\u014fk-tong",
    "gn:population":0,
    "gn:timezone":"Asia/Seoul",
    "iso:country":"KR",
    "name:und_x_variant":[
        "\uc11d\ub3d9",
        "S\u014fk-tong"
    ],
    "wof:name":"Sok-tong",
    "wof:placetype":"locality"
},
  "geometry": {"coordinates":[127.86645,35.76837000000001],"type":"Point"}
}