{
  "type": "Feature",
  "properties": {
    "gn:admin1_code":"16.0",
    "gn:asciiname":"Naepan",
    "gn:country_code":"KR",
    "gn:dem":132,
    "gn:feature_class":"P",
    "gn:feature_code":"PPL",
    "gn:name":"Naepan",
    "gn:population":0,
    "gn:timezone":"Asia/Seoul",
    "iso:country":"KR",
    "name:kor_x_preferred":[
        "\ub0b4\ud310"
    ],
    "name:kor_x_variant":[
        "Naep\u2019an"
    ],
    "wof:name":"Naepan",
    "wof:placetype":"locality"
},
  "geometry": {"coordinates":[127.16213999999999,34.89077],"type":"Point"}
}