{
  "type": "Feature",
  "properties": {
    "gn:admin1_code":"14.0",
    "gn:asciiname":"Wondusup",
    "gn:country_code":"KR",
    "gn:dem":187,
    "gn:feature_class":"P",
    "gn:feature_code":"PPL",
    "gn:name":"Wondusup",
    "gn:population":0,
    "gn:timezone":"Asia/Seoul",
    "iso:country":"KR",
    "name:kor_x_preferred":[
        "\uc6d0\ub450\uc232"
    ],
    "wof:name":"Wondusup",
    "wof:placetype":"locality"
},
  "geometry": {"coordinates":[129.03516999999999,35.75633],"type":"Point"}
}