{
  "type": "Feature",
  "properties": {
    "gn:admin1_code":"14.0",
    "gn:asciiname":"Gamcheon",
    "gn:country_code":"KR",
    "gn:dem":152,
    "gn:feature_class":"P",
    "gn:feature_code":"PPL",
    "gn:name":"Gamcheon",
    "gn:population":0,
    "gn:timezone":"Asia/Seoul",
    "iso:country":"KR",
    "name:kor_x_preferred":[
        "\uac10\ucc9c"
    ],
    "name:und_x_variant":[
        "Taesan-dong",
        "Kamch\u2019\u014fn",
        "Gamcheon"
    ],
    "wof:name":"Gamcheon",
    "wof:placetype":"locality"
},
  "geometry": {"coordinates":[128.52733999999998,36.7221],"type":"Point"}
}