{
  "type": "Feature",
  "properties": {
    "gn:admin1_code":"16.0",
    "gn:asciiname":"Toksong-ni",
    "gn:cc2":"KR",
    "gn:country_code":"KR",
    "gn:dem":68,
    "gn:feature_class":"P",
    "gn:feature_code":"PPL",
    "gn:name":"T\u014fks\u014fng-ni",
    "gn:population":0,
    "gn:timezone":"Asia/Seoul",
    "iso:country":"KR",
    "name:und_x_variant":[
        "T\u014fks\u014fng",
        "T\u014fks\u014fng-ni"
    ],
    "wof:name":"Toksong-ni",
    "wof:placetype":"locality"
},
  "geometry": {"coordinates":[126.77110999999999,35.25194000000001],"type":"Point"}
}