{
  "type": "Feature",
  "properties": {
    "gn:admin1_code":"13.0",
    "gn:asciiname":"Tolmuni",
    "gn:country_code":"KR",
    "gn:dem":139,
    "gn:feature_class":"P",
    "gn:feature_code":"PPL",
    "gn:name":"Tolmuni",
    "gn:population":0,
    "gn:timezone":"Asia/Seoul",
    "iso:country":"KR",
    "name:und_x_variant":[
        "\ub3cc\ubb38\uc774",
        "Dolmuni",
        "Tolmuni"
    ],
    "wof:name":"Tolmuni",
    "wof:placetype":"locality"
},
  "geometry": {"coordinates":[127.38388999999999,37.33222],"type":"Point"}
}