{
  "type": "Feature",
  "properties": {
    "gn:admin1_code":"17.0",
    "gn:asciiname":"Sahang",
    "gn:country_code":"KR",
    "gn:dem":22,
    "gn:feature_class":"P",
    "gn:feature_code":"PPL",
    "gn:name":"Sahang",
    "gn:population":0,
    "gn:timezone":"Asia/Seoul",
    "iso:country":"KR",
    "name:und_x_variant":[
        "Naesahangch\u2019on",
        "\uc0ac\ud56d",
        "Sahang"
    ],
    "wof:name":"Sahang",
    "wof:placetype":"locality"
},
  "geometry": {"coordinates":[126.29600000000001,36.9207],"type":"Point"}
}