{
  "type": "Feature",
  "properties": {
    "gn:admin1_code":"13.0",
    "gn:admin2_code":"Ans\u014fng-si",
    "gn:asciiname":"Myeongnyun-dong",
    "gn:country_code":"KR",
    "gn:dem":55,
    "gn:feature_class":"P",
    "gn:feature_code":"PPLL",
    "gn:name":"Myeongnyun-dong",
    "gn:population":0,
    "gn:timezone":"Asia/Seoul",
    "iso:country":"KR",
    "name:kor_x_preferred":[
        "\uba85\ub95c\ub3d9"
    ],
    "name:kor_x_variant":[
        "My\u014fngnyun-dong"
    ],
    "wof:name":"Myeongnyun-dong",
    "wof:placetype":"locality"
},
  "geometry": {"coordinates":[127.27443999999998,37.02],"type":"Point"}
}