{
  "type": "Feature",
  "properties": {
    "gn:admin1_code":"16.0",
    "gn:asciiname":"Bongdeok",
    "gn:country_code":"KR",
    "gn:dem":14,
    "gn:feature_class":"P",
    "gn:feature_code":"PPL",
    "gn:name":"Bongdeok",
    "gn:population":0,
    "gn:timezone":"Asia/Seoul",
    "iso:country":"KR",
    "name:kor_x_preferred":[
        "\ubd09\ub355"
    ],
    "name:kor_x_variant":[
        "Pongd\u014fk"
    ],
    "wof:name":"Bongdeok",
    "wof:placetype":"locality"
},
  "geometry": {"coordinates":[127.44401999999999,34.87241],"type":"Point"}
}