{
  "type": "Feature",
  "properties": {
    "gn:admin1_code":"17.0",
    "gn:asciiname":"Chadolbaegi",
    "gn:country_code":"KR",
    "gn:dem":23,
    "gn:feature_class":"P",
    "gn:feature_code":"PPL",
    "gn:name":"Chadolbaegi",
    "gn:population":0,
    "gn:timezone":"Asia/Seoul",
    "iso:country":"KR",
    "name:und_x_variant":[
        "\ucc28\ub3cc\ubc31\uc774",
        "Ch\u2019adolbaegi",
        "Chadolbaegi"
    ],
    "wof:name":"Chadolbaegi",
    "wof:placetype":"locality"
},
  "geometry": {"coordinates":[127.07737,36.92874000000001],"type":"Point"}
}