{
  "type": "Feature",
  "properties": {
    "gn:admin1_code":"16.0",
    "gn:asciiname":"Gaedong",
    "gn:country_code":"KR",
    "gn:dem":36,
    "gn:feature_class":"P",
    "gn:feature_code":"PPL",
    "gn:name":"Gaedong",
    "gn:population":0,
    "gn:timezone":"Asia/Seoul",
    "iso:country":"KR",
    "name:kor_x_preferred":[
        "\uac1c\ub3d9"
    ],
    "wof:name":"Gaedong",
    "wof:placetype":"locality"
},
  "geometry": {"coordinates":[126.94113,35.28465],"type":"Point"}
}