{
  "type": "Feature",
  "properties": {
    "gn:admin1_code":"20.0",
    "gn:asciiname":"Nakchong",
    "gn:country_code":"KR",
    "gn:dem":14,
    "gn:feature_class":"P",
    "gn:feature_code":"PPL",
    "gn:name":"Nakch\u014fng",
    "gn:population":0,
    "gn:timezone":"Asia/Seoul",
    "iso:country":"KR",
    "name:und_x_variant":[
        "\ub099\uc815",
        "Nakch\u014fng"
    ],
    "wof:name":"Nakchong",
    "wof:placetype":"locality"
},
  "geometry": {"coordinates":[128.35869,35.01875],"type":"Point"}
}