{
  "type": "Feature",
  "properties": {
    "gn:admin1_code":"6.0",
    "gn:asciiname":"Pongo-ri",
    "gn:cc2":"KR",
    "gn:country_code":"KR",
    "gn:dem":305,
    "gn:feature_class":"P",
    "gn:feature_code":"PPL",
    "gn:name":"Pongo-ri",
    "gn:population":0,
    "gn:timezone":"Asia/Seoul",
    "iso:country":"KR",
    "name:und_x_variant":[
        "Samgeori",
        "Pongo-il-li",
        "Bongo 1-ri",
        "\ubd09\uc6241\ub9ac",
        "Pongo-ri"
    ],
    "wof:name":"Pongo-ri",
    "wof:placetype":"locality"
},
  "geometry": {"coordinates":[127.59999999999999,38.19],"type":"Point"}
}