{
  "type": "Feature",
  "properties": {
    "gn:admin1_code":"3.0",
    "gn:asciiname":"Tonggok",
    "gn:country_code":"KR",
    "gn:dem":58,
    "gn:feature_class":"P",
    "gn:feature_code":"PPL",
    "gn:name":"Tonggok",
    "gn:population":0,
    "gn:timezone":"Asia/Seoul",
    "iso:country":"KR",
    "name:und_x_variant":[
        "\ub3d9\uace1",
        "Tonggok"
    ],
    "wof:name":"Tonggok",
    "wof:placetype":"locality"
},
  "geometry": {"coordinates":[127.0215,35.72753],"type":"Point"}
}