{
  "type": "Feature",
  "properties": {
    "gn:admin1_code":"20.0",
    "gn:asciiname":"Taman",
    "gn:country_code":"KR",
    "gn:dem":59,
    "gn:feature_class":"P",
    "gn:feature_code":"PPL",
    "gn:name":"Taman",
    "gn:population":0,
    "gn:timezone":"Asia/Seoul",
    "iso:country":"KR",
    "name:und_x_variant":[
        "Tamwon",
        "\ub2f4\uc548",
        "Taman"
    ],
    "wof:name":"Taman",
    "wof:placetype":"locality"
},
  "geometry": {"coordinates":[128.37606,35.11984],"type":"Point"}
}