{
  "type": "Feature",
  "properties": {
    "gn:admin1_code":"16.0",
    "gn:asciiname":"Namdong",
    "gn:country_code":"KR",
    "gn:dem":17,
    "gn:feature_class":"P",
    "gn:feature_code":"PPL",
    "gn:name":"Namdong",
    "gn:population":0,
    "gn:timezone":"Asia/Seoul",
    "iso:country":"KR",
    "name:kor_x_preferred":[
        "\ub0a8\ub3d9"
    ],
    "name:und_x_variant":[
        "Namdo",
        "Nant\u014d",
        "Namdong"
    ],
    "wof:name":"Namdong",
    "wof:placetype":"locality"
},
  "geometry": {"coordinates":[126.16562999999999,34.36493],"type":"Point"}
}