{
  "type": "Feature",
  "properties": {
    "gn:country":"KR",
    "gn:fcode":"ADM3",
    "gn:pop":0,
    "iso:country":"KR",
    "name:eng_x_preferred":[
        "Buk-myeon"
    ],
    "name:kor_x_preferred":[
        "\ubd81\uba74"
    ],
    "name:unk_x_variant":[
        "\ubd81\uba74"
    ],
    "qs:name":"Pung-my\u014fn",
    "qs:photos_9r":0,
    "qs:photos_sr":0,
    "qs:pop_sr":"0",
    "wof:name":"Pung-my\u014fn",
    "wof:placetype":"localadmin",
    "wof:population":0
},
  "geometry": {"coordinates":[129.31434999999999,37.06954],"type":"Point"}
}