{
  "type": "Feature",
  "properties": {
    "gn:admin1_code":"14.0",
    "gn:asciiname":"Jaegung",
    "gn:country_code":"KR",
    "gn:dem":255,
    "gn:feature_class":"P",
    "gn:feature_code":"PPL",
    "gn:name":"Jaegung",
    "gn:population":0,
    "gn:timezone":"Asia/Seoul",
    "iso:country":"KR",
    "name:kor_x_preferred":[
        "\uc7ac\uad81"
    ],
    "wof:name":"Jaegung",
    "wof:placetype":"locality"
},
  "geometry": {"coordinates":[129.03254999999999,35.72450999999999],"type":"Point"}
}