{
  "type": "Feature",
  "properties": {
    "gn:admin1_code":"14.0",
    "gn:asciiname":"Chinbat",
    "gn:country_code":"KR",
    "gn:dem":295,
    "gn:feature_class":"P",
    "gn:feature_code":"PPL",
    "gn:name":"Chinbat",
    "gn:population":0,
    "gn:timezone":"Asia/Seoul",
    "iso:country":"KR",
    "name:und_x_variant":[
        "\uc9c4\ubc2d",
        "Chinbat"
    ],
    "wof:name":"Chinbat",
    "wof:placetype":"locality"
},
  "geometry": {"coordinates":[128.97640000000001,36.2825],"type":"Point"}
}