{
  "type": "Feature",
  "properties": {
    "gn:admin1_code":"13.0",
    "gn:asciiname":"Duilli",
    "gn:country_code":"KR",
    "gn:dem":34,
    "gn:feature_class":"P",
    "gn:feature_code":"PPL",
    "gn:name":"Duilli",
    "gn:population":0,
    "gn:timezone":"Asia/Seoul",
    "iso:country":"KR",
    "name:kor_x_preferred":[
        "\ub450\uc77c\ub9ac"
    ],
    "wof:name":"Duilli",
    "wof:placetype":"locality"
},
  "geometry": {"coordinates":[126.90951,38.03034],"type":"Point"}
}