{
  "type": "Feature",
  "properties": {
    "gn:admin1_code":"6.0",
    "gn:asciiname":"San'gye-ri",
    "gn:country_code":"KR",
    "gn:dem":140,
    "gn:feature_class":"P",
    "gn:feature_code":"PPLL",
    "gn:name":"San\u2019gye-ri",
    "gn:population":0,
    "gn:timezone":"Asia/Seoul",
    "iso:country":"KR",
    "name:kor_x_preferred":[
        "\uc0b0\uacc4\ub9ac"
    ],
    "name:kor_x_variant":[
        "San\u2019gye-ri"
    ],
    "name:und_x_variant":[
        "San\u2019ge-ri"
    ],
    "wof:name":"San'gye-ri",
    "wof:placetype":"locality"
},
  "geometry": {"coordinates":[128.96337,37.57709000000001],"type":"Point"}
}