{
  "type": "Feature",
  "properties": {
    "gn:admin1_code":"14.0",
    "gn:asciiname":"Sadure",
    "gn:country_code":"KR",
    "gn:dem":265,
    "gn:feature_class":"P",
    "gn:feature_code":"PPL",
    "gn:name":"Sad\u016dre",
    "gn:population":0,
    "gn:timezone":"Asia/Seoul",
    "iso:country":"KR",
    "name:und_x_variant":[
        "Sad\u016dng-ni",
        "\uc0ac\ub4dc\ub808",
        "Sad\u016drae",
        "Sad\u016dre"
    ],
    "wof:name":"Sadure",
    "wof:placetype":"locality"
},
  "geometry": {"coordinates":[127.95905,35.99048],"type":"Point"}
}