{
  "type": "Feature",
  "properties": {
    "gn:admin1_code":"17.0",
    "gn:asciiname":"Kambat",
    "gn:country_code":"KR",
    "gn:dem":131,
    "gn:feature_class":"P",
    "gn:feature_code":"PPL",
    "gn:name":"Kambat",
    "gn:population":0,
    "gn:timezone":"Asia/Seoul",
    "iso:country":"KR",
    "name:und_x_variant":[
        "\uac10\ubc2d",
        "Kambat"
    ],
    "wof:name":"Kambat",
    "wof:placetype":"locality"
},
  "geometry": {"coordinates":[126.8528,36.4685],"type":"Point"}
}