{
  "type": "Feature",
  "properties": {
    "gn:admin1_code":"17.0",
    "gn:asciiname":"Cheongsan",
    "gn:country_code":"KR",
    "gn:dem":59,
    "gn:feature_class":"P",
    "gn:feature_code":"PPL",
    "gn:name":"Cheongsan",
    "gn:population":0,
    "gn:timezone":"Asia/Seoul",
    "iso:country":"KR",
    "name:kor_x_preferred":[
        "\uccad\uc0b0"
    ],
    "wof:name":"Cheongsan",
    "wof:placetype":"locality"
},
  "geometry": {"coordinates":[127.23372999999999,36.66373],"type":"Point"}
}