{
  "type": "Feature",
  "properties": {
    "gn:admin1_code":"14.0",
    "gn:asciiname":"Makgol",
    "gn:country_code":"KR",
    "gn:dem":158,
    "gn:feature_class":"P",
    "gn:feature_code":"PPL",
    "gn:name":"Makgol",
    "gn:population":0,
    "gn:timezone":"Asia/Seoul",
    "iso:country":"KR",
    "name:kor_x_preferred":[
        "\ub9c9\uace8"
    ],
    "wof:name":"Makgol",
    "wof:placetype":"locality"
},
  "geometry": {"coordinates":[128.20476000000002,36.68056],"type":"Point"}
}