{
  "type": "Feature",
  "properties": {
    "gn:admin1_code":"13.0",
    "gn:asciiname":"Oryong-gol",
    "gn:country_code":"KR",
    "gn:dem":69,
    "gn:feature_class":"P",
    "gn:feature_code":"PPL",
    "gn:name":"Oryong-gol",
    "gn:population":0,
    "gn:timezone":"Asia/Seoul",
    "iso:country":"KR",
    "name:und_x_variant":[
        "\uc624\ub8e1\uace8",
        "Oryong-gol"
    ],
    "wof:name":"Oryong-gol",
    "wof:placetype":"locality"
},
  "geometry": {"coordinates":[127.61694,37.37778],"type":"Point"}
}