{
  "type": "Feature",
  "properties": {
    "gn:admin1_code":"15.0",
    "gn:asciiname":"P'ajam",
    "gn:country_code":"KR",
    "gn:dem":86,
    "gn:feature_class":"P",
    "gn:feature_code":"PPL",
    "gn:name":"P\u2019ajam",
    "gn:population":0,
    "gn:timezone":"Asia/Seoul",
    "iso:country":"KR",
    "name:und_x_variant":[
        "P\u2019a-dong",
        "P\u2019ajam"
    ],
    "wof:name":"P'ajam",
    "wof:placetype":"locality"
},
  "geometry": {"coordinates":[128.62056000000001,35.81083],"type":"Point"}
}