{
  "type": "Feature",
  "properties": {
    "gn:admin1_code":"20.0",
    "gn:asciiname":"Minam-ni",
    "gn:country_code":"KR",
    "gn:dem":51,
    "gn:feature_class":"P",
    "gn:feature_code":"PPL",
    "gn:name":"Minam-ni",
    "gn:population":0,
    "gn:timezone":"Asia/Seoul",
    "iso:country":"KR",
    "name:eng_x_preferred":[
        "Minam"
    ],
    "name:eng_x_variant":[
        "Minam-ni"
    ],
    "wof:name":"Minam",
    "wof:placetype":"locality"
},
  "geometry": {"coordinates":[128.42055999999999,34.76667],"type":"Point"}
}