{
  "type": "Feature",
  "properties": {
    "gn:admin1_code":"0.0",
    "gn:asciiname":"P'yonggum",
    "gn:country_code":"KR",
    "gn:dem":51,
    "gn:feature_class":"P",
    "gn:feature_code":"PPL",
    "gn:name":"P\u2019y\u014fngg\u016dm",
    "gn:population":0,
    "gn:timezone":"Asia/Seoul",
    "iso:country":"KR",
    "name:kor_x_preferred":[
        "\ud3c9\uae08"
    ],
    "name:und_x_variant":[
        "P\u2019y\u014fngg\u016dm-ni",
        "P\u2019y\u014fngg\u016dm",
        "Pyeonggeum"
    ],
    "wof:name":"P'yonggum",
    "wof:placetype":"locality"
},
  "geometry": {"coordinates":[126.61667,35.31667],"type":"Point"}
}