{
  "type": "Feature",
  "properties": {
    "gn:admin1_code":"17.0",
    "gn:asciiname":"Kumji-ri",
    "gn:country_code":"KR",
    "gn:dem":119,
    "gn:feature_class":"P",
    "gn:feature_code":"PPL",
    "gn:name":"K\u016dmji-ri",
    "gn:population":0,
    "gn:timezone":"Asia/Seoul",
    "iso:country":"KR",
    "name:und_x_variant":[
        "K\u016dmji-ri",
        "\uae08\uc9c0\ub9ac",
        "K\u016dmji"
    ],
    "wof:name":"Kumji-ri",
    "wof:placetype":"locality"
},
  "geometry": {"coordinates":[126.738,36.269],"type":"Point"}
}