{
  "type": "Feature",
  "properties": {
    "gn:admin1_code":"13.0",
    "gn:asciiname":"Seokpo",
    "gn:country_code":"KR",
    "gn:dem":48,
    "gn:feature_class":"P",
    "gn:feature_code":"PPL",
    "gn:name":"Seokpo",
    "gn:population":0,
    "gn:timezone":"Asia/Seoul",
    "iso:country":"KR",
    "name:kor_x_preferred":[
        "\uc11d\ud3ec"
    ],
    "name:und_x_variant":[
        "Seokpo"
    ],
    "wof:name":"Seokpo",
    "wof:placetype":"locality"
},
  "geometry": {"coordinates":[127.1992,37.6083],"type":"Point"}
}