{
  "type": "Feature",
  "properties": {
    "gn:admin1_code":"1.0",
    "gn:asciiname":"Maheuldong",
    "gn:country_code":"KR",
    "gn:dem":57,
    "gn:feature_class":"P",
    "gn:feature_code":"PPL",
    "gn:name":"Maheuldong",
    "gn:population":0,
    "gn:timezone":"Asia/Seoul",
    "iso:country":"KR",
    "name:kor_x_preferred":[
        "\ub9c8\ud758\ub3d9"
    ],
    "name:und_x_variant":[
        "Mah\u016dl-tong"
    ],
    "wof:name":"Maheuldong",
    "wof:placetype":"locality"
},
  "geometry": {"coordinates":[126.29782,33.41775],"type":"Point"}
}