{
  "type": "Feature",
  "properties": {
    "gn:admin1_code":"18.0",
    "gn:asciiname":"Seongchon",
    "gn:country_code":"KR",
    "gn:dem":123,
    "gn:feature_class":"P",
    "gn:feature_code":"PPL",
    "gn:name":"Seongchon",
    "gn:population":0,
    "gn:timezone":"Asia/Seoul",
    "iso:country":"KR",
    "name:kor_x_preferred":[
        "\uc131\ucd0c"
    ],
    "name:und_x_variant":[
        "S\u014fngch\u2019on"
    ],
    "wof:name":"Seongchon",
    "wof:placetype":"locality"
},
  "geometry": {"coordinates":[126.95341999999999,35.1355],"type":"Point"}
}