{
  "type": "Feature",
  "properties": {
    "gn:admin1_code":"3.0",
    "gn:asciiname":"Tuwol",
    "gn:cc2":"KR",
    "gn:country_code":"KR",
    "gn:dem":7,
    "gn:feature_class":"P",
    "gn:feature_code":"PPL",
    "gn:name":"Tuw\u014fl",
    "gn:population":0,
    "gn:timezone":"Asia/Seoul",
    "iso:country":"KR",
    "name:und_x_variant":[
        "Tuw\u014fl-li",
        "Tuw\u014fl"
    ],
    "wof:name":"Tuwol",
    "wof:placetype":"locality"
},
  "geometry": {"coordinates":[126.93917,35.79639],"type":"Point"}
}