{
  "type": "Feature",
  "properties": {
    "gn:admin1_code":"14.0",
    "gn:asciiname":"Saemaeul",
    "gn:country_code":"KR",
    "gn:dem":185,
    "gn:feature_class":"P",
    "gn:feature_code":"PPL",
    "gn:name":"Saemaeul",
    "gn:population":0,
    "gn:timezone":"Asia/Seoul",
    "iso:country":"KR",
    "name:jpn_x_preferred":[
        "\u30bb\u30de\u30a6\u30eb"
    ],
    "name:kor_x_preferred":[
        "\uc0c8\ub9c8\uc744"
    ],
    "wof:name":"Saemaeul",
    "wof:placetype":"locality"
},
  "geometry": {"coordinates":[128.87409,36.63567000000001],"type":"Point"}
}