{
  "type": "Feature",
  "properties": {
    "gn:admin1_code":"20.0",
    "gn:asciiname":"Deungnim",
    "gn:country_code":"KR",
    "gn:dem":27,
    "gn:feature_class":"P",
    "gn:feature_code":"PPL",
    "gn:name":"Deungnim",
    "gn:population":0,
    "gn:timezone":"Asia/Seoul",
    "iso:country":"KR",
    "name:kor_x_preferred":[
        "\ub4f1\ub9bc"
    ],
    "wof:name":"Deungnim",
    "wof:placetype":"locality"
},
  "geometry": {"coordinates":[128.37126999999998,35.58056],"type":"Point"}
}