{
  "type": "Feature",
  "properties": {
    "gn:admin1_code":"14.0",
    "gn:asciiname":"Singi",
    "gn:country_code":"KR",
    "gn:dem":55,
    "gn:feature_class":"P",
    "gn:feature_code":"PPL",
    "gn:name":"Singi",
    "gn:population":0,
    "gn:timezone":"Asia/Seoul",
    "iso:country":"KR",
    "name:deu_x_preferred":[
        "Singi"
    ],
    "name:kor_x_preferred":[
        "\uc2e0\uae30"
    ],
    "name:nor_x_preferred":[
        "Singi"
    ],
    "name:swe_x_preferred":[
        "Singi"
    ],
    "name:und_x_variant":[
        "\uc0c8\ud130",
        "Saet\u2019\u014f"
    ],
    "wof:name":"Singi",
    "wof:placetype":"locality"
},
  "geometry": {"coordinates":[128.40194,35.72263],"type":"Point"}
}