{
  "type": "Feature",
  "properties": {
    "gn:admin1_code":"14.0",
    "gn:asciiname":"Wolhang",
    "gn:country_code":"KR",
    "gn:dem":367,
    "gn:feature_class":"P",
    "gn:feature_code":"PPL",
    "gn:name":"Wolhang",
    "gn:population":0,
    "gn:timezone":"Asia/Seoul",
    "iso:country":"KR",
    "name:kor_x_preferred":[
        "\uc6d4\ud56d"
    ],
    "wof:name":"Wolhang",
    "wof:placetype":"locality"
},
  "geometry": {"coordinates":[129.01724999999999,35.78065],"type":"Point"}
}