{
  "type": "Feature",
  "properties": {
    "gn:admin1_code":"19.0",
    "gn:asciiname":"Yuseong",
    "gn:country_code":"KR",
    "gn:dem":52,
    "gn:feature_class":"P",
    "gn:feature_code":"PPL",
    "gn:name":"Yuseong",
    "gn:population":0,
    "gn:timezone":"Asia/Seoul",
    "iso:country":"KR",
    "name:und_x_variant":[
        "Juj\u014d",
        "Yus\u014fng",
        "\uc720\uc131",
        "Yuseong"
    ],
    "wof:name":"Yuseong",
    "wof:placetype":"locality"
},
  "geometry": {"coordinates":[127.33667,36.35389],"type":"Point"}
}