{
  "type": "Feature",
  "properties": {
    "gn:admin1_code":"13.0",
    "gn:asciiname":"Ma-gol",
    "gn:country_code":"KR",
    "gn:dem":247,
    "gn:feature_class":"P",
    "gn:feature_code":"PPL",
    "gn:name":"Ma-gol",
    "gn:population":0,
    "gn:timezone":"Asia/Seoul",
    "iso:country":"KR",
    "name:und_x_variant":[
        "\ub9c8\uace8",
        "Ma-gol"
    ],
    "wof:name":"Ma-gol",
    "wof:placetype":"locality"
},
  "geometry": {"coordinates":[127.73333,37.41944],"type":"Point"}
}