{
  "type": "Feature",
  "properties": {
    "gn:admin1_code":"16.0",
    "gn:asciiname":"Odo",
    "gn:country_code":"KR",
    "gn:dem":168,
    "gn:feature_class":"P",
    "gn:feature_code":"PPL",
    "gn:name":"Odo",
    "gn:population":0,
    "gn:timezone":"Asia/Seoul",
    "iso:country":"KR",
    "name:bre_x_preferred":[
        "Odo"
    ],
    "name:deu_x_preferred":[
        "Odo"
    ],
    "name:kor_x_preferred":[
        "\uc624\ub3c4"
    ],
    "name:por_x_preferred":[
        "Od\u00e3o"
    ],
    "wof:name":"Odo",
    "wof:placetype":"locality"
},
  "geometry": {"coordinates":[127.17091000000001,34.80097],"type":"Point"}
}