{
  "type": "Feature",
  "properties": {
    "gn:admin1_code":"18.0",
    "gn:asciiname":"Pungsuk",
    "gn:country_code":"KR",
    "gn:dem":29,
    "gn:feature_class":"P",
    "gn:feature_code":"PPL",
    "gn:name":"Pungsuk",
    "gn:population":0,
    "gn:timezone":"Asia/Seoul",
    "iso:country":"KR",
    "name:kor_x_preferred":[
        "\ud48d\uc219"
    ],
    "wof:name":"Pungsuk",
    "wof:placetype":"locality"
},
  "geometry": {"coordinates":[126.72578,35.17279],"type":"Point"}
}