{
  "type": "Feature",
  "properties": {
    "gn:admin1_code":"13.0",
    "gn:asciiname":"Sanggullyang",
    "gn:country_code":"KR",
    "gn:dem":80,
    "gn:feature_class":"P",
    "gn:feature_code":"PPL",
    "gn:name":"Sanggullyang",
    "gn:population":0,
    "gn:timezone":"Asia/Seoul",
    "iso:country":"KR",
    "name:kor_x_preferred":[
        "\uc0c1\uad70\ub7c9"
    ],
    "wof:name":"Sanggullyang",
    "wof:placetype":"locality"
},
  "geometry": {"coordinates":[127.50178,37.17426],"type":"Point"}
}