{
  "type": "Feature",
  "properties": {
    "gn:admin1_code":"14.0",
    "gn:asciiname":"Ganggu",
    "gn:country_code":"KR",
    "gn:dem":15,
    "gn:feature_class":"P",
    "gn:feature_code":"PPL",
    "gn:name":"Ganggu",
    "gn:population":0,
    "gn:timezone":"Asia/Seoul",
    "iso:country":"KR",
    "name:kor_x_preferred":[
        "\uac15\uad6c"
    ],
    "name:und_x_variant":[
        "Kanggu-dong",
        "Kokodo",
        "Kanggu",
        "Ganggu"
    ],
    "wof:name":"Ganggu",
    "wof:placetype":"locality"
},
  "geometry": {"coordinates":[129.38651000000002,36.36006],"type":"Point"}
}