{
  "type": "Feature",
  "properties": {
    "gn:admin1_code":"14.0",
    "gn:asciiname":"Salgujim",
    "gn:country_code":"KR",
    "gn:dem":163,
    "gn:feature_class":"P",
    "gn:feature_code":"PPL",
    "gn:name":"Salgujim",
    "gn:population":0,
    "gn:timezone":"Asia/Seoul",
    "iso:country":"KR",
    "name:und_x_variant":[
        "\uc0b4\uad6c\uc9d0",
        "Salgujim"
    ],
    "wof:name":"Salgujim",
    "wof:placetype":"locality"
},
  "geometry": {"coordinates":[128.23249999999999,36.0855],"type":"Point"}
}