{
  "type": "Feature",
  "properties": {
    "gn:admin1_code":"16.0",
    "gn:asciiname":"Gaksamchi",
    "gn:country_code":"KR",
    "gn:dem":170,
    "gn:feature_class":"P",
    "gn:feature_code":"PPL",
    "gn:name":"Gaksamchi",
    "gn:population":0,
    "gn:timezone":"Asia/Seoul",
    "iso:country":"KR",
    "name:kor_x_preferred":[
        "\uac01\uc0bc\uc9c0"
    ],
    "name:und_x_variant":[
        "Kaksamji",
        "Gaksamchi"
    ],
    "wof:name":"Gaksamchi",
    "wof:placetype":"locality"
},
  "geometry": {"coordinates":[127.07979,34.75468],"type":"Point"}
}