{
  "type": "Feature",
  "properties": {
    "gn:admin1_code":"17.0",
    "gn:asciiname":"Wonjaul",
    "gn:country_code":"KR",
    "gn:dem":83,
    "gn:feature_class":"P",
    "gn:feature_code":"PPL",
    "gn:name":"W\u014fnjaul",
    "gn:population":0,
    "gn:timezone":"Asia/Seoul",
    "iso:country":"KR",
    "name:und_x_variant":[
        "\uc6d0\uc790\uc6b8",
        "W\u014fnjaul"
    ],
    "wof:name":"Wonjaul",
    "wof:placetype":"locality"
},
  "geometry": {"coordinates":[126.6635,36.3995],"type":"Point"}
}