{
  "type": "Feature",
  "properties": {
    "gn:admin1_code":"14.0",
    "gn:asciiname":"Mal-gol",
    "gn:country_code":"KR",
    "gn:dem":100,
    "gn:feature_class":"P",
    "gn:feature_code":"PPL",
    "gn:name":"Mal-gol",
    "gn:population":0,
    "gn:timezone":"Asia/Seoul",
    "iso:country":"KR",
    "name:und_x_variant":[
        "\ub9d0\uace8",
        "Mal-gol"
    ],
    "wof:name":"Mal-gol",
    "wof:placetype":"locality"
},
  "geometry": {"coordinates":[129.27557999999999,36.04002],"type":"Point"}
}