{
  "type": "Feature",
  "properties": {
    "gn:admin1_code":"12.0",
    "gn:asciiname":"Neungdong",
    "gn:country_code":"KR",
    "gn:dem":95,
    "gn:feature_class":"P",
    "gn:feature_code":"PPL",
    "gn:name":"Neungdong",
    "gn:population":0,
    "gn:timezone":"Asia/Seoul",
    "iso:country":"KR",
    "name:und_x_variant":[
        "S\u014fng-dong",
        "\ub2a5\ub3d9",
        "Neungdong",
        "N\u016dng-dong"
    ],
    "wof:name":"Neungdong",
    "wof:placetype":"locality"
},
  "geometry": {"coordinates":[126.10254,37.25692],"type":"Point"}
}