{
  "type": "Feature",
  "properties": {
    "gn:admin1_code":"13.0",
    "gn:asciiname":"Arisil",
    "gn:country_code":"KR",
    "gn:dem":60,
    "gn:feature_class":"P",
    "gn:feature_code":"PPL",
    "gn:name":"Arisil",
    "gn:population":0,
    "gn:timezone":"Asia/Seoul",
    "iso:country":"KR",
    "name:und_x_variant":[
        "\uc544\ub9ac\uc2e4",
        "Arisil"
    ],
    "wof:name":"Arisil",
    "wof:placetype":"locality"
},
  "geometry": {"coordinates":[127.17889,37.09778],"type":"Point"}
}