{
  "type": "Feature",
  "properties": {
    "gn:admin1_code":"17.0",
    "gn:asciiname":"Dongokgol",
    "gn:country_code":"KR",
    "gn:dem":239,
    "gn:feature_class":"P",
    "gn:feature_code":"PPL",
    "gn:name":"Dongokgol",
    "gn:population":0,
    "gn:timezone":"Asia/Seoul",
    "iso:country":"KR",
    "name:kor_x_preferred":[
        "\ub3d9\uc625\uace8"
    ],
    "wof:name":"Dongokgol",
    "wof:placetype":"locality"
},
  "geometry": {"coordinates":[127.22143,36.29318],"type":"Point"}
}