{
  "type": "Feature",
  "properties": {
    "gn:admin1_code":"10.0",
    "gn:asciiname":"Deoksan",
    "gn:country_code":"KR",
    "gn:dem":36,
    "gn:feature_class":"P",
    "gn:feature_code":"PPL",
    "gn:name":"Deoksan",
    "gn:population":0,
    "gn:timezone":"Asia/Seoul",
    "iso:country":"KR",
    "name:kor_x_preferred":[
        "\ub355\uc0b0"
    ],
    "wof:name":"Deoksan",
    "wof:placetype":"locality"
},
  "geometry": {"coordinates":[129.24028999999999,35.32638],"type":"Point"}
}