{
  "type": "Feature",
  "properties": {
    "gn:admin1_code":"5.0",
    "gn:asciiname":"Chung-mal",
    "gn:country_code":"KR",
    "gn:dem":330,
    "gn:feature_class":"P",
    "gn:feature_code":"PPL",
    "gn:name":"Chung-mal",
    "gn:population":0,
    "gn:timezone":"Asia/Seoul",
    "iso:country":"KR",
    "name:kor_x_preferred":[
        "\uc911\ub9d0"
    ],
    "wof:name":"Chung-mal",
    "wof:placetype":"locality"
},
  "geometry": {"coordinates":[127.99079999999999,37.1396],"type":"Point"}
}