{
  "type": "Feature",
  "properties": {
    "gn:admin1_code":"3.0",
    "gn:asciiname":"Soyong",
    "gn:country_code":"KR",
    "gn:dem":120,
    "gn:feature_class":"P",
    "gn:feature_code":"PPL",
    "gn:name":"Soyong",
    "gn:population":0,
    "gn:timezone":"Asia/Seoul",
    "iso:country":"KR",
    "name:und_x_variant":[
        "\uc18c\uc6a9",
        "Soyong"
    ],
    "wof:name":"Soyong",
    "wof:placetype":"locality"
},
  "geometry": {"coordinates":[127.15097,35.76044],"type":"Point"}
}