{
  "type": "Feature",
  "properties": {
    "gn:admin1_code":"13.0",
    "gn:asciiname":"Gajaul",
    "gn:country_code":"KR",
    "gn:dem":18,
    "gn:feature_class":"P",
    "gn:feature_code":"PPL",
    "gn:name":"Gajaul",
    "gn:population":0,
    "gn:timezone":"Asia/Seoul",
    "iso:country":"KR",
    "name:kor_x_preferred":[
        "\uac00\uc790\uc6b8"
    ],
    "wof:name":"Gajaul",
    "wof:placetype":"locality"
},
  "geometry": {"coordinates":[126.72962,37.71028],"type":"Point"}
}