{
  "type": "Feature",
  "properties": {
    "gn:admin1_code":"6.0",
    "gn:asciiname":"Kul-gol",
    "gn:country_code":"KR",
    "gn:dem":570,
    "gn:feature_class":"P",
    "gn:feature_code":"PPL",
    "gn:name":"Kul-gol",
    "gn:population":0,
    "gn:timezone":"Asia/Seoul",
    "iso:country":"KR",
    "name:kor_x_preferred":[
        "\uad74\uace8"
    ],
    "wof:name":"Kul-gol",
    "wof:placetype":"locality"
},
  "geometry": {"coordinates":[128.3228,37.4689],"type":"Point"}
}