{
  "type": "Feature",
  "properties": {
    "gn:admin1_code":"17.0",
    "gn:asciiname":"Solbaegi",
    "gn:country_code":"KR",
    "gn:dem":42,
    "gn:feature_class":"P",
    "gn:feature_code":"PPL",
    "gn:name":"Solbaegi",
    "gn:population":0,
    "gn:timezone":"Asia/Seoul",
    "iso:country":"KR",
    "name:kor_x_preferred":[
        "\uc194\ubc30\uae30"
    ],
    "wof:name":"Solbaegi",
    "wof:placetype":"locality"
},
  "geometry": {"coordinates":[127.08319,36.76061],"type":"Point"}
}