{
  "type": "Feature",
  "properties": {
    "gn:admin1_code":"10.0",
    "gn:asciiname":"Oryundae",
    "gn:country_code":"KR",
    "gn:dem":44,
    "gn:feature_class":"P",
    "gn:feature_code":"PPL",
    "gn:name":"Oryundae",
    "gn:population":0,
    "gn:timezone":"Asia/Seoul",
    "iso:country":"KR",
    "name:kor_x_preferred":[
        "\uc624\ub95c\ub300"
    ],
    "wof:name":"Oryundae",
    "wof:placetype":"locality"
},
  "geometry": {"coordinates":[129.11632,35.24811],"type":"Point"}
}