{
  "type": "Feature",
  "properties": {
    "gn:admin1_code":"16.0",
    "gn:asciiname":"Haechang",
    "gn:country_code":"KR",
    "gn:dem":7,
    "gn:feature_class":"P",
    "gn:feature_code":"PPL",
    "gn:name":"Haechang",
    "gn:population":0,
    "gn:timezone":"Asia/Seoul",
    "iso:country":"KR",
    "name:kor_x_preferred":[
        "\ud574\ucc3d"
    ],
    "name:und_x_variant":[
        "Kais\u014d",
        "Haech\u2019ang",
        "Haechang"
    ],
    "wof:name":"Haechang",
    "wof:placetype":"locality"
},
  "geometry": {"coordinates":[127.58944,34.94073],"type":"Point"}
}