{
  "type": "Feature",
  "properties": {
    "gn:admin1_code":"13.0",
    "gn:admin2_code":"P'aju-si",
    "gn:asciiname":"Geomjeondong",
    "gn:country_code":"KR",
    "gn:dem":27,
    "gn:feature_class":"P",
    "gn:feature_code":"PPL",
    "gn:name":"Geomjeondong",
    "gn:population":0,
    "gn:timezone":"Asia/Seoul",
    "iso:country":"KR",
    "name:kor_x_preferred":[
        "\uac80\uc804\ub3d9"
    ],
    "name:und_x_variant":[
        "K\u014fmj\u014fl-li",
        "K\u014fmj\u014fn-dong",
        "Geomjeondong"
    ],
    "wof:name":"Geomjeondong",
    "wof:placetype":"locality"
},
  "geometry": {"coordinates":[126.84692,37.80926],"type":"Point"}
}