{
  "type": "Feature",
  "properties": {
    "gn:admin1_code":"14.0",
    "gn:asciiname":"Kulgol",
    "gn:cc2":"KR",
    "gn:country_code":"KR",
    "gn:dem":545,
    "gn:feature_class":"P",
    "gn:feature_code":"PPL",
    "gn:name":"Kulgol",
    "gn:population":0,
    "gn:timezone":"Asia/Seoul",
    "iso:country":"KR",
    "name:und_x_variant":[
        "Pongha-ri",
        "Kulkol",
        "Kulgol"
    ],
    "wof:name":"Kulgol",
    "wof:placetype":"locality"
},
  "geometry": {"coordinates":[128.18333000000001,36.73333],"type":"Point"}
}