{
  "type": "Feature",
  "properties": {
    "gn:admin1_code":"17.0",
    "gn:asciiname":"Sonangdang",
    "gn:country_code":"KR",
    "gn:dem":184,
    "gn:feature_class":"P",
    "gn:feature_code":"PPL",
    "gn:name":"S\u014fnangdang",
    "gn:population":0,
    "gn:timezone":"Asia/Seoul",
    "iso:country":"KR",
    "name:und_x_variant":[
        "\uc11c\ub0ad\ub2f9",
        "S\u014fnangdang"
    ],
    "wof:name":"Sonangdang",
    "wof:placetype":"locality"
},
  "geometry": {"coordinates":[127.4796,36.0946],"type":"Point"}
}