{
  "type": "Feature",
  "properties": {
    "gn:admin1_code":"13.0",
    "gn:asciiname":"Soran-mal",
    "gn:country_code":"KR",
    "gn:dem":30,
    "gn:feature_class":"P",
    "gn:feature_code":"PPL",
    "gn:name":"S\u014fran-mal",
    "gn:population":0,
    "gn:timezone":"Asia/Seoul",
    "iso:country":"KR",
    "name:kor_x_preferred":[
        "\uc194\uc548\ub9d0"
    ],
    "name:kor_x_variant":[
        "S\u014fran-mal"
    ],
    "wof:name":"Soran-mal",
    "wof:placetype":"locality"
},
  "geometry": {"coordinates":[126.82333,37.10833],"type":"Point"}
}