{
  "type": "Feature",
  "properties": {
    "gn:admin1_code":"14.0",
    "gn:asciiname":"Magong-ni",
    "gn:country_code":"KR",
    "gn:dem":88,
    "gn:feature_class":"P",
    "gn:feature_code":"PPLL",
    "gn:name":"Magong-ni",
    "gn:population":0,
    "gn:timezone":"Asia/Seoul",
    "iso:country":"KR",
    "name:und_x_variant":[
        "\ub9c8\uacf5\ub9ac",
        "Magong-ni"
    ],
    "wof:name":"Magong-ni",
    "wof:placetype":"locality"
},
  "geometry": {"coordinates":[128.12323000000001,36.31724000000001],"type":"Point"}
}