{
  "type": "Feature",
  "properties": {
    "gn:admin1_code":"14.0",
    "gn:asciiname":"Sanmak",
    "gn:country_code":"KR",
    "gn:dem":71,
    "gn:feature_class":"P",
    "gn:feature_code":"PPL",
    "gn:name":"Sanmak",
    "gn:population":0,
    "gn:timezone":"Asia/Seoul",
    "iso:country":"KR",
    "name:und_x_variant":[
        "\uc0b0\ub9c9",
        "Sanmak"
    ],
    "wof:name":"Sanmak",
    "wof:placetype":"locality"
},
  "geometry": {"coordinates":[128.38956999999999,36.49519],"type":"Point"}
}