{
  "type": "Feature",
  "properties": {
    "gn:admin1_code":"17.0",
    "gn:asciiname":"Yu-dong",
    "gn:country_code":"KR",
    "gn:dem":56,
    "gn:feature_class":"P",
    "gn:feature_code":"PPL",
    "gn:name":"Yu-dong",
    "gn:population":0,
    "gn:timezone":"Asia/Seoul",
    "iso:country":"KR",
    "name:und_x_variant":[
        "\uc720\ub3d9",
        "P\u014fd\u016dl",
        "Yu-dong"
    ],
    "wof:name":"Yu-dong",
    "wof:placetype":"locality"
},
  "geometry": {"coordinates":[126.676,36.8624],"type":"Point"}
}