{
  "type": "Feature",
  "properties": {
    "gn:admin1_code":"14.0",
    "gn:asciiname":"Yeongcheong",
    "gn:country_code":"KR",
    "gn:dem":38,
    "gn:feature_class":"P",
    "gn:feature_code":"PPL",
    "gn:name":"Yeongcheong",
    "gn:population":0,
    "gn:timezone":"Asia/Seoul",
    "iso:country":"KR",
    "name:und_x_variant":[
        "\uc601\uccad",
        "Y\u014fngch\u2019\u014fng",
        "Yeongcheong"
    ],
    "wof:name":"Yeongcheong",
    "wof:placetype":"locality"
},
  "geometry": {"coordinates":[128.48325,35.91847999999999],"type":"Point"}
}