{
  "type": "Feature",
  "properties": {
    "gn:admin1_code":"5.0",
    "gn:asciiname":"Ohyanggol",
    "gn:country_code":"KR",
    "gn:dem":122,
    "gn:feature_class":"P",
    "gn:feature_code":"PPL",
    "gn:name":"Ohyanggol",
    "gn:population":0,
    "gn:timezone":"Asia/Seoul",
    "iso:country":"KR",
    "name:kor_x_preferred":[
        "\uc624\ud5a5\uace8"
    ],
    "wof:name":"Ohyanggol",
    "wof:placetype":"locality"
},
  "geometry": {"coordinates":[127.83732999999999,36.77281],"type":"Point"}
}