{
  "type": "Feature",
  "properties": {
    "gn:admin1_code":"20.0",
    "gn:asciiname":"Yanghwa-dong",
    "gn:cc2":"KR",
    "gn:country_code":"KR",
    "gn:dem":121,
    "gn:feature_class":"P",
    "gn:feature_code":"PPL",
    "gn:name":"Yanghwa-dong",
    "gn:population":0,
    "gn:timezone":"Asia/Seoul",
    "iso:country":"KR",
    "name:und_x_variant":[
        "Yanghwa-ri",
        "Yanghwa-dong"
    ],
    "wof:name":"Yanghwa-dong",
    "wof:placetype":"locality"
},
  "geometry": {"coordinates":[128.28333000000001,35.01667],"type":"Point"}
}