{
  "type": "Feature",
  "properties": {
    "gn:admin1_code":"17.0",
    "gn:asciiname":"Mong-mal",
    "gn:country_code":"KR",
    "gn:dem":11,
    "gn:feature_class":"P",
    "gn:feature_code":"PPL",
    "gn:name":"Mong-mal",
    "gn:population":0,
    "gn:timezone":"Asia/Seoul",
    "iso:country":"KR",
    "name:und_x_variant":[
        "Ch\u2019\u014fngchon-ni",
        "\ubaa9\ub9d0",
        "Mong-mal"
    ],
    "wof:name":"Mong-mal",
    "wof:placetype":"locality"
},
  "geometry": {"coordinates":[126.2158,36.8658],"type":"Point"}
}