{
  "type": "Feature",
  "properties": {
    "gn:admin1_code":"17.0",
    "gn:asciiname":"Sammagol",
    "gn:country_code":"KR",
    "gn:dem":82,
    "gn:feature_class":"P",
    "gn:feature_code":"PPL",
    "gn:name":"Sammagol",
    "gn:population":0,
    "gn:timezone":"Asia/Seoul",
    "iso:country":"KR",
    "name:und_x_variant":[
        "\uc0bc\ub9c8\uace8",
        "Sammagol"
    ],
    "wof:name":"Sammagol",
    "wof:placetype":"locality"
},
  "geometry": {"coordinates":[127.32902,36.4632],"type":"Point"}
}