{
  "type": "Feature",
  "properties": {
    "gn:admin1_code":"21.0",
    "gn:asciiname":"Anyeongchuk",
    "gn:country_code":"KR",
    "gn:dem":115,
    "gn:feature_class":"P",
    "gn:feature_code":"PPL",
    "gn:name":"Anyeongchuk",
    "gn:population":0,
    "gn:timezone":"Asia/Seoul",
    "iso:country":"KR",
    "name:kor_x_preferred":[
        "\uc548\uc601\ucd95"
    ],
    "wof:name":"Anyeongchuk",
    "wof:placetype":"locality"
},
  "geometry": {"coordinates":[129.23071000000002,35.52941],"type":"Point"}
}