{
  "type": "Feature",
  "properties": {
    "gn:admin1_code":"14.0",
    "gn:asciiname":"Dusirwon",
    "gn:country_code":"KR",
    "gn:dem":145,
    "gn:feature_class":"P",
    "gn:feature_code":"PPL",
    "gn:name":"Dusirwon",
    "gn:population":0,
    "gn:timezone":"Asia/Seoul",
    "iso:country":"KR",
    "name:kor_x_preferred":[
        "\ub450\uc2e4\uc6d0"
    ],
    "name:und_x_variant":[
        "Tusorw\u014fn",
        "Tujorw\u014fn",
        "Tusirw\u014fn",
        "Dusirwon"
    ],
    "wof:name":"Dusirwon",
    "wof:placetype":"locality"
},
  "geometry": {"coordinates":[128.64521999999999,36.58761],"type":"Point"}
}