{
  "type": "Feature",
  "properties": {
    "gn:admin1_code":"16.0",
    "gn:asciiname":"Kumsodong",
    "gn:country_code":"KR",
    "gn:dem":118,
    "gn:feature_class":"P",
    "gn:feature_code":"PPL",
    "gn:name":"K\u016dmsodong",
    "gn:population":0,
    "gn:timezone":"Asia/Seoul",
    "iso:country":"KR",
    "name:kor_x_preferred":[
        "\uae08\uc18c\ub3d9"
    ],
    "name:kor_x_variant":[
        "K\u016dmsodong"
    ],
    "wof:name":"Kumsodong",
    "wof:placetype":"locality"
},
  "geometry": {"coordinates":[127.03761000000002,34.86644],"type":"Point"}
}