{
  "type": "Feature",
  "properties": {
    "gn:admin1_code":"6.0",
    "gn:asciiname":"Tosagok",
    "gn:country_code":"KR",
    "gn:dem":404,
    "gn:feature_class":"P",
    "gn:feature_code":"PPL",
    "gn:name":"Tosagok",
    "gn:population":0,
    "gn:timezone":"Asia/Seoul",
    "iso:country":"KR",
    "name:kor_x_preferred":[
        "\ub3c4\uc0ac\uace1"
    ],
    "wof:name":"Tosagok",
    "wof:placetype":"locality"
},
  "geometry": {"coordinates":[128.7311,37.3707],"type":"Point"}
}