{
  "type": "Feature",
  "properties": {
    "gn:admin1_code":"13.0",
    "gn:asciiname":"Munaemi",
    "gn:country_code":"KR",
    "gn:dem":17,
    "gn:feature_class":"P",
    "gn:feature_code":"PPL",
    "gn:name":"Munaemi",
    "gn:population":0,
    "gn:timezone":"Asia/Seoul",
    "iso:country":"KR",
    "name:und_x_variant":[
        "\ubb34\ub0b4\ubbf8",
        "Munaemi"
    ],
    "wof:name":"Munaemi",
    "wof:placetype":"locality"
},
  "geometry": {"coordinates":[126.53916,37.7232],"type":"Point"}
}