{
  "type": "Feature",
  "properties": {
    "gn:admin1_code":"20.0",
    "gn:asciiname":"Rinsen-ri",
    "gn:country_code":"KR",
    "gn:dem":9,
    "gn:feature_class":"P",
    "gn:feature_code":"PPL",
    "gn:name":"Rinsen-ri",
    "gn:population":0,
    "gn:timezone":"Asia/Seoul",
    "iso:country":"KR",
    "name:und_x_variant":[
        "Imch\u2019\u014fn-ni",
        "Imch\u2019\u014fl-li",
        "insen",
        "Imch\u2019\u014fn"
    ],
    "wof:name":"Rinsen-ri",
    "wof:placetype":"locality"
},
  "geometry": {"coordinates":[128.80000000000001,35.45],"type":"Point"}
}