{
  "type": "Feature",
  "properties": {
    "gn:admin1_code":"14.0",
    "gn:asciiname":"Sot'obaegi",
    "gn:country_code":"KR",
    "gn:dem":264,
    "gn:feature_class":"P",
    "gn:feature_code":"PPL",
    "gn:name":"Sot\u2019obaegi",
    "gn:population":0,
    "gn:timezone":"Asia/Seoul",
    "iso:country":"KR",
    "name:und_x_variant":[
        "\uc18c\ud1a0\ubc30\uae30",
        "Sot\u2019obaegi"
    ],
    "wof:name":"Sot'obaegi",
    "wof:placetype":"locality"
},
  "geometry": {"coordinates":[129.07830000000001,36.4736],"type":"Point"}
}