{
  "type": "Feature",
  "properties": {
    "gn:admin1_code":"13.0",
    "gn:asciiname":"Yeomsim",
    "gn:country_code":"KR",
    "gn:dem":29,
    "gn:feature_class":"P",
    "gn:feature_code":"PPL",
    "gn:name":"Yeomsim",
    "gn:population":0,
    "gn:timezone":"Asia/Seoul",
    "iso:country":"KR",
    "name:und_x_variant":[
        "\uc5fc\uc2ec",
        "Yeomsim",
        "Y\u014fmsim"
    ],
    "wof:name":"Yeomsim",
    "wof:placetype":"locality"
},
  "geometry": {"coordinates":[127.15139000000001,37.10889],"type":"Point"}
}