{
  "type": "Feature",
  "properties": {
    "gn:admin1_code":"16.0",
    "gn:asciiname":"Bunjidong",
    "gn:country_code":"KR",
    "gn:dem":29,
    "gn:feature_class":"P",
    "gn:feature_code":"PPL",
    "gn:name":"Bunjidong",
    "gn:population":0,
    "gn:timezone":"Asia/Seoul",
    "iso:country":"KR",
    "name:kor_x_preferred":[
        "\ubd84\uc9c0\ub3d9"
    ],
    "name:und_x_variant":[
        "Punji-dong",
        "Bunjidong"
    ],
    "wof:name":"Bunjidong",
    "wof:placetype":"locality"
},
  "geometry": {"coordinates":[127.17224,34.77541],"type":"Point"}
}