{
  "type": "Feature",
  "properties": {
    "gn:admin1_code":"17.0",
    "gn:asciiname":"Neunganmal",
    "gn:country_code":"KR",
    "gn:dem":19,
    "gn:feature_class":"P",
    "gn:feature_code":"PPL",
    "gn:name":"Neunganmal",
    "gn:population":0,
    "gn:timezone":"Asia/Seoul",
    "iso:country":"KR",
    "name:und_x_variant":[
        "\ub2a5\uc548\ub9d0",
        "N\u016dngan-mal",
        "Neunganmal"
    ],
    "wof:name":"Neunganmal",
    "wof:placetype":"locality"
},
  "geometry": {"coordinates":[127.05806,36.93203],"type":"Point"}
}