{
  "type": "Feature",
  "properties": {
    "gn:admin1_code":"5.0",
    "gn:asciiname":"Kwin-mal",
    "gn:country_code":"KR",
    "gn:dem":218,
    "gn:feature_class":"P",
    "gn:feature_code":"PPL",
    "gn:name":"Kwin-mal",
    "gn:population":0,
    "gn:timezone":"Asia/Seoul",
    "iso:country":"KR",
    "name:kor_x_preferred":[
        "\uadd3\ub9d0"
    ],
    "wof:name":"Kwin-mal",
    "wof:placetype":"locality"
},
  "geometry": {"coordinates":[128.41380000000001,37.107],"type":"Point"}
}