{
  "type": "Feature",
  "properties": {
    "gn:admin1_code":"13.0",
    "gn:asciiname":"Yangjitmal",
    "gn:country_code":"KR",
    "gn:dem":94,
    "gn:feature_class":"P",
    "gn:feature_code":"PPL",
    "gn:name":"Yangjitmal",
    "gn:population":0,
    "gn:timezone":"Asia/Seoul",
    "iso:country":"KR",
    "name:kor_x_preferred":[
        "\uc591\uc9c0\ub9d0"
    ],
    "name:kor_x_variant":[
        "\uc591\uc9d3\ub9d0"
    ],
    "name:und_x_variant":[
        "Yangjimal",
        "Yangjitmal"
    ],
    "wof:name":"Yangjitmal",
    "wof:placetype":"locality"
},
  "geometry": {"coordinates":[127.46038,37.76946],"type":"Point"}
}