{
  "type": "Feature",
  "properties": {
    "gn:admin1_code":"12.0",
    "gn:asciiname":"Bonghwachon",
    "gn:country_code":"KR",
    "gn:dem":21,
    "gn:feature_class":"P",
    "gn:feature_code":"PPL",
    "gn:name":"Bonghwachon",
    "gn:population":0,
    "gn:timezone":"Asia/Seoul",
    "iso:country":"KR",
    "name:kor_x_preferred":[
        "\ubd09\ud654\ucd0c"
    ],
    "wof:name":"Bonghwachon",
    "wof:placetype":"locality"
},
  "geometry": {"coordinates":[126.64310999999999,37.59976],"type":"Point"}
}