{
  "type": "Feature",
  "properties": {
    "gn:admin1_code":"14.0",
    "gn:asciiname":"Heukjingae",
    "gn:country_code":"KR",
    "gn:dem":103,
    "gn:feature_class":"P",
    "gn:feature_code":"PPL",
    "gn:name":"Heukjingae",
    "gn:population":0,
    "gn:timezone":"Asia/Seoul",
    "iso:country":"KR",
    "name:kor_x_preferred":[
        "\ud759\uc9c4\uac1c"
    ],
    "wof:name":"Heukjingae",
    "wof:placetype":"locality"
},
  "geometry": {"coordinates":[128.42925,36.64813],"type":"Point"}
}