{
  "type": "Feature",
  "properties": {
    "gn:admin1_code":"13.0",
    "gn:asciiname":"Bukhan",
    "gn:country_code":"KR",
    "gn:dem":210,
    "gn:feature_class":"P",
    "gn:feature_code":"PPL",
    "gn:name":"Bukhan",
    "gn:population":0,
    "gn:timezone":"Asia/Seoul",
    "iso:country":"KR",
    "name:kor_x_preferred":[
        "\ubd81\ud55c"
    ],
    "wof:name":"Bukhan",
    "wof:placetype":"locality"
},
  "geometry": {"coordinates":[126.96321,37.65257],"type":"Point"}
}