{
  "type": "Feature",
  "properties": {
    "iso:country":"KR",
    "name:eng_x_preferred":[
        "Geumchon 2(i)-dong"
    ],
    "name:kor_x_preferred":[
        "\uae08\ucd0c2\ub3d9"
    ],
    "qs:name":"\uae08\ucd0c2\ub3d9",
    "qs:name_adm0":"\ud55c\uad6d",
    "qs:name_adm1":"\uacbd\uae30\ub3c4",
    "qs:photos":21,
    "qs:photos_1k":4,
    "qs:photos_9k":1,
    "qs:photos_9r":1,
    "qs:photos_all":21,
    "qs:photos_sr":1,
    "qs:placetype":"LocalAdmin",
    "qs:pop_sr":"0",
    "wof:name":"Geumchon 2(i)-dong",
    "wof:placetype":"localadmin"
},
  "geometry": {"coordinates":[126.719398,37.905199],"type":"Point"}
}