{
  "type": "Feature",
  "properties": {
    "gn:admin1_code":"5.0",
    "gn:asciiname":"Munji",
    "gn:country_code":"KR",
    "gn:dem":153,
    "gn:feature_class":"P",
    "gn:feature_code":"PPL",
    "gn:name":"Munji",
    "gn:population":0,
    "gn:timezone":"Asia/Seoul",
    "iso:country":"KR",
    "wof:name":"Munji",
    "wof:placetype":"locality"
},
  "geometry": {"coordinates":[128.03333000000001,36.95],"type":"Point"}
}