{
  "type": "Feature",
  "properties": {
    "gn:admin1_code":"14.0",
    "gn:asciiname":"Tongsu-gol",
    "gn:country_code":"KR",
    "gn:dem":332,
    "gn:feature_class":"P",
    "gn:feature_code":"PPL",
    "gn:name":"Tongsu-gol",
    "gn:population":0,
    "gn:timezone":"Asia/Seoul",
    "iso:country":"KR",
    "name:und_x_variant":[
        "\ub3d9\uc218\uace8",
        "Tongsu-gol"
    ],
    "wof:name":"Tongsu-gol",
    "wof:placetype":"locality"
},
  "geometry": {"coordinates":[129.23519999999999,36.897],"type":"Point"}
}