{
  "type": "Feature",
  "properties": {
    "gn:admin1_code":"6.0",
    "gn:asciiname":"Twin-mal",
    "gn:country_code":"KR",
    "gn:dem":115,
    "gn:feature_class":"P",
    "gn:feature_code":"PPL",
    "gn:name":"Twin-mal",
    "gn:population":0,
    "gn:timezone":"Asia/Seoul",
    "iso:country":"KR",
    "name:und_x_variant":[
        "\ub4b7\ub9d0",
        "Twin-mal"
    ],
    "wof:name":"Twin-mal",
    "wof:placetype":"locality"
},
  "geometry": {"coordinates":[127.6604,37.9855],"type":"Point"}
}