{
  "type": "Feature",
  "properties": {
    "gn:admin1_code":"16.0",
    "gn:asciiname":"Daejeon",
    "gn:country_code":"KR",
    "gn:dem":10,
    "gn:feature_class":"P",
    "gn:feature_code":"PPL",
    "gn:name":"Daejeon",
    "gn:population":0,
    "gn:timezone":"Asia/Seoul",
    "iso:country":"KR",
    "name:kor_x_preferred":[
        "\ub300\uc804"
    ],
    "name:kor_x_variant":[
        "Taej\u014fn"
    ],
    "name:rus_x_preferred":[
        "\u0414\u044d\u0447\u043e\u043d"
    ],
    "wof:name":"Daejeon",
    "wof:placetype":"locality"
},
  "geometry": {"coordinates":[127.24109,34.79102],"type":"Point"}
}