{
  "type": "Feature",
  "properties": {
    "gn:admin1_code":"17.0",
    "gn:asciiname":"Nongol",
    "gn:country_code":"KR",
    "gn:dem":91,
    "gn:feature_class":"P",
    "gn:feature_code":"PPL",
    "gn:name":"Nongol",
    "gn:population":0,
    "gn:timezone":"Asia/Seoul",
    "iso:country":"KR",
    "name:kor_x_preferred":[
        "\ub17c\uace8"
    ],
    "wof:name":"Nongol",
    "wof:placetype":"locality"
},
  "geometry": {"coordinates":[126.92486,36.70524],"type":"Point"}
}