{
  "type": "Feature",
  "properties": {
    "gn:admin1_code":"3.0",
    "gn:asciiname":"Wonisong",
    "gn:country_code":"KR",
    "gn:dem":50,
    "gn:feature_class":"P",
    "gn:feature_code":"PPL",
    "gn:name":"W\u014fnis\u014fng",
    "gn:population":0,
    "gn:timezone":"Asia/Seoul",
    "iso:country":"KR",
    "name:und_x_variant":[
        "\uc6d0\uc774\uc131",
        "W\u014fnis\u014fng"
    ],
    "wof:name":"Wonisong",
    "wof:placetype":"locality"
},
  "geometry": {"coordinates":[127.04783,35.80698],"type":"Point"}
}