{
  "type": "Feature",
  "properties": {
    "gn:admin1_code":"14.0",
    "gn:asciiname":"Noha-ri",
    "gn:cc2":"KR",
    "gn:country_code":"KR",
    "gn:dem":114,
    "gn:feature_class":"P",
    "gn:feature_code":"PPL",
    "gn:name":"Noha-ri",
    "gn:population":0,
    "gn:timezone":"Asia/Seoul",
    "iso:country":"KR",
    "name:und_x_variant":[
        "Noha-dong",
        "Noha-ri"
    ],
    "wof:name":"Noha-ri",
    "wof:placetype":"locality"
},
  "geometry": {"coordinates":[128.68082999999999,36.58],"type":"Point"}
}