{
  "type": "Feature",
  "properties": {
    "iso:country":"KR",
    "name:eng_x_preferred":[
        "Gurim-myeon"
    ],
    "name:kor_x_preferred":[
        "\uad6c\ub9bc\uba74"
    ],
    "qs:name":"\uad6c\ub9bc\uba74",
    "qs:name_adm0":"\ud55c\uad6d",
    "qs:name_adm1":"\uc804\ub77c\ubd81\ub3c4",
    "qs:photos":33,
    "qs:photos_1k":7,
    "qs:photos_9k":1,
    "qs:photos_9r":2,
    "qs:photos_all":33,
    "qs:photos_sr":2,
    "qs:placetype":"LocalAdmin",
    "qs:pop_sr":"0",
    "wof:name":"Gurim-myeon",
    "wof:placetype":"localadmin"
},
  "geometry": {"coordinates":[127.013369,35.426057],"type":"Point"}
}