{
  "type": "Feature",
  "properties": {
    "gn:admin1_code":"14.0",
    "gn:asciiname":"Yangjima",
    "gn:country_code":"KR",
    "gn:dem":117,
    "gn:feature_class":"P",
    "gn:feature_code":"PPL",
    "gn:name":"Yangjima",
    "gn:population":0,
    "gn:timezone":"Asia/Seoul",
    "iso:country":"KR",
    "name:und_x_variant":[
        "\uc591\uc9c0\ub9c8",
        "Yangjima"
    ],
    "wof:name":"Yangjima",
    "wof:placetype":"locality"
},
  "geometry": {"coordinates":[128.02449999999999,36.1452],"type":"Point"}
}