{
  "type": "Feature",
  "properties": {
    "gn:admin1_code":"3.0",
    "gn:asciiname":"Togam-ni",
    "gn:country_code":"KR",
    "gn:dem":229,
    "gn:feature_class":"P",
    "gn:feature_code":"PPLL",
    "gn:name":"T\u014fgam-ni",
    "gn:population":0,
    "gn:timezone":"Asia/Seoul",
    "iso:country":"KR",
    "name:eng_x_preferred":[
        "Togam"
    ],
    "name:eng_x_variant":[
        "Togam-ni"
    ],
    "name:und_x_variant":[
        "\ub355\uc554\ub9ac",
        "T\u014fgam-ni"
    ],
    "wof:name":"Togam",
    "wof:placetype":"locality"
},
  "geometry": {"coordinates":[127.22702,35.63413],"type":"Point"}
}