{
  "type": "Feature",
  "properties": {
    "gn:admin1_code":"16.0",
    "gn:asciiname":"Haksong-ni",
    "gn:country_code":"KR",
    "gn:dem":101,
    "gn:feature_class":"P",
    "gn:feature_code":"PPL",
    "gn:name":"Haks\u014fng-ni",
    "gn:population":0,
    "gn:timezone":"Asia/Seoul",
    "iso:country":"KR",
    "wof:name":"Haksong-ni",
    "wof:placetype":"locality"
},
  "geometry": {"coordinates":[126.60666999999999,35.25083],"type":"Point"}
}