{
  "type": "Feature",
  "properties": {
    "gn:admin1_code":"5.0",
    "gn:asciiname":"Kuram",
    "gn:cc2":"KR",
    "gn:country_code":"KR",
    "gn:dem":293,
    "gn:feature_class":"P",
    "gn:feature_code":"PPL",
    "gn:name":"Kuram",
    "gn:population":0,
    "gn:timezone":"Asia/Seoul",
    "iso:country":"KR",
    "name:und_x_variant":[
        "Kutsugan",
        "Kuram"
    ],
    "wof:name":"Kuram",
    "wof:placetype":"locality"
},
  "geometry": {"coordinates":[128.25,37.21667],"type":"Point"}
}