{
  "type": "Feature",
  "properties": {
    "gn:admin1_code":"5.0",
    "gn:asciiname":"Hyanggagol",
    "gn:country_code":"KR",
    "gn:dem":73,
    "gn:feature_class":"P",
    "gn:feature_code":"PPL",
    "gn:name":"Hyanggagol",
    "gn:population":0,
    "gn:timezone":"Asia/Seoul",
    "iso:country":"KR",
    "name:kor_x_preferred":[
        "\ud5a5\uac00\uace8"
    ],
    "wof:name":"Hyanggagol",
    "wof:placetype":"locality"
},
  "geometry": {"coordinates":[127.41482999999999,36.62956],"type":"Point"}
}