{
  "type": "Feature",
  "properties": {
    "gn:admin1_code":"20.0",
    "gn:asciiname":"Mich'on",
    "gn:country_code":"KR",
    "gn:dem":131,
    "gn:feature_class":"P",
    "gn:feature_code":"PPL",
    "gn:name":"Mich\u2019\u014fn",
    "gn:population":0,
    "gn:timezone":"Asia/Seoul",
    "iso:country":"KR",
    "name:und_x_variant":[
        "\ubbf8\ucc9c",
        "Mich\u2019\u014fn"
    ],
    "wof:name":"Mich'on",
    "wof:placetype":"locality"
},
  "geometry": {"coordinates":[128.39869999999999,35.15438],"type":"Point"}
}