{
  "type": "Feature",
  "properties": {
    "gn:admin1_code":"16.0",
    "gn:asciiname":"Haech'ang",
    "gn:country_code":"KR",
    "gn:dem":19,
    "gn:feature_class":"P",
    "gn:feature_code":"PPL",
    "gn:name":"Haech\u2019ang",
    "gn:population":0,
    "gn:timezone":"Asia/Seoul",
    "iso:country":"KR",
    "name:kor_x_preferred":[
        "\uc7a5\uc218"
    ],
    "name:kor_x_variant":[
        "Haech\u2019ang"
    ],
    "wof:name":"Haech'ang",
    "wof:placetype":"locality"
},
  "geometry": {"coordinates":[126.6825,34.48083],"type":"Point"}
}