{
  "type": "Feature",
  "properties": {
    "gn:admin1_code":"6.0",
    "gn:asciiname":"Wira-ri",
    "gn:country_code":"KR",
    "gn:dem":118,
    "gn:feature_class":"P",
    "gn:feature_code":"PPL",
    "gn:name":"Wira-ri",
    "gn:population":0,
    "gn:timezone":"Asia/Seoul",
    "iso:country":"KR",
    "name:und_x_variant":[
        "\uc704\ub77c\ub9ac",
        "Wira-ri"
    ],
    "wof:name":"Wira-ri",
    "wof:placetype":"locality"
},
  "geometry": {"coordinates":[127.7175,38.09389],"type":"Point"}
}