{
  "type": "Feature",
  "properties": {
    "gn:admin1_code":"16.0",
    "gn:asciiname":"Yong-ni",
    "gn:country_code":"KR",
    "gn:dem":25,
    "gn:feature_class":"P",
    "gn:feature_code":"PPL",
    "gn:name":"Yong-ni",
    "gn:population":0,
    "gn:timezone":"Asia/Seoul",
    "iso:country":"KR",
    "name:und_x_variant":[
        "Y\u014fn-ni",
        "Y\u014fn-dong",
        "Yong-ni",
        "Y\u014fl-li"
    ],
    "wof:name":"Yong-ni",
    "wof:placetype":"locality"
},
  "geometry": {"coordinates":[126.34083,34.96083],"type":"Point"}
}