{
  "type": "Feature",
  "properties": {
    "gn:admin1_code":"20.0",
    "gn:asciiname":"Porim-dong",
    "gn:country_code":"KR",
    "gn:dem":61,
    "gn:feature_class":"P",
    "gn:feature_code":"PPL",
    "gn:name":"Porim-dong",
    "gn:population":0,
    "gn:timezone":"Asia/Seoul",
    "iso:country":"KR",
    "name:und_x_variant":[
        "\ubcf4\ub9bc\ub3d9",
        "Porim-dong"
    ],
    "wof:name":"Porim-dong",
    "wof:placetype":"locality"
},
  "geometry": {"coordinates":[128.15038999999999,35.59702],"type":"Point"}
}