{
  "type": "Feature",
  "properties": {
    "gn:admin1_code":"14.0",
    "gn:asciiname":"Mang-gol",
    "gn:country_code":"KR",
    "gn:dem":236,
    "gn:feature_class":"P",
    "gn:feature_code":"PPL",
    "gn:name":"Mang-gol",
    "gn:population":0,
    "gn:timezone":"Asia/Seoul",
    "iso:country":"KR",
    "name:und_x_variant":[
        "\ub9dd\uace8",
        "Mang-gol"
    ],
    "wof:name":"Mang-gol",
    "wof:placetype":"locality"
},
  "geometry": {"coordinates":[128.83879999999999,36.3757],"type":"Point"}
}