{
  "type": "Feature",
  "properties": {
    "gn:admin1_code":"3.0",
    "gn:asciiname":"Kolttum",
    "gn:country_code":"KR",
    "gn:dem":45,
    "gn:feature_class":"P",
    "gn:feature_code":"PPL",
    "gn:name":"Koltt\u016dm",
    "gn:population":0,
    "gn:timezone":"Asia/Seoul",
    "iso:country":"KR",
    "name:und_x_variant":[
        "\uace8\ub738",
        "Koltt\u016dm"
    ],
    "wof:name":"Kolttum",
    "wof:placetype":"locality"
},
  "geometry": {"coordinates":[127.10661,35.95899],"type":"Point"}
}