{
  "type": "Feature",
  "properties": {
    "gn:admin1_code":"17.0",
    "gn:asciiname":"Doengalmak",
    "gn:country_code":"KR",
    "gn:dem":111,
    "gn:feature_class":"P",
    "gn:feature_code":"PPL",
    "gn:name":"Doengalmak",
    "gn:population":0,
    "gn:timezone":"Asia/Seoul",
    "iso:country":"KR",
    "name:kor_x_preferred":[
        "\ub41c\uac08\ub9c9"
    ],
    "wof:name":"Doengalmak",
    "wof:placetype":"locality"
},
  "geometry": {"coordinates":[127.01483,36.71016],"type":"Point"}
}