{
  "type": "Feature",
  "properties": {
    "gn:admin1_code":"6.0",
    "gn:asciiname":"Saemaeul",
    "gn:country_code":"KR",
    "gn:dem":111,
    "gn:feature_class":"P",
    "gn:feature_code":"PPL",
    "gn:name":"Saemaeul",
    "gn:population":0,
    "gn:timezone":"Asia/Seoul",
    "iso:country":"KR",
    "name:jpn_x_preferred":[
        "\u30bb\u30de\u30a6\u30eb"
    ],
    "name:kor_x_preferred":[
        "\uc0c8\ub9c8\uc744"
    ],
    "name:und_x_variant":[
        "Sinp\u2019y\u014fng-ni",
        "Saema\u016dl",
        "Saemaeul"
    ],
    "wof:name":"Saemaeul",
    "wof:placetype":"locality"
},
  "geometry": {"coordinates":[128.38065,38.33039],"type":"Point"}
}