{
  "type": "Feature",
  "properties": {
    "gn:admin1_code":"17.0",
    "gn:asciiname":"Komugi",
    "gn:country_code":"KR",
    "gn:dem":10,
    "gn:feature_class":"P",
    "gn:feature_code":"PPL",
    "gn:name":"K\u014fmugi",
    "gn:population":0,
    "gn:timezone":"Asia/Seoul",
    "iso:country":"KR",
    "name:und_x_variant":[
        "\uac70\ubb35\uc774",
        "K\u014fmugi"
    ],
    "wof:name":"Komugi",
    "wof:placetype":"locality"
},
  "geometry": {"coordinates":[126.6418,36.9504],"type":"Point"}
}