{
  "type": "Feature",
  "properties": {
    "gn:admin1_code":"14.0",
    "gn:asciiname":"Kogong-ni",
    "gn:country_code":"KR",
    "gn:dem":121,
    "gn:feature_class":"P",
    "gn:feature_code":"PPL",
    "gn:name":"Kogong-ni",
    "gn:population":0,
    "gn:timezone":"Asia/Seoul",
    "iso:country":"KR",
    "name:und_x_variant":[
        "\uace0\uace1\ub9ac",
        "Kogong-ni"
    ],
    "wof:name":"Kogong-ni",
    "wof:placetype":"locality"
},
  "geometry": {"coordinates":[128.86250000000001,36.4952],"type":"Point"}
}