{
  "type": "Feature",
  "properties": {
    "gn:admin1_code":"13.0",
    "gn:admin2_code":"Yongin-si",
    "gn:asciiname":"Nambatan",
    "gn:country_code":"KR",
    "gn:dem":163,
    "gn:feature_class":"P",
    "gn:feature_code":"PPL",
    "gn:name":"Nambatan",
    "gn:population":0,
    "gn:timezone":"Asia/Seoul",
    "iso:country":"KR",
    "name:kor_x_preferred":[
        "\ub0a8\ubc1c\uc548"
    ],
    "name:kor_x_variant":[
        "\ub0a8\ubc2d\uc548"
    ],
    "name:und_x_variant":[
        "Nambaran",
        "Nambalan",
        "Nambatan"
    ],
    "wof:name":"Nambatan",
    "wof:placetype":"locality"
},
  "geometry": {"coordinates":[127.28488,37.22415],"type":"Point"}
}