{
  "type": "Feature",
  "properties": {
    "gn:admin1_code":"20.0",
    "gn:asciiname":"Seokgyo",
    "gn:country_code":"KR",
    "gn:dem":13,
    "gn:feature_class":"P",
    "gn:feature_code":"PPL",
    "gn:name":"Seokgyo",
    "gn:population":0,
    "gn:timezone":"Asia/Seoul",
    "iso:country":"KR",
    "name:kor_x_preferred":[
        "\uc11d\uad50"
    ],
    "name:und_x_variant":[
        "Suk\u2019o",
        "Sukho-ri",
        "Sukho",
        "Seokgyo"
    ],
    "wof:name":"Seokgyo",
    "wof:placetype":"locality"
},
  "geometry": {"coordinates":[127.89792,34.76695],"type":"Point"}
}