{
  "type": "Feature",
  "properties": {
    "gn:admin1_code":"21.0",
    "gn:asciiname":"Yeongnam",
    "gn:country_code":"KR",
    "gn:dem":26,
    "gn:feature_class":"P",
    "gn:feature_code":"PPL",
    "gn:name":"Yeongnam",
    "gn:population":0,
    "gn:timezone":"Asia/Seoul",
    "iso:country":"KR",
    "name:kor_x_preferred":[
        "\uc601\ub0a8"
    ],
    "wof:name":"Yeongnam",
    "wof:placetype":"locality"
},
  "geometry": {"coordinates":[129.31208000000001,35.43618],"type":"Point"}
}