{
  "type": "Feature",
  "properties": {
    "gn:admin1_code":"21.0",
    "gn:asciiname":"Yeongnam",
    "gn:country_code":"KR",
    "gn:dem":26,
    "gn:feature_class":"P",
    "gn:feature_code":"PPL",
    "gn:name":"Yeongnam",
    "gn:population":0,
    "gn:timezone":"Asia/Seoul",
    "iso:country":"KR",
    "name:ara_x_preferred":[
        "\u064a\u0648\u0646\u063a\u0646\u0627\u0645"
    ],
    "name:fas_x_preferred":[
        "\u06cc\u0648\u0646\u06af\u0646\u0627\u0645"
    ],
    "name:hun_x_preferred":[
        "Jongnam"
    ],
    "name:ind_x_preferred":[
        "Yeongnam"
    ],
    "name:kor_x_preferred":[
        "\uc601\ub0a8"
    ],
    "name:kor_x_variant":[
        "\uc601\ub0a8 \uc9c0\ubc29"
    ],
    "name:nor_x_preferred":[
        "Yeongnam"
    ],
    "name:rus_x_preferred":[
        "\u0419\u043e\u043d\u043d\u0430\u043c"
    ],
    "name:tha_x_preferred":[
        "\u0e22\u0e47\u0e2d\u0e07\u0e19\u0e31\u0e21"
    ],
    "name:urd_x_preferred":[
        "\u06cc\u0626\u0648\u0646\u06af\u0646\u0627\u0645"
    ],
    "name:vie_x_preferred":[
        "Yeongnam"
    ],
    "name:zho_x_preferred":[
        "\u5cad\u5357\u5730\u65b9"
    ],
    "wof:name":"Yeongnam",
    "wof:placetype":"locality"
},
  "geometry": {"coordinates":[129.31208000000001,35.43618],"type":"Point"}
}