{
  "type": "Feature",
  "properties": {
    "gn:admin1_code":"14.0",
    "gn:asciiname":"Paeyang-gol",
    "gn:country_code":"KR",
    "gn:dem":244,
    "gn:feature_class":"P",
    "gn:feature_code":"PPL",
    "gn:name":"Paeyang-gol",
    "gn:population":0,
    "gn:timezone":"Asia/Seoul",
    "iso:country":"KR",
    "name:und_x_variant":[
        "\ubc30\uc591\uace8",
        "Paeyang-gol"
    ],
    "wof:name":"Paeyang-gol",
    "wof:placetype":"locality"
},
  "geometry": {"coordinates":[129.05008999999998,36.13538],"type":"Point"}
}