{
  "type": "Feature",
  "properties": {
    "gn:admin1_code":"11.0",
    "gn:asciiname":"Sadangil-tong",
    "gn:country_code":"KR",
    "gn:dem":27,
    "gn:feature_class":"P",
    "gn:feature_code":"PPL",
    "gn:name":"Sadangil-tong",
    "gn:population":0,
    "gn:timezone":"Asia/Seoul",
    "iso:country":"KR",
    "name:eng_x_preferred":[
        "Sadangil"
    ],
    "name:eng_x_variant":[
        "Sadangil-tong"
    ],
    "name:und_x_variant":[
        "\uc0ac\ub2f91\ub3d9",
        "Sadangil-dong"
    ],
    "wof:name":"Sadangil",
    "wof:placetype":"locality"
},
  "geometry": {"coordinates":[126.97611000000001,37.48028],"type":"Point"}
}