{
  "type": "Feature",
  "properties": {
    "gn:admin1_code":"17.0",
    "gn:asciiname":"Oncheon",
    "gn:country_code":"KR",
    "gn:dem":90,
    "gn:feature_class":"P",
    "gn:feature_code":"PPL",
    "gn:name":"Oncheon",
    "gn:population":0,
    "gn:timezone":"Asia/Seoul",
    "iso:country":"KR",
    "name:und_x_variant":[
        "Onch\u2019\u014fn",
        "\uc628\ucc9c",
        "Onch\u2019\u014fl-li",
        "Oncheon"
    ],
    "wof:name":"Oncheon",
    "wof:placetype":"locality"
},
  "geometry": {"coordinates":[127.25725,36.38693],"type":"Point"}
}