{
  "type": "Feature",
  "properties": {
    "gn:admin1_code":"6.0",
    "gn:asciiname":"Pyokt'an",
    "gn:country_code":"KR",
    "gn:dem":297,
    "gn:feature_class":"P",
    "gn:feature_code":"PPL",
    "gn:name":"Py\u014fkt\u2019an",
    "gn:population":0,
    "gn:timezone":"Asia/Seoul",
    "iso:country":"KR",
    "name:kor_x_preferred":[
        "\ubcbd\ud0c4"
    ],
    "name:kor_x_variant":[
        "Py\u014fkt\u2019an"
    ],
    "name:und_x_variant":[
        "Py\u014fkt\u2019an-ni"
    ],
    "wof:name":"Pyokt'an",
    "wof:placetype":"locality"
},
  "geometry": {"coordinates":[128.60159999999999,37.3935],"type":"Point"}
}