{
  "type": "Feature",
  "properties": {
    "gn:admin1_code":"14.0",
    "gn:asciiname":"Sanhap",
    "gn:country_code":"KR",
    "gn:dem":102,
    "gn:feature_class":"P",
    "gn:feature_code":"PPL",
    "gn:name":"Sanhap",
    "gn:population":0,
    "gn:timezone":"Asia/Seoul",
    "iso:country":"KR",
    "name:kor_x_preferred":[
        "\uc0b0\ud569"
    ],
    "wof:name":"Sanhap",
    "wof:placetype":"locality"
},
  "geometry": {"coordinates":[128.47811000000002,36.57985],"type":"Point"}
}