{
  "type": "Feature",
  "properties": {
    "gn:admin1_code":"5.0",
    "gn:asciiname":"Angeoni",
    "gn:country_code":"KR",
    "gn:dem":280,
    "gn:feature_class":"P",
    "gn:feature_code":"PPL",
    "gn:name":"Angeoni",
    "gn:population":0,
    "gn:timezone":"Asia/Seoul",
    "iso:country":"KR",
    "name:kor_x_preferred":[
        "\uc548\uac74\uc774"
    ],
    "wof:name":"Angeoni",
    "wof:placetype":"locality"
},
  "geometry": {"coordinates":[127.57962000000001,36.6274],"type":"Point"}
}