{
  "type": "Feature",
  "properties": {
    "gn:admin1_code":"13.0",
    "gn:asciiname":"Wondang-ri",
    "gn:country_code":"KR",
    "gn:dem":88,
    "gn:feature_class":"P",
    "gn:feature_code":"PPLL",
    "gn:name":"Wondang-ri",
    "gn:population":0,
    "gn:timezone":"Asia/Seoul",
    "iso:country":"KR",
    "name:und_x_variant":[
        "\uc6d0\ub2f9\ub9ac",
        "Wondang-ri",
        "W\u014fndang-ni"
    ],
    "wof:name":"Wondang-ri",
    "wof:placetype":"locality"
},
  "geometry": {"coordinates":[127.32222,37.4325],"type":"Point"}
}