{
  "type": "Feature",
  "properties": {
    "gn:admin1_code":"16.0",
    "gn:asciiname":"Tongjok",
    "gn:country_code":"KR",
    "gn:dem":40,
    "gn:feature_class":"P",
    "gn:feature_code":"PPL",
    "gn:name":"Tongj\u014fk",
    "gn:population":0,
    "gn:timezone":"Asia/Seoul",
    "iso:country":"KR",
    "name:kor_x_preferred":[
        "\ub3d9\uc801"
    ],
    "name:kor_x_variant":[
        "Tongj\u014fk"
    ],
    "wof:name":"Tongjok",
    "wof:placetype":"locality"
},
  "geometry": {"coordinates":[127.23412,34.53814000000001],"type":"Point"}
}