{
  "type": "Feature",
  "properties": {
    "gn:admin1_code":"13.0",
    "gn:asciiname":"Sanjung",
    "gn:country_code":"KR",
    "gn:dem":271,
    "gn:feature_class":"P",
    "gn:feature_code":"PPL",
    "gn:name":"Sanjung",
    "gn:population":0,
    "gn:timezone":"Asia/Seoul",
    "iso:country":"KR",
    "name:und_x_variant":[
        "\uc0b0\uc911",
        "Sanjung"
    ],
    "wof:name":"Sanjung",
    "wof:placetype":"locality"
},
  "geometry": {"coordinates":[127.45778,37.455],"type":"Point"}
}