{
  "type": "Feature",
  "properties": {
    "gn:admin1_code":"16.0",
    "gn:asciiname":"Jungbang",
    "gn:country_code":"KR",
    "gn:dem":37,
    "gn:feature_class":"P",
    "gn:feature_code":"PPL",
    "gn:name":"Jungbang",
    "gn:population":0,
    "gn:timezone":"Asia/Seoul",
    "iso:country":"KR",
    "name:kor_x_preferred":[
        "\uc911\ubc29"
    ],
    "wof:name":"Jungbang",
    "wof:placetype":"locality"
},
  "geometry": {"coordinates":[126.9528,35.00217],"type":"Point"}
}