{
  "type": "Feature",
  "properties": {
    "gn:admin1_code":"16.0",
    "gn:asciiname":"Pongsong",
    "gn:country_code":"KR",
    "gn:dem":6,
    "gn:feature_class":"P",
    "gn:feature_code":"PPL",
    "gn:name":"Pongs\u014fng",
    "gn:population":0,
    "gn:timezone":"Asia/Seoul",
    "iso:country":"KR",
    "name:kor_x_preferred":[
        "\ubd09\uc131"
    ],
    "name:kor_x_variant":[
        "Pongs\u014fng"
    ],
    "wof:name":"Pongsong",
    "wof:placetype":"locality"
},
  "geometry": {"coordinates":[127.17586,34.55302],"type":"Point"}
}