{
  "type": "Feature",
  "properties": {
    "gn:admin1_code":"13.0",
    "gn:asciiname":"Wondeongmok",
    "gn:country_code":"KR",
    "gn:dem":28,
    "gn:feature_class":"P",
    "gn:feature_code":"PPL",
    "gn:name":"Wondeongmok",
    "gn:population":0,
    "gn:timezone":"Asia/Seoul",
    "iso:country":"KR",
    "name:und_x_variant":[
        "\uc6d0\ub355\ubaa9",
        "W\u014fnd\u014fngmok",
        "Wondeongmok"
    ],
    "wof:name":"Wondeongmok",
    "wof:placetype":"locality"
},
  "geometry": {"coordinates":[126.9558,36.9489],"type":"Point"}
}