{
  "type": "Feature",
  "properties": {
    "gn:admin1_code":"20.0",
    "gn:asciiname":"Yerimilgu",
    "gn:cc2":"KR",
    "gn:country_code":"KR",
    "gn:dem":69,
    "gn:feature_class":"P",
    "gn:feature_code":"PPL",
    "gn:name":"Yerimilgu",
    "gn:population":0,
    "gn:timezone":"Asia/Seoul",
    "iso:country":"KR",
    "name:und_x_variant":[
        "Yerim-ni",
        "Yerim",
        "Yeim-ni",
        "Yerimilgu"
    ],
    "wof:name":"Yerimilgu",
    "wof:placetype":"locality"
},
  "geometry": {"coordinates":[128.75443999999999,35.47027999999999],"type":"Point"}
}