{
  "type": "Feature",
  "properties": {
    "gn:admin1_code":"6.0",
    "gn:asciiname":"Sabuk",
    "gn:country_code":"KR",
    "gn:dem":607,
    "gn:feature_class":"P",
    "gn:feature_code":"PPL",
    "gn:name":"Sabuk",
    "gn:population":0,
    "gn:timezone":"Asia/Seoul",
    "iso:country":"KR",
    "name:kor_x_preferred":[
        "\uc0ac\ubd81"
    ],
    "name:und_x_variant":[
        "Sabung-ni",
        "Sabuk"
    ],
    "wof:name":"Sabuk",
    "wof:placetype":"locality"
},
  "geometry": {"coordinates":[128.81790000000001,37.2273],"type":"Point"}
}