{
  "type": "Feature",
  "properties": {
    "iso:country":"KR",
    "name:kor_x_preferred":[
        "\ucd08\uc7a5\ub3d9"
    ],
    "qs:gn_adm0_cc":"KR",
    "qs:gn_fcode":"PPL",
    "qs:gn_local":1838524,
    "qs:gn_namadm1":"10",
    "qs:gn_name":"Ch\u2019ojang-dong",
    "qs:local_max":2765,
    "qs:local_sum":24552,
    "qs:localhoods":60,
    "qs:name":"\ucd08\uc7a5\ub3d9",
    "qs:name_adm0":"\ud55c\uad6d",
    "qs:name_adm1":"\ubd80\uc0b0",
    "qs:name_adm2":"\uc11c\uad6c",
    "qs:name_lau":"\ucd08\uc7a5\ub3d9",
    "qs:name_local":"\ubd80\uc0b0",
    "qs:photo_max":68,
    "qs:photo_sum":86,
    "qs:placetype":"Suburb",
    "qs:quad_count":5,
    "qs:woe_adm0":23424868,
    "qs:woe_adm1":2345968,
    "qs:woe_adm2":28289277,
    "qs:woe_lau":28805958,
    "qs:woe_local":1132447,
    "qs:woe_ver":"7.10.0",
    "wof:lang":[
        "kor"
    ],
    "wof:name":"\ucd08\uc7a5\ub3d9",
    "wof:placetype":"neighbourhood"
},
  "geometry": {"coordinates":[129.01549800000001,35.092027],"type":"Point"}
}