{
  "type": "Feature",
  "properties": {
    "gn:admin1_code":"17.0",
    "gn:asciiname":"Sungson'gul",
    "gn:country_code":"KR",
    "gn:dem":36,
    "gn:feature_class":"P",
    "gn:feature_code":"PPL",
    "gn:name":"S\u016dngs\u014fn\u2019gul",
    "gn:population":0,
    "gn:timezone":"Asia/Seoul",
    "iso:country":"KR",
    "name:und_x_variant":[
        "S\u016dngs\u014fn-dong",
        "S\u016dngs\u014fn\u2019gul"
    ],
    "wof:name":"Sungson'gul",
    "wof:placetype":"locality"
},
  "geometry": {"coordinates":[126.53333000000001,36.88333],"type":"Point"}
}