{
  "type": "Feature",
  "properties": {
    "gn:admin1_code":"12.0",
    "gn:asciiname":"Jongang",
    "gn:country_code":"KR",
    "gn:dem":25,
    "gn:feature_class":"P",
    "gn:feature_code":"PPL",
    "gn:name":"Jongang",
    "gn:population":0,
    "gn:timezone":"Asia/Seoul",
    "iso:country":"KR",
    "name:und_x_variant":[
        "Chongang-dong",
        "\uc874\uac15",
        "Jongang",
        "Chon\u2019gang"
    ],
    "wof:name":"Jongang",
    "wof:placetype":"locality"
},
  "geometry": {"coordinates":[126.41542,37.6804],"type":"Point"}
}