{
  "type": "Feature",
  "properties": {
    "gn:admin1_code":"21.0",
    "gn:asciiname":"Pogan",
    "gn:cc2":"KR",
    "gn:country_code":"KR",
    "gn:dem":121,
    "gn:feature_class":"P",
    "gn:feature_code":"PPL",
    "gn:name":"Pogan",
    "gn:population":0,
    "gn:timezone":"Asia/Seoul",
    "iso:country":"KR",
    "name:und_x_variant":[
        "Yangji",
        "Pogan-dong",
        "Pogal-li",
        "Pogan"
    ],
    "wof:name":"Pogan",
    "wof:placetype":"locality"
},
  "geometry": {"coordinates":[129.15889000000001,35.70389],"type":"Point"}
}