{
  "type": "Feature",
  "properties": {
    "gn:admin1_code":"6.0",
    "gn:asciiname":"Wonsugol",
    "gn:country_code":"KR",
    "gn:dem":151,
    "gn:feature_class":"P",
    "gn:feature_code":"PPL",
    "gn:name":"Wonsugol",
    "gn:population":0,
    "gn:timezone":"Asia/Seoul",
    "iso:country":"KR",
    "name:kor_x_preferred":[
        "\uc6d0\uc218\uace8"
    ],
    "name:kor_x_variant":[
        "W\u014fnsu-gol"
    ],
    "wof:name":"Wonsugol",
    "wof:placetype":"locality"
},
  "geometry": {"coordinates":[127.73390000000001,37.72676],"type":"Point"}
}