{
  "type": "Feature",
  "properties": {
    "gn:admin1_code":"6.0",
    "gn:asciiname":"Myongwolil-li",
    "gn:country_code":"KR",
    "gn:dem":373,
    "gn:feature_class":"P",
    "gn:feature_code":"PPL",
    "gn:name":"My\u014fngw\u014flil-li",
    "gn:population":0,
    "gn:timezone":"Asia/Seoul",
    "iso:country":"KR",
    "name:und_x_variant":[
        "\uba85\uc6d41\ub9ac",
        "My\u014fngw\u014flil-li"
    ],
    "wof:name":"Myongwolil-li",
    "wof:placetype":"locality"
},
  "geometry": {"coordinates":[127.51056,38.10139],"type":"Point"}
}