{
  "type": "Feature",
  "properties": {
    "gn:admin1_code":"16.0",
    "gn:asciiname":"Sinp'yong-ni",
    "gn:country_code":"KR",
    "gn:dem":1,
    "gn:feature_class":"P",
    "gn:feature_code":"PPL",
    "gn:name":"Sinp\u2019y\u014fng-ni",
    "gn:population":0,
    "gn:timezone":"Asia/Seoul",
    "iso:country":"KR",
    "wof:name":"Sinp'yong-ni",
    "wof:placetype":"locality"
},
  "geometry": {"coordinates":[127.23166999999999,34.46639],"type":"Point"}
}