{
  "type": "Feature",
  "properties": {
    "gn:admin1_code":"20.0",
    "gn:asciiname":"Sanhak",
    "gn:country_code":"KR",
    "gn:dem":59,
    "gn:feature_class":"P",
    "gn:feature_code":"PPL",
    "gn:name":"Sanhak",
    "gn:population":0,
    "gn:timezone":"Asia/Seoul",
    "iso:country":"KR",
    "name:und_x_variant":[
        "\uc0b0\ud559",
        "Sanhak"
    ],
    "wof:name":"Sanhak",
    "wof:placetype":"locality"
},
  "geometry": {"coordinates":[128.30162000000001,35.34825],"type":"Point"}
}