{
  "type": "Feature",
  "properties": {
    "gn:admin1_code":"13.0",
    "gn:asciiname":"Joje",
    "gn:country_code":"KR",
    "gn:dem":89,
    "gn:feature_class":"P",
    "gn:feature_code":"PPL",
    "gn:name":"Joje",
    "gn:population":0,
    "gn:timezone":"Asia/Seoul",
    "iso:country":"KR",
    "name:kor_x_preferred":[
        "\uc870\uc81c"
    ],
    "name:und_x_variant":[
        "Choje"
    ],
    "wof:name":"Joje",
    "wof:placetype":"locality"
},
  "geometry": {"coordinates":[127.5283,37.0917],"type":"Point"}
}