{
  "type": "Feature",
  "properties": {
    "gn:admin1_code":"16.0",
    "gn:asciiname":"Geonneoseom",
    "gn:country_code":"KR",
    "gn:dem":81,
    "gn:feature_class":"P",
    "gn:feature_code":"PPL",
    "gn:name":"Geonneoseom",
    "gn:population":0,
    "gn:timezone":"Asia/Seoul",
    "iso:country":"KR",
    "name:kor_x_preferred":[
        "\uac74\ub108\uc12c"
    ],
    "wof:name":"Geonneoseom",
    "wof:placetype":"locality"
},
  "geometry": {"coordinates":[126.93917999999999,34.95595],"type":"Point"}
}