{
  "type": "Feature",
  "properties": {
    "gn:admin1_code":"6.0",
    "gn:asciiname":"Kaekkut",
    "gn:country_code":"KR",
    "gn:dem":322,
    "gn:feature_class":"P",
    "gn:feature_code":"PPL",
    "gn:name":"Kaekk\u016dt",
    "gn:population":0,
    "gn:timezone":"Asia/Seoul",
    "iso:country":"KR",
    "name:kor_x_preferred":[
        "\uac1c\ub05d"
    ],
    "name:kor_x_variant":[
        "Kaekk\u016dt"
    ],
    "wof:name":"Kaekkut",
    "wof:placetype":"locality"
},
  "geometry": {"coordinates":[128.67590000000001,37.3988],"type":"Point"}
}