{
  "type": "Feature",
  "properties": {
    "gn:admin1_code":"13.0",
    "gn:asciiname":"Sangsil-li",
    "gn:country_code":"KR",
    "gn:dem":27,
    "gn:feature_class":"P",
    "gn:feature_code":"PPL",
    "gn:name":"Sangsil-li",
    "gn:population":0,
    "gn:timezone":"Asia/Seoul",
    "iso:country":"KR",
    "name:kor_x_preferred":[
        "\uc0c1\uc2e0\ub9ac"
    ],
    "wof:name":"Sangsil-li",
    "wof:placetype":"locality"
},
  "geometry": {"coordinates":[126.89610999999999,37.09833],"type":"Point"}
}