{
  "type": "Feature",
  "properties": {
    "gn:admin1_code":"17.0",
    "gn:asciiname":"Wigipeunnae",
    "gn:country_code":"KR",
    "gn:dem":46,
    "gn:feature_class":"P",
    "gn:feature_code":"PPL",
    "gn:name":"Wigipeunnae",
    "gn:population":0,
    "gn:timezone":"Asia/Seoul",
    "iso:country":"KR",
    "name:kor_x_preferred":[
        "\uc704\uae4a\uc740\ub0b4"
    ],
    "wof:name":"Wigipeunnae",
    "wof:placetype":"locality"
},
  "geometry": {"coordinates":[127.25673,36.6443],"type":"Point"}
}