{
  "type": "Feature",
  "properties": {
    "gn:admin1_code":"13.0",
    "gn:asciiname":"Daechu",
    "gn:country_code":"KR",
    "gn:dem":15,
    "gn:feature_class":"P",
    "gn:feature_code":"PPL",
    "gn:name":"Daechu",
    "gn:population":0,
    "gn:timezone":"Asia/Seoul",
    "iso:country":"KR",
    "name:kor_x_preferred":[
        "\ub300\ucd94"
    ],
    "name:und_x_variant":[
        "\ub300\ucd94\ub9ac",
        "Taech\u2019u-ri",
        "Daechu"
    ],
    "wof:name":"Daechu",
    "wof:placetype":"locality"
},
  "geometry": {"coordinates":[127.01527,36.9707],"type":"Point"}
}