{
  "type": "Feature",
  "properties": {
    "gn:admin1_code":"17.0",
    "gn:asciiname":"Tangjinp'o-ri",
    "gn:country_code":"KR",
    "gn:dem":14,
    "gn:feature_class":"P",
    "gn:feature_code":"PPLL",
    "gn:name":"Tangjinp\u2019o-ri",
    "gn:population":0,
    "gn:timezone":"Asia/Seoul",
    "iso:country":"KR",
    "name:und_x_variant":[
        "\ub2f9\uc9c4\ud3ec\ub9ac",
        "Tangjinp\u2019o-ri"
    ],
    "wof:name":"Tangjinp'o-ri",
    "wof:placetype":"locality"
},
  "geometry": {"coordinates":[126.5552,36.958],"type":"Point"}
}