{
  "type": "Feature",
  "properties": {
    "gn:admin1_code":"16.0",
    "gn:asciiname":"Maegye",
    "gn:cc2":"KR",
    "gn:country_code":"KR",
    "gn:dem":5,
    "gn:feature_class":"P",
    "gn:feature_code":"PPL",
    "gn:name":"Maegye",
    "gn:population":0,
    "gn:timezone":"Asia/Seoul",
    "iso:country":"KR",
    "name:und_x_variant":[
        "Maege",
        "Maegye"
    ],
    "wof:name":"Maegye",
    "wof:placetype":"locality"
},
  "geometry": {"coordinates":[126.25,34.98333],"type":"Point"}
}