{
  "type": "Feature",
  "properties": {
    "gn:admin1_code":"14.0",
    "gn:asciiname":"Hwadang",
    "gn:country_code":"KR",
    "gn:dem":36,
    "gn:feature_class":"P",
    "gn:feature_code":"PPL",
    "gn:name":"Hwadang",
    "gn:population":0,
    "gn:timezone":"Asia/Seoul",
    "iso:country":"KR",
    "name:und_x_variant":[
        "\ud654\ub2f9",
        "Hwadang"
    ],
    "wof:name":"Hwadang",
    "wof:placetype":"locality"
},
  "geometry": {"coordinates":[129.21437,36.06003],"type":"Point"}
}