{
  "type": "Feature",
  "properties": {
    "gn:admin1_code":"17.0",
    "gn:asciiname":"An-mal",
    "gn:country_code":"KR",
    "gn:dem":16,
    "gn:feature_class":"P",
    "gn:feature_code":"PPL",
    "gn:name":"An-mal",
    "gn:population":0,
    "gn:timezone":"Asia/Seoul",
    "iso:country":"KR",
    "name:und_x_variant":[
        "\uc548\ub9d0",
        "An-mal"
    ],
    "wof:name":"An-mal",
    "wof:placetype":"locality"
},
  "geometry": {"coordinates":[126.3031,36.6759],"type":"Point"}
}