{
  "type": "Feature",
  "properties": {
    "iso:country":"KR",
    "name:eng_x_preferred":[
        "Saengyeon 2(i)-dong"
    ],
    "name:kor_x_preferred":[
        "\uc0dd\uc5f02\ub3d9"
    ],
    "qs:name":"\uc0dd\uc5f02\ub3d9",
    "qs:name_adm0":"\ud55c\uad6d",
    "qs:name_adm1":"\uacbd\uae30\ub3c4",
    "qs:photos":36,
    "qs:photos_1k":7,
    "qs:photos_9k":1,
    "qs:photos_9r":2,
    "qs:photos_all":36,
    "qs:photos_sr":2,
    "qs:placetype":"LocalAdmin",
    "qs:pop_sr":"0",
    "wof:name":"Saengyeon 2(i)-dong",
    "wof:placetype":"localadmin"
},
  "geometry": {"coordinates":[127.055834,37.895421],"type":"Point"}
}