{
  "type": "Feature",
  "properties": {
    "gn:admin1_code":"13.0",
    "gn:asciiname":"Haktunji",
    "gn:cc2":"KR",
    "gn:country_code":"KR",
    "gn:dem":168,
    "gn:feature_class":"P",
    "gn:feature_code":"PPL",
    "gn:name":"Haktunji",
    "gn:population":0,
    "gn:timezone":"Asia/Seoul",
    "iso:country":"KR",
    "name:und_x_variant":[
        "Hakch\u2019on",
        "Kakuson",
        "Haktunji"
    ],
    "wof:name":"Haktunji",
    "wof:placetype":"locality"
},
  "geometry": {"coordinates":[127.75,37.41667],"type":"Point"}
}