{
  "type": "Feature",
  "properties": {
    "gn:admin1_code":"14.0",
    "gn:asciiname":"Inso-gol",
    "gn:country_code":"KR",
    "gn:dem":59,
    "gn:feature_class":"P",
    "gn:feature_code":"PPL",
    "gn:name":"Ins\u014f-gol",
    "gn:population":0,
    "gn:timezone":"Asia/Seoul",
    "iso:country":"KR",
    "name:und_x_variant":[
        "Ins\u014f-kol",
        "Ins\u014f-dong",
        "\uc778\uc11c\uace8",
        "Ins\u014f-gol"
    ],
    "wof:name":"Inso-gol",
    "wof:placetype":"locality"
},
  "geometry": {"coordinates":[128.34790000000001,36.1644],"type":"Point"}
}