{
  "type": "Feature",
  "properties": {
    "gn:admin1_code":"5.0",
    "gn:asciiname":"Yeonbangchuk",
    "gn:country_code":"KR",
    "gn:dem":104,
    "gn:feature_class":"P",
    "gn:feature_code":"PPL",
    "gn:name":"Yeonbangchuk",
    "gn:population":0,
    "gn:timezone":"Asia/Seoul",
    "iso:country":"KR",
    "name:kor_x_preferred":[
        "\uc5f0\ubc29\ucd95"
    ],
    "wof:name":"Yeonbangchuk",
    "wof:placetype":"locality"
},
  "geometry": {"coordinates":[127.5248,36.99735],"type":"Point"}
}