{
  "type": "Feature",
  "properties": {
    "gn:admin1_code":"6.0",
    "gn:asciiname":"Sang-ch'on",
    "gn:country_code":"KR",
    "gn:dem":624,
    "gn:feature_class":"P",
    "gn:feature_code":"PPL",
    "gn:name":"Sang-ch\u2019on",
    "gn:population":0,
    "gn:timezone":"Asia/Seoul",
    "iso:country":"KR",
    "name:kor_x_preferred":[
        "\uc0c1\ucd0c"
    ],
    "name:kor_x_variant":[
        "Sang-ch\u2019on"
    ],
    "wof:name":"Sang-ch'on",
    "wof:placetype":"locality"
},
  "geometry": {"coordinates":[128.87819999999999,37.2868],"type":"Point"}
}