{
  "type": "Feature",
  "properties": {
    "gn:admin1_code":"6.0",
    "gn:asciiname":"Mulgol",
    "gn:country_code":"KR",
    "gn:dem":448,
    "gn:feature_class":"P",
    "gn:feature_code":"PPL",
    "gn:name":"Mulgol",
    "gn:population":0,
    "gn:timezone":"Asia/Seoul",
    "iso:country":"KR",
    "name:kor_x_preferred":[
        "\ubb3c\uace8"
    ],
    "wof:name":"Mulgol",
    "wof:placetype":"locality"
},
  "geometry": {"coordinates":[127.94508,37.84658],"type":"Point"}
}