{
  "type": "Feature",
  "properties": {
    "gn:admin1_code":"14.0",
    "gn:asciiname":"Wonhung",
    "gn:country_code":"KR",
    "gn:dem":47,
    "gn:feature_class":"P",
    "gn:feature_code":"PPL",
    "gn:name":"W\u014fnh\u016dng",
    "gn:population":0,
    "gn:timezone":"Asia/Seoul",
    "iso:country":"KR",
    "name:und_x_variant":[
        "\uc6d0\ud765",
        "W\u014fnh\u016dng"
    ],
    "wof:name":"Wonhung",
    "wof:placetype":"locality"
},
  "geometry": {"coordinates":[128.29769999999999,36.3193],"type":"Point"}
}