{
  "type": "Feature",
  "properties": {
    "gn:admin1_code":"17.0",
    "gn:asciiname":"Tosal-li",
    "gn:country_code":"KR",
    "gn:dem":22,
    "gn:feature_class":"P",
    "gn:feature_code":"PPL",
    "gn:name":"Tosal-li",
    "gn:population":0,
    "gn:timezone":"Asia/Seoul",
    "iso:country":"KR",
    "name:und_x_variant":[
        "\ub3c4\uc0b0\ub9ac",
        "Tosan-ni",
        "Tosal-li"
    ],
    "wof:name":"Tosal-li",
    "wof:placetype":"locality"
},
  "geometry": {"coordinates":[126.5552,36.8679],"type":"Point"}
}