{
  "type": "Feature",
  "properties": {
    "iso:country":"KR",
    "qs:name":"\uc8fd\uc655\uba74",
    "qs:name_adm0":"\ud55c\uad6d",
    "qs:name_adm1":"\uac15\uc6d0\ub3c4",
    "qs:photos":104,
    "qs:photos_1k":21,
    "qs:photos_9k":1,
    "qs:photos_9r":3,
    "qs:photos_all":104,
    "qs:photos_sr":3,
    "qs:placetype":"LocalAdmin",
    "qs:pop_sr":"0",
    "wof:name":"\uc8fd\uc655\uba74",
    "wof:placetype":"localadmin"
},
  "geometry": {"coordinates":[128.52828,38.331099],"type":"Point"}
}