{
  "type": "Feature",
  "properties": {
    "iso:country":"KR",
    "qs:name":"\uc1a1\uc0b01\ub3d9",
    "qs:name_adm0":"\ud55c\uad6d",
    "qs:name_adm1":"\uacbd\uae30\ub3c4",
    "qs:photos":184,
    "qs:photos_1k":37,
    "qs:photos_9k":1,
    "qs:photos_9r":4,
    "qs:photos_all":184,
    "qs:photos_sr":4,
    "qs:placetype":"LocalAdmin",
    "qs:pop_sr":"0",
    "wof:name":"\uc1a1\uc0b01\ub3d9",
    "wof:placetype":"localadmin"
},
  "geometry": {"coordinates":[127.110078,37.713158],"type":"Point"}
}