{
  "type": "Feature",
  "properties": {
    "gn:admin1_code":"6.0",
    "gn:asciiname":"Moun-dong",
    "gn:country_code":"KR",
    "gn:dem":565,
    "gn:feature_class":"P",
    "gn:feature_code":"PPL",
    "gn:name":"Moun-dong",
    "gn:population":0,
    "gn:timezone":"Asia/Seoul",
    "iso:country":"KR",
    "name:kor_x_preferred":[
        "\ubaa8\uc6b4\ub3d9"
    ],
    "name:und_x_variant":[
        "Moun"
    ],
    "wof:name":"Moun-dong",
    "wof:placetype":"locality"
},
  "geometry": {"coordinates":[128.61778000000001,37.13861],"type":"Point"}
}