{
  "type": "Feature",
  "properties": {
    "gn:admin1_code":"3.0",
    "gn:asciiname":"Poksil-li",
    "gn:country_code":"KR",
    "gn:dem":117,
    "gn:feature_class":"P",
    "gn:feature_code":"PPL",
    "gn:name":"Poksil-li",
    "gn:population":0,
    "gn:timezone":"Asia/Seoul",
    "iso:country":"KR",
    "name:kor_x_preferred":[
        "\ubcf5\uc2e4"
    ],
    "name:und_x_variant":[
        "Boksil",
        "Poksil-li"
    ],
    "wof:name":"Poksil-li",
    "wof:placetype":"locality"
},
  "geometry": {"coordinates":[127.1375,35.395],"type":"Point"}
}