{
  "type": "Feature",
  "properties": {
    "gn:admin1_code":"6.0",
    "gn:asciiname":"Araenmunjeong",
    "gn:country_code":"KR",
    "gn:dem":83,
    "gn:feature_class":"P",
    "gn:feature_code":"PPL",
    "gn:name":"Araenmunjeong",
    "gn:population":0,
    "gn:timezone":"Asia/Seoul",
    "iso:country":"KR",
    "name:und_x_variant":[
        "Hamuny\u014fn-ni",
        "Hamunj\u014fng-ni",
        "\uc544\ub7ab\ubb38\uc815",
        "Sinbuk",
        "Araenmunj\u014fng",
        "Araenmunjeong"
    ],
    "wof:name":"Araenmunjeong",
    "wof:placetype":"locality"
},
  "geometry": {"coordinates":[127.7565,37.9328],"type":"Point"}
}