{
  "type": "Feature",
  "properties": {
    "gn:admin1_code":"20.0",
    "gn:asciiname":"Witdeokjeong",
    "gn:country_code":"KR",
    "gn:dem":62,
    "gn:feature_class":"P",
    "gn:feature_code":"PPL",
    "gn:name":"Witdeokjeong",
    "gn:population":0,
    "gn:timezone":"Asia/Seoul",
    "iso:country":"KR",
    "name:kor_x_preferred":[
        "\uc717\ub355\uc815"
    ],
    "wof:name":"Witdeokjeong",
    "wof:placetype":"locality"
},
  "geometry": {"coordinates":[128.79498000000001,35.18059],"type":"Point"}
}