{
  "type": "Feature",
  "properties": {
    "gn:admin1_code":"14.0",
    "gn:asciiname":"Gwandong",
    "gn:country_code":"KR",
    "gn:dem":53,
    "gn:feature_class":"P",
    "gn:feature_code":"PPL",
    "gn:name":"Gwandong",
    "gn:population":0,
    "gn:timezone":"Asia/Seoul",
    "iso:country":"KR",
    "name:kor_x_preferred":[
        "\uad00\ub3d9"
    ],
    "wof:name":"Gwandong",
    "wof:placetype":"locality"
},
  "geometry": {"coordinates":[129.33895000000001,36.20224],"type":"Point"}
}