{
  "type": "Feature",
  "properties": {
    "gn:admin1_code":"3.0",
    "gn:asciiname":"Sonch'on",
    "gn:country_code":"KR",
    "gn:dem":155,
    "gn:feature_class":"P",
    "gn:feature_code":"PPL",
    "gn:name":"S\u014fnch\u2019\u014fn",
    "gn:population":0,
    "gn:timezone":"Asia/Seoul",
    "iso:country":"KR",
    "name:und_x_variant":[
        "\uc120\ucc9c",
        "S\u014fnch\u2019\u014fn"
    ],
    "wof:name":"Sonch'on",
    "wof:placetype":"locality"
},
  "geometry": {"coordinates":[127.36444,35.58564000000001],"type":"Point"}
}