{
  "type": "Feature",
  "properties": {
    "gn:admin1_code":"14.0",
    "gn:asciiname":"Buldanggol",
    "gn:country_code":"KR",
    "gn:dem":127,
    "gn:feature_class":"P",
    "gn:feature_code":"PPL",
    "gn:name":"Buldanggol",
    "gn:population":0,
    "gn:timezone":"Asia/Seoul",
    "iso:country":"KR",
    "name:kor_x_preferred":[
        "\ubd88\ub2f9\uace8"
    ],
    "wof:name":"Buldanggol",
    "wof:placetype":"locality"
},
  "geometry": {"coordinates":[128.56421,36.73328],"type":"Point"}
}