{
  "type": "Feature",
  "properties": {
    "gn:admin1_code":"1.0",
    "gn:admin2_code":"Pukcheju-gun",
    "gn:asciiname":"Joseongdong",
    "gn:country_code":"KR",
    "gn:dem":144,
    "gn:feature_class":"P",
    "gn:feature_code":"PPL",
    "gn:name":"Joseongdong",
    "gn:population":0,
    "gn:timezone":"Asia/Seoul",
    "iso:country":"KR",
    "name:kor_x_preferred":[
        "\uc870\uc131\ub3d9"
    ],
    "name:und_x_variant":[
        "Chos\u014fng-dong"
    ],
    "wof:name":"Joseongdong",
    "wof:placetype":"locality"
},
  "geometry": {"coordinates":[126.27666000000001,33.3522],"type":"Point"}
}