{
  "type": "Feature",
  "properties": {
    "gn:admin1_code":"11.0",
    "gn:asciiname":"Ch'angsam-dong",
    "gn:country_code":"KR",
    "gn:dem":37,
    "gn:feature_class":"P",
    "gn:feature_code":"PPL",
    "gn:name":"Ch\u2019angsam-dong",
    "gn:population":0,
    "gn:timezone":"Asia/Seoul",
    "iso:country":"KR",
    "name:und_x_variant":[
        "\ucc3d3\ub3d9",
        "Ch\u2019angsam-dong"
    ],
    "wof:name":"Ch'angsam-dong",
    "wof:placetype":"locality"
},
  "geometry": {"coordinates":[127.04136,37.63771],"type":"Point"}
}