{
  "type": "Feature",
  "properties": {
    "gn:admin1_code":"6.0",
    "gn:asciiname":"Chaesal-li",
    "gn:country_code":"KR",
    "gn:dem":597,
    "gn:feature_class":"P",
    "gn:feature_code":"PPLL",
    "gn:name":"Chaesal-li",
    "gn:population":0,
    "gn:timezone":"Asia/Seoul",
    "iso:country":"KR",
    "name:kor_x_preferred":[
        "\uc7ac\uc0b0\ub9ac"
    ],
    "wof:name":"Chaesal-li",
    "wof:placetype":"locality"
},
  "geometry": {"coordinates":[128.42643000000001,37.56154],"type":"Point"}
}