{
  "type": "Feature",
  "properties": {
    "gn:admin1_code":"10.0",
    "gn:asciiname":"Seoksan",
    "gn:country_code":"KR",
    "gn:dem":35,
    "gn:feature_class":"P",
    "gn:feature_code":"PPL",
    "gn:name":"Seoksan",
    "gn:population":0,
    "gn:timezone":"Asia/Seoul",
    "iso:country":"KR",
    "name:kor_x_preferred":[
        "\uc11d\uc0b0"
    ],
    "name:und_x_variant":[
        "S\u014fksan"
    ],
    "wof:name":"Seoksan",
    "wof:placetype":"locality"
},
  "geometry": {"coordinates":[129.2122,35.20733],"type":"Point"}
}