{
  "type": "Feature",
  "properties": {
    "gn:admin1_code":"16.0",
    "gn:asciiname":"Dongchon",
    "gn:country_code":"KR",
    "gn:dem":29,
    "gn:feature_class":"P",
    "gn:feature_code":"PPL",
    "gn:name":"Dongchon",
    "gn:population":0,
    "gn:timezone":"Asia/Seoul",
    "iso:country":"KR",
    "name:kor_x_preferred":[
        "Tongch\u2019on"
    ],
    "name:kor_x_variant":[
        "\ub3d9\ucd0c"
    ],
    "wof:name":"Dongchon",
    "wof:placetype":"locality"
},
  "geometry": {"coordinates":[126.81274000000001,34.40284],"type":"Point"}
}