{
  "type": "Feature",
  "properties": {
    "gn:admin1_code":"21.0",
    "gn:asciiname":"Hwajeong",
    "gn:country_code":"KR",
    "gn:dem":17,
    "gn:feature_class":"P",
    "gn:feature_code":"PPL",
    "gn:name":"Hwajeong",
    "gn:population":0,
    "gn:timezone":"Asia/Seoul",
    "iso:country":"KR",
    "name:kor_x_preferred":[
        "\ud654\uc815"
    ],
    "wof:name":"Hwajeong",
    "wof:placetype":"locality"
},
  "geometry": {"coordinates":[129.28093000000001,35.48824000000001],"type":"Point"}
}