{
  "type": "Feature",
  "properties": {
    "gn:admin1_code":"6.0",
    "gn:asciiname":"Oun-dong",
    "gn:country_code":"KR",
    "gn:dem":824,
    "gn:feature_class":"P",
    "gn:feature_code":"PPL",
    "gn:name":"\u014e\u016dn-dong",
    "gn:population":0,
    "gn:timezone":"Asia/Seoul",
    "iso:country":"KR",
    "name:kor_x_preferred":[
        "\uc5b4\uc740\ub3d9"
    ],
    "name:kor_x_variant":[
        "\u014e\u016dn-dong"
    ],
    "wof:name":"Oun-dong",
    "wof:placetype":"locality"
},
  "geometry": {"coordinates":[128.5658,37.4403],"type":"Point"}
}