{
  "type": "Feature",
  "properties": {
    "gn:admin1_code":"13.0",
    "gn:asciiname":"Teot-gol",
    "gn:country_code":"KR",
    "gn:dem":90,
    "gn:feature_class":"P",
    "gn:feature_code":"PPL",
    "gn:name":"Teot-gol",
    "gn:population":0,
    "gn:timezone":"Asia/Seoul",
    "iso:country":"KR",
    "name:und_x_variant":[
        "T\u2019\u014f-gol",
        "\ud143\uace8",
        "Teot-gol",
        "T\u2019\u014fk-kol"
    ],
    "wof:name":"Teot-gol",
    "wof:placetype":"locality"
},
  "geometry": {"coordinates":[127.21528000000001,37.40806],"type":"Point"}
}