{
  "type": "Feature",
  "properties": {
    "gn:admin1_code":"0.0",
    "gn:asciiname":"Kuryong-dong",
    "gn:cc2":"KR",
    "gn:country_code":"KR",
    "gn:dem":1,
    "gn:feature_class":"P",
    "gn:feature_code":"PPL",
    "gn:name":"Kuryong-dong",
    "gn:population":0,
    "gn:timezone":"Asia/Seoul",
    "iso:country":"KR",
    "name:und_x_variant":[
        "Kuyong-dong",
        "Kuryong-dong"
    ],
    "wof:name":"Kuryong-dong",
    "wof:placetype":"locality"
},
  "geometry": {"coordinates":[127.96666999999999,34.85],"type":"Point"}
}