{
  "type": "Feature",
  "properties": {
    "gn:admin1_code":"16.0",
    "gn:asciiname":"Sinji",
    "gn:country_code":"KR",
    "gn:dem":8,
    "gn:feature_class":"P",
    "gn:feature_code":"PPL",
    "gn:name":"Sinji",
    "gn:population":0,
    "gn:timezone":"Asia/Seoul",
    "iso:country":"KR",
    "name:kor_x_preferred":[
        "\uc798\ud3ec"
    ],
    "wof:name":"Sinji",
    "wof:placetype":"locality"
},
  "geometry": {"coordinates":[126.56471999999999,34.18861],"type":"Point"}
}