{
  "type": "Feature",
  "properties": {
    "gn:admin1_code":"17.0",
    "gn:asciiname":"Paekkyo-ri",
    "gn:country_code":"KR",
    "gn:dem":114,
    "gn:feature_class":"P",
    "gn:feature_code":"PPL",
    "gn:name":"Paekkyo-ri",
    "gn:population":0,
    "gn:timezone":"Asia/Seoul",
    "iso:country":"KR",
    "name:und_x_variant":[
        "H\u016dindari"
    ],
    "wof:name":"Paekkyo-ri",
    "wof:placetype":"locality"
},
  "geometry": {"coordinates":[126.93333,36.55],"type":"Point"}
}