{
  "type": "Feature",
  "properties": {
    "gn:admin1_code":"5.0",
    "gn:asciiname":"Araettogasil",
    "gn:country_code":"KR",
    "gn:dem":225,
    "gn:feature_class":"P",
    "gn:feature_code":"PPL",
    "gn:name":"Araettogasil",
    "gn:population":0,
    "gn:timezone":"Asia/Seoul",
    "iso:country":"KR",
    "name:und_x_variant":[
        "\uc544\ub7ab\ub3c4\uac00\uc2e4",
        "Araettogasil"
    ],
    "wof:name":"Araettogasil",
    "wof:placetype":"locality"
},
  "geometry": {"coordinates":[127.61969999999999,36.1742],"type":"Point"}
}