{
  "type": "Feature",
  "properties": {
    "gn:admin1_code":"13.0",
    "gn:asciiname":"Baeul",
    "gn:country_code":"KR",
    "gn:dem":70,
    "gn:feature_class":"P",
    "gn:feature_code":"PPL",
    "gn:name":"Baeul",
    "gn:population":0,
    "gn:timezone":"Asia/Seoul",
    "iso:country":"KR",
    "name:und_x_variant":[
        "\ubc30\uc6b8",
        "Paeul",
        "Baeul"
    ],
    "wof:name":"Baeul",
    "wof:placetype":"locality"
},
  "geometry": {"coordinates":[126.93994000000001,37.69798],"type":"Point"}
}