{
  "type": "Feature",
  "properties": {
    "gn:admin1_code":"5.0",
    "gn:asciiname":"Kwangch'ol-li",
    "gn:country_code":"KR",
    "gn:dem":243,
    "gn:feature_class":"P",
    "gn:feature_code":"PPL",
    "gn:name":"Kwangch\u2019ol-li",
    "gn:population":0,
    "gn:timezone":"Asia/Seoul",
    "iso:country":"KR",
    "name:und_x_variant":[
        "\uad11\ucd0c\ub9ac",
        "Kwangch\u2019ol-li"
    ],
    "wof:name":"Kwangch'ol-li",
    "wof:placetype":"locality"
},
  "geometry": {"coordinates":[127.6841,36.4426],"type":"Point"}
}