{
  "type": "Feature",
  "properties": {
    "gn:admin1_code":"6.0",
    "gn:asciiname":"Samsani-ri",
    "gn:country_code":"KR",
    "gn:dem":198,
    "gn:feature_class":"P",
    "gn:feature_code":"PPLL",
    "gn:name":"Samsani-ri",
    "gn:population":0,
    "gn:timezone":"Asia/Seoul",
    "iso:country":"KR",
    "name:kor_x_preferred":[
        "\uc0bc\uc0b02\ub9ac"
    ],
    "wof:name":"Samsani-ri",
    "wof:placetype":"locality"
},
  "geometry": {"coordinates":[128.71215000000001,37.82238],"type":"Point"}
}