{
  "type": "Feature",
  "properties": {
    "gn:admin1_code":"15.0",
    "gn:asciiname":"Dansan",
    "gn:country_code":"KR",
    "gn:dem":43,
    "gn:feature_class":"P",
    "gn:feature_code":"PPL",
    "gn:name":"Dansan",
    "gn:population":0,
    "gn:timezone":"Asia/Seoul",
    "iso:country":"KR",
    "name:kor_x_preferred":[
        "\ub2e8\uc0b0"
    ],
    "name:und_x_variant":[
        "Tansan"
    ],
    "wof:name":"Dansan",
    "wof:placetype":"locality"
},
  "geometry": {"coordinates":[128.64538999999999,35.92269],"type":"Point"}
}