{
  "type": "Feature",
  "properties": {
    "gn:admin1_code":"13.0",
    "gn:asciiname":"Jeomchon",
    "gn:country_code":"KR",
    "gn:dem":16,
    "gn:feature_class":"P",
    "gn:feature_code":"PPL",
    "gn:name":"Jeomchon",
    "gn:population":0,
    "gn:timezone":"Asia/Seoul",
    "iso:country":"KR",
    "name:und_x_variant":[
        "\uc810\ucd0c",
        "Ch\u014fm-ch\u2019on",
        "Jeomchon",
        "Cheomchon"
    ],
    "wof:name":"Jeomchon",
    "wof:placetype":"locality"
},
  "geometry": {"coordinates":[126.93186,36.96315],"type":"Point"}
}