{
  "type": "Feature",
  "properties": {
    "gn:admin1_code":"14.0",
    "gn:asciiname":"Yuchon",
    "gn:country_code":"KR",
    "gn:dem":42,
    "gn:feature_class":"P",
    "gn:feature_code":"PPL",
    "gn:name":"Yuchon",
    "gn:population":0,
    "gn:timezone":"Asia/Seoul",
    "iso:country":"KR",
    "name:und_x_variant":[
        "\uc720\ucd0c",
        "Yu-ch\u2019on",
        "Yuchon"
    ],
    "wof:name":"Yuchon",
    "wof:placetype":"locality"
},
  "geometry": {"coordinates":[128.35068000000001,35.88458],"type":"Point"}
}