{
  "type": "Feature",
  "properties": {
    "gn:admin1_code":"20.0",
    "gn:asciiname":"Chongp'yong-ni",
    "gn:country_code":"KR",
    "gn:dem":136,
    "gn:feature_class":"P",
    "gn:feature_code":"PPL",
    "gn:name":"Ch\u014fngp\u2019y\u014fng-ni",
    "gn:population":0,
    "gn:timezone":"Asia/Seoul",
    "iso:country":"KR",
    "name:eng_x_preferred":[
        "Chongp'yong"
    ],
    "name:eng_x_variant":[
        "Chongp'yong-ni"
    ],
    "wof:name":"Chongp'yong",
    "wof:placetype":"locality"
},
  "geometry": {"coordinates":[128.05944,35.28639],"type":"Point"}
}