{
  "type": "Feature",
  "properties": {
    "gn:admin1_code":"6.0",
    "gn:asciiname":"Yangji-mal",
    "gn:country_code":"KR",
    "gn:dem":190,
    "gn:feature_class":"P",
    "gn:feature_code":"PPL",
    "gn:name":"Yangji-mal",
    "gn:population":0,
    "gn:timezone":"Asia/Seoul",
    "iso:country":"KR",
    "name:kor_x_preferred":[
        "\uc591\uc9c0\ub9d0"
    ],
    "name:und_x_variant":[
        "Yangjima\u016dl",
        "Yangjich\u2019on",
        "Yangji-mal"
    ],
    "wof:name":"Yangji-mal",
    "wof:placetype":"locality"
},
  "geometry": {"coordinates":[128.0625,37.53807000000001],"type":"Point"}
}