{
  "type": "Feature",
  "properties": {
    "gn:admin1_code":"16.0",
    "gn:asciiname":"Hak-tong",
    "gn:country_code":"KR",
    "gn:dem":36,
    "gn:feature_class":"P",
    "gn:feature_code":"PPL",
    "gn:name":"Hak-tong",
    "gn:population":0,
    "gn:timezone":"Asia/Seoul",
    "iso:country":"KR",
    "name:eng_x_preferred":[
        "Hak"
    ],
    "name:eng_x_variant":[
        "Hak-tong"
    ],
    "name:und_x_variant":[
        "\ud559\ub3d9",
        "Hak-tong"
    ],
    "wof:name":"Hak",
    "wof:placetype":"locality"
},
  "geometry": {"coordinates":[126.57971999999999,34.58472],"type":"Point"}
}