{
  "type": "Feature",
  "properties": {
    "iso:country":"KR",
    "qs:name":"\uc548\uc131\uba74",
    "qs:name_adm0":"\ud55c\uad6d",
    "qs:name_adm1":"\uc804\ub77c\ubd81\ub3c4",
    "qs:photos":99,
    "qs:photos_1k":20,
    "qs:photos_9k":1,
    "qs:photos_9r":3,
    "qs:photos_all":99,
    "qs:photos_sr":3,
    "qs:placetype":"LocalAdmin",
    "qs:pop_sr":"0",
    "wof:name":"\uc548\uc131\uba74",
    "wof:placetype":"localadmin"
},
  "geometry": {"coordinates":[127.749702,35.859474],"type":"Point"}
}