{
  "type": "Feature",
  "properties": {
    "gn:admin1_code":"6.0",
    "gn:asciiname":"Ukkolmi",
    "gn:country_code":"KR",
    "gn:dem":576,
    "gn:feature_class":"P",
    "gn:feature_code":"PPL",
    "gn:name":"Ukkolmi",
    "gn:population":0,
    "gn:timezone":"Asia/Seoul",
    "iso:country":"KR",
    "name:kor_x_preferred":[
        "\uc6c3\uace8\ubbf8"
    ],
    "wof:name":"Ukkolmi",
    "wof:placetype":"locality"
},
  "geometry": {"coordinates":[128.17679999999999,37.3603],"type":"Point"}
}