{
  "type": "Feature",
  "properties": {
    "gn:admin1_code":"12.0",
    "gn:asciiname":"Banwolchon",
    "gn:country_code":"KR",
    "gn:dem":23,
    "gn:feature_class":"P",
    "gn:feature_code":"PPL",
    "gn:name":"Banwolchon",
    "gn:population":0,
    "gn:timezone":"Asia/Seoul",
    "iso:country":"KR",
    "name:kor_x_preferred":[
        "\ubc18\uc6d4\ucd0c"
    ],
    "name:kor_x_variant":[
        "Panw\u014flch\u2019on"
    ],
    "wof:name":"Banwolchon",
    "wof:placetype":"locality"
},
  "geometry": {"coordinates":[126.62658999999999,37.5991],"type":"Point"}
}