{
  "type": "Feature",
  "properties": {
    "gn:admin1_code":"13.0",
    "gn:asciiname":"Seokgol",
    "gn:country_code":"KR",
    "gn:dem":161,
    "gn:feature_class":"P",
    "gn:feature_code":"PPL",
    "gn:name":"Seokgol",
    "gn:population":0,
    "gn:timezone":"Asia/Seoul",
    "iso:country":"KR",
    "name:kor_x_preferred":[
        "\uc11d\uace8"
    ],
    "name:und_x_variant":[
        "\uc11d\uace1",
        "S\u014fkkok",
        "Seokgol"
    ],
    "wof:name":"Seokgol",
    "wof:placetype":"locality"
},
  "geometry": {"coordinates":[126.94244,37.77864],"type":"Point"}
}