{
  "type": "Feature",
  "properties": {
    "gn:admin1_code":"14.0",
    "gn:asciiname":"Witdongnae",
    "gn:country_code":"KR",
    "gn:dem":37,
    "gn:feature_class":"P",
    "gn:feature_code":"PPL",
    "gn:name":"Witdongnae",
    "gn:population":0,
    "gn:timezone":"Asia/Seoul",
    "iso:country":"KR",
    "name:kor_x_preferred":[
        "\uc717\ub3d9\ub0b4"
    ],
    "wof:name":"Witdongnae",
    "wof:placetype":"locality"
},
  "geometry": {"coordinates":[129.34121999999999,35.97157],"type":"Point"}
}