{
  "type": "Feature",
  "properties": {
    "gn:admin1_code":"14.0",
    "gn:asciiname":"Naejeong",
    "gn:country_code":"KR",
    "gn:dem":78,
    "gn:feature_class":"P",
    "gn:feature_code":"PPL",
    "gn:name":"Naejeong",
    "gn:population":0,
    "gn:timezone":"Asia/Seoul",
    "iso:country":"KR",
    "name:kor_x_preferred":[
        "\ub0b4\uc815"
    ],
    "wof:name":"Naejeong",
    "wof:placetype":"locality"
},
  "geometry": {"coordinates":[129.27322000000001,36.13589],"type":"Point"}
}