{
  "type": "Feature",
  "properties": {
    "gn:admin1_code":"6.0",
    "gn:asciiname":"Koptolchae",
    "gn:country_code":"KR",
    "gn:dem":380,
    "gn:feature_class":"P",
    "gn:feature_code":"PPL",
    "gn:name":"Koptolchae",
    "gn:population":0,
    "gn:timezone":"Asia/Seoul",
    "iso:country":"KR",
    "name:kor_x_preferred":[
        "\uacf1\ub3cc\uc7ac"
    ],
    "wof:name":"Koptolchae",
    "wof:placetype":"locality"
},
  "geometry": {"coordinates":[128.11409,37.62869],"type":"Point"}
}