{
  "type": "Feature",
  "properties": {
    "gn:admin1_code":"3.0",
    "gn:asciiname":"Tangwol",
    "gn:country_code":"KR",
    "gn:dem":63,
    "gn:feature_class":"P",
    "gn:feature_code":"PPL",
    "gn:name":"Tangw\u014fl",
    "gn:population":0,
    "gn:timezone":"Asia/Seoul",
    "iso:country":"KR",
    "name:und_x_variant":[
        "\ub2f9\uc6d4",
        "Tangw\u014fl"
    ],
    "wof:name":"Tangwol",
    "wof:placetype":"locality"
},
  "geometry": {"coordinates":[127.03406,35.77627000000001],"type":"Point"}
}