{
  "type": "Feature",
  "properties": {
    "gn:admin1_code":"16.0",
    "gn:asciiname":"Solch'i",
    "gn:country_code":"KR",
    "gn:dem":93,
    "gn:feature_class":"P",
    "gn:feature_code":"PPL",
    "gn:name":"Solch\u2019i",
    "gn:population":0,
    "gn:timezone":"Asia/Seoul",
    "iso:country":"KR",
    "name:kor_x_preferred":[
        "\uc194\uce58"
    ],
    "name:kor_x_variant":[
        "Solch\u2019i"
    ],
    "name:und_x_variant":[
        "Songch\u2019i"
    ],
    "wof:name":"Solch'i",
    "wof:placetype":"locality"
},
  "geometry": {"coordinates":[126.92749999999999,34.58167],"type":"Point"}
}