{
  "type": "Feature",
  "properties": {
    "iso:country":"KR",
    "name:eng_x_preferred":[
        "Gongdo-eup"
    ],
    "name:kor_x_preferred":[
        "\uacf5\ub3c4\uc74d"
    ],
    "qs:name":"\uacf5\ub3c4\uc74d",
    "qs:name_adm0":"\ud55c\uad6d",
    "qs:name_adm1":"\uacbd\uae30\ub3c4",
    "qs:photos":6,
    "qs:photos_1k":1,
    "qs:photos_9k":1,
    "qs:photos_9r":1,
    "qs:photos_all":6,
    "qs:photos_sr":1,
    "qs:placetype":"LocalAdmin",
    "qs:pop_sr":"0",
    "wof:name":"Gongdo-eup",
    "wof:placetype":"localadmin"
},
  "geometry": {"coordinates":[127.18680999999999,36.9857],"type":"Point"}
}