{
  "type": "Feature",
  "properties": {
    "gn:admin1_code":"14.0",
    "gn:asciiname":"Yurhyon",
    "gn:country_code":"KR",
    "gn:dem":293,
    "gn:feature_class":"P",
    "gn:feature_code":"PPL",
    "gn:name":"Yurhy\u014fn",
    "gn:population":0,
    "gn:timezone":"Asia/Seoul",
    "iso:country":"KR",
    "name:und_x_variant":[
        "\uc728\ud604",
        "Yurhy\u014fn"
    ],
    "wof:name":"Yurhyon",
    "wof:placetype":"locality"
},
  "geometry": {"coordinates":[127.93680000000001,36.41349],"type":"Point"}
}