{
  "type": "Feature",
  "properties": {
    "gn:admin1_code":"14.0",
    "gn:asciiname":"Gubangdong",
    "gn:country_code":"KR",
    "gn:dem":146,
    "gn:feature_class":"P",
    "gn:feature_code":"PPL",
    "gn:name":"Gubangdong",
    "gn:population":0,
    "gn:timezone":"Asia/Seoul",
    "iso:country":"KR",
    "name:kor_x_preferred":[
        "\uad6c\ubc29\ub3d9"
    ],
    "name:und_x_variant":[
        "Kubang-dong"
    ],
    "wof:name":"Gubangdong",
    "wof:placetype":"locality"
},
  "geometry": {"coordinates":[128.65998000000002,36.10374],"type":"Point"}
}