{
  "type": "Feature",
  "properties": {
    "gn:admin1_code":"6.0",
    "gn:asciiname":"Taejigok",
    "gn:country_code":"KR",
    "gn:dem":173,
    "gn:feature_class":"P",
    "gn:feature_code":"PPL",
    "gn:name":"Taejigok",
    "gn:population":0,
    "gn:timezone":"Asia/Seoul",
    "iso:country":"KR",
    "name:kor_x_preferred":[
        "\ub300\uc9c0\uace1"
    ],
    "wof:name":"Taejigok",
    "wof:placetype":"locality"
},
  "geometry": {"coordinates":[128.06530000000001,37.4945],"type":"Point"}
}