{
  "type": "Feature",
  "properties": {
    "gn:admin1_code":"14.0",
    "gn:asciiname":"Talbat",
    "gn:country_code":"KR",
    "gn:dem":440,
    "gn:feature_class":"P",
    "gn:feature_code":"PPL",
    "gn:name":"Talbat",
    "gn:population":0,
    "gn:timezone":"Asia/Seoul",
    "iso:country":"KR",
    "name:und_x_variant":[
        "\ub2ec\ubc2d",
        "Talbat"
    ],
    "wof:name":"Talbat",
    "wof:placetype":"locality"
},
  "geometry": {"coordinates":[129.29480000000001,36.9833],"type":"Point"}
}