{
  "type": "Feature",
  "properties": {
    "gn:admin1_code":"16.0",
    "gn:asciiname":"Koemong-ni",
    "gn:cc2":"KR",
    "gn:country_code":"KR",
    "gn:dem":79,
    "gn:feature_class":"P",
    "gn:feature_code":"PPL",
    "gn:name":"Koemong-ni",
    "gn:population":0,
    "gn:timezone":"Asia/Seoul",
    "iso:country":"KR",
    "name:und_x_variant":[
        "Hoemong-ni",
        "Koemok",
        "Kaiboku-ri",
        "Kaimokuri",
        "Koemong-ni"
    ],
    "wof:name":"Koemong-ni",
    "wof:placetype":"locality"
},
  "geometry": {"coordinates":[127.42944,35.10306],"type":"Point"}
}