{
  "type": "Feature",
  "properties": {
    "gn:admin1_code":"14.0",
    "gn:asciiname":"Winnara-gol",
    "gn:country_code":"KR",
    "gn:dem":24,
    "gn:feature_class":"P",
    "gn:feature_code":"PPL",
    "gn:name":"Winnara-gol",
    "gn:population":0,
    "gn:timezone":"Asia/Seoul",
    "iso:country":"KR",
    "name:und_x_variant":[
        "Insang",
        "Winnara-kol",
        "\uc717\ub098\ub77c\uace8",
        "Winnara-gol"
    ],
    "wof:name":"Winnara-gol",
    "wof:placetype":"locality"
},
  "geometry": {"coordinates":[129.3657,36.5528],"type":"Point"}
}