{
  "type": "Feature",
  "properties": {
    "gn:admin1_code":"13.0",
    "gn:asciiname":"Dawolli",
    "gn:country_code":"KR",
    "gn:dem":78,
    "gn:feature_class":"P",
    "gn:feature_code":"PPL",
    "gn:name":"Dawolli",
    "gn:population":0,
    "gn:timezone":"Asia/Seoul",
    "iso:country":"KR",
    "name:kor_x_preferred":[
        "\ub2e4\uc6d0\ub9ac"
    ],
    "wof:name":"Dawolli",
    "wof:placetype":"locality"
},
  "geometry": {"coordinates":[127.40561,37.75483],"type":"Point"}
}