{
  "type": "Feature",
  "properties": {
    "gn:admin1_code":"20.0",
    "gn:asciiname":"Kail-li",
    "gn:cc2":"KR",
    "gn:country_code":"KR",
    "gn:dem":106,
    "gn:feature_class":"P",
    "gn:feature_code":"PPL",
    "gn:name":"Kail-li",
    "gn:population":0,
    "gn:timezone":"Asia/Seoul",
    "iso:country":"KR",
    "name:und_x_variant":[
        "Kain-ni",
        "Kain",
        "Kail-li"
    ],
    "wof:name":"Kail-li",
    "wof:placetype":"locality"
},
  "geometry": {"coordinates":[128.04056,34.87528],"type":"Point"}
}