{
  "type": "Feature",
  "properties": {
    "gn:admin1_code":"14.0",
    "gn:asciiname":"Wisseolmot",
    "gn:country_code":"KR",
    "gn:dem":110,
    "gn:feature_class":"P",
    "gn:feature_code":"PPL",
    "gn:name":"Wisseolmot",
    "gn:population":0,
    "gn:timezone":"Asia/Seoul",
    "iso:country":"KR",
    "name:kor_x_preferred":[
        "\uc717\uc124\ubabb"
    ],
    "wof:name":"Wisseolmot",
    "wof:placetype":"locality"
},
  "geometry": {"coordinates":[128.53858,36.57909],"type":"Point"}
}