{
  "type": "Feature",
  "properties": {
    "gn:admin1_code":"13.0",
    "gn:asciiname":"Kawol-li",
    "gn:country_code":"KR",
    "gn:dem":31,
    "gn:feature_class":"P",
    "gn:feature_code":"PPL",
    "gn:name":"Kaw\u014fl-li",
    "gn:population":0,
    "gn:timezone":"Asia/Seoul",
    "iso:country":"KR",
    "name:kor_x_preferred":[
        "\uac00\uc6d4\ub9ac"
    ],
    "name:kor_x_variant":[
        "Kaw\u014fl-li"
    ],
    "wof:name":"Kawol-li",
    "wof:placetype":"locality"
},
  "geometry": {"coordinates":[126.9166,37.9785],"type":"Point"}
}