{
  "type": "Feature",
  "properties": {
    "gn:admin1_code":"17.0",
    "gn:asciiname":"Yongsong",
    "gn:country_code":"KR",
    "gn:dem":50,
    "gn:feature_class":"P",
    "gn:feature_code":"PPL",
    "gn:name":"Y\u014fngs\u014fng",
    "gn:population":0,
    "gn:timezone":"Asia/Seoul",
    "iso:country":"KR",
    "name:und_x_variant":[
        "\uc601\uc131",
        "Y\u014fngs\u014fng"
    ],
    "wof:name":"Yongsong",
    "wof:placetype":"locality"
},
  "geometry": {"coordinates":[127.1305,36.8427],"type":"Point"}
}