{
  "type": "Feature",
  "properties": {
    "gn:admin1_code":"6.0",
    "gn:asciiname":"Ch'adolbaegi",
    "gn:country_code":"KR",
    "gn:dem":517,
    "gn:feature_class":"P",
    "gn:feature_code":"PPL",
    "gn:name":"Ch\u2019adolbaegi",
    "gn:population":0,
    "gn:timezone":"Asia/Seoul",
    "iso:country":"KR",
    "name:kor_x_preferred":[
        "\ucc28\ub3cc\ubc31\uc774"
    ],
    "name:kor_x_variant":[
        "Ch\u2019adolbaegi"
    ],
    "wof:name":"Ch'adolbaegi",
    "wof:placetype":"locality"
},
  "geometry": {"coordinates":[128.2276,37.5058],"type":"Point"}
}