{
  "type": "Feature",
  "properties": {
    "gn:admin1_code":"17.0",
    "gn:asciiname":"Kosil",
    "gn:country_code":"KR",
    "gn:dem":31,
    "gn:feature_class":"P",
    "gn:feature_code":"PPL",
    "gn:name":"Kosil",
    "gn:population":0,
    "gn:timezone":"Asia/Seoul",
    "iso:country":"KR",
    "name:und_x_variant":[
        "Tonggosil",
        "Tonggogok",
        "Tonggogol",
        "\uace0\uc2e4",
        "Kosil"
    ],
    "wof:name":"Kosil",
    "wof:placetype":"locality"
},
  "geometry": {"coordinates":[126.6532,36.8953],"type":"Point"}
}