{
  "type": "Feature",
  "properties": {
    "gn:admin1_code":"3.0",
    "gn:asciiname":"Puam",
    "gn:country_code":"KR",
    "gn:dem":411,
    "gn:feature_class":"P",
    "gn:feature_code":"PPL",
    "gn:name":"Puam",
    "gn:population":0,
    "gn:timezone":"Asia/Seoul",
    "iso:country":"KR",
    "name:und_x_variant":[
        "\ubd80\uc554",
        "Puam"
    ],
    "wof:name":"Puam",
    "wof:placetype":"locality"
},
  "geometry": {"coordinates":[127.30947,35.79593],"type":"Point"}
}