{
  "type": "Feature",
  "properties": {
    "gn:admin1_code":"6.0",
    "gn:asciiname":"Jijil",
    "gn:country_code":"KR",
    "gn:dem":185,
    "gn:feature_class":"P",
    "gn:feature_code":"PPL",
    "gn:name":"Jijil",
    "gn:population":0,
    "gn:timezone":"Asia/Seoul",
    "iso:country":"KR",
    "name:kor_x_preferred":[
        "\uc9c0\uc9c8"
    ],
    "wof:name":"Jijil",
    "wof:placetype":"locality"
},
  "geometry": {"coordinates":[127.61277,37.7269],"type":"Point"}
}