{
  "type": "Feature",
  "properties": {
    "gn:admin1_code":"6.0",
    "gn:asciiname":"Sonuigok",
    "gn:country_code":"KR",
    "gn:dem":87,
    "gn:feature_class":"P",
    "gn:feature_code":"PPL",
    "gn:name":"S\u014fn\u016digok",
    "gn:population":0,
    "gn:timezone":"Asia/Seoul",
    "iso:country":"KR",
    "name:und_x_variant":[
        "\uc120\uc758\uace1",
        "S\u014fn\u016digok"
    ],
    "wof:name":"Sonuigok",
    "wof:placetype":"locality"
},
  "geometry": {"coordinates":[129.25299999999999,37.1419],"type":"Point"}
}