{
  "type": "Feature",
  "properties": {
    "gn:admin1_code":"6.0",
    "gn:asciiname":"Kusiul",
    "gn:country_code":"KR",
    "gn:dem":171,
    "gn:feature_class":"P",
    "gn:feature_code":"PPL",
    "gn:name":"Kusiul",
    "gn:population":0,
    "gn:timezone":"Asia/Seoul",
    "iso:country":"KR",
    "name:kor_x_preferred":[
        "\uad6c\uc2dc\uc6b8"
    ],
    "wof:name":"Kusiul",
    "wof:placetype":"locality"
},
  "geometry": {"coordinates":[127.82689999999999,37.67018],"type":"Point"}
}