{
  "type": "Feature",
  "properties": {
    "gn:admin1_code":"20.0",
    "gn:asciiname":"Sodong-ni",
    "gn:cc2":"KR",
    "gn:country_code":"KR",
    "gn:dem":36,
    "gn:feature_class":"P",
    "gn:feature_code":"PPL",
    "gn:name":"Sodong-ni",
    "gn:population":0,
    "gn:timezone":"Asia/Seoul",
    "iso:country":"KR",
    "name:und_x_variant":[
        "Sodong",
        "Sodong-ni"
    ],
    "wof:name":"Sodong-ni",
    "wof:placetype":"locality"
},
  "geometry": {"coordinates":[128.69221999999999,34.83778],"type":"Point"}
}