{
  "type": "Feature",
  "properties": {
    "gn:admin1_code":"3.0",
    "gn:asciiname":"Umji",
    "gn:country_code":"KR",
    "gn:dem":341,
    "gn:feature_class":"P",
    "gn:feature_code":"PPL",
    "gn:name":"\u016cmji",
    "gn:population":0,
    "gn:timezone":"Asia/Seoul",
    "iso:country":"KR",
    "name:und_x_variant":[
        "\uc74c\uc9c0",
        "\u016cmji"
    ],
    "wof:name":"Umji",
    "wof:placetype":"locality"
},
  "geometry": {"coordinates":[127.40527,35.71978],"type":"Point"}
}