{
  "type": "Feature",
  "properties": {
    "gn:admin1_code":"17.0",
    "gn:asciiname":"Chogum-ni",
    "gn:country_code":"KR",
    "gn:dem":8,
    "gn:feature_class":"P",
    "gn:feature_code":"PPL",
    "gn:name":"Chog\u016dm-ni",
    "gn:population":0,
    "gn:timezone":"Asia/Seoul",
    "iso:country":"KR",
    "name:und_x_variant":[
        "Su\u016dnt\u2019\u014f",
        "Sas\u014fng-ni",
        "Chog\u016dmjin-ni",
        "\uc870\uae08\ub9ac",
        "Chog\u016dm-ni"
    ],
    "wof:name":"Chogum-ni",
    "wof:placetype":"locality"
},
  "geometry": {"coordinates":[126.5009,36.9002],"type":"Point"}
}