{
  "type": "Feature",
  "properties": {
    "gn:admin1_code":"13.0",
    "gn:asciiname":"Sindam-ni",
    "gn:country_code":"KR",
    "gn:dem":91,
    "gn:feature_class":"P",
    "gn:feature_code":"PPL",
    "gn:name":"Sindam-ni",
    "gn:population":0,
    "gn:timezone":"Asia/Seoul",
    "iso:country":"KR",
    "name:eng_x_preferred":[
        "Sindam"
    ],
    "name:eng_x_variant":[
        "Sindam-ni"
    ],
    "wof:name":"Sindam",
    "wof:placetype":"locality"
},
  "geometry": {"coordinates":[127.10611,38.05444],"type":"Point"}
}