{
  "type": "Feature",
  "properties": {
    "gn:admin1_code":"15.0",
    "gn:asciiname":"Bansong",
    "gn:country_code":"KR",
    "gn:dem":106,
    "gn:feature_class":"P",
    "gn:feature_code":"PPL",
    "gn:name":"Bansong",
    "gn:population":0,
    "gn:timezone":"Asia/Seoul",
    "iso:country":"KR",
    "name:kor_x_preferred":[
        "\ubc18\uc1a1"
    ],
    "wof:name":"Bansong",
    "wof:placetype":"locality"
},
  "geometry": {"coordinates":[128.49797000000001,35.75577],"type":"Point"}
}