{
  "type": "Feature",
  "properties": {
    "gn:admin1_code":"20.0",
    "gn:asciiname":"Tanmok",
    "gn:cc2":"KR",
    "gn:country_code":"KR",
    "gn:dem":76,
    "gn:feature_class":"P",
    "gn:feature_code":"PPL",
    "gn:name":"Tanmok",
    "gn:population":0,
    "gn:timezone":"Asia/Seoul",
    "iso:country":"KR",
    "name:und_x_variant":[
        "Tanmong-ni",
        "Tanmok"
    ],
    "wof:name":"Tanmok",
    "wof:placetype":"locality"
},
  "geometry": {"coordinates":[128.14028000000002,35.25360999999999],"type":"Point"}
}