{
  "type": "Feature",
  "properties": {
    "gn:admin1_code":"20.0",
    "gn:asciiname":"Kuryong-dong",
    "gn:country_code":"KR",
    "gn:dem":444,
    "gn:feature_class":"P",
    "gn:feature_code":"PPL",
    "gn:name":"Kuryong-dong",
    "gn:population":0,
    "gn:timezone":"Asia/Seoul",
    "iso:country":"KR",
    "name:und_x_variant":[
        "\uad6c\ub8e1\ub3d9",
        "Kuryong-dong"
    ],
    "wof:name":"Kuryong-dong",
    "wof:placetype":"locality"
},
  "geometry": {"coordinates":[127.88097999999999,35.86448],"type":"Point"}
}