{
  "type": "Feature",
  "properties": {
    "gn:admin1_code":"17.0",
    "gn:asciiname":"K'un-mal",
    "gn:country_code":"KR",
    "gn:dem":20,
    "gn:feature_class":"P",
    "gn:feature_code":"PPL",
    "gn:name":"K\u2019\u016dn-mal",
    "gn:population":0,
    "gn:timezone":"Asia/Seoul",
    "iso:country":"KR",
    "name:und_x_variant":[
        "\ud070\ub9d0",
        "K\u2019\u016dn-mal"
    ],
    "wof:name":"K'un-mal",
    "wof:placetype":"locality"
},
  "geometry": {"coordinates":[126.41679999999999,36.6115],"type":"Point"}
}