{
  "type": "Feature",
  "properties": {
    "gn:admin1_code":"16.0",
    "gn:asciiname":"Sinyeonggol",
    "gn:country_code":"KR",
    "gn:dem":209,
    "gn:feature_class":"P",
    "gn:feature_code":"PPL",
    "gn:name":"Sinyeonggol",
    "gn:population":0,
    "gn:timezone":"Asia/Seoul",
    "iso:country":"KR",
    "name:kor_x_preferred":[
        "\uc2e0\uc601\uace8"
    ],
    "wof:name":"Sinyeonggol",
    "wof:placetype":"locality"
},
  "geometry": {"coordinates":[126.99590000000001,35.38845999999999],"type":"Point"}
}