{
  "type": "Feature",
  "properties": {
    "gn:admin1_code":"14.0",
    "gn:asciiname":"Saedeul",
    "gn:country_code":"KR",
    "gn:dem":143,
    "gn:feature_class":"P",
    "gn:feature_code":"PPL",
    "gn:name":"Saedeul",
    "gn:population":0,
    "gn:timezone":"Asia/Seoul",
    "iso:country":"KR",
    "name:kor_x_preferred":[
        "\uc0c8\ub4e4"
    ],
    "wof:name":"Saedeul",
    "wof:placetype":"locality"
},
  "geometry": {"coordinates":[129.24051,35.71775],"type":"Point"}
}