{
  "type": "Feature",
  "properties": {
    "gn:admin1_code":"14.0",
    "gn:asciiname":"Samga",
    "gn:country_code":"KR",
    "gn:dem":144,
    "gn:feature_class":"P",
    "gn:feature_code":"PPL",
    "gn:name":"Samga",
    "gn:population":0,
    "gn:timezone":"Asia/Seoul",
    "iso:country":"KR",
    "name:und_x_variant":[
        "Saejimmae",
        "Samga",
        "\uc0bc\uac00"
    ],
    "wof:name":"Samga",
    "wof:placetype":"locality"
},
  "geometry": {"coordinates":[128.25869,36.09658],"type":"Point"}
}