{
  "type": "Feature",
  "properties": {
    "gn:admin1_code":"13.0",
    "gn:asciiname":"Gwinongchon",
    "gn:country_code":"KR",
    "gn:dem":26,
    "gn:feature_class":"P",
    "gn:feature_code":"PPL",
    "gn:name":"Gwinongchon",
    "gn:population":0,
    "gn:timezone":"Asia/Seoul",
    "iso:country":"KR",
    "name:kor_x_preferred":[
        "\uadc0\ub18d\ucd0c"
    ],
    "name:und_x_variant":[
        "\uc218\uc6a9\uc18c",
        "Suyongso",
        "Gwinongchon"
    ],
    "wof:name":"Gwinongchon",
    "wof:placetype":"locality"
},
  "geometry": {"coordinates":[127.0791,36.9477],"type":"Point"}
}