{
  "type": "Feature",
  "properties": {
    "gn:admin1_code":"16.0",
    "gn:asciiname":"Wolgyo",
    "gn:country_code":"KR",
    "gn:dem":21,
    "gn:feature_class":"P",
    "gn:feature_code":"PPL",
    "gn:name":"W\u014flgyo",
    "gn:population":0,
    "gn:timezone":"Asia/Seoul",
    "iso:country":"KR",
    "name:kor_x_preferred":[
        "\uc6d4\uad50"
    ],
    "name:kor_x_variant":[
        "W\u014flgyo"
    ],
    "name:und_x_variant":[
        "Sej\u014fn-ni",
        "Saej\u014fng-ni"
    ],
    "wof:name":"Wolgyo",
    "wof:placetype":"locality"
},
  "geometry": {"coordinates":[126.54167,34.54306],"type":"Point"}
}