{
  "type": "Feature",
  "properties": {
    "gn:admin1_code":"20.0",
    "gn:asciiname":"Sinam-ni",
    "gn:country_code":"KR",
    "gn:dem":44,
    "gn:feature_class":"P",
    "gn:feature_code":"PPL",
    "gn:name":"Sinam-ni",
    "gn:population":0,
    "gn:timezone":"Asia/Seoul",
    "iso:country":"KR",
    "name:eng_x_preferred":[
        "Sinam"
    ],
    "name:eng_x_variant":[
        "Sinam-ni"
    ],
    "name:und_x_variant":[
        "\uc2dc\ub0a8\ub9ac",
        "Sinam-ni"
    ],
    "wof:name":"Sinam",
    "wof:placetype":"locality"
},
  "geometry": {"coordinates":[128.42092,35.46242],"type":"Point"}
}