{
  "type": "Feature",
  "properties": {
    "gn:admin1_code":"6.0",
    "gn:asciiname":"Munwang-gol",
    "gn:country_code":"KR",
    "gn:dem":598,
    "gn:feature_class":"P",
    "gn:feature_code":"PPL",
    "gn:name":"Munwang-gol",
    "gn:population":0,
    "gn:timezone":"Asia/Seoul",
    "iso:country":"KR",
    "name:kor_x_preferred":[
        "\ubb38\uc655\uace8"
    ],
    "wof:name":"Munwang-gol",
    "wof:placetype":"locality"
},
  "geometry": {"coordinates":[128.89330000000001,37.3947],"type":"Point"}
}