{
  "type": "Feature",
  "properties": {
    "gn:admin1_code":"21.0",
    "gn:asciiname":"Gumdagae",
    "gn:country_code":"KR",
    "gn:dem":156,
    "gn:feature_class":"P",
    "gn:feature_code":"PPL",
    "gn:name":"Gumdagae",
    "gn:population":0,
    "gn:timezone":"Asia/Seoul",
    "iso:country":"KR",
    "name:kor_x_preferred":[
        "\uad7c\ub2e4\uac1c"
    ],
    "wof:name":"Gumdagae",
    "wof:placetype":"locality"
},
  "geometry": {"coordinates":[129.11953,35.60951],"type":"Point"}
}