{
  "type": "Feature",
  "properties": {
    "iso:country":"KR",
    "qs:name":"\ubd09\uc218\ub3d9",
    "qs:name_adm0":"\ud55c\uad6d",
    "qs:name_adm1":"\uacbd\uc0c1\ub0a8\ub3c4",
    "qs:photos":2926,
    "qs:photos_1k":593,
    "qs:photos_9k":13,
    "qs:photos_9r":11,
    "qs:photos_all":2926,
    "qs:photos_sr":19,
    "qs:placetype":"LocalAdmin",
    "qs:pop_sr":"0",
    "wof:name":"\ubd09\uc218\ub3d9",
    "wof:placetype":"localadmin"
},
  "geometry": {"coordinates":[128.07861299999999,35.192328],"type":"Point"}
}