{
  "type": "Feature",
  "properties": {
    "gn:admin1_code":"16.0",
    "gn:asciiname":"Hoam",
    "gn:country_code":"KR",
    "gn:dem":107,
    "gn:feature_class":"P",
    "gn:feature_code":"PPL",
    "gn:name":"Hoam",
    "gn:population":0,
    "gn:timezone":"Asia/Seoul",
    "iso:country":"KR",
    "name:kor_x_preferred":[
        "\ud638\uc554"
    ],
    "name:und_x_variant":[
        "Pombau",
        "Hoam"
    ],
    "wof:name":"Hoam",
    "wof:placetype":"locality"
},
  "geometry": {"coordinates":[127.65197000000001,34.96646],"type":"Point"}
}