{
  "type": "Feature",
  "properties": {
    "gn:admin1_code":"17.0",
    "gn:asciiname":"Talgoji",
    "gn:country_code":"KR",
    "gn:dem":6,
    "gn:feature_class":"P",
    "gn:feature_code":"PPL",
    "gn:name":"Talgoji",
    "gn:population":0,
    "gn:timezone":"Asia/Seoul",
    "iso:country":"KR",
    "name:und_x_variant":[
        "W\u014flgoji"
    ],
    "wof:name":"Talgoji",
    "wof:placetype":"locality"
},
  "geometry": {"coordinates":[126.41916999999999,36.40611],"type":"Point"}
}