{
  "type": "Feature",
  "properties": {
    "gn:admin1_code":"5.0",
    "gn:asciiname":"Tuam-ni",
    "gn:country_code":"KR",
    "gn:dem":108,
    "gn:feature_class":"P",
    "gn:feature_code":"PPL",
    "gn:name":"Tuam-ni",
    "gn:population":0,
    "gn:timezone":"Asia/Seoul",
    "iso:country":"KR",
    "name:eng_x_preferred":[
        "Tuam"
    ],
    "name:eng_x_variant":[
        "Tuam-ni"
    ],
    "name:und_x_variant":[
        "\ub450\uc554\ub9ac",
        "Tuam-ni"
    ],
    "wof:name":"Tuam",
    "wof:placetype":"locality"
},
  "geometry": {"coordinates":[127.6317,36.2439],"type":"Point"}
}