{
  "type": "Feature",
  "properties": {
    "iso:country":"KR",
    "name:eng_x_preferred":[
        "Bisan 2(i)-dong"
    ],
    "name:kor_x_preferred":[
        "\ube44\uc0b02\ub3d9"
    ],
    "qs:name":"\ube44\uc0b02\ub3d9",
    "qs:name_adm0":"\ud55c\uad6d",
    "qs:name_adm1":"\uacbd\uae30\ub3c4",
    "qs:photos":39,
    "qs:photos_1k":8,
    "qs:photos_9k":1,
    "qs:photos_9r":2,
    "qs:photos_all":39,
    "qs:photos_sr":2,
    "qs:placetype":"Suburb",
    "qs:pop_sr":"0",
    "wof:name":"Bisan 2(i)-dong",
    "wof:placetype":"neighbourhood"
},
  "geometry": {"coordinates":[126.94833,37.405],"type":"Point"}
}