{
  "type": "Feature",
  "properties": {
    "gn:admin1_code":"13.0",
    "gn:asciiname":"Sandallangi",
    "gn:country_code":"KR",
    "gn:dem":167,
    "gn:feature_class":"P",
    "gn:feature_code":"PPL",
    "gn:name":"Sandallangi",
    "gn:population":0,
    "gn:timezone":"Asia/Seoul",
    "iso:country":"KR",
    "name:kor_x_preferred":[
        "\uc0b0\ub4e4\ub791\uc774"
    ],
    "name:kor_x_variant":[
        "Sand\u016dllangi",
        "\uc0b0\ub2ec\ub791\uc774"
    ],
    "wof:name":"Sandallangi",
    "wof:placetype":"locality"
},
  "geometry": {"coordinates":[127.343,37.84863],"type":"Point"}
}