{
  "type": "Feature",
  "properties": {
    "gn:admin1_code":"13.0",
    "gn:asciiname":"Origol",
    "gn:country_code":"KR",
    "gn:dem":105,
    "gn:feature_class":"P",
    "gn:feature_code":"PPL",
    "gn:name":"Origol",
    "gn:population":0,
    "gn:timezone":"Asia/Seoul",
    "iso:country":"KR",
    "name:und_x_variant":[
        "\uc624\ub9ac\uace8",
        "Origol"
    ],
    "wof:name":"Origol",
    "wof:placetype":"locality"
},
  "geometry": {"coordinates":[127.08551,37.83117],"type":"Point"}
}