{
  "type": "Feature",
  "properties": {
    "gn:admin1_code":"3.0",
    "gn:asciiname":"Pom-gol",
    "gn:country_code":"KR",
    "gn:dem":373,
    "gn:feature_class":"P",
    "gn:feature_code":"PPL",
    "gn:name":"Pom-gol",
    "gn:population":0,
    "gn:timezone":"Asia/Seoul",
    "iso:country":"KR",
    "name:und_x_variant":[
        "Ch\u2019un-dong",
        "Pom-kol",
        "\ubd04\uace8",
        "Pom-gol"
    ],
    "wof:name":"Pom-gol",
    "wof:placetype":"locality"
},
  "geometry": {"coordinates":[127.54239,35.73227],"type":"Point"}
}