{
  "type": "Feature",
  "properties": {
    "gn:admin1_code":"6.0",
    "gn:asciiname":"Anseoil",
    "gn:country_code":"KR",
    "gn:dem":254,
    "gn:feature_class":"P",
    "gn:feature_code":"PPL",
    "gn:name":"Anseoil",
    "gn:population":0,
    "gn:timezone":"Asia/Seoul",
    "iso:country":"KR",
    "name:kor_x_preferred":[
        "\uc548\uc11c\uc77c"
    ],
    "name:kor_x_variant":[
        "Ans\u014fil"
    ],
    "wof:name":"Anseoil",
    "wof:placetype":"locality"
},
  "geometry": {"coordinates":[128.11058,37.81516],"type":"Point"}
}