{
  "type": "Feature",
  "properties": {
    "gn:admin1_code":"6.0",
    "gn:asciiname":"K'unsorae",
    "gn:country_code":"KR",
    "gn:dem":612,
    "gn:feature_class":"P",
    "gn:feature_code":"PPL",
    "gn:name":"K\u2019\u016dnsorae",
    "gn:population":0,
    "gn:timezone":"Asia/Seoul",
    "iso:country":"KR",
    "name:kor_x_preferred":[
        "\ud070\uc18c\ub798"
    ],
    "name:kor_x_variant":[
        "K\u2019\u016dnsorae"
    ],
    "wof:name":"K'unsorae",
    "wof:placetype":"locality"
},
  "geometry": {"coordinates":[128.84909999999999,37.3938],"type":"Point"}
}