{
  "type": "Feature",
  "properties": {
    "gn:admin1_code":"6.0",
    "gn:asciiname":"Nojaengi",
    "gn:country_code":"KR",
    "gn:dem":296,
    "gn:feature_class":"P",
    "gn:feature_code":"PPL",
    "gn:name":"Nojaengi",
    "gn:population":0,
    "gn:timezone":"Asia/Seoul",
    "iso:country":"KR",
    "name:kor_x_preferred":[
        "\ub178\uc7c1\uc774"
    ],
    "wof:name":"Nojaengi",
    "wof:placetype":"locality"
},
  "geometry": {"coordinates":[128.01669999999999,37.6745],"type":"Point"}
}