{
  "type": "Feature",
  "properties": {
    "gn:admin1_code":"14.0",
    "gn:asciiname":"Sabugok",
    "gn:country_code":"KR",
    "gn:dem":62,
    "gn:feature_class":"P",
    "gn:feature_code":"PPL",
    "gn:name":"Sabugok",
    "gn:population":0,
    "gn:timezone":"Asia/Seoul",
    "iso:country":"KR",
    "name:kor_x_preferred":[
        "\uc0ac\ubd80\uace1"
    ],
    "name:und_x_variant":[
        "\uc0ac\ubd80\ub9ac",
        "Sabu-ri",
        "Sabugok"
    ],
    "wof:name":"Sabugok",
    "wof:placetype":"locality"
},
  "geometry": {"coordinates":[128.31951000000001,35.74332000000001],"type":"Point"}
}