{
  "type": "Feature",
  "properties": {
    "gn:admin1_code":"6.0",
    "gn:asciiname":"Durubong",
    "gn:country_code":"KR",
    "gn:dem":152,
    "gn:feature_class":"P",
    "gn:feature_code":"PPL",
    "gn:name":"Durubong",
    "gn:population":0,
    "gn:timezone":"Asia/Seoul",
    "iso:country":"KR",
    "name:kor_x_preferred":[
        "\ub450\ub8e8\ubd09"
    ],
    "name:und_x_variant":[
        "Turubong",
        "Durubong"
    ],
    "wof:name":"Durubong",
    "wof:placetype":"locality"
},
  "geometry": {"coordinates":[127.91842,37.7135],"type":"Point"}
}