{
  "type": "Feature",
  "properties": {
    "gn:admin1_code":"14.0",
    "gn:asciiname":"Pamjol",
    "gn:country_code":"KR",
    "gn:dem":72,
    "gn:feature_class":"P",
    "gn:feature_code":"PPL",
    "gn:name":"Pamj\u014fl",
    "gn:population":0,
    "gn:timezone":"Asia/Seoul",
    "iso:country":"KR",
    "name:und_x_variant":[
        "\ubc24\uc808",
        "Pamj\u014fl"
    ],
    "wof:name":"Pamjol",
    "wof:placetype":"locality"
},
  "geometry": {"coordinates":[128.38759999999999,36.4328],"type":"Point"}
}