{
  "type": "Feature",
  "properties": {
    "gn:admin1_code":"13.0",
    "gn:asciiname":"Yangji-mal",
    "gn:country_code":"KR",
    "gn:dem":186,
    "gn:feature_class":"P",
    "gn:feature_code":"PPL",
    "gn:name":"Yangji-mal",
    "gn:population":0,
    "gn:timezone":"Asia/Seoul",
    "iso:country":"KR",
    "name:und_x_variant":[
        "\uc591\uc9c0\ub9d0",
        "Yangji-mal"
    ],
    "wof:name":"Yangji-mal",
    "wof:placetype":"locality"
},
  "geometry": {"coordinates":[127.71111000000001,37.38972],"type":"Point"}
}