{
  "type": "Feature",
  "properties": {
    "gn:admin1_code":"6.0",
    "gn:asciiname":"Gonggol",
    "gn:country_code":"KR",
    "gn:dem":213,
    "gn:feature_class":"P",
    "gn:feature_code":"PPL",
    "gn:name":"Gonggol",
    "gn:population":0,
    "gn:timezone":"Asia/Seoul",
    "iso:country":"KR",
    "name:kor_x_preferred":[
        "\uacf5\uace8"
    ],
    "name:und_x_variant":[
        "Kong-gol",
        "Gonggol"
    ],
    "wof:name":"Gonggol",
    "wof:placetype":"locality"
},
  "geometry": {"coordinates":[127.89041,38.01418],"type":"Point"}
}