{
  "type": "Feature",
  "properties": {
    "iso:country":"KR",
    "name:eng_x_preferred":[
        "Yangji-Myeon"
    ],
    "name:eng_x_variant":[
        "Yangjimyeon",
        "Yangji-Myeon"
    ],
    "name:kor_x_preferred":[
        "\uc591\uc9c0\uba74"
    ],
    "qs:gn_local":0,
    "qs:local_max":2788,
    "qs:local_sum":3498,
    "qs:localhoods":6,
    "qs:name":"\uc591\uc9c0\uba74",
    "qs:name_adm0":"\ud55c\uad6d",
    "qs:name_adm1":"\uacbd\uae30\ub3c4",
    "qs:name_adm2":"\uc6a9\uc778\uc2dc",
    "qs:name_en":"Yangji-Myeon",
    "qs:name_lau":"\ucc98\uc778\uad6c",
    "qs:name_local":"\ucc98\uc778\uad6c",
    "qs:photo_max":86,
    "qs:photo_sum":216,
    "qs:placetype":"Suburb",
    "qs:quad_count":23,
    "qs:woe_adm0":23424868,
    "qs:woe_adm1":2345969,
    "qs:woe_adm2":28289337,
    "qs:woe_lau":28997212,
    "qs:woe_local":28997212,
    "qs:woe_ver":"7.10.0",
    "wof:lang":[
        "kor"
    ],
    "wof:name":"\uc591\uc9c0\uba74",
    "wof:placetype":"neighbourhood"
},
  "geometry": {"coordinates":[127.32034299999999,37.217043],"type":"Point"}
}