{
  "type": "Feature",
  "properties": {
    "gn:admin1_code":"6.0",
    "gn:asciiname":"Sangbanam",
    "gn:country_code":"KR",
    "gn:dem":67,
    "gn:feature_class":"P",
    "gn:feature_code":"PPL",
    "gn:name":"Sangbanam",
    "gn:population":0,
    "gn:timezone":"Asia/Seoul",
    "iso:country":"KR",
    "name:kor_x_preferred":[
        "\uc0c1\ubc18\uc554"
    ],
    "wof:name":"Sangbanam",
    "wof:placetype":"locality"
},
  "geometry": {"coordinates":[128.97595000000001,37.58066],"type":"Point"}
}