{
  "type": "Feature",
  "properties": {
    "gn:admin1_code":"20.0",
    "gn:asciiname":"Changbaek",
    "gn:cc2":"KR",
    "gn:country_code":"KR",
    "gn:dem":-9999,
    "gn:feature_class":"P",
    "gn:feature_code":"PPL",
    "gn:name":"Changbaek",
    "gn:population":0,
    "gn:timezone":"Asia/Seoul",
    "iso:country":"KR",
    "name:und_x_variant":[
        "Changbak",
        "Changbaek"
    ],
    "wof:name":"Changbaek",
    "wof:placetype":"locality"
},
  "geometry": {"coordinates":[128.23333,34.93333],"type":"Point"}
}