{
  "type": "Feature",
  "properties": {
    "gn:admin1_code":"12.0",
    "gn:asciiname":"Ssukbatdari",
    "gn:country_code":"KR",
    "gn:dem":19,
    "gn:feature_class":"P",
    "gn:feature_code":"PPL",
    "gn:name":"Ssukbatdari",
    "gn:population":0,
    "gn:timezone":"Asia/Seoul",
    "iso:country":"KR",
    "name:und_x_variant":[
        "\uc465\ubc2d\ub2e4\ub9ac",
        "Ssukbatdari",
        "Ssukpatt\u2019ari"
    ],
    "wof:name":"Ssukbatdari",
    "wof:placetype":"locality"
},
  "geometry": {"coordinates":[126.50198,37.62157],"type":"Point"}
}