{
  "type": "Feature",
  "properties": {
    "gn:admin1_code":"13.0",
    "gn:asciiname":"Yadong",
    "gn:country_code":"KR",
    "gn:dem":21,
    "gn:feature_class":"P",
    "gn:feature_code":"PPL",
    "gn:name":"Yadong",
    "gn:population":0,
    "gn:timezone":"Asia/Seoul",
    "iso:country":"KR",
    "name:und_x_variant":[
        "\uc57c\ub3d9",
        "Yadong"
    ],
    "wof:name":"Yadong",
    "wof:placetype":"locality"
},
  "geometry": {"coordinates":[126.89026,36.98922],"type":"Point"}
}