{
  "type": "Feature",
  "properties": {
    "gn:admin1_code":"17.0",
    "gn:asciiname":"Hari",
    "gn:country_code":"KR",
    "gn:dem":27,
    "gn:feature_class":"P",
    "gn:feature_code":"PPL",
    "gn:name":"Hari",
    "gn:population":0,
    "gn:timezone":"Asia/Seoul",
    "iso:country":"KR",
    "name:deu_x_preferred":[
        "Hari"
    ],
    "name:ita_x_preferred":[
        "Hari"
    ],
    "name:kan_x_preferred":[
        "\u0cb9\u0cb0\u0cbf"
    ],
    "name:kaz_x_preferred":[
        "\u0425\u0430\u0440\u0438"
    ],
    "name:pol_x_preferred":[
        "Hari"
    ],
    "name:por_x_preferred":[
        "Hari"
    ],
    "name:rus_x_preferred":[
        "\u0425\u0430\u0440\u0438"
    ],
    "name:tam_x_preferred":[
        "\u0bb9\u0bb0\u0bbf"
    ],
    "name:tel_x_preferred":[
        "\u0c39\u0c30\u0c3f"
    ],
    "name:ukr_x_preferred":[
        "\u0425\u0430\u0440\u0456"
    ],
    "name:und_x_variant":[
        "\ud558\ub9ac",
        "Hari"
    ],
    "wof:name":"Hari",
    "wof:placetype":"locality"
},
  "geometry": {"coordinates":[127.16946000000002,36.94587],"type":"Point"}
}