{
  "type": "Feature",
  "properties": {
    "gn:admin1_code":"0.0",
    "gn:asciiname":"Kosap'o",
    "gn:country_code":"KR",
    "gn:dem":144,
    "gn:feature_class":"P",
    "gn:feature_code":"PPL",
    "gn:name":"Kosap\u2019o",
    "gn:population":0,
    "gn:timezone":"Asia/Seoul",
    "iso:country":"KR",
    "wof:name":"Kosap'o",
    "wof:placetype":"locality"
},
  "geometry": {"coordinates":[126.51667,35.65],"type":"Point"}
}