{
  "type": "Feature",
  "properties": {
    "gn:admin1_code":"16.0",
    "gn:asciiname":"Oeda",
    "gn:country_code":"KR",
    "gn:dem":48,
    "gn:feature_class":"P",
    "gn:feature_code":"PPL",
    "gn:name":"Oeda",
    "gn:population":0,
    "gn:timezone":"Asia/Seoul",
    "iso:country":"KR",
    "name:kor_x_preferred":[
        "\uc678\ub2e4"
    ],
    "wof:name":"Oeda",
    "wof:placetype":"locality"
},
  "geometry": {"coordinates":[126.9632,35.32241],"type":"Point"}
}