{
  "type": "Feature",
  "properties": {
    "gn:admin1_code":"13.0",
    "gn:asciiname":"Sanboni-dong",
    "gn:country_code":"KR",
    "gn:dem":79,
    "gn:feature_class":"P",
    "gn:feature_code":"PPL",
    "gn:name":"Sanboni-dong",
    "gn:population":0,
    "gn:timezone":"Asia/Seoul",
    "iso:country":"KR",
    "name:und_x_variant":[
        "\uc0b0\ubcf82\ub3d9",
        "Sanboni-dong"
    ],
    "wof:name":"Sanboni-dong",
    "wof:placetype":"locality"
},
  "geometry": {"coordinates":[126.93028,37.36972],"type":"Point"}
}