{
  "type": "Feature",
  "properties": {
    "gn:admin1_code":"14.0",
    "gn:asciiname":"Geogok",
    "gn:country_code":"KR",
    "gn:dem":400,
    "gn:feature_class":"P",
    "gn:feature_code":"PPL",
    "gn:name":"Geogok",
    "gn:population":0,
    "gn:timezone":"Asia/Seoul",
    "iso:country":"KR",
    "name:kor_x_preferred":[
        "\uac70\uace1"
    ],
    "wof:name":"Geogok",
    "wof:placetype":"locality"
},
  "geometry": {"coordinates":[128.90161000000001,36.95925],"type":"Point"}
}