{
  "type": "Feature",
  "properties": {
    "gn:admin1_code":"3.0",
    "gn:asciiname":"Silgok",
    "gn:country_code":"KR",
    "gn:dem":132,
    "gn:feature_class":"P",
    "gn:feature_code":"PPL",
    "gn:name":"Silgok",
    "gn:population":0,
    "gn:timezone":"Asia/Seoul",
    "iso:country":"KR",
    "name:und_x_variant":[
        "\uc2e4\uace1",
        "Silgok"
    ],
    "wof:name":"Silgok",
    "wof:placetype":"locality"
},
  "geometry": {"coordinates":[127.36105000000001,35.56015],"type":"Point"}
}