{
  "type": "Feature",
  "properties": {
    "gn:admin1_code":"20.0",
    "gn:asciiname":"Imnae",
    "gn:country_code":"KR",
    "gn:dem":268,
    "gn:feature_class":"P",
    "gn:feature_code":"PPL",
    "gn:name":"Imnae",
    "gn:population":0,
    "gn:timezone":"Asia/Seoul",
    "iso:country":"KR",
    "name:und_x_variant":[
        "\uc784\ub0b4",
        "Imnae"
    ],
    "wof:name":"Imnae",
    "wof:placetype":"locality"
},
  "geometry": {"coordinates":[127.83553999999999,35.63757000000001],"type":"Point"}
}