{
  "type": "Feature",
  "properties": {
    "gn:admin1_code":"10.0",
    "gn:asciiname":"Pyeongseong",
    "gn:country_code":"KR",
    "gn:dem":2,
    "gn:feature_class":"P",
    "gn:feature_code":"PPL",
    "gn:name":"Pyeongseong",
    "gn:population":0,
    "gn:timezone":"Asia/Seoul",
    "iso:country":"KR",
    "name:kor_x_preferred":[
        "\ud3c9\uc131"
    ],
    "name:und_x_variant":[
        "P\u2019y\u014fngs\u014fng"
    ],
    "wof:name":"Pyeongseong",
    "wof:placetype":"locality"
},
  "geometry": {"coordinates":[128.9145,35.10089],"type":"Point"}
}