{
  "type": "Feature",
  "properties": {
    "gn:admin1_code":"1.0",
    "gn:admin2_code":"Pukcheju-gun",
    "gn:asciiname":"Kumnung-ni",
    "gn:country_code":"KR",
    "gn:dem":7,
    "gn:feature_class":"P",
    "gn:feature_code":"PPL",
    "gn:name":"K\u016dmn\u016dng-ni",
    "gn:population":0,
    "gn:timezone":"Asia/Seoul",
    "iso:country":"KR",
    "name:und_x_variant":[
        "K\u016dmn\u016dng",
        "Kinry\u014d-ri",
        "K\u016dmn\u016dng-ni"
    ],
    "wof:name":"Kumnung-ni",
    "wof:placetype":"locality"
},
  "geometry": {"coordinates":[126.22889000000001,33.38778],"type":"Point"}
}