{
  "type": "Feature",
  "properties": {
    "gn:admin1_code":"16.0",
    "gn:asciiname":"Ch'ungdo-ri",
    "gn:country_code":"KR",
    "gn:dem":11,
    "gn:feature_class":"P",
    "gn:feature_code":"PPL",
    "gn:name":"Ch\u2019ungdo-ri",
    "gn:population":0,
    "gn:timezone":"Asia/Seoul",
    "iso:country":"KR",
    "name:kor_x_preferred":[
        "\ucda9\ub3c4\ub9ac"
    ],
    "name:kor_x_variant":[
        "Ch\u2019ungdo-ri"
    ],
    "name:und_x_variant":[
        "Ch\u016bd\u014d-ri"
    ],
    "wof:name":"Ch'ungdo-ri",
    "wof:placetype":"locality"
},
  "geometry": {"coordinates":[126.60167,34.19361],"type":"Point"}
}