{
  "type": "Feature",
  "properties": {
    "gn:admin1_code":"14.0",
    "gn:asciiname":"Sin'gabusil",
    "gn:country_code":"KR",
    "gn:dem":345,
    "gn:feature_class":"P",
    "gn:feature_code":"PPL",
    "gn:name":"Sin\u2019gabusil",
    "gn:population":0,
    "gn:timezone":"Asia/Seoul",
    "iso:country":"KR",
    "name:und_x_variant":[
        "\uc2e0\uac00\ubd80\uc2e4",
        "Sin\u2019gabusil"
    ],
    "wof:name":"Sin'gabusil",
    "wof:placetype":"locality"
},
  "geometry": {"coordinates":[128.90001999999998,36.26099],"type":"Point"}
}