{
  "type": "Feature",
  "properties": {
    "gn:admin1_code":"6.0",
    "gn:asciiname":"Suabat",
    "gn:country_code":"KR",
    "gn:dem":715,
    "gn:feature_class":"P",
    "gn:feature_code":"PPL",
    "gn:name":"Suabat",
    "gn:population":0,
    "gn:timezone":"Asia/Seoul",
    "iso:country":"KR",
    "name:kor_x_preferred":[
        "\uc218\uc544\ubc2d"
    ],
    "wof:name":"Suabat",
    "wof:placetype":"locality"
},
  "geometry": {"coordinates":[128.9716,37.1807],"type":"Point"}
}