{
  "type": "Feature",
  "properties": {
    "gn:admin1_code":"6.0",
    "gn:asciiname":"Teogol",
    "gn:country_code":"KR",
    "gn:dem":455,
    "gn:feature_class":"P",
    "gn:feature_code":"PPL",
    "gn:name":"Teogol",
    "gn:population":0,
    "gn:timezone":"Asia/Seoul",
    "iso:country":"KR",
    "name:kor_x_preferred":[
        "\ud130\uace8"
    ],
    "name:kor_x_variant":[
        "T\u2019\u014f-gol"
    ],
    "wof:name":"Teogol",
    "wof:placetype":"locality"
},
  "geometry": {"coordinates":[127.86796,37.83024],"type":"Point"}
}