{
  "type": "Feature",
  "properties": {
    "gn:admin1_code":"14.0",
    "gn:asciiname":"Kimji",
    "gn:country_code":"KR",
    "gn:dem":299,
    "gn:feature_class":"P",
    "gn:feature_code":"PPL",
    "gn:name":"Kimji",
    "gn:population":0,
    "gn:timezone":"Asia/Seoul",
    "iso:country":"KR",
    "name:und_x_variant":[
        "\uae40\uc9c0",
        "Kimji"
    ],
    "wof:name":"Kimji",
    "wof:placetype":"locality"
},
  "geometry": {"coordinates":[128.96100000000001,36.2707],"type":"Point"}
}