{
  "type": "Feature",
  "properties": {
    "gn:admin1_code":"13.0",
    "gn:asciiname":"Saneum",
    "gn:country_code":"KR",
    "gn:dem":20,
    "gn:feature_class":"P",
    "gn:feature_code":"PPL",
    "gn:name":"Saneum",
    "gn:population":0,
    "gn:timezone":"Asia/Seoul",
    "iso:country":"KR",
    "name:und_x_variant":[
        "\uc0b0\uc74c",
        "Saneum",
        "San\u016dm"
    ],
    "wof:name":"Saneum",
    "wof:placetype":"locality"
},
  "geometry": {"coordinates":[126.55302,37.63864],"type":"Point"}
}