{
  "type": "Feature",
  "properties": {
    "gn:admin1_code":"13.0",
    "gn:asciiname":"Igok",
    "gn:country_code":"KR",
    "gn:dem":70,
    "gn:feature_class":"P",
    "gn:feature_code":"PPL",
    "gn:name":"Igok",
    "gn:population":0,
    "gn:timezone":"Asia/Seoul",
    "iso:country":"KR",
    "name:kor_x_preferred":[
        "\uc774\uace1"
    ],
    "wof:name":"Igok",
    "wof:placetype":"locality"
},
  "geometry": {"coordinates":[126.94029999999999,37.69845],"type":"Point"}
}