{
  "type": "Feature",
  "properties": {
    "gn:admin1_code":"6.0",
    "gn:asciiname":"Kakkok",
    "gn:country_code":"KR",
    "gn:dem":199,
    "gn:feature_class":"P",
    "gn:feature_code":"PPL",
    "gn:name":"Kakkok",
    "gn:population":0,
    "gn:timezone":"Asia/Seoul",
    "iso:country":"KR",
    "name:kor_x_preferred":[
        "\uac01\uace1"
    ],
    "wof:name":"Kakkok",
    "wof:placetype":"locality"
},
  "geometry": {"coordinates":[128.4554,37.1698],"type":"Point"}
}