{
  "type": "Feature",
  "properties": {
    "gn:admin1_code":"3.0",
    "gn:asciiname":"Changjae",
    "gn:country_code":"KR",
    "gn:dem":305,
    "gn:feature_class":"P",
    "gn:feature_code":"PPL",
    "gn:name":"Changjae",
    "gn:population":0,
    "gn:timezone":"Asia/Seoul",
    "iso:country":"KR",
    "name:und_x_variant":[
        "\uc7a5\uc7ac",
        "Changjae"
    ],
    "wof:name":"Changjae",
    "wof:placetype":"locality"
},
  "geometry": {"coordinates":[127.32567,35.7652],"type":"Point"}
}