{
  "type": "Feature",
  "properties": {
    "gn:admin1_code":"6.0",
    "gn:asciiname":"Kyonso",
    "gn:country_code":"KR",
    "gn:dem":5,
    "gn:feature_class":"P",
    "gn:feature_code":"PPL",
    "gn:name":"Ky\u014fnso",
    "gn:population":0,
    "gn:timezone":"Asia/Seoul",
    "iso:country":"KR",
    "name:kor_x_preferred":[
        "\uacac\uc18c"
    ],
    "name:kor_x_variant":[
        "Ky\u014fnso"
    ],
    "name:und_x_variant":[
        "Kensh\u014dshin-ri",
        "Ky\u014fnsojin-ni"
    ],
    "wof:name":"Kyonso",
    "wof:placetype":"locality"
},
  "geometry": {"coordinates":[128.94749999999999,37.7719],"type":"Point"}
}