{
  "type": "Feature",
  "properties": {
    "gn:admin1_code":"6.0",
    "gn:asciiname":"Hanyo",
    "gn:country_code":"KR",
    "gn:dem":291,
    "gn:feature_class":"P",
    "gn:feature_code":"PPL",
    "gn:name":"Hany\u014f",
    "gn:population":0,
    "gn:timezone":"Asia/Seoul",
    "iso:country":"KR",
    "name:kor_x_preferred":[
        "\ud55c\uc5ec"
    ],
    "name:kor_x_variant":[
        "Hany\u014f"
    ],
    "wof:name":"Hanyo",
    "wof:placetype":"locality"
},
  "geometry": {"coordinates":[128.00919999999999,37.2736],"type":"Point"}
}