{
  "type": "Feature",
  "properties": {
    "gn:admin1_code":"6.0",
    "gn:asciiname":"Jungchugok",
    "gn:country_code":"KR",
    "gn:dem":208,
    "gn:feature_class":"P",
    "gn:feature_code":"PPL",
    "gn:name":"Jungchugok",
    "gn:population":0,
    "gn:timezone":"Asia/Seoul",
    "iso:country":"KR",
    "name:kor_x_preferred":[
        "\uc911\ucd94\uace1"
    ],
    "name:kor_x_variant":[
        "Chungch\u2019ugok"
    ],
    "wof:name":"Jungchugok",
    "wof:placetype":"locality"
},
  "geometry": {"coordinates":[127.88182,38.02696],"type":"Point"}
}