{
  "type": "Feature",
  "properties": {
    "gn:admin1_code":"19.0",
    "gn:asciiname":"Saeteomal",
    "gn:country_code":"KR",
    "gn:dem":77,
    "gn:feature_class":"P",
    "gn:feature_code":"PPL",
    "gn:name":"Saeteomal",
    "gn:population":0,
    "gn:timezone":"Asia/Seoul",
    "iso:country":"KR",
    "name:und_x_variant":[
        "\uc0c8\ud130\ub9d0",
        "Saet\u2019\u014f-mal",
        "Saeteomal"
    ],
    "wof:name":"Saeteomal",
    "wof:placetype":"locality"
},
  "geometry": {"coordinates":[127.31446,36.30551],"type":"Point"}
}