{
  "type": "Feature",
  "properties": {
    "gn:admin1_code":"20.0",
    "gn:asciiname":"Igyo",
    "gn:cc2":"KR",
    "gn:country_code":"KR",
    "gn:dem":268,
    "gn:feature_class":"P",
    "gn:feature_code":"PPL",
    "gn:name":"Igyo",
    "gn:population":0,
    "gn:timezone":"Asia/Seoul",
    "iso:country":"KR",
    "name:und_x_variant":[
        "Igyo-ri",
        "Igyo"
    ],
    "wof:name":"Igyo",
    "wof:placetype":"locality"
},
  "geometry": {"coordinates":[127.99139,35.42472],"type":"Point"}
}