{
  "type": "Feature",
  "properties": {
    "gn:admin1_code":"20.0",
    "gn:asciiname":"Jahyeon",
    "gn:country_code":"KR",
    "gn:dem":13,
    "gn:feature_class":"P",
    "gn:feature_code":"PPL",
    "gn:name":"Jahyeon",
    "gn:population":0,
    "gn:timezone":"Asia/Seoul",
    "iso:country":"KR",
    "name:kor_x_preferred":[
        "\uc790\ud604"
    ],
    "wof:name":"Jahyeon",
    "wof:placetype":"locality"
},
  "geometry": {"coordinates":[128.81731000000002,35.22551],"type":"Point"}
}