{
  "type": "Feature",
  "properties": {
    "gn:admin1_code":"5.0",
    "gn:asciiname":"Deokjeong",
    "gn:country_code":"KR",
    "gn:dem":104,
    "gn:feature_class":"P",
    "gn:feature_code":"PPL",
    "gn:name":"Deokjeong",
    "gn:population":0,
    "gn:timezone":"Asia/Seoul",
    "iso:country":"KR",
    "name:kor_x_preferred":[
        "\ub3c5\uc815"
    ],
    "name:und_x_variant":[
        "Tokch\u014fng-ni",
        "Tokch\u014fng",
        "Deokjeong"
    ],
    "wof:name":"Deokjeong",
    "wof:placetype":"locality"
},
  "geometry": {"coordinates":[127.87062,36.95782],"type":"Point"}
}