{
  "type": "Feature",
  "properties": {
    "gn:admin1_code":"3.0",
    "gn:asciiname":"Obong-ni",
    "gn:country_code":"KR",
    "gn:dem":97,
    "gn:feature_class":"P",
    "gn:feature_code":"PPL",
    "gn:name":"Obong-ni",
    "gn:population":0,
    "gn:timezone":"Asia/Seoul",
    "iso:country":"KR",
    "name:eng_x_preferred":[
        "Obong"
    ],
    "name:eng_x_variant":[
        "Obong-ni"
    ],
    "name:und_x_variant":[
        "\uc624\ubd09\ub9ac",
        "Obong-ni"
    ],
    "wof:name":"Obong",
    "wof:placetype":"locality"
},
  "geometry": {"coordinates":[127.2628,36.0269],"type":"Point"}
}