{
  "type": "Feature",
  "properties": {
    "gn:admin1_code":"13.0",
    "gn:asciiname":"Dunjeon-dong",
    "gn:country_code":"KR",
    "gn:dem":37,
    "gn:feature_class":"P",
    "gn:feature_code":"PPLL",
    "gn:name":"Dunjeon-dong",
    "gn:population":0,
    "gn:timezone":"Asia/Seoul",
    "iso:country":"KR",
    "name:und_x_variant":[
        "\ub454\uc804\ub3d9",
        "Dunjeon-dong",
        "Tunj\u014fn-dong"
    ],
    "wof:name":"Dunjeon-dong",
    "wof:placetype":"locality"
},
  "geometry": {"coordinates":[127.10778000000001,37.42694],"type":"Point"}
}