{
  "type": "Feature",
  "properties": {
    "gn:admin1_code":"3.0",
    "gn:asciiname":"Songnam",
    "gn:country_code":"KR",
    "gn:dem":185,
    "gn:feature_class":"P",
    "gn:feature_code":"PPL",
    "gn:name":"S\u014fngnam",
    "gn:population":0,
    "gn:timezone":"Asia/Seoul",
    "iso:country":"KR",
    "name:und_x_variant":[
        "\uc131\ub0a8",
        "S\u014fngnam",
        "Seongnam"
    ],
    "wof:name":"Songnam",
    "wof:placetype":"locality"
},
  "geometry": {"coordinates":[127.39594,35.53882],"type":"Point"}
}