{
  "type": "Feature",
  "properties": {
    "gn:admin1_code":"14.0",
    "gn:asciiname":"Nodawol",
    "gn:country_code":"KR",
    "gn:dem":217,
    "gn:feature_class":"P",
    "gn:feature_code":"PPL",
    "gn:name":"Nodaw\u014fl",
    "gn:population":0,
    "gn:timezone":"Asia/Seoul",
    "iso:country":"KR",
    "name:und_x_variant":[
        "\ub178\ub2e4\uc6d4",
        "Nodaw\u014fl"
    ],
    "wof:name":"Nodawol",
    "wof:placetype":"locality"
},
  "geometry": {"coordinates":[127.85624,36.31429],"type":"Point"}
}