{
  "type": "Feature",
  "properties": {
    "gn:admin1_code":"3.0",
    "gn:asciiname":"Tokkok",
    "gn:country_code":"KR",
    "gn:dem":409,
    "gn:feature_class":"P",
    "gn:feature_code":"PPL",
    "gn:name":"T\u014fkkok",
    "gn:population":0,
    "gn:timezone":"Asia/Seoul",
    "iso:country":"KR",
    "name:und_x_variant":[
        "\ub355\uace1",
        "T\u014fkkok"
    ],
    "wof:name":"Tokkok",
    "wof:placetype":"locality"
},
  "geometry": {"coordinates":[127.57489,35.6921],"type":"Point"}
}