{
  "type": "Feature",
  "properties": {
    "gn:admin1_code":"12.0",
    "gn:asciiname":"Dolmoru",
    "gn:country_code":"KR",
    "gn:dem":16,
    "gn:feature_class":"P",
    "gn:feature_code":"PPL",
    "gn:name":"Dolmoru",
    "gn:population":0,
    "gn:timezone":"Asia/Seoul",
    "iso:country":"KR",
    "name:kor_x_preferred":[
        "\ub3cc\ubaa8\ub8e8"
    ],
    "wof:name":"Dolmoru",
    "wof:placetype":"locality"
},
  "geometry": {"coordinates":[126.50123000000001,37.77912],"type":"Point"}
}