{
  "type": "Feature",
  "properties": {
    "gn:admin1_code":"14.0",
    "gn:asciiname":"Taeyol-li",
    "gn:cc2":"KR",
    "gn:country_code":"KR",
    "gn:dem":62,
    "gn:feature_class":"P",
    "gn:feature_code":"PPL",
    "gn:name":"Taey\u014fl-li",
    "gn:population":0,
    "gn:timezone":"Asia/Seoul",
    "iso:country":"KR",
    "name:und_x_variant":[
        "Taery\u014fn",
        "Taey\u014fl-li"
    ],
    "wof:name":"Taeyol-li",
    "wof:placetype":"locality"
},
  "geometry": {"coordinates":[129.33056000000002,36.0475],"type":"Point"}
}