{
  "type": "Feature",
  "properties": {
    "gn:admin1_code":"14.0",
    "gn:asciiname":"Konnosa-ch'on",
    "gn:country_code":"KR",
    "gn:dem":175,
    "gn:feature_class":"P",
    "gn:feature_code":"PPL",
    "gn:name":"K\u014fnn\u014fsa-ch\u2019on",
    "gn:population":0,
    "gn:timezone":"Asia/Seoul",
    "iso:country":"KR",
    "name:und_x_variant":[
        "Sach\u2019on-dong",
        "K\u014fnn\u014fsa-ch\u2019on",
        "\uac74\ub108\uc0ac\ucd0c"
    ],
    "wof:name":"Konnosa-ch'on",
    "wof:placetype":"locality"
},
  "geometry": {"coordinates":[128.75470000000001,36.4076],"type":"Point"}
}