{
  "type": "Feature",
  "properties": {
    "gn:admin1_code":"20.0",
    "gn:asciiname":"Kugir-am",
    "gn:country_code":"KR",
    "gn:dem":622,
    "gn:feature_class":"P",
    "gn:feature_code":"PPL",
    "gn:name":"Kugir-am",
    "gn:population":0,
    "gn:timezone":"Asia/Seoul",
    "iso:country":"KR",
    "name:und_x_variant":[
        "\uad6d\uc77c\uc554",
        "Kugir-am"
    ],
    "wof:name":"Kugir-am",
    "wof:placetype":"locality"
},
  "geometry": {"coordinates":[128.09939,35.7962],"type":"Point"}
}