{
  "type": "Feature",
  "properties": {
    "gn:admin1_code":"13.0",
    "gn:asciiname":"Kyongbal-li",
    "gn:country_code":"KR",
    "gn:dem":118,
    "gn:feature_class":"P",
    "gn:feature_code":"PPLL",
    "gn:name":"Ky\u014fngbal-li",
    "gn:population":0,
    "gn:timezone":"Asia/Seoul",
    "iso:country":"KR",
    "name:kor_x_preferred":[
        "\uacbd\ubc18\ub9ac"
    ],
    "name:kor_x_variant":[
        "Ky\u014fngbal-li"
    ],
    "wof:name":"Kyongbal-li",
    "wof:placetype":"locality"
},
  "geometry": {"coordinates":[127.4828,37.82753],"type":"Point"}
}