{
  "type": "Feature",
  "properties": {
    "gn:admin1_code":"16.0",
    "gn:asciiname":"Yesong",
    "gn:country_code":"KR",
    "gn:dem":16,
    "gn:feature_class":"P",
    "gn:feature_code":"PPL",
    "gn:name":"Yesong",
    "gn:population":0,
    "gn:timezone":"Asia/Seoul",
    "iso:country":"KR",
    "name:kor_x_preferred":[
        "\uc608\uc1a1"
    ],
    "name:und_x_variant":[
        "Reish\u014d-ri",
        "Yesong-ni",
        "Yesong"
    ],
    "wof:name":"Yesong",
    "wof:placetype":"locality"
},
  "geometry": {"coordinates":[126.56139,34.14083],"type":"Point"}
}