{
  "type": "Feature",
  "properties": {
    "gn:admin1_code":"13.0",
    "gn:admin2_code":"Y\u014fnch'\u014fn-gun",
    "gn:asciiname":"Jeongok",
    "gn:country_code":"KR",
    "gn:dem":66,
    "gn:feature_class":"P",
    "gn:feature_code":"PPLA3",
    "gn:name":"Jeongok",
    "gn:population":0,
    "gn:timezone":"Asia/Seoul",
    "iso:country":"KR",
    "name:kor_x_preferred":[
        "\uc804\uace1"
    ],
    "name:und_x_variant":[
        "Ch\u014fn\u2019gong-ni",
        "Ch\u014fn\u2019gok",
        "Jeongok"
    ],
    "wof:name":"Jeongok",
    "wof:placetype":"locality"
},
  "geometry": {"coordinates":[127.07021,38.02596],"type":"Point"}
}