{
  "type": "Feature",
  "properties": {
    "gn:admin1_code":"20.0",
    "gn:asciiname":"Sangyul",
    "gn:country_code":"KR",
    "gn:dem":282,
    "gn:feature_class":"P",
    "gn:feature_code":"PPL",
    "gn:name":"Sangyul",
    "gn:population":0,
    "gn:timezone":"Asia/Seoul",
    "iso:country":"KR",
    "name:und_x_variant":[
        "\uc0c1\uc728",
        "Sangyul"
    ],
    "wof:name":"Sangyul",
    "wof:placetype":"locality"
},
  "geometry": {"coordinates":[127.85862,35.73943],"type":"Point"}
}