{
  "type": "Feature",
  "properties": {
    "gn:admin1_code":"3.0",
    "gn:asciiname":"Taeya",
    "gn:country_code":"KR",
    "gn:dem":38,
    "gn:feature_class":"P",
    "gn:feature_code":"PPL",
    "gn:name":"Taeya",
    "gn:population":0,
    "gn:timezone":"Asia/Seoul",
    "iso:country":"KR",
    "name:und_x_variant":[
        "\ub300\uc57c",
        "Taeya"
    ],
    "wof:name":"Taeya",
    "wof:placetype":"locality"
},
  "geometry": {"coordinates":[127.04438,35.7915],"type":"Point"}
}