{
  "type": "Feature",
  "properties": {
    "gn:admin1_code":"16.0",
    "gn:asciiname":"Witotbawi",
    "gn:country_code":"KR",
    "gn:dem":16,
    "gn:feature_class":"P",
    "gn:feature_code":"PPL",
    "gn:name":"Witotbawi",
    "gn:population":0,
    "gn:timezone":"Asia/Seoul",
    "iso:country":"KR",
    "name:kor_x_preferred":[
        "\uc717\uc637\ubc14\uc704"
    ],
    "name:und_x_variant":[
        "\u016cibau",
        "\u016ciam-ni",
        "Wibawi",
        "Witotbawi"
    ],
    "wof:name":"Witotbawi",
    "wof:placetype":"locality"
},
  "geometry": {"coordinates":[127.71816,34.97201],"type":"Point"}
}