{
  "type": "Feature",
  "properties": {
    "gn:admin1_code":"14.0",
    "gn:asciiname":"P'o-ri",
    "gn:country_code":"KR",
    "gn:dem":21,
    "gn:feature_class":"P",
    "gn:feature_code":"PPLL",
    "gn:name":"P\u2019o-ri",
    "gn:population":0,
    "gn:timezone":"Asia/Seoul",
    "iso:country":"KR",
    "name:und_x_variant":[
        "\ud3ec\ub9ac",
        "P\u2019o-ri"
    ],
    "wof:name":"P'o-ri",
    "wof:placetype":"locality"
},
  "geometry": {"coordinates":[128.37093000000002,35.62005999999999],"type":"Point"}
}