{
  "type": "Feature",
  "properties": {
    "gn:admin1_code":"14.0",
    "gn:asciiname":"Bugyeongdong",
    "gn:country_code":"KR",
    "gn:dem":117,
    "gn:feature_class":"P",
    "gn:feature_code":"PPL",
    "gn:name":"Bugyeongdong",
    "gn:population":0,
    "gn:timezone":"Asia/Seoul",
    "iso:country":"KR",
    "name:kor_x_preferred":[
        "\ubd80\uacbd\ub3d9"
    ],
    "wof:name":"Bugyeongdong",
    "wof:placetype":"locality"
},
  "geometry": {"coordinates":[129.37482,36.27635],"type":"Point"}
}