{
  "type": "Feature",
  "properties": {
    "gn:admin1_code":"3.0",
    "gn:asciiname":"Kayang",
    "gn:country_code":"KR",
    "gn:dem":57,
    "gn:feature_class":"P",
    "gn:feature_code":"PPL",
    "gn:name":"Kayang",
    "gn:population":0,
    "gn:timezone":"Asia/Seoul",
    "iso:country":"KR",
    "name:und_x_variant":[
        "\uac00\uc591",
        "Kayang"
    ],
    "wof:name":"Kayang",
    "wof:placetype":"locality"
},
  "geometry": {"coordinates":[127.21756000000001,35.99909],"type":"Point"}
}