{
  "type": "Feature",
  "properties": {
    "gn:admin1_code":"14.0",
    "gn:asciiname":"Naebong",
    "gn:country_code":"KR",
    "gn:dem":16,
    "gn:feature_class":"P",
    "gn:feature_code":"PPL",
    "gn:name":"Naebong",
    "gn:population":0,
    "gn:timezone":"Asia/Seoul",
    "iso:country":"KR",
    "name:und_x_variant":[
        "\ub0b4\ubd09",
        "Naebong"
    ],
    "wof:name":"Naebong",
    "wof:placetype":"locality"
},
  "geometry": {"coordinates":[129.41650000000001,37.002],"type":"Point"}
}