{
  "type": "Feature",
  "properties": {
    "gn:admin1_code":"6.0",
    "gn:asciiname":"Haengch'i-gol",
    "gn:country_code":"KR",
    "gn:dem":382,
    "gn:feature_class":"P",
    "gn:feature_code":"PPL",
    "gn:name":"Haengch\u2019i-gol",
    "gn:population":0,
    "gn:timezone":"Asia/Seoul",
    "iso:country":"KR",
    "name:kor_x_preferred":[
        "\ud589\uce58\uace8"
    ],
    "name:kor_x_variant":[
        "Haengch\u2019i-gol"
    ],
    "wof:name":"Haengch'i-gol",
    "wof:placetype":"locality"
},
  "geometry": {"coordinates":[128.20397,37.79906],"type":"Point"}
}