{
  "type": "Feature",
  "properties": {
    "gn:admin1_code":"6.0",
    "gn:asciiname":"Yongam-ri Igu",
    "gn:country_code":"KR",
    "gn:dem":18,
    "gn:feature_class":"P",
    "gn:feature_code":"PPL",
    "gn:name":"Yongam-ri Igu",
    "gn:population":0,
    "gn:timezone":"Asia/Seoul",
    "iso:country":"KR",
    "name:kor_x_preferred":[
        "\uc6a9\uc554\ub9ac\uc774\uad6c"
    ],
    "name:kor_x_variant":[
        "\uc6a9\uc554\ub9ac2\uad6c"
    ],
    "name:und_x_variant":[
        "Yongam-ri 2 gu"
    ],
    "wof:name":"Yongam-ri Igu",
    "wof:placetype":"locality"
},
  "geometry": {"coordinates":[128.54316,38.26451],"type":"Point"}
}