{
  "type": "Feature",
  "properties": {
    "gn:admin1_code":"20.0",
    "gn:asciiname":"Mugon-ni",
    "gn:country_code":"KR",
    "gn:dem":191,
    "gn:feature_class":"P",
    "gn:feature_code":"PPL",
    "gn:name":"Mugon-ni",
    "gn:population":0,
    "gn:timezone":"Asia/Seoul",
    "iso:country":"KR",
    "name:und_x_variant":[
        "Butsukinri",
        "Kotsukin-ri",
        "Fukkin-ri",
        "Mugon-ni",
        "Mulg\u014fn-ni",
        "Mulg\u014fn-ri",
        "Mulg\u014fl-li"
    ],
    "wof:name":"Mugon-ni",
    "wof:placetype":"locality"
},
  "geometry": {"coordinates":[128.04306,34.79139],"type":"Point"}
}