{
  "type": "Feature",
  "properties": {
    "gn:admin1_code":"14.0",
    "gn:asciiname":"Hasan-ni",
    "gn:country_code":"KR",
    "gn:dem":280,
    "gn:feature_class":"P",
    "gn:feature_code":"PPL",
    "gn:name":"Hasan-ni",
    "gn:population":0,
    "gn:timezone":"Asia/Seoul",
    "iso:country":"KR",
    "name:und_x_variant":[
        "Sanhy\u014fn"
    ],
    "wof:name":"Hasan-ni",
    "wof:placetype":"locality"
},
  "geometry": {"coordinates":[129.11667,36.16667],"type":"Point"}
}