{
  "type": "Feature",
  "properties": {
    "gn:admin1_code":"12.0",
    "gn:asciiname":"Ori-gol",
    "gn:country_code":"KR",
    "gn:dem":11,
    "gn:feature_class":"P",
    "gn:feature_code":"PPL",
    "gn:name":"\u014eri-gol",
    "gn:population":0,
    "gn:timezone":"Asia/Seoul",
    "iso:country":"KR",
    "name:kor_x_preferred":[
        "\uc5b4\ub9ac\uace8"
    ],
    "name:kor_x_variant":[
        "\u014eri-gol"
    ],
    "wof:name":"Ori-gol",
    "wof:placetype":"locality"
},
  "geometry": {"coordinates":[124.68194,37.97778],"type":"Point"}
}