{
  "type": "Feature",
  "properties": {
    "gn:admin1_code":"20.0",
    "gn:asciiname":"Yongdang",
    "gn:country_code":"KR",
    "gn:dem":47,
    "gn:feature_class":"P",
    "gn:feature_code":"PPL",
    "gn:name":"Yongdang",
    "gn:population":0,
    "gn:timezone":"Asia/Seoul",
    "iso:country":"KR",
    "name:und_x_variant":[
        "\uc6a9\ub2f9",
        "Yongdang"
    ],
    "wof:name":"Yongdang",
    "wof:placetype":"locality"
},
  "geometry": {"coordinates":[128.32977,35.08325],"type":"Point"}
}