{
  "type": "Feature",
  "properties": {
    "gn:admin1_code":"20.0",
    "gn:asciiname":"Soya",
    "gn:country_code":"KR",
    "gn:dem":24,
    "gn:feature_class":"P",
    "gn:feature_code":"PPL",
    "gn:name":"Soya",
    "gn:population":0,
    "gn:timezone":"Asia/Seoul",
    "iso:country":"KR",
    "name:ceb_x_preferred":[
        "Soya"
    ],
    "name:dan_x_preferred":[
        "Soya"
    ],
    "name:deu_x_preferred":[
        "Soya"
    ],
    "name:fas_x_preferred":[
        "\u0633\u0648\u06cc\u0627"
    ],
    "name:fra_x_preferred":[
        "Soya"
    ],
    "name:rus_x_preferred":[
        "\u0421\u043e\u044f"
    ],
    "name:spa_x_preferred":[
        "Soya"
    ],
    "name:swe_x_preferred":[
        "Soya"
    ],
    "name:ukr_x_preferred":[
        "\u0421\u043e\u044f"
    ],
    "name:und_x_variant":[
        "\uc18c\uc57c",
        "Soya"
    ],
    "wof:name":"Soya",
    "wof:placetype":"locality"
},
  "geometry": {"coordinates":[128.44980000000001,35.56027],"type":"Point"}
}