{
  "type": "Feature",
  "properties": {
    "gn:admin1_code":"13.0",
    "gn:asciiname":"Tong-gol",
    "gn:country_code":"KR",
    "gn:dem":60,
    "gn:feature_class":"P",
    "gn:feature_code":"PPL",
    "gn:name":"Tong-gol",
    "gn:population":0,
    "gn:timezone":"Asia/Seoul",
    "iso:country":"KR",
    "name:und_x_variant":[
        "\ud1b5\uace8",
        "Tong-gol",
        "T\u2019ong-gol"
    ],
    "wof:name":"Tong-gol",
    "wof:placetype":"locality"
},
  "geometry": {"coordinates":[127.12555999999999,37.12361],"type":"Point"}
}