{
  "type": "Feature",
  "properties": {
    "gn:admin1_code":"14.0",
    "gn:asciiname":"Yunisil",
    "gn:country_code":"KR",
    "gn:dem":201,
    "gn:feature_class":"P",
    "gn:feature_code":"PPL",
    "gn:name":"Yunisil",
    "gn:population":0,
    "gn:timezone":"Asia/Seoul",
    "iso:country":"KR",
    "name:und_x_variant":[
        "\uc724\uc774\uc2e4",
        "Yunisil"
    ],
    "wof:name":"Yunisil",
    "wof:placetype":"locality"
},
  "geometry": {"coordinates":[128.77330000000001,36.4019],"type":"Point"}
}