{
  "type": "Feature",
  "properties": {
    "gn:admin1_code":"16.0",
    "gn:asciiname":"Renchi-ri",
    "gn:country_code":"KR",
    "gn:dem":28,
    "gn:feature_class":"P",
    "gn:feature_code":"PPL",
    "gn:name":"Renchi-ri",
    "gn:population":0,
    "gn:timezone":"Asia/Seoul",
    "iso:country":"KR",
    "name:kor_x_preferred":[
        "\uc5f0\uc9c0"
    ],
    "name:kor_x_variant":[
        "Y\u014fnji"
    ],
    "name:und_x_variant":[
        "Y\u014fnji-ri"
    ],
    "wof:name":"Renchi-ri",
    "wof:placetype":"locality"
},
  "geometry": {"coordinates":[126.90194,34.50694],"type":"Point"}
}