{
  "type": "Feature",
  "properties": {
    "gn:admin1_code":"14.0",
    "gn:asciiname":"Araetgiil",
    "gn:country_code":"KR",
    "gn:dem":55,
    "gn:feature_class":"P",
    "gn:feature_code":"PPL",
    "gn:name":"Araetgiil",
    "gn:population":0,
    "gn:timezone":"Asia/Seoul",
    "iso:country":"KR",
    "name:kor_x_preferred":[
        "\uc544\ub7ab\uae30\uc77c"
    ],
    "wof:name":"Araetgiil",
    "wof:placetype":"locality"
},
  "geometry": {"coordinates":[129.48433,35.90712],"type":"Point"}
}