{
  "type": "Feature",
  "properties": {
    "gn:admin1_code":"6.0",
    "gn:asciiname":"Araenmal",
    "gn:country_code":"KR",
    "gn:dem":187,
    "gn:feature_class":"P",
    "gn:feature_code":"PPL",
    "gn:name":"Araenmal",
    "gn:population":0,
    "gn:timezone":"Asia/Seoul",
    "iso:country":"KR",
    "name:und_x_variant":[
        "\uc544\ub7ab\ub9d0",
        "Araenmal"
    ],
    "wof:name":"Araenmal",
    "wof:placetype":"locality"
},
  "geometry": {"coordinates":[127.61518,38.04805],"type":"Point"}
}