{
  "type": "Feature",
  "properties": {
    "gn:admin1_code":"12.0",
    "gn:asciiname":"Wougumi",
    "gn:country_code":"KR",
    "gn:dem":10,
    "gn:feature_class":"P",
    "gn:feature_code":"PPL",
    "gn:name":"W\u014fugumi",
    "gn:population":0,
    "gn:timezone":"Asia/Seoul",
    "iso:country":"KR",
    "name:kor_x_preferred":[
        "\uc6d0\uad6c\ubbf8"
    ],
    "name:kor_x_variant":[
        "W\u014fugumi"
    ],
    "wof:name":"Wougumi",
    "wof:placetype":"locality"
},
  "geometry": {"coordinates":[126.74583,37.5075],"type":"Point"}
}