{
  "type": "Feature",
  "properties": {
    "gn:admin1_code":"16.0",
    "gn:asciiname":"Daemun",
    "gn:country_code":"KR",
    "gn:dem":7,
    "gn:feature_class":"P",
    "gn:feature_code":"PPL",
    "gn:name":"Daemun",
    "gn:population":0,
    "gn:timezone":"Asia/Seoul",
    "iso:country":"KR",
    "name:kor_x_preferred":[
        "\ub300\ubb38"
    ],
    "name:und_x_variant":[
        "Taemun",
        "Daemun"
    ],
    "wof:name":"Daemun",
    "wof:placetype":"locality"
},
  "geometry": {"coordinates":[126.64333000000001,34.37306],"type":"Point"}
}