{
  "type": "Feature",
  "properties": {
    "gn:admin1_code":"12.0",
    "gn:asciiname":"Keunmal",
    "gn:country_code":"KR",
    "gn:dem":19,
    "gn:feature_class":"P",
    "gn:feature_code":"PPL",
    "gn:name":"Keunmal",
    "gn:population":0,
    "gn:timezone":"Asia/Seoul",
    "iso:country":"KR",
    "name:und_x_variant":[
        "\ud070\ub9d0",
        "Keunmal",
        "K\u2019\u016dn-mal"
    ],
    "wof:name":"Keunmal",
    "wof:placetype":"locality"
},
  "geometry": {"coordinates":[126.48971,37.70476],"type":"Point"}
}