{
  "type": "Feature",
  "properties": {
    "gn:admin1_code":"16.0",
    "gn:asciiname":"Dudong",
    "gn:country_code":"KR",
    "gn:dem":43,
    "gn:feature_class":"P",
    "gn:feature_code":"PPL",
    "gn:name":"Dudong",
    "gn:population":0,
    "gn:timezone":"Asia/Seoul",
    "iso:country":"KR",
    "name:kor_x_preferred":[
        "\ub450\ub3d9"
    ],
    "wof:name":"Dudong",
    "wof:placetype":"locality"
},
  "geometry": {"coordinates":[126.68725000000001,35.22893],"type":"Point"}
}