{
  "type": "Feature",
  "properties": {
    "gn:admin1_code":"16.0",
    "gn:asciiname":"Japo",
    "gn:country_code":"KR",
    "gn:dem":148,
    "gn:feature_class":"P",
    "gn:feature_code":"PPL",
    "gn:name":"Japo",
    "gn:population":0,
    "gn:timezone":"Asia/Seoul",
    "iso:country":"KR",
    "name:kor_x_preferred":[
        "\uc790\ud3ec"
    ],
    "name:kor_x_variant":[
        "Chap\u2019o"
    ],
    "wof:name":"Japo",
    "wof:placetype":"locality"
},
  "geometry": {"coordinates":[127.15577999999999,34.83583],"type":"Point"}
}