{
  "type": "Feature",
  "properties": {
    "gn:gn_country":"KR",
    "gn:gn_fcode":"PPL",
    "gn:gn_pop":0,
    "iso:country":"KR",
    "qs_pg:aaroncc":"KR",
    "qs_pg:gn_country":"KR",
    "qs_pg:gn_fcode":"PPL",
    "qs_pg:gn_pop":0,
    "qs_pg:name":"\ud574\uc548\ub3d9",
    "qs_pg:name_adm0":"\ud55c\uad6d",
    "qs_pg:name_adm1":"\ub300\uad6c",
    "qs_pg:photos":4,
    "qs_pg:photos_1k":1,
    "qs_pg:photos_9k":1,
    "qs_pg:photos_9r":1,
    "qs_pg:photos_all":4,
    "qs_pg:photos_sr":1,
    "qs_pg:pop_sr":0,
    "qs_pg:qs_pg_placetype":"neighbourhood",
    "qs_pg:qs_pg_placetype_gp":"Suburb",
    "qs_pg:woe_adm0":23424868,
    "woe:adm0_id":23424868,
    "woe:name_adm0":"\ud55c\uad6d",
    "woe:name_adm1":"\ub300\uad6c",
    "woe:placetype":"Suburb",
    "wof:name":"\ud574\uc548\ub3d9",
    "wof:placetype":"neighbourhood"
},
  "geometry": {"coordinates":[128.62416999999999,36.21111],"type":"Point"}
}