{
  "type": "Feature",
  "properties": {
    "gn:admin1_code":"14.0",
    "gn:asciiname":"Omi",
    "gn:country_code":"KR",
    "gn:dem":774,
    "gn:feature_class":"P",
    "gn:feature_code":"PPL",
    "gn:name":"Omi",
    "gn:population":0,
    "gn:timezone":"Asia/Seoul",
    "iso:country":"KR",
    "name:ita_x_preferred":[
        "Omi"
    ],
    "name:por_x_preferred":[
        "Omi"
    ],
    "name:rus_x_preferred":[
        "\u041e\u043c\u0438"
    ],
    "name:ukr_x_preferred":[
        "\u041e\u043c\u0456"
    ],
    "name:und_x_variant":[
        "\uc624\ubbf8"
    ],
    "name:zho_x_preferred":[
        "\u81e3"
    ],
    "wof:name":"Omi",
    "wof:placetype":"locality"
},
  "geometry": {"coordinates":[129.08709999999999,36.8243],"type":"Point"}
}