{
  "type": "Feature",
  "properties": {
    "gn:admin1_code":"14.0",
    "gn:asciiname":"Omi",
    "gn:country_code":"KR",
    "gn:dem":774,
    "gn:feature_class":"P",
    "gn:feature_code":"PPL",
    "gn:name":"Omi",
    "gn:population":0,
    "gn:timezone":"Asia/Seoul",
    "iso:country":"KR",
    "name:und_x_variant":[
        "\uc624\ubbf8",
        "Omi"
    ],
    "wof:name":"Omi",
    "wof:placetype":"locality"
},
  "geometry": {"coordinates":[129.08709999999999,36.8243],"type":"Point"}
}