{
  "type": "Feature",
  "properties": {
    "gn:admin1_code":"6.0",
    "gn:asciiname":"Wolhari",
    "gn:country_code":"KR",
    "gn:dem":213,
    "gn:feature_class":"P",
    "gn:feature_code":"PPL",
    "gn:name":"Wolhari",
    "gn:population":0,
    "gn:timezone":"Asia/Seoul",
    "iso:country":"KR",
    "name:kor_x_preferred":[
        "\uc6d4\ud558\ub9ac"
    ],
    "wof:name":"Wolhari",
    "wof:placetype":"locality"
},
  "geometry": {"coordinates":[127.20511999999999,38.24824],"type":"Point"}
}