{
  "type": "Feature",
  "properties": {
    "gn:admin1_code":"6.0",
    "gn:asciiname":"Hwajonminch'on",
    "gn:country_code":"KR",
    "gn:dem":80,
    "gn:feature_class":"P",
    "gn:feature_code":"PPL",
    "gn:name":"Hwaj\u014fnminch\u2019on",
    "gn:population":0,
    "gn:timezone":"Asia/Seoul",
    "iso:country":"KR",
    "name:und_x_variant":[
        "Hwaj\u014fnminch\u2019on",
        "\ud654\uc804\ucd0c"
    ],
    "wof:name":"Hwajonminch'on",
    "wof:placetype":"locality"
},
  "geometry": {"coordinates":[128.52289999999999,38.23217],"type":"Point"}
}