{
  "type": "Feature",
  "properties": {
    "gn:admin1_code":"5.0",
    "gn:asciiname":"Soep'ak-kol",
    "gn:country_code":"KR",
    "gn:dem":73,
    "gn:feature_class":"P",
    "gn:feature_code":"PPL",
    "gn:name":"Soep\u2019ak-kol",
    "gn:population":0,
    "gn:timezone":"Asia/Seoul",
    "iso:country":"KR",
    "name:kor_x_preferred":[
        "\uc1e0\ud30d\uace8"
    ],
    "name:kor_x_variant":[
        "Soep\u2019ak-kol"
    ],
    "wof:name":"Soep'ak-kol",
    "wof:placetype":"locality"
},
  "geometry": {"coordinates":[127.8142,37.0871],"type":"Point"}
}