{
  "type": "Feature",
  "properties": {
    "gn:admin1_code":"10.0",
    "gn:asciiname":"Galgujaegol",
    "gn:country_code":"KR",
    "gn:dem":32,
    "gn:feature_class":"P",
    "gn:feature_code":"PPL",
    "gn:name":"Galgujaegol",
    "gn:population":0,
    "gn:timezone":"Asia/Seoul",
    "iso:country":"KR",
    "name:kor_x_preferred":[
        "\uac08\uad6c\uc7ac\uace8"
    ],
    "wof:name":"Galgujaegol",
    "wof:placetype":"locality"
},
  "geometry": {"coordinates":[129.28903,35.33407000000001],"type":"Point"}
}