{
  "type": "Feature",
  "properties": {
    "gn:admin1_code":"5.0",
    "gn:asciiname":"Simbangi",
    "gn:country_code":"KR",
    "gn:dem":156,
    "gn:feature_class":"P",
    "gn:feature_code":"PPL",
    "gn:name":"Simbangi",
    "gn:population":0,
    "gn:timezone":"Asia/Seoul",
    "iso:country":"KR",
    "name:kor_x_preferred":[
        "\uc2ec\ubc29\uc774"
    ],
    "wof:name":"Simbangi",
    "wof:placetype":"locality"
},
  "geometry": {"coordinates":[127.73903,37.0244],"type":"Point"}
}