{
  "type": "Feature",
  "properties": {
    "gn:admin1_code":"5.0",
    "gn:asciiname":"Jungdong",
    "gn:country_code":"KR",
    "gn:dem":181,
    "gn:feature_class":"P",
    "gn:feature_code":"PPL",
    "gn:name":"Jungdong",
    "gn:population":0,
    "gn:timezone":"Asia/Seoul",
    "iso:country":"KR",
    "name:kor_x_preferred":[
        "\uc911\ub3d9"
    ],
    "wof:name":"Jungdong",
    "wof:placetype":"locality"
},
  "geometry": {"coordinates":[128.22661000000002,36.94025],"type":"Point"}
}