{
  "type": "Feature",
  "properties": {
    "gn:admin1_code":"6.0",
    "gn:asciiname":"Sok-kol",
    "gn:country_code":"KR",
    "gn:dem":306,
    "gn:feature_class":"P",
    "gn:feature_code":"PPL",
    "gn:name":"Sok-kol",
    "gn:population":0,
    "gn:timezone":"Asia/Seoul",
    "iso:country":"KR",
    "name:kor_x_preferred":[
        "\uc18d\uace8"
    ],
    "wof:name":"Sok-kol",
    "wof:placetype":"locality"
},
  "geometry": {"coordinates":[128.4752,37.2107],"type":"Point"}
}