{
  "type": "Feature",
  "properties": {
    "gn:admin1_code":"10.0",
    "gn:asciiname":"Wolp'yong-ni",
    "gn:country_code":"KR",
    "gn:dem":134,
    "gn:feature_class":"P",
    "gn:feature_code":"PPL",
    "gn:name":"W\u014flp\u2019y\u014fng-ni",
    "gn:population":0,
    "gn:timezone":"Asia/Seoul",
    "iso:country":"KR",
    "name:und_x_variant":[
        "W\u014flp\u2019y\u014fng-ri",
        "W\u014flp\u2019y\u014fng-ni"
    ],
    "wof:name":"Wolp'yong-ni",
    "wof:placetype":"locality"
},
  "geometry": {"coordinates":[129.13806,35.36306],"type":"Point"}
}