{
  "type": "Feature",
  "properties": {
    "gn:admin1_code":"6.0",
    "gn:asciiname":"Pugil",
    "gn:country_code":"KR",
    "gn:dem":741,
    "gn:feature_class":"P",
    "gn:feature_code":"PPL",
    "gn:name":"Pugil",
    "gn:population":0,
    "gn:timezone":"Asia/Seoul",
    "iso:country":"KR",
    "name:kor_x_preferred":[
        "\ubd81\uc77c"
    ],
    "wof:name":"Pugil",
    "wof:placetype":"locality"
},
  "geometry": {"coordinates":[128.8595,37.2372],"type":"Point"}
}