{
  "type": "Feature",
  "properties": {
    "gn:admin1_code":"6.0",
    "gn:asciiname":"Wissongnam",
    "gn:country_code":"KR",
    "gn:dem":394,
    "gn:feature_class":"P",
    "gn:feature_code":"PPL",
    "gn:name":"Wiss\u014fngnam",
    "gn:population":0,
    "gn:timezone":"Asia/Seoul",
    "iso:country":"KR",
    "name:kor_x_preferred":[
        "\uc717\uc131\ub0a8"
    ],
    "name:kor_x_variant":[
        "Wiss\u014fngnam"
    ],
    "name:und_x_variant":[
        "Uss\u014fngnam"
    ],
    "wof:name":"Wissongnam",
    "wof:placetype":"locality"
},
  "geometry": {"coordinates":[128.0831,37.269],"type":"Point"}
}