{
  "type": "Feature",
  "properties": {
    "gn:admin1_code":"14.0",
    "gn:asciiname":"Nosan",
    "gn:country_code":"KR",
    "gn:dem":105,
    "gn:feature_class":"P",
    "gn:feature_code":"PPL",
    "gn:name":"Nosan",
    "gn:population":0,
    "gn:timezone":"Asia/Seoul",
    "iso:country":"KR",
    "name:und_x_variant":[
        "Is\u014flmi",
        "Nosan-dong",
        "\ub178\uc0b0",
        "Nosan"
    ],
    "wof:name":"Nosan",
    "wof:placetype":"locality"
},
  "geometry": {"coordinates":[128.70818,35.68054],"type":"Point"}
}