{
  "type": "Feature",
  "properties": {
    "gn:admin1_code":"12.0",
    "gn:asciiname":"Norup'I",
    "gn:country_code":"KR",
    "gn:dem":14,
    "gn:feature_class":"P",
    "gn:feature_code":"PPL",
    "gn:name":"Norup\u2019I",
    "gn:population":0,
    "gn:timezone":"Asia/Seoul",
    "iso:country":"KR",
    "name:kor_x_preferred":[
        "\ub178\ub8e8\ud53c"
    ],
    "name:kor_x_variant":[
        "Norup\u2019I"
    ],
    "wof:name":"Norup'I",
    "wof:placetype":"locality"
},
  "geometry": {"coordinates":[126.78417,37.55611],"type":"Point"}
}