{
  "type": "Feature",
  "properties": {
    "gn:admin1_code":"5.0",
    "gn:asciiname":"Gudeulgi",
    "gn:country_code":"KR",
    "gn:dem":35,
    "gn:feature_class":"P",
    "gn:feature_code":"PPL",
    "gn:name":"Gudeulgi",
    "gn:population":0,
    "gn:timezone":"Asia/Seoul",
    "iso:country":"KR",
    "name:kor_x_preferred":[
        "\uad6c\ub4e4\uae30"
    ],
    "wof:name":"Gudeulgi",
    "wof:placetype":"locality"
},
  "geometry": {"coordinates":[127.36986,36.51957],"type":"Point"}
}