{
  "type": "Feature",
  "properties": {
    "gn:admin1_code":"15.0",
    "gn:asciiname":"Munyang",
    "gn:country_code":"KR",
    "gn:dem":28,
    "gn:feature_class":"P",
    "gn:feature_code":"PPL",
    "gn:name":"Munyang",
    "gn:population":0,
    "gn:timezone":"Asia/Seoul",
    "iso:country":"KR",
    "name:und_x_variant":[
        "Munyang-ni",
        "\ubb38\uc591",
        "Munyang"
    ],
    "wof:name":"Munyang",
    "wof:placetype":"locality"
},
  "geometry": {"coordinates":[128.43724,35.86192],"type":"Point"}
}