{
  "type": "Feature",
  "properties": {
    "gn:admin1_code":"6.0",
    "gn:asciiname":"Hajohang",
    "gn:country_code":"KR",
    "gn:dem":662,
    "gn:feature_class":"P",
    "gn:feature_code":"PPL",
    "gn:name":"Hajohang",
    "gn:population":0,
    "gn:timezone":"Asia/Seoul",
    "iso:country":"KR",
    "name:kor_x_preferred":[
        "\ud558\uc870\ud56d"
    ],
    "wof:name":"Hajohang",
    "wof:placetype":"locality"
},
  "geometry": {"coordinates":[128.40219999999999,37.7441],"type":"Point"}
}