{
  "type": "Feature",
  "properties": {
    "gn:admin1_code":"16.0",
    "gn:asciiname":"Ch'ungok",
    "gn:country_code":"KR",
    "gn:dem":30,
    "gn:feature_class":"P",
    "gn:feature_code":"PPL",
    "gn:name":"Ch\u2019ungok",
    "gn:population":0,
    "gn:timezone":"Asia/Seoul",
    "iso:country":"KR",
    "name:kor_x_preferred":[
        "\uc7a5\uc804"
    ],
    "name:kor_x_variant":[
        "Ch\u2019ungok"
    ],
    "wof:name":"Ch'ungok",
    "wof:placetype":"locality"
},
  "geometry": {"coordinates":[126.67833,34.48444],"type":"Point"}
}