{
  "type": "Feature",
  "properties": {
    "gn:admin1_code":"13.0",
    "gn:asciiname":"Witbeol",
    "gn:country_code":"KR",
    "gn:dem":73,
    "gn:feature_class":"P",
    "gn:feature_code":"PPL",
    "gn:name":"Witbeol",
    "gn:population":0,
    "gn:timezone":"Asia/Seoul",
    "iso:country":"KR",
    "name:und_x_variant":[
        "\uc717\ubc8c",
        "Witbeol",
        "Wipp\u014fl"
    ],
    "wof:name":"Witbeol",
    "wof:placetype":"locality"
},
  "geometry": {"coordinates":[127.45083,37.31972],"type":"Point"}
}