{
  "type": "Feature",
  "properties": {
    "gn:admin1_code":"17.0",
    "gn:asciiname":"Simong-ni",
    "gn:country_code":"KR",
    "gn:dem":25,
    "gn:feature_class":"P",
    "gn:feature_code":"PPLL",
    "gn:name":"Simong-ni",
    "gn:population":0,
    "gn:timezone":"Asia/Seoul",
    "iso:country":"KR",
    "name:und_x_variant":[
        "\uc2dc\ubaa9\ub9ac",
        "Simok",
        "Simong-ni"
    ],
    "wof:name":"Simong-ni",
    "wof:placetype":"locality"
},
  "geometry": {"coordinates":[126.2238,36.7669],"type":"Point"}
}