{
  "type": "Feature",
  "properties": {
    "gn:admin1_code":"6.0",
    "gn:asciiname":"Cholt'o",
    "gn:country_code":"KR",
    "gn:dem":469,
    "gn:feature_class":"P",
    "gn:feature_code":"PPL",
    "gn:name":"Ch\u014flt\u2019\u014f",
    "gn:population":0,
    "gn:timezone":"Asia/Seoul",
    "iso:country":"KR",
    "name:kor_x_preferred":[
        "\uc808\ud130"
    ],
    "name:kor_x_variant":[
        "Ch\u014flt\u2019\u014f"
    ],
    "wof:name":"Cholt'o",
    "wof:placetype":"locality"
},
  "geometry": {"coordinates":[128.52000000000001,37.3324],"type":"Point"}
}