{
  "type": "Feature",
  "properties": {
    "gn:admin1_code":"5.0",
    "gn:asciiname":"Nongil",
    "gn:country_code":"KR",
    "gn:dem":273,
    "gn:feature_class":"P",
    "gn:feature_code":"PPL",
    "gn:name":"Nongil",
    "gn:population":0,
    "gn:timezone":"Asia/Seoul",
    "iso:country":"KR",
    "name:kor_x_preferred":[
        "\ub17c\uae38"
    ],
    "name:und_x_variant":[
        "Non\u2019gil-li",
        "Non\u2019gil",
        "Nongil"
    ],
    "wof:name":"Nongil",
    "wof:placetype":"locality"
},
  "geometry": {"coordinates":[128.28466,36.97264000000001],"type":"Point"}
}