{
  "type": "Feature",
  "properties": {
    "gn:admin1_code":"15.0",
    "gn:asciiname":"Sutae",
    "gn:country_code":"KR",
    "gn:dem":424,
    "gn:feature_class":"P",
    "gn:feature_code":"PPL",
    "gn:name":"Sutae",
    "gn:population":0,
    "gn:timezone":"Asia/Seoul",
    "iso:country":"KR",
    "name:kor_x_preferred":[
        "\uc218\ud0dc"
    ],
    "wof:name":"Sutae",
    "wof:placetype":"locality"
},
  "geometry": {"coordinates":[128.67975000000001,35.99055],"type":"Point"}
}