{
  "type": "Feature",
  "properties": {
    "gn:admin1_code":"17.0",
    "gn:asciiname":"Chewon",
    "gn:country_code":"KR",
    "gn:dem":139,
    "gn:feature_class":"P",
    "gn:feature_code":"PPL",
    "gn:name":"Chew\u014fn",
    "gn:population":0,
    "gn:timezone":"Asia/Seoul",
    "iso:country":"KR",
    "name:und_x_variant":[
        "Chew\u014fn",
        "Chew\u014fn-ni",
        "\uc81c\uc6d0",
        "Chew\u014fl-li"
    ],
    "wof:name":"Chewon",
    "wof:placetype":"locality"
},
  "geometry": {"coordinates":[127.54583,36.11333],"type":"Point"}
}