{
  "type": "Feature",
  "properties": {
    "gn:admin1_code":"6.0",
    "gn:asciiname":"Sannomo",
    "gn:country_code":"KR",
    "gn:dem":622,
    "gn:feature_class":"P",
    "gn:feature_code":"PPL",
    "gn:name":"Sann\u014fm\u014f",
    "gn:population":0,
    "gn:timezone":"Asia/Seoul",
    "iso:country":"KR",
    "name:kor_x_preferred":[
        "\uc0b0\ub118\uc5b4"
    ],
    "name:kor_x_variant":[
        "Sann\u014fm\u014f"
    ],
    "wof:name":"Sannomo",
    "wof:placetype":"locality"
},
  "geometry": {"coordinates":[128.4708,37.3653],"type":"Point"}
}