{
  "type": "Feature",
  "properties": {
    "gn:admin1_code":"6.0",
    "gn:asciiname":"Nyogunemi",
    "gn:country_code":"KR",
    "gn:dem":150,
    "gn:feature_class":"P",
    "gn:feature_code":"PPL",
    "gn:name":"Ny\u014fgunemi",
    "gn:population":0,
    "gn:timezone":"Asia/Seoul",
    "iso:country":"KR",
    "name:kor_x_preferred":[
        "\ub140\uad6c\ub124\ubbf8"
    ],
    "name:kor_x_variant":[
        "Ny\u014fgunemi"
    ],
    "wof:name":"Nyogunemi",
    "wof:placetype":"locality"
},
  "geometry": {"coordinates":[127.8676,37.6943],"type":"Point"}
}