{
  "type": "Feature",
  "properties": {
    "gn:admin1_code":"16.0",
    "gn:asciiname":"Simjang-ni",
    "gn:country_code":"KR",
    "gn:dem":7,
    "gn:feature_class":"P",
    "gn:feature_code":"PPL",
    "gn:name":"Simjang-ni",
    "gn:population":0,
    "gn:timezone":"Asia/Seoul",
    "iso:country":"KR",
    "name:eng_x_preferred":[
        "Simjang"
    ],
    "name:eng_x_variant":[
        "Simjang-ni"
    ],
    "wof:name":"Simjang",
    "wof:placetype":"locality"
},
  "geometry": {"coordinates":[127.77361000000001,34.50139],"type":"Point"}
}