{
  "type": "Feature",
  "properties": {
    "gn:admin1_code":"17.0",
    "gn:asciiname":"Konjiul",
    "gn:country_code":"KR",
    "gn:dem":35,
    "gn:feature_class":"P",
    "gn:feature_code":"PPL",
    "gn:name":"K\u014fnjiul",
    "gn:population":0,
    "gn:timezone":"Asia/Seoul",
    "iso:country":"KR",
    "name:und_x_variant":[
        "\uac74\uc9c0\uc6b8",
        "K\u014fnjiul"
    ],
    "wof:name":"Konjiul",
    "wof:placetype":"locality"
},
  "geometry": {"coordinates":[127.015,36.425],"type":"Point"}
}