{
  "type": "Feature",
  "properties": {
    "gn:admin1_code":"13.0",
    "gn:asciiname":"Geonjaengi",
    "gn:country_code":"KR",
    "gn:dem":76,
    "gn:feature_class":"P",
    "gn:feature_code":"PPL",
    "gn:name":"Geonjaengi",
    "gn:population":0,
    "gn:timezone":"Asia/Seoul",
    "iso:country":"KR",
    "name:kor_x_preferred":[
        "\uac74\uc7c1\uc774"
    ],
    "name:kor_x_variant":[
        "K\u014fnjaengi"
    ],
    "wof:name":"Geonjaengi",
    "wof:placetype":"locality"
},
  "geometry": {"coordinates":[127.54895999999999,37.18911],"type":"Point"}
}