{
  "type": "Feature",
  "properties": {
    "gn:admin1_code":"17.0",
    "gn:asciiname":"Sangwon",
    "gn:country_code":"KR",
    "gn:dem":44,
    "gn:feature_class":"P",
    "gn:feature_code":"PPL",
    "gn:name":"Sangw\u014fn",
    "gn:population":0,
    "gn:timezone":"Asia/Seoul",
    "iso:country":"KR",
    "name:und_x_variant":[
        "Sangw\u014fn-ni",
        "\uc0c1\uc6d0",
        "Sangw\u014fn"
    ],
    "wof:name":"Sangwon",
    "wof:placetype":"locality"
},
  "geometry": {"coordinates":[126.68510000000001,36.5429],"type":"Point"}
}