{
  "type": "Feature",
  "properties": {
    "gn:admin1_code":"14.0",
    "gn:asciiname":"Gamjagol",
    "gn:country_code":"KR",
    "gn:dem":699,
    "gn:feature_class":"P",
    "gn:feature_code":"PPL",
    "gn:name":"Gamjagol",
    "gn:population":0,
    "gn:timezone":"Asia/Seoul",
    "iso:country":"KR",
    "name:kor_x_preferred":[
        "\uac10\uc790\uace8"
    ],
    "wof:name":"Gamjagol",
    "wof:placetype":"locality"
},
  "geometry": {"coordinates":[128.76859999999999,36.0982],"type":"Point"}
}