{
  "type": "Feature",
  "properties": {
    "gn:admin1_code":"13.0",
    "gn:asciiname":"Karwol",
    "gn:country_code":"KR",
    "gn:dem":114,
    "gn:feature_class":"P",
    "gn:feature_code":"PPL",
    "gn:name":"Karwol",
    "gn:population":0,
    "gn:timezone":"Asia/Seoul",
    "iso:country":"KR",
    "name:und_x_variant":[
        "\uac08\uc6d4",
        "Garwol",
        "Karwol"
    ],
    "wof:name":"Karwol",
    "wof:placetype":"locality"
},
  "geometry": {"coordinates":[127.58499999999999,37.48806],"type":"Point"}
}