{
  "type": "Feature",
  "properties": {
    "gn:admin1_code":"20.0",
    "gn:asciiname":"Jungdae-ri",
    "gn:country_code":"KR",
    "gn:dem":96,
    "gn:feature_class":"P",
    "gn:feature_code":"PPL",
    "gn:name":"Jungdae-ri",
    "gn:population":0,
    "gn:timezone":"Asia/Seoul",
    "iso:country":"KR",
    "name:und_x_variant":[
        "\uc911\ub300\ub9ac",
        "Chungdae-ri",
        "Jungdae-ri"
    ],
    "wof:name":"Jungdae-ri",
    "wof:placetype":"locality"
},
  "geometry": {"coordinates":[128.50774999999999,35.58565],"type":"Point"}
}