{
  "type": "Feature",
  "properties": {
    "gn:admin1_code":"14.0",
    "gn:asciiname":"Haebyeongsaemaeul",
    "gn:country_code":"KR",
    "gn:dem":36,
    "gn:feature_class":"P",
    "gn:feature_code":"PPL",
    "gn:name":"Haebyeongsaemaeul",
    "gn:population":0,
    "gn:timezone":"Asia/Seoul",
    "iso:country":"KR",
    "name:kor_x_preferred":[
        "\ud574\ubcd1\uc0c8\ub9c8\uc744"
    ],
    "wof:name":"Haebyeongsaemaeul",
    "wof:placetype":"locality"
},
  "geometry": {"coordinates":[129.33448999999999,36.09782],"type":"Point"}
}