{
  "type": "Feature",
  "properties": {
    "gn:admin1_code":"14.0",
    "gn:asciiname":"Sodang-maul",
    "gn:country_code":"KR",
    "gn:dem":212,
    "gn:feature_class":"P",
    "gn:feature_code":"PPL",
    "gn:name":"S\u014fdang-ma\u016dl",
    "gn:population":0,
    "gn:timezone":"Asia/Seoul",
    "iso:country":"KR",
    "name:kor_x_preferred":[
        "\uc11c\ub2f9\ub9c8\uc744"
    ],
    "name:kor_x_variant":[
        "S\u014fdang-ma\u016dl"
    ],
    "wof:name":"Sodang-maul",
    "wof:placetype":"locality"
},
  "geometry": {"coordinates":[130.84710000000001,37.4779],"type":"Point"}
}