{
  "type": "Feature",
  "properties": {
    "gn:admin1_code":"20.0",
    "gn:asciiname":"Sanji-ri",
    "gn:country_code":"KR",
    "gn:dem":25,
    "gn:feature_class":"P",
    "gn:feature_code":"PPL",
    "gn:name":"Sanji-ri",
    "gn:population":0,
    "gn:timezone":"Asia/Seoul",
    "iso:country":"KR",
    "name:und_x_variant":[
        "\uc0b0\uc9c0\ub9ac",
        "Sanji",
        "Sanji-ri"
    ],
    "wof:name":"Sanji-ri",
    "wof:placetype":"locality"
},
  "geometry": {"coordinates":[128.46851000000001,35.47181],"type":"Point"}
}