{
  "type": "Feature",
  "properties": {
    "gn:admin1_code":"13.0",
    "gn:asciiname":"Pyeongni",
    "gn:country_code":"KR",
    "gn:dem":65,
    "gn:feature_class":"P",
    "gn:feature_code":"PPL",
    "gn:name":"Pyeongni",
    "gn:population":0,
    "gn:timezone":"Asia/Seoul",
    "iso:country":"KR",
    "name:kor_x_preferred":[
        "\ud3c9\ub9ac"
    ],
    "name:und_x_variant":[
        "P\u2019y\u014fng-ni",
        "Pyeong-ri"
    ],
    "wof:name":"Pyeongni",
    "wof:placetype":"locality"
},
  "geometry": {"coordinates":[127.56610000000001,37.24294],"type":"Point"}
}