{
  "type": "Feature",
  "properties": {
    "gn:admin1_code":"16.0",
    "gn:asciiname":"Pongso-ri",
    "gn:cc2":"KR",
    "gn:country_code":"KR",
    "gn:dem":15,
    "gn:feature_class":"P",
    "gn:feature_code":"PPL",
    "gn:name":"Pongso-ri",
    "gn:population":0,
    "gn:timezone":"Asia/Seoul",
    "iso:country":"KR",
    "name:und_x_variant":[
        "Pongso",
        "Pongso-ri"
    ],
    "wof:name":"Pongso-ri",
    "wof:placetype":"locality"
},
  "geometry": {"coordinates":[126.58222000000001,34.84917],"type":"Point"}
}