{
  "type": "Feature",
  "properties": {
    "gn:admin1_code":"13.0",
    "gn:asciiname":"Doteo-gol",
    "gn:country_code":"KR",
    "gn:dem":155,
    "gn:feature_class":"P",
    "gn:feature_code":"PPL",
    "gn:name":"Doteo-gol",
    "gn:population":0,
    "gn:timezone":"Asia/Seoul",
    "iso:country":"KR",
    "name:und_x_variant":[
        "\ub3c4\ud130\uace8",
        "Doteo-gol",
        "Tot\u2019\u014f-gol"
    ],
    "wof:name":"Doteo-gol",
    "wof:placetype":"locality"
},
  "geometry": {"coordinates":[127.75,37.39583],"type":"Point"}
}