{
  "type": "Feature",
  "properties": {
    "gn:admin1_code":"16.0",
    "gn:asciiname":"Kurim-ni",
    "gn:country_code":"KR",
    "gn:dem":51,
    "gn:feature_class":"P",
    "gn:feature_code":"PPL",
    "gn:name":"Kurim-ni",
    "gn:population":0,
    "gn:timezone":"Asia/Seoul",
    "iso:country":"KR",
    "name:kor_x_preferred":[
        "\uad6c\ub9bc\ub9ac"
    ],
    "name:und_x_variant":[
        "Ky\u016brin",
        "Kurim",
        "Ky\u016brin-ri",
        "Kurim-ni"
    ],
    "wof:name":"Kurim-ni",
    "wof:placetype":"locality"
},
  "geometry": {"coordinates":[126.59889,34.51278],"type":"Point"}
}