{
  "type": "Feature",
  "properties": {
    "gn:admin1_code":"13.0",
    "gn:asciiname":"Ipyeong",
    "gn:country_code":"KR",
    "gn:dem":22,
    "gn:feature_class":"P",
    "gn:feature_code":"PPL",
    "gn:name":"Ipyeong",
    "gn:population":0,
    "gn:timezone":"Asia/Seoul",
    "iso:country":"KR",
    "name:und_x_variant":[
        "\uc774\ud3c9",
        "Ip\u2019y\u014fng",
        "Ipyeong"
    ],
    "wof:name":"Ipyeong",
    "wof:placetype":"locality"
},
  "geometry": {"coordinates":[126.88827999999999,36.97794],"type":"Point"}
}