{
  "type": "Feature",
  "properties": {
    "gn:admin1_code":"20.0",
    "gn:asciiname":"Tapch'on",
    "gn:country_code":"KR",
    "gn:dem":41,
    "gn:feature_class":"P",
    "gn:feature_code":"PPL",
    "gn:name":"Tapch\u2019\u014fn",
    "gn:population":0,
    "gn:timezone":"Asia/Seoul",
    "iso:country":"KR",
    "name:und_x_variant":[
        "\ub2f5\ucc9c",
        "Tapch\u2019\u014fn"
    ],
    "wof:name":"Tapch'on",
    "wof:placetype":"locality"
},
  "geometry": {"coordinates":[128.28477000000001,35.15762],"type":"Point"}
}