{
  "type": "Feature",
  "properties": {
    "gn:admin1_code":"16.0",
    "gn:asciiname":"Sinpung",
    "gn:country_code":"KR",
    "gn:dem":129,
    "gn:feature_class":"P",
    "gn:feature_code":"PPL",
    "gn:name":"Sinpung",
    "gn:population":0,
    "gn:timezone":"Asia/Seoul",
    "iso:country":"KR",
    "name:kor_x_preferred":[
        "\uc2e0\ud48d"
    ],
    "name:und_x_variant":[
        "Saett\u2019o",
        "Sin\u2019gi",
        "Sinp\u2019ung",
        "Sinpung"
    ],
    "wof:name":"Sinpung",
    "wof:placetype":"locality"
},
  "geometry": {"coordinates":[126.84312,34.80157],"type":"Point"}
}