{
  "type": "Feature",
  "properties": {
    "gn:admin1_code":"16.0",
    "gn:asciiname":"Wolpyeong-ri",
    "gn:country_code":"KR",
    "gn:dem":36,
    "gn:feature_class":"P",
    "gn:feature_code":"PPL",
    "gn:name":"Wolpyeong-ri",
    "gn:population":0,
    "gn:timezone":"Asia/Seoul",
    "iso:country":"KR",
    "name:kor_x_preferred":[
        "\uc6d4\ud3c9\ub9ac"
    ],
    "name:und_x_variant":[
        "W\u014flp\u2019y\u014fng",
        "W\u014flpy\u014fng-ni",
        "Wolpyeong-ri"
    ],
    "wof:name":"Wolpyeong-ri",
    "wof:placetype":"locality"
},
  "geometry": {"coordinates":[126.68785,34.89453],"type":"Point"}
}