{
  "type": "Feature",
  "properties": {
    "gn:admin1_code":"5.0",
    "gn:asciiname":"Winmal",
    "gn:country_code":"KR",
    "gn:dem":230,
    "gn:feature_class":"P",
    "gn:feature_code":"PPL",
    "gn:name":"Winmal",
    "gn:population":0,
    "gn:timezone":"Asia/Seoul",
    "iso:country":"KR",
    "name:kor_x_preferred":[
        "\uc717\ub9d0"
    ],
    "wof:name":"Winmal",
    "wof:placetype":"locality"
},
  "geometry": {"coordinates":[127.72555,36.74472],"type":"Point"}
}