{
  "type": "Feature",
  "properties": {
    "gn:admin1_code":"13.0",
    "gn:asciiname":"Saetnondeul",
    "gn:country_code":"KR",
    "gn:dem":100,
    "gn:feature_class":"P",
    "gn:feature_code":"PPL",
    "gn:name":"Saetnondeul",
    "gn:population":0,
    "gn:timezone":"Asia/Seoul",
    "iso:country":"KR",
    "name:kor_x_preferred":[
        "\uc0db\ub17c\ub4e4"
    ],
    "wof:name":"Saetnondeul",
    "wof:placetype":"locality"
},
  "geometry": {"coordinates":[126.99975000000001,37.83131],"type":"Point"}
}