{
  "type": "Feature",
  "properties": {
    "gn:admin1_code":"16.0",
    "gn:asciiname":"Wondo",
    "gn:cc2":"KR",
    "gn:country_code":"KR",
    "gn:dem":43,
    "gn:feature_class":"P",
    "gn:feature_code":"PPL",
    "gn:name":"W\u014fndo",
    "gn:population":0,
    "gn:timezone":"Asia/Seoul",
    "iso:country":"KR",
    "name:und_x_variant":[
        "W\u014fndo-ri",
        "W\u014fndo"
    ],
    "wof:name":"Wondo",
    "wof:placetype":"locality"
},
  "geometry": {"coordinates":[126.91667,34.68333],"type":"Point"}
}