{
  "type": "Feature",
  "properties": {
    "gn:admin1_code":"6.0",
    "gn:asciiname":"Araetdosimi",
    "gn:country_code":"KR",
    "gn:dem":281,
    "gn:feature_class":"P",
    "gn:feature_code":"PPL",
    "gn:name":"Araetdosimi",
    "gn:population":0,
    "gn:timezone":"Asia/Seoul",
    "iso:country":"KR",
    "name:kor_x_preferred":[
        "\uc544\ub7ab\ub3c4\uc2ec\uc774"
    ],
    "name:und_x_variant":[
        "Araettosimi",
        "Araetdosimi"
    ],
    "wof:name":"Araetdosimi",
    "wof:placetype":"locality"
},
  "geometry": {"coordinates":[127.89188,37.79348],"type":"Point"}
}