{
  "type": "Feature",
  "properties": {
    "gn:admin1_code":"6.0",
    "gn:asciiname":"Chungbangnim",
    "gn:country_code":"KR",
    "gn:dem":366,
    "gn:feature_class":"P",
    "gn:feature_code":"PPL",
    "gn:name":"Chungbangnim",
    "gn:population":0,
    "gn:timezone":"Asia/Seoul",
    "iso:country":"KR",
    "name:kor_x_preferred":[
        "\uc911\ubc29\ub9bc"
    ],
    "wof:name":"Chungbangnim",
    "wof:placetype":"locality"
},
  "geometry": {"coordinates":[128.40520000000001,37.4269],"type":"Point"}
}