{
  "type": "Feature",
  "properties": {
    "gn:admin1_code":"12.0",
    "gn:asciiname":"Yukto",
    "gn:country_code":"KR",
    "gn:dem":9,
    "gn:feature_class":"P",
    "gn:feature_code":"PPL",
    "gn:name":"Yukto",
    "gn:population":0,
    "gn:timezone":"Asia/Seoul",
    "iso:country":"KR",
    "name:kor_x_preferred":[
        "\uc721\ub3c4"
    ],
    "wof:name":"Yukto",
    "wof:placetype":"locality"
},
  "geometry": {"coordinates":[126.60666999999999,37.59278],"type":"Point"}
}