{
  "type": "Feature",
  "properties": {
    "gn:admin1_code":"20.0",
    "gn:asciiname":"Chunggye",
    "gn:country_code":"KR",
    "gn:dem":88,
    "gn:feature_class":"P",
    "gn:feature_code":"PPL",
    "gn:name":"Chunggye",
    "gn:population":0,
    "gn:timezone":"Asia/Seoul",
    "iso:country":"KR",
    "name:und_x_variant":[
        "\uc911\uacc4",
        "Chunggye"
    ],
    "wof:name":"Chunggye",
    "wof:placetype":"locality"
},
  "geometry": {"coordinates":[128.49721,35.23274],"type":"Point"}
}