{
  "type": "Feature",
  "properties": {
    "gn:admin1_code":"6.0",
    "gn:asciiname":"Gojigol",
    "gn:country_code":"KR",
    "gn:dem":53,
    "gn:feature_class":"P",
    "gn:feature_code":"PPL",
    "gn:name":"Gojigol",
    "gn:population":0,
    "gn:timezone":"Asia/Seoul",
    "iso:country":"KR",
    "name:kor_x_preferred":[
        "\uace0\uc9c0\uace8"
    ],
    "name:und_x_variant":[
        "Koji-gol",
        "Gojigol"
    ],
    "wof:name":"Gojigol",
    "wof:placetype":"locality"
},
  "geometry": {"coordinates":[128.52416000000002,38.21606],"type":"Point"}
}