{
  "type": "Feature",
  "properties": {
    "gn:admin1_code":"13.0",
    "gn:asciiname":"Haebangchon",
    "gn:country_code":"KR",
    "gn:dem":80,
    "gn:feature_class":"P",
    "gn:feature_code":"PPL",
    "gn:name":"Haebangchon",
    "gn:population":0,
    "gn:timezone":"Asia/Seoul",
    "iso:country":"KR",
    "name:kor_x_preferred":[
        "\ud574\ubc29\ucd0c"
    ],
    "name:vie_x_preferred":[
        "Haebangchon"
    ],
    "wof:name":"Haebangchon",
    "wof:placetype":"locality"
},
  "geometry": {"coordinates":[127.04958000000001,37.85639000000001],"type":"Point"}
}