{
  "type": "Feature",
  "properties": {
    "gn:admin1_code":"13.0",
    "gn:asciiname":"Chugye-ri",
    "gn:country_code":"KR",
    "gn:dem":299,
    "gn:feature_class":"P",
    "gn:feature_code":"PPL",
    "gn:name":"Chugye-ri",
    "gn:population":0,
    "gn:timezone":"Asia/Seoul",
    "iso:country":"KR",
    "name:und_x_variant":[
        "\ucd94\uacc4\ub9ac",
        "Chugye-ri",
        "Ch\u2019ugye-ri"
    ],
    "wof:name":"Chugye-ri",
    "wof:placetype":"locality"
},
  "geometry": {"coordinates":[127.31482,37.25469],"type":"Point"}
}