{
  "type": "Feature",
  "properties": {
    "gn:admin1_code":"14.0",
    "gn:asciiname":"Taebau",
    "gn:country_code":"KR",
    "gn:dem":51,
    "gn:feature_class":"P",
    "gn:feature_code":"PPL",
    "gn:name":"Taebau",
    "gn:population":0,
    "gn:timezone":"Asia/Seoul",
    "iso:country":"KR",
    "name:und_x_variant":[
        "\ub300\ubc14\uc6b0",
        "Taebau"
    ],
    "wof:name":"Taebau",
    "wof:placetype":"locality"
},
  "geometry": {"coordinates":[128.27189999999999,36.4095],"type":"Point"}
}