{
  "type": "Feature",
  "properties": {
    "gn:admin1_code":"14.0",
    "gn:asciiname":"Hansil",
    "gn:country_code":"KR",
    "gn:dem":215,
    "gn:feature_class":"P",
    "gn:feature_code":"PPL",
    "gn:name":"Hansil",
    "gn:population":0,
    "gn:timezone":"Asia/Seoul",
    "iso:country":"KR",
    "name:und_x_variant":[
        "\ud55c\uc2e4",
        "Hansil"
    ],
    "wof:name":"Hansil",
    "wof:placetype":"locality"
},
  "geometry": {"coordinates":[128.95948000000001,36.47309],"type":"Point"}
}