{
  "type": "Feature",
  "properties": {
    "gn:admin1_code":"14.0",
    "gn:asciiname":"Dammit",
    "gn:country_code":"KR",
    "gn:dem":107,
    "gn:feature_class":"P",
    "gn:feature_code":"PPL",
    "gn:name":"Dammit",
    "gn:population":0,
    "gn:timezone":"Asia/Seoul",
    "iso:country":"KR",
    "name:fra_x_preferred":[
        "Dammit"
    ],
    "name:ita_x_preferred":[
        "Dammit"
    ],
    "name:por_x_preferred":[
        "Dammit"
    ],
    "name:rus_x_preferred":[
        "Dammit"
    ],
    "name:spa_x_preferred":[
        "Dammit"
    ],
    "name:swe_x_preferred":[
        "Dammit"
    ],
    "name:und_x_variant":[
        "\ub2f4\ubc11",
        "Tammit"
    ],
    "wof:name":"Dammit",
    "wof:placetype":"locality"
},
  "geometry": {"coordinates":[128.32962000000001,35.75968],"type":"Point"}
}