{
  "type": "Feature",
  "properties": {
    "gn:admin1_code":"13.0",
    "gn:asciiname":"Makdong",
    "gn:country_code":"KR",
    "gn:dem":144,
    "gn:feature_class":"P",
    "gn:feature_code":"PPL",
    "gn:name":"Makdong",
    "gn:population":0,
    "gn:timezone":"Asia/Seoul",
    "iso:country":"KR",
    "name:kor_x_preferred":[
        "\ub9c9\ub3d9"
    ],
    "name:und_x_variant":[
        "Mak-tong",
        "Makdong"
    ],
    "wof:name":"Makdong",
    "wof:placetype":"locality"
},
  "geometry": {"coordinates":[127.60966000000001,37.52476],"type":"Point"}
}