{
  "type": "Feature",
  "properties": {
    "gn:admin1_code":"6.0",
    "gn:asciiname":"Taekobinae-ri",
    "gn:country_code":"KR",
    "gn:dem":219,
    "gn:feature_class":"P",
    "gn:feature_code":"PPL",
    "gn:name":"Taekobinae-ri",
    "gn:population":0,
    "gn:timezone":"Asia/Seoul",
    "iso:country":"KR",
    "name:und_x_variant":[
        "Daegobinae-ri",
        "\ub300\uace0\ube44\ub0b4\ub9ac",
        "Taekobinae-ri"
    ],
    "wof:name":"Taekobinae-ri",
    "wof:placetype":"locality"
},
  "geometry": {"coordinates":[127.78361,38.25194000000001],"type":"Point"}
}