{
  "type": "Feature",
  "properties": {
    "gn:admin1_code":"16.0",
    "gn:asciiname":"Songdo",
    "gn:country_code":"KR",
    "gn:dem":-9999,
    "gn:feature_class":"P",
    "gn:feature_code":"PPL",
    "gn:name":"Songdo",
    "gn:population":0,
    "gn:timezone":"Asia/Seoul",
    "iso:country":"KR",
    "name:kor_x_preferred":[
        "\uc1a1\ub3c4"
    ],
    "name:und_x_variant":[
        "Songjang-ni",
        "Songdo"
    ],
    "wof:name":"Songdo",
    "wof:placetype":"locality"
},
  "geometry": {"coordinates":[127.6148,34.88043],"type":"Point"}
}