{
  "type": "Feature",
  "properties": {
    "gn:admin1_code":"14.0",
    "gn:asciiname":"Chongja",
    "gn:country_code":"KR",
    "gn:dem":166,
    "gn:feature_class":"P",
    "gn:feature_code":"PPL",
    "gn:name":"Ch\u014fngja",
    "gn:population":0,
    "gn:timezone":"Asia/Seoul",
    "iso:country":"KR",
    "name:und_x_variant":[
        "\uc815\uc790",
        "Ch\u014fngja"
    ],
    "wof:name":"Chongja",
    "wof:placetype":"locality"
},
  "geometry": {"coordinates":[129.18606,36.15362],"type":"Point"}
}