{
  "type": "Feature",
  "properties": {
    "gn:admin1_code":"14.0",
    "gn:asciiname":"Jinti",
    "gn:country_code":"KR",
    "gn:dem":197,
    "gn:feature_class":"P",
    "gn:feature_code":"PPL",
    "gn:name":"Jinti",
    "gn:population":0,
    "gn:timezone":"Asia/Seoul",
    "iso:country":"KR",
    "name:kor_x_preferred":[
        "\uc9c4\ud2f0"
    ],
    "wof:name":"Jinti",
    "wof:placetype":"locality"
},
  "geometry": {"coordinates":[129.33393999999998,35.7813],"type":"Point"}
}