{
  "type": "Feature",
  "properties": {
    "gn:admin1_code":"13.0",
    "gn:asciiname":"Kungp'yong-ni",
    "gn:country_code":"KR",
    "gn:dem":21,
    "gn:feature_class":"P",
    "gn:feature_code":"PPL",
    "gn:name":"Kungp\u2019y\u014fng-ni",
    "gn:population":0,
    "gn:timezone":"Asia/Seoul",
    "iso:country":"KR",
    "name:kor_x_preferred":[
        "\uad81\ud3c9\ub9ac"
    ],
    "name:kor_x_variant":[
        "Kungp\u2019y\u014fng-ni"
    ],
    "wof:name":"Kungp'yong-ni",
    "wof:placetype":"locality"
},
  "geometry": {"coordinates":[126.69,37.12528],"type":"Point"}
}