{
  "type": "Feature",
  "properties": {
    "gn:admin1_code":"14.0",
    "gn:asciiname":"Taeson",
    "gn:country_code":"KR",
    "gn:dem":295,
    "gn:feature_class":"P",
    "gn:feature_code":"PPL",
    "gn:name":"Taeson",
    "gn:population":0,
    "gn:timezone":"Asia/Seoul",
    "iso:country":"KR",
    "name:und_x_variant":[
        "\ub300\uc190",
        "Taeson"
    ],
    "wof:name":"Taeson",
    "wof:placetype":"locality"
},
  "geometry": {"coordinates":[129.06954999999999,36.18626],"type":"Point"}
}