{
  "type": "Feature",
  "properties": {
    "gn:admin1_code":"14.0",
    "gn:asciiname":"Wissaejae",
    "gn:country_code":"KR",
    "gn:dem":357,
    "gn:feature_class":"P",
    "gn:feature_code":"PPL",
    "gn:name":"Wissaejae",
    "gn:population":0,
    "gn:timezone":"Asia/Seoul",
    "iso:country":"KR",
    "name:und_x_variant":[
        "Ponggong-ni",
        "Witsaejae",
        "\uc717\uc0c8\uc7ac",
        "Wissaejae"
    ],
    "wof:name":"Wissaejae",
    "wof:placetype":"locality"
},
  "geometry": {"coordinates":[127.93885,35.95845999999999],"type":"Point"}
}