{
  "type": "Feature",
  "properties": {
    "gn:admin1_code":"12.0",
    "gn:asciiname":"Neomeonggol",
    "gn:country_code":"KR",
    "gn:dem":9,
    "gn:feature_class":"P",
    "gn:feature_code":"PPL",
    "gn:name":"Neomeonggol",
    "gn:population":0,
    "gn:timezone":"Asia/Seoul",
    "iso:country":"KR",
    "name:und_x_variant":[
        "\ub108\uba4d\uace8",
        "Neomeonggol",
        "N\u014fm\u014fn-gol"
    ],
    "wof:name":"Neomeonggol",
    "wof:placetype":"locality"
},
  "geometry": {"coordinates":[126.51615,37.60744],"type":"Point"}
}