{
  "type": "Feature",
  "properties": {
    "gn:admin1_code":"16.0",
    "gn:asciiname":"Dugang",
    "gn:country_code":"KR",
    "gn:dem":124,
    "gn:feature_class":"P",
    "gn:feature_code":"PPL",
    "gn:name":"Dugang",
    "gn:population":0,
    "gn:timezone":"Asia/Seoul",
    "iso:country":"KR",
    "name:kor_x_preferred":[
        "\ub450\uac15"
    ],
    "name:und_x_variant":[
        "Tugang",
        "Dugang"
    ],
    "wof:name":"Dugang",
    "wof:placetype":"locality"
},
  "geometry": {"coordinates":[127.13103999999998,34.9997],"type":"Point"}
}