{
  "type": "Feature",
  "properties": {
    "gn:admin1_code":"6.0",
    "gn:asciiname":"Deongman",
    "gn:country_code":"KR",
    "gn:dem":319,
    "gn:feature_class":"P",
    "gn:feature_code":"PPL",
    "gn:name":"Deongman",
    "gn:population":0,
    "gn:timezone":"Asia/Seoul",
    "iso:country":"KR",
    "name:und_x_variant":[
        "\ub355\ub9cc",
        "T\u014fngman",
        "Deongman"
    ],
    "wof:name":"Deongman",
    "wof:placetype":"locality"
},
  "geometry": {"coordinates":[127.71986,37.76895],"type":"Point"}
}