{
  "type": "Feature",
  "properties": {
    "gn:admin1_code":"17.0",
    "gn:asciiname":"Panggok",
    "gn:country_code":"KR",
    "gn:dem":61,
    "gn:feature_class":"P",
    "gn:feature_code":"PPL",
    "gn:name":"Panggok",
    "gn:population":0,
    "gn:timezone":"Asia/Seoul",
    "iso:country":"KR",
    "name:und_x_variant":[
        "\ubc29\uace1",
        "Panggok"
    ],
    "wof:name":"Panggok",
    "wof:placetype":"locality"
},
  "geometry": {"coordinates":[126.5474,36.6234],"type":"Point"}
}