{
  "type": "Feature",
  "properties": {
    "gn:admin1_code":"16.0",
    "gn:asciiname":"Eumji",
    "gn:country_code":"KR",
    "gn:dem":85,
    "gn:feature_class":"P",
    "gn:feature_code":"PPL",
    "gn:name":"Eumji",
    "gn:population":0,
    "gn:timezone":"Asia/Seoul",
    "iso:country":"KR",
    "name:kor_x_preferred":[
        "\uc74c\uc9c0"
    ],
    "wof:name":"Eumji",
    "wof:placetype":"locality"
},
  "geometry": {"coordinates":[126.64530999999999,35.1144],"type":"Point"}
}