{
  "type": "Feature",
  "properties": {
    "gn:admin1_code":"14.0",
    "gn:asciiname":"Yongch'umaegi",
    "gn:country_code":"KR",
    "gn:dem":110,
    "gn:feature_class":"P",
    "gn:feature_code":"PPL",
    "gn:name":"Yongch\u2019umaegi",
    "gn:population":0,
    "gn:timezone":"Asia/Seoul",
    "iso:country":"KR",
    "name:und_x_variant":[
        "\uc6a9\ucd94\ub9e4\uae30",
        "Yongch\u2019umaegi"
    ],
    "wof:name":"Yongch'umaegi",
    "wof:placetype":"locality"
},
  "geometry": {"coordinates":[129.26070000000001,36.4455],"type":"Point"}
}