{
  "type": "Feature",
  "properties": {
    "gn:admin1_code":"16.0",
    "gn:asciiname":"Norumok",
    "gn:country_code":"KR",
    "gn:dem":58,
    "gn:feature_class":"P",
    "gn:feature_code":"PPL",
    "gn:name":"Norumok",
    "gn:population":0,
    "gn:timezone":"Asia/Seoul",
    "iso:country":"KR",
    "name:kor_x_preferred":[
        "\ub178\ub8e8\ubaa9"
    ],
    "wof:name":"Norumok",
    "wof:placetype":"locality"
},
  "geometry": {"coordinates":[127.25165,34.561],"type":"Point"}
}