{
  "type": "Feature",
  "properties": {
    "gn:admin1_code":"6.0",
    "gn:asciiname":"Sokchon",
    "gn:country_code":"KR",
    "gn:dem":177,
    "gn:feature_class":"P",
    "gn:feature_code":"PPL",
    "gn:name":"S\u014fkch\u014fn",
    "gn:population":0,
    "gn:timezone":"Asia/Seoul",
    "iso:country":"KR",
    "name:kor_x_preferred":[
        "\uc11d\uc804"
    ],
    "name:kor_x_variant":[
        "S\u014fkch\u014fn"
    ],
    "wof:name":"Sokchon",
    "wof:placetype":"locality"
},
  "geometry": {"coordinates":[127.9922,37.4633],"type":"Point"}
}