{
  "type": "Feature",
  "properties": {
    "gn:admin1_code":"20.0",
    "gn:asciiname":"Susil",
    "gn:country_code":"KR",
    "gn:dem":37,
    "gn:feature_class":"P",
    "gn:feature_code":"PPL",
    "gn:name":"Susil",
    "gn:population":0,
    "gn:timezone":"Asia/Seoul",
    "iso:country":"KR",
    "name:und_x_variant":[
        "\uc218\uc2e4",
        "Susil"
    ],
    "wof:name":"Susil",
    "wof:placetype":"locality"
},
  "geometry": {"coordinates":[128.19859,35.55895],"type":"Point"}
}