{
  "type": "Feature",
  "properties": {
    "gn:admin1_code":"19.0",
    "gn:asciiname":"Sirubong",
    "gn:country_code":"KR",
    "gn:dem":180,
    "gn:feature_class":"P",
    "gn:feature_code":"PPL",
    "gn:name":"Sirubong",
    "gn:population":0,
    "gn:timezone":"Asia/Seoul",
    "iso:country":"KR",
    "name:und_x_variant":[
        "\uc2dc\ub8e8\ubd09",
        "Sirubong"
    ],
    "wof:name":"Sirubong",
    "wof:placetype":"locality"
},
  "geometry": {"coordinates":[127.44201,36.21892],"type":"Point"}
}