{
  "type": "Feature",
  "properties": {
    "gn:admin1_code":"16.0",
    "gn:asciiname":"Geumseong",
    "gn:country_code":"KR",
    "gn:dem":173,
    "gn:feature_class":"P",
    "gn:feature_code":"PPL",
    "gn:name":"Geumseong",
    "gn:population":0,
    "gn:timezone":"Asia/Seoul",
    "iso:country":"KR",
    "name:kor_x_preferred":[
        "\uae08\uc131"
    ],
    "name:kor_x_variant":[
        "K\u016dms\u014fng"
    ],
    "wof:name":"Geumseong",
    "wof:placetype":"locality"
},
  "geometry": {"coordinates":[127.27307,34.94098],"type":"Point"}
}