{
  "type": "Feature",
  "properties": {
    "gn:admin1_code":"14.0",
    "gn:asciiname":"Kwangp'yong",
    "gn:country_code":"KR",
    "gn:dem":678,
    "gn:feature_class":"P",
    "gn:feature_code":"PPL",
    "gn:name":"Kwangp\u2019y\u014fng",
    "gn:population":0,
    "gn:timezone":"Asia/Seoul",
    "iso:country":"KR",
    "name:und_x_variant":[
        "\uad11\ud3c9",
        "Kwangp\u2019y\u014fng"
    ],
    "wof:name":"Kwangp'yong",
    "wof:placetype":"locality"
},
  "geometry": {"coordinates":[129.1053,37.084],"type":"Point"}
}