{
  "type": "Feature",
  "properties": {
    "gn:admin1_code":"17.0",
    "gn:asciiname":"Songjae",
    "gn:country_code":"KR",
    "gn:dem":14,
    "gn:feature_class":"P",
    "gn:feature_code":"PPL",
    "gn:name":"S\u014fngjae",
    "gn:population":0,
    "gn:timezone":"Asia/Seoul",
    "iso:country":"KR",
    "name:und_x_variant":[
        "\uc131\uc7ac",
        "S\u014fngjae"
    ],
    "wof:name":"Songjae",
    "wof:placetype":"locality"
},
  "geometry": {"coordinates":[126.4259,36.7407],"type":"Point"}
}