{
  "type": "Feature",
  "properties": {
    "gn:admin1_code":"16.0",
    "gn:asciiname":"Sucha",
    "gn:country_code":"KR",
    "gn:dem":8,
    "gn:feature_class":"P",
    "gn:feature_code":"PPL",
    "gn:name":"Sucha",
    "gn:population":0,
    "gn:timezone":"Asia/Seoul",
    "iso:country":"KR",
    "name:kor_x_preferred":[
        "\uc218\ucc28"
    ],
    "name:kor_x_variant":[
        "Such\u2019a"
    ],
    "wof:name":"Sucha",
    "wof:placetype":"locality"
},
  "geometry": {"coordinates":[127.4085,34.83718],"type":"Point"}
}