{
  "type": "Feature",
  "properties": {
    "gn:admin1_code":"17.0",
    "gn:asciiname":"Inchugol",
    "gn:country_code":"KR",
    "gn:dem":66,
    "gn:feature_class":"P",
    "gn:feature_code":"PPL",
    "gn:name":"Inchugol",
    "gn:population":0,
    "gn:timezone":"Asia/Seoul",
    "iso:country":"KR",
    "name:kor_x_preferred":[
        "\uc778\ucd94\uace8"
    ],
    "wof:name":"Inchugol",
    "wof:placetype":"locality"
},
  "geometry": {"coordinates":[126.91005,36.735],"type":"Point"}
}