{
  "type": "Feature",
  "properties": {
    "gn:admin1_code":"15.0",
    "gn:asciiname":"Otgol",
    "gn:country_code":"KR",
    "gn:dem":93,
    "gn:feature_class":"P",
    "gn:feature_code":"PPL",
    "gn:name":"Otgol",
    "gn:population":0,
    "gn:timezone":"Asia/Seoul",
    "iso:country":"KR",
    "name:kor_x_preferred":[
        "\uc63b\uace8"
    ],
    "name:und_x_variant":[
        "Ch\u2019il-tong",
        "Ok-kol",
        "Otgol"
    ],
    "wof:name":"Otgol",
    "wof:placetype":"locality"
},
  "geometry": {"coordinates":[128.68691000000001,35.90707000000001],"type":"Point"}
}