{
  "type": "Feature",
  "properties": {
    "gn:admin1_code":"20.0",
    "gn:asciiname":"Myonbak-kol",
    "gn:country_code":"KR",
    "gn:dem":55,
    "gn:feature_class":"P",
    "gn:feature_code":"PPL",
    "gn:name":"My\u014fnbak-kol",
    "gn:population":0,
    "gn:timezone":"Asia/Seoul",
    "iso:country":"KR",
    "name:und_x_variant":[
        "\uba74\ubc2d\uace8",
        "My\u014fnbak-kol"
    ],
    "wof:name":"Myonbak-kol",
    "wof:placetype":"locality"
},
  "geometry": {"coordinates":[128.45795000000001,35.25671],"type":"Point"}
}