{
  "type": "Feature",
  "properties": {
    "gn:admin1_code":"14.0",
    "gn:asciiname":"Kalma-dong",
    "gn:country_code":"KR",
    "gn:dem":129,
    "gn:feature_class":"P",
    "gn:feature_code":"PPL",
    "gn:name":"Kalma-dong",
    "gn:population":0,
    "gn:timezone":"Asia/Seoul",
    "iso:country":"KR",
    "name:und_x_variant":[
        "Kalmaj\u014fm",
        "\uac08\ub9c8\uc804",
        "Kalma-dong",
        "Kalmaj\u014fn"
    ],
    "wof:name":"Kalma-dong",
    "wof:placetype":"locality"
},
  "geometry": {"coordinates":[129.34639000000001,36.84435],"type":"Point"}
}