{
  "type": "Feature",
  "properties": {
    "gn:admin1_code":"13.0",
    "gn:asciiname":"Kullyang-gol",
    "gn:country_code":"KR",
    "gn:dem":42,
    "gn:feature_class":"P",
    "gn:feature_code":"PPL",
    "gn:name":"Kullyang-gol",
    "gn:population":0,
    "gn:timezone":"Asia/Seoul",
    "iso:country":"KR",
    "name:kor_x_preferred":[
        "\uad70\ub7c9\uace8"
    ],
    "name:und_x_variant":[
        "Kullyang-gol"
    ],
    "wof:name":"Kullyang-gol",
    "wof:placetype":"locality"
},
  "geometry": {"coordinates":[127.18819999999999,37.5407],"type":"Point"}
}