{
  "type": "Feature",
  "properties": {
    "gn:admin1_code":"14.0",
    "gn:asciiname":"Chunggan-maul",
    "gn:country_code":"KR",
    "gn:dem":256,
    "gn:feature_class":"P",
    "gn:feature_code":"PPL",
    "gn:name":"Chunggan-ma\u016dl",
    "gn:population":0,
    "gn:timezone":"Asia/Seoul",
    "iso:country":"KR",
    "name:und_x_variant":[
        "\uc911\uac04\ub9c8\uc744",
        "Chunggan-ma\u016dl"
    ],
    "wof:name":"Chunggan-maul",
    "wof:placetype":"locality"
},
  "geometry": {"coordinates":[129.13380000000001,36.496],"type":"Point"}
}