{
  "type": "Feature",
  "properties": {
    "iso:country":"KR",
    "name:eng_x_preferred":[
        "Okcheon-eup"
    ],
    "name:kor_x_preferred":[
        "\uc625\ucc9c\uc74d"
    ],
    "qs:name":"\uc625\ucc9c\uc74d",
    "qs:name_adm0":"\ud55c\uad6d",
    "qs:name_adm1":"\ucda9\uccad\ubd81\ub3c4",
    "qs:photos":10,
    "qs:photos_1k":2,
    "qs:photos_9k":1,
    "qs:photos_9r":1,
    "qs:photos_all":10,
    "qs:photos_sr":1,
    "qs:placetype":"LocalAdmin",
    "qs:pop_sr":"0",
    "wof:name":"Okcheon-eup",
    "wof:placetype":"localadmin"
},
  "geometry": {"coordinates":[127.67372,36.2794135],"type":"Point"}
}