{
  "type": "Feature",
  "properties": {
    "gn:admin1_code":"20.0",
    "gn:asciiname":"Seopyeon",
    "gn:country_code":"KR",
    "gn:dem":58,
    "gn:feature_class":"P",
    "gn:feature_code":"PPL",
    "gn:name":"Seopyeon",
    "gn:population":0,
    "gn:timezone":"Asia/Seoul",
    "iso:country":"KR",
    "name:kor_x_preferred":[
        "\uc11c\ud3b8"
    ],
    "wof:name":"Seopyeon",
    "wof:placetype":"locality"
},
  "geometry": {"coordinates":[128.97158000000002,35.36417],"type":"Point"}
}