{
  "type": "Feature",
  "properties": {
    "gn:admin1_code":"17.0",
    "gn:asciiname":"Galteo",
    "gn:country_code":"KR",
    "gn:dem":47,
    "gn:feature_class":"P",
    "gn:feature_code":"PPL",
    "gn:name":"Galteo",
    "gn:population":0,
    "gn:timezone":"Asia/Seoul",
    "iso:country":"KR",
    "name:kor_x_preferred":[
        "\uac08\ud130"
    ],
    "wof:name":"Galteo",
    "wof:placetype":"locality"
},
  "geometry": {"coordinates":[126.88216,36.75314],"type":"Point"}
}