{
  "type": "Feature",
  "properties": {
    "gn:admin1_code":"13.0",
    "gn:asciiname":"Eun-gol",
    "gn:country_code":"KR",
    "gn:dem":64,
    "gn:feature_class":"P",
    "gn:feature_code":"PPL",
    "gn:name":"Eun-gol",
    "gn:population":0,
    "gn:timezone":"Asia/Seoul",
    "iso:country":"KR",
    "name:und_x_variant":[
        "\uc740\uace8",
        "Eun-gol",
        "\u016cn-gol"
    ],
    "wof:name":"Eun-gol",
    "wof:placetype":"locality"
},
  "geometry": {"coordinates":[127.56278,37.32417],"type":"Point"}
}