{
  "type": "Feature",
  "properties": {
    "gn:gn_country":"KR",
    "gn:gn_fcode":"PPL",
    "gn:gn_pop":0,
    "iso:country":"KR",
    "qs_pg:aaroncc":"KR",
    "qs_pg:gn_country":"KR",
    "qs_pg:gn_fcode":"PPL",
    "qs_pg:gn_pop":0,
    "qs_pg:name":"\uc591\uc7ac\ub3d9",
    "qs_pg:name_adm0":"\ud55c\uad6d",
    "qs_pg:name_adm1":"\uc11c\uc6b8",
    "qs_pg:photos":1971,
    "qs_pg:photos_1k":399,
    "qs_pg:photos_9k":9,
    "qs_pg:photos_9r":9,
    "qs_pg:photos_all":1971,
    "qs_pg:photos_sr":15,
    "qs_pg:pop_sr":0,
    "qs_pg:qs_pg_placetype":"neighbourhood",
    "qs_pg:qs_pg_placetype_gp":"Suburb",
    "qs_pg:woe_adm0":23424868,
    "woe:adm0_id":23424868,
    "woe:name_adm0":"\ud55c\uad6d",
    "woe:name_adm1":"\uc11c\uc6b8",
    "woe:placetype":"Suburb",
    "wof:name":"\uc591\uc7ac\ub3d9",
    "wof:placetype":"neighbourhood"
},
  "geometry": {"coordinates":[127.04361,37.47222],"type":"Point"}
}