{
  "type": "Feature",
  "properties": {
    "gn:admin1_code":"6.0",
    "gn:asciiname":"Konji-dong",
    "gn:country_code":"KR",
    "gn:dem":21,
    "gn:feature_class":"P",
    "gn:feature_code":"PPL",
    "gn:name":"K\u014fnji-dong",
    "gn:population":0,
    "gn:timezone":"Asia/Seoul",
    "iso:country":"KR",
    "name:und_x_variant":[
        "\uac74\uc9c0\ub3d9",
        "K\u014fnji-dong"
    ],
    "wof:name":"Konji-dong",
    "wof:placetype":"locality"
},
  "geometry": {"coordinates":[129.14680000000001,37.4353],"type":"Point"}
}