{
  "type": "Feature",
  "properties": {
    "gn:admin1_code":"17.0",
    "gn:asciiname":"Malmagotchi",
    "gn:country_code":"KR",
    "gn:dem":16,
    "gn:feature_class":"P",
    "gn:feature_code":"PPL",
    "gn:name":"Malmagotchi",
    "gn:population":0,
    "gn:timezone":"Asia/Seoul",
    "iso:country":"KR",
    "name:und_x_variant":[
        "\ub9d0\ub9c8\uacf3\uc9c0",
        "Malmagotchi"
    ],
    "wof:name":"Malmagotchi",
    "wof:placetype":"locality"
},
  "geometry": {"coordinates":[126.3827,36.9506],"type":"Point"}
}