{
  "type": "Feature",
  "properties": {
    "gn:admin1_code":"13.0",
    "gn:asciiname":"Hapseong",
    "gn:country_code":"KR",
    "gn:dem":60,
    "gn:feature_class":"P",
    "gn:feature_code":"PPL",
    "gn:name":"Hapseong",
    "gn:population":0,
    "gn:timezone":"Asia/Seoul",
    "iso:country":"KR",
    "name:kor_x_preferred":[
        "\ud569\uc131"
    ],
    "name:und_x_variant":[
        "\ud569\uc131",
        "Hapseong"
    ],
    "wof:name":"Hapseong",
    "wof:placetype":"locality"
},
  "geometry": {"coordinates":[127.20099999999999,37.6404],"type":"Point"}
}