{
  "type": "Feature",
  "properties": {
    "gn:admin1_code":"16.0",
    "gn:asciiname":"Aengmuchon",
    "gn:country_code":"KR",
    "gn:dem":77,
    "gn:feature_class":"P",
    "gn:feature_code":"PPL",
    "gn:name":"Aengmuchon",
    "gn:population":0,
    "gn:timezone":"Asia/Seoul",
    "iso:country":"KR",
    "name:kor_x_preferred":[
        "\uc575\ubb34\ucd0c"
    ],
    "name:und_x_variant":[
        "Aengmuch\u2019on"
    ],
    "wof:name":"Aengmuchon",
    "wof:placetype":"locality"
},
  "geometry": {"coordinates":[126.90902,35.05474],"type":"Point"}
}