{
  "type": "Feature",
  "properties": {
    "gn:country":"KR",
    "gn:fcode":"UNIV",
    "gn:pop":100,
    "iso:country":"KR",
    "qs:name":"Yonsei Institute of Convergence Technology",
    "qs:photos_9r":0,
    "qs:photos_sr":0,
    "qs:pop_sr":"1",
    "wof:name":"Yonsei Institute of Convergence Technology",
    "wof:placetype":"locality",
    "wof:population":100
},
  "geometry": {"coordinates":[126.66643999999999,37.38612],"type":"Point"}
}