{
  "type": "Feature",
  "properties": {
    "gn:admin1_code":"13.0",
    "gn:admin2_code":"Yongin-si",
    "gn:asciiname":"Neopsil",
    "gn:country_code":"KR",
    "gn:dem":136,
    "gn:feature_class":"P",
    "gn:feature_code":"PPL",
    "gn:name":"Neopsil",
    "gn:population":0,
    "gn:timezone":"Asia/Seoul",
    "iso:country":"KR",
    "name:kor_x_preferred":[
        "\ub113\uc2e4"
    ],
    "name:kor_x_variant":[
        "N\u014fksil",
        "N\u014fpsil"
    ],
    "wof:name":"Neopsil",
    "wof:placetype":"locality"
},
  "geometry": {"coordinates":[127.30307000000001,37.19158],"type":"Point"}
}