{
  "type": "Feature",
  "properties": {
    "gn:admin1_code":"13.0",
    "gn:asciiname":"Yeongseongni",
    "gn:country_code":"KR",
    "gn:dem":70,
    "gn:feature_class":"P",
    "gn:feature_code":"PPL",
    "gn:name":"Yeongseongni",
    "gn:population":0,
    "gn:timezone":"Asia/Seoul",
    "iso:country":"KR",
    "name:kor_x_preferred":[
        "\uc601\uc131\ub9ac"
    ],
    "wof:name":"Yeongseongni",
    "wof:placetype":"locality"
},
  "geometry": {"coordinates":[127.20977000000001,38.00492],"type":"Point"}
}