{
  "type": "Feature",
  "properties": {
    "gn:admin1_code":"3.0",
    "gn:asciiname":"Pogul-li",
    "gn:country_code":"KR",
    "gn:dem":152,
    "gn:feature_class":"P",
    "gn:feature_code":"PPL",
    "gn:name":"Pog\u016dl-li",
    "gn:population":0,
    "gn:timezone":"Asia/Seoul",
    "iso:country":"KR",
    "name:und_x_variant":[
        "\ubcf5\uc740\ub9ac",
        "Pog\u016dl-li"
    ],
    "wof:name":"Pogul-li",
    "wof:placetype":"locality"
},
  "geometry": {"coordinates":[127.29980999999999,35.85642],"type":"Point"}
}