{
  "type": "Feature",
  "properties": {
    "gn:admin1_code":"14.0",
    "gn:asciiname":"Chukchang",
    "gn:country_code":"KR",
    "gn:dem":210,
    "gn:feature_class":"P",
    "gn:feature_code":"PPL",
    "gn:name":"Chukchang",
    "gn:population":0,
    "gn:timezone":"Asia/Seoul",
    "iso:country":"KR",
    "name:und_x_variant":[
        "\uc8fd\uc7a5",
        "Chukchang"
    ],
    "wof:name":"Chukchang",
    "wof:placetype":"locality"
},
  "geometry": {"coordinates":[129.09386000000001,36.16091],"type":"Point"}
}