{
  "type": "Feature",
  "properties": {
    "gn:admin1_code":"20.0",
    "gn:asciiname":"Deokgok",
    "gn:country_code":"KR",
    "gn:dem":161,
    "gn:feature_class":"P",
    "gn:feature_code":"PPL",
    "gn:name":"Deokgok",
    "gn:population":0,
    "gn:timezone":"Asia/Seoul",
    "iso:country":"KR",
    "name:kor_x_preferred":[
        "\ub355\uace1"
    ],
    "name:und_x_variant":[
        "\ub355\uace1\ub9ac",
        "T\u014fkkong-ni",
        "Deokgok",
        "T\u014fkkok"
    ],
    "wof:name":"Deokgok",
    "wof:placetype":"locality"
},
  "geometry": {"coordinates":[128.55604,35.59503],"type":"Point"}
}