{
  "type": "Feature",
  "properties": {
    "gn:admin1_code":"13.0",
    "gn:asciiname":"Wonjangdong",
    "gn:country_code":"KR",
    "gn:dem":21,
    "gn:feature_class":"P",
    "gn:feature_code":"PPL",
    "gn:name":"Wonjangdong",
    "gn:population":0,
    "gn:timezone":"Asia/Seoul",
    "iso:country":"KR",
    "name:und_x_variant":[
        "\uc6d0\uc7a5\ub3d9",
        "Wonjangdong",
        "W\u014fnjang-dong"
    ],
    "wof:name":"Wonjangdong",
    "wof:placetype":"locality"
},
  "geometry": {"coordinates":[127.02697000000001,37.07551],"type":"Point"}
}