{
  "type": "Feature",
  "properties": {
    "gn:admin1_code":"13.0",
    "gn:asciiname":"Maebawi",
    "gn:country_code":"KR",
    "gn:dem":12,
    "gn:feature_class":"P",
    "gn:feature_code":"PPL",
    "gn:name":"Maebawi",
    "gn:population":0,
    "gn:timezone":"Asia/Seoul",
    "iso:country":"KR",
    "name:kor_x_preferred":[
        "\ub9e4\ubc14\uc704"
    ],
    "wof:name":"Maebawi",
    "wof:placetype":"locality"
},
  "geometry": {"coordinates":[126.79306,37.15306],"type":"Point"}
}