{
  "type": "Feature",
  "properties": {
    "gn:admin1_code":"11.0",
    "gn:asciiname":"Amsai-dong",
    "gn:country_code":"KR",
    "gn:dem":9,
    "gn:feature_class":"P",
    "gn:feature_code":"PPL",
    "gn:name":"Amsai-dong",
    "gn:population":0,
    "gn:timezone":"Asia/Seoul",
    "iso:country":"KR",
    "name:und_x_variant":[
        "\uc554\uc0ac2\ub3d9",
        "Amsai-dong"
    ],
    "wof:name":"Amsai-dong",
    "wof:placetype":"locality"
},
  "geometry": {"coordinates":[127.12309999999999,37.55815],"type":"Point"}
}