{
  "type": "Feature",
  "properties": {
    "gn:admin1_code":"13.0",
    "gn:asciiname":"Munbasil",
    "gn:country_code":"KR",
    "gn:dem":95,
    "gn:feature_class":"P",
    "gn:feature_code":"PPL",
    "gn:name":"Munbasil",
    "gn:population":0,
    "gn:timezone":"Asia/Seoul",
    "iso:country":"KR",
    "name:und_x_variant":[
        "\ubb38\ubc14\uc2e4",
        "Munbasil"
    ],
    "wof:name":"Munbasil",
    "wof:placetype":"locality"
},
  "geometry": {"coordinates":[127.50528,37.36222],"type":"Point"}
}