{
  "type": "Feature",
  "properties": {
    "gn:admin1_code":"13.0",
    "gn:asciiname":"Habugok",
    "gn:country_code":"KR",
    "gn:dem":75,
    "gn:feature_class":"P",
    "gn:feature_code":"PPL",
    "gn:name":"Habugok",
    "gn:population":0,
    "gn:timezone":"Asia/Seoul",
    "iso:country":"KR",
    "name:und_x_variant":[
        "\ud558\ubd80\uace1",
        "Habugok"
    ],
    "wof:name":"Habugok",
    "wof:placetype":"locality"
},
  "geometry": {"coordinates":[127.24666999999999,37.31306],"type":"Point"}
}