{
  "type": "Feature",
  "properties": {
    "gn:admin1_code":"5.0",
    "gn:asciiname":"Darigol",
    "gn:country_code":"KR",
    "gn:dem":251,
    "gn:feature_class":"P",
    "gn:feature_code":"PPL",
    "gn:name":"Darigol",
    "gn:population":0,
    "gn:timezone":"Asia/Seoul",
    "iso:country":"KR",
    "name:kor_x_preferred":[
        "\ub2e4\ub9ac\uace8"
    ],
    "name:und_x_variant":[
        "Tari-gol",
        "Darigol"
    ],
    "wof:name":"Darigol",
    "wof:placetype":"locality"
},
  "geometry": {"coordinates":[128.00604999999999,37.02479],"type":"Point"}
}