{
  "type": "Feature",
  "properties": {
    "gn:admin1_code":"6.0",
    "gn:asciiname":"Kalbat",
    "gn:country_code":"KR",
    "gn:dem":615,
    "gn:feature_class":"P",
    "gn:feature_code":"PPL",
    "gn:name":"Kalbat",
    "gn:population":0,
    "gn:timezone":"Asia/Seoul",
    "iso:country":"KR",
    "name:kor_x_preferred":[
        "\uac08\ubc2d"
    ],
    "wof:name":"Kalbat",
    "wof:placetype":"locality"
},
  "geometry": {"coordinates":[128.91470000000001,37.3671],"type":"Point"}
}