{
  "type": "Feature",
  "properties": {
    "gn:admin1_code":"6.0",
    "gn:asciiname":"Bangye-dong",
    "gn:country_code":"KR",
    "gn:dem":74,
    "gn:feature_class":"P",
    "gn:feature_code":"PPL",
    "gn:name":"Bangye-dong",
    "gn:population":0,
    "gn:timezone":"Asia/Seoul",
    "iso:country":"KR",
    "name:und_x_variant":[
        "\ubc18\uacc4\ub3d9",
        "Bangye-dong",
        "Pan\u2019gye-dong"
    ],
    "wof:name":"Bangye-dong",
    "wof:placetype":"locality"
},
  "geometry": {"coordinates":[127.79028,37.29361],"type":"Point"}
}