{
  "type": "Feature",
  "properties": {
    "gn:admin1_code":"17.0",
    "gn:asciiname":"Sat'ae-mal",
    "gn:country_code":"KR",
    "gn:dem":49,
    "gn:feature_class":"P",
    "gn:feature_code":"PPL",
    "gn:name":"Sat\u2019ae-mal",
    "gn:population":0,
    "gn:timezone":"Asia/Seoul",
    "iso:country":"KR",
    "name:und_x_variant":[
        "\uc0ac\ud0dc\ub9d0",
        "Sat\u2019ae-mal"
    ],
    "wof:name":"Sat'ae-mal",
    "wof:placetype":"locality"
},
  "geometry": {"coordinates":[126.8434,36.643],"type":"Point"}
}