{
  "type": "Feature",
  "properties": {
    "gn:admin1_code":"17.0",
    "gn:asciiname":"Karhyol-li",
    "gn:country_code":"KR",
    "gn:dem":38,
    "gn:feature_class":"P",
    "gn:feature_code":"PPL",
    "gn:name":"Karhy\u014fl-li",
    "gn:population":0,
    "gn:timezone":"Asia/Seoul",
    "iso:country":"KR",
    "name:und_x_variant":[
        "\uac08\ud604\ub9ac",
        "Karhy\u014fl-li"
    ],
    "wof:name":"Karhyol-li",
    "wof:placetype":"locality"
},
  "geometry": {"coordinates":[126.4735,36.8264],"type":"Point"}
}