{
  "type": "Feature",
  "properties": {
    "gn:admin1_code":"14.0",
    "gn:asciiname":"Jeondu",
    "gn:country_code":"KR",
    "gn:dem":291,
    "gn:feature_class":"P",
    "gn:feature_code":"PPL",
    "gn:name":"Jeondu",
    "gn:population":0,
    "gn:timezone":"Asia/Seoul",
    "iso:country":"KR",
    "name:kor_x_preferred":[
        "\uc804\ub450"
    ],
    "wof:name":"Jeondu",
    "wof:placetype":"locality"
},
  "geometry": {"coordinates":[128.25221999999999,36.74589],"type":"Point"}
}