{
  "type": "Feature",
  "properties": {
    "iso:country":"KR",
    "name:eng_x_preferred":[
        "Unsan-myeon"
    ],
    "name:kor_x_preferred":[
        "\uc6b4\uc0b0\uba74"
    ],
    "qs:name":"\uc6b4\uc0b0\uba74",
    "qs:name_adm0":"\ud55c\uad6d",
    "qs:name_adm1":"\ucda9\uccad\ub0a8\ub3c4",
    "qs:photos":43,
    "qs:photos_1k":9,
    "qs:photos_9k":1,
    "qs:photos_9r":2,
    "qs:photos_all":43,
    "qs:photos_sr":2,
    "qs:placetype":"LocalAdmin",
    "qs:pop_sr":"0",
    "wof:name":"Unsan-myeon",
    "wof:placetype":"localadmin"
},
  "geometry": {"coordinates":[126.59683200000001,36.809284],"type":"Point"}
}