{
  "type": "Feature",
  "properties": {
    "gn:admin1_code":"13.0",
    "gn:asciiname":"Dangmugae",
    "gn:country_code":"KR",
    "gn:dem":83,
    "gn:feature_class":"P",
    "gn:feature_code":"PPL",
    "gn:name":"Dangmugae",
    "gn:population":0,
    "gn:timezone":"Asia/Seoul",
    "iso:country":"KR",
    "name:kor_x_preferred":[
        "\ub2f9\ubb34\uac1c"
    ],
    "name:und_x_variant":[
        "\ub2f9\ubb35\uac1c",
        "Tangmukkae",
        "Dangmugae"
    ],
    "wof:name":"Dangmugae",
    "wof:placetype":"locality"
},
  "geometry": {"coordinates":[127.52827000000001,37.86265],"type":"Point"}
}