{
  "type": "Feature",
  "properties": {
    "gn:admin1_code":"18.0",
    "gn:asciiname":"Masan",
    "gn:country_code":"KR",
    "gn:dem":18,
    "gn:feature_class":"P",
    "gn:feature_code":"PPL",
    "gn:name":"Masan",
    "gn:population":434371,
    "gn:timezone":"Asia/Seoul",
    "iso:country":"KR",
    "name:kor_x_preferred":[
        "\ub9c8\uc0b0"
    ],
    "name:und_x_variant":[
        "Masan-ni",
        "Masan"
    ],
    "wof:name":"Masan",
    "wof:placetype":"locality",
    "wof:population":434371
},
  "geometry": {"coordinates":[126.83149,35.12725],"type":"Point"}
}