{
  "type": "Feature",
  "properties": {
    "gn:admin1_code":"6.0",
    "gn:asciiname":"Gwangyangdong",
    "gn:country_code":"KR",
    "gn:dem":154,
    "gn:feature_class":"P",
    "gn:feature_code":"PPL",
    "gn:name":"Gwangyangdong",
    "gn:population":0,
    "gn:timezone":"Asia/Seoul",
    "iso:country":"KR",
    "name:kor_x_preferred":[
        "\uad11\uc591\ub3d9"
    ],
    "name:und_x_variant":[
        "Kwangyang-dong",
        "Gwangyangdong"
    ],
    "wof:name":"Gwangyangdong",
    "wof:placetype":"locality"
},
  "geometry": {"coordinates":[128.8254,37.7814],"type":"Point"}
}