{
  "type": "Feature",
  "properties": {
    "gn:admin1_code":"12.0",
    "gn:asciiname":"Yuldo",
    "gn:country_code":"KR",
    "gn:dem":10,
    "gn:feature_class":"P",
    "gn:feature_code":"PPL",
    "gn:name":"Yuldo",
    "gn:population":0,
    "gn:timezone":"Asia/Seoul",
    "iso:country":"KR",
    "name:kor_x_preferred":[
        "\uc728\ub3c4"
    ],
    "name:und_x_variant":[
        "Yulto",
        "Yuldo"
    ],
    "wof:name":"Yuldo",
    "wof:placetype":"locality"
},
  "geometry": {"coordinates":[126.63212,37.50944000000001],"type":"Point"}
}