{
  "type": "Feature",
  "properties": {
    "gn:admin1_code":"3.0",
    "gn:asciiname":"Sinae",
    "gn:country_code":"KR",
    "gn:dem":269,
    "gn:feature_class":"P",
    "gn:feature_code":"PPL",
    "gn:name":"Sinae",
    "gn:population":0,
    "gn:timezone":"Asia/Seoul",
    "iso:country":"KR",
    "name:und_x_variant":[
        "\uc2dc\ub0b4",
        "Sinae"
    ],
    "wof:name":"Sinae",
    "wof:placetype":"locality"
},
  "geometry": {"coordinates":[127.3428,35.73755999999999],"type":"Point"}
}