{
  "type": "Feature",
  "properties": {
    "gn:admin1_code":"14.0",
    "gn:asciiname":"Wolgu",
    "gn:country_code":"KR",
    "gn:dem":386,
    "gn:feature_class":"P",
    "gn:feature_code":"PPL",
    "gn:name":"W\u014flgu",
    "gn:population":0,
    "gn:timezone":"Asia/Seoul",
    "iso:country":"KR",
    "name:und_x_variant":[
        "\uc6d4\uad6c",
        "W\u014flgu"
    ],
    "wof:name":"Wolgu",
    "wof:placetype":"locality"
},
  "geometry": {"coordinates":[129.02520000000001,36.7387],"type":"Point"}
}