{
  "type": "Feature",
  "properties": {
    "gn:admin1_code":"14.0",
    "gn:asciiname":"Maribogi",
    "gn:country_code":"KR",
    "gn:dem":164,
    "gn:feature_class":"P",
    "gn:feature_code":"PPL",
    "gn:name":"Maribogi",
    "gn:population":0,
    "gn:timezone":"Asia/Seoul",
    "iso:country":"KR",
    "name:und_x_variant":[
        "\ub9c8\ub9ac\ubcf4\uae30",
        "Maribogi"
    ],
    "wof:name":"Maribogi",
    "wof:placetype":"locality"
},
  "geometry": {"coordinates":[129.2903,36.5742],"type":"Point"}
}