{
  "type": "Feature",
  "properties": {
    "gn:admin1_code":"17.0",
    "gn:asciiname":"Song-gol",
    "gn:country_code":"KR",
    "gn:dem":152,
    "gn:feature_class":"P",
    "gn:feature_code":"PPL",
    "gn:name":"Song-gol",
    "gn:population":0,
    "gn:timezone":"Asia/Seoul",
    "iso:country":"KR",
    "name:und_x_variant":[
        "\uc1a1\uace8",
        "Song-gol"
    ],
    "wof:name":"Song-gol",
    "wof:placetype":"locality"
},
  "geometry": {"coordinates":[126.8593,36.4172],"type":"Point"}
}