{
  "type": "Feature",
  "properties": {
    "gn:admin1_code":"14.0",
    "gn:asciiname":"Nonusil",
    "gn:country_code":"KR",
    "gn:dem":95,
    "gn:feature_class":"P",
    "gn:feature_code":"PPL",
    "gn:name":"Non\u016dsil",
    "gn:population":0,
    "gn:timezone":"Asia/Seoul",
    "iso:country":"KR",
    "name:und_x_variant":[
        "\ub178\ub290\uc2e4",
        "Non\u016dsil"
    ],
    "wof:name":"Nonusil",
    "wof:placetype":"locality"
},
  "geometry": {"coordinates":[129.3751,36.7046],"type":"Point"}
}