{
  "type": "Feature",
  "properties": {
    "gn:admin1_code":"10.0",
    "gn:asciiname":"Bongha",
    "gn:country_code":"KR",
    "gn:dem":4,
    "gn:feature_class":"P",
    "gn:feature_code":"PPL",
    "gn:name":"Bongha",
    "gn:population":0,
    "gn:timezone":"Asia/Seoul",
    "iso:country":"KR",
    "name:kor_x_preferred":[
        "\ubd09\ud558"
    ],
    "wof:name":"Bongha",
    "wof:placetype":"locality"
},
  "geometry": {"coordinates":[128.89021,35.19654],"type":"Point"}
}