{
  "type": "Feature",
  "properties": {
    "gn:admin1_code":"13.0",
    "gn:asciiname":"Paeyang-ni",
    "gn:country_code":"KR",
    "gn:dem":56,
    "gn:feature_class":"P",
    "gn:feature_code":"PPLL",
    "gn:name":"Paeyang-ni",
    "gn:population":0,
    "gn:timezone":"Asia/Seoul",
    "iso:country":"KR",
    "name:und_x_variant":[
        "\ubc30\uc591\ub9ac",
        "Baeyang-ri",
        "Paeyang-ni"
    ],
    "wof:name":"Paeyang-ni",
    "wof:placetype":"locality"
},
  "geometry": {"coordinates":[126.98888999999998,37.2175],"type":"Point"}
}