{
  "type": "Feature",
  "properties": {
    "gn:admin1_code":"5.0",
    "gn:asciiname":"Jangbong",
    "gn:country_code":"KR",
    "gn:dem":95,
    "gn:feature_class":"P",
    "gn:feature_code":"PPL",
    "gn:name":"Jangbong",
    "gn:population":0,
    "gn:timezone":"Asia/Seoul",
    "iso:country":"KR",
    "name:kor_x_preferred":[
        "\uc7a5\ubd09"
    ],
    "wof:name":"Jangbong",
    "wof:placetype":"locality"
},
  "geometry": {"coordinates":[127.61579999999999,36.76354],"type":"Point"}
}