{
  "type": "Feature",
  "properties": {
    "gn:admin1_code":"5.0",
    "gn:asciiname":"Manji",
    "gn:country_code":"KR",
    "gn:dem":200,
    "gn:feature_class":"P",
    "gn:feature_code":"PPL",
    "gn:name":"Manji",
    "gn:population":0,
    "gn:timezone":"Asia/Seoul",
    "iso:country":"KR",
    "name:ceb_x_preferred":[
        "Manji"
    ],
    "name:deu_x_preferred":[
        "Manji"
    ],
    "name:fra_x_preferred":[
        "Manji"
    ],
    "name:ita_x_preferred":[
        "Manji"
    ],
    "name:jpn_x_preferred":[
        "\u534d"
    ],
    "name:kor_x_preferred":[
        "\ub9cc\uc9c0"
    ],
    "wof:name":"Manji",
    "wof:placetype":"locality"
},
  "geometry": {"coordinates":[128.07148999999998,36.99967],"type":"Point"}
}