{
  "type": "Feature",
  "properties": {
    "gn:admin1_code":"16.0",
    "gn:asciiname":"Waryong",
    "gn:country_code":"KR",
    "gn:dem":19,
    "gn:feature_class":"P",
    "gn:feature_code":"PPL",
    "gn:name":"Waryong",
    "gn:population":0,
    "gn:timezone":"Asia/Seoul",
    "iso:country":"KR",
    "name:kor_x_preferred":[
        "\uc640\ub8e1"
    ],
    "wof:name":"Waryong",
    "wof:placetype":"locality"
},
  "geometry": {"coordinates":[126.75409000000001,34.96394],"type":"Point"}
}