{
  "type": "Feature",
  "properties": {
    "gn:admin1_code":"12.0",
    "gn:asciiname":"Tonggae",
    "gn:country_code":"KR",
    "gn:dem":15,
    "gn:feature_class":"P",
    "gn:feature_code":"PPL",
    "gn:name":"Tonggae",
    "gn:population":0,
    "gn:timezone":"Asia/Seoul",
    "iso:country":"KR",
    "name:und_x_variant":[
        "\ud1b5\uac1c",
        "T\u2019onggae",
        "Tonggae"
    ],
    "wof:name":"Tonggae",
    "wof:placetype":"locality"
},
  "geometry": {"coordinates":[126.37268,37.46744],"type":"Point"}
}