{
  "type": "Feature",
  "properties": {
    "gn:admin1_code":"13.0",
    "gn:asciiname":"Karumul",
    "gn:country_code":"KR",
    "gn:dem":22,
    "gn:feature_class":"P",
    "gn:feature_code":"PPL",
    "gn:name":"Karumul",
    "gn:population":0,
    "gn:timezone":"Asia/Seoul",
    "iso:country":"KR",
    "name:kor_x_preferred":[
        "\uac08\uc6b0\ubb3c"
    ],
    "wof:name":"Karumul",
    "wof:placetype":"locality"
},
  "geometry": {"coordinates":[126.82111,37.04917],"type":"Point"}
}