{
  "type": "Feature",
  "properties": {
    "gn:admin1_code":"16.0",
    "gn:asciiname":"Ch'ongbi",
    "gn:country_code":"KR",
    "gn:dem":9,
    "gn:feature_class":"P",
    "gn:feature_code":"PPL",
    "gn:name":"Ch\u2019\u014fngbi",
    "gn:population":0,
    "gn:timezone":"Asia/Seoul",
    "iso:country":"KR",
    "name:kor_x_preferred":[
        "Ch\u2019\u014fngbi"
    ],
    "wof:name":"Ch'ongbi",
    "wof:placetype":"locality"
},
  "geometry": {"coordinates":[126.72806,34.36472],"type":"Point"}
}