{
  "type": "Feature",
  "properties": {
    "gn:admin1_code":"13.0",
    "gn:asciiname":"Saegaraeul",
    "gn:country_code":"KR",
    "gn:dem":121,
    "gn:feature_class":"P",
    "gn:feature_code":"PPL",
    "gn:name":"Saegaraeul",
    "gn:population":0,
    "gn:timezone":"Asia/Seoul",
    "iso:country":"KR",
    "name:kor_x_preferred":[
        "\uc0c8\uac00\ub798\uc6b8"
    ],
    "wof:name":"Saegaraeul",
    "wof:placetype":"locality"
},
  "geometry": {"coordinates":[127.55195000000001,37.13191],"type":"Point"}
}