{
  "type": "Feature",
  "properties": {
    "gn:admin1_code":"3.0",
    "gn:asciiname":"Wolgye",
    "gn:country_code":"KR",
    "gn:dem":271,
    "gn:feature_class":"P",
    "gn:feature_code":"PPL",
    "gn:name":"W\u014flgye",
    "gn:population":0,
    "gn:timezone":"Asia/Seoul",
    "iso:country":"KR",
    "name:und_x_variant":[
        "\uc6d4\uacc4",
        "W\u014flgye"
    ],
    "wof:name":"Wolgye",
    "wof:placetype":"locality"
},
  "geometry": {"coordinates":[127.48683,35.93698],"type":"Point"}
}