{
  "type": "Feature",
  "properties": {
    "gn:admin1_code":"16.0",
    "gn:asciiname":"Hupo",
    "gn:country_code":"KR",
    "gn:dem":29,
    "gn:feature_class":"P",
    "gn:feature_code":"PPL",
    "gn:name":"Hupo",
    "gn:population":0,
    "gn:timezone":"Asia/Seoul",
    "iso:country":"KR",
    "name:kor_x_preferred":[
        "\ud6c4\ud3ec"
    ],
    "name:und_x_variant":[
        "Huha-ri",
        "Hup\u2019o",
        "Hupo"
    ],
    "wof:name":"Hupo",
    "wof:placetype":"locality"
},
  "geometry": {"coordinates":[126.28115,34.70703],"type":"Point"}
}