{
  "type": "Feature",
  "properties": {
    "gn:admin1_code":"17.0",
    "gn:asciiname":"Baegamdong",
    "gn:country_code":"KR",
    "gn:dem":180,
    "gn:feature_class":"P",
    "gn:feature_code":"PPL",
    "gn:name":"Baegamdong",
    "gn:population":0,
    "gn:timezone":"Asia/Seoul",
    "iso:country":"KR",
    "name:und_x_variant":[
        "Paegam-ni",
        "Paegam-dong",
        "\ubc31\uc554\ub3d9",
        "Baegamdong"
    ],
    "wof:name":"Baegamdong",
    "wof:placetype":"locality"
},
  "geometry": {"coordinates":[127.22028,36.32417],"type":"Point"}
}