{
  "type": "Feature",
  "properties": {
    "gn:admin1_code":"6.0",
    "gn:asciiname":"Somok",
    "gn:country_code":"KR",
    "gn:dem":242,
    "gn:feature_class":"P",
    "gn:feature_code":"PPL",
    "gn:name":"Somok",
    "gn:population":0,
    "gn:timezone":"Asia/Seoul",
    "iso:country":"KR",
    "name:kor_x_preferred":[
        "\uc18c\ubaa9"
    ],
    "wof:name":"Somok",
    "wof:placetype":"locality"
},
  "geometry": {"coordinates":[128.34569999999999,37.2676],"type":"Point"}
}