{
  "type": "Feature",
  "properties": {
    "gn:admin1_code":"17.0",
    "gn:asciiname":"Kung-gol",
    "gn:country_code":"KR",
    "gn:dem":18,
    "gn:feature_class":"P",
    "gn:feature_code":"PPL",
    "gn:name":"Kung-gol",
    "gn:population":0,
    "gn:timezone":"Asia/Seoul",
    "iso:country":"KR",
    "name:und_x_variant":[
        "\uad81\uace8",
        "Kung-gol"
    ],
    "wof:name":"Kung-gol",
    "wof:placetype":"locality"
},
  "geometry": {"coordinates":[126.90900000000001,36.8027],"type":"Point"}
}