{
  "type": "Feature",
  "properties": {
    "gn:admin1_code":"6.0",
    "gn:asciiname":"Sagimak",
    "gn:country_code":"KR",
    "gn:dem":45,
    "gn:feature_class":"P",
    "gn:feature_code":"PPL",
    "gn:name":"Sagimak",
    "gn:population":0,
    "gn:timezone":"Asia/Seoul",
    "iso:country":"KR",
    "name:kor_x_preferred":[
        "\uc0ac\uae30\ub9c9"
    ],
    "wof:name":"Sagimak",
    "wof:placetype":"locality"
},
  "geometry": {"coordinates":[128.99250000000001,37.6189],"type":"Point"}
}