{
  "type": "Feature",
  "properties": {
    "gn:admin1_code":"17.0",
    "gn:asciiname":"Kaul",
    "gn:country_code":"KR",
    "gn:dem":29,
    "gn:feature_class":"P",
    "gn:feature_code":"PPL",
    "gn:name":"Kaul",
    "gn:population":0,
    "gn:timezone":"Asia/Seoul",
    "iso:country":"KR",
    "name:und_x_variant":[
        "\uac00\uc6b8",
        "Kaul"
    ],
    "wof:name":"Kaul",
    "wof:placetype":"locality"
},
  "geometry": {"coordinates":[126.7385,36.8391],"type":"Point"}
}