{
  "type": "Feature",
  "properties": {
    "gn:admin1_code":"14.0",
    "gn:asciiname":"Yongbawi",
    "gn:country_code":"KR",
    "gn:dem":296,
    "gn:feature_class":"P",
    "gn:feature_code":"PPL",
    "gn:name":"Yongbawi",
    "gn:population":0,
    "gn:timezone":"Asia/Seoul",
    "iso:country":"KR",
    "name:kor_x_preferred":[
        "\uc6a9\ubc14\uc704"
    ],
    "name:kor_x_variant":[
        "\uc6a9\ubc14\uc6b0"
    ],
    "name:und_x_variant":[
        "Yongbau"
    ],
    "wof:name":"Yongbawi",
    "wof:placetype":"locality"
},
  "geometry": {"coordinates":[128.68036000000001,36.96703],"type":"Point"}
}