{
  "type": "Feature",
  "properties": {
    "gn:admin1_code":"17.0",
    "gn:asciiname":"Changgot'o",
    "gn:country_code":"KR",
    "gn:dem":181,
    "gn:feature_class":"P",
    "gn:feature_code":"PPL",
    "gn:name":"Changgot\u2019\u014f",
    "gn:population":0,
    "gn:timezone":"Asia/Seoul",
    "iso:country":"KR",
    "name:und_x_variant":[
        "Changgoch\u2019i",
        "Changgot\u2019\u014f",
        "\uc7a5\uace0\ud130"
    ],
    "wof:name":"Changgot'o",
    "wof:placetype":"locality"
},
  "geometry": {"coordinates":[127.3159,36.1614],"type":"Point"}
}