{
  "type": "Feature",
  "properties": {
    "gn:admin1_code":"20.0",
    "gn:asciiname":"Wolmi",
    "gn:country_code":"KR",
    "gn:dem":85,
    "gn:feature_class":"P",
    "gn:feature_code":"PPL",
    "gn:name":"Wolmi",
    "gn:population":0,
    "gn:timezone":"Asia/Seoul",
    "iso:country":"KR",
    "name:und_x_variant":[
        "\uc6d4\ubbf8",
        "W\u014flmi",
        "Wolmi"
    ],
    "wof:name":"Wolmi",
    "wof:placetype":"locality"
},
  "geometry": {"coordinates":[128.52176,35.57257],"type":"Point"}
}