{
  "type": "Feature",
  "properties": {
    "gn:admin1_code":"13.0",
    "gn:asciiname":"Nuchon",
    "gn:country_code":"KR",
    "gn:dem":12,
    "gn:feature_class":"P",
    "gn:feature_code":"PPL",
    "gn:name":"Nuchon",
    "gn:population":0,
    "gn:timezone":"Asia/Seoul",
    "iso:country":"KR",
    "name:kor_x_preferred":[
        "\ub204\ucd0c"
    ],
    "name:kor_x_variant":[
        "Nuch\u2019on"
    ],
    "wof:name":"Nuchon",
    "wof:placetype":"locality"
},
  "geometry": {"coordinates":[126.64496,37.67796],"type":"Point"}
}