{
  "type": "Feature",
  "properties": {
    "gn:admin1_code":"3.0",
    "gn:asciiname":"Nongso-ri",
    "gn:country_code":"KR",
    "gn:dem":455,
    "gn:feature_class":"P",
    "gn:feature_code":"PPL",
    "gn:name":"Nongso-ri",
    "gn:population":0,
    "gn:timezone":"Asia/Seoul",
    "iso:country":"KR",
    "name:und_x_variant":[
        "\ub18d\uc18c\ub9ac",
        "Nongso-ri"
    ],
    "wof:name":"Nongso-ri",
    "wof:placetype":"locality"
},
  "geometry": {"coordinates":[127.61216,35.7724],"type":"Point"}
}