{
  "type": "Feature",
  "properties": {
    "gn:admin1_code":"6.0",
    "gn:asciiname":"Yongsugol",
    "gn:country_code":"KR",
    "gn:dem":11,
    "gn:feature_class":"P",
    "gn:feature_code":"PPL",
    "gn:name":"Yongsugol",
    "gn:population":0,
    "gn:timezone":"Asia/Seoul",
    "iso:country":"KR",
    "name:kor_x_preferred":[
        "\uc6a9\uc218\uace8"
    ],
    "wof:name":"Yongsugol",
    "wof:placetype":"locality"
},
  "geometry": {"coordinates":[128.74886999999998,37.98442],"type":"Point"}
}