{
  "type": "Feature",
  "properties": {
    "gn:admin1_code":"5.0",
    "gn:asciiname":"Gamadong",
    "gn:country_code":"KR",
    "gn:dem":204,
    "gn:feature_class":"P",
    "gn:feature_code":"PPL",
    "gn:name":"Gamadong",
    "gn:population":0,
    "gn:timezone":"Asia/Seoul",
    "iso:country":"KR",
    "name:kor_x_preferred":[
        "\uac00\ub9c8\ub3d9"
    ],
    "wof:name":"Gamadong",
    "wof:placetype":"locality"
},
  "geometry": {"coordinates":[128.29329999999999,36.95688],"type":"Point"}
}