{
  "type": "Feature",
  "properties": {
    "gn:admin1_code":"14.0",
    "gn:asciiname":"Jeokseongmaeul",
    "gn:country_code":"KR",
    "gn:dem":11,
    "gn:feature_class":"P",
    "gn:feature_code":"PPL",
    "gn:name":"Jeokseongmaeul",
    "gn:population":0,
    "gn:timezone":"Asia/Seoul",
    "iso:country":"KR",
    "name:kor_x_preferred":[
        "\uc801\uc11d\ub9c8\uc744"
    ],
    "wof:name":"Jeokseongmaeul",
    "wof:placetype":"locality"
},
  "geometry": {"coordinates":[129.51476,35.8437],"type":"Point"}
}