{
  "type": "Feature",
  "properties": {
    "gn:admin1_code":"13.0",
    "gn:asciiname":"Hwarangpo",
    "gn:country_code":"KR",
    "gn:dem":45,
    "gn:feature_class":"P",
    "gn:feature_code":"PPL",
    "gn:name":"Hwarangpo",
    "gn:population":0,
    "gn:timezone":"Asia/Seoul",
    "iso:country":"KR",
    "name:kor_x_preferred":[
        "\ud654\ub791\ud3ec"
    ],
    "name:und_x_variant":[
        "\ud654\ub791\ud3ec",
        "Hwarangp\u2019o",
        "Hwarangpo"
    ],
    "wof:name":"Hwarangpo",
    "wof:placetype":"locality"
},
  "geometry": {"coordinates":[127.378,37.6806],"type":"Point"}
}