{
  "type": "Feature",
  "properties": {
    "gn:admin1_code":"17.0",
    "gn:asciiname":"Kunamch'ang",
    "gn:country_code":"KR",
    "gn:dem":16,
    "gn:feature_class":"P",
    "gn:feature_code":"PPL",
    "gn:name":"Kunamch\u2019ang",
    "gn:population":0,
    "gn:timezone":"Asia/Seoul",
    "iso:country":"KR",
    "name:und_x_variant":[
        "\uad6c\ub0a8\ucc3d",
        "Kunamch\u2019ang"
    ],
    "wof:name":"Kunamch'ang",
    "wof:placetype":"locality"
},
  "geometry": {"coordinates":[126.60469999999999,36.4846],"type":"Point"}
}