{
  "type": "Feature",
  "properties": {
    "gn:admin1_code":"5.0",
    "gn:asciiname":"Tongi",
    "gn:country_code":"KR",
    "gn:dem":107,
    "gn:feature_class":"P",
    "gn:feature_code":"PPL",
    "gn:name":"Tongi",
    "gn:population":0,
    "gn:timezone":"Asia/Seoul",
    "iso:country":"KR",
    "name:bar_x_preferred":[
        "Tongi"
    ],
    "name:ben_x_preferred":[
        "\u099f\u0999\u09cd\u0997\u09c0"
    ],
    "name:ceb_x_preferred":[
        "Tungi"
    ],
    "name:dan_x_preferred":[
        "Tongi"
    ],
    "name:deu_x_preferred":[
        "Tongi"
    ],
    "name:ell_x_preferred":[
        "\u03a4\u03cc\u03bd\u03b3\u03ba\u03b9"
    ],
    "name:epo_x_preferred":[
        "Tongi"
    ],
    "name:fin_x_preferred":[
        "Tongi"
    ],
    "name:fra_x_preferred":[
        "Tongi"
    ],
    "name:heb_x_preferred":[
        "\u05d8\u05d5\u05e0\u05d2\u05d9"
    ],
    "name:jpn_x_preferred":[
        "\u30c8\u30f3\u30ae"
    ],
    "name:kaz_x_preferred":[
        "\u0422\u043e\u043d\u0433\u0438"
    ],
    "name:lit_x_preferred":[
        "Tungis"
    ],
    "name:pol_x_preferred":[
        "Tongi"
    ],
    "name:rus_x_preferred":[
        "\u0422\u043e\u043d\u0433\u0438"
    ],
    "name:swe_x_preferred":[
        "Tongi"
    ],
    "name:und_x_variant":[
        "\ub3d9\uc774",
        "Tongi"
    ],
    "name:war_x_preferred":[
        "Tongi"
    ],
    "wof:name":"Tongi",
    "wof:placetype":"locality"
},
  "geometry": {"coordinates":[127.6199,36.2844],"type":"Point"}
}