{
  "type": "Feature",
  "properties": {
    "gn:admin1_code":"5.0",
    "gn:asciiname":"Tongi",
    "gn:country_code":"KR",
    "gn:dem":107,
    "gn:feature_class":"P",
    "gn:feature_code":"PPL",
    "gn:name":"Tongi",
    "gn:population":0,
    "gn:timezone":"Asia/Seoul",
    "iso:country":"KR",
    "name:und_x_variant":[
        "\ub3d9\uc774",
        "Tongi"
    ],
    "wof:name":"Tongi",
    "wof:placetype":"locality"
},
  "geometry": {"coordinates":[127.6199,36.2844],"type":"Point"}
}