{
  "type": "Feature",
  "properties": {
    "gn:admin1_code":"20.0",
    "gn:asciiname":"Sinbal-li",
    "gn:cc2":"KR",
    "gn:country_code":"KR",
    "gn:dem":26,
    "gn:feature_class":"P",
    "gn:feature_code":"PPL",
    "gn:name":"Sinbal-li",
    "gn:population":0,
    "gn:timezone":"Asia/Seoul",
    "iso:country":"KR",
    "name:und_x_variant":[
        "Shinhan-ri",
        "Shinban-ni",
        "Sinban-ni",
        "Sinbal-li"
    ],
    "wof:name":"Sinbal-li",
    "wof:placetype":"locality"
},
  "geometry": {"coordinates":[128.32277999999999,35.46694],"type":"Point"}
}