{
  "type": "Feature",
  "properties": {
    "gn:admin1_code":"20.0",
    "gn:asciiname":"Modan",
    "gn:country_code":"KR",
    "gn:dem":47,
    "gn:feature_class":"P",
    "gn:feature_code":"PPL",
    "gn:name":"Modan",
    "gn:population":0,
    "gn:timezone":"Asia/Seoul",
    "iso:country":"KR",
    "name:und_x_variant":[
        "\ubabb\uc548",
        "Modan"
    ],
    "wof:name":"Modan",
    "wof:placetype":"locality"
},
  "geometry": {"coordinates":[128.36607000000001,34.96745],"type":"Point"}
}