{
  "type": "Feature",
  "properties": {
    "gn:admin1_code":"13.0",
    "gn:asciiname":"Ttalgiwon",
    "gn:country_code":"KR",
    "gn:dem":81,
    "gn:feature_class":"P",
    "gn:feature_code":"PPL",
    "gn:name":"Ttalgiwon",
    "gn:population":0,
    "gn:timezone":"Asia/Seoul",
    "iso:country":"KR",
    "name:kor_x_preferred":[
        "\ub538\uae30\uc6d0"
    ],
    "wof:name":"Ttalgiwon",
    "wof:placetype":"locality"
},
  "geometry": {"coordinates":[127.12067,37.60255],"type":"Point"}
}