{
  "type": "Feature",
  "properties": {
    "gn:admin1_code":"13.0",
    "gn:admin2_code":"P'aju-si",
    "gn:asciiname":"Heogidong",
    "gn:country_code":"KR",
    "gn:dem":59,
    "gn:feature_class":"P",
    "gn:feature_code":"PPL",
    "gn:name":"Heogidong",
    "gn:population":0,
    "gn:timezone":"Asia/Seoul",
    "iso:country":"KR",
    "name:kor_x_preferred":[
        "\ud5c8\uae30\ub3d9"
    ],
    "name:und_x_variant":[
        "Hagi-dong"
    ],
    "wof:name":"Heogidong",
    "wof:placetype":"locality"
},
  "geometry": {"coordinates":[126.8596,37.83935],"type":"Point"}
}