{
  "type": "Feature",
  "properties": {
    "gn:admin1_code":"14.0",
    "gn:asciiname":"Heungmunjeong",
    "gn:country_code":"KR",
    "gn:dem":240,
    "gn:feature_class":"P",
    "gn:feature_code":"PPL",
    "gn:name":"Heungmunjeong",
    "gn:population":0,
    "gn:timezone":"Asia/Seoul",
    "iso:country":"KR",
    "name:kor_x_preferred":[
        "\ud765\ubb38\uc815"
    ],
    "name:und_x_variant":[
        "Hongmunj\u014fng"
    ],
    "wof:name":"Heungmunjeong",
    "wof:placetype":"locality"
},
  "geometry": {"coordinates":[128.01946999999998,36.69602],"type":"Point"}
}