{
  "type": "Feature",
  "properties": {
    "gn:admin1_code":"13.0",
    "gn:asciiname":"Saemal",
    "gn:country_code":"KR",
    "gn:dem":111,
    "gn:feature_class":"P",
    "gn:feature_code":"PPL",
    "gn:name":"Saemal",
    "gn:population":0,
    "gn:timezone":"Asia/Seoul",
    "iso:country":"KR",
    "name:kor_x_preferred":[
        "\uc0c8\ub9d0"
    ],
    "name:und_x_variant":[
        "\uc2e0\ucd0c",
        "Sin-ch\u2019on",
        "Saemal"
    ],
    "wof:name":"Saemal",
    "wof:placetype":"locality"
},
  "geometry": {"coordinates":[127.1707,37.7627],"type":"Point"}
}