{
  "type": "Feature",
  "properties": {
    "gn:admin1_code":"14.0",
    "gn:asciiname":"Samgo-ri",
    "gn:country_code":"KR",
    "gn:dem":289,
    "gn:feature_class":"P",
    "gn:feature_code":"PPL",
    "gn:name":"Samg\u014f-ri",
    "gn:population":0,
    "gn:timezone":"Asia/Seoul",
    "iso:country":"KR",
    "name:und_x_variant":[
        "\uc0bc\uac70\ub9ac",
        "Samg\u014f-ri"
    ],
    "wof:name":"Samgo-ri",
    "wof:placetype":"locality"
},
  "geometry": {"coordinates":[128.23421000000002,35.85735],"type":"Point"}
}