{
  "type": "Feature",
  "properties": {
    "gn:admin1_code":"3.0",
    "gn:asciiname":"Kunnam",
    "gn:country_code":"KR",
    "gn:dem":26,
    "gn:feature_class":"P",
    "gn:feature_code":"PPL",
    "gn:name":"K\u016dnnam",
    "gn:population":0,
    "gn:timezone":"Asia/Seoul",
    "iso:country":"KR",
    "name:und_x_variant":[
        "\uadfc\ub0a8",
        "K\u016dnnam"
    ],
    "wof:name":"Kunnam",
    "wof:placetype":"locality"
},
  "geometry": {"coordinates":[127.06142,35.96449000000001],"type":"Point"}
}