{
  "type": "Feature",
  "properties": {
    "gn:admin1_code":"6.0",
    "gn:asciiname":"Jomakdong",
    "gn:country_code":"KR",
    "gn:dem":318,
    "gn:feature_class":"P",
    "gn:feature_code":"PPL",
    "gn:name":"Jomakdong",
    "gn:population":0,
    "gn:timezone":"Asia/Seoul",
    "iso:country":"KR",
    "name:kor_x_preferred":[
        "\uc870\ub9c9\ub3d9"
    ],
    "wof:name":"Jomakdong",
    "wof:placetype":"locality"
},
  "geometry": {"coordinates":[127.41798,38.16077],"type":"Point"}
}