{
  "type": "Feature",
  "properties": {
    "gn:admin1_code":"6.0",
    "gn:admin2_code":"Samch'\u014fk-si",
    "gn:asciiname":"Kallam",
    "gn:country_code":"KR",
    "gn:dem":8,
    "gn:feature_class":"P",
    "gn:feature_code":"PPL",
    "gn:name":"Kallam",
    "gn:population":0,
    "gn:timezone":"Asia/Seoul",
    "iso:country":"KR",
    "name:und_x_variant":[
        "Kalsan",
        "Kallam"
    ],
    "wof:name":"Kallam",
    "wof:placetype":"locality"
},
  "geometry": {"coordinates":[129.32943999999998,37.27889],"type":"Point"}
}