{
  "type": "Feature",
  "properties": {
    "gn:admin1_code":"6.0",
    "gn:asciiname":"Yangjich'on",
    "gn:country_code":"KR",
    "gn:dem":245,
    "gn:feature_class":"P",
    "gn:feature_code":"PPL",
    "gn:name":"Yangjich\u2019on",
    "gn:population":0,
    "gn:timezone":"Asia/Seoul",
    "iso:country":"KR",
    "name:kor_x_preferred":[
        "\uc591\uc9c0\ucd0c"
    ],
    "name:kor_x_variant":[
        "Yangjich\u2019on"
    ],
    "wof:name":"Yangjich'on",
    "wof:placetype":"locality"
},
  "geometry": {"coordinates":[128.1018,37.51],"type":"Point"}
}