{
  "type": "Feature",
  "properties": {
    "gn:admin1_code":"20.0",
    "gn:asciiname":"Sangch'on",
    "gn:country_code":"KR",
    "gn:dem":311,
    "gn:feature_class":"P",
    "gn:feature_code":"PPL",
    "gn:name":"Sangch\u2019\u014fn",
    "gn:population":0,
    "gn:timezone":"Asia/Seoul",
    "iso:country":"KR",
    "name:und_x_variant":[
        "\uc0c1\ucc9c",
        "Sangch\u2019\u014fn"
    ],
    "wof:name":"Sangch'on",
    "wof:placetype":"locality"
},
  "geometry": {"coordinates":[127.82249,35.74593],"type":"Point"}
}