{
  "type": "Feature",
  "properties": {
    "gn:admin1_code":"16.0",
    "gn:asciiname":"Mok-kol",
    "gn:country_code":"KR",
    "gn:dem":43,
    "gn:feature_class":"P",
    "gn:feature_code":"PPL",
    "gn:name":"Mok-kol",
    "gn:population":0,
    "gn:timezone":"Asia/Seoul",
    "iso:country":"KR",
    "name:kor_x_preferred":[
        "\ubaa9\uace8"
    ],
    "wof:name":"Mok-kol",
    "wof:placetype":"locality"
},
  "geometry": {"coordinates":[127.0938,34.69264],"type":"Point"}
}