{
  "type": "Feature",
  "properties": {
    "gn:admin1_code":"16.0",
    "gn:asciiname":"Heungnyongdong",
    "gn:country_code":"KR",
    "gn:dem":27,
    "gn:feature_class":"P",
    "gn:feature_code":"PPL",
    "gn:name":"Heungnyongdong",
    "gn:population":0,
    "gn:timezone":"Asia/Seoul",
    "iso:country":"KR",
    "name:kor_x_preferred":[
        "\ud765\ub8e1\ub3d9"
    ],
    "wof:name":"Heungnyongdong",
    "wof:placetype":"locality"
},
  "geometry": {"coordinates":[126.71243,35.0179],"type":"Point"}
}