{
  "type": "Feature",
  "properties": {
    "gn:admin1_code":"10.0",
    "gn:asciiname":"Midong",
    "gn:country_code":"KR",
    "gn:dem":126,
    "gn:feature_class":"P",
    "gn:feature_code":"PPL",
    "gn:name":"Midong",
    "gn:population":0,
    "gn:timezone":"Asia/Seoul",
    "iso:country":"KR",
    "name:kor_x_preferred":[
        "\ubbf8\ub3d9"
    ],
    "wof:name":"Midong",
    "wof:placetype":"locality"
},
  "geometry": {"coordinates":[129.17087000000001,35.28688],"type":"Point"}
}