{
  "type": "Feature",
  "properties": {
    "gn:admin1_code":"14.0",
    "gn:asciiname":"Taegok",
    "gn:country_code":"KR",
    "gn:dem":468,
    "gn:feature_class":"P",
    "gn:feature_code":"PPL",
    "gn:name":"Taegok",
    "gn:population":0,
    "gn:timezone":"Asia/Seoul",
    "iso:country":"KR",
    "name:und_x_variant":[
        "\ub300\uace1",
        "Taegok"
    ],
    "wof:name":"Taegok",
    "wof:placetype":"locality"
},
  "geometry": {"coordinates":[129.0438,36.8464],"type":"Point"}
}