{
  "type": "Feature",
  "properties": {
    "gn:admin1_code":"14.0",
    "gn:asciiname":"Gamusil",
    "gn:country_code":"KR",
    "gn:dem":51,
    "gn:feature_class":"P",
    "gn:feature_code":"PPL",
    "gn:name":"Gamusil",
    "gn:population":0,
    "gn:timezone":"Asia/Seoul",
    "iso:country":"KR",
    "name:kor_x_preferred":[
        "\uac00\ubb34\uc2e4"
    ],
    "wof:name":"Gamusil",
    "wof:placetype":"locality"
},
  "geometry": {"coordinates":[128.53218000000001,35.9376],"type":"Point"}
}