{
  "type": "Feature",
  "properties": {
    "gn:admin1_code":"13.0",
    "gn:asciiname":"Anseombu-ri",
    "gn:country_code":"KR",
    "gn:dem":173,
    "gn:feature_class":"P",
    "gn:feature_code":"PPL",
    "gn:name":"Anseombu-ri",
    "gn:population":0,
    "gn:timezone":"Asia/Seoul",
    "iso:country":"KR",
    "name:und_x_variant":[
        "\uc548\uc12c\ubd80\ub9ac",
        "Anseombu-ri",
        "Ans\u014fmbu-ri"
    ],
    "wof:name":"Anseombu-ri",
    "wof:placetype":"locality"
},
  "geometry": {"coordinates":[127.65000000000001,37.45694],"type":"Point"}
}