{
  "type": "Feature",
  "properties": {
    "gn:admin1_code":"6.0",
    "gn:asciiname":"P'ungsuwon",
    "gn:country_code":"KR",
    "gn:dem":342,
    "gn:feature_class":"P",
    "gn:feature_code":"PPL",
    "gn:name":"P\u2019ungsuw\u014fn",
    "gn:population":0,
    "gn:timezone":"Asia/Seoul",
    "iso:country":"KR",
    "name:kor_x_preferred":[
        "\ud48d\uc218\uc6d0"
    ],
    "name:kor_x_variant":[
        "P\u2019ungsuw\u014fn"
    ],
    "wof:name":"P'ungsuwon",
    "wof:placetype":"locality"
},
  "geometry": {"coordinates":[127.81780000000001,37.5292],"type":"Point"}
}