{
  "type": "Feature",
  "properties": {
    "gn:admin1_code":"14.0",
    "gn:asciiname":"Monmit",
    "gn:country_code":"KR",
    "gn:dem":29,
    "gn:feature_class":"P",
    "gn:feature_code":"PPL",
    "gn:name":"Monmit",
    "gn:population":0,
    "gn:timezone":"Asia/Seoul",
    "iso:country":"KR",
    "name:kor_x_preferred":[
        "\ubabb\ubc11"
    ],
    "wof:name":"Monmit",
    "wof:placetype":"locality"
},
  "geometry": {"coordinates":[129.33420000000001,36.13503],"type":"Point"}
}