{
  "type": "Feature",
  "properties": {
    "gn:admin1_code":"0.0",
    "gn:asciiname":"Jitsuhei-ri",
    "gn:country_code":"KR",
    "gn:dem":299,
    "gn:feature_class":"P",
    "gn:feature_code":"PPL",
    "gn:name":"Jitsuhei-ri",
    "gn:population":0,
    "gn:timezone":"Asia/Seoul",
    "iso:country":"KR",
    "name:und_x_variant":[
        "Iepyung-ri",
        "Ilp\u2019y\u014fng-ni",
        "Ilp\u2019y\u014fng-ch\u2019on"
    ],
    "wof:name":"Jitsuhei-ri",
    "wof:placetype":"locality"
},
  "geometry": {"coordinates":[126.83333,35.33333],"type":"Point"}
}