{
  "type": "Feature",
  "properties": {
    "gn:admin1_code":"13.0",
    "gn:asciiname":"Taebong",
    "gn:country_code":"KR",
    "gn:dem":97,
    "gn:feature_class":"P",
    "gn:feature_code":"PPL",
    "gn:name":"Taebong",
    "gn:population":0,
    "gn:timezone":"Asia/Seoul",
    "iso:country":"KR",
    "name:kor_x_preferred":[
        "\ud0dc\ubd09"
    ],
    "wof:name":"Taebong",
    "wof:placetype":"locality"
},
  "geometry": {"coordinates":[127.25584000000001,37.97216],"type":"Point"}
}