{
  "type": "Feature",
  "properties": {
    "gn:admin1_code":"13.0",
    "gn:asciiname":"Taebong",
    "gn:country_code":"KR",
    "gn:dem":97,
    "gn:feature_class":"P",
    "gn:feature_code":"PPL",
    "gn:name":"Taebong",
    "gn:population":0,
    "gn:timezone":"Asia/Seoul",
    "iso:country":"KR",
    "name:ast_x_preferred":[
        "Taebong"
    ],
    "name:azb_x_preferred":[
        "\u06cc\u0626\u0646\u06cc \u0642\u0648\u0642\u0648\u0631\u06cc\u0648"
    ],
    "name:ckb_x_preferred":[
        "\u062a\u0627\u06cc\u0628\u06c6\u0646\u06af"
    ],
    "name:dan_x_preferred":[
        "Taebong"
    ],
    "name:fas_x_preferred":[
        "\u06af\u0648\u06af\u0648\u0631\u06cc\u0648 \u062c\u062f\u06cc\u062f"
    ],
    "name:ind_x_preferred":[
        "Taebong"
    ],
    "name:jpn_x_preferred":[
        "\u5f8c\u9ad8\u53e5\u9e97"
    ],
    "name:kat_x_preferred":[
        "\u10e2\u10ee\u10d4\u10d1\u10dd\u10dc\u10d8"
    ],
    "name:kor_x_preferred":[
        "\ud0dc\ubd09"
    ],
    "name:nor_x_preferred":[
        "Taebong"
    ],
    "name:rus_x_preferred":[
        "\u0422\u0445\u044d\u0431\u043e\u043d"
    ],
    "name:sin_x_preferred":[
        "\u0dad\u0dda\u0db6\u0ddc\u0d82"
    ],
    "name:slk_x_preferred":[
        "Tch\u00e4bong"
    ],
    "name:spa_x_preferred":[
        "Taebong"
    ],
    "name:tha_x_preferred":[
        "\u0e2d\u0e32\u0e13\u0e32\u0e08\u0e31\u0e01\u0e23\u0e42\u0e04\u0e01\u0e39\u0e23\u0e22\u0e2d\u0e43\u0e2b\u0e21\u0e48"
    ],
    "name:tur_x_preferred":[
        "Taebong"
    ],
    "name:ukr_x_preferred":[
        "\u0422\u0445\u0435\u0431\u043e\u043d"
    ],
    "name:vie_x_preferred":[
        "Th\u00e1i Phong"
    ],
    "name:zho_x_preferred":[
        "\u5f8c\u9ad8\u53e5\u9e97"
    ],
    "wof:name":"Taebong",
    "wof:placetype":"locality"
},
  "geometry": {"coordinates":[127.25584000000001,37.97216],"type":"Point"}
}