{
  "type": "Feature",
  "properties": {
    "gn:admin1_code":"11.0",
    "gn:asciiname":"Sindang-dong",
    "gn:country_code":"KR",
    "gn:dem":33,
    "gn:feature_class":"P",
    "gn:feature_code":"PPL",
    "gn:name":"Sindang-dong",
    "gn:population":0,
    "gn:timezone":"Asia/Seoul",
    "iso:country":"KR",
    "name:ceb_x_preferred":[
        "Sindang-dong"
    ],
    "name:jpn_x_preferred":[
        "\u65b0\u5802\u6d1e"
    ],
    "name:kor_x_preferred":[
        "\uc2e0\ub2f9\ub3d9"
    ],
    "name:tha_x_preferred":[
        "\u0e41\u0e02\u0e27\u0e07\u0e0a\u0e34\u0e19\u0e14\u0e31\u0e07"
    ],
    "name:und_x_variant":[
        "\uc2e0\ub2f9\ub3d9",
        "Sindang-dong"
    ],
    "name:vie_x_preferred":[
        "Sindang-dong"
    ],
    "name:zho_x_preferred":[
        "\u65b0\u5802\u6d1e"
    ],
    "wof:name":"Sindang-dong",
    "wof:placetype":"locality"
},
  "geometry": {"coordinates":[127.0187,37.5623],"type":"Point"}
}