{
  "type": "Feature",
  "properties": {
    "gn:admin1_code":"11.0",
    "gn:asciiname":"Sindang-dong",
    "gn:country_code":"KR",
    "gn:dem":33,
    "gn:feature_class":"P",
    "gn:feature_code":"PPL",
    "gn:name":"Sindang-dong",
    "gn:population":0,
    "gn:timezone":"Asia/Seoul",
    "iso:country":"KR",
    "name:und_x_variant":[
        "\uc2e0\ub2f9\ub3d9",
        "Sindang-dong"
    ],
    "wof:name":"Sindang-dong",
    "wof:placetype":"locality"
},
  "geometry": {"coordinates":[127.0187,37.5623],"type":"Point"}
}