{
  "type": "Feature",
  "properties": {
    "gn:admin1_code":"16.0",
    "gn:asciiname":"Jibu",
    "gn:country_code":"KR",
    "gn:dem":159,
    "gn:feature_class":"P",
    "gn:feature_code":"PPL",
    "gn:name":"Jibu",
    "gn:population":0,
    "gn:timezone":"Asia/Seoul",
    "iso:country":"KR",
    "name:kor_x_preferred":[
        "\uc9c0\ubd80"
    ],
    "name:und_x_variant":[
        "Chibu",
        "Jibu"
    ],
    "wof:name":"Jibu",
    "wof:placetype":"locality"
},
  "geometry": {"coordinates":[127.17943,34.80815],"type":"Point"}
}