{
  "type": "Feature",
  "properties": {
    "gn:admin1_code":"17.0",
    "gn:asciiname":"Ansagiso",
    "gn:country_code":"KR",
    "gn:dem":112,
    "gn:feature_class":"P",
    "gn:feature_code":"PPL",
    "gn:name":"Ansagiso",
    "gn:population":0,
    "gn:timezone":"Asia/Seoul",
    "iso:country":"KR",
    "name:und_x_variant":[
        "\uc548\uc0ac\uae30\uc18c",
        "Ansagiso"
    ],
    "wof:name":"Ansagiso",
    "wof:placetype":"locality"
},
  "geometry": {"coordinates":[126.6337,36.8456],"type":"Point"}
}