{
  "type": "Feature",
  "properties": {
    "gn:admin1_code":"15.0",
    "gn:asciiname":"Maenam",
    "gn:country_code":"KR",
    "gn:dem":143,
    "gn:feature_class":"P",
    "gn:feature_code":"PPL",
    "gn:name":"Maenam",
    "gn:population":0,
    "gn:timezone":"Asia/Seoul",
    "iso:country":"KR",
    "name:kor_x_preferred":[
        "\ub9e4\ub0a8"
    ],
    "name:und_x_variant":[
        "Maey\u014f"
    ],
    "wof:name":"Maenam",
    "wof:placetype":"locality"
},
  "geometry": {"coordinates":[128.71761999999998,35.91039],"type":"Point"}
}