{
  "type": "Feature",
  "properties": {
    "gn:admin1_code":"20.0",
    "gn:asciiname":"Kuch'ongnim",
    "gn:country_code":"KR",
    "gn:dem":196,
    "gn:feature_class":"P",
    "gn:feature_code":"PPL",
    "gn:name":"Kuch\u2019\u014fngnim",
    "gn:population":0,
    "gn:timezone":"Asia/Seoul",
    "iso:country":"KR",
    "name:und_x_variant":[
        "\uad6c\uccad\ub9bc",
        "Kuch\u2019\u014fngnim"
    ],
    "wof:name":"Kuch'ongnim",
    "wof:placetype":"locality"
},
  "geometry": {"coordinates":[127.92328999999999,35.65085],"type":"Point"}
}