{
  "type": "Feature",
  "properties": {
    "gn:admin1_code":"5.0",
    "gn:asciiname":"Ch'ang-gol",
    "gn:country_code":"KR",
    "gn:dem":294,
    "gn:feature_class":"P",
    "gn:feature_code":"PPL",
    "gn:name":"Ch\u2019ang-gol",
    "gn:population":0,
    "gn:timezone":"Asia/Seoul",
    "iso:country":"KR",
    "name:und_x_variant":[
        "Ch\u2019angjae-dong",
        "Ch\u2019ang-mal",
        "Ch\u2019angch\u2019on-dong",
        "Ch\u2019ang-gol",
        "\ucc3d\uace8"
    ],
    "wof:name":"Ch'ang-gol",
    "wof:placetype":"locality"
},
  "geometry": {"coordinates":[127.7632,36.0343],"type":"Point"}
}