{
  "type": "Feature",
  "properties": {
    "gn:admin1_code":"1.0",
    "gn:admin2_code":"Pukcheju-gun",
    "gn:asciiname":"Mangodong",
    "gn:country_code":"KR",
    "gn:dem":111,
    "gn:feature_class":"P",
    "gn:feature_code":"PPL",
    "gn:name":"Mangodong",
    "gn:population":0,
    "gn:timezone":"Asia/Seoul",
    "iso:country":"KR",
    "name:kor_x_preferred":[
        "\ub9cc\uace0\ub3d9"
    ],
    "name:und_x_variant":[
        "Man\u2019go-dong"
    ],
    "wof:name":"Mangodong",
    "wof:placetype":"locality"
},
  "geometry": {"coordinates":[126.26263,33.33409],"type":"Point"}
}