{
  "type": "Feature",
  "properties": {
    "gn:admin1_code":"20.0",
    "gn:asciiname":"Panyang",
    "gn:country_code":"KR",
    "gn:dem":302,
    "gn:feature_class":"P",
    "gn:feature_code":"PPL",
    "gn:name":"Panyang",
    "gn:population":0,
    "gn:timezone":"Asia/Seoul",
    "iso:country":"KR",
    "name:und_x_variant":[
        "\ubc18\uc591",
        "Panyang"
    ],
    "wof:name":"Panyang",
    "wof:placetype":"locality"
},
  "geometry": {"coordinates":[128.03443999999999,35.64129000000001],"type":"Point"}
}