{
  "type": "Feature",
  "properties": {
    "gn:admin1_code":"3.0",
    "gn:asciiname":"Sunji",
    "gn:country_code":"KR",
    "gn:dem":39,
    "gn:feature_class":"P",
    "gn:feature_code":"PPL",
    "gn:name":"Sunji",
    "gn:population":0,
    "gn:timezone":"Asia/Seoul",
    "iso:country":"KR",
    "name:ceb_x_preferred":[
        "Sunji"
    ],
    "name:swe_x_preferred":[
        "Sunji"
    ],
    "name:und_x_variant":[
        "\uc21c\uc9c0"
    ],
    "wof:name":"Sunji",
    "wof:placetype":"locality"
},
  "geometry": {"coordinates":[127.17829999999999,35.93869],"type":"Point"}
}