{
  "type": "Feature",
  "properties": {
    "gn:admin1_code":"6.0",
    "gn:asciiname":"Togijeom",
    "gn:country_code":"KR",
    "gn:dem":41,
    "gn:feature_class":"P",
    "gn:feature_code":"PPL",
    "gn:name":"Togijeom",
    "gn:population":0,
    "gn:timezone":"Asia/Seoul",
    "iso:country":"KR",
    "name:kor_x_preferred":[
        "\ud1a0\uae30\uc810"
    ],
    "name:und_x_variant":[
        "T\u2019ogij\u014fm-ni",
        "\ud1a0\uae30\uc810\ub9ac",
        "Togijeom"
    ],
    "wof:name":"Togijeom",
    "wof:placetype":"locality"
},
  "geometry": {"coordinates":[128.39793,38.37399],"type":"Point"}
}