{
  "type": "Feature",
  "properties": {
    "gn:admin1_code":"1.0",
    "gn:asciiname":"Jungangdong",
    "gn:country_code":"KR",
    "gn:dem":92,
    "gn:feature_class":"P",
    "gn:feature_code":"PPL",
    "gn:name":"Jungangdong",
    "gn:population":0,
    "gn:timezone":"Asia/Seoul",
    "iso:country":"KR",
    "name:kor_x_preferred":[
        "\uc911\uc559\ub3d9"
    ],
    "wof:name":"Jungangdong",
    "wof:placetype":"locality"
},
  "geometry": {"coordinates":[126.71643,33.31125],"type":"Point"}
}