{
  "type": "Feature",
  "properties": {
    "gn:admin1_code":"16.0",
    "gn:asciiname":"Tang-ni",
    "gn:country_code":"KR",
    "gn:dem":32,
    "gn:feature_class":"P",
    "gn:feature_code":"PPL",
    "gn:name":"Tang-ni",
    "gn:population":0,
    "gn:timezone":"Asia/Seoul",
    "iso:country":"KR",
    "wof:name":"Tang-ni",
    "wof:placetype":"locality"
},
  "geometry": {"coordinates":[126.86417,34.17306],"type":"Point"}
}