{
  "type": "Feature",
  "properties": {
    "gn:admin1_code":"3.0",
    "gn:asciiname":"Hao",
    "gn:country_code":"KR",
    "gn:dem":164,
    "gn:feature_class":"P",
    "gn:feature_code":"PPL",
    "gn:name":"Hao",
    "gn:population":0,
    "gn:timezone":"Asia/Seoul",
    "iso:country":"KR",
    "name:und_x_variant":[
        "\ud558\uc624",
        "Hao"
    ],
    "wof:name":"Hao",
    "wof:placetype":"locality"
},
  "geometry": {"coordinates":[127.38565,35.58818],"type":"Point"}
}