{
  "type": "Feature",
  "properties": {
    "gn:admin1_code":"13.0",
    "gn:asciiname":"Saewon",
    "gn:country_code":"KR",
    "gn:dem":15,
    "gn:feature_class":"P",
    "gn:feature_code":"PPL",
    "gn:name":"Saewon",
    "gn:population":0,
    "gn:timezone":"Asia/Seoul",
    "iso:country":"KR",
    "name:kor_x_preferred":[
        "\uc0c8\uc6d0"
    ],
    "name:kor_x_variant":[
        "Saew\u014fn"
    ],
    "wof:name":"Saewon",
    "wof:placetype":"locality"
},
  "geometry": {"coordinates":[126.88592,37.00555],"type":"Point"}
}