{
  "type": "Feature",
  "properties": {
    "gn:admin1_code":"6.0",
    "gn:asciiname":"Sangmyeongam",
    "gn:country_code":"KR",
    "gn:dem":203,
    "gn:feature_class":"P",
    "gn:feature_code":"PPL",
    "gn:name":"Sangmyeongam",
    "gn:population":0,
    "gn:timezone":"Asia/Seoul",
    "iso:country":"KR",
    "name:kor_x_preferred":[
        "\uc0c1\uba85\uc554"
    ],
    "name:kor_x_variant":[
        "Sangmy\u014fngam"
    ],
    "wof:name":"Sangmyeongam",
    "wof:placetype":"locality"
},
  "geometry": {"coordinates":[127.80611,37.76669],"type":"Point"}
}