{
  "type": "Feature",
  "properties": {
    "gn:admin1_code":"17.0",
    "gn:asciiname":"Cho-dong",
    "gn:country_code":"KR",
    "gn:dem":193,
    "gn:feature_class":"P",
    "gn:feature_code":"PPL",
    "gn:name":"Ch\u014f-dong",
    "gn:population":0,
    "gn:timezone":"Asia/Seoul",
    "iso:country":"KR",
    "name:und_x_variant":[
        "\uc800\ub3d9",
        "Ch\u014f-dong"
    ],
    "wof:name":"Cho-dong",
    "wof:placetype":"locality"
},
  "geometry": {"coordinates":[126.7189,36.3604],"type":"Point"}
}