{
  "type": "Feature",
  "properties": {
    "gn:admin1_code":"6.0",
    "gn:asciiname":"Eungok",
    "gn:country_code":"KR",
    "gn:dem":328,
    "gn:feature_class":"P",
    "gn:feature_code":"PPL",
    "gn:name":"Eungok",
    "gn:population":0,
    "gn:timezone":"Asia/Seoul",
    "iso:country":"KR",
    "name:kor_x_preferred":[
        "\uc740\uace1"
    ],
    "wof:name":"Eungok",
    "wof:placetype":"locality"
},
  "geometry": {"coordinates":[127.60617000000001,38.09774],"type":"Point"}
}