{
  "type": "Feature",
  "properties": {
    "gn:admin1_code":"17.0",
    "gn:asciiname":"Gurigol",
    "gn:country_code":"KR",
    "gn:dem":94,
    "gn:feature_class":"P",
    "gn:feature_code":"PPL",
    "gn:name":"Gurigol",
    "gn:population":0,
    "gn:timezone":"Asia/Seoul",
    "iso:country":"KR",
    "name:kor_x_preferred":[
        "\uad6c\ub9ac\uace8"
    ],
    "wof:name":"Gurigol",
    "wof:placetype":"locality"
},
  "geometry": {"coordinates":[127.2316,36.62527],"type":"Point"}
}