{
  "type": "Feature",
  "properties": {
    "gn:admin1_code":"13.0",
    "gn:asciiname":"Kwonmun'gok",
    "gn:country_code":"KR",
    "gn:dem":12,
    "gn:feature_class":"P",
    "gn:feature_code":"PPL",
    "gn:name":"Kw\u014fnmun\u2019gok",
    "gn:population":0,
    "gn:timezone":"Asia/Seoul",
    "iso:country":"KR",
    "name:und_x_variant":[
        "\uad8c\ubb38\uace1",
        "Kw\u014fnmun\u2019gok"
    ],
    "wof:name":"Kwonmun'gok",
    "wof:placetype":"locality"
},
  "geometry": {"coordinates":[126.9188,36.9212],"type":"Point"}
}