{
  "type": "Feature",
  "properties": {
    "gn:admin1_code":"17.0",
    "gn:asciiname":"Pyongmogan",
    "gn:country_code":"KR",
    "gn:dem":135,
    "gn:feature_class":"P",
    "gn:feature_code":"PPL",
    "gn:name":"Py\u014fngmogan",
    "gn:population":0,
    "gn:timezone":"Asia/Seoul",
    "iso:country":"KR",
    "name:und_x_variant":[
        "\ubcd1\ubaa9\uc548",
        "Py\u014fngmogan"
    ],
    "wof:name":"Pyongmogan",
    "wof:placetype":"locality"
},
  "geometry": {"coordinates":[126.81999999999999,36.3101],"type":"Point"}
}