{
  "type": "Feature",
  "properties": {
    "gn:admin1_code":"20.0",
    "gn:asciiname":"Sap'ajong-ni",
    "gn:country_code":"KR",
    "gn:dem":89,
    "gn:feature_class":"P",
    "gn:feature_code":"PPL",
    "gn:name":"Sap\u2019aj\u014fng-ni",
    "gn:population":0,
    "gn:timezone":"Asia/Seoul",
    "iso:country":"KR",
    "name:eng_x_preferred":[
        "Sap'ajong"
    ],
    "name:eng_x_variant":[
        "Sap'ajong-ni"
    ],
    "wof:name":"Sap'ajong",
    "wof:placetype":"locality"
},
  "geometry": {"coordinates":[128.69999999999999,35.21667],"type":"Point"}
}