{
  "type": "Feature",
  "properties": {
    "gn:admin1_code":"6.0",
    "gn:asciiname":"Suhang-dong",
    "gn:country_code":"KR",
    "gn:dem":585,
    "gn:feature_class":"P",
    "gn:feature_code":"PPL",
    "gn:name":"Suhang-dong",
    "gn:population":0,
    "gn:timezone":"Asia/Seoul",
    "iso:country":"KR",
    "name:kor_x_preferred":[
        "\uc218\ud56d\ub3d9"
    ],
    "wof:name":"Suhang-dong",
    "wof:placetype":"locality"
},
  "geometry": {"coordinates":[128.39349999999999,37.5788],"type":"Point"}
}