{
  "type": "Feature",
  "properties": {
    "gn:admin1_code":"6.0",
    "gn:asciiname":"Pyeongnae",
    "gn:country_code":"KR",
    "gn:dem":229,
    "gn:feature_class":"P",
    "gn:feature_code":"PPL",
    "gn:name":"Pyeongnae",
    "gn:population":0,
    "gn:timezone":"Asia/Seoul",
    "iso:country":"KR",
    "name:kor_x_preferred":[
        "\ud3c9\ub0b4"
    ],
    "name:kor_x_variant":[
        "P\u2019y\u014fngnae"
    ],
    "wof:name":"Pyeongnae",
    "wof:placetype":"locality"
},
  "geometry": {"coordinates":[128.00264000000001,37.84558],"type":"Point"}
}