{
  "type": "Feature",
  "properties": {
    "gn:admin1_code":"16.0",
    "gn:asciiname":"Myeongam",
    "gn:country_code":"KR",
    "gn:dem":23,
    "gn:feature_class":"P",
    "gn:feature_code":"PPL",
    "gn:name":"Myeongam",
    "gn:population":0,
    "gn:timezone":"Asia/Seoul",
    "iso:country":"KR",
    "name:kor_x_preferred":[
        "My\u014fngam"
    ],
    "name:kor_x_variant":[
        "\uba85\uc554"
    ],
    "wof:name":"Myeongam",
    "wof:placetype":"locality"
},
  "geometry": {"coordinates":[126.86517000000001,34.65332],"type":"Point"}
}