{
  "type": "Feature",
  "properties": {
    "gn:admin1_code":"5.0",
    "gn:asciiname":"Sangnamcheon",
    "gn:country_code":"KR",
    "gn:dem":195,
    "gn:feature_class":"P",
    "gn:feature_code":"PPL",
    "gn:name":"Sangnamcheon",
    "gn:population":0,
    "gn:timezone":"Asia/Seoul",
    "iso:country":"KR",
    "name:kor_x_preferred":[
        "\uc0c1\ub0a8\ucc9c"
    ],
    "name:kor_x_variant":[
        "Sangnamch\u2019\u014fn"
    ],
    "wof:name":"Sangnamcheon",
    "wof:placetype":"locality"
},
  "geometry": {"coordinates":[128.50556,37.05226],"type":"Point"}
}