{
  "type": "Feature",
  "properties": {
    "gn:admin1_code":"5.0",
    "gn:asciiname":"Wondok-tong",
    "gn:country_code":"KR",
    "gn:dem":393,
    "gn:feature_class":"P",
    "gn:feature_code":"PPL",
    "gn:name":"W\u014fnd\u014fk-tong",
    "gn:population":0,
    "gn:timezone":"Asia/Seoul",
    "iso:country":"KR",
    "name:kor_x_preferred":[
        "\uc6d0\ub355\ub3d9"
    ],
    "name:kor_x_variant":[
        "W\u014fnd\u014fk-tong"
    ],
    "name:und_x_variant":[
        "T\u014fktong-ni"
    ],
    "wof:name":"Wondok-tong",
    "wof:placetype":"locality"
},
  "geometry": {"coordinates":[127.958,37.2145],"type":"Point"}
}