{
  "type": "Feature",
  "properties": {
    "gn:admin1_code":"13.0",
    "gn:asciiname":"Gonjul",
    "gn:country_code":"KR",
    "gn:dem":121,
    "gn:feature_class":"P",
    "gn:feature_code":"PPL",
    "gn:name":"Gonjul",
    "gn:population":0,
    "gn:timezone":"Asia/Seoul",
    "iso:country":"KR",
    "name:und_x_variant":[
        "\uace4\uc904",
        "Konjul",
        "Gonjul"
    ],
    "wof:name":"Gonjul",
    "wof:placetype":"locality"
},
  "geometry": {"coordinates":[126.96284,37.84365],"type":"Point"}
}