{
  "type": "Feature",
  "properties": {
    "gn:admin1_code":"13.0",
    "gn:asciiname":"Naedong",
    "gn:country_code":"KR",
    "gn:dem":27,
    "gn:feature_class":"P",
    "gn:feature_code":"PPL",
    "gn:name":"Naedong",
    "gn:population":0,
    "gn:timezone":"Asia/Seoul",
    "iso:country":"KR",
    "name:kor_x_preferred":[
        "\ub0b4\ub3d9"
    ],
    "wof:name":"Naedong",
    "wof:placetype":"locality"
},
  "geometry": {"coordinates":[126.80373,37.78826],"type":"Point"}
}