{
  "type": "Feature",
  "properties": {
    "gn:admin1_code":"14.0",
    "gn:asciiname":"Golgasari",
    "gn:country_code":"KR",
    "gn:dem":579,
    "gn:feature_class":"P",
    "gn:feature_code":"PPL",
    "gn:name":"Golgasari",
    "gn:population":0,
    "gn:timezone":"Asia/Seoul",
    "iso:country":"KR",
    "name:kor_x_preferred":[
        "\uace8\uac00\uc0ac\ub9ac"
    ],
    "wof:name":"Golgasari",
    "wof:placetype":"locality"
},
  "geometry": {"coordinates":[128.91021999999998,36.75708],"type":"Point"}
}