{
  "type": "Feature",
  "properties": {
    "gn:admin1_code":"3.0",
    "gn:asciiname":"Sin'gang",
    "gn:country_code":"KR",
    "gn:dem":29,
    "gn:feature_class":"P",
    "gn:feature_code":"PPL",
    "gn:name":"Sin\u2019gang",
    "gn:population":0,
    "gn:timezone":"Asia/Seoul",
    "iso:country":"KR",
    "name:und_x_variant":[
        "\uc2e0\uac15",
        "Sin\u2019gang"
    ],
    "wof:name":"Sin'gang",
    "wof:placetype":"locality"
},
  "geometry": {"coordinates":[127.15864000000001,35.90495],"type":"Point"}
}