{
  "type": "Feature",
  "properties": {
    "gn:admin1_code":"0.0",
    "gn:asciiname":"Sanggwi-ri",
    "gn:country_code":"KR",
    "gn:dem":419,
    "gn:feature_class":"P",
    "gn:feature_code":"PPL",
    "gn:name":"Sanggwi-ri",
    "gn:population":0,
    "gn:timezone":"Asia/Seoul",
    "iso:country":"KR",
    "name:und_x_variant":[
        "Sanggi-ri",
        "Sanggwi-ri",
        "Wissangw\u014fl"
    ],
    "wof:name":"Sanggwi-ri",
    "wof:placetype":"locality"
},
  "geometry": {"coordinates":[127.26667,35.75],"type":"Point"}
}