{
  "type": "Feature",
  "properties": {
    "gn:admin1_code":"3.0",
    "gn:asciiname":"Ant'o",
    "gn:country_code":"KR",
    "gn:dem":29,
    "gn:feature_class":"P",
    "gn:feature_code":"PPL",
    "gn:name":"Ant\u2019\u014f",
    "gn:population":0,
    "gn:timezone":"Asia/Seoul",
    "iso:country":"KR",
    "name:und_x_variant":[
        "\uc548\ud130",
        "Ant\u2019\u014f"
    ],
    "wof:name":"Ant'o",
    "wof:placetype":"locality"
},
  "geometry": {"coordinates":[127.00602000000001,35.82516],"type":"Point"}
}