{
  "type": "Feature",
  "properties": {
    "gn:admin1_code":"20.0",
    "gn:asciiname":"Songdang",
    "gn:country_code":"KR",
    "gn:dem":11,
    "gn:feature_class":"P",
    "gn:feature_code":"PPL",
    "gn:name":"S\u014fngdang",
    "gn:population":0,
    "gn:timezone":"Asia/Seoul",
    "iso:country":"KR",
    "name:und_x_variant":[
        "\uc131\ub2f9",
        "S\u014fngdang"
    ],
    "wof:name":"Songdang",
    "wof:placetype":"locality"
},
  "geometry": {"coordinates":[128.38824,35.36373],"type":"Point"}
}