{
  "type": "Feature",
  "properties": {
    "gn:admin1_code":"5.0",
    "gn:asciiname":"Oesanmak",
    "gn:country_code":"KR",
    "gn:dem":290,
    "gn:feature_class":"P",
    "gn:feature_code":"PPL",
    "gn:name":"Oesanmak",
    "gn:population":0,
    "gn:timezone":"Asia/Seoul",
    "iso:country":"KR",
    "name:kor_x_preferred":[
        "\uc678\uc0b0\ub9c9"
    ],
    "wof:name":"Oesanmak",
    "wof:placetype":"locality"
},
  "geometry": {"coordinates":[127.76261,36.69668],"type":"Point"}
}