{
  "type": "Feature",
  "properties": {
    "gn:admin1_code":"12.0",
    "gn:asciiname":"Magamyo",
    "gn:country_code":"KR",
    "gn:dem":10,
    "gn:feature_class":"P",
    "gn:feature_code":"PPL",
    "gn:name":"Magamyo",
    "gn:population":0,
    "gn:timezone":"Asia/Seoul",
    "iso:country":"KR",
    "name:kor_x_preferred":[
        "\ub9c8\uac00\ubb18"
    ],
    "wof:name":"Magamyo",
    "wof:placetype":"locality"
},
  "geometry": {"coordinates":[126.75972,37.54111],"type":"Point"}
}