{
  "type": "Feature",
  "properties": {
    "gn:admin1_code":"5.0",
    "gn:asciiname":"Hongchanggol",
    "gn:country_code":"KR",
    "gn:dem":93,
    "gn:feature_class":"P",
    "gn:feature_code":"PPL",
    "gn:name":"Hongchanggol",
    "gn:population":0,
    "gn:timezone":"Asia/Seoul",
    "iso:country":"KR",
    "name:kor_x_preferred":[
        "\ud64d\ucc3d\uace8"
    ],
    "wof:name":"Hongchanggol",
    "wof:placetype":"locality"
},
  "geometry": {"coordinates":[127.52948000000001,36.95792],"type":"Point"}
}