{
  "type": "Feature",
  "properties": {
    "gn:admin1_code":"14.0",
    "gn:asciiname":"Toltam",
    "gn:country_code":"KR",
    "gn:dem":34,
    "gn:feature_class":"P",
    "gn:feature_code":"PPL",
    "gn:name":"Toltam",
    "gn:population":0,
    "gn:timezone":"Asia/Seoul",
    "iso:country":"KR",
    "name:und_x_variant":[
        "\ub3cc\ub2f4",
        "Toltam"
    ],
    "wof:name":"Toltam",
    "wof:placetype":"locality"
},
  "geometry": {"coordinates":[129.4288,36.8332],"type":"Point"}
}