{
  "type": "Feature",
  "properties": {
    "gn:admin1_code":"13.0",
    "gn:admin2_code":"P'aju-si",
    "gn:asciiname":"Marumul",
    "gn:country_code":"KR",
    "gn:dem":14,
    "gn:feature_class":"P",
    "gn:feature_code":"PPL",
    "gn:name":"Marumul",
    "gn:population":0,
    "gn:timezone":"Asia/Seoul",
    "iso:country":"KR",
    "name:kor_x_preferred":[
        "\ub9d0\uc6b0\ubb3c"
    ],
    "name:und_x_variant":[
        "Maj\u014fng-ni",
        "Marumul"
    ],
    "wof:name":"Marumul",
    "wof:placetype":"locality"
},
  "geometry": {"coordinates":[126.75203,37.88368],"type":"Point"}
}