{
  "type": "Feature",
  "properties": {
    "gn:admin1_code":"6.0",
    "gn:asciiname":"Toch'an-dong",
    "gn:country_code":"KR",
    "gn:dem":383,
    "gn:feature_class":"P",
    "gn:feature_code":"PPL",
    "gn:name":"Toch\u2019an-dong",
    "gn:population":0,
    "gn:timezone":"Asia/Seoul",
    "iso:country":"KR",
    "wof:name":"Toch'an-dong",
    "wof:placetype":"locality"
},
  "geometry": {"coordinates":[128.22693999999998,37.70139],"type":"Point"}
}