{
  "type": "Feature",
  "properties": {
    "gn:admin1_code":"13.0",
    "gn:asciiname":"Yeon-gol",
    "gn:country_code":"KR",
    "gn:dem":145,
    "gn:feature_class":"P",
    "gn:feature_code":"PPL",
    "gn:name":"Yeon-gol",
    "gn:population":0,
    "gn:timezone":"Asia/Seoul",
    "iso:country":"KR",
    "name:und_x_variant":[
        "\uc5f0\uace8",
        "Yeon-gol",
        "Y\u014fn-gol"
    ],
    "wof:name":"Yeon-gol",
    "wof:placetype":"locality"
},
  "geometry": {"coordinates":[127.38611000000002,37.37361],"type":"Point"}
}