{
  "type": "Feature",
  "properties": {
    "gn:admin1_code":"20.0",
    "gn:asciiname":"Sangbukjeong",
    "gn:country_code":"KR",
    "gn:dem":35,
    "gn:feature_class":"P",
    "gn:feature_code":"PPL",
    "gn:name":"Sangbukjeong",
    "gn:population":0,
    "gn:timezone":"Asia/Seoul",
    "iso:country":"KR",
    "name:kor_x_preferred":[
        "\uc0c1\ubd81\uc815"
    ],
    "name:und_x_variant":[
        "Sangbukch\u014fng"
    ],
    "wof:name":"Sangbukjeong",
    "wof:placetype":"locality"
},
  "geometry": {"coordinates":[129.05041,35.36267],"type":"Point"}
}