{
  "type": "Feature",
  "properties": {
    "gn:admin1_code":"16.0",
    "gn:asciiname":"An-dong",
    "gn:country_code":"KR",
    "gn:dem":6,
    "gn:feature_class":"P",
    "gn:feature_code":"PPL",
    "gn:name":"An-dong",
    "gn:population":0,
    "gn:timezone":"Asia/Seoul",
    "iso:country":"KR",
    "wof:name":"An-dong",
    "wof:placetype":"locality"
},
  "geometry": {"coordinates":[126.31667,34.56667],"type":"Point"}
}