{
  "type": "Feature",
  "properties": {
    "gn:admin1_code":"16.0",
    "gn:asciiname":"Dohoe",
    "gn:country_code":"KR",
    "gn:dem":26,
    "gn:feature_class":"P",
    "gn:feature_code":"PPL",
    "gn:name":"Dohoe",
    "gn:population":0,
    "gn:timezone":"Asia/Seoul",
    "iso:country":"KR",
    "name:kor_x_preferred":[
        "\ub3c4\ud68c\ub4f1"
    ],
    "name:kor_x_variant":[
        "Tohoed\u016dng",
        "\ub3c4\ud68c"
    ],
    "wof:name":"Dohoe",
    "wof:placetype":"locality"
},
  "geometry": {"coordinates":[127.37617,34.80928],"type":"Point"}
}