{
  "type": "Feature",
  "properties": {
    "gn:admin1_code":"13.0",
    "gn:asciiname":"Tanggok",
    "gn:country_code":"KR",
    "gn:dem":87,
    "gn:feature_class":"P",
    "gn:feature_code":"PPL",
    "gn:name":"Tanggok",
    "gn:population":0,
    "gn:timezone":"Asia/Seoul",
    "iso:country":"KR",
    "name:und_x_variant":[
        "\ub2f9\uace1",
        "Danggok",
        "Tanggok"
    ],
    "wof:name":"Tanggok",
    "wof:placetype":"locality"
},
  "geometry": {"coordinates":[127.23806,37.2875],"type":"Point"}
}