{
  "type": "Feature",
  "properties": {
    "gn:admin1_code":"17.0",
    "gn:asciiname":"Simch'on",
    "gn:country_code":"KR",
    "gn:dem":226,
    "gn:feature_class":"P",
    "gn:feature_code":"PPL",
    "gn:name":"Simch\u2019\u014fn",
    "gn:population":0,
    "gn:timezone":"Asia/Seoul",
    "iso:country":"KR",
    "name:und_x_variant":[
        "Kip\u2019unae",
        "Kip\u2019unnae",
        "\uc2ec\ucc9c",
        "Simch\u2019\u014fn"
    ],
    "wof:name":"Simch'on",
    "wof:placetype":"locality"
},
  "geometry": {"coordinates":[127.4752,36.052],"type":"Point"}
}