{
  "type": "Feature",
  "properties": {
    "gn:admin1_code":"13.0",
    "gn:asciiname":"Sinjang-dong",
    "gn:country_code":"KR",
    "gn:dem":46,
    "gn:feature_class":"P",
    "gn:feature_code":"PPLL",
    "gn:name":"Sinjang-dong",
    "gn:population":0,
    "gn:timezone":"Asia/Seoul",
    "iso:country":"KR",
    "name:und_x_variant":[
        "\uc2e0\uc7a5\ub3d9",
        "Sinjang-dong"
    ],
    "wof:name":"Sinjang-dong",
    "wof:placetype":"locality"
},
  "geometry": {"coordinates":[127.05556,37.17528],"type":"Point"}
}