{
  "type": "Feature",
  "properties": {
    "gn:admin1_code":"6.0",
    "gn:asciiname":"Komjinbon-dong",
    "gn:country_code":"KR",
    "gn:dem":23,
    "gn:feature_class":"P",
    "gn:feature_code":"PPL",
    "gn:name":"Komjinbon-dong",
    "gn:population":0,
    "gn:timezone":"Asia/Seoul",
    "iso:country":"KR",
    "wof:name":"Komjinbon-dong",
    "wof:placetype":"locality"
},
  "geometry": {"coordinates":[129.04193999999998,37.64194000000001],"type":"Point"}
}