{
  "type": "Feature",
  "properties": {
    "gn:admin1_code":"14.0",
    "gn:asciiname":"Ori-mal",
    "gn:country_code":"KR",
    "gn:dem":120,
    "gn:feature_class":"P",
    "gn:feature_code":"PPL",
    "gn:name":"Ori-mal",
    "gn:population":0,
    "gn:timezone":"Asia/Seoul",
    "iso:country":"KR",
    "name:und_x_variant":[
        "\uc624\ub9ac\ub9d0",
        "Ori-mal"
    ],
    "wof:name":"Ori-mal",
    "wof:placetype":"locality"
},
  "geometry": {"coordinates":[129.33019999999999,36.9204],"type":"Point"}
}