{
  "type": "Feature",
  "properties": {
    "gn:admin1_code":"16.0",
    "gn:asciiname":"Jangsan",
    "gn:country_code":"KR",
    "gn:dem":5,
    "gn:feature_class":"P",
    "gn:feature_code":"PPL",
    "gn:name":"Jangsan",
    "gn:population":0,
    "gn:timezone":"Asia/Seoul",
    "iso:country":"KR",
    "name:kor_x_preferred":[
        "\uc7a5\uc0b0"
    ],
    "name:und_x_variant":[
        "Changsan"
    ],
    "wof:name":"Jangsan",
    "wof:placetype":"locality"
},
  "geometry": {"coordinates":[127.4885,34.86524],"type":"Point"}
}