{
  "type": "Feature",
  "properties": {
    "gn:admin1_code":"20.0",
    "gn:asciiname":"Taech'ol-li",
    "gn:country_code":"KR",
    "gn:dem":36,
    "gn:feature_class":"P",
    "gn:feature_code":"PPL",
    "gn:name":"Taech\u2019ol-li",
    "gn:population":0,
    "gn:timezone":"Asia/Seoul",
    "iso:country":"KR",
    "name:und_x_variant":[
        "\ub300\ucd0c\ub9ac",
        "Taech\u2019ol-li"
    ],
    "wof:name":"Taech'ol-li",
    "wof:placetype":"locality"
},
  "geometry": {"coordinates":[128.47978000000001,34.78496],"type":"Point"}
}