{
  "type": "Feature",
  "properties": {
    "gn:admin1_code":"13.0",
    "gn:asciiname":"Musu",
    "gn:country_code":"KR",
    "gn:dem":16,
    "gn:feature_class":"P",
    "gn:feature_code":"PPL",
    "gn:name":"Musu",
    "gn:population":0,
    "gn:timezone":"Asia/Seoul",
    "iso:country":"KR",
    "name:ceb_x_preferred":[
        "Musu"
    ],
    "name:fra_x_preferred":[
        "Musu"
    ],
    "name:swe_x_preferred":[
        "Musu"
    ],
    "name:und_x_variant":[
        "\ubb34\uc218"
    ],
    "wof:name":"Musu",
    "wof:placetype":"locality"
},
  "geometry": {"coordinates":[126.87988,36.9885],"type":"Point"}
}