{
  "type": "Feature",
  "properties": {
    "gn:admin1_code":"14.0",
    "gn:asciiname":"Woncheon",
    "gn:country_code":"KR",
    "gn:dem":154,
    "gn:feature_class":"P",
    "gn:feature_code":"PPL",
    "gn:name":"Woncheon",
    "gn:population":0,
    "gn:timezone":"Asia/Seoul",
    "iso:country":"KR",
    "name:kor_x_preferred":[
        "\uc6d0\ucc9c"
    ],
    "wof:name":"Woncheon",
    "wof:placetype":"locality"
},
  "geometry": {"coordinates":[128.87835000000001,36.73478],"type":"Point"}
}