{
  "type": "Feature",
  "properties": {
    "gn:admin1_code":"3.0",
    "gn:asciiname":"Pulloch'i",
    "gn:country_code":"KR",
    "gn:dem":282,
    "gn:feature_class":"P",
    "gn:feature_code":"PPL",
    "gn:name":"Pulloch\u2019i",
    "gn:population":0,
    "gn:timezone":"Asia/Seoul",
    "iso:country":"KR",
    "name:und_x_variant":[
        "\ubd88\ub85c\uce58",
        "Pulloch\u2019i"
    ],
    "wof:name":"Pulloch'i",
    "wof:placetype":"locality"
},
  "geometry": {"coordinates":[127.52073,35.8832],"type":"Point"}
}