{
  "type": "Feature",
  "properties": {
    "gn:admin1_code":"14.0",
    "gn:asciiname":"Georisil",
    "gn:country_code":"KR",
    "gn:dem":93,
    "gn:feature_class":"P",
    "gn:feature_code":"PPL",
    "gn:name":"Georisil",
    "gn:population":0,
    "gn:timezone":"Asia/Seoul",
    "iso:country":"KR",
    "name:kor_x_preferred":[
        "\uac70\ub77c\uc2e4"
    ],
    "wof:name":"Georisil",
    "wof:placetype":"locality"
},
  "geometry": {"coordinates":[128.40733,36.57872],"type":"Point"}
}