{
  "type": "Feature",
  "properties": {
    "gn:admin1_code":"16.0",
    "gn:asciiname":"Gureunggol",
    "gn:country_code":"KR",
    "gn:dem":56,
    "gn:feature_class":"P",
    "gn:feature_code":"PPL",
    "gn:name":"Gureunggol",
    "gn:population":0,
    "gn:timezone":"Asia/Seoul",
    "iso:country":"KR",
    "name:kor_x_preferred":[
        "\ud568\uc815\uace8"
    ],
    "name:kor_x_variant":[
        "T\u014fk-tong"
    ],
    "wof:name":"Gureunggol",
    "wof:placetype":"locality"
},
  "geometry": {"coordinates":[126.75139,34.70278],"type":"Point"}
}