{
  "type": "Feature",
  "properties": {
    "gn:admin1_code":"3.0",
    "gn:asciiname":"Myongdong-ni",
    "gn:country_code":"KR",
    "gn:dem":54,
    "gn:feature_class":"P",
    "gn:feature_code":"PPL",
    "gn:name":"My\u014fngd\u014fng-ni",
    "gn:population":0,
    "gn:timezone":"Asia/Seoul",
    "iso:country":"KR",
    "name:und_x_variant":[
        "\uba85\ub355\ub9ac",
        "My\u014fngd\u014fng-ni"
    ],
    "wof:name":"Myongdong-ni",
    "wof:placetype":"locality"
},
  "geometry": {"coordinates":[127.21185,35.8619],"type":"Point"}
}