{
  "type": "Feature",
  "properties": {
    "gn:admin1_code":"6.0",
    "gn:asciiname":"Gaeyonggae",
    "gn:country_code":"KR",
    "gn:dem":88,
    "gn:feature_class":"P",
    "gn:feature_code":"PPL",
    "gn:name":"Gaeyonggae",
    "gn:population":0,
    "gn:timezone":"Asia/Seoul",
    "iso:country":"KR",
    "name:kor_x_preferred":[
        "\uac1c\uc639\uac1c"
    ],
    "name:kor_x_variant":[
        "\uac1c\uc6a9\uac1c"
    ],
    "name:und_x_variant":[
        "Kaeonggae",
        "Gaeyonggae"
    ],
    "wof:name":"Gaeyonggae",
    "wof:placetype":"locality"
},
  "geometry": {"coordinates":[127.52164999999999,37.73011],"type":"Point"}
}