{
  "type": "Feature",
  "properties": {
    "gn:admin1_code":"17.0",
    "gn:asciiname":"Hamakhyeolli",
    "gn:country_code":"KR",
    "gn:dem":120,
    "gn:feature_class":"P",
    "gn:feature_code":"PPL",
    "gn:name":"Hamakhyeolli",
    "gn:population":0,
    "gn:timezone":"Asia/Seoul",
    "iso:country":"KR",
    "name:und_x_variant":[
        "\ud558\ub9c9\ud604\ub9ac",
        "Hamakhy\u014fl-li",
        "Hamakhyeolli"
    ],
    "wof:name":"Hamakhyeolli",
    "wof:placetype":"locality"
},
  "geometry": {"coordinates":[127.36816,36.20456],"type":"Point"}
}