{
  "type": "Feature",
  "properties": {
    "gn:admin1_code":"3.0",
    "gn:asciiname":"Pang-dong",
    "gn:country_code":"KR",
    "gn:dem":248,
    "gn:feature_class":"P",
    "gn:feature_code":"PPL",
    "gn:name":"Pang-dong",
    "gn:population":0,
    "gn:timezone":"Asia/Seoul",
    "iso:country":"KR",
    "name:und_x_variant":[
        "\ubc29\ub3d9",
        "Pang-gol",
        "Pang-dong"
    ],
    "wof:name":"Pang-dong",
    "wof:placetype":"locality"
},
  "geometry": {"coordinates":[127.27782999999999,35.69991],"type":"Point"}
}