{
  "type": "Feature",
  "properties": {
    "gn:admin1_code":"14.0",
    "gn:asciiname":"Naktong-ni",
    "gn:country_code":"KR",
    "gn:dem":50,
    "gn:feature_class":"P",
    "gn:feature_code":"PPL",
    "gn:name":"Naktong-ni",
    "gn:population":0,
    "gn:timezone":"Asia/Seoul",
    "iso:country":"KR",
    "name:eng_x_preferred":[
        "Naktong"
    ],
    "name:eng_x_variant":[
        "Naktong-ni"
    ],
    "name:und_x_variant":[
        "Rakut\u014d-ri",
        "Naktong",
        "\ub099\ub3d9\ub9ac",
        "Naktong-ni"
    ],
    "wof:name":"Naktong",
    "wof:placetype":"locality"
},
  "geometry": {"coordinates":[128.298,36.3642],"type":"Point"}
}