{
  "type": "Feature",
  "properties": {
    "gn:admin1_code":"13.0",
    "gn:asciiname":"Birugae",
    "gn:country_code":"KR",
    "gn:dem":170,
    "gn:feature_class":"P",
    "gn:feature_code":"PPL",
    "gn:name":"Birugae",
    "gn:population":0,
    "gn:timezone":"Asia/Seoul",
    "iso:country":"KR",
    "name:und_x_variant":[
        "\ube44\ub8e8\uac1c",
        "Pirugae",
        "Birugae"
    ],
    "wof:name":"Birugae",
    "wof:placetype":"locality"
},
  "geometry": {"coordinates":[127.12726000000001,37.74157],"type":"Point"}
}