{
  "type": "Feature",
  "properties": {
    "gn:admin1_code":"14.0",
    "gn:asciiname":"Yongsil-li",
    "gn:country_code":"KR",
    "gn:dem":162,
    "gn:feature_class":"P",
    "gn:feature_code":"PPLL",
    "gn:name":"Yongsil-li",
    "gn:population":0,
    "gn:timezone":"Asia/Seoul",
    "iso:country":"KR",
    "name:und_x_variant":[
        "\uc6a9\uc2e0\ub9ac",
        "Yongsil-li"
    ],
    "wof:name":"Yongsil-li",
    "wof:placetype":"locality"
},
  "geometry": {"coordinates":[128.06398999999999,36.31581],"type":"Point"}
}