{
  "type": "Feature",
  "properties": {
    "gn:admin1_code":"12.0",
    "gn:asciiname":"Suyongso",
    "gn:country_code":"KR",
    "gn:dem":12,
    "gn:feature_class":"P",
    "gn:feature_code":"PPL",
    "gn:name":"Suyongso",
    "gn:population":0,
    "gn:timezone":"Asia/Seoul",
    "iso:country":"KR",
    "name:kor_x_preferred":[
        "\uc218\uc6a9\uc18c"
    ],
    "wof:name":"Suyongso",
    "wof:placetype":"locality"
},
  "geometry": {"coordinates":[126.66943999999999,37.52972000000001],"type":"Point"}
}