{
  "type": "Feature",
  "properties": {
    "gn:admin1_code":"16.0",
    "gn:asciiname":"Moksin",
    "gn:country_code":"KR",
    "gn:dem":27,
    "gn:feature_class":"P",
    "gn:feature_code":"PPL",
    "gn:name":"Moksin",
    "gn:population":0,
    "gn:timezone":"Asia/Seoul",
    "iso:country":"KR",
    "name:kor_x_preferred":[
        "\ubaa9\uc2e0"
    ],
    "wof:name":"Moksin",
    "wof:placetype":"locality"
},
  "geometry": {"coordinates":[126.56389,34.51639],"type":"Point"}
}