{
  "type": "Feature",
  "properties": {
    "gn:admin1_code":"6.0",
    "gn:asciiname":"Sambari",
    "gn:country_code":"KR",
    "gn:dem":47,
    "gn:feature_class":"P",
    "gn:feature_code":"PPL",
    "gn:name":"Sambari",
    "gn:population":0,
    "gn:timezone":"Asia/Seoul",
    "iso:country":"KR",
    "name:kor_x_preferred":[
        "\uc0bc\ubc14\ub9ac"
    ],
    "wof:name":"Sambari",
    "wof:placetype":"locality"
},
  "geometry": {"coordinates":[128.60896,38.0307],"type":"Point"}
}