{
  "type": "Feature",
  "properties": {
    "gn:admin1_code":"3.0",
    "gn:asciiname":"Ch'iruni",
    "gn:country_code":"KR",
    "gn:dem":361,
    "gn:feature_class":"P",
    "gn:feature_code":"PPL",
    "gn:name":"Ch\u2019ir\u016dni",
    "gn:population":0,
    "gn:timezone":"Asia/Seoul",
    "iso:country":"KR",
    "name:und_x_variant":[
        "\uce60\uc740\uc774",
        "Ch\u2019ir\u016dni"
    ],
    "wof:name":"Ch'iruni",
    "wof:placetype":"locality"
},
  "geometry": {"coordinates":[127.39724,35.97619],"type":"Point"}
}