{
  "type": "Feature",
  "properties": {
    "gn:admin1_code":"14.0",
    "gn:asciiname":"Kyejon-dong",
    "gn:country_code":"KR",
    "gn:dem":234,
    "gn:feature_class":"P",
    "gn:feature_code":"PPL",
    "gn:name":"Kyej\u014fn-dong",
    "gn:population":0,
    "gn:timezone":"Asia/Seoul",
    "iso:country":"KR",
    "name:und_x_variant":[
        "\uacc4\uc804\ub3d9",
        "Kyej\u014fn-dong"
    ],
    "wof:name":"Kyejon-dong",
    "wof:placetype":"locality"
},
  "geometry": {"coordinates":[129.29310000000001,36.968],"type":"Point"}
}