{
  "type": "Feature",
  "properties": {
    "gn:admin1_code":"13.0",
    "gn:admin2_code":"P'aju-si",
    "gn:asciiname":"Pongam-ni",
    "gn:country_code":"KR",
    "gn:dem":47,
    "gn:feature_class":"P",
    "gn:feature_code":"PPL",
    "gn:name":"Pongam-ni",
    "gn:population":0,
    "gn:timezone":"Asia/Seoul",
    "iso:country":"KR",
    "name:eng_x_preferred":[
        "Pongam"
    ],
    "name:eng_x_variant":[
        "Pongam-ni"
    ],
    "wof:name":"Pongam",
    "wof:placetype":"locality"
},
  "geometry": {"coordinates":[126.79861,37.82361],"type":"Point"}
}