{
  "type": "Feature",
  "properties": {
    "gn:admin1_code":"20.0",
    "gn:asciiname":"Yeso-dong",
    "gn:country_code":"KR",
    "gn:dem":510,
    "gn:feature_class":"P",
    "gn:feature_code":"PPL",
    "gn:name":"Yes\u014f-dong",
    "gn:population":0,
    "gn:timezone":"Asia/Seoul",
    "iso:country":"KR",
    "name:und_x_variant":[
        "\uc608\uc11c\ub3d9",
        "Yes\u014f-dong"
    ],
    "wof:name":"Yeso-dong",
    "wof:placetype":"locality"
},
  "geometry": {"coordinates":[127.92979,35.87484],"type":"Point"}
}