{
  "type": "Feature",
  "properties": {
    "gn:admin1_code":"16.0",
    "gn:admin2_code":"Chindo-gun",
    "gn:asciiname":"Jungnim",
    "gn:country_code":"KR",
    "gn:dem":21,
    "gn:feature_class":"P",
    "gn:feature_code":"PPL",
    "gn:name":"Jungnim",
    "gn:population":0,
    "gn:timezone":"Asia/Seoul",
    "iso:country":"KR",
    "name:kor_x_preferred":[
        "\uc8fd\ub9bc"
    ],
    "name:und_x_variant":[
        "Chungnim"
    ],
    "wof:name":"Jungnim",
    "wof:placetype":"locality"
},
  "geometry": {"coordinates":[126.25402,34.39034],"type":"Point"}
}