{
  "type": "Feature",
  "properties": {
    "gn:admin1_code":"6.0",
    "gn:asciiname":"Chamsaemi",
    "gn:country_code":"KR",
    "gn:dem":20,
    "gn:feature_class":"P",
    "gn:feature_code":"PPL",
    "gn:name":"Chamsaemi",
    "gn:population":0,
    "gn:timezone":"Asia/Seoul",
    "iso:country":"KR",
    "name:und_x_variant":[
        "\uc7a0\uc0c8\ubbf8"
    ],
    "wof:name":"Chamsaemi",
    "wof:placetype":"locality"
},
  "geometry": {"coordinates":[128.52715000000001,38.26032],"type":"Point"}
}