{
  "type": "Feature",
  "properties": {
    "gn:admin1_code":"14.0",
    "gn:asciiname":"Choksong",
    "gn:country_code":"KR",
    "gn:dem":134,
    "gn:feature_class":"P",
    "gn:feature_code":"PPL",
    "gn:name":"Ch\u014fksong",
    "gn:population":0,
    "gn:timezone":"Asia/Seoul",
    "iso:country":"KR",
    "name:und_x_variant":[
        "\uc801\uc1a1",
        "Ch\u014fksong"
    ],
    "wof:name":"Choksong",
    "wof:placetype":"locality"
},
  "geometry": {"coordinates":[128.18554,35.83232],"type":"Point"}
}