{
  "type": "Feature",
  "properties": {
    "gn:admin1_code":"14.0",
    "gn:asciiname":"Tang-dong",
    "gn:country_code":"KR",
    "gn:dem":383,
    "gn:feature_class":"P",
    "gn:feature_code":"PPL",
    "gn:name":"Tang-dong",
    "gn:population":0,
    "gn:timezone":"Asia/Seoul",
    "iso:country":"KR",
    "name:und_x_variant":[
        "\ub2f9\ub3d9",
        "Tang-dong"
    ],
    "wof:name":"Tang-dong",
    "wof:placetype":"locality"
},
  "geometry": {"coordinates":[129.05109999999999,36.7555],"type":"Point"}
}