{
  "type": "Feature",
  "properties": {
    "gn:admin1_code":"20.0",
    "gn:asciiname":"Oso-dong",
    "gn:country_code":"KR",
    "gn:dem":32,
    "gn:feature_class":"P",
    "gn:feature_code":"PPL",
    "gn:name":"Os\u014f-dong",
    "gn:population":0,
    "gn:timezone":"Asia/Seoul",
    "iso:country":"KR",
    "name:und_x_variant":[
        "\uc624\uc11c\ub3d9",
        "Os\u014f-dong"
    ],
    "wof:name":"Oso-dong",
    "wof:placetype":"locality"
},
  "geometry": {"coordinates":[128.26868000000002,35.5752],"type":"Point"}
}