{
  "type": "Feature",
  "properties": {
    "gn:admin1_code":"20.0",
    "gn:asciiname":"Yomhae",
    "gn:cc2":"KR",
    "gn:country_code":"KR",
    "gn:dem":15,
    "gn:feature_class":"P",
    "gn:feature_code":"PPL",
    "gn:name":"Y\u014fmhae",
    "gn:population":0,
    "gn:timezone":"Asia/Seoul",
    "iso:country":"KR",
    "name:und_x_variant":[
        "Y\u014fomhae-ri",
        "Y\u014fmhaech\u2019\u014fn",
        "Y\u014fmhae-ri",
        "Y\u014fmhae"
    ],
    "wof:name":"Yomhae",
    "wof:placetype":"locality"
},
  "geometry": {"coordinates":[127.81389,34.85444],"type":"Point"}
}