{
  "type": "Feature",
  "properties": {
    "gn:admin1_code":"6.0",
    "gn:asciiname":"Chi-ch'on",
    "gn:country_code":"KR",
    "gn:dem":173,
    "gn:feature_class":"P",
    "gn:feature_code":"PPL",
    "gn:name":"Chi-ch\u2019on",
    "gn:population":0,
    "gn:timezone":"Asia/Seoul",
    "iso:country":"KR",
    "name:kor_x_preferred":[
        "\uc9c0\ucd0c"
    ],
    "name:kor_x_variant":[
        "Chi-ch\u2019on"
    ],
    "wof:name":"Chi-ch'on",
    "wof:placetype":"locality"
},
  "geometry": {"coordinates":[127.87269999999999,37.3639],"type":"Point"}
}