{
  "type": "Feature",
  "properties": {
    "gn:admin1_code":"13.0",
    "gn:asciiname":"Anbanggol",
    "gn:country_code":"KR",
    "gn:dem":174,
    "gn:feature_class":"P",
    "gn:feature_code":"PPL",
    "gn:name":"Anbanggol",
    "gn:population":0,
    "gn:timezone":"Asia/Seoul",
    "iso:country":"KR",
    "name:kor_x_preferred":[
        "\uc548\ubc29\uace8"
    ],
    "name:und_x_variant":[
        "\uc548\ubc29\uace8",
        "Anbanggol"
    ],
    "wof:name":"Anbanggol",
    "wof:placetype":"locality"
},
  "geometry": {"coordinates":[127.2908,37.744],"type":"Point"}
}