{
  "type": "Feature",
  "properties": {
    "gn:admin1_code":"6.0",
    "gn:asciiname":"Saem-gol",
    "gn:country_code":"KR",
    "gn:dem":272,
    "gn:feature_class":"P",
    "gn:feature_code":"PPL",
    "gn:name":"Saem-gol",
    "gn:population":0,
    "gn:timezone":"Asia/Seoul",
    "iso:country":"KR",
    "name:kor_x_preferred":[
        "\uc0d8\uace8"
    ],
    "wof:name":"Saem-gol",
    "wof:placetype":"locality"
},
  "geometry": {"coordinates":[128.01689999999999,37.6443],"type":"Point"}
}