{
  "type": "Feature",
  "properties": {
    "gn:admin1_code":"17.0",
    "gn:asciiname":"Taep'yong-gol",
    "gn:country_code":"KR",
    "gn:dem":38,
    "gn:feature_class":"P",
    "gn:feature_code":"PPL",
    "gn:name":"Taep\u2019y\u014fng-gol",
    "gn:population":0,
    "gn:timezone":"Asia/Seoul",
    "iso:country":"KR",
    "name:und_x_variant":[
        "\ub300\ud3c9\uace8",
        "Taep\u2019y\u014fng-gol"
    ],
    "wof:name":"Taep'yong-gol",
    "wof:placetype":"locality"
},
  "geometry": {"coordinates":[126.9958,36.4083],"type":"Point"}
}