{
  "type": "Feature",
  "properties": {
    "gn:admin1_code":"17.0",
    "gn:asciiname":"Salgoji",
    "gn:country_code":"KR",
    "gn:dem":39,
    "gn:feature_class":"P",
    "gn:feature_code":"PPL",
    "gn:name":"Salgoji",
    "gn:population":0,
    "gn:timezone":"Asia/Seoul",
    "iso:country":"KR",
    "name:und_x_variant":[
        "\uc0b4\uace0\uc9c0",
        "Salgoji"
    ],
    "wof:name":"Salgoji",
    "wof:placetype":"locality"
},
  "geometry": {"coordinates":[126.5419,36.913],"type":"Point"}
}