{
  "type": "Feature",
  "properties": {
    "gn:admin1_code":"5.0",
    "gn:asciiname":"Seizan",
    "gn:country_code":"KR",
    "gn:dem":118,
    "gn:feature_class":"P",
    "gn:feature_code":"PPL",
    "gn:name":"Seizan",
    "gn:population":0,
    "gn:timezone":"Asia/Seoul",
    "iso:country":"KR",
    "name:fra_x_preferred":[
        "Seizan"
    ],
    "name:und_x_variant":[
        "Ch\u2019\u014fngsan",
        "\uccad\uc0b0"
    ],
    "wof:name":"Seizan",
    "wof:placetype":"locality"
},
  "geometry": {"coordinates":[127.79130000000001,36.3484],"type":"Point"}
}