{
  "type": "Feature",
  "properties": {
    "gn:admin1_code":"6.0",
    "gn:asciiname":"Songji",
    "gn:country_code":"KR",
    "gn:dem":465,
    "gn:feature_class":"P",
    "gn:feature_code":"PPL",
    "gn:name":"Songji",
    "gn:population":0,
    "gn:timezone":"Asia/Seoul",
    "iso:country":"KR",
    "name:und_x_variant":[
        "Songjae",
        "Songch\u2019i",
        "Solch\u2019i"
    ],
    "wof:name":"Songji",
    "wof:placetype":"locality"
},
  "geometry": {"coordinates":[128.46666999999999,37.28333],"type":"Point"}
}