{
  "type": "Feature",
  "properties": {
    "gn:admin1_code":"17.0",
    "gn:asciiname":"Torimi",
    "gn:country_code":"KR",
    "gn:dem":15,
    "gn:feature_class":"P",
    "gn:feature_code":"PPL",
    "gn:name":"T\u014frimi",
    "gn:population":0,
    "gn:timezone":"Asia/Seoul",
    "iso:country":"KR",
    "name:und_x_variant":[
        "\ub354\ub9ac\ubbf8",
        "T\u014frimi"
    ],
    "wof:name":"Torimi",
    "wof:placetype":"locality"
},
  "geometry": {"coordinates":[127.0371,36.9107],"type":"Point"}
}