{
  "type": "Feature",
  "properties": {
    "gn:admin1_code":"14.0",
    "gn:asciiname":"Araetgeo",
    "gn:country_code":"KR",
    "gn:dem":128,
    "gn:feature_class":"P",
    "gn:feature_code":"PPL",
    "gn:name":"Araetgeo",
    "gn:population":0,
    "gn:timezone":"Asia/Seoul",
    "iso:country":"KR",
    "name:kor_x_preferred":[
        "\uc544\ub7ab\uac70"
    ],
    "wof:name":"Araetgeo",
    "wof:placetype":"locality"
},
  "geometry": {"coordinates":[128.69245000000001,36.62803],"type":"Point"}
}