{
  "type": "Feature",
  "properties": {
    "gn:admin1_code":"14.0",
    "gn:asciiname":"Chup'a",
    "gn:country_code":"KR",
    "gn:dem":209,
    "gn:feature_class":"P",
    "gn:feature_code":"PPL",
    "gn:name":"Chup\u2019a",
    "gn:population":0,
    "gn:timezone":"Asia/Seoul",
    "iso:country":"KR",
    "name:und_x_variant":[
        "\uc8fc\ud30c",
        "Chup\u2019a"
    ],
    "wof:name":"Chup'a",
    "wof:placetype":"locality"
},
  "geometry": {"coordinates":[129.05860000000001,36.6027],"type":"Point"}
}