{
  "type": "Feature",
  "properties": {
    "gn:admin1_code":"13.0",
    "gn:admin2_code":"Yongin-si",
    "gn:asciiname":"Oksal-li",
    "gn:country_code":"KR",
    "gn:dem":105,
    "gn:feature_class":"P",
    "gn:feature_code":"PPLL",
    "gn:name":"Oksal-li",
    "gn:population":0,
    "gn:timezone":"Asia/Seoul",
    "iso:country":"KR",
    "name:kor_x_preferred":[
        "\uc625\uc0b0\ub9ac"
    ],
    "name:und_x_variant":[
        "Oksan-ri"
    ],
    "wof:name":"Oksal-li",
    "wof:placetype":"locality"
},
  "geometry": {"coordinates":[127.39972,37.10667],"type":"Point"}
}