{
  "type": "Feature",
  "properties": {
    "gn:admin1_code":"13.0",
    "gn:asciiname":"Gangchangdong",
    "gn:country_code":"KR",
    "gn:dem":13,
    "gn:feature_class":"P",
    "gn:feature_code":"PPL",
    "gn:name":"Gangchangdong",
    "gn:population":0,
    "gn:timezone":"Asia/Seoul",
    "iso:country":"KR",
    "name:kor_x_preferred":[
        "\uac15\ucc3d\ub3d9"
    ],
    "wof:name":"Gangchangdong",
    "wof:placetype":"locality"
},
  "geometry": {"coordinates":[126.82254,37.40231],"type":"Point"}
}