{
  "type": "Feature",
  "properties": {
    "gn:admin1_code":"14.0",
    "gn:asciiname":"Wittaejang",
    "gn:country_code":"KR",
    "gn:dem":179,
    "gn:feature_class":"P",
    "gn:feature_code":"PPL",
    "gn:name":"Wittaejang",
    "gn:population":0,
    "gn:timezone":"Asia/Seoul",
    "iso:country":"KR",
    "name:kor_x_preferred":[
        "\uc717\ud0dc\uc7a5"
    ],
    "wof:name":"Wittaejang",
    "wof:placetype":"locality"
},
  "geometry": {"coordinates":[128.67431999999999,36.63898],"type":"Point"}
}