{
  "type": "Feature",
  "properties": {
    "gn:admin1_code":"14.0",
    "gn:asciiname":"Sego-ri",
    "gn:country_code":"KR",
    "gn:dem":109,
    "gn:feature_class":"P",
    "gn:feature_code":"PPL",
    "gn:name":"Seg\u014f-ri",
    "gn:population":0,
    "gn:timezone":"Asia/Seoul",
    "iso:country":"KR",
    "name:und_x_variant":[
        "Samg\u014fri",
        "\uc138\uac70\ub9ac",
        "Seg\u014fri-dong",
        "Seg\u014f-ri"
    ],
    "wof:name":"Sego-ri",
    "wof:placetype":"locality"
},
  "geometry": {"coordinates":[129.36760000000001,37.0407],"type":"Point"}
}