{
  "type": "Feature",
  "properties": {
    "gn:admin1_code":"13.0",
    "gn:asciiname":"Yoyeonpyeong",
    "gn:country_code":"KR",
    "gn:dem":44,
    "gn:feature_class":"P",
    "gn:feature_code":"PPL",
    "gn:name":"Yoyeonpyeong",
    "gn:population":0,
    "gn:timezone":"Asia/Seoul",
    "iso:country":"KR",
    "name:kor_x_preferred":[
        "\uc694\uc5f0\ud3c9"
    ],
    "wof:name":"Yoyeonpyeong",
    "wof:placetype":"locality"
},
  "geometry": {"coordinates":[127.17497,37.69974000000001],"type":"Point"}
}