{
  "type": "Feature",
  "properties": {
    "gn:admin1_code":"17.0",
    "gn:asciiname":"Namsanso",
    "gn:country_code":"KR",
    "gn:dem":93,
    "gn:feature_class":"P",
    "gn:feature_code":"PPL",
    "gn:name":"Namsanso",
    "gn:population":0,
    "gn:timezone":"Asia/Seoul",
    "iso:country":"KR",
    "name:kor_x_preferred":[
        "\ub0a8\uc0b0\uc18c"
    ],
    "wof:name":"Namsanso",
    "wof:placetype":"locality"
},
  "geometry": {"coordinates":[127.24986,36.41048],"type":"Point"}
}