{
  "type": "Feature",
  "properties": {
    "gn:admin1_code":"14.0",
    "gn:asciiname":"Araenmaeseong",
    "gn:country_code":"KR",
    "gn:dem":160,
    "gn:feature_class":"P",
    "gn:feature_code":"PPL",
    "gn:name":"Araenmaeseong",
    "gn:population":0,
    "gn:timezone":"Asia/Seoul",
    "iso:country":"KR",
    "name:kor_x_preferred":[
        "\uc544\ub7ab\ub9e4\uc131"
    ],
    "wof:name":"Araenmaeseong",
    "wof:placetype":"locality"
},
  "geometry": {"coordinates":[128.75226999999998,36.14948],"type":"Point"}
}