{
  "type": "Feature",
  "properties": {
    "gn:admin1_code":"20.0",
    "gn:asciiname":"Pisong",
    "gn:country_code":"KR",
    "gn:dem":31,
    "gn:feature_class":"P",
    "gn:feature_code":"PPL",
    "gn:name":"Pis\u014fng",
    "gn:population":0,
    "gn:timezone":"Asia/Seoul",
    "iso:country":"KR",
    "name:und_x_variant":[
        "\ube44\uc131",
        "Pis\u014fng"
    ],
    "wof:name":"Pisong",
    "wof:placetype":"locality"
},
  "geometry": {"coordinates":[128.25545,35.30775999999999],"type":"Point"}
}