{
  "type": "Feature",
  "properties": {
    "gn:admin1_code":"13.0",
    "gn:asciiname":"Pangmok",
    "gn:country_code":"KR",
    "gn:dem":54,
    "gn:feature_class":"P",
    "gn:feature_code":"PPL",
    "gn:name":"Pangmok",
    "gn:population":0,
    "gn:timezone":"Asia/Seoul",
    "iso:country":"KR",
    "name:und_x_variant":[
        "\ubc29\ubaa9",
        "Bangmok",
        "Pangmok"
    ],
    "wof:name":"Pangmok",
    "wof:placetype":"locality"
},
  "geometry": {"coordinates":[127.19278,37.10639000000001],"type":"Point"}
}