{
  "type": "Feature",
  "properties": {
    "gn:admin1_code":"14.0",
    "gn:asciiname":"Mullaesil",
    "gn:country_code":"KR",
    "gn:dem":108,
    "gn:feature_class":"P",
    "gn:feature_code":"PPL",
    "gn:name":"Mullaesil",
    "gn:population":0,
    "gn:timezone":"Asia/Seoul",
    "iso:country":"KR",
    "name:kor_x_preferred":[
        "\ubb38\ub798\uc2e4"
    ],
    "wof:name":"Mullaesil",
    "wof:placetype":"locality"
},
  "geometry": {"coordinates":[128.57061000000002,36.69227],"type":"Point"}
}