{
  "type": "Feature",
  "properties": {
    "gn:admin1_code":"15.0",
    "gn:asciiname":"Motmit",
    "gn:country_code":"KR",
    "gn:dem":84,
    "gn:feature_class":"P",
    "gn:feature_code":"PPL",
    "gn:name":"Motmit",
    "gn:population":0,
    "gn:timezone":"Asia/Seoul",
    "iso:country":"KR",
    "name:kor_x_preferred":[
        "\ubabb\ubc11"
    ],
    "wof:name":"Motmit",
    "wof:placetype":"locality"
},
  "geometry": {"coordinates":[128.54328999999998,35.96428],"type":"Point"}
}