{
  "type": "Feature",
  "properties": {
    "gn:admin1_code":"5.0",
    "gn:asciiname":"Kumwol-li",
    "gn:cc2":"KR",
    "gn:country_code":"KR",
    "gn:dem":240,
    "gn:feature_class":"P",
    "gn:feature_code":"PPL",
    "gn:name":"K\u016dmw\u014fl-li",
    "gn:population":0,
    "gn:timezone":"Asia/Seoul",
    "iso:country":"KR",
    "name:und_x_variant":[
        "K\u016dmw\u014fl-tong",
        "K\u016dmw\u014fl-li"
    ],
    "wof:name":"Kumwol-li",
    "wof:placetype":"locality"
},
  "geometry": {"coordinates":[127.83333,36.28333],"type":"Point"}
}