{
  "type": "Feature",
  "properties": {
    "gn:admin1_code":"6.0",
    "gn:asciiname":"Norumok",
    "gn:country_code":"KR",
    "gn:dem":222,
    "gn:feature_class":"P",
    "gn:feature_code":"PPL",
    "gn:name":"Norumok",
    "gn:population":0,
    "gn:timezone":"Asia/Seoul",
    "iso:country":"KR",
    "name:und_x_variant":[
        "\ub178\ub8e8\ubaa9"
    ],
    "wof:name":"Norumok",
    "wof:placetype":"locality"
},
  "geometry": {"coordinates":[128.19444999999999,38.06744000000001],"type":"Point"}
}