{
  "type": "Feature",
  "properties": {
    "gn:admin1_code":"5.0",
    "gn:asciiname":"Changnim-ni",
    "gn:cc2":"KR",
    "gn:country_code":"KR",
    "gn:dem":171,
    "gn:feature_class":"P",
    "gn:feature_code":"PPL",
    "gn:name":"Changnim-ni",
    "gn:population":0,
    "gn:timezone":"Asia/Seoul",
    "iso:country":"KR",
    "name:eng_x_preferred":[
        "Changnim"
    ],
    "name:eng_x_variant":[
        "Changnim-ni"
    ],
    "name:und_x_variant":[
        "Changnimnim",
        "Changnim-ni"
    ],
    "wof:name":"Changnim",
    "wof:placetype":"locality"
},
  "geometry": {"coordinates":[128.35444000000001,36.92222],"type":"Point"}
}