{
  "type": "Feature",
  "properties": {
    "gn:admin1_code":"5.0",
    "gn:asciiname":"Ungch'on",
    "gn:country_code":"KR",
    "gn:dem":105,
    "gn:feature_class":"P",
    "gn:feature_code":"PPL",
    "gn:name":"\u016cngch\u2019\u014fn",
    "gn:population":0,
    "gn:timezone":"Asia/Seoul",
    "iso:country":"KR",
    "name:und_x_variant":[
        "\uc751\ucc9c",
        "\u016cngch\u2019\u014fn"
    ],
    "wof:name":"Ungch'on",
    "wof:placetype":"locality"
},
  "geometry": {"coordinates":[127.5723,36.2887],"type":"Point"}
}