{
  "type": "Feature",
  "properties": {
    "gn:admin1_code":"14.0",
    "gn:asciiname":"T'onggumi",
    "gn:country_code":"KR",
    "gn:dem":65,
    "gn:feature_class":"P",
    "gn:feature_code":"PPL",
    "gn:name":"T\u2019onggumi",
    "gn:population":0,
    "gn:timezone":"Asia/Seoul",
    "iso:country":"KR",
    "name:kor_x_preferred":[
        "\ud1b5\uad6c\ubbf8"
    ],
    "name:kor_x_variant":[
        "T\u2019onggumi"
    ],
    "wof:name":"T'onggumi",
    "wof:placetype":"locality"
},
  "geometry": {"coordinates":[130.8579,37.4636],"type":"Point"}
}