{
  "type": "Feature",
  "properties": {
    "gn:admin1_code":"3.0",
    "gn:asciiname":"Sulsal-li",
    "gn:cc2":"KR",
    "gn:country_code":"KR",
    "gn:dem":10,
    "gn:feature_class":"P",
    "gn:feature_code":"PPL",
    "gn:name":"Sulsal-li",
    "gn:population":0,
    "gn:timezone":"Asia/Seoul",
    "iso:country":"KR",
    "name:und_x_variant":[
        "Musan-ni",
        "Sulsan-ni",
        "Sulsal-li"
    ],
    "wof:name":"Sulsal-li",
    "wof:placetype":"locality"
},
  "geometry": {"coordinates":[126.86611000000001,35.95778],"type":"Point"}
}