{
  "type": "Feature",
  "properties": {
    "gn:admin1_code":"13.0",
    "gn:asciiname":"Sangcheonggye",
    "gn:country_code":"KR",
    "gn:dem":146,
    "gn:feature_class":"P",
    "gn:feature_code":"PPL",
    "gn:name":"Sangcheonggye",
    "gn:population":0,
    "gn:timezone":"Asia/Seoul",
    "iso:country":"KR",
    "name:und_x_variant":[
        "\uc0c1\uccad\uacc4",
        "Sangcheonggye",
        "Sangch\u2019\u014fnggye"
    ],
    "wof:name":"Sangcheonggye",
    "wof:placetype":"locality"
},
  "geometry": {"coordinates":[127.01721999999999,37.4075],"type":"Point"}
}