{
  "type": "Feature",
  "properties": {
    "gn:admin1_code":"6.0",
    "gn:asciiname":"Toe-gol",
    "gn:country_code":"KR",
    "gn:dem":674,
    "gn:feature_class":"P",
    "gn:feature_code":"PPL",
    "gn:name":"Toe-gol",
    "gn:population":0,
    "gn:timezone":"Asia/Seoul",
    "iso:country":"KR",
    "name:kor_x_preferred":[
        "\ub418\uace8"
    ],
    "wof:name":"Toe-gol",
    "wof:placetype":"locality"
},
  "geometry": {"coordinates":[128.7552,37.4974],"type":"Point"}
}