{
  "type": "Feature",
  "properties": {
    "gn:admin1_code":"6.0",
    "gn:asciiname":"Kurap",
    "gn:country_code":"KR",
    "gn:dem":309,
    "gn:feature_class":"P",
    "gn:feature_code":"PPL",
    "gn:name":"Kurap",
    "gn:population":0,
    "gn:timezone":"Asia/Seoul",
    "iso:country":"KR",
    "name:kor_x_preferred":[
        "\uad74\uc55e"
    ],
    "name:und_x_variant":[
        "Kurap-mal",
        "Kurap"
    ],
    "wof:name":"Kurap",
    "wof:placetype":"locality"
},
  "geometry": {"coordinates":[128.44,37.3094],"type":"Point"}
}