{
  "type": "Feature",
  "properties": {
    "gn:admin1_code":"13.0",
    "gn:asciiname":"Dongye",
    "gn:country_code":"KR",
    "gn:dem":100,
    "gn:feature_class":"P",
    "gn:feature_code":"PPL",
    "gn:name":"Dongye",
    "gn:population":0,
    "gn:timezone":"Asia/Seoul",
    "iso:country":"KR",
    "name:kor_x_preferred":[
        "\ub3c8\uacc4"
    ],
    "name:und_x_variant":[
        "\ub3c8\uacc4\ub3d9",
        "Ton\u2019gye-dong",
        "Dongye"
    ],
    "wof:name":"Dongye",
    "wof:placetype":"locality"
},
  "geometry": {"coordinates":[127.04300000000001,37.82585],"type":"Point"}
}