{
  "type": "Feature",
  "properties": {
    "gn:admin1_code":"14.0",
    "gn:asciiname":"Songhak",
    "gn:country_code":"KR",
    "gn:dem":68,
    "gn:feature_class":"P",
    "gn:feature_code":"PPL",
    "gn:name":"Songhak",
    "gn:population":0,
    "gn:timezone":"Asia/Seoul",
    "iso:country":"KR",
    "name:kor_x_preferred":[
        "\uc1a1\ud559"
    ],
    "wof:name":"Songhak",
    "wof:placetype":"locality"
},
  "geometry": {"coordinates":[129.29839999999999,36.04365],"type":"Point"}
}