{
  "type": "Feature",
  "properties": {
    "gn:admin1_code":"17.0",
    "gn:asciiname":"Punt'o-gol",
    "gn:country_code":"KR",
    "gn:dem":65,
    "gn:feature_class":"P",
    "gn:feature_code":"PPL",
    "gn:name":"Punt\u2019o-gol",
    "gn:population":0,
    "gn:timezone":"Asia/Seoul",
    "iso:country":"KR",
    "name:und_x_variant":[
        "\ubd84\ud1a0\uace8",
        "Punt\u2019o-gol"
    ],
    "wof:name":"Punt'o-gol",
    "wof:placetype":"locality"
},
  "geometry": {"coordinates":[126.6969,36.497],"type":"Point"}
}