{
  "type": "Feature",
  "properties": {
    "gn:admin1_code":"14.0",
    "gn:asciiname":"Unggok",
    "gn:country_code":"KR",
    "gn:dem":98,
    "gn:feature_class":"P",
    "gn:feature_code":"PPL",
    "gn:name":"\u016cnggok",
    "gn:population":0,
    "gn:timezone":"Asia/Seoul",
    "iso:country":"KR",
    "name:und_x_variant":[
        "\uc751\uace1",
        "\u016cnggok"
    ],
    "wof:name":"Unggok",
    "wof:placetype":"locality"
},
  "geometry": {"coordinates":[128.1514,36.109],"type":"Point"}
}