{
  "type": "Feature",
  "properties": {
    "gn:admin1_code":"13.0",
    "gn:asciiname":"Bingjeongmal",
    "gn:country_code":"KR",
    "gn:dem":84,
    "gn:feature_class":"P",
    "gn:feature_code":"PPL",
    "gn:name":"Bingjeongmal",
    "gn:population":0,
    "gn:timezone":"Asia/Seoul",
    "iso:country":"KR",
    "name:kor_x_preferred":[
        "\ube59\uc815\ub9d0"
    ],
    "name:kor_x_variant":[
        "Pingj\u014fng-mal"
    ],
    "wof:name":"Bingjeongmal",
    "wof:placetype":"locality"
},
  "geometry": {"coordinates":[127.59491,37.12853],"type":"Point"}
}