{
  "type": "Feature",
  "properties": {
    "gn:admin1_code":"14.0",
    "gn:asciiname":"Majibawi",
    "gn:country_code":"KR",
    "gn:dem":474,
    "gn:feature_class":"P",
    "gn:feature_code":"PPL",
    "gn:name":"Majibawi",
    "gn:population":0,
    "gn:timezone":"Asia/Seoul",
    "iso:country":"KR",
    "name:kor_x_preferred":[
        "\ub9c8\uc9c0\ubc14\uc704"
    ],
    "wof:name":"Majibawi",
    "wof:placetype":"locality"
},
  "geometry": {"coordinates":[128.60398000000001,37.03888],"type":"Point"}
}