{
  "type": "Feature",
  "properties": {
    "gn:admin1_code":"16.0",
    "gn:asciiname":"Seokhyeon",
    "gn:country_code":"KR",
    "gn:dem":20,
    "gn:feature_class":"P",
    "gn:feature_code":"PPL",
    "gn:name":"Seokhyeon",
    "gn:population":0,
    "gn:timezone":"Asia/Seoul",
    "iso:country":"KR",
    "name:kor_x_preferred":[
        "\uc11d\ud604"
    ],
    "name:kor_x_variant":[
        "S\u014fkhy\u014fn"
    ],
    "wof:name":"Seokhyeon",
    "wof:placetype":"locality"
},
  "geometry": {"coordinates":[127.45265000000001,34.87787],"type":"Point"}
}