{
  "type": "Feature",
  "properties": {
    "gn:admin1_code":"5.0",
    "gn:asciiname":"Meogureokji",
    "gn:country_code":"KR",
    "gn:dem":107,
    "gn:feature_class":"P",
    "gn:feature_code":"PPL",
    "gn:name":"Meogureokji",
    "gn:population":0,
    "gn:timezone":"Asia/Seoul",
    "iso:country":"KR",
    "name:kor_x_preferred":[
        "\uba38\uad6c\ub7ed\uc9c0"
    ],
    "wof:name":"Meogureokji",
    "wof:placetype":"locality"
},
  "geometry": {"coordinates":[127.56336,36.96934],"type":"Point"}
}