{
  "type": "Feature",
  "properties": {
    "gn:admin1_code":"19.0",
    "gn:asciiname":"Hadeuri",
    "gn:country_code":"KR",
    "gn:dem":84,
    "gn:feature_class":"P",
    "gn:feature_code":"PPL",
    "gn:name":"Hadeuri",
    "gn:population":0,
    "gn:timezone":"Asia/Seoul",
    "iso:country":"KR",
    "name:kor_x_preferred":[
        "\ud558\ub4e4\uc774"
    ],
    "wof:name":"Hadeuri",
    "wof:placetype":"locality"
},
  "geometry": {"coordinates":[127.30347999999999,36.35786],"type":"Point"}
}