{
  "type": "Feature",
  "properties": {
    "gn:admin1_code":"6.0",
    "gn:asciiname":"Chunggan-mal",
    "gn:country_code":"KR",
    "gn:dem":113,
    "gn:feature_class":"P",
    "gn:feature_code":"PPL",
    "gn:name":"Chunggan-mal",
    "gn:population":0,
    "gn:timezone":"Asia/Seoul",
    "iso:country":"KR",
    "name:und_x_variant":[
        "\uc911\uac04\ub9d0",
        "Chunggan-mal"
    ],
    "wof:name":"Chunggan-mal",
    "wof:placetype":"locality"
},
  "geometry": {"coordinates":[127.6688,37.907],"type":"Point"}
}