{
  "type": "Feature",
  "properties": {
    "gn:admin1_code":"14.0",
    "gn:asciiname":"Sagol",
    "gn:country_code":"KR",
    "gn:dem":315,
    "gn:feature_class":"P",
    "gn:feature_code":"PPL",
    "gn:name":"Sagol",
    "gn:population":0,
    "gn:timezone":"Asia/Seoul",
    "iso:country":"KR",
    "name:kor_x_preferred":[
        "\uc0ac\uace8"
    ],
    "wof:name":"Sagol",
    "wof:placetype":"locality"
},
  "geometry": {"coordinates":[128.7193,36.97632],"type":"Point"}
}