{
  "type": "Feature",
  "properties": {
    "gn:admin1_code":"5.0",
    "gn:asciiname":"Ya-ch'on",
    "gn:country_code":"KR",
    "gn:dem":120,
    "gn:feature_class":"P",
    "gn:feature_code":"PPL",
    "gn:name":"Ya-ch\u2019on",
    "gn:population":0,
    "gn:timezone":"Asia/Seoul",
    "iso:country":"KR",
    "name:kor_x_preferred":[
        "\uc57c\ucd0c"
    ],
    "name:kor_x_variant":[
        "Ya-ch\u2019on"
    ],
    "wof:name":"Ya-ch'on",
    "wof:placetype":"locality"
},
  "geometry": {"coordinates":[127.8652,37.1588],"type":"Point"}
}