{
  "type": "Feature",
  "properties": {
    "gn:admin1_code":"6.0",
    "gn:asciiname":"Chagol",
    "gn:country_code":"KR",
    "gn:dem":157,
    "gn:feature_class":"P",
    "gn:feature_code":"PPL",
    "gn:name":"Chagol",
    "gn:population":0,
    "gn:timezone":"Asia/Seoul",
    "iso:country":"KR",
    "name:kor_x_preferred":[
        "\ucc28\uace8"
    ],
    "name:kor_x_variant":[
        "Ch\u2019a-gol"
    ],
    "wof:name":"Chagol",
    "wof:placetype":"locality"
},
  "geometry": {"coordinates":[128.71860000000001,37.9773],"type":"Point"}
}