{
  "type": "Feature",
  "properties": {
    "gn:admin1_code":"14.0",
    "gn:asciiname":"Jeoldwi",
    "gn:country_code":"KR",
    "gn:dem":123,
    "gn:feature_class":"P",
    "gn:feature_code":"PPL",
    "gn:name":"Jeoldwi",
    "gn:population":0,
    "gn:timezone":"Asia/Seoul",
    "iso:country":"KR",
    "name:kor_x_preferred":[
        "\uc808\ub4a4"
    ],
    "wof:name":"Jeoldwi",
    "wof:placetype":"locality"
},
  "geometry": {"coordinates":[128.53715,36.60527],"type":"Point"}
}