{
  "type": "Feature",
  "properties": {
    "gn:admin1_code":"16.0",
    "gn:asciiname":"Jungnim",
    "gn:country_code":"KR",
    "gn:dem":14,
    "gn:feature_class":"P",
    "gn:feature_code":"PPL",
    "gn:name":"Jungnim",
    "gn:population":0,
    "gn:timezone":"Asia/Seoul",
    "iso:country":"KR",
    "name:kor_x_preferred":[
        "\uc8fd\ub9bc"
    ],
    "name:und_x_variant":[
        "Chungnim",
        "Jungnim"
    ],
    "wof:name":"Jungnim",
    "wof:placetype":"locality"
},
  "geometry": {"coordinates":[127.38573,34.78834000000001],"type":"Point"}
}