{
  "type": "Feature",
  "properties": {
    "gn:admin1_code":"16.0",
    "gn:asciiname":"Sangnim",
    "gn:country_code":"KR",
    "gn:dem":80,
    "gn:feature_class":"P",
    "gn:feature_code":"PPL",
    "gn:name":"Sangnim",
    "gn:population":0,
    "gn:timezone":"Asia/Seoul",
    "iso:country":"KR",
    "name:kor_x_preferred":[
        "\uc0c1\ub9bc"
    ],
    "wof:name":"Sangnim",
    "wof:placetype":"locality"
},
  "geometry": {"coordinates":[126.85974,35.27301],"type":"Point"}
}