{
  "type": "Feature",
  "properties": {
    "gn:admin1_code":"16.0",
    "gn:asciiname":"Ho-dong",
    "gn:country_code":"KR",
    "gn:dem":37,
    "gn:feature_class":"P",
    "gn:feature_code":"PPL",
    "gn:name":"Ho-dong",
    "gn:population":0,
    "gn:timezone":"Asia/Seoul",
    "iso:country":"KR",
    "name:kor_x_preferred":[
        "\ud638\ub3d9"
    ],
    "wof:name":"Ho-dong",
    "wof:placetype":"locality"
},
  "geometry": {"coordinates":[126.85556,34.47111],"type":"Point"}
}