{
  "type": "Feature",
  "properties": {
    "gn:admin1_code":"16.0",
    "gn:asciiname":"Soundong",
    "gn:country_code":"KR",
    "gn:dem":70,
    "gn:feature_class":"P",
    "gn:feature_code":"PPL",
    "gn:name":"Soundong",
    "gn:population":0,
    "gn:timezone":"Asia/Seoul",
    "iso:country":"KR",
    "name:kor_x_preferred":[
        "\uc18c\uc740\ub3d9"
    ],
    "name:kor_x_variant":[
        "So\u016dn-dong"
    ],
    "wof:name":"Soundong",
    "wof:placetype":"locality"
},
  "geometry": {"coordinates":[126.67749999999999,34.61917],"type":"Point"}
}