{
  "type": "Feature",
  "properties": {
    "gn:admin1_code":"5.0",
    "gn:asciiname":"Mujuri",
    "gn:country_code":"KR",
    "gn:dem":290,
    "gn:feature_class":"P",
    "gn:feature_code":"PPL",
    "gn:name":"Mujuri",
    "gn:population":0,
    "gn:timezone":"Asia/Seoul",
    "iso:country":"KR",
    "name:kor_x_preferred":[
        "\ubb34\uc8fc\ub9ac"
    ],
    "wof:name":"Mujuri",
    "wof:placetype":"locality"
},
  "geometry": {"coordinates":[127.63356,36.69241],"type":"Point"}
}