{
  "type": "Feature",
  "properties": {
    "gn:admin1_code":"17.0",
    "gn:asciiname":"Houm-ni",
    "gn:country_code":"KR",
    "gn:dem":22,
    "gn:feature_class":"P",
    "gn:feature_code":"PPL",
    "gn:name":"Ho\u016dm-ni",
    "gn:population":0,
    "gn:timezone":"Asia/Seoul",
    "iso:country":"KR",
    "name:eng_x_preferred":[
        "Houm"
    ],
    "name:eng_x_variant":[
        "Houm-ni"
    ],
    "name:und_x_variant":[
        "\ud638\uc74c\ub9ac",
        "Ho\u016dm-ni"
    ],
    "wof:name":"Houm",
    "wof:placetype":"locality"
},
  "geometry": {"coordinates":[126.7197,36.7829],"type":"Point"}
}