{
  "type": "Feature",
  "properties": {
    "gn:admin1_code":"5.0",
    "gn:asciiname":"Junganggol",
    "gn:country_code":"KR",
    "gn:dem":303,
    "gn:feature_class":"P",
    "gn:feature_code":"PPL",
    "gn:name":"Junganggol",
    "gn:population":0,
    "gn:timezone":"Asia/Seoul",
    "iso:country":"KR",
    "name:kor_x_preferred":[
        "\uc911\uc559\uace8"
    ],
    "name:und_x_variant":[
        "Chungang-gol",
        "Junganggol"
    ],
    "wof:name":"Junganggol",
    "wof:placetype":"locality"
},
  "geometry": {"coordinates":[128.12783999999999,37.05988],"type":"Point"}
}