{
  "type": "Feature",
  "properties": {
    "gn:admin1_code":"17.0",
    "gn:asciiname":"Geumho",
    "gn:country_code":"KR",
    "gn:dem":38,
    "gn:feature_class":"P",
    "gn:feature_code":"PPL",
    "gn:name":"Geumho",
    "gn:population":0,
    "gn:timezone":"Asia/Seoul",
    "iso:country":"KR",
    "name:kor_x_preferred":[
        "\uae08\ud638"
    ],
    "wof:name":"Geumho",
    "wof:placetype":"locality"
},
  "geometry": {"coordinates":[127.09341000000001,36.74884],"type":"Point"}
}