{
  "type": "Feature",
  "properties": {
    "gn:admin1_code":"13.0",
    "gn:asciiname":"Banmaeul",
    "gn:country_code":"KR",
    "gn:dem":212,
    "gn:feature_class":"P",
    "gn:feature_code":"PPL",
    "gn:name":"Banmaeul",
    "gn:population":0,
    "gn:timezone":"Asia/Seoul",
    "iso:country":"KR",
    "name:kor_x_preferred":[
        "\ubc2d\ub9c8\uc744"
    ],
    "name:kor_x_variant":[
        "Pan-ma\u016dl"
    ],
    "wof:name":"Banmaeul",
    "wof:placetype":"locality"
},
  "geometry": {"coordinates":[127.37864999999999,37.85282],"type":"Point"}
}