{
  "type": "Feature",
  "properties": {
    "gn:admin1_code":"17.0",
    "gn:asciiname":"Munsan",
    "gn:country_code":"KR",
    "gn:dem":53,
    "gn:feature_class":"P",
    "gn:feature_code":"PPL",
    "gn:name":"Munsan",
    "gn:population":0,
    "gn:timezone":"Asia/Seoul",
    "iso:country":"KR",
    "name:und_x_variant":[
        "\ubb38\uc0b0",
        "Munsan"
    ],
    "wof:name":"Munsan",
    "wof:placetype":"locality"
},
  "geometry": {"coordinates":[126.7022,36.5406],"type":"Point"}
}