{
  "type": "Feature",
  "properties": {
    "gn:admin1_code":"17.0",
    "gn:asciiname":"Kujin",
    "gn:country_code":"KR",
    "gn:dem":30,
    "gn:feature_class":"P",
    "gn:feature_code":"PPL",
    "gn:name":"Kujin",
    "gn:population":0,
    "gn:timezone":"Asia/Seoul",
    "iso:country":"KR",
    "name:und_x_variant":[
        "\uad6c\uc9c4",
        "Kujin"
    ],
    "wof:name":"Kujin",
    "wof:placetype":"locality"
},
  "geometry": {"coordinates":[126.435,36.93889],"type":"Point"}
}