{
  "type": "Feature",
  "properties": {
    "gn:admin1_code":"13.0",
    "gn:asciiname":"Maehwa-ri",
    "gn:country_code":"KR",
    "gn:dem":18,
    "gn:feature_class":"P",
    "gn:feature_code":"PPL",
    "gn:name":"Maehwa-ri",
    "gn:population":0,
    "gn:timezone":"Asia/Seoul",
    "iso:country":"KR",
    "name:kor_x_preferred":[
        "\ub9e4\ud654\ub9ac"
    ],
    "wof:name":"Maehwa-ri",
    "wof:placetype":"locality"
},
  "geometry": {"coordinates":[126.70361,37.16889000000001],"type":"Point"}
}