{
  "type": "Feature",
  "properties": {
    "gn:admin1_code":"14.0",
    "gn:asciiname":"Onch'on-dong",
    "gn:country_code":"KR",
    "gn:dem":115,
    "gn:feature_class":"P",
    "gn:feature_code":"PPL",
    "gn:name":"Onch\u2019\u014fn-dong",
    "gn:population":0,
    "gn:timezone":"Asia/Seoul",
    "iso:country":"KR",
    "name:und_x_variant":[
        "\uc628\ucc9c\ub3d9",
        "Onj\u014fng-dong",
        "Onch\u2019\u014fn-dong"
    ],
    "wof:name":"Onch'on-dong",
    "wof:placetype":"locality"
},
  "geometry": {"coordinates":[129.28909999999999,37.0782],"type":"Point"}
}