{
  "type": "Feature",
  "properties": {
    "gn:admin1_code":"6.0",
    "gn:asciiname":"Teokgol",
    "gn:country_code":"KR",
    "gn:dem":287,
    "gn:feature_class":"P",
    "gn:feature_code":"PPL",
    "gn:name":"Teokgol",
    "gn:population":0,
    "gn:timezone":"Asia/Seoul",
    "iso:country":"KR",
    "name:kor_x_preferred":[
        "\ud131\uace8"
    ],
    "name:kor_x_variant":[
        "T\u2019\u014fk-kol"
    ],
    "wof:name":"Teokgol",
    "wof:placetype":"locality"
},
  "geometry": {"coordinates":[128.07943999999998,38.04694],"type":"Point"}
}