{
  "type": "Feature",
  "properties": {
    "gn:admin1_code":"20.0",
    "gn:asciiname":"Naech'on",
    "gn:country_code":"KR",
    "gn:dem":183,
    "gn:feature_class":"P",
    "gn:feature_code":"PPL",
    "gn:name":"Naech\u2019on",
    "gn:population":0,
    "gn:timezone":"Asia/Seoul",
    "iso:country":"KR",
    "wof:name":"Naech'on",
    "wof:placetype":"locality"
},
  "geometry": {"coordinates":[128.55916999999999,35.45889000000001],"type":"Point"}
}