{
  "type": "Feature",
  "properties": {
    "gn:admin1_code":"14.0",
    "gn:asciiname":"Handul",
    "gn:country_code":"KR",
    "gn:dem":110,
    "gn:feature_class":"P",
    "gn:feature_code":"PPL",
    "gn:name":"Hand\u016dl",
    "gn:population":0,
    "gn:timezone":"Asia/Seoul",
    "iso:country":"KR",
    "name:und_x_variant":[
        "\ud55c\ub4e4",
        "Hand\u016dl"
    ],
    "wof:name":"Handul",
    "wof:placetype":"locality"
},
  "geometry": {"coordinates":[129.15955,36.12025],"type":"Point"}
}