{
  "type": "Feature",
  "properties": {
    "gn:admin1_code":"16.0",
    "gn:asciiname":"Bunsan",
    "gn:country_code":"KR",
    "gn:dem":47,
    "gn:feature_class":"P",
    "gn:feature_code":"PPL",
    "gn:name":"Bunsan",
    "gn:population":0,
    "gn:timezone":"Asia/Seoul",
    "iso:country":"KR",
    "name:kor_x_preferred":[
        "\ubd84\uc0b0"
    ],
    "wof:name":"Bunsan",
    "wof:placetype":"locality"
},
  "geometry": {"coordinates":[126.66955,35.17403],"type":"Point"}
}