{
  "type": "Feature",
  "properties": {
    "gn:admin1_code":"17.0",
    "gn:asciiname":"Kundol",
    "gn:country_code":"KR",
    "gn:dem":38,
    "gn:feature_class":"P",
    "gn:feature_code":"PPL",
    "gn:name":"Kundol",
    "gn:population":0,
    "gn:timezone":"Asia/Seoul",
    "iso:country":"KR",
    "name:und_x_variant":[
        "\uad70\ub3cc",
        "Kundol"
    ],
    "wof:name":"Kundol",
    "wof:placetype":"locality"
},
  "geometry": {"coordinates":[126.94119999999999,36.2669],"type":"Point"}
}