{
  "type": "Feature",
  "properties": {
    "gn:admin1_code":"16.0",
    "gn:asciiname":"Danggok",
    "gn:country_code":"KR",
    "gn:dem":62,
    "gn:feature_class":"P",
    "gn:feature_code":"PPL",
    "gn:name":"Danggok",
    "gn:population":0,
    "gn:timezone":"Asia/Seoul",
    "iso:country":"KR",
    "name:kor_x_preferred":[
        "\ub2f9\uace1"
    ],
    "name:und_x_variant":[
        "Tanggok",
        "Danggok"
    ],
    "wof:name":"Danggok",
    "wof:placetype":"locality"
},
  "geometry": {"coordinates":[127.328,34.79652],"type":"Point"}
}