{
  "type": "Feature",
  "properties": {
    "iso:country":"KR",
    "name:kor_x_preferred":[
        "\uc11c\ub300\uc2e0\ub3d9"
    ],
    "name:kor_x_variant":[
        "\uc11c\ub300\uc2e0"
    ],
    "qs:gn_adm0_cc":"KR",
    "qs:gn_local":1838524,
    "qs:local_max":2765,
    "qs:local_sum":24552,
    "qs:localhoods":60,
    "qs:name":"\uc11c\ub300\uc2e0\ub3d9",
    "qs:name_adm0":"\ud55c\uad6d",
    "qs:name_adm1":"\ubd80\uc0b0",
    "qs:name_adm2":"\uc11c\uad6c",
    "qs:name_local":"\ubd80\uc0b0",
    "qs:photo_max":26,
    "qs:photo_sum":73,
    "qs:placetype":"Suburb",
    "qs:quad_count":7,
    "qs:woe_adm0":23424868,
    "qs:woe_adm1":2345968,
    "qs:woe_adm2":28289277,
    "qs:woe_lau":0,
    "qs:woe_local":1132447,
    "qs:woe_ver":"7.10.0",
    "wof:lang":[
        "kor"
    ],
    "wof:name":"\uc11c\ub300\uc2e0\ub3d9",
    "wof:placetype":"neighbourhood"
},
  "geometry": {"coordinates":[129.00692000000001,35.125048],"type":"Point"}
}