{
  "type": "Feature",
  "properties": {
    "gn:admin1_code":"13.0",
    "gn:asciiname":"Beommi",
    "gn:country_code":"KR",
    "gn:dem":93,
    "gn:feature_class":"P",
    "gn:feature_code":"PPL",
    "gn:name":"Beommi",
    "gn:population":0,
    "gn:timezone":"Asia/Seoul",
    "iso:country":"KR",
    "name:und_x_variant":[
        "\ubc94\ubbf8",
        "Beommi",
        "P\u014fmmi"
    ],
    "wof:name":"Beommi",
    "wof:placetype":"locality"
},
  "geometry": {"coordinates":[127.20389,37.28083],"type":"Point"}
}