{
  "type": "Feature",
  "properties": {
    "gn:admin1_code":"5.0",
    "gn:asciiname":"Sangipjang",
    "gn:country_code":"KR",
    "gn:dem":167,
    "gn:feature_class":"P",
    "gn:feature_code":"PPL",
    "gn:name":"Sangipjang",
    "gn:population":0,
    "gn:timezone":"Asia/Seoul",
    "iso:country":"KR",
    "name:kor_x_preferred":[
        "\uc0c1\uc785\uc7a5"
    ],
    "name:und_x_variant":[
        "Ipchang",
        "Sangipjang",
        "Sangipchang"
    ],
    "wof:name":"Sangipjang",
    "wof:placetype":"locality"
},
  "geometry": {"coordinates":[127.7578,37.0525],"type":"Point"}
}