{
  "type": "Feature",
  "properties": {
    "gn:admin1_code":"14.0",
    "gn:asciiname":"Twikkae",
    "gn:country_code":"KR",
    "gn:dem":129,
    "gn:feature_class":"P",
    "gn:feature_code":"PPL",
    "gn:name":"Twikkae",
    "gn:population":0,
    "gn:timezone":"Asia/Seoul",
    "iso:country":"KR",
    "name:und_x_variant":[
        "\ub4b7\uac1c",
        "Twikkae"
    ],
    "wof:name":"Twikkae",
    "wof:placetype":"locality"
},
  "geometry": {"coordinates":[128.17972,35.90127000000001],"type":"Point"}
}