{
  "type": "Feature",
  "properties": {
    "gn:admin1_code":"13.0",
    "gn:asciiname":"Bongam",
    "gn:country_code":"KR",
    "gn:dem":69,
    "gn:feature_class":"P",
    "gn:feature_code":"PPL",
    "gn:name":"Bongam",
    "gn:population":0,
    "gn:timezone":"Asia/Seoul",
    "iso:country":"KR",
    "name:kor_x_preferred":[
        "\uc548\ubd09\ubc14\uc704"
    ],
    "name:kor_x_variant":[
        "\ubd09\uc554"
    ],
    "name:und_x_variant":[
        "Anbongbawi",
        "Bongam"
    ],
    "wof:name":"Bongam",
    "wof:placetype":"locality"
},
  "geometry": {"coordinates":[127.61906,37.15075],"type":"Point"}
}