{
  "type": "Feature",
  "properties": {
    "gn:admin1_code":"17.0",
    "gn:asciiname":"Pyongp'ungi",
    "gn:country_code":"KR",
    "gn:dem":21,
    "gn:feature_class":"P",
    "gn:feature_code":"PPL",
    "gn:name":"Py\u014fngp\u2019ungi",
    "gn:population":0,
    "gn:timezone":"Asia/Seoul",
    "iso:country":"KR",
    "name:und_x_variant":[
        "Py\u014fngp\u2019ung-ni",
        "\ubcd1\ud48d\uc774",
        "Py\u014fngp\u2019ungi"
    ],
    "wof:name":"Pyongp'ungi",
    "wof:placetype":"locality"
},
  "geometry": {"coordinates":[126.37869999999999,36.5231],"type":"Point"}
}