{
  "type": "Feature",
  "properties": {
    "gn:admin1_code":"13.0",
    "gn:asciiname":"Taejeon-dong",
    "gn:country_code":"KR",
    "gn:dem":74,
    "gn:feature_class":"P",
    "gn:feature_code":"PPLL",
    "gn:name":"Taejeon-dong",
    "gn:population":0,
    "gn:timezone":"Asia/Seoul",
    "iso:country":"KR",
    "name:und_x_variant":[
        "\ud0dc\uc804\ub3d9",
        "Taejeon-dong",
        "T\u2019aej\u014fn-dong"
    ],
    "wof:name":"Taejeon-dong",
    "wof:placetype":"locality"
},
  "geometry": {"coordinates":[127.21666999999999,37.38611],"type":"Point"}
}