{
  "type": "Feature",
  "properties": {
    "gn:admin1_code":"14.0",
    "gn:asciiname":"Ching-ni",
    "gn:country_code":"KR",
    "gn:dem":26,
    "gn:feature_class":"P",
    "gn:feature_code":"PPL",
    "gn:name":"Ching-ni",
    "gn:population":0,
    "gn:timezone":"Asia/Seoul",
    "iso:country":"KR",
    "name:und_x_variant":[
        "\uc9c1\ub9ac",
        "Ching-ni"
    ],
    "wof:name":"Ching-ni",
    "wof:placetype":"locality"
},
  "geometry": {"coordinates":[128.31403999999998,35.72033],"type":"Point"}
}