{
  "type": "Feature",
  "properties": {
    "gn:admin1_code":"6.0",
    "gn:asciiname":"Tunjol-li",
    "gn:country_code":"KR",
    "gn:dem":133,
    "gn:feature_class":"P",
    "gn:feature_code":"PPL",
    "gn:name":"Tunj\u014fl-li",
    "gn:population":0,
    "gn:timezone":"Asia/Seoul",
    "iso:country":"KR",
    "name:kor_x_preferred":[
        "\ub454\uc804\ub9ac"
    ],
    "name:und_x_variant":[
        "Tunj\u014fl-li"
    ],
    "wof:name":"Tunjol-li",
    "wof:placetype":"locality"
},
  "geometry": {"coordinates":[128.55944,38.12139000000001],"type":"Point"}
}