{
  "type": "Feature",
  "properties": {
    "gn:admin1_code":"6.0",
    "gn:asciiname":"Angeonbae",
    "gn:country_code":"KR",
    "gn:dem":361,
    "gn:feature_class":"P",
    "gn:feature_code":"PPL",
    "gn:name":"Angeonbae",
    "gn:population":0,
    "gn:timezone":"Asia/Seoul",
    "iso:country":"KR",
    "name:kor_x_preferred":[
        "\uc548\uac74\ubc30"
    ],
    "name:und_x_variant":[
        "Sangg\u014fnbae"
    ],
    "wof:name":"Angeonbae",
    "wof:placetype":"locality"
},
  "geometry": {"coordinates":[127.98842999999999,38.28473],"type":"Point"}
}