{
  "type": "Feature",
  "properties": {
    "gn:admin1_code":"13.0",
    "gn:asciiname":"Tolgoji",
    "gn:country_code":"KR",
    "gn:dem":28,
    "gn:feature_class":"P",
    "gn:feature_code":"PPL",
    "gn:name":"Tolgoji",
    "gn:population":0,
    "gn:timezone":"Asia/Seoul",
    "iso:country":"KR",
    "name:und_x_variant":[
        "\ub3cc\uace0\uc9c0",
        "Dolgoji",
        "Tolgoji"
    ],
    "wof:name":"Tolgoji",
    "wof:placetype":"locality"
},
  "geometry": {"coordinates":[127.00360999999999,37.19333],"type":"Point"}
}