{
  "type": "Feature",
  "properties": {
    "gn:admin1_code":"20.0",
    "gn:asciiname":"Nuha",
    "gn:country_code":"KR",
    "gn:dem":68,
    "gn:feature_class":"P",
    "gn:feature_code":"PPL",
    "gn:name":"Nuha",
    "gn:population":0,
    "gn:timezone":"Asia/Seoul",
    "iso:country":"KR",
    "name:ceb_x_preferred":[
        "Nuha"
    ],
    "name:swe_x_preferred":[
        "Nuha"
    ],
    "name:und_x_variant":[
        "Nuha-ri",
        "\ub204\ud558",
        "Nuha"
    ],
    "wof:name":"Nuha",
    "wof:placetype":"locality"
},
  "geometry": {"coordinates":[128.26660000000001,35.52841],"type":"Point"}
}