{
  "type": "Feature",
  "properties": {
    "gn:admin1_code":"5.0",
    "gn:asciiname":"Chojeong",
    "gn:country_code":"KR",
    "gn:dem":102,
    "gn:feature_class":"P",
    "gn:feature_code":"PPL",
    "gn:name":"Chojeong",
    "gn:population":0,
    "gn:timezone":"Asia/Seoul",
    "iso:country":"KR",
    "name:kor_x_preferred":[
        "\ucd08\uc815"
    ],
    "wof:name":"Chojeong",
    "wof:placetype":"locality"
},
  "geometry": {"coordinates":[127.60104,36.72248],"type":"Point"}
}