{
  "type": "Feature",
  "properties": {
    "gn:admin1_code":"14.0",
    "gn:asciiname":"Paekkol",
    "gn:cc2":"KR",
    "gn:country_code":"KR",
    "gn:dem":142,
    "gn:feature_class":"P",
    "gn:feature_code":"PPL",
    "gn:name":"Paekkol",
    "gn:population":0,
    "gn:timezone":"Asia/Seoul",
    "iso:country":"KR",
    "name:und_x_variant":[
        "Paekkok",
        "Paekkol"
    ],
    "wof:name":"Paekkol",
    "wof:placetype":"locality"
},
  "geometry": {"coordinates":[128.40000000000001,36.55],"type":"Point"}
}