{
  "type": "Feature",
  "properties": {
    "gn:admin1_code":"16.0",
    "gn:asciiname":"Won'gi",
    "gn:country_code":"KR",
    "gn:dem":60,
    "gn:feature_class":"P",
    "gn:feature_code":"PPL",
    "gn:name":"W\u014fn\u2019gi",
    "gn:population":0,
    "gn:timezone":"Asia/Seoul",
    "iso:country":"KR",
    "name:kor_x_preferred":[
        "\uc6d0\uae30"
    ],
    "name:kor_x_variant":[
        "W\u014fn\u2019gi"
    ],
    "wof:name":"Won'gi",
    "wof:placetype":"locality"
},
  "geometry": {"coordinates":[126.93861,34.58917],"type":"Point"}
}