{
  "type": "Feature",
  "properties": {
    "gn:admin1_code":"5.0",
    "gn:asciiname":"Chabak-kol",
    "gn:country_code":"KR",
    "gn:dem":156,
    "gn:feature_class":"P",
    "gn:feature_code":"PPL",
    "gn:name":"Chabak-kol",
    "gn:population":0,
    "gn:timezone":"Asia/Seoul",
    "iso:country":"KR",
    "name:und_x_variant":[
        "\uc790\ubc15\uace8",
        "Chabak-kol"
    ],
    "wof:name":"Chabak-kol",
    "wof:placetype":"locality"
},
  "geometry": {"coordinates":[127.76090000000001,36.4411],"type":"Point"}
}