{
  "type": "Feature",
  "properties": {
    "gn:admin1_code":"17.0",
    "gn:asciiname":"Sanggoemok-tong",
    "gn:country_code":"KR",
    "gn:dem":260,
    "gn:feature_class":"P",
    "gn:feature_code":"PPL",
    "gn:name":"Sanggoemok-tong",
    "gn:population":0,
    "gn:timezone":"Asia/Seoul",
    "iso:country":"KR",
    "name:und_x_variant":[
        "\uc0c1\uad34\ubaa9\ub3d9",
        "Sanggoemok-tong"
    ],
    "wof:name":"Sanggoemok-tong",
    "wof:placetype":"locality"
},
  "geometry": {"coordinates":[127.377,36.0595],"type":"Point"}
}