{
  "type": "Feature",
  "properties": {
    "gn:admin1_code":"16.0",
    "gn:asciiname":"Sangye",
    "gn:country_code":"KR",
    "gn:dem":44,
    "gn:feature_class":"P",
    "gn:feature_code":"PPL",
    "gn:name":"Sangye",
    "gn:population":0,
    "gn:timezone":"Asia/Seoul",
    "iso:country":"KR",
    "name:kor_x_preferred":[
        "\uc0b0\uacc4"
    ],
    "name:und_x_variant":[
        "San\u2019gye-ri",
        "San\u2019gye",
        "Sangye"
    ],
    "wof:name":"Sangye",
    "wof:placetype":"locality"
},
  "geometry": {"coordinates":[126.74101,34.9084],"type":"Point"}
}