{
  "type": "Feature",
  "properties": {
    "gn:admin1_code":"16.0",
    "gn:asciiname":"Chukkkok",
    "gn:country_code":"KR",
    "gn:dem":14,
    "gn:feature_class":"P",
    "gn:feature_code":"PPL",
    "gn:name":"Chukkkok",
    "gn:population":0,
    "gn:timezone":"Asia/Seoul",
    "iso:country":"KR",
    "name:kor_x_preferred":[
        "\uc8fd\uace1"
    ],
    "name:und_x_variant":[
        "Chikky\u014d-ri",
        "Chukkyoilgu",
        "Chukkkok"
    ],
    "wof:name":"Chukkkok",
    "wof:placetype":"locality"
},
  "geometry": {"coordinates":[126.95083,34.56861],"type":"Point"}
}