{
  "type": "Feature",
  "properties": {
    "gn:admin1_code":"14.0",
    "gn:asciiname":"Hwarangt'o",
    "gn:country_code":"KR",
    "gn:dem":438,
    "gn:feature_class":"P",
    "gn:feature_code":"PPL",
    "gn:name":"Hwarangt\u2019\u014f",
    "gn:population":0,
    "gn:timezone":"Asia/Seoul",
    "iso:country":"KR",
    "name:und_x_variant":[
        "\ud654\ub791\ud130",
        "Hwarangt\u2019\u014f"
    ],
    "wof:name":"Hwarangt'o",
    "wof:placetype":"locality"
},
  "geometry": {"coordinates":[129.2106,36.6617],"type":"Point"}
}