{
  "type": "Feature",
  "properties": {
    "gn:admin1_code":"20.0",
    "gn:asciiname":"Kkaech'am-gol",
    "gn:country_code":"KR",
    "gn:dem":23,
    "gn:feature_class":"P",
    "gn:feature_code":"PPL",
    "gn:name":"Kkaech\u2019am-gol",
    "gn:population":0,
    "gn:timezone":"Asia/Seoul",
    "iso:country":"KR",
    "name:und_x_variant":[
        "\uae68\ucc38\uace8",
        "Kkaech\u2019am-gol"
    ],
    "wof:name":"Kkaech'am-gol",
    "wof:placetype":"locality"
},
  "geometry": {"coordinates":[128.35276000000002,34.96506],"type":"Point"}
}