{
  "type": "Feature",
  "properties": {
    "gn:admin1_code":"13.0",
    "gn:asciiname":"Seom-mal",
    "gn:country_code":"KR",
    "gn:dem":38,
    "gn:feature_class":"P",
    "gn:feature_code":"PPL",
    "gn:name":"Seom-mal",
    "gn:population":0,
    "gn:timezone":"Asia/Seoul",
    "iso:country":"KR",
    "name:kor_x_preferred":[
        "\uc12c\ub9d0"
    ],
    "name:und_x_variant":[
        "Seom-mal",
        "S\u014fm-mal"
    ],
    "wof:name":"Seom-mal",
    "wof:placetype":"locality"
},
  "geometry": {"coordinates":[127.38861,37.49778],"type":"Point"}
}