{
  "type": "Feature",
  "properties": {
    "gn:admin1_code":"16.0",
    "gn:asciiname":"Cheongneung",
    "gn:country_code":"KR",
    "gn:dem":33,
    "gn:feature_class":"P",
    "gn:feature_code":"PPL",
    "gn:name":"Cheongneung",
    "gn:population":0,
    "gn:timezone":"Asia/Seoul",
    "iso:country":"KR",
    "name:kor_x_preferred":[
        "\uccad\ub8e1"
    ],
    "name:kor_x_variant":[
        "Ch\u2019\u014fngnyong",
        "\uccad\ub2a5"
    ],
    "wof:name":"Cheongneung",
    "wof:placetype":"locality"
},
  "geometry": {"coordinates":[127.22657,34.79959],"type":"Point"}
}