{
  "type": "Feature",
  "properties": {
    "gn:admin1_code":"6.0",
    "gn:asciiname":"Naegapyeong",
    "gn:country_code":"KR",
    "gn:dem":358,
    "gn:feature_class":"P",
    "gn:feature_code":"PPL",
    "gn:name":"Naegapyeong",
    "gn:population":0,
    "gn:timezone":"Asia/Seoul",
    "iso:country":"KR",
    "name:kor_x_preferred":[
        "\ub0b4\uac00\ud3c9"
    ],
    "name:und_x_variant":[
        "Naegap\u2019y\u014fng",
        "Naegapyeong"
    ],
    "wof:name":"Naegapyeong",
    "wof:placetype":"locality"
},
  "geometry": {"coordinates":[128.34999999999999,38.19444],"type":"Point"}
}