{
  "type": "Feature",
  "properties": {
    "gn:admin1_code":"14.0",
    "gn:asciiname":"Chongnae-dong",
    "gn:country_code":"KR",
    "gn:dem":117,
    "gn:feature_class":"P",
    "gn:feature_code":"PPL",
    "gn:name":"Ch\u014fngnae-dong",
    "gn:population":0,
    "gn:timezone":"Asia/Seoul",
    "iso:country":"KR",
    "wof:name":"Chongnae-dong",
    "wof:placetype":"locality"
},
  "geometry": {"coordinates":[129.29889,35.78389],"type":"Point"}
}