{
  "type": "Feature",
  "properties": {
    "gn:admin1_code":"13.0",
    "gn:admin2_code":"P'aju-si",
    "gn:asciiname":"Saekkot",
    "gn:country_code":"KR",
    "gn:dem":12,
    "gn:feature_class":"P",
    "gn:feature_code":"PPL",
    "gn:name":"Saekkot",
    "gn:population":0,
    "gn:timezone":"Asia/Seoul",
    "iso:country":"KR",
    "name:kor_x_preferred":[
        "K\u2019\u016dnsaegot"
    ],
    "name:kor_x_variant":[
        "\uc0c8\uaf43"
    ],
    "name:und_x_variant":[
        "Sinwha-ri",
        "Sinhwa-ri",
        "Saek-kol",
        "Saekkot"
    ],
    "wof:name":"Saekkot",
    "wof:placetype":"locality"
},
  "geometry": {"coordinates":[126.76661,37.76114000000001],"type":"Point"}
}