{
  "type": "Feature",
  "properties": {
    "gn:admin1_code":"3.0",
    "gn:asciiname":"Puma",
    "gn:cc2":"KR",
    "gn:country_code":"KR",
    "gn:dem":9,
    "gn:feature_class":"P",
    "gn:feature_code":"PPL",
    "gn:name":"Puma",
    "gn:population":0,
    "gn:timezone":"Asia/Seoul",
    "iso:country":"KR",
    "name:und_x_variant":[
        "Maj\u014fn-ni",
        "Puma"
    ],
    "wof:name":"Puma",
    "wof:placetype":"locality"
},
  "geometry": {"coordinates":[126.93333,36.01667],"type":"Point"}
}