{
  "type": "Feature",
  "properties": {
    "gn:admin1_code":"5.0",
    "gn:asciiname":"Eomjeong",
    "gn:country_code":"KR",
    "gn:dem":51,
    "gn:feature_class":"P",
    "gn:feature_code":"PPL",
    "gn:name":"Eomjeong",
    "gn:population":0,
    "gn:timezone":"Asia/Seoul",
    "iso:country":"KR",
    "name:kor_x_preferred":[
        "\uc5c4\uc815"
    ],
    "wof:name":"Eomjeong",
    "wof:placetype":"locality"
},
  "geometry": {"coordinates":[127.34220999999999,36.64494000000001],"type":"Point"}
}