{
  "type": "Feature",
  "properties": {
    "gn:admin1_code":"13.0",
    "gn:asciiname":"Pyeongchon",
    "gn:country_code":"KR",
    "gn:dem":71,
    "gn:feature_class":"P",
    "gn:feature_code":"PPL",
    "gn:name":"Pyeongchon",
    "gn:population":0,
    "gn:timezone":"Asia/Seoul",
    "iso:country":"KR",
    "name:kor_x_preferred":[
        "\ud3c9\ucd0c"
    ],
    "name:kor_x_variant":[
        "\ud3c9\ucd0c\uc2e0\ub3c4\uc2dc"
    ],
    "wof:name":"Pyeongchon",
    "wof:placetype":"locality"
},
  "geometry": {"coordinates":[127.51079,37.84558],"type":"Point"}
}