{
  "type": "Feature",
  "properties": {
    "gn:admin1_code":"3.0",
    "gn:asciiname":"Nego-ri",
    "gn:country_code":"KR",
    "gn:dem":70,
    "gn:feature_class":"P",
    "gn:feature_code":"PPL",
    "gn:name":"Neg\u014f-ri",
    "gn:population":0,
    "gn:timezone":"Asia/Seoul",
    "iso:country":"KR",
    "name:und_x_variant":[
        "\ub124\uac70\ub9ac",
        "Neg\u014f-ri"
    ],
    "wof:name":"Nego-ri",
    "wof:placetype":"locality"
},
  "geometry": {"coordinates":[127.06592999999999,35.63278],"type":"Point"}
}