{
  "type": "Feature",
  "properties": {
    "gn:admin1_code":"6.0",
    "gn:asciiname":"Araeotbawi",
    "gn:country_code":"KR",
    "gn:dem":82,
    "gn:feature_class":"P",
    "gn:feature_code":"PPL",
    "gn:name":"Araeotbawi",
    "gn:population":0,
    "gn:timezone":"Asia/Seoul",
    "iso:country":"KR",
    "name:kor_x_preferred":[
        "\uc544\ub798\uc637\ubc14\uc704"
    ],
    "wof:name":"Araeotbawi",
    "wof:placetype":"locality"
},
  "geometry": {"coordinates":[127.68225,37.83209],"type":"Point"}
}