{
  "type": "Feature",
  "properties": {
    "gn:admin1_code":"6.0",
    "gn:asciiname":"Araetgwangchi",
    "gn:country_code":"KR",
    "gn:dem":257,
    "gn:feature_class":"P",
    "gn:feature_code":"PPL",
    "gn:name":"Araetgwangchi",
    "gn:population":0,
    "gn:timezone":"Asia/Seoul",
    "iso:country":"KR",
    "name:kor_x_preferred":[
        "\uc544\ub798\uad11\uce58"
    ],
    "name:kor_x_variant":[
        "Araegwangch\u2019i",
        "\uc544\ub7ab\uad11\uce58"
    ],
    "name:und_x_variant":[
        "Araegwangchi",
        "Araetgwangchi"
    ],
    "wof:name":"Araetgwangchi",
    "wof:placetype":"locality"
},
  "geometry": {"coordinates":[128.05365,38.12998],"type":"Point"}
}