{
  "type": "Feature",
  "properties": {
    "gn:admin1_code":"20.0",
    "gn:admin2_code":"K\u014fje-si",
    "gn:asciiname":"Chindu",
    "gn:country_code":"KR",
    "gn:dem":-9999,
    "gn:feature_class":"P",
    "gn:feature_code":"PPL",
    "gn:name":"Chindu",
    "gn:population":0,
    "gn:timezone":"Asia/Seoul",
    "iso:country":"KR",
    "name:und_x_variant":[
        "Ch\u014fndu"
    ],
    "wof:name":"Chindu",
    "wof:placetype":"locality"
},
  "geometry": {"coordinates":[128.52194,34.92444],"type":"Point"}
}