{
  "type": "Feature",
  "properties": {
    "gn:admin1_code":"14.0",
    "gn:asciiname":"Jeonghyeon",
    "gn:country_code":"KR",
    "gn:dem":122,
    "gn:feature_class":"P",
    "gn:feature_code":"PPL",
    "gn:name":"Jeonghyeon",
    "gn:population":0,
    "gn:timezone":"Asia/Seoul",
    "iso:country":"KR",
    "name:kor_x_preferred":[
        "\uc815\ud604"
    ],
    "wof:name":"Jeonghyeon",
    "wof:placetype":"locality"
},
  "geometry": {"coordinates":[128.11931000000001,36.67546],"type":"Point"}
}