{
  "type": "Feature",
  "properties": {
    "gn:admin1_code":"16.0",
    "gn:asciiname":"Unsan",
    "gn:country_code":"KR",
    "gn:dem":135,
    "gn:feature_class":"P",
    "gn:feature_code":"PPL",
    "gn:name":"Unsan",
    "gn:population":0,
    "gn:timezone":"Asia/Seoul",
    "iso:country":"KR",
    "name:kor_x_preferred":[
        "\uc6b4\uc0b0"
    ],
    "wof:name":"Unsan",
    "wof:placetype":"locality"
},
  "geometry": {"coordinates":[127.02163,34.99749],"type":"Point"}
}