{
  "type": "Feature",
  "properties": {
    "gn:admin1_code":"16.0",
    "gn:asciiname":"Dongnyeong",
    "gn:country_code":"KR",
    "gn:dem":60,
    "gn:feature_class":"P",
    "gn:feature_code":"PPL",
    "gn:name":"Dongnyeong",
    "gn:population":0,
    "gn:timezone":"Asia/Seoul",
    "iso:country":"KR",
    "name:kor_x_preferred":[
        "\ub3d9\ub839"
    ],
    "name:kor_x_variant":[
        "Tongny\u014fng"
    ],
    "wof:name":"Dongnyeong",
    "wof:placetype":"locality"
},
  "geometry": {"coordinates":[126.73778,34.69058],"type":"Point"}
}