{
  "type": "Feature",
  "properties": {
    "gn:admin1_code":"14.0",
    "gn:asciiname":"Chol-gol",
    "gn:country_code":"KR",
    "gn:dem":130,
    "gn:feature_class":"P",
    "gn:feature_code":"PPL",
    "gn:name":"Ch\u014fl-gol",
    "gn:population":0,
    "gn:timezone":"Asia/Seoul",
    "iso:country":"KR",
    "name:und_x_variant":[
        "\uc808\uace8",
        "Ch\u014fl-gol"
    ],
    "wof:name":"Chol-gol",
    "wof:placetype":"locality"
},
  "geometry": {"coordinates":[129.29369,37.10535],"type":"Point"}
}