{
  "type": "Feature",
  "properties": {
    "gn:admin1_code":"14.0",
    "gn:asciiname":"Hongmun-dong",
    "gn:country_code":"KR",
    "gn:dem":255,
    "gn:feature_class":"P",
    "gn:feature_code":"PPL",
    "gn:name":"Hongmun-dong",
    "gn:population":0,
    "gn:timezone":"Asia/Seoul",
    "iso:country":"KR",
    "name:kor_x_preferred":[
        "\ud64d\ubb38\ub3d9"
    ],
    "wof:name":"Hongmun-dong",
    "wof:placetype":"locality"
},
  "geometry": {"coordinates":[130.87289999999999,37.5298],"type":"Point"}
}