{
  "type": "Feature",
  "properties": {
    "gn:admin1_code":"14.0",
    "gn:asciiname":"Geopo",
    "gn:country_code":"KR",
    "gn:dem":483,
    "gn:feature_class":"P",
    "gn:feature_code":"PPL",
    "gn:name":"Geopo",
    "gn:population":0,
    "gn:timezone":"Asia/Seoul",
    "iso:country":"KR",
    "name:kor_x_preferred":[
        "\uac70\ud3ec"
    ],
    "wof:name":"Geopo",
    "wof:placetype":"locality"
},
  "geometry": {"coordinates":[128.88932,36.96224],"type":"Point"}
}