{
  "type": "Feature",
  "properties": {
    "gn:admin1_code":"13.0",
    "gn:asciiname":"Binggojae",
    "gn:country_code":"KR",
    "gn:dem":18,
    "gn:feature_class":"P",
    "gn:feature_code":"PPL",
    "gn:name":"Binggojae",
    "gn:population":0,
    "gn:timezone":"Asia/Seoul",
    "iso:country":"KR",
    "name:kor_x_preferred":[
        "\ube59\uace0\uc7ac"
    ],
    "name:und_x_variant":[
        "Pinggojae",
        "Binggojae"
    ],
    "wof:name":"Binggojae",
    "wof:placetype":"locality"
},
  "geometry": {"coordinates":[126.745,37.75194000000001],"type":"Point"}
}