{
  "type": "Feature",
  "properties": {
    "gn:admin1_code":"3.0",
    "gn:asciiname":"Kumma",
    "gn:country_code":"KR",
    "gn:dem":34,
    "gn:feature_class":"P",
    "gn:feature_code":"PPL",
    "gn:name":"K\u016dmma",
    "gn:population":0,
    "gn:timezone":"Asia/Seoul",
    "iso:country":"KR",
    "name:und_x_variant":[
        "\uae08\ub9c8",
        "K\u016dmma"
    ],
    "wof:name":"Kumma",
    "wof:placetype":"locality"
},
  "geometry": {"coordinates":[127.05303000000001,35.99148],"type":"Point"}
}