{
  "type": "Feature",
  "properties": {
    "gn:admin1_code":"14.0",
    "gn:asciiname":"Kalgun",
    "gn:country_code":"KR",
    "gn:dem":311,
    "gn:feature_class":"P",
    "gn:feature_code":"PPL",
    "gn:name":"Kalg\u016dn",
    "gn:population":0,
    "gn:timezone":"Asia/Seoul",
    "iso:country":"KR",
    "name:und_x_variant":[
        "\uac08\uadfc",
        "Kalg\u016dn"
    ],
    "wof:name":"Kalgun",
    "wof:placetype":"locality"
},
  "geometry": {"coordinates":[129.12418,36.21605],"type":"Point"}
}