{
  "type": "Feature",
  "properties": {
    "gn:admin1_code":"18.0",
    "gn:asciiname":"Sanjeong",
    "gn:country_code":"KR",
    "gn:dem":34,
    "gn:feature_class":"P",
    "gn:feature_code":"PPL",
    "gn:name":"Sanjeong",
    "gn:population":0,
    "gn:timezone":"Asia/Seoul",
    "iso:country":"KR",
    "name:kor_x_preferred":[
        "\uc0b0\uc815"
    ],
    "wof:name":"Sanjeong",
    "wof:placetype":"locality"
},
  "geometry": {"coordinates":[126.79264000000001,35.1735],"type":"Point"}
}