{
  "type": "Feature",
  "properties": {
    "gn:admin1_code":"17.0",
    "gn:asciiname":"Chiam",
    "gn:country_code":"KR",
    "gn:dem":199,
    "gn:feature_class":"P",
    "gn:feature_code":"PPL",
    "gn:name":"Chiam",
    "gn:population":0,
    "gn:timezone":"Asia/Seoul",
    "iso:country":"KR",
    "name:und_x_variant":[
        "\uc9c0\uc554",
        "Chiam"
    ],
    "wof:name":"Chiam",
    "wof:placetype":"locality"
},
  "geometry": {"coordinates":[127.3686,36.0807],"type":"Point"}
}