{
  "type": "Feature",
  "properties": {
    "gn:admin1_code":"17.0",
    "gn:asciiname":"An'gul",
    "gn:country_code":"KR",
    "gn:dem":93,
    "gn:feature_class":"P",
    "gn:feature_code":"PPL",
    "gn:name":"An\u2019gul",
    "gn:population":0,
    "gn:timezone":"Asia/Seoul",
    "iso:country":"KR",
    "name:und_x_variant":[
        "\uc548\uad74",
        "An\u2019gul"
    ],
    "wof:name":"An'gul",
    "wof:placetype":"locality"
},
  "geometry": {"coordinates":[126.7362,36.5335],"type":"Point"}
}