{
  "type": "Feature",
  "properties": {
    "gn:admin1_code":"17.0",
    "gn:asciiname":"Jangchon",
    "gn:country_code":"KR",
    "gn:dem":28,
    "gn:feature_class":"P",
    "gn:feature_code":"PPL",
    "gn:name":"Jangchon",
    "gn:population":0,
    "gn:timezone":"Asia/Seoul",
    "iso:country":"KR",
    "name:kor_x_preferred":[
        "\uc7a5\ucd0c"
    ],
    "wof:name":"Jangchon",
    "wof:placetype":"locality"
},
  "geometry": {"coordinates":[127.01915,36.75379],"type":"Point"}
}