{
  "type": "Feature",
  "properties": {
    "gn:admin1_code":"6.0",
    "gn:asciiname":"Pult'ant'o",
    "gn:country_code":"KR",
    "gn:dem":210,
    "gn:feature_class":"P",
    "gn:feature_code":"PPL",
    "gn:name":"Pult\u2019ant\u2019\u014f",
    "gn:population":0,
    "gn:timezone":"Asia/Seoul",
    "iso:country":"KR",
    "name:kor_x_preferred":[
        "\ubd88\ud0c4\ud130"
    ],
    "name:kor_x_variant":[
        "Pult\u2019ant\u2019\u014f"
    ],
    "wof:name":"Pult'ant'o",
    "wof:placetype":"locality"
},
  "geometry": {"coordinates":[127.98520000000001,37.5849],"type":"Point"}
}