{
  "type": "Feature",
  "properties": {
    "gn:admin1_code":"5.0",
    "gn:asciiname":"Witnakbatgol",
    "gn:country_code":"KR",
    "gn:dem":147,
    "gn:feature_class":"P",
    "gn:feature_code":"PPL",
    "gn:name":"Witnakbatgol",
    "gn:population":0,
    "gn:timezone":"Asia/Seoul",
    "iso:country":"KR",
    "name:kor_x_preferred":[
        "\uc717\ub2e5\ubc2d\uace8"
    ],
    "name:kor_x_variant":[
        "\uc717\ub099\ubc2d\uace8"
    ],
    "name:und_x_variant":[
        "Witdakbatgol",
        "Wittakpak-kol",
        "Witnakbatgol"
    ],
    "wof:name":"Witnakbatgol",
    "wof:placetype":"locality"
},
  "geometry": {"coordinates":[127.75302000000001,37.0504],"type":"Point"}
}