{
  "type": "Feature",
  "properties": {
    "gn:admin1_code":"20.0",
    "gn:asciiname":"Araetchagusil",
    "gn:country_code":"KR",
    "gn:dem":123,
    "gn:feature_class":"P",
    "gn:feature_code":"PPL",
    "gn:name":"Araetchagusil",
    "gn:population":0,
    "gn:timezone":"Asia/Seoul",
    "iso:country":"KR",
    "name:und_x_variant":[
        "\uc544\ub7ab\uc790\uad6c\uc2e4",
        "Araetchagusil"
    ],
    "wof:name":"Araetchagusil",
    "wof:placetype":"locality"
},
  "geometry": {"coordinates":[128.28617,35.08141],"type":"Point"}
}