{
  "type": "Feature",
  "properties": {
    "gn:admin1_code":"0.0",
    "gn:asciiname":"Paeksong-ni",
    "gn:country_code":"KR",
    "gn:dem":248,
    "gn:feature_class":"P",
    "gn:feature_code":"PPL",
    "gn:name":"Paeks\u014fng-ni",
    "gn:population":0,
    "gn:timezone":"Asia/Seoul",
    "iso:country":"KR",
    "name:kor_x_preferred":[
        "\ubc31\uc11d"
    ],
    "name:und_x_variant":[
        "Baekseok",
        "Paeks\u014fng-ni"
    ],
    "wof:name":"Paeksong-ni",
    "wof:placetype":"locality"
},
  "geometry": {"coordinates":[126.93333,35.53333],"type":"Point"}
}