{
  "type": "Feature",
  "properties": {
    "gn:admin1_code":"14.0",
    "gn:asciiname":"Chinsu-gol",
    "gn:country_code":"KR",
    "gn:dem":240,
    "gn:feature_class":"P",
    "gn:feature_code":"PPL",
    "gn:name":"Chinsu-gol",
    "gn:population":0,
    "gn:timezone":"Asia/Seoul",
    "iso:country":"KR",
    "name:und_x_variant":[
        "\uc9c4\uc218\uace8",
        "Chinsu-gol"
    ],
    "wof:name":"Chinsu-gol",
    "wof:placetype":"locality"
},
  "geometry": {"coordinates":[129.1173,36.5314],"type":"Point"}
}