{
  "type": "Feature",
  "properties": {
    "gn:admin1_code":"13.0",
    "gn:asciiname":"Dongsindong",
    "gn:country_code":"KR",
    "gn:dem":127,
    "gn:feature_class":"P",
    "gn:feature_code":"PPL",
    "gn:name":"Dongsindong",
    "gn:population":0,
    "gn:timezone":"Asia/Seoul",
    "iso:country":"KR",
    "name:kor_x_preferred":[
        "\ub3d9\uc2e0\ub3d9"
    ],
    "wof:name":"Dongsindong",
    "wof:placetype":"locality"
},
  "geometry": {"coordinates":[126.98184000000001,37.72161],"type":"Point"}
}