{
  "type": "Feature",
  "properties": {
    "gn:admin1_code":"13.0",
    "gn:asciiname":"Nogok",
    "gn:country_code":"KR",
    "gn:dem":113,
    "gn:feature_class":"P",
    "gn:feature_code":"PPL",
    "gn:name":"Nogok",
    "gn:population":0,
    "gn:timezone":"Asia/Seoul",
    "iso:country":"KR",
    "name:kor_x_preferred":[
        "\ub178\uad6d"
    ],
    "wof:name":"Nogok",
    "wof:placetype":"locality"
},
  "geometry": {"coordinates":[127.20641999999999,37.20768],"type":"Point"}
}