{
  "type": "Feature",
  "properties": {
    "gn:admin1_code":"14.0",
    "gn:asciiname":"Sach'ol-li",
    "gn:country_code":"KR",
    "gn:dem":109,
    "gn:feature_class":"P",
    "gn:feature_code":"PPL",
    "gn:name":"Sach\u2019\u014fl-li",
    "gn:population":0,
    "gn:timezone":"Asia/Seoul",
    "iso:country":"KR",
    "name:und_x_variant":[
        "Sach\u2019\u014fn-dong",
        "Sach\u2019\u014fl-li"
    ],
    "wof:name":"Sach'ol-li",
    "wof:placetype":"locality"
},
  "geometry": {"coordinates":[128.91889,36.04111],"type":"Point"}
}