{
  "type": "Feature",
  "properties": {
    "iso:country":"KR",
    "name:eng_x_preferred":[
        "Jangan-gu"
    ],
    "name:eng_x_variant":[
        "Jangangu",
        "Jangan-gu"
    ],
    "name:kor_x_preferred":[
        "\uc728\ucc9c\ub3d9"
    ],
    "name:kor_x_variant":[
        "\uc728\uc804\ub3d9",
        "\ucc9c\ucc9c\ub3d9"
    ],
    "name:und_x_variant":[
        "Yulcheon-dong"
    ],
    "qs:gn_fcode":"PPL",
    "qs:gn_local":0,
    "qs:gn_namadm1":"13",
    "qs:gn_name":"Yulcheon-dong",
    "qs:local_max":599,
    "qs:local_sum":2052,
    "qs:localhoods":9,
    "qs:name":"\uc728\ucc9c\ub3d9",
    "qs:name_adm0":"\ud55c\uad6d",
    "qs:name_adm1":"\uacbd\uae30\ub3c4",
    "qs:name_adm2":"\uc218\uc6d0\uc2dc",
    "qs:name_en":"Jangan-gu",
    "qs:name_lau":"\uc7a5\uc548\uad6c",
    "qs:name_local":"\uc7a5\uc548\uad6c",
    "qs:photo_max":41,
    "qs:photo_sum":174,
    "qs:placetype":"Suburb",
    "qs:quad_count":13,
    "qs:woe_adm0":23424868,
    "qs:woe_adm1":2345969,
    "qs:woe_adm2":28289297,
    "qs:woe_lau":28997195,
    "qs:woe_local":28997195,
    "qs:woe_ver":"7.10.0",
    "wof:lang":[
        "kor"
    ],
    "wof:name":"\uc728\ucc9c\ub3d9",
    "wof:placetype":"neighbourhood"
},
  "geometry": {"coordinates":[126.973319,37.296798],"type":"Point"}
}