{
  "type": "Feature",
  "properties": {
    "gn:admin1_code":"5.0",
    "gn:asciiname":"Hadaeeum",
    "gn:country_code":"KR",
    "gn:dem":55,
    "gn:feature_class":"P",
    "gn:feature_code":"PPL",
    "gn:name":"Hadaeeum",
    "gn:population":0,
    "gn:timezone":"Asia/Seoul",
    "iso:country":"KR",
    "name:kor_x_preferred":[
        "\ud558\ub300\uc74c"
    ],
    "wof:name":"Hadaeeum",
    "wof:placetype":"locality"
},
  "geometry": {"coordinates":[127.44464000000001,36.7556],"type":"Point"}
}