{
  "type": "Feature",
  "properties": {
    "gn:admin1_code":"13.0",
    "gn:asciiname":"Saeteo-mal",
    "gn:country_code":"KR",
    "gn:dem":79,
    "gn:feature_class":"P",
    "gn:feature_code":"PPL",
    "gn:name":"Saeteo-mal",
    "gn:population":0,
    "gn:timezone":"Asia/Seoul",
    "iso:country":"KR",
    "name:und_x_variant":[
        "\uc0c8\ud130\ub9d0",
        "Saeteo-mal",
        "Saet\u2019\u014f-mal"
    ],
    "wof:name":"Saeteo-mal",
    "wof:placetype":"locality"
},
  "geometry": {"coordinates":[127.15639,37.42139],"type":"Point"}
}