{
  "type": "Feature",
  "properties": {
    "gn:admin1_code":"17.0",
    "gn:asciiname":"Sangjangch'on",
    "gn:country_code":"KR",
    "gn:dem":158,
    "gn:feature_class":"P",
    "gn:feature_code":"PPL",
    "gn:name":"Sangjangch\u2019\u014fn",
    "gn:population":0,
    "gn:timezone":"Asia/Seoul",
    "iso:country":"KR",
    "name:und_x_variant":[
        "Sangjangch\u2019\u014fn-ni",
        "Sang-changch\u2019\u014fn",
        "Sangjangch\u2019\u014fn"
    ],
    "wof:name":"Sangjangch'on",
    "wof:placetype":"locality"
},
  "geometry": {"coordinates":[126.93333,36.58333],"type":"Point"}
}