{
  "type": "Feature",
  "properties": {
    "gn:admin1_code":"20.0",
    "gn:asciiname":"Pundu-gol",
    "gn:country_code":"KR",
    "gn:dem":56,
    "gn:feature_class":"P",
    "gn:feature_code":"PPL",
    "gn:name":"Pundu-gol",
    "gn:population":0,
    "gn:timezone":"Asia/Seoul",
    "iso:country":"KR",
    "name:und_x_variant":[
        "\ubd84\ub450\uace8",
        "Pundu-gol"
    ],
    "wof:name":"Pundu-gol",
    "wof:placetype":"locality"
},
  "geometry": {"coordinates":[128.49485000000001,35.50438],"type":"Point"}
}