{
  "type": "Feature",
  "properties": {
    "gn:admin1_code":"14.0",
    "gn:asciiname":"Yangjam",
    "gn:country_code":"KR",
    "gn:dem":180,
    "gn:feature_class":"P",
    "gn:feature_code":"PPL",
    "gn:name":"Yangjam",
    "gn:population":0,
    "gn:timezone":"Asia/Seoul",
    "iso:country":"KR",
    "name:kor_x_preferred":[
        "\uc591\uc7a0"
    ],
    "wof:name":"Yangjam",
    "wof:placetype":"locality"
},
  "geometry": {"coordinates":[128.79589999999999,36.67045],"type":"Point"}
}