{
  "type": "Feature",
  "properties": {
    "gn:admin1_code":"6.0",
    "gn:asciiname":"Saeil",
    "gn:country_code":"KR",
    "gn:dem":125,
    "gn:feature_class":"P",
    "gn:feature_code":"PPL",
    "gn:name":"Saeil",
    "gn:population":0,
    "gn:timezone":"Asia/Seoul",
    "iso:country":"KR",
    "name:kor_x_preferred":[
        "\uc0c8\uc77c"
    ],
    "name:und_x_variant":[
        "Sail",
        "Araesail",
        "Saeil"
    ],
    "wof:name":"Saeil",
    "wof:placetype":"locality"
},
  "geometry": {"coordinates":[127.85472,37.45139],"type":"Point"}
}