{
  "type": "Feature",
  "properties": {
    "gn:admin1_code":"14.0",
    "gn:asciiname":"Cheongchon",
    "gn:country_code":"KR",
    "gn:dem":47,
    "gn:feature_class":"P",
    "gn:feature_code":"PPL",
    "gn:name":"Cheongchon",
    "gn:population":0,
    "gn:timezone":"Asia/Seoul",
    "iso:country":"KR",
    "name:kor_x_preferred":[
        "\uccad\ucc9c"
    ],
    "wof:name":"Cheongchon",
    "wof:placetype":"locality"
},
  "geometry": {"coordinates":[128.76232999999999,35.88026],"type":"Point"}
}