{
  "type": "Feature",
  "properties": {
    "gn:admin1_code":"16.0",
    "gn:asciiname":"Eobul",
    "gn:country_code":"KR",
    "gn:dem":12,
    "gn:feature_class":"P",
    "gn:feature_code":"PPL",
    "gn:name":"Eobul",
    "gn:population":0,
    "gn:timezone":"Asia/Seoul",
    "iso:country":"KR",
    "name:kor_x_preferred":[
        "\uc5b4\ubd88"
    ],
    "name:und_x_variant":[
        "\u014ebul"
    ],
    "wof:name":"Eobul",
    "wof:placetype":"locality"
},
  "geometry": {"coordinates":[126.47333,34.33889],"type":"Point"}
}