{
  "type": "Feature",
  "properties": {
    "gn:admin1_code":"3.0",
    "gn:asciiname":"Chongp'yon",
    "gn:country_code":"KR",
    "gn:dem":39,
    "gn:feature_class":"P",
    "gn:feature_code":"PPL",
    "gn:name":"Chongp\u2019y\u014fn",
    "gn:population":0,
    "gn:timezone":"Asia/Seoul",
    "iso:country":"KR",
    "name:und_x_variant":[
        "\uc885\ud3b8",
        "Chongp\u2019y\u014fn"
    ],
    "wof:name":"Chongp'yon",
    "wof:placetype":"locality"
},
  "geometry": {"coordinates":[127.04151,36.00054],"type":"Point"}
}