{
  "type": "Feature",
  "properties": {
    "gn:admin1_code":"13.0",
    "gn:admin2_code":"P'aju-si",
    "gn:asciiname":"Jingol",
    "gn:country_code":"KR",
    "gn:dem":63,
    "gn:feature_class":"P",
    "gn:feature_code":"PPL",
    "gn:name":"Jingol",
    "gn:population":0,
    "gn:timezone":"Asia/Seoul",
    "iso:country":"KR",
    "name:kor_x_preferred":[
        "\uc9c4\uace8"
    ],
    "name:und_x_variant":[
        "Chin-gol"
    ],
    "wof:name":"Jingol",
    "wof:placetype":"locality"
},
  "geometry": {"coordinates":[126.82722,37.83722],"type":"Point"}
}