{
  "type": "Feature",
  "properties": {
    "gn:country":"KR",
    "gn:fcode":"ADM3",
    "gn:population":0,
    "iso:country":"KR",
    "name:eng_x_preferred":[
        "Pyeongchang-eup"
    ],
    "name:kor_x_preferred":[
        "\ud3c9\ucc3d\uc74d"
    ],
    "name:kor_x_variant":[
        "P\u2019y\u014fngch\u2019ang-\u016dp",
        "\u5e73\u660c\u9091"
    ],
    "qs:name":"P\u2019y\u014fngch\u2019ang-\u016dp",
    "qs:photos_9r":0,
    "qs:photos_sr":0,
    "qs:pop_sr":"0",
    "wof:name":"P\u2019y\u014fngch\u2019ang-\u016dp",
    "wof:placetype":"localadmin",
    "wof:population":0
},
  "geometry": {"coordinates":[128.40092999999999,37.35873],"type":"Point"}
}