{
  "type": "Feature",
  "properties": {
    "gn:admin1_code":"17.0",
    "gn:asciiname":"Buyeo-eup",
    "gn:country_code":"KR",
    "gn:dem":20,
    "gn:feature_class":"P",
    "gn:feature_code":"PPL",
    "gn:name":"Buyeo-eup",
    "gn:population":0,
    "gn:timezone":"Asia/Seoul",
    "iso:country":"KR",
    "wof:name":"Buyeo-eup",
    "wof:placetype":"locality"
},
  "geometry": {"coordinates":[126.91136000000002,36.27531],"type":"Point"}
}