{
  "type": "Feature",
  "properties": {
    "gn:admin1_code":"13.0",
    "gn:asciiname":"Myeokgok-ri",
    "gn:country_code":"KR",
    "gn:dem":70,
    "gn:feature_class":"P",
    "gn:feature_code":"PPL",
    "gn:name":"Myeokgok-ri",
    "gn:population":0,
    "gn:timezone":"Asia/Seoul",
    "iso:country":"KR",
    "name:kor_x_preferred":[
        "\uba71\uace1\ub9ac"
    ],
    "name:und_x_variant":[
        "Myeokgok-ri",
        "My\u014fkkong-ni"
    ],
    "wof:name":"Myeokgok-ri",
    "wof:placetype":"locality"
},
  "geometry": {"coordinates":[127.66388999999999,37.25972],"type":"Point"}
}