{
  "type": "Feature",
  "properties": {
    "gn:admin1_code":"16.0",
    "gn:asciiname":"Sanghwachon",
    "gn:country_code":"KR",
    "gn:dem":168,
    "gn:feature_class":"P",
    "gn:feature_code":"PPL",
    "gn:name":"Sanghwachon",
    "gn:population":0,
    "gn:timezone":"Asia/Seoul",
    "iso:country":"KR",
    "name:kor_x_preferred":[
        "\uc0c1\ud654\ucd0c"
    ],
    "name:kor_x_variant":[
        "Sanghwach\u2019on"
    ],
    "wof:name":"Sanghwachon",
    "wof:placetype":"locality"
},
  "geometry": {"coordinates":[127.09483,34.8295],"type":"Point"}
}