{
  "type": "Feature",
  "properties": {
    "gn:admin1_code":"5.0",
    "gn:asciiname":"Mundong-ni",
    "gn:country_code":"KR",
    "gn:dem":123,
    "gn:feature_class":"P",
    "gn:feature_code":"PPL",
    "gn:name":"Mund\u014fng-ni",
    "gn:population":0,
    "gn:timezone":"Asia/Seoul",
    "iso:country":"KR",
    "name:und_x_variant":[
        "\ubb38\ub355\ub9ac",
        "Mund\u014fng-ni"
    ],
    "wof:name":"Mundong-ni",
    "wof:placetype":"locality"
},
  "geometry": {"coordinates":[127.51819999999999,36.466],"type":"Point"}
}