{
  "type": "Feature",
  "properties": {
    "gn:admin1_code":"6.0",
    "gn:asciiname":"Damanmal",
    "gn:country_code":"KR",
    "gn:dem":245,
    "gn:feature_class":"P",
    "gn:feature_code":"PPL",
    "gn:name":"Damanmal",
    "gn:population":0,
    "gn:timezone":"Asia/Seoul",
    "iso:country":"KR",
    "name:kor_x_preferred":[
        "\ub2f4\uc548\ub9d0"
    ],
    "wof:name":"Damanmal",
    "wof:placetype":"locality"
},
  "geometry": {"coordinates":[127.96845,38.16214],"type":"Point"}
}