{
  "type": "Feature",
  "properties": {
    "gn:admin1_code":"5.0",
    "gn:asciiname":"Gisogol",
    "gn:country_code":"KR",
    "gn:dem":334,
    "gn:feature_class":"P",
    "gn:feature_code":"PPL",
    "gn:name":"Gisogol",
    "gn:population":0,
    "gn:timezone":"Asia/Seoul",
    "iso:country":"KR",
    "name:kor_x_preferred":[
        "\uae30\uc18c\uace8"
    ],
    "name:und_x_variant":[
        "Kiso-gol",
        "Gisogol"
    ],
    "wof:name":"Gisogol",
    "wof:placetype":"locality"
},
  "geometry": {"coordinates":[128.11335,37.05616],"type":"Point"}
}