{
  "type": "Feature",
  "properties": {
    "gn:admin1_code":"13.0",
    "gn:asciiname":"Achiul",
    "gn:country_code":"KR",
    "gn:dem":16,
    "gn:feature_class":"P",
    "gn:feature_code":"PPL",
    "gn:name":"Achiul",
    "gn:population":0,
    "gn:timezone":"Asia/Seoul",
    "iso:country":"KR",
    "name:kor_x_preferred":[
        "\uc544\uce58\uc6b8"
    ],
    "name:und_x_variant":[
        "\uc544\uce58\uc6b8",
        "Ach\u2019iul",
        "Achiul"
    ],
    "wof:name":"Achiul",
    "wof:placetype":"locality"
},
  "geometry": {"coordinates":[127.12474,37.57252],"type":"Point"}
}