{
  "type": "Feature",
  "properties": {
    "gn:admin1_code":"14.0",
    "gn:asciiname":"Chigyong",
    "gn:country_code":"KR",
    "gn:dem":123,
    "gn:feature_class":"P",
    "gn:feature_code":"PPL",
    "gn:name":"Chigy\u014fng",
    "gn:population":0,
    "gn:timezone":"Asia/Seoul",
    "iso:country":"KR",
    "name:und_x_variant":[
        "\uc9c0\uacbd",
        "Chigy\u014fng"
    ],
    "wof:name":"Chigyong",
    "wof:placetype":"locality"
},
  "geometry": {"coordinates":[129.02012999999999,36.03763],"type":"Point"}
}