{
  "type": "Feature",
  "properties": {
    "gn:admin1_code":"17.0",
    "gn:asciiname":"Winnongjang",
    "gn:country_code":"KR",
    "gn:dem":25,
    "gn:feature_class":"P",
    "gn:feature_code":"PPL",
    "gn:name":"Winnongjang",
    "gn:population":0,
    "gn:timezone":"Asia/Seoul",
    "iso:country":"KR",
    "name:und_x_variant":[
        "\uc717\ub18d\uc7a5",
        "Winnongjang"
    ],
    "wof:name":"Winnongjang",
    "wof:placetype":"locality"
},
  "geometry": {"coordinates":[126.72539999999999,36.735],"type":"Point"}
}