{
  "type": "Feature",
  "properties": {
    "gn:admin1_code":"6.0",
    "gn:asciiname":"Naptok",
    "gn:country_code":"KR",
    "gn:dem":424,
    "gn:feature_class":"P",
    "gn:feature_code":"PPL",
    "gn:name":"Napt\u014fk",
    "gn:population":0,
    "gn:timezone":"Asia/Seoul",
    "iso:country":"KR",
    "name:kor_x_preferred":[
        "\ub0a9\ub355"
    ],
    "name:kor_x_variant":[
        "Napt\u014fk"
    ],
    "wof:name":"Naptok",
    "wof:placetype":"locality"
},
  "geometry": {"coordinates":[128.66139999999999,37.4003],"type":"Point"}
}