{
  "type": "Feature",
  "properties": {
    "gn:admin1_code":"14.0",
    "gn:asciiname":"Nomun-gol",
    "gn:country_code":"KR",
    "gn:dem":297,
    "gn:feature_class":"P",
    "gn:feature_code":"PPL",
    "gn:name":"N\u014fmun-gol",
    "gn:population":0,
    "gn:timezone":"Asia/Seoul",
    "iso:country":"KR",
    "name:und_x_variant":[
        "\ub108\ubb38\uace8",
        "N\u014fmun-gol"
    ],
    "wof:name":"Nomun-gol",
    "wof:placetype":"locality"
},
  "geometry": {"coordinates":[129.04339999999999,36.706],"type":"Point"}
}