{
  "type": "Feature",
  "properties": {
    "gn:admin1_code":"5.0",
    "gn:asciiname":"Chinbol",
    "gn:country_code":"KR",
    "gn:dem":121,
    "gn:feature_class":"P",
    "gn:feature_code":"PPL",
    "gn:name":"Chinb\u014fl",
    "gn:population":0,
    "gn:timezone":"Asia/Seoul",
    "iso:country":"KR",
    "name:und_x_variant":[
        "\uc9c4\ubc8c",
        "Chinb\u014fl"
    ],
    "wof:name":"Chinbol",
    "wof:placetype":"locality"
},
  "geometry": {"coordinates":[127.6844,36.3414],"type":"Point"}
}