{
  "type": "Feature",
  "properties": {
    "gn:admin1_code":"17.0",
    "gn:asciiname":"Twik-gol",
    "gn:country_code":"KR",
    "gn:dem":48,
    "gn:feature_class":"P",
    "gn:feature_code":"PPL",
    "gn:name":"Twik-gol",
    "gn:population":0,
    "gn:timezone":"Asia/Seoul",
    "iso:country":"KR",
    "name:und_x_variant":[
        "\ub4b7\uace8",
        "Twik-gol"
    ],
    "wof:name":"Twik-gol",
    "wof:placetype":"locality"
},
  "geometry": {"coordinates":[126.7015,36.7836],"type":"Point"}
}