{
  "type": "Feature",
  "properties": {
    "gn:admin1_code":"6.0",
    "gn:asciiname":"Yok-kol",
    "gn:country_code":"KR",
    "gn:dem":185,
    "gn:feature_class":"P",
    "gn:feature_code":"PPL",
    "gn:name":"Yok-kol",
    "gn:population":0,
    "gn:timezone":"Asia/Seoul",
    "iso:country":"KR",
    "name:und_x_variant":[
        "\uc6a7\uace8",
        "Yok-kol"
    ],
    "wof:name":"Yok-kol",
    "wof:placetype":"locality"
},
  "geometry": {"coordinates":[127.64861000000001,38.10111],"type":"Point"}
}