{
  "type": "Feature",
  "properties": {
    "gn:admin1_code":"17.0",
    "gn:asciiname":"Misil",
    "gn:country_code":"KR",
    "gn:dem":59,
    "gn:feature_class":"P",
    "gn:feature_code":"PPL",
    "gn:name":"Misil",
    "gn:population":0,
    "gn:timezone":"Asia/Seoul",
    "iso:country":"KR",
    "name:und_x_variant":[
        "\ubbf8\uc2e4",
        "Misil"
    ],
    "wof:name":"Misil",
    "wof:placetype":"locality"
},
  "geometry": {"coordinates":[126.80119999999999,36.5542],"type":"Point"}
}