{
  "type": "Feature",
  "properties": {
    "gn:admin1_code":"17.0",
    "gn:asciiname":"Hongam",
    "gn:country_code":"KR",
    "gn:dem":120,
    "gn:feature_class":"P",
    "gn:feature_code":"PPL",
    "gn:name":"Hongam",
    "gn:population":0,
    "gn:timezone":"Asia/Seoul",
    "iso:country":"KR",
    "name:und_x_variant":[
        "Hongam-my\u014fn",
        "Hongam-ni",
        "\ud64d\uc554",
        "Hongam"
    ],
    "wof:name":"Hongam",
    "wof:placetype":"locality"
},
  "geometry": {"coordinates":[126.599,36.6604],"type":"Point"}
}