{
  "type": "Feature",
  "properties": {
    "gn:admin1_code":"16.0",
    "gn:asciiname":"Yongban",
    "gn:country_code":"KR",
    "gn:dem":41,
    "gn:feature_class":"P",
    "gn:feature_code":"PPL",
    "gn:name":"Yongban",
    "gn:population":0,
    "gn:timezone":"Asia/Seoul",
    "iso:country":"KR",
    "name:kor_x_preferred":[
        "\uc6a9\ubc18"
    ],
    "name:und_x_variant":[
        "Yongban-ni",
        "Yongban"
    ],
    "wof:name":"Yongban",
    "wof:placetype":"locality"
},
  "geometry": {"coordinates":[126.54472,34.60722],"type":"Point"}
}