{
  "type": "Feature",
  "properties": {
    "gn:admin1_code":"17.0",
    "gn:asciiname":"Tongp'yon-mal",
    "gn:country_code":"KR",
    "gn:dem":66,
    "gn:feature_class":"P",
    "gn:feature_code":"PPL",
    "gn:name":"Tongp\u2019y\u014fn-mal",
    "gn:population":0,
    "gn:timezone":"Asia/Seoul",
    "iso:country":"KR",
    "name:und_x_variant":[
        "\ub3d9\ud3b8\ub9d0",
        "Tongp\u2019y\u014fn-mal"
    ],
    "wof:name":"Tongp'yon-mal",
    "wof:placetype":"locality"
},
  "geometry": {"coordinates":[127.1808,36.4939],"type":"Point"}
}