{
  "type": "Feature",
  "properties": {
    "gn:admin1_code":"13.0",
    "gn:asciiname":"Sang-ni",
    "gn:country_code":"KR",
    "gn:dem":138,
    "gn:feature_class":"P",
    "gn:feature_code":"PPL",
    "gn:name":"Sang-ni",
    "gn:population":0,
    "gn:timezone":"Asia/Seoul",
    "iso:country":"KR",
    "name:und_x_variant":[
        "\uc0c1\ub9ac",
        "Sang-ri",
        "Sang-ni"
    ],
    "wof:name":"Sang-ni",
    "wof:placetype":"locality"
},
  "geometry": {"coordinates":[127.26528,37.26472],"type":"Point"}
}