{
  "type": "Feature",
  "properties": {
    "gn:admin1_code":"14.0",
    "gn:asciiname":"Nabal-tong",
    "gn:country_code":"KR",
    "gn:dem":255,
    "gn:feature_class":"P",
    "gn:feature_code":"PPL",
    "gn:name":"Nabal-tong",
    "gn:population":0,
    "gn:timezone":"Asia/Seoul",
    "iso:country":"KR",
    "name:eng_x_preferred":[
        "Nabal"
    ],
    "name:eng_x_variant":[
        "Nabal-tong"
    ],
    "name:kor_x_preferred":[
        "\ub098\ubc1c\ub3d9"
    ],
    "wof:name":"Nabal",
    "wof:placetype":"locality"
},
  "geometry": {"coordinates":[130.8348,37.4866],"type":"Point"}
}