{
  "type": "Feature",
  "properties": {
    "gn:admin1_code":"13.0",
    "gn:asciiname":"Ansangol",
    "gn:country_code":"KR",
    "gn:dem":100,
    "gn:feature_class":"P",
    "gn:feature_code":"PPL",
    "gn:name":"Ansangol",
    "gn:population":0,
    "gn:timezone":"Asia/Seoul",
    "iso:country":"KR",
    "name:kor_x_preferred":[
        "\uc548\uc0b0\uace8"
    ],
    "wof:name":"Ansangol",
    "wof:placetype":"locality"
},
  "geometry": {"coordinates":[127.21275,37.7134],"type":"Point"}
}