{
  "type": "Feature",
  "properties": {
    "gn:admin1_code":"17.0",
    "gn:asciiname":"Chine-mal",
    "gn:country_code":"KR",
    "gn:dem":243,
    "gn:feature_class":"P",
    "gn:feature_code":"PPL",
    "gn:name":"Chine-mal",
    "gn:population":0,
    "gn:timezone":"Asia/Seoul",
    "iso:country":"KR",
    "name:und_x_variant":[
        "\uc9c0\ub124\ub9d0",
        "Chine-mal"
    ],
    "wof:name":"Chine-mal",
    "wof:placetype":"locality"
},
  "geometry": {"coordinates":[127.5719,36.2128],"type":"Point"}
}