{
  "type": "Feature",
  "properties": {
    "gn:admin1_code":"14.0",
    "gn:asciiname":"Yangho-dong",
    "gn:country_code":"KR",
    "gn:dem":44,
    "gn:feature_class":"P",
    "gn:feature_code":"PPLL",
    "gn:name":"Yangho-dong",
    "gn:population":0,
    "gn:timezone":"Asia/Seoul",
    "iso:country":"KR",
    "name:und_x_variant":[
        "\uc591\ud638\ub3d9",
        "Yangho-dong"
    ],
    "wof:name":"Yangho-dong",
    "wof:placetype":"locality"
},
  "geometry": {"coordinates":[128.38225,36.13638],"type":"Point"}
}