{
  "type": "Feature",
  "properties": {
    "gn:admin1_code":"16.0",
    "gn:admin2_code":"Chindo-gun",
    "gn:asciiname":"Jungni",
    "gn:country_code":"KR",
    "gn:dem":19,
    "gn:feature_class":"P",
    "gn:feature_code":"PPL",
    "gn:name":"Jungni",
    "gn:population":0,
    "gn:timezone":"Asia/Seoul",
    "iso:country":"KR",
    "name:kor_x_preferred":[
        "\uc911\ub9ac"
    ],
    "name:und_x_variant":[
        "Chung-ni"
    ],
    "wof:name":"Jungni",
    "wof:placetype":"locality"
},
  "geometry": {"coordinates":[126.29389,34.44333],"type":"Point"}
}