{
  "type": "Feature",
  "properties": {
    "gn:admin1_code":"17.0",
    "gn:asciiname":"Gaetae",
    "gn:country_code":"KR",
    "gn:dem":79,
    "gn:feature_class":"P",
    "gn:feature_code":"PPL",
    "gn:name":"Gaetae",
    "gn:population":0,
    "gn:timezone":"Asia/Seoul",
    "iso:country":"KR",
    "name:und_x_variant":[
        "\uac1c\ud0dc",
        "Kaet\u2019ae",
        "Gaetae"
    ],
    "wof:name":"Gaetae",
    "wof:placetype":"locality"
},
  "geometry": {"coordinates":[127.23062,36.24062],"type":"Point"}
}