{
  "type": "Feature",
  "properties": {
    "iso:country":"KR",
    "name:eng_x_preferred":[
        "Jeokseong-myeon"
    ],
    "name:kor_x_preferred":[
        "\uc801\uc131\uba74"
    ],
    "qs:name":"\uc801\uc131\uba74",
    "qs:name_adm0":"\ud55c\uad6d",
    "qs:name_adm1":"\ucda9\uccad\ubd81\ub3c4",
    "qs:photos":1,
    "qs:photos_1k":1,
    "qs:photos_9k":1,
    "qs:photos_9r":1,
    "qs:photos_all":1,
    "qs:photos_sr":1,
    "qs:placetype":"LocalAdmin",
    "qs:pop_sr":"0",
    "wof:name":"Jeokseong-myeon",
    "wof:placetype":"localadmin"
},
  "geometry": {"coordinates":[128.30959999999999,36.995633],"type":"Point"}
}