{
  "type": "Feature",
  "properties": {
    "gn:admin1_code":"16.0",
    "gn:asciiname":"Su-ri",
    "gn:cc2":"KR",
    "gn:country_code":"KR",
    "gn:dem":43,
    "gn:feature_class":"P",
    "gn:feature_code":"PPL",
    "gn:name":"Su-ri",
    "gn:population":0,
    "gn:timezone":"Asia/Seoul",
    "iso:country":"KR",
    "name:und_x_variant":[
        "Suison",
        "Sui-ri",
        "Su-ri"
    ],
    "wof:name":"Su-ri",
    "wof:placetype":"locality"
},
  "geometry": {"coordinates":[125.46583,34.72972],"type":"Point"}
}