{
  "type": "Feature",
  "properties": {
    "gn:admin1_code":"13.0",
    "gn:asciiname":"Bonjeong",
    "gn:country_code":"KR",
    "gn:dem":13,
    "gn:feature_class":"P",
    "gn:feature_code":"PPL",
    "gn:name":"Bonjeong",
    "gn:population":0,
    "gn:timezone":"Asia/Seoul",
    "iso:country":"KR",
    "name:kor_x_preferred":[
        "\ubcf8\uc815"
    ],
    "name:und_x_variant":[
        "\ubcf8\uc815\ub9ac",
        "Ponj\u014fng-ni",
        "Bonjeong"
    ],
    "wof:name":"Bonjeong",
    "wof:placetype":"locality"
},
  "geometry": {"coordinates":[127.01176,36.94557],"type":"Point"}
}