{
  "type": "Feature",
  "properties": {
    "gn:admin1_code":"13.0",
    "gn:asciiname":"Idaengi",
    "gn:country_code":"KR",
    "gn:dem":69,
    "gn:feature_class":"P",
    "gn:feature_code":"PPL",
    "gn:name":"Idaengi",
    "gn:population":0,
    "gn:timezone":"Asia/Seoul",
    "iso:country":"KR",
    "name:kor_x_preferred":[
        "\uc774\ub315\uc774"
    ],
    "wof:name":"Idaengi",
    "wof:placetype":"locality"
},
  "geometry": {"coordinates":[127.5485,37.2193],"type":"Point"}
}