{
  "type": "Feature",
  "properties": {
    "gn:admin1_code":"17.0",
    "gn:asciiname":"Ch'a-dong",
    "gn:country_code":"KR",
    "gn:dem":56,
    "gn:feature_class":"P",
    "gn:feature_code":"PPL",
    "gn:name":"Ch\u2019a-dong",
    "gn:population":0,
    "gn:timezone":"Asia/Seoul",
    "iso:country":"KR",
    "name:und_x_variant":[
        "\ucc28\ub3d9",
        "Ch\u2019a-dong"
    ],
    "wof:name":"Ch'a-dong",
    "wof:placetype":"locality"
},
  "geometry": {"coordinates":[126.389,36.7839],"type":"Point"}
}