{
  "type": "Feature",
  "properties": {
    "gn:admin1_code":"13.0",
    "gn:asciiname":"Changnok-tong",
    "gn:country_code":"KR",
    "gn:dem":56,
    "gn:feature_class":"P",
    "gn:feature_code":"PPL",
    "gn:name":"Changnok-tong",
    "gn:population":0,
    "gn:timezone":"Asia/Seoul",
    "iso:country":"KR",
    "name:eng_x_preferred":[
        "Changnok"
    ],
    "name:eng_x_variant":[
        "Changnok-tong"
    ],
    "name:und_x_variant":[
        "\uc7a5\ub85d\ub3d9",
        "Jangnok-dong",
        "Changnok-tong"
    ],
    "wof:name":"Changnok",
    "wof:placetype":"locality"
},
  "geometry": {"coordinates":[127.45471999999999,37.25667],"type":"Point"}
}