{
  "type": "Feature",
  "properties": {
    "gn:admin1_code":"5.0",
    "gn:asciiname":"Sae-maul",
    "gn:country_code":"KR",
    "gn:dem":142,
    "gn:feature_class":"P",
    "gn:feature_code":"PPL",
    "gn:name":"Sae-ma\u016dl",
    "gn:population":0,
    "gn:timezone":"Asia/Seoul",
    "iso:country":"KR",
    "name:und_x_variant":[
        "\uc0c8\ub9c8\uc744",
        "Sae-ma\u016dl"
    ],
    "wof:name":"Sae-maul",
    "wof:placetype":"locality"
},
  "geometry": {"coordinates":[127.8168,36.3243],"type":"Point"}
}