{
  "type": "Feature",
  "properties": {
    "gn:admin1_code":"16.0",
    "gn:asciiname":"Yongso",
    "gn:country_code":"KR",
    "gn:dem":11,
    "gn:feature_class":"P",
    "gn:feature_code":"PPL",
    "gn:name":"Yongso",
    "gn:population":0,
    "gn:timezone":"Asia/Seoul",
    "iso:country":"KR",
    "name:kor_x_preferred":[
        "\uc6a9\uc18c"
    ],
    "name:und_x_variant":[
        "Y\u014fngsu"
    ],
    "wof:name":"Yongso",
    "wof:placetype":"locality"
},
  "geometry": {"coordinates":[127.74563999999999,34.98708],"type":"Point"}
}