{
  "type": "Feature",
  "properties": {
    "gn:admin1_code":"17.0",
    "gn:asciiname":"Kulmi",
    "gn:country_code":"KR",
    "gn:dem":16,
    "gn:feature_class":"P",
    "gn:feature_code":"PPL",
    "gn:name":"Kulmi",
    "gn:population":0,
    "gn:timezone":"Asia/Seoul",
    "iso:country":"KR",
    "name:rus_x_preferred":[
        "\u041a\u0443\u043b\u044c\u043c\u0438"
    ],
    "name:ukr_x_preferred":[
        "\u041a\u0443\u043b\u044c\u043c\u0456"
    ],
    "name:und_x_variant":[
        "\uad74\ubbf8",
        "Kulmi"
    ],
    "wof:name":"Kulmi",
    "wof:placetype":"locality"
},
  "geometry": {"coordinates":[126.76430000000001,36.8028],"type":"Point"}
}