{
  "type": "Feature",
  "properties": {
    "gn:admin1_code":"3.0",
    "gn:asciiname":"Omgye",
    "gn:country_code":"KR",
    "gn:dem":97,
    "gn:feature_class":"P",
    "gn:feature_code":"PPL",
    "gn:name":"\u014emgye",
    "gn:population":0,
    "gn:timezone":"Asia/Seoul",
    "iso:country":"KR",
    "name:und_x_variant":[
        "\uc5c4\uacc4",
        "\u014emgye"
    ],
    "wof:name":"Omgye",
    "wof:placetype":"locality"
},
  "geometry": {"coordinates":[127.07810000000001,35.64501],"type":"Point"}
}