{
  "type": "Feature",
  "properties": {
    "gn:admin1_code":"14.0",
    "gn:asciiname":"Chom-mal",
    "gn:country_code":"KR",
    "gn:dem":359,
    "gn:feature_class":"P",
    "gn:feature_code":"PPL",
    "gn:name":"Ch\u014fm-mal",
    "gn:population":0,
    "gn:timezone":"Asia/Seoul",
    "iso:country":"KR",
    "name:und_x_variant":[
        "\uc810\ub9d0",
        "Ch\u014fm-mal"
    ],
    "wof:name":"Chom-mal",
    "wof:placetype":"locality"
},
  "geometry": {"coordinates":[129.09211000000002,36.25068],"type":"Point"}
}