{
  "type": "Feature",
  "properties": {
    "gn:admin1_code":"14.0",
    "gn:asciiname":"Muraesil",
    "gn:country_code":"KR",
    "gn:dem":75,
    "gn:feature_class":"P",
    "gn:feature_code":"PPL",
    "gn:name":"Muraesil",
    "gn:population":0,
    "gn:timezone":"Asia/Seoul",
    "iso:country":"KR",
    "name:kor_x_preferred":[
        "\ubb34\ub798\uc2e4"
    ],
    "wof:name":"Muraesil",
    "wof:placetype":"locality"
},
  "geometry": {"coordinates":[128.37053999999998,35.96073],"type":"Point"}
}