{
  "type": "Feature",
  "properties": {
    "gn:admin1_code":"17.0",
    "gn:asciiname":"Sojong",
    "gn:country_code":"KR",
    "gn:dem":15,
    "gn:feature_class":"P",
    "gn:feature_code":"PPL",
    "gn:name":"S\u014fj\u014fng",
    "gn:population":0,
    "gn:timezone":"Asia/Seoul",
    "iso:country":"KR",
    "name:und_x_variant":[
        "\uc11c\uc815",
        "S\u014fj\u014fng"
    ],
    "wof:name":"Sojong",
    "wof:placetype":"locality"
},
  "geometry": {"coordinates":[126.69110000000001,36.9652],"type":"Point"}
}