{
  "type": "Feature",
  "properties": {
    "gn:admin1_code":"5.0",
    "gn:asciiname":"Tugumae",
    "gn:country_code":"KR",
    "gn:dem":249,
    "gn:feature_class":"P",
    "gn:feature_code":"PPL",
    "gn:name":"Tugumae",
    "gn:population":0,
    "gn:timezone":"Asia/Seoul",
    "iso:country":"KR",
    "name:kor_x_preferred":[
        "\ub450\uad6c\ub9e4"
    ],
    "wof:name":"Tugumae",
    "wof:placetype":"locality"
},
  "geometry": {"coordinates":[128.22810000000001,37.1437],"type":"Point"}
}