{
  "type": "Feature",
  "properties": {
    "gn:admin1_code":"12.0",
    "gn:asciiname":"Gang-chon",
    "gn:country_code":"KR",
    "gn:dem":31,
    "gn:feature_class":"P",
    "gn:feature_code":"PPL",
    "gn:name":"Gang-chon",
    "gn:population":0,
    "gn:timezone":"Asia/Seoul",
    "iso:country":"KR",
    "name:und_x_variant":[
        "\uac15\ucd0c",
        "Gang-chon",
        "Kang-ch\u2019on"
    ],
    "wof:name":"Gang-chon",
    "wof:placetype":"locality"
},
  "geometry": {"coordinates":[126.5125,37.52556],"type":"Point"}
}