{
  "type": "Feature",
  "properties": {
    "gn:admin1_code":"13.0",
    "gn:admin2_code":"Ich'\u014fn-si",
    "gn:asciiname":"Daesandong",
    "gn:country_code":"KR",
    "gn:dem":150,
    "gn:feature_class":"P",
    "gn:feature_code":"PPL",
    "gn:name":"Daesandong",
    "gn:population":0,
    "gn:timezone":"Asia/Seoul",
    "iso:country":"KR",
    "name:kor_x_preferred":[
        "\ub300\uc0b0\ub3d9"
    ],
    "name:und_x_variant":[
        "Taesan-dong",
        "Daesandong"
    ],
    "wof:name":"Daesandong",
    "wof:placetype":"locality"
},
  "geometry": {"coordinates":[127.46276,37.139],"type":"Point"}
}