{
  "type": "Feature",
  "properties": {
    "gn:admin1_code":"13.0",
    "gn:asciiname":"Mejaengi",
    "gn:country_code":"KR",
    "gn:dem":70,
    "gn:feature_class":"P",
    "gn:feature_code":"PPL",
    "gn:name":"Mejaengi",
    "gn:population":0,
    "gn:timezone":"Asia/Seoul",
    "iso:country":"KR",
    "name:und_x_variant":[
        "\uba54\uc7c1\uc774",
        "Mejaengi"
    ],
    "wof:name":"Mejaengi",
    "wof:placetype":"locality"
},
  "geometry": {"coordinates":[127.50528,37.315],"type":"Point"}
}