{
  "type": "Feature",
  "properties": {
    "gn:admin1_code":"17.0",
    "gn:asciiname":"Pan'gyejangt'o",
    "gn:country_code":"KR",
    "gn:dem":71,
    "gn:feature_class":"P",
    "gn:feature_code":"PPL",
    "gn:name":"Pan\u2019gyejangt\u2019\u014f",
    "gn:population":0,
    "gn:timezone":"Asia/Seoul",
    "iso:country":"KR",
    "name:und_x_variant":[
        "\ubc18\uacc4\uc7a5\ud130",
        "Pan\u2019gyejangt\u2019\u014f"
    ],
    "wof:name":"Pan'gyejangt'o",
    "wof:placetype":"locality"
},
  "geometry": {"coordinates":[126.74290000000001,36.4879],"type":"Point"}
}