{
  "type": "Feature",
  "properties": {
    "gn:admin1_code":"20.0",
    "gn:asciiname":"Sonjon",
    "gn:country_code":"KR",
    "gn:dem":36,
    "gn:feature_class":"P",
    "gn:feature_code":"PPL",
    "gn:name":"S\u014fnj\u014fn",
    "gn:population":0,
    "gn:timezone":"Asia/Seoul",
    "iso:country":"KR",
    "wof:name":"Sonjon",
    "wof:placetype":"locality"
},
  "geometry": {"coordinates":[128.06666999999999,34.96667],"type":"Point"}
}