{
  "type": "Feature",
  "properties": {
    "gn:admin1_code":"0.0",
    "gn:asciiname":"P'yonghyon-ni",
    "gn:country_code":"KR",
    "gn:dem":131,
    "gn:feature_class":"P",
    "gn:feature_code":"PPL",
    "gn:name":"P\u2019y\u014fnghy\u014fn-ni",
    "gn:population":0,
    "gn:timezone":"Asia/Seoul",
    "iso:country":"KR",
    "wof:name":"P'yonghyon-ni",
    "wof:placetype":"locality"
},
  "geometry": {"coordinates":[127.88333,34.81667],"type":"Point"}
}