{
  "type": "Feature",
  "properties": {
    "gn:admin1_code":"13.0",
    "gn:admin2_code":"Ich'\u014fn-si",
    "gn:asciiname":"Chungni-dong",
    "gn:country_code":"KR",
    "gn:dem":86,
    "gn:feature_class":"P",
    "gn:feature_code":"PPL",
    "gn:name":"Chungni-dong",
    "gn:population":0,
    "gn:timezone":"Asia/Seoul",
    "iso:country":"KR",
    "name:kor_x_preferred":[
        "\uc911\ub9ac\ub3d9"
    ],
    "name:und_x_variant":[
        "Jungni-dong"
    ],
    "wof:name":"Chungni-dong",
    "wof:placetype":"locality"
},
  "geometry": {"coordinates":[127.46083,37.23778],"type":"Point"}
}