{
  "type": "Feature",
  "properties": {
    "gn:admin1_code":"14.0",
    "gn:asciiname":"Utkkachideul",
    "gn:country_code":"KR",
    "gn:dem":150,
    "gn:feature_class":"P",
    "gn:feature_code":"PPL",
    "gn:name":"Utkkachideul",
    "gn:population":0,
    "gn:timezone":"Asia/Seoul",
    "iso:country":"KR",
    "name:kor_x_preferred":[
        "\uc6c3\uae4c\uce58\ub4e4"
    ],
    "wof:name":"Utkkachideul",
    "wof:placetype":"locality"
},
  "geometry": {"coordinates":[128.53319999999999,36.67107],"type":"Point"}
}