{
  "type": "Feature",
  "properties": {
    "gn:admin1_code":"14.0",
    "gn:asciiname":"Mudomsil",
    "gn:country_code":"KR",
    "gn:dem":432,
    "gn:feature_class":"P",
    "gn:feature_code":"PPL",
    "gn:name":"Mud\u014fmsil",
    "gn:population":0,
    "gn:timezone":"Asia/Seoul",
    "iso:country":"KR",
    "name:und_x_variant":[
        "\ubb34\ub364\uc2e4",
        "Mud\u014fmsil"
    ],
    "wof:name":"Mudomsil",
    "wof:placetype":"locality"
},
  "geometry": {"coordinates":[129.16050000000001,36.3183],"type":"Point"}
}