{
  "type": "Feature",
  "properties": {
    "gn:admin1_code":"5.0",
    "gn:asciiname":"Ttukkyeongsaemgeori",
    "gn:country_code":"KR",
    "gn:dem":69,
    "gn:feature_class":"P",
    "gn:feature_code":"PPL",
    "gn:name":"Ttukkyeongsaemgeori",
    "gn:population":0,
    "gn:timezone":"Asia/Seoul",
    "iso:country":"KR",
    "name:kor_x_preferred":[
        "\ub69c\uaf09\uc0d8\uac70\ub9ac"
    ],
    "wof:name":"Ttukkyeongsaemgeori",
    "wof:placetype":"locality"
},
  "geometry": {"coordinates":[127.50216,36.68026],"type":"Point"}
}