{
  "type": "Feature",
  "properties": {
    "gn:admin1_code":"14.0",
    "gn:asciiname":"Ansim",
    "gn:country_code":"KR",
    "gn:dem":87,
    "gn:feature_class":"P",
    "gn:feature_code":"PPL",
    "gn:name":"Ansim",
    "gn:population":0,
    "gn:timezone":"Asia/Seoul",
    "iso:country":"KR",
    "name:kor_x_preferred":[
        "\uc548\uc2ec"
    ],
    "wof:name":"Ansim",
    "wof:placetype":"locality"
},
  "geometry": {"coordinates":[128.49538999999999,36.53486],"type":"Point"}
}