{
  "type": "Feature",
  "properties": {
    "gn:admin1_code":"13.0",
    "gn:asciiname":"Wonudong",
    "gn:country_code":"KR",
    "gn:dem":74,
    "gn:feature_class":"P",
    "gn:feature_code":"PPL",
    "gn:name":"Wonudong",
    "gn:population":0,
    "gn:timezone":"Asia/Seoul",
    "iso:country":"KR",
    "name:kor_x_preferred":[
        "\uc6d0\uc6b0\ub3d9"
    ],
    "name:und_x_variant":[
        "\uc6d0\uc6b0",
        "W\u014fnu",
        "Wonudong"
    ],
    "wof:name":"Wonudong",
    "wof:placetype":"locality"
},
  "geometry": {"coordinates":[127.02397000000001,37.78513],"type":"Point"}
}