{
  "type": "Feature",
  "properties": {
    "gn:admin1_code":"6.0",
    "gn:asciiname":"Chungdaehwa",
    "gn:country_code":"KR",
    "gn:dem":445,
    "gn:feature_class":"P",
    "gn:feature_code":"PPL",
    "gn:name":"Chungdaehwa",
    "gn:population":0,
    "gn:timezone":"Asia/Seoul",
    "iso:country":"KR",
    "name:kor_x_preferred":[
        "\uc911\ub300\ud654"
    ],
    "wof:name":"Chungdaehwa",
    "wof:placetype":"locality"
},
  "geometry": {"coordinates":[128.45939999999999,37.506],"type":"Point"}
}