{
  "type": "Feature",
  "properties": {
    "gn:admin1_code":"15.0",
    "gn:asciiname":"Doya",
    "gn:country_code":"KR",
    "gn:dem":21,
    "gn:feature_class":"P",
    "gn:feature_code":"PPL",
    "gn:name":"Doya",
    "gn:population":0,
    "gn:timezone":"Asia/Seoul",
    "iso:country":"KR",
    "name:und_x_variant":[
        "\ub3c4\uc57c",
        "Toya",
        "Doya"
    ],
    "wof:name":"Doya",
    "wof:placetype":"locality"
},
  "geometry": {"coordinates":[128.39174,35.61423],"type":"Point"}
}