{
  "type": "Feature",
  "properties": {
    "gn:admin1_code":"20.0",
    "gn:asciiname":"Kwanam",
    "gn:country_code":"KR",
    "gn:dem":32,
    "gn:feature_class":"P",
    "gn:feature_code":"PPL",
    "gn:name":"Kwanam",
    "gn:population":0,
    "gn:timezone":"Asia/Seoul",
    "iso:country":"KR",
    "name:und_x_variant":[
        "\uad00\uc554",
        "Kwanam"
    ],
    "wof:name":"Kwanam",
    "wof:placetype":"locality"
},
  "geometry": {"coordinates":[128.46806000000001,34.81288],"type":"Point"}
}