{
  "type": "Feature",
  "properties": {
    "gn:admin1_code":"6.0",
    "gn:asciiname":"Sallae-gol",
    "gn:country_code":"KR",
    "gn:dem":792,
    "gn:feature_class":"P",
    "gn:feature_code":"PPL",
    "gn:name":"Sallae-gol",
    "gn:population":0,
    "gn:timezone":"Asia/Seoul",
    "iso:country":"KR",
    "name:kor_x_preferred":[
        "\uc0b4\ub798\uace8"
    ],
    "wof:name":"Sallae-gol",
    "wof:placetype":"locality"
},
  "geometry": {"coordinates":[128.92500000000001,37.1302],"type":"Point"}
}