{
  "type": "Feature",
  "properties": {
    "gn:admin1_code":"14.0",
    "gn:asciiname":"Taeyangmyo",
    "gn:country_code":"KR",
    "gn:dem":90,
    "gn:feature_class":"P",
    "gn:feature_code":"PPL",
    "gn:name":"Taeyangmyo",
    "gn:population":0,
    "gn:timezone":"Asia/Seoul",
    "iso:country":"KR",
    "name:und_x_variant":[
        "\ub300\uc591\ubb18",
        "Taeyangmyo"
    ],
    "wof:name":"Taeyangmyo",
    "wof:placetype":"locality"
},
  "geometry": {"coordinates":[128.16749999999999,36.2011],"type":"Point"}
}