{
  "type": "Feature",
  "properties": {
    "gn:admin1_code":"6.0",
    "gn:asciiname":"Chojeondong",
    "gn:country_code":"KR",
    "gn:dem":248,
    "gn:feature_class":"P",
    "gn:feature_code":"PPL",
    "gn:name":"Chojeondong",
    "gn:population":0,
    "gn:timezone":"Asia/Seoul",
    "iso:country":"KR",
    "name:kor_x_preferred":[
        "\ucd08\uc804\ub3d9"
    ],
    "wof:name":"Chojeondong",
    "wof:placetype":"locality"
},
  "geometry": {"coordinates":[127.38852,38.22581],"type":"Point"}
}