{
  "type": "Feature",
  "properties": {
    "gn:admin1_code":"17.0",
    "gn:asciiname":"Mullomok",
    "gn:country_code":"KR",
    "gn:dem":93,
    "gn:feature_class":"P",
    "gn:feature_code":"PPL",
    "gn:name":"Mull\u014fmok",
    "gn:population":0,
    "gn:timezone":"Asia/Seoul",
    "iso:country":"KR",
    "name:und_x_variant":[
        "\ubb3c\ub108\ubaa9",
        "Mull\u014fmok"
    ],
    "wof:name":"Mullomok",
    "wof:placetype":"locality"
},
  "geometry": {"coordinates":[127.03360000000001,36.8448],"type":"Point"}
}