{
  "type": "Feature",
  "properties": {
    "gn:admin1_code":"17.0",
    "gn:asciiname":"Dundae",
    "gn:country_code":"KR",
    "gn:dem":84,
    "gn:feature_class":"P",
    "gn:feature_code":"PPL",
    "gn:name":"Dundae",
    "gn:population":0,
    "gn:timezone":"Asia/Seoul",
    "iso:country":"KR",
    "name:kor_x_preferred":[
        "\ub454\ub300"
    ],
    "name:kor_x_variant":[
        "\uc74c\ub2ec\ub454\ub300"
    ],
    "name:und_x_variant":[
        "\uc591\ub2ec\ub454\ub300",
        "Yangdaltundae",
        "Dundae",
        "\u016cmdaltundae"
    ],
    "wof:name":"Dundae",
    "wof:placetype":"locality"
},
  "geometry": {"coordinates":[127.33291,36.45893],"type":"Point"}
}