{
  "type": "Feature",
  "properties": {
    "gn:admin1_code":"20.0",
    "gn:asciiname":"Toksan-ni",
    "gn:country_code":"KR",
    "gn:dem":344,
    "gn:feature_class":"P",
    "gn:feature_code":"PPL",
    "gn:name":"T\u014fksan-ni",
    "gn:population":0,
    "gn:timezone":"Asia/Seoul",
    "iso:country":"KR",
    "wof:name":"Toksan-ni",
    "wof:placetype":"locality"
},
  "geometry": {"coordinates":[128.69999999999999,35.43333],"type":"Point"}
}