{
  "type": "Feature",
  "properties": {
    "gn:admin1_code":"6.0",
    "gn:asciiname":"Dokgachon",
    "gn:country_code":"KR",
    "gn:dem":161,
    "gn:feature_class":"P",
    "gn:feature_code":"PPL",
    "gn:name":"Dokgachon",
    "gn:population":0,
    "gn:timezone":"Asia/Seoul",
    "iso:country":"KR",
    "name:kor_x_preferred":[
        "\ub3c5\uac00\ucd0c"
    ],
    "name:kor_x_variant":[
        "Tokkach\u2019on"
    ],
    "wof:name":"Dokgachon",
    "wof:placetype":"locality"
},
  "geometry": {"coordinates":[128.66292000000001,37.93961],"type":"Point"}
}