{
  "type": "Feature",
  "properties": {
    "gn:admin1_code":"13.0",
    "gn:asciiname":"Ugum-ni",
    "gn:country_code":"KR",
    "gn:dem":178,
    "gn:feature_class":"P",
    "gn:feature_code":"PPLL",
    "gn:name":"Ug\u016dm-ni",
    "gn:population":0,
    "gn:timezone":"Asia/Seoul",
    "iso:country":"KR",
    "name:kor_x_preferred":[
        "\uc6b0\uae08\ub9ac"
    ],
    "name:kor_x_variant":[
        "Ug\u016dm-ni"
    ],
    "wof:name":"Ugum-ni",
    "wof:placetype":"locality"
},
  "geometry": {"coordinates":[127.21666999999999,37.8302],"type":"Point"}
}