{
  "type": "Feature",
  "properties": {
    "gn:admin1_code":"13.0",
    "gn:asciiname":"Mukpangi",
    "gn:country_code":"KR",
    "gn:dem":95,
    "gn:feature_class":"P",
    "gn:feature_code":"PPL",
    "gn:name":"Mukpangi",
    "gn:population":0,
    "gn:timezone":"Asia/Seoul",
    "iso:country":"KR",
    "name:und_x_variant":[
        "\ubb35\ubc29\uc774",
        "Mukbangi",
        "Mukpangi"
    ],
    "wof:name":"Mukpangi",
    "wof:placetype":"locality"
},
  "geometry": {"coordinates":[127.34917,37.34194],"type":"Point"}
}