{
  "type": "Feature",
  "properties": {
    "gn:admin1_code":"14.0",
    "gn:asciiname":"Withandu-ri",
    "gn:cc2":"KR",
    "gn:country_code":"KR",
    "gn:dem":108,
    "gn:feature_class":"P",
    "gn:feature_code":"PPL",
    "gn:name":"Withandu-ri",
    "gn:population":0,
    "gn:timezone":"Asia/Seoul",
    "iso:country":"KR",
    "name:und_x_variant":[
        "Taeha-ri",
        "Withandu-ri"
    ],
    "wof:name":"Withandu-ri",
    "wof:placetype":"locality"
},
  "geometry": {"coordinates":[128.26667,36.66833],"type":"Point"}
}