{
  "type": "Feature",
  "properties": {
    "gn:admin1_code":"14.0",
    "gn:asciiname":"Mugunjom",
    "gn:country_code":"KR",
    "gn:dem":340,
    "gn:feature_class":"P",
    "gn:feature_code":"PPL",
    "gn:name":"Mug\u016dnj\u014fm",
    "gn:population":0,
    "gn:timezone":"Asia/Seoul",
    "iso:country":"KR",
    "name:und_x_variant":[
        "\ubb35\uc740\uc810",
        "Mug\u016dnj\u014fm"
    ],
    "wof:name":"Mugunjom",
    "wof:placetype":"locality"
},
  "geometry": {"coordinates":[127.971,36.0347],"type":"Point"}
}