{
  "type": "Feature",
  "properties": {
    "gn:admin1_code":"13.0",
    "gn:asciiname":"Araen-mal",
    "gn:country_code":"KR",
    "gn:dem":37,
    "gn:feature_class":"P",
    "gn:feature_code":"PPL",
    "gn:name":"Araen-mal",
    "gn:population":0,
    "gn:timezone":"Asia/Seoul",
    "iso:country":"KR",
    "name:und_x_variant":[
        "\uc544\ub7ab\ub9d0",
        "Araet-mal",
        "Araen-mal"
    ],
    "wof:name":"Araen-mal",
    "wof:placetype":"locality"
},
  "geometry": {"coordinates":[127.09111,37.20667],"type":"Point"}
}