{
  "type": "Feature",
  "properties": {
    "gn:admin1_code":"6.0",
    "gn:asciiname":"Tonggol",
    "gn:country_code":"KR",
    "gn:dem":467,
    "gn:feature_class":"P",
    "gn:feature_code":"PPL",
    "gn:name":"Tonggol",
    "gn:population":0,
    "gn:timezone":"Asia/Seoul",
    "iso:country":"KR",
    "name:kor_x_preferred":[
        "\ud1b5\uace8"
    ],
    "name:kor_x_variant":[
        "T\u2019ong-gol"
    ],
    "wof:name":"Tonggol",
    "wof:placetype":"locality"
},
  "geometry": {"coordinates":[127.9905,37.9681],"type":"Point"}
}