{
  "type": "Feature",
  "properties": {
    "gn:admin1_code":"17.0",
    "gn:asciiname":"Araesyangsimni",
    "gn:country_code":"KR",
    "gn:dem":125,
    "gn:feature_class":"P",
    "gn:feature_code":"PPL",
    "gn:name":"Araesyangsimni",
    "gn:population":0,
    "gn:timezone":"Asia/Seoul",
    "iso:country":"KR",
    "name:kor_x_preferred":[
        "\uc544\ub7ab\uc591\uc2ec\ub9ac"
    ],
    "wof:name":"Araesyangsimni",
    "wof:placetype":"locality"
},
  "geometry": {"coordinates":[127.51533000000001,36.26979],"type":"Point"}
}