{
  "type": "Feature",
  "properties": {
    "gn:admin1_code":"5.0",
    "gn:asciiname":"Annae",
    "gn:country_code":"KR",
    "gn:dem":87,
    "gn:feature_class":"P",
    "gn:feature_code":"PPL",
    "gn:name":"Annae",
    "gn:population":0,
    "gn:timezone":"Asia/Seoul",
    "iso:country":"KR",
    "name:und_x_variant":[
        "\uc548\ub0b4",
        "Annae"
    ],
    "wof:name":"Annae",
    "wof:placetype":"locality"
},
  "geometry": {"coordinates":[127.6598,36.3943],"type":"Point"}
}