{
  "type": "Feature",
  "properties": {
    "gn:admin1_code":"5.0",
    "gn:asciiname":"Oryong",
    "gn:country_code":"KR",
    "gn:dem":176,
    "gn:feature_class":"P",
    "gn:feature_code":"PPL",
    "gn:name":"Oryong",
    "gn:population":0,
    "gn:timezone":"Asia/Seoul",
    "iso:country":"KR",
    "name:kor_x_preferred":[
        "\uc624\ub8e1"
    ],
    "wof:name":"Oryong",
    "wof:placetype":"locality"
},
  "geometry": {"coordinates":[127.64695,37.00487],"type":"Point"}
}