{
  "type": "Feature",
  "properties": {
    "gn:admin1_code":"13.0",
    "gn:asciiname":"Changjagwon",
    "gn:country_code":"KR",
    "gn:dem":26,
    "gn:feature_class":"P",
    "gn:feature_code":"PPL",
    "gn:name":"Changjagw\u014fn",
    "gn:population":0,
    "gn:timezone":"Asia/Seoul",
    "iso:country":"KR",
    "name:kor_x_preferred":[
        "\uc7a5\uc791\uc6d0"
    ],
    "wof:name":"Changjagwon",
    "wof:placetype":"locality"
},
  "geometry": {"coordinates":[126.81528,37.12639],"type":"Point"}
}