{
  "type": "Feature",
  "properties": {
    "gn:admin1_code":"17.0",
    "gn:asciiname":"Daebak",
    "gn:country_code":"KR",
    "gn:dem":54,
    "gn:feature_class":"P",
    "gn:feature_code":"PPL",
    "gn:name":"Daebak",
    "gn:population":0,
    "gn:timezone":"Asia/Seoul",
    "iso:country":"KR",
    "name:kor_x_preferred":[
        "\ub300\ubc15"
    ],
    "wof:name":"Daebak",
    "wof:placetype":"locality"
},
  "geometry": {"coordinates":[127.34466999999999,36.4796],"type":"Point"}
}