{
  "type": "Feature",
  "properties": {
    "gn:admin1_code":"3.0",
    "gn:asciiname":"Haengch'i",
    "gn:country_code":"KR",
    "gn:dem":66,
    "gn:feature_class":"P",
    "gn:feature_code":"PPL",
    "gn:name":"Haengch\u2019i",
    "gn:population":0,
    "gn:timezone":"Asia/Seoul",
    "iso:country":"KR",
    "name:und_x_variant":[
        "\ud589\uce58",
        "Haengch\u2019i"
    ],
    "wof:name":"Haengch'i",
    "wof:placetype":"locality"
},
  "geometry": {"coordinates":[127.17631000000002,35.83234],"type":"Point"}
}