{
  "type": "Feature",
  "properties": {
    "gn:admin1_code":"16.0",
    "gn:asciiname":"Bogwang",
    "gn:country_code":"KR",
    "gn:dem":95,
    "gn:feature_class":"P",
    "gn:feature_code":"PPL",
    "gn:name":"Bogwang",
    "gn:population":0,
    "gn:timezone":"Asia/Seoul",
    "iso:country":"KR",
    "name:kor_x_preferred":[
        "\ubcf4\uad11"
    ],
    "wof:name":"Bogwang",
    "wof:placetype":"locality"
},
  "geometry": {"coordinates":[126.67628000000001,35.04243],"type":"Point"}
}