{
  "type": "Feature",
  "properties": {
    "gn:admin1_code":"13.0",
    "gn:admin2_code":"Kimp'o-si",
    "gn:asciiname":"Bosuguji",
    "gn:country_code":"KR",
    "gn:dem":23,
    "gn:feature_class":"P",
    "gn:feature_code":"PPL",
    "gn:name":"Bosuguji",
    "gn:population":0,
    "gn:timezone":"Asia/Seoul",
    "iso:country":"KR",
    "name:kor_x_preferred":[
        "\ubcf4\uc218\uad6c\uc9c0"
    ],
    "name:und_x_variant":[
        "Kekke-dong",
        "Pogon-ni",
        "Kaekkye-dong",
        "Kae\u016dl-tong",
        "Posuguji",
        "Bosuguji"
    ],
    "wof:name":"Bosuguji",
    "wof:placetype":"locality"
},
  "geometry": {"coordinates":[126.53222,37.76083],"type":"Point"}
}