{
  "type": "Feature",
  "properties": {
    "gn:admin1_code":"0.0",
    "gn:asciiname":"Nojong-ni",
    "gn:cc2":"KR",
    "gn:country_code":"KR",
    "gn:dem":233,
    "gn:feature_class":"P",
    "gn:feature_code":"PPL",
    "gn:name":"Noj\u014fng-ni",
    "gn:population":0,
    "gn:timezone":"Asia/Seoul",
    "iso:country":"KR",
    "name:und_x_variant":[
        "Noj\u014fk",
        "Noj\u014fng-ni"
    ],
    "wof:name":"Nojong-ni",
    "wof:placetype":"locality"
},
  "geometry": {"coordinates":[126.61667,35.65],"type":"Point"}
}