{
  "type": "Feature",
  "properties": {
    "gn:admin1_code":"13.0",
    "gn:asciiname":"Cheoncheon-ri",
    "gn:country_code":"KR",
    "gn:dem":22,
    "gn:feature_class":"P",
    "gn:feature_code":"PPLL",
    "gn:name":"Cheoncheon-ri",
    "gn:population":0,
    "gn:timezone":"Asia/Seoul",
    "iso:country":"KR",
    "name:und_x_variant":[
        "\ucc9c\ucc9c\ub9ac",
        "Cheoncheon-ri",
        "Ch\u2019\u014fnch\u2019\u014fl-li"
    ],
    "wof:name":"Cheoncheon-ri",
    "wof:placetype":"locality"
},
  "geometry": {"coordinates":[126.94667,37.2425],"type":"Point"}
}