{
  "type": "Feature",
  "properties": {
    "gn:admin1_code":"3.0",
    "gn:asciiname":"Sangdokhyon",
    "gn:country_code":"KR",
    "gn:dem":356,
    "gn:feature_class":"P",
    "gn:feature_code":"PPL",
    "gn:name":"Sangd\u014fkhy\u014fn",
    "gn:population":0,
    "gn:timezone":"Asia/Seoul",
    "iso:country":"KR",
    "name:und_x_variant":[
        "\uc0c1\ub355\ud604",
        "Sangd\u014fkhy\u014fn"
    ],
    "wof:name":"Sangdokhyon",
    "wof:placetype":"locality"
},
  "geometry": {"coordinates":[127.3789,35.68083],"type":"Point"}
}