{
  "type": "Feature",
  "properties": {
    "gn:admin1_code":"14.0",
    "gn:asciiname":"Amnyeonggol",
    "gn:country_code":"KR",
    "gn:dem":127,
    "gn:feature_class":"P",
    "gn:feature_code":"PPL",
    "gn:name":"Amnyeonggol",
    "gn:population":0,
    "gn:timezone":"Asia/Seoul",
    "iso:country":"KR",
    "name:kor_x_preferred":[
        "\uc555\ub839\uace8"
    ],
    "wof:name":"Amnyeonggol",
    "wof:placetype":"locality"
},
  "geometry": {"coordinates":[128.60235,36.71353],"type":"Point"}
}