{
  "type": "Feature",
  "properties": {
    "gn:admin1_code":"14.0",
    "gn:asciiname":"Kwaebaek",
    "gn:country_code":"KR",
    "gn:dem":347,
    "gn:feature_class":"P",
    "gn:feature_code":"PPL",
    "gn:name":"Kwaebaek",
    "gn:population":0,
    "gn:timezone":"Asia/Seoul",
    "iso:country":"KR",
    "name:und_x_variant":[
        "\uad18\ubc31",
        "Kwaebaek"
    ],
    "wof:name":"Kwaebaek",
    "wof:placetype":"locality"
},
  "geometry": {"coordinates":[129.24680000000001,36.807],"type":"Point"}
}