{
  "type": "Feature",
  "properties": {
    "gn:admin1_code":"14.0",
    "gn:asciiname":"Wanjang",
    "gn:country_code":"KR",
    "gn:dem":206,
    "gn:feature_class":"P",
    "gn:feature_code":"PPL",
    "gn:name":"Wanjang",
    "gn:population":0,
    "gn:timezone":"Asia/Seoul",
    "iso:country":"KR",
    "name:kor_x_preferred":[
        "\uc644\uc7a5"
    ],
    "name:und_x_variant":[
        "Wanjang-ni",
        "Wanjang"
    ],
    "wof:name":"Wanjang",
    "wof:placetype":"locality"
},
  "geometry": {"coordinates":[127.98999999999999,36.67523],"type":"Point"}
}