{
  "type": "Feature",
  "properties": {
    "gn:admin1_code":"6.0",
    "gn:asciiname":"Toryong",
    "gn:country_code":"KR",
    "gn:dem":359,
    "gn:feature_class":"P",
    "gn:feature_code":"PPL",
    "gn:name":"Toryong",
    "gn:population":0,
    "gn:timezone":"Asia/Seoul",
    "iso:country":"KR",
    "name:kor_x_preferred":[
        "\ub3c4\ub8e1"
    ],
    "wof:name":"Toryong",
    "wof:placetype":"locality"
},
  "geometry": {"coordinates":[128.1935,37.2712],"type":"Point"}
}