{
  "type": "Feature",
  "properties": {
    "gn:admin1_code":"6.0",
    "gn:asciiname":"Hoendorajimaeul",
    "gn:country_code":"KR",
    "gn:dem":193,
    "gn:feature_class":"P",
    "gn:feature_code":"PPL",
    "gn:name":"Hoendorajimaeul",
    "gn:population":0,
    "gn:timezone":"Asia/Seoul",
    "iso:country":"KR",
    "name:kor_x_preferred":[
        "\ud690\ub3c4\ub77c\uc9c0\ub9c8\uc744"
    ],
    "name:und_x_variant":[
        "\ud754\ub4e4\uc5d0\uace8",
        "H\u016dnd\u016dre-gol",
        "Hoendorajimaeul"
    ],
    "wof:name":"Hoendorajimaeul",
    "wof:placetype":"locality"
},
  "geometry": {"coordinates":[127.63890000000001,37.76192],"type":"Point"}
}