{
  "type": "Feature",
  "properties": {
    "gn:admin1_code":"6.0",
    "gn:asciiname":"Sumil",
    "gn:country_code":"KR",
    "gn:dem":304,
    "gn:feature_class":"P",
    "gn:feature_code":"PPL",
    "gn:name":"Sumil",
    "gn:population":0,
    "gn:timezone":"Asia/Seoul",
    "iso:country":"KR",
    "name:und_x_variant":[
        "\uc218\ubc00",
        "Sumil"
    ],
    "wof:name":"Sumil",
    "wof:placetype":"locality"
},
  "geometry": {"coordinates":[127.50611000000001,38.05056],"type":"Point"}
}