{
  "type": "Feature",
  "properties": {
    "gn:admin1_code":"5.0",
    "gn:asciiname":"Wolgol",
    "gn:country_code":"KR",
    "gn:dem":87,
    "gn:feature_class":"P",
    "gn:feature_code":"PPL",
    "gn:name":"Wolgol",
    "gn:population":0,
    "gn:timezone":"Asia/Seoul",
    "iso:country":"KR",
    "name:kor_x_preferred":[
        "\uc6d4\uace8"
    ],
    "wof:name":"Wolgol",
    "wof:placetype":"locality"
},
  "geometry": {"coordinates":[127.45247000000001,36.97075],"type":"Point"}
}