{
  "type": "Feature",
  "properties": {
    "gn:admin1_code":"6.0",
    "gn:asciiname":"Jipeum",
    "gn:country_code":"KR",
    "gn:dem":184,
    "gn:feature_class":"P",
    "gn:feature_code":"PPL",
    "gn:name":"Jipeum",
    "gn:population":0,
    "gn:timezone":"Asia/Seoul",
    "iso:country":"KR",
    "name:und_x_variant":[
        "\uc9c0\ud488",
        "Chip\u2019um",
        "Jipeum"
    ],
    "wof:name":"Jipeum",
    "wof:placetype":"locality"
},
  "geometry": {"coordinates":[127.73966,37.82347],"type":"Point"}
}