{
  "type": "Feature",
  "properties": {
    "gn:admin1_code":"14.0",
    "gn:asciiname":"Sillim",
    "gn:country_code":"KR",
    "gn:dem":118,
    "gn:feature_class":"P",
    "gn:feature_code":"PPL",
    "gn:name":"Sillim",
    "gn:population":0,
    "gn:timezone":"Asia/Seoul",
    "iso:country":"KR",
    "name:und_x_variant":[
        "\uc2e0\ub9bc",
        "Sillim"
    ],
    "wof:name":"Sillim",
    "wof:placetype":"locality"
},
  "geometry": {"coordinates":[129.37190000000001,36.7083],"type":"Point"}
}