{
  "type": "Feature",
  "properties": {
    "gn:admin1_code":"14.0",
    "gn:asciiname":"Yun-ch'on",
    "gn:country_code":"KR",
    "gn:dem":236,
    "gn:feature_class":"P",
    "gn:feature_code":"PPL",
    "gn:name":"Yun-ch\u2019on",
    "gn:population":0,
    "gn:timezone":"Asia/Seoul",
    "iso:country":"KR",
    "name:und_x_variant":[
        "\uc724\ucd0c",
        "Yun-ch\u2019on"
    ],
    "wof:name":"Yun-ch'on",
    "wof:placetype":"locality"
},
  "geometry": {"coordinates":[129.2544,36.477],"type":"Point"}
}