{
  "type": "Feature",
  "properties": {
    "gn:admin1_code":"20.0",
    "gn:asciiname":"Naei-dong",
    "gn:country_code":"KR",
    "gn:dem":22,
    "gn:feature_class":"P",
    "gn:feature_code":"PPL",
    "gn:name":"Naei-dong",
    "gn:population":0,
    "gn:timezone":"Asia/Seoul",
    "iso:country":"KR",
    "name:und_x_variant":[
        "\ub0b4\uc774\ub3d9",
        "Naei-dong"
    ],
    "wof:name":"Naei-dong",
    "wof:placetype":"locality"
},
  "geometry": {"coordinates":[128.73599999999999,35.50468],"type":"Point"}
}