{
  "type": "Feature",
  "properties": {
    "gn:admin1_code":"6.0",
    "gn:asciiname":"Towol-li",
    "gn:country_code":"KR",
    "gn:dem":137,
    "gn:feature_class":"P",
    "gn:feature_code":"PPL",
    "gn:name":"Tow\u014fl-li",
    "gn:population":0,
    "gn:timezone":"Asia/Seoul",
    "iso:country":"KR",
    "name:kor_x_preferred":[
        "\ub3c4\uc6d0\ub9ac"
    ],
    "name:und_x_variant":[
        "Tow\u014fn-ni",
        "Tow\u014fl-li"
    ],
    "wof:name":"Towol-li",
    "wof:placetype":"locality"
},
  "geometry": {"coordinates":[128.47568000000001,38.27459],"type":"Point"}
}