{
  "type": "Feature",
  "properties": {
    "gn:admin1_code":"5.0",
    "gn:asciiname":"Deogeun",
    "gn:country_code":"KR",
    "gn:dem":65,
    "gn:feature_class":"P",
    "gn:feature_code":"PPL",
    "gn:name":"Deogeun",
    "gn:population":0,
    "gn:timezone":"Asia/Seoul",
    "iso:country":"KR",
    "name:kor_x_preferred":[
        "\ub355\uc740"
    ],
    "name:kor_x_variant":[
        "T\u014fg\u016dn"
    ],
    "wof:name":"Deogeun",
    "wof:placetype":"locality"
},
  "geometry": {"coordinates":[127.79568,37.14089],"type":"Point"}
}