{
  "type": "Feature",
  "properties": {
    "gn:country":"KR",
    "gn:fcode":"PPL",
    "gn:population":0,
    "iso:country":"KR",
    "name:eng_x_preferred":[
        "Eomgung-dong"
    ],
    "name:kor_x_preferred":[
        "\uc5c4\uad81\ub3d9"
    ],
    "name:und_x_variant":[
        "\u014emgung-ni"
    ],
    "qs:name":"\uc5c4\uad81\ub3d9",
    "qs:name_adm0":"\ud55c\uad6d",
    "qs:name_adm1":"\ubd80\uc0b0",
    "qs:photos":2,
    "qs:photos_1k":1,
    "qs:photos_9k":1,
    "qs:photos_9r":1,
    "qs:photos_all":2,
    "qs:photos_sr":1,
    "qs:placetype":"Suburb",
    "qs:pop_sr":"0",
    "wof:name":"Eomgung-dong",
    "wof:placetype":"neighbourhood",
    "wof:population":0
},
  "geometry": {"coordinates":[128.97721999999999,35.12861],"type":"Point"}
}