{
  "type": "Feature",
  "properties": {
    "gn:admin1_code":"17.0",
    "gn:asciiname":"Saegat",
    "gn:country_code":"KR",
    "gn:dem":34,
    "gn:feature_class":"P",
    "gn:feature_code":"PPL",
    "gn:name":"Saegat",
    "gn:population":0,
    "gn:timezone":"Asia/Seoul",
    "iso:country":"KR",
    "name:und_x_variant":[
        "\uc0c8\uac13",
        "Saegat"
    ],
    "wof:name":"Saegat",
    "wof:placetype":"locality"
},
  "geometry": {"coordinates":[127.08,36.3355],"type":"Point"}
}