{
  "type": "Feature",
  "properties": {
    "gn:admin1_code":"14.0",
    "gn:asciiname":"Jakcheon",
    "gn:country_code":"KR",
    "gn:dem":147,
    "gn:feature_class":"P",
    "gn:feature_code":"PPL",
    "gn:name":"Jakcheon",
    "gn:population":0,
    "gn:timezone":"Asia/Seoul",
    "iso:country":"KR",
    "name:kor_x_preferred":[
        "\uc791\ucc9c"
    ],
    "wof:name":"Jakcheon",
    "wof:placetype":"locality"
},
  "geometry": {"coordinates":[128.04808,36.63735],"type":"Point"}
}