{
  "type": "Feature",
  "properties": {
    "gn:admin1_code":"17.0",
    "gn:asciiname":"Araetbaeil",
    "gn:country_code":"KR",
    "gn:dem":73,
    "gn:feature_class":"P",
    "gn:feature_code":"PPL",
    "gn:name":"Araetbaeil",
    "gn:population":0,
    "gn:timezone":"Asia/Seoul",
    "iso:country":"KR",
    "name:kor_x_preferred":[
        "\uc544\ub7ab\ubc30\uc77c"
    ],
    "wof:name":"Araetbaeil",
    "wof:placetype":"locality"
},
  "geometry": {"coordinates":[127.25444,36.67005],"type":"Point"}
}