{
  "type": "Feature",
  "properties": {
    "gn:admin1_code":"6.0",
    "gn:asciiname":"Kwangam",
    "gn:country_code":"KR",
    "gn:dem":180,
    "gn:feature_class":"P",
    "gn:feature_code":"PPL",
    "gn:name":"Kwangam",
    "gn:population":0,
    "gn:timezone":"Asia/Seoul",
    "iso:country":"KR",
    "name:kor_x_preferred":[
        "\uad11\uc554"
    ],
    "wof:name":"Kwangam",
    "wof:placetype":"locality"
},
  "geometry": {"coordinates":[128.07299999999998,37.4892],"type":"Point"}
}