{
  "type": "Feature",
  "properties": {
    "gn:admin1_code":"13.0",
    "gn:asciiname":"Gaemigol",
    "gn:country_code":"KR",
    "gn:dem":25,
    "gn:feature_class":"P",
    "gn:feature_code":"PPL",
    "gn:name":"Gaemigol",
    "gn:population":0,
    "gn:timezone":"Asia/Seoul",
    "iso:country":"KR",
    "name:und_x_variant":[
        "\uac1c\ubbf8\uace8",
        "Gaemigol",
        "Kaemi-gol"
    ],
    "wof:name":"Gaemigol",
    "wof:placetype":"locality"
},
  "geometry": {"coordinates":[126.92083,37.055],"type":"Point"}
}