{
  "type": "Feature",
  "properties": {
    "gn:admin1_code":"6.0",
    "gn:asciiname":"Ansamgul-li",
    "gn:country_code":"KR",
    "gn:dem":392,
    "gn:feature_class":"P",
    "gn:feature_code":"PPL",
    "gn:name":"Ansamgul-li",
    "gn:population":0,
    "gn:timezone":"Asia/Seoul",
    "iso:country":"KR",
    "name:kor_x_preferred":[
        "\uc548\uc0bc\uad70\ub9ac"
    ],
    "wof:name":"Ansamgul-li",
    "wof:placetype":"locality"
},
  "geometry": {"coordinates":[128.02350000000001,37.5856],"type":"Point"}
}