{
  "type": "Feature",
  "properties": {
    "gn:admin1_code":"13.0",
    "gn:admin2_code":"P'aju-si",
    "gn:asciiname":"Dunbang",
    "gn:country_code":"KR",
    "gn:dem":53,
    "gn:feature_class":"P",
    "gn:feature_code":"PPL",
    "gn:name":"Dunbang",
    "gn:population":0,
    "gn:timezone":"Asia/Seoul",
    "iso:country":"KR",
    "name:kor_x_preferred":[
        "\ub454\ubc29"
    ],
    "name:und_x_variant":[
        "Tunbang"
    ],
    "wof:name":"Dunbang",
    "wof:placetype":"locality"
},
  "geometry": {"coordinates":[126.87241000000002,37.83269],"type":"Point"}
}