{
  "type": "Feature",
  "properties": {
    "gn:admin1_code":"14.0",
    "gn:asciiname":"Nae-gol",
    "gn:country_code":"KR",
    "gn:dem":123,
    "gn:feature_class":"P",
    "gn:feature_code":"PPL",
    "gn:name":"Nae-gol",
    "gn:population":0,
    "gn:timezone":"Asia/Seoul",
    "iso:country":"KR",
    "name:und_x_variant":[
        "\ub0b4\uace8",
        "Nae-gol"
    ],
    "wof:name":"Nae-gol",
    "wof:placetype":"locality"
},
  "geometry": {"coordinates":[128.08680000000001,36.3732],"type":"Point"}
}