{
  "type": "Feature",
  "properties": {
    "gn:admin1_code":"17.0",
    "gn:asciiname":"Tarich'i",
    "gn:country_code":"KR",
    "gn:dem":124,
    "gn:feature_class":"P",
    "gn:feature_code":"PPL",
    "gn:name":"Tarich\u2019i",
    "gn:population":0,
    "gn:timezone":"Asia/Seoul",
    "iso:country":"KR",
    "name:und_x_variant":[
        "W\u014flchi-ri",
        "Talch\u2019i",
        "\ub2e4\ub9ac\uce58",
        "Tarich\u2019i"
    ],
    "wof:name":"Tarich'i",
    "wof:placetype":"locality"
},
  "geometry": {"coordinates":[126.69370000000001,36.3804],"type":"Point"}
}