{
  "type": "Feature",
  "properties": {
    "gn:admin1_code":"5.0",
    "gn:asciiname":"Jungtungmal",
    "gn:country_code":"KR",
    "gn:dem":75,
    "gn:feature_class":"P",
    "gn:feature_code":"PPL",
    "gn:name":"Jungtungmal",
    "gn:population":0,
    "gn:timezone":"Asia/Seoul",
    "iso:country":"KR",
    "name:kor_x_preferred":[
        "\uc911\ud241\ub9d0"
    ],
    "wof:name":"Jungtungmal",
    "wof:placetype":"locality"
},
  "geometry": {"coordinates":[127.60154,37.06927],"type":"Point"}
}