{
  "type": "Feature",
  "properties": {
    "gn:admin1_code":"16.0",
    "gn:asciiname":"Kyo-dong",
    "gn:country_code":"KR",
    "gn:dem":35,
    "gn:feature_class":"P",
    "gn:feature_code":"PPL",
    "gn:name":"Kyo-dong",
    "gn:population":0,
    "gn:timezone":"Asia/Seoul",
    "iso:country":"KR",
    "name:kor_x_preferred":[
        "\ub4ec\uc0b0"
    ],
    "wof:name":"Kyo-dong",
    "wof:placetype":"locality"
},
  "geometry": {"coordinates":[126.81083,34.62],"type":"Point"}
}