{
  "type": "Feature",
  "properties": {
    "gn:admin1_code":"16.0",
    "gn:asciiname":"Choran",
    "gn:country_code":"KR",
    "gn:dem":13,
    "gn:feature_class":"P",
    "gn:feature_code":"PPL",
    "gn:name":"Choran",
    "gn:population":0,
    "gn:timezone":"Asia/Seoul",
    "iso:country":"KR",
    "name:fas_x_preferred":[
        "\u0686\u0648\u0631\u0627\u0646"
    ],
    "name:kor_x_preferred":[
        "\ucd08\ub780"
    ],
    "name:und_x_variant":[
        "Ch\u2019orando"
    ],
    "name:urd_x_preferred":[
        "\u0686\u0648\u0631\u0627\u0646"
    ],
    "wof:name":"Choran",
    "wof:placetype":"locality"
},
  "geometry": {"coordinates":[126.16853999999999,34.88372],"type":"Point"}
}