{
  "type": "Feature",
  "properties": {
    "gn:admin1_code":"17.0",
    "gn:asciiname":"Aejong-ni",
    "gn:country_code":"KR",
    "gn:dem":17,
    "gn:feature_class":"P",
    "gn:feature_code":"PPLL",
    "gn:name":"Aej\u014fng-ni",
    "gn:population":0,
    "gn:timezone":"Asia/Seoul",
    "iso:country":"KR",
    "name:eng_x_preferred":[
        "Aejong"
    ],
    "name:eng_x_variant":[
        "Aejong-ni"
    ],
    "name:und_x_variant":[
        "Yej\u014fng-ni",
        "\uc560\uc815\ub9ac",
        "Aej\u014fng-ni"
    ],
    "wof:name":"Aejong",
    "wof:placetype":"locality"
},
  "geometry": {"coordinates":[126.42034,36.73191],"type":"Point"}
}