{
  "type": "Feature",
  "properties": {
    "gn:admin1_code":"5.0",
    "gn:asciiname":"Mosil",
    "gn:country_code":"KR",
    "gn:dem":247,
    "gn:feature_class":"P",
    "gn:feature_code":"PPL",
    "gn:name":"Mosil",
    "gn:population":0,
    "gn:timezone":"Asia/Seoul",
    "iso:country":"KR",
    "name:kor_x_preferred":[
        "\ubaa8\uc2e4"
    ],
    "wof:name":"Mosil",
    "wof:placetype":"locality"
},
  "geometry": {"coordinates":[128.32380000000001,37.0919],"type":"Point"}
}