{
  "type": "Feature",
  "properties": {
    "gn:admin1_code":"6.0",
    "gn:asciiname":"Beomuri",
    "gn:country_code":"KR",
    "gn:dem":595,
    "gn:feature_class":"P",
    "gn:feature_code":"PPL",
    "gn:name":"Beomuri",
    "gn:population":0,
    "gn:timezone":"Asia/Seoul",
    "iso:country":"KR",
    "name:kor_x_preferred":[
        "\uc6c3\ubc94\uc6b0\ub9ac"
    ],
    "name:kor_x_variant":[
        "Upp\u014fmu-ri",
        "\ubc94\uc6b0\ub9ac"
    ],
    "wof:name":"Beomuri",
    "wof:placetype":"locality"
},
  "geometry": {"coordinates":[128.58914999999999,37.65143],"type":"Point"}
}