{
  "type": "Feature",
  "properties": {
    "gn:admin1_code":"14.0",
    "gn:asciiname":"Ha-ch'on",
    "gn:country_code":"KR",
    "gn:dem":124,
    "gn:feature_class":"P",
    "gn:feature_code":"PPL",
    "gn:name":"Ha-ch\u2019on",
    "gn:population":0,
    "gn:timezone":"Asia/Seoul",
    "iso:country":"KR",
    "name:und_x_variant":[
        "\ud558\ucd0c",
        "Ha-ch\u2019on"
    ],
    "wof:name":"Ha-ch'on",
    "wof:placetype":"locality"
},
  "geometry": {"coordinates":[128.07210000000001,36.0421],"type":"Point"}
}