{
  "type": "Feature",
  "properties": {
    "iso:country":"KR",
    "qs:name":"\uc625\ub3c4\uba74",
    "qs:name_adm0":"\ud55c\uad6d",
    "qs:name_adm1":"\uc804\ub77c\ubd81\ub3c4",
    "qs:photos":19,
    "qs:photos_1k":4,
    "qs:photos_9k":1,
    "qs:photos_9r":1,
    "qs:photos_all":19,
    "qs:photos_sr":1,
    "qs:placetype":"LocalAdmin",
    "qs:pop_sr":"0",
    "wof:name":"\uc625\ub3c4\uba74",
    "wof:placetype":"localadmin"
},
  "geometry": {"coordinates":[126.448516,35.8245285],"type":"Point"}
}