{
  "type": "Feature",
  "properties": {
    "gn:admin1_code":"17.0",
    "gn:asciiname":"Yangsanmal",
    "gn:country_code":"KR",
    "gn:dem":116,
    "gn:feature_class":"P",
    "gn:feature_code":"PPL",
    "gn:name":"Yangsanmal",
    "gn:population":0,
    "gn:timezone":"Asia/Seoul",
    "iso:country":"KR",
    "name:und_x_variant":[
        "\uc591\uc0b0\ub9d0",
        "Yangsanmal"
    ],
    "wof:name":"Yangsanmal",
    "wof:placetype":"locality"
},
  "geometry": {"coordinates":[127.26683,36.20947],"type":"Point"}
}