{
  "type": "Feature",
  "properties": {
    "gn:admin1_code":"20.0",
    "gn:asciiname":"Kump'yong",
    "gn:country_code":"KR",
    "gn:dem":38,
    "gn:feature_class":"P",
    "gn:feature_code":"PPL",
    "gn:name":"K\u016dmp\u2019y\u014fng",
    "gn:population":0,
    "gn:timezone":"Asia/Seoul",
    "iso:country":"KR",
    "name:und_x_variant":[
        "\uae08\ud3c9",
        "K\u016dmp\u2019y\u014fng"
    ],
    "wof:name":"Kump'yong",
    "wof:placetype":"locality"
},
  "geometry": {"coordinates":[128.16717,35.52753],"type":"Point"}
}