{
  "type": "Feature",
  "properties": {
    "gn:admin1_code":"14.0",
    "gn:asciiname":"Ch'ilsong-ni",
    "gn:country_code":"KR",
    "gn:dem":74,
    "gn:feature_class":"P",
    "gn:feature_code":"PPL",
    "gn:name":"Ch\u2019ils\u014fng-ni",
    "gn:population":0,
    "gn:timezone":"Asia/Seoul",
    "iso:country":"KR",
    "name:und_x_variant":[
        "\uce60\uc131\ub9ac",
        "Ch\u2019ils\u014fng-ni"
    ],
    "wof:name":"Ch'ilsong-ni",
    "wof:placetype":"locality"
},
  "geometry": {"coordinates":[128.26485,35.99799],"type":"Point"}
}