{
  "type": "Feature",
  "properties": {
    "gn:admin1_code":"17.0",
    "gn:asciiname":"Kobun",
    "gn:country_code":"KR",
    "gn:dem":43,
    "gn:feature_class":"P",
    "gn:feature_code":"PPL",
    "gn:name":"Kobun",
    "gn:population":0,
    "gn:timezone":"Asia/Seoul",
    "iso:country":"KR",
    "name:und_x_variant":[
        "Maj\u014fl-li"
    ],
    "wof:name":"Kobun",
    "wof:placetype":"locality"
},
  "geometry": {"coordinates":[127.09083,36.08611],"type":"Point"}
}