{
  "type": "Feature",
  "properties": {
    "gn:admin1_code":"13.0",
    "gn:asciiname":"Garim",
    "gn:country_code":"KR",
    "gn:dem":309,
    "gn:feature_class":"P",
    "gn:feature_code":"PPL",
    "gn:name":"Garim",
    "gn:population":0,
    "gn:timezone":"Asia/Seoul",
    "iso:country":"KR",
    "name:kor_x_preferred":[
        "\uac00\ub9bc"
    ],
    "name:und_x_variant":[
        "Karim",
        "Garim"
    ],
    "wof:name":"Garim",
    "wof:placetype":"locality"
},
  "geometry": {"coordinates":[127.44273,37.97671],"type":"Point"}
}