{
  "type": "Feature",
  "properties": {
    "gn:admin1_code":"17.0",
    "gn:asciiname":"P'yongt'i",
    "gn:country_code":"KR",
    "gn:dem":101,
    "gn:feature_class":"P",
    "gn:feature_code":"PPL",
    "gn:name":"P\u2019y\u014fngt\u2019i",
    "gn:population":0,
    "gn:timezone":"Asia/Seoul",
    "iso:country":"KR",
    "name:und_x_variant":[
        "\ud3c9\ud2f0",
        "P\u2019y\u014fngt\u2019i"
    ],
    "wof:name":"P'yongt'i",
    "wof:placetype":"locality"
},
  "geometry": {"coordinates":[126.7223,36.4998],"type":"Point"}
}