{
  "type": "Feature",
  "properties": {
    "gn:admin1_code":"16.0",
    "gn:asciiname":"Sogoji",
    "gn:cc2":"KR",
    "gn:country_code":"KR",
    "gn:dem":42,
    "gn:feature_class":"P",
    "gn:feature_code":"PPL",
    "gn:name":"S\u014fgoji",
    "gn:population":0,
    "gn:timezone":"Asia/Seoul",
    "iso:country":"KR",
    "name:und_x_variant":[
        "S\u014f-koji",
        "S\u014fguji",
        "S\u014fgoji"
    ],
    "wof:name":"Sogoji",
    "wof:placetype":"locality"
},
  "geometry": {"coordinates":[127.80056,34.47833],"type":"Point"}
}