{
  "type": "Feature",
  "properties": {
    "gn:admin1_code":"16.0",
    "gn:asciiname":"Cheongnyong",
    "gn:country_code":"KR",
    "gn:dem":47,
    "gn:feature_class":"P",
    "gn:feature_code":"PPL",
    "gn:name":"Cheongnyong",
    "gn:population":0,
    "gn:timezone":"Asia/Seoul",
    "iso:country":"KR",
    "name:kor_x_preferred":[
        "\uccad\ub8e1"
    ],
    "name:und_x_variant":[
        "Ch\u2019\u014fngnyang",
        "Ch\u2019\u014fngnyong",
        "Cheongnyong"
    ],
    "wof:name":"Cheongnyong",
    "wof:placetype":"locality"
},
  "geometry": {"coordinates":[126.71173,34.88402],"type":"Point"}
}