{
  "type": "Feature",
  "properties": {
    "gn:admin1_code":"6.0",
    "gn:asciiname":"Anmaeil",
    "gn:country_code":"KR",
    "gn:dem":273,
    "gn:feature_class":"P",
    "gn:feature_code":"PPL",
    "gn:name":"Anmaeil",
    "gn:population":0,
    "gn:timezone":"Asia/Seoul",
    "iso:country":"KR",
    "name:kor_x_preferred":[
        "\uc548\ub9e4\uc77c"
    ],
    "wof:name":"Anmaeil",
    "wof:placetype":"locality"
},
  "geometry": {"coordinates":[128.13299999999998,37.5476],"type":"Point"}
}