{
  "type": "Feature",
  "properties": {
    "gn:admin1_code":"11.0",
    "gn:asciiname":"Wolgyeil-tong",
    "gn:country_code":"KR",
    "gn:dem":46,
    "gn:feature_class":"P",
    "gn:feature_code":"PPL",
    "gn:name":"Wolgyeil-tong",
    "gn:population":0,
    "gn:timezone":"Asia/Seoul",
    "iso:country":"KR",
    "name:und_x_variant":[
        "\uc6d4\uacc41\ub3d9",
        "Wolgyeil-tong"
    ],
    "wof:name":"Wolgyeil-tong",
    "wof:placetype":"locality"
},
  "geometry": {"coordinates":[127.06251,37.61874],"type":"Point"}
}