{
  "type": "Feature",
  "properties": {
    "gn:admin1_code":"5.0",
    "gn:asciiname":"Kwangsan",
    "gn:country_code":"KR",
    "gn:dem":238,
    "gn:feature_class":"P",
    "gn:feature_code":"PPL",
    "gn:name":"Kwangsan",
    "gn:population":0,
    "gn:timezone":"Asia/Seoul",
    "iso:country":"KR",
    "name:und_x_variant":[
        "Kwangsan-ch\u2019on",
        "\uad11\uc0b0\ucd0c"
    ],
    "wof:name":"Kwangsan",
    "wof:placetype":"locality"
},
  "geometry": {"coordinates":[127.8749,36.3536],"type":"Point"}
}