{
  "type": "Feature",
  "properties": {
    "gn:admin1_code":"5.0",
    "gn:asciiname":"Tongmulppuri",
    "gn:country_code":"KR",
    "gn:dem":119,
    "gn:feature_class":"P",
    "gn:feature_code":"PPL",
    "gn:name":"Tongmulppuri",
    "gn:population":0,
    "gn:timezone":"Asia/Seoul",
    "iso:country":"KR",
    "name:kor_x_preferred":[
        "\uc6d4\ud3ec"
    ],
    "name:kor_x_variant":[
        "W\u014flp\u2019o",
        "\ud1b5\ubb3c\ubfcc\ub9ac"
    ],
    "name:und_x_variant":[
        "Wolpo",
        "Tongmulppuri"
    ],
    "wof:name":"Tongmulppuri",
    "wof:placetype":"locality"
},
  "geometry": {"coordinates":[127.75211000000002,37.11246],"type":"Point"}
}