{
  "type": "Feature",
  "properties": {
    "gn:admin1_code":"14.0",
    "gn:asciiname":"Anhwanghae",
    "gn:country_code":"KR",
    "gn:dem":248,
    "gn:feature_class":"P",
    "gn:feature_code":"PPL",
    "gn:name":"Anhwanghae",
    "gn:population":0,
    "gn:timezone":"Asia/Seoul",
    "iso:country":"KR",
    "name:kor_x_preferred":[
        "\uc548\ud669\ud574"
    ],
    "wof:name":"Anhwanghae",
    "wof:placetype":"locality"
},
  "geometry": {"coordinates":[128.74274,36.94848],"type":"Point"}
}