{
  "type": "Feature",
  "properties": {
    "gn:admin1_code":"17.0",
    "gn:asciiname":"Angol",
    "gn:country_code":"KR",
    "gn:dem":41,
    "gn:feature_class":"P",
    "gn:feature_code":"PPL",
    "gn:name":"Angol",
    "gn:population":0,
    "gn:timezone":"Asia/Seoul",
    "iso:country":"KR",
    "name:kor_x_preferred":[
        "\uc548\uace8"
    ],
    "wof:name":"Angol",
    "wof:placetype":"locality"
},
  "geometry": {"coordinates":[127.28675,36.62497000000001],"type":"Point"}
}