{
  "type": "Feature",
  "properties": {
    "gn:admin1_code":"5.0",
    "gn:asciiname":"Ogung-ri",
    "gn:country_code":"KR",
    "gn:dem":127,
    "gn:feature_class":"P",
    "gn:feature_code":"PPLL",
    "gn:name":"Ogung-ri",
    "gn:population":0,
    "gn:timezone":"Asia/Seoul",
    "iso:country":"KR",
    "name:kor_x_preferred":[
        "\uc624\uad81\ub9ac"
    ],
    "name:und_x_variant":[
        "Ogung-ni"
    ],
    "wof:name":"Ogung-ri",
    "wof:placetype":"locality"
},
  "geometry": {"coordinates":[127.68923999999998,37.10816],"type":"Point"}
}