{
  "type": "Feature",
  "properties": {
    "gn:admin1_code":"6.0",
    "gn:asciiname":"Choridong",
    "gn:country_code":"KR",
    "gn:dem":209,
    "gn:feature_class":"P",
    "gn:feature_code":"PPL",
    "gn:name":"Choridong",
    "gn:population":0,
    "gn:timezone":"Asia/Seoul",
    "iso:country":"KR",
    "name:kor_x_preferred":[
        "\ucd08\ub9ac\ub3d9"
    ],
    "wof:name":"Choridong",
    "wof:placetype":"locality"
},
  "geometry": {"coordinates":[127.29688,38.21882],"type":"Point"}
}