{
  "type": "Feature",
  "properties": {
    "gn:admin1_code":"6.0",
    "gn:asciiname":"Changch'ang-dong",
    "gn:country_code":"KR",
    "gn:dem":601,
    "gn:feature_class":"P",
    "gn:feature_code":"PPL",
    "gn:name":"Changch\u2019ang-dong",
    "gn:population":0,
    "gn:timezone":"Asia/Seoul",
    "iso:country":"KR",
    "name:kor_x_preferred":[
        "\uc7a5\ucc3d\ub3d9"
    ],
    "name:kor_x_variant":[
        "Changch\u2019ang-dong"
    ],
    "wof:name":"Changch'ang-dong",
    "wof:placetype":"locality"
},
  "geometry": {"coordinates":[128.8699,37.4733],"type":"Point"}
}