{
  "type": "Feature",
  "properties": {
    "gn:admin1_code":"17.0",
    "gn:asciiname":"Kuong-mal",
    "gn:country_code":"KR",
    "gn:dem":37,
    "gn:feature_class":"P",
    "gn:feature_code":"PPL",
    "gn:name":"Kuong-mal",
    "gn:population":0,
    "gn:timezone":"Asia/Seoul",
    "iso:country":"KR",
    "name:und_x_variant":[
        "\uad6c\uc625\ub9d0",
        "Kuong-mal"
    ],
    "wof:name":"Kuong-mal",
    "wof:placetype":"locality"
},
  "geometry": {"coordinates":[126.81229999999999,36.2679],"type":"Point"}
}