{
  "type": "Feature",
  "properties": {
    "gn:admin1_code":"17.0",
    "gn:asciiname":"Tong-ch'on",
    "gn:country_code":"KR",
    "gn:dem":58,
    "gn:feature_class":"P",
    "gn:feature_code":"PPL",
    "gn:name":"Tong-ch\u2019on",
    "gn:population":0,
    "gn:timezone":"Asia/Seoul",
    "iso:country":"KR",
    "name:und_x_variant":[
        "\ub3d9\ucd0c",
        "Tong-ch\u2019on"
    ],
    "wof:name":"Tong-ch'on",
    "wof:placetype":"locality"
},
  "geometry": {"coordinates":[126.8728,36.5809],"type":"Point"}
}