{
  "type": "Feature",
  "properties": {
    "gn:admin1_code":"6.0",
    "gn:asciiname":"Towon-dong",
    "gn:country_code":"KR",
    "gn:dem":426,
    "gn:feature_class":"P",
    "gn:feature_code":"PPL",
    "gn:name":"Tow\u014fn-dong",
    "gn:population":0,
    "gn:timezone":"Asia/Seoul",
    "iso:country":"KR",
    "name:kor_x_preferred":[
        "\ub3c4\uc6d0\ub3d9"
    ],
    "name:kor_x_variant":[
        "Tow\u014fn-dong"
    ],
    "wof:name":"Towon-dong",
    "wof:placetype":"locality"
},
  "geometry": {"coordinates":[128.46180000000001,37.4485],"type":"Point"}
}