{
  "type": "Feature",
  "properties": {
    "gn:admin1_code":"13.0",
    "gn:asciiname":"Seongchon",
    "gn:country_code":"KR",
    "gn:dem":64,
    "gn:feature_class":"P",
    "gn:feature_code":"PPL",
    "gn:name":"Seongchon",
    "gn:population":0,
    "gn:timezone":"Asia/Seoul",
    "iso:country":"KR",
    "name:und_x_variant":[
        "\uc131\ucd0c",
        "S\u014fngch\u2019on",
        "Seongchon"
    ],
    "wof:name":"Seongchon",
    "wof:placetype":"locality"
},
  "geometry": {"coordinates":[126.90876000000002,37.68883],"type":"Point"}
}