{
  "type": "Feature",
  "properties": {
    "gn:admin1_code":"16.0",
    "gn:asciiname":"Haeryong",
    "gn:country_code":"KR",
    "gn:dem":231,
    "gn:feature_class":"P",
    "gn:feature_code":"PPL",
    "gn:name":"Haeryong",
    "gn:population":0,
    "gn:timezone":"Asia/Seoul",
    "iso:country":"KR",
    "name:kor_x_preferred":[
        "\ud574\ub8e1"
    ],
    "name:und_x_variant":[
        "Haeryong-ni",
        "Haeyong-ni",
        "Haeryong"
    ],
    "wof:name":"Haeryong",
    "wof:placetype":"locality"
},
  "geometry": {"coordinates":[127.00445999999999,34.70422],"type":"Point"}
}