{
  "type": "Feature",
  "properties": {
    "iso:country":"KR",
    "name:eng_x_preferred":[
        "Iwol-myeon"
    ],
    "name:kor_x_preferred":[
        "\uc774\uc6d4\uba74"
    ],
    "qs:name":"\uc774\uc6d4\uba74",
    "qs:name_adm0":"\ud55c\uad6d",
    "qs:name_adm1":"\ucda9\uccad\ubd81\ub3c4",
    "qs:photos":1,
    "qs:photos_1k":1,
    "qs:photos_9k":1,
    "qs:photos_9r":1,
    "qs:photos_all":1,
    "qs:photos_sr":1,
    "qs:placetype":"LocalAdmin",
    "qs:pop_sr":"0",
    "wof:name":"Iwol-myeon",
    "wof:placetype":"localadmin"
},
  "geometry": {"coordinates":[127.429275,36.885033],"type":"Point"}
}