{
  "type": "Feature",
  "properties": {
    "gn:admin1_code":"13.0",
    "gn:asciiname":"Songchon-ri",
    "gn:country_code":"KR",
    "gn:dem":44,
    "gn:feature_class":"P",
    "gn:feature_code":"PPLL",
    "gn:name":"Songchon-ri",
    "gn:population":0,
    "gn:timezone":"Asia/Seoul",
    "iso:country":"KR",
    "name:und_x_variant":[
        "\uc1a1\ucd0c\ub9ac",
        "Songchon-ri",
        "Songch\u2019ol-li"
    ],
    "wof:name":"Songchon-ri",
    "wof:placetype":"locality"
},
  "geometry": {"coordinates":[127.56222,37.40722],"type":"Point"}
}