{
  "type": "Feature",
  "properties": {
    "gn:admin1_code":"6.0",
    "gn:asciiname":"Hwap'yong-dong",
    "gn:country_code":"KR",
    "gn:dem":24,
    "gn:feature_class":"P",
    "gn:feature_code":"PPL",
    "gn:name":"Hwap\u2019y\u014fng-dong",
    "gn:population":0,
    "gn:timezone":"Asia/Seoul",
    "iso:country":"KR",
    "name:kor_x_preferred":[
        "\ud654\ud3c9\ub3d9"
    ],
    "name:kor_x_variant":[
        "Hwap\u2019y\u014fng-dong"
    ],
    "name:und_x_variant":[
        "Kahei-d\u014d",
        "Hap\u2019y\u014fng-dong",
        "Kahy\u014d-d\u014d"
    ],
    "wof:name":"Hwap'yong-dong",
    "wof:placetype":"locality"
},
  "geometry": {"coordinates":[128.869,37.8409],"type":"Point"}
}