{
  "type": "Feature",
  "properties": {
    "gn:admin1_code":"16.0",
    "gn:asciiname":"Yangchon",
    "gn:country_code":"KR",
    "gn:dem":55,
    "gn:feature_class":"P",
    "gn:feature_code":"PPL",
    "gn:name":"Yangchon",
    "gn:population":0,
    "gn:timezone":"Asia/Seoul",
    "iso:country":"KR",
    "name:kor_x_preferred":[
        "Yangch\u2019on"
    ],
    "name:kor_x_variant":[
        "\uc591\ucd0c"
    ],
    "wof:name":"Yangchon",
    "wof:placetype":"locality"
},
  "geometry": {"coordinates":[126.89659,34.72826],"type":"Point"}
}