{
  "type": "Feature",
  "properties": {
    "gn:admin1_code":"17.0",
    "gn:asciiname":"Jungsamni",
    "gn:country_code":"KR",
    "gn:dem":52,
    "gn:feature_class":"P",
    "gn:feature_code":"PPL",
    "gn:name":"Jungsamni",
    "gn:population":0,
    "gn:timezone":"Asia/Seoul",
    "iso:country":"KR",
    "name:kor_x_preferred":[
        "\uc911\uc0bc\ub9ac"
    ],
    "wof:name":"Jungsamni",
    "wof:placetype":"locality"
},
  "geometry": {"coordinates":[126.89995999999999,36.63716],"type":"Point"}
}