{
  "type": "Feature",
  "properties": {
    "gn:admin1_code":"13.0",
    "gn:asciiname":"Paemi",
    "gn:country_code":"KR",
    "gn:dem":54,
    "gn:feature_class":"P",
    "gn:feature_code":"PPL",
    "gn:name":"Paemi",
    "gn:population":0,
    "gn:timezone":"Asia/Seoul",
    "iso:country":"KR",
    "name:und_x_variant":[
        "\ubc30\ubbf8",
        "Baemi",
        "Paemi"
    ],
    "wof:name":"Paemi",
    "wof:placetype":"locality"
},
  "geometry": {"coordinates":[127.68389000000001,37.28889],"type":"Point"}
}