{
  "type": "Feature",
  "properties": {
    "gn:admin1_code":"13.0",
    "gn:asciiname":"Neureupjeongi",
    "gn:country_code":"KR",
    "gn:dem":118,
    "gn:feature_class":"P",
    "gn:feature_code":"PPL",
    "gn:name":"Neureupjeongi",
    "gn:population":0,
    "gn:timezone":"Asia/Seoul",
    "iso:country":"KR",
    "name:kor_x_preferred":[
        "\ub290\ub985\uc815\uc774"
    ],
    "wof:name":"Neureupjeongi",
    "wof:placetype":"locality"
},
  "geometry": {"coordinates":[127.25492,38.03382],"type":"Point"}
}