{
  "type": "Feature",
  "properties": {
    "gn:admin1_code":"5.0",
    "gn:asciiname":"Bangunde",
    "gn:country_code":"KR",
    "gn:dem":85,
    "gn:feature_class":"P",
    "gn:feature_code":"PPL",
    "gn:name":"Bangunde",
    "gn:population":0,
    "gn:timezone":"Asia/Seoul",
    "iso:country":"KR",
    "name:kor_x_preferred":[
        "\ubc29\uc6b4\ub370"
    ],
    "wof:name":"Bangunde",
    "wof:placetype":"locality"
},
  "geometry": {"coordinates":[127.52552,36.93817],"type":"Point"}
}