{
  "type": "Feature",
  "properties": {
    "gn:admin1_code":"5.0",
    "gn:asciiname":"Tonggubak",
    "gn:country_code":"KR",
    "gn:dem":283,
    "gn:feature_class":"P",
    "gn:feature_code":"PPL",
    "gn:name":"Tonggubak",
    "gn:population":0,
    "gn:timezone":"Asia/Seoul",
    "iso:country":"KR",
    "name:kor_x_preferred":[
        "\ub3d9\uad6c\ubc16"
    ],
    "wof:name":"Tonggubak",
    "wof:placetype":"locality"
},
  "geometry": {"coordinates":[128.10290000000001,37.1561],"type":"Point"}
}