{
  "type": "Feature",
  "properties": {
    "gn:admin1_code":"17.0",
    "gn:asciiname":"Mok-kol",
    "gn:country_code":"KR",
    "gn:dem":221,
    "gn:feature_class":"P",
    "gn:feature_code":"PPL",
    "gn:name":"Mok-kol",
    "gn:population":0,
    "gn:timezone":"Asia/Seoul",
    "iso:country":"KR",
    "name:und_x_variant":[
        "\ubaa9\uace8",
        "Mok-kol"
    ],
    "wof:name":"Mok-kol",
    "wof:placetype":"locality"
},
  "geometry": {"coordinates":[127.3775,36.1338],"type":"Point"}
}