{
  "type": "Feature",
  "properties": {
    "gn:admin1_code":"16.0",
    "gn:asciiname":"Chuksan-ni",
    "gn:country_code":"KR",
    "gn:dem":14,
    "gn:feature_class":"P",
    "gn:feature_code":"PPL",
    "gn:name":"Chuksan-ni",
    "gn:population":0,
    "gn:timezone":"Asia/Seoul",
    "iso:country":"KR",
    "name:eng_x_preferred":[
        "Chuksan"
    ],
    "name:eng_x_variant":[
        "Chuksan-ni"
    ],
    "name:und_x_variant":[
        "Ch\u014fgu",
        "Ch\u014flgu",
        "Chuksal-li"
    ],
    "wof:name":"Chuksan",
    "wof:placetype":"locality"
},
  "geometry": {"coordinates":[126.61667,34.98333],"type":"Point"}
}