{
  "type": "Feature",
  "properties": {
    "gn:admin1_code":"16.0",
    "gn:asciiname":"T'aesang",
    "gn:country_code":"KR",
    "gn:dem":32,
    "gn:feature_class":"P",
    "gn:feature_code":"PPL",
    "gn:name":"T\u2019aesang",
    "gn:population":0,
    "gn:timezone":"Asia/Seoul",
    "iso:country":"KR",
    "name:kor_x_preferred":[
        "T\u2019aesang"
    ],
    "name:und_x_variant":[
        "\ud0dc\uc0c1"
    ],
    "wof:name":"T'aesang",
    "wof:placetype":"locality"
},
  "geometry": {"coordinates":[126.53610999999999,34.60722],"type":"Point"}
}