{
  "type": "Feature",
  "properties": {
    "gn:admin1_code":"20.0",
    "gn:asciiname":"Bamgum",
    "gn:country_code":"KR",
    "gn:dem":23,
    "gn:feature_class":"P",
    "gn:feature_code":"PPL",
    "gn:name":"Bamgum",
    "gn:population":0,
    "gn:timezone":"Asia/Seoul",
    "iso:country":"KR",
    "name:und_x_variant":[
        "\ubc24\uad7c",
        "Pamgum",
        "Bamgum"
    ],
    "wof:name":"Bamgum",
    "wof:placetype":"locality"
},
  "geometry": {"coordinates":[128.42416,35.60196],"type":"Point"}
}