{
  "type": "Feature",
  "properties": {
    "gn:admin1_code":"17.0",
    "gn:asciiname":"K'unsonjang",
    "gn:country_code":"KR",
    "gn:dem":16,
    "gn:feature_class":"P",
    "gn:feature_code":"PPL",
    "gn:name":"K\u2019\u016dns\u014fnjang",
    "gn:population":0,
    "gn:timezone":"Asia/Seoul",
    "iso:country":"KR",
    "name:und_x_variant":[
        "\ud070\uc120\uc7a5",
        "K\u2019\u016dns\u014fnjang"
    ],
    "wof:name":"K'unsonjang",
    "wof:placetype":"locality"
},
  "geometry": {"coordinates":[126.8725,36.7934],"type":"Point"}
}