{
  "type": "Feature",
  "properties": {
    "gn:admin1_code":"17.0",
    "gn:asciiname":"Araetboraegol",
    "gn:country_code":"KR",
    "gn:dem":93,
    "gn:feature_class":"P",
    "gn:feature_code":"PPL",
    "gn:name":"Araetboraegol",
    "gn:population":0,
    "gn:timezone":"Asia/Seoul",
    "iso:country":"KR",
    "name:kor_x_preferred":[
        "\uc544\ub7ab\ubcf4\ub798\uace8"
    ],
    "wof:name":"Araetboraegol",
    "wof:placetype":"locality"
},
  "geometry": {"coordinates":[127.13718,36.69057],"type":"Point"}
}