{
  "type": "Feature",
  "properties": {
    "gn:admin1_code":"20.0",
    "gn:asciiname":"Yuch'on",
    "gn:country_code":"KR",
    "gn:dem":24,
    "gn:feature_class":"P",
    "gn:feature_code":"PPL",
    "gn:name":"Yuch\u2019\u014fn",
    "gn:population":0,
    "gn:timezone":"Asia/Seoul",
    "iso:country":"KR",
    "name:und_x_variant":[
        "Yuch\u2019\u014fl-li",
        "\uc720\ucc9c",
        "Yuch\u2019\u014fn"
    ],
    "wof:name":"Yuch'on",
    "wof:placetype":"locality"
},
  "geometry": {"coordinates":[128.36016000000001,35.50415],"type":"Point"}
}