{
  "type": "Feature",
  "properties": {
    "iso:country":"KR",
    "name:eng_x_preferred":[
        "Seojeong-dong"
    ],
    "name:kor_x_preferred":[
        "\uc11c\uc815\ub3d9"
    ],
    "qs:name":"\uc11c\uc815\ub3d9",
    "qs:name_adm0":"\ud55c\uad6d",
    "qs:name_adm1":"\uacbd\uae30\ub3c4",
    "qs:photos":197,
    "qs:photos_1k":40,
    "qs:photos_9k":1,
    "qs:photos_9r":4,
    "qs:photos_all":197,
    "qs:photos_sr":4,
    "qs:placetype":"LocalAdmin",
    "qs:pop_sr":"0",
    "wof:name":"Seojeong-dong",
    "wof:placetype":"localadmin"
},
  "geometry": {"coordinates":[127.05255,37.079333],"type":"Point"}
}