{
  "type": "Feature",
  "properties": {
    "gn:admin1_code":"5.0",
    "gn:asciiname":"Madangteo",
    "gn:country_code":"KR",
    "gn:dem":112,
    "gn:feature_class":"P",
    "gn:feature_code":"PPL",
    "gn:name":"Madangteo",
    "gn:population":0,
    "gn:timezone":"Asia/Seoul",
    "iso:country":"KR",
    "name:kor_x_preferred":[
        "\ub9c8\ub2f9\ud130"
    ],
    "wof:name":"Madangteo",
    "wof:placetype":"locality"
},
  "geometry": {"coordinates":[127.87058,36.99328],"type":"Point"}
}