{
  "type": "Feature",
  "properties": {
    "gn:admin1_code":"14.0",
    "gn:asciiname":"Sindang",
    "gn:country_code":"KR",
    "gn:dem":54,
    "gn:feature_class":"P",
    "gn:feature_code":"PPL",
    "gn:name":"Sindang",
    "gn:population":0,
    "gn:timezone":"Asia/Seoul",
    "iso:country":"KR",
    "name:und_x_variant":[
        "\uc2e0\ub2f9",
        "Sindang"
    ],
    "wof:name":"Sindang",
    "wof:placetype":"locality"
},
  "geometry": {"coordinates":[128.3826,36.3702],"type":"Point"}
}