{
  "type": "Feature",
  "properties": {
    "iso:country":"KR",
    "name:kor_x_preferred":[
        "\ubc95\ub3d9"
    ],
    "qs:gn_adm0_cc":"KR",
    "qs:gn_local":1835235,
    "qs:local_max":1052,
    "qs:local_sum":4707,
    "qs:localhoods":21,
    "qs:name":"\ubc95\ub3d9",
    "qs:name_adm0":"\ud55c\uad6d",
    "qs:name_adm1":"\ub300\uc804",
    "qs:name_adm2":"\ub300\ub355\uad6c",
    "qs:name_local":"\ub300\uc804",
    "qs:photo_max":8,
    "qs:photo_sum":17,
    "qs:placetype":"Suburb",
    "qs:quad_count":4,
    "qs:woe_adm0":23424868,
    "qs:woe_adm1":2345975,
    "qs:woe_adm2":28289139,
    "qs:woe_lau":0,
    "qs:woe_local":1132467,
    "qs:woe_ver":"7.10.0",
    "wof:lang":[
        "kor"
    ],
    "wof:name":"\ubc95\ub3d9",
    "wof:placetype":"neighbourhood"
},
  "geometry": {"coordinates":[127.439955,36.368091],"type":"Point"}
}