{
  "type": "Feature",
  "properties": {
    "gn:admin1_code":"5.0",
    "gn:asciiname":"Ch'ang-ni",
    "gn:country_code":"KR",
    "gn:dem":275,
    "gn:feature_class":"P",
    "gn:feature_code":"PPL",
    "gn:name":"Ch\u2019ang-ni",
    "gn:population":0,
    "gn:timezone":"Asia/Seoul",
    "iso:country":"KR",
    "wof:name":"Ch'ang-ni",
    "wof:placetype":"locality"
},
  "geometry": {"coordinates":[127.66667,36.58333],"type":"Point"}
}