{
  "type": "Feature",
  "properties": {
    "gn:admin1_code":"3.0",
    "gn:asciiname":"Mangsan",
    "gn:country_code":"KR",
    "gn:dem":80,
    "gn:feature_class":"P",
    "gn:feature_code":"PPL",
    "gn:name":"Mangsan",
    "gn:population":0,
    "gn:timezone":"Asia/Seoul",
    "iso:country":"KR",
    "name:und_x_variant":[
        "\ub9dd\uc0b0",
        "Mangsan"
    ],
    "wof:name":"Mangsan",
    "wof:placetype":"locality"
},
  "geometry": {"coordinates":[127.12542999999999,35.71153],"type":"Point"}
}