{
  "type": "Feature",
  "properties": {
    "gn:admin1_code":"13.0",
    "gn:asciiname":"Kapchinmal",
    "gn:country_code":"KR",
    "gn:dem":12,
    "gn:feature_class":"P",
    "gn:feature_code":"PPL",
    "gn:name":"Kapchinmal",
    "gn:population":0,
    "gn:timezone":"Asia/Seoul",
    "iso:country":"KR",
    "name:und_x_variant":[
        "\uac11\uc9c4\ub9d0",
        "Gapjinmal",
        "Kapchinmal"
    ],
    "wof:name":"Kapchinmal",
    "wof:placetype":"locality"
},
  "geometry": {"coordinates":[126.52943999999999,37.23722],"type":"Point"}
}