{
  "type": "Feature",
  "properties": {
    "gn:admin1_code":"6.0",
    "gn:asciiname":"Taegong-ni",
    "gn:country_code":"KR",
    "gn:dem":407,
    "gn:feature_class":"P",
    "gn:feature_code":"PPL",
    "gn:name":"Taegong-ni",
    "gn:population":0,
    "gn:timezone":"Asia/Seoul",
    "iso:country":"KR",
    "name:kor_x_preferred":[
        "\ub300\uace1\ub9ac"
    ],
    "wof:name":"Taegong-ni",
    "wof:placetype":"locality"
},
  "geometry": {"coordinates":[128.24778000000001,38.26778],"type":"Point"}
}