{
  "type": "Feature",
  "properties": {
    "gn:admin1_code":"11.0",
    "gn:asciiname":"Sillim 13-dong",
    "gn:country_code":"KR",
    "gn:dem":55,
    "gn:feature_class":"P",
    "gn:feature_code":"PPL",
    "gn:name":"Sillim 13-dong",
    "gn:population":0,
    "gn:timezone":"Asia/Seoul",
    "iso:country":"KR",
    "name:eng_x_preferred":[
        "Sillim 13-dong"
    ],
    "name:eng_x_variant":[
        "Sillim 13(sipsam)-dong"
    ],
    "name:kor_x_preferred":[
        "\uc2e0\ub9bc13\ub3d9"
    ],
    "wof:name":"Sillim 13-dong",
    "wof:placetype":"locality"
},
  "geometry": {"coordinates":[126.92,37.46861],"type":"Point"}
}