{
  "type": "Feature",
  "properties": {
    "gn:admin1_code":"5.0",
    "gn:asciiname":"Ip'yong-dong",
    "gn:country_code":"KR",
    "gn:dem":121,
    "gn:feature_class":"P",
    "gn:feature_code":"PPL",
    "gn:name":"Ip\u2019y\u014fng-dong",
    "gn:population":0,
    "gn:timezone":"Asia/Seoul",
    "iso:country":"KR",
    "name:und_x_variant":[
        "\uc774\ud3c9\ub3d9",
        "Ip\u2019y\u014fng-dong"
    ],
    "wof:name":"Ip'yong-dong",
    "wof:placetype":"locality"
},
  "geometry": {"coordinates":[127.5321,36.2977],"type":"Point"}
}