{
  "type": "Feature",
  "properties": {
    "gn:admin1_code":"6.0",
    "gn:asciiname":"Anmasan-gol",
    "gn:country_code":"KR",
    "gn:dem":285,
    "gn:feature_class":"P",
    "gn:feature_code":"PPL",
    "gn:name":"Anmasan-gol",
    "gn:population":0,
    "gn:timezone":"Asia/Seoul",
    "iso:country":"KR",
    "name:und_x_variant":[
        "\uc548\ub9c8\uc0b0\uace8",
        "Anmasan-gol"
    ],
    "wof:name":"Anmasan-gol",
    "wof:placetype":"locality"
},
  "geometry": {"coordinates":[127.68333,38.20333],"type":"Point"}
}