{
  "type": "Feature",
  "properties": {
    "gn:admin1_code":"11.0",
    "gn:asciiname":"Chamsilsam-dong",
    "gn:country_code":"KR",
    "gn:dem":21,
    "gn:feature_class":"P",
    "gn:feature_code":"PPL",
    "gn:name":"Chamsilsam-dong",
    "gn:population":0,
    "gn:timezone":"Asia/Seoul",
    "iso:country":"KR",
    "name:und_x_variant":[
        "\uc7a0\uc2e43\ub3d9",
        "Chamsilsam-dong"
    ],
    "wof:name":"Chamsilsam-dong",
    "wof:placetype":"locality"
},
  "geometry": {"coordinates":[127.09473,37.50982],"type":"Point"}
}