{
  "type": "Feature",
  "properties": {
    "gn:admin1_code":"16.0",
    "gn:asciiname":"Haengjeong",
    "gn:country_code":"KR",
    "gn:dem":48,
    "gn:feature_class":"P",
    "gn:feature_code":"PPL",
    "gn:name":"Haengjeong",
    "gn:population":0,
    "gn:timezone":"Asia/Seoul",
    "iso:country":"KR",
    "name:kor_x_preferred":[
        "\ud589\uc815"
    ],
    "wof:name":"Haengjeong",
    "wof:placetype":"locality"
},
  "geometry": {"coordinates":[126.8222,35.00398],"type":"Point"}
}