{
  "type": "Feature",
  "properties": {
    "gn:admin1_code":"14.0",
    "gn:asciiname":"Hyol-tong",
    "gn:country_code":"KR",
    "gn:dem":213,
    "gn:feature_class":"P",
    "gn:feature_code":"PPL",
    "gn:name":"Hy\u014fl-tong",
    "gn:population":0,
    "gn:timezone":"Asia/Seoul",
    "iso:country":"KR",
    "name:und_x_variant":[
        "\ud608\ub3d9",
        "Hy\u014fl-tong"
    ],
    "wof:name":"Hyol-tong",
    "wof:placetype":"locality"
},
  "geometry": {"coordinates":[128.84309999999999,36.2766],"type":"Point"}
}