{
  "type": "Feature",
  "properties": {
    "gn:admin1_code":"20.0",
    "gn:asciiname":"Hansan",
    "gn:country_code":"KR",
    "gn:dem":208,
    "gn:feature_class":"P",
    "gn:feature_code":"PPL",
    "gn:name":"Hansan",
    "gn:population":0,
    "gn:timezone":"Asia/Seoul",
    "iso:country":"KR",
    "name:ceb_x_preferred":[
        "Hansan"
    ],
    "name:swe_x_preferred":[
        "Hansan"
    ],
    "name:und_x_variant":[
        "\ud55c\uc0b0"
    ],
    "wof:name":"Hansan",
    "wof:placetype":"locality"
},
  "geometry": {"coordinates":[127.93805,35.64116],"type":"Point"}
}