{
  "type": "Feature",
  "properties": {
    "gn:admin1_code":"6.0",
    "gn:asciiname":"Song-gol",
    "gn:country_code":"KR",
    "gn:dem":316,
    "gn:feature_class":"P",
    "gn:feature_code":"PPL",
    "gn:name":"Song-gol",
    "gn:population":0,
    "gn:timezone":"Asia/Seoul",
    "iso:country":"KR",
    "name:kor_x_preferred":[
        "\uc1a1\uace8"
    ],
    "wof:name":"Song-gol",
    "wof:placetype":"locality"
},
  "geometry": {"coordinates":[128.26669999999999,37.3023],"type":"Point"}
}