{
  "type": "Feature",
  "properties": {
    "gn:admin1_code":"16.0",
    "gn:asciiname":"Yongdu",
    "gn:country_code":"KR",
    "gn:dem":19,
    "gn:feature_class":"P",
    "gn:feature_code":"PPL",
    "gn:name":"Yongdu",
    "gn:population":0,
    "gn:timezone":"Asia/Seoul",
    "iso:country":"KR",
    "name:kor_x_preferred":[
        "\uc6a9\ub450"
    ],
    "wof:name":"Yongdu",
    "wof:placetype":"locality"
},
  "geometry": {"coordinates":[126.68416999999999,35.0117],"type":"Point"}
}