{
  "type": "Feature",
  "properties": {
    "gn:admin1_code":"14.0",
    "gn:asciiname":"Puin",
    "gn:country_code":"KR",
    "gn:dem":240,
    "gn:feature_class":"P",
    "gn:feature_code":"PPL",
    "gn:name":"Puin",
    "gn:population":0,
    "gn:timezone":"Asia/Seoul",
    "iso:country":"KR",
    "name:und_x_variant":[
        "\ubd80\uc778",
        "Puin"
    ],
    "wof:name":"Puin",
    "wof:placetype":"locality"
},
  "geometry": {"coordinates":[128.3005,36.0109],"type":"Point"}
}