{
  "type": "Feature",
  "properties": {
    "gn:admin1_code":"14.0",
    "gn:asciiname":"Kujang-dong",
    "gn:country_code":"KR",
    "gn:dem":41,
    "gn:feature_class":"P",
    "gn:feature_code":"PPL",
    "gn:name":"Kujang-dong",
    "gn:population":0,
    "gn:timezone":"Asia/Seoul",
    "iso:country":"KR",
    "name:und_x_variant":[
        "\uad6c\uc7a5\ub3d9",
        "Kujang-gol"
    ],
    "wof:name":"Kujang-dong",
    "wof:placetype":"locality"
},
  "geometry": {"coordinates":[129.37721999999999,37.07778],"type":"Point"}
}