{
  "type": "Feature",
  "properties": {
    "gn:admin1_code":"5.0",
    "gn:asciiname":"Darangmal",
    "gn:country_code":"KR",
    "gn:dem":51,
    "gn:feature_class":"P",
    "gn:feature_code":"PPL",
    "gn:name":"Darangmal",
    "gn:population":0,
    "gn:timezone":"Asia/Seoul",
    "iso:country":"KR",
    "name:kor_x_preferred":[
        "\ub2e4\ub77d\ub9d0"
    ],
    "wof:name":"Darangmal",
    "wof:placetype":"locality"
},
  "geometry": {"coordinates":[127.51973999999998,36.7381],"type":"Point"}
}