{
  "type": "Feature",
  "properties": {
    "gn:admin1_code":"13.0",
    "gn:asciiname":"Soeteo",
    "gn:country_code":"KR",
    "gn:dem":69,
    "gn:feature_class":"P",
    "gn:feature_code":"PPL",
    "gn:name":"Soeteo",
    "gn:population":0,
    "gn:timezone":"Asia/Seoul",
    "iso:country":"KR",
    "name:kor_x_preferred":[
        "\uc1e0\ud130"
    ],
    "name:und_x_variant":[
        "\ube44\ub7ec\ud130",
        "Pir\u014ft\u2019\u014f",
        "Soeteo"
    ],
    "wof:name":"Soeteo",
    "wof:placetype":"locality"
},
  "geometry": {"coordinates":[127.53542,37.75691],"type":"Point"}
}