{
  "type": "Feature",
  "properties": {
    "gn:admin1_code":"13.0",
    "gn:asciiname":"P'yokchanggol",
    "gn:country_code":"KR",
    "gn:dem":12,
    "gn:feature_class":"P",
    "gn:feature_code":"PPL",
    "gn:name":"P\u2019y\u014fkchanggol",
    "gn:population":0,
    "gn:timezone":"Asia/Seoul",
    "iso:country":"KR",
    "name:kor_x_preferred":[
        "\ubcbd\uc7a5\uace8"
    ],
    "name:kor_x_variant":[
        "P\u2019y\u014fkchanggol"
    ],
    "wof:name":"P'yokchanggol",
    "wof:placetype":"locality"
},
  "geometry": {"coordinates":[126.78528,37.0875],"type":"Point"}
}