{
  "type": "Feature",
  "properties": {
    "gn:admin1_code":"13.0",
    "gn:asciiname":"Jeonnamu-gol",
    "gn:country_code":"KR",
    "gn:dem":81,
    "gn:feature_class":"P",
    "gn:feature_code":"PPL",
    "gn:name":"Jeonnamu-gol",
    "gn:population":0,
    "gn:timezone":"Asia/Seoul",
    "iso:country":"KR",
    "name:und_x_variant":[
        "\uc804\ub098\ubb34\uace8",
        "Jeonnamu-gol",
        "Ch\u014fnnamu-gol"
    ],
    "wof:name":"Jeonnamu-gol",
    "wof:placetype":"locality"
},
  "geometry": {"coordinates":[127.12472,37.15639],"type":"Point"}
}