{
  "type": "Feature",
  "properties": {
    "gn:admin1_code":"5.0",
    "gn:asciiname":"Solgaesil",
    "gn:country_code":"KR",
    "gn:dem":434,
    "gn:feature_class":"P",
    "gn:feature_code":"PPL",
    "gn:name":"Solgaesil",
    "gn:population":0,
    "gn:timezone":"Asia/Seoul",
    "iso:country":"KR",
    "name:kor_x_preferred":[
        "\uc194\uac1c\uc2e4"
    ],
    "wof:name":"Solgaesil",
    "wof:placetype":"locality"
},
  "geometry": {"coordinates":[128.63218999999998,37.05706],"type":"Point"}
}