{
  "type": "Feature",
  "properties": {
    "gn:admin1_code":"11.0",
    "gn:asciiname":"Hwarang",
    "gn:country_code":"KR",
    "gn:dem":146,
    "gn:feature_class":"P",
    "gn:feature_code":"PPL",
    "gn:name":"Hwarang",
    "gn:population":0,
    "gn:timezone":"Asia/Seoul",
    "iso:country":"KR",
    "name:kor_x_preferred":[
        "\ud654\ub791"
    ],
    "wof:name":"Hwarang",
    "wof:placetype":"locality"
},
  "geometry": {"coordinates":[126.46448999999998,33.461],"type":"Point"}
}