{
  "type": "Feature",
  "properties": {
    "gn:admin1_code":"11.0",
    "gn:asciiname":"Hwarang",
    "gn:country_code":"KR",
    "gn:dem":146,
    "gn:feature_class":"P",
    "gn:feature_code":"PPL",
    "gn:name":"Hwarang",
    "gn:population":0,
    "gn:timezone":"Asia/Seoul",
    "iso:country":"KR",
    "name:ara_x_preferred":[
        "\u0647\u0648\u0627\u0631\u0627\u0646\u063a"
    ],
    "name:ast_x_preferred":[
        "Hwarang"
    ],
    "name:deu_x_preferred":[
        "Hwarang"
    ],
    "name:fin_x_preferred":[
        "Hwarangdo"
    ],
    "name:heb_x_preferred":[
        "\u05d4\u05d5\u05d5\u05d0\u05e8\u05e0\u05d2"
    ],
    "name:hun_x_preferred":[
        "Hvarang"
    ],
    "name:ind_x_preferred":[
        "Hwarang"
    ],
    "name:ita_x_preferred":[
        "Hwarang"
    ],
    "name:jav_x_preferred":[
        "Hwarang"
    ],
    "name:kat_x_preferred":[
        "\u10f0\u10d5\u10d0\u10e0\u10d0\u10dc\u10d8"
    ],
    "name:kaz_x_preferred":[
        "\u04ba\u0443\u0430\u0440\u0430\u04a3"
    ],
    "name:kor_x_preferred":[
        "\ud654\ub791"
    ],
    "name:nld_x_preferred":[
        "Hwarang"
    ],
    "name:pol_x_preferred":[
        "Hwarang"
    ],
    "name:por_x_preferred":[
        "Hwarang"
    ],
    "name:rus_x_preferred":[
        "\u0425\u0432\u0430\u0440\u0430\u043d"
    ],
    "name:spa_x_preferred":[
        "Hwarang"
    ],
    "name:tur_x_preferred":[
        "Hwarang"
    ],
    "name:ukr_x_preferred":[
        "\u0425\u0432\u0430\u0440\u0430\u043d"
    ],
    "name:vie_x_preferred":[
        "Hoa lang"
    ],
    "wof:name":"Hwarang",
    "wof:placetype":"locality"
},
  "geometry": {"coordinates":[126.46448999999998,33.461],"type":"Point"}
}