{
  "type": "Feature",
  "properties": {
    "gn:admin1_code":"14.0",
    "gn:asciiname":"Munbanggol",
    "gn:country_code":"KR",
    "gn:dem":20,
    "gn:feature_class":"P",
    "gn:feature_code":"PPL",
    "gn:name":"Munbanggol",
    "gn:population":0,
    "gn:timezone":"Asia/Seoul",
    "iso:country":"KR",
    "name:kor_x_preferred":[
        "\ubb38\ubc29\uace8"
    ],
    "wof:name":"Munbanggol",
    "wof:placetype":"locality"
},
  "geometry": {"coordinates":[129.36596,36.37426],"type":"Point"}
}