{
  "type": "Feature",
  "properties": {
    "gn:admin1_code":"1.0",
    "gn:admin2_code":"Pukcheju-gun",
    "gn:asciiname":"Dumandong",
    "gn:country_code":"KR",
    "gn:dem":39,
    "gn:feature_class":"P",
    "gn:feature_code":"PPL",
    "gn:name":"Dumandong",
    "gn:population":0,
    "gn:timezone":"Asia/Seoul",
    "iso:country":"KR",
    "name:kor_x_preferred":[
        "\ub450\ub9cc\ub3d9"
    ],
    "name:und_x_variant":[
        "Tuman-dong"
    ],
    "wof:name":"Dumandong",
    "wof:placetype":"locality"
},
  "geometry": {"coordinates":[126.19833,33.31179],"type":"Point"}
}