{
  "type": "Feature",
  "properties": {
    "iso:country":"KR",
    "name:kor_x_preferred":[
        "\uc7a5\uae30\ub3d9"
    ],
    "name:und_x_variant":[
        "Changgi-dong"
    ],
    "qs:gn_adm0_cc":"KR",
    "qs:gn_fcode":"PPL",
    "qs:gn_local":1835329,
    "qs:gn_namadm1":"14",
    "qs:gn_name":"Yanggi-dong",
    "qs:local_max":1440,
    "qs:local_sum":5303,
    "qs:localhoods":33,
    "qs:name":"\uc7a5\uae30\ub3d9",
    "qs:name_adm0":"\ud55c\uad6d",
    "qs:name_adm1":"\ub300\uad6c",
    "qs:name_adm2":"\ub2ec\uc11c\uad6c",
    "qs:name_lau":"\uc7a5\uae30\ub3d9",
    "qs:name_local":"\ub300\uad6c",
    "qs:photo_max":3,
    "qs:photo_sum":8,
    "qs:placetype":"Suburb",
    "qs:quad_count":3,
    "qs:woe_adm0":23424868,
    "qs:woe_adm1":2345971,
    "qs:woe_adm2":28289140,
    "qs:woe_lau":28806278,
    "qs:woe_local":1132466,
    "qs:woe_ver":"7.10.0",
    "wof:lang":[
        "kor"
    ],
    "wof:name":"\uc7a5\uae30\ub3d9",
    "wof:placetype":"neighbourhood"
},
  "geometry": {"coordinates":[128.51944,35.835071],"type":"Point"}
}