{
  "type": "Feature",
  "properties": {
    "gn:admin1_code":"17.0",
    "gn:asciiname":"Wihang",
    "gn:country_code":"KR",
    "gn:dem":4,
    "gn:feature_class":"P",
    "gn:feature_code":"PPL",
    "gn:name":"Wihang",
    "gn:population":0,
    "gn:timezone":"Asia/Seoul",
    "iso:country":"KR",
    "name:und_x_variant":[
        "Uigong",
        "\u016cihang"
    ],
    "wof:name":"Wihang",
    "wof:placetype":"locality"
},
  "geometry": {"coordinates":[126.56667,36.28333],"type":"Point"}
}