{
  "type": "Feature",
  "properties": {
    "gn:admin1_code":"0.0",
    "gn:asciiname":"Soyu",
    "gn:cc2":"KR",
    "gn:country_code":"KR",
    "gn:dem":-9999,
    "gn:feature_class":"P",
    "gn:feature_code":"PPL",
    "gn:name":"Soyu",
    "gn:population":0,
    "gn:timezone":"Asia/Seoul",
    "iso:country":"KR",
    "name:und_x_variant":[
        "Chag\u016dnb\u014fd\u016dlgae",
        "Soryup\u2019o",
        "Soyup\u2019o",
        "Soyu"
    ],
    "wof:name":"Soyu",
    "wof:placetype":"locality"
},
  "geometry": {"coordinates":[127.76667,34.53333],"type":"Point"}
}