{
  "type": "Feature",
  "properties": {
    "gn:admin1_code":"14.0",
    "gn:asciiname":"Doradong",
    "gn:country_code":"KR",
    "gn:dem":77,
    "gn:feature_class":"P",
    "gn:feature_code":"PPL",
    "gn:name":"Doradong",
    "gn:population":0,
    "gn:timezone":"Asia/Seoul",
    "iso:country":"KR",
    "name:kor_x_preferred":[
        "\ub3c4\ub77c\ub3d9"
    ],
    "wof:name":"Doradong",
    "wof:placetype":"locality"
},
  "geometry": {"coordinates":[129.40152,35.91465],"type":"Point"}
}