{
  "type": "Feature",
  "properties": {
    "gn:admin1_code":"16.0",
    "gn:asciiname":"Jeongjinae",
    "gn:country_code":"KR",
    "gn:dem":142,
    "gn:feature_class":"P",
    "gn:feature_code":"PPL",
    "gn:name":"Jeongjinae",
    "gn:population":0,
    "gn:timezone":"Asia/Seoul",
    "iso:country":"KR",
    "name:kor_x_preferred":[
        "\uc815\uc790"
    ],
    "name:kor_x_variant":[
        "Ch\u014fngja",
        "\uc815\uc9c0\ub0b4"
    ],
    "name:und_x_variant":[
        "Ch\u014fngja-ri",
        "Ch\u014fngjinae",
        "Jeongjinae"
    ],
    "wof:name":"Jeongjinae",
    "wof:placetype":"locality"
},
  "geometry": {"coordinates":[127.09251999999999,34.79379],"type":"Point"}
}