{
  "type": "Feature",
  "properties": {
    "gn:admin1_code":"6.0",
    "gn:asciiname":"Podulmigi",
    "gn:country_code":"KR",
    "gn:dem":336,
    "gn:feature_class":"P",
    "gn:feature_code":"PPL",
    "gn:name":"P\u014fd\u016dlmigi",
    "gn:population":0,
    "gn:timezone":"Asia/Seoul",
    "iso:country":"KR",
    "name:kor_x_preferred":[
        "\ubc84\ub4e4\ubbf8\uae30"
    ],
    "name:kor_x_variant":[
        "P\u014fd\u016dlmigi"
    ],
    "wof:name":"Podulmigi",
    "wof:placetype":"locality"
},
  "geometry": {"coordinates":[128.20750000000001,37.7084],"type":"Point"}
}