{
  "type": "Feature",
  "properties": {
    "gn:admin1_code":"3.0",
    "gn:asciiname":"Kojong",
    "gn:country_code":"KR",
    "gn:dem":142,
    "gn:feature_class":"P",
    "gn:feature_code":"PPL",
    "gn:name":"Koj\u014fng",
    "gn:population":0,
    "gn:timezone":"Asia/Seoul",
    "iso:country":"KR",
    "name:und_x_variant":[
        "\uace0\uc815",
        "Koj\u014fng",
        "Gojeong"
    ],
    "wof:name":"Kojong",
    "wof:placetype":"locality"
},
  "geometry": {"coordinates":[127.36694,35.52853],"type":"Point"}
}