{
  "type": "Feature",
  "properties": {
    "gn:admin1_code":"6.0",
    "gn:asciiname":"Malgori",
    "gn:country_code":"KR",
    "gn:dem":238,
    "gn:feature_class":"P",
    "gn:feature_code":"PPL",
    "gn:name":"Malg\u014fri",
    "gn:population":0,
    "gn:timezone":"Asia/Seoul",
    "iso:country":"KR",
    "name:kor_x_preferred":[
        "\ub9d0\uac70\ub9ac"
    ],
    "name:und_x_variant":[
        "Malg\u014fri"
    ],
    "wof:name":"Malgori",
    "wof:placetype":"locality"
},
  "geometry": {"coordinates":[128.19611,38.13778],"type":"Point"}
}