{
  "type": "Feature",
  "properties": {
    "gn:admin1_code":"17.0",
    "gn:asciiname":"Hanyanggol",
    "gn:country_code":"KR",
    "gn:dem":46,
    "gn:feature_class":"P",
    "gn:feature_code":"PPL",
    "gn:name":"Hanyanggol",
    "gn:population":0,
    "gn:timezone":"Asia/Seoul",
    "iso:country":"KR",
    "name:und_x_variant":[
        "\ud55c\uc591\uace8",
        "Hanyanggol"
    ],
    "wof:name":"Hanyanggol",
    "wof:placetype":"locality"
},
  "geometry": {"coordinates":[127.25331,36.45414],"type":"Point"}
}