{
  "type": "Feature",
  "properties": {
    "gn:admin1_code":"5.0",
    "gn:asciiname":"Garugae",
    "gn:country_code":"KR",
    "gn:dem":97,
    "gn:feature_class":"P",
    "gn:feature_code":"PPL",
    "gn:name":"Garugae",
    "gn:population":0,
    "gn:timezone":"Asia/Seoul",
    "iso:country":"KR",
    "name:kor_x_preferred":[
        "\uac00\ub8e8\uac1c"
    ],
    "wof:name":"Garugae",
    "wof:placetype":"locality"
},
  "geometry": {"coordinates":[127.40012,36.50126],"type":"Point"}
}