{
  "type": "Feature",
  "properties": {
    "gn:admin1_code":"6.0",
    "gn:asciiname":"Jeongson",
    "gn:country_code":"KR",
    "gn:dem":30,
    "gn:feature_class":"P",
    "gn:feature_code":"PPL",
    "gn:name":"Jeongson",
    "gn:population":0,
    "gn:timezone":"Asia/Seoul",
    "iso:country":"KR",
    "name:kor_x_preferred":[
        "\uc815\uc190"
    ],
    "wof:name":"Jeongson",
    "wof:placetype":"locality"
},
  "geometry": {"coordinates":[128.61705000000001,38.10202],"type":"Point"}
}