{
  "type": "Feature",
  "properties": {
    "gn:admin1_code":"17.0",
    "gn:asciiname":"Jigyeongteo",
    "gn:country_code":"KR",
    "gn:dem":23,
    "gn:feature_class":"P",
    "gn:feature_code":"PPL",
    "gn:name":"Jigyeongteo",
    "gn:population":0,
    "gn:timezone":"Asia/Seoul",
    "iso:country":"KR",
    "name:kor_x_preferred":[
        "\uc9c0\uacbd\ud130"
    ],
    "name:und_x_variant":[
        "\uc9c0\uacbd\ucc98",
        "Chigy\u014fngch\u2019\u014f",
        "Jigyeongteo"
    ],
    "wof:name":"Jigyeongteo",
    "wof:placetype":"locality"
},
  "geometry": {"coordinates":[127.14952,36.30117],"type":"Point"}
}