{
  "type": "Feature",
  "properties": {
    "gn:admin1_code":"13.0",
    "gn:asciiname":"Jeongbong",
    "gn:country_code":"KR",
    "gn:dem":82,
    "gn:feature_class":"P",
    "gn:feature_code":"PPL",
    "gn:name":"Jeongbong",
    "gn:population":0,
    "gn:timezone":"Asia/Seoul",
    "iso:country":"KR",
    "name:kor_x_preferred":[
        "\uc815\ubd09"
    ],
    "name:kor_x_variant":[
        "Ch\u014fngbong"
    ],
    "wof:name":"Jeongbong",
    "wof:placetype":"locality"
},
  "geometry": {"coordinates":[127.56180999999999,37.20205],"type":"Point"}
}