{
  "type": "Feature",
  "properties": {
    "gn:admin1_code":"6.0",
    "gn:asciiname":"Ch'ang-mal",
    "gn:country_code":"KR",
    "gn:dem":433,
    "gn:feature_class":"P",
    "gn:feature_code":"PPL",
    "gn:name":"Ch\u2019ang-mal",
    "gn:population":0,
    "gn:timezone":"Asia/Seoul",
    "iso:country":"KR",
    "name:kor_x_preferred":[
        "\ucc3d\ub9d0"
    ],
    "name:kor_x_variant":[
        "Ch\u2019ang-mal"
    ],
    "wof:name":"Ch'ang-mal",
    "wof:placetype":"locality"
},
  "geometry": {"coordinates":[128.167,37.4279],"type":"Point"}
}