{
  "type": "Feature",
  "properties": {
    "gn:admin1_code":"13.0",
    "gn:admin2_code":"P'aju-si",
    "gn:asciiname":"Jajipo",
    "gn:country_code":"KR",
    "gn:dem":37,
    "gn:feature_class":"P",
    "gn:feature_code":"PPL",
    "gn:name":"Jajipo",
    "gn:population":0,
    "gn:timezone":"Asia/Seoul",
    "iso:country":"KR",
    "name:kor_x_preferred":[
        "\uc790\uc9c0\ud3ec"
    ],
    "name:und_x_variant":[
        "Chajip\u2019o"
    ],
    "wof:name":"Jajipo",
    "wof:placetype":"locality"
},
  "geometry": {"coordinates":[126.85498,37.98968],"type":"Point"}
}