{
  "type": "Feature",
  "properties": {
    "gn:admin1_code":"20.0",
    "gn:asciiname":"Saet'o",
    "gn:country_code":"KR",
    "gn:dem":221,
    "gn:feature_class":"P",
    "gn:feature_code":"PPL",
    "gn:name":"Saet\u2019\u014f",
    "gn:population":0,
    "gn:timezone":"Asia/Seoul",
    "iso:country":"KR",
    "name:und_x_variant":[
        "\uc0c8\ud130",
        "Saet\u2019\u014f"
    ],
    "wof:name":"Saet'o",
    "wof:placetype":"locality"
},
  "geometry": {"coordinates":[128.06874999999999,35.59751],"type":"Point"}
}