{
  "type": "Feature",
  "properties": {
    "gn:admin1_code":"13.0",
    "gn:asciiname":"Mugeondong",
    "gn:country_code":"KR",
    "gn:dem":90,
    "gn:feature_class":"P",
    "gn:feature_code":"PPL",
    "gn:name":"Mugeondong",
    "gn:population":0,
    "gn:timezone":"Asia/Seoul",
    "iso:country":"KR",
    "name:kor_x_preferred":[
        "\ubb34\uac74\ub3d9"
    ],
    "wof:name":"Mugeondong",
    "wof:placetype":"locality"
},
  "geometry": {"coordinates":[126.92108,37.91148],"type":"Point"}
}