{
  "type": "Feature",
  "properties": {
    "gn:admin1_code":"20.0",
    "gn:asciiname":"Tokkong-ni",
    "gn:country_code":"KR",
    "gn:dem":41,
    "gn:feature_class":"P",
    "gn:feature_code":"PPL",
    "gn:name":"T\u014fkkong-ni",
    "gn:population":0,
    "gn:timezone":"Asia/Seoul",
    "iso:country":"KR",
    "name:und_x_variant":[
        "\ub355\uace1\ub9ac",
        "T\u014fkkong-ni"
    ],
    "wof:name":"Tokkong-ni",
    "wof:placetype":"locality"
},
  "geometry": {"coordinates":[128.71008,35.51207],"type":"Point"}
}