{
  "type": "Feature",
  "properties": {
    "gn:admin1_code":"14.0",
    "gn:asciiname":"Dwitgol",
    "gn:country_code":"KR",
    "gn:dem":86,
    "gn:feature_class":"P",
    "gn:feature_code":"PPL",
    "gn:name":"Dwitgol",
    "gn:population":0,
    "gn:timezone":"Asia/Seoul",
    "iso:country":"KR",
    "name:kor_x_preferred":[
        "\ub4b7\uace8"
    ],
    "wof:name":"Dwitgol",
    "wof:placetype":"locality"
},
  "geometry": {"coordinates":[128.48255,36.53122000000001],"type":"Point"}
}