{
  "type": "Feature",
  "properties": {
    "gn:admin1_code":"13.0",
    "gn:asciiname":"An-gol",
    "gn:country_code":"KR",
    "gn:dem":46,
    "gn:feature_class":"P",
    "gn:feature_code":"PPL",
    "gn:name":"An-gol",
    "gn:population":0,
    "gn:timezone":"Asia/Seoul",
    "iso:country":"KR",
    "name:kor_x_preferred":[
        "\uc548\uace8"
    ],
    "name:und_x_variant":[
        "\uc548\uace8",
        "An-gol"
    ],
    "wof:name":"An-gol",
    "wof:placetype":"locality"
},
  "geometry": {"coordinates":[127.30222000000001,37.49639000000001],"type":"Point"}
}