{
  "type": "Feature",
  "properties": {
    "gn:admin1_code":"6.0",
    "gn:asciiname":"Saejae",
    "gn:country_code":"KR",
    "gn:dem":261,
    "gn:feature_class":"P",
    "gn:feature_code":"PPL",
    "gn:name":"Saejae",
    "gn:population":0,
    "gn:timezone":"Asia/Seoul",
    "iso:country":"KR",
    "name:kor_x_preferred":[
        "\uc0c8\uc7ac"
    ],
    "wof:name":"Saejae",
    "wof:placetype":"locality"
},
  "geometry": {"coordinates":[128.20523,38.15764],"type":"Point"}
}