{
  "type": "Feature",
  "properties": {
    "gn:admin1_code":"6.0",
    "gn:asciiname":"Udu-dong",
    "gn:country_code":"KR",
    "gn:dem":85,
    "gn:feature_class":"P",
    "gn:feature_code":"PPL",
    "gn:name":"Udu-dong",
    "gn:population":0,
    "gn:timezone":"Asia/Seoul",
    "iso:country":"KR",
    "name:und_x_variant":[
        "Udu-il-tong",
        "Udu",
        "Udu-ri",
        "\uc6b0\ub450\ub3d9",
        "Udu-dong"
    ],
    "wof:name":"Udu-dong",
    "wof:placetype":"locality"
},
  "geometry": {"coordinates":[127.74250000000001,37.9096],"type":"Point"}
}