{
  "type": "Feature",
  "properties": {
    "gn:admin1_code":"6.0",
    "gn:asciiname":"Wittokchol-li",
    "gn:country_code":"KR",
    "gn:dem":325,
    "gn:feature_class":"P",
    "gn:feature_code":"PPL",
    "gn:name":"Witt\u014fkch\u014fl-li",
    "gn:population":0,
    "gn:timezone":"Asia/Seoul",
    "iso:country":"KR",
    "name:kor_x_preferred":[
        "\uc717\ub355\uc804\ub9ac"
    ],
    "name:kor_x_variant":[
        "Witt\u014fkch\u014fl-li"
    ],
    "wof:name":"Wittokchol-li",
    "wof:placetype":"locality"
},
  "geometry": {"coordinates":[128.39019999999999,37.2545],"type":"Point"}
}