{
  "type": "Feature",
  "properties": {
    "gn:admin1_code":"17.0",
    "gn:asciiname":"Nonji-ri",
    "gn:country_code":"KR",
    "gn:dem":25,
    "gn:feature_class":"P",
    "gn:feature_code":"PPL",
    "gn:name":"Nonji-ri",
    "gn:population":0,
    "gn:timezone":"Asia/Seoul",
    "iso:country":"KR",
    "name:und_x_variant":[
        "Nont\u2019i-ri",
        "Nonji-ri",
        "Nonch\u2019i",
        "Nonch\u2019i-ri"
    ],
    "wof:name":"Nonji-ri",
    "wof:placetype":"locality"
},
  "geometry": {"coordinates":[126.80694,36.24278],"type":"Point"}
}