{
  "type": "Feature",
  "properties": {
    "gn:admin1_code":"21.0",
    "gn:asciiname":"Ongok",
    "gn:country_code":"KR",
    "gn:dem":11,
    "gn:feature_class":"P",
    "gn:feature_code":"PPL",
    "gn:name":"Ongok",
    "gn:population":0,
    "gn:timezone":"Asia/Seoul",
    "iso:country":"KR",
    "name:kor_x_preferred":[
        "\uc628\uace1"
    ],
    "wof:name":"Ongok",
    "wof:placetype":"locality"
},
  "geometry": {"coordinates":[129.28851,35.34433],"type":"Point"}
}