{
  "type": "Feature",
  "properties": {
    "gn:admin1_code":"20.0",
    "gn:asciiname":"Deokgye",
    "gn:country_code":"KR",
    "gn:dem":126,
    "gn:feature_class":"P",
    "gn:feature_code":"PPL",
    "gn:name":"Deokgye",
    "gn:population":0,
    "gn:timezone":"Asia/Seoul",
    "iso:country":"KR",
    "name:kor_x_preferred":[
        "\ub355\uacc4"
    ],
    "wof:name":"Deokgye",
    "wof:placetype":"locality"
},
  "geometry": {"coordinates":[129.15889000000001,35.38111],"type":"Point"}
}