{
  "type": "Feature",
  "properties": {
    "gn:admin1_code":"5.0",
    "gn:asciiname":"Pinae",
    "gn:country_code":"KR",
    "gn:dem":77,
    "gn:feature_class":"P",
    "gn:feature_code":"PPL",
    "gn:name":"Pinae",
    "gn:population":0,
    "gn:timezone":"Asia/Seoul",
    "iso:country":"KR",
    "name:kor_x_preferred":[
        "\ube44\ub0b4"
    ],
    "wof:name":"Pinae",
    "wof:placetype":"locality"
},
  "geometry": {"coordinates":[127.8062,37.1094],"type":"Point"}
}