{
  "type": "Feature",
  "properties": {
    "gn:admin1_code":"13.0",
    "gn:asciiname":"Soyugok",
    "gn:country_code":"KR",
    "gn:dem":220,
    "gn:feature_class":"P",
    "gn:feature_code":"PPL",
    "gn:name":"Soyugok",
    "gn:population":0,
    "gn:timezone":"Asia/Seoul",
    "iso:country":"KR",
    "name:kor_x_preferred":[
        "\uc18c\uc720\uace1"
    ],
    "name:und_x_variant":[
        "\uc18c\uc720\uace1",
        "Soyugok"
    ],
    "wof:name":"Soyugok",
    "wof:placetype":"locality"
},
  "geometry": {"coordinates":[127.4494,37.6182],"type":"Point"}
}