{
  "type": "Feature",
  "properties": {
    "gn:admin1_code":"14.0",
    "gn:asciiname":"Banggol",
    "gn:country_code":"KR",
    "gn:dem":195,
    "gn:feature_class":"P",
    "gn:feature_code":"PPL",
    "gn:name":"Banggol",
    "gn:population":0,
    "gn:timezone":"Asia/Seoul",
    "iso:country":"KR",
    "name:kor_x_preferred":[
        "\ubc29\uace8"
    ],
    "wof:name":"Banggol",
    "wof:placetype":"locality"
},
  "geometry": {"coordinates":[128.65142,36.61091],"type":"Point"}
}