{
  "type": "Feature",
  "properties": {
    "gn:admin1_code":"20.0",
    "gn:asciiname":"Kumch'on",
    "gn:country_code":"KR",
    "gn:dem":42,
    "gn:feature_class":"P",
    "gn:feature_code":"PPL",
    "gn:name":"K\u016dmch\u2019\u014fn",
    "gn:population":0,
    "gn:timezone":"Asia/Seoul",
    "iso:country":"KR",
    "name:und_x_variant":[
        "\uae08\ucc9c",
        "K\u016dmch\u2019\u014fn"
    ],
    "wof:name":"Kumch'on",
    "wof:placetype":"locality"
},
  "geometry": {"coordinates":[128.43226000000001,35.25395],"type":"Point"}
}