{
  "type": "Feature",
  "properties": {
    "gn:admin1_code":"13.0",
    "gn:asciiname":"Tongmak",
    "gn:country_code":"KR",
    "gn:dem":94,
    "gn:feature_class":"P",
    "gn:feature_code":"PPL",
    "gn:name":"Tongmak",
    "gn:population":0,
    "gn:timezone":"Asia/Seoul",
    "iso:country":"KR",
    "name:und_x_variant":[
        "\ub3d9\ub9c9",
        "Dongmak",
        "Tongmak"
    ],
    "wof:name":"Tongmak",
    "wof:placetype":"locality"
},
  "geometry": {"coordinates":[127.62721999999999,37.39028],"type":"Point"}
}