{
  "type": "Feature",
  "properties": {
    "gn:admin1_code":"6.0",
    "gn:asciiname":"Ipsit'o",
    "gn:country_code":"KR",
    "gn:dem":294,
    "gn:feature_class":"P",
    "gn:feature_code":"PPL",
    "gn:name":"Ipsit\u2019\u014f",
    "gn:population":0,
    "gn:timezone":"Asia/Seoul",
    "iso:country":"KR",
    "name:und_x_variant":[
        "\uc785\uc2dc\ud130",
        "Ipsit\u2019\u014f"
    ],
    "wof:name":"Ipsit'o",
    "wof:placetype":"locality"
},
  "geometry": {"coordinates":[129.1431,37.3873],"type":"Point"}
}