{
  "type": "Feature",
  "properties": {
    "gn:admin1_code":"14.0",
    "gn:asciiname":"Hai-dong",
    "gn:country_code":"KR",
    "gn:dem":83,
    "gn:feature_class":"P",
    "gn:feature_code":"PPL",
    "gn:name":"Hai-dong",
    "gn:population":0,
    "gn:timezone":"Asia/Seoul",
    "iso:country":"KR",
    "name:und_x_variant":[
        "\ud558\uc774\ub3d9",
        "Hai-dong"
    ],
    "wof:name":"Hai-dong",
    "wof:placetype":"locality"
},
  "geometry": {"coordinates":[129.15984,36.07911],"type":"Point"}
}