{
  "type": "Feature",
  "properties": {
    "gn:admin1_code":"12.0",
    "gn:asciiname":"Korant'ae",
    "gn:country_code":"KR",
    "gn:dem":13,
    "gn:feature_class":"P",
    "gn:feature_code":"PPL",
    "gn:name":"Korant\u2019ae",
    "gn:population":0,
    "gn:timezone":"Asia/Seoul",
    "iso:country":"KR",
    "name:kor_x_preferred":[
        "\uace0\ub780\ud0dc"
    ],
    "name:kor_x_variant":[
        "Korant\u2019ae"
    ],
    "wof:name":"Korant'ae",
    "wof:placetype":"locality"
},
  "geometry": {"coordinates":[126.74917000000001,37.60528],"type":"Point"}
}