{
  "type": "Feature",
  "properties": {
    "gn:admin1_code":"20.0",
    "gn:asciiname":"Onsu-gol",
    "gn:country_code":"KR",
    "gn:dem":60,
    "gn:feature_class":"P",
    "gn:feature_code":"PPL",
    "gn:name":"Onsu-gol",
    "gn:population":0,
    "gn:timezone":"Asia/Seoul",
    "iso:country":"KR",
    "name:und_x_variant":[
        "\uc628\uc218\uace8",
        "Onsu-ri",
        "Onsu-gol"
    ],
    "wof:name":"Onsu-gol",
    "wof:placetype":"locality"
},
  "geometry": {"coordinates":[128.43743999999998,35.1207],"type":"Point"}
}