{
  "type": "Feature",
  "properties": {
    "gn:admin1_code":"5.0",
    "gn:asciiname":"Kaemijae",
    "gn:country_code":"KR",
    "gn:dem":93,
    "gn:feature_class":"P",
    "gn:feature_code":"PPL",
    "gn:name":"Kaemijae",
    "gn:population":0,
    "gn:timezone":"Asia/Seoul",
    "iso:country":"KR",
    "name:und_x_variant":[
        "\uac1c\ubbf8\uc7ac",
        "Kaemijae"
    ],
    "wof:name":"Kaemijae",
    "wof:placetype":"locality"
},
  "geometry": {"coordinates":[127.61199999999999,36.31],"type":"Point"}
}