{
  "type": "Feature",
  "properties": {
    "gn:admin1_code":"6.0",
    "gn:asciiname":"Hwangjong-gol",
    "gn:country_code":"KR",
    "gn:dem":434,
    "gn:feature_class":"P",
    "gn:feature_code":"PPL",
    "gn:name":"Hwangj\u014fng-gol",
    "gn:population":0,
    "gn:timezone":"Asia/Seoul",
    "iso:country":"KR",
    "name:kor_x_preferred":[
        "\ud669\uc815\uace8"
    ],
    "name:kor_x_variant":[
        "Hwangj\u014fng-gol"
    ],
    "wof:name":"Hwangjong-gol",
    "wof:placetype":"locality"
},
  "geometry": {"coordinates":[128.19409999999999,37.6297],"type":"Point"}
}