{
  "type": "Feature",
  "properties": {
    "gn:admin1_code":"5.0",
    "gn:asciiname":"Kasal-li",
    "gn:cc2":"KR",
    "gn:country_code":"KR",
    "gn:dem":314,
    "gn:feature_class":"P",
    "gn:feature_code":"PPL",
    "gn:name":"Kasal-li",
    "gn:population":0,
    "gn:timezone":"Asia/Seoul",
    "iso:country":"KR",
    "name:und_x_variant":[
        "Kasan-ni",
        "Kasal-li"
    ],
    "wof:name":"Kasal-li",
    "wof:placetype":"locality"
},
  "geometry": {"coordinates":[128.30306000000002,36.89278],"type":"Point"}
}