{
  "type": "Feature",
  "properties": {
    "gn:admin1_code":"11.0",
    "gn:asciiname":"Namgajwa-dong",
    "gn:country_code":"KR",
    "gn:dem":26,
    "gn:feature_class":"P",
    "gn:feature_code":"PPL",
    "gn:name":"Namgajwa-dong",
    "gn:population":0,
    "gn:timezone":"Asia/Seoul",
    "iso:country":"KR",
    "name:und_x_variant":[
        "Nam-kajwa-dong",
        "Namkafwa",
        "Namgajwa-ri",
        "\ub0a8\uac00\uc88c\ub3d9",
        "Namgajwa-dong"
    ],
    "wof:name":"Namgajwa-dong",
    "wof:placetype":"locality"
},
  "geometry": {"coordinates":[126.9233,37.5765],"type":"Point"}
}