{
  "type": "Feature",
  "properties": {
    "gn:admin1_code":"14.0",
    "gn:asciiname":"Yul-li",
    "gn:country_code":"KR",
    "gn:dem":79,
    "gn:feature_class":"P",
    "gn:feature_code":"PPLL",
    "gn:name":"Yul-li",
    "gn:population":0,
    "gn:timezone":"Asia/Seoul",
    "iso:country":"KR",
    "name:und_x_variant":[
        "\uc728\ub9ac",
        "Yul-li"
    ],
    "wof:name":"Yul-li",
    "wof:placetype":"locality"
},
  "geometry": {"coordinates":[128.10415,36.35311],"type":"Point"}
}