{
  "type": "Feature",
  "properties": {
    "gn:admin1_code":"17.0",
    "gn:asciiname":"Pyongchang",
    "gn:country_code":"KR",
    "gn:dem":19,
    "gn:feature_class":"P",
    "gn:feature_code":"PPL",
    "gn:name":"Pyongchang",
    "gn:population":0,
    "gn:timezone":"Asia/Seoul",
    "iso:country":"KR",
    "name:und_x_variant":[
        "P\u2019y\u014fngch\u2019on"
    ],
    "wof:name":"Pyongchang",
    "wof:placetype":"locality"
},
  "geometry": {"coordinates":[126.58333,36.43333],"type":"Point"}
}