{
  "type": "Feature",
  "properties": {
    "gn:admin1_code":"17.0",
    "gn:asciiname":"Karugogae",
    "gn:country_code":"KR",
    "gn:dem":41,
    "gn:feature_class":"P",
    "gn:feature_code":"PPL",
    "gn:name":"Karugogae",
    "gn:population":0,
    "gn:timezone":"Asia/Seoul",
    "iso:country":"KR",
    "name:und_x_variant":[
        "\uac00\ub8e8\uace0\uac1c",
        "Karugogae"
    ],
    "wof:name":"Karugogae",
    "wof:placetype":"locality"
},
  "geometry": {"coordinates":[126.8377,36.2839],"type":"Point"}
}