{
  "type": "Feature",
  "properties": {
    "gn:admin1_code":"13.0",
    "gn:asciiname":"Maegok",
    "gn:country_code":"KR",
    "gn:dem":145,
    "gn:feature_class":"P",
    "gn:feature_code":"PPL",
    "gn:name":"Maegok",
    "gn:population":0,
    "gn:timezone":"Asia/Seoul",
    "iso:country":"KR",
    "name:kor_x_preferred":[
        "\ub9e4\uace1"
    ],
    "name:und_x_variant":[
        "\ub9e4\uace1",
        "Maegok"
    ],
    "wof:name":"Maegok",
    "wof:placetype":"locality"
},
  "geometry": {"coordinates":[127.40219999999999,37.606],"type":"Point"}
}