{
  "type": "Feature",
  "properties": {
    "gn:admin1_code":"13.0",
    "gn:asciiname":"Saenmal",
    "gn:country_code":"KR",
    "gn:dem":94,
    "gn:feature_class":"P",
    "gn:feature_code":"PPL",
    "gn:name":"Saenmal",
    "gn:population":0,
    "gn:timezone":"Asia/Seoul",
    "iso:country":"KR",
    "name:kor_x_preferred":[
        "\uc0db\ub9d0"
    ],
    "name:und_x_variant":[
        "\uc0db\ub9d0",
        "Saenmal"
    ],
    "wof:name":"Saenmal",
    "wof:placetype":"locality"
},
  "geometry": {"coordinates":[127.2642,37.6125],"type":"Point"}
}