{
  "type": "Feature",
  "properties": {
    "gn:admin1_code":"15.0",
    "gn:asciiname":"Geumgang",
    "gn:country_code":"KR",
    "gn:dem":42,
    "gn:feature_class":"P",
    "gn:feature_code":"PPL",
    "gn:name":"Geumgang",
    "gn:population":0,
    "gn:timezone":"Asia/Seoul",
    "iso:country":"KR",
    "name:kor_x_preferred":[
        "\uae08\uac15"
    ],
    "name:und_x_variant":[
        "K\u016dmgang"
    ],
    "wof:name":"Geumgang",
    "wof:placetype":"locality"
},
  "geometry": {"coordinates":[128.73973999999998,35.85965],"type":"Point"}
}