{
  "type": "Feature",
  "properties": {
    "gn:admin1_code":"5.0",
    "gn:asciiname":"Sogum-dong",
    "gn:country_code":"KR",
    "gn:dem":108,
    "gn:feature_class":"P",
    "gn:feature_code":"PPL",
    "gn:name":"S\u014fg\u016dm-dong",
    "gn:population":0,
    "gn:timezone":"Asia/Seoul",
    "iso:country":"KR",
    "name:und_x_variant":[
        "\uc11c\uae08\ub3d9",
        "S\u014fg\u016dm-dong"
    ],
    "wof:name":"Sogum-dong",
    "wof:placetype":"locality"
},
  "geometry": {"coordinates":[127.7368,36.2304],"type":"Point"}
}