{
  "type": "Feature",
  "properties": {
    "gn:country":"KR",
    "iso:country":"KR",
    "qs:name":"\uc18c\ub8e1\ub3d9",
    "qs:name_adm0":"\ud55c\uad6d",
    "qs:name_adm1":"\uc804\ub77c\ubd81\ub3c4",
    "qs:photos":12,
    "qs:photos_1k":2,
    "qs:photos_9k":1,
    "qs:photos_9r":1,
    "qs:photos_all":12,
    "qs:photos_sr":1,
    "qs:placetype":"LocalAdmin",
    "qs:pop_sr":"0",
    "wof:name":"\uc18c\ub8e1\ub3d9",
    "wof:placetype":"localadmin"
},
  "geometry": {"coordinates":[126.719055,35.998007],"type":"Point"}
}