{
  "type": "Feature",
  "properties": {
    "gn:admin1_code":"6.0",
    "gn:asciiname":"Chol-gol",
    "gn:country_code":"KR",
    "gn:dem":194,
    "gn:feature_class":"P",
    "gn:feature_code":"PPL",
    "gn:name":"Ch\u014fl-gol",
    "gn:population":0,
    "gn:timezone":"Asia/Seoul",
    "iso:country":"KR",
    "name:kor_x_preferred":[
        "\uc808\uace8"
    ],
    "name:kor_x_variant":[
        "Ch\u014fl-gol"
    ],
    "wof:name":"Chol-gol",
    "wof:placetype":"locality"
},
  "geometry": {"coordinates":[128.96367000000001,37.66384],"type":"Point"}
}