{
  "type": "Feature",
  "properties": {
    "gn:admin1_code":"20.0",
    "gn:asciiname":"Sulgok",
    "gn:country_code":"KR",
    "gn:dem":204,
    "gn:feature_class":"P",
    "gn:feature_code":"PPL",
    "gn:name":"Sulgok",
    "gn:population":0,
    "gn:timezone":"Asia/Seoul",
    "iso:country":"KR",
    "name:und_x_variant":[
        "\uc220\uace1",
        "Sulgok"
    ],
    "wof:name":"Sulgok",
    "wof:placetype":"locality"
},
  "geometry": {"coordinates":[127.99115,35.57695],"type":"Point"}
}