{
  "type": "Feature",
  "properties": {
    "gn:admin1_code":"17.0",
    "gn:asciiname":"Sinyangtteum",
    "gn:country_code":"KR",
    "gn:dem":65,
    "gn:feature_class":"P",
    "gn:feature_code":"PPL",
    "gn:name":"Sinyangtteum",
    "gn:population":0,
    "gn:timezone":"Asia/Seoul",
    "iso:country":"KR",
    "name:kor_x_preferred":[
        "\uc2e0\uc591\ub738"
    ],
    "wof:name":"Sinyangtteum",
    "wof:placetype":"locality"
},
  "geometry": {"coordinates":[127.22205,36.19329000000001],"type":"Point"}
}