{
  "type": "Feature",
  "properties": {
    "gn:admin1_code":"16.0",
    "gn:asciiname":"Un'gong-ni",
    "gn:country_code":"KR",
    "gn:dem":18,
    "gn:feature_class":"P",
    "gn:feature_code":"PPL",
    "gn:name":"\u016cn\u2019gong-ni",
    "gn:population":0,
    "gn:timezone":"Asia/Seoul",
    "iso:country":"KR",
    "name:und_x_variant":[
        "\u016cmgong-ni",
        "\u016cn\u2019gok",
        "\u016cn\u2019gong-ni"
    ],
    "wof:name":"Un'gong-ni",
    "wof:placetype":"locality"
},
  "geometry": {"coordinates":[126.53471999999999,34.76194],"type":"Point"}
}