{
  "type": "Feature",
  "properties": {
    "gn:admin1_code":"6.0",
    "gn:asciiname":"Gimjangso",
    "gn:country_code":"KR",
    "gn:dem":285,
    "gn:feature_class":"P",
    "gn:feature_code":"PPL",
    "gn:name":"Gimjangso",
    "gn:population":0,
    "gn:timezone":"Asia/Seoul",
    "iso:country":"KR",
    "name:kor_x_preferred":[
        "\uae40\uc7a5\uc18c"
    ],
    "wof:name":"Gimjangso",
    "wof:placetype":"locality"
},
  "geometry": {"coordinates":[128.19511,38.12391],"type":"Point"}
}