{
  "type": "Feature",
  "properties": {
    "gn:admin1_code":"14.0",
    "gn:asciiname":"Saesan",
    "gn:country_code":"KR",
    "gn:dem":255,
    "gn:feature_class":"P",
    "gn:feature_code":"PPL",
    "gn:name":"Saesan",
    "gn:population":0,
    "gn:timezone":"Asia/Seoul",
    "iso:country":"KR",
    "name:kor_x_preferred":[
        "\uc0c8\uc0b0"
    ],
    "wof:name":"Saesan",
    "wof:placetype":"locality"
},
  "geometry": {"coordinates":[128.82112000000001,36.11234],"type":"Point"}
}