{
  "type": "Feature",
  "properties": {
    "gn:admin1_code":"20.0",
    "gn:asciiname":"Chi-dong",
    "gn:country_code":"KR",
    "gn:dem":90,
    "gn:feature_class":"P",
    "gn:feature_code":"PPL",
    "gn:name":"Chi-dong",
    "gn:population":0,
    "gn:timezone":"Asia/Seoul",
    "iso:country":"KR",
    "wof:name":"Chi-dong",
    "wof:placetype":"locality"
},
  "geometry": {"coordinates":[128.28333000000001,34.98333],"type":"Point"}
}