{
  "type": "Feature",
  "properties": {
    "gn:admin1_code":"3.0",
    "gn:asciiname":"Myonggok",
    "gn:country_code":"KR",
    "gn:dem":195,
    "gn:feature_class":"P",
    "gn:feature_code":"PPL",
    "gn:name":"My\u014fnggok",
    "gn:population":0,
    "gn:timezone":"Asia/Seoul",
    "iso:country":"KR",
    "wof:name":"Myonggok",
    "wof:placetype":"locality"
},
  "geometry": {"coordinates":[127.13333,36.01667],"type":"Point"}
}