{
  "type": "Feature",
  "properties": {
    "gn:admin1_code":"13.0",
    "gn:asciiname":"Ihwa-ri",
    "gn:country_code":"KR",
    "gn:dem":12,
    "gn:feature_class":"P",
    "gn:feature_code":"PPL",
    "gn:name":"Ihwa-ri",
    "gn:population":0,
    "gn:timezone":"Asia/Seoul",
    "iso:country":"KR",
    "name:kor_x_preferred":[
        "\uc774\ud654\ub9ac"
    ],
    "wof:name":"Ihwa-ri",
    "wof:placetype":"locality"
},
  "geometry": {"coordinates":[126.79028,37.03528],"type":"Point"}
}