{
  "type": "Feature",
  "properties": {
    "gn:admin1_code":"6.0",
    "gn:asciiname":"Saenmal",
    "gn:country_code":"KR",
    "gn:dem":273,
    "gn:feature_class":"P",
    "gn:feature_code":"PPL",
    "gn:name":"Saenmal",
    "gn:population":0,
    "gn:timezone":"Asia/Seoul",
    "iso:country":"KR",
    "name:kor_x_preferred":[
        "\uc0db\ub9d0"
    ],
    "wof:name":"Saenmal",
    "wof:placetype":"locality"
},
  "geometry": {"coordinates":[128.23304999999999,38.00202],"type":"Point"}
}