{
  "type": "Feature",
  "properties": {
    "gn:admin1_code":"16.0",
    "gn:asciiname":"Botdeung",
    "gn:country_code":"KR",
    "gn:dem":18,
    "gn:feature_class":"P",
    "gn:feature_code":"PPL",
    "gn:name":"Botdeung",
    "gn:population":0,
    "gn:timezone":"Asia/Seoul",
    "iso:country":"KR",
    "name:kor_x_preferred":[
        "\ubd07\ub4f1"
    ],
    "name:kor_x_variant":[
        "Pott\u016dng"
    ],
    "wof:name":"Botdeung",
    "wof:placetype":"locality"
},
  "geometry": {"coordinates":[127.20923999999999,34.73005999999999],"type":"Point"}
}