{
  "type": "Feature",
  "properties": {
    "gn:admin1_code":"16.0",
    "gn:asciiname":"Unwolli",
    "gn:country_code":"KR",
    "gn:dem":207,
    "gn:feature_class":"P",
    "gn:feature_code":"PPL",
    "gn:name":"Unwolli",
    "gn:population":0,
    "gn:timezone":"Asia/Seoul",
    "iso:country":"KR",
    "name:kor_x_preferred":[
        "\uc6b4\uc6d4\ub9ac"
    ],
    "name:und_x_variant":[
        "Unw\u014fl-li"
    ],
    "wof:name":"Unwolli",
    "wof:placetype":"locality"
},
  "geometry": {"coordinates":[126.88111000000001,34.86472],"type":"Point"}
}