{
  "type": "Feature",
  "properties": {
    "gn:admin1_code":"16.0",
    "gn:asciiname":"Anjeong",
    "gn:country_code":"KR",
    "gn:dem":17,
    "gn:feature_class":"P",
    "gn:feature_code":"PPL",
    "gn:name":"Anjeong",
    "gn:population":0,
    "gn:timezone":"Asia/Seoul",
    "iso:country":"KR",
    "name:kor_x_preferred":[
        "\uc548\uc815"
    ],
    "name:kor_x_variant":[
        "Anj\u014fng"
    ],
    "name:und_x_variant":[
        "Anj\u014fng-ni",
        "Anjeong"
    ],
    "wof:name":"Anjeong",
    "wof:placetype":"locality"
},
  "geometry": {"coordinates":[126.50482,34.44621],"type":"Point"}
}