{
  "type": "Feature",
  "properties": {
    "gn:admin1_code":"5.0",
    "gn:asciiname":"Ttakpak-kol",
    "gn:country_code":"KR",
    "gn:dem":278,
    "gn:feature_class":"P",
    "gn:feature_code":"PPL",
    "gn:name":"Ttakpak-kol",
    "gn:population":0,
    "gn:timezone":"Asia/Seoul",
    "iso:country":"KR",
    "name:kor_x_preferred":[
        "\ub531\ubc15\uace8"
    ],
    "wof:name":"Ttakpak-kol",
    "wof:placetype":"locality"
},
  "geometry": {"coordinates":[128.3486,37.1002],"type":"Point"}
}