{
  "type": "Feature",
  "properties": {
    "gn:admin1_code":"17.0",
    "gn:asciiname":"Sangnon",
    "gn:cc2":"KR",
    "gn:country_code":"KR",
    "gn:dem":-9999,
    "gn:feature_class":"P",
    "gn:feature_code":"PPL",
    "gn:name":"Sangnon",
    "gn:population":0,
    "gn:timezone":"Asia/Seoul",
    "iso:country":"KR",
    "name:und_x_variant":[
        "Sangnolly\u014fng",
        "Sangnongny\u014fng",
        "Sangnon"
    ],
    "wof:name":"Sangnon",
    "wof:placetype":"locality"
},
  "geometry": {"coordinates":[126.40000000000001,36.23333],"type":"Point"}
}