{
  "type": "Feature",
  "properties": {
    "gn:admin1_code":"14.0",
    "gn:asciiname":"Ganggol",
    "gn:country_code":"KR",
    "gn:dem":160,
    "gn:feature_class":"P",
    "gn:feature_code":"PPL",
    "gn:name":"Ganggol",
    "gn:population":0,
    "gn:timezone":"Asia/Seoul",
    "iso:country":"KR",
    "name:kor_x_preferred":[
        "\uac15\uace8"
    ],
    "wof:name":"Ganggol",
    "wof:placetype":"locality"
},
  "geometry": {"coordinates":[128.77314999999999,35.95645],"type":"Point"}
}