{
  "type": "Feature",
  "properties": {
    "gn:admin1_code":"6.0",
    "gn:asciiname":"Myeongsaengdong",
    "gn:country_code":"KR",
    "gn:dem":716,
    "gn:feature_class":"P",
    "gn:feature_code":"PPL",
    "gn:name":"Myeongsaengdong",
    "gn:population":0,
    "gn:timezone":"Asia/Seoul",
    "iso:country":"KR",
    "name:kor_x_preferred":[
        "\uba85\uc0dd\ub3d9"
    ],
    "name:kor_x_variant":[
        "My\u014fngsaeng-dong"
    ],
    "wof:name":"Myeongsaengdong",
    "wof:placetype":"locality"
},
  "geometry": {"coordinates":[128.64681000000002,37.08066],"type":"Point"}
}