{
  "type": "Feature",
  "properties": {
    "gn:admin1_code":"16.0",
    "gn:asciiname":"Ch'ijaengi",
    "gn:country_code":"KR",
    "gn:dem":44,
    "gn:feature_class":"P",
    "gn:feature_code":"PPL",
    "gn:name":"Ch\u2019ijaengi",
    "gn:population":0,
    "gn:timezone":"Asia/Seoul",
    "iso:country":"KR",
    "name:kor_x_preferred":[
        "\uce58\uc7c1\uc774"
    ],
    "name:kor_x_variant":[
        "Ch\u2019ijaengi"
    ],
    "wof:name":"Ch'ijaengi",
    "wof:placetype":"locality"
},
  "geometry": {"coordinates":[127.34884,34.68292],"type":"Point"}
}