{
  "type": "Feature",
  "properties": {
    "gn:admin1_code":"17.0",
    "gn:asciiname":"Chung-ni",
    "gn:country_code":"KR",
    "gn:dem":106,
    "gn:feature_class":"P",
    "gn:feature_code":"PPL",
    "gn:name":"Chung-ni",
    "gn:population":0,
    "gn:timezone":"Asia/Seoul",
    "iso:country":"KR",
    "name:und_x_variant":[
        "\uc911\ub9ac",
        "Chung-ni"
    ],
    "wof:name":"Chung-ni",
    "wof:placetype":"locality"
},
  "geometry": {"coordinates":[126.6396,36.7807],"type":"Point"}
}