{
  "type": "Feature",
  "properties": {
    "gn:admin1_code":"6.0",
    "gn:asciiname":"Cheongpyeonggol",
    "gn:country_code":"KR",
    "gn:dem":224,
    "gn:feature_class":"P",
    "gn:feature_code":"PPL",
    "gn:name":"Cheongpyeonggol",
    "gn:population":0,
    "gn:timezone":"Asia/Seoul",
    "iso:country":"KR",
    "name:kor_x_preferred":[
        "\uccad\ud3c9\uace8"
    ],
    "name:kor_x_variant":[
        "Ch\u2019\u014fngp\u2019y\u014fng-gol"
    ],
    "wof:name":"Cheongpyeonggol",
    "wof:placetype":"locality"
},
  "geometry": {"coordinates":[127.81985,37.97285],"type":"Point"}
}