{
  "type": "Feature",
  "properties": {
    "gn:admin1_code":"6.0",
    "gn:asciiname":"Sindae",
    "gn:country_code":"KR",
    "gn:dem":563,
    "gn:feature_class":"P",
    "gn:feature_code":"PPL",
    "gn:name":"Sindae",
    "gn:population":0,
    "gn:timezone":"Asia/Seoul",
    "iso:country":"KR",
    "name:kor_x_preferred":[
        "\uc2e0\ub300"
    ],
    "wof:name":"Sindae",
    "wof:placetype":"locality"
},
  "geometry": {"coordinates":[128.3708,37.616],"type":"Point"}
}