{
  "type": "Feature",
  "properties": {
    "gn:admin1_code":"14.0",
    "gn:asciiname":"Unsok-kol",
    "gn:country_code":"KR",
    "gn:dem":141,
    "gn:feature_class":"P",
    "gn:feature_code":"PPL",
    "gn:name":"\u016cns\u014fk-kol",
    "gn:population":0,
    "gn:timezone":"Asia/Seoul",
    "iso:country":"KR",
    "name:und_x_variant":[
        "\uc740\uc11d\uace8",
        "\u016cns\u014fk-kol"
    ],
    "wof:name":"Unsok-kol",
    "wof:placetype":"locality"
},
  "geometry": {"coordinates":[128.09280000000001,36.1966],"type":"Point"}
}