{
  "type": "Feature",
  "properties": {
    "iso:country":"KR",
    "qs:name":"\ud654\uac1c\uba74",
    "qs:name_adm0":"\ud55c\uad6d",
    "qs:name_adm1":"\uacbd\uc0c1\ub0a8\ub3c4",
    "qs:photos":38,
    "qs:photos_1k":8,
    "qs:photos_9k":1,
    "qs:photos_9r":2,
    "qs:photos_all":38,
    "qs:photos_sr":2,
    "qs:placetype":"LocalAdmin",
    "qs:pop_sr":"0",
    "wof:name":"\ud654\uac1c\uba74",
    "wof:placetype":"localadmin"
},
  "geometry": {"coordinates":[127.650661,35.236225],"type":"Point"}
}