{
  "type": "Feature",
  "properties": {
    "gn:admin1_code":"5.0",
    "gn:asciiname":"Jeungsin",
    "gn:country_code":"KR",
    "gn:dem":100,
    "gn:feature_class":"P",
    "gn:feature_code":"PPL",
    "gn:name":"Jeungsin",
    "gn:population":0,
    "gn:timezone":"Asia/Seoul",
    "iso:country":"KR",
    "name:kor_x_preferred":[
        "\uc99d\uc2e0"
    ],
    "wof:name":"Jeungsin",
    "wof:placetype":"locality"
},
  "geometry": {"coordinates":[127.5528,36.96082],"type":"Point"}
}