{
  "type": "Feature",
  "properties": {
    "gn:admin1_code":"16.0",
    "gn:asciiname":"Namch'ang",
    "gn:country_code":"KR",
    "gn:dem":16,
    "gn:feature_class":"P",
    "gn:feature_code":"PPL",
    "gn:name":"Namch\u2019ang",
    "gn:population":0,
    "gn:timezone":"Asia/Seoul",
    "iso:country":"KR",
    "name:kor_x_preferred":[
        "Namch\u2019ang"
    ],
    "wof:name":"Namch'ang",
    "wof:placetype":"locality"
},
  "geometry": {"coordinates":[126.62778,34.40639],"type":"Point"}
}