{
  "type": "Feature",
  "properties": {
    "gn:admin1_code":"12.0",
    "gn:asciiname":"Sicheondonggol",
    "gn:country_code":"KR",
    "gn:dem":46,
    "gn:feature_class":"P",
    "gn:feature_code":"PPL",
    "gn:name":"Sicheondonggol",
    "gn:population":0,
    "gn:timezone":"Asia/Seoul",
    "iso:country":"KR",
    "name:kor_x_preferred":[
        "\uc2dc\ucc9c\ub3d9\uace8"
    ],
    "wof:name":"Sicheondonggol",
    "wof:placetype":"locality"
},
  "geometry": {"coordinates":[126.68527,37.55975],"type":"Point"}
}