{
  "type": "Feature",
  "properties": {
    "gn:admin1_code":"14.0",
    "gn:asciiname":"Wonji",
    "gn:country_code":"KR",
    "gn:dem":185,
    "gn:feature_class":"P",
    "gn:feature_code":"PPL",
    "gn:name":"W\u014fnji",
    "gn:population":0,
    "gn:timezone":"Asia/Seoul",
    "iso:country":"KR",
    "name:und_x_variant":[
        "\uc6d0\uc9c0",
        "W\u014fnji"
    ],
    "wof:name":"Wonji",
    "wof:placetype":"locality"
},
  "geometry": {"coordinates":[128.80500000000001,36.4152],"type":"Point"}
}