{
  "type": "Feature",
  "properties": {
    "gn:admin1_code":"3.0",
    "gn:asciiname":"Mijok-tong",
    "gn:country_code":"KR",
    "gn:dem":306,
    "gn:feature_class":"P",
    "gn:feature_code":"PPL",
    "gn:name":"Mij\u014fk-tong",
    "gn:population":0,
    "gn:timezone":"Asia/Seoul",
    "iso:country":"KR",
    "name:eng_x_preferred":[
        "Mijok"
    ],
    "name:eng_x_variant":[
        "Mijok-tong"
    ],
    "name:und_x_variant":[
        "\ubbf8\uc801\ub3d9",
        "Mij\u014fk-tong"
    ],
    "wof:name":"Mijok",
    "wof:placetype":"locality"
},
  "geometry": {"coordinates":[127.43268999999999,35.9924],"type":"Point"}
}