{
  "type": "Feature",
  "properties": {
    "gn:admin1_code":"5.0",
    "gn:asciiname":"Kamakchae",
    "gn:country_code":"KR",
    "gn:dem":185,
    "gn:feature_class":"P",
    "gn:feature_code":"PPL",
    "gn:name":"Kamakchae",
    "gn:population":0,
    "gn:timezone":"Asia/Seoul",
    "iso:country":"KR",
    "name:und_x_variant":[
        "\uac00\ub9c9\uc7ac",
        "Kamakchae"
    ],
    "wof:name":"Kamakchae",
    "wof:placetype":"locality"
},
  "geometry": {"coordinates":[127.6974,36.4537],"type":"Point"}
}