{
  "type": "Feature",
  "properties": {
    "gn:admin1_code":"13.0",
    "gn:asciiname":"Jangsugol",
    "gn:country_code":"KR",
    "gn:dem":102,
    "gn:feature_class":"P",
    "gn:feature_code":"PPL",
    "gn:name":"Jangsugol",
    "gn:population":0,
    "gn:timezone":"Asia/Seoul",
    "iso:country":"KR",
    "name:kor_x_preferred":[
        "\uc7a5\uc218\uace8"
    ],
    "name:und_x_variant":[
        "Changsu-gol"
    ],
    "wof:name":"Jangsugol",
    "wof:placetype":"locality"
},
  "geometry": {"coordinates":[127.52930000000001,37.13015],"type":"Point"}
}