{
  "type": "Feature",
  "properties": {
    "gn:admin1_code":"11.0",
    "gn:asciiname":"Changanil-tong",
    "gn:country_code":"KR",
    "gn:dem":18,
    "gn:feature_class":"P",
    "gn:feature_code":"PPL",
    "gn:name":"Changanil-tong",
    "gn:population":0,
    "gn:timezone":"Asia/Seoul",
    "iso:country":"KR",
    "name:und_x_variant":[
        "\uc7a5\uc5481\ub3d9",
        "Changanil-tong"
    ],
    "wof:name":"Changanil-tong",
    "wof:placetype":"locality"
},
  "geometry": {"coordinates":[127.06456,37.56711],"type":"Point"}
}