{
  "type": "Feature",
  "properties": {
    "gn:admin1_code":"5.0",
    "gn:asciiname":"Choegadong",
    "gn:country_code":"KR",
    "gn:dem":273,
    "gn:feature_class":"P",
    "gn:feature_code":"PPL",
    "gn:name":"Choegadong",
    "gn:population":0,
    "gn:timezone":"Asia/Seoul",
    "iso:country":"KR",
    "name:kor_x_preferred":[
        "\ucd5c\uac00\ub3d9"
    ],
    "name:kor_x_variant":[
        "Ch\u2019oega-dong"
    ],
    "wof:name":"Choegadong",
    "wof:placetype":"locality"
},
  "geometry": {"coordinates":[128.48303999999999,37.05408],"type":"Point"}
}