{
  "type": "Feature",
  "properties": {
    "gn:admin1_code":"13.0",
    "gn:asciiname":"Haepyeong",
    "gn:country_code":"KR",
    "gn:dem":13,
    "gn:feature_class":"P",
    "gn:feature_code":"PPL",
    "gn:name":"Haepyeong",
    "gn:population":0,
    "gn:timezone":"Asia/Seoul",
    "iso:country":"KR",
    "name:kor_x_preferred":[
        "\ud574\ud3c9"
    ],
    "name:kor_x_variant":[
        "Haep\u2019y\u014fng"
    ],
    "wof:name":"Haepyeong",
    "wof:placetype":"locality"
},
  "geometry": {"coordinates":[126.65949999999999,37.66065],"type":"Point"}
}