{
  "type": "Feature",
  "properties": {
    "gn:admin1_code":"18.0",
    "gn:asciiname":"Gigok",
    "gn:country_code":"KR",
    "gn:dem":37,
    "gn:feature_class":"P",
    "gn:feature_code":"PPL",
    "gn:name":"Gigok",
    "gn:population":0,
    "gn:timezone":"Asia/Seoul",
    "iso:country":"KR",
    "name:kor_x_preferred":[
        "\uae30\uace1"
    ],
    "wof:name":"Gigok",
    "wof:placetype":"locality"
},
  "geometry": {"coordinates":[126.74117,35.13127],"type":"Point"}
}