{
  "type": "Feature",
  "properties": {
    "gn:admin1_code":"17.0",
    "gn:asciiname":"Jaesil",
    "gn:country_code":"KR",
    "gn:dem":71,
    "gn:feature_class":"P",
    "gn:feature_code":"PPL",
    "gn:name":"Jaesil",
    "gn:population":0,
    "gn:timezone":"Asia/Seoul",
    "iso:country":"KR",
    "name:kor_x_preferred":[
        "\uc7ac\uc2e4"
    ],
    "wof:name":"Jaesil",
    "wof:placetype":"locality"
},
  "geometry": {"coordinates":[127.25633999999999,36.73548],"type":"Point"}
}