{
  "type": "Feature",
  "properties": {
    "gn:admin1_code":"17.0",
    "gn:asciiname":"Garyong",
    "gn:country_code":"KR",
    "gn:dem":13,
    "gn:feature_class":"P",
    "gn:feature_code":"PPL",
    "gn:name":"Garyong",
    "gn:population":0,
    "gn:timezone":"Asia/Seoul",
    "iso:country":"KR",
    "name:und_x_variant":[
        "\uac00\ub8e1",
        "Karyong",
        "Garyong"
    ],
    "wof:name":"Garyong",
    "wof:placetype":"locality"
},
  "geometry": {"coordinates":[127.12608,36.9627],"type":"Point"}
}