{
  "type": "Feature",
  "properties": {
    "gn:admin1_code":"16.0",
    "gn:asciiname":"Jangdong",
    "gn:country_code":"KR",
    "gn:dem":142,
    "gn:feature_class":"P",
    "gn:feature_code":"PPL",
    "gn:name":"Jangdong",
    "gn:population":0,
    "gn:timezone":"Asia/Seoul",
    "iso:country":"KR",
    "name:kor_x_preferred":[
        "\uc7a5\ub3d9"
    ],
    "name:und_x_variant":[
        "Chang-gol",
        "Kin-gol",
        "Chang-dong",
        "Jangdong"
    ],
    "wof:name":"Jangdong",
    "wof:placetype":"locality"
},
  "geometry": {"coordinates":[127.20246000000002,34.96083],"type":"Point"}
}