{
  "type": "Feature",
  "properties": {
    "gn:admin1_code":"13.0",
    "gn:asciiname":"Jongmi",
    "gn:country_code":"KR",
    "gn:dem":14,
    "gn:feature_class":"P",
    "gn:feature_code":"PPL",
    "gn:name":"Jongmi",
    "gn:population":0,
    "gn:timezone":"Asia/Seoul",
    "iso:country":"KR",
    "name:kor_x_preferred":[
        "\uc885\ubbf8"
    ],
    "name:und_x_variant":[
        "Changmi",
        "Jongmi"
    ],
    "wof:name":"Jongmi",
    "wof:placetype":"locality"
},
  "geometry": {"coordinates":[126.73237,37.68627],"type":"Point"}
}