{
  "type": "Feature",
  "properties": {
    "gn:admin1_code":"13.0",
    "gn:asciiname":"Geonneomal",
    "gn:country_code":"KR",
    "gn:dem":80,
    "gn:feature_class":"P",
    "gn:feature_code":"PPL",
    "gn:name":"Geonneomal",
    "gn:population":0,
    "gn:timezone":"Asia/Seoul",
    "iso:country":"KR",
    "name:kor_x_preferred":[
        "\uc911\ud314\uacc4"
    ],
    "name:kor_x_variant":[
        "Chungp\u2019algye",
        "\uac74\ub108\ub9d0"
    ],
    "name:und_x_variant":[
        "Jungpalgye",
        "Geonneomal"
    ],
    "wof:name":"Geonneomal",
    "wof:placetype":"locality"
},
  "geometry": {"coordinates":[127.51841,37.17039000000001],"type":"Point"}
}