{
  "type": "Feature",
  "properties": {
    "gn:admin1_code":"14.0",
    "gn:asciiname":"Kuch'on",
    "gn:country_code":"KR",
    "gn:dem":303,
    "gn:feature_class":"P",
    "gn:feature_code":"PPL",
    "gn:name":"Kuch\u2019\u014fn",
    "gn:population":0,
    "gn:timezone":"Asia/Seoul",
    "iso:country":"KR",
    "name:und_x_variant":[
        "Kuch\u2019\u014fn-dong",
        "Kuch\u2019\u014fn"
    ],
    "wof:name":"Kuch'on",
    "wof:placetype":"locality"
},
  "geometry": {"coordinates":[129.1054,36.3119],"type":"Point"}
}