{
  "type": "Feature",
  "properties": {
    "gn:admin1_code":"15.0",
    "gn:asciiname":"Sukcheondong",
    "gn:country_code":"KR",
    "gn:dem":85,
    "gn:feature_class":"P",
    "gn:feature_code":"PPL",
    "gn:name":"Sukcheondong",
    "gn:population":0,
    "gn:timezone":"Asia/Seoul",
    "iso:country":"KR",
    "name:kor_x_preferred":[
        "\uc219\ucc9c\ub3d9"
    ],
    "wof:name":"Sukcheondong",
    "wof:placetype":"locality"
},
  "geometry": {"coordinates":[128.74209999999999,35.87746],"type":"Point"}
}