{
  "type": "Feature",
  "properties": {
    "gn:admin1_code":"20.0",
    "gn:asciiname":"Taegyol-li",
    "gn:country_code":"KR",
    "gn:dem":45,
    "gn:feature_class":"P",
    "gn:feature_code":"PPL",
    "gn:name":"Taegy\u014fl-li",
    "gn:population":0,
    "gn:timezone":"Asia/Seoul",
    "iso:country":"KR",
    "name:und_x_variant":[
        "Taegy\u014fn-ri",
        "\ub300\uacac\ub9ac",
        "Taegy\u014fl-li"
    ],
    "wof:name":"Taegyol-li",
    "wof:placetype":"locality"
},
  "geometry": {"coordinates":[128.46048000000002,35.63776],"type":"Point"}
}