{
  "type": "Feature",
  "properties": {
    "gn:admin1_code":"13.0",
    "gn:asciiname":"Tugyeul",
    "gn:country_code":"KR",
    "gn:dem":70,
    "gn:feature_class":"P",
    "gn:feature_code":"PPL",
    "gn:name":"Tugyeul",
    "gn:population":0,
    "gn:timezone":"Asia/Seoul",
    "iso:country":"KR",
    "name:und_x_variant":[
        "Dukge-ri",
        "Tuge-ri",
        "Tugye-ri",
        "\ub450\uacc4\uc6b8",
        "Dugyeul",
        "Tugyeul"
    ],
    "wof:name":"Tugyeul",
    "wof:placetype":"locality"
},
  "geometry": {"coordinates":[127.2325,37.28139],"type":"Point"}
}