{
  "type": "Feature",
  "properties": {
    "gn:admin1_code":"16.0",
    "gn:asciiname":"Buchon",
    "gn:country_code":"KR",
    "gn:dem":21,
    "gn:feature_class":"P",
    "gn:feature_code":"PPL",
    "gn:name":"Buchon",
    "gn:population":0,
    "gn:timezone":"Asia/Seoul",
    "iso:country":"KR",
    "name:deu_x_preferred":[
        "Buchon"
    ],
    "name:fra_x_preferred":[
        "Buchon"
    ],
    "name:kor_x_preferred":[
        "\ubd80\ucd0c"
    ],
    "wof:name":"Buchon",
    "wof:placetype":"locality"
},
  "geometry": {"coordinates":[126.72676,34.98869000000001],"type":"Point"}
}