{
  "type": "Feature",
  "properties": {
    "gn:admin1_code":"16.0",
    "gn:asciiname":"Hamgumi",
    "gn:cc2":"KR",
    "gn:country_code":"KR",
    "gn:dem":27,
    "gn:feature_class":"P",
    "gn:feature_code":"PPL",
    "gn:name":"Hamgumi",
    "gn:population":0,
    "gn:timezone":"Asia/Seoul",
    "iso:country":"KR",
    "name:und_x_variant":[
        "Kanky\u016bmi",
        "Hamgumi"
    ],
    "wof:name":"Hamgumi",
    "wof:placetype":"locality"
},
  "geometry": {"coordinates":[127.71222,34.53722],"type":"Point"}
}