{
  "type": "Feature",
  "properties": {
    "gn:admin1_code":"6.0",
    "gn:asciiname":"Malgol",
    "gn:country_code":"KR",
    "gn:dem":183,
    "gn:feature_class":"P",
    "gn:feature_code":"PPL",
    "gn:name":"Malgol",
    "gn:population":0,
    "gn:timezone":"Asia/Seoul",
    "iso:country":"KR",
    "name:und_x_variant":[
        "\ub9d0\uace8",
        "Malgol"
    ],
    "wof:name":"Malgol",
    "wof:placetype":"locality"
},
  "geometry": {"coordinates":[127.65367999999999,37.81636],"type":"Point"}
}