{
  "type": "Feature",
  "properties": {
    "gn:admin1_code":"6.0",
    "gn:asciiname":"Sangol",
    "gn:country_code":"KR",
    "gn:dem":304,
    "gn:feature_class":"P",
    "gn:feature_code":"PPL",
    "gn:name":"Sangol",
    "gn:population":0,
    "gn:timezone":"Asia/Seoul",
    "iso:country":"KR",
    "name:kor_x_preferred":[
        "\uac08\uace8"
    ],
    "name:kor_x_variant":[
        "\uc0b0\uace8"
    ],
    "name:und_x_variant":[
        "Kal-gol",
        "Sangol",
        "Galgol"
    ],
    "wof:name":"Sangol",
    "wof:placetype":"locality"
},
  "geometry": {"coordinates":[127.89549,37.77545],"type":"Point"}
}