{
  "type": "Feature",
  "properties": {
    "gn:admin1_code":"3.0",
    "gn:asciiname":"Namsan",
    "gn:country_code":"KR",
    "gn:dem":430,
    "gn:feature_class":"P",
    "gn:feature_code":"PPL",
    "gn:name":"Namsan",
    "gn:population":0,
    "gn:timezone":"Asia/Seoul",
    "iso:country":"KR",
    "name:ceb_x_preferred":[
        "Namsan"
    ],
    "name:deu_x_preferred":[
        "Namsan"
    ],
    "name:fra_x_preferred":[
        "Namsan"
    ],
    "name:hun_x_preferred":[
        "Namszan"
    ],
    "name:por_x_preferred":[
        "Namsan"
    ],
    "name:rus_x_preferred":[
        "\u041d\u0430\u043c\u0441\u0430\u043d"
    ],
    "name:sco_x_preferred":[
        "Namsan"
    ],
    "name:spa_x_preferred":[
        "Namsan"
    ],
    "name:swe_x_preferred":[
        "Namsan"
    ],
    "name:und_x_variant":[
        "\ub0a8\uc0b0",
        "Namsan"
    ],
    "wof:name":"Namsan",
    "wof:placetype":"locality"
},
  "geometry": {"coordinates":[127.5993,35.71693],"type":"Point"}
}