{
  "type": "Feature",
  "properties": {
    "gn:admin1_code":"6.0",
    "gn:asciiname":"Nohwa-dong",
    "gn:country_code":"KR",
    "gn:dem":293,
    "gn:feature_class":"P",
    "gn:feature_code":"PPL",
    "gn:name":"Nohwa-dong",
    "gn:population":0,
    "gn:timezone":"Asia/Seoul",
    "iso:country":"KR",
    "wof:name":"Nohwa-dong",
    "wof:placetype":"locality"
},
  "geometry": {"coordinates":[127.73333,37.76667],"type":"Point"}
}