{
  "type": "Feature",
  "properties": {
    "gn:admin1_code":"14.0",
    "gn:asciiname":"Tangnamuma",
    "gn:country_code":"KR",
    "gn:dem":253,
    "gn:feature_class":"P",
    "gn:feature_code":"PPL",
    "gn:name":"Tangnamuma",
    "gn:population":0,
    "gn:timezone":"Asia/Seoul",
    "iso:country":"KR",
    "name:und_x_variant":[
        "\ub2f9\ub098\ubb34\ub9c8",
        "Tangnamuma"
    ],
    "wof:name":"Tangnamuma",
    "wof:placetype":"locality"
},
  "geometry": {"coordinates":[129.1771,36.4635],"type":"Point"}
}