{
  "type": "Feature",
  "properties": {
    "gn:admin1_code":"14.0",
    "gn:asciiname":"Gwangpyeong",
    "gn:country_code":"KR",
    "gn:dem":143,
    "gn:feature_class":"P",
    "gn:feature_code":"PPL",
    "gn:name":"Gwangpyeong",
    "gn:population":0,
    "gn:timezone":"Asia/Seoul",
    "iso:country":"KR",
    "name:kor_x_preferred":[
        "\uad11\ud3c9"
    ],
    "wof:name":"Gwangpyeong",
    "wof:placetype":"locality"
},
  "geometry": {"coordinates":[128.69997000000001,36.65093],"type":"Point"}
}