{
  "type": "Feature",
  "properties": {
    "gn:admin1_code":"1.0",
    "gn:asciiname":"Ganggudong",
    "gn:country_code":"KR",
    "gn:dem":35,
    "gn:feature_class":"P",
    "gn:feature_code":"PPL",
    "gn:name":"Ganggudong",
    "gn:population":0,
    "gn:timezone":"Asia/Seoul",
    "iso:country":"KR",
    "name:kor_x_preferred":[
        "\uac15\uad6c\ub3d9"
    ],
    "name:und_x_variant":[
        "Kanggu-dong"
    ],
    "wof:name":"Ganggudong",
    "wof:placetype":"locality"
},
  "geometry": {"coordinates":[126.27688000000001,33.40902],"type":"Point"}
}