{
  "type": "Feature",
  "properties": {
    "gn:admin1_code":"14.0",
    "gn:asciiname":"Somok-kol",
    "gn:country_code":"KR",
    "gn:dem":88,
    "gn:feature_class":"P",
    "gn:feature_code":"PPL",
    "gn:name":"S\u014fmok-kol",
    "gn:population":0,
    "gn:timezone":"Asia/Seoul",
    "iso:country":"KR",
    "name:und_x_variant":[
        "\uc11c\ubabb\uace8",
        "S\u014fmok-kol"
    ],
    "wof:name":"Somok-kol",
    "wof:placetype":"locality"
},
  "geometry": {"coordinates":[128.1061,36.0642],"type":"Point"}
}