{
  "type": "Feature",
  "properties": {
    "gn:admin1_code":"14.0",
    "gn:asciiname":"Sungdang",
    "gn:country_code":"KR",
    "gn:dem":55,
    "gn:feature_class":"P",
    "gn:feature_code":"PPL",
    "gn:name":"S\u016dngdang",
    "gn:population":0,
    "gn:timezone":"Asia/Seoul",
    "iso:country":"KR",
    "name:und_x_variant":[
        "\uc2b9\ub2f9",
        "S\u016dngdang"
    ],
    "wof:name":"Sungdang",
    "wof:placetype":"locality"
},
  "geometry": {"coordinates":[128.3785,36.3808],"type":"Point"}
}