{
  "type": "Feature",
  "properties": {
    "gn:admin1_code":"17.0",
    "gn:asciiname":"Garaeteo",
    "gn:country_code":"KR",
    "gn:dem":57,
    "gn:feature_class":"P",
    "gn:feature_code":"PPL",
    "gn:name":"Garaeteo",
    "gn:population":0,
    "gn:timezone":"Asia/Seoul",
    "iso:country":"KR",
    "name:kor_x_preferred":[
        "\uac00\ub798\ud130"
    ],
    "wof:name":"Garaeteo",
    "wof:placetype":"locality"
},
  "geometry": {"coordinates":[127.28939,36.57925],"type":"Point"}
}