{
  "type": "Feature",
  "properties": {
    "gn:admin1_code":"13.0",
    "gn:asciiname":"Bongmyeong-ri",
    "gn:country_code":"KR",
    "gn:dem":44,
    "gn:feature_class":"P",
    "gn:feature_code":"PPLL",
    "gn:name":"Bongmyeong-ri",
    "gn:population":0,
    "gn:timezone":"Asia/Seoul",
    "iso:country":"KR",
    "name:und_x_variant":[
        "\ubd09\uba85\ub9ac",
        "Bongmyeong-ri",
        "Pongmy\u014fng-ni"
    ],
    "wof:name":"Bongmyeong-ri",
    "wof:placetype":"locality"
},
  "geometry": {"coordinates":[127.12417000000001,37.11917],"type":"Point"}
}