{
  "type": "Feature",
  "properties": {
    "gn:admin1_code":"14.0",
    "gn:asciiname":"Hobakpat",
    "gn:country_code":"KR",
    "gn:dem":263,
    "gn:feature_class":"P",
    "gn:feature_code":"PPL",
    "gn:name":"Hobakpat",
    "gn:population":0,
    "gn:timezone":"Asia/Seoul",
    "iso:country":"KR",
    "name:und_x_variant":[
        "\ud638\ubc15\ubc2d",
        "Hobakpat"
    ],
    "wof:name":"Hobakpat",
    "wof:placetype":"locality"
},
  "geometry": {"coordinates":[129.27019999999999,36.8948],"type":"Point"}
}