{
  "type": "Feature",
  "properties": {
    "gn:admin1_code":"6.0",
    "gn:asciiname":"Kadok-tong",
    "gn:country_code":"KR",
    "gn:dem":539,
    "gn:feature_class":"P",
    "gn:feature_code":"PPL",
    "gn:name":"Kad\u014fk-tong",
    "gn:population":0,
    "gn:timezone":"Asia/Seoul",
    "iso:country":"KR",
    "name:kor_x_preferred":[
        "\uac00\ub355\ub3d9"
    ],
    "name:kor_x_variant":[
        "Kad\u014fk-tong"
    ],
    "wof:name":"Kadok-tong",
    "wof:placetype":"locality"
},
  "geometry": {"coordinates":[128.41299999999998,37.8277],"type":"Point"}
}