{
  "type": "Feature",
  "properties": {
    "gn:admin1_code":"14.0",
    "gn:asciiname":"Polmae",
    "gn:country_code":"KR",
    "gn:dem":397,
    "gn:feature_class":"P",
    "gn:feature_code":"PPL",
    "gn:name":"P\u014flmae",
    "gn:population":0,
    "gn:timezone":"Asia/Seoul",
    "iso:country":"KR",
    "name:und_x_variant":[
        "\ubc8c\ub9e4",
        "P\u014flmae"
    ],
    "wof:name":"Polmae",
    "wof:placetype":"locality"
},
  "geometry": {"coordinates":[129.14760000000001,36.7847],"type":"Point"}
}