{
  "type": "Feature",
  "properties": {
    "gn:admin1_code":"13.0",
    "gn:asciiname":"Hwanggeo",
    "gn:country_code":"KR",
    "gn:dem":258,
    "gn:feature_class":"P",
    "gn:feature_code":"PPL",
    "gn:name":"Hwanggeo",
    "gn:population":0,
    "gn:timezone":"Asia/Seoul",
    "iso:country":"KR",
    "name:und_x_variant":[
        "\ud669\uac70",
        "Hwanggeo",
        "Hwangg\u014f"
    ],
    "wof:name":"Hwanggeo",
    "wof:placetype":"locality"
},
  "geometry": {"coordinates":[127.71167,37.46111],"type":"Point"}
}