{
  "type": "Feature",
  "properties": {
    "gn:admin1_code":"3.0",
    "gn:asciiname":"P'imong-ni",
    "gn:country_code":"KR",
    "gn:dem":202,
    "gn:feature_class":"P",
    "gn:feature_code":"PPL",
    "gn:name":"P\u2019imong-ni",
    "gn:population":0,
    "gn:timezone":"Asia/Seoul",
    "iso:country":"KR",
    "name:eng_x_preferred":[
        "P'imong"
    ],
    "name:eng_x_variant":[
        "P'imong-ni"
    ],
    "name:und_x_variant":[
        "P\u2019imong-ni",
        "\ud53c\ubaa9\ub9ac"
    ],
    "wof:name":"P'imong",
    "wof:placetype":"locality"
},
  "geometry": {"coordinates":[127.3489,36.027],"type":"Point"}
}