{
  "type": "Feature",
  "properties": {
    "gn:admin1_code":"6.0",
    "gn:asciiname":"Yeongtong",
    "gn:country_code":"KR",
    "gn:dem":93,
    "gn:feature_class":"P",
    "gn:feature_code":"PPL",
    "gn:name":"Yeongtong",
    "gn:population":0,
    "gn:timezone":"Asia/Seoul",
    "iso:country":"KR",
    "name:kor_x_preferred":[
        "\uc601\ud1b5"
    ],
    "name:und_x_variant":[
        "Y\u014fngt\u2019ong",
        "Yeongtong"
    ],
    "wof:name":"Yeongtong",
    "wof:placetype":"locality"
},
  "geometry": {"coordinates":[128.64328,38.03154],"type":"Point"}
}