{
  "type": "Feature",
  "properties": {
    "gn:admin1_code":"5.0",
    "gn:asciiname":"Song-gol",
    "gn:country_code":"KR",
    "gn:dem":306,
    "gn:feature_class":"P",
    "gn:feature_code":"PPL",
    "gn:name":"Song-gol",
    "gn:population":0,
    "gn:timezone":"Asia/Seoul",
    "iso:country":"KR",
    "name:kor_x_preferred":[
        "\uc1a1\uace8"
    ],
    "wof:name":"Song-gol",
    "wof:placetype":"locality"
},
  "geometry": {"coordinates":[127.9601,37.1731],"type":"Point"}
}