{
  "type": "Feature",
  "properties": {
    "gn:admin1_code":"20.0",
    "gn:asciiname":"Naewol-li",
    "gn:country_code":"KR",
    "gn:dem":685,
    "gn:feature_class":"P",
    "gn:feature_code":"PPL",
    "gn:name":"Naew\u014fl-li",
    "gn:population":0,
    "gn:timezone":"Asia/Seoul",
    "iso:country":"KR",
    "wof:name":"Naewol-li",
    "wof:placetype":"locality"
},
  "geometry": {"coordinates":[127.78917,35.30722],"type":"Point"}
}