{
  "type": "Feature",
  "properties": {
    "gn:admin1_code":"17.0",
    "gn:asciiname":"Chiji-gol",
    "gn:cc2":"KR",
    "gn:country_code":"KR",
    "gn:dem":19,
    "gn:feature_class":"P",
    "gn:feature_code":"PPL",
    "gn:name":"Chiji-gol",
    "gn:population":0,
    "gn:timezone":"Asia/Seoul",
    "iso:country":"KR",
    "name:und_x_variant":[
        "Chiji Gol",
        "Chiji-gol",
        "\uc9c0\uc9c0\uace8"
    ],
    "wof:name":"Chiji-gol",
    "wof:placetype":"locality"
},
  "geometry": {"coordinates":[126.39,36.67306],"type":"Point"}
}