{
  "type": "Feature",
  "properties": {
    "gn:admin1_code":"19.0",
    "gn:asciiname":"Wongyesan",
    "gn:country_code":"KR",
    "gn:dem":109,
    "gn:feature_class":"P",
    "gn:feature_code":"PPL",
    "gn:name":"Wongyesan",
    "gn:population":0,
    "gn:timezone":"Asia/Seoul",
    "iso:country":"KR",
    "name:und_x_variant":[
        "\uc6d0\uacc4\uc0b0",
        "W\u014fn\u2019gyesan",
        "Wongyesan"
    ],
    "wof:name":"Wongyesan",
    "wof:placetype":"locality"
},
  "geometry": {"coordinates":[127.29966,36.33379],"type":"Point"}
}