{
  "type": "Feature",
  "properties": {
    "gn:admin1_code":"6.0",
    "gn:asciiname":"Kungjang-dong",
    "gn:country_code":"KR",
    "gn:dem":607,
    "gn:feature_class":"P",
    "gn:feature_code":"PPL",
    "gn:name":"Kungjang-dong",
    "gn:population":0,
    "gn:timezone":"Asia/Seoul",
    "iso:country":"KR",
    "name:kor_x_preferred":[
        "\uad81\uc7a5\ub3d9"
    ],
    "wof:name":"Kungjang-dong",
    "wof:placetype":"locality"
},
  "geometry": {"coordinates":[128.60759999999999,37.1708],"type":"Point"}
}