{
  "type": "Feature",
  "properties": {
    "gn:admin1_code":"14.0",
    "gn:asciiname":"Karaesil",
    "gn:country_code":"KR",
    "gn:dem":277,
    "gn:feature_class":"P",
    "gn:feature_code":"PPL",
    "gn:name":"Karaesil",
    "gn:population":0,
    "gn:timezone":"Asia/Seoul",
    "iso:country":"KR",
    "name:und_x_variant":[
        "\uac00\ub798\uc2e4",
        "Karaesil"
    ],
    "wof:name":"Karaesil",
    "wof:placetype":"locality"
},
  "geometry": {"coordinates":[127.98273,35.92073],"type":"Point"}
}