{
  "type": "Feature",
  "properties": {
    "gn:admin1_code":"20.0",
    "gn:asciiname":"Nampo",
    "gn:country_code":"KR",
    "gn:dem":2,
    "gn:feature_class":"P",
    "gn:feature_code":"PPL",
    "gn:name":"Nampo",
    "gn:population":0,
    "gn:timezone":"Asia/Seoul",
    "iso:country":"KR",
    "name:ace_x_preferred":[
        "Nampo"
    ],
    "name:ara_x_preferred":[
        "\u0646\u0627\u0645\u0628\u0648"
    ],
    "name:aze_x_preferred":[
        "Nampxo"
    ],
    "name:bul_x_preferred":[
        "\u041d\u0430\u043c\u043f\u0445\u043e"
    ],
    "name:cat_x_preferred":[
        "Nampo"
    ],
    "name:cdo_x_preferred":[
        "Namp'o"
    ],
    "name:ceb_x_preferred":[
        "Namp'o"
    ],
    "name:ces_x_preferred":[
        "Nampcho"
    ],
    "name:dan_x_preferred":[
        "Nampho"
    ],
    "name:deu_x_preferred":[
        "Namp\u2019o"
    ],
    "name:epo_x_preferred":[
        "Nampo"
    ],
    "name:est_x_preferred":[
        "Namp'o"
    ],
    "name:eus_x_preferred":[
        "Nampo"
    ],
    "name:fas_x_preferred":[
        "\u0646\u0627\u0645\u067e\u0648"
    ],
    "name:fin_x_preferred":[
        "Nampo"
    ],
    "name:fra_x_preferred":[
        "Nampo"
    ],
    "name:hak_x_preferred":[
        "Namp'o"
    ],
    "name:heb_x_preferred":[
        "\u05e0\u05d0\u05de\u05e4\u05d5"
    ],
    "name:hun_x_preferred":[
        "Nampho"
    ],
    "name:ita_x_preferred":[
        "Namp'o"
    ],
    "name:jpn_x_preferred":[
        "\u5357\u6d66\u7279\u5225\u5e02"
    ],
    "name:kal_x_preferred":[
        "Namp'o"
    ],
    "name:kor_x_preferred":[
        "\ub0a8\ud3ec"
    ],
    "name:kor_x_variant":[
        "\ub0a8\ud3ec\ud2b9\ubcc4\uc2dc"
    ],
    "name:lit_x_preferred":[
        "Nampo"
    ],
    "name:mon_x_preferred":[
        "\u041d\u0430\u043c\u043f\u0443"
    ],
    "name:mri_x_preferred":[
        "Nampho"
    ],
    "name:msa_x_preferred":[
        "Nampo"
    ],
    "name:nds_x_preferred":[
        "Nampo"
    ],
    "name:nld_x_preferred":[
        "Namp'o"
    ],
    "name:nor_x_preferred":[
        "Nampo"
    ],
    "name:pnb_x_preferred":[
        "\u0646\u06cc\u0645\u067e\u06be\u0648"
    ],
    "name:pol_x_preferred":[
        "Namp\u2019o"
    ],
    "name:por_x_preferred":[
        "Nampo"
    ],
    "name:ron_x_preferred":[
        "Namp'o"
    ],
    "name:rus_x_preferred":[
        "\u041d\u0430\u043c\u043f\u0445\u043e"
    ],
    "name:sco_x_preferred":[
        "Namp'o"
    ],
    "name:spa_x_preferred":[
        "Namp'o"
    ],
    "name:swa_x_preferred":[
        "Nampho"
    ],
    "name:swe_x_preferred":[
        "Nampo"
    ],
    "name:tgl_x_preferred":[
        "Nampo"
    ],
    "name:tha_x_preferred":[
        "\u0e19\u0e31\u0e21\u0e42\u0e1e"
    ],
    "name:tur_x_preferred":[
        "Nampho"
    ],
    "name:ukr_x_preferred":[
        "\u041d\u0430\u043c\u043f\u0445\u043e"
    ],
    "name:urd_x_preferred":[
        "\u0646\u0627\u0645\u067e\u0648"
    ],
    "name:vie_x_preferred":[
        "Nampho"
    ],
    "name:war_x_preferred":[
        "Nampho"
    ],
    "name:zho_x_preferred":[
        "\u5357\u6d66\u7279\u5225\u5e02"
    ],
    "wof:name":"Nampo",
    "wof:placetype":"locality"
},
  "geometry": {"coordinates":[128.85437999999999,35.1856],"type":"Point"}
}