{
  "type": "Feature",
  "properties": {
    "gn:admin1_code":"20.0",
    "gn:asciiname":"Saebaji",
    "gn:country_code":"KR",
    "gn:dem":21,
    "gn:feature_class":"P",
    "gn:feature_code":"PPL",
    "gn:name":"Saebaji",
    "gn:population":0,
    "gn:timezone":"Asia/Seoul",
    "iso:country":"KR",
    "name:und_x_variant":[
        "\uc0c8\ubc14\uc9c0",
        "Saebaji"
    ],
    "wof:name":"Saebaji",
    "wof:placetype":"locality"
},
  "geometry": {"coordinates":[128.48926,34.93466],"type":"Point"}
}