{
  "type": "Feature",
  "properties": {
    "gn:admin1_code":"17.0",
    "gn:asciiname":"Mayang-ni",
    "gn:cc2":"KR",
    "gn:country_code":"KR",
    "gn:dem":13,
    "gn:feature_class":"P",
    "gn:feature_code":"PPL",
    "gn:name":"Mayang-ni",
    "gn:population":0,
    "gn:timezone":"Asia/Seoul",
    "iso:country":"KR",
    "name:und_x_variant":[
        "Maryang-ni",
        "Mayang-ni"
    ],
    "wof:name":"Mayang-ni",
    "wof:placetype":"locality"
},
  "geometry": {"coordinates":[126.83333,36.08333],"type":"Point"}
}