{
  "type": "Feature",
  "properties": {
    "iso:country":"KR",
    "qs:name":"\ud559\uad50\uba74",
    "qs:name_adm0":"\ud55c\uad6d",
    "qs:name_adm1":"\uc804\ub77c\ub0a8\ub3c4",
    "qs:photos":42,
    "qs:photos_1k":9,
    "qs:photos_9k":1,
    "qs:photos_9r":2,
    "qs:photos_all":42,
    "qs:photos_sr":2,
    "qs:placetype":"LocalAdmin",
    "qs:pop_sr":"0",
    "wof:name":"\ud559\uad50\uba74",
    "wof:placetype":"localadmin"
},
  "geometry": {"coordinates":[126.4773555,35.0359845],"type":"Point"}
}