{
  "type": "Feature",
  "properties": {
    "gn:admin1_code":"20.0",
    "gn:asciiname":"Sansu-dong",
    "gn:country_code":"KR",
    "gn:dem":573,
    "gn:feature_class":"P",
    "gn:feature_code":"PPL",
    "gn:name":"Sansu-dong",
    "gn:population":0,
    "gn:timezone":"Asia/Seoul",
    "iso:country":"KR",
    "name:und_x_variant":[
        "\uc0b0\uc218\ub3d9",
        "Sansu-dong"
    ],
    "wof:name":"Sansu-dong",
    "wof:placetype":"locality"
},
  "geometry": {"coordinates":[127.97306,35.81517],"type":"Point"}
}