{
  "type": "Feature",
  "properties": {
    "gn:admin1_code":"14.0",
    "gn:asciiname":"Yangju-dong",
    "gn:country_code":"KR",
    "gn:dem":490,
    "gn:feature_class":"P",
    "gn:feature_code":"PPL",
    "gn:name":"Yangju-dong",
    "gn:population":0,
    "gn:timezone":"Asia/Seoul",
    "iso:country":"KR",
    "wof:name":"Yangju-dong",
    "wof:placetype":"locality"
},
  "geometry": {"coordinates":[128.21666999999999,36.86667],"type":"Point"}
}