{
  "type": "Feature",
  "properties": {
    "gn:admin1_code":"13.0",
    "gn:admin2_code":"Ans\u014fng-si",
    "gn:asciiname":"Bokgeo",
    "gn:country_code":"KR",
    "gn:dem":59,
    "gn:feature_class":"P",
    "gn:feature_code":"PPL",
    "gn:name":"Bokgeo",
    "gn:population":0,
    "gn:timezone":"Asia/Seoul",
    "iso:country":"KR",
    "name:kor_x_preferred":[
        "\ubcf5\uac70"
    ],
    "name:kor_x_variant":[
        "Pokk\u014f"
    ],
    "wof:name":"Bokgeo",
    "wof:placetype":"locality"
},
  "geometry": {"coordinates":[127.32449,37.00487],"type":"Point"}
}