{
  "type": "Feature",
  "properties": {
    "gn:country":"KR",
    "gn:fcode":"PPL",
    "gn:pop":0,
    "iso:country":"KR",
    "name:kor_x_preferred":[
        "\uc911\uc559\ub3d9\uc0ac\ubb34\uc18c"
    ],
    "name:unk_x_variant":[
        "Jungangdong"
    ],
    "qs:name":"\uc911\uc559\ub3d9",
    "qs:name_adm0":"\ud55c\uad6d",
    "qs:name_adm1":"\ucda9\uccad\ubd81\ub3c4",
    "qs:photos":155,
    "qs:photos_1k":31,
    "qs:photos_9k":1,
    "qs:photos_9r":4,
    "qs:photos_all":155,
    "qs:photos_sr":4,
    "qs:placetype":"Suburb",
    "qs:pop_sr":"0",
    "wof:name":"\uc911\uc559\ub3d9",
    "wof:placetype":"neighbourhood",
    "wof:population":0
},
  "geometry": {"coordinates":[127.06,37.04833],"type":"Point"}
}