{
  "type": "Feature",
  "properties": {
    "gn:admin1_code":"5.0",
    "gn:asciiname":"Bakkattdosawol",
    "gn:country_code":"KR",
    "gn:dem":170,
    "gn:feature_class":"P",
    "gn:feature_code":"PPL",
    "gn:name":"Bakkattdosawol",
    "gn:population":0,
    "gn:timezone":"Asia/Seoul",
    "iso:country":"KR",
    "name:kor_x_preferred":[
        "\ubc14\uae65\ub3c4\uc0ac\uc6d4"
    ],
    "name:kor_x_variant":[
        "Pakkattosaw\u014fl"
    ],
    "wof:name":"Bakkattdosawol",
    "wof:placetype":"locality"
},
  "geometry": {"coordinates":[128.03928999999999,37.06997],"type":"Point"}
}