{
  "type": "Feature",
  "properties": {
    "gn:admin1_code":"17.0",
    "gn:asciiname":"Paryong",
    "gn:country_code":"KR",
    "gn:dem":43,
    "gn:feature_class":"P",
    "gn:feature_code":"PPL",
    "gn:name":"Pary\u014fng",
    "gn:population":0,
    "gn:timezone":"Asia/Seoul",
    "iso:country":"KR",
    "name:und_x_variant":[
        "\ubc1c\uc601",
        "Pary\u014fng"
    ],
    "wof:name":"Paryong",
    "wof:placetype":"locality"
},
  "geometry": {"coordinates":[126.5508,36.8524],"type":"Point"}
}