{
  "type": "Feature",
  "properties": {
    "gn:admin1_code":"17.0",
    "gn:asciiname":"Ponggi-ri",
    "gn:country_code":"KR",
    "gn:dem":44,
    "gn:feature_class":"P",
    "gn:feature_code":"PPL",
    "gn:name":"Ponggi-ri",
    "gn:population":0,
    "gn:timezone":"Asia/Seoul",
    "iso:country":"KR",
    "name:und_x_variant":[
        "\ubd09\uae30\ub9ac",
        "Ponggi-ri"
    ],
    "wof:name":"Ponggi-ri",
    "wof:placetype":"locality"
},
  "geometry": {"coordinates":[127.32989999999999,36.4977],"type":"Point"}
}