{
  "type": "Feature",
  "properties": {
    "gn:admin1_code":"20.0",
    "gn:asciiname":"Sobusil",
    "gn:country_code":"KR",
    "gn:dem":81,
    "gn:feature_class":"P",
    "gn:feature_code":"PPL",
    "gn:name":"S\u014fbusil",
    "gn:population":0,
    "gn:timezone":"Asia/Seoul",
    "iso:country":"KR",
    "name:und_x_variant":[
        "\uc11c\ubd80\uc2e4",
        "S\u014fbusil"
    ],
    "wof:name":"Sobusil",
    "wof:placetype":"locality"
},
  "geometry": {"coordinates":[128.34141,35.1809],"type":"Point"}
}