{
  "type": "Feature",
  "properties": {
    "gn:admin1_code":"16.0",
    "gn:asciiname":"Mallisong",
    "gn:country_code":"KR",
    "gn:dem":5,
    "gn:feature_class":"P",
    "gn:feature_code":"PPL",
    "gn:name":"Mallis\u014fng",
    "gn:population":0,
    "gn:timezone":"Asia/Seoul",
    "iso:country":"KR",
    "name:kor_x_preferred":[
        "\uc791\uc740\ub9e4"
    ],
    "name:kor_x_variant":[
        "Mallis\u014fng"
    ],
    "wof:name":"Mallisong",
    "wof:placetype":"locality"
},
  "geometry": {"coordinates":[126.96889,34.47833],"type":"Point"}
}