{
  "type": "Feature",
  "properties": {
    "gn:admin1_code":"14.0",
    "gn:asciiname":"Pangsan",
    "gn:country_code":"KR",
    "gn:dem":137,
    "gn:feature_class":"P",
    "gn:feature_code":"PPL",
    "gn:name":"Pangsan",
    "gn:population":0,
    "gn:timezone":"Asia/Seoul",
    "iso:country":"KR",
    "name:und_x_variant":[
        "\ubc29\uc0b0",
        "Pangsan"
    ],
    "wof:name":"Pangsan",
    "wof:placetype":"locality"
},
  "geometry": {"coordinates":[128.0291,36.0081],"type":"Point"}
}