{
  "type": "Feature",
  "properties": {
    "gn:admin1_code":"13.0",
    "gn:asciiname":"Yeodeolbami",
    "gn:country_code":"KR",
    "gn:dem":88,
    "gn:feature_class":"P",
    "gn:feature_code":"PPL",
    "gn:name":"Yeodeolbami",
    "gn:population":0,
    "gn:timezone":"Asia/Seoul",
    "iso:country":"KR",
    "name:kor_x_preferred":[
        "\uc5ec\ub35c\ubc24\uc774"
    ],
    "wof:name":"Yeodeolbami",
    "wof:placetype":"locality"
},
  "geometry": {"coordinates":[127.21778,37.75613],"type":"Point"}
}