{
  "type": "Feature",
  "properties": {
    "gn:admin1_code":"21.0",
    "gn:asciiname":"Neumne",
    "gn:country_code":"KR",
    "gn:dem":31,
    "gn:feature_class":"P",
    "gn:feature_code":"PPL",
    "gn:name":"Neumne",
    "gn:population":0,
    "gn:timezone":"Asia/Seoul",
    "iso:country":"KR",
    "name:kor_x_preferred":[
        "\ub2a0\ub124"
    ],
    "wof:name":"Neumne",
    "wof:placetype":"locality"
},
  "geometry": {"coordinates":[129.20003,35.573],"type":"Point"}
}