{
  "type": "Feature",
  "properties": {
    "gn:admin1_code":"10.0",
    "gn:asciiname":"Jomanpo",
    "gn:country_code":"KR",
    "gn:dem":3,
    "gn:feature_class":"P",
    "gn:feature_code":"PPL",
    "gn:name":"Jomanpo",
    "gn:population":0,
    "gn:timezone":"Asia/Seoul",
    "iso:country":"KR",
    "name:kor_x_preferred":[
        "\uc870\ub9cc\ud3ec"
    ],
    "wof:name":"Jomanpo",
    "wof:placetype":"locality"
},
  "geometry": {"coordinates":[128.89453999999998,35.1609],"type":"Point"}
}