{
  "type": "Feature",
  "properties": {
    "gn:admin1_code":"14.0",
    "gn:asciiname":"Okkye",
    "gn:country_code":"KR",
    "gn:dem":194,
    "gn:feature_class":"P",
    "gn:feature_code":"PPL",
    "gn:name":"Okkye",
    "gn:population":0,
    "gn:timezone":"Asia/Seoul",
    "iso:country":"KR",
    "name:und_x_variant":[
        "\uc625\uacc4"
    ],
    "wof:name":"Okkye",
    "wof:placetype":"locality"
},
  "geometry": {"coordinates":[128.13193999999999,35.99444000000001],"type":"Point"}
}