{
  "type": "Feature",
  "properties": {
    "gn:admin1_code":"17.0",
    "gn:asciiname":"Kama-gol",
    "gn:country_code":"KR",
    "gn:dem":15,
    "gn:feature_class":"P",
    "gn:feature_code":"PPL",
    "gn:name":"Kama-gol",
    "gn:population":0,
    "gn:timezone":"Asia/Seoul",
    "iso:country":"KR",
    "name:und_x_variant":[
        "\uac00\ub9c8\uace8",
        "Kama-gol"
    ],
    "wof:name":"Kama-gol",
    "wof:placetype":"locality"
},
  "geometry": {"coordinates":[126.98139999999999,36.3879],"type":"Point"}
}