{
  "type": "Feature",
  "properties": {
    "gn:admin1_code":"13.0",
    "gn:asciiname":"Sangchon",
    "gn:country_code":"KR",
    "gn:dem":150,
    "gn:feature_class":"P",
    "gn:feature_code":"PPL",
    "gn:name":"Sangchon",
    "gn:population":0,
    "gn:timezone":"Asia/Seoul",
    "iso:country":"KR",
    "name:kor_x_preferred":[
        "\uc0c1\ucd0c"
    ],
    "name:kor_x_variant":[
        "Sang-ch\u2019on"
    ],
    "wof:name":"Sangchon",
    "wof:placetype":"locality"
},
  "geometry": {"coordinates":[127.50246,37.64357],"type":"Point"}
}