{
  "type": "Feature",
  "properties": {
    "gn:admin1_code":"6.0",
    "gn:asciiname":"Sae-gol",
    "gn:country_code":"KR",
    "gn:dem":479,
    "gn:feature_class":"P",
    "gn:feature_code":"PPL",
    "gn:name":"Sae-gol",
    "gn:population":0,
    "gn:timezone":"Asia/Seoul",
    "iso:country":"KR",
    "name:kor_x_preferred":[
        "\uc0c8\uace8"
    ],
    "wof:name":"Sae-gol",
    "wof:placetype":"locality"
},
  "geometry": {"coordinates":[128.67563999999999,37.22103],"type":"Point"}
}