{
  "type": "Feature",
  "properties": {
    "gn:admin1_code":"13.0",
    "gn:asciiname":"Neunganmal",
    "gn:country_code":"KR",
    "gn:dem":70,
    "gn:feature_class":"P",
    "gn:feature_code":"PPL",
    "gn:name":"Neunganmal",
    "gn:population":0,
    "gn:timezone":"Asia/Seoul",
    "iso:country":"KR",
    "name:kor_x_preferred":[
        "\ub2a5\uc548\ub9d0"
    ],
    "wof:name":"Neunganmal",
    "wof:placetype":"locality"
},
  "geometry": {"coordinates":[127.10597,37.73235],"type":"Point"}
}