{
  "type": "Feature",
  "properties": {
    "gn:admin1_code":"5.0",
    "gn:asciiname":"Togun",
    "gn:country_code":"KR",
    "gn:dem":108,
    "gn:feature_class":"P",
    "gn:feature_code":"PPL",
    "gn:name":"Tog\u016dn",
    "gn:population":0,
    "gn:timezone":"Asia/Seoul",
    "iso:country":"KR",
    "name:und_x_variant":[
        "\ub3c4\uadfc",
        "Tog\u016dn"
    ],
    "wof:name":"Togun",
    "wof:placetype":"locality"
},
  "geometry": {"coordinates":[127.6871,36.3601],"type":"Point"}
}