{
  "type": "Feature",
  "properties": {
    "gn:admin1_code":"20.0",
    "gn:asciiname":"Pongp'yong-ni",
    "gn:country_code":"KR",
    "gn:dem":160,
    "gn:feature_class":"P",
    "gn:feature_code":"PPL",
    "gn:name":"Pongp\u2019y\u014fng-ni",
    "gn:population":0,
    "gn:timezone":"Asia/Seoul",
    "iso:country":"KR",
    "wof:name":"Pongp'yong-ni",
    "wof:placetype":"locality"
},
  "geometry": {"coordinates":[128.41666999999998,34.81667],"type":"Point"}
}