{
  "type": "Feature",
  "properties": {
    "gn:admin1_code":"5.0",
    "gn:asciiname":"Uryeong",
    "gn:country_code":"KR",
    "gn:dem":107,
    "gn:feature_class":"P",
    "gn:feature_code":"PPL",
    "gn:name":"Uryeong",
    "gn:population":0,
    "gn:timezone":"Asia/Seoul",
    "iso:country":"KR",
    "name:kor_x_preferred":[
        "\uc6b8\uc601"
    ],
    "wof:name":"Uryeong",
    "wof:placetype":"locality"
},
  "geometry": {"coordinates":[127.49347,37.00914],"type":"Point"}
}