{
  "type": "Feature",
  "properties": {
    "gn:admin1_code":"6.0",
    "gn:asciiname":"Binjagol",
    "gn:country_code":"KR",
    "gn:dem":535,
    "gn:feature_class":"P",
    "gn:feature_code":"PPL",
    "gn:name":"Binjagol",
    "gn:population":0,
    "gn:timezone":"Asia/Seoul",
    "iso:country":"KR",
    "name:kor_x_preferred":[
        "\ube48\uc9c0\ub3d9"
    ],
    "name:kor_x_variant":[
        "\ube48\uc790\uace8"
    ],
    "name:und_x_variant":[
        "Pinji-dong",
        "Binjagol"
    ],
    "wof:name":"Binjagol",
    "wof:placetype":"locality"
},
  "geometry": {"coordinates":[128.51251999999999,37.91285],"type":"Point"}
}