{
  "type": "Feature",
  "properties": {
    "gn:admin1_code":"16.0",
    "gn:asciiname":"Yucheon",
    "gn:country_code":"KR",
    "gn:dem":167,
    "gn:feature_class":"P",
    "gn:feature_code":"PPL",
    "gn:name":"Yucheon",
    "gn:population":0,
    "gn:timezone":"Asia/Seoul",
    "iso:country":"KR",
    "name:kor_x_preferred":[
        "\uc720\ucd0c"
    ],
    "name:kor_x_variant":[
        "Yuch\u2019on",
        "\uc720\ucc9c"
    ],
    "wof:name":"Yucheon",
    "wof:placetype":"locality"
},
  "geometry": {"coordinates":[127.2282,34.87765],"type":"Point"}
}