{
  "type": "Feature",
  "properties": {
    "gn:admin1_code":"6.0",
    "gn:asciiname":"Chigyong-ni",
    "gn:country_code":"KR",
    "gn:dem":10,
    "gn:feature_class":"P",
    "gn:feature_code":"PPLL",
    "gn:name":"Chigy\u014fng-ni",
    "gn:population":0,
    "gn:timezone":"Asia/Seoul",
    "iso:country":"KR",
    "name:kor_x_preferred":[
        "\uc9c0\uacbd\ub9ac"
    ],
    "name:kor_x_variant":[
        "Chigy\u014fng-ni"
    ],
    "wof:name":"Chigyong-ni",
    "wof:placetype":"locality"
},
  "geometry": {"coordinates":[128.79910000000001,37.92027],"type":"Point"}
}