{
  "type": "Feature",
  "properties": {
    "gn:admin1_code":"13.0",
    "gn:asciiname":"Deokmokjae",
    "gn:country_code":"KR",
    "gn:dem":23,
    "gn:feature_class":"P",
    "gn:feature_code":"PPL",
    "gn:name":"Deokmokjae",
    "gn:population":0,
    "gn:timezone":"Asia/Seoul",
    "iso:country":"KR",
    "name:kor_x_preferred":[
        "\ub355\ubaa9\uc7ac"
    ],
    "wof:name":"Deokmokjae",
    "wof:placetype":"locality"
},
  "geometry": {"coordinates":[126.63616,37.72522],"type":"Point"}
}