{
  "type": "Feature",
  "properties": {
    "gn:admin1_code":"14.0",
    "gn:asciiname":"Araenmunbawi",
    "gn:country_code":"KR",
    "gn:dem":122,
    "gn:feature_class":"P",
    "gn:feature_code":"PPL",
    "gn:name":"Araenmunbawi",
    "gn:population":0,
    "gn:timezone":"Asia/Seoul",
    "iso:country":"KR",
    "name:kor_x_preferred":[
        "\uc544\ub7ab\ubb38\ubc14\uc704"
    ],
    "wof:name":"Araenmunbawi",
    "wof:placetype":"locality"
},
  "geometry": {"coordinates":[128.52663000000001,36.66277],"type":"Point"}
}