{
  "type": "Feature",
  "properties": {
    "gn:admin1_code":"16.0",
    "gn:asciiname":"Kurim-ni",
    "gn:cc2":"KR",
    "gn:country_code":"KR",
    "gn:dem":4,
    "gn:feature_class":"P",
    "gn:feature_code":"PPL",
    "gn:name":"Kurim-ni",
    "gn:population":0,
    "gn:timezone":"Asia/Seoul",
    "iso:country":"KR",
    "name:und_x_variant":[
        "Ky\u016brin-ri",
        "Kurim",
        "Kurim-ni"
    ],
    "wof:name":"Kurim-ni",
    "wof:placetype":"locality"
},
  "geometry": {"coordinates":[125.93444,34.76861],"type":"Point"}
}