{
  "type": "Feature",
  "properties": {
    "gn:admin1_code":"6.0",
    "gn:asciiname":"Musit'o",
    "gn:country_code":"KR",
    "gn:dem":621,
    "gn:feature_class":"P",
    "gn:feature_code":"PPL",
    "gn:name":"Musit\u2019\u014f",
    "gn:population":0,
    "gn:timezone":"Asia/Seoul",
    "iso:country":"KR",
    "name:und_x_variant":[
        "\ubb34\uc2dc\ud130",
        "Musit\u2019\u014f"
    ],
    "wof:name":"Musit'o",
    "wof:placetype":"locality"
},
  "geometry": {"coordinates":[129.07589999999999,37.2379],"type":"Point"}
}