{
  "type": "Feature",
  "properties": {
    "gn:admin1_code":"13.0",
    "gn:asciiname":"Jungteokgol",
    "gn:country_code":"KR",
    "gn:dem":43,
    "gn:feature_class":"P",
    "gn:feature_code":"PPL",
    "gn:name":"Jungteokgol",
    "gn:population":0,
    "gn:timezone":"Asia/Seoul",
    "iso:country":"KR",
    "name:kor_x_preferred":[
        "\uc911\ud131\uace8"
    ],
    "name:und_x_variant":[
        "Jungteokgol"
    ],
    "wof:name":"Jungteokgol",
    "wof:placetype":"locality"
},
  "geometry": {"coordinates":[127.2277,37.5254],"type":"Point"}
}