{
  "type": "Feature",
  "properties": {
    "gn:admin1_code":"14.0",
    "gn:asciiname":"Taengdaei",
    "gn:country_code":"KR",
    "gn:dem":442,
    "gn:feature_class":"P",
    "gn:feature_code":"PPL",
    "gn:name":"Taengdaei",
    "gn:population":0,
    "gn:timezone":"Asia/Seoul",
    "iso:country":"KR",
    "name:und_x_variant":[
        "\ub315\ub300\uc774",
        "Taengdaei"
    ],
    "wof:name":"Taengdaei",
    "wof:placetype":"locality"
},
  "geometry": {"coordinates":[129.11619999999999,36.4528],"type":"Point"}
}