{
  "type": "Feature",
  "properties": {
    "gn:admin1_code":"1.0",
    "gn:admin2_code":"Namjeju-gun",
    "gn:asciiname":"Musulpo",
    "gn:country_code":"KR",
    "gn:dem":9,
    "gn:feature_class":"P",
    "gn:feature_code":"PPL",
    "gn:name":"Musulpo",
    "gn:population":0,
    "gn:timezone":"Asia/Seoul",
    "iso:country":"KR",
    "name:und_x_variant":[
        "Momiruho",
        "Mohitsuho",
        "Boshippo",
        "Musulpo",
        "Mos\u016dlp\u2019o"
    ],
    "wof:name":"Musulpo",
    "wof:placetype":"locality"
},
  "geometry": {"coordinates":[126.25360999999999,33.22278],"type":"Point"}
}