{
  "type": "Feature",
  "properties": {
    "gn:admin1_code":"13.0",
    "gn:asciiname":"Neopheunjeori",
    "gn:country_code":"KR",
    "gn:dem":58,
    "gn:feature_class":"P",
    "gn:feature_code":"PPL",
    "gn:name":"Neopheunjeori",
    "gn:population":0,
    "gn:timezone":"Asia/Seoul",
    "iso:country":"KR",
    "name:und_x_variant":[
        "\ub119\ud754\uc808\uc774",
        "Neopheunjeori",
        "N\u014fph\u016dnj\u014fri"
    ],
    "wof:name":"Neopheunjeori",
    "wof:placetype":"locality"
},
  "geometry": {"coordinates":[127.52778000000001,37.30056],"type":"Point"}
}