{
  "type": "Feature",
  "properties": {
    "gn:admin1_code":"17.0",
    "gn:asciiname":"Hanojang",
    "gn:country_code":"KR",
    "gn:dem":47,
    "gn:feature_class":"P",
    "gn:feature_code":"PPL",
    "gn:name":"Hanojang",
    "gn:population":0,
    "gn:timezone":"Asia/Seoul",
    "iso:country":"KR",
    "name:kor_x_preferred":[
        "\ud558\ub178\uc7a5"
    ],
    "wof:name":"Hanojang",
    "wof:placetype":"locality"
},
  "geometry": {"coordinates":[127.26595,36.65565],"type":"Point"}
}