{
  "type": "Feature",
  "properties": {
    "gn:admin1_code":"5.0",
    "gn:asciiname":"Witbo",
    "gn:country_code":"KR",
    "gn:dem":256,
    "gn:feature_class":"P",
    "gn:feature_code":"PPL",
    "gn:name":"Witbo",
    "gn:population":0,
    "gn:timezone":"Asia/Seoul",
    "iso:country":"KR",
    "name:kor_x_preferred":[
        "\uc717\ubcf4"
    ],
    "wof:name":"Witbo",
    "wof:placetype":"locality"
},
  "geometry": {"coordinates":[128.01044999999999,36.75238],"type":"Point"}
}