{
  "type": "Feature",
  "properties": {
    "gn:admin1_code":"13.0",
    "gn:asciiname":"Jungbuheung",
    "gn:country_code":"KR",
    "gn:dem":15,
    "gn:feature_class":"P",
    "gn:feature_code":"PPL",
    "gn:name":"Jungbuheung",
    "gn:population":0,
    "gn:timezone":"Asia/Seoul",
    "iso:country":"KR",
    "name:und_x_variant":[
        "\uc911\ubd80\ud765",
        "Jungbuheung",
        "Chungbuh\u016dng"
    ],
    "wof:name":"Jungbuheung",
    "wof:placetype":"locality"
},
  "geometry": {"coordinates":[126.59139,37.22111],"type":"Point"}
}