{
  "type": "Feature",
  "properties": {
    "gn:admin1_code":"3.0",
    "gn:asciiname":"Songgok",
    "gn:country_code":"KR",
    "gn:dem":542,
    "gn:feature_class":"P",
    "gn:feature_code":"PPL",
    "gn:name":"S\u014fnggok",
    "gn:population":0,
    "gn:timezone":"Asia/Seoul",
    "iso:country":"KR",
    "name:und_x_variant":[
        "\uc131\uace1",
        "S\u014fnggok"
    ],
    "wof:name":"Songgok",
    "wof:placetype":"locality"
},
  "geometry": {"coordinates":[127.62352,35.68299000000001],"type":"Point"}
}