{
  "type": "Feature",
  "properties": {
    "gn:admin1_code":"16.0",
    "gn:asciiname":"Namho",
    "gn:country_code":"KR",
    "gn:dem":45,
    "gn:feature_class":"P",
    "gn:feature_code":"PPL",
    "gn:name":"Namho",
    "gn:population":0,
    "gn:timezone":"Asia/Seoul",
    "iso:country":"KR",
    "name:kor_x_preferred":[
        "\ub0a8\ud638"
    ],
    "name:und_x_variant":[
        "Namho-ri",
        "Nanko",
        "Namho"
    ],
    "wof:name":"Namho",
    "wof:placetype":"locality"
},
  "geometry": {"coordinates":[126.79333,34.47333],"type":"Point"}
}