{
  "type": "Feature",
  "properties": {
    "gn:admin1_code":"14.0",
    "gn:asciiname":"Korak",
    "gn:country_code":"KR",
    "gn:dem":55,
    "gn:feature_class":"P",
    "gn:feature_code":"PPL",
    "gn:name":"Korak",
    "gn:population":0,
    "gn:timezone":"Asia/Seoul",
    "iso:country":"KR",
    "name:und_x_variant":[
        "\uace0\ub77d",
        "Korak"
    ],
    "wof:name":"Korak",
    "wof:placetype":"locality"
},
  "geometry": {"coordinates":[128.37719999999999,36.4297],"type":"Point"}
}