{
  "type": "Feature",
  "properties": {
    "gn:admin1_code":"14.0",
    "gn:asciiname":"Banmalli",
    "gn:country_code":"KR",
    "gn:dem":28,
    "gn:feature_class":"P",
    "gn:feature_code":"PPL",
    "gn:name":"Banmalli",
    "gn:population":0,
    "gn:timezone":"Asia/Seoul",
    "iso:country":"KR",
    "name:kor_x_preferred":[
        "\ubc18\ub9cc\ub9ac"
    ],
    "wof:name":"Banmalli",
    "wof:placetype":"locality"
},
  "geometry": {"coordinates":[128.35638,35.89713],"type":"Point"}
}