{
  "type": "Feature",
  "properties": {
    "gn:admin1_code":"5.0",
    "gn:asciiname":"Norumegi",
    "gn:country_code":"KR",
    "gn:dem":404,
    "gn:feature_class":"P",
    "gn:feature_code":"PPL",
    "gn:name":"Norumegi",
    "gn:population":0,
    "gn:timezone":"Asia/Seoul",
    "iso:country":"KR",
    "name:kor_x_preferred":[
        "\ub178\ub8e8\uba54\uae30"
    ],
    "wof:name":"Norumegi",
    "wof:placetype":"locality"
},
  "geometry": {"coordinates":[128.60019,37.07346],"type":"Point"}
}