{
  "type": "Feature",
  "properties": {
    "gn:admin1_code":"16.0",
    "gn:asciiname":"Taech'o-ri",
    "gn:country_code":"KR",
    "gn:dem":72,
    "gn:feature_class":"P",
    "gn:feature_code":"PPL",
    "gn:name":"Taech\u2019o-ri",
    "gn:population":0,
    "gn:timezone":"Asia/Seoul",
    "iso:country":"KR",
    "name:und_x_variant":[
        "Ch\u2019\u014fnch\u2019o-ri",
        "Taech\u2019o-ri"
    ],
    "wof:name":"Taech'o-ri",
    "wof:placetype":"locality"
},
  "geometry": {"coordinates":[125.83528,34.61278],"type":"Point"}
}