{
  "type": "Feature",
  "properties": {
    "gn:admin1_code":"5.0",
    "gn:asciiname":"Geotteori",
    "gn:country_code":"KR",
    "gn:dem":91,
    "gn:feature_class":"P",
    "gn:feature_code":"PPL",
    "gn:name":"Geotteori",
    "gn:population":0,
    "gn:timezone":"Asia/Seoul",
    "iso:country":"KR",
    "name:kor_x_preferred":[
        "\uac70\ub5a0\ub9ac"
    ],
    "name:und_x_variant":[
        "\uac83\ub2e4\ub9ac",
        "K\u014ftta-ri",
        "Geotteori"
    ],
    "wof:name":"Geotteori",
    "wof:placetype":"locality"
},
  "geometry": {"coordinates":[127.58301000000002,36.45295],"type":"Point"}
}