{
  "type": "Feature",
  "properties": {
    "gn:admin1_code":"5.0",
    "gn:asciiname":"Sindam",
    "gn:country_code":"KR",
    "gn:dem":269,
    "gn:feature_class":"P",
    "gn:feature_code":"PPL",
    "gn:name":"Sindam",
    "gn:population":0,
    "gn:timezone":"Asia/Seoul",
    "iso:country":"KR",
    "name:kor_x_preferred":[
        "\uc2e0\ub2f4"
    ],
    "wof:name":"Sindam",
    "wof:placetype":"locality"
},
  "geometry": {"coordinates":[128.00349,37.0674],"type":"Point"}
}