{
  "type": "Feature",
  "properties": {
    "gn:admin1_code":"16.0",
    "gn:asciiname":"Nabul-li",
    "gn:cc2":"KR",
    "gn:country_code":"KR",
    "gn:dem":5,
    "gn:feature_class":"P",
    "gn:feature_code":"PPL",
    "gn:name":"Nabul-li",
    "gn:population":0,
    "gn:timezone":"Asia/Seoul",
    "iso:country":"KR",
    "name:und_x_variant":[
        "Rabutsu-ri",
        "Nabul-li"
    ],
    "wof:name":"Nabul-li",
    "wof:placetype":"locality"
},
  "geometry": {"coordinates":[126.46666999999999,34.76667],"type":"Point"}
}