{
  "type": "Feature",
  "properties": {
    "gn:admin1_code":"3.0",
    "gn:asciiname":"Chaesil",
    "gn:country_code":"KR",
    "gn:dem":218,
    "gn:feature_class":"P",
    "gn:feature_code":"PPL",
    "gn:name":"Chaesil",
    "gn:population":0,
    "gn:timezone":"Asia/Seoul",
    "iso:country":"KR",
    "name:und_x_variant":[
        "\uc7ac\uc2e4",
        "Chaesil"
    ],
    "wof:name":"Chaesil",
    "wof:placetype":"locality"
},
  "geometry": {"coordinates":[127.3366,36.1147],"type":"Point"}
}