{
  "type": "Feature",
  "properties": {
    "gn:admin1_code":"14.0",
    "gn:asciiname":"Pangji",
    "gn:country_code":"KR",
    "gn:dem":141,
    "gn:feature_class":"P",
    "gn:feature_code":"PPL",
    "gn:name":"Pangji",
    "gn:population":0,
    "gn:timezone":"Asia/Seoul",
    "iso:country":"KR",
    "name:und_x_variant":[
        "Pangji-dong",
        "\ubc29\uc9c0",
        "Pangji"
    ],
    "wof:name":"Pangji",
    "wof:placetype":"locality"
},
  "geometry": {"coordinates":[128.59514999999999,35.67805],"type":"Point"}
}