{
  "type": "Feature",
  "properties": {
    "gn:admin1_code":"5.0",
    "gn:asciiname":"Jeongmunantteum",
    "gn:country_code":"KR",
    "gn:dem":42,
    "gn:feature_class":"P",
    "gn:feature_code":"PPL",
    "gn:name":"Jeongmunantteum",
    "gn:population":0,
    "gn:timezone":"Asia/Seoul",
    "iso:country":"KR",
    "name:kor_x_preferred":[
        "\uc815\ubb38\uc548\ub738"
    ],
    "wof:name":"Jeongmunantteum",
    "wof:placetype":"locality"
},
  "geometry": {"coordinates":[127.36545,36.6134],"type":"Point"}
}