{
  "type": "Feature",
  "properties": {
    "gn:admin1_code":"14.0",
    "gn:asciiname":"Sonyu-dong",
    "gn:country_code":"KR",
    "gn:dem":308,
    "gn:feature_class":"P",
    "gn:feature_code":"PPL",
    "gn:name":"S\u014fnyu-dong",
    "gn:population":0,
    "gn:timezone":"Asia/Seoul",
    "iso:country":"KR",
    "name:und_x_variant":[
        "\uc120\uc720\ub3d9",
        "S\u014fnyu-dong"
    ],
    "wof:name":"Sonyu-dong",
    "wof:placetype":"locality"
},
  "geometry": {"coordinates":[127.98739999999999,36.3552],"type":"Point"}
}