{
  "type": "Feature",
  "properties": {
    "gn:admin1_code":"14.0",
    "gn:asciiname":"Eosa",
    "gn:country_code":"KR",
    "gn:dem":185,
    "gn:feature_class":"P",
    "gn:feature_code":"PPL",
    "gn:name":"Eosa",
    "gn:population":0,
    "gn:timezone":"Asia/Seoul",
    "iso:country":"KR",
    "name:kor_x_preferred":[
        "\uc5b4\uc0ac"
    ],
    "wof:name":"Eosa",
    "wof:placetype":"locality"
},
  "geometry": {"coordinates":[128.96778999999998,36.54989000000001],"type":"Point"}
}