{
  "type": "Feature",
  "properties": {
    "gn:admin1_code":"13.0",
    "gn:asciiname":"Karumae",
    "gn:country_code":"KR",
    "gn:dem":90,
    "gn:feature_class":"P",
    "gn:feature_code":"PPL",
    "gn:name":"Karumae",
    "gn:population":0,
    "gn:timezone":"Asia/Seoul",
    "iso:country":"KR",
    "name:und_x_variant":[
        "\uac00\ub8e8\ub9e4",
        "Garumae"
    ],
    "wof:name":"Karumae",
    "wof:placetype":"locality"
},
  "geometry": {"coordinates":[127.6275,37.44111],"type":"Point"}
}