{
  "type": "Feature",
  "properties": {
    "gn:admin1_code":"17.0",
    "gn:asciiname":"Yonipp'i",
    "gn:country_code":"KR",
    "gn:dem":46,
    "gn:feature_class":"P",
    "gn:feature_code":"PPL",
    "gn:name":"Y\u014fnipp\u2019i",
    "gn:population":0,
    "gn:timezone":"Asia/Seoul",
    "iso:country":"KR",
    "name:und_x_variant":[
        "\uc5f0\uc785\ud53c",
        "Y\u014fnipp\u2019i"
    ],
    "wof:name":"Yonipp'i",
    "wof:placetype":"locality"
},
  "geometry": {"coordinates":[126.6506,36.6284],"type":"Point"}
}