{
  "type": "Feature",
  "properties": {
    "gn:admin1_code":"13.0",
    "gn:asciiname":"Chigum-dong",
    "gn:country_code":"KR",
    "gn:dem":97,
    "gn:feature_class":"P",
    "gn:feature_code":"PPL",
    "gn:name":"Chig\u016dm-dong",
    "gn:population":0,
    "gn:timezone":"Asia/Seoul",
    "iso:country":"KR",
    "name:kor_x_preferred":[
        "\uc9c0\uae08\ub3d9"
    ],
    "name:und_x_variant":[
        "Chig\u016dm-dong"
    ],
    "wof:name":"Chigum-dong",
    "wof:placetype":"locality"
},
  "geometry": {"coordinates":[127.16735,37.60371],"type":"Point"}
}