{
  "type": "Feature",
  "properties": {
    "gn:admin1_code":"1.0",
    "gn:asciiname":"Dogeunnae",
    "gn:country_code":"KR",
    "gn:dem":12,
    "gn:feature_class":"P",
    "gn:feature_code":"PPL",
    "gn:name":"Dogeunnae",
    "gn:population":0,
    "gn:timezone":"Asia/Seoul",
    "iso:country":"KR",
    "name:kor_x_preferred":[
        "\ub3c4\uadfc\ub0b4"
    ],
    "name:und_x_variant":[
        "Tog\u016dnnae"
    ],
    "wof:name":"Dogeunnae",
    "wof:placetype":"locality"
},
  "geometry": {"coordinates":[126.44259,33.49397],"type":"Point"}
}