{
  "type": "Feature",
  "properties": {
    "iso:country":"KR",
    "name:eng_x_preferred":[
        "Seonbu 3(sam)-dong"
    ],
    "name:kor_x_preferred":[
        "\uc120\ubd803\ub3d9"
    ],
    "qs:name":"\uc120\ubd803\ub3d9",
    "qs:name_adm0":"\ud55c\uad6d",
    "qs:name_adm1":"\uacbd\uae30\ub3c4",
    "qs:photos":42,
    "qs:photos_1k":9,
    "qs:photos_9k":1,
    "qs:photos_9r":2,
    "qs:photos_all":42,
    "qs:photos_sr":2,
    "qs:placetype":"Suburb",
    "qs:pop_sr":"0",
    "wof:name":"Seonbu 3(sam)-dong",
    "wof:placetype":"neighbourhood"
},
  "geometry": {"coordinates":[127.46778,37.12417],"type":"Point"}
}