{
  "type": "Feature",
  "properties": {
    "gn:admin1_code":"16.0",
    "gn:admin2_code":"Chindo-gun",
    "gn:asciiname":"Orijong",
    "gn:country_code":"KR",
    "gn:dem":21,
    "gn:feature_class":"P",
    "gn:feature_code":"PPL",
    "gn:name":"Orij\u014fng",
    "gn:population":0,
    "gn:timezone":"Asia/Seoul",
    "iso:country":"KR",
    "wof:name":"Orijong",
    "wof:placetype":"locality"
},
  "geometry": {"coordinates":[126.27443999999998,34.48056],"type":"Point"}
}