{
  "type": "Feature",
  "properties": {
    "gn:admin1_code":"21.0",
    "gn:asciiname":"Songnakgol",
    "gn:country_code":"KR",
    "gn:dem":156,
    "gn:feature_class":"P",
    "gn:feature_code":"PPL",
    "gn:name":"Songnakgol",
    "gn:population":0,
    "gn:timezone":"Asia/Seoul",
    "iso:country":"KR",
    "name:kor_x_preferred":[
        "\uc1a1\ub77d\uace8"
    ],
    "wof:name":"Songnakgol",
    "wof:placetype":"locality"
},
  "geometry": {"coordinates":[129.09795,35.59841],"type":"Point"}
}