{
  "type": "Feature",
  "properties": {
    "gn:admin1_code":"6.0",
    "gn:asciiname":"Naegok",
    "gn:country_code":"KR",
    "gn:dem":38,
    "gn:feature_class":"P",
    "gn:feature_code":"PPL",
    "gn:name":"Naegok",
    "gn:population":0,
    "gn:timezone":"Asia/Seoul",
    "iso:country":"KR",
    "name:kor_x_preferred":[
        "\ub0b4\uace1"
    ],
    "wof:name":"Naegok",
    "wof:placetype":"locality"
},
  "geometry": {"coordinates":[128.87756000000002,37.73533],"type":"Point"}
}