{
  "type": "Feature",
  "properties": {
    "gn:admin1_code":"11.0",
    "gn:asciiname":"Ch'ongp'a-dong",
    "gn:country_code":"KR",
    "gn:dem":60,
    "gn:feature_class":"P",
    "gn:feature_code":"PPL",
    "gn:name":"Ch\u2019\u014fngp\u2019a-dong",
    "gn:population":0,
    "gn:timezone":"Asia/Seoul",
    "iso:country":"KR",
    "name:und_x_variant":[
        "\uccad\ud30c\ub3d9",
        "Ch\u2019\u014fngp\u2019a-dong"
    ],
    "wof:name":"Ch'ongp'a-dong",
    "wof:placetype":"locality"
},
  "geometry": {"coordinates":[126.9663,37.548],"type":"Point"}
}