{
  "type": "Feature",
  "properties": {
    "gn:admin1_code":"19.0",
    "gn:asciiname":"Madul",
    "gn:country_code":"KR",
    "gn:dem":95,
    "gn:feature_class":"P",
    "gn:feature_code":"PPL",
    "gn:name":"Mad\u016dl",
    "gn:population":0,
    "gn:timezone":"Asia/Seoul",
    "iso:country":"KR",
    "name:und_x_variant":[
        "\ub9c8\ub4e4",
        "Mad\u016dl"
    ],
    "wof:name":"Madul",
    "wof:placetype":"locality"
},
  "geometry": {"coordinates":[127.4761,36.4094],"type":"Point"}
}