{
  "type": "Feature",
  "properties": {
    "gn:admin1_code":"3.0",
    "gn:asciiname":"Koch'ang-ni",
    "gn:country_code":"KR",
    "gn:dem":249,
    "gn:feature_class":"P",
    "gn:feature_code":"PPL",
    "gn:name":"Koch\u2019ang-ni",
    "gn:population":0,
    "gn:timezone":"Asia/Seoul",
    "iso:country":"KR",
    "name:und_x_variant":[
        "Koch\u2019ang",
        "\uace0\ucc3d\ub9ac",
        "Koch\u2019ang-ni"
    ],
    "wof:name":"Koch'ang-ni",
    "wof:placetype":"locality"
},
  "geometry": {"coordinates":[127.56856000000001,35.94313],"type":"Point"}
}