{
  "type": "Feature",
  "properties": {
    "gn:admin1_code":"20.0",
    "gn:asciiname":"Chongsong-dong",
    "gn:cc2":"KR",
    "gn:country_code":"KR",
    "gn:dem":30,
    "gn:feature_class":"P",
    "gn:feature_code":"PPL",
    "gn:name":"Ch\u014fngs\u014fng-dong",
    "gn:population":0,
    "gn:timezone":"Asia/Seoul",
    "iso:country":"KR",
    "name:und_x_variant":[
        "Ch\u014fngs\u014fng-ni",
        "Ch\u014fngs\u014fng-dong"
    ],
    "wof:name":"Chongsong-dong",
    "wof:placetype":"locality"
},
  "geometry": {"coordinates":[128.12222,35.28556],"type":"Point"}
}