{
  "type": "Feature",
  "properties": {
    "gn:admin1_code":"17.0",
    "gn:asciiname":"Pongsong-ni",
    "gn:country_code":"KR",
    "gn:dem":89,
    "gn:feature_class":"P",
    "gn:feature_code":"PPL",
    "gn:name":"Pongs\u014fng-ni",
    "gn:population":0,
    "gn:timezone":"Asia/Seoul",
    "iso:country":"KR",
    "wof:name":"Pongsong-ni",
    "wof:placetype":"locality"
},
  "geometry": {"coordinates":[126.69167,36.23889000000001],"type":"Point"}
}