{
  "type": "Feature",
  "properties": {
    "gn:admin1_code":"5.0",
    "gn:asciiname":"Hagu-gol",
    "gn:country_code":"KR",
    "gn:dem":217,
    "gn:feature_class":"P",
    "gn:feature_code":"PPL",
    "gn:name":"Hagu-gol",
    "gn:population":0,
    "gn:timezone":"Asia/Seoul",
    "iso:country":"KR",
    "name:kor_x_preferred":[
        "\ud558\uad6c\uace8"
    ],
    "wof:name":"Hagu-gol",
    "wof:placetype":"locality"
},
  "geometry": {"coordinates":[128.10429999999999,37.0934],"type":"Point"}
}