{
  "type": "Feature",
  "properties": {
    "gn:admin1_code":"13.0",
    "gn:asciiname":"Maengganggol",
    "gn:country_code":"KR",
    "gn:dem":37,
    "gn:feature_class":"P",
    "gn:feature_code":"PPL",
    "gn:name":"Maengganggol",
    "gn:population":0,
    "gn:timezone":"Asia/Seoul",
    "iso:country":"KR",
    "name:kor_x_preferred":[
        "\ub9f9\uac15\uace8"
    ],
    "wof:name":"Maengganggol",
    "wof:placetype":"locality"
},
  "geometry": {"coordinates":[126.94304,37.99392],"type":"Point"}
}