{
  "type": "Feature",
  "properties": {
    "gn:admin1_code":"20.0",
    "gn:asciiname":"Hagaegum",
    "gn:country_code":"KR",
    "gn:dem":700,
    "gn:feature_class":"P",
    "gn:feature_code":"PPL",
    "gn:name":"Hagaeg\u016dm",
    "gn:population":0,
    "gn:timezone":"Asia/Seoul",
    "iso:country":"KR",
    "name:und_x_variant":[
        "\ud558\uac1c\uae08",
        "Hagaeg\u016dm"
    ],
    "wof:name":"Hagaegum",
    "wof:placetype":"locality"
},
  "geometry": {"coordinates":[128.06702000000001,35.82362],"type":"Point"}
}