{
  "type": "Feature",
  "properties": {
    "gn:admin1_code":"20.0",
    "gn:asciiname":"Su-dong",
    "gn:country_code":"KR",
    "gn:dem":138,
    "gn:feature_class":"P",
    "gn:feature_code":"PPL",
    "gn:name":"Su-dong",
    "gn:population":0,
    "gn:timezone":"Asia/Seoul",
    "iso:country":"KR",
    "name:und_x_variant":[
        "\uc218\ub3d9",
        "Su-dong"
    ],
    "wof:name":"Su-dong",
    "wof:placetype":"locality"
},
  "geometry": {"coordinates":[127.78888000000001,35.52160999999999],"type":"Point"}
}