{
  "type": "Feature",
  "properties": {
    "gn:admin1_code":"14.0",
    "gn:asciiname":"Chunggu-gol",
    "gn:country_code":"KR",
    "gn:dem":371,
    "gn:feature_class":"P",
    "gn:feature_code":"PPL",
    "gn:name":"Chunggu-gol",
    "gn:population":0,
    "gn:timezone":"Asia/Seoul",
    "iso:country":"KR",
    "name:und_x_variant":[
        "\uc911\uad6c\uace8",
        "Chunggu-gol"
    ],
    "wof:name":"Chunggu-gol",
    "wof:placetype":"locality"
},
  "geometry": {"coordinates":[129.0077,36.8008],"type":"Point"}
}