{
  "type": "Feature",
  "properties": {
    "gn:admin1_code":"13.0",
    "gn:asciiname":"Gwangseok-dong",
    "gn:country_code":"KR",
    "gn:dem":69,
    "gn:feature_class":"P",
    "gn:feature_code":"PPL",
    "gn:name":"Gwangseok-dong",
    "gn:population":0,
    "gn:timezone":"Asia/Seoul",
    "iso:country":"KR",
    "name:kor_x_preferred":[
        "\uad11\uc11d\ub3d9"
    ],
    "name:und_x_variant":[
        "Gwangseok-dong",
        "Kwangs\u014fk-tong"
    ],
    "wof:name":"Gwangseok-dong",
    "wof:placetype":"locality"
},
  "geometry": {"coordinates":[127.58111,37.26417],"type":"Point"}
}