{
  "type": "Feature",
  "properties": {
    "gn:admin1_code":"12.0",
    "gn:admin2_code":"Kanghwa-gun",
    "gn:asciiname":"Jongchon",
    "gn:country_code":"KR",
    "gn:dem":38,
    "gn:feature_class":"P",
    "gn:feature_code":"PPL",
    "gn:name":"Jongchon",
    "gn:population":0,
    "gn:timezone":"Asia/Seoul",
    "iso:country":"KR",
    "name:kor_x_preferred":[
        "\uc885\ucd0c"
    ],
    "name:kor_x_variant":[
        "Chong-ch\u2019on"
    ],
    "wof:name":"Jongchon",
    "wof:placetype":"locality"
},
  "geometry": {"coordinates":[126.43765999999999,37.78585],"type":"Point"}
}