{
  "type": "Feature",
  "properties": {
    "gn:admin1_code":"15.0",
    "gn:asciiname":"Wigwimyeong",
    "gn:country_code":"KR",
    "gn:dem":40,
    "gn:feature_class":"P",
    "gn:feature_code":"PPL",
    "gn:name":"Wigwimyeong",
    "gn:population":0,
    "gn:timezone":"Asia/Seoul",
    "iso:country":"KR",
    "name:kor_x_preferred":[
        "\uc704\uadc0\uba85"
    ],
    "name:kor_x_variant":[
        "Ukkwimy\u014fng"
    ],
    "wof:name":"Wigwimyeong",
    "wof:placetype":"locality"
},
  "geometry": {"coordinates":[128.56245000000001,35.93037],"type":"Point"}
}