{
  "type": "Feature",
  "properties": {
    "gn:admin1_code":"17.0",
    "gn:asciiname":"Sinsamgeori",
    "gn:country_code":"KR",
    "gn:dem":38,
    "gn:feature_class":"P",
    "gn:feature_code":"PPL",
    "gn:name":"Sinsamgeori",
    "gn:population":0,
    "gn:timezone":"Asia/Seoul",
    "iso:country":"KR",
    "name:kor_x_preferred":[
        "\uc2e0\uc0bc\uac70\ub9ac"
    ],
    "wof:name":"Sinsamgeori",
    "wof:placetype":"locality"
},
  "geometry": {"coordinates":[127.14924000000001,36.21005],"type":"Point"}
}