{
  "type": "Feature",
  "properties": {
    "gn:admin1_code":"3.0",
    "gn:asciiname":"Wonam",
    "gn:country_code":"KR",
    "gn:dem":104,
    "gn:feature_class":"P",
    "gn:feature_code":"PPL",
    "gn:name":"W\u014fnam",
    "gn:population":0,
    "gn:timezone":"Asia/Seoul",
    "iso:country":"KR",
    "name:und_x_variant":[
        "\uc6d0\uc554",
        "W\u014fnam"
    ],
    "wof:name":"Wonam",
    "wof:placetype":"locality"
},
  "geometry": {"coordinates":[127.26143999999999,35.87838],"type":"Point"}
}