{
  "type": "Feature",
  "properties": {
    "gn:admin1_code":"6.0",
    "gn:asciiname":"Chongjon",
    "gn:country_code":"KR",
    "gn:dem":72,
    "gn:feature_class":"P",
    "gn:feature_code":"PPL",
    "gn:name":"Chongj\u014fn",
    "gn:population":0,
    "gn:timezone":"Asia/Seoul",
    "iso:country":"KR",
    "name:und_x_variant":[
        "\uc885\uc804",
        "Chongj\u014fn"
    ],
    "wof:name":"Chongjon",
    "wof:placetype":"locality"
},
  "geometry": {"coordinates":[129.077,37.4425],"type":"Point"}
}