{
  "type": "Feature",
  "properties": {
    "gn:admin1_code":"6.0",
    "gn:asciiname":"To-ri",
    "gn:country_code":"KR",
    "gn:dem":86,
    "gn:feature_class":"P",
    "gn:feature_code":"PPL",
    "gn:name":"To-ri",
    "gn:population":0,
    "gn:timezone":"Asia/Seoul",
    "iso:country":"KR",
    "name:kor_x_preferred":[
        "\ub3c4\ub9ac"
    ],
    "wof:name":"To-ri",
    "wof:placetype":"locality"
},
  "geometry": {"coordinates":[128.63,38.00361],"type":"Point"}
}