{
  "type": "Feature",
  "properties": {
    "gn:admin1_code":"16.0",
    "gn:asciiname":"Worang",
    "gn:country_code":"KR",
    "gn:dem":43,
    "gn:feature_class":"P",
    "gn:feature_code":"PPL",
    "gn:name":"Worang",
    "gn:population":0,
    "gn:timezone":"Asia/Seoul",
    "iso:country":"KR",
    "name:kor_x_preferred":[
        "\uc6d4\uc559"
    ],
    "name:und_x_variant":[
        "W\u014frang"
    ],
    "wof:name":"Worang",
    "wof:placetype":"locality"
},
  "geometry": {"coordinates":[127.66718,34.7888],"type":"Point"}
}