{
  "type": "Feature",
  "properties": {
    "gn:admin1_code":"6.0",
    "gn:asciiname":"Gajokdong",
    "gn:country_code":"KR",
    "gn:dem":518,
    "gn:feature_class":"P",
    "gn:feature_code":"PPL",
    "gn:name":"Gajokdong",
    "gn:population":0,
    "gn:timezone":"Asia/Seoul",
    "iso:country":"KR",
    "name:kor_x_preferred":[
        "\uac00\uc871\ub3d9"
    ],
    "name:und_x_variant":[
        "Kajuk-tong",
        "Kajok-tong",
        "Gajokdong"
    ],
    "wof:name":"Gajokdong",
    "wof:placetype":"locality"
},
  "geometry": {"coordinates":[128.10314,37.85095],"type":"Point"}
}