{
  "type": "Feature",
  "properties": {
    "gn:admin1_code":"20.0",
    "gn:asciiname":"Pusuam",
    "gn:country_code":"KR",
    "gn:dem":35,
    "gn:feature_class":"P",
    "gn:feature_code":"PPL",
    "gn:name":"Pusuam",
    "gn:population":0,
    "gn:timezone":"Asia/Seoul",
    "iso:country":"KR",
    "name:und_x_variant":[
        "\ubd80\uc218\uc554",
        "Pusuam"
    ],
    "wof:name":"Pusuam",
    "wof:placetype":"locality"
},
  "geometry": {"coordinates":[128.31333999999998,34.99979],"type":"Point"}
}