{
  "type": "Feature",
  "properties": {
    "gn:admin1_code":"17.0",
    "gn:asciiname":"Haeng-dong",
    "gn:country_code":"KR",
    "gn:dem":129,
    "gn:feature_class":"P",
    "gn:feature_code":"PPL",
    "gn:name":"Haeng-dong",
    "gn:population":0,
    "gn:timezone":"Asia/Seoul",
    "iso:country":"KR",
    "name:und_x_variant":[
        "\ud589\ub3d9",
        "Haeng-dong"
    ],
    "wof:name":"Haeng-dong",
    "wof:placetype":"locality"
},
  "geometry": {"coordinates":[126.77079999999999,36.466],"type":"Point"}
}