{
  "type": "Feature",
  "properties": {
    "gn:admin1_code":"6.0",
    "gn:asciiname":"Swindonggol",
    "gn:country_code":"KR",
    "gn:dem":320,
    "gn:feature_class":"P",
    "gn:feature_code":"PPL",
    "gn:name":"Swindonggol",
    "gn:population":0,
    "gn:timezone":"Asia/Seoul",
    "iso:country":"KR",
    "name:und_x_variant":[
        "\uc270\ub3d9\uace8",
        "Swindonggol"
    ],
    "wof:name":"Swindonggol",
    "wof:placetype":"locality"
},
  "geometry": {"coordinates":[127.79216,37.80512],"type":"Point"}
}