{
  "type": "Feature",
  "properties": {
    "gn:admin1_code":"6.0",
    "gn:asciiname":"Tari-gol",
    "gn:country_code":"KR",
    "gn:dem":437,
    "gn:feature_class":"P",
    "gn:feature_code":"PPL",
    "gn:name":"Tari-gol",
    "gn:population":0,
    "gn:timezone":"Asia/Seoul",
    "iso:country":"KR",
    "name:kor_x_preferred":[
        "\ub2e4\ub9ac\uace8"
    ],
    "wof:name":"Tari-gol",
    "wof:placetype":"locality"
},
  "geometry": {"coordinates":[128.2431,37.6799],"type":"Point"}
}