{
  "type": "Feature",
  "properties": {
    "gn:admin1_code":"13.0",
    "gn:asciiname":"Bangjukmal",
    "gn:country_code":"KR",
    "gn:dem":80,
    "gn:feature_class":"P",
    "gn:feature_code":"PPL",
    "gn:name":"Bangjukmal",
    "gn:population":0,
    "gn:timezone":"Asia/Seoul",
    "iso:country":"KR",
    "name:kor_x_preferred":[
        "\ubc29\uc8fd\ub9d0"
    ],
    "name:und_x_variant":[
        "Pangjung-mal"
    ],
    "wof:name":"Bangjukmal",
    "wof:placetype":"locality"
},
  "geometry": {"coordinates":[127.64082999999999,37.15461],"type":"Point"}
}