{
  "type": "Feature",
  "properties": {
    "gn:admin1_code":"14.0",
    "gn:asciiname":"Jeorigol",
    "gn:country_code":"KR",
    "gn:dem":178,
    "gn:feature_class":"P",
    "gn:feature_code":"PPL",
    "gn:name":"Jeorigol",
    "gn:population":0,
    "gn:timezone":"Asia/Seoul",
    "iso:country":"KR",
    "name:kor_x_preferred":[
        "\uc800\ub9ac\uace8"
    ],
    "wof:name":"Jeorigol",
    "wof:placetype":"locality"
},
  "geometry": {"coordinates":[129.31047000000001,35.84699000000001],"type":"Point"}
}