{
  "type": "Feature",
  "properties": {
    "gn:admin1_code":"12.0",
    "gn:asciiname":"Yorae",
    "gn:country_code":"KR",
    "gn:dem":54,
    "gn:feature_class":"P",
    "gn:feature_code":"PPL",
    "gn:name":"Y\u014frae",
    "gn:population":0,
    "gn:timezone":"Asia/Seoul",
    "iso:country":"KR",
    "name:kor_x_preferred":[
        "\uc5ec\ub798"
    ],
    "name:kor_x_variant":[
        "Y\u014frae"
    ],
    "wof:name":"Yorae",
    "wof:placetype":"locality"
},
  "geometry": {"coordinates":[126.67083,37.61222],"type":"Point"}
}