{
  "type": "Feature",
  "properties": {
    "gn:admin1_code":"21.0",
    "gn:asciiname":"Seori",
    "gn:country_code":"KR",
    "gn:dem":133,
    "gn:feature_class":"P",
    "gn:feature_code":"PPL",
    "gn:name":"Seori",
    "gn:population":0,
    "gn:timezone":"Asia/Seoul",
    "iso:country":"KR",
    "name:kor_x_preferred":[
        "\uc11c\ub9ac"
    ],
    "wof:name":"Seori",
    "wof:placetype":"locality"
},
  "geometry": {"coordinates":[129.16341,35.46476],"type":"Point"}
}