{
  "type": "Feature",
  "properties": {
    "gn:admin1_code":"16.0",
    "gn:asciiname":"Yangsaem",
    "gn:country_code":"KR",
    "gn:dem":57,
    "gn:feature_class":"P",
    "gn:feature_code":"PPL",
    "gn:name":"Yangsaem",
    "gn:population":0,
    "gn:timezone":"Asia/Seoul",
    "iso:country":"KR",
    "name:kor_x_preferred":[
        "\uc591\uc0d8"
    ],
    "wof:name":"Yangsaem",
    "wof:placetype":"locality"
},
  "geometry": {"coordinates":[126.89726,35.28022],"type":"Point"}
}