{
  "type": "Feature",
  "properties": {
    "gn:admin1_code":"6.0",
    "gn:asciiname":"Jaegungdong",
    "gn:country_code":"KR",
    "gn:dem":32,
    "gn:feature_class":"P",
    "gn:feature_code":"PPL",
    "gn:name":"Jaegungdong",
    "gn:population":0,
    "gn:timezone":"Asia/Seoul",
    "iso:country":"KR",
    "name:kor_x_preferred":[
        "\uc7ac\uad81\ub3d9"
    ],
    "name:und_x_variant":[
        "Chaegung-dong",
        "Jaegungdong"
    ],
    "wof:name":"Jaegungdong",
    "wof:placetype":"locality"
},
  "geometry": {"coordinates":[128.77177,37.88299],"type":"Point"}
}