{
  "type": "Feature",
  "properties": {
    "gn:admin1_code":"1.0",
    "gn:asciiname":"Hadong",
    "gn:country_code":"KR",
    "gn:dem":7,
    "gn:feature_class":"P",
    "gn:feature_code":"PPL",
    "gn:name":"Hadong",
    "gn:population":0,
    "gn:timezone":"Asia/Seoul",
    "iso:country":"KR",
    "name:kor_x_preferred":[
        "\ud558\ub3d9"
    ],
    "wof:name":"Hadong",
    "wof:placetype":"locality"
},
  "geometry": {"coordinates":[126.30056999999999,33.44604],"type":"Point"}
}