{
  "type": "Feature",
  "properties": {
    "gn:admin1_code":"13.0",
    "gn:asciiname":"Okteogeo-ri",
    "gn:country_code":"KR",
    "gn:dem":80,
    "gn:feature_class":"P",
    "gn:feature_code":"PPL",
    "gn:name":"Okteogeo-ri",
    "gn:population":0,
    "gn:timezone":"Asia/Seoul",
    "iso:country":"KR",
    "name:und_x_variant":[
        "\uc625\ud130\uac70\ub9ac",
        "Okteogeo-ri",
        "Okt\u2019\u014fg\u014f-ri"
    ],
    "wof:name":"Okteogeo-ri",
    "wof:placetype":"locality"
},
  "geometry": {"coordinates":[127.625,37.40417],"type":"Point"}
}