{
  "type": "Feature",
  "properties": {
    "gn:admin1_code":"6.0",
    "gn:asciiname":"Sinheung Igu",
    "gn:country_code":"KR",
    "gn:dem":34,
    "gn:feature_class":"P",
    "gn:feature_code":"PPL",
    "gn:name":"Sinheung Igu",
    "gn:population":0,
    "gn:timezone":"Asia/Seoul",
    "iso:country":"KR",
    "name:kor_x_preferred":[
        "\uc2e0\ud765\uc774\uad6c"
    ],
    "name:kor_x_variant":[
        "\uc2e0\ud7652\uad6c"
    ],
    "name:und_x_variant":[
        "Sinheung 2 Gu"
    ],
    "wof:name":"Sinheung Igu",
    "wof:placetype":"locality"
},
  "geometry": {"coordinates":[128.54288,38.18968],"type":"Point"}
}