{
  "type": "Feature",
  "properties": {
    "gn:admin1_code":"14.0",
    "gn:asciiname":"Hunggak-tong",
    "gn:country_code":"KR",
    "gn:dem":74,
    "gn:feature_class":"P",
    "gn:feature_code":"PPL",
    "gn:name":"H\u016dnggak-tong",
    "gn:population":0,
    "gn:timezone":"Asia/Seoul",
    "iso:country":"KR",
    "name:eng_x_preferred":[
        "Hunggak"
    ],
    "name:eng_x_variant":[
        "Hunggak-tong"
    ],
    "name:und_x_variant":[
        "\ud765\uac01\ub3d9",
        "H\u016dnggak-tong"
    ],
    "wof:name":"Hunggak",
    "wof:placetype":"locality"
},
  "geometry": {"coordinates":[128.16560000000001,36.3822],"type":"Point"}
}