{
  "type": "Feature",
  "properties": {
    "gn:admin1_code":"5.0",
    "gn:asciiname":"Tungjeong",
    "gn:country_code":"KR",
    "gn:dem":107,
    "gn:feature_class":"P",
    "gn:feature_code":"PPL",
    "gn:name":"Tungjeong",
    "gn:population":0,
    "gn:timezone":"Asia/Seoul",
    "iso:country":"KR",
    "name:kor_x_preferred":[
        "\ud241\uc815"
    ],
    "name:kor_x_variant":[
        "\ud241\uc810"
    ],
    "name:und_x_variant":[
        "Tungjeom"
    ],
    "wof:name":"Tungjeong",
    "wof:placetype":"locality"
},
  "geometry": {"coordinates":[127.38652,36.75174000000001],"type":"Point"}
}