{
  "type": "Feature",
  "properties": {
    "gn:admin1_code":"5.0",
    "gn:asciiname":"Araetmaeul",
    "gn:country_code":"KR",
    "gn:dem":151,
    "gn:feature_class":"P",
    "gn:feature_code":"PPL",
    "gn:name":"Araetmaeul",
    "gn:population":0,
    "gn:timezone":"Asia/Seoul",
    "iso:country":"KR",
    "name:kor_x_preferred":[
        "\uc544\ub7ab\ub9c8\uc744"
    ],
    "wof:name":"Araetmaeul",
    "wof:placetype":"locality"
},
  "geometry": {"coordinates":[128.32181,36.96616],"type":"Point"}
}