{
  "type": "Feature",
  "properties": {
    "gn:admin1_code":"14.0",
    "gn:asciiname":"Okcheon",
    "gn:country_code":"KR",
    "gn:dem":140,
    "gn:feature_class":"P",
    "gn:feature_code":"PPL",
    "gn:name":"Okcheon",
    "gn:population":0,
    "gn:timezone":"Asia/Seoul",
    "iso:country":"KR",
    "name:kor_x_preferred":[
        "\uc625\ucc9c"
    ],
    "wof:name":"Okcheon",
    "wof:placetype":"locality"
},
  "geometry": {"coordinates":[128.55313999999998,36.70976],"type":"Point"}
}