{
  "type": "Feature",
  "properties": {
    "gn:admin1_code":"5.0",
    "gn:asciiname":"Yongsingi",
    "gn:country_code":"KR",
    "gn:dem":126,
    "gn:feature_class":"P",
    "gn:feature_code":"PPL",
    "gn:name":"Y\u014fngsingi",
    "gn:population":0,
    "gn:timezone":"Asia/Seoul",
    "iso:country":"KR",
    "name:und_x_variant":[
        "\uc601\uc2f1\uc774",
        "Y\u014fngsingi"
    ],
    "wof:name":"Yongsingi",
    "wof:placetype":"locality"
},
  "geometry": {"coordinates":[127.78570000000001,36.3245],"type":"Point"}
}