{
  "type": "Feature",
  "properties": {
    "gn:admin1_code":"6.0",
    "gn:asciiname":"Jageunseolmi",
    "gn:country_code":"KR",
    "gn:dem":158,
    "gn:feature_class":"P",
    "gn:feature_code":"PPL",
    "gn:name":"Jageunseolmi",
    "gn:population":0,
    "gn:timezone":"Asia/Seoul",
    "iso:country":"KR",
    "name:kor_x_preferred":[
        "\uc791\uc740\uc124\ubbf8"
    ],
    "wof:name":"Jageunseolmi",
    "wof:placetype":"locality"
},
  "geometry": {"coordinates":[127.69172,37.81103],"type":"Point"}
}