{
  "type": "Feature",
  "properties": {
    "gn:admin1_code":"11.0",
    "gn:asciiname":"Chamsiri-dong",
    "gn:country_code":"KR",
    "gn:dem":9,
    "gn:feature_class":"P",
    "gn:feature_code":"PPL",
    "gn:name":"Chamsiri-dong",
    "gn:population":0,
    "gn:timezone":"Asia/Seoul",
    "iso:country":"KR",
    "name:und_x_variant":[
        "\uc7a0\uc2e42\ub3d9",
        "Chamsiri-dong"
    ],
    "wof:name":"Chamsiri-dong",
    "wof:placetype":"locality"
},
  "geometry": {"coordinates":[127.08839,37.51848],"type":"Point"}
}