{
  "type": "Feature",
  "properties": {
    "gn:admin1_code":"5.0",
    "gn:asciiname":"Geonji",
    "gn:country_code":"KR",
    "gn:dem":234,
    "gn:feature_class":"P",
    "gn:feature_code":"PPL",
    "gn:name":"Geonji",
    "gn:population":0,
    "gn:timezone":"Asia/Seoul",
    "iso:country":"KR",
    "name:kor_x_preferred":[
        "\uac74\uc9c0"
    ],
    "name:kor_x_variant":[
        "K\u014fnji"
    ],
    "wof:name":"Geonji",
    "wof:placetype":"locality"
},
  "geometry": {"coordinates":[127.97841,37.01988],"type":"Point"}
}