{
  "type": "Feature",
  "properties": {
    "gn:admin1_code":"20.0",
    "gn:asciiname":"Pyokchon",
    "gn:country_code":"KR",
    "gn:dem":46,
    "gn:feature_class":"P",
    "gn:feature_code":"PPL",
    "gn:name":"Py\u014fkch\u014fn",
    "gn:population":0,
    "gn:timezone":"Asia/Seoul",
    "iso:country":"KR",
    "name:und_x_variant":[
        "\ubcbd\uc804",
        "Py\u014fkch\u014fn"
    ],
    "wof:name":"Pyokchon",
    "wof:placetype":"locality"
},
  "geometry": {"coordinates":[128.22006000000002,35.56740999999999],"type":"Point"}
}