{
  "type": "Feature",
  "properties": {
    "gn:admin1_code":"17.0",
    "gn:asciiname":"Changch'ok",
    "gn:country_code":"KR",
    "gn:dem":35,
    "gn:feature_class":"P",
    "gn:feature_code":"PPL",
    "gn:name":"Changch\u2019\u014fk",
    "gn:population":0,
    "gn:timezone":"Asia/Seoul",
    "iso:country":"KR",
    "name:und_x_variant":[
        "\uc7a5\ucc99",
        "Changch\u2019\u014fk"
    ],
    "wof:name":"Changch'ok",
    "wof:placetype":"locality"
},
  "geometry": {"coordinates":[126.6022,36.5015],"type":"Point"}
}