{
  "type": "Feature",
  "properties": {
    "gn:admin1_code":"6.0",
    "gn:asciiname":"Tungdae",
    "gn:country_code":"KR",
    "gn:dem":159,
    "gn:feature_class":"P",
    "gn:feature_code":"PPL",
    "gn:name":"T\u016dngdae",
    "gn:population":0,
    "gn:timezone":"Asia/Seoul",
    "iso:country":"KR",
    "name:kor_x_preferred":[
        "\ub4f1\ub300"
    ],
    "name:kor_x_variant":[
        "T\u016dngdae"
    ],
    "wof:name":"Tungdae",
    "wof:placetype":"locality"
},
  "geometry": {"coordinates":[127.93317999999999,37.67834000000001],"type":"Point"}
}