{
  "type": "Feature",
  "properties": {
    "gn:admin1_code":"6.0",
    "gn:asciiname":"Surijae",
    "gn:country_code":"KR",
    "gn:dem":487,
    "gn:feature_class":"P",
    "gn:feature_code":"PPL",
    "gn:name":"Surijae",
    "gn:population":0,
    "gn:timezone":"Asia/Seoul",
    "iso:country":"KR",
    "name:kor_x_preferred":[
        "\uc218\ub9ac\uc7ac"
    ],
    "wof:name":"Surijae",
    "wof:placetype":"locality"
},
  "geometry": {"coordinates":[128.48699999999999,37.3675],"type":"Point"}
}