{
  "type": "Feature",
  "properties": {
    "gn:admin1_code":"14.0",
    "gn:asciiname":"Araenmakhyeon",
    "gn:country_code":"KR",
    "gn:dem":173,
    "gn:feature_class":"P",
    "gn:feature_code":"PPL",
    "gn:name":"Araenmakhyeon",
    "gn:population":0,
    "gn:timezone":"Asia/Seoul",
    "iso:country":"KR",
    "name:kor_x_preferred":[
        "\uc544\ub7ab\ub9c9\ud604"
    ],
    "wof:name":"Araenmakhyeon",
    "wof:placetype":"locality"
},
  "geometry": {"coordinates":[128.63258999999999,36.75337],"type":"Point"}
}