{
  "type": "Feature",
  "properties": {
    "gn:admin1_code":"17.0",
    "gn:asciiname":"Chogaesan",
    "gn:country_code":"KR",
    "gn:dem":19,
    "gn:feature_class":"P",
    "gn:feature_code":"PPL",
    "gn:name":"Chogaesan",
    "gn:population":0,
    "gn:timezone":"Asia/Seoul",
    "iso:country":"KR",
    "name:und_x_variant":[
        "\uc870\uac1c\uc0b0",
        "Chogaesan"
    ],
    "wof:name":"Chogaesan",
    "wof:placetype":"locality"
},
  "geometry": {"coordinates":[126.3522,36.5048],"type":"Point"}
}