{
  "type": "Feature",
  "properties": {
    "gn:admin1_code":"17.0",
    "gn:asciiname":"Saewonjang",
    "gn:country_code":"KR",
    "gn:dem":4,
    "gn:feature_class":"P",
    "gn:feature_code":"PPL",
    "gn:name":"Saew\u014fnjang",
    "gn:population":0,
    "gn:timezone":"Asia/Seoul",
    "iso:country":"KR",
    "name:und_x_variant":[
        "\uc0c8\uc6d0\uc7a5",
        "Saew\u014fnjang"
    ],
    "wof:name":"Saewonjang",
    "wof:placetype":"locality"
},
  "geometry": {"coordinates":[126.84990000000001,36.7804],"type":"Point"}
}