{
  "type": "Feature",
  "properties": {
    "gn:admin1_code":"20.0",
    "gn:asciiname":"Tul-mal",
    "gn:country_code":"KR",
    "gn:dem":262,
    "gn:feature_class":"P",
    "gn:feature_code":"PPL",
    "gn:name":"T\u016dl-mal",
    "gn:population":0,
    "gn:timezone":"Asia/Seoul",
    "iso:country":"KR",
    "name:und_x_variant":[
        "\ub4e4\ub9d0",
        "T\u016dl-mal"
    ],
    "wof:name":"Tul-mal",
    "wof:placetype":"locality"
},
  "geometry": {"coordinates":[128.02213,35.69194],"type":"Point"}
}