{
  "type": "Feature",
  "properties": {
    "gn:admin1_code":"11.0",
    "gn:asciiname":"Ahyon-dong",
    "gn:country_code":"KR",
    "gn:dem":79,
    "gn:feature_class":"P",
    "gn:feature_code":"PPL",
    "gn:name":"Ahy\u014fn-dong",
    "gn:population":0,
    "gn:timezone":"Asia/Seoul",
    "iso:country":"KR",
    "name:und_x_variant":[
        "Ahy\u014fn-j\u014fng",
        "\uc544\ud604\ub3d9",
        "Ahy\u014fn-dong"
    ],
    "wof:name":"Ahyon-dong",
    "wof:placetype":"locality"
},
  "geometry": {"coordinates":[126.9507,37.5546],"type":"Point"}
}