{
  "type": "Feature",
  "properties": {
    "gn:admin1_code":"16.0",
    "gn:asciiname":"Simwon",
    "gn:country_code":"KR",
    "gn:dem":362,
    "gn:feature_class":"P",
    "gn:feature_code":"PPL",
    "gn:name":"Simw\u014fn",
    "gn:population":0,
    "gn:timezone":"Asia/Seoul",
    "iso:country":"KR",
    "wof:name":"Simwon",
    "wof:placetype":"locality"
},
  "geometry": {"coordinates":[127.59778,35.0875],"type":"Point"}
}