{
  "type": "Feature",
  "properties": {
    "gn:admin1_code":"20.0",
    "gn:asciiname":"T'aebu-ri",
    "gn:country_code":"KR",
    "gn:dem":70,
    "gn:feature_class":"P",
    "gn:feature_code":"PPL",
    "gn:name":"T\u2019aebu-ri",
    "gn:population":0,
    "gn:timezone":"Asia/Seoul",
    "iso:country":"KR",
    "name:und_x_variant":[
        "\ud0dc\ubd80\ub9ac",
        "T\u2019aebu",
        "T\u2019aebu-ri"
    ],
    "wof:name":"T'aebu-ri",
    "wof:placetype":"locality"
},
  "geometry": {"coordinates":[128.36098999999999,35.40361],"type":"Point"}
}