{
  "type": "Feature",
  "properties": {
    "gn:admin1_code":"17.0",
    "gn:asciiname":"Yut'ujong",
    "gn:country_code":"KR",
    "gn:dem":156,
    "gn:feature_class":"P",
    "gn:feature_code":"PPL",
    "gn:name":"Yut\u2019uj\u014fng",
    "gn:population":0,
    "gn:timezone":"Asia/Seoul",
    "iso:country":"KR",
    "name:und_x_variant":[
        "\uc720\ud22c\uc815",
        "Yut\u2019uj\u014fng"
    ],
    "wof:name":"Yut'ujong",
    "wof:placetype":"locality"
},
  "geometry": {"coordinates":[126.93380000000001,36.4632],"type":"Point"}
}