{
  "type": "Feature",
  "properties": {
    "gn:admin1_code":"13.0",
    "gn:admin2_code":"Yongin-si",
    "gn:asciiname":"Cheon-ri",
    "gn:country_code":"KR",
    "gn:dem":150,
    "gn:feature_class":"P",
    "gn:feature_code":"PPLL",
    "gn:name":"Cheon-ri",
    "gn:population":0,
    "gn:timezone":"Asia/Seoul",
    "iso:country":"KR",
    "name:kor_x_preferred":[
        "\ucc9c\ub9ac"
    ],
    "name:kor_x_variant":[
        "Ch\u2019\u014fn-ni",
        "Ch\u2019\u014fl-li"
    ],
    "wof:name":"Cheon-ri",
    "wof:placetype":"locality"
},
  "geometry": {"coordinates":[127.22221999999999,37.20222],"type":"Point"}
}