{
  "type": "Feature",
  "properties": {
    "gn:admin1_code":"5.0",
    "gn:asciiname":"Gomachang",
    "gn:country_code":"KR",
    "gn:dem":300,
    "gn:feature_class":"P",
    "gn:feature_code":"PPL",
    "gn:name":"Gomachang",
    "gn:population":0,
    "gn:timezone":"Asia/Seoul",
    "iso:country":"KR",
    "name:kor_x_preferred":[
        "\uace0\ub9c8\ucc3d"
    ],
    "name:kor_x_variant":[
        "Komach\u2019ang"
    ],
    "wof:name":"Gomachang",
    "wof:placetype":"locality"
},
  "geometry": {"coordinates":[128.23006000000001,37.07315],"type":"Point"}
}