{
  "type": "Feature",
  "properties": {
    "gn:admin1_code":"21.0",
    "gn:asciiname":"Murangol",
    "gn:country_code":"KR",
    "gn:dem":108,
    "gn:feature_class":"P",
    "gn:feature_code":"PPL",
    "gn:name":"Murangol",
    "gn:population":0,
    "gn:timezone":"Asia/Seoul",
    "iso:country":"KR",
    "name:kor_x_preferred":[
        "\ubb3c\uc548\uace8"
    ],
    "wof:name":"Murangol",
    "wof:placetype":"locality"
},
  "geometry": {"coordinates":[129.27139,35.38354],"type":"Point"}
}