{
  "type": "Feature",
  "properties": {
    "gn:admin1_code":"20.0",
    "gn:asciiname":"Taech'ong",
    "gn:country_code":"KR",
    "gn:dem":35,
    "gn:feature_class":"P",
    "gn:feature_code":"PPL",
    "gn:name":"Taech\u2019\u014fng",
    "gn:population":0,
    "gn:timezone":"Asia/Seoul",
    "iso:country":"KR",
    "name:und_x_variant":[
        "Taech\u2019\u014fng-dong",
        "\ub300\uccad",
        "Taech\u2019\u014fng"
    ],
    "wof:name":"Taech'ong",
    "wof:placetype":"locality"
},
  "geometry": {"coordinates":[128.38457,34.79373],"type":"Point"}
}