{
  "type": "Feature",
  "properties": {
    "gn:admin1_code":"6.0",
    "gn:asciiname":"Sarangmal",
    "gn:country_code":"KR",
    "gn:dem":314,
    "gn:feature_class":"P",
    "gn:feature_code":"PPL",
    "gn:name":"Sarangmal",
    "gn:population":0,
    "gn:timezone":"Asia/Seoul",
    "iso:country":"KR",
    "name:kor_x_preferred":[
        "\uc0ac\ub791\ub9d0"
    ],
    "wof:name":"Sarangmal",
    "wof:placetype":"locality"
},
  "geometry": {"coordinates":[127.84927999999999,37.81541],"type":"Point"}
}