{
  "type": "Feature",
  "properties": {
    "gn:admin1_code":"21.0",
    "gn:asciiname":"Oeyang",
    "gn:country_code":"KR",
    "gn:dem":72,
    "gn:feature_class":"P",
    "gn:feature_code":"PPL",
    "gn:name":"Oeyang",
    "gn:population":0,
    "gn:timezone":"Asia/Seoul",
    "iso:country":"KR",
    "name:kor_x_preferred":[
        "\uc678\uc591"
    ],
    "wof:name":"Oeyang",
    "wof:placetype":"locality"
},
  "geometry": {"coordinates":[129.13733999999999,35.50660999999999],"type":"Point"}
}