{
  "type": "Feature",
  "properties": {
    "gn:admin1_code":"20.0",
    "gn:asciiname":"Kun'gi",
    "gn:country_code":"KR",
    "gn:dem":96,
    "gn:feature_class":"P",
    "gn:feature_code":"PPL",
    "gn:name":"K\u016dn\u2019gi",
    "gn:population":0,
    "gn:timezone":"Asia/Seoul",
    "iso:country":"KR",
    "name:und_x_variant":[
        "\uadfc\uae30",
        "K\u016dn\u2019gi"
    ],
    "wof:name":"Kun'gi",
    "wof:placetype":"locality"
},
  "geometry": {"coordinates":[128.61855,35.54038],"type":"Point"}
}