{
  "type": "Feature",
  "properties": {
    "gn:admin1_code":"6.0",
    "gn:asciiname":"Beolmok",
    "gn:country_code":"KR",
    "gn:dem":531,
    "gn:feature_class":"P",
    "gn:feature_code":"PPL",
    "gn:name":"Beolmok",
    "gn:population":0,
    "gn:timezone":"Asia/Seoul",
    "iso:country":"KR",
    "name:kor_x_preferred":[
        "\ubc8c\ubaa9"
    ],
    "wof:name":"Beolmok",
    "wof:placetype":"locality"
},
  "geometry": {"coordinates":[128.31222,38.06199],"type":"Point"}
}