{
  "type": "Feature",
  "properties": {
    "gn:admin1_code":"0.0",
    "gn:asciiname":"Saegol",
    "gn:country_code":"KR",
    "gn:dem":106,
    "gn:feature_class":"P",
    "gn:feature_code":"PPL",
    "gn:name":"Saegol",
    "gn:population":0,
    "gn:timezone":"Asia/Seoul",
    "iso:country":"KR",
    "name:und_x_variant":[
        "\uc0c8\uace8",
        "Saegol"
    ],
    "wof:name":"Saegol",
    "wof:placetype":"locality"
},
  "geometry": {"coordinates":[127.29264000000001,36.22452],"type":"Point"}
}