{
  "type": "Feature",
  "properties": {
    "gn:admin1_code":"15.0",
    "gn:asciiname":"Chungdam",
    "gn:country_code":"KR",
    "gn:dem":55,
    "gn:feature_class":"P",
    "gn:feature_code":"PPL",
    "gn:name":"Chungdam",
    "gn:population":0,
    "gn:timezone":"Asia/Seoul",
    "iso:country":"KR",
    "name:und_x_variant":[
        "\uc911\ub2f4",
        "Chungdam"
    ],
    "wof:name":"Chungdam",
    "wof:placetype":"locality"
},
  "geometry": {"coordinates":[128.40254999999999,35.66882000000001],"type":"Point"}
}