{
  "type": "Feature",
  "properties": {
    "gn:admin1_code":"17.0",
    "gn:asciiname":"Kwangsi",
    "gn:country_code":"KR",
    "gn:dem":29,
    "gn:feature_class":"P",
    "gn:feature_code":"PPL",
    "gn:name":"Kwangsi",
    "gn:population":0,
    "gn:timezone":"Asia/Seoul",
    "iso:country":"KR",
    "name:und_x_variant":[
        "K\u2019\u016dn\u2019gwangsi",
        "\uad11\uc2dc",
        "Kwangsi-ri",
        "Kwangsi"
    ],
    "wof:name":"Kwangsi",
    "wof:placetype":"locality"
},
  "geometry": {"coordinates":[126.77549,36.54642],"type":"Point"}
}