{
  "type": "Feature",
  "properties": {
    "gn:admin1_code":"13.0",
    "gn:asciiname":"Oyakkol",
    "gn:country_code":"KR",
    "gn:dem":30,
    "gn:feature_class":"P",
    "gn:feature_code":"PPL",
    "gn:name":"Oyakkol",
    "gn:population":0,
    "gn:timezone":"Asia/Seoul",
    "iso:country":"KR",
    "name:kor_x_preferred":[
        "\uc624\uc58f\uace8"
    ],
    "wof:name":"Oyakkol",
    "wof:placetype":"locality"
},
  "geometry": {"coordinates":[126.68832999999999,37.18083],"type":"Point"}
}