{
  "type": "Feature",
  "properties": {
    "gn:admin1_code":"12.0",
    "gn:asciiname":"Minbeop",
    "gn:country_code":"KR",
    "gn:dem":16,
    "gn:feature_class":"P",
    "gn:feature_code":"PPL",
    "gn:name":"Minbeop",
    "gn:population":0,
    "gn:timezone":"Asia/Seoul",
    "iso:country":"KR",
    "name:kor_x_preferred":[
        "\ubbfc\ubc95"
    ],
    "name:und_x_variant":[
        "Mib\u014fm-ni",
        "\ubbf8\ubc95\ub9ac",
        "Mibeop-ri",
        "Minb\u014fp",
        "Minbeop"
    ],
    "wof:name":"Minbeop",
    "wof:placetype":"locality"
},
  "geometry": {"coordinates":[126.26517,37.72895],"type":"Point"}
}