{
  "type": "Feature",
  "properties": {
    "gn:admin1_code":"6.0",
    "gn:asciiname":"Tokp'o-ri",
    "gn:country_code":"KR",
    "gn:dem":277,
    "gn:feature_class":"P",
    "gn:feature_code":"PPLL",
    "gn:name":"T\u014fkp\u2019o-ri",
    "gn:population":0,
    "gn:timezone":"Asia/Seoul",
    "iso:country":"KR",
    "name:kor_x_preferred":[
        "\ub355\ud3ec\ub9ac"
    ],
    "name:kor_x_variant":[
        "T\u014fkp\u2019o-ri"
    ],
    "wof:name":"Tokp'o-ri",
    "wof:placetype":"locality"
},
  "geometry": {"coordinates":[128.49052,37.17706],"type":"Point"}
}