{
  "type": "Feature",
  "properties": {
    "gn:admin1_code":"6.0",
    "gn:asciiname":"Angol",
    "gn:country_code":"KR",
    "gn:dem":84,
    "gn:feature_class":"P",
    "gn:feature_code":"PPL",
    "gn:name":"Angol",
    "gn:population":0,
    "gn:timezone":"Asia/Seoul",
    "iso:country":"KR",
    "name:ang_x_preferred":[
        "Angol"
    ],
    "name:ara_x_preferred":[
        "\u0623\u0646\u062e\u0648\u0644"
    ],
    "name:arg_x_preferred":[
        "Angol"
    ],
    "name:ast_x_preferred":[
        "Angol"
    ],
    "name:aym_x_preferred":[
        "Angol"
    ],
    "name:aze_x_preferred":[
        "Angol"
    ],
    "name:ceb_x_preferred":[
        "Angol"
    ],
    "name:dan_x_preferred":[
        "Angol"
    ],
    "name:deu_x_preferred":[
        "Angol"
    ],
    "name:eus_x_preferred":[
        "Angol"
    ],
    "name:fas_x_preferred":[
        "\u0627\u0646\u06af\u0644"
    ],
    "name:fra_x_preferred":[
        "Angol"
    ],
    "name:frr_x_preferred":[
        "Angol"
    ],
    "name:glg_x_preferred":[
        "Angol"
    ],
    "name:grn_x_preferred":[
        "Angol"
    ],
    "name:hat_x_preferred":[
        "Angol"
    ],
    "name:hun_x_preferred":[
        "Angol"
    ],
    "name:ita_x_preferred":[
        "Angol"
    ],
    "name:jpn_x_preferred":[
        "\u30a2\u30f3\u30b4\u30eb"
    ],
    "name:kal_x_preferred":[
        "Angol"
    ],
    "name:kor_x_preferred":[
        "\uc548\uace8"
    ],
    "name:lad_x_preferred":[
        "Angol"
    ],
    "name:lit_x_preferred":[
        "Angolis"
    ],
    "name:nld_x_preferred":[
        "Angol"
    ],
    "name:nrm_x_preferred":[
        "Angol"
    ],
    "name:oci_x_preferred":[
        "Angol"
    ],
    "name:pol_x_preferred":[
        "Angol"
    ],
    "name:por_x_preferred":[
        "Angol"
    ],
    "name:que_x_preferred":[
        "Angol"
    ],
    "name:ron_x_preferred":[
        "Angol"
    ],
    "name:rus_x_preferred":[
        "\u0410\u043d\u0433\u043e\u043b\u044c"
    ],
    "name:spa_x_preferred":[
        "Angol"
    ],
    "name:srp_x_preferred":[
        "\u0410\u043d\u0433\u043e\u043b"
    ],
    "name:swe_x_preferred":[
        "Angol"
    ],
    "name:tur_x_preferred":[
        "Angol"
    ],
    "name:vol_x_preferred":[
        "Angol"
    ],
    "name:war_x_preferred":[
        "Angol"
    ],
    "name:zho_x_preferred":[
        "\u5b89\u6208\u723e"
    ],
    "wof:name":"Angol",
    "wof:placetype":"locality"
},
  "geometry": {"coordinates":[127.75354,37.93866],"type":"Point"}
}