{
  "type": "Feature",
  "properties": {
    "iso:country":"KR",
    "name:ara_x_preferred":[
        "\u0645\u062d\u0627\u0641\u0638\u0629 \u064a\u062a\u0634\u0648\u0646"
    ],
    "name:ceb_x_preferred":[
        "Yecheon-gun"
    ],
    "name:cym_x_preferred":[
        "Sir Yecheon"
    ],
    "name:deu_x_preferred":[
        "Yecheon"
    ],
    "name:eng_x_preferred":[
        "Yecheon County"
    ],
    "name:fas_x_preferred":[
        "\u06cc\u0686\u0626\u0648\u0646"
    ],
    "name:frr_x_preferred":[
        "Yecheon"
    ],
    "name:ita_x_preferred":[
        "Yecheon"
    ],
    "name:jpn_x_preferred":[
        "\u91b4\u6cc9\u90e1"
    ],
    "name:kor_x_preferred":[
        "\uc608\ucc9c\uad70"
    ],
    "name:mon_x_preferred":[
        "\u0415\u0447\u043e\u043d\u044c-\u0433\u04af\u043d\u044c"
    ],
    "name:nan_x_preferred":[
        "Yecheon K\u016bn"
    ],
    "name:nld_x_preferred":[
        "Yecheon County"
    ],
    "name:nob_x_preferred":[
        "Yecheon"
    ],
    "name:rus_x_preferred":[
        "\u0419\u0435\u0447\u0445\u043e\u043d"
    ],
    "name:spa_x_preferred":[
        "Yecheon"
    ],
    "name:swe_x_preferred":[
        "Yecheon"
    ],
    "name:urd_x_preferred":[
        "\u06cc\u0686\u06cc\u0648\u0646 \u06a9\u0627\u0624\u0646\u0679\u06cc"
    ],
    "name:vie_x_preferred":[
        "Yecheon"
    ],
    "name:yue_x_preferred":[
        "\u91b4\u6cc9\u90e1"
    ],
    "name:zho_x_preferred":[
        "\u91b4\u6cc9\u90e1"
    ],
    "qs:name":"\uac10\ucc9c\uba74",
    "qs:name_adm0":"\ud55c\uad6d",
    "qs:name_adm1":"\uacbd\uc0c1\ubd81\ub3c4",
    "qs:photos":1,
    "qs:photos_1k":1,
    "qs:photos_9k":1,
    "qs:photos_9r":1,
    "qs:photos_all":1,
    "qs:photos_sr":1,
    "qs:placetype":"LocalAdmin",
    "qs:pop_sr":"0",
    "wd:wordcount":732,
    "wof:name":"\uac10\ucc9c\uba74",
    "wof:placetype":"localadmin"
},
  "geometry": {"coordinates":[128.10822400000001,36.115551],"type":"Point"}
}