{
  "type": "Feature",
  "properties": {
    "gn:admin1_code":"20.0",
    "gn:asciiname":"Mangdeok",
    "gn:country_code":"KR",
    "gn:dem":6,
    "gn:feature_class":"P",
    "gn:feature_code":"PPL",
    "gn:name":"Mangdeok",
    "gn:population":0,
    "gn:timezone":"Asia/Seoul",
    "iso:country":"KR",
    "name:kor_x_preferred":[
        "\ub9dd\ub355"
    ],
    "wof:name":"Mangdeok",
    "wof:placetype":"locality"
},
  "geometry": {"coordinates":[128.8312,35.22156],"type":"Point"}
}