{
  "type": "Feature",
  "properties": {
    "gn:admin1_code":"20.0",
    "gn:asciiname":"Ko-ch'on",
    "gn:country_code":"KR",
    "gn:dem":282,
    "gn:feature_class":"P",
    "gn:feature_code":"PPL",
    "gn:name":"Ko-ch\u2019on",
    "gn:population":0,
    "gn:timezone":"Asia/Seoul",
    "iso:country":"KR",
    "name:und_x_variant":[
        "\uace0\ucd0c",
        "Ko-ch\u2019on"
    ],
    "wof:name":"Ko-ch'on",
    "wof:placetype":"locality"
},
  "geometry": {"coordinates":[127.85878999999998,35.54481],"type":"Point"}
}