{
  "type": "Feature",
  "properties": {
    "gn:admin1_code":"13.0",
    "gn:asciiname":"Yeougumeongppuri",
    "gn:country_code":"KR",
    "gn:dem":5,
    "gn:feature_class":"P",
    "gn:feature_code":"PPL",
    "gn:name":"Yeougumeongppuri",
    "gn:population":0,
    "gn:timezone":"Asia/Seoul",
    "iso:country":"KR",
    "name:kor_x_preferred":[
        "\uc5ec\uc6b0\uad6c\uba4d\ubfcc\ub9ac"
    ],
    "wof:name":"Yeougumeongppuri",
    "wof:placetype":"locality"
},
  "geometry": {"coordinates":[126.66922,37.24419],"type":"Point"}
}