{
  "type": "Feature",
  "properties": {
    "gn:admin1_code":"16.0",
    "gn:asciiname":"Yon-dong",
    "gn:country_code":"KR",
    "gn:dem":53,
    "gn:feature_class":"P",
    "gn:feature_code":"PPL",
    "gn:name":"Y\u014fn-dong",
    "gn:population":0,
    "gn:timezone":"Asia/Seoul",
    "iso:country":"KR",
    "name:kor_x_preferred":[
        "Y\u014fn-dong"
    ],
    "name:und_x_variant":[
        "\uc5f0\ub3d9"
    ],
    "wof:name":"Yon-dong",
    "wof:placetype":"locality"
},
  "geometry": {"coordinates":[126.61750000000001,34.54861],"type":"Point"}
}