{
  "type": "Feature",
  "properties": {
    "gn:admin1_code":"14.0",
    "gn:asciiname":"Sinbang",
    "gn:country_code":"KR",
    "gn:dem":170,
    "gn:feature_class":"P",
    "gn:feature_code":"PPL",
    "gn:name":"Sinbang",
    "gn:population":0,
    "gn:timezone":"Asia/Seoul",
    "iso:country":"KR",
    "name:kor_x_preferred":[
        "\uc2e0\ubc29"
    ],
    "name:und_x_variant":[
        "Sinbang-dong",
        "Sinbang-ni",
        "Sinbang"
    ],
    "wof:name":"Sinbang",
    "wof:placetype":"locality"
},
  "geometry": {"coordinates":[128.77661000000001,35.75825],"type":"Point"}
}