{
  "type": "Feature",
  "properties": {
    "gn:admin1_code":"16.0",
    "gn:asciiname":"Saphwa",
    "gn:country_code":"KR",
    "gn:dem":244,
    "gn:feature_class":"P",
    "gn:feature_code":"PPL",
    "gn:name":"Saphwa",
    "gn:population":0,
    "gn:timezone":"Asia/Seoul",
    "iso:country":"KR",
    "name:kor_x_preferred":[
        "\uc0bd\ud654"
    ],
    "wof:name":"Saphwa",
    "wof:placetype":"locality"
},
  "geometry": {"coordinates":[127.08459999999999,34.84626],"type":"Point"}
}