{
  "type": "Feature",
  "properties": {
    "gn:admin1_code":"17.0",
    "gn:asciiname":"Appak-kol",
    "gn:country_code":"KR",
    "gn:dem":46,
    "gn:feature_class":"P",
    "gn:feature_code":"PPL",
    "gn:name":"Appak-kol",
    "gn:population":0,
    "gn:timezone":"Asia/Seoul",
    "iso:country":"KR",
    "name:und_x_variant":[
        "\uc555\ubc15\uace8",
        "Appak-kol"
    ],
    "wof:name":"Appak-kol",
    "wof:placetype":"locality"
},
  "geometry": {"coordinates":[126.8532,36.6731],"type":"Point"}
}