{
  "type": "Feature",
  "properties": {
    "gn:admin1_code":"14.0",
    "gn:asciiname":"Hyangch'ol-li",
    "gn:country_code":"KR",
    "gn:dem":185,
    "gn:feature_class":"P",
    "gn:feature_code":"PPLL",
    "gn:name":"Hyangch\u2019\u014fl-li",
    "gn:population":0,
    "gn:timezone":"Asia/Seoul",
    "iso:country":"KR",
    "name:und_x_variant":[
        "\ud5a5\ucc9c\ub9ac",
        "Hyangch\u2019\u014fl-li"
    ],
    "wof:name":"Hyangch'ol-li",
    "wof:placetype":"locality"
},
  "geometry": {"coordinates":[128.00422,36.13683],"type":"Point"}
}