{
  "type": "Feature",
  "properties": {
    "gn:admin1_code":"14.0",
    "gn:asciiname":"Posin",
    "gn:country_code":"KR",
    "gn:dem":51,
    "gn:feature_class":"P",
    "gn:feature_code":"PPL",
    "gn:name":"Posin",
    "gn:population":0,
    "gn:timezone":"Asia/Seoul",
    "iso:country":"KR",
    "name:und_x_variant":[
        "\ubcf4\uc2e0"
    ],
    "wof:name":"Posin",
    "wof:placetype":"locality"
},
  "geometry": {"coordinates":[128.2535,36.1856],"type":"Point"}
}