{
  "type": "Feature",
  "properties": {
    "gn:admin1_code":"13.0",
    "gn:asciiname":"Gongdongjippuri",
    "gn:country_code":"KR",
    "gn:dem":24,
    "gn:feature_class":"P",
    "gn:feature_code":"PPL",
    "gn:name":"Gongdongjippuri",
    "gn:population":0,
    "gn:timezone":"Asia/Seoul",
    "iso:country":"KR",
    "name:kor_x_preferred":[
        "\uacf5\ub3d9\uc9c0\ubfcc\ub9ac"
    ],
    "wof:name":"Gongdongjippuri",
    "wof:placetype":"locality"
},
  "geometry": {"coordinates":[126.61824,37.24796],"type":"Point"}
}