{
  "type": "Feature",
  "properties": {
    "gn:admin1_code":"17.0",
    "gn:asciiname":"Naeung",
    "gn:country_code":"KR",
    "gn:dem":26,
    "gn:feature_class":"P",
    "gn:feature_code":"PPL",
    "gn:name":"Naeung",
    "gn:population":0,
    "gn:timezone":"Asia/Seoul",
    "iso:country":"KR",
    "name:und_x_variant":[
        "Naegom",
        "\uacf0\uc12c",
        "Koms\u014fm"
    ],
    "wof:name":"Naeung",
    "wof:placetype":"locality"
},
  "geometry": {"coordinates":[126.2865,36.5951],"type":"Point"}
}