{
  "type": "Feature",
  "properties": {
    "gn:admin1_code":"14.0",
    "gn:asciiname":"Sojae-gol",
    "gn:country_code":"KR",
    "gn:dem":45,
    "gn:feature_class":"P",
    "gn:feature_code":"PPL",
    "gn:name":"S\u014fjae-gol",
    "gn:population":0,
    "gn:timezone":"Asia/Seoul",
    "iso:country":"KR",
    "name:und_x_variant":[
        "\uc11c\uc7ac\uace8",
        "S\u014fjae-gol"
    ],
    "wof:name":"Sojae-gol",
    "wof:placetype":"locality"
},
  "geometry": {"coordinates":[128.24251000000001,35.68295999999999],"type":"Point"}
}