{
  "type": "Feature",
  "properties": {
    "gn:admin1_code":"14.0",
    "gn:asciiname":"Sopori",
    "gn:country_code":"KR",
    "gn:dem":16,
    "gn:feature_class":"P",
    "gn:feature_code":"PPL",
    "gn:name":"Sopori",
    "gn:population":0,
    "gn:timezone":"Asia/Seoul",
    "iso:country":"KR",
    "name:kor_x_preferred":[
        "\uc18c\ud3ec\ub9ac"
    ],
    "wof:name":"Sopori",
    "wof:placetype":"locality"
},
  "geometry": {"coordinates":[129.34936999999999,36.09432],"type":"Point"}
}