{
  "type": "Feature",
  "properties": {
    "gn:admin1_code":"14.0",
    "gn:asciiname":"Taebuk",
    "gn:cc2":"KR",
    "gn:country_code":"KR",
    "gn:dem":111,
    "gn:feature_class":"P",
    "gn:feature_code":"PPL",
    "gn:name":"Taebuk",
    "gn:population":0,
    "gn:timezone":"Asia/Seoul",
    "iso:country":"KR",
    "name:und_x_variant":[
        "Chungbuk",
        "Taebug-dong",
        "Ch\u016bhoku",
        "Chungduck",
        "Taebuk"
    ],
    "wof:name":"Taebuk",
    "wof:placetype":"locality"
},
  "geometry": {"coordinates":[128.56666999999999,36.26667],"type":"Point"}
}