{
  "type": "Feature",
  "properties": {
    "gn:admin1_code":"17.0",
    "gn:asciiname":"Tapsalli",
    "gn:country_code":"KR",
    "gn:dem":231,
    "gn:feature_class":"P",
    "gn:feature_code":"PPL",
    "gn:name":"Tapsalli",
    "gn:population":0,
    "gn:timezone":"Asia/Seoul",
    "iso:country":"KR",
    "name:kor_x_preferred":[
        "\ud0d1\uc0b0\ub9ac"
    ],
    "name:und_x_variant":[
        "T\u2019amnim-ni",
        "T\u2019apsan-ni",
        "Tapsalli"
    ],
    "wof:name":"Tapsalli",
    "wof:placetype":"locality"
},
  "geometry": {"coordinates":[126.96666999999999,36.66667],"type":"Point"}
}