{
  "type": "Feature",
  "properties": {
    "gn:admin1_code":"14.0",
    "gn:asciiname":"Dwitdeul",
    "gn:country_code":"KR",
    "gn:dem":214,
    "gn:feature_class":"P",
    "gn:feature_code":"PPL",
    "gn:name":"Dwitdeul",
    "gn:population":0,
    "gn:timezone":"Asia/Seoul",
    "iso:country":"KR",
    "name:kor_x_preferred":[
        "\ub4b7\ub4e4"
    ],
    "wof:name":"Dwitdeul",
    "wof:placetype":"locality"
},
  "geometry": {"coordinates":[128.80757,36.72582],"type":"Point"}
}