{
  "type": "Feature",
  "properties": {
    "gn:admin1_code":"6.0",
    "gn:asciiname":"Hasuha",
    "gn:country_code":"KR",
    "gn:dem":782,
    "gn:feature_class":"P",
    "gn:feature_code":"PPL",
    "gn:name":"Hasuha",
    "gn:population":0,
    "gn:timezone":"Asia/Seoul",
    "iso:country":"KR",
    "name:kor_x_preferred":[
        "\ud558\uc218\ud558"
    ],
    "wof:name":"Hasuha",
    "wof:placetype":"locality"
},
  "geometry": {"coordinates":[128.71799999999999,37.6223],"type":"Point"}
}