{
  "type": "Feature",
  "properties": {
    "gn:admin1_code":"15.0",
    "gn:asciiname":"Kuji",
    "gn:country_code":"KR",
    "gn:dem":26,
    "gn:feature_class":"P",
    "gn:feature_code":"PPL",
    "gn:name":"Kuji",
    "gn:population":0,
    "gn:timezone":"Asia/Seoul",
    "iso:country":"KR",
    "name:und_x_variant":[
        "\uad6c\uc9c0",
        "Kuji"
    ],
    "wof:name":"Kuji",
    "wof:placetype":"locality"
},
  "geometry": {"coordinates":[128.41252,35.65861],"type":"Point"}
}