{
  "type": "Feature",
  "properties": {
    "gn:admin1_code":"14.0",
    "gn:asciiname":"Sonhak",
    "gn:country_code":"KR",
    "gn:dem":64,
    "gn:feature_class":"P",
    "gn:feature_code":"PPL",
    "gn:name":"S\u014fnhak",
    "gn:population":0,
    "gn:timezone":"Asia/Seoul",
    "iso:country":"KR",
    "name:und_x_variant":[
        "\uc120\ud559",
        "S\u014fnhak"
    ],
    "wof:name":"Sonhak",
    "wof:placetype":"locality"
},
  "geometry": {"coordinates":[128.37260000000001,36.3751],"type":"Point"}
}