{
  "type": "Feature",
  "properties": {
    "gn:admin1_code":"16.0",
    "gn:asciiname":"Tokhung",
    "gn:country_code":"KR",
    "gn:dem":67,
    "gn:feature_class":"P",
    "gn:feature_code":"PPL",
    "gn:name":"T\u014fkh\u016dng",
    "gn:population":0,
    "gn:timezone":"Asia/Seoul",
    "iso:country":"KR",
    "name:kor_x_preferred":[
        "\ub355\ud765"
    ],
    "name:kor_x_variant":[
        "T\u014fkh\u016dng"
    ],
    "name:und_x_variant":[
        "Tokk\u014d",
        "T\u014fkh\u016dng-ni",
        "Tokk\u014d-ri"
    ],
    "wof:name":"Tokhung",
    "wof:placetype":"locality"
},
  "geometry": {"coordinates":[126.5925,34.47555999999999],"type":"Point"}
}