{
  "type": "Feature",
  "properties": {
    "gn:admin1_code":"17.0",
    "gn:asciiname":"Seopbanmal",
    "gn:country_code":"KR",
    "gn:dem":129,
    "gn:feature_class":"P",
    "gn:feature_code":"PPL",
    "gn:name":"Seopbanmal",
    "gn:population":0,
    "gn:timezone":"Asia/Seoul",
    "iso:country":"KR",
    "name:kor_x_preferred":[
        "\uc12d\ubc2d\ub9d0"
    ],
    "wof:name":"Seopbanmal",
    "wof:placetype":"locality"
},
  "geometry": {"coordinates":[127.06389,36.63324],"type":"Point"}
}