{
  "type": "Feature",
  "properties": {
    "gn:admin1_code":"14.0",
    "gn:asciiname":"Soho-ri",
    "gn:cc2":"KR",
    "gn:country_code":"KR",
    "gn:dem":161,
    "gn:feature_class":"P",
    "gn:feature_code":"PPL",
    "gn:name":"Soho-ri",
    "gn:population":0,
    "gn:timezone":"Asia/Seoul",
    "iso:country":"KR",
    "name:und_x_variant":[
        "Soho-dong",
        "Soho-ri"
    ],
    "wof:name":"Soho-ri",
    "wof:placetype":"locality"
},
  "geometry": {"coordinates":[128.66666999999998,36.46667],"type":"Point"}
}