{
  "type": "Feature",
  "properties": {
    "gn:admin1_code":"19.0",
    "gn:asciiname":"Choejeonggol",
    "gn:country_code":"KR",
    "gn:dem":101,
    "gn:feature_class":"P",
    "gn:feature_code":"PPL",
    "gn:name":"Choejeonggol",
    "gn:population":0,
    "gn:timezone":"Asia/Seoul",
    "iso:country":"KR",
    "name:und_x_variant":[
        "\ucd5c\uc815\uace8",
        "Ch\u2019oej\u014fng-gol",
        "Choejeonggol"
    ],
    "wof:name":"Choejeonggol",
    "wof:placetype":"locality"
},
  "geometry": {"coordinates":[127.32885,36.28681],"type":"Point"}
}