{
  "type": "Feature",
  "properties": {
    "gn:admin1_code":"17.0",
    "gn:asciiname":"Kak-kol",
    "gn:country_code":"KR",
    "gn:dem":99,
    "gn:feature_class":"P",
    "gn:feature_code":"PPL",
    "gn:name":"Kak-kol",
    "gn:population":0,
    "gn:timezone":"Asia/Seoul",
    "iso:country":"KR",
    "name:und_x_variant":[
        "\uac13\uace8",
        "Kak-kol"
    ],
    "wof:name":"Kak-kol",
    "wof:placetype":"locality"
},
  "geometry": {"coordinates":[126.7837,36.4289],"type":"Point"}
}