{
  "type": "Feature",
  "properties": {
    "gn:admin1_code":"21.0",
    "gn:asciiname":"Songjeong",
    "gn:country_code":"KR",
    "gn:dem":28,
    "gn:feature_class":"P",
    "gn:feature_code":"PPL",
    "gn:name":"Songjeong",
    "gn:population":0,
    "gn:timezone":"Asia/Seoul",
    "iso:country":"KR",
    "name:kor_x_preferred":[
        "\uc1a1\uc815"
    ],
    "name:und_x_variant":[
        "Songj\u014fng-dong",
        "Songj\u014fng-ni",
        "Songj\u014fng",
        "Songjeong"
    ],
    "wof:name":"Songjeong",
    "wof:placetype":"locality"
},
  "geometry": {"coordinates":[129.36147,35.60079],"type":"Point"}
}