{
  "type": "Feature",
  "properties": {
    "gn:admin1_code":"14.0",
    "gn:asciiname":"Jigogae",
    "gn:country_code":"KR",
    "gn:dem":104,
    "gn:feature_class":"P",
    "gn:feature_code":"PPL",
    "gn:name":"Jigogae",
    "gn:population":0,
    "gn:timezone":"Asia/Seoul",
    "iso:country":"KR",
    "name:kor_x_preferred":[
        "\uc9c0\uace0\uac1c"
    ],
    "wof:name":"Jigogae",
    "wof:placetype":"locality"
},
  "geometry": {"coordinates":[128.44271000000001,36.65222],"type":"Point"}
}