{
  "type": "Feature",
  "properties": {
    "gn:admin1_code":"10.0",
    "gn:asciiname":"Seolman",
    "gn:country_code":"KR",
    "gn:dem":2,
    "gn:feature_class":"P",
    "gn:feature_code":"PPL",
    "gn:name":"Seolman",
    "gn:population":0,
    "gn:timezone":"Asia/Seoul",
    "iso:country":"KR",
    "name:kor_x_preferred":[
        "\uc124\ub9cc"
    ],
    "name:und_x_variant":[
        "S\u014flman"
    ],
    "wof:name":"Seolman",
    "wof:placetype":"locality"
},
  "geometry": {"coordinates":[128.92873,35.17623],"type":"Point"}
}