{
  "type": "Feature",
  "properties": {
    "gn:admin1_code":"13.0",
    "gn:asciiname":"Twinmul",
    "gn:country_code":"KR",
    "gn:dem":31,
    "gn:feature_class":"P",
    "gn:feature_code":"PPL",
    "gn:name":"Twinmul",
    "gn:population":0,
    "gn:timezone":"Asia/Seoul",
    "iso:country":"KR",
    "name:und_x_variant":[
        "\ub4b7\ubb3c",
        "Dwitmul",
        "Twinmul"
    ],
    "wof:name":"Twinmul",
    "wof:placetype":"locality"
},
  "geometry": {"coordinates":[126.96611,37.25056],"type":"Point"}
}