{
  "type": "Feature",
  "properties": {
    "gn:admin1_code":"1.0",
    "gn:admin2_code":"Pukcheju-gun",
    "gn:asciiname":"Sinyang-ni",
    "gn:country_code":"KR",
    "gn:dem":92,
    "gn:feature_class":"P",
    "gn:feature_code":"PPL",
    "gn:name":"Sinyang-ni",
    "gn:population":0,
    "gn:timezone":"Asia/Seoul",
    "iso:country":"KR",
    "name:und_x_variant":[
        "Sanyang-ni",
        "Sinyang-ni"
    ],
    "wof:name":"Sinyang-ni",
    "wof:placetype":"locality"
},
  "geometry": {"coordinates":[126.22389,33.29278],"type":"Point"}
}