{
  "type": "Feature",
  "properties": {
    "gn:admin1_code":"11.0",
    "gn:asciiname":"Yangwon",
    "gn:country_code":"KR",
    "gn:dem":57,
    "gn:feature_class":"P",
    "gn:feature_code":"PPL",
    "gn:name":"Yangw\u014fn",
    "gn:population":0,
    "gn:timezone":"Asia/Seoul",
    "iso:country":"KR",
    "name:kor_x_preferred":[
        "\uc591\uc6d0"
    ],
    "name:und_x_variant":[
        "\uc591\uc6d0",
        "Yangw\u014fn"
    ],
    "wof:name":"Yangwon",
    "wof:placetype":"locality"
},
  "geometry": {"coordinates":[127.1117,37.6156],"type":"Point"}
}