{
  "type": "Feature",
  "properties": {
    "gn:admin1_code":"17.0",
    "gn:asciiname":"Onyangmo-ri",
    "gn:country_code":"KR",
    "gn:dem":25,
    "gn:feature_class":"P",
    "gn:feature_code":"PPL",
    "gn:name":"Onyangm\u014f-ri",
    "gn:population":0,
    "gn:timezone":"Asia/Seoul",
    "iso:country":"KR",
    "name:und_x_variant":[
        "\uc628\uc591\uba38\ub9ac",
        "Onyangm\u014f-ri"
    ],
    "wof:name":"Onyangmo-ri",
    "wof:placetype":"locality"
},
  "geometry": {"coordinates":[126.79559999999999,36.7006],"type":"Point"}
}