{
  "type": "Feature",
  "properties": {
    "gn:admin1_code":"17.0",
    "gn:asciiname":"Sangjok",
    "gn:country_code":"KR",
    "gn:dem":100,
    "gn:feature_class":"P",
    "gn:feature_code":"PPL",
    "gn:name":"Sangj\u014fk",
    "gn:population":0,
    "gn:timezone":"Asia/Seoul",
    "iso:country":"KR",
    "name:und_x_variant":[
        "Sangj\u014fng-ni",
        "Sangj\u014fk",
        "\uc0c1\uc801"
    ],
    "wof:name":"Sangjok",
    "wof:placetype":"locality"
},
  "geometry": {"coordinates":[126.8008,36.4269],"type":"Point"}
}