{
  "type": "Feature",
  "properties": {
    "gn:admin1_code":"13.0",
    "gn:asciiname":"Gukjeonggae",
    "gn:country_code":"KR",
    "gn:dem":175,
    "gn:feature_class":"P",
    "gn:feature_code":"PPL",
    "gn:name":"Gukjeonggae",
    "gn:population":0,
    "gn:timezone":"Asia/Seoul",
    "iso:country":"KR",
    "name:und_x_variant":[
        "\uad6d\uc815\uac1c",
        "Gukjeonggae",
        "Kukch\u014fnggae"
    ],
    "wof:name":"Gukjeonggae",
    "wof:placetype":"locality"
},
  "geometry": {"coordinates":[127.43832999999999,37.38139],"type":"Point"}
}