{
  "type": "Feature",
  "properties": {
    "gn:admin1_code":"5.0",
    "gn:asciiname":"Mojong",
    "gn:country_code":"KR",
    "gn:dem":200,
    "gn:feature_class":"P",
    "gn:feature_code":"PPL",
    "gn:name":"Moj\u014fng",
    "gn:population":0,
    "gn:timezone":"Asia/Seoul",
    "iso:country":"KR",
    "name:und_x_variant":[
        "\ubaa8\uc815",
        "Moj\u014fng"
    ],
    "wof:name":"Mojong",
    "wof:placetype":"locality"
},
  "geometry": {"coordinates":[127.6506,36.0705],"type":"Point"}
}