{
  "type": "Feature",
  "properties": {
    "gn:admin1_code":"16.0",
    "gn:asciiname":"Jangnim",
    "gn:country_code":"KR",
    "gn:dem":16,
    "gn:feature_class":"P",
    "gn:feature_code":"PPL",
    "gn:name":"Jangnim",
    "gn:population":0,
    "gn:timezone":"Asia/Seoul",
    "iso:country":"KR",
    "name:kor_x_preferred":[
        "\uc7a5\ub9bc"
    ],
    "wof:name":"Jangnim",
    "wof:placetype":"locality"
},
  "geometry": {"coordinates":[126.73829000000001,35.06783],"type":"Point"}
}