{
  "type": "Feature",
  "properties": {
    "gn:admin1_code":"16.0",
    "gn:asciiname":"Kugyo",
    "gn:country_code":"KR",
    "gn:dem":55,
    "gn:feature_class":"P",
    "gn:feature_code":"PPL",
    "gn:name":"Kugyo",
    "gn:population":0,
    "gn:timezone":"Asia/Seoul",
    "iso:country":"KR",
    "name:und_x_variant":[
        "\uad6c\uad50",
        "Kugyo"
    ],
    "wof:name":"Kugyo",
    "wof:placetype":"locality"
},
  "geometry": {"coordinates":[126.59721999999999,34.57889],"type":"Point"}
}