{
  "type": "Feature",
  "properties": {
    "gn:admin1_code":"13.0",
    "gn:asciiname":"Unp'yong-ni",
    "gn:country_code":"KR",
    "gn:dem":18,
    "gn:feature_class":"P",
    "gn:feature_code":"PPL",
    "gn:name":"Unp\u2019y\u014fng-ni",
    "gn:population":0,
    "gn:timezone":"Asia/Seoul",
    "iso:country":"KR",
    "name:kor_x_preferred":[
        "\uc6b4\ud3c9\ub9ac"
    ],
    "name:kor_x_variant":[
        "Unp\u2019y\u014fng-ni"
    ],
    "wof:name":"Unp'yong-ni",
    "wof:placetype":"locality"
},
  "geometry": {"coordinates":[126.77833,37.08306],"type":"Point"}
}