{
  "type": "Feature",
  "properties": {
    "gn:admin1_code":"13.0",
    "gn:asciiname":"Sinseongdong",
    "gn:country_code":"KR",
    "gn:dem":45,
    "gn:feature_class":"P",
    "gn:feature_code":"PPL",
    "gn:name":"Sinseongdong",
    "gn:population":0,
    "gn:timezone":"Asia/Seoul",
    "iso:country":"KR",
    "name:kor_x_preferred":[
        "\uc2e0\uc131\ub3d9"
    ],
    "name:kor_x_variant":[
        "Sins\u014fng-dong"
    ],
    "wof:name":"Sinseongdong",
    "wof:placetype":"locality"
},
  "geometry": {"coordinates":[126.84951,37.72517],"type":"Point"}
}