{
  "type": "Feature",
  "properties": {
    "gn:admin1_code":"3.0",
    "gn:asciiname":"Hwarin-dong",
    "gn:country_code":"KR",
    "gn:dem":326,
    "gn:feature_class":"P",
    "gn:feature_code":"PPL",
    "gn:name":"Hwarin-dong",
    "gn:population":0,
    "gn:timezone":"Asia/Seoul",
    "iso:country":"KR",
    "name:und_x_variant":[
        "\ud65c\uc778\ub3d9",
        "Hwarin-dong"
    ],
    "wof:name":"Hwarin-dong",
    "wof:placetype":"locality"
},
  "geometry": {"coordinates":[127.40561,35.78209000000001],"type":"Point"}
}