{
  "type": "Feature",
  "properties": {
    "gn:admin1_code":"20.0",
    "gn:asciiname":"Hwach'ol-li",
    "gn:country_code":"KR",
    "gn:dem":33,
    "gn:feature_class":"P",
    "gn:feature_code":"PPL",
    "gn:name":"Hwach\u2019\u014fl-li",
    "gn:population":0,
    "gn:timezone":"Asia/Seoul",
    "iso:country":"KR",
    "name:und_x_variant":[
        "Hwach\u2019\u014fn",
        "Hwach\u2019\u014fl-li"
    ],
    "wof:name":"Hwach'ol-li",
    "wof:placetype":"locality"
},
  "geometry": {"coordinates":[128.03416999999999,34.82056],"type":"Point"}
}