{
  "type": "Feature",
  "properties": {
    "gn:admin1_code":"14.0",
    "gn:asciiname":"Sagok-tong",
    "gn:cc2":"KR",
    "gn:country_code":"KR",
    "gn:dem":441,
    "gn:feature_class":"P",
    "gn:feature_code":"PPL",
    "gn:name":"Sagok-tong",
    "gn:population":0,
    "gn:timezone":"Asia/Seoul",
    "iso:country":"KR",
    "name:eng_x_preferred":[
        "Sagok"
    ],
    "name:eng_x_variant":[
        "Sagok-tong"
    ],
    "name:und_x_variant":[
        "Sagong-ni",
        "Sagok-tong"
    ],
    "wof:name":"Sagok",
    "wof:placetype":"locality"
},
  "geometry": {"coordinates":[128.33332999999999,36.68333],"type":"Point"}
}