{
  "type": "Feature",
  "properties": {
    "gn:admin1_code":"13.0",
    "gn:asciiname":"Gyeongneungi",
    "gn:country_code":"KR",
    "gn:dem":61,
    "gn:feature_class":"P",
    "gn:feature_code":"PPL",
    "gn:name":"Gyeongneungi",
    "gn:population":0,
    "gn:timezone":"Asia/Seoul",
    "iso:country":"KR",
    "name:kor_x_preferred":[
        "\uacbd\ub2a5\uc774"
    ],
    "name:und_x_variant":[
        "Gyeongneungi",
        "Ky\u014fngn\u016dngi"
    ],
    "wof:name":"Gyeongneungi",
    "wof:placetype":"locality"
},
  "geometry": {"coordinates":[127.54056,37.25528],"type":"Point"}
}