{
  "type": "Feature",
  "properties": {
    "gn:admin1_code":"0.0",
    "gn:asciiname":"Okdong",
    "gn:country_code":"KR",
    "gn:dem":16,
    "gn:feature_class":"P",
    "gn:feature_code":"PPL",
    "gn:name":"Okdong",
    "gn:population":0,
    "gn:timezone":"Asia/Seoul",
    "iso:country":"KR",
    "name:kor_x_preferred":[
        "\uc625\ub3d9"
    ],
    "name:und_x_variant":[
        "Ok-tong"
    ],
    "wof:name":"Okdong",
    "wof:placetype":"locality"
},
  "geometry": {"coordinates":[126.58886,35.08028],"type":"Point"}
}