{
  "type": "Feature",
  "properties": {
    "gn:admin1_code":"14.0",
    "gn:asciiname":"Kaya-ri",
    "gn:cc2":"KR",
    "gn:country_code":"KR",
    "gn:dem":53,
    "gn:feature_class":"P",
    "gn:feature_code":"PPL",
    "gn:name":"Kaya-ri",
    "gn:population":0,
    "gn:timezone":"Asia/Seoul",
    "iso:country":"KR",
    "name:und_x_variant":[
        "Kaya",
        "Kaya-dong",
        "Kaya-ri"
    ],
    "wof:name":"Kaya-ri",
    "wof:placetype":"locality"
},
  "geometry": {"coordinates":[128.79944,35.85167],"type":"Point"}
}