{
  "type": "Feature",
  "properties": {
    "gn:admin1_code":"14.0",
    "gn:asciiname":"Apsil",
    "gn:country_code":"KR",
    "gn:dem":409,
    "gn:feature_class":"P",
    "gn:feature_code":"PPL",
    "gn:name":"Apsil",
    "gn:population":0,
    "gn:timezone":"Asia/Seoul",
    "iso:country":"KR",
    "name:und_x_variant":[
        "\uc555\uc2e4",
        "Apsil"
    ],
    "wof:name":"Apsil",
    "wof:placetype":"locality"
},
  "geometry": {"coordinates":[129.00700000000001,36.6873],"type":"Point"}
}