{
  "type": "Feature",
  "properties": {
    "gn:admin1_code":"3.0",
    "gn:asciiname":"Won'gaejong",
    "gn:country_code":"KR",
    "gn:dem":461,
    "gn:feature_class":"P",
    "gn:feature_code":"PPL",
    "gn:name":"W\u014fn\u2019gaej\u014fng",
    "gn:population":0,
    "gn:timezone":"Asia/Seoul",
    "iso:country":"KR",
    "name:und_x_variant":[
        "\uc6d0\uac1c\uc815",
        "W\u014fn\u2019gaej\u014fng"
    ],
    "wof:name":"Won'gaejong",
    "wof:placetype":"locality"
},
  "geometry": {"coordinates":[127.50942999999999,35.61565],"type":"Point"}
}