{
  "type": "Feature",
  "properties": {
    "gn:admin1_code":"6.0",
    "gn:asciiname":"Turung-dong",
    "gn:country_code":"KR",
    "gn:dem":690,
    "gn:feature_class":"P",
    "gn:feature_code":"PPL",
    "gn:name":"Tur\u016dng-dong",
    "gn:population":0,
    "gn:timezone":"Asia/Seoul",
    "iso:country":"KR",
    "name:kor_x_preferred":[
        "\ub450\ub989\ub3d9"
    ],
    "name:kor_x_variant":[
        "Tur\u016dng-dong"
    ],
    "wof:name":"Turung-dong",
    "wof:placetype":"locality"
},
  "geometry": {"coordinates":[128.1541,37.3239],"type":"Point"}
}