{
  "type": "Feature",
  "properties": {
    "gn:admin1_code":"13.0",
    "gn:asciiname":"Ssaryeom",
    "gn:country_code":"KR",
    "gn:dem":11,
    "gn:feature_class":"P",
    "gn:feature_code":"PPL",
    "gn:name":"Ssaryeom",
    "gn:population":0,
    "gn:timezone":"Asia/Seoul",
    "iso:country":"KR",
    "name:und_x_variant":[
        "\uc2f8\ub834",
        "Ssaryeom",
        "Ssary\u014fm"
    ],
    "wof:name":"Ssaryeom",
    "wof:placetype":"locality"
},
  "geometry": {"coordinates":[126.5943,37.61043],"type":"Point"}
}