{
  "type": "Feature",
  "properties": {
    "gn:admin1_code":"16.0",
    "gn:asciiname":"Ch'ungyol-li",
    "gn:country_code":"KR",
    "gn:dem":38,
    "gn:feature_class":"P",
    "gn:feature_code":"PPL",
    "gn:name":"Ch\u2019ungy\u014fl-li",
    "gn:population":0,
    "gn:timezone":"Asia/Seoul",
    "iso:country":"KR",
    "name:kor_x_preferred":[
        "\uc911\uc5f4\ub9ac"
    ],
    "name:kor_x_variant":[
        "Ch\u2019ungy\u014fl-li"
    ],
    "name:und_x_variant":[
        "Ch\u2019ungny\u014fl-li"
    ],
    "wof:name":"Ch'ungyol-li",
    "wof:placetype":"locality"
},
  "geometry": {"coordinates":[126.89417,34.67167],"type":"Point"}
}