{
  "type": "Feature",
  "properties": {
    "gn:admin1_code":"13.0",
    "gn:asciiname":"Sangbaeng-ni",
    "gn:country_code":"KR",
    "gn:dem":67,
    "gn:feature_class":"P",
    "gn:feature_code":"PPLL",
    "gn:name":"Sangbaeng-ni",
    "gn:population":0,
    "gn:timezone":"Asia/Seoul",
    "iso:country":"KR",
    "name:und_x_variant":[
        "\uc0c1\ubc31\ub9ac",
        "Sangbaek-ri",
        "Sangbaeng-ni"
    ],
    "wof:name":"Sangbaeng-ni",
    "wof:placetype":"locality"
},
  "geometry": {"coordinates":[127.55306000000002,37.3575],"type":"Point"}
}