{
  "type": "Feature",
  "properties": {
    "gn:admin1_code":"6.0",
    "gn:asciiname":"P'ung-ch'on",
    "gn:country_code":"KR",
    "gn:dem":555,
    "gn:feature_class":"P",
    "gn:feature_code":"PPL",
    "gn:name":"P\u2019ung-ch\u2019on",
    "gn:population":0,
    "gn:timezone":"Asia/Seoul",
    "iso:country":"KR",
    "name:kor_x_preferred":[
        "\ud48d\ucd0c"
    ],
    "name:kor_x_variant":[
        "P\u2019ung-ch\u2019on"
    ],
    "wof:name":"P'ung-ch'on",
    "wof:placetype":"locality"
},
  "geometry": {"coordinates":[128.82560000000001,37.3033],"type":"Point"}
}