{
  "type": "Feature",
  "properties": {
    "gn:admin1_code":"20.0",
    "gn:asciiname":"Oegan",
    "gn:cc2":"KR",
    "gn:country_code":"KR",
    "gn:dem":20,
    "gn:feature_class":"P",
    "gn:feature_code":"PPL",
    "gn:name":"Oegan",
    "gn:population":0,
    "gn:timezone":"Asia/Seoul",
    "iso:country":"KR",
    "name:und_x_variant":[
        "Egan-ni",
        "Oegan-ni",
        "Gaikan-ri",
        "Oegal-li",
        "Gaikan",
        "Oegan"
    ],
    "wof:name":"Oegan",
    "wof:placetype":"locality"
},
  "geometry": {"coordinates":[128.57277999999999,34.85972],"type":"Point"}
}