{
  "type": "Feature",
  "properties": {
    "gn:admin1_code":"14.0",
    "gn:asciiname":"Umdal",
    "gn:country_code":"KR",
    "gn:dem":624,
    "gn:feature_class":"P",
    "gn:feature_code":"PPL",
    "gn:name":"\u016cmdal",
    "gn:population":0,
    "gn:timezone":"Asia/Seoul",
    "iso:country":"KR",
    "wof:name":"Umdal",
    "wof:placetype":"locality"
},
  "geometry": {"coordinates":[128.37916999999999,36.795],"type":"Point"}
}