{
  "type": "Feature",
  "properties": {
    "gn:admin1_code":"6.0",
    "gn:asciiname":"Maettolgori",
    "gn:country_code":"KR",
    "gn:dem":688,
    "gn:feature_class":"P",
    "gn:feature_code":"PPL",
    "gn:name":"Maettolg\u014fri",
    "gn:population":0,
    "gn:timezone":"Asia/Seoul",
    "iso:country":"KR",
    "name:kor_x_preferred":[
        "\ub9f7\ub3cc\uac70\ub9ac"
    ],
    "name:kor_x_variant":[
        "Maettolg\u014fri"
    ],
    "wof:name":"Maettolgori",
    "wof:placetype":"locality"
},
  "geometry": {"coordinates":[128.2655,37.5232],"type":"Point"}
}