{
  "type": "Feature",
  "properties": {
    "gn:admin1_code":"21.0",
    "gn:asciiname":"Naegwang",
    "gn:country_code":"KR",
    "gn:dem":136,
    "gn:feature_class":"P",
    "gn:feature_code":"PPL",
    "gn:name":"Naegwang",
    "gn:population":0,
    "gn:timezone":"Asia/Seoul",
    "iso:country":"KR",
    "name:kor_x_preferred":[
        "\ub0b4\uad11"
    ],
    "wof:name":"Naegwang",
    "wof:placetype":"locality"
},
  "geometry": {"coordinates":[129.20848000000001,35.42854000000001],"type":"Point"}
}