{
  "type": "Feature",
  "properties": {
    "gn:admin1_code":"11.0",
    "gn:asciiname":"Yeoui-dong",
    "gn:country_code":"KR",
    "gn:dem":19,
    "gn:feature_class":"P",
    "gn:feature_code":"PPL",
    "gn:name":"Yeoui-dong",
    "gn:population":0,
    "gn:timezone":"Asia/Seoul",
    "iso:country":"KR",
    "name:eng_x_preferred":[
        "Yeoui-dong"
    ],
    "name:kor_x_preferred":[
        "\uc5ec\uc758\ub3d9"
    ],
    "wof:name":"Yeoui-dong",
    "wof:placetype":"locality"
},
  "geometry": {"coordinates":[126.92903,37.52864],"type":"Point"}
}