{
  "type": "Feature",
  "properties": {
    "gn:admin1_code":"20.0",
    "gn:asciiname":"Hangnim-ni",
    "gn:cc2":"KR",
    "gn:country_code":"KR",
    "gn:dem":17,
    "gn:feature_class":"P",
    "gn:feature_code":"PPL",
    "gn:name":"Hangnim-ni",
    "gn:population":0,
    "gn:timezone":"Asia/Seoul",
    "iso:country":"KR",
    "name:eng_x_preferred":[
        "Hangnim"
    ],
    "name:eng_x_variant":[
        "Hangnim-ni"
    ],
    "name:und_x_variant":[
        "Hak-tong",
        "Hangnim-ni"
    ],
    "wof:name":"Hangnim",
    "wof:placetype":"locality"
},
  "geometry": {"coordinates":[128.19193999999999,34.94333],"type":"Point"}
}