{
  "type": "Feature",
  "properties": {
    "gn:admin1_code":"12.0",
    "gn:admin2_code":"Kanghwa-gun",
    "gn:asciiname":"Jitjeolmi",
    "gn:country_code":"KR",
    "gn:dem":24,
    "gn:feature_class":"P",
    "gn:feature_code":"PPL",
    "gn:name":"Jitjeolmi",
    "gn:population":0,
    "gn:timezone":"Asia/Seoul",
    "iso:country":"KR",
    "name:kor_x_preferred":[
        "\uc9d3\uc808\ubbf8"
    ],
    "name:kor_x_variant":[
        "Chitch\u014flmi"
    ],
    "wof:name":"Jitjeolmi",
    "wof:placetype":"locality"
},
  "geometry": {"coordinates":[126.38911,37.79037],"type":"Point"}
}