{
  "type": "Feature",
  "properties": {
    "gn:admin1_code":"17.0",
    "gn:asciiname":"Gatbawi",
    "gn:country_code":"KR",
    "gn:dem":39,
    "gn:feature_class":"P",
    "gn:feature_code":"PPL",
    "gn:name":"Gatbawi",
    "gn:population":0,
    "gn:timezone":"Asia/Seoul",
    "iso:country":"KR",
    "name:und_x_variant":[
        "Ibam",
        "Katpawi",
        "Ipak",
        "Ip\u2019am",
        "\uac13\ubc14\uc704",
        "Kappawi",
        "Gatbawi"
    ],
    "wof:name":"Gatbawi",
    "wof:placetype":"locality"
},
  "geometry": {"coordinates":[126.97985,36.75396],"type":"Point"}
}