{
  "type": "Feature",
  "properties": {
    "gn:admin1_code":"13.0",
    "gn:asciiname":"Bakdari",
    "gn:country_code":"KR",
    "gn:dem":97,
    "gn:feature_class":"P",
    "gn:feature_code":"PPL",
    "gn:name":"Bakdari",
    "gn:population":0,
    "gn:timezone":"Asia/Seoul",
    "iso:country":"KR",
    "name:kor_x_preferred":[
        "\ubc15\ub2e4\ub9ac"
    ],
    "wof:name":"Bakdari",
    "wof:placetype":"locality"
},
  "geometry": {"coordinates":[126.98235,37.83507],"type":"Point"}
}