{
  "type": "Feature",
  "properties": {
    "gn:admin1_code":"13.0",
    "gn:asciiname":"Utbaechi",
    "gn:country_code":"KR",
    "gn:dem":219,
    "gn:feature_class":"P",
    "gn:feature_code":"PPL",
    "gn:name":"Utbaechi",
    "gn:population":0,
    "gn:timezone":"Asia/Seoul",
    "iso:country":"KR",
    "name:kor_x_preferred":[
        "\uc6c3\ubc30\uce58"
    ],
    "name:und_x_variant":[
        "Utbaechi"
    ],
    "wof:name":"Utbaechi",
    "wof:placetype":"locality"
},
  "geometry": {"coordinates":[127.44629999999999,37.66345],"type":"Point"}
}