{
  "type": "Feature",
  "properties": {
    "gn:admin1_code":"5.0",
    "gn:asciiname":"Dongmak",
    "gn:country_code":"KR",
    "gn:dem":107,
    "gn:feature_class":"P",
    "gn:feature_code":"PPL",
    "gn:name":"Dongmak",
    "gn:population":0,
    "gn:timezone":"Asia/Seoul",
    "iso:country":"KR",
    "name:kor_x_preferred":[
        "\ub3d9\ub9c9"
    ],
    "name:und_x_variant":[
        "Tongmak"
    ],
    "wof:name":"Dongmak",
    "wof:placetype":"locality"
},
  "geometry": {"coordinates":[127.64236,37.09075],"type":"Point"}
}