{
  "type": "Feature",
  "properties": {
    "gn:admin1_code":"16.0",
    "gn:asciiname":"Hoeryong",
    "gn:country_code":"KR",
    "gn:dem":49,
    "gn:feature_class":"P",
    "gn:feature_code":"PPL",
    "gn:name":"Hoeryong",
    "gn:population":0,
    "gn:timezone":"Asia/Seoul",
    "iso:country":"KR",
    "name:ace_x_preferred":[
        "Hoeryeong"
    ],
    "name:aze_x_preferred":[
        "Hveryon"
    ],
    "name:ceb_x_preferred":[
        "Hoery\u014fng"
    ],
    "name:ces_x_preferred":[
        "H\u00f6rjong"
    ],
    "name:epo_x_preferred":[
        "Horjong"
    ],
    "name:est_x_preferred":[
        "Hoery\u014fng"
    ],
    "name:fas_x_preferred":[
        "\u0647\u0648\u0626\u0631\u06cc\u0648\u0646\u06af"
    ],
    "name:fin_x_preferred":[
        "Hoeryeong"
    ],
    "name:fra_x_preferred":[
        "Hoeryong"
    ],
    "name:heb_x_preferred":[
        "\u05d4\u05d5\u05d0\u05e8\u05d9\u05d5\u05e0\u05d2"
    ],
    "name:hun_x_preferred":[
        "H\u00f6rjong"
    ],
    "name:ind_x_preferred":[
        "Hoeryong"
    ],
    "name:ita_x_preferred":[
        "Hoeryong"
    ],
    "name:jpn_x_preferred":[
        "\u4f1a\u5be7\u5e02"
    ],
    "name:kor_x_preferred":[
        "\ud68c\ub8e1"
    ],
    "name:kor_x_variant":[
        "\ud68c\ub839\uc2dc"
    ],
    "name:nld_x_preferred":[
        "Hoery\u014fng"
    ],
    "name:nor_x_preferred":[
        "Hoeryong"
    ],
    "name:pol_x_preferred":[
        "Hoery\u014fng"
    ],
    "name:rus_x_preferred":[
        "\u0425\u0432\u0435\u0440\u0451\u043d"
    ],
    "name:swe_x_preferred":[
        "Hoeryong"
    ],
    "name:tur_x_preferred":[
        "Hoeryong"
    ],
    "name:urd_x_preferred":[
        "\u06c1\u0648\u0626\u0631\u06cc\u0648\u0646\u06af"
    ],
    "name:vie_x_preferred":[
        "Hoeryong"
    ],
    "name:zho_x_preferred":[
        "\u4f1a\u5b81\u5e02"
    ],
    "wof:name":"Hoeryong",
    "wof:placetype":"locality"
},
  "geometry": {"coordinates":[126.78478,35.25145999999999],"type":"Point"}
}