{
  "type": "Feature",
  "properties": {
    "gn:admin1_code":"17.0",
    "gn:asciiname":"Taemajik",
    "gn:country_code":"KR",
    "gn:dem":224,
    "gn:feature_class":"P",
    "gn:feature_code":"PPL",
    "gn:name":"Taemajik",
    "gn:population":0,
    "gn:timezone":"Asia/Seoul",
    "iso:country":"KR",
    "name:und_x_variant":[
        "\ub300\ub9c8\uc9c1",
        "Taemajik"
    ],
    "wof:name":"Taemajik",
    "wof:placetype":"locality"
},
  "geometry": {"coordinates":[126.8745,36.5022],"type":"Point"}
}