{
  "type": "Feature",
  "properties": {
    "gn:admin1_code":"13.0",
    "gn:asciiname":"Wontong",
    "gn:country_code":"KR",
    "gn:dem":168,
    "gn:feature_class":"P",
    "gn:feature_code":"PPL",
    "gn:name":"Wontong",
    "gn:population":0,
    "gn:timezone":"Asia/Seoul",
    "iso:country":"KR",
    "name:kor_x_preferred":[
        "\uc6d0\ud1b5"
    ],
    "name:kor_x_variant":[
        "W\u014fnt\u2019ong"
    ],
    "wof:name":"Wontong",
    "wof:placetype":"locality"
},
  "geometry": {"coordinates":[127.31153,37.93708],"type":"Point"}
}