{
  "type": "Feature",
  "properties": {
    "gn:admin1_code":"16.0",
    "gn:asciiname":"Wonseochang",
    "gn:country_code":"KR",
    "gn:dem":13,
    "gn:feature_class":"P",
    "gn:feature_code":"PPL",
    "gn:name":"Wonseochang",
    "gn:population":0,
    "gn:timezone":"Asia/Seoul",
    "iso:country":"KR",
    "name:kor_x_preferred":[
        "\uc6d0\uc11c\uc7a5"
    ],
    "name:und_x_variant":[
        "W\u014fns\u014fjang",
        "Wonseochang"
    ],
    "wof:name":"Wonseochang",
    "wof:placetype":"locality"
},
  "geometry": {"coordinates":[126.53888000000001,34.72812],"type":"Point"}
}