{
  "type": "Feature",
  "properties": {
    "gn:admin1_code":"14.0",
    "gn:asciiname":"Komji-gol",
    "gn:country_code":"KR",
    "gn:dem":294,
    "gn:feature_class":"P",
    "gn:feature_code":"PPL",
    "gn:name":"Komji-gol",
    "gn:population":0,
    "gn:timezone":"Asia/Seoul",
    "iso:country":"KR",
    "name:und_x_variant":[
        "\uacf0\uc9c0\uace8",
        "Komji-gol"
    ],
    "wof:name":"Komji-gol",
    "wof:placetype":"locality"
},
  "geometry": {"coordinates":[128.24698999999998,35.87079],"type":"Point"}
}