{
  "type": "Feature",
  "properties": {
    "gn:admin1_code":"14.0",
    "gn:asciiname":"Sinnae",
    "gn:country_code":"KR",
    "gn:dem":46,
    "gn:feature_class":"P",
    "gn:feature_code":"PPL",
    "gn:name":"Sinnae",
    "gn:population":0,
    "gn:timezone":"Asia/Seoul",
    "iso:country":"KR",
    "name:und_x_variant":[
        "\uc2e0\ub0b4",
        "Sinnae"
    ],
    "wof:name":"Sinnae",
    "wof:placetype":"locality"
},
  "geometry": {"coordinates":[128.3175,36.2951],"type":"Point"}
}