{
  "type": "Feature",
  "properties": {
    "gn:admin1_code":"5.0",
    "gn:asciiname":"Oegongsu-dong",
    "gn:country_code":"KR",
    "gn:dem":209,
    "gn:feature_class":"P",
    "gn:feature_code":"PPL",
    "gn:name":"Oegongsu-dong",
    "gn:population":0,
    "gn:timezone":"Asia/Seoul",
    "iso:country":"KR",
    "name:und_x_variant":[
        "Oesongsu-dong",
        "Oe-kongsu-dong",
        "\uc678\uacf5\uc218\ub3d9",
        "Oegongsu-dong"
    ],
    "wof:name":"Oegongsu-dong",
    "wof:placetype":"locality"
},
  "geometry": {"coordinates":[127.7559,36.1154],"type":"Point"}
}