{
  "type": "Feature",
  "properties": {
    "gn:admin1_code":"14.0",
    "gn:asciiname":"Ttakbakgueok",
    "gn:country_code":"KR",
    "gn:dem":182,
    "gn:feature_class":"P",
    "gn:feature_code":"PPL",
    "gn:name":"Ttakbakgueok",
    "gn:population":0,
    "gn:timezone":"Asia/Seoul",
    "iso:country":"KR",
    "name:kor_x_preferred":[
        "\ub531\ubc15\uad6c\uc5b5"
    ],
    "wof:name":"Ttakbakgueok",
    "wof:placetype":"locality"
},
  "geometry": {"coordinates":[128.96901,36.56769],"type":"Point"}
}