{
  "type": "Feature",
  "properties": {
    "gn:admin1_code":"6.0",
    "gn:asciiname":"Sohuri",
    "gn:country_code":"KR",
    "gn:dem":217,
    "gn:feature_class":"P",
    "gn:feature_code":"PPL",
    "gn:name":"Sohuri",
    "gn:population":0,
    "gn:timezone":"Asia/Seoul",
    "iso:country":"KR",
    "name:kor_x_preferred":[
        "\uc18c\ud6c4\ub9ac"
    ],
    "wof:name":"Sohuri",
    "wof:placetype":"locality"
},
  "geometry": {"coordinates":[127.26403000000001,38.23407],"type":"Point"}
}