{
  "type": "Feature",
  "properties": {
    "gn:admin1_code":"16.0",
    "gn:asciiname":"Yeongheung",
    "gn:country_code":"KR",
    "gn:dem":70,
    "gn:feature_class":"P",
    "gn:feature_code":"PPL",
    "gn:name":"Yeongheung",
    "gn:population":0,
    "gn:timezone":"Asia/Seoul",
    "iso:country":"KR",
    "name:kor_x_preferred":[
        "Y\u014fngh\u016dng"
    ],
    "name:und_x_variant":[
        "\uc601\ud765",
        "Yeongheung"
    ],
    "wof:name":"Yeongheung",
    "wof:placetype":"locality"
},
  "geometry": {"coordinates":[126.71693999999999,34.70333],"type":"Point"}
}