{
  "type": "Feature",
  "properties": {
    "gn:admin1_code":"14.0",
    "gn:asciiname":"Abangsil",
    "gn:country_code":"KR",
    "gn:dem":305,
    "gn:feature_class":"P",
    "gn:feature_code":"PPL",
    "gn:name":"Abangsil",
    "gn:population":0,
    "gn:timezone":"Asia/Seoul",
    "iso:country":"KR",
    "name:und_x_variant":[
        "\uc544\ubc29\uc2e4",
        "Abangsil"
    ],
    "wof:name":"Abangsil",
    "wof:placetype":"locality"
},
  "geometry": {"coordinates":[129.05109999999999,36.3448],"type":"Point"}
}