{
  "type": "Feature",
  "properties": {
    "gn:admin1_code":"16.0",
    "gn:asciiname":"Bangchon",
    "gn:country_code":"KR",
    "gn:dem":95,
    "gn:feature_class":"P",
    "gn:feature_code":"PPL",
    "gn:name":"Bangchon",
    "gn:population":0,
    "gn:timezone":"Asia/Seoul",
    "iso:country":"KR",
    "name:kor_x_preferred":[
        "\ubc29\ucd0c"
    ],
    "name:und_x_variant":[
        "Pangch\u2019on"
    ],
    "wof:name":"Bangchon",
    "wof:placetype":"locality"
},
  "geometry": {"coordinates":[126.85082,34.91054],"type":"Point"}
}