{
  "type": "Feature",
  "properties": {
    "gn:admin1_code":"6.0",
    "gn:asciiname":"Solp'igol",
    "gn:country_code":"KR",
    "gn:dem":472,
    "gn:feature_class":"P",
    "gn:feature_code":"PPL",
    "gn:name":"S\u014flp\u2019igol",
    "gn:population":0,
    "gn:timezone":"Asia/Seoul",
    "iso:country":"KR",
    "name:und_x_variant":[
        "S\u014flp\u2019igol",
        "\uc124\ud53c\uace8"
    ],
    "wof:name":"Solp'igol",
    "wof:placetype":"locality"
},
  "geometry": {"coordinates":[128.26381999999998,38.17737],"type":"Point"}
}