{
  "type": "Feature",
  "properties": {
    "gn:admin1_code":"14.0",
    "gn:asciiname":"Haeindong",
    "gn:country_code":"KR",
    "gn:dem":89,
    "gn:feature_class":"P",
    "gn:feature_code":"PPL",
    "gn:name":"Haeindong",
    "gn:population":0,
    "gn:timezone":"Asia/Seoul",
    "iso:country":"KR",
    "name:kor_x_preferred":[
        "\ud574\uc778\ub3d9"
    ],
    "wof:name":"Haeindong",
    "wof:placetype":"locality"
},
  "geometry": {"coordinates":[129.44898000000001,35.91145],"type":"Point"}
}