{
  "type": "Feature",
  "properties": {
    "gn:admin1_code":"11.0",
    "gn:asciiname":"Sogyo-dong",
    "gn:country_code":"KR",
    "gn:dem":22,
    "gn:feature_class":"P",
    "gn:feature_code":"PPL",
    "gn:name":"S\u014fgyo-dong",
    "gn:population":0,
    "gn:timezone":"Asia/Seoul",
    "iso:country":"KR",
    "name:und_x_variant":[
        "S\u014fgyo-j\u014fng",
        "\uc11c\uad50\ub3d9",
        "S\u014fgyo-dong"
    ],
    "wof:name":"Sogyo-dong",
    "wof:placetype":"locality"
},
  "geometry": {"coordinates":[126.9165,37.55356],"type":"Point"}
}