{
  "type": "Feature",
  "properties": {
    "gn:admin1_code":"20.0",
    "gn:asciiname":"Taegu",
    "gn:cc2":"KR",
    "gn:country_code":"KR",
    "gn:dem":49,
    "gn:feature_class":"P",
    "gn:feature_code":"PPL",
    "gn:name":"Taegu",
    "gn:population":0,
    "gn:timezone":"Asia/Seoul",
    "iso:country":"KR",
    "name:rus_x_preferred":[
        "\u0422\u044d\u0433\u0443"
    ],
    "name:und_x_variant":[
        "Taegu-dong",
        "Taegu"
    ],
    "wof:name":"Taegu",
    "wof:placetype":"locality"
},
  "geometry": {"coordinates":[128.07277999999999,34.88889],"type":"Point"}
}