{
  "type": "Feature",
  "properties": {
    "gn:admin1_code":"13.0",
    "gn:asciiname":"Paejuri",
    "gn:country_code":"KR",
    "gn:dem":90,
    "gn:feature_class":"P",
    "gn:feature_code":"PPL",
    "gn:name":"Paejuri",
    "gn:population":0,
    "gn:timezone":"Asia/Seoul",
    "iso:country":"KR",
    "name:und_x_variant":[
        "\ubc30\uc8fc\ub9ac",
        "Baejuri",
        "Paejuri"
    ],
    "wof:name":"Paejuri",
    "wof:placetype":"locality"
},
  "geometry": {"coordinates":[127.455,37.41917],"type":"Point"}
}