{
  "type": "Feature",
  "properties": {
    "gn:admin1_code":"13.0",
    "gn:asciiname":"Apkoji",
    "gn:country_code":"KR",
    "gn:dem":85,
    "gn:feature_class":"P",
    "gn:feature_code":"PPL",
    "gn:name":"Apkoji",
    "gn:population":0,
    "gn:timezone":"Asia/Seoul",
    "iso:country":"KR",
    "name:und_x_variant":[
        "\uc55e\uace0\uc9c0",
        "Apgoji",
        "Apkoji"
    ],
    "wof:name":"Apkoji",
    "wof:placetype":"locality"
},
  "geometry": {"coordinates":[127.21778,37.28611],"type":"Point"}
}