{
  "type": "Feature",
  "properties": {
    "gn:admin1_code":"14.0",
    "gn:asciiname":"Akdae",
    "gn:country_code":"KR",
    "gn:dem":252,
    "gn:feature_class":"P",
    "gn:feature_code":"PPL",
    "gn:name":"Akdae",
    "gn:population":0,
    "gn:timezone":"Asia/Seoul",
    "iso:country":"KR",
    "name:kor_x_preferred":[
        "\uc545\ub300"
    ],
    "wof:name":"Akdae",
    "wof:placetype":"locality"
},
  "geometry": {"coordinates":[128.58921000000001,36.64058],"type":"Point"}
}