{
  "type": "Feature",
  "properties": {
    "gn:admin1_code":"13.0",
    "gn:asciiname":"Dojanggol",
    "gn:country_code":"KR",
    "gn:dem":13,
    "gn:feature_class":"P",
    "gn:feature_code":"PPL",
    "gn:name":"Dojanggol",
    "gn:population":0,
    "gn:timezone":"Asia/Seoul",
    "iso:country":"KR",
    "name:und_x_variant":[
        "\ub3c4\uc7a5\uace8",
        "Dojanggol",
        "Tojang-gol"
    ],
    "wof:name":"Dojanggol",
    "wof:placetype":"locality"
},
  "geometry": {"coordinates":[126.57567,37.61158],"type":"Point"}
}