{
  "type": "Feature",
  "properties": {
    "gn:admin1_code":"1.0",
    "gn:asciiname":"Gaecheokdanji",
    "gn:country_code":"KR",
    "gn:dem":322,
    "gn:feature_class":"P",
    "gn:feature_code":"PPL",
    "gn:name":"Gaecheokdanji",
    "gn:population":0,
    "gn:timezone":"Asia/Seoul",
    "iso:country":"KR",
    "name:kor_x_preferred":[
        "\uac1c\ucc99\ub2e8\uc9c0"
    ],
    "name:und_x_variant":[
        "Kaech\u2019\u014fk-tanji"
    ],
    "wof:name":"Gaecheokdanji",
    "wof:placetype":"locality"
},
  "geometry": {"coordinates":[126.3952,33.42364],"type":"Point"}
}