{
  "type": "Feature",
  "properties": {
    "gn:admin1_code":"13.0",
    "gn:asciiname":"Hapyeong",
    "gn:country_code":"KR",
    "gn:dem":45,
    "gn:feature_class":"P",
    "gn:feature_code":"PPL",
    "gn:name":"Hapyeong",
    "gn:population":0,
    "gn:timezone":"Asia/Seoul",
    "iso:country":"KR",
    "name:kor_x_preferred":[
        "\ud558\ud3c9"
    ],
    "name:und_x_variant":[
        "Hapyeong"
    ],
    "wof:name":"Hapyeong",
    "wof:placetype":"locality"
},
  "geometry": {"coordinates":[127.48399999999999,37.5041],"type":"Point"}
}