{
  "type": "Feature",
  "properties": {
    "gn:admin1_code":"16.0",
    "gn:asciiname":"Wolgok",
    "gn:country_code":"KR",
    "gn:dem":27,
    "gn:feature_class":"P",
    "gn:feature_code":"PPL",
    "gn:name":"Wolgok",
    "gn:population":0,
    "gn:timezone":"Asia/Seoul",
    "iso:country":"KR",
    "name:kor_x_preferred":[
        "\uc6d4\uace1"
    ],
    "name:kor_x_variant":[
        "W\u014flgok"
    ],
    "wof:name":"Wolgok",
    "wof:placetype":"locality"
},
  "geometry": {"coordinates":[127.32411,34.83309000000001],"type":"Point"}
}