{
  "type": "Feature",
  "properties": {
    "gn:admin1_code":"6.0",
    "gn:asciiname":"Won-dong",
    "gn:country_code":"KR",
    "gn:dem":344,
    "gn:feature_class":"P",
    "gn:feature_code":"PPL",
    "gn:name":"W\u014fn-dong",
    "gn:population":0,
    "gn:timezone":"Asia/Seoul",
    "iso:country":"KR",
    "name:kor_x_preferred":[
        "\uc6d0\ub3d9"
    ],
    "name:kor_x_variant":[
        "W\u014fn-dong"
    ],
    "wof:name":"Won-dong",
    "wof:placetype":"locality"
},
  "geometry": {"coordinates":[128.0274,37.2638],"type":"Point"}
}