{
  "type": "Feature",
  "properties": {
    "gn:admin1_code":"19.0",
    "gn:asciiname":"Eocheonggol",
    "gn:country_code":"KR",
    "gn:dem":161,
    "gn:feature_class":"P",
    "gn:feature_code":"PPL",
    "gn:name":"Eocheonggol",
    "gn:population":0,
    "gn:timezone":"Asia/Seoul",
    "iso:country":"KR",
    "name:und_x_variant":[
        "\uc5b4\uccad\uace8",
        "\u014ech\u2019\u014fng-gol",
        "Eocheonggol"
    ],
    "wof:name":"Eocheonggol",
    "wof:placetype":"locality"
},
  "geometry": {"coordinates":[127.42744,36.28303],"type":"Point"}
}