{
  "type": "Feature",
  "properties": {
    "gn:admin1_code":"14.0",
    "gn:asciiname":"Saemi",
    "gn:country_code":"KR",
    "gn:dem":252,
    "gn:feature_class":"P",
    "gn:feature_code":"PPL",
    "gn:name":"Saemi",
    "gn:population":0,
    "gn:timezone":"Asia/Seoul",
    "iso:country":"KR",
    "wof:name":"Saemi",
    "wof:placetype":"locality"
},
  "geometry": {"coordinates":[128.78222,36.80444],"type":"Point"}
}