{
  "type": "Feature",
  "properties": {
    "gn:admin1_code":"13.0",
    "gn:admin2_code":"Ans\u014fng-si",
    "gn:asciiname":"Utnamugol",
    "gn:country_code":"KR",
    "gn:dem":98,
    "gn:feature_class":"P",
    "gn:feature_code":"PPL",
    "gn:name":"Utnamugol",
    "gn:population":0,
    "gn:timezone":"Asia/Seoul",
    "iso:country":"KR",
    "name:kor_x_preferred":[
        "\uc637\ub098\ubb34\uace8"
    ],
    "name:kor_x_variant":[
        "\uc6c3\ub098\ubb34\uace8"
    ],
    "name:und_x_variant":[
        "Onnamu-gol",
        "Otnamu-gol",
        "Utnamugol"
    ],
    "wof:name":"Utnamugol",
    "wof:placetype":"locality"
},
  "geometry": {"coordinates":[127.32796,37.08997],"type":"Point"}
}