{
  "type": "Feature",
  "properties": {
    "gn:admin1_code":"20.0",
    "gn:asciiname":"Naejungsan",
    "gn:country_code":"KR",
    "gn:dem":722,
    "gn:feature_class":"P",
    "gn:feature_code":"PPL",
    "gn:name":"Naejungsan",
    "gn:population":0,
    "gn:timezone":"Asia/Seoul",
    "iso:country":"KR",
    "name:und_x_variant":[
        "Anjungsan",
        "\ub0b4\uc911\uc0b0",
        "Naejungsan"
    ],
    "wof:name":"Naejungsan",
    "wof:placetype":"locality"
},
  "geometry": {"coordinates":[127.70963,35.61732999999999],"type":"Point"}
}