{
  "type": "Feature",
  "properties": {
    "gn:admin1_code":"6.0",
    "gn:asciiname":"Ponmal",
    "gn:country_code":"KR",
    "gn:dem":140,
    "gn:feature_class":"P",
    "gn:feature_code":"PPL",
    "gn:name":"Ponmal",
    "gn:population":0,
    "gn:timezone":"Asia/Seoul",
    "iso:country":"KR",
    "name:und_x_variant":[
        "\ubcf8\ub9d0",
        "Ponmal"
    ],
    "wof:name":"Ponmal",
    "wof:placetype":"locality"
},
  "geometry": {"coordinates":[127.68832999999999,38.02417],"type":"Point"}
}