{
  "type": "Feature",
  "properties": {
    "gn:admin1_code":"19.0",
    "gn:asciiname":"Myogakgol",
    "gn:country_code":"KR",
    "gn:dem":156,
    "gn:feature_class":"P",
    "gn:feature_code":"PPL",
    "gn:name":"Myogakgol",
    "gn:population":0,
    "gn:timezone":"Asia/Seoul",
    "iso:country":"KR",
    "name:und_x_variant":[
        "\ubb18\uac01\uace8",
        "Myogak-kol",
        "Myogakgol"
    ],
    "wof:name":"Myogakgol",
    "wof:placetype":"locality"
},
  "geometry": {"coordinates":[127.39876,36.24081],"type":"Point"}
}