{
  "type": "Feature",
  "properties": {
    "gn:admin1_code":"16.0",
    "gn:asciiname":"Gwangtan",
    "gn:country_code":"KR",
    "gn:dem":149,
    "gn:feature_class":"P",
    "gn:feature_code":"PPL",
    "gn:name":"Gwangtan",
    "gn:population":0,
    "gn:timezone":"Asia/Seoul",
    "iso:country":"KR",
    "name:kor_x_preferred":[
        "\uad11\ud654"
    ],
    "name:kor_x_variant":[
        "\uad11\ud0c4"
    ],
    "name:und_x_variant":[
        "Kwanghwa",
        "Gwangtan",
        "Kwangt\u2019an-ni",
        "Kwangt\u2019an",
        "Kwangdan-ni"
    ],
    "wof:name":"Gwangtan",
    "wof:placetype":"locality"
},
  "geometry": {"coordinates":[127.07513,34.79685],"type":"Point"}
}