{
  "type": "Feature",
  "properties": {
    "gn:admin1_code":"6.0",
    "gn:asciiname":"Borigol",
    "gn:country_code":"KR",
    "gn:dem":102,
    "gn:feature_class":"P",
    "gn:feature_code":"PPL",
    "gn:name":"Borigol",
    "gn:population":0,
    "gn:timezone":"Asia/Seoul",
    "iso:country":"KR",
    "name:kor_x_preferred":[
        "\ubcf4\ub9ac\uace8"
    ],
    "name:kor_x_variant":[
        "\ubcf4\ub9bf\uace8"
    ],
    "name:und_x_variant":[
        "Porik-kol",
        "Borigol",
        "Boritgol"
    ],
    "wof:name":"Borigol",
    "wof:placetype":"locality"
},
  "geometry": {"coordinates":[127.58020999999999,37.6967],"type":"Point"}
}