{
  "type": "Feature",
  "properties": {
    "gn:admin1_code":"14.0",
    "gn:asciiname":"Sobyol-li",
    "gn:country_code":"KR",
    "gn:dem":170,
    "gn:feature_class":"P",
    "gn:feature_code":"PPL",
    "gn:name":"S\u014fby\u014fl-li",
    "gn:population":0,
    "gn:timezone":"Asia/Seoul",
    "iso:country":"KR",
    "name:und_x_variant":[
        "S\u014fby\u014fn",
        "\uc11c\ubcc0\ub9ac",
        "S\u014fby\u014fl-li"
    ],
    "wof:name":"Sobyol-li",
    "wof:placetype":"locality"
},
  "geometry": {"coordinates":[128.76668999999998,36.42381],"type":"Point"}
}