{
  "type": "Feature",
  "properties": {
    "gn:admin1_code":"6.0",
    "gn:asciiname":"Jidari",
    "gn:country_code":"KR",
    "gn:dem":292,
    "gn:feature_class":"P",
    "gn:feature_code":"PPL",
    "gn:name":"Jidari",
    "gn:population":0,
    "gn:timezone":"Asia/Seoul",
    "iso:country":"KR",
    "name:kor_x_preferred":[
        "\uc9c4\ub2e4\ub9ac"
    ],
    "name:kor_x_variant":[
        "\uc9c0\ub2e4\ub9ac"
    ],
    "name:und_x_variant":[
        "Chinda-ri",
        "Jidari"
    ],
    "wof:name":"Jidari",
    "wof:placetype":"locality"
},
  "geometry": {"coordinates":[128.32641000000001,37.97028],"type":"Point"}
}