{
  "type": "Feature",
  "properties": {
    "gn:admin1_code":"20.0",
    "gn:asciiname":"Chomma",
    "gn:country_code":"KR",
    "gn:dem":286,
    "gn:feature_class":"P",
    "gn:feature_code":"PPL",
    "gn:name":"Ch\u014fmma",
    "gn:population":0,
    "gn:timezone":"Asia/Seoul",
    "iso:country":"KR",
    "name:und_x_variant":[
        "\uc810\ub9c8",
        "Ch\u014fmma"
    ],
    "wof:name":"Chomma",
    "wof:placetype":"locality"
},
  "geometry": {"coordinates":[127.98555,35.52118],"type":"Point"}
}