{
  "type": "Feature",
  "properties": {
    "gn:admin1_code":"6.0",
    "gn:asciiname":"Mamu-ri",
    "gn:country_code":"KR",
    "gn:dem":214,
    "gn:feature_class":"P",
    "gn:feature_code":"PPL",
    "gn:name":"Mamu-ri",
    "gn:population":0,
    "gn:timezone":"Asia/Seoul",
    "iso:country":"KR",
    "name:kor_x_preferred":[
        "\ub9c8\ubb34\ub9ac"
    ],
    "name:und_x_variant":[
        "Much\u2019on",
        "Mamu-ri"
    ],
    "wof:name":"Mamu-ri",
    "wof:placetype":"locality"
},
  "geometry": {"coordinates":[128.09870000000001,37.5435],"type":"Point"}
}