{
  "type": "Feature",
  "properties": {
    "gn:admin1_code":"14.0",
    "gn:asciiname":"P'yongbakko-ri",
    "gn:country_code":"KR",
    "gn:dem":519,
    "gn:feature_class":"P",
    "gn:feature_code":"PPL",
    "gn:name":"P\u2019y\u014fngbakk\u014f-ri",
    "gn:population":0,
    "gn:timezone":"Asia/Seoul",
    "iso:country":"KR",
    "name:und_x_variant":[
        "P\u2019y\u014fngbat",
        "\ud3c9\ubc15\uac70\ub9ac",
        "P\u2019y\u014fngj\u014fn",
        "P\u2019y\u014fngbakk\u014f-ri"
    ],
    "wof:name":"P'yongbakko-ri",
    "wof:placetype":"locality"
},
  "geometry": {"coordinates":[129.17509999999999,36.9752],"type":"Point"}
}