{
  "type": "Feature",
  "properties": {
    "gn:admin1_code":"6.0",
    "gn:asciiname":"Yanjimal",
    "gn:country_code":"KR",
    "gn:dem":222,
    "gn:feature_class":"P",
    "gn:feature_code":"PPL",
    "gn:name":"Yanjimal",
    "gn:population":0,
    "gn:timezone":"Asia/Seoul",
    "iso:country":"KR",
    "name:kor_x_preferred":[
        "\uc591\uc9c0\ub9d0"
    ],
    "wof:name":"Yanjimal",
    "wof:placetype":"locality"
},
  "geometry": {"coordinates":[127.96160999999999,37.81334],"type":"Point"}
}