{
  "type": "Feature",
  "properties": {
    "gn:admin1_code":"5.0",
    "gn:asciiname":"Hagae-ri",
    "gn:country_code":"KR",
    "gn:dem":161,
    "gn:feature_class":"P",
    "gn:feature_code":"PPL",
    "gn:name":"Hagae-ri",
    "gn:population":0,
    "gn:timezone":"Asia/Seoul",
    "iso:country":"KR",
    "name:und_x_variant":[
        "\ud558\uac1c\ub9ac",
        "Hagae-ri"
    ],
    "wof:name":"Hagae-ri",
    "wof:placetype":"locality"
},
  "geometry": {"coordinates":[127.7928,36.4695],"type":"Point"}
}