{
  "type": "Feature",
  "properties": {
    "gn:admin1_code":"20.0",
    "gn:asciiname":"Nabuli",
    "gn:cc2":"KR",
    "gn:country_code":"KR",
    "gn:dem":86,
    "gn:feature_class":"P",
    "gn:feature_code":"PPL",
    "gn:name":"Nabuli",
    "gn:population":0,
    "gn:timezone":"Asia/Seoul",
    "iso:country":"KR",
    "name:und_x_variant":[
        "Nabul",
        "Nabul-ri",
        "Nabuli"
    ],
    "wof:name":"Nabuli",
    "wof:placetype":"locality"
},
  "geometry": {"coordinates":[128.03778,35.20861],"type":"Point"}
}