{
  "type": "Feature",
  "properties": {
    "gn:admin1_code":"20.0",
    "gn:asciiname":"Yonp'o",
    "gn:country_code":"KR",
    "gn:dem":15,
    "gn:feature_class":"P",
    "gn:feature_code":"PPL",
    "gn:name":"Y\u014fnp\u2019o",
    "gn:population":0,
    "gn:timezone":"Asia/Seoul",
    "iso:country":"KR",
    "name:und_x_variant":[
        "\uc5f0\ud3ec",
        "Y\u014fnp\u2019o"
    ],
    "wof:name":"Yonp'o",
    "wof:placetype":"locality"
},
  "geometry": {"coordinates":[128.48531,35.43533],"type":"Point"}
}