{
  "type": "Feature",
  "properties": {
    "gn:admin1_code":"6.0",
    "gn:asciiname":"Samgo-ri",
    "gn:country_code":"KR",
    "gn:dem":422,
    "gn:feature_class":"P",
    "gn:feature_code":"PPL",
    "gn:name":"Samg\u014f-ri",
    "gn:population":0,
    "gn:timezone":"Asia/Seoul",
    "iso:country":"KR",
    "name:kor_x_preferred":[
        "\uc0bc\uac70\ub9ac"
    ],
    "name:kor_x_variant":[
        "Samg\u014f-ri"
    ],
    "wof:name":"Samgo-ri",
    "wof:placetype":"locality"
},
  "geometry": {"coordinates":[127.91361000000001,37.58164],"type":"Point"}
}