{
  "type": "Feature",
  "properties": {
    "gn:admin1_code":"14.0",
    "gn:asciiname":"Koran",
    "gn:country_code":"KR",
    "gn:dem":411,
    "gn:feature_class":"P",
    "gn:feature_code":"PPL",
    "gn:name":"Koran",
    "gn:population":0,
    "gn:timezone":"Asia/Seoul",
    "iso:country":"KR",
    "name:und_x_variant":[
        "\uace8\uc548",
        "Koran"
    ],
    "wof:name":"Koran",
    "wof:placetype":"locality"
},
  "geometry": {"coordinates":[129.24420000000001,36.9081],"type":"Point"}
}