{
  "type": "Feature",
  "properties": {
    "gn:admin1_code":"20.0",
    "gn:asciiname":"Songgye",
    "gn:country_code":"KR",
    "gn:dem":6,
    "gn:feature_class":"P",
    "gn:feature_code":"PPL",
    "gn:name":"Songgye",
    "gn:population":0,
    "gn:timezone":"Asia/Seoul",
    "iso:country":"KR",
    "name:und_x_variant":[
        "\uc1a1\uacc4",
        "Songgye"
    ],
    "wof:name":"Songgye",
    "wof:placetype":"locality"
},
  "geometry": {"coordinates":[128.37157999999999,34.88569],"type":"Point"}
}