{
  "type": "Feature",
  "properties": {
    "gn:admin1_code":"14.0",
    "gn:asciiname":"Eupsil",
    "gn:country_code":"KR",
    "gn:dem":155,
    "gn:feature_class":"P",
    "gn:feature_code":"PPL",
    "gn:name":"Eupsil",
    "gn:population":0,
    "gn:timezone":"Asia/Seoul",
    "iso:country":"KR",
    "name:kor_x_preferred":[
        "\uc74d\uc2e4"
    ],
    "name:und_x_variant":[
        "Ugok-tong",
        "Ugok",
        "\u016cpsil",
        "Eupsil"
    ],
    "wof:name":"Eupsil",
    "wof:placetype":"locality"
},
  "geometry": {"coordinates":[128.44151000000002,36.74172],"type":"Point"}
}