{
  "type": "Feature",
  "properties": {
    "gn:admin1_code":"20.0",
    "gn:asciiname":"Hant'i-gol",
    "gn:country_code":"KR",
    "gn:dem":165,
    "gn:feature_class":"P",
    "gn:feature_code":"PPL",
    "gn:name":"Hant\u2019i-gol",
    "gn:population":0,
    "gn:timezone":"Asia/Seoul",
    "iso:country":"KR",
    "name:und_x_variant":[
        "\ud55c\ud2f0\uace8",
        "Hant\u2019i-gol"
    ],
    "wof:name":"Hant'i-gol",
    "wof:placetype":"locality"
},
  "geometry": {"coordinates":[128.46293,35.18656],"type":"Point"}
}