{
  "type": "Feature",
  "properties": {
    "gn:admin1_code":"16.0",
    "gn:asciiname":"Changjwa-ri",
    "gn:country_code":"KR",
    "gn:dem":6,
    "gn:feature_class":"P",
    "gn:feature_code":"PPL",
    "gn:name":"Changjwa-ri",
    "gn:population":0,
    "gn:timezone":"Asia/Seoul",
    "iso:country":"KR",
    "name:kor_x_preferred":[
        "\uc7a5\uc88c\ub9ac"
    ],
    "name:und_x_variant":[
        "Changsa-ri",
        "Changjwa",
        "Changjwa-ri"
    ],
    "wof:name":"Changjwa-ri",
    "wof:placetype":"locality"
},
  "geometry": {"coordinates":[127.34326,34.8383],"type":"Point"}
}