{
  "type": "Feature",
  "properties": {
    "gn:admin1_code":"17.0",
    "gn:asciiname":"P'yongdae-ri",
    "gn:country_code":"KR",
    "gn:dem":170,
    "gn:feature_class":"P",
    "gn:feature_code":"PPL",
    "gn:name":"P\u2019y\u014fngdae-ri",
    "gn:population":0,
    "gn:timezone":"Asia/Seoul",
    "iso:country":"KR",
    "name:und_x_variant":[
        "\ud3c9\ub300\ub9ac",
        "P\u2019y\u014fngdae-ri"
    ],
    "wof:name":"P'yongdae-ri",
    "wof:placetype":"locality"
},
  "geometry": {"coordinates":[127.5154,36.03],"type":"Point"}
}