{
  "type": "Feature",
  "properties": {
    "gn:admin1_code":"6.0",
    "gn:asciiname":"Jaegeonchon",
    "gn:country_code":"KR",
    "gn:dem":285,
    "gn:feature_class":"P",
    "gn:feature_code":"PPL",
    "gn:name":"Jaegeonchon",
    "gn:population":0,
    "gn:timezone":"Asia/Seoul",
    "iso:country":"KR",
    "name:und_x_variant":[
        "Chaeg\u014fnch\u2019on"
    ],
    "wof:name":"Jaegeonchon",
    "wof:placetype":"locality"
},
  "geometry": {"coordinates":[127.52222,38.26917],"type":"Point"}
}