{
  "type": "Feature",
  "properties": {
    "gn:admin1_code":"17.0",
    "gn:asciiname":"Jeommal",
    "gn:country_code":"KR",
    "gn:dem":38,
    "gn:feature_class":"P",
    "gn:feature_code":"PPL",
    "gn:name":"Jeommal",
    "gn:population":0,
    "gn:timezone":"Asia/Seoul",
    "iso:country":"KR",
    "name:und_x_variant":[
        "\uc810\ub9d0",
        "Ch\u014fm-mal",
        "Jeommal"
    ],
    "wof:name":"Jeommal",
    "wof:placetype":"locality"
},
  "geometry": {"coordinates":[127.17701,36.30425],"type":"Point"}
}