{
  "type": "Feature",
  "properties": {
    "gn:admin1_code":"6.0",
    "gn:asciiname":"Ido-dong",
    "gn:country_code":"KR",
    "gn:dem":13,
    "gn:feature_class":"P",
    "gn:feature_code":"PPL",
    "gn:name":"Ido-dong",
    "gn:population":0,
    "gn:timezone":"Asia/Seoul",
    "iso:country":"KR",
    "name:und_x_variant":[
        "\uc774\ub3c4\ub3d9",
        "Ido-dong"
    ],
    "wof:name":"Ido-dong",
    "wof:placetype":"locality"
},
  "geometry": {"coordinates":[129.10560000000001,37.4782],"type":"Point"}
}