{
  "type": "Feature",
  "properties": {
    "gn:admin1_code":"5.0",
    "gn:asciiname":"Masirani",
    "gn:country_code":"KR",
    "gn:dem":86,
    "gn:feature_class":"P",
    "gn:feature_code":"PPL",
    "gn:name":"Masirani",
    "gn:population":0,
    "gn:timezone":"Asia/Seoul",
    "iso:country":"KR",
    "name:kor_x_preferred":[
        "\ub9c8\uc2e4\uc548\uc774"
    ],
    "wof:name":"Masirani",
    "wof:placetype":"locality"
},
  "geometry": {"coordinates":[127.52558999999999,36.94739000000001],"type":"Point"}
}