{
  "type": "Feature",
  "properties": {
    "gn:admin1_code":"13.0",
    "gn:asciiname":"Namtteum",
    "gn:country_code":"KR",
    "gn:dem":33,
    "gn:feature_class":"P",
    "gn:feature_code":"PPL",
    "gn:name":"Namtteum",
    "gn:population":0,
    "gn:timezone":"Asia/Seoul",
    "iso:country":"KR",
    "name:und_x_variant":[
        "\ub0a8\ub738",
        "Namtteum",
        "Namtt\u016dm"
    ],
    "wof:name":"Namtteum",
    "wof:placetype":"locality"
},
  "geometry": {"coordinates":[127.11499999999999,37.11194],"type":"Point"}
}