{
  "type": "Feature",
  "properties": {
    "gn:admin1_code":"6.0",
    "gn:asciiname":"Kalmul-li",
    "gn:country_code":"KR",
    "gn:dem":304,
    "gn:feature_class":"P",
    "gn:feature_code":"PPL",
    "gn:name":"Kalmul-li",
    "gn:population":0,
    "gn:timezone":"Asia/Seoul",
    "iso:country":"KR",
    "name:kor_x_preferred":[
        "\uac08\ubb38\ub9ac"
    ],
    "wof:name":"Kalmul-li",
    "wof:placetype":"locality"
},
  "geometry": {"coordinates":[128.3519,37.1791],"type":"Point"}
}