{
  "type": "Feature",
  "properties": {
    "gn:admin1_code":"14.0",
    "gn:asciiname":"Dolmaraemi",
    "gn:country_code":"KR",
    "gn:dem":272,
    "gn:feature_class":"P",
    "gn:feature_code":"PPL",
    "gn:name":"Dolmaraemi",
    "gn:population":0,
    "gn:timezone":"Asia/Seoul",
    "iso:country":"KR",
    "name:kor_x_preferred":[
        "\ub3cc\ub9c8\ub798\ubbf8"
    ],
    "wof:name":"Dolmaraemi",
    "wof:placetype":"locality"
},
  "geometry": {"coordinates":[128.09391000000002,36.62081],"type":"Point"}
}