{
  "type": "Feature",
  "properties": {
    "gn:admin1_code":"14.0",
    "gn:asciiname":"Jungmochi",
    "gn:country_code":"KR",
    "gn:dem":237,
    "gn:feature_class":"P",
    "gn:feature_code":"PPL",
    "gn:name":"Jungmochi",
    "gn:population":0,
    "gn:timezone":"Asia/Seoul",
    "iso:country":"KR",
    "name:kor_x_preferred":[
        "\uc911\ubaa8\uce58"
    ],
    "wof:name":"Jungmochi",
    "wof:placetype":"locality"
},
  "geometry": {"coordinates":[128.62221,36.92609],"type":"Point"}
}