{
  "type": "Feature",
  "properties": {
    "gn:admin1_code":"6.0",
    "gn:asciiname":"Tasu-ri",
    "gn:country_code":"KR",
    "gn:dem":402,
    "gn:feature_class":"P",
    "gn:feature_code":"PPL",
    "gn:name":"Tasu-ri",
    "gn:population":0,
    "gn:timezone":"Asia/Seoul",
    "iso:country":"KR",
    "name:kor_x_preferred":[
        "\ub2e4\uc218\ub9ac"
    ],
    "wof:name":"Tasu-ri",
    "wof:placetype":"locality"
},
  "geometry": {"coordinates":[128.3717,37.403],"type":"Point"}
}