{
  "type": "Feature",
  "properties": {
    "gn:admin1_code":"3.0",
    "gn:asciiname":"O-dong",
    "gn:country_code":"KR",
    "gn:dem":286,
    "gn:feature_class":"P",
    "gn:feature_code":"PPL",
    "gn:name":"O-dong",
    "gn:population":0,
    "gn:timezone":"Asia/Seoul",
    "iso:country":"KR",
    "name:und_x_variant":[
        "\uc624\ub3d9",
        "O-dong"
    ],
    "wof:name":"O-dong",
    "wof:placetype":"locality"
},
  "geometry": {"coordinates":[127.35463,35.72547],"type":"Point"}
}