{
  "type": "Feature",
  "properties": {
    "gn:admin1_code":"5.0",
    "gn:asciiname":"Seian",
    "gn:country_code":"KR",
    "gn:dem":99,
    "gn:feature_class":"P",
    "gn:feature_code":"PPL",
    "gn:name":"Seian",
    "gn:population":0,
    "gn:timezone":"Asia/Seoul",
    "iso:country":"KR",
    "name:und_x_variant":[
        "Ch\u2019\u014fngan"
    ],
    "wof:name":"Seian",
    "wof:placetype":"locality"
},
  "geometry": {"coordinates":[127.63333,36.76667],"type":"Point"}
}