{
  "type": "Feature",
  "properties": {
    "gn:admin1_code":"14.0",
    "gn:asciiname":"Migok",
    "gn:country_code":"KR",
    "gn:dem":293,
    "gn:feature_class":"P",
    "gn:feature_code":"PPL",
    "gn:name":"Migok",
    "gn:population":0,
    "gn:timezone":"Asia/Seoul",
    "iso:country":"KR",
    "name:und_x_variant":[
        "\ubbf8\uace1",
        "Migok"
    ],
    "wof:name":"Migok",
    "wof:placetype":"locality"
},
  "geometry": {"coordinates":[128.09438,35.98217],"type":"Point"}
}