{
  "type": "Feature",
  "properties": {
    "gn:admin1_code":"21.0",
    "gn:asciiname":"Yeonbong",
    "gn:country_code":"KR",
    "gn:dem":150,
    "gn:feature_class":"P",
    "gn:feature_code":"PPL",
    "gn:name":"Yeonbong",
    "gn:population":0,
    "gn:timezone":"Asia/Seoul",
    "iso:country":"KR",
    "name:kor_x_preferred":[
        "\uc5f0\ubd09"
    ],
    "wof:name":"Yeonbong",
    "wof:placetype":"locality"
},
  "geometry": {"coordinates":[129.09679,35.51087000000001],"type":"Point"}
}