{
  "type": "Feature",
  "properties": {
    "gn:admin1_code":"16.0",
    "gn:asciiname":"Sojin",
    "gn:country_code":"KR",
    "gn:dem":41,
    "gn:feature_class":"P",
    "gn:feature_code":"PPL",
    "gn:name":"S\u014fjin",
    "gn:population":0,
    "gn:timezone":"Asia/Seoul",
    "iso:country":"KR",
    "name:kor_x_preferred":[
        "\uc11c\uc9c4"
    ],
    "name:kor_x_variant":[
        "S\u014fjin"
    ],
    "wof:name":"Sojin",
    "wof:placetype":"locality"
},
  "geometry": {"coordinates":[126.64082999999999,34.13389],"type":"Point"}
}