{
  "type": "Feature",
  "properties": {
    "gn:admin1_code":"17.0",
    "gn:asciiname":"Soep'yon",
    "gn:country_code":"KR",
    "gn:dem":76,
    "gn:feature_class":"P",
    "gn:feature_code":"PPL",
    "gn:name":"Soep\u2019y\u014fn",
    "gn:population":0,
    "gn:timezone":"Asia/Seoul",
    "iso:country":"KR",
    "name:und_x_variant":[
        "\uc1e0\ud3b8",
        "Soep\u2019y\u014fn"
    ],
    "wof:name":"Soep'yon",
    "wof:placetype":"locality"
},
  "geometry": {"coordinates":[126.8171,36.3937],"type":"Point"}
}