{
  "type": "Feature",
  "properties": {
    "gn:admin1_code":"16.0",
    "gn:asciiname":"Taesal-li",
    "gn:country_code":"KR",
    "gn:dem":210,
    "gn:feature_class":"P",
    "gn:feature_code":"PPL",
    "gn:name":"Taesal-li",
    "gn:population":0,
    "gn:timezone":"Asia/Seoul",
    "iso:country":"KR",
    "name:kor_x_preferred":[
        "\ub300\uc0b0\ub9ac"
    ],
    "name:und_x_variant":[
        "Taesan-ni",
        "Taesal-li"
    ],
    "wof:name":"Taesal-li",
    "wof:placetype":"locality"
},
  "geometry": {"coordinates":[127.0147,34.70375],"type":"Point"}
}