{
  "type": "Feature",
  "properties": {
    "gn:admin1_code":"14.0",
    "gn:asciiname":"Saema",
    "gn:country_code":"KR",
    "gn:dem":126,
    "gn:feature_class":"P",
    "gn:feature_code":"PPL",
    "gn:name":"Saema",
    "gn:population":0,
    "gn:timezone":"Asia/Seoul",
    "iso:country":"KR",
    "name:und_x_variant":[
        "\uc0c8\ub9c8",
        "Saema"
    ],
    "wof:name":"Saema",
    "wof:placetype":"locality"
},
  "geometry": {"coordinates":[128.15880000000001,36.2717],"type":"Point"}
}