{
  "type": "Feature",
  "properties": {
    "gn:admin1_code":"14.0",
    "gn:asciiname":"Gamdonggol",
    "gn:country_code":"KR",
    "gn:dem":437,
    "gn:feature_class":"P",
    "gn:feature_code":"PPL",
    "gn:name":"Gamdonggol",
    "gn:population":0,
    "gn:timezone":"Asia/Seoul",
    "iso:country":"KR",
    "name:kor_x_preferred":[
        "\uac10\ub3d9\uace8"
    ],
    "wof:name":"Gamdonggol",
    "wof:placetype":"locality"
},
  "geometry": {"coordinates":[128.86412000000001,36.98315],"type":"Point"}
}