{
  "type": "Feature",
  "properties": {
    "gn:admin1_code":"13.0",
    "gn:asciiname":"Deogu-ri",
    "gn:country_code":"KR",
    "gn:dem":56,
    "gn:feature_class":"P",
    "gn:feature_code":"PPLL",
    "gn:name":"Deogu-ri",
    "gn:population":0,
    "gn:timezone":"Asia/Seoul",
    "iso:country":"KR",
    "name:und_x_variant":[
        "\ub355\uc6b0\ub9ac",
        "Deogu-ri",
        "T\u014fgu-ri"
    ],
    "wof:name":"Deogu-ri",
    "wof:placetype":"locality"
},
  "geometry": {"coordinates":[126.91667,37.17278],"type":"Point"}
}