{
  "type": "Feature",
  "properties": {
    "gn:admin1_code":"20.0",
    "gn:asciiname":"Tokpong-ni",
    "gn:country_code":"KR",
    "gn:dem":90,
    "gn:feature_class":"P",
    "gn:feature_code":"PPLL",
    "gn:name":"T\u014fkpong-ni",
    "gn:population":0,
    "gn:timezone":"Asia/Seoul",
    "iso:country":"KR",
    "name:eng_x_preferred":[
        "Tokpong"
    ],
    "name:eng_x_variant":[
        "Tokpong-ni"
    ],
    "name:und_x_variant":[
        "\ub355\ubd09\ub9ac",
        "T\u014fkpong-ni"
    ],
    "wof:name":"Tokpong",
    "wof:placetype":"locality"
},
  "geometry": {"coordinates":[128.28357,35.61271],"type":"Point"}
}