{
  "type": "Feature",
  "properties": {
    "gn:admin1_code":"13.0",
    "gn:asciiname":"Geonui",
    "gn:country_code":"KR",
    "gn:dem":32,
    "gn:feature_class":"P",
    "gn:feature_code":"PPL",
    "gn:name":"Geonui",
    "gn:population":0,
    "gn:timezone":"Asia/Seoul",
    "iso:country":"KR",
    "name:und_x_variant":[
        "\uac74\uc758",
        "Geonui",
        "K\u014fn\u016di"
    ],
    "wof:name":"Geonui",
    "wof:placetype":"locality"
},
  "geometry": {"coordinates":[126.94891,37.05108],"type":"Point"}
}