{
  "type": "Feature",
  "properties": {
    "gn:admin1_code":"3.0",
    "gn:asciiname":"Kyodong-ni",
    "gn:cc2":"KR",
    "gn:country_code":"KR",
    "gn:dem":13,
    "gn:feature_class":"P",
    "gn:feature_code":"PPL",
    "gn:name":"Kyodong-ni",
    "gn:population":0,
    "gn:timezone":"Asia/Seoul",
    "iso:country":"KR",
    "name:und_x_variant":[
        "Kyodong",
        "Kyodong-ni"
    ],
    "wof:name":"Kyodong-ni",
    "wof:placetype":"locality"
},
  "geometry": {"coordinates":[126.95583000000001,36.11556],"type":"Point"}
}