{
  "type": "Feature",
  "properties": {
    "gn:admin1_code":"6.0",
    "gn:asciiname":"Banggol",
    "gn:country_code":"KR",
    "gn:dem":425,
    "gn:feature_class":"P",
    "gn:feature_code":"PPL",
    "gn:name":"Banggol",
    "gn:population":0,
    "gn:timezone":"Asia/Seoul",
    "iso:country":"KR",
    "name:kor_x_preferred":[
        "\ubc29\uace8"
    ],
    "name:und_x_variant":[
        "Pang-gol",
        "Banggol"
    ],
    "wof:name":"Banggol",
    "wof:placetype":"locality"
},
  "geometry": {"coordinates":[128.37961000000001,37.9445],"type":"Point"}
}