{
  "type": "Feature",
  "properties": {
    "gn:admin1_code":"13.0",
    "gn:asciiname":"Kusan-mal",
    "gn:country_code":"KR",
    "gn:dem":57,
    "gn:feature_class":"P",
    "gn:feature_code":"PPLL",
    "gn:name":"Kusan-mal",
    "gn:population":0,
    "gn:timezone":"Asia/Seoul",
    "iso:country":"KR",
    "name:und_x_variant":[
        "\uad6c\uc0b0\ub9d0",
        "Gusan-mal",
        "Kusan-mal"
    ],
    "wof:name":"Kusan-mal",
    "wof:placetype":"locality"
},
  "geometry": {"coordinates":[126.93194,37.32361],"type":"Point"}
}