{
  "type": "Feature",
  "properties": {
    "gn:admin1_code":"5.0",
    "gn:asciiname":"Songmun",
    "gn:country_code":"KR",
    "gn:dem":234,
    "gn:feature_class":"P",
    "gn:feature_code":"PPL",
    "gn:name":"S\u014fngmun",
    "gn:population":0,
    "gn:timezone":"Asia/Seoul",
    "iso:country":"KR",
    "name:kor_x_preferred":[
        "\uc11d\ubb38"
    ],
    "name:kor_x_variant":[
        "S\u014fngmun"
    ],
    "wof:name":"Songmun",
    "wof:placetype":"locality"
},
  "geometry": {"coordinates":[128.0301,37.1061],"type":"Point"}
}