{
  "type": "Feature",
  "properties": {
    "gn:admin1_code":"12.0",
    "gn:asciiname":"Jogu-chon",
    "gn:country_code":"KR",
    "gn:dem":38,
    "gn:feature_class":"P",
    "gn:feature_code":"PPL",
    "gn:name":"Jogu-chon",
    "gn:population":0,
    "gn:timezone":"Asia/Seoul",
    "iso:country":"KR",
    "name:und_x_variant":[
        "\uc870\uad6c\ucd0c",
        "Jogu-chon",
        "Chogu-ch\u2019on"
    ],
    "wof:name":"Jogu-chon",
    "wof:placetype":"locality"
},
  "geometry": {"coordinates":[126.43694000000001,37.65472000000001],"type":"Point"}
}