{
  "type": "Feature",
  "properties": {
    "gn:admin1_code":"13.0",
    "gn:asciiname":"Ponghwa-ch'on",
    "gn:country_code":"KR",
    "gn:dem":40,
    "gn:feature_class":"P",
    "gn:feature_code":"PPL",
    "gn:name":"Ponghwa-ch\u2019on",
    "gn:population":0,
    "gn:timezone":"Asia/Seoul",
    "iso:country":"KR",
    "name:und_x_variant":[
        "\ubd09\ud654\ucd0c",
        "Ponghwa-ch\u2019on"
    ],
    "wof:name":"Ponghwa-ch'on",
    "wof:placetype":"locality"
},
  "geometry": {"coordinates":[126.98439999999999,38.0004],"type":"Point"}
}