{
  "type": "Feature",
  "properties": {
    "gn:admin1_code":"5.0",
    "gn:asciiname":"Songjong",
    "gn:country_code":"KR",
    "gn:dem":135,
    "gn:feature_class":"P",
    "gn:feature_code":"PPL",
    "gn:name":"Songj\u014fng",
    "gn:population":0,
    "gn:timezone":"Asia/Seoul",
    "iso:country":"KR",
    "name:kor_x_preferred":[
        "\uc1a1\uc815"
    ],
    "name:kor_x_variant":[
        "Songj\u014fng"
    ],
    "wof:name":"Songjong",
    "wof:placetype":"locality"
},
  "geometry": {"coordinates":[127.95440000000001,37.0958],"type":"Point"}
}