{
  "type": "Feature",
  "properties": {
    "gn:admin1_code":"13.0",
    "gn:admin2_code":"Ans\u014fng-si",
    "gn:asciiname":"Dongan",
    "gn:country_code":"KR",
    "gn:dem":92,
    "gn:feature_class":"P",
    "gn:feature_code":"PPL",
    "gn:name":"Dongan",
    "gn:population":0,
    "gn:timezone":"Asia/Seoul",
    "iso:country":"KR",
    "name:kor_x_preferred":[
        "\ub3d9\uc548"
    ],
    "name:und_x_variant":[
        "Tongan",
        "Dongan"
    ],
    "wof:name":"Dongan",
    "wof:placetype":"locality"
},
  "geometry": {"coordinates":[127.31564,37.05237],"type":"Point"}
}