{
  "type": "Feature",
  "properties": {
    "gn:admin1_code":"13.0",
    "gn:asciiname":"Daedong",
    "gn:country_code":"KR",
    "gn:dem":72,
    "gn:feature_class":"P",
    "gn:feature_code":"PPL",
    "gn:name":"Daedong",
    "gn:population":0,
    "gn:timezone":"Asia/Seoul",
    "iso:country":"KR",
    "name:kor_x_preferred":[
        "\ub300\ub3d9"
    ],
    "name:und_x_variant":[
        "\ub300\ub3d9",
        "Daedong"
    ],
    "wof:name":"Daedong",
    "wof:placetype":"locality"
},
  "geometry": {"coordinates":[127.2225,37.6182],"type":"Point"}
}