{
  "type": "Feature",
  "properties": {
    "gn:admin1_code":"20.0",
    "gn:asciiname":"Changja-dong",
    "gn:country_code":"KR",
    "gn:dem":197,
    "gn:feature_class":"P",
    "gn:feature_code":"PPL",
    "gn:name":"Changja-dong",
    "gn:population":0,
    "gn:timezone":"Asia/Seoul",
    "iso:country":"KR",
    "name:und_x_variant":[
        "\uc7a5\uc790\ub3d9",
        "Changja-dong"
    ],
    "wof:name":"Changja-dong",
    "wof:placetype":"locality"
},
  "geometry": {"coordinates":[127.80249000000001,35.61620999999999],"type":"Point"}
}