{
  "type": "Feature",
  "properties": {
    "gn:admin1_code":"16.0",
    "gn:asciiname":"Gosajeong",
    "gn:country_code":"KR",
    "gn:dem":57,
    "gn:feature_class":"P",
    "gn:feature_code":"PPL",
    "gn:name":"Gosajeong",
    "gn:population":0,
    "gn:timezone":"Asia/Seoul",
    "iso:country":"KR",
    "name:kor_x_preferred":[
        "\uace0\uc0ac\uc815"
    ],
    "wof:name":"Gosajeong",
    "wof:placetype":"locality"
},
  "geometry": {"coordinates":[126.98724,35.05224],"type":"Point"}
}