{
  "type": "Feature",
  "properties": {
    "gn:admin1_code":"3.0",
    "gn:asciiname":"Chibo",
    "gn:country_code":"KR",
    "gn:dem":535,
    "gn:feature_class":"P",
    "gn:feature_code":"PPL",
    "gn:name":"Chibo",
    "gn:population":0,
    "gn:timezone":"Asia/Seoul",
    "iso:country":"KR",
    "name:und_x_variant":[
        "\uc9c0\ubcf4",
        "Chiboch\u2019on",
        "Chibo"
    ],
    "wof:name":"Chibo",
    "wof:placetype":"locality"
},
  "geometry": {"coordinates":[127.58945,35.65065999999999],"type":"Point"}
}