{
  "type": "Feature",
  "properties": {
    "gn:admin1_code":"14.0",
    "gn:asciiname":"Chukchon",
    "gn:cc2":"KR",
    "gn:country_code":"KR",
    "gn:dem":261,
    "gn:feature_class":"P",
    "gn:feature_code":"PPL",
    "gn:name":"Chukch\u014fn",
    "gn:population":0,
    "gn:timezone":"Asia/Seoul",
    "iso:country":"KR",
    "name:und_x_variant":[
        "Chikuden-d\u014d",
        "Chukch\u014fn-dong",
        "Chukch\u014fn",
        "\uc8fd\uc804\ub9ac",
        "Chukch\u014fl-li"
    ],
    "wof:name":"Chukchon",
    "wof:placetype":"locality"
},
  "geometry": {"coordinates":[128.91666999999998,36.15],"type":"Point"}
}