{
  "type": "Feature",
  "properties": {
    "gn:admin1_code":"5.0",
    "gn:asciiname":"Witgeolpigi",
    "gn:country_code":"KR",
    "gn:dem":125,
    "gn:feature_class":"P",
    "gn:feature_code":"PPL",
    "gn:name":"Witgeolpigi",
    "gn:population":0,
    "gn:timezone":"Asia/Seoul",
    "iso:country":"KR",
    "name:kor_x_preferred":[
        "\uc717\uac78\ud53c\uae30"
    ],
    "name:kor_x_variant":[
        "Wikk\u014flp\u2019igi"
    ],
    "wof:name":"Witgeolpigi",
    "wof:placetype":"locality"
},
  "geometry": {"coordinates":[127.821,37.04117],"type":"Point"}
}