{
  "type": "Feature",
  "properties": {
    "gn:admin1_code":"14.0",
    "gn:asciiname":"Songi-gol",
    "gn:country_code":"KR",
    "gn:dem":503,
    "gn:feature_class":"P",
    "gn:feature_code":"PPL",
    "gn:name":"Songi-gol",
    "gn:population":0,
    "gn:timezone":"Asia/Seoul",
    "iso:country":"KR",
    "name:und_x_variant":[
        "\uc1a1\uc774\uace8",
        "Songi-gol"
    ],
    "wof:name":"Songi-gol",
    "wof:placetype":"locality"
},
  "geometry": {"coordinates":[129.13538,36.23127],"type":"Point"}
}