{
  "type": "Feature",
  "properties": {
    "gn:admin1_code":"6.0",
    "gn:asciiname":"Chojil-li",
    "gn:cc2":"KR",
    "gn:country_code":"KR",
    "gn:dem":20,
    "gn:feature_class":"P",
    "gn:feature_code":"PPL",
    "gn:name":"Ch\u014fjil-li",
    "gn:population":0,
    "gn:timezone":"Asia/Seoul",
    "iso:country":"KR",
    "name:kor_x_preferred":[
        "\uc870\uc9c8\ub9ac"
    ],
    "name:und_x_variant":[
        "Ch\u014fjin-ni",
        "Ch\u014fjil-li",
        "Jejil-ri"
    ],
    "wof:name":"Chojil-li",
    "wof:placetype":"locality"
},
  "geometry": {"coordinates":[128.40360999999999,38.55583],"type":"Point"}
}