{
  "type": "Feature",
  "properties": {
    "gn:admin1_code":"21.0",
    "gn:asciiname":"Songni",
    "gn:country_code":"KR",
    "gn:dem":4,
    "gn:feature_class":"P",
    "gn:feature_code":"PPL",
    "gn:name":"Songni",
    "gn:population":0,
    "gn:timezone":"Asia/Seoul",
    "iso:country":"KR",
    "name:kor_x_preferred":[
        "\uc1a1\ub9ac"
    ],
    "wof:name":"Songni",
    "wof:placetype":"locality"
},
  "geometry": {"coordinates":[129.32461999999998,35.34789],"type":"Point"}
}