{
  "type": "Feature",
  "properties": {
    "gn:admin1_code":"17.0",
    "gn:asciiname":"Kolsagosi",
    "gn:cc2":"KR",
    "gn:country_code":"KR",
    "gn:dem":113,
    "gn:feature_class":"P",
    "gn:feature_code":"PPL",
    "gn:name":"Kolsagosi",
    "gn:population":0,
    "gn:timezone":"Asia/Seoul",
    "iso:country":"KR",
    "name:und_x_variant":[
        "Sangsadam",
        "Kolsagosi"
    ],
    "wof:name":"Kolsagosi",
    "wof:placetype":"locality"
},
  "geometry": {"coordinates":[127.26667,36.83333],"type":"Point"}
}