{
  "type": "Feature",
  "properties": {
    "gn:admin1_code":"13.0",
    "gn:asciiname":"Nongchon",
    "gn:country_code":"KR",
    "gn:dem":45,
    "gn:feature_class":"P",
    "gn:feature_code":"PPL",
    "gn:name":"Nongchon",
    "gn:population":0,
    "gn:timezone":"Asia/Seoul",
    "iso:country":"KR",
    "name:kor_x_preferred":[
        "\ub18d\ucd0c"
    ],
    "name:und_x_variant":[
        "Nongch\u2019on-ni",
        "Nong-ch\u2019on",
        "Nongchon"
    ],
    "wof:name":"Nongchon",
    "wof:placetype":"locality"
},
  "geometry": {"coordinates":[127.28131,36.98475],"type":"Point"}
}