{
  "type": "Feature",
  "properties": {
    "gn:admin1_code":"14.0",
    "gn:asciiname":"Tundok",
    "gn:country_code":"KR",
    "gn:dem":64,
    "gn:feature_class":"P",
    "gn:feature_code":"PPL",
    "gn:name":"Tund\u014fk",
    "gn:population":0,
    "gn:timezone":"Asia/Seoul",
    "iso:country":"KR",
    "name:und_x_variant":[
        "\ub454\ub355",
        "Tund\u014fgi",
        "Tund\u014fk"
    ],
    "wof:name":"Tundok",
    "wof:placetype":"locality"
},
  "geometry": {"coordinates":[128.24293,35.74958],"type":"Point"}
}