{
  "type": "Feature",
  "properties": {
    "gn:admin1_code":"14.0",
    "gn:asciiname":"Muran",
    "gn:country_code":"KR",
    "gn:dem":260,
    "gn:feature_class":"P",
    "gn:feature_code":"PPL",
    "gn:name":"Muran",
    "gn:population":0,
    "gn:timezone":"Asia/Seoul",
    "iso:country":"KR",
    "name:ceb_x_preferred":[
        "Muran"
    ],
    "name:kor_x_preferred":[
        "\ubb3c\uc548"
    ],
    "name:swe_x_preferred":[
        "Muran"
    ],
    "wof:name":"Muran",
    "wof:placetype":"locality"
},
  "geometry": {"coordinates":[128.48728,36.76828],"type":"Point"}
}