{
  "type": "Feature",
  "properties": {
    "gn:admin1_code":"16.0",
    "gn:asciiname":"Chillyeongol",
    "gn:country_code":"KR",
    "gn:dem":24,
    "gn:feature_class":"P",
    "gn:feature_code":"PPL",
    "gn:name":"Chillyeongol",
    "gn:population":0,
    "gn:timezone":"Asia/Seoul",
    "iso:country":"KR",
    "name:kor_x_preferred":[
        "\uce60\ub144\uace8"
    ],
    "wof:name":"Chillyeongol",
    "wof:placetype":"locality"
},
  "geometry": {"coordinates":[126.7188,35.05486],"type":"Point"}
}