{
  "type": "Feature",
  "properties": {
    "gn:admin1_code":"20.0",
    "gn:asciiname":"Apkok",
    "gn:country_code":"KR",
    "gn:dem":44,
    "gn:feature_class":"P",
    "gn:feature_code":"PPL",
    "gn:name":"Apkok",
    "gn:population":0,
    "gn:timezone":"Asia/Seoul",
    "iso:country":"KR",
    "name:und_x_variant":[
        "\uc555\uace1",
        "Apkok"
    ],
    "wof:name":"Apkok",
    "wof:placetype":"locality"
},
  "geometry": {"coordinates":[128.28315000000001,35.29274],"type":"Point"}
}