{
  "type": "Feature",
  "properties": {
    "gn:admin1_code":"14.0",
    "gn:asciiname":"Chungwang-ni",
    "gn:country_code":"KR",
    "gn:dem":87,
    "gn:feature_class":"P",
    "gn:feature_code":"PPL",
    "gn:name":"Chungwang-ni",
    "gn:population":0,
    "gn:timezone":"Asia/Seoul",
    "iso:country":"KR",
    "name:und_x_variant":[
        "\uc911\uc655\ub9ac",
        "Chungwang-ni"
    ],
    "wof:name":"Chungwang-ni",
    "wof:placetype":"locality"
},
  "geometry": {"coordinates":[128.1165,36.1814],"type":"Point"}
}