{
  "type": "Feature",
  "properties": {
    "gn:admin1_code":"21.0",
    "gn:asciiname":"Seokcheon",
    "gn:country_code":"KR",
    "gn:dem":51,
    "gn:feature_class":"P",
    "gn:feature_code":"PPL",
    "gn:name":"Seokcheon",
    "gn:population":0,
    "gn:timezone":"Asia/Seoul",
    "iso:country":"KR",
    "name:kor_x_preferred":[
        "\uc11d\ucc9c"
    ],
    "wof:name":"Seokcheon",
    "wof:placetype":"locality"
},
  "geometry": {"coordinates":[129.23327,35.47061],"type":"Point"}
}