{
  "type": "Feature",
  "properties": {
    "gn:admin1_code":"16.0",
    "gn:asciiname":"Chang-dong",
    "gn:country_code":"KR",
    "gn:dem":59,
    "gn:feature_class":"P",
    "gn:feature_code":"PPL",
    "gn:name":"Chang-dong",
    "gn:population":0,
    "gn:timezone":"Asia/Seoul",
    "iso:country":"KR",
    "name:kor_x_preferred":[
        "\uc7a5\ub3d9"
    ],
    "name:und_x_variant":[
        "Changdong-ni",
        "Chang-dong"
    ],
    "wof:name":"Chang-dong",
    "wof:placetype":"locality"
},
  "geometry": {"coordinates":[126.72139,34.61222],"type":"Point"}
}