{
  "type": "Feature",
  "properties": {
    "gn:admin1_code":"11.0",
    "gn:asciiname":"Singiro-dong",
    "gn:country_code":"KR",
    "gn:dem":16,
    "gn:feature_class":"P",
    "gn:feature_code":"PPL",
    "gn:name":"Singiro-dong",
    "gn:population":0,
    "gn:timezone":"Asia/Seoul",
    "iso:country":"KR",
    "name:und_x_variant":[
        "\uc2e0\uae385\ub3d9",
        "Singiro-dong",
        "Sin\u2019giro-dong"
    ],
    "wof:name":"Singiro-dong",
    "wof:placetype":"locality"
},
  "geometry": {"coordinates":[126.90528,37.50083],"type":"Point"}
}