{
  "type": "Feature",
  "properties": {
    "gn:admin1_code":"14.0",
    "gn:asciiname":"Iha-ri",
    "gn:country_code":"KR",
    "gn:dem":206,
    "gn:feature_class":"P",
    "gn:feature_code":"PPL",
    "gn:name":"Iha-ri",
    "gn:population":0,
    "gn:timezone":"Asia/Seoul",
    "iso:country":"KR",
    "name:kor_x_preferred":[
        "\uc774\ud558\ub9ac"
    ],
    "wof:name":"Iha-ri",
    "wof:placetype":"locality"
},
  "geometry": {"coordinates":[128.73401000000001,36.60811],"type":"Point"}
}