{
  "type": "Feature",
  "properties": {
    "gn:admin1_code":"19.0",
    "gn:asciiname":"Araetteotgol",
    "gn:country_code":"KR",
    "gn:dem":81,
    "gn:feature_class":"P",
    "gn:feature_code":"PPL",
    "gn:name":"Araetteotgol",
    "gn:population":0,
    "gn:timezone":"Asia/Seoul",
    "iso:country":"KR",
    "name:kor_x_preferred":[
        "\uc544\ub7ab\ud143\uace8"
    ],
    "wof:name":"Araetteotgol",
    "wof:placetype":"locality"
},
  "geometry": {"coordinates":[127.33691,36.38597],"type":"Point"}
}