{
  "type": "Feature",
  "properties": {
    "gn:admin1_code":"17.0",
    "gn:asciiname":"Seonangdang-i",
    "gn:country_code":"KR",
    "gn:dem":18,
    "gn:feature_class":"P",
    "gn:feature_code":"PPL",
    "gn:name":"Seonangdang-i",
    "gn:population":0,
    "gn:timezone":"Asia/Seoul",
    "iso:country":"KR",
    "name:und_x_variant":[
        "\uc11c\ub0ad\ub2f9\uc774",
        "Seonangdang-i",
        "S\u014fnangdangi"
    ],
    "wof:name":"Seonangdang-i",
    "wof:placetype":"locality"
},
  "geometry": {"coordinates":[126.54416999999999,37.00444],"type":"Point"}
}