{
  "type": "Feature",
  "properties": {
    "gn:admin1_code":"14.0",
    "gn:asciiname":"Jungdan",
    "gn:country_code":"KR",
    "gn:dem":5,
    "gn:feature_class":"P",
    "gn:feature_code":"PPL",
    "gn:name":"Jungdan",
    "gn:population":0,
    "gn:timezone":"Asia/Seoul",
    "iso:country":"KR",
    "name:kor_x_preferred":[
        "\uc911\ub2e8"
    ],
    "wof:name":"Jungdan",
    "wof:placetype":"locality"
},
  "geometry": {"coordinates":[129.32578000000001,35.99290999999999],"type":"Point"}
}