{
  "type": "Feature",
  "properties": {
    "gn:admin1_code":"14.0",
    "gn:asciiname":"Piri-gol",
    "gn:country_code":"KR",
    "gn:dem":310,
    "gn:feature_class":"P",
    "gn:feature_code":"PPL",
    "gn:name":"Piri-gol",
    "gn:population":0,
    "gn:timezone":"Asia/Seoul",
    "iso:country":"KR",
    "name:und_x_variant":[
        "\ube44\ub9ac\uace8",
        "Piri-gol"
    ],
    "wof:name":"Piri-gol",
    "wof:placetype":"locality"
},
  "geometry": {"coordinates":[129.16480000000001,36.7114],"type":"Point"}
}