{
  "type": "Feature",
  "properties": {
    "gn:admin1_code":"11.0",
    "gn:asciiname":"Sandangi-dong",
    "gn:country_code":"KR",
    "gn:dem":37,
    "gn:feature_class":"P",
    "gn:feature_code":"PPL",
    "gn:name":"Sandangi-dong",
    "gn:population":0,
    "gn:timezone":"Asia/Seoul",
    "iso:country":"KR",
    "name:und_x_variant":[
        "\uc0ac\ub2f92\ub3d9",
        "Sandangi-dong"
    ],
    "wof:name":"Sandangi-dong",
    "wof:placetype":"locality"
},
  "geometry": {"coordinates":[126.97750000000001,37.48889000000001],"type":"Point"}
}