{
  "type": "Feature",
  "properties": {
    "gn:admin1_code":"6.0",
    "gn:asciiname":"Su-ri",
    "gn:country_code":"KR",
    "gn:dem":54,
    "gn:feature_class":"P",
    "gn:feature_code":"PPL",
    "gn:name":"Su-ri",
    "gn:population":0,
    "gn:timezone":"Asia/Seoul",
    "iso:country":"KR",
    "name:kor_x_preferred":[
        "\uc218\ub9ac"
    ],
    "wof:name":"Su-ri",
    "wof:placetype":"locality"
},
  "geometry": {"coordinates":[128.59416999999999,38.03667],"type":"Point"}
}