{
  "type": "Feature",
  "properties": {
    "gn:admin1_code":"6.0",
    "gn:asciiname":"Song-gol",
    "gn:country_code":"KR",
    "gn:dem":361,
    "gn:feature_class":"P",
    "gn:feature_code":"PPL",
    "gn:name":"S\u014fng-gol",
    "gn:population":0,
    "gn:timezone":"Asia/Seoul",
    "iso:country":"KR",
    "name:kor_x_preferred":[
        "\uc131\uace8"
    ],
    "name:kor_x_variant":[
        "S\u014fng-gol"
    ],
    "wof:name":"Song-gol",
    "wof:placetype":"locality"
},
  "geometry": {"coordinates":[128.2328,37.5898],"type":"Point"}
}