{
  "type": "Feature",
  "properties": {
    "gn:admin1_code":"14.0",
    "gn:asciiname":"Yangji",
    "gn:country_code":"KR",
    "gn:dem":99,
    "gn:feature_class":"P",
    "gn:feature_code":"PPL",
    "gn:name":"Yangji",
    "gn:population":0,
    "gn:timezone":"Asia/Seoul",
    "iso:country":"KR",
    "name:kor_x_preferred":[
        "\uc591\uc9c0"
    ],
    "wof:name":"Yangji",
    "wof:placetype":"locality"
},
  "geometry": {"coordinates":[128.57105000000001,35.98498],"type":"Point"}
}