{
  "type": "Feature",
  "properties": {
    "gn:admin1_code":"13.0",
    "gn:asciiname":"Samjeong-gol",
    "gn:country_code":"KR",
    "gn:dem":59,
    "gn:feature_class":"P",
    "gn:feature_code":"PPL",
    "gn:name":"Samjeong-gol",
    "gn:population":0,
    "gn:timezone":"Asia/Seoul",
    "iso:country":"KR",
    "name:und_x_variant":[
        "\uc0bc\uc815\uace8",
        "Samjeong-gol",
        "Samj\u014fng-gol"
    ],
    "wof:name":"Samjeong-gol",
    "wof:placetype":"locality"
},
  "geometry": {"coordinates":[127.28,37.4825],"type":"Point"}
}