{
  "type": "Feature",
  "properties": {
    "gn:admin1_code":"6.0",
    "gn:asciiname":"Podongmal",
    "gn:country_code":"KR",
    "gn:dem":424,
    "gn:feature_class":"P",
    "gn:feature_code":"PPL",
    "gn:name":"P\u014fd\u014fngmal",
    "gn:population":0,
    "gn:timezone":"Asia/Seoul",
    "iso:country":"KR",
    "name:kor_x_preferred":[
        "\ubc84\ub369\ub9d0"
    ],
    "name:und_x_variant":[
        "P\u014fd\u014fngmal"
    ],
    "wof:name":"Podongmal",
    "wof:placetype":"locality"
},
  "geometry": {"coordinates":[128.37535,38.01461],"type":"Point"}
}