{
  "type": "Feature",
  "properties": {
    "iso:country":"KR",
    "qs:name":"\uc704\ub3c4\uba74",
    "qs:name_adm0":"\ud55c\uad6d",
    "qs:name_adm1":"\uc804\ub77c\ubd81\ub3c4",
    "qs:photos":29,
    "qs:photos_1k":6,
    "qs:photos_9k":1,
    "qs:photos_9r":2,
    "qs:photos_all":29,
    "qs:photos_sr":2,
    "qs:placetype":"LocalAdmin",
    "qs:pop_sr":"0",
    "wof:name":"\uc704\ub3c4\uba74",
    "wof:placetype":"localadmin"
},
  "geometry": {"coordinates":[126.304074,35.617256],"type":"Point"}
}