{
  "type": "Feature",
  "properties": {
    "gn:admin1_code":"16.0",
    "gn:asciiname":"Samma",
    "gn:country_code":"KR",
    "gn:dem":32,
    "gn:feature_class":"P",
    "gn:feature_code":"PPL",
    "gn:name":"Samma",
    "gn:population":0,
    "gn:timezone":"Asia/Seoul",
    "iso:country":"KR",
    "name:deu_x_preferred":[
        "Samma"
    ],
    "name:kor_x_preferred":[
        "\uc0bc\ub9c8"
    ],
    "name:und_x_variant":[
        "Samma-ri",
        "Samma"
    ],
    "wof:name":"Samma",
    "wof:placetype":"locality"
},
  "geometry": {"coordinates":[126.54944,34.40194],"type":"Point"}
}