{
  "type": "Feature",
  "properties": {
    "gn:admin1_code":"17.0",
    "gn:asciiname":"Sigye",
    "gn:country_code":"KR",
    "gn:dem":47,
    "gn:feature_class":"P",
    "gn:feature_code":"PPL",
    "gn:name":"Sigye",
    "gn:population":0,
    "gn:timezone":"Asia/Seoul",
    "iso:country":"KR",
    "name:und_x_variant":[
        "\uc2dc\uacc4",
        "Sigye"
    ],
    "wof:name":"Sigye",
    "wof:placetype":"locality"
},
  "geometry": {"coordinates":[126.6947,36.8716],"type":"Point"}
}