{
  "type": "Feature",
  "properties": {
    "gn:admin1_code":"14.0",
    "gn:asciiname":"Bukjeolgol",
    "gn:country_code":"KR",
    "gn:dem":332,
    "gn:feature_class":"P",
    "gn:feature_code":"PPL",
    "gn:name":"Bukjeolgol",
    "gn:population":0,
    "gn:timezone":"Asia/Seoul",
    "iso:country":"KR",
    "name:kor_x_preferred":[
        "\ubd81\uc808\uace8"
    ],
    "wof:name":"Bukjeolgol",
    "wof:placetype":"locality"
},
  "geometry": {"coordinates":[128.61693,36.67486],"type":"Point"}
}