{
  "type": "Feature",
  "properties": {
    "gn:admin1_code":"5.0",
    "gn:asciiname":"Paekpong-ni",
    "gn:cc2":"KR",
    "gn:country_code":"KR",
    "gn:dem":234,
    "gn:feature_class":"P",
    "gn:feature_code":"PPL",
    "gn:name":"Paekpong-ni",
    "gn:population":0,
    "gn:timezone":"Asia/Seoul",
    "iso:country":"KR",
    "name:eng_x_preferred":[
        "Paekpong"
    ],
    "name:eng_x_variant":[
        "Paekpong-ni"
    ],
    "name:und_x_variant":[
        "Paekpong-ri",
        "Paekpong-ni"
    ],
    "wof:name":"Paekpong",
    "wof:placetype":"locality"
},
  "geometry": {"coordinates":[127.71111000000001,36.73],"type":"Point"}
}