{
  "type": "Feature",
  "properties": {
    "gn:admin1_code":"5.0",
    "gn:asciiname":"Araetjeomgol",
    "gn:country_code":"KR",
    "gn:dem":132,
    "gn:feature_class":"P",
    "gn:feature_code":"PPL",
    "gn:name":"Araetjeomgol",
    "gn:population":0,
    "gn:timezone":"Asia/Seoul",
    "iso:country":"KR",
    "name:kor_x_preferred":[
        "\uc544\ub7ab\uc810\uace8"
    ],
    "wof:name":"Araetjeomgol",
    "wof:placetype":"locality"
},
  "geometry": {"coordinates":[127.45544,37.01241],"type":"Point"}
}