{
  "type": "Feature",
  "properties": {
    "gn:admin1_code":"5.0",
    "gn:asciiname":"Chirakgol",
    "gn:country_code":"KR",
    "gn:dem":82,
    "gn:feature_class":"P",
    "gn:feature_code":"PPL",
    "gn:name":"Chirakgol",
    "gn:population":0,
    "gn:timezone":"Asia/Seoul",
    "iso:country":"KR",
    "name:kor_x_preferred":[
        "\uce58\ub77d\uace8"
    ],
    "wof:name":"Chirakgol",
    "wof:placetype":"locality"
},
  "geometry": {"coordinates":[127.33495000000001,36.70411],"type":"Point"}
}