{
  "type": "Feature",
  "properties": {
    "gn:admin1_code":"0.0",
    "gn:asciiname":"Se-dong",
    "gn:cc2":"KR",
    "gn:country_code":"KR",
    "gn:dem":244,
    "gn:feature_class":"P",
    "gn:feature_code":"PPL",
    "gn:name":"Se-dong",
    "gn:population":0,
    "gn:timezone":"Asia/Seoul",
    "iso:country":"KR",
    "name:und_x_variant":[
        "Kan\u016dn-gol",
        "Se-dong"
    ],
    "wof:name":"Se-dong",
    "wof:placetype":"locality"
},
  "geometry": {"coordinates":[127.51667,35.88333],"type":"Point"}
}