{
  "type": "Feature",
  "properties": {
    "gn:admin1_code":"17.0",
    "gn:asciiname":"Sinp'yong-ni",
    "gn:country_code":"KR",
    "gn:dem":166,
    "gn:feature_class":"P",
    "gn:feature_code":"PPL",
    "gn:name":"Sinp\u2019y\u014fng-ni",
    "gn:population":0,
    "gn:timezone":"Asia/Seoul",
    "iso:country":"KR",
    "name:eng_x_preferred":[
        "Sinp'yong"
    ],
    "name:eng_x_variant":[
        "Sinp'yong-ni"
    ],
    "wof:name":"Sinp'yong",
    "wof:placetype":"locality"
},
  "geometry": {"coordinates":[127.50667,36.22528],"type":"Point"}
}