{
  "type": "Feature",
  "properties": {
    "gn:admin1_code":"13.0",
    "gn:asciiname":"Gudae",
    "gn:country_code":"KR",
    "gn:dem":21,
    "gn:feature_class":"P",
    "gn:feature_code":"PPL",
    "gn:name":"Gudae",
    "gn:population":0,
    "gn:timezone":"Asia/Seoul",
    "iso:country":"KR",
    "name:und_x_variant":[
        "\uad6c\ub300",
        "Gudae",
        "Kudae"
    ],
    "wof:name":"Gudae",
    "wof:placetype":"locality"
},
  "geometry": {"coordinates":[127.06151,37.02081],"type":"Point"}
}