{
  "type": "Feature",
  "properties": {
    "gn:admin1_code":"17.0",
    "gn:asciiname":"Malmudom",
    "gn:country_code":"KR",
    "gn:dem":11,
    "gn:feature_class":"P",
    "gn:feature_code":"PPL",
    "gn:name":"Malmud\u014fm",
    "gn:population":0,
    "gn:timezone":"Asia/Seoul",
    "iso:country":"KR",
    "name:und_x_variant":[
        "\ub9d0\ubb34\ub364",
        "Malmud\u014fm"
    ],
    "wof:name":"Malmudom",
    "wof:placetype":"locality"
},
  "geometry": {"coordinates":[126.5108,36.7217],"type":"Point"}
}