{
  "type": "Feature",
  "properties": {
    "gn:admin1_code":"17.0",
    "gn:asciiname":"Sumunmok",
    "gn:country_code":"KR",
    "gn:dem":14,
    "gn:feature_class":"P",
    "gn:feature_code":"PPL",
    "gn:name":"Sumunmok",
    "gn:population":0,
    "gn:timezone":"Asia/Seoul",
    "iso:country":"KR",
    "name:und_x_variant":[
        "\uc218\ubb38\ubaa9",
        "Sumunmok"
    ],
    "wof:name":"Sumunmok",
    "wof:placetype":"locality"
},
  "geometry": {"coordinates":[126.4259,36.9657],"type":"Point"}
}