{
  "type": "Feature",
  "properties": {
    "gn:admin1_code":"6.0",
    "gn:asciiname":"Soran-dong",
    "gn:country_code":"KR",
    "gn:dem":113,
    "gn:feature_class":"P",
    "gn:feature_code":"PPL",
    "gn:name":"S\u014fran-dong",
    "gn:population":0,
    "gn:timezone":"Asia/Seoul",
    "iso:country":"KR",
    "name:kor_x_preferred":[
        "\uc124\uc548\ub3d9"
    ],
    "name:kor_x_variant":[
        "S\u014fran-dong"
    ],
    "wof:name":"Soran-dong",
    "wof:placetype":"locality"
},
  "geometry": {"coordinates":[127.7983,37.3534],"type":"Point"}
}