{
  "type": "Feature",
  "properties": {
    "gn:admin1_code":"6.0",
    "gn:asciiname":"Noraegol",
    "gn:country_code":"KR",
    "gn:dem":83,
    "gn:feature_class":"P",
    "gn:feature_code":"PPL",
    "gn:name":"Noraegol",
    "gn:population":0,
    "gn:timezone":"Asia/Seoul",
    "iso:country":"KR",
    "name:und_x_variant":[
        "\ub178\ub798\uace8"
    ],
    "wof:name":"Noraegol",
    "wof:placetype":"locality"
},
  "geometry": {"coordinates":[128.42382000000001,38.34553],"type":"Point"}
}