{
  "type": "Feature",
  "properties": {
    "gn:admin1_code":"17.0",
    "gn:asciiname":"Paek-tong",
    "gn:country_code":"KR",
    "gn:dem":41,
    "gn:feature_class":"P",
    "gn:feature_code":"PPL",
    "gn:name":"Paek-tong",
    "gn:population":0,
    "gn:timezone":"Asia/Seoul",
    "iso:country":"KR",
    "name:und_x_variant":[
        "\ubc31\ub3d9",
        "Paek-tong"
    ],
    "wof:name":"Paek-tong",
    "wof:placetype":"locality"
},
  "geometry": {"coordinates":[126.61790000000001,36.5264],"type":"Point"}
}