{
  "type": "Feature",
  "properties": {
    "gn:admin1_code":"6.0",
    "gn:asciiname":"Kosok-kol",
    "gn:country_code":"KR",
    "gn:dem":380,
    "gn:feature_class":"P",
    "gn:feature_code":"PPL",
    "gn:name":"Kos\u014fk-kol",
    "gn:population":0,
    "gn:timezone":"Asia/Seoul",
    "iso:country":"KR",
    "name:kor_x_preferred":[
        "\uace0\uc11d\uace8"
    ],
    "name:und_x_variant":[
        "Kos\u014fk-kol"
    ],
    "wof:name":"Kosok-kol",
    "wof:placetype":"locality"
},
  "geometry": {"coordinates":[128.33703,38.01302],"type":"Point"}
}