{
  "type": "Feature",
  "properties": {
    "gn:admin1_code":"17.0",
    "gn:asciiname":"Sinseondong",
    "gn:country_code":"KR",
    "gn:dem":63,
    "gn:feature_class":"P",
    "gn:feature_code":"PPL",
    "gn:name":"Sinseondong",
    "gn:population":0,
    "gn:timezone":"Asia/Seoul",
    "iso:country":"KR",
    "name:kor_x_preferred":[
        "\uc2e0\uc120\ub3d9"
    ],
    "wof:name":"Sinseondong",
    "wof:placetype":"locality"
},
  "geometry": {"coordinates":[127.29416999999999,36.75932],"type":"Point"}
}