{
  "type": "Feature",
  "properties": {
    "gn:admin1_code":"6.0",
    "gn:asciiname":"Chiksan",
    "gn:country_code":"KR",
    "gn:dem":192,
    "gn:feature_class":"P",
    "gn:feature_code":"PPL",
    "gn:name":"Chiksan",
    "gn:population":0,
    "gn:timezone":"Asia/Seoul",
    "iso:country":"KR",
    "name:kor_x_preferred":[
        "\uc9c1\uc0b0"
    ],
    "wof:name":"Chiksan",
    "wof:placetype":"locality"
},
  "geometry": {"coordinates":[127.99299999999999,37.3814],"type":"Point"}
}