{
  "type": "Feature",
  "properties": {
    "gn:admin1_code":"20.0",
    "gn:asciiname":"Witchagusil",
    "gn:country_code":"KR",
    "gn:dem":137,
    "gn:feature_class":"P",
    "gn:feature_code":"PPL",
    "gn:name":"Witchagusil",
    "gn:population":0,
    "gn:timezone":"Asia/Seoul",
    "iso:country":"KR",
    "name:und_x_variant":[
        "\uc717\uc790\uad6c\uc2e4",
        "Witchagusil"
    ],
    "wof:name":"Witchagusil",
    "wof:placetype":"locality"
},
  "geometry": {"coordinates":[128.29910000000001,35.07948],"type":"Point"}
}