{
  "type": "Feature",
  "properties": {
    "gn:admin1_code":"16.0",
    "gn:asciiname":"Yongsu",
    "gn:country_code":"KR",
    "gn:dem":39,
    "gn:feature_class":"P",
    "gn:feature_code":"PPL",
    "gn:name":"Yongsu",
    "gn:population":0,
    "gn:timezone":"Asia/Seoul",
    "iso:country":"KR",
    "name:und_x_variant":[
        "\uc6a9\uc218",
        "Yongsu"
    ],
    "wof:name":"Yongsu",
    "wof:placetype":"locality"
},
  "geometry": {"coordinates":[126.68611,34.56778],"type":"Point"}
}