{
  "type": "Feature",
  "properties": {
    "gn:admin1_code":"13.0",
    "gn:asciiname":"Konjiam-ni",
    "gn:country_code":"KR",
    "gn:dem":88,
    "gn:feature_class":"P",
    "gn:feature_code":"PPLL",
    "gn:name":"Konjiam-ni",
    "gn:population":0,
    "gn:timezone":"Asia/Seoul",
    "iso:country":"KR",
    "name:und_x_variant":[
        "Konchigan-ri",
        "\uace4\uc9c0\uc554\ub9ac",
        "Gonjiam-ri",
        "Konjiam-ni"
    ],
    "wof:name":"Konjiam-ni",
    "wof:placetype":"locality"
},
  "geometry": {"coordinates":[127.35527999999999,37.34722],"type":"Point"}
}