{
  "type": "Feature",
  "properties": {
    "gn:admin1_code":"5.0",
    "gn:asciiname":"Gorae",
    "gn:country_code":"KR",
    "gn:dem":74,
    "gn:feature_class":"P",
    "gn:feature_code":"PPL",
    "gn:name":"Gorae",
    "gn:population":0,
    "gn:timezone":"Asia/Seoul",
    "iso:country":"KR",
    "name:kor_x_preferred":[
        "\uace0\ub798"
    ],
    "name:kor_x_variant":[
        "\uace0\ub798\ub9d0"
    ],
    "name:und_x_variant":[
        "Goraemal"
    ],
    "wof:name":"Gorae",
    "wof:placetype":"locality"
},
  "geometry": {"coordinates":[127.54613000000001,36.76143],"type":"Point"}
}