{
  "type": "Feature",
  "properties": {
    "gn:admin1_code":"16.0",
    "gn:asciiname":"Gongpyeong",
    "gn:country_code":"KR",
    "gn:dem":114,
    "gn:feature_class":"P",
    "gn:feature_code":"PPL",
    "gn:name":"Gongpyeong",
    "gn:population":0,
    "gn:timezone":"Asia/Seoul",
    "iso:country":"KR",
    "name:kor_x_preferred":[
        "\uacf5\ud3c9"
    ],
    "wof:name":"Gongpyeong",
    "wof:placetype":"locality"
},
  "geometry": {"coordinates":[126.77361000000001,35.36489],"type":"Point"}
}