{
  "type": "Feature",
  "properties": {
    "gn:admin1_code":"3.0",
    "gn:asciiname":"Chidong",
    "gn:country_code":"KR",
    "gn:dem":90,
    "gn:feature_class":"P",
    "gn:feature_code":"PPL",
    "gn:name":"Chidong",
    "gn:population":0,
    "gn:timezone":"Asia/Seoul",
    "iso:country":"KR",
    "name:kor_x_preferred":[
        "\uce58\ub3d9"
    ],
    "wof:name":"Chidong",
    "wof:placetype":"locality"
},
  "geometry": {"coordinates":[126.65561,35.36063],"type":"Point"}
}