{
  "type": "Feature",
  "properties": {
    "gn:admin1_code":"6.0",
    "gn:asciiname":"Changjinp'yong",
    "gn:country_code":"KR",
    "gn:dem":631,
    "gn:feature_class":"P",
    "gn:feature_code":"PPL",
    "gn:name":"Changjinp\u2019y\u014fng",
    "gn:population":0,
    "gn:timezone":"Asia/Seoul",
    "iso:country":"KR",
    "name:kor_x_preferred":[
        "\uc7a5\uc9c4\ud3c9"
    ],
    "name:kor_x_variant":[
        "Changjinp\u2019y\u014fng"
    ],
    "wof:name":"Changjinp'yong",
    "wof:placetype":"locality"
},
  "geometry": {"coordinates":[128.3699,37.7428],"type":"Point"}
}