{
  "type": "Feature",
  "properties": {
    "gn:admin1_code":"13.0",
    "gn:asciiname":"Sahyeon",
    "gn:country_code":"KR",
    "gn:dem":26,
    "gn:feature_class":"P",
    "gn:feature_code":"PPL",
    "gn:name":"Sahyeon",
    "gn:population":0,
    "gn:timezone":"Asia/Seoul",
    "iso:country":"KR",
    "name:und_x_variant":[
        "\uc0ac\ud604",
        "Sahyeon",
        "Sahy\u014fn"
    ],
    "wof:name":"Sahyeon",
    "wof:placetype":"locality"
},
  "geometry": {"coordinates":[126.58362,37.67408],"type":"Point"}
}