{
  "type": "Feature",
  "properties": {
    "gn:admin1_code":"5.0",
    "gn:asciiname":"Eunggol",
    "gn:country_code":"KR",
    "gn:dem":121,
    "gn:feature_class":"P",
    "gn:feature_code":"PPL",
    "gn:name":"Eunggol",
    "gn:population":0,
    "gn:timezone":"Asia/Seoul",
    "iso:country":"KR",
    "name:kor_x_preferred":[
        "\uc751\uace8"
    ],
    "wof:name":"Eunggol",
    "wof:placetype":"locality"
},
  "geometry": {"coordinates":[127.43463,36.97882],"type":"Point"}
}