{
  "type": "Feature",
  "properties": {
    "gn:admin1_code":"14.0",
    "gn:asciiname":"Sigeori",
    "gn:country_code":"KR",
    "gn:dem":53,
    "gn:feature_class":"P",
    "gn:feature_code":"PPL",
    "gn:name":"Sigeori",
    "gn:population":0,
    "gn:timezone":"Asia/Seoul",
    "iso:country":"KR",
    "name:kor_x_preferred":[
        "\uc2dc\uac70\ub9ac"
    ],
    "wof:name":"Sigeori",
    "wof:placetype":"locality"
},
  "geometry": {"coordinates":[129.40178,36.42908],"type":"Point"}
}