{
  "type": "Feature",
  "properties": {
    "gn:admin1_code":"13.0",
    "gn:asciiname":"Dodalmi",
    "gn:country_code":"KR",
    "gn:dem":103,
    "gn:feature_class":"P",
    "gn:feature_code":"PPL",
    "gn:name":"Dodalmi",
    "gn:population":0,
    "gn:timezone":"Asia/Seoul",
    "iso:country":"KR",
    "name:kor_x_preferred":[
        "\ub3c4\ub2ec\ubbf8"
    ],
    "wof:name":"Dodalmi",
    "wof:placetype":"locality"
},
  "geometry": {"coordinates":[127.56097,37.07745],"type":"Point"}
}