{
  "type": "Feature",
  "properties": {
    "gn:admin1_code":"14.0",
    "gn:asciiname":"Sangni-ri",
    "gn:country_code":"KR",
    "gn:dem":169,
    "gn:feature_class":"P",
    "gn:feature_code":"PPLL",
    "gn:name":"Sangni-ri",
    "gn:population":0,
    "gn:timezone":"Asia/Seoul",
    "iso:country":"KR",
    "name:und_x_variant":[
        "\uc0c1\ub9ac\ub9ac",
        "Sangni-ri"
    ],
    "wof:name":"Sangni-ri",
    "wof:placetype":"locality"
},
  "geometry": {"coordinates":[128.73615000000001,36.34758],"type":"Point"}
}