{
  "type": "Feature",
  "properties": {
    "gn:admin1_code":"6.0",
    "gn:admin2_code":"Ch'\u014frw\u014fn-gun",
    "gn:asciiname":"Cheontong",
    "gn:country_code":"KR",
    "gn:dem":226,
    "gn:feature_class":"P",
    "gn:feature_code":"PPL",
    "gn:name":"Cheontong",
    "gn:population":0,
    "gn:timezone":"Asia/Seoul",
    "iso:country":"KR",
    "name:kor_x_preferred":[
        "\ucc9c\ud1b5"
    ],
    "name:und_x_variant":[
        "Ch\u2019\u014fnt\u2019ong-ni"
    ],
    "wof:name":"Cheontong",
    "wof:placetype":"locality"
},
  "geometry": {"coordinates":[127.22475,38.28275],"type":"Point"}
}