{
  "type": "Feature",
  "properties": {
    "gn:admin1_code":"17.0",
    "gn:asciiname":"Ye-dong",
    "gn:country_code":"KR",
    "gn:dem":7,
    "gn:feature_class":"P",
    "gn:feature_code":"PPL",
    "gn:name":"Ye-dong",
    "gn:population":0,
    "gn:timezone":"Asia/Seoul",
    "iso:country":"KR",
    "name:und_x_variant":[
        "\uc608\ub3d9",
        "Ye-dong"
    ],
    "wof:name":"Ye-dong",
    "wof:placetype":"locality"
},
  "geometry": {"coordinates":[126.771,36.7403],"type":"Point"}
}