{
  "type": "Feature",
  "properties": {
    "gn:admin1_code":"20.0",
    "gn:asciiname":"Songmu",
    "gn:country_code":"KR",
    "gn:dem":13,
    "gn:feature_class":"P",
    "gn:feature_code":"PPL",
    "gn:name":"S\u014fngmu",
    "gn:population":0,
    "gn:timezone":"Asia/Seoul",
    "iso:country":"KR",
    "name:und_x_variant":[
        "\uc11d\ubb34",
        "S\u014fngmu"
    ],
    "wof:name":"Songmu",
    "wof:placetype":"locality"
},
  "geometry": {"coordinates":[128.38346999999999,35.31989],"type":"Point"}
}