{
  "type": "Feature",
  "properties": {
    "gn:admin1_code":"6.0",
    "gn:asciiname":"Uam-ni",
    "gn:country_code":"KR",
    "gn:dem":99,
    "gn:feature_class":"P",
    "gn:feature_code":"PPL",
    "gn:name":"Uam-ni",
    "gn:population":0,
    "gn:timezone":"Asia/Seoul",
    "iso:country":"KR",
    "name:kor_x_preferred":[
        "\uc6b0\uc554\ub9ac"
    ],
    "wof:name":"Uam-ni",
    "wof:placetype":"locality"
},
  "geometry": {"coordinates":[128.63861,38.03861],"type":"Point"}
}