{
  "type": "Feature",
  "properties": {
    "gn:admin1_code":"20.0",
    "gn:asciiname":"Obang",
    "gn:cc2":"KR",
    "gn:country_code":"KR",
    "gn:dem":56,
    "gn:feature_class":"P",
    "gn:feature_code":"PPL",
    "gn:name":"Obang",
    "gn:population":0,
    "gn:timezone":"Asia/Seoul",
    "iso:country":"KR",
    "name:und_x_variant":[
        "Obang-ni",
        "Obang"
    ],
    "wof:name":"Obang",
    "wof:placetype":"locality"
},
  "geometry": {"coordinates":[128.18333000000001,34.93333],"type":"Point"}
}