{
  "type": "Feature",
  "properties": {
    "gn:admin1_code":"16.0",
    "gn:asciiname":"Olgim",
    "gn:cc2":"KR",
    "gn:country_code":"KR",
    "gn:dem":15,
    "gn:feature_class":"P",
    "gn:feature_code":"PPL",
    "gn:name":"\u014elgim",
    "gn:population":0,
    "gn:timezone":"Asia/Seoul",
    "iso:country":"KR",
    "name:und_x_variant":[
        "\u014erikkimi",
        "\u014elgim"
    ],
    "wof:name":"Olgim",
    "wof:placetype":"locality"
},
  "geometry": {"coordinates":[125.97417,34.66194],"type":"Point"}
}