{
  "type": "Feature",
  "properties": {
    "gn:admin1_code":"5.0",
    "gn:asciiname":"Keunmal",
    "gn:country_code":"KR",
    "gn:dem":224,
    "gn:feature_class":"P",
    "gn:feature_code":"PPL",
    "gn:name":"Keunmal",
    "gn:population":0,
    "gn:timezone":"Asia/Seoul",
    "iso:country":"KR",
    "name:kor_x_preferred":[
        "\ud070\ub9d0"
    ],
    "wof:name":"Keunmal",
    "wof:placetype":"locality"
},
  "geometry": {"coordinates":[127.6443,36.94235],"type":"Point"}
}