{
  "type": "Feature",
  "properties": {
    "gn:admin1_code":"20.0",
    "gn:asciiname":"Aaraean-gol",
    "gn:country_code":"KR",
    "gn:dem":354,
    "gn:feature_class":"P",
    "gn:feature_code":"PPL",
    "gn:name":"Aaraean-gol",
    "gn:population":0,
    "gn:timezone":"Asia/Seoul",
    "iso:country":"KR",
    "name:und_x_variant":[
        "\uc544\ub798\uc548\uace8",
        "Aaraean-gol"
    ],
    "wof:name":"Aaraean-gol",
    "wof:placetype":"locality"
},
  "geometry": {"coordinates":[127.61866000000001,35.55509],"type":"Point"}
}