{
  "type": "Feature",
  "properties": {
    "gn:admin1_code":"3.0",
    "gn:asciiname":"Oe-maul",
    "gn:country_code":"KR",
    "gn:dem":96,
    "gn:feature_class":"P",
    "gn:feature_code":"PPL",
    "gn:name":"Oe-ma\u016dl",
    "gn:population":0,
    "gn:timezone":"Asia/Seoul",
    "iso:country":"KR",
    "name:und_x_variant":[
        "\uc678\ub9c8\uc744",
        "Oe-ma\u016dl"
    ],
    "wof:name":"Oe-maul",
    "wof:placetype":"locality"
},
  "geometry": {"coordinates":[127.2419,36.0331],"type":"Point"}
}