{
  "type": "Feature",
  "properties": {
    "gn:admin1_code":"16.0",
    "gn:asciiname":"Hyang-dong",
    "gn:country_code":"KR",
    "gn:dem":0,
    "gn:feature_class":"P",
    "gn:feature_code":"PPL",
    "gn:name":"Hyang-dong",
    "gn:population":0,
    "gn:timezone":"Asia/Seoul",
    "iso:country":"KR",
    "wof:name":"Hyang-dong",
    "wof:placetype":"locality"
},
  "geometry": {"coordinates":[126.58333,34.98333],"type":"Point"}
}