{
  "type": "Feature",
  "properties": {
    "gn:admin1_code":"16.0",
    "gn:asciiname":"Teojinmok",
    "gn:country_code":"KR",
    "gn:dem":6,
    "gn:feature_class":"P",
    "gn:feature_code":"PPL",
    "gn:name":"Teojinmok",
    "gn:population":0,
    "gn:timezone":"Asia/Seoul",
    "iso:country":"KR",
    "name:kor_x_preferred":[
        "\ud130\uc9c4\ubaa9"
    ],
    "name:und_x_variant":[
        "Maehwa-ri"
    ],
    "wof:name":"Teojinmok",
    "wof:placetype":"locality"
},
  "geometry": {"coordinates":[126.23922,34.91801],"type":"Point"}
}