{
  "type": "Feature",
  "properties": {
    "gn:admin1_code":"6.0",
    "gn:asciiname":"Cheukdong",
    "gn:country_code":"KR",
    "gn:dem":302,
    "gn:feature_class":"P",
    "gn:feature_code":"PPL",
    "gn:name":"Cheukdong",
    "gn:population":0,
    "gn:timezone":"Asia/Seoul",
    "iso:country":"KR",
    "name:kor_x_preferred":[
        "\uce21\ub3d9"
    ],
    "wof:name":"Cheukdong",
    "wof:placetype":"locality"
},
  "geometry": {"coordinates":[127.52463,38.07243],"type":"Point"}
}