{
  "type": "Feature",
  "properties": {
    "gn:admin1_code":"16.0",
    "gn:asciiname":"Sepo",
    "gn:country_code":"KR",
    "gn:dem":151,
    "gn:feature_class":"P",
    "gn:feature_code":"PPL",
    "gn:name":"Sepo",
    "gn:population":0,
    "gn:timezone":"Asia/Seoul",
    "iso:country":"KR",
    "name:ceb_x_preferred":[
        "Sepo"
    ],
    "name:deu_x_preferred":[
        "Sepo"
    ],
    "name:kor_x_preferred":[
        "\uc138\ud3ec"
    ],
    "name:swe_x_preferred":[
        "Sepo"
    ],
    "wof:name":"Sepo",
    "wof:placetype":"locality"
},
  "geometry": {"coordinates":[126.7538,35.36483],"type":"Point"}
}