{
  "type": "Feature",
  "properties": {
    "gn:admin1_code":"6.0",
    "gn:asciiname":"Hoe-ch'on",
    "gn:country_code":"KR",
    "gn:dem":263,
    "gn:feature_class":"P",
    "gn:feature_code":"PPL",
    "gn:name":"Hoe-ch\u2019on",
    "gn:population":0,
    "gn:timezone":"Asia/Seoul",
    "iso:country":"KR",
    "name:kor_x_preferred":[
        "\ud68c\ucd0c"
    ],
    "name:kor_x_variant":[
        "Hoe-ch\u2019on"
    ],
    "wof:name":"Hoe-ch'on",
    "wof:placetype":"locality"
},
  "geometry": {"coordinates":[127.911,37.2551],"type":"Point"}
}