{
  "type": "Feature",
  "properties": {
    "gn:admin1_code":"13.0",
    "gn:asciiname":"Muk-tong",
    "gn:country_code":"KR",
    "gn:dem":73,
    "gn:feature_class":"P",
    "gn:feature_code":"PPL",
    "gn:name":"Muk-tong",
    "gn:population":0,
    "gn:timezone":"Asia/Seoul",
    "iso:country":"KR",
    "name:msa_x_preferred":[
        "Muk-dong"
    ],
    "name:tha_x_preferred":[
        "\u0e41\u0e02\u0e27\u0e07\u0e21\u0e38\u0e01"
    ],
    "name:und_x_variant":[
        "\ubb35\ub3d9",
        "Muk-tong"
    ],
    "name:vie_x_preferred":[
        "Muk-dong"
    ],
    "wof:name":"Muk-tong",
    "wof:placetype":"locality"
},
  "geometry": {"coordinates":[127.10666999999999,37.25028],"type":"Point"}
}