{
  "type": "Feature",
  "properties": {
    "gn:admin1_code":"14.0",
    "gn:asciiname":"Solbau",
    "gn:country_code":"KR",
    "gn:dem":182,
    "gn:feature_class":"P",
    "gn:feature_code":"PPL",
    "gn:name":"S\u014flbau",
    "gn:population":0,
    "gn:timezone":"Asia/Seoul",
    "iso:country":"KR",
    "name:und_x_variant":[
        "\uc124\ubc14\uc6b0",
        "S\u014flbau"
    ],
    "wof:name":"Solbau",
    "wof:placetype":"locality"
},
  "geometry": {"coordinates":[129.38990000000001,36.6885],"type":"Point"}
}