{
  "type": "Feature",
  "properties": {
    "gn:admin1_code":"6.0",
    "gn:asciiname":"Modul-gol",
    "gn:country_code":"KR",
    "gn:dem":279,
    "gn:feature_class":"P",
    "gn:feature_code":"PPL",
    "gn:name":"M\u014fd\u016dl-gol",
    "gn:population":0,
    "gn:timezone":"Asia/Seoul",
    "iso:country":"KR",
    "name:kor_x_preferred":[
        "\uba38\ub4e4\uace8"
    ],
    "name:kor_x_variant":[
        "M\u014fd\u016dl-gol"
    ],
    "wof:name":"Modul-gol",
    "wof:placetype":"locality"
},
  "geometry": {"coordinates":[127.5585,37.682],"type":"Point"}
}