{
  "type": "Feature",
  "properties": {
    "iso:country":"KR",
    "name:eng_x_preferred":[
        "Gwangcheon-dong"
    ],
    "name:kor_x_preferred":[
        "\uad11\ucc9c\ub3d9"
    ],
    "name:kor_x_variant":[
        "\uad11\ucc9c\ub3d9"
    ],
    "qs:gn_adm0_cc":"KR",
    "qs:gn_local":1841811,
    "qs:gn_nam_loc":"Kwangju",
    "qs:gn_namadm1":"18",
    "qs:local_max":1454,
    "qs:local_sum":2956,
    "qs:localhoods":12,
    "qs:name":"\uad11\ucc9c\ub3d9",
    "qs:name_adm0":"\ud55c\uad6d",
    "qs:name_adm1":"\uad11\uc8fc",
    "qs:name_adm2":"\uc11c\uad6c",
    "qs:name_lau":"\uad11\ucc9c\ub3d9",
    "qs:name_local":"\uad11\uc8fc",
    "qs:photo_max":211,
    "qs:photo_sum":242,
    "qs:placetype":"Suburb",
    "qs:quad_count":11,
    "qs:woe_adm0":23424868,
    "qs:woe_adm1":2345974,
    "qs:woe_adm2":28289278,
    "qs:woe_lau":28806454,
    "qs:woe_local":1132481,
    "qs:woe_ver":"7.10.0",
    "wof:lang":[
        "kor"
    ],
    "wof:name":"Gwangcheon-dong",
    "wof:placetype":"neighbourhood"
},
  "geometry": {"coordinates":[126.88470100000001,35.161294],"type":"Point"}
}