{
  "type": "Feature",
  "properties": {
    "gn:admin1_code":"5.0",
    "gn:asciiname":"Yonghwa",
    "gn:country_code":"KR",
    "gn:dem":270,
    "gn:feature_class":"P",
    "gn:feature_code":"PPL",
    "gn:name":"Yonghwa",
    "gn:population":0,
    "gn:timezone":"Asia/Seoul",
    "iso:country":"KR",
    "name:und_x_variant":[
        "Yonghwa-ri",
        "Yonghwa",
        "\uc6a9\ud654"
    ],
    "wof:name":"Yonghwa",
    "wof:placetype":"locality"
},
  "geometry": {"coordinates":[127.76649999999999,36.0213],"type":"Point"}
}