{
  "type": "Feature",
  "properties": {
    "gn:admin1_code":"13.0",
    "gn:asciiname":"Samtaegol",
    "gn:country_code":"KR",
    "gn:dem":182,
    "gn:feature_class":"P",
    "gn:feature_code":"PPL",
    "gn:name":"Samtaegol",
    "gn:population":0,
    "gn:timezone":"Asia/Seoul",
    "iso:country":"KR",
    "name:kor_x_preferred":[
        "\uc0bc\ud0dc\uace8"
    ],
    "name:kor_x_variant":[
        "Samt\u2019ae-gol"
    ],
    "wof:name":"Samtaegol",
    "wof:placetype":"locality"
},
  "geometry": {"coordinates":[127.50579,37.52063],"type":"Point"}
}