{
  "type": "Feature",
  "properties": {
    "gn:admin1_code":"17.0",
    "gn:asciiname":"Sangnabaegi",
    "gn:country_code":"KR",
    "gn:dem":6,
    "gn:feature_class":"P",
    "gn:feature_code":"PPL",
    "gn:name":"Sangnabaegi",
    "gn:population":0,
    "gn:timezone":"Asia/Seoul",
    "iso:country":"KR",
    "name:und_x_variant":[
        "\uc0c1\ub098\ubc30\uae30",
        "Sangnabaegi"
    ],
    "wof:name":"Sangnabaegi",
    "wof:placetype":"locality"
},
  "geometry": {"coordinates":[126.8128,36.7931],"type":"Point"}
}