{
  "type": "Feature",
  "properties": {
    "gn:admin1_code":"14.0",
    "gn:asciiname":"Jagaedong",
    "gn:country_code":"KR",
    "gn:dem":177,
    "gn:feature_class":"P",
    "gn:feature_code":"PPL",
    "gn:name":"Jagaedong",
    "gn:population":0,
    "gn:timezone":"Asia/Seoul",
    "iso:country":"KR",
    "name:kor_x_preferred":[
        "\uc790\uac1c\ub3d9"
    ],
    "wof:name":"Jagaedong",
    "wof:placetype":"locality"
},
  "geometry": {"coordinates":[128.56305,36.48201],"type":"Point"}
}