{
  "type": "Feature",
  "properties": {
    "gn:admin1_code":"16.0",
    "gn:asciiname":"Wau",
    "gn:country_code":"KR",
    "gn:dem":16,
    "gn:feature_class":"P",
    "gn:feature_code":"PPL",
    "gn:name":"Wau",
    "gn:population":0,
    "gn:timezone":"Asia/Seoul",
    "iso:country":"KR",
    "name:ceb_x_preferred":[
        "Wau"
    ],
    "name:deu_x_preferred":[
        "Wau"
    ],
    "name:fin_x_preferred":[
        "Wau"
    ],
    "name:fra_x_preferred":[
        "Wau"
    ],
    "name:kor_x_preferred":[
        "\uc640\uc6b0"
    ],
    "name:nld_x_preferred":[
        "Wau"
    ],
    "name:pol_x_preferred":[
        "Wau"
    ],
    "name:swe_x_preferred":[
        "Wau"
    ],
    "wof:name":"Wau",
    "wof:placetype":"locality"
},
  "geometry": {"coordinates":[127.71012,34.94363],"type":"Point"}
}