{
  "type": "Feature",
  "properties": {
    "gn:admin1_code":"17.0",
    "gn:asciiname":"Poktae-dong",
    "gn:country_code":"KR",
    "gn:dem":154,
    "gn:feature_class":"P",
    "gn:feature_code":"PPL",
    "gn:name":"Poktae-dong",
    "gn:population":0,
    "gn:timezone":"Asia/Seoul",
    "iso:country":"KR",
    "name:und_x_variant":[
        "\ubcf5\ub300\ub3d9",
        "Poktae-dong"
    ],
    "wof:name":"Poktae-dong",
    "wof:placetype":"locality"
},
  "geometry": {"coordinates":[126.90860000000001,36.4807],"type":"Point"}
}