{
  "type": "Feature",
  "properties": {
    "gn:admin1_code":"14.0",
    "gn:asciiname":"Jangjin",
    "gn:country_code":"KR",
    "gn:dem":5,
    "gn:feature_class":"P",
    "gn:feature_code":"PPL",
    "gn:name":"Jangjin",
    "gn:population":0,
    "gn:timezone":"Asia/Seoul",
    "iso:country":"KR",
    "name:kor_x_preferred":[
        "\uc7a5\uc9c4"
    ],
    "wof:name":"Jangjin",
    "wof:placetype":"locality"
},
  "geometry": {"coordinates":[129.49441999999999,35.79218],"type":"Point"}
}