{
  "type": "Feature",
  "properties": {
    "gn:admin1_code":"17.0",
    "gn:asciiname":"Kal-gol",
    "gn:country_code":"KR",
    "gn:dem":75,
    "gn:feature_class":"P",
    "gn:feature_code":"PPL",
    "gn:name":"Kal-gol",
    "gn:population":0,
    "gn:timezone":"Asia/Seoul",
    "iso:country":"KR",
    "name:und_x_variant":[
        "\uac08\uace8",
        "Kal-gol"
    ],
    "wof:name":"Kal-gol",
    "wof:placetype":"locality"
},
  "geometry": {"coordinates":[126.5659,36.8602],"type":"Point"}
}