{
  "type": "Feature",
  "properties": {
    "gn:admin1_code":"14.0",
    "gn:asciiname":"Chukchon-dong",
    "gn:country_code":"KR",
    "gn:dem":68,
    "gn:feature_class":"P",
    "gn:feature_code":"PPL",
    "gn:name":"Chukch\u014fn-dong",
    "gn:population":0,
    "gn:timezone":"Asia/Seoul",
    "iso:country":"KR",
    "name:und_x_variant":[
        "\uc8fd\uc804\ub3d9",
        "Chukch\u014fn-dong"
    ],
    "wof:name":"Chukchon-dong",
    "wof:placetype":"locality"
},
  "geometry": {"coordinates":[128.16229999999999,36.4446],"type":"Point"}
}