{
  "type": "Feature",
  "properties": {
    "gn:admin1_code":"6.0",
    "gn:asciiname":"Ogwon",
    "gn:country_code":"KR",
    "gn:dem":25,
    "gn:feature_class":"P",
    "gn:feature_code":"PPL",
    "gn:name":"Ogw\u014fn",
    "gn:population":0,
    "gn:timezone":"Asia/Seoul",
    "iso:country":"KR",
    "name:und_x_variant":[
        "Ogw\u014fn-ni",
        "\uc625\uc6d0",
        "Ogw\u014fn"
    ],
    "wof:name":"Ogwon",
    "wof:placetype":"locality"
},
  "geometry": {"coordinates":[129.32069999999999,37.1853],"type":"Point"}
}