{
  "type": "Feature",
  "properties": {
    "gn:admin1_code":"14.0",
    "gn:asciiname":"Gwangdaejeong",
    "gn:country_code":"KR",
    "gn:dem":58,
    "gn:feature_class":"P",
    "gn:feature_code":"PPL",
    "gn:name":"Gwangdaejeong",
    "gn:population":0,
    "gn:timezone":"Asia/Seoul",
    "iso:country":"KR",
    "name:kor_x_preferred":[
        "\uad11\ub300\uc815"
    ],
    "wof:name":"Gwangdaejeong",
    "wof:placetype":"locality"
},
  "geometry": {"coordinates":[128.26407,36.52052],"type":"Point"}
}