{
  "type": "Feature",
  "properties": {
    "gn:admin1_code":"17.0",
    "gn:asciiname":"Pumu-gol",
    "gn:country_code":"KR",
    "gn:dem":21,
    "gn:feature_class":"P",
    "gn:feature_code":"PPL",
    "gn:name":"Pumu-gol",
    "gn:population":0,
    "gn:timezone":"Asia/Seoul",
    "iso:country":"KR",
    "name:und_x_variant":[
        "\ubd80\ubb34\uace8",
        "Pumu-gol"
    ],
    "wof:name":"Pumu-gol",
    "wof:placetype":"locality"
},
  "geometry": {"coordinates":[126.28230000000001,36.8556],"type":"Point"}
}