{
  "type": "Feature",
  "properties": {
    "gn:admin1_code":"16.0",
    "gn:asciiname":"Hansadong",
    "gn:country_code":"KR",
    "gn:dem":193,
    "gn:feature_class":"P",
    "gn:feature_code":"PPL",
    "gn:name":"Hansadong",
    "gn:population":0,
    "gn:timezone":"Asia/Seoul",
    "iso:country":"KR",
    "name:kor_x_preferred":[
        "\ud55c\uc0ac\ub3d9"
    ],
    "wof:name":"Hansadong",
    "wof:placetype":"locality"
},
  "geometry": {"coordinates":[126.67019000000001,35.32393],"type":"Point"}
}