{
  "type": "Feature",
  "properties": {
    "gn:admin1_code":"1.0",
    "gn:asciiname":"Junghadong",
    "gn:country_code":"KR",
    "gn:dem":6,
    "gn:feature_class":"P",
    "gn:feature_code":"PPL",
    "gn:name":"Junghadong",
    "gn:population":0,
    "gn:timezone":"Asia/Seoul",
    "iso:country":"KR",
    "name:kor_x_preferred":[
        "\uc911\ud558\ub3d9"
    ],
    "wof:name":"Junghadong",
    "wof:placetype":"locality"
},
  "geometry": {"coordinates":[126.25005,33.22239],"type":"Point"}
}