{
  "type": "Feature",
  "properties": {
    "gn:admin1_code":"17.0",
    "gn:asciiname":"Araenmalmo-ri",
    "gn:country_code":"KR",
    "gn:dem":201,
    "gn:feature_class":"P",
    "gn:feature_code":"PPL",
    "gn:name":"Araenmalm\u014f-ri",
    "gn:population":0,
    "gn:timezone":"Asia/Seoul",
    "iso:country":"KR",
    "name:und_x_variant":[
        "\uc544\ub7ab\ub9d0\uba38\ub9ac",
        "Araenmalm\u014f-ri"
    ],
    "wof:name":"Araenmalmo-ri",
    "wof:placetype":"locality"
},
  "geometry": {"coordinates":[127.4753,36.1488],"type":"Point"}
}