{
  "type": "Feature",
  "properties": {
    "gn:admin1_code":"21.0",
    "gn:asciiname":"Banjeong",
    "gn:country_code":"KR",
    "gn:dem":146,
    "gn:feature_class":"P",
    "gn:feature_code":"PPL",
    "gn:name":"Banjeong",
    "gn:population":0,
    "gn:timezone":"Asia/Seoul",
    "iso:country":"KR",
    "name:kor_x_preferred":[
        "\ubc18\uc815"
    ],
    "wof:name":"Banjeong",
    "wof:placetype":"locality"
},
  "geometry": {"coordinates":[129.24232000000001,35.5006],"type":"Point"}
}