{
  "type": "Feature",
  "properties": {
    "gn:admin1_code":"13.0",
    "gn:asciiname":"Jangjagol",
    "gn:country_code":"KR",
    "gn:dem":131,
    "gn:feature_class":"P",
    "gn:feature_code":"PPL",
    "gn:name":"Jangjagol",
    "gn:population":0,
    "gn:timezone":"Asia/Seoul",
    "iso:country":"KR",
    "name:kor_x_preferred":[
        "\uc7a5\uc790\uace8"
    ],
    "wof:name":"Jangjagol",
    "wof:placetype":"locality"
},
  "geometry": {"coordinates":[127.28203999999999,37.9311],"type":"Point"}
}