{
  "type": "Feature",
  "properties": {
    "gn:admin1_code":"5.0",
    "gn:asciiname":"Bonmal",
    "gn:country_code":"KR",
    "gn:dem":94,
    "gn:feature_class":"P",
    "gn:feature_code":"PPL",
    "gn:name":"Bonmal",
    "gn:population":0,
    "gn:timezone":"Asia/Seoul",
    "iso:country":"KR",
    "name:kor_x_preferred":[
        "\ubcf8\ub9d0"
    ],
    "name:und_x_variant":[
        "Pon-mal"
    ],
    "wof:name":"Bonmal",
    "wof:placetype":"locality"
},
  "geometry": {"coordinates":[127.61095,37.05054000000001],"type":"Point"}
}