{
  "type": "Feature",
  "properties": {
    "gn:admin1_code":"14.0",
    "gn:asciiname":"Sajeong",
    "gn:country_code":"KR",
    "gn:dem":77,
    "gn:feature_class":"P",
    "gn:feature_code":"PPL",
    "gn:name":"Sajeong",
    "gn:population":0,
    "gn:timezone":"Asia/Seoul",
    "iso:country":"KR",
    "name:kor_x_preferred":[
        "\uc0ac\uc815"
    ],
    "wof:name":"Sajeong",
    "wof:placetype":"locality"
},
  "geometry": {"coordinates":[128.72558999999998,35.81571],"type":"Point"}
}