{
  "type": "Feature",
  "properties": {
    "gn:admin1_code":"17.0",
    "gn:asciiname":"Osal-li",
    "gn:country_code":"KR",
    "gn:dem":25,
    "gn:feature_class":"P",
    "gn:feature_code":"PPL",
    "gn:name":"Osal-li",
    "gn:population":0,
    "gn:timezone":"Asia/Seoul",
    "iso:country":"KR",
    "name:und_x_variant":[
        "\uc624\uc0b0\ub9ac",
        "Osal-li"
    ],
    "wof:name":"Osal-li",
    "wof:placetype":"locality"
},
  "geometry": {"coordinates":[126.925,36.7987],"type":"Point"}
}