{
  "type": "Feature",
  "properties": {
    "gn:admin1_code":"6.0",
    "gn:asciiname":"Hyeonchon",
    "gn:country_code":"KR",
    "gn:dem":331,
    "gn:feature_class":"P",
    "gn:feature_code":"PPL",
    "gn:name":"Hyeonchon",
    "gn:population":0,
    "gn:timezone":"Asia/Seoul",
    "iso:country":"KR",
    "name:kor_x_preferred":[
        "\ud604\ucd0c"
    ],
    "wof:name":"Hyeonchon",
    "wof:placetype":"locality"
},
  "geometry": {"coordinates":[128.21311,38.2496],"type":"Point"}
}