{
  "type": "Feature",
  "properties": {
    "gn:admin1_code":"13.0",
    "gn:asciiname":"Jangdan",
    "gn:country_code":"KR",
    "gn:dem":42,
    "gn:feature_class":"P",
    "gn:feature_code":"PPL",
    "gn:name":"Jangdan",
    "gn:population":0,
    "gn:timezone":"Asia/Seoul",
    "iso:country":"KR",
    "name:kor_x_preferred":[
        "\uc7a5\ub2e8"
    ],
    "name:und_x_variant":[
        "\u016cmnae-ri",
        "Ch\u014dtan",
        "Changdan",
        "Jangdan"
    ],
    "wof:name":"Jangdan",
    "wof:placetype":"locality"
},
  "geometry": {"coordinates":[126.74672,37.93779],"type":"Point"}
}