{
  "type": "Feature",
  "properties": {
    "gn:admin1_code":"5.0",
    "gn:asciiname":"Keunjakgol",
    "gn:country_code":"KR",
    "gn:dem":74,
    "gn:feature_class":"P",
    "gn:feature_code":"PPL",
    "gn:name":"Keunjakgol",
    "gn:population":0,
    "gn:timezone":"Asia/Seoul",
    "iso:country":"KR",
    "name:kor_x_preferred":[
        "\ud070\uc791\uace8"
    ],
    "wof:name":"Keunjakgol",
    "wof:placetype":"locality"
},
  "geometry": {"coordinates":[127.56433,36.73342],"type":"Point"}
}