{
  "type": "Feature",
  "properties": {
    "gn:admin1_code":"5.0",
    "gn:asciiname":"Borijae",
    "gn:country_code":"KR",
    "gn:dem":248,
    "gn:feature_class":"P",
    "gn:feature_code":"PPL",
    "gn:name":"Borijae",
    "gn:population":0,
    "gn:timezone":"Asia/Seoul",
    "iso:country":"KR",
    "name:kor_x_preferred":[
        "\ubcf4\ub9ac\uc7ac"
    ],
    "wof:name":"Borijae",
    "wof:placetype":"locality"
},
  "geometry": {"coordinates":[127.67144,36.64815],"type":"Point"}
}