{
  "type": "Feature",
  "properties": {
    "gn:admin1_code":"14.0",
    "gn:asciiname":"Saemaul-ch'on",
    "gn:country_code":"KR",
    "gn:dem":229,
    "gn:feature_class":"P",
    "gn:feature_code":"PPL",
    "gn:name":"Saema\u016dl-ch\u2019on",
    "gn:population":0,
    "gn:timezone":"Asia/Seoul",
    "iso:country":"KR",
    "name:und_x_variant":[
        "\uc0c8\ub9c8\uc744\ucd0c",
        "Saema\u016dl-ch\u2019on"
    ],
    "wof:name":"Saemaul-ch'on",
    "wof:placetype":"locality"
},
  "geometry": {"coordinates":[129.14269999999999,36.591],"type":"Point"}
}