{
  "type": "Feature",
  "properties": {
    "gn:admin1_code":"17.0",
    "gn:asciiname":"Kkakkun-mal",
    "gn:country_code":"KR",
    "gn:dem":65,
    "gn:feature_class":"P",
    "gn:feature_code":"PPL",
    "gn:name":"Kkakk\u016dn-mal",
    "gn:population":0,
    "gn:timezone":"Asia/Seoul",
    "iso:country":"KR",
    "name:und_x_variant":[
        "\uae4d\ub048\ub9d0",
        "Kkakk\u016dn-mal"
    ],
    "wof:name":"Kkakkun-mal",
    "wof:placetype":"locality"
},
  "geometry": {"coordinates":[126.8074,36.5769],"type":"Point"}
}