{
  "type": "Feature",
  "properties": {
    "gn:admin1_code":"5.0",
    "gn:asciiname":"Muryodae",
    "gn:country_code":"KR",
    "gn:dem":261,
    "gn:feature_class":"P",
    "gn:feature_code":"PPL",
    "gn:name":"Mury\u014fdae",
    "gn:population":0,
    "gn:timezone":"Asia/Seoul",
    "iso:country":"KR",
    "name:und_x_variant":[
        "\ubb3c\uc5ec\ub300",
        "Mury\u014fdae"
    ],
    "wof:name":"Muryodae",
    "wof:placetype":"locality"
},
  "geometry": {"coordinates":[127.96040000000001,36.1601],"type":"Point"}
}