{
  "type": "Feature",
  "properties": {
    "gn:admin1_code":"13.0",
    "gn:asciiname":"Heonteo",
    "gn:country_code":"KR",
    "gn:dem":67,
    "gn:feature_class":"P",
    "gn:feature_code":"PPL",
    "gn:name":"Heonteo",
    "gn:population":0,
    "gn:timezone":"Asia/Seoul",
    "iso:country":"KR",
    "name:kor_x_preferred":[
        "\ud5cc\ud130"
    ],
    "name:kor_x_variant":[
        "H\u014fnt\u2019\u014f"
    ],
    "wof:name":"Heonteo",
    "wof:placetype":"locality"
},
  "geometry": {"coordinates":[127.63952999999999,37.17529],"type":"Point"}
}