{
  "type": "Feature",
  "properties": {
    "gn:admin1_code":"6.0",
    "gn:asciiname":"Chungson",
    "gn:country_code":"KR",
    "gn:dem":354,
    "gn:feature_class":"P",
    "gn:feature_code":"PPL",
    "gn:name":"Chungs\u014fn",
    "gn:population":0,
    "gn:timezone":"Asia/Seoul",
    "iso:country":"KR",
    "name:kor_x_preferred":[
        "\uc911\uc120"
    ],
    "name:kor_x_variant":[
        "Chungs\u014fn"
    ],
    "wof:name":"Chungson",
    "wof:placetype":"locality"
},
  "geometry": {"coordinates":[128.3091,37.3373],"type":"Point"}
}