{
  "type": "Feature",
  "properties": {
    "gn:admin1_code":"3.0",
    "gn:asciiname":"Kajong",
    "gn:country_code":"KR",
    "gn:dem":216,
    "gn:feature_class":"P",
    "gn:feature_code":"PPL",
    "gn:name":"Kaj\u014fng",
    "gn:population":0,
    "gn:timezone":"Asia/Seoul",
    "iso:country":"KR",
    "name:und_x_variant":[
        "Kaj\u014fng-ni",
        "Kaj\u014fng",
        "\uac00\uc815"
    ],
    "wof:name":"Kajong",
    "wof:placetype":"locality"
},
  "geometry": {"coordinates":[127.5806,36.014],"type":"Point"}
}