{
  "type": "Feature",
  "properties": {
    "gn:admin1_code":"13.0",
    "gn:asciiname":"Kujae",
    "gn:country_code":"KR",
    "gn:dem":82,
    "gn:feature_class":"P",
    "gn:feature_code":"PPL",
    "gn:name":"Kujae",
    "gn:population":0,
    "gn:timezone":"Asia/Seoul",
    "iso:country":"KR",
    "name:und_x_variant":[
        "\uad6c\uc7ac",
        "Gujae",
        "Kujae"
    ],
    "wof:name":"Kujae",
    "wof:placetype":"locality"
},
  "geometry": {"coordinates":[127.62333,37.37556],"type":"Point"}
}