{
  "type": "Feature",
  "properties": {
    "gn:admin1_code":"16.0",
    "gn:asciiname":"Sangok",
    "gn:country_code":"KR",
    "gn:dem":8,
    "gn:feature_class":"P",
    "gn:feature_code":"PPL",
    "gn:name":"Sangok",
    "gn:population":0,
    "gn:timezone":"Asia/Seoul",
    "iso:country":"KR",
    "name:kor_x_preferred":[
        "\uc0b0\uace1"
    ],
    "name:und_x_variant":[
        "San\u2019gok"
    ],
    "wof:name":"Sangok",
    "wof:placetype":"locality"
},
  "geometry": {"coordinates":[127.60944000000001,34.83907],"type":"Point"}
}