{
  "type": "Feature",
  "properties": {
    "gn:admin1_code":"6.0",
    "gn:asciiname":"Won-ri",
    "gn:country_code":"KR",
    "gn:dem":286,
    "gn:feature_class":"P",
    "gn:feature_code":"PPL",
    "gn:name":"Won-ri",
    "gn:population":0,
    "gn:timezone":"Asia/Seoul",
    "iso:country":"KR",
    "name:kor_x_preferred":[
        "\uc6d0\ub9ac"
    ],
    "name:kor_x_variant":[
        "W\u014fl-li"
    ],
    "wof:name":"Won-ri",
    "wof:placetype":"locality"
},
  "geometry": {"coordinates":[128.04721999999998,38.05361],"type":"Point"}
}