{
  "type": "Feature",
  "properties": {
    "gn:admin1_code":"13.0",
    "gn:asciiname":"Gwangcheon",
    "gn:country_code":"KR",
    "gn:dem":30,
    "gn:feature_class":"P",
    "gn:feature_code":"PPL",
    "gn:name":"Gwangcheon",
    "gn:population":0,
    "gn:timezone":"Asia/Seoul",
    "iso:country":"KR",
    "name:und_x_variant":[
        "\uad11\ucc9c",
        "Gwangcheon",
        "Kwangch\u2019\u014fn"
    ],
    "wof:name":"Gwangcheon",
    "wof:placetype":"locality"
},
  "geometry": {"coordinates":[127.06386999999999,37.0339],"type":"Point"}
}