{
  "type": "Feature",
  "properties": {
    "gn:admin1_code":"14.0",
    "gn:asciiname":"Arunosan",
    "gn:country_code":"KR",
    "gn:dem":135,
    "gn:feature_class":"P",
    "gn:feature_code":"PPL",
    "gn:name":"Arunosan",
    "gn:population":0,
    "gn:timezone":"Asia/Seoul",
    "iso:country":"KR",
    "name:und_x_variant":[
        "\uc544\ub8e8\ub178\uc0b0",
        "Arunosan"
    ],
    "wof:name":"Arunosan",
    "wof:placetype":"locality"
},
  "geometry": {"coordinates":[128.02590000000001,36.3725],"type":"Point"}
}