{
  "type": "Feature",
  "properties": {
    "gn:admin1_code":"16.0",
    "gn:asciiname":"Daesil",
    "gn:country_code":"KR",
    "gn:dem":179,
    "gn:feature_class":"P",
    "gn:feature_code":"PPL",
    "gn:name":"Daesil",
    "gn:population":0,
    "gn:timezone":"Asia/Seoul",
    "iso:country":"KR",
    "name:kor_x_preferred":[
        "\ub300\uc2e4"
    ],
    "name:und_x_variant":[
        "Taesil",
        "Chuksil",
        "Chukkok"
    ],
    "wof:name":"Daesil",
    "wof:placetype":"locality"
},
  "geometry": {"coordinates":[127.64388999999998,34.97944],"type":"Point"}
}