{
  "type": "Feature",
  "properties": {
    "gn:admin1_code":"6.0",
    "gn:asciiname":"Changjonp'yong-ni",
    "gn:country_code":"KR",
    "gn:dem":245,
    "gn:feature_class":"P",
    "gn:feature_code":"PPLL",
    "gn:name":"Changj\u014fnp\u2019y\u014fng-ni",
    "gn:population":0,
    "gn:timezone":"Asia/Seoul",
    "iso:country":"KR",
    "name:kor_x_preferred":[
        "\uc7a5\uc804\ud3c9\ub9ac"
    ],
    "name:kor_x_variant":[
        "Changj\u014fnp\u2019y\u014fng-ni"
    ],
    "wof:name":"Changjonp'yong-ni",
    "wof:placetype":"locality"
},
  "geometry": {"coordinates":[127.88618999999998,37.65135],"type":"Point"}
}