{
  "type": "Feature",
  "properties": {
    "gn:admin1_code":"14.0",
    "gn:asciiname":"Waenaru",
    "gn:country_code":"KR",
    "gn:dem":30,
    "gn:feature_class":"P",
    "gn:feature_code":"PPL",
    "gn:name":"Waenaru",
    "gn:population":0,
    "gn:timezone":"Asia/Seoul",
    "iso:country":"KR",
    "name:kor_x_preferred":[
        "\uc65c\ub098\ub8e8"
    ],
    "wof:name":"Waenaru",
    "wof:placetype":"locality"
},
  "geometry": {"coordinates":[128.38369,35.70792],"type":"Point"}
}