{
  "type": "Feature",
  "properties": {
    "gn:admin1_code":"14.0",
    "gn:asciiname":"Eumjimaeul",
    "gn:country_code":"KR",
    "gn:dem":72,
    "gn:feature_class":"P",
    "gn:feature_code":"PPL",
    "gn:name":"Eumjimaeul",
    "gn:population":0,
    "gn:timezone":"Asia/Seoul",
    "iso:country":"KR",
    "name:kor_x_preferred":[
        "\uc74c\uc9c0\ub9c8\uc744"
    ],
    "wof:name":"Eumjimaeul",
    "wof:placetype":"locality"
},
  "geometry": {"coordinates":[129.2259,35.8227],"type":"Point"}
}