{
  "type": "Feature",
  "properties": {
    "gn:admin1_code":"5.0",
    "gn:asciiname":"Suryeul",
    "gn:country_code":"KR",
    "gn:dem":203,
    "gn:feature_class":"P",
    "gn:feature_code":"PPL",
    "gn:name":"Suryeul",
    "gn:population":0,
    "gn:timezone":"Asia/Seoul",
    "iso:country":"KR",
    "name:kor_x_preferred":[
        "\uc218\ub808\uc6b8"
    ],
    "name:kor_x_variant":[
        "\uc218\ub840\uc6b8"
    ],
    "name:und_x_variant":[
        "Sureul"
    ],
    "wof:name":"Suryeul",
    "wof:placetype":"locality"
},
  "geometry": {"coordinates":[127.64708,37.04518],"type":"Point"}
}