{
  "type": "Feature",
  "properties": {
    "gn:admin1_code":"17.0",
    "gn:asciiname":"Malmok",
    "gn:country_code":"KR",
    "gn:dem":27,
    "gn:feature_class":"P",
    "gn:feature_code":"PPL",
    "gn:name":"Malmok",
    "gn:population":0,
    "gn:timezone":"Asia/Seoul",
    "iso:country":"KR",
    "name:und_x_variant":[
        "\ub9d0\ubaa9",
        "Malmok"
    ],
    "wof:name":"Malmok",
    "wof:placetype":"locality"
},
  "geometry": {"coordinates":[126.59950000000001,36.8607],"type":"Point"}
}