{
  "type": "Feature",
  "properties": {
    "gn:admin1_code":"14.0",
    "gn:asciiname":"Byeokgye",
    "gn:country_code":"KR",
    "gn:dem":42,
    "gn:feature_class":"P",
    "gn:feature_code":"PPL",
    "gn:name":"Byeokgye",
    "gn:population":0,
    "gn:timezone":"Asia/Seoul",
    "iso:country":"KR",
    "name:und_x_variant":[
        "\ubcbd\uacc4",
        "Py\u014fkkye",
        "Byeokgye"
    ],
    "wof:name":"Byeokgye",
    "wof:placetype":"locality"
},
  "geometry": {"coordinates":[129.24903999999998,36.05941],"type":"Point"}
}