{
  "type": "Feature",
  "properties": {
    "gn:admin1_code":"0.0",
    "gn:asciiname":"Pison-ni",
    "gn:country_code":"KR",
    "gn:dem":28,
    "gn:feature_class":"P",
    "gn:feature_code":"PPL",
    "gn:name":"Pis\u014fn-ni",
    "gn:population":0,
    "gn:timezone":"Asia/Seoul",
    "iso:country":"KR",
    "name:eng_x_preferred":[
        "Pison"
    ],
    "name:eng_x_variant":[
        "Pison-ni"
    ],
    "wof:name":"Pison",
    "wof:placetype":"locality"
},
  "geometry": {"coordinates":[126.90000000000001,35.63333],"type":"Point"}
}