{
  "type": "Feature",
  "properties": {
    "gn:admin1_code":"20.0",
    "gn:asciiname":"Samdae-ri",
    "gn:country_code":"KR",
    "gn:dem":82,
    "gn:feature_class":"P",
    "gn:feature_code":"PPL",
    "gn:name":"Samdae-ri",
    "gn:population":0,
    "gn:timezone":"Asia/Seoul",
    "iso:country":"KR",
    "name:und_x_variant":[
        "Samt\u2019ae-ri"
    ],
    "wof:name":"Samdae-ri",
    "wof:placetype":"locality"
},
  "geometry": {"coordinates":[128.65000000000001,35.48333],"type":"Point"}
}