{
  "type": "Feature",
  "properties": {
    "gn:admin1_code":"20.0",
    "gn:asciiname":"Anmasil",
    "gn:country_code":"KR",
    "gn:dem":138,
    "gn:feature_class":"P",
    "gn:feature_code":"PPL",
    "gn:name":"Anmasil",
    "gn:population":0,
    "gn:timezone":"Asia/Seoul",
    "iso:country":"KR",
    "name:und_x_variant":[
        "\uc548\ub9c8\uc2e4",
        "Anmasil"
    ],
    "wof:name":"Anmasil",
    "wof:placetype":"locality"
},
  "geometry": {"coordinates":[128.54230999999999,35.60270999999999],"type":"Point"}
}