{
  "type": "Feature",
  "properties": {
    "gn:admin1_code":"6.0",
    "gn:asciiname":"Gundeul",
    "gn:country_code":"KR",
    "gn:dem":378,
    "gn:feature_class":"P",
    "gn:feature_code":"PPL",
    "gn:name":"Gundeul",
    "gn:population":0,
    "gn:timezone":"Asia/Seoul",
    "iso:country":"KR",
    "name:kor_x_preferred":[
        "\ud558\uad70\ub4e4"
    ],
    "name:kor_x_variant":[
        "Hagund\u016dl",
        "\uad70\ub4e4"
    ],
    "wof:name":"Gundeul",
    "wof:placetype":"locality"
},
  "geometry": {"coordinates":[128.07076000000001,37.72192],"type":"Point"}
}