{
  "type": "Feature",
  "properties": {
    "gn:admin1_code":"13.0",
    "gn:asciiname":"Wonbong",
    "gn:country_code":"KR",
    "gn:dem":61,
    "gn:feature_class":"P",
    "gn:feature_code":"PPL",
    "gn:name":"Wonbong",
    "gn:population":0,
    "gn:timezone":"Asia/Seoul",
    "iso:country":"KR",
    "name:kor_x_preferred":[
        "\uc6d0\ubd09"
    ],
    "wof:name":"Wonbong",
    "wof:placetype":"locality"
},
  "geometry": {"coordinates":[126.9311,38.01074000000001],"type":"Point"}
}