{
  "type": "Feature",
  "properties": {
    "gn:admin1_code":"14.0",
    "gn:asciiname":"Sangseok",
    "gn:country_code":"KR",
    "gn:dem":88,
    "gn:feature_class":"P",
    "gn:feature_code":"PPL",
    "gn:name":"Sangseok",
    "gn:population":0,
    "gn:timezone":"Asia/Seoul",
    "iso:country":"KR",
    "name:kor_x_preferred":[
        "\uc0c1\uc11d"
    ],
    "name:und_x_variant":[
        "Sangs\u014fng-ni",
        "Sans\u014fk",
        "Sangseok"
    ],
    "wof:name":"Sangseok",
    "wof:placetype":"locality"
},
  "geometry": {"coordinates":[129.2919,35.66956],"type":"Point"}
}