{
  "type": "Feature",
  "properties": {
    "gn:admin1_code":"16.0",
    "gn:asciiname":"Miya",
    "gn:country_code":"KR",
    "gn:dem":10,
    "gn:feature_class":"P",
    "gn:feature_code":"PPL",
    "gn:name":"Miya",
    "gn:population":0,
    "gn:timezone":"Asia/Seoul",
    "iso:country":"KR",
    "name:deu_x_preferred":[
        "Miya"
    ],
    "name:fra_x_preferred":[
        "Miya"
    ],
    "name:kor_x_preferred":[
        "\ubbf8\uc57c"
    ],
    "name:nld_x_preferred":[
        "Miya"
    ],
    "name:ukr_x_preferred":[
        "\u041c\u0456\u044f"
    ],
    "name:vie_x_preferred":[
        "Cung"
    ],
    "name:zho_x_preferred":[
        "\u5bae"
    ],
    "wof:name":"Miya",
    "wof:placetype":"locality"
},
  "geometry": {"coordinates":[126.52139,34.37944],"type":"Point"}
}