{
  "type": "Feature",
  "properties": {
    "gn:admin1_code":"13.0",
    "gn:asciiname":"Chuk-kol",
    "gn:country_code":"KR",
    "gn:dem":71,
    "gn:feature_class":"P",
    "gn:feature_code":"PPL",
    "gn:name":"Chuk-kol",
    "gn:population":0,
    "gn:timezone":"Asia/Seoul",
    "iso:country":"KR",
    "name:und_x_variant":[
        "\uc8fd\uace8",
        "Juk-gol",
        "Chuk-kol"
    ],
    "wof:name":"Chuk-kol",
    "wof:placetype":"locality"
},
  "geometry": {"coordinates":[127.51694000000001,37.27917],"type":"Point"}
}