{
  "type": "Feature",
  "properties": {
    "gn:admin1_code":"17.0",
    "gn:asciiname":"Geombawi",
    "gn:country_code":"KR",
    "gn:dem":71,
    "gn:feature_class":"P",
    "gn:feature_code":"PPL",
    "gn:name":"Geombawi",
    "gn:population":0,
    "gn:timezone":"Asia/Seoul",
    "iso:country":"KR",
    "name:und_x_variant":[
        "\uac80\ubc14\uc704",
        "K\u014fmbawi",
        "Geombawi"
    ],
    "wof:name":"Geombawi",
    "wof:placetype":"locality"
},
  "geometry": {"coordinates":[127.34174,36.46922],"type":"Point"}
}