{
  "type": "Feature",
  "properties": {
    "gn:admin1_code":"16.0",
    "gn:asciiname":"Daebeol-ri",
    "gn:country_code":"KR",
    "gn:dem":9,
    "gn:feature_class":"P",
    "gn:feature_code":"PPL",
    "gn:name":"Daebeol-ri",
    "gn:population":0,
    "gn:timezone":"Asia/Seoul",
    "iso:country":"KR",
    "name:kor_x_preferred":[
        "\ub300\ubc8c\ub9ac"
    ],
    "name:und_x_variant":[
        "Taeb\u014fl",
        "Taeb\u014fl-li",
        "Daebeol-ri"
    ],
    "wof:name":"Daebeol-ri",
    "wof:placetype":"locality"
},
  "geometry": {"coordinates":[126.27043999999999,34.85925],"type":"Point"}
}