{
  "type": "Feature",
  "properties": {
    "gn:admin1_code":"17.0",
    "gn:asciiname":"Anakkul",
    "gn:country_code":"KR",
    "gn:dem":5,
    "gn:feature_class":"P",
    "gn:feature_code":"PPL",
    "gn:name":"Anakkul",
    "gn:population":0,
    "gn:timezone":"Asia/Seoul",
    "iso:country":"KR",
    "name:und_x_variant":[
        "\uc544\ub099\uad74",
        "Anakkul"
    ],
    "wof:name":"Anakkul",
    "wof:placetype":"locality"
},
  "geometry": {"coordinates":[126.4884,36.5302],"type":"Point"}
}