{
  "type": "Feature",
  "properties": {
    "gn:admin1_code":"0.0",
    "gn:asciiname":"Punt'ong",
    "gn:country_code":"KR",
    "gn:dem":173,
    "gn:feature_class":"P",
    "gn:feature_code":"PPL",
    "gn:name":"Punt\u2019ong",
    "gn:population":0,
    "gn:timezone":"Asia/Seoul",
    "iso:country":"KR",
    "name:kor_x_preferred":[
        "\ubd84\ud1b5"
    ],
    "name:und_x_variant":[
        "Punt\u2019ong-ni",
        "Punt\u2019ong",
        "Buntong"
    ],
    "wof:name":"Punt'ong",
    "wof:placetype":"locality"
},
  "geometry": {"coordinates":[127.03333000000001,35.41667],"type":"Point"}
}