{
  "type": "Feature",
  "properties": {
    "gn:admin1_code":"13.0",
    "gn:admin2_code":"Ans\u014fng-si",
    "gn:asciiname":"Baetimaeul",
    "gn:country_code":"KR",
    "gn:dem":93,
    "gn:feature_class":"P",
    "gn:feature_code":"PPL",
    "gn:name":"Baetimaeul",
    "gn:population":0,
    "gn:timezone":"Asia/Seoul",
    "iso:country":"KR",
    "name:kor_x_preferred":[
        "\ubc30\ud2f0\ub9c8\uc744"
    ],
    "name:kor_x_variant":[
        "Paet\u2019i-ma\u016dl"
    ],
    "wof:name":"Baetimaeul",
    "wof:placetype":"locality"
},
  "geometry": {"coordinates":[127.21863999999999,37.09325],"type":"Point"}
}