{
  "type": "Feature",
  "properties": {
    "gn:admin1_code":"6.0",
    "gn:asciiname":"Dongmaedong",
    "gn:country_code":"KR",
    "gn:dem":300,
    "gn:feature_class":"P",
    "gn:feature_code":"PPLL",
    "gn:name":"Dongmaedong",
    "gn:population":0,
    "gn:timezone":"Asia/Seoul",
    "iso:country":"KR",
    "name:kor_x_preferred":[
        "\ub3d9\ub9e4\ub3d9"
    ],
    "wof:name":"Dongmaedong",
    "wof:placetype":"locality"
},
  "geometry": {"coordinates":[127.94653999999998,38.23117],"type":"Point"}
}