{
  "type": "Feature",
  "properties": {
    "gn:admin1_code":"15.0",
    "gn:asciiname":"Gangyeong",
    "gn:country_code":"KR",
    "gn:dem":30,
    "gn:feature_class":"P",
    "gn:feature_code":"PPL",
    "gn:name":"Gangyeong",
    "gn:population":0,
    "gn:timezone":"Asia/Seoul",
    "iso:country":"KR",
    "name:kor_x_preferred":[
        "\uac04\uacbd"
    ],
    "wof:name":"Gangyeong",
    "wof:placetype":"locality"
},
  "geometry": {"coordinates":[128.46907999999999,35.79347999999999],"type":"Point"}
}