{
  "type": "Feature",
  "properties": {
    "gn:admin1_code":"13.0",
    "gn:asciiname":"Sangmosan",
    "gn:country_code":"KR",
    "gn:dem":59,
    "gn:feature_class":"P",
    "gn:feature_code":"PPL",
    "gn:name":"Sangmosan",
    "gn:population":0,
    "gn:timezone":"Asia/Seoul",
    "iso:country":"KR",
    "name:kor_x_preferred":[
        "\uc0c1\ubaa8\uc0b0"
    ],
    "wof:name":"Sangmosan",
    "wof:placetype":"locality"
},
  "geometry": {"coordinates":[127.24078,37.0407],"type":"Point"}
}