{
  "type": "Feature",
  "properties": {
    "gn:admin1_code":"17.0",
    "gn:asciiname":"Wittaesil",
    "gn:country_code":"KR",
    "gn:dem":57,
    "gn:feature_class":"P",
    "gn:feature_code":"PPL",
    "gn:name":"Wittaesil",
    "gn:population":0,
    "gn:timezone":"Asia/Seoul",
    "iso:country":"KR",
    "name:und_x_variant":[
        "\uc717\ub300\uc2e4",
        "Wittaesil"
    ],
    "wof:name":"Wittaesil",
    "wof:placetype":"locality"
},
  "geometry": {"coordinates":[126.98439999999999,36.8282],"type":"Point"}
}