{
  "type": "Feature",
  "properties": {
    "gn:admin1_code":"14.0",
    "gn:asciiname":"Tari-gol",
    "gn:country_code":"KR",
    "gn:dem":312,
    "gn:feature_class":"P",
    "gn:feature_code":"PPL",
    "gn:name":"Tari-gol",
    "gn:population":0,
    "gn:timezone":"Asia/Seoul",
    "iso:country":"KR",
    "wof:name":"Tari-gol",
    "wof:placetype":"locality"
},
  "geometry": {"coordinates":[129.09970000000001,36.4107],"type":"Point"}
}