{
  "type": "Feature",
  "properties": {
    "gn:admin1_code":"6.0",
    "gn:asciiname":"Gasandong",
    "gn:country_code":"KR",
    "gn:dem":481,
    "gn:feature_class":"P",
    "gn:feature_code":"PPL",
    "gn:name":"Gasandong",
    "gn:population":0,
    "gn:timezone":"Asia/Seoul",
    "iso:country":"KR",
    "name:kor_x_preferred":[
        "\uac00\uc0b0\ub3d9"
    ],
    "name:und_x_variant":[
        "Kasan-dong",
        "Gasandong"
    ],
    "wof:name":"Gasandong",
    "wof:placetype":"locality"
},
  "geometry": {"coordinates":[128.29989,37.91058],"type":"Point"}
}