{
  "type": "Feature",
  "properties": {
    "gn:admin1_code":"3.0",
    "gn:asciiname":"Mangdok",
    "gn:country_code":"KR",
    "gn:dem":274,
    "gn:feature_class":"P",
    "gn:feature_code":"PPL",
    "gn:name":"Mangd\u014fk",
    "gn:population":0,
    "gn:timezone":"Asia/Seoul",
    "iso:country":"KR",
    "name:und_x_variant":[
        "Mangd\u014fng-ni",
        "\ub9dd\ub355",
        "Moj\u014fng-ni",
        "Mangd\u014fk"
    ],
    "wof:name":"Mangdok",
    "wof:placetype":"locality"
},
  "geometry": {"coordinates":[127.48241000000002,35.89726],"type":"Point"}
}