{
  "type": "Feature",
  "properties": {
    "gn:admin1_code":"14.0",
    "gn:asciiname":"Sotgol",
    "gn:country_code":"KR",
    "gn:dem":397,
    "gn:feature_class":"P",
    "gn:feature_code":"PPL",
    "gn:name":"Sotgol",
    "gn:population":0,
    "gn:timezone":"Asia/Seoul",
    "iso:country":"KR",
    "name:kor_x_preferred":[
        "\uc19f\uace8"
    ],
    "wof:name":"Sotgol",
    "wof:placetype":"locality"
},
  "geometry": {"coordinates":[128.89926,36.93342],"type":"Point"}
}