{
  "type": "Feature",
  "properties": {
    "gn:admin1_code":"6.0",
    "gn:asciiname":"Kwangsan",
    "gn:country_code":"KR",
    "gn:dem":25,
    "gn:feature_class":"P",
    "gn:feature_code":"PPL",
    "gn:name":"Kwangsan",
    "gn:population":0,
    "gn:timezone":"Asia/Seoul",
    "iso:country":"KR",
    "name:kor_x_preferred":[
        "\uad11\uc0b0"
    ],
    "wof:name":"Kwangsan",
    "wof:placetype":"locality"
},
  "geometry": {"coordinates":[128.42221999999998,38.37667],"type":"Point"}
}