{
  "type": "Feature",
  "properties": {
    "gn:admin1_code":"15.0",
    "gn:asciiname":"Wonsan",
    "gn:country_code":"KR",
    "gn:dem":50,
    "gn:feature_class":"P",
    "gn:feature_code":"PPL",
    "gn:name":"Wonsan",
    "gn:population":0,
    "gn:timezone":"Asia/Seoul",
    "iso:country":"KR",
    "name:und_x_variant":[
        "\uc6d0\uc0b0",
        "W\u014fnsan",
        "Wonsan"
    ],
    "wof:name":"Wonsan",
    "wof:placetype":"locality"
},
  "geometry": {"coordinates":[128.46073999999999,35.64922],"type":"Point"}
}