{
  "type": "Feature",
  "properties": {
    "gn:admin1_code":"16.0",
    "gn:asciiname":"Samsal-li",
    "gn:country_code":"KR",
    "gn:dem":20,
    "gn:feature_class":"P",
    "gn:feature_code":"PPL",
    "gn:name":"Samsal-li",
    "gn:population":0,
    "gn:timezone":"Asia/Seoul",
    "iso:country":"KR",
    "name:kor_x_preferred":[
        "\uc0bc\uc0b0\ub9ac"
    ],
    "name:und_x_variant":[
        "Samsan-ni",
        "Samsan",
        "Samsanilgu",
        "Sanzan-ri",
        "Samsal-li"
    ],
    "wof:name":"Samsal-li",
    "wof:placetype":"locality"
},
  "geometry": {"coordinates":[126.95389,34.51944],"type":"Point"}
}