{
  "type": "Feature",
  "properties": {
    "gn:admin1_code":"13.0",
    "gn:asciiname":"Araebakdong",
    "gn:country_code":"KR",
    "gn:dem":136,
    "gn:feature_class":"P",
    "gn:feature_code":"PPL",
    "gn:name":"Araebakdong",
    "gn:population":0,
    "gn:timezone":"Asia/Seoul",
    "iso:country":"KR",
    "name:kor_x_preferred":[
        "\uc544\ub798\ubc15\ub3d9"
    ],
    "name:und_x_variant":[
        "Araeppaek-tong",
        "Araebakdong"
    ],
    "wof:name":"Araebakdong",
    "wof:placetype":"locality"
},
  "geometry": {"coordinates":[127.68356,37.55089],"type":"Point"}
}