{
  "type": "Feature",
  "properties": {
    "gn:admin1_code":"20.0",
    "gn:asciiname":"Saetdol",
    "gn:country_code":"KR",
    "gn:dem":5,
    "gn:feature_class":"P",
    "gn:feature_code":"PPL",
    "gn:name":"Saetdol",
    "gn:population":0,
    "gn:timezone":"Asia/Seoul",
    "iso:country":"KR",
    "name:kor_x_preferred":[
        "\uc0db\ub3cc"
    ],
    "wof:name":"Saetdol",
    "wof:placetype":"locality"
},
  "geometry": {"coordinates":[128.80609999999999,35.09099000000001],"type":"Point"}
}