{
  "type": "Feature",
  "properties": {
    "gn:admin1_code":"16.0",
    "gn:asciiname":"Seochon",
    "gn:country_code":"KR",
    "gn:dem":13,
    "gn:feature_class":"P",
    "gn:feature_code":"PPL",
    "gn:name":"Seochon",
    "gn:population":0,
    "gn:timezone":"Asia/Seoul",
    "iso:country":"KR",
    "name:kor_x_preferred":[
        "\uc11c\ucd0c"
    ],
    "name:und_x_variant":[
        "Sins\u014f-ri",
        "S\u014fch\u2019on",
        "Seochon"
    ],
    "wof:name":"Seochon",
    "wof:placetype":"locality"
},
  "geometry": {"coordinates":[126.30329999999999,34.86776],"type":"Point"}
}