{
  "type": "Feature",
  "properties": {
    "gn:admin1_code":"14.0",
    "gn:asciiname":"Chodongjae",
    "gn:country_code":"KR",
    "gn:dem":41,
    "gn:feature_class":"P",
    "gn:feature_code":"PPL",
    "gn:name":"Ch\u014fdongjae",
    "gn:population":0,
    "gn:timezone":"Asia/Seoul",
    "iso:country":"KR",
    "name:kor_x_preferred":[
        "\uc800\ub3d9\uc7ac"
    ],
    "name:kor_x_variant":[
        "Ch\u014fdongjae"
    ],
    "wof:name":"Chodongjae",
    "wof:placetype":"locality"
},
  "geometry": {"coordinates":[130.9076,37.4931],"type":"Point"}
}