{
  "type": "Feature",
  "properties": {
    "gn:admin1_code":"17.0",
    "gn:asciiname":"Sindae",
    "gn:country_code":"KR",
    "gn:dem":219,
    "gn:feature_class":"P",
    "gn:feature_code":"PPL",
    "gn:name":"Sindae",
    "gn:population":0,
    "gn:timezone":"Asia/Seoul",
    "iso:country":"KR",
    "name:und_x_variant":[
        "Haamsam",
        "Haamsan",
        "Sindae",
        "\uc2e0\ub300"
    ],
    "wof:name":"Sindae",
    "wof:placetype":"locality"
},
  "geometry": {"coordinates":[127.37820000000001,36.0765],"type":"Point"}
}