{
  "type": "Feature",
  "properties": {
    "gn:admin1_code":"14.0",
    "gn:asciiname":"Hwangyong",
    "gn:country_code":"KR",
    "gn:dem":352,
    "gn:feature_class":"P",
    "gn:feature_code":"PPL",
    "gn:name":"Hwangyong",
    "gn:population":0,
    "gn:timezone":"Asia/Seoul",
    "iso:country":"KR",
    "name:und_x_variant":[
        "\ud669\uc6a9",
        "Hwangyong"
    ],
    "wof:name":"Hwangyong",
    "wof:placetype":"locality"
},
  "geometry": {"coordinates":[129.10230000000001,36.6911],"type":"Point"}
}