{
  "type": "Feature",
  "properties": {
    "gn:admin1_code":"19.0",
    "gn:asciiname":"Sansong-dong",
    "gn:country_code":"KR",
    "gn:dem":107,
    "gn:feature_class":"P",
    "gn:feature_code":"PPL",
    "gn:name":"Sans\u014fng-dong",
    "gn:population":0,
    "gn:timezone":"Asia/Seoul",
    "iso:country":"KR",
    "name:und_x_variant":[
        "\uc0b0\uc131\ub3d9",
        "Sans\u014fng-dong"
    ],
    "wof:name":"Sansong-dong",
    "wof:placetype":"locality"
},
  "geometry": {"coordinates":[127.40615,36.26052],"type":"Point"}
}