{
  "type": "Feature",
  "properties": {
    "gn:admin1_code":"14.0",
    "gn:asciiname":"Hyojadong",
    "gn:country_code":"KR",
    "gn:dem":190,
    "gn:feature_class":"P",
    "gn:feature_code":"PPL",
    "gn:name":"Hyojadong",
    "gn:population":0,
    "gn:timezone":"Asia/Seoul",
    "iso:country":"KR",
    "name:kor_x_preferred":[
        "\ud6a8\uc790\ub3d9"
    ],
    "wof:name":"Hyojadong",
    "wof:placetype":"locality"
},
  "geometry": {"coordinates":[128.07363000000001,36.67763],"type":"Point"}
}