{
  "type": "Feature",
  "properties": {
    "gn:admin1_code":"14.0",
    "gn:asciiname":"Nanyeoul",
    "gn:country_code":"KR",
    "gn:dem":19,
    "gn:feature_class":"P",
    "gn:feature_code":"PPL",
    "gn:name":"Nanyeoul",
    "gn:population":0,
    "gn:timezone":"Asia/Seoul",
    "iso:country":"KR",
    "name:und_x_variant":[
        "\ub09c\uc5ec\uc6b8",
        "Nany\u014ful",
        "Nanyeoul"
    ],
    "wof:name":"Nanyeoul",
    "wof:placetype":"locality"
},
  "geometry": {"coordinates":[128.33725000000001,35.66302],"type":"Point"}
}