{
  "type": "Feature",
  "properties": {
    "gn:admin1_code":"18.0",
    "gn:asciiname":"Songgye",
    "gn:country_code":"KR",
    "gn:dem":42,
    "gn:feature_class":"P",
    "gn:feature_code":"PPL",
    "gn:name":"Songgye",
    "gn:population":0,
    "gn:timezone":"Asia/Seoul",
    "iso:country":"KR",
    "name:kor_x_preferred":[
        "\uc1a1\uacc4"
    ],
    "wof:name":"Songgye",
    "wof:placetype":"locality"
},
  "geometry": {"coordinates":[126.67735999999999,35.10827],"type":"Point"}
}