{
  "type": "Feature",
  "properties": {
    "gn:admin1_code":"19.0",
    "gn:asciiname":"Winnokgol",
    "gn:country_code":"KR",
    "gn:dem":90,
    "gn:feature_class":"P",
    "gn:feature_code":"PPL",
    "gn:name":"Winnokgol",
    "gn:population":0,
    "gn:timezone":"Asia/Seoul",
    "iso:country":"KR",
    "name:kor_x_preferred":[
        "\uc717\ub179\uace8"
    ],
    "wof:name":"Winnokgol",
    "wof:placetype":"locality"
},
  "geometry": {"coordinates":[127.36537,36.4815],"type":"Point"}
}