{
  "type": "Feature",
  "properties": {
    "gn:admin1_code":"14.0",
    "gn:asciiname":"Nonttung-mal",
    "gn:country_code":"KR",
    "gn:dem":249,
    "gn:feature_class":"P",
    "gn:feature_code":"PPL",
    "gn:name":"Nonttung-mal",
    "gn:population":0,
    "gn:timezone":"Asia/Seoul",
    "iso:country":"KR",
    "name:und_x_variant":[
        "\ub17c\ub69d\ub9d0",
        "Nonttung-mal"
    ],
    "wof:name":"Nonttung-mal",
    "wof:placetype":"locality"
},
  "geometry": {"coordinates":[129.0239,36.5936],"type":"Point"}
}