{
  "type": "Feature",
  "properties": {
    "gn:admin1_code":"6.0",
    "gn:asciiname":"Neungdong",
    "gn:country_code":"KR",
    "gn:dem":231,
    "gn:feature_class":"P",
    "gn:feature_code":"PPL",
    "gn:name":"Neungdong",
    "gn:population":0,
    "gn:timezone":"Asia/Seoul",
    "iso:country":"KR",
    "name:kor_x_preferred":[
        "\ub2a5\ub3d9"
    ],
    "wof:name":"Neungdong",
    "wof:placetype":"locality"
},
  "geometry": {"coordinates":[127.29178,38.23013],"type":"Point"}
}