{
  "type": "Feature",
  "properties": {
    "gn:admin1_code":"16.0",
    "gn:asciiname":"Sancheok",
    "gn:country_code":"KR",
    "gn:dem":177,
    "gn:feature_class":"P",
    "gn:feature_code":"PPL",
    "gn:name":"Sancheok",
    "gn:population":0,
    "gn:timezone":"Asia/Seoul",
    "iso:country":"KR",
    "name:kor_x_preferred":[
        "\uc0b0\ucc99"
    ],
    "name:kor_x_variant":[
        "Sanch\u2019\u014fk"
    ],
    "wof:name":"Sancheok",
    "wof:placetype":"locality"
},
  "geometry": {"coordinates":[127.25987000000001,34.98539],"type":"Point"}
}