{
  "type": "Feature",
  "properties": {
    "gn:admin1_code":"6.0",
    "gn:asciiname":"Galgol",
    "gn:country_code":"KR",
    "gn:dem":227,
    "gn:feature_class":"P",
    "gn:feature_code":"PPL",
    "gn:name":"Galgol",
    "gn:population":0,
    "gn:timezone":"Asia/Seoul",
    "iso:country":"KR",
    "name:kor_x_preferred":[
        "\uac08\uace8"
    ],
    "wof:name":"Galgol",
    "wof:placetype":"locality"
},
  "geometry": {"coordinates":[127.33409,38.23019],"type":"Point"}
}