{
  "type": "Feature",
  "properties": {
    "gn:admin1_code":"17.0",
    "gn:asciiname":"Hwa-gol",
    "gn:country_code":"KR",
    "gn:dem":86,
    "gn:feature_class":"P",
    "gn:feature_code":"PPL",
    "gn:name":"Hwa-gol",
    "gn:population":0,
    "gn:timezone":"Asia/Seoul",
    "iso:country":"KR",
    "name:und_x_variant":[
        "\ud654\uace8",
        "Hwa-gol"
    ],
    "wof:name":"Hwa-gol",
    "wof:placetype":"locality"
},
  "geometry": {"coordinates":[127.2188,36.2506],"type":"Point"}
}