{
  "type": "Feature",
  "properties": {
    "gn:admin1_code":"14.0",
    "gn:asciiname":"Pop'yong",
    "gn:country_code":"KR",
    "gn:dem":135,
    "gn:feature_class":"P",
    "gn:feature_code":"PPL",
    "gn:name":"Pop\u2019y\u014fng",
    "gn:population":0,
    "gn:timezone":"Asia/Seoul",
    "iso:country":"KR",
    "name:und_x_variant":[
        "\ubcf4\ud3c9",
        "Pop\u2019y\u014fng"
    ],
    "wof:name":"Pop'yong",
    "wof:placetype":"locality"
},
  "geometry": {"coordinates":[128.09209999999999,36.3725],"type":"Point"}
}