{
  "type": "Feature",
  "properties": {
    "gn:admin1_code":"14.0",
    "gn:asciiname":"Sanyang",
    "gn:country_code":"KR",
    "gn:dem":203,
    "gn:feature_class":"P",
    "gn:feature_code":"PPL",
    "gn:name":"Sanyang",
    "gn:population":0,
    "gn:timezone":"Asia/Seoul",
    "iso:country":"KR",
    "name:ceb_x_preferred":[
        "Sanyang"
    ],
    "name:deu_x_preferred":[
        "Sanyang"
    ],
    "name:swe_x_preferred":[
        "Sanyang"
    ],
    "wof:name":"Sanyang",
    "wof:placetype":"locality"
},
  "geometry": {"coordinates":[128.90278000000001,35.73305999999999],"type":"Point"}
}