{
  "type": "Feature",
  "properties": {
    "gn:admin1_code":"0.0",
    "gn:asciiname":"Tongp'yon",
    "gn:country_code":"KR",
    "gn:dem":11,
    "gn:feature_class":"P",
    "gn:feature_code":"PPL",
    "gn:name":"Tongp\u2019y\u014fn",
    "gn:population":0,
    "gn:timezone":"Asia/Seoul",
    "iso:country":"KR",
    "name:kor_x_preferred":[
        "\ub3d9\ud3b8"
    ],
    "name:und_x_variant":[
        "Tongby\u014fng-ri",
        "Tongby\u014fn-ni",
        "Tongp\u2019y\u014fn",
        "Dongpyeon"
    ],
    "wof:name":"Tongp'yon",
    "wof:placetype":"locality"
},
  "geometry": {"coordinates":[126.48333,35.23333],"type":"Point"}
}