{
  "type": "Feature",
  "properties": {
    "iso:country":"KR",
    "qs:name":"\ubb34\uc8fc\uc74d",
    "qs:name_adm0":"\ud55c\uad6d",
    "qs:name_adm1":"\uc804\ub77c\ubd81\ub3c4",
    "qs:photos":32,
    "qs:photos_1k":6,
    "qs:photos_9k":1,
    "qs:photos_9r":2,
    "qs:photos_all":32,
    "qs:photos_sr":2,
    "qs:placetype":"LocalAdmin",
    "qs:pop_sr":"0",
    "wof:name":"\ubb34\uc8fc\uc74d",
    "wof:placetype":"localadmin"
},
  "geometry": {"coordinates":[127.749702,35.859474],"type":"Point"}
}