{
  "type": "Feature",
  "properties": {
    "gn:admin1_code":"16.0",
    "gn:admin2_code":"Chindo-gun",
    "gn:asciiname":"Ganggye",
    "gn:country_code":"KR",
    "gn:dem":5,
    "gn:feature_class":"P",
    "gn:feature_code":"PPL",
    "gn:name":"Ganggye",
    "gn:population":0,
    "gn:timezone":"Asia/Seoul",
    "iso:country":"KR",
    "name:kor_x_preferred":[
        "\uac15\uacc4"
    ],
    "name:und_x_variant":[
        "Kanggye-ri"
    ],
    "wof:name":"Ganggye",
    "wof:placetype":"locality"
},
  "geometry": {"coordinates":[126.26056,34.39333],"type":"Point"}
}