{
  "type": "Feature",
  "properties": {
    "gn:admin1_code":"20.0",
    "gn:asciiname":"Yugye",
    "gn:country_code":"KR",
    "gn:dem":54,
    "gn:feature_class":"P",
    "gn:feature_code":"PPL",
    "gn:name":"Yugye",
    "gn:population":0,
    "gn:timezone":"Asia/Seoul",
    "iso:country":"KR",
    "name:und_x_variant":[
        "\uc720\uacc4",
        "Yugye"
    ],
    "wof:name":"Yugye",
    "wof:placetype":"locality"
},
  "geometry": {"coordinates":[128.24591000000001,35.54045],"type":"Point"}
}