{
  "type": "Feature",
  "properties": {
    "gn:admin1_code":"13.0",
    "gn:asciiname":"Yongmeo-ri",
    "gn:country_code":"KR",
    "gn:dem":140,
    "gn:feature_class":"P",
    "gn:feature_code":"PPL",
    "gn:name":"Yongmeo-ri",
    "gn:population":0,
    "gn:timezone":"Asia/Seoul",
    "iso:country":"KR",
    "name:und_x_variant":[
        "\uc6a9\uba38\ub9ac",
        "Yongmeo-ri",
        "Yongm\u014f-ri"
    ],
    "wof:name":"Yongmeo-ri",
    "wof:placetype":"locality"
},
  "geometry": {"coordinates":[127.01278000000001,37.32167000000001],"type":"Point"}
}