{
  "type": "Feature",
  "properties": {
    "gn:admin1_code":"5.0",
    "gn:asciiname":"Seoraemal",
    "gn:country_code":"KR",
    "gn:dem":114,
    "gn:feature_class":"P",
    "gn:feature_code":"PPL",
    "gn:name":"Seoraemal",
    "gn:population":0,
    "gn:timezone":"Asia/Seoul",
    "iso:country":"KR",
    "name:kor_x_preferred":[
        "\uc11c\ub798\ub9d0"
    ],
    "wof:name":"Seoraemal",
    "wof:placetype":"locality"
},
  "geometry": {"coordinates":[127.81871,36.96515],"type":"Point"}
}