{
  "type": "Feature",
  "properties": {
    "gn:admin1_code":"13.0",
    "gn:asciiname":"Yongbawi",
    "gn:country_code":"KR",
    "gn:dem":117,
    "gn:feature_class":"P",
    "gn:feature_code":"PPL",
    "gn:name":"Yongbawi",
    "gn:population":0,
    "gn:timezone":"Asia/Seoul",
    "iso:country":"KR",
    "name:kor_x_preferred":[
        "\uc6a9\ubc14\uc704"
    ],
    "wof:name":"Yongbawi",
    "wof:placetype":"locality"
},
  "geometry": {"coordinates":[127.43971000000001,37.04888],"type":"Point"}
}