{
  "type": "Feature",
  "properties": {
    "gn:admin1_code":"14.0",
    "gn:asciiname":"Kawon",
    "gn:country_code":"KR",
    "gn:dem":43,
    "gn:feature_class":"P",
    "gn:feature_code":"PPL",
    "gn:name":"Kaw\u014fn",
    "gn:population":0,
    "gn:timezone":"Asia/Seoul",
    "iso:country":"KR",
    "wof:name":"Kawon",
    "wof:placetype":"locality"
},
  "geometry": {"coordinates":[129.38138999999998,37.005],"type":"Point"}
}