{
  "type": "Feature",
  "properties": {
    "gn:admin1_code":"17.0",
    "gn:asciiname":"Sinjon",
    "gn:country_code":"KR",
    "gn:dem":16,
    "gn:feature_class":"P",
    "gn:feature_code":"PPL",
    "gn:name":"Sinj\u014fn",
    "gn:population":0,
    "gn:timezone":"Asia/Seoul",
    "iso:country":"KR",
    "name:und_x_variant":[
        "\uc2e0\uc804",
        "Sinj\u014fn"
    ],
    "wof:name":"Sinjon",
    "wof:placetype":"locality"
},
  "geometry": {"coordinates":[126.9528,36.3634],"type":"Point"}
}