{
  "type": "Feature",
  "properties": {
    "gn:admin1_code":"20.0",
    "gn:asciiname":"Tokch'i",
    "gn:country_code":"KR",
    "gn:dem":19,
    "gn:feature_class":"P",
    "gn:feature_code":"PPL",
    "gn:name":"T\u014fkch\u2019i",
    "gn:population":0,
    "gn:timezone":"Asia/Seoul",
    "iso:country":"KR",
    "name:und_x_variant":[
        "\ub355\uce58",
        "T\u014fkch\u2019i"
    ],
    "wof:name":"Tokch'i",
    "wof:placetype":"locality"
},
  "geometry": {"coordinates":[128.38030000000001,34.90273],"type":"Point"}
}