{
  "type": "Feature",
  "properties": {
    "gn:admin1_code":"11.0",
    "gn:asciiname":"Sokkwani-dong",
    "gn:country_code":"KR",
    "gn:dem":34,
    "gn:feature_class":"P",
    "gn:feature_code":"PPL",
    "gn:name":"S\u014fkkwani-dong",
    "gn:population":0,
    "gn:timezone":"Asia/Seoul",
    "iso:country":"KR",
    "name:und_x_variant":[
        "\uc11d\uad002\ub3d9",
        "S\u014fkkwani-dong"
    ],
    "wof:name":"Sokkwani-dong",
    "wof:placetype":"locality"
},
  "geometry": {"coordinates":[127.05627,37.60539],"type":"Point"}
}