{
  "type": "Feature",
  "properties": {
    "gn:admin1_code":"17.0",
    "gn:asciiname":"Dangmaru",
    "gn:country_code":"KR",
    "gn:dem":75,
    "gn:feature_class":"P",
    "gn:feature_code":"PPL",
    "gn:name":"Dangmaru",
    "gn:population":0,
    "gn:timezone":"Asia/Seoul",
    "iso:country":"KR",
    "name:kor_x_preferred":[
        "\ub2f9\ub9c8\ub8e8"
    ],
    "wof:name":"Dangmaru",
    "wof:placetype":"locality"
},
  "geometry": {"coordinates":[127.15306,36.41004],"type":"Point"}
}