{
  "type": "Feature",
  "properties": {
    "gn:admin1_code":"16.0",
    "gn:asciiname":"Jaetdeung",
    "gn:country_code":"KR",
    "gn:dem":57,
    "gn:feature_class":"P",
    "gn:feature_code":"PPL",
    "gn:name":"Jaetdeung",
    "gn:population":0,
    "gn:timezone":"Asia/Seoul",
    "iso:country":"KR",
    "name:kor_x_preferred":[
        "\uc7bf\ub4ec"
    ],
    "name:kor_x_variant":[
        "\uc7bf\ub4f1"
    ],
    "name:und_x_variant":[
        "Chaett\u016dm"
    ],
    "wof:name":"Jaetdeung",
    "wof:placetype":"locality"
},
  "geometry": {"coordinates":[127.33772999999999,34.82826],"type":"Point"}
}