{
  "type": "Feature",
  "properties": {
    "gn:admin1_code":"17.0",
    "gn:asciiname":"Kyo-ch'on",
    "gn:country_code":"KR",
    "gn:dem":35,
    "gn:feature_class":"P",
    "gn:feature_code":"PPL",
    "gn:name":"Kyo-ch\u2019on",
    "gn:population":0,
    "gn:timezone":"Asia/Seoul",
    "iso:country":"KR",
    "name:und_x_variant":[
        "\uad50\ucd0c",
        "Kyo-ch\u2019on"
    ],
    "wof:name":"Kyo-ch'on",
    "wof:placetype":"locality"
},
  "geometry": {"coordinates":[126.5432,36.5304],"type":"Point"}
}