{
  "type": "Feature",
  "properties": {
    "gn:admin1_code":"16.0",
    "gn:asciiname":"Wolsandong",
    "gn:country_code":"KR",
    "gn:dem":43,
    "gn:feature_class":"P",
    "gn:feature_code":"PPL",
    "gn:name":"Wolsandong",
    "gn:population":0,
    "gn:timezone":"Asia/Seoul",
    "iso:country":"KR",
    "name:kor_x_preferred":[
        "\uc6d4\uc0b0\ub3d9"
    ],
    "wof:name":"Wolsandong",
    "wof:placetype":"locality"
},
  "geometry": {"coordinates":[126.77128,35.28814000000001],"type":"Point"}
}