{
  "type": "Feature",
  "properties": {
    "gn:admin1_code":"17.0",
    "gn:asciiname":"Changsu",
    "gn:country_code":"KR",
    "gn:dem":27,
    "gn:feature_class":"P",
    "gn:feature_code":"PPL",
    "gn:name":"Changsu",
    "gn:population":0,
    "gn:timezone":"Asia/Seoul",
    "iso:country":"KR",
    "name:und_x_variant":[
        "\uc7a5\uc218",
        "Changsu"
    ],
    "wof:name":"Changsu",
    "wof:placetype":"locality"
},
  "geometry": {"coordinates":[126.9058,36.8682],"type":"Point"}
}