{
  "type": "Feature",
  "properties": {
    "gn:admin1_code":"13.0",
    "gn:asciiname":"Pangch'on-mal",
    "gn:country_code":"KR",
    "gn:dem":183,
    "gn:feature_class":"P",
    "gn:feature_code":"PPL",
    "gn:name":"Pangch\u2019on-mal",
    "gn:population":0,
    "gn:timezone":"Asia/Seoul",
    "iso:country":"KR",
    "name:kor_x_preferred":[
        "\ubc29\ucd0c\ub9d0"
    ],
    "name:kor_x_variant":[
        "Pangch\u2019on-mal"
    ],
    "wof:name":"Pangch'on-mal",
    "wof:placetype":"locality"
},
  "geometry": {"coordinates":[127.64,37.5817],"type":"Point"}
}