{
  "type": "Feature",
  "properties": {
    "gn:admin1_code":"21.0",
    "gn:asciiname":"Myeongdong",
    "gn:country_code":"KR",
    "gn:dem":128,
    "gn:feature_class":"P",
    "gn:feature_code":"PPL",
    "gn:name":"Myeongdong",
    "gn:population":0,
    "gn:timezone":"Asia/Seoul",
    "iso:country":"KR",
    "name:kor_x_preferred":[
        "\uba85\ub3d9"
    ],
    "wof:name":"Myeongdong",
    "wof:placetype":"locality"
},
  "geometry": {"coordinates":[129.10502,35.59151],"type":"Point"}
}