{
  "type": "Feature",
  "properties": {
    "gn:admin1_code":"13.0",
    "gn:asciiname":"Taejol-li",
    "gn:cc2":"KR",
    "gn:country_code":"KR",
    "gn:dem":62,
    "gn:feature_class":"P",
    "gn:feature_code":"PPL",
    "gn:name":"Taej\u014fl-li",
    "gn:population":0,
    "gn:timezone":"Asia/Seoul",
    "iso:country":"KR",
    "name:und_x_variant":[
        "Taej\u014fn-ni",
        "Taej\u014fl-li"
    ],
    "wof:name":"Taejol-li",
    "wof:placetype":"locality"
},
  "geometry": {"coordinates":[127.08333,38.01056],"type":"Point"}
}