{
  "type": "Feature",
  "properties": {
    "gn:admin1_code":"13.0",
    "gn:admin2_code":"Ich'\u014fn-si",
    "gn:asciiname":"Yusal-li",
    "gn:country_code":"KR",
    "gn:dem":72,
    "gn:feature_class":"P",
    "gn:feature_code":"PPLL",
    "gn:name":"Yusal-li",
    "gn:population":0,
    "gn:timezone":"Asia/Seoul",
    "iso:country":"KR",
    "name:kor_x_preferred":[
        "\uc720\uc0b0\ub9ac"
    ],
    "name:und_x_variant":[
        "Yusan-ni",
        "Yusan-ri"
    ],
    "wof:name":"Yusal-li",
    "wof:placetype":"locality"
},
  "geometry": {"coordinates":[127.43306,37.23722],"type":"Point"}
}