{
  "type": "Feature",
  "properties": {
    "gn:admin1_code":"14.0",
    "gn:asciiname":"Tapso",
    "gn:country_code":"KR",
    "gn:dem":68,
    "gn:feature_class":"P",
    "gn:feature_code":"PPL",
    "gn:name":"Tapso",
    "gn:population":0,
    "gn:timezone":"Asia/Seoul",
    "iso:country":"KR",
    "name:kor_x_preferred":[
        "\ud0d1\uc18c"
    ],
    "wof:name":"Tapso",
    "wof:placetype":"locality"
},
  "geometry": {"coordinates":[128.78807,35.90000999999999],"type":"Point"}
}