{
  "type": "Feature",
  "properties": {
    "gn:admin1_code":"14.0",
    "gn:asciiname":"Kop'yong",
    "gn:country_code":"KR",
    "gn:dem":83,
    "gn:feature_class":"P",
    "gn:feature_code":"PPL",
    "gn:name":"Kop\u2019y\u014fng",
    "gn:population":0,
    "gn:timezone":"Asia/Seoul",
    "iso:country":"KR",
    "name:und_x_variant":[
        "\uace0\ud3c9",
        "Kop\u2019y\u014fng"
    ],
    "wof:name":"Kop'yong",
    "wof:placetype":"locality"
},
  "geometry": {"coordinates":[128.71831,35.66942],"type":"Point"}
}