{
  "type": "Feature",
  "properties": {
    "gn:admin1_code":"14.0",
    "gn:asciiname":"Heumgol",
    "gn:country_code":"KR",
    "gn:dem":150,
    "gn:feature_class":"P",
    "gn:feature_code":"PPL",
    "gn:name":"Heumgol",
    "gn:population":0,
    "gn:timezone":"Asia/Seoul",
    "iso:country":"KR",
    "name:kor_x_preferred":[
        "\ud760\uace8"
    ],
    "wof:name":"Heumgol",
    "wof:placetype":"locality"
},
  "geometry": {"coordinates":[128.1293,36.7075],"type":"Point"}
}