{
  "type": "Feature",
  "properties": {
    "gn:admin1_code":"14.0",
    "gn:asciiname":"Apgamagol",
    "gn:country_code":"KR",
    "gn:dem":340,
    "gn:feature_class":"P",
    "gn:feature_code":"PPL",
    "gn:name":"Apgamagol",
    "gn:population":0,
    "gn:timezone":"Asia/Seoul",
    "iso:country":"KR",
    "name:kor_x_preferred":[
        "\uc55e\uac00\ub9c8\uace8"
    ],
    "wof:name":"Apgamagol",
    "wof:placetype":"locality"
},
  "geometry": {"coordinates":[128.54334,36.93456],"type":"Point"}
}