{
  "type": "Feature",
  "properties": {
    "gn:admin1_code":"6.0",
    "gn:asciiname":"Son'gama-gol",
    "gn:country_code":"KR",
    "gn:dem":474,
    "gn:feature_class":"P",
    "gn:feature_code":"PPL",
    "gn:name":"S\u014fn\u2019gama-gol",
    "gn:population":0,
    "gn:timezone":"Asia/Seoul",
    "iso:country":"KR",
    "name:kor_x_preferred":[
        "\uc120\uac00\ub9c8\uace8"
    ],
    "name:kor_x_variant":[
        "S\u014fn\u2019gama-gol"
    ],
    "wof:name":"Son'gama-gol",
    "wof:placetype":"locality"
},
  "geometry": {"coordinates":[128.4736,37.2856],"type":"Point"}
}