{
  "type": "Feature",
  "properties": {
    "gn:admin1_code":"21.0",
    "gn:asciiname":"Hwajeong",
    "gn:country_code":"KR",
    "gn:dem":49,
    "gn:feature_class":"P",
    "gn:feature_code":"PPL",
    "gn:name":"Hwajeong",
    "gn:population":0,
    "gn:timezone":"Asia/Seoul",
    "iso:country":"KR",
    "name:kor_x_preferred":[
        "\ud654\uc815"
    ],
    "name:und_x_variant":[
        "Hwaj\u014fng"
    ],
    "wof:name":"Hwajeong",
    "wof:placetype":"locality"
},
  "geometry": {"coordinates":[129.34273000000002,35.65745],"type":"Point"}
}