{
  "type": "Feature",
  "properties": {
    "gn:admin1_code":"17.0",
    "gn:asciiname":"Sae-mal",
    "gn:country_code":"KR",
    "gn:dem":27,
    "gn:feature_class":"P",
    "gn:feature_code":"PPL",
    "gn:name":"Sae-mal",
    "gn:population":0,
    "gn:timezone":"Asia/Seoul",
    "iso:country":"KR",
    "name:und_x_variant":[
        "\uc0c8\ub9d0",
        "Sae-mal"
    ],
    "wof:name":"Sae-mal",
    "wof:placetype":"locality"
},
  "geometry": {"coordinates":[126.63549999999999,36.537],"type":"Point"}
}