{
  "type": "Feature",
  "properties": {
    "gn:admin1_code":"5.0",
    "gn:asciiname":"Seosil",
    "gn:country_code":"KR",
    "gn:dem":267,
    "gn:feature_class":"P",
    "gn:feature_code":"PPL",
    "gn:name":"Seosil",
    "gn:population":0,
    "gn:timezone":"Asia/Seoul",
    "iso:country":"KR",
    "name:kor_x_preferred":[
        "\uc11c\uc2e4"
    ],
    "wof:name":"Seosil",
    "wof:placetype":"locality"
},
  "geometry": {"coordinates":[127.63777,36.64933],"type":"Point"}
}