{
  "type": "Feature",
  "properties": {
    "gn:admin1_code":"13.0",
    "gn:asciiname":"Kambuk-tong",
    "gn:country_code":"KR",
    "gn:dem":73,
    "gn:feature_class":"P",
    "gn:feature_code":"PPL",
    "gn:name":"Kambuk-tong",
    "gn:population":0,
    "gn:timezone":"Asia/Seoul",
    "iso:country":"KR",
    "name:eng_x_preferred":[
        "Kambuk"
    ],
    "name:eng_x_variant":[
        "Kambuk-tong"
    ],
    "name:und_x_variant":[
        "\uac10\ubd81\ub3d9",
        "Gambuk-dong",
        "Kambuk-tong"
    ],
    "wof:name":"Kambuk",
    "wof:placetype":"locality"
},
  "geometry": {"coordinates":[127.16028,37.50139],"type":"Point"}
}