{
  "type": "Feature",
  "properties": {
    "gn:admin1_code":"13.0",
    "gn:asciiname":"Wolliteo",
    "gn:country_code":"KR",
    "gn:dem":163,
    "gn:feature_class":"P",
    "gn:feature_code":"PPL",
    "gn:name":"Wolliteo",
    "gn:population":0,
    "gn:timezone":"Asia/Seoul",
    "iso:country":"KR",
    "name:und_x_variant":[
        "\uc6d4\ub9ac\ud130",
        "Wolliteo",
        "W\u014fllit\u2019\u014f"
    ],
    "wof:name":"Wolliteo",
    "wof:placetype":"locality"
},
  "geometry": {"coordinates":[127.73472,37.45667],"type":"Point"}
}