{
  "type": "Feature",
  "properties": {
    "gn:admin1_code":"14.0",
    "gn:asciiname":"Bamnamugol",
    "gn:country_code":"KR",
    "gn:dem":234,
    "gn:feature_class":"P",
    "gn:feature_code":"PPL",
    "gn:name":"Bamnamugol",
    "gn:population":0,
    "gn:timezone":"Asia/Seoul",
    "iso:country":"KR",
    "name:kor_x_preferred":[
        "\ubc24\ub098\ubb34\uace8"
    ],
    "wof:name":"Bamnamugol",
    "wof:placetype":"locality"
},
  "geometry": {"coordinates":[128.75998000000001,36.61711],"type":"Point"}
}