{
  "type": "Feature",
  "properties": {
    "gn:admin1_code":"13.0",
    "gn:asciiname":"Wangdae-ri",
    "gn:country_code":"KR",
    "gn:dem":55,
    "gn:feature_class":"P",
    "gn:feature_code":"PPLL",
    "gn:name":"Wangdae-ri",
    "gn:population":0,
    "gn:timezone":"Asia/Seoul",
    "iso:country":"KR",
    "name:und_x_variant":[
        "\uc655\ub300\ub9ac",
        "Wangdae-ri"
    ],
    "wof:name":"Wangdae-ri",
    "wof:placetype":"locality"
},
  "geometry": {"coordinates":[127.60306,37.32028],"type":"Point"}
}