{
  "type": "Feature",
  "properties": {
    "gn:admin1_code":"17.0",
    "gn:asciiname":"Kyo-dong",
    "gn:country_code":"KR",
    "gn:dem":33,
    "gn:feature_class":"P",
    "gn:feature_code":"PPL",
    "gn:name":"Kyo-dong",
    "gn:population":0,
    "gn:timezone":"Asia/Seoul",
    "iso:country":"KR",
    "name:und_x_variant":[
        "\uad50\ub3d9",
        "Kyo-dong"
    ],
    "wof:name":"Kyo-dong",
    "wof:placetype":"locality"
},
  "geometry": {"coordinates":[127.11206,36.45846],"type":"Point"}
}