{
  "type": "Feature",
  "properties": {
    "gn:admin1_code":"13.0",
    "gn:asciiname":"Withongjeok",
    "gn:country_code":"KR",
    "gn:dem":202,
    "gn:feature_class":"P",
    "gn:feature_code":"PPL",
    "gn:name":"Withongjeok",
    "gn:population":0,
    "gn:timezone":"Asia/Seoul",
    "iso:country":"KR",
    "name:und_x_variant":[
        "\uc717\ud64d\uc801",
        "Withongj\u014fk",
        "Withongjeok"
    ],
    "wof:name":"Withongjeok",
    "wof:placetype":"locality"
},
  "geometry": {"coordinates":[127.57722,37.94895],"type":"Point"}
}