{
  "type": "Feature",
  "properties": {
    "gn:admin1_code":"12.0",
    "gn:asciiname":"Yokkol",
    "gn:country_code":"KR",
    "gn:dem":33,
    "gn:feature_class":"P",
    "gn:feature_code":"PPL",
    "gn:name":"Y\u014fkkol",
    "gn:population":0,
    "gn:timezone":"Asia/Seoul",
    "iso:country":"KR",
    "name:kor_x_preferred":[
        "\uc5ed\uace8"
    ],
    "name:kor_x_variant":[
        "Y\u014fkkol"
    ],
    "wof:name":"Yokkol",
    "wof:placetype":"locality"
},
  "geometry": {"coordinates":[126.72221999999999,37.56889],"type":"Point"}
}