{
  "type": "Feature",
  "properties": {
    "gn:admin1_code":"17.0",
    "gn:asciiname":"Ch'wip'yong-ni",
    "gn:country_code":"KR",
    "gn:dem":21,
    "gn:feature_class":"P",
    "gn:feature_code":"PPL",
    "gn:name":"Ch\u2019wip\u2019y\u014fng-ni",
    "gn:population":0,
    "gn:timezone":"Asia/Seoul",
    "iso:country":"KR",
    "name:und_x_variant":[
        "Chup\u2019y\u014fng-ni",
        "Ch\u2019wip\u2019y\u014fng-ri",
        "Ch\u2019wip\u2019y\u014fng-ni",
        "\ucde8\ud3c9\ub9ac"
    ],
    "wof:name":"Ch'wip'yong-ni",
    "wof:placetype":"locality"
},
  "geometry": {"coordinates":[126.39167,36.71444],"type":"Point"}
}