{
  "type": "Feature",
  "properties": {
    "gn:admin1_code":"5.0",
    "gn:asciiname":"Keunsaemal",
    "gn:country_code":"KR",
    "gn:dem":50,
    "gn:feature_class":"P",
    "gn:feature_code":"PPL",
    "gn:name":"Keunsaemal",
    "gn:population":0,
    "gn:timezone":"Asia/Seoul",
    "iso:country":"KR",
    "name:kor_x_preferred":[
        "\ud070\uc0c8\ub9d0"
    ],
    "wof:name":"Keunsaemal",
    "wof:placetype":"locality"
},
  "geometry": {"coordinates":[127.54582000000001,36.72846],"type":"Point"}
}