{
  "type": "Feature",
  "properties": {
    "iso:country":"KR",
    "name:ceb_x_preferred":[
        "Dong-gu"
    ],
    "name:ell_x_preferred":[
        "\u0395\u03c0\u03b1\u03c1\u03c7\u03af\u03b1 \u039d\u03c4\u03bf\u03bd\u03b3\u03ba"
    ],
    "name:ind_x_preferred":[
        "Distrik Dong"
    ],
    "name:jpn_x_preferred":[
        "\u6771\u533a"
    ],
    "name:kor_x_preferred":[
        "\ub3d9\uad6c"
    ],
    "name:spa_x_preferred":[
        "Dong"
    ],
    "name:urd_x_preferred":[
        "\u062f\u0648\u0646\u06af \u0636\u0644\u0639"
    ],
    "name:vie_x_preferred":[
        "Qu\u1eadn \u0110\u00f4ng"
    ],
    "name:zho_x_preferred":[
        "\u6771\u5340"
    ],
    "qs:name":"\uc77c\uc0b0\ub3d9",
    "qs:name_adm0":"\ud55c\uad6d",
    "qs:name_adm1":"\uac15\uc6d0\ub3c4",
    "qs:photos":19,
    "qs:photos_1k":4,
    "qs:photos_9k":1,
    "qs:photos_9r":1,
    "qs:photos_all":19,
    "qs:photos_sr":1,
    "qs:placetype":"LocalAdmin",
    "qs:pop_sr":"0",
    "wd:wordcount":90,
    "wof:name":"\uc77c\uc0b0\ub3d9",
    "wof:placetype":"localadmin"
},
  "geometry": {"coordinates":[127.821979,37.375613],"type":"Point"}
}