{
  "type": "Feature",
  "properties": {
    "gn:admin1_code":"16.0",
    "gn:asciiname":"Hoeryong",
    "gn:country_code":"KR",
    "gn:dem":53,
    "gn:feature_class":"P",
    "gn:feature_code":"PPL",
    "gn:name":"Hoeryong",
    "gn:population":0,
    "gn:timezone":"Asia/Seoul",
    "iso:country":"KR",
    "name:kor_x_preferred":[
        "\ud68c\ub8e1"
    ],
    "wof:name":"Hoeryong",
    "wof:placetype":"locality"
},
  "geometry": {"coordinates":[126.68971999999999,34.59167],"type":"Point"}
}