{
  "type": "Feature",
  "properties": {
    "gn:admin1_code":"6.0",
    "gn:asciiname":"Sangwolsal-li",
    "gn:country_code":"KR",
    "gn:dem":197,
    "gn:feature_class":"P",
    "gn:feature_code":"PPL",
    "gn:name":"Sangw\u014flsal-li",
    "gn:population":0,
    "gn:timezone":"Asia/Seoul",
    "iso:country":"KR",
    "name:und_x_variant":[
        "\uc0c1\uc6d4\uc0b0\ub9ac",
        "Sangw\u014flsal-li"
    ],
    "wof:name":"Sangwolsal-li",
    "wof:placetype":"locality"
},
  "geometry": {"coordinates":[129.15719999999999,37.3363],"type":"Point"}
}