{
  "type": "Feature",
  "properties": {
    "gn:admin1_code":"14.0",
    "gn:asciiname":"Gomusil",
    "gn:country_code":"KR",
    "gn:dem":115,
    "gn:feature_class":"P",
    "gn:feature_code":"PPL",
    "gn:name":"G\u014fmusil",
    "gn:population":0,
    "gn:timezone":"Asia/Seoul",
    "iso:country":"KR",
    "name:und_x_variant":[
        "\uac70\ubb34\uc2e4",
        "G\u014fmusil"
    ],
    "wof:name":"Gomusil",
    "wof:placetype":"locality"
},
  "geometry": {"coordinates":[128.1816,36.3845],"type":"Point"}
}