{
  "type": "Feature",
  "properties": {
    "gn:admin1_code":"17.0",
    "gn:asciiname":"Kajaeul",
    "gn:country_code":"KR",
    "gn:dem":30,
    "gn:feature_class":"P",
    "gn:feature_code":"PPL",
    "gn:name":"Kajaeul",
    "gn:population":0,
    "gn:timezone":"Asia/Seoul",
    "iso:country":"KR",
    "name:und_x_variant":[
        "\uac00\uc7ac\uc6b8",
        "Kajaeul"
    ],
    "wof:name":"Kajaeul",
    "wof:placetype":"locality"
},
  "geometry": {"coordinates":[126.727,36.6718],"type":"Point"}
}