{
  "type": "Feature",
  "properties": {
    "gn:admin1_code":"20.0",
    "gn:asciiname":"Yongdongp'o",
    "gn:country_code":"KR",
    "gn:dem":-4,
    "gn:feature_class":"P",
    "gn:feature_code":"PPL",
    "gn:name":"Y\u014fngdongp\u2019o",
    "gn:population":0,
    "gn:timezone":"Asia/Seoul",
    "iso:country":"KR",
    "wof:name":"Yongdongp'o",
    "wof:placetype":"locality"
},
  "geometry": {"coordinates":[128.47528,34.85667],"type":"Point"}
}