{
  "type": "Feature",
  "properties": {
    "gn:admin1_code":"13.0",
    "gn:asciiname":"Yangdonggol",
    "gn:country_code":"KR",
    "gn:dem":197,
    "gn:feature_class":"P",
    "gn:feature_code":"PPL",
    "gn:name":"Yangdonggol",
    "gn:population":0,
    "gn:timezone":"Asia/Seoul",
    "iso:country":"KR",
    "name:kor_x_preferred":[
        "\uc591\ub3d9\uace8"
    ],
    "wof:name":"Yangdonggol",
    "wof:placetype":"locality"
},
  "geometry": {"coordinates":[127.35011000000002,37.85132],"type":"Point"}
}