{
  "type": "Feature",
  "properties": {
    "gn:admin1_code":"16.0",
    "gn:asciiname":"Pyeongjangdong",
    "gn:country_code":"KR",
    "gn:dem":117,
    "gn:feature_class":"P",
    "gn:feature_code":"PPL",
    "gn:name":"Pyeongjangdong",
    "gn:population":0,
    "gn:timezone":"Asia/Seoul",
    "iso:country":"KR",
    "name:kor_x_preferred":[
        "\ud3c9\uc7a5\ub3d9"
    ],
    "name:und_x_variant":[
        "P\u2019y\u014fngjang-ni",
        "P\u2019yongjang-dong",
        "Pyeongjangdong"
    ],
    "wof:name":"Pyeongjangdong",
    "wof:placetype":"locality"
},
  "geometry": {"coordinates":[126.8768,35.29153],"type":"Point"}
}