{
  "type": "Feature",
  "properties": {
    "gn:admin1_code":"13.0",
    "gn:asciiname":"Chuktul-li",
    "gn:cc2":"KR",
    "gn:country_code":"KR",
    "gn:dem":117,
    "gn:feature_class":"P",
    "gn:feature_code":"PPL",
    "gn:name":"Chuktul-li",
    "gn:population":0,
    "gn:timezone":"Asia/Seoul",
    "iso:country":"KR",
    "name:und_x_variant":[
        "Chuktun-ni",
        "Chugam",
        "Chuktul-li"
    ],
    "wof:name":"Chuktul-li",
    "wof:placetype":"locality"
},
  "geometry": {"coordinates":[127.55194,37.88167],"type":"Point"}
}