{
  "type": "Feature",
  "properties": {
    "gn:admin1_code":"16.0",
    "gn:asciiname":"Taegang-ni",
    "gn:country_code":"KR",
    "gn:dem":159,
    "gn:feature_class":"P",
    "gn:feature_code":"PPLL",
    "gn:name":"Taegang-ni",
    "gn:population":0,
    "gn:timezone":"Asia/Seoul",
    "iso:country":"KR",
    "name:kor_x_preferred":[
        "\ub300\uac15\ub9ac"
    ],
    "name:und_x_variant":[
        "Sadong-ni",
        "Taegang-ni"
    ],
    "wof:name":"Taegang-ni",
    "wof:placetype":"locality"
},
  "geometry": {"coordinates":[127.31453999999999,34.79127],"type":"Point"}
}