{
  "type": "Feature",
  "properties": {
    "gn:admin1_code":"13.0",
    "gn:asciiname":"Jikdong",
    "gn:country_code":"KR",
    "gn:dem":116,
    "gn:feature_class":"P",
    "gn:feature_code":"PPL",
    "gn:name":"Jikdong",
    "gn:population":0,
    "gn:timezone":"Asia/Seoul",
    "iso:country":"KR",
    "name:kor_x_preferred":[
        "\uc9c1\ub3d9"
    ],
    "name:und_x_variant":[
        "\ud3c9\ucd0c",
        "P\u2019y\u014fng-ch\u2019on",
        "Jikdong"
    ],
    "wof:name":"Jikdong",
    "wof:placetype":"locality"
},
  "geometry": {"coordinates":[127.16686,37.77003],"type":"Point"}
}