{
  "type": "Feature",
  "properties": {
    "gn:admin1_code":"17.0",
    "gn:asciiname":"Galmaji",
    "gn:country_code":"KR",
    "gn:dem":55,
    "gn:feature_class":"P",
    "gn:feature_code":"PPL",
    "gn:name":"Galmaji",
    "gn:population":0,
    "gn:timezone":"Asia/Seoul",
    "iso:country":"KR",
    "name:kor_x_preferred":[
        "\uac08\ub9c8\uc9c0"
    ],
    "wof:name":"Galmaji",
    "wof:placetype":"locality"
},
  "geometry": {"coordinates":[127.01047,36.74664],"type":"Point"}
}