{
  "type": "Feature",
  "properties": {
    "gn:admin1_code":"14.0",
    "gn:asciiname":"Dongjidong",
    "gn:country_code":"KR",
    "gn:dem":202,
    "gn:feature_class":"P",
    "gn:feature_code":"PPL",
    "gn:name":"Dongjidong",
    "gn:population":0,
    "gn:timezone":"Asia/Seoul",
    "iso:country":"KR",
    "name:kor_x_preferred":[
        "\ub3d9\uc9c0\ub3d9"
    ],
    "wof:name":"Dongjidong",
    "wof:placetype":"locality"
},
  "geometry": {"coordinates":[128.71993999999998,36.06723],"type":"Point"}
}