{
  "type": "Feature",
  "properties": {
    "gn:admin1_code":"16.0",
    "gn:asciiname":"Tungam",
    "gn:country_code":"KR",
    "gn:dem":46,
    "gn:feature_class":"P",
    "gn:feature_code":"PPL",
    "gn:name":"T\u016dngam",
    "gn:population":0,
    "gn:timezone":"Asia/Seoul",
    "iso:country":"KR",
    "name:kor_x_preferred":[
        "\ub4f1\uc554"
    ],
    "name:kor_x_variant":[
        "T\u016dngam"
    ],
    "name:und_x_variant":[
        "T\u016dngam-ni"
    ],
    "wof:name":"Tungam",
    "wof:placetype":"locality"
},
  "geometry": {"coordinates":[127.2726,34.59519],"type":"Point"}
}