{
  "type": "Feature",
  "properties": {
    "gn:admin1_code":"5.0",
    "gn:asciiname":"Song-ni",
    "gn:country_code":"KR",
    "gn:dem":200,
    "gn:feature_class":"P",
    "gn:feature_code":"PPL",
    "gn:name":"S\u014fng-ni",
    "gn:population":0,
    "gn:timezone":"Asia/Seoul",
    "iso:country":"KR",
    "wof:name":"Song-ni",
    "wof:placetype":"locality"
},
  "geometry": {"coordinates":[127.40000000000001,36.78333],"type":"Point"}
}