{
  "type": "Feature",
  "properties": {
    "gn:admin1_code":"5.0",
    "gn:asciiname":"Soran",
    "gn:country_code":"KR",
    "gn:dem":301,
    "gn:feature_class":"P",
    "gn:feature_code":"PPL",
    "gn:name":"Soran",
    "gn:population":0,
    "gn:timezone":"Asia/Seoul",
    "iso:country":"KR",
    "name:bul_x_preferred":[
        "\u0421\u043e\u0440\u0430\u043d"
    ],
    "name:ceb_x_preferred":[
        "Soran"
    ],
    "name:kor_x_preferred":[
        "\uc18c\ub780"
    ],
    "name:kur_x_preferred":[
        "Soran"
    ],
    "name:swe_x_preferred":[
        "Soran"
    ],
    "wof:name":"Soran",
    "wof:placetype":"locality"
},
  "geometry": {"coordinates":[127.63261,36.69561],"type":"Point"}
}