{
  "type": "Feature",
  "properties": {
    "gn:admin1_code":"20.0",
    "gn:asciiname":"Paengnyon-am",
    "gn:country_code":"KR",
    "gn:dem":802,
    "gn:feature_class":"P",
    "gn:feature_code":"PPL",
    "gn:name":"Paengny\u014fn-am",
    "gn:population":0,
    "gn:timezone":"Asia/Seoul",
    "iso:country":"KR",
    "name:und_x_variant":[
        "\ubc31\ub828\uc554",
        "Paengny\u014fn-am"
    ],
    "wof:name":"Paengnyon-am",
    "wof:placetype":"locality"
},
  "geometry": {"coordinates":[128.10641000000001,35.79812000000001],"type":"Point"}
}