{
  "type": "Feature",
  "properties": {
    "gn:admin1_code":"17.0",
    "gn:asciiname":"Nobyon",
    "gn:country_code":"KR",
    "gn:dem":7,
    "gn:feature_class":"P",
    "gn:feature_code":"PPL",
    "gn:name":"Noby\u014fn",
    "gn:population":0,
    "gn:timezone":"Asia/Seoul",
    "iso:country":"KR",
    "name:und_x_variant":[
        "\ub178\ubcc0",
        "Noby\u014fn"
    ],
    "wof:name":"Nobyon",
    "wof:placetype":"locality"
},
  "geometry": {"coordinates":[126.80070000000001,36.8152],"type":"Point"}
}