{
  "type": "Feature",
  "properties": {
    "gn:admin1_code":"13.0",
    "gn:asciiname":"Su-dong",
    "gn:country_code":"KR",
    "gn:dem":71,
    "gn:feature_class":"P",
    "gn:feature_code":"PPLA3",
    "gn:name":"Su-dong",
    "gn:population":0,
    "gn:timezone":"Asia/Seoul",
    "iso:country":"KR",
    "name:kor_x_preferred":[
        "\uc218\ub3d9"
    ],
    "wof:name":"Su-dong",
    "wof:placetype":"locality"
},
  "geometry": {"coordinates":[127.3258,37.70353],"type":"Point"}
}