{
  "type": "Feature",
  "properties": {
    "gn:admin1_code":"20.0",
    "gn:asciiname":"Jutsueki",
    "gn:country_code":"KR",
    "gn:dem":9,
    "gn:feature_class":"P",
    "gn:feature_code":"PPL",
    "gn:name":"Jutsueki",
    "gn:population":0,
    "gn:timezone":"Asia/Seoul",
    "iso:country":"KR",
    "name:und_x_variant":[
        "Suy\u014fng-ni",
        "Kuy\u014fng-ni",
        "Sury\u014fni",
        "Ky\u016beki-ri",
        "Sulch\u014fng-ni",
        "\uc220\uc5ed\ub9ac",
        "Sury\u014fk",
        "Sury\u014fng-ni"
    ],
    "wof:name":"Jutsueki",
    "wof:placetype":"locality"
},
  "geometry": {"coordinates":[128.48196999999999,34.84604],"type":"Point"}
}