{
  "type": "Feature",
  "properties": {
    "gn:admin1_code":"19.0",
    "gn:asciiname":"Baeal",
    "gn:country_code":"KR",
    "gn:dem":89,
    "gn:feature_class":"P",
    "gn:feature_code":"PPL",
    "gn:name":"Baeal",
    "gn:population":0,
    "gn:timezone":"Asia/Seoul",
    "iso:country":"KR",
    "name:kor_x_preferred":[
        "\ubc30\uc54c"
    ],
    "name:und_x_variant":[
        "\uc640\uc815\uace8",
        "Waj\u014fng-gol",
        "Baeal"
    ],
    "wof:name":"Baeal",
    "wof:placetype":"locality"
},
  "geometry": {"coordinates":[127.53019999999999,36.39791],"type":"Point"}
}