{
  "type": "Feature",
  "properties": {
    "gn:admin1_code":"3.0",
    "gn:asciiname":"Sinhung-ch'on",
    "gn:country_code":"KR",
    "gn:dem":270,
    "gn:feature_class":"P",
    "gn:feature_code":"PPL",
    "gn:name":"Sinh\u016dng-ch\u2019on",
    "gn:population":0,
    "gn:timezone":"Asia/Seoul",
    "iso:country":"KR",
    "name:und_x_variant":[
        "\uc2e0\ud765\ucd0c",
        "Sinh\u016dng-ch\u2019on"
    ],
    "wof:name":"Sinhung-ch'on",
    "wof:placetype":"locality"
},
  "geometry": {"coordinates":[127.32277999999999,35.64445],"type":"Point"}
}