{
  "type": "Feature",
  "properties": {
    "gn:admin1_code":"14.0",
    "gn:asciiname":"Chukchang-ni",
    "gn:country_code":"KR",
    "gn:dem":65,
    "gn:feature_class":"P",
    "gn:feature_code":"PPL",
    "gn:name":"Chukchang-ni",
    "gn:population":0,
    "gn:timezone":"Asia/Seoul",
    "iso:country":"KR",
    "name:eng_x_preferred":[
        "Chukchang"
    ],
    "name:eng_x_variant":[
        "Chukchang-ni"
    ],
    "name:und_x_variant":[
        "\uc8fd\uc7a5\ub9ac",
        "Chukchang-ni"
    ],
    "wof:name":"Chukchang",
    "wof:placetype":"locality"
},
  "geometry": {"coordinates":[128.2826,36.244],"type":"Point"}
}