{
  "type": "Feature",
  "properties": {
    "gn:admin1_code":"14.0",
    "gn:asciiname":"Saemok",
    "gn:country_code":"KR",
    "gn:dem":258,
    "gn:feature_class":"P",
    "gn:feature_code":"PPL",
    "gn:name":"Saemok",
    "gn:population":0,
    "gn:timezone":"Asia/Seoul",
    "iso:country":"KR",
    "name:und_x_variant":[
        "\uc0c8\ubaa9",
        "Saemok"
    ],
    "wof:name":"Saemok",
    "wof:placetype":"locality"
},
  "geometry": {"coordinates":[128.17084,35.85027],"type":"Point"}
}