{
  "type": "Feature",
  "properties": {
    "gn:admin1_code":"16.0",
    "gn:asciiname":"Dongmuji",
    "gn:country_code":"KR",
    "gn:dem":50,
    "gn:feature_class":"P",
    "gn:feature_code":"PPL",
    "gn:name":"Dongmuji",
    "gn:population":0,
    "gn:timezone":"Asia/Seoul",
    "iso:country":"KR",
    "name:kor_x_preferred":[
        "\ub3d9\ubb34\uc9c0"
    ],
    "wof:name":"Dongmuji",
    "wof:placetype":"locality"
},
  "geometry": {"coordinates":[126.88983,34.96515],"type":"Point"}
}