{
  "type": "Feature",
  "properties": {
    "gn:admin1_code":"13.0",
    "gn:asciiname":"Darigogae",
    "gn:country_code":"KR",
    "gn:dem":149,
    "gn:feature_class":"P",
    "gn:feature_code":"PPL",
    "gn:name":"Darigogae",
    "gn:population":0,
    "gn:timezone":"Asia/Seoul",
    "iso:country":"KR",
    "name:und_x_variant":[
        "Kyohy\u014fn-ni",
        "\ub2e4\ub9ac\uace0\uac1c",
        "Tarigogae",
        "Darigogae"
    ],
    "wof:name":"Darigogae",
    "wof:placetype":"locality"
},
  "geometry": {"coordinates":[126.96869,37.69325],"type":"Point"}
}