{
  "type": "Feature",
  "properties": {
    "gn:admin1_code":"14.0",
    "gn:asciiname":"Ibokgol",
    "gn:country_code":"KR",
    "gn:dem":164,
    "gn:feature_class":"P",
    "gn:feature_code":"PPL",
    "gn:name":"Ibokgol",
    "gn:population":0,
    "gn:timezone":"Asia/Seoul",
    "iso:country":"KR",
    "name:kor_x_preferred":[
        "\uc774\ubcf5\uace8"
    ],
    "wof:name":"Ibokgol",
    "wof:placetype":"locality"
},
  "geometry": {"coordinates":[128.66753,36.09093],"type":"Point"}
}