{
  "type": "Feature",
  "properties": {
    "gn:admin1_code":"3.0",
    "gn:asciiname":"Kusan",
    "gn:country_code":"KR",
    "gn:dem":351,
    "gn:feature_class":"P",
    "gn:feature_code":"PPL",
    "gn:name":"Kusan",
    "gn:population":0,
    "gn:timezone":"Asia/Seoul",
    "iso:country":"KR",
    "name:fas_x_preferred":[
        "\u06a9\u0648\u0633\u0627\u0646"
    ],
    "name:und_x_variant":[
        "\uad6c\uc0b0",
        "Kusan"
    ],
    "wof:name":"Kusan",
    "wof:placetype":"locality"
},
  "geometry": {"coordinates":[127.78426,35.97449],"type":"Point"}
}