{
  "type": "Feature",
  "properties": {
    "gn:admin1_code":"16.0",
    "gn:asciiname":"Songjae-ri",
    "gn:cc2":"KR",
    "gn:country_code":"KR",
    "gn:dem":30,
    "gn:feature_class":"P",
    "gn:feature_code":"PPL",
    "gn:name":"S\u014fngjae-ri",
    "gn:population":0,
    "gn:timezone":"Asia/Seoul",
    "iso:country":"KR",
    "name:und_x_variant":[
        "S\u014fngjae",
        "S\u014fngjae-ri"
    ],
    "wof:name":"Songjae-ri",
    "wof:placetype":"locality"
},
  "geometry": {"coordinates":[126.58083000000001,34.80139],"type":"Point"}
}