{
  "type": "Feature",
  "properties": {
    "gn:admin1_code":"13.0",
    "gn:asciiname":"Changdong-ni",
    "gn:country_code":"KR",
    "gn:dem":121,
    "gn:feature_class":"P",
    "gn:feature_code":"PPLL",
    "gn:name":"Changdong-ni",
    "gn:population":0,
    "gn:timezone":"Asia/Seoul",
    "iso:country":"KR",
    "name:und_x_variant":[
        "\uc7a5\ub3d9\ub9ac",
        "Jangdong-ri",
        "Changdong-ni"
    ],
    "wof:name":"Changdong-ni",
    "wof:placetype":"locality"
},
  "geometry": {"coordinates":[127.43667000000001,37.33278],"type":"Point"}
}