{
  "type": "Feature",
  "properties": {
    "gn:admin1_code":"6.0",
    "gn:asciiname":"Yaksudong",
    "gn:country_code":"KR",
    "gn:dem":180,
    "gn:feature_class":"P",
    "gn:feature_code":"PPL",
    "gn:name":"Yaksudong",
    "gn:population":0,
    "gn:timezone":"Asia/Seoul",
    "iso:country":"KR",
    "name:kor_x_preferred":[
        "\uc57d\uc218\ub3d9"
    ],
    "wof:name":"Yaksudong",
    "wof:placetype":"locality"
},
  "geometry": {"coordinates":[127.24708,38.19084],"type":"Point"}
}