{
  "type": "Feature",
  "properties": {
    "gn:admin1_code":"13.0",
    "gn:asciiname":"Sajang-ni",
    "gn:country_code":"KR",
    "gn:dem":29,
    "gn:feature_class":"P",
    "gn:feature_code":"PPL",
    "gn:name":"Sajang-ni",
    "gn:population":0,
    "gn:timezone":"Asia/Seoul",
    "iso:country":"KR",
    "name:und_x_variant":[
        "Sach\u2019ang-ni",
        "Sajang-ni",
        "\uc0ac\ucc3d\ub3d9",
        "Sachang-dong",
        "Sach\u2019ang-dong"
    ],
    "wof:name":"Sajang-ni",
    "wof:placetype":"locality"
},
  "geometry": {"coordinates":[126.9725,37.0925],"type":"Point"}
}