{
  "type": "Feature",
  "properties": {
    "gn:admin1_code":"6.0",
    "gn:asciiname":"Ttoeryong-gol",
    "gn:country_code":"KR",
    "gn:dem":223,
    "gn:feature_class":"P",
    "gn:feature_code":"PPL",
    "gn:name":"Ttoeryong-gol",
    "gn:population":0,
    "gn:timezone":"Asia/Seoul",
    "iso:country":"KR",
    "name:kor_x_preferred":[
        "\ub664\ub8e1\uace8"
    ],
    "wof:name":"Ttoeryong-gol",
    "wof:placetype":"locality"
},
  "geometry": {"coordinates":[128.39570000000001,37.2136],"type":"Point"}
}