{
  "type": "Feature",
  "properties": {
    "gn:admin1_code":"14.0",
    "gn:asciiname":"Nondul",
    "gn:cc2":"KR",
    "gn:country_code":"KR",
    "gn:dem":488,
    "gn:feature_class":"P",
    "gn:feature_code":"PPL",
    "gn:name":"Nond\u016dl",
    "gn:population":0,
    "gn:timezone":"Asia/Seoul",
    "iso:country":"KR",
    "name:und_x_variant":[
        "Tapp\u2019y\u014fng",
        "Nond\u016dl"
    ],
    "wof:name":"Nondul",
    "wof:placetype":"locality"
},
  "geometry": {"coordinates":[128.84999999999999,36.16667],"type":"Point"}
}