{
  "type": "Feature",
  "properties": {
    "gn:admin1_code":"13.0",
    "gn:asciiname":"Soraebi",
    "gn:country_code":"KR",
    "gn:dem":80,
    "gn:feature_class":"P",
    "gn:feature_code":"PPL",
    "gn:name":"Soraebi",
    "gn:population":0,
    "gn:timezone":"Asia/Seoul",
    "iso:country":"KR",
    "name:kor_x_preferred":[
        "\uc18c\ub798\ube44"
    ],
    "name:und_x_variant":[
        "Soraebi"
    ],
    "wof:name":"Soraebi",
    "wof:placetype":"locality"
},
  "geometry": {"coordinates":[127.3319,37.6831],"type":"Point"}
}