{
  "type": "Feature",
  "properties": {
    "gn:admin1_code":"5.0",
    "gn:asciiname":"Yangdari",
    "gn:country_code":"KR",
    "gn:dem":788,
    "gn:feature_class":"P",
    "gn:feature_code":"PPL",
    "gn:name":"Yangdari",
    "gn:population":0,
    "gn:timezone":"Asia/Seoul",
    "iso:country":"KR",
    "name:kor_x_preferred":[
        "\uc591\ub2e4\ub9ac"
    ],
    "wof:name":"Yangdari",
    "wof:placetype":"locality"
},
  "geometry": {"coordinates":[128.55860000000001,37.0212],"type":"Point"}
}