{
  "type": "Feature",
  "properties": {
    "gn:admin1_code":"14.0",
    "gn:asciiname":"Hasa",
    "gn:country_code":"KR",
    "gn:dem":327,
    "gn:feature_class":"P",
    "gn:feature_code":"PPL",
    "gn:name":"Hasa",
    "gn:population":0,
    "gn:timezone":"Asia/Seoul",
    "iso:country":"KR",
    "name:ceb_x_preferred":[
        "Hasa"
    ],
    "name:deu_x_preferred":[
        "Hasa"
    ],
    "name:fin_x_preferred":[
        "Hasa"
    ],
    "name:und_x_variant":[
        "\ud558\uc0ac",
        "Hasa"
    ],
    "wof:name":"Hasa",
    "wof:placetype":"locality"
},
  "geometry": {"coordinates":[128.10806000000002,35.86485],"type":"Point"}
}