{
  "type": "Feature",
  "properties": {
    "gn:admin1_code":"6.0",
    "gn:asciiname":"Hojok-kol",
    "gn:country_code":"KR",
    "gn:dem":129,
    "gn:feature_class":"P",
    "gn:feature_code":"PPL",
    "gn:name":"Hoj\u014fk-kol",
    "gn:population":0,
    "gn:timezone":"Asia/Seoul",
    "iso:country":"KR",
    "name:kor_x_preferred":[
        "\ud638\uc801\uace8"
    ],
    "name:kor_x_variant":[
        "Hoj\u014fk-kol"
    ],
    "wof:name":"Hojok-kol",
    "wof:placetype":"locality"
},
  "geometry": {"coordinates":[127.8471,37.3212],"type":"Point"}
}