{
  "type": "Feature",
  "properties": {
    "gn:admin1_code":"14.0",
    "gn:asciiname":"Songdong-dong",
    "gn:country_code":"KR",
    "gn:dem":56,
    "gn:feature_class":"P",
    "gn:feature_code":"PPL",
    "gn:name":"S\u014fngdong-dong",
    "gn:population":0,
    "gn:timezone":"Asia/Seoul",
    "iso:country":"KR",
    "name:und_x_variant":[
        "\uc131\ub3d9\ub3d9",
        "S\u014fngdong-dong"
    ],
    "wof:name":"Songdong-dong",
    "wof:placetype":"locality"
},
  "geometry": {"coordinates":[128.1679,36.4154],"type":"Point"}
}