{
  "type": "Feature",
  "properties": {
    "gn:admin1_code":"16.0",
    "gn:asciiname":"Gettei",
    "gn:country_code":"KR",
    "gn:dem":64,
    "gn:feature_class":"P",
    "gn:feature_code":"PPL",
    "gn:name":"Gettei",
    "gn:population":0,
    "gn:timezone":"Asia/Seoul",
    "iso:country":"KR",
    "name:kor_x_preferred":[
        "\uc6d4\uc815"
    ],
    "name:kor_x_variant":[
        "W\u014flch\u014fng"
    ],
    "wof:name":"Gettei",
    "wof:placetype":"locality"
},
  "geometry": {"coordinates":[126.86583,34.50722],"type":"Point"}
}