{
  "type": "Feature",
  "properties": {
    "gn:admin1_code":"20.0",
    "gn:asciiname":"P'alch'ongok",
    "gn:country_code":"KR",
    "gn:dem":65,
    "gn:feature_class":"P",
    "gn:feature_code":"PPL",
    "gn:name":"P\u2019alch\u2019\u014fngok",
    "gn:population":0,
    "gn:timezone":"Asia/Seoul",
    "iso:country":"KR",
    "name:und_x_variant":[
        "\ud314\ucc9c\uace1",
        "P\u2019alch\u2019\u014fngok"
    ],
    "wof:name":"P'alch'ongok",
    "wof:placetype":"locality"
},
  "geometry": {"coordinates":[128.40325000000001,34.96809],"type":"Point"}
}