{
  "type": "Feature",
  "properties": {
    "gn:admin1_code":"14.0",
    "gn:asciiname":"Seongjam",
    "gn:country_code":"KR",
    "gn:dem":146,
    "gn:feature_class":"P",
    "gn:feature_code":"PPL",
    "gn:name":"Seongjam",
    "gn:population":0,
    "gn:timezone":"Asia/Seoul",
    "iso:country":"KR",
    "name:kor_x_preferred":[
        "\uc131\uc7a0"
    ],
    "wof:name":"Seongjam",
    "wof:placetype":"locality"
},
  "geometry": {"coordinates":[128.62683000000001,36.7605],"type":"Point"}
}