{
  "type": "Feature",
  "properties": {
    "gn:admin1_code":"17.0",
    "gn:asciiname":"Kisa",
    "gn:country_code":"KR",
    "gn:dem":13,
    "gn:feature_class":"P",
    "gn:feature_code":"PPL",
    "gn:name":"Kisa",
    "gn:population":0,
    "gn:timezone":"Asia/Seoul",
    "iso:country":"KR",
    "name:ceb_x_preferred":[
        "Kisa"
    ],
    "name:deu_x_preferred":[
        "Kisa"
    ],
    "name:rus_x_preferred":[
        "\u041a\u0438\u0441\u0430"
    ],
    "name:swe_x_preferred":[
        "Kisa"
    ],
    "name:und_x_variant":[
        "Kisa-ri",
        "\uae30\uc0ac"
    ],
    "wof:name":"Kisa",
    "wof:placetype":"locality"
},
  "geometry": {"coordinates":[126.8082,36.724],"type":"Point"}
}