{
  "type": "Feature",
  "properties": {
    "gn:admin1_code":"16.0",
    "gn:asciiname":"Deokcheon",
    "gn:country_code":"KR",
    "gn:dem":62,
    "gn:feature_class":"P",
    "gn:feature_code":"PPL",
    "gn:name":"Deokcheon",
    "gn:population":0,
    "gn:timezone":"Asia/Seoul",
    "iso:country":"KR",
    "name:kor_x_preferred":[
        "\ub355\ucc9c"
    ],
    "wof:name":"Deokcheon",
    "wof:placetype":"locality"
},
  "geometry": {"coordinates":[126.83735,35.264],"type":"Point"}
}