{
  "type": "Feature",
  "properties": {
    "gn:admin1_code":"16.0",
    "gn:asciiname":"Usal-li",
    "gn:cc2":"KR",
    "gn:country_code":"KR",
    "gn:dem":49,
    "gn:feature_class":"P",
    "gn:feature_code":"PPL",
    "gn:name":"Usal-li",
    "gn:population":0,
    "gn:timezone":"Asia/Seoul",
    "iso:country":"KR",
    "name:und_x_variant":[
        "Usan-ni",
        "Usal-li"
    ],
    "wof:name":"Usal-li",
    "wof:placetype":"locality"
},
  "geometry": {"coordinates":[126.87944,34.98472],"type":"Point"}
}