{
  "type": "Feature",
  "properties": {
    "gn:admin1_code":"17.0",
    "gn:asciiname":"Wittok-kol",
    "gn:country_code":"KR",
    "gn:dem":42,
    "gn:feature_class":"P",
    "gn:feature_code":"PPL",
    "gn:name":"Wittok-kol",
    "gn:population":0,
    "gn:timezone":"Asia/Seoul",
    "iso:country":"KR",
    "name:und_x_variant":[
        "\uc717\ub3c5\uace8",
        "Wittok-kol"
    ],
    "wof:name":"Wittok-kol",
    "wof:placetype":"locality"
},
  "geometry": {"coordinates":[126.7436,36.6729],"type":"Point"}
}