{
  "type": "Feature",
  "properties": {
    "gn:admin1_code":"12.0",
    "gn:asciiname":"Bakgongjae",
    "gn:country_code":"KR",
    "gn:dem":23,
    "gn:feature_class":"P",
    "gn:feature_code":"PPL",
    "gn:name":"Bakgongjae",
    "gn:population":0,
    "gn:timezone":"Asia/Seoul",
    "iso:country":"KR",
    "name:und_x_variant":[
        "\ubc15\uacf5\uc7ac",
        "Bakgongjae",
        "Pakkongjae"
    ],
    "wof:name":"Bakgongjae",
    "wof:placetype":"locality"
},
  "geometry": {"coordinates":[126.46808,37.69283],"type":"Point"}
}