{
  "type": "Feature",
  "properties": {
    "gn:admin1_code":"14.0",
    "gn:asciiname":"Ch'ang-mal",
    "gn:country_code":"KR",
    "gn:dem":49,
    "gn:feature_class":"P",
    "gn:feature_code":"PPL",
    "gn:name":"Ch\u2019ang-mal",
    "gn:population":0,
    "gn:timezone":"Asia/Seoul",
    "iso:country":"KR",
    "name:und_x_variant":[
        "\ucc3d\ub9d0",
        "Ch\u2019ang-mal"
    ],
    "wof:name":"Ch'ang-mal",
    "wof:placetype":"locality"
},
  "geometry": {"coordinates":[128.3853,36.1975],"type":"Point"}
}