{
  "type": "Feature",
  "properties": {
    "gn:admin1_code":"15.0",
    "gn:asciiname":"Dunsan",
    "gn:country_code":"KR",
    "gn:dem":52,
    "gn:feature_class":"P",
    "gn:feature_code":"PPL",
    "gn:name":"Dunsan",
    "gn:population":0,
    "gn:timezone":"Asia/Seoul",
    "iso:country":"KR",
    "name:kor_x_preferred":[
        "\ub454\uc0b0"
    ],
    "wof:name":"Dunsan",
    "wof:placetype":"locality"
},
  "geometry": {"coordinates":[128.67223999999999,35.89859000000001],"type":"Point"}
}