{
  "type": "Feature",
  "properties": {
    "gn:admin1_code":"17.0",
    "gn:asciiname":"Ch'amsae-gol",
    "gn:country_code":"KR",
    "gn:dem":14,
    "gn:feature_class":"P",
    "gn:feature_code":"PPL",
    "gn:name":"Ch\u2019amsae-gol",
    "gn:population":0,
    "gn:timezone":"Asia/Seoul",
    "iso:country":"KR",
    "name:und_x_variant":[
        "\ucc38\uc0c8\uace8",
        "Ch\u2019amsae-gol"
    ],
    "wof:name":"Ch'amsae-gol",
    "wof:placetype":"locality"
},
  "geometry": {"coordinates":[126.32989999999999,36.5894],"type":"Point"}
}