{
  "type": "Feature",
  "properties": {
    "gn:admin1_code":"13.0",
    "gn:asciiname":"Jeom-mal",
    "gn:country_code":"KR",
    "gn:dem":89,
    "gn:feature_class":"P",
    "gn:feature_code":"PPL",
    "gn:name":"Jeom-mal",
    "gn:population":0,
    "gn:timezone":"Asia/Seoul",
    "iso:country":"KR",
    "name:und_x_variant":[
        "\uc810\ub9d0",
        "Jeom-mal",
        "Ch\u014fm-mal"
    ],
    "wof:name":"Jeom-mal",
    "wof:placetype":"locality"
},
  "geometry": {"coordinates":[127.58611000000001,37.49583],"type":"Point"}
}