{
  "type": "Feature",
  "properties": {
    "gn:admin1_code":"20.0",
    "gn:asciiname":"Saetdam",
    "gn:country_code":"KR",
    "gn:dem":25,
    "gn:feature_class":"P",
    "gn:feature_code":"PPL",
    "gn:name":"Saetdam",
    "gn:population":0,
    "gn:timezone":"Asia/Seoul",
    "iso:country":"KR",
    "name:kor_x_preferred":[
        "\uc0db\ub2f4"
    ],
    "wof:name":"Saetdam",
    "wof:placetype":"locality"
},
  "geometry": {"coordinates":[128.39379,35.58745],"type":"Point"}
}