{
  "type": "Feature",
  "properties": {
    "gn:admin1_code":"6.0",
    "gn:asciiname":"Geonneomal",
    "gn:country_code":"KR",
    "gn:dem":29,
    "gn:feature_class":"P",
    "gn:feature_code":"PPL",
    "gn:name":"Geonneomal",
    "gn:population":0,
    "gn:timezone":"Asia/Seoul",
    "iso:country":"KR",
    "name:kor_x_preferred":[
        "\uac74\ub108\ub9d0"
    ],
    "wof:name":"Geonneomal",
    "wof:placetype":"locality"
},
  "geometry": {"coordinates":[128.66908000000001,38.04021],"type":"Point"}
}