{
  "type": "Feature",
  "properties": {
    "gn:admin1_code":"12.0",
    "gn:asciiname":"Naerigot",
    "gn:country_code":"KR",
    "gn:dem":6,
    "gn:feature_class":"P",
    "gn:feature_code":"PPL",
    "gn:name":"Naerigot",
    "gn:population":0,
    "gn:timezone":"Asia/Seoul",
    "iso:country":"KR",
    "name:kor_x_preferred":[
        "\ub0b4\ub9ac\uacf3"
    ],
    "wof:name":"Naerigot",
    "wof:placetype":"locality"
},
  "geometry": {"coordinates":[126.40652,37.46141],"type":"Point"}
}