{
  "type": "Feature",
  "properties": {
    "gn:admin1_code":"6.0",
    "gn:asciiname":"Soyongdong",
    "gn:country_code":"KR",
    "gn:dem":275,
    "gn:feature_class":"P",
    "gn:feature_code":"PPL",
    "gn:name":"Soyongdong",
    "gn:population":0,
    "gn:timezone":"Asia/Seoul",
    "iso:country":"KR",
    "name:kor_x_preferred":[
        "\uc218\uc6a9\ub3d9"
    ],
    "wof:name":"Soyongdong",
    "wof:placetype":"locality"
},
  "geometry": {"coordinates":[127.5553,38.05243],"type":"Point"}
}