{
  "type": "Feature",
  "properties": {
    "gn:admin1_code":"14.0",
    "gn:asciiname":"Gamnamubiri",
    "gn:country_code":"KR",
    "gn:dem":191,
    "gn:feature_class":"P",
    "gn:feature_code":"PPL",
    "gn:name":"Gamnamubiri",
    "gn:population":0,
    "gn:timezone":"Asia/Seoul",
    "iso:country":"KR",
    "name:kor_x_preferred":[
        "\uac10\ub098\ubb34\ube44\ub9ac"
    ],
    "wof:name":"Gamnamubiri",
    "wof:placetype":"locality"
},
  "geometry": {"coordinates":[128.00247999999999,36.66703],"type":"Point"}
}