{
  "type": "Feature",
  "properties": {
    "gn:admin1_code":"20.0",
    "gn:asciiname":"Tokkong-ni",
    "gn:country_code":"KR",
    "gn:dem":67,
    "gn:feature_class":"P",
    "gn:feature_code":"PPL",
    "gn:name":"T\u014fkkong-ni",
    "gn:population":0,
    "gn:timezone":"Asia/Seoul",
    "iso:country":"KR",
    "name:eng_x_preferred":[
        "Tokkong"
    ],
    "name:eng_x_variant":[
        "Tokkong-ni"
    ],
    "wof:name":"Tokkong",
    "wof:placetype":"locality"
},
  "geometry": {"coordinates":[128.55722,35.44056],"type":"Point"}
}