{
  "type": "Feature",
  "properties": {
    "gn:admin1_code":"16.0",
    "gn:asciiname":"Wangsan",
    "gn:country_code":"KR",
    "gn:dem":80,
    "gn:feature_class":"P",
    "gn:feature_code":"PPL",
    "gn:name":"Wangsan",
    "gn:population":0,
    "gn:timezone":"Asia/Seoul",
    "iso:country":"KR",
    "name:kor_x_preferred":[
        "\uc655\uc0b0"
    ],
    "wof:name":"Wangsan",
    "wof:placetype":"locality"
},
  "geometry": {"coordinates":[126.95138,35.34846],"type":"Point"}
}