{
  "type": "Feature",
  "properties": {
    "gn:admin1_code":"17.0",
    "gn:asciiname":"Baeti",
    "gn:country_code":"KR",
    "gn:dem":174,
    "gn:feature_class":"P",
    "gn:feature_code":"PPL",
    "gn:name":"Baeti",
    "gn:population":0,
    "gn:timezone":"Asia/Seoul",
    "iso:country":"KR",
    "name:und_x_variant":[
        "\ubc30\ud2f0",
        "Paet\u2019i",
        "Baeti"
    ],
    "wof:name":"Baeti",
    "wof:placetype":"locality"
},
  "geometry": {"coordinates":[127.27642,36.17986],"type":"Point"}
}