{
  "type": "Feature",
  "properties": {
    "gn:admin1_code":"6.0",
    "gn:asciiname":"Songgang-ni",
    "gn:country_code":"KR",
    "gn:dem":29,
    "gn:feature_class":"P",
    "gn:feature_code":"PPL",
    "gn:name":"Songgang-ni",
    "gn:population":0,
    "gn:timezone":"Asia/Seoul",
    "iso:country":"KR",
    "name:eng_x_preferred":[
        "Songgang"
    ],
    "name:eng_x_variant":[
        "Songgang-ni"
    ],
    "name:kor_x_preferred":[
        "\uc1a1\uac15\ub9ac"
    ],
    "wof:name":"Songgang",
    "wof:placetype":"locality"
},
  "geometry": {"coordinates":[128.40360999999999,38.43889],"type":"Point"}
}