{
  "type": "Feature",
  "properties": {
    "gn:admin1_code":"0.0",
    "gn:asciiname":"Sanjong-ni",
    "gn:country_code":"KR",
    "gn:dem":176,
    "gn:feature_class":"P",
    "gn:feature_code":"PPL",
    "gn:name":"Sanj\u014fng-ni",
    "gn:population":0,
    "gn:timezone":"Asia/Seoul",
    "iso:country":"KR",
    "name:eng_x_preferred":[
        "Sanjong"
    ],
    "name:eng_x_variant":[
        "Sanjong-ni"
    ],
    "wof:name":"Sanjong",
    "wof:placetype":"locality"
},
  "geometry": {"coordinates":[127.55,35.15],"type":"Point"}
}