{
  "type": "Feature",
  "properties": {
    "gn:admin1_code":"6.0",
    "gn:asciiname":"Punsil-gol",
    "gn:country_code":"KR",
    "gn:dem":274,
    "gn:feature_class":"P",
    "gn:feature_code":"PPL",
    "gn:name":"Punsil-gol",
    "gn:population":0,
    "gn:timezone":"Asia/Seoul",
    "iso:country":"KR",
    "wof:name":"Punsil-gol",
    "wof:placetype":"locality"
},
  "geometry": {"coordinates":[129.30082999999999,37.20944],"type":"Point"}
}