{
  "type": "Feature",
  "properties": {
    "gn:admin1_code":"6.0",
    "gn:asciiname":"Myongch'on-dong",
    "gn:country_code":"KR",
    "gn:dem":322,
    "gn:feature_class":"P",
    "gn:feature_code":"PPL",
    "gn:name":"My\u014fngch\u2019\u014fn-dong",
    "gn:population":0,
    "gn:timezone":"Asia/Seoul",
    "iso:country":"KR",
    "name:kor_x_preferred":[
        "\uba85\ucc9c\ub3d9"
    ],
    "name:kor_x_variant":[
        "My\u014fngch\u2019\u014fn-dong"
    ],
    "wof:name":"Myongch'on-dong",
    "wof:placetype":"locality"
},
  "geometry": {"coordinates":[127.9241,37.5112],"type":"Point"}
}