{
  "type": "Feature",
  "properties": {
    "gn:admin1_code":"13.0",
    "gn:asciiname":"Yangjin",
    "gn:country_code":"KR",
    "gn:dem":67,
    "gn:feature_class":"P",
    "gn:feature_code":"PPL",
    "gn:name":"Yangjin",
    "gn:population":0,
    "gn:timezone":"Asia/Seoul",
    "iso:country":"KR",
    "name:kor_x_preferred":[
        "\uc591\uc9c4"
    ],
    "name:und_x_variant":[
        "\uc591\uc9c4",
        "Yangjin"
    ],
    "wof:name":"Yangjin",
    "wof:placetype":"locality"
},
  "geometry": {"coordinates":[127.48538000000001,37.71518],"type":"Point"}
}