{
  "type": "Feature",
  "properties": {
    "gn:admin1_code":"16.0",
    "gn:asciiname":"Jungnam",
    "gn:country_code":"KR",
    "gn:dem":34,
    "gn:feature_class":"P",
    "gn:feature_code":"PPL",
    "gn:name":"Jungnam",
    "gn:population":0,
    "gn:timezone":"Asia/Seoul",
    "iso:country":"KR",
    "name:kor_x_preferred":[
        "\uc911\ub0a8"
    ],
    "name:und_x_variant":[
        "Chungnam-ni",
        "Chungnam",
        "Jungnam"
    ],
    "wof:name":"Jungnam",
    "wof:placetype":"locality"
},
  "geometry": {"coordinates":[126.86265,35.01917],"type":"Point"}
}