{
  "type": "Feature",
  "properties": {
    "gn:admin1_code":"14.0",
    "gn:asciiname":"Doraema",
    "gn:country_code":"KR",
    "gn:dem":265,
    "gn:feature_class":"P",
    "gn:feature_code":"PPL",
    "gn:name":"Doraema",
    "gn:population":0,
    "gn:timezone":"Asia/Seoul",
    "iso:country":"KR",
    "name:kor_x_preferred":[
        "\ub3c4\ub798\ub9c8"
    ],
    "wof:name":"Doraema",
    "wof:placetype":"locality"
},
  "geometry": {"coordinates":[128.76438999999999,36.66721],"type":"Point"}
}