{
  "type": "Feature",
  "properties": {
    "iso:country":"KR",
    "name:ceb_x_preferred":[
        "Geumseong-dong"
    ],
    "name:eng_x_preferred":[
        "Geumseong-dong"
    ],
    "name:fas_x_preferred":[
        "\u06af\u0648\u0645\u0633\u0626\u0648\u0646\u06af-\u062f\u0648\u0646\u06af"
    ],
    "name:kor_x_preferred":[
        "\uae08\uc131\ub3d9"
    ],
    "name:swe_x_preferred":[
        "Geumseong-dong"
    ],
    "wof:lang":[
        "kor"
    ],
    "wof:name":"\uae08\uc131\ub3d9",
    "wof:placetype":"neighbourhood"
},
  "geometry": {"coordinates":[129.058156,35.241939],"type":"Point"}
}