{
  "type": "Feature",
  "properties": {
    "gn:admin1_code":"14.0",
    "gn:asciiname":"Hasa-dong",
    "gn:country_code":"KR",
    "gn:dem":7,
    "gn:feature_class":"P",
    "gn:feature_code":"PPL",
    "gn:name":"Hasa-dong",
    "gn:population":0,
    "gn:timezone":"Asia/Seoul",
    "iso:country":"KR",
    "name:und_x_variant":[
        "\ud558\uc0ac\ub3d9",
        "Hasa-ri",
        "Hasa-dong"
    ],
    "wof:name":"Hasa-dong",
    "wof:placetype":"locality"
},
  "geometry": {"coordinates":[129.44589999999999,36.8249],"type":"Point"}
}