{
  "type": "Feature",
  "properties": {
    "gn:admin1_code":"17.0",
    "gn:asciiname":"Araetchung-mal",
    "gn:country_code":"KR",
    "gn:dem":261,
    "gn:feature_class":"P",
    "gn:feature_code":"PPL",
    "gn:name":"Araetchung-mal",
    "gn:population":0,
    "gn:timezone":"Asia/Seoul",
    "iso:country":"KR",
    "name:und_x_variant":[
        "\uc544\ub7ab\uc8fd\ub9d0",
        "Araetchung-mal"
    ],
    "wof:name":"Araetchung-mal",
    "wof:placetype":"locality"
},
  "geometry": {"coordinates":[127.5774,36.2069],"type":"Point"}
}