{
  "type": "Feature",
  "properties": {
    "gn:admin1_code":"20.0",
    "gn:asciiname":"Sinui",
    "gn:country_code":"KR",
    "gn:dem":69,
    "gn:feature_class":"P",
    "gn:feature_code":"PPL",
    "gn:name":"Sin\u016di",
    "gn:population":0,
    "gn:timezone":"Asia/Seoul",
    "iso:country":"KR",
    "name:und_x_variant":[
        "\uc2e0\uc758",
        "Sin\u016di"
    ],
    "wof:name":"Sinui",
    "wof:placetype":"locality"
},
  "geometry": {"coordinates":[128.46677,35.26331],"type":"Point"}
}