{
  "type": "Feature",
  "properties": {
    "gn:admin1_code":"6.0",
    "gn:asciiname":"Bangcheon 2-ri",
    "gn:country_code":"KR",
    "gn:dem":282,
    "gn:feature_class":"P",
    "gn:feature_code":"PPL",
    "gn:name":"Bangcheon 2-ri",
    "gn:population":0,
    "gn:timezone":"Asia/Seoul",
    "iso:country":"KR",
    "name:kor_x_preferred":[
        "\ubc29\ucc9c2\ub9ac"
    ],
    "name:kor_x_variant":[
        "Pangch\u2019\u014fni-ri"
    ],
    "wof:name":"Bangcheon 2-ri",
    "wof:placetype":"locality"
},
  "geometry": {"coordinates":[127.87333,38.0625],"type":"Point"}
}