{
  "type": "Feature",
  "properties": {
    "gn:admin1_code":"20.0",
    "gn:asciiname":"Chimun",
    "gn:country_code":"KR",
    "gn:dem":240,
    "gn:feature_class":"P",
    "gn:feature_code":"PPL",
    "gn:name":"Chimun",
    "gn:population":0,
    "gn:timezone":"Asia/Seoul",
    "iso:country":"KR",
    "name:und_x_variant":[
        "\uc9c0\ubb38",
        "Chimun"
    ],
    "wof:name":"Chimun",
    "wof:placetype":"locality"
},
  "geometry": {"coordinates":[128.15617,35.68778],"type":"Point"}
}