{
  "type": "Feature",
  "properties": {
    "gn:admin1_code":"16.0",
    "gn:asciiname":"Sacheonri",
    "gn:country_code":"KR",
    "gn:dem":22,
    "gn:feature_class":"P",
    "gn:feature_code":"PPL",
    "gn:name":"Sacheonri",
    "gn:population":0,
    "gn:timezone":"Asia/Seoul",
    "iso:country":"KR",
    "name:kor_x_preferred":[
        "\uc0ac\ucc9c\ub9ac"
    ],
    "name:und_x_variant":[
        "Sach\u2019\u014fn-ni",
        "Sach\u2019\u014fl-li",
        "Sacheonri"
    ],
    "wof:name":"Sacheonri",
    "wof:placetype":"locality"
},
  "geometry": {"coordinates":[126.15551000000001,34.40532],"type":"Point"}
}