{
  "type": "Feature",
  "properties": {
    "gn:admin1_code":"13.0",
    "gn:asciiname":"Dongsinwangdong",
    "gn:country_code":"KR",
    "gn:dem":33,
    "gn:feature_class":"P",
    "gn:feature_code":"PPL",
    "gn:name":"Dongsinwangdong",
    "gn:population":0,
    "gn:timezone":"Asia/Seoul",
    "iso:country":"KR",
    "name:und_x_variant":[
        "\ub3d9\uc2e0\uc655\ub3d9",
        "Dongsinwangdong",
        "Tongsinwang-dong"
    ],
    "wof:name":"Dongsinwangdong",
    "wof:placetype":"locality"
},
  "geometry": {"coordinates":[126.9525,37.08096],"type":"Point"}
}