{
  "type": "Feature",
  "properties": {
    "gn:admin1_code":"5.0",
    "gn:asciiname":"Yeonmotgol",
    "gn:country_code":"KR",
    "gn:dem":145,
    "gn:feature_class":"P",
    "gn:feature_code":"PPL",
    "gn:name":"Yeonmotgol",
    "gn:population":0,
    "gn:timezone":"Asia/Seoul",
    "iso:country":"KR",
    "name:kor_x_preferred":[
        "\uc5f0\ubabb\uace8"
    ],
    "wof:name":"Yeonmotgol",
    "wof:placetype":"locality"
},
  "geometry": {"coordinates":[127.85680000000001,36.77389],"type":"Point"}
}