{
  "type": "Feature",
  "properties": {
    "gn:admin1_code":"6.0",
    "gn:asciiname":"Paenaduri",
    "gn:country_code":"KR",
    "gn:dem":593,
    "gn:feature_class":"P",
    "gn:feature_code":"PPL",
    "gn:name":"Paenad\u016dri",
    "gn:population":0,
    "gn:timezone":"Asia/Seoul",
    "iso:country":"KR",
    "name:kor_x_preferred":[
        "\ubc30\ub098\ub4dc\ub9ac"
    ],
    "name:kor_x_variant":[
        "Paenad\u016dri"
    ],
    "wof:name":"Paenaduri",
    "wof:placetype":"locality"
},
  "geometry": {"coordinates":[128.74180000000001,37.5761],"type":"Point"}
}