{
  "type": "Feature",
  "properties": {
    "gn:admin1_code":"5.0",
    "gn:asciiname":"Gyeongjimmal",
    "gn:country_code":"KR",
    "gn:dem":101,
    "gn:feature_class":"P",
    "gn:feature_code":"PPL",
    "gn:name":"Gyeongjimmal",
    "gn:population":0,
    "gn:timezone":"Asia/Seoul",
    "iso:country":"KR",
    "name:kor_x_preferred":[
        "\uacbd\uc9d0\ub9d0"
    ],
    "wof:name":"Gyeongjimmal",
    "wof:placetype":"locality"
},
  "geometry": {"coordinates":[127.5996,37.00102],"type":"Point"}
}