{
  "type": "Feature",
  "properties": {
    "gn:admin1_code":"14.0",
    "gn:asciiname":"Araetgalpyeong",
    "gn:country_code":"KR",
    "gn:dem":71,
    "gn:feature_class":"P",
    "gn:feature_code":"PPL",
    "gn:name":"Araetgalpyeong",
    "gn:population":0,
    "gn:timezone":"Asia/Seoul",
    "iso:country":"KR",
    "name:kor_x_preferred":[
        "\uc544\ub7ab\uac08\ud3c9"
    ],
    "wof:name":"Araetgalpyeong",
    "wof:placetype":"locality"
},
  "geometry": {"coordinates":[129.40200000000002,35.91965],"type":"Point"}
}