{
  "type": "Feature",
  "properties": {
    "gn:admin1_code":"17.0",
    "gn:asciiname":"Yonhwa-dong",
    "gn:country_code":"KR",
    "gn:dem":19,
    "gn:feature_class":"P",
    "gn:feature_code":"PPL",
    "gn:name":"Y\u014fnhwa-dong",
    "gn:population":0,
    "gn:timezone":"Asia/Seoul",
    "iso:country":"KR",
    "name:und_x_variant":[
        "\uc5f0\ud654\ub3d9",
        "Y\u014fnhwa-dong"
    ],
    "wof:name":"Yonhwa-dong",
    "wof:placetype":"locality"
},
  "geometry": {"coordinates":[127.0903,36.7875],"type":"Point"}
}