{
  "type": "Feature",
  "properties": {
    "gn:admin1_code":"5.0",
    "gn:asciiname":"Hyoch'on",
    "gn:country_code":"KR",
    "gn:dem":62,
    "gn:feature_class":"P",
    "gn:feature_code":"PPL",
    "gn:name":"Hyoch\u2019on",
    "gn:population":0,
    "gn:timezone":"Asia/Seoul",
    "iso:country":"KR",
    "name:und_x_variant":[
        "Hyoch\u2019\u014fn-ni",
        "Hyoch\u2019on"
    ],
    "wof:name":"Hyoch'on",
    "wof:placetype":"locality"
},
  "geometry": {"coordinates":[127.50861,36.59],"type":"Point"}
}