{
  "type": "Feature",
  "properties": {
    "gn:admin1_code":"6.0",
    "gn:asciiname":"Hamak-tong",
    "gn:country_code":"KR",
    "gn:dem":436,
    "gn:feature_class":"P",
    "gn:feature_code":"PPL",
    "gn:name":"Hamak-tong",
    "gn:population":0,
    "gn:timezone":"Asia/Seoul",
    "iso:country":"KR",
    "name:eng_x_preferred":[
        "Hamak"
    ],
    "name:eng_x_variant":[
        "Hamak-tong"
    ],
    "name:kor_x_preferred":[
        "\ud558\ub9c9\ub3d9"
    ],
    "wof:name":"Hamak",
    "wof:placetype":"locality"
},
  "geometry": {"coordinates":[128.74010000000001,37.1779],"type":"Point"}
}