{
  "type": "Feature",
  "properties": {
    "gn:admin1_code":"5.0",
    "gn:asciiname":"Golmal",
    "gn:country_code":"KR",
    "gn:dem":177,
    "gn:feature_class":"P",
    "gn:feature_code":"PPL",
    "gn:name":"Golmal",
    "gn:population":0,
    "gn:timezone":"Asia/Seoul",
    "iso:country":"KR",
    "name:kor_x_preferred":[
        "\uace8\ub9d0"
    ],
    "wof:name":"Golmal",
    "wof:placetype":"locality"
},
  "geometry": {"coordinates":[127.39157,36.53707],"type":"Point"}
}