{
  "type": "Feature",
  "properties": {
    "gn:admin1_code":"18.0",
    "gn:asciiname":"Maehwadong",
    "gn:country_code":"KR",
    "gn:dem":20,
    "gn:feature_class":"P",
    "gn:feature_code":"PPL",
    "gn:name":"Maehwadong",
    "gn:population":0,
    "gn:timezone":"Asia/Seoul",
    "iso:country":"KR",
    "name:kor_x_preferred":[
        "\ub9e4\ud654\ub3d9"
    ],
    "wof:name":"Maehwadong",
    "wof:placetype":"locality"
},
  "geometry": {"coordinates":[126.7651,35.1415],"type":"Point"}
}