{
  "type": "Feature",
  "properties": {
    "gn:admin1_code":"16.0",
    "gn:asciiname":"Kumsan",
    "gn:country_code":"KR",
    "gn:dem":55,
    "gn:feature_class":"P",
    "gn:feature_code":"PPL",
    "gn:name":"K\u016dmsan",
    "gn:population":0,
    "gn:timezone":"Asia/Seoul",
    "iso:country":"KR",
    "name:kor_x_preferred":[
        "\uae08\uc0b0"
    ],
    "name:und_x_variant":[
        "K\u016dmsan"
    ],
    "wof:name":"Kumsan",
    "wof:placetype":"locality"
},
  "geometry": {"coordinates":[126.59583000000001,34.53805999999999],"type":"Point"}
}