{
  "type": "Feature",
  "properties": {
    "gn:admin1_code":"6.0",
    "gn:asciiname":"Ch'ilsibsam-dong",
    "gn:country_code":"KR",
    "gn:dem":178,
    "gn:feature_class":"P",
    "gn:feature_code":"PPL",
    "gn:name":"Ch\u2019ilsibsam-dong",
    "gn:population":0,
    "gn:timezone":"Asia/Seoul",
    "iso:country":"KR",
    "name:und_x_variant":[
        "Ch\u2019ilsibsam-dong",
        "\uce60\uc2ed\uc0bc\ub3d9"
    ],
    "wof:name":"Ch'ilsibsam-dong",
    "wof:placetype":"locality"
},
  "geometry": {"coordinates":[128.49189999999999,38.22821],"type":"Point"}
}