{
  "type": "Feature",
  "properties": {
    "gn:admin1_code":"5.0",
    "gn:asciiname":"Sinan-dong",
    "gn:country_code":"KR",
    "gn:dem":375,
    "gn:feature_class":"P",
    "gn:feature_code":"PPL",
    "gn:name":"Sinan-dong",
    "gn:population":0,
    "gn:timezone":"Asia/Seoul",
    "iso:country":"KR",
    "name:und_x_variant":[
        "\uc2e0\uc548\ub3d9",
        "Sinan-dong"
    ],
    "wof:name":"Sinan-dong",
    "wof:placetype":"locality"
},
  "geometry": {"coordinates":[128.02080000000001,36.2481],"type":"Point"}
}