{
  "type": "Feature",
  "properties": {
    "gn:admin1_code":"16.0",
    "gn:asciiname":"Maengsol-li",
    "gn:country_code":"KR",
    "gn:dem":32,
    "gn:feature_class":"P",
    "gn:feature_code":"PPL",
    "gn:name":"Maengs\u014fl-li",
    "gn:population":0,
    "gn:timezone":"Asia/Seoul",
    "iso:country":"KR",
    "name:kor_x_preferred":[
        "\ub9f9\uc120\ub9ac"
    ],
    "name:kor_x_variant":[
        "Maengs\u014fl-li"
    ],
    "name:und_x_variant":[
        "Maenys\u014fn-ni",
        "M\u014dsen-ri",
        "Maengs\u014fn-ni",
        "Maengs\u014fn"
    ],
    "wof:name":"Maengsol-li",
    "wof:placetype":"locality"
},
  "geometry": {"coordinates":[126.63722,34.14917],"type":"Point"}
}