{
  "type": "Feature",
  "properties": {
    "gn:admin1_code":"14.0",
    "gn:asciiname":"Haein-dong",
    "gn:country_code":"KR",
    "gn:dem":478,
    "gn:feature_class":"P",
    "gn:feature_code":"PPL",
    "gn:name":"Haein-dong",
    "gn:population":0,
    "gn:timezone":"Asia/Seoul",
    "iso:country":"KR",
    "name:und_x_variant":[
        "\ud574\uc778\ub3d9",
        "Haein-dong"
    ],
    "wof:name":"Haein-dong",
    "wof:placetype":"locality"
},
  "geometry": {"coordinates":[127.90349999999999,36.0138],"type":"Point"}
}