{
  "type": "Feature",
  "properties": {
    "gn:admin1_code":"11.0",
    "gn:asciiname":"Pangii-dong",
    "gn:country_code":"KR",
    "gn:dem":19,
    "gn:feature_class":"P",
    "gn:feature_code":"PPL",
    "gn:name":"Pangii-dong",
    "gn:population":0,
    "gn:timezone":"Asia/Seoul",
    "iso:country":"KR",
    "name:und_x_variant":[
        "\ubc29\uc7742\ub3d9",
        "Pangii-dong"
    ],
    "wof:name":"Pangii-dong",
    "wof:placetype":"locality"
},
  "geometry": {"coordinates":[127.11381000000002,37.51262],"type":"Point"}
}