{
  "type": "Feature",
  "properties": {
    "gn:admin1_code":"16.0",
    "gn:asciiname":"Bonchon",
    "gn:country_code":"KR",
    "gn:dem":63,
    "gn:feature_class":"P",
    "gn:feature_code":"PPL",
    "gn:name":"Bonchon",
    "gn:population":0,
    "gn:timezone":"Asia/Seoul",
    "iso:country":"KR",
    "name:kor_x_preferred":[
        "\ubcf8\ucd0c"
    ],
    "wof:name":"Bonchon",
    "wof:placetype":"locality"
},
  "geometry": {"coordinates":[126.6442,35.06406],"type":"Point"}
}