{
  "type": "Feature",
  "properties": {
    "gn:admin1_code":"6.0",
    "gn:asciiname":"Tulmoringi",
    "gn:country_code":"KR",
    "gn:dem":216,
    "gn:feature_class":"P",
    "gn:feature_code":"PPL",
    "gn:name":"T\u016dlmoringi",
    "gn:population":0,
    "gn:timezone":"Asia/Seoul",
    "iso:country":"KR",
    "name:kor_x_preferred":[
        "\ub4e4\ubaa8\ub9c1\uc774"
    ],
    "name:kor_x_variant":[
        "T\u016dlmoringi"
    ],
    "wof:name":"Tulmoringi",
    "wof:placetype":"locality"
},
  "geometry": {"coordinates":[128.59989999999999,37.1221],"type":"Point"}
}