{
  "type": "Feature",
  "properties": {
    "gn:admin1_code":"14.0",
    "gn:asciiname":"T'ongsibang",
    "gn:country_code":"KR",
    "gn:dem":218,
    "gn:feature_class":"P",
    "gn:feature_code":"PPL",
    "gn:name":"T\u2019ongsibang",
    "gn:population":0,
    "gn:timezone":"Asia/Seoul",
    "iso:country":"KR",
    "name:und_x_variant":[
        "\ud1b5\uc2dc\ubc29",
        "T\u2019ongsibang"
    ],
    "wof:name":"T'ongsibang",
    "wof:placetype":"locality"
},
  "geometry": {"coordinates":[129.10210000000001,36.6451],"type":"Point"}
}