{
  "type": "Feature",
  "properties": {
    "gn:admin1_code":"13.0",
    "gn:asciiname":"Dokjeongi",
    "gn:country_code":"KR",
    "gn:dem":130,
    "gn:feature_class":"P",
    "gn:feature_code":"PPL",
    "gn:name":"Dokjeongi",
    "gn:population":0,
    "gn:timezone":"Asia/Seoul",
    "iso:country":"KR",
    "name:und_x_variant":[
        "\ub3c5\uc815\uc774",
        "Dokjeongi",
        "Tokch\u014fngi"
    ],
    "wof:name":"Dokjeongi",
    "wof:placetype":"locality"
},
  "geometry": {"coordinates":[127.0175,37.39611],"type":"Point"}
}