{
  "type": "Feature",
  "properties": {
    "gn:admin1_code":"17.0",
    "gn:asciiname":"Pangjuk-kol",
    "gn:country_code":"KR",
    "gn:dem":75,
    "gn:feature_class":"P",
    "gn:feature_code":"PPL",
    "gn:name":"Pangjuk-kol",
    "gn:population":0,
    "gn:timezone":"Asia/Seoul",
    "iso:country":"KR",
    "name:und_x_variant":[
        "\ubc29\uc8fd\uace8",
        "Pangjuk-kol"
    ],
    "wof:name":"Pangjuk-kol",
    "wof:placetype":"locality"
},
  "geometry": {"coordinates":[126.758,36.4813],"type":"Point"}
}