{
  "type": "Feature",
  "properties": {
    "gn:admin1_code":"13.0",
    "gn:asciiname":"Anchangmoru",
    "gn:country_code":"KR",
    "gn:dem":33,
    "gn:feature_class":"P",
    "gn:feature_code":"PPL",
    "gn:name":"Anchangmoru",
    "gn:population":0,
    "gn:timezone":"Asia/Seoul",
    "iso:country":"KR",
    "name:kor_x_preferred":[
        "\uc548\ucc3d\ubaa8\ub8e8"
    ],
    "name:und_x_variant":[
        "\uc548\ucc3d\ubaa8\ub8e8",
        "Anchangmoru"
    ],
    "wof:name":"Anchangmoru",
    "wof:placetype":"locality"
},
  "geometry": {"coordinates":[127.2303,37.5374],"type":"Point"}
}