{
  "type": "Feature",
  "properties": {
    "gn:admin1_code":"15.0",
    "gn:asciiname":"Jaksalgogae",
    "gn:country_code":"KR",
    "gn:dem":35,
    "gn:feature_class":"P",
    "gn:feature_code":"PPL",
    "gn:name":"Jaksalgogae",
    "gn:population":0,
    "gn:timezone":"Asia/Seoul",
    "iso:country":"KR",
    "name:kor_x_preferred":[
        "\uc791\uc0b4\uace0\uac1c"
    ],
    "wof:name":"Jaksalgogae",
    "wof:placetype":"locality"
},
  "geometry": {"coordinates":[128.40073000000001,35.66461],"type":"Point"}
}