{
  "type": "Feature",
  "properties": {
    "gn:admin1_code":"13.0",
    "gn:asciiname":"Neolmuni",
    "gn:country_code":"KR",
    "gn:dem":63,
    "gn:feature_class":"P",
    "gn:feature_code":"PPL",
    "gn:name":"Neolmuni",
    "gn:population":0,
    "gn:timezone":"Asia/Seoul",
    "iso:country":"KR",
    "name:kor_x_preferred":[
        "\ub110\ubb34\ub2c8"
    ],
    "name:und_x_variant":[
        "\ub110\ubb38\uc774",
        "Neolmuni",
        "N\u014flmuni"
    ],
    "wof:name":"Neolmuni",
    "wof:placetype":"locality"
},
  "geometry": {"coordinates":[127.16331,37.49782],"type":"Point"}
}