{
  "type": "Feature",
  "properties": {
    "gn:admin1_code":"3.0",
    "gn:asciiname":"Chon'gang",
    "gn:country_code":"KR",
    "gn:dem":47,
    "gn:feature_class":"P",
    "gn:feature_code":"PPL",
    "gn:name":"Ch\u014fn\u2019gang",
    "gn:population":0,
    "gn:timezone":"Asia/Seoul",
    "iso:country":"KR",
    "name:und_x_variant":[
        "\uc804\uac15",
        "Ch\u014fn\u2019gang"
    ],
    "wof:name":"Chon'gang",
    "wof:placetype":"locality"
},
  "geometry": {"coordinates":[127.10767,35.9742],"type":"Point"}
}