{
  "type": "Feature",
  "properties": {
    "gn:admin1_code":"13.0",
    "gn:asciiname":"Haniljut'aek",
    "gn:country_code":"KR",
    "gn:dem":20,
    "gn:feature_class":"P",
    "gn:feature_code":"PPL",
    "gn:name":"Haniljut\u2019aek",
    "gn:population":0,
    "gn:timezone":"Asia/Seoul",
    "iso:country":"KR",
    "name:kor_x_preferred":[
        "\ud55c\uc77c\uc8fc\ud0dd"
    ],
    "name:kor_x_variant":[
        "Haniljut\u2019aek"
    ],
    "wof:name":"Haniljut'aek",
    "wof:placetype":"locality"
},
  "geometry": {"coordinates":[126.82167,37.005],"type":"Point"}
}