{
  "type": "Feature",
  "properties": {
    "gn:admin1_code":"14.0",
    "gn:asciiname":"Tunjon",
    "gn:country_code":"KR",
    "gn:dem":224,
    "gn:feature_class":"P",
    "gn:feature_code":"PPL",
    "gn:name":"Tunj\u014fn",
    "gn:population":0,
    "gn:timezone":"Asia/Seoul",
    "iso:country":"KR",
    "name:und_x_variant":[
        "\ub454\uc804",
        "Tunj\u014fn"
    ],
    "wof:name":"Tunjon",
    "wof:placetype":"locality"
},
  "geometry": {"coordinates":[128.92570000000001,36.3455],"type":"Point"}
}