{
  "type": "Feature",
  "properties": {
    "gn:admin1_code":"14.0",
    "gn:asciiname":"Hasijang",
    "gn:country_code":"KR",
    "gn:dem":717,
    "gn:feature_class":"P",
    "gn:feature_code":"PPL",
    "gn:name":"Hasijang",
    "gn:population":0,
    "gn:timezone":"Asia/Seoul",
    "iso:country":"KR",
    "name:kor_x_preferred":[
        "\ud558\uc2dc\uc7a5"
    ],
    "wof:name":"Hasijang",
    "wof:placetype":"locality"
},
  "geometry": {"coordinates":[128.81205,37.0626],"type":"Point"}
}