{
  "type": "Feature",
  "properties": {
    "gn:admin1_code":"3.0",
    "gn:asciiname":"Namak",
    "gn:country_code":"KR",
    "gn:dem":68,
    "gn:feature_class":"P",
    "gn:feature_code":"PPL",
    "gn:name":"Namak",
    "gn:population":0,
    "gn:timezone":"Asia/Seoul",
    "iso:country":"KR",
    "name:und_x_variant":[
        "\ub0a8\uc545",
        "Namak"
    ],
    "wof:name":"Namak",
    "wof:placetype":"locality"
},
  "geometry": {"coordinates":[127.20694,35.94463],"type":"Point"}
}