{
  "type": "Feature",
  "properties": {
    "gn:admin1_code":"17.0",
    "gn:asciiname":"Okkasil",
    "gn:country_code":"KR",
    "gn:dem":60,
    "gn:feature_class":"P",
    "gn:feature_code":"PPL",
    "gn:name":"Okkasil",
    "gn:population":0,
    "gn:timezone":"Asia/Seoul",
    "iso:country":"KR",
    "name:und_x_variant":[
        "\uc625\uac00\uc2e4",
        "Okkasil"
    ],
    "wof:name":"Okkasil",
    "wof:placetype":"locality"
},
  "geometry": {"coordinates":[126.83759999999999,36.3468],"type":"Point"}
}