{
  "type": "Feature",
  "properties": {
    "gn:admin1_code":"6.0",
    "gn:asciiname":"Oktong-ni",
    "gn:country_code":"KR",
    "gn:dem":264,
    "gn:feature_class":"P",
    "gn:feature_code":"PPLL",
    "gn:name":"Oktong-ni",
    "gn:population":0,
    "gn:timezone":"Asia/Seoul",
    "iso:country":"KR",
    "name:eng_x_preferred":[
        "Oktong"
    ],
    "name:eng_x_variant":[
        "Oktong-ni"
    ],
    "name:kor_x_preferred":[
        "\uc625\ub3d9\ub9ac"
    ],
    "wof:name":"Oktong",
    "wof:placetype":"locality"
},
  "geometry": {"coordinates":[128.03774999999999,37.52166],"type":"Point"}
}