{
  "type": "Feature",
  "properties": {
    "gn:admin1_code":"13.0",
    "gn:asciiname":"Kurisom",
    "gn:country_code":"KR",
    "gn:dem":10,
    "gn:feature_class":"P",
    "gn:feature_code":"PPL",
    "gn:name":"Kuris\u014fm",
    "gn:population":0,
    "gn:timezone":"Asia/Seoul",
    "iso:country":"KR",
    "name:kor_x_preferred":[
        "\uad6c\ub9ac\uc12c"
    ],
    "name:kor_x_variant":[
        "Kuris\u014fm"
    ],
    "wof:name":"Kurisom",
    "wof:placetype":"locality"
},
  "geometry": {"coordinates":[126.76416999999999,37.20944],"type":"Point"}
}