{
  "type": "Feature",
  "properties": {
    "gn:admin1_code":"17.0",
    "gn:asciiname":"Ch'omi-dong",
    "gn:country_code":"KR",
    "gn:dem":243,
    "gn:feature_class":"P",
    "gn:feature_code":"PPL",
    "gn:name":"Ch\u2019omi-dong",
    "gn:population":0,
    "gn:timezone":"Asia/Seoul",
    "iso:country":"KR",
    "name:und_x_variant":[
        "\ucd08\ubbf8\ub3d9",
        "Ch\u2019omi-dong"
    ],
    "wof:name":"Ch'omi-dong",
    "wof:placetype":"locality"
},
  "geometry": {"coordinates":[127.44280000000001,36.1556],"type":"Point"}
}