{
  "type": "Feature",
  "properties": {
    "gn:admin1_code":"5.0",
    "gn:asciiname":"Garyeongsan",
    "gn:country_code":"KR",
    "gn:dem":522,
    "gn:feature_class":"P",
    "gn:feature_code":"PPL",
    "gn:name":"Garyeongsan",
    "gn:population":0,
    "gn:timezone":"Asia/Seoul",
    "iso:country":"KR",
    "name:kor_x_preferred":[
        "\uac00\ub839\uc0b0"
    ],
    "wof:name":"Garyeongsan",
    "wof:placetype":"locality"
},
  "geometry": {"coordinates":[127.85742999999999,36.69328],"type":"Point"}
}