{
  "type": "Feature",
  "properties": {
    "gn:admin1_code":"14.0",
    "gn:asciiname":"Hahambak",
    "gn:country_code":"KR",
    "gn:dem":119,
    "gn:feature_class":"P",
    "gn:feature_code":"PPL",
    "gn:name":"Hahambak",
    "gn:population":0,
    "gn:timezone":"Asia/Seoul",
    "iso:country":"KR",
    "name:und_x_variant":[
        "\ud558\ud568\ubc15",
        "Hahambak"
    ],
    "wof:name":"Hahambak",
    "wof:placetype":"locality"
},
  "geometry": {"coordinates":[128.64080000000001,35.61564],"type":"Point"}
}