{
  "type": "Feature",
  "properties": {
    "gn:admin1_code":"17.0",
    "gn:asciiname":"Sinbu-dong",
    "gn:country_code":"KR",
    "gn:dem":126,
    "gn:feature_class":"P",
    "gn:feature_code":"PPL",
    "gn:name":"Sinbu-dong",
    "gn:population":0,
    "gn:timezone":"Asia/Seoul",
    "iso:country":"KR",
    "name:und_x_variant":[
        "\uc2e0\ubd80\ub3d9",
        "Sinbu-dong"
    ],
    "wof:name":"Sinbu-dong",
    "wof:placetype":"locality"
},
  "geometry": {"coordinates":[126.7792,36.372],"type":"Point"}
}