{
  "type": "Feature",
  "properties": {
    "gn:admin1_code":"13.0",
    "gn:asciiname":"Joganggeori",
    "gn:country_code":"KR",
    "gn:dem":17,
    "gn:feature_class":"P",
    "gn:feature_code":"PPL",
    "gn:name":"Joganggeori",
    "gn:population":0,
    "gn:timezone":"Asia/Seoul",
    "iso:country":"KR",
    "name:kor_x_preferred":[
        "\uc870\uac15\uac70\ub9ac"
    ],
    "name:kor_x_variant":[
        "Chogangg\u014fri"
    ],
    "wof:name":"Joganggeori",
    "wof:placetype":"locality"
},
  "geometry": {"coordinates":[126.60433,37.6885],"type":"Point"}
}