{
  "type": "Feature",
  "properties": {
    "gn:admin1_code":"13.0",
    "gn:asciiname":"Eungdalpyeon",
    "gn:country_code":"KR",
    "gn:dem":83,
    "gn:feature_class":"P",
    "gn:feature_code":"PPL",
    "gn:name":"Eungdalpyeon",
    "gn:population":0,
    "gn:timezone":"Asia/Seoul",
    "iso:country":"KR",
    "name:und_x_variant":[
        "\uc751\ub2ec\ud3b8",
        "\u016cngdalp\u2019y\u014fn",
        "Eungdalpyeon"
    ],
    "wof:name":"Eungdalpyeon",
    "wof:placetype":"locality"
},
  "geometry": {"coordinates":[126.93729999999999,37.7105],"type":"Point"}
}