{
  "type": "Feature",
  "properties": {
    "gn:admin1_code":"13.0",
    "gn:asciiname":"Seonbawi",
    "gn:country_code":"KR",
    "gn:dem":99,
    "gn:feature_class":"P",
    "gn:feature_code":"PPL",
    "gn:name":"Seonbawi",
    "gn:population":0,
    "gn:timezone":"Asia/Seoul",
    "iso:country":"KR",
    "name:kor_x_preferred":[
        "\uc120\ubc14\uc704"
    ],
    "name:kor_x_variant":[
        "S\u014fnbawi"
    ],
    "wof:name":"Seonbawi",
    "wof:placetype":"locality"
},
  "geometry": {"coordinates":[127.6799,37.5227],"type":"Point"}
}