{
  "type": "Feature",
  "properties": {
    "gn:admin1_code":"20.0",
    "gn:asciiname":"Chinjong-ni",
    "gn:cc2":"KR",
    "gn:country_code":"KR",
    "gn:dem":4,
    "gn:feature_class":"P",
    "gn:feature_code":"PPL",
    "gn:name":"Chinj\u014fng-ni",
    "gn:population":0,
    "gn:timezone":"Asia/Seoul",
    "iso:country":"KR",
    "name:und_x_variant":[
        "Chinj\u014fng",
        "Chinj\u014fng-ni"
    ],
    "wof:name":"Chinjong-ni",
    "wof:placetype":"locality"
},
  "geometry": {"coordinates":[127.82306,34.98444],"type":"Point"}
}