{
  "type": "Feature",
  "properties": {
    "gn:admin1_code":"16.0",
    "gn:asciiname":"Dangsa",
    "gn:country_code":"KR",
    "gn:dem":9,
    "gn:feature_class":"P",
    "gn:feature_code":"PPL",
    "gn:name":"Dangsa",
    "gn:population":0,
    "gn:timezone":"Asia/Seoul",
    "iso:country":"KR",
    "name:kor_x_preferred":[
        "\ub2f9\uc0ac"
    ],
    "name:und_x_variant":[
        "T\u014dsha-ri",
        "Tangsa",
        "Tangsa-ri",
        "Dangsa"
    ],
    "wof:name":"Dangsa",
    "wof:placetype":"locality"
},
  "geometry": {"coordinates":[126.17679,34.88632],"type":"Point"}
}