{
  "type": "Feature",
  "properties": {
    "gn:admin1_code":"6.0",
    "gn:asciiname":"Hwanghakdong",
    "gn:country_code":"KR",
    "gn:dem":223,
    "gn:feature_class":"P",
    "gn:feature_code":"PPL",
    "gn:name":"Hwanghakdong",
    "gn:population":0,
    "gn:timezone":"Asia/Seoul",
    "iso:country":"KR",
    "name:kor_x_preferred":[
        "\ud669\ud559\ub3d9"
    ],
    "wof:name":"Hwanghakdong",
    "wof:placetype":"locality"
},
  "geometry": {"coordinates":[127.65685000000001,38.18644000000001],"type":"Point"}
}