{
  "type": "Feature",
  "properties": {
    "gn:admin1_code":"14.0",
    "gn:asciiname":"Tonam-dong",
    "gn:country_code":"KR",
    "gn:dem":85,
    "gn:feature_class":"P",
    "gn:feature_code":"PPL",
    "gn:name":"Tonam-dong",
    "gn:population":0,
    "gn:timezone":"Asia/Seoul",
    "iso:country":"KR",
    "wof:name":"Tonam-dong",
    "wof:placetype":"locality"
},
  "geometry": {"coordinates":[128.94999999999999,35.93333],"type":"Point"}
}