{
  "type": "Feature",
  "properties": {
    "gn:admin1_code":"17.0",
    "gn:asciiname":"Nanjong",
    "gn:country_code":"KR",
    "gn:dem":6,
    "gn:feature_class":"P",
    "gn:feature_code":"PPL",
    "gn:name":"Nanj\u014fng",
    "gn:population":0,
    "gn:timezone":"Asia/Seoul",
    "iso:country":"KR",
    "name:und_x_variant":[
        "Nanj\u014fng-ni",
        "\ub09c\uc815",
        "Nanj\u014fng"
    ],
    "wof:name":"Nanjong",
    "wof:placetype":"locality"
},
  "geometry": {"coordinates":[126.5226,36.5233],"type":"Point"}
}