{
  "type": "Feature",
  "properties": {
    "gn:admin1_code":"13.0",
    "gn:admin2_code":"Ans\u014fng-si",
    "gn:asciiname":"Sangsam-ni",
    "gn:country_code":"KR",
    "gn:dem":69,
    "gn:feature_class":"P",
    "gn:feature_code":"PPLL",
    "gn:name":"Sangsam-ni",
    "gn:population":0,
    "gn:timezone":"Asia/Seoul",
    "iso:country":"KR",
    "name:eng_x_preferred":[
        "Sangsam"
    ],
    "name:eng_x_variant":[
        "Sangsam-ni"
    ],
    "name:kor_x_preferred":[
        "\uc0c1\uc0bc\ub9ac"
    ],
    "name:und_x_variant":[
        "Sangsang-dong",
        "Sangsam-ni",
        "Sangsam-dong",
        "Sangsam-ri"
    ],
    "wof:name":"Sangsam",
    "wof:placetype":"locality"
},
  "geometry": {"coordinates":[127.32056,37.02417],"type":"Point"}
}