{
  "type": "Feature",
  "properties": {
    "gn:admin1_code":"13.0",
    "gn:asciiname":"Biseokgeori",
    "gn:country_code":"KR",
    "gn:dem":105,
    "gn:feature_class":"P",
    "gn:feature_code":"PPL",
    "gn:name":"Biseokgeori",
    "gn:population":0,
    "gn:timezone":"Asia/Seoul",
    "iso:country":"KR",
    "name:kor_x_preferred":[
        "\ube44\uc11d\uac70\ub9ac"
    ],
    "wof:name":"Biseokgeori",
    "wof:placetype":"locality"
},
  "geometry": {"coordinates":[127.18745,37.88171],"type":"Point"}
}