{
  "type": "Feature",
  "properties": {
    "gn:admin1_code":"6.0",
    "gn:asciiname":"Araethwangi",
    "gn:country_code":"KR",
    "gn:dem":184,
    "gn:feature_class":"P",
    "gn:feature_code":"PPL",
    "gn:name":"Araethwangi",
    "gn:population":0,
    "gn:timezone":"Asia/Seoul",
    "iso:country":"KR",
    "name:kor_x_preferred":[
        "\uc544\ub798\ud669\uc774"
    ],
    "name:kor_x_variant":[
        "\uc544\ub7ab\ud669\uc774"
    ],
    "name:und_x_variant":[
        "Araehwangi",
        "Araethwangi"
    ],
    "wof:name":"Araethwangi",
    "wof:placetype":"locality"
},
  "geometry": {"coordinates":[128.52180000000001,37.9711],"type":"Point"}
}