{
  "type": "Feature",
  "properties": {
    "gn:admin1_code":"14.0",
    "gn:asciiname":"Wonma",
    "gn:country_code":"KR",
    "gn:dem":154,
    "gn:feature_class":"P",
    "gn:feature_code":"PPL",
    "gn:name":"W\u014fnma",
    "gn:population":0,
    "gn:timezone":"Asia/Seoul",
    "iso:country":"KR",
    "name:und_x_variant":[
        "\uc6d0\ub9c8",
        "W\u014fnma"
    ],
    "wof:name":"Wonma",
    "wof:placetype":"locality"
},
  "geometry": {"coordinates":[129.33940000000001,36.7595],"type":"Point"}
}