{
  "type": "Feature",
  "properties": {
    "gn:admin1_code":"20.0",
    "gn:asciiname":"Obok-kol",
    "gn:country_code":"KR",
    "gn:dem":30,
    "gn:feature_class":"P",
    "gn:feature_code":"PPL",
    "gn:name":"Obok-kol",
    "gn:population":0,
    "gn:timezone":"Asia/Seoul",
    "iso:country":"KR",
    "name:und_x_variant":[
        "\uc624\ubcf5\uace8",
        "Obok-kol"
    ],
    "wof:name":"Obok-kol",
    "wof:placetype":"locality"
},
  "geometry": {"coordinates":[128.21090000000001,35.60923],"type":"Point"}
}