{
  "type": "Feature",
  "properties": {
    "gn:admin1_code":"16.0",
    "gn:asciiname":"Songho-ri",
    "gn:country_code":"KR",
    "gn:dem":86,
    "gn:feature_class":"P",
    "gn:feature_code":"PPL",
    "gn:name":"Songho-ri",
    "gn:population":0,
    "gn:timezone":"Asia/Seoul",
    "iso:country":"KR",
    "name:und_x_variant":[
        "Songj\u014fng"
    ],
    "wof:name":"Songho-ri",
    "wof:placetype":"locality"
},
  "geometry": {"coordinates":[126.56667,34.96667],"type":"Point"}
}