{
  "type": "Feature",
  "properties": {
    "gn:admin1_code":"5.0",
    "gn:asciiname":"Kwan'gi",
    "gn:country_code":"KR",
    "gn:dem":239,
    "gn:feature_class":"P",
    "gn:feature_code":"PPL",
    "gn:name":"Kwan\u2019gi",
    "gn:population":0,
    "gn:timezone":"Asia/Seoul",
    "iso:country":"KR",
    "wof:name":"Kwan'gi",
    "wof:placetype":"locality"
},
  "geometry": {"coordinates":[127.63333,36.61667],"type":"Point"}
}