{
  "type": "Feature",
  "properties": {
    "gn:admin1_code":"16.0",
    "gn:asciiname":"Gaesan",
    "gn:country_code":"KR",
    "gn:dem":6,
    "gn:feature_class":"P",
    "gn:feature_code":"PPL",
    "gn:name":"Gaesan",
    "gn:population":0,
    "gn:timezone":"Asia/Seoul",
    "iso:country":"KR",
    "name:kor_x_preferred":[
        "\uac1c\uc0b0"
    ],
    "name:und_x_variant":[
        "Tangmoe-ri",
        "Kyesan-ni",
        "Kyesan",
        "Kaesan",
        "Gaesan"
    ],
    "wof:name":"Gaesan",
    "wof:placetype":"locality"
},
  "geometry": {"coordinates":[126.58826000000001,34.88212],"type":"Point"}
}