{
  "type": "Feature",
  "properties": {
    "gn:admin1_code":"17.0",
    "gn:asciiname":"Jeongdong",
    "gn:country_code":"KR",
    "gn:dem":54,
    "gn:feature_class":"P",
    "gn:feature_code":"PPL",
    "gn:name":"Jeongdong",
    "gn:population":0,
    "gn:timezone":"Asia/Seoul",
    "iso:country":"KR",
    "name:und_x_variant":[
        "\uc815\ub3d9",
        "Ch\u014fng-dong",
        "Jeongdong"
    ],
    "wof:name":"Jeongdong",
    "wof:placetype":"locality"
},
  "geometry": {"coordinates":[127.22476,36.46127],"type":"Point"}
}