{
  "type": "Feature",
  "properties": {
    "gn:admin1_code":"20.0",
    "gn:asciiname":"Waryong-dong",
    "gn:cc2":"KR",
    "gn:country_code":"KR",
    "gn:dem":230,
    "gn:feature_class":"P",
    "gn:feature_code":"PPL",
    "gn:name":"Waryong-dong",
    "gn:population":0,
    "gn:timezone":"Asia/Seoul",
    "iso:country":"KR",
    "name:und_x_variant":[
        "Waryong-ni",
        "Waryong-dong"
    ],
    "wof:name":"Waryong-dong",
    "wof:placetype":"locality"
},
  "geometry": {"coordinates":[128.09999999999999,34.96667],"type":"Point"}
}