{
  "type": "Feature",
  "properties": {
    "gn:admin1_code":"5.0",
    "gn:asciiname":"Sae-mal",
    "gn:country_code":"KR",
    "gn:dem":251,
    "gn:feature_class":"P",
    "gn:feature_code":"PPL",
    "gn:name":"Sae-mal",
    "gn:population":0,
    "gn:timezone":"Asia/Seoul",
    "iso:country":"KR",
    "name:kor_x_preferred":[
        "\uc0c8\ub9d0"
    ],
    "wof:name":"Sae-mal",
    "wof:placetype":"locality"
},
  "geometry": {"coordinates":[128.20330000000001,37.1109],"type":"Point"}
}