{
  "type": "Feature",
  "properties": {
    "gn:admin1_code":"14.0",
    "gn:asciiname":"Sangneungnae",
    "gn:country_code":"KR",
    "gn:dem":331,
    "gn:feature_class":"P",
    "gn:feature_code":"PPL",
    "gn:name":"Sangneungnae",
    "gn:population":0,
    "gn:timezone":"Asia/Seoul",
    "iso:country":"KR",
    "name:kor_x_preferred":[
        "\uc0c1\ub2a5\ub0b4"
    ],
    "wof:name":"Sangneungnae",
    "wof:placetype":"locality"
},
  "geometry": {"coordinates":[128.42317,36.71191],"type":"Point"}
}