{
  "type": "Feature",
  "properties": {
    "gn:admin1_code":"16.0",
    "gn:asciiname":"Sadong",
    "gn:country_code":"KR",
    "gn:dem":256,
    "gn:feature_class":"P",
    "gn:feature_code":"PPL",
    "gn:name":"Sadong",
    "gn:population":0,
    "gn:timezone":"Asia/Seoul",
    "iso:country":"KR",
    "name:kor_x_preferred":[
        "\uc0ac\ub3d9"
    ],
    "name:und_x_variant":[
        "Sadong-ni"
    ],
    "wof:name":"Sadong",
    "wof:placetype":"locality"
},
  "geometry": {"coordinates":[126.95166,34.81672],"type":"Point"}
}