{
  "type": "Feature",
  "properties": {
    "gn:admin1_code":"16.0",
    "gn:asciiname":"Hwapo",
    "gn:country_code":"KR",
    "gn:dem":14,
    "gn:feature_class":"P",
    "gn:feature_code":"PPL",
    "gn:name":"Hwapo",
    "gn:population":0,
    "gn:timezone":"Asia/Seoul",
    "iso:country":"KR",
    "name:kor_x_preferred":[
        "Hwap\u2019o"
    ],
    "name:kor_x_variant":[
        "\ud654\ud3ec"
    ],
    "wof:name":"Hwapo",
    "wof:placetype":"locality"
},
  "geometry": {"coordinates":[127.48472,34.84139],"type":"Point"}
}