{
  "type": "Feature",
  "properties": {
    "gn:admin1_code":"3.0",
    "gn:asciiname":"Hawangdung-ni",
    "gn:cc2":"KR",
    "gn:country_code":"KR",
    "gn:dem":132,
    "gn:feature_class":"P",
    "gn:feature_code":"PPL",
    "gn:name":"Hawangd\u016dng-ni",
    "gn:population":0,
    "gn:timezone":"Asia/Seoul",
    "iso:country":"KR",
    "name:und_x_variant":[
        "Hawangd\u016dng",
        "Hawangd\u016dng-ni"
    ],
    "wof:name":"Hawangdung-ni",
    "wof:placetype":"locality"
},
  "geometry": {"coordinates":[126.11750000000001,35.64333],"type":"Point"}
}