{
  "type": "Feature",
  "properties": {
    "gn:admin1_code":"5.0",
    "gn:asciiname":"Samgok",
    "gn:country_code":"KR",
    "gn:dem":199,
    "gn:feature_class":"P",
    "gn:feature_code":"PPL",
    "gn:name":"Samgok",
    "gn:population":0,
    "gn:timezone":"Asia/Seoul",
    "iso:country":"KR",
    "name:kor_x_preferred":[
        "\uc0bc\uace1"
    ],
    "wof:name":"Samgok",
    "wof:placetype":"locality"
},
  "geometry": {"coordinates":[128.27072999999999,37.07297],"type":"Point"}
}