{
  "type": "Feature",
  "properties": {
    "gn:admin1_code":"17.0",
    "gn:asciiname":"Seolhwari",
    "gn:country_code":"KR",
    "gn:dem":94,
    "gn:feature_class":"P",
    "gn:feature_code":"PPL",
    "gn:name":"Seolhwari",
    "gn:population":0,
    "gn:timezone":"Asia/Seoul",
    "iso:country":"KR",
    "name:kor_x_preferred":[
        "\uc124\ud654\ub9ac"
    ],
    "wof:name":"Seolhwari",
    "wof:placetype":"locality"
},
  "geometry": {"coordinates":[127.02289,36.73265],"type":"Point"}
}