{
  "type": "Feature",
  "properties": {
    "gn:admin1_code":"14.0",
    "gn:asciiname":"Dochigol",
    "gn:country_code":"KR",
    "gn:dem":176,
    "gn:feature_class":"P",
    "gn:feature_code":"PPL",
    "gn:name":"Dochigol",
    "gn:population":0,
    "gn:timezone":"Asia/Seoul",
    "iso:country":"KR",
    "name:kor_x_preferred":[
        "\ub3c4\uce58\uace8"
    ],
    "name:und_x_variant":[
        "Toji-dong",
        "Toch\u2019i-kol",
        "Toch\u2019i-dong",
        "Toch\u2019i-gol",
        "Dochigol"
    ],
    "wof:name":"Dochigol",
    "wof:placetype":"locality"
},
  "geometry": {"coordinates":[128.24475000000001,36.70515],"type":"Point"}
}