{
  "type": "Feature",
  "properties": {
    "gn:admin1_code":"6.0",
    "gn:asciiname":"Yokp'yong",
    "gn:country_code":"KR",
    "gn:dem":492,
    "gn:feature_class":"P",
    "gn:feature_code":"PPL",
    "gn:name":"Y\u014fkp\u2019y\u014fng",
    "gn:population":0,
    "gn:timezone":"Asia/Seoul",
    "iso:country":"KR",
    "name:kor_x_preferred":[
        "\uc5ed\ud3c9"
    ],
    "name:kor_x_variant":[
        "Y\u014fkp\u2019y\u014fng"
    ],
    "wof:name":"Yokp'yong",
    "wof:placetype":"locality"
},
  "geometry": {"coordinates":[128.84880000000001,37.4709],"type":"Point"}
}