{
  "type": "Feature",
  "properties": {
    "gn:admin1_code":"0.0",
    "gn:asciiname":"Hansil",
    "gn:cc2":"KR",
    "gn:country_code":"KR",
    "gn:dem":244,
    "gn:feature_class":"P",
    "gn:feature_code":"PPL",
    "gn:name":"Hansil",
    "gn:population":0,
    "gn:timezone":"Asia/Seoul",
    "iso:country":"KR",
    "name:und_x_variant":[
        "Taegong-ni",
        "Hansil"
    ],
    "wof:name":"Hansil",
    "wof:placetype":"locality"
},
  "geometry": {"coordinates":[127.23333,34.98333],"type":"Point"}
}