{
  "type": "Feature",
  "properties": {
    "gn:admin1_code":"17.0",
    "gn:asciiname":"Orak-tong",
    "gn:country_code":"KR",
    "gn:dem":-9999,
    "gn:feature_class":"P",
    "gn:feature_code":"PPL",
    "gn:name":"\u014erak-tong",
    "gn:population":0,
    "gn:timezone":"Asia/Seoul",
    "iso:country":"KR",
    "name:eng_x_preferred":[
        "Orak"
    ],
    "name:eng_x_variant":[
        "Orak-tong"
    ],
    "wof:name":"Orak",
    "wof:placetype":"locality"
},
  "geometry": {"coordinates":[126.38333,36.55],"type":"Point"}
}