{
  "type": "Feature",
  "properties": {
    "gn:admin1_code":"14.0",
    "gn:asciiname":"Ganmit",
    "gn:country_code":"KR",
    "gn:dem":133,
    "gn:feature_class":"P",
    "gn:feature_code":"PPL",
    "gn:name":"Ganmit",
    "gn:population":0,
    "gn:timezone":"Asia/Seoul",
    "iso:country":"KR",
    "name:kor_x_preferred":[
        "\uac13\ubc11"
    ],
    "wof:name":"Ganmit",
    "wof:placetype":"locality"
},
  "geometry": {"coordinates":[129.33711,35.72042000000001],"type":"Point"}
}