{
  "type": "Feature",
  "properties": {
    "gn:admin1_code":"6.0",
    "gn:asciiname":"Hanbak-kol",
    "gn:country_code":"KR",
    "gn:dem":782,
    "gn:feature_class":"P",
    "gn:feature_code":"PPL",
    "gn:name":"Hanbak-kol",
    "gn:population":0,
    "gn:timezone":"Asia/Seoul",
    "iso:country":"KR",
    "name:kor_x_preferred":[
        "\ud55c\ubc2d\uace8"
    ],
    "wof:name":"Hanbak-kol",
    "wof:placetype":"locality"
},
  "geometry": {"coordinates":[128.71610000000001,37.1894],"type":"Point"}
}