{
  "type": "Feature",
  "properties": {
    "gn:admin1_code":"3.0",
    "gn:asciiname":"Oeyul",
    "gn:country_code":"KR",
    "gn:dem":69,
    "gn:feature_class":"P",
    "gn:feature_code":"PPL",
    "gn:name":"Oeyul",
    "gn:population":0,
    "gn:timezone":"Asia/Seoul",
    "iso:country":"KR",
    "name:und_x_variant":[
        "\uc678\uc728",
        "Oeyul"
    ],
    "wof:name":"Oeyul",
    "wof:placetype":"locality"
},
  "geometry": {"coordinates":[127.18295000000001,35.97705],"type":"Point"}
}