{
  "type": "Feature",
  "properties": {
    "gn:admin1_code":"3.0",
    "gn:asciiname":"Eunseon",
    "gn:country_code":"KR",
    "gn:dem":124,
    "gn:feature_class":"P",
    "gn:feature_code":"PPL",
    "gn:name":"Eunseon",
    "gn:population":0,
    "gn:timezone":"Asia/Seoul",
    "iso:country":"KR",
    "name:kor_x_preferred":[
        "\uc740\uc120"
    ],
    "wof:name":"Eunseon",
    "wof:placetype":"locality"
},
  "geometry": {"coordinates":[126.68657,35.3658],"type":"Point"}
}