{
  "type": "Feature",
  "properties": {
    "gn:admin1_code":"3.0",
    "gn:asciiname":"Twissom",
    "gn:country_code":"KR",
    "gn:dem":169,
    "gn:feature_class":"P",
    "gn:feature_code":"PPL",
    "gn:name":"Twiss\u014fm",
    "gn:population":0,
    "gn:timezone":"Asia/Seoul",
    "iso:country":"KR",
    "name:und_x_variant":[
        "\ub4b7\uc12c",
        "Twiss\u014fm"
    ],
    "wof:name":"Twissom",
    "wof:placetype":"locality"
},
  "geometry": {"coordinates":[127.6443,36.0314],"type":"Point"}
}