{
  "type": "Feature",
  "properties": {
    "iso:country":"KR",
    "name:eng_x_preferred":[
        "Madu 1(il)-dong"
    ],
    "name:kor_x_preferred":[
        "\ub9c8\ub4501\ub3d9"
    ],
    "qs:name":"\ub9c8\ub4501\ub3d9",
    "qs:name_adm0":"\ud55c\uad6d",
    "qs:name_adm1":"\uacbd\uae30\ub3c4",
    "qs:photos":52,
    "qs:photos_1k":11,
    "qs:photos_9k":1,
    "qs:photos_9r":2,
    "qs:photos_all":52,
    "qs:photos_sr":2,
    "qs:placetype":"Suburb",
    "qs:pop_sr":"0",
    "wof:name":"Madu 1(il)-dong",
    "wof:placetype":"neighbourhood"
},
  "geometry": {"coordinates":[126.77472,37.64778],"type":"Point"}
}