{
  "type": "Feature",
  "properties": {
    "gn:admin1_code":"19.0",
    "gn:asciiname":"Hwasan",
    "gn:country_code":"KR",
    "gn:dem":122,
    "gn:feature_class":"P",
    "gn:feature_code":"PPL",
    "gn:name":"Hwasan",
    "gn:population":0,
    "gn:timezone":"Asia/Seoul",
    "iso:country":"KR",
    "name:und_x_variant":[
        "\ud654\uc0b0",
        "Hwasan"
    ],
    "wof:name":"Hwasan",
    "wof:placetype":"locality"
},
  "geometry": {"coordinates":[127.29325,36.34966],"type":"Point"}
}