{
  "type": "Feature",
  "properties": {
    "gn:admin1_code":"6.0",
    "gn:asciiname":"Donggumal",
    "gn:country_code":"KR",
    "gn:dem":151,
    "gn:feature_class":"P",
    "gn:feature_code":"PPL",
    "gn:name":"Donggumal",
    "gn:population":0,
    "gn:timezone":"Asia/Seoul",
    "iso:country":"KR",
    "name:kor_x_preferred":[
        "\ub3d9\uad6c\ub9d0"
    ],
    "name:und_x_variant":[
        "Tonggu-mal",
        "Donggumal"
    ],
    "wof:name":"Donggumal",
    "wof:placetype":"locality"
},
  "geometry": {"coordinates":[128.71714,37.9247],"type":"Point"}
}