{
  "type": "Feature",
  "properties": {
    "gn:admin1_code":"20.0",
    "gn:asciiname":"Pinggisil",
    "gn:country_code":"KR",
    "gn:dem":499,
    "gn:feature_class":"P",
    "gn:feature_code":"PPL",
    "gn:name":"Pinggisil",
    "gn:population":0,
    "gn:timezone":"Asia/Seoul",
    "iso:country":"KR",
    "name:und_x_variant":[
        "Pinggishil",
        "\ube59\uae30\uc2e4",
        "Pinggisil"
    ],
    "wof:name":"Pinggisil",
    "wof:placetype":"locality"
},
  "geometry": {"coordinates":[127.77459,35.81079000000001],"type":"Point"}
}