{
  "type": "Feature",
  "properties": {
    "gn:admin1_code":"14.0",
    "gn:asciiname":"Pakchom",
    "gn:country_code":"KR",
    "gn:dem":436,
    "gn:feature_class":"P",
    "gn:feature_code":"PPL",
    "gn:name":"Pakch\u014fm",
    "gn:population":0,
    "gn:timezone":"Asia/Seoul",
    "iso:country":"KR",
    "name:und_x_variant":[
        "\ubc15\uc810",
        "Pakch\u014fm"
    ],
    "wof:name":"Pakchom",
    "wof:placetype":"locality"
},
  "geometry": {"coordinates":[129.2201,36.5314],"type":"Point"}
}