{
  "type": "Feature",
  "properties": {
    "gn:admin1_code":"13.0",
    "gn:asciiname":"Harang-mal",
    "gn:country_code":"KR",
    "gn:dem":67,
    "gn:feature_class":"P",
    "gn:feature_code":"PPL",
    "gn:name":"Harang-mal",
    "gn:population":0,
    "gn:timezone":"Asia/Seoul",
    "iso:country":"KR",
    "name:und_x_variant":[
        "\ud558\ub77d\ub9d0",
        "Harak-mal",
        "Harang-mal"
    ],
    "wof:name":"Harang-mal",
    "wof:placetype":"locality"
},
  "geometry": {"coordinates":[127.48361,37.285],"type":"Point"}
}