{
  "type": "Feature",
  "properties": {
    "gn:admin1_code":"5.0",
    "gn:asciiname":"Wa-ch'on",
    "gn:country_code":"KR",
    "gn:dem":83,
    "gn:feature_class":"P",
    "gn:feature_code":"PPL",
    "gn:name":"Wa-ch\u2019on",
    "gn:population":0,
    "gn:timezone":"Asia/Seoul",
    "iso:country":"KR",
    "name:und_x_variant":[
        "\uc640\ucd0c",
        "Wa-ch\u2019on"
    ],
    "wof:name":"Wa-ch'on",
    "wof:placetype":"locality"
},
  "geometry": {"coordinates":[127.6747,36.3568],"type":"Point"}
}