{
  "type": "Feature",
  "properties": {
    "gn:admin1_code":"14.0",
    "gn:asciiname":"Sarae",
    "gn:country_code":"KR",
    "gn:dem":199,
    "gn:feature_class":"P",
    "gn:feature_code":"PPL",
    "gn:name":"Sarae",
    "gn:population":0,
    "gn:timezone":"Asia/Seoul",
    "iso:country":"KR",
    "name:und_x_variant":[
        "\uc0ac\ub798",
        "Sarae"
    ],
    "wof:name":"Sarae",
    "wof:placetype":"locality"
},
  "geometry": {"coordinates":[129.06100000000001,36.609],"type":"Point"}
}