{
  "type": "Feature",
  "properties": {
    "gn:admin1_code":"13.0",
    "gn:asciiname":"Goeeum",
    "gn:country_code":"KR",
    "gn:dem":98,
    "gn:feature_class":"P",
    "gn:feature_code":"PPL",
    "gn:name":"Goeeum",
    "gn:population":0,
    "gn:timezone":"Asia/Seoul",
    "iso:country":"KR",
    "name:und_x_variant":[
        "\uad34\uc74c",
        "Koe\u016dm",
        "Goeeum"
    ],
    "wof:name":"Goeeum",
    "wof:placetype":"locality"
},
  "geometry": {"coordinates":[126.92807000000001,37.80794],"type":"Point"}
}