{
  "type": "Feature",
  "properties": {
    "gn:admin1_code":"5.0",
    "gn:asciiname":"Umji-mal",
    "gn:country_code":"KR",
    "gn:dem":74,
    "gn:feature_class":"P",
    "gn:feature_code":"PPL",
    "gn:name":"\u016cmji-mal",
    "gn:population":0,
    "gn:timezone":"Asia/Seoul",
    "iso:country":"KR",
    "name:kor_x_preferred":[
        "\uc74c\uc9c0\ub9d0"
    ],
    "name:kor_x_variant":[
        "\u016cmji-mal"
    ],
    "wof:name":"Umji-mal",
    "wof:placetype":"locality"
},
  "geometry": {"coordinates":[127.8237,37.12],"type":"Point"}
}