{
  "type": "Feature",
  "properties": {
    "gn:admin1_code":"14.0",
    "gn:asciiname":"Kwanjae",
    "gn:cc2":"KR",
    "gn:country_code":"KR",
    "gn:dem":307,
    "gn:feature_class":"P",
    "gn:feature_code":"PPL",
    "gn:name":"Kwanjae",
    "gn:population":0,
    "gn:timezone":"Asia/Seoul",
    "iso:country":"KR",
    "name:und_x_variant":[
        "Kwangjae",
        "Kwanje",
        "Kwanjae"
    ],
    "wof:name":"Kwanjae",
    "wof:placetype":"locality"
},
  "geometry": {"coordinates":[127.96666999999999,36.38333],"type":"Point"}
}