{
  "type": "Feature",
  "properties": {
    "gn:admin1_code":"20.0",
    "gn:asciiname":"Chigye-dong",
    "gn:country_code":"KR",
    "gn:dem":79,
    "gn:feature_class":"P",
    "gn:feature_code":"PPL",
    "gn:name":"Chigye-dong",
    "gn:population":0,
    "gn:timezone":"Asia/Seoul",
    "iso:country":"KR",
    "name:und_x_variant":[
        "\uc9c0\uacc4\ub3d9",
        "Chigye-dong"
    ],
    "wof:name":"Chigye-dong",
    "wof:placetype":"locality"
},
  "geometry": {"coordinates":[128.10013999999998,35.57559000000001],"type":"Point"}
}