{
  "type": "Feature",
  "properties": {
    "gn:admin1_code":"13.0",
    "gn:admin2_code":"Yongin-si",
    "gn:asciiname":"Kodang-ni",
    "gn:country_code":"KR",
    "gn:dem":113,
    "gn:feature_class":"P",
    "gn:feature_code":"PPLL",
    "gn:name":"Kodang-ni",
    "gn:population":0,
    "gn:timezone":"Asia/Seoul",
    "iso:country":"KR",
    "name:kor_x_preferred":[
        "\uace0\ub2f9\ub9ac"
    ],
    "name:und_x_variant":[
        "Godang-ri"
    ],
    "wof:name":"Kodang-ni",
    "wof:placetype":"locality"
},
  "geometry": {"coordinates":[127.30833,37.17083],"type":"Point"}
}