{
  "type": "Feature",
  "properties": {
    "gn:admin1_code":"5.0",
    "gn:asciiname":"Saeboro",
    "gn:country_code":"KR",
    "gn:dem":141,
    "gn:feature_class":"P",
    "gn:feature_code":"PPL",
    "gn:name":"Saeboro",
    "gn:population":0,
    "gn:timezone":"Asia/Seoul",
    "iso:country":"KR",
    "name:und_x_variant":[
        "\uc0c8\ubcf4\ub85c",
        "Saeboro"
    ],
    "wof:name":"Saeboro",
    "wof:placetype":"locality"
},
  "geometry": {"coordinates":[127.59910000000001,36.2822],"type":"Point"}
}