{
  "type": "Feature",
  "properties": {
    "gn:admin1_code":"14.0",
    "gn:asciiname":"Orin",
    "gn:cc2":"KR",
    "gn:country_code":"KR",
    "gn:dem":177,
    "gn:feature_class":"P",
    "gn:feature_code":"PPL",
    "gn:name":"\u014erin",
    "gn:population":0,
    "gn:timezone":"Asia/Seoul",
    "iso:country":"KR",
    "name:ceb_x_preferred":[
        "Orin"
    ],
    "name:fra_x_preferred":[
        "Orin"
    ],
    "name:srp_x_preferred":[
        "\u041e\u0440\u0438\u043d"
    ],
    "name:swe_x_preferred":[
        "Orin"
    ],
    "name:und_x_variant":[
        "\u014erin-dong",
        "\u014erin"
    ],
    "wof:name":"Orin",
    "wof:placetype":"locality"
},
  "geometry": {"coordinates":[128.78083000000001,35.58778],"type":"Point"}
}