{
  "type": "Feature",
  "properties": {
    "gn:admin1_code":"11.0",
    "gn:asciiname":"Chae-mal",
    "gn:country_code":"KR",
    "gn:dem":107,
    "gn:feature_class":"P",
    "gn:feature_code":"PPL",
    "gn:name":"Chae-mal",
    "gn:population":0,
    "gn:timezone":"Asia/Seoul",
    "iso:country":"KR",
    "name:und_x_variant":[
        "\uc7ac\ub9d0",
        "Chae-mal"
    ],
    "wof:name":"Chae-mal",
    "wof:placetype":"locality"
},
  "geometry": {"coordinates":[126.934,37.6396],"type":"Point"}
}