{
  "type": "Feature",
  "properties": {
    "gn:admin1_code":"14.0",
    "gn:asciiname":"Miruktang",
    "gn:country_code":"KR",
    "gn:dem":227,
    "gn:feature_class":"P",
    "gn:feature_code":"PPL",
    "gn:name":"Mir\u016dktang",
    "gn:population":0,
    "gn:timezone":"Asia/Seoul",
    "iso:country":"KR",
    "name:und_x_variant":[
        "\ubbf8\ub975\ub2f9",
        "Mir\u016dktang"
    ],
    "wof:name":"Miruktang",
    "wof:placetype":"locality"
},
  "geometry": {"coordinates":[128.0659,36.2396],"type":"Point"}
}