{
  "type": "Feature",
  "properties": {
    "gn:admin1_code":"16.0",
    "gn:asciiname":"Ch'ung-ni",
    "gn:country_code":"KR",
    "gn:dem":23,
    "gn:feature_class":"P",
    "gn:feature_code":"PPL",
    "gn:name":"Ch\u2019ung-ni",
    "gn:population":0,
    "gn:timezone":"Asia/Seoul",
    "iso:country":"KR",
    "name:kor_x_preferred":[
        "\ucda9\ub9ac"
    ],
    "name:kor_x_variant":[
        "Ch\u2019ung-ni"
    ],
    "name:und_x_variant":[
        "Ch\u016b-ri"
    ],
    "wof:name":"Ch'ung-ni",
    "wof:placetype":"locality"
},
  "geometry": {"coordinates":[126.59528,34.51833],"type":"Point"}
}