{
  "type": "Feature",
  "properties": {
    "gn:admin1_code":"5.0",
    "gn:asciiname":"Galgasil",
    "gn:country_code":"KR",
    "gn:dem":109,
    "gn:feature_class":"P",
    "gn:feature_code":"PPL",
    "gn:name":"Galgasil",
    "gn:population":0,
    "gn:timezone":"Asia/Seoul",
    "iso:country":"KR",
    "name:kor_x_preferred":[
        "\uac08\uac00\uc2e4"
    ],
    "wof:name":"Galgasil",
    "wof:placetype":"locality"
},
  "geometry": {"coordinates":[127.82878999999998,36.96261],"type":"Point"}
}