{
  "type": "Feature",
  "properties": {
    "gn:admin1_code":"17.0",
    "gn:asciiname":"Sagusi",
    "gn:country_code":"KR",
    "gn:dem":16,
    "gn:feature_class":"P",
    "gn:feature_code":"PPL",
    "gn:name":"Sagusi",
    "gn:population":0,
    "gn:timezone":"Asia/Seoul",
    "iso:country":"KR",
    "name:und_x_variant":[
        "\uc0ac\uad6c\uc2dc",
        "Sagusi"
    ],
    "wof:name":"Sagusi",
    "wof:placetype":"locality"
},
  "geometry": {"coordinates":[126.5029,36.5403],"type":"Point"}
}