{
  "type": "Feature",
  "properties": {
    "gn:admin1_code":"14.0",
    "gn:asciiname":"Ihyon",
    "gn:country_code":"KR",
    "gn:dem":392,
    "gn:feature_class":"P",
    "gn:feature_code":"PPL",
    "gn:name":"Ihy\u014fn",
    "gn:population":0,
    "gn:timezone":"Asia/Seoul",
    "iso:country":"KR",
    "name:und_x_variant":[
        "Ihy\u014fn-dong",
        "Ihy\u014fn"
    ],
    "wof:name":"Ihyon",
    "wof:placetype":"locality"
},
  "geometry": {"coordinates":[129.17619999999999,36.298],"type":"Point"}
}