{
  "type": "Feature",
  "properties": {
    "gn:admin1_code":"14.0",
    "gn:asciiname":"Bajigol",
    "gn:country_code":"KR",
    "gn:dem":311,
    "gn:feature_class":"P",
    "gn:feature_code":"PPL",
    "gn:name":"Bajigol",
    "gn:population":0,
    "gn:timezone":"Asia/Seoul",
    "iso:country":"KR",
    "name:kor_x_preferred":[
        "\ubc14\uc9c0\uace8"
    ],
    "wof:name":"Bajigol",
    "wof:placetype":"locality"
},
  "geometry": {"coordinates":[127.99312,36.64191],"type":"Point"}
}