{
  "type": "Feature",
  "properties": {
    "gn:admin1_code":"11.0",
    "gn:asciiname":"Kirumil-tong",
    "gn:country_code":"KR",
    "gn:dem":44,
    "gn:feature_class":"P",
    "gn:feature_code":"PPL",
    "gn:name":"Kir\u016dmil-tong",
    "gn:population":0,
    "gn:timezone":"Asia/Seoul",
    "iso:country":"KR",
    "name:eng_x_preferred":[
        "Kirumil"
    ],
    "name:eng_x_variant":[
        "Kirumil-tong"
    ],
    "name:und_x_variant":[
        "\uae38\uc74c1\ub3d9",
        "Kir\u016dmil-tong"
    ],
    "wof:name":"Kirumil",
    "wof:placetype":"locality"
},
  "geometry": {"coordinates":[127.02137,37.60488],"type":"Point"}
}