{
  "type": "Feature",
  "properties": {
    "gn:admin1_code":"14.0",
    "gn:asciiname":"Guryongpan",
    "gn:country_code":"KR",
    "gn:dem":108,
    "gn:feature_class":"P",
    "gn:feature_code":"PPL",
    "gn:name":"Guryongpan",
    "gn:population":0,
    "gn:timezone":"Asia/Seoul",
    "iso:country":"KR",
    "name:kor_x_preferred":[
        "\uad6c\ub8e1\ud310"
    ],
    "wof:name":"Guryongpan",
    "wof:placetype":"locality"
},
  "geometry": {"coordinates":[128.26660000000001,36.6544],"type":"Point"}
}