{
  "type": "Feature",
  "properties": {
    "gn:admin1_code":"13.0",
    "gn:asciiname":"Pandari",
    "gn:country_code":"KR",
    "gn:dem":52,
    "gn:feature_class":"P",
    "gn:feature_code":"PPL",
    "gn:name":"Pandari",
    "gn:population":0,
    "gn:timezone":"Asia/Seoul",
    "iso:country":"KR",
    "name:und_x_variant":[
        "\ubc18\ub2ec\uc774",
        "Bandari",
        "Pandari"
    ],
    "wof:name":"Pandari",
    "wof:placetype":"locality"
},
  "geometry": {"coordinates":[127.06833,37.235],"type":"Point"}
}