{
  "type": "Feature",
  "properties": {
    "gn:admin1_code":"11.0",
    "gn:asciiname":"Mugil-tong",
    "gn:country_code":"KR",
    "gn:dem":72,
    "gn:feature_class":"P",
    "gn:feature_code":"PPL",
    "gn:name":"Mugil-tong",
    "gn:population":0,
    "gn:timezone":"Asia/Seoul",
    "iso:country":"KR",
    "name:und_x_variant":[
        "\ubb351\ub3d9",
        "Mugil-tong"
    ],
    "wof:name":"Mugil-tong",
    "wof:placetype":"locality"
},
  "geometry": {"coordinates":[127.08316000000001,37.61281],"type":"Point"}
}