{
  "type": "Feature",
  "properties": {
    "gn:admin1_code":"14.0",
    "gn:asciiname":"Gyeongam",
    "gn:country_code":"KR",
    "gn:dem":94,
    "gn:feature_class":"P",
    "gn:feature_code":"PPL",
    "gn:name":"Gyeongam",
    "gn:population":0,
    "gn:timezone":"Asia/Seoul",
    "iso:country":"KR",
    "name:kor_x_preferred":[
        "\uacbd\uc554"
    ],
    "wof:name":"Gyeongam",
    "wof:placetype":"locality"
},
  "geometry": {"coordinates":[128.30144000000001,36.63445],"type":"Point"}
}