{
  "type": "Feature",
  "properties": {
    "gn:admin1_code":"20.0",
    "gn:asciiname":"Tongmae",
    "gn:country_code":"KR",
    "gn:dem":263,
    "gn:feature_class":"P",
    "gn:feature_code":"PPL",
    "gn:name":"Tongmae",
    "gn:population":0,
    "gn:timezone":"Asia/Seoul",
    "iso:country":"KR",
    "name:und_x_variant":[
        "\ub3c5\ub9e4",
        "Tongmae"
    ],
    "wof:name":"Tongmae",
    "wof:placetype":"locality"
},
  "geometry": {"coordinates":[127.79776,35.64743],"type":"Point"}
}