{
  "type": "Feature",
  "properties": {
    "gn:admin1_code":"13.0",
    "gn:asciiname":"Hwaryong",
    "gn:country_code":"KR",
    "gn:dem":9,
    "gn:feature_class":"P",
    "gn:feature_code":"PPL",
    "gn:name":"Hwary\u014fng",
    "gn:population":0,
    "gn:timezone":"Asia/Seoul",
    "iso:country":"KR",
    "name:kor_x_preferred":[
        "\ud654\ub839"
    ],
    "name:kor_x_variant":[
        "Hwary\u014fng"
    ],
    "wof:name":"Hwaryong",
    "wof:placetype":"locality"
},
  "geometry": {"coordinates":[126.67749999999999,37.20333],"type":"Point"}
}