{
  "type": "Feature",
  "properties": {
    "gn:admin1_code":"13.0",
    "gn:asciiname":"Karhyon",
    "gn:country_code":"KR",
    "gn:dem":481,
    "gn:feature_class":"P",
    "gn:feature_code":"PPL",
    "gn:name":"Karhy\u014fn",
    "gn:population":0,
    "gn:timezone":"Asia/Seoul",
    "iso:country":"KR",
    "name:kor_x_preferred":[
        "\uac08\ud604"
    ],
    "name:kor_x_variant":[
        "Karhy\u014fn"
    ],
    "name:und_x_variant":[
        "Kalhy\u014fn"
    ],
    "wof:name":"Karhyon",
    "wof:placetype":"locality"
},
  "geometry": {"coordinates":[127.53700000000001,37.5824],"type":"Point"}
}