{
  "type": "Feature",
  "properties": {
    "gn:admin1_code":"20.0",
    "gn:asciiname":"Sangju",
    "gn:country_code":"KR",
    "gn:dem":16,
    "gn:feature_class":"P",
    "gn:feature_code":"PPLA3",
    "gn:name":"Sangju",
    "gn:population":0,
    "gn:timezone":"Asia/Seoul",
    "iso:country":"KR",
    "name:kor_x_preferred":[
        "\uc0c1\uc8fc"
    ],
    "name:und_x_variant":[
        "Sh\u014dsh\u016b-ri",
        "Sangju-ri",
        "Sanju-ri",
        "Sy\u014ds\u016bri",
        "Sangju"
    ],
    "wof:name":"Sangju",
    "wof:placetype":"locality"
},
  "geometry": {"coordinates":[127.98521,34.72423],"type":"Point"}
}