{
  "type": "Feature",
  "properties": {
    "gn:admin1_code":"20.0",
    "gn:asciiname":"Sangju",
    "gn:country_code":"KR",
    "gn:dem":16,
    "gn:feature_class":"P",
    "gn:feature_code":"PPLA3",
    "gn:name":"Sangju",
    "gn:population":0,
    "gn:timezone":"Asia/Seoul",
    "iso:country":"KR",
    "name:ara_x_preferred":[
        "\u0633\u0627\u0646\u063a\u062c\u0648"
    ],
    "name:ceb_x_preferred":[
        "Sangju"
    ],
    "name:ces_x_preferred":[
        "Sangd\u017eu"
    ],
    "name:deu_x_preferred":[
        "Sangju"
    ],
    "name:epo_x_preferred":[
        "San\u011du"
    ],
    "name:fas_x_preferred":[
        "\u0633\u0627\u0646\u06af\u0698\u0648"
    ],
    "name:fra_x_preferred":[
        "Sangju"
    ],
    "name:ind_x_preferred":[
        "Sangju"
    ],
    "name:ita_x_preferred":[
        "Sangju"
    ],
    "name:jpn_x_preferred":[
        "\u5c1a\u5dde\u5e02"
    ],
    "name:kor_x_preferred":[
        "\uc0c1\uc8fc"
    ],
    "name:kor_x_variant":[
        "\uc0c1\uc8fc\uc2dc"
    ],
    "name:lmo_x_preferred":[
        "Sangju"
    ],
    "name:msa_x_preferred":[
        "Sangju"
    ],
    "name:nld_x_preferred":[
        "Sangju"
    ],
    "name:nor_x_preferred":[
        "Sangju"
    ],
    "name:pol_x_preferred":[
        "Sangju"
    ],
    "name:rus_x_preferred":[
        "\u0421\u0430\u043d\u0434\u0436\u0443"
    ],
    "name:spa_x_preferred":[
        "Sangju"
    ],
    "name:swe_x_preferred":[
        "Sangju"
    ],
    "name:tgl_x_preferred":[
        "Sangju"
    ],
    "name:tur_x_preferred":[
        "Sangju"
    ],
    "name:und_x_variant":[
        "Sh\u014dsh\u016b-ri",
        "Sangju-ri",
        "Sanju-ri",
        "Sy\u014ds\u016bri"
    ],
    "name:urd_x_preferred":[
        "\u0633\u0627\u0646\u06af\u062c\u0648"
    ],
    "name:vie_x_preferred":[
        "Sangju"
    ],
    "name:war_x_preferred":[
        "Sangju"
    ],
    "name:zho_x_preferred":[
        "\u5c1a\u5dde\u5e02"
    ],
    "wof:name":"Sangju",
    "wof:placetype":"locality"
},
  "geometry": {"coordinates":[127.98521,34.72423],"type":"Point"}
}