{
  "type": "Feature",
  "properties": {
    "gn:admin1_code":"17.0",
    "gn:asciiname":"Neuratchi",
    "gn:country_code":"KR",
    "gn:dem":27,
    "gn:feature_class":"P",
    "gn:feature_code":"PPL",
    "gn:name":"Neuratchi",
    "gn:population":0,
    "gn:timezone":"Asia/Seoul",
    "iso:country":"KR",
    "name:und_x_variant":[
        "\ub298\uc557\uce58",
        "N\u016dratch\u2019i",
        "Neuratchi"
    ],
    "wof:name":"Neuratchi",
    "wof:placetype":"locality"
},
  "geometry": {"coordinates":[127.1643,36.4553],"type":"Point"}
}