{
  "type": "Feature",
  "properties": {
    "gn:admin1_code":"6.0",
    "gn:asciiname":"Garaegolli",
    "gn:country_code":"KR",
    "gn:dem":302,
    "gn:feature_class":"P",
    "gn:feature_code":"PPL",
    "gn:name":"Garaegolli",
    "gn:population":0,
    "gn:timezone":"Asia/Seoul",
    "iso:country":"KR",
    "name:kor_x_preferred":[
        "\uac00\ub798\uace8\ub9ac"
    ],
    "wof:name":"Garaegolli",
    "wof:placetype":"locality"
},
  "geometry": {"coordinates":[127.54624,38.26673],"type":"Point"}
}