{
  "type": "Feature",
  "properties": {
    "gn:admin1_code":"11.0",
    "gn:asciiname":"Samson-dong",
    "gn:country_code":"KR",
    "gn:dem":57,
    "gn:feature_class":"P",
    "gn:feature_code":"PPL",
    "gn:name":"Sams\u014fn-dong",
    "gn:population":0,
    "gn:timezone":"Asia/Seoul",
    "iso:country":"KR",
    "name:und_x_variant":[
        "\uc0bc\uc120\ub3d9",
        "Sams\u014fn-dong"
    ],
    "wof:name":"Samson-dong",
    "wof:placetype":"locality"
},
  "geometry": {"coordinates":[127.01139999999999,37.5882],"type":"Point"}
}