{
  "type": "Feature",
  "properties": {
    "gn:admin1_code":"17.0",
    "gn:asciiname":"Hamjeokgol",
    "gn:country_code":"KR",
    "gn:dem":70,
    "gn:feature_class":"P",
    "gn:feature_code":"PPL",
    "gn:name":"Hamjeokgol",
    "gn:population":0,
    "gn:timezone":"Asia/Seoul",
    "iso:country":"KR",
    "name:kor_x_preferred":[
        "\ud568\uc801\uace8"
    ],
    "wof:name":"Hamjeokgol",
    "wof:placetype":"locality"
},
  "geometry": {"coordinates":[127.16262,36.28924],"type":"Point"}
}