{
  "type": "Feature",
  "properties": {
    "gn:admin1_code":"19.0",
    "gn:asciiname":"Hyanggyomal",
    "gn:country_code":"KR",
    "gn:dem":71,
    "gn:feature_class":"P",
    "gn:feature_code":"PPL",
    "gn:name":"Hyanggyomal",
    "gn:population":0,
    "gn:timezone":"Asia/Seoul",
    "iso:country":"KR",
    "name:kor_x_preferred":[
        "\ud5a5\uad50\ub9d0"
    ],
    "wof:name":"Hyanggyomal",
    "wof:placetype":"locality"
},
  "geometry": {"coordinates":[127.3168,36.30435],"type":"Point"}
}