{
  "type": "Feature",
  "properties": {
    "gn:admin1_code":"6.0",
    "gn:asciiname":"Pingsu-ch'on",
    "gn:country_code":"KR",
    "gn:dem":433,
    "gn:feature_class":"P",
    "gn:feature_code":"PPL",
    "gn:name":"Pingsu-ch\u2019on",
    "gn:population":0,
    "gn:timezone":"Asia/Seoul",
    "iso:country":"KR",
    "name:und_x_variant":[
        "\ube59\uc218\ucd0c",
        "Pingsu-ch\u2019on"
    ],
    "wof:name":"Pingsu-ch'on",
    "wof:placetype":"locality"
},
  "geometry": {"coordinates":[129.1148,37.1581],"type":"Point"}
}