{
  "type": "Feature",
  "properties": {
    "gn:admin1_code":"13.0",
    "gn:asciiname":"Hogyeil-tong",
    "gn:country_code":"KR",
    "gn:dem":49,
    "gn:feature_class":"P",
    "gn:feature_code":"PPL",
    "gn:name":"Hogyeil-tong",
    "gn:population":0,
    "gn:timezone":"Asia/Seoul",
    "iso:country":"KR",
    "name:und_x_variant":[
        "\ud638\uacc41\ub3d9",
        "Hogyeil-dong",
        "Hogyeil-tong"
    ],
    "wof:name":"Hogyeil-tong",
    "wof:placetype":"locality"
},
  "geometry": {"coordinates":[126.95444000000001,37.37278],"type":"Point"}
}