{
  "type": "Feature",
  "properties": {
    "gn:admin1_code":"14.0",
    "gn:asciiname":"Geumgok-ri",
    "gn:country_code":"KR",
    "gn:dem":159,
    "gn:feature_class":"P",
    "gn:feature_code":"PPL",
    "gn:name":"Geumgok-ri",
    "gn:population":0,
    "gn:timezone":"Asia/Seoul",
    "iso:country":"KR",
    "name:kor_x_preferred":[
        "\uae08\uace1\ub9ac"
    ],
    "name:und_x_variant":[
        "K\u016dmgong-ni",
        "K\u016dmgok",
        "Geumgok-ri"
    ],
    "wof:name":"Geumgok-ri",
    "wof:placetype":"locality"
},
  "geometry": {"coordinates":[128.20743000000002,36.52609],"type":"Point"}
}