{
  "type": "Feature",
  "properties": {
    "gn:admin1_code":"6.0",
    "gn:asciiname":"Sangyo-gol",
    "gn:country_code":"KR",
    "gn:dem":451,
    "gn:feature_class":"P",
    "gn:feature_code":"PPL",
    "gn:name":"Sangy\u014f-gol",
    "gn:population":0,
    "gn:timezone":"Asia/Seoul",
    "iso:country":"KR",
    "name:kor_x_preferred":[
        "\uc0c1\uc5ec\uace8"
    ],
    "name:kor_x_variant":[
        "Sangy\u014f-gol"
    ],
    "wof:name":"Sangyo-gol",
    "wof:placetype":"locality"
},
  "geometry": {"coordinates":[128.47829999999999,37.3573],"type":"Point"}
}