{
  "type": "Feature",
  "properties": {
    "gn:admin1_code":"15.0",
    "gn:asciiname":"Yongdugok",
    "gn:country_code":"KR",
    "gn:dem":38,
    "gn:feature_class":"P",
    "gn:feature_code":"PPL",
    "gn:name":"Yongdugok",
    "gn:population":0,
    "gn:timezone":"Asia/Seoul",
    "iso:country":"KR",
    "name:kor_x_preferred":[
        "\uc6a9\ub450\uace1"
    ],
    "wof:name":"Yongdugok",
    "wof:placetype":"locality"
},
  "geometry": {"coordinates":[128.42500000000001,35.86714],"type":"Point"}
}