{
  "type": "Feature",
  "properties": {
    "gn:admin1_code":"14.0",
    "gn:asciiname":"Anbuljeong",
    "gn:country_code":"KR",
    "gn:dem":179,
    "gn:feature_class":"P",
    "gn:feature_code":"PPL",
    "gn:name":"Anbuljeong",
    "gn:population":0,
    "gn:timezone":"Asia/Seoul",
    "iso:country":"KR",
    "name:kor_x_preferred":[
        "\uc548\ubd88\uc815"
    ],
    "wof:name":"Anbuljeong",
    "wof:placetype":"locality"
},
  "geometry": {"coordinates":[128.12991,36.62779000000001],"type":"Point"}
}