{
  "type": "Feature",
  "properties": {
    "gn:admin1_code":"14.0",
    "gn:asciiname":"Ki-dong",
    "gn:country_code":"KR",
    "gn:dem":260,
    "gn:feature_class":"P",
    "gn:feature_code":"PPL",
    "gn:name":"Ki-dong",
    "gn:population":0,
    "gn:timezone":"Asia/Seoul",
    "iso:country":"KR",
    "name:und_x_variant":[
        "\uae30\ub3d9",
        "Ki-dong"
    ],
    "wof:name":"Ki-dong",
    "wof:placetype":"locality"
},
  "geometry": {"coordinates":[127.96474000000001,35.90944000000001],"type":"Point"}
}