{
  "type": "Feature",
  "properties": {
    "gn:admin1_code":"16.0",
    "gn:asciiname":"Cheonjeon",
    "gn:country_code":"KR",
    "gn:dem":29,
    "gn:feature_class":"P",
    "gn:feature_code":"PPL",
    "gn:name":"Cheonjeon",
    "gn:population":0,
    "gn:timezone":"Asia/Seoul",
    "iso:country":"KR",
    "name:kor_x_preferred":[
        "Ch\u2019\u014fngj\u014fn"
    ],
    "name:kor_x_variant":[
        "\ucc9c\uc804",
        "\uccad\uc804"
    ],
    "name:und_x_variant":[
        "Kittae-bong"
    ],
    "wof:name":"Cheonjeon",
    "wof:placetype":"locality"
},
  "geometry": {"coordinates":[126.92100000000001,34.62273],"type":"Point"}
}