{
  "type": "Feature",
  "properties": {
    "gn:admin1_code":"16.0",
    "gn:asciiname":"Gaennadeul",
    "gn:country_code":"KR",
    "gn:dem":17,
    "gn:feature_class":"P",
    "gn:feature_code":"PPL",
    "gn:name":"Gaennadeul",
    "gn:population":0,
    "gn:timezone":"Asia/Seoul",
    "iso:country":"KR",
    "name:kor_x_preferred":[
        "Kaennad\u016dl"
    ],
    "name:kor_x_variant":[
        "\uac2f\ub098\ub4e4"
    ],
    "wof:name":"Gaennadeul",
    "wof:placetype":"locality"
},
  "geometry": {"coordinates":[126.91167,34.46583],"type":"Point"}
}