{
  "type": "Feature",
  "properties": {
    "gn:admin1_code":"6.0",
    "gn:asciiname":"Tonghwa-gol",
    "gn:country_code":"KR",
    "gn:dem":128,
    "gn:feature_class":"P",
    "gn:feature_code":"PPL",
    "gn:name":"Tonghwa-gol",
    "gn:population":0,
    "gn:timezone":"Asia/Seoul",
    "iso:country":"KR",
    "name:kor_x_preferred":[
        "\ub3d9\ud654\uace8"
    ],
    "name:und_x_variant":[
        "Tonghwa-ri",
        "Tonghwa-dong",
        "Tonghwa-gol"
    ],
    "wof:name":"Tonghwa-gol",
    "wof:placetype":"locality"
},
  "geometry": {"coordinates":[127.8511,37.322],"type":"Point"}
}