{
  "type": "Feature",
  "properties": {
    "gn:admin1_code":"3.0",
    "gn:asciiname":"Puhung-ni",
    "gn:country_code":"KR",
    "gn:dem":150,
    "gn:feature_class":"P",
    "gn:feature_code":"PPLL",
    "gn:name":"Puh\u016dng-ni",
    "gn:population":0,
    "gn:timezone":"Asia/Seoul",
    "iso:country":"KR",
    "name:und_x_variant":[
        "\ubd80\ud765\ub9ac",
        "Puh\u016dng-ni"
    ],
    "wof:name":"Puhung-ni",
    "wof:placetype":"locality"
},
  "geometry": {"coordinates":[127.17138,35.54257],"type":"Point"}
}