{
  "type": "Feature",
  "properties": {
    "gn:admin1_code":"13.0",
    "gn:asciiname":"Usal-li",
    "gn:country_code":"KR",
    "gn:dem":171,
    "gn:feature_class":"P",
    "gn:feature_code":"PPLL",
    "gn:name":"Usal-li",
    "gn:population":0,
    "gn:timezone":"Asia/Seoul",
    "iso:country":"KR",
    "name:und_x_variant":[
        "Usan-ni",
        "\uc6b0\uc0b0\ub9ac",
        "Usan-ri",
        "Usal-li"
    ],
    "wof:name":"Usal-li",
    "wof:placetype":"locality"
},
  "geometry": {"coordinates":[127.36278,37.43278],"type":"Point"}
}