{
  "type": "Feature",
  "properties": {
    "gn:admin1_code":"6.0",
    "gn:asciiname":"Hanch'i",
    "gn:country_code":"KR",
    "gn:dem":531,
    "gn:feature_class":"P",
    "gn:feature_code":"PPL",
    "gn:name":"Hanch\u2019i",
    "gn:population":0,
    "gn:timezone":"Asia/Seoul",
    "iso:country":"KR",
    "name:kor_x_preferred":[
        "Hanch\u2019i"
    ],
    "name:kor_x_variant":[
        "\ud55c\uce58"
    ],
    "wof:name":"Hanch'i",
    "wof:placetype":"locality"
},
  "geometry": {"coordinates":[128.81,37.31944],"type":"Point"}
}