{
  "type": "Feature",
  "properties": {
    "gn:admin1_code":"16.0",
    "gn:asciiname":"Oegi",
    "gn:country_code":"KR",
    "gn:dem":35,
    "gn:feature_class":"P",
    "gn:feature_code":"PPL",
    "gn:name":"Oegi",
    "gn:population":0,
    "gn:timezone":"Asia/Seoul",
    "iso:country":"KR",
    "name:kor_x_preferred":[
        "\uc678\uae30"
    ],
    "wof:name":"Oegi",
    "wof:placetype":"locality"
},
  "geometry": {"coordinates":[126.91197,34.71866],"type":"Point"}
}