{
  "type": "Feature",
  "properties": {
    "gn:admin1_code":"13.0",
    "gn:asciiname":"Heungyanggul",
    "gn:country_code":"KR",
    "gn:dem":15,
    "gn:feature_class":"P",
    "gn:feature_code":"PPL",
    "gn:name":"Heungyanggul",
    "gn:population":0,
    "gn:timezone":"Asia/Seoul",
    "iso:country":"KR",
    "name:kor_x_preferred":[
        "\ud64d\uc591\uace8"
    ],
    "name:kor_x_variant":[
        "\ud765\uc591\uad74"
    ],
    "name:und_x_variant":[
        "Honnayonggol",
        "Heungyanggul"
    ],
    "wof:name":"Heungyanggul",
    "wof:placetype":"locality"
},
  "geometry": {"coordinates":[126.61358,37.6805],"type":"Point"}
}