{
  "type": "Feature",
  "properties": {
    "gn:admin1_code":"17.0",
    "gn:asciiname":"Keunsol",
    "gn:country_code":"KR",
    "gn:dem":68,
    "gn:feature_class":"P",
    "gn:feature_code":"PPL",
    "gn:name":"Keunsol",
    "gn:population":0,
    "gn:timezone":"Asia/Seoul",
    "iso:country":"KR",
    "name:und_x_variant":[
        "\ud070\uc194",
        "K\u2019\u016dnsol",
        "Keunsol"
    ],
    "wof:name":"Keunsol",
    "wof:placetype":"locality"
},
  "geometry": {"coordinates":[127.18204,36.27803],"type":"Point"}
}