{
  "type": "Feature",
  "properties": {
    "gn:admin1_code":"20.0",
    "gn:asciiname":"Tungnim-ni",
    "gn:country_code":"KR",
    "gn:dem":37,
    "gn:feature_class":"P",
    "gn:feature_code":"PPL",
    "gn:name":"T\u016dngnim-ni",
    "gn:population":0,
    "gn:timezone":"Asia/Seoul",
    "iso:country":"KR",
    "name:und_x_variant":[
        "\ub4f1\ub9bc\ub9ac",
        "T\u016dngnim-ni"
    ],
    "wof:name":"Tungnim-ni",
    "wof:placetype":"locality"
},
  "geometry": {"coordinates":[128.37063000000001,35.58049000000001],"type":"Point"}
}