{
  "type": "Feature",
  "properties": {
    "gn:admin1_code":"6.0",
    "gn:asciiname":"Hamchun-ri",
    "gn:country_code":"KR",
    "gn:dem":214,
    "gn:feature_class":"P",
    "gn:feature_code":"PPL",
    "gn:name":"Hamchun-ri",
    "gn:population":0,
    "gn:timezone":"Asia/Seoul",
    "iso:country":"KR",
    "name:kor_x_preferred":[
        "\ud568\ucd98\ub9ac"
    ],
    "name:kor_x_variant":[
        "Hamch\u2019ul-li"
    ],
    "wof:name":"Hamchun-ri",
    "wof:placetype":"locality"
},
  "geometry": {"coordinates":[127.99222,38.11861],"type":"Point"}
}