{
  "type": "Feature",
  "properties": {
    "gn:country":"KR",
    "gn:fcode":"UNIV",
    "gn:pop":8000,
    "iso:country":"KR",
    "qs:name":"Ajou University",
    "qs:photos_9r":0,
    "qs:photos_sr":0,
    "qs:pop_sr":"5",
    "wd:wordcount":816,
    "wof:name":"Ajou University",
    "wof:placetype":"locality",
    "wof:population":8000
},
  "geometry": {"coordinates":[127.04564000000001,37.28129],"type":"Point"}
}