{
  "type": "Feature",
  "properties": {
    "gn:country":"KR",
    "gn:fcode":"UNIV",
    "gn:population":8000,
    "iso:country":"KR",
    "name:ceb_x_preferred":[
        "Ajou University"
    ],
    "name:eng_x_preferred":[
        "Ajou University"
    ],
    "name:fin_x_preferred":[
        "Ajou University"
    ],
    "name:fra_x_preferred":[
        "universit\u00e9 Ajou"
    ],
    "name:jpn_x_preferred":[
        "\u4e9c\u6d32\u5927\u5b66\u6821"
    ],
    "name:kor_x_preferred":[
        "\uc544\uc8fc\ub300\ud559\uad50"
    ],
    "name:rus_x_preferred":[
        "\u0423\u043d\u0438\u0432\u0435\u0440\u0441\u0438\u0442\u0435\u0442 \u0410\u0434\u0436\u0443"
    ],
    "name:swe_x_preferred":[
        "Ajou University"
    ],
    "name:tgl_x_preferred":[
        "Pamantasang Ajou"
    ],
    "name:zho_x_preferred":[
        "\u4e9e\u6d32\u5927\u5b78"
    ],
    "qs:name":"Ajou University",
    "qs:photos_9r":0,
    "qs:photos_sr":0,
    "qs:pop_sr":"5",
    "wd:wordcount":816,
    "wof:name":"Ajou University",
    "wof:placetype":"locality",
    "wof:population":8000
},
  "geometry": {"coordinates":[127.04564000000001,37.28129],"type":"Point"}
}