{
  "type": "Feature",
  "properties": {
    "gn:admin1_code":"5.0",
    "gn:asciiname":"Hakso",
    "gn:country_code":"KR",
    "gn:dem":59,
    "gn:feature_class":"P",
    "gn:feature_code":"PPL",
    "gn:name":"Hakso",
    "gn:population":0,
    "gn:timezone":"Asia/Seoul",
    "iso:country":"KR",
    "name:kor_x_preferred":[
        "\ud559\uc18c"
    ],
    "wof:name":"Hakso",
    "wof:placetype":"locality"
},
  "geometry": {"coordinates":[127.46781,36.74751],"type":"Point"}
}