{
  "type": "Feature",
  "properties": {
    "gn:admin1_code":"13.0",
    "gn:asciiname":"Chondwi",
    "gn:country_code":"KR",
    "gn:dem":40,
    "gn:feature_class":"P",
    "gn:feature_code":"PPL",
    "gn:name":"Ch\u014fndwi",
    "gn:population":0,
    "gn:timezone":"Asia/Seoul",
    "iso:country":"KR",
    "name:kor_x_preferred":[
        "\uc804\ub4a4"
    ],
    "name:kor_x_variant":[
        "Ch\u014fndwi"
    ],
    "wof:name":"Chondwi",
    "wof:placetype":"locality"
},
  "geometry": {"coordinates":[126.71222,37.16417],"type":"Point"}
}