{
  "type": "Feature",
  "properties": {
    "gn:admin1_code":"13.0",
    "gn:admin2_code":"Ans\u014fng-si",
    "gn:asciiname":"Sirwang-dong",
    "gn:country_code":"KR",
    "gn:dem":36,
    "gn:feature_class":"P",
    "gn:feature_code":"PPLL",
    "gn:name":"Sirwang-dong",
    "gn:population":0,
    "gn:timezone":"Asia/Seoul",
    "iso:country":"KR",
    "name:kor_x_preferred":[
        "\uc2e4\uc655\ub3d9"
    ],
    "wof:name":"Sirwang-dong",
    "wof:placetype":"locality"
},
  "geometry": {"coordinates":[127.26528,37.02556],"type":"Point"}
}