{
  "type": "Feature",
  "properties": {
    "gn:admin1_code":"14.0",
    "gn:asciiname":"Tongbu-ri",
    "gn:country_code":"KR",
    "gn:dem":64,
    "gn:feature_class":"P",
    "gn:feature_code":"PPLL",
    "gn:name":"Tongbu-ri",
    "gn:population":0,
    "gn:timezone":"Asia/Seoul",
    "iso:country":"KR",
    "name:und_x_variant":[
        "\ub3d9\ubd80\ub9ac",
        "Tongbu-ri"
    ],
    "wof:name":"Tongbu-ri",
    "wof:placetype":"locality"
},
  "geometry": {"coordinates":[128.30958999999999,36.24646],"type":"Point"}
}