{
  "type": "Feature",
  "properties": {
    "gn:admin1_code":"6.0",
    "gn:admin2_code":"Ch'\u014flw\u014fn-gun",
    "gn:asciiname":"Buam",
    "gn:country_code":"KR",
    "gn:dem":254,
    "gn:feature_class":"P",
    "gn:feature_code":"PPL",
    "gn:name":"Buam",
    "gn:population":0,
    "gn:timezone":"Asia/Seoul",
    "iso:country":"KR",
    "name:kor_x_preferred":[
        "\ubd80\uc554"
    ],
    "name:und_x_variant":[
        "Puam"
    ],
    "wof:name":"Buam",
    "wof:placetype":"locality"
},
  "geometry": {"coordinates":[127.48254,38.28003],"type":"Point"}
}