{
  "type": "Feature",
  "properties": {
    "gn:admin1_code":"1.0",
    "gn:admin2_code":"Pukcheju-gun",
    "gn:asciiname":"Myeongidong",
    "gn:country_code":"KR",
    "gn:dem":137,
    "gn:feature_class":"P",
    "gn:feature_code":"PPL",
    "gn:name":"Myeongidong",
    "gn:population":0,
    "gn:timezone":"Asia/Seoul",
    "iso:country":"KR",
    "name:kor_x_preferred":[
        "\uba85\uc774\ub3d9"
    ],
    "name:und_x_variant":[
        "My\u014fngi-dong"
    ],
    "wof:name":"Myeongidong",
    "wof:placetype":"locality"
},
  "geometry": {"coordinates":[126.26997,33.31815],"type":"Point"}
}