{
  "type": "Feature",
  "properties": {
    "gn:admin1_code":"17.0",
    "gn:asciiname":"Samga-ri",
    "gn:country_code":"KR",
    "gn:dem":209,
    "gn:feature_class":"P",
    "gn:feature_code":"PPLL",
    "gn:name":"Samga-ri",
    "gn:population":0,
    "gn:timezone":"Asia/Seoul",
    "iso:country":"KR",
    "name:und_x_variant":[
        "\uc0bc\uac00\ub9ac",
        "Samga-ri"
    ],
    "wof:name":"Samga-ri",
    "wof:placetype":"locality"
},
  "geometry": {"coordinates":[127.39400999999999,36.13319],"type":"Point"}
}