{
  "type": "Feature",
  "properties": {
    "gn:admin1_code":"14.0",
    "gn:asciiname":"Sunji",
    "gn:country_code":"KR",
    "gn:dem":86,
    "gn:feature_class":"P",
    "gn:feature_code":"PPL",
    "gn:name":"Sunji",
    "gn:population":0,
    "gn:timezone":"Asia/Seoul",
    "iso:country":"KR",
    "name:ceb_x_preferred":[
        "Sunji"
    ],
    "name:kor_x_preferred":[
        "\uc21c\uc9c0"
    ],
    "name:swe_x_preferred":[
        "Sunji"
    ],
    "wof:name":"Sunji",
    "wof:placetype":"locality"
},
  "geometry": {"coordinates":[129.29568999999998,35.73994000000001],"type":"Point"}
}