{
  "type": "Feature",
  "properties": {
    "gn:admin1_code":"6.0",
    "gn:asciiname":"Tungdung",
    "gn:country_code":"KR",
    "gn:dem":443,
    "gn:feature_class":"P",
    "gn:feature_code":"PPL",
    "gn:name":"Tungdung",
    "gn:population":0,
    "gn:timezone":"Asia/Seoul",
    "iso:country":"KR",
    "name:kor_x_preferred":[
        "\ub465\ub465"
    ],
    "wof:name":"Tungdung",
    "wof:placetype":"locality"
},
  "geometry": {"coordinates":[128.04553000000001,37.24125],"type":"Point"}
}