{
  "type": "Feature",
  "properties": {
    "gn:admin1_code":"10.0",
    "gn:asciiname":"Seojung",
    "gn:country_code":"KR",
    "gn:dem":7,
    "gn:feature_class":"P",
    "gn:feature_code":"PPL",
    "gn:name":"Seojung",
    "gn:population":0,
    "gn:timezone":"Asia/Seoul",
    "iso:country":"KR",
    "name:kor_x_preferred":[
        "\uc11c\uc911"
    ],
    "name:und_x_variant":[
        "S\u014fjung"
    ],
    "wof:name":"Seojung",
    "wof:placetype":"locality"
},
  "geometry": {"coordinates":[128.81614999999999,35.02946],"type":"Point"}
}