{
  "type": "Feature",
  "properties": {
    "gn:admin1_code":"13.0",
    "gn:asciiname":"Sil-li",
    "gn:country_code":"KR",
    "gn:dem":17,
    "gn:feature_class":"P",
    "gn:feature_code":"PPL",
    "gn:name":"Sil-li",
    "gn:population":0,
    "gn:timezone":"Asia/Seoul",
    "iso:country":"KR",
    "name:und_x_variant":[
        "Shini",
        "\uc2e0\ub9ac",
        "Chinwi",
        "Sin-ri",
        "Sil-li"
    ],
    "wof:name":"Sil-li",
    "wof:placetype":"locality"
},
  "geometry": {"coordinates":[127.06999999999999,37.09639],"type":"Point"}
}