{
  "type": "Feature",
  "properties": {
    "iso:country":"KR",
    "name:eng_x_preferred":[
        "Chahwang-myeon"
    ],
    "name:kor_x_preferred":[
        "\ucc28\ud669\uba74"
    ],
    "qs:name":"\ucc28\ud669\uba74",
    "qs:name_adm0":"\ud55c\uad6d",
    "qs:name_adm1":"\uacbd\uc0c1\ub0a8\ub3c4",
    "qs:photos":14,
    "qs:photos_1k":3,
    "qs:photos_9k":1,
    "qs:photos_9r":1,
    "qs:photos_all":14,
    "qs:photos_sr":1,
    "qs:placetype":"LocalAdmin",
    "qs:pop_sr":"0",
    "wof:name":"Chahwang-myeon",
    "wof:placetype":"localadmin"
},
  "geometry": {"coordinates":[127.847943,35.353594],"type":"Point"}
}