{
  "type": "Feature",
  "properties": {
    "gn:admin1_code":"17.0",
    "gn:asciiname":"Sansongmi",
    "gn:cc2":"KR",
    "gn:country_code":"KR",
    "gn:dem":79,
    "gn:feature_class":"P",
    "gn:feature_code":"PPL",
    "gn:name":"Sans\u014fngmi",
    "gn:population":0,
    "gn:timezone":"Asia/Seoul",
    "iso:country":"KR",
    "name:und_x_variant":[
        "San\u016dm-ni",
        "Sans\u014fngmi"
    ],
    "wof:name":"Sansongmi",
    "wof:placetype":"locality"
},
  "geometry": {"coordinates":[126.95,36.51667],"type":"Point"}
}