{
  "type": "Feature",
  "properties": {
    "gn:admin1_code":"21.0",
    "gn:asciiname":"Jeonggeori",
    "gn:country_code":"KR",
    "gn:dem":104,
    "gn:feature_class":"P",
    "gn:feature_code":"PPL",
    "gn:name":"Jeonggeori",
    "gn:population":0,
    "gn:timezone":"Asia/Seoul",
    "iso:country":"KR",
    "name:kor_x_preferred":[
        "\uc815\uac70\ub9ac"
    ],
    "wof:name":"Jeonggeori",
    "wof:placetype":"locality"
},
  "geometry": {"coordinates":[129.13262,35.59722],"type":"Point"}
}