{
  "type": "Feature",
  "properties": {
    "gn:admin1_code":"17.0",
    "gn:asciiname":"Osan",
    "gn:country_code":"KR",
    "gn:dem":30,
    "gn:feature_class":"P",
    "gn:feature_code":"PPL",
    "gn:name":"Osan",
    "gn:population":0,
    "gn:timezone":"Asia/Seoul",
    "iso:country":"KR",
    "name:und_x_variant":[
        "\uc624\uc0b0",
        "Osan"
    ],
    "wof:name":"Osan",
    "wof:placetype":"locality"
},
  "geometry": {"coordinates":[126.9529,36.2782],"type":"Point"}
}