{
  "type": "Feature",
  "properties": {
    "gn:admin1_code":"21.0",
    "gn:asciiname":"Yejeon",
    "gn:country_code":"KR",
    "gn:dem":12,
    "gn:feature_class":"P",
    "gn:feature_code":"PPL",
    "gn:name":"Yejeon",
    "gn:population":0,
    "gn:timezone":"Asia/Seoul",
    "iso:country":"KR",
    "name:kor_x_preferred":[
        "\uc608\uc804"
    ],
    "wof:name":"Yejeon",
    "wof:placetype":"locality"
},
  "geometry": {"coordinates":[129.40178999999998,35.50875],"type":"Point"}
}