{
  "type": "Feature",
  "properties": {
    "gn:admin1_code":"14.0",
    "gn:asciiname":"Yong-ch'on",
    "gn:country_code":"KR",
    "gn:dem":179,
    "gn:feature_class":"P",
    "gn:feature_code":"PPL",
    "gn:name":"Yong-ch\u2019on",
    "gn:population":0,
    "gn:timezone":"Asia/Seoul",
    "iso:country":"KR",
    "name:und_x_variant":[
        "\uc6a9\ucd0c",
        "Yong-ch\u2019on"
    ],
    "wof:name":"Yong-ch'on",
    "wof:placetype":"locality"
},
  "geometry": {"coordinates":[127.98990000000001,35.98492],"type":"Point"}
}