{
  "type": "Feature",
  "properties": {
    "gn:admin1_code":"17.0",
    "gn:asciiname":"Tonae-ri",
    "gn:cc2":"KR",
    "gn:country_code":"KR",
    "gn:dem":2,
    "gn:feature_class":"P",
    "gn:feature_code":"PPL",
    "gn:name":"Tonae-ri",
    "gn:population":0,
    "gn:timezone":"Asia/Seoul",
    "iso:country":"KR",
    "name:und_x_variant":[
        "Tonae",
        "Tonae-ri"
    ],
    "wof:name":"Tonae-ri",
    "wof:placetype":"locality"
},
  "geometry": {"coordinates":[126.34193999999999,36.80306],"type":"Point"}
}