{
  "type": "Feature",
  "properties": {
    "gn:admin1_code":"16.0",
    "gn:asciiname":"Jangjaedong",
    "gn:country_code":"KR",
    "gn:dem":16,
    "gn:feature_class":"P",
    "gn:feature_code":"PPL",
    "gn:name":"Jangjaedong",
    "gn:population":0,
    "gn:timezone":"Asia/Seoul",
    "iso:country":"KR",
    "name:kor_x_preferred":[
        "\uc7a5\uc7ac\ub3d9"
    ],
    "wof:name":"Jangjaedong",
    "wof:placetype":"locality"
},
  "geometry": {"coordinates":[126.71357,34.94386],"type":"Point"}
}