{
  "type": "Feature",
  "properties": {
    "gn:admin1_code":"5.0",
    "gn:asciiname":"Yangman",
    "gn:country_code":"KR",
    "gn:dem":109,
    "gn:feature_class":"P",
    "gn:feature_code":"PPL",
    "gn:name":"Yangman",
    "gn:population":0,
    "gn:timezone":"Asia/Seoul",
    "iso:country":"KR",
    "name:kor_x_preferred":[
        "\uc591\ub9cc"
    ],
    "wof:name":"Yangman",
    "wof:placetype":"locality"
},
  "geometry": {"coordinates":[127.41956,36.95492],"type":"Point"}
}