{
  "type": "Feature",
  "properties": {
    "gn:admin1_code":"13.0",
    "gn:asciiname":"Solcheongnon",
    "gn:country_code":"KR",
    "gn:dem":66,
    "gn:feature_class":"P",
    "gn:feature_code":"PPL",
    "gn:name":"Solcheongnon",
    "gn:population":0,
    "gn:timezone":"Asia/Seoul",
    "iso:country":"KR",
    "name:kor_x_preferred":[
        "\uc194\uccad\ub17c"
    ],
    "wof:name":"Solcheongnon",
    "wof:placetype":"locality"
},
  "geometry": {"coordinates":[127.04653999999999,37.79932],"type":"Point"}
}