{
  "type": "Feature",
  "properties": {
    "gn:admin1_code":"16.0",
    "gn:asciiname":"Sangil",
    "gn:country_code":"KR",
    "gn:dem":250,
    "gn:feature_class":"P",
    "gn:feature_code":"PPL",
    "gn:name":"Sangil",
    "gn:population":0,
    "gn:timezone":"Asia/Seoul",
    "iso:country":"KR",
    "name:kor_x_preferred":[
        "\uc0c1\uc77c"
    ],
    "wof:name":"Sangil",
    "wof:placetype":"locality"
},
  "geometry": {"coordinates":[127.20222,34.8628],"type":"Point"}
}