{
  "type": "Feature",
  "properties": {
    "gn:admin1_code":"20.0",
    "gn:asciiname":"Yangch'ol-li",
    "gn:country_code":"KR",
    "gn:dem":123,
    "gn:feature_class":"P",
    "gn:feature_code":"PPL",
    "gn:name":"Yangch\u2019ol-li",
    "gn:population":0,
    "gn:timezone":"Asia/Seoul",
    "iso:country":"KR",
    "name:und_x_variant":[
        "Yang-ch\u2019on",
        "Yangch\u2019ol-li"
    ],
    "wof:name":"Yangch'ol-li",
    "wof:placetype":"locality"
},
  "geometry": {"coordinates":[127.86111,35.45944],"type":"Point"}
}