{
  "type": "Feature",
  "properties": {
    "gn:admin1_code":"5.0",
    "gn:asciiname":"Neulchi",
    "gn:country_code":"KR",
    "gn:dem":237,
    "gn:feature_class":"P",
    "gn:feature_code":"PPL",
    "gn:name":"Neulchi",
    "gn:population":0,
    "gn:timezone":"Asia/Seoul",
    "iso:country":"KR",
    "name:und_x_variant":[
        "\ub298\uce58",
        "N\u016dlch\u2019i",
        "Neulchi"
    ],
    "wof:name":"Neulchi",
    "wof:placetype":"locality"
},
  "geometry": {"coordinates":[127.6087,36.4219],"type":"Point"}
}