{
  "type": "Feature",
  "properties": {
    "gn:admin1_code":"16.0",
    "gn:asciiname":"Buchundong",
    "gn:country_code":"KR",
    "gn:dem":61,
    "gn:feature_class":"P",
    "gn:feature_code":"PPL",
    "gn:name":"Buchundong",
    "gn:population":0,
    "gn:timezone":"Asia/Seoul",
    "iso:country":"KR",
    "name:kor_x_preferred":[
        "\ubd80\ucd98\ub3d9"
    ],
    "wof:name":"Buchundong",
    "wof:placetype":"locality"
},
  "geometry": {"coordinates":[126.97812999999999,34.95738],"type":"Point"}
}