{
  "type": "Feature",
  "properties": {
    "gn:admin1_code":"16.0",
    "gn:asciiname":"Byeokdong",
    "gn:country_code":"KR",
    "gn:dem":69,
    "gn:feature_class":"P",
    "gn:feature_code":"PPL",
    "gn:name":"Byeokdong",
    "gn:population":0,
    "gn:timezone":"Asia/Seoul",
    "iso:country":"KR",
    "name:kor_x_preferred":[
        "\ubcbd\ub3d9"
    ],
    "name:und_x_variant":[
        "Py\u014fk-tong"
    ],
    "wof:name":"Byeokdong",
    "wof:placetype":"locality"
},
  "geometry": {"coordinates":[126.88816,34.95529000000001],"type":"Point"}
}