{
  "type": "Feature",
  "properties": {
    "gn:admin1_code":"6.0",
    "gn:asciiname":"Baegi",
    "gn:country_code":"KR",
    "gn:dem":156,
    "gn:feature_class":"P",
    "gn:feature_code":"PPL",
    "gn:name":"Baegi",
    "gn:population":0,
    "gn:timezone":"Asia/Seoul",
    "iso:country":"KR",
    "name:kor_x_preferred":[
        "\ubc31\uc774"
    ],
    "name:und_x_variant":[
        "Paegi",
        "Baegi"
    ],
    "wof:name":"Baegi",
    "wof:placetype":"locality"
},
  "geometry": {"coordinates":[127.8441,37.7068],"type":"Point"}
}