{
  "type": "Feature",
  "properties": {
    "gn:admin1_code":"17.0",
    "gn:asciiname":"Yongwang-dong",
    "gn:country_code":"KR",
    "gn:dem":67,
    "gn:feature_class":"P",
    "gn:feature_code":"PPL",
    "gn:name":"Yongwang-dong",
    "gn:population":0,
    "gn:timezone":"Asia/Seoul",
    "iso:country":"KR",
    "name:und_x_variant":[
        "\uc6a9\uc655\ub3d9",
        "Yongwang-dong"
    ],
    "wof:name":"Yongwang-dong",
    "wof:placetype":"locality"
},
  "geometry": {"coordinates":[126.8481,36.5812],"type":"Point"}
}