{
  "type": "Feature",
  "properties": {
    "gn:admin1_code":"20.0",
    "gn:asciiname":"Chinan",
    "gn:country_code":"KR",
    "gn:dem":112,
    "gn:feature_class":"P",
    "gn:feature_code":"PPL",
    "gn:name":"Chinan",
    "gn:population":0,
    "gn:timezone":"Asia/Seoul",
    "iso:country":"KR",
    "name:und_x_variant":[
        "\uc9c4\uc548",
        "Chinan"
    ],
    "wof:name":"Chinan",
    "wof:placetype":"locality"
},
  "geometry": {"coordinates":[128.35477,35.18677],"type":"Point"}
}