{
  "type": "Feature",
  "properties": {
    "gn:admin1_code":"14.0",
    "gn:asciiname":"Seomi",
    "gn:country_code":"KR",
    "gn:dem":231,
    "gn:feature_class":"P",
    "gn:feature_code":"PPL",
    "gn:name":"Seomi",
    "gn:population":0,
    "gn:timezone":"Asia/Seoul",
    "iso:country":"KR",
    "name:kor_x_preferred":[
        "\uc11c\ubbf8"
    ],
    "name:und_x_variant":[
        "S\u014fmi-dong",
        "S\u014fmi-gol",
        "S\u014fmi",
        "Seomi"
    ],
    "wof:name":"Seomi",
    "wof:placetype":"locality"
},
  "geometry": {"coordinates":[128.56623000000002,36.63363],"type":"Point"}
}