{
  "type": "Feature",
  "properties": {
    "gn:admin1_code":"16.0",
    "gn:asciiname":"Ch'ongnyong",
    "gn:country_code":"KR",
    "gn:dem":34,
    "gn:feature_class":"P",
    "gn:feature_code":"PPL",
    "gn:name":"Ch\u2019\u014fngnyong",
    "gn:population":0,
    "gn:timezone":"Asia/Seoul",
    "iso:country":"KR",
    "name:kor_x_preferred":[
        "\uccad\ub8e1"
    ],
    "name:und_x_variant":[
        "Ch\u2019\u014fngnyong-ni",
        "Ch\u2019\u014fngyong"
    ],
    "wof:name":"Ch'ongnyong",
    "wof:placetype":"locality"
},
  "geometry": {"coordinates":[127.24629,34.56669],"type":"Point"}
}