{
  "type": "Feature",
  "properties": {
    "gn:admin1_code":"14.0",
    "gn:asciiname":"Anjilla",
    "gn:country_code":"KR",
    "gn:dem":124,
    "gn:feature_class":"P",
    "gn:feature_code":"PPL",
    "gn:name":"Anjilla",
    "gn:population":0,
    "gn:timezone":"Asia/Seoul",
    "iso:country":"KR",
    "name:und_x_variant":[
        "\uc548\uc9c4\ub77c",
        "Anjilla"
    ],
    "wof:name":"Anjilla",
    "wof:placetype":"locality"
},
  "geometry": {"coordinates":[128.73508000000001,35.67768],"type":"Point"}
}