{
  "type": "Feature",
  "properties": {
    "gn:admin1_code":"16.0",
    "gn:asciiname":"Nurokto-ri",
    "gn:country_code":"KR",
    "gn:dem":40,
    "gn:feature_class":"P",
    "gn:feature_code":"PPL",
    "gn:name":"Nurokto-ri",
    "gn:population":0,
    "gn:timezone":"Asia/Seoul",
    "iso:country":"KR",
    "wof:name":"Nurokto-ri",
    "wof:placetype":"locality"
},
  "geometry": {"coordinates":[125.95667,34.34806],"type":"Point"}
}