{
  "type": "Feature",
  "properties": {
    "gn:admin1_code":"14.0",
    "gn:asciiname":"Yongch'on",
    "gn:country_code":"KR",
    "gn:dem":102,
    "gn:feature_class":"P",
    "gn:feature_code":"PPL",
    "gn:name":"Yongch\u2019\u014fn",
    "gn:population":0,
    "gn:timezone":"Asia/Seoul",
    "iso:country":"KR",
    "name:und_x_variant":[
        "\uc6a9\ucc9c",
        "Yongch\u2019\u014fn"
    ],
    "wof:name":"Yongch'on",
    "wof:placetype":"locality"
},
  "geometry": {"coordinates":[129.25756999999999,36.09068],"type":"Point"}
}