{
  "type": "Feature",
  "properties": {
    "gn:admin1_code":"5.0",
    "gn:asciiname":"Dongam",
    "gn:country_code":"KR",
    "gn:dem":116,
    "gn:feature_class":"P",
    "gn:feature_code":"PPL",
    "gn:name":"Dongam",
    "gn:population":0,
    "gn:timezone":"Asia/Seoul",
    "iso:country":"KR",
    "name:kor_x_preferred":[
        "\ub3d9\uc554"
    ],
    "name:und_x_variant":[
        "Tongam"
    ],
    "wof:name":"Dongam",
    "wof:placetype":"locality"
},
  "geometry": {"coordinates":[127.79031999999999,37.08993],"type":"Point"}
}