{
  "type": "Feature",
  "properties": {
    "gn:admin1_code":"6.0",
    "gn:asciiname":"Kung-ch'on",
    "gn:country_code":"KR",
    "gn:dem":264,
    "gn:feature_class":"P",
    "gn:feature_code":"PPL",
    "gn:name":"Kung-ch\u2019on",
    "gn:population":0,
    "gn:timezone":"Asia/Seoul",
    "iso:country":"KR",
    "name:und_x_variant":[
        "\uad81\ucd0c",
        "Kung-ch\u2019on"
    ],
    "wof:name":"Kung-ch'on",
    "wof:placetype":"locality"
},
  "geometry": {"coordinates":[129.14410000000001,37.1478],"type":"Point"}
}