{
  "type": "Feature",
  "properties": {
    "gn:admin1_code":"16.0",
    "gn:asciiname":"Daeeun",
    "gn:country_code":"KR",
    "gn:dem":227,
    "gn:feature_class":"P",
    "gn:feature_code":"PPL",
    "gn:name":"Daeeun",
    "gn:population":0,
    "gn:timezone":"Asia/Seoul",
    "iso:country":"KR",
    "name:kor_x_preferred":[
        "\ub300\uc740"
    ],
    "name:kor_x_variant":[
        "Tae\u016dn"
    ],
    "wof:name":"Daeeun",
    "wof:placetype":"locality"
},
  "geometry": {"coordinates":[127.03003,34.69895],"type":"Point"}
}