{
  "type": "Feature",
  "properties": {
    "gn:admin1_code":"13.0",
    "gn:asciiname":"Kumi-ri",
    "gn:country_code":"KR",
    "gn:dem":38,
    "gn:feature_class":"P",
    "gn:feature_code":"PPL",
    "gn:name":"Kumi-ri",
    "gn:population":0,
    "gn:timezone":"Asia/Seoul",
    "iso:country":"KR",
    "name:und_x_variant":[
        "\uad6c\ubbf8\ub9ac",
        "Gumi-ri",
        "Kumi-ri"
    ],
    "wof:name":"Kumi-ri",
    "wof:placetype":"locality"
},
  "geometry": {"coordinates":[127.51389,37.44611],"type":"Point"}
}