{
  "type": "Feature",
  "properties": {
    "gn:admin1_code":"6.0",
    "gn:asciiname":"Ha-ch'on",
    "gn:country_code":"KR",
    "gn:dem":51,
    "gn:feature_class":"P",
    "gn:feature_code":"PPL",
    "gn:name":"Ha-ch\u2019on",
    "gn:population":0,
    "gn:timezone":"Asia/Seoul",
    "iso:country":"KR",
    "name:und_x_variant":[
        "Ha-ch\u2019on",
        "\ud558\ucd0c"
    ],
    "wof:name":"Ha-ch'on",
    "wof:placetype":"locality"
},
  "geometry": {"coordinates":[129.27056000000002,37.14444],"type":"Point"}
}