{
  "type": "Feature",
  "properties": {
    "gn:admin1_code":"14.0",
    "gn:asciiname":"Hwangsan",
    "gn:country_code":"KR",
    "gn:dem":316,
    "gn:feature_class":"P",
    "gn:feature_code":"PPL",
    "gn:name":"Hwangsan",
    "gn:population":0,
    "gn:timezone":"Asia/Seoul",
    "iso:country":"KR",
    "name:und_x_variant":[
        "\ud669\uc0b0",
        "Hwangsan"
    ],
    "wof:name":"Hwangsan",
    "wof:placetype":"locality"
},
  "geometry": {"coordinates":[127.91041,36.42533],"type":"Point"}
}