{
  "type": "Feature",
  "properties": {
    "gn:admin1_code":"14.0",
    "gn:asciiname":"Sangjwaseok",
    "gn:country_code":"KR",
    "gn:dem":509,
    "gn:feature_class":"P",
    "gn:feature_code":"PPL",
    "gn:name":"Sangjwaseok",
    "gn:population":0,
    "gn:timezone":"Asia/Seoul",
    "iso:country":"KR",
    "name:kor_x_preferred":[
        "\uc0c1\uc88c\uc11d"
    ],
    "wof:name":"Sangjwaseok",
    "wof:placetype":"locality"
},
  "geometry": {"coordinates":[128.55653000000001,36.98306],"type":"Point"}
}