{
  "type": "Feature",
  "properties": {
    "gn:admin1_code":"6.0",
    "gn:asciiname":"Suyu-dong",
    "gn:country_code":"KR",
    "gn:dem":556,
    "gn:feature_class":"P",
    "gn:feature_code":"PPL",
    "gn:name":"Suyu-dong",
    "gn:population":0,
    "gn:timezone":"Asia/Seoul",
    "iso:country":"KR",
    "name:fas_x_preferred":[
        "\u0633\u0648\u06cc\u0648-\u062f\u0648\u0646\u06af"
    ],
    "name:kor_x_preferred":[
        "\uc218\uc720\ub3d9"
    ],
    "name:msa_x_preferred":[
        "Suyu-dong"
    ],
    "name:tha_x_preferred":[
        "\u0e41\u0e02\u0e27\u0e07\u0e0b\u0e39\u0e22\u0e39"
    ],
    "name:vie_x_preferred":[
        "Suyu-dong"
    ],
    "wof:name":"Suyu-dong",
    "wof:placetype":"locality"
},
  "geometry": {"coordinates":[128.2286,37.8152],"type":"Point"}
}