{
  "type": "Feature",
  "properties": {
    "gn:admin1_code":"6.0",
    "gn:asciiname":"Suyu-dong",
    "gn:country_code":"KR",
    "gn:dem":556,
    "gn:feature_class":"P",
    "gn:feature_code":"PPL",
    "gn:name":"Suyu-dong",
    "gn:population":0,
    "gn:timezone":"Asia/Seoul",
    "iso:country":"KR",
    "name:kor_x_preferred":[
        "\uc218\uc720\ub3d9"
    ],
    "wof:name":"Suyu-dong",
    "wof:placetype":"locality"
},
  "geometry": {"coordinates":[128.2286,37.8152],"type":"Point"}
}