{
  "type": "Feature",
  "properties": {
    "gn:admin1_code":"16.0",
    "gn:asciiname":"Songhyon",
    "gn:country_code":"KR",
    "gn:dem":43,
    "gn:feature_class":"P",
    "gn:feature_code":"PPL",
    "gn:name":"Songhy\u014fn",
    "gn:population":0,
    "gn:timezone":"Asia/Seoul",
    "iso:country":"KR",
    "name:kor_x_preferred":[
        "Songhy\u014fn"
    ],
    "wof:name":"Songhyon",
    "wof:placetype":"locality"
},
  "geometry": {"coordinates":[126.95638999999998,34.54639],"type":"Point"}
}