{
  "type": "Feature",
  "properties": {
    "gn:admin1_code":"6.0",
    "gn:asciiname":"Haduwon",
    "gn:country_code":"KR",
    "gn:dem":542,
    "gn:feature_class":"P",
    "gn:feature_code":"PPL",
    "gn:name":"Haduw\u014fn",
    "gn:population":0,
    "gn:timezone":"Asia/Seoul",
    "iso:country":"KR",
    "name:kor_x_preferred":[
        "\ud558\ub450\uc6d0"
    ],
    "name:kor_x_variant":[
        "Haduw\u014fn"
    ],
    "wof:name":"Haduwon",
    "wof:placetype":"locality"
},
  "geometry": {"coordinates":[128.2372,37.497],"type":"Point"}
}