{
  "type": "Feature",
  "properties": {
    "gn:admin1_code":"11.0",
    "gn:asciiname":"Samsong-dong",
    "gn:country_code":"KR",
    "gn:dem":57,
    "gn:feature_class":"P",
    "gn:feature_code":"PPL",
    "gn:name":"Sams\u014fng-dong",
    "gn:population":0,
    "gn:timezone":"Asia/Seoul",
    "iso:country":"KR",
    "name:und_x_variant":[
        "\uc0bc\uc131\ub3d9",
        "Sams\u014fng-dong"
    ],
    "wof:name":"Samsong-dong",
    "wof:placetype":"locality"
},
  "geometry": {"coordinates":[127.0432,37.5124],"type":"Point"}
}