{
  "type": "Feature",
  "properties": {
    "gn:admin1_code":"13.0",
    "gn:asciiname":"Siksong",
    "gn:country_code":"KR",
    "gn:dem":140,
    "gn:feature_class":"P",
    "gn:feature_code":"PPL",
    "gn:name":"Siksong",
    "gn:population":0,
    "gn:timezone":"Asia/Seoul",
    "iso:country":"KR",
    "name:und_x_variant":[
        "\uc2dd\uc1a1",
        "Siksong"
    ],
    "wof:name":"Siksong",
    "wof:placetype":"locality"
},
  "geometry": {"coordinates":[127.33083000000001,37.26528],"type":"Point"}
}