{
  "type": "Feature",
  "properties": {
    "gn:admin1_code":"17.0",
    "gn:asciiname":"Silt'o",
    "gn:country_code":"KR",
    "gn:dem":155,
    "gn:feature_class":"P",
    "gn:feature_code":"PPL",
    "gn:name":"Silt\u2019\u014f",
    "gn:population":0,
    "gn:timezone":"Asia/Seoul",
    "iso:country":"KR",
    "name:und_x_variant":[
        "\uc2e4\ud130",
        "Silt\u2019\u014f"
    ],
    "wof:name":"Silt'o",
    "wof:placetype":"locality"
},
  "geometry": {"coordinates":[126.6401,36.7471],"type":"Point"}
}