{
  "type": "Feature",
  "properties": {
    "gn:admin1_code":"6.0",
    "gn:asciiname":"Eumhyanggol",
    "gn:country_code":"KR",
    "gn:dem":279,
    "gn:feature_class":"P",
    "gn:feature_code":"PPL",
    "gn:name":"Eumhyanggol",
    "gn:population":0,
    "gn:timezone":"Asia/Seoul",
    "iso:country":"KR",
    "name:kor_x_preferred":[
        "\uc74c\ud56d\uace1"
    ],
    "name:kor_x_variant":[
        "\u016cmhanggok",
        "\uc74c\ud5a5\uace8"
    ],
    "wof:name":"Eumhyanggol",
    "wof:placetype":"locality"
},
  "geometry": {"coordinates":[128.16428999999999,37.76001],"type":"Point"}
}