{
  "type": "Feature",
  "properties": {
    "gn:admin1_code":"16.0",
    "gn:asciiname":"Kwansan",
    "gn:country_code":"KR",
    "gn:dem":18,
    "gn:feature_class":"P",
    "gn:feature_code":"PPL",
    "gn:name":"Kwansan",
    "gn:population":0,
    "gn:timezone":"Asia/Seoul",
    "iso:country":"KR",
    "name:kor_x_preferred":[
        "\uad00\uc0b0"
    ],
    "wof:name":"Kwansan",
    "wof:placetype":"locality"
},
  "geometry": {"coordinates":[126.93861,34.56111],"type":"Point"}
}