{
  "type": "Feature",
  "properties": {
    "gn:admin1_code":"14.0",
    "gn:asciiname":"Solmeori",
    "gn:country_code":"KR",
    "gn:dem":167,
    "gn:feature_class":"P",
    "gn:feature_code":"PPL",
    "gn:name":"Solmeori",
    "gn:population":0,
    "gn:timezone":"Asia/Seoul",
    "iso:country":"KR",
    "name:kor_x_preferred":[
        "\uc194\uba38\ub9ac"
    ],
    "wof:name":"Solmeori",
    "wof:placetype":"locality"
},
  "geometry": {"coordinates":[128.77223000000001,36.69636],"type":"Point"}
}