{
  "type": "Feature",
  "properties": {
    "gn:admin1_code":"20.0",
    "gn:asciiname":"Yonhwa-ri",
    "gn:country_code":"KR",
    "gn:dem":224,
    "gn:feature_class":"P",
    "gn:feature_code":"PPL",
    "gn:name":"Y\u014fnhwa-ri",
    "gn:population":0,
    "gn:timezone":"Asia/Seoul",
    "iso:country":"KR",
    "name:und_x_variant":[
        "\uc5f0\ud654\ub9ac",
        "Y\u014fnhwa-ri"
    ],
    "wof:name":"Yonhwa-ri",
    "wof:placetype":"locality"
},
  "geometry": {"coordinates":[128.25276000000002,35.07376],"type":"Point"}
}