{
  "type": "Feature",
  "properties": {
    "gn:admin1_code":"17.0",
    "gn:asciiname":"Uryeoul",
    "gn:country_code":"KR",
    "gn:dem":62,
    "gn:feature_class":"P",
    "gn:feature_code":"PPL",
    "gn:name":"Uryeoul",
    "gn:population":0,
    "gn:timezone":"Asia/Seoul",
    "iso:country":"KR",
    "name:kor_x_preferred":[
        "\uc6b8\uc5ec\uc6b8"
    ],
    "name:und_x_variant":[
        "\uc6b0\ub824\uc6b8",
        "Ury\u014ful",
        "Uryeoul"
    ],
    "wof:name":"Uryeoul",
    "wof:placetype":"locality"
},
  "geometry": {"coordinates":[127.33360999999999,36.46627],"type":"Point"}
}