{
  "type": "Feature",
  "properties": {
    "gn:admin1_code":"17.0",
    "gn:asciiname":"Sokkyo-ri",
    "gn:country_code":"KR",
    "gn:dem":49,
    "gn:feature_class":"P",
    "gn:feature_code":"PPL",
    "gn:name":"S\u014fkkyo-ri",
    "gn:population":0,
    "gn:timezone":"Asia/Seoul",
    "iso:country":"KR",
    "name:und_x_variant":[
        "\uc11d\uad50\ub9ac",
        "S\u014fkkyo-ri"
    ],
    "wof:name":"Sokkyo-ri",
    "wof:placetype":"locality"
},
  "geometry": {"coordinates":[127.3177,36.4861],"type":"Point"}
}