{
  "type": "Feature",
  "properties": {
    "gn:admin1_code":"16.0",
    "gn:asciiname":"Neopdo",
    "gn:country_code":"KR",
    "gn:dem":12,
    "gn:feature_class":"P",
    "gn:feature_code":"PPL",
    "gn:name":"Neopdo",
    "gn:population":0,
    "gn:timezone":"Asia/Seoul",
    "iso:country":"KR",
    "name:kor_x_preferred":[
        "\ub118\ub3c4"
    ],
    "name:kor_x_variant":[
        "S\u014fjae-jae",
        "\ub119\ub3c4"
    ],
    "name:und_x_variant":[
        "Neomdo",
        "N\u014fmdo"
    ],
    "wof:name":"Neopdo",
    "wof:placetype":"locality"
},
  "geometry": {"coordinates":[126.855,34.42694],"type":"Point"}
}