{
  "type": "Feature",
  "properties": {
    "gn:admin1_code":"5.0",
    "gn:asciiname":"Majanggol",
    "gn:country_code":"KR",
    "gn:dem":225,
    "gn:feature_class":"P",
    "gn:feature_code":"PPL",
    "gn:name":"Majanggol",
    "gn:population":0,
    "gn:timezone":"Asia/Seoul",
    "iso:country":"KR",
    "name:kor_x_preferred":[
        "\ub9c8\uc7a5\uace8"
    ],
    "wof:name":"Majanggol",
    "wof:placetype":"locality"
},
  "geometry": {"coordinates":[128.33432999999999,37.07266],"type":"Point"}
}