{
  "type": "Feature",
  "properties": {
    "gn:admin1_code":"12.0",
    "gn:asciiname":"Kkach'iul",
    "gn:country_code":"KR",
    "gn:dem":37,
    "gn:feature_class":"P",
    "gn:feature_code":"PPL",
    "gn:name":"Kkach\u2019iul",
    "gn:population":0,
    "gn:timezone":"Asia/Seoul",
    "iso:country":"KR",
    "name:kor_x_preferred":[
        "\uae4c\uce58\uc6b8"
    ],
    "name:kor_x_variant":[
        "Kkach\u2019iul"
    ],
    "wof:name":"Kkach'iul",
    "wof:placetype":"locality"
},
  "geometry": {"coordinates":[126.81610999999999,37.5125],"type":"Point"}
}