{
  "type": "Feature",
  "properties": {
    "iso:country":"KR",
    "name:eng_x_preferred":[
        "Geumam 1(il)-dong"
    ],
    "name:kor_x_preferred":[
        "\uae08\uc5541\ub3d9"
    ],
    "qs:gn_local":0,
    "qs:local_max":1112,
    "qs:local_sum":1824,
    "qs:localhoods":7,
    "qs:name":"\uae08\uc5541\ub3d9",
    "qs:name_adm0":"\ud55c\uad6d",
    "qs:name_adm1":"\uc804\ub77c\ubd81\ub3c4",
    "qs:name_adm2":"\uc804\uc8fc\uc2dc",
    "qs:name_lau":"\ub355\uc9c4\uad6c",
    "qs:name_local":"\ub355\uc9c4\uad6c",
    "qs:photo_max":2,
    "qs:photo_sum":4,
    "qs:placetype":"Suburb",
    "qs:quad_count":3,
    "qs:woe_adm0":23424868,
    "qs:woe_adm1":2345964,
    "qs:woe_adm2":28289219,
    "qs:woe_lau":28997218,
    "qs:woe_local":28997218,
    "qs:woe_ver":"7.10.0",
    "wof:lang":[
        "kor"
    ],
    "wof:name":"Geumam 1(il)-dong",
    "wof:placetype":"neighbourhood"
},
  "geometry": {"coordinates":[127.12829600000001,35.832288],"type":"Point"}
}