{
  "type": "Feature",
  "properties": {
    "gn:admin1_code":"5.0",
    "gn:asciiname":"Sansu",
    "gn:country_code":"KR",
    "gn:dem":86,
    "gn:feature_class":"P",
    "gn:feature_code":"PPL",
    "gn:name":"Sansu",
    "gn:population":0,
    "gn:timezone":"Asia/Seoul",
    "iso:country":"KR",
    "name:kor_x_preferred":[
        "\uc0b0\uc218"
    ],
    "name:und_x_variant":[
        "\uc0b0\uc218\ub9ac",
        "Sansu-ri",
        "Sansu"
    ],
    "wof:name":"Sansu",
    "wof:placetype":"locality"
},
  "geometry": {"coordinates":[127.53795,36.43533],"type":"Point"}
}