{
  "type": "Feature",
  "properties": {
    "gn:admin1_code":"17.0",
    "gn:asciiname":"Wonyongyon",
    "gn:country_code":"KR",
    "gn:dem":12,
    "gn:feature_class":"P",
    "gn:feature_code":"PPL",
    "gn:name":"W\u014fnyongy\u014fn",
    "gn:population":0,
    "gn:timezone":"Asia/Seoul",
    "iso:country":"KR",
    "name:und_x_variant":[
        "\uc6d0\uc6a9\uc5f0",
        "W\u014fnyongy\u014fn"
    ],
    "wof:name":"Wonyongyon",
    "wof:placetype":"locality"
},
  "geometry": {"coordinates":[126.6125,36.8671],"type":"Point"}
}