{
  "type": "Feature",
  "properties": {
    "gn:admin1_code":"17.0",
    "gn:asciiname":"Hwiyujae",
    "gn:country_code":"KR",
    "gn:dem":59,
    "gn:feature_class":"P",
    "gn:feature_code":"PPL",
    "gn:name":"Hwiyujae",
    "gn:population":0,
    "gn:timezone":"Asia/Seoul",
    "iso:country":"KR",
    "name:und_x_variant":[
        "\ud718\uc720\uc7ac",
        "Hwiyujae"
    ],
    "wof:name":"Hwiyujae",
    "wof:placetype":"locality"
},
  "geometry": {"coordinates":[126.6528,36.395],"type":"Point"}
}