{
  "type": "Feature",
  "properties": {
    "gn:admin1_code":"14.0",
    "gn:asciiname":"Ttibat",
    "gn:country_code":"KR",
    "gn:dem":30,
    "gn:feature_class":"P",
    "gn:feature_code":"PPL",
    "gn:name":"Ttibat",
    "gn:population":0,
    "gn:timezone":"Asia/Seoul",
    "iso:country":"KR",
    "name:und_x_variant":[
        "\ub760\ubc2d",
        "Ttibat"
    ],
    "wof:name":"Ttibat",
    "wof:placetype":"locality"
},
  "geometry": {"coordinates":[128.39401999999998,35.91324],"type":"Point"}
}