{
  "type": "Feature",
  "properties": {
    "gn:admin1_code":"13.0",
    "gn:asciiname":"Daechumal",
    "gn:country_code":"KR",
    "gn:dem":22,
    "gn:feature_class":"P",
    "gn:feature_code":"PPL",
    "gn:name":"Daechumal",
    "gn:population":0,
    "gn:timezone":"Asia/Seoul",
    "iso:country":"KR",
    "name:kor_x_preferred":[
        "\ub300\ucd94\ub9d0"
    ],
    "name:und_x_variant":[
        "Daechumal"
    ],
    "wof:name":"Daechumal",
    "wof:placetype":"locality"
},
  "geometry": {"coordinates":[127.2022,37.5766],"type":"Point"}
}