{
  "type": "Feature",
  "properties": {
    "gn:admin1_code":"16.0",
    "gn:asciiname":"Jungnimdong",
    "gn:country_code":"KR",
    "gn:dem":87,
    "gn:feature_class":"P",
    "gn:feature_code":"PPL",
    "gn:name":"Jungnimdong",
    "gn:population":0,
    "gn:timezone":"Asia/Seoul",
    "iso:country":"KR",
    "name:kor_x_preferred":[
        "\uc8fd\ub9bc\ub3d9"
    ],
    "wof:name":"Jungnimdong",
    "wof:placetype":"locality"
},
  "geometry": {"coordinates":[126.7715,35.2691],"type":"Point"}
}