{
  "type": "Feature",
  "properties": {
    "gn:admin1_code":"17.0",
    "gn:asciiname":"Choppawi",
    "gn:country_code":"KR",
    "gn:dem":177,
    "gn:feature_class":"P",
    "gn:feature_code":"PPL",
    "gn:name":"Ch\u014fppawi",
    "gn:population":0,
    "gn:timezone":"Asia/Seoul",
    "iso:country":"KR",
    "name:und_x_variant":[
        "\uc811\ubc14\uc704",
        "Ch\u014fppawi"
    ],
    "wof:name":"Choppawi",
    "wof:placetype":"locality"
},
  "geometry": {"coordinates":[127.3565,36.1551],"type":"Point"}
}