{
  "type": "Feature",
  "properties": {
    "gn:admin1_code":"20.0",
    "gn:asciiname":"Saemol",
    "gn:country_code":"KR",
    "gn:dem":51,
    "gn:feature_class":"P",
    "gn:feature_code":"PPL",
    "gn:name":"Saemol",
    "gn:population":0,
    "gn:timezone":"Asia/Seoul",
    "iso:country":"KR",
    "name:und_x_variant":[
        "\uc0c8\ubab0",
        "Saemol"
    ],
    "wof:name":"Saemol",
    "wof:placetype":"locality"
},
  "geometry": {"coordinates":[128.24871000000002,35.21949],"type":"Point"}
}