{
  "type": "Feature",
  "properties": {
    "gn:admin1_code":"14.0",
    "gn:asciiname":"Sarigol",
    "gn:country_code":"KR",
    "gn:dem":110,
    "gn:feature_class":"P",
    "gn:feature_code":"PPL",
    "gn:name":"Sarigol",
    "gn:population":0,
    "gn:timezone":"Asia/Seoul",
    "iso:country":"KR",
    "name:kor_x_preferred":[
        "\uc0ac\ub9ac\uace8"
    ],
    "wof:name":"Sarigol",
    "wof:placetype":"locality"
},
  "geometry": {"coordinates":[129.24921000000001,36.13287],"type":"Point"}
}