{
  "type": "Feature",
  "properties": {
    "gn:admin1_code":"6.0",
    "gn:asciiname":"Norumok",
    "gn:country_code":"KR",
    "gn:dem":113,
    "gn:feature_class":"P",
    "gn:feature_code":"PPL",
    "gn:name":"Norumok",
    "gn:population":0,
    "gn:timezone":"Asia/Seoul",
    "iso:country":"KR",
    "name:kor_x_preferred":[
        "\ub178\ub8e8\ubaa9"
    ],
    "name:und_x_variant":[
        "\ub180\ubaa9",
        "Nolmok",
        "Norumok"
    ],
    "wof:name":"Norumok",
    "wof:placetype":"locality"
},
  "geometry": {"coordinates":[127.76860000000001,37.9001],"type":"Point"}
}