{
  "type": "Feature",
  "properties": {
    "gn:admin1_code":"6.0",
    "gn:asciiname":"Taegu-dong",
    "gn:country_code":"KR",
    "gn:dem":31,
    "gn:feature_class":"P",
    "gn:feature_code":"PPL",
    "gn:name":"Taegu-dong",
    "gn:population":0,
    "gn:timezone":"Asia/Seoul",
    "iso:country":"KR",
    "name:und_x_variant":[
        "\ub300\uad6c\ub3d9",
        "Taegu-dong"
    ],
    "wof:name":"Taegu-dong",
    "wof:placetype":"locality"
},
  "geometry": {"coordinates":[129.13630000000001,37.4676],"type":"Point"}
}