{
  "type": "Feature",
  "properties": {
    "gn:admin1_code":"6.0",
    "gn:asciiname":"Ch'onggye-dong",
    "gn:country_code":"KR",
    "gn:dem":695,
    "gn:feature_class":"P",
    "gn:feature_code":"PPL",
    "gn:name":"Ch\u2019\u014fnggye-dong",
    "gn:population":0,
    "gn:timezone":"Asia/Seoul",
    "iso:country":"KR",
    "name:kor_x_preferred":[
        "Ch\u2019\u014fnggye-dong"
    ],
    "name:kor_x_variant":[
        "\uccad\uacc4\ub3d9"
    ],
    "wof:name":"Ch'onggye-dong",
    "wof:placetype":"locality"
},
  "geometry": {"coordinates":[128.40528,37.71861],"type":"Point"}
}