{
  "type": "Feature",
  "properties": {
    "gn:admin1_code":"3.0",
    "gn:asciiname":"Mijae",
    "gn:country_code":"KR",
    "gn:dem":201,
    "gn:feature_class":"P",
    "gn:feature_code":"PPL",
    "gn:name":"Mijae",
    "gn:population":0,
    "gn:timezone":"Asia/Seoul",
    "iso:country":"KR",
    "name:und_x_variant":[
        "\ubbf8\uc7ac",
        "Mijae"
    ],
    "wof:name":"Mijae",
    "wof:placetype":"locality"
},
  "geometry": {"coordinates":[127.09144000000001,35.70193],"type":"Point"}
}