{
  "type": "Feature",
  "properties": {
    "gn:admin1_code":"13.0",
    "gn:asciiname":"Jaun",
    "gn:country_code":"KR",
    "gn:dem":74,
    "gn:feature_class":"P",
    "gn:feature_code":"PPL",
    "gn:name":"Jaun",
    "gn:population":0,
    "gn:timezone":"Asia/Seoul",
    "iso:country":"KR",
    "name:kor_x_preferred":[
        "\uc790\uc6b4"
    ],
    "name:und_x_variant":[
        "\uc790\uc6b4",
        "Jaun"
    ],
    "wof:name":"Jaun",
    "wof:placetype":"locality"
},
  "geometry": {"coordinates":[127.2427,37.5848],"type":"Point"}
}