{
  "type": "Feature",
  "properties": {
    "gn:admin1_code":"13.0",
    "gn:asciiname":"Jaun",
    "gn:country_code":"KR",
    "gn:dem":74,
    "gn:feature_class":"P",
    "gn:feature_code":"PPL",
    "gn:name":"Jaun",
    "gn:population":0,
    "gn:timezone":"Asia/Seoul",
    "iso:country":"KR",
    "name:als_x_preferred":[
        "Jaun"
    ],
    "name:ceb_x_preferred":[
        "Jaun"
    ],
    "name:deu_x_preferred":[
        "Jaun"
    ],
    "name:epo_x_preferred":[
        "Jaun"
    ],
    "name:eus_x_preferred":[
        "Jaun"
    ],
    "name:fra_x_preferred":[
        "Jaun"
    ],
    "name:ita_x_preferred":[
        "Jaun"
    ],
    "name:kor_x_preferred":[
        "\uc790\uc6b4"
    ],
    "name:lmo_x_preferred":[
        "Jaun"
    ],
    "name:msa_x_preferred":[
        "Jaun"
    ],
    "name:nld_x_preferred":[
        "Jaun"
    ],
    "name:nno_x_preferred":[
        "Jaun"
    ],
    "name:pms_x_preferred":[
        "Jaun"
    ],
    "name:por_x_preferred":[
        "Jaun"
    ],
    "name:roh_x_preferred":[
        "Jaun"
    ],
    "name:spa_x_preferred":[
        "Jaun"
    ],
    "name:sqi_x_preferred":[
        "Jaun"
    ],
    "name:swe_x_preferred":[
        "Jaun"
    ],
    "name:vol_x_preferred":[
        "Jaun"
    ],
    "name:war_x_preferred":[
        "Jaun"
    ],
    "wof:name":"Jaun",
    "wof:placetype":"locality"
},
  "geometry": {"coordinates":[127.2427,37.5848],"type":"Point"}
}