{
  "type": "Feature",
  "properties": {
    "gn:admin1_code":"14.0",
    "gn:asciiname":"Kkaribak-kol",
    "gn:country_code":"KR",
    "gn:dem":451,
    "gn:feature_class":"P",
    "gn:feature_code":"PPL",
    "gn:name":"Kkaribak-kol",
    "gn:population":0,
    "gn:timezone":"Asia/Seoul",
    "iso:country":"KR",
    "name:und_x_variant":[
        "\uae4c\ub9ac\ubc2d\uace8",
        "Kkaribak-kol"
    ],
    "wof:name":"Kkaribak-kol",
    "wof:placetype":"locality"
},
  "geometry": {"coordinates":[127.9243,36.0224],"type":"Point"}
}