{
  "type": "Feature",
  "properties": {
    "gn:admin1_code":"16.0",
    "gn:asciiname":"Paekhwa",
    "gn:country_code":"KR",
    "gn:dem":32,
    "gn:feature_class":"P",
    "gn:feature_code":"PPL",
    "gn:name":"Paekhwa",
    "gn:population":0,
    "gn:timezone":"Asia/Seoul",
    "iso:country":"KR",
    "name:kor_x_preferred":[
        "\ubc31\ud654"
    ],
    "name:und_x_variant":[
        "Paekhwa-dong",
        "Paekhwa"
    ],
    "wof:name":"Paekhwa",
    "wof:placetype":"locality"
},
  "geometry": {"coordinates":[126.70778,34.48472],"type":"Point"}
}