{
  "type": "Feature",
  "properties": {
    "gn:admin1_code":"20.0",
    "gn:asciiname":"Panggok",
    "gn:country_code":"KR",
    "gn:dem":320,
    "gn:feature_class":"P",
    "gn:feature_code":"PPL",
    "gn:name":"Panggok",
    "gn:population":0,
    "gn:timezone":"Asia/Seoul",
    "iso:country":"KR",
    "wof:name":"Panggok",
    "wof:placetype":"locality"
},
  "geometry": {"coordinates":[127.77639000000001,35.41972],"type":"Point"}
}