{
  "type": "Feature",
  "properties": {
    "gn:admin1_code":"17.0",
    "gn:asciiname":"Hodunamu-gol",
    "gn:country_code":"KR",
    "gn:dem":40,
    "gn:feature_class":"P",
    "gn:feature_code":"PPL",
    "gn:name":"Hodunamu-gol",
    "gn:population":0,
    "gn:timezone":"Asia/Seoul",
    "iso:country":"KR",
    "name:und_x_variant":[
        "Pan\u2019gyo-ri",
        "Sindae-ri",
        "Hodunamukol",
        "\ud638\ub450\ub098\ubb34\uace8",
        "Hodunamu-gol"
    ],
    "wof:name":"Hodunamu-gol",
    "wof:placetype":"locality"
},
  "geometry": {"coordinates":[126.99120000000001,36.315],"type":"Point"}
}