{
  "type": "Feature",
  "properties": {
    "gn:admin1_code":"17.0",
    "gn:asciiname":"Sosikgol",
    "gn:country_code":"KR",
    "gn:dem":54,
    "gn:feature_class":"P",
    "gn:feature_code":"PPL",
    "gn:name":"Sosikgol",
    "gn:population":0,
    "gn:timezone":"Asia/Seoul",
    "iso:country":"KR",
    "name:kor_x_preferred":[
        "\uc18c\uc2dd\uace8"
    ],
    "wof:name":"Sosikgol",
    "wof:placetype":"locality"
},
  "geometry": {"coordinates":[127.16817,36.73574],"type":"Point"}
}