{
  "type": "Feature",
  "properties": {
    "gn:admin1_code":"20.0",
    "gn:asciiname":"Sangp'a",
    "gn:country_code":"KR",
    "gn:dem":68,
    "gn:feature_class":"P",
    "gn:feature_code":"PPL",
    "gn:name":"Sangp\u2019a",
    "gn:population":0,
    "gn:timezone":"Asia/Seoul",
    "iso:country":"KR",
    "name:und_x_variant":[
        "\uc0c1\ud30c",
        "Sangp\u2019a"
    ],
    "wof:name":"Sangp'a",
    "wof:placetype":"locality"
},
  "geometry": {"coordinates":[128.40468000000001,35.23361],"type":"Point"}
}