{
  "type": "Feature",
  "properties": {
    "gn:admin1_code":"17.0",
    "gn:asciiname":"Worani",
    "gn:country_code":"KR",
    "gn:dem":94,
    "gn:feature_class":"P",
    "gn:feature_code":"PPL",
    "gn:name":"Worani",
    "gn:population":0,
    "gn:timezone":"Asia/Seoul",
    "iso:country":"KR",
    "name:kor_x_preferred":[
        "\uc6d4\uc548\uc774"
    ],
    "wof:name":"Worani",
    "wof:placetype":"locality"
},
  "geometry": {"coordinates":[127.08118,36.62334],"type":"Point"}
}