{
  "type": "Feature",
  "properties": {
    "gn:admin1_code":"5.0",
    "gn:asciiname":"Keuntteum",
    "gn:country_code":"KR",
    "gn:dem":46,
    "gn:feature_class":"P",
    "gn:feature_code":"PPL",
    "gn:name":"Keuntteum",
    "gn:population":0,
    "gn:timezone":"Asia/Seoul",
    "iso:country":"KR",
    "name:kor_x_preferred":[
        "\ud070\ub738"
    ],
    "wof:name":"Keuntteum",
    "wof:placetype":"locality"
},
  "geometry": {"coordinates":[127.36251,36.60303],"type":"Point"}
}