{
  "type": "Feature",
  "properties": {
    "gn:admin1_code":"12.0",
    "gn:asciiname":"Koumdal",
    "gn:country_code":"KR",
    "gn:dem":21,
    "gn:feature_class":"P",
    "gn:feature_code":"PPL",
    "gn:name":"Ko\u016dmdal",
    "gn:population":0,
    "gn:timezone":"Asia/Seoul",
    "iso:country":"KR",
    "name:kor_x_preferred":[
        "\uace0\uc74c\ub2ec"
    ],
    "name:kor_x_variant":[
        "Ko\u016dmdal"
    ],
    "wof:name":"Koumdal",
    "wof:placetype":"locality"
},
  "geometry": {"coordinates":[126.61444,37.61833],"type":"Point"}
}