{
  "type": "Feature",
  "properties": {
    "gn:admin1_code":"20.0",
    "gn:asciiname":"Ppondok",
    "gn:country_code":"KR",
    "gn:dem":30,
    "gn:feature_class":"P",
    "gn:feature_code":"PPL",
    "gn:name":"Pp\u014fnd\u014fk",
    "gn:population":0,
    "gn:timezone":"Asia/Seoul",
    "iso:country":"KR",
    "name:und_x_variant":[
        "\ubed4\ub355",
        "Pp\u014fnd\u014fk"
    ],
    "wof:name":"Ppondok",
    "wof:placetype":"locality"
},
  "geometry": {"coordinates":[128.45507000000001,35.04272],"type":"Point"}
}