{
  "type": "Feature",
  "properties": {
    "gn:admin1_code":"13.0",
    "gn:asciiname":"Seryusam-dong",
    "gn:country_code":"KR",
    "gn:dem":50,
    "gn:feature_class":"P",
    "gn:feature_code":"PPL",
    "gn:name":"Seryusam-dong",
    "gn:population":0,
    "gn:timezone":"Asia/Seoul",
    "iso:country":"KR",
    "name:und_x_variant":[
        "\uc138\ub9583\ub3d9",
        "Seryusam-dong"
    ],
    "wof:name":"Seryusam-dong",
    "wof:placetype":"locality"
},
  "geometry": {"coordinates":[127.015,37.25972],"type":"Point"}
}