{
  "type": "Feature",
  "properties": {
    "gn:admin1_code":"13.0",
    "gn:asciiname":"Simyo-gol",
    "gn:country_code":"KR",
    "gn:dem":52,
    "gn:feature_class":"P",
    "gn:feature_code":"PPL",
    "gn:name":"Simyo-gol",
    "gn:population":0,
    "gn:timezone":"Asia/Seoul",
    "iso:country":"KR",
    "name:und_x_variant":[
        "\uc2dc\ubb18\uace8",
        "Simyo-gol"
    ],
    "wof:name":"Simyo-gol",
    "wof:placetype":"locality"
},
  "geometry": {"coordinates":[126.96611,37.19528],"type":"Point"}
}