{
  "type": "Feature",
  "properties": {
    "gn:admin1_code":"16.0",
    "gn:asciiname":"Osan",
    "gn:country_code":"KR",
    "gn:dem":33,
    "gn:feature_class":"P",
    "gn:feature_code":"PPL",
    "gn:name":"Osan",
    "gn:population":0,
    "gn:timezone":"Asia/Seoul",
    "iso:country":"KR",
    "name:kor_x_preferred":[
        "\uc624\uc0b0"
    ],
    "name:und_x_variant":[
        "Osan-ni",
        "Tosan-ni",
        "Osan"
    ],
    "wof:name":"Osan",
    "wof:placetype":"locality"
},
  "geometry": {"coordinates":[127.45869,34.62895],"type":"Point"}
}