{
  "type": "Feature",
  "properties": {
    "gn:admin1_code":"3.0",
    "gn:asciiname":"Kongdok",
    "gn:country_code":"KR",
    "gn:dem":55,
    "gn:feature_class":"P",
    "gn:feature_code":"PPL",
    "gn:name":"Kongd\u014fk",
    "gn:population":0,
    "gn:timezone":"Asia/Seoul",
    "iso:country":"KR",
    "name:und_x_variant":[
        "\uacf5\ub355",
        "Kongd\u014fk"
    ],
    "wof:name":"Kongdok",
    "wof:placetype":"locality"
},
  "geometry": {"coordinates":[127.20199,35.84779],"type":"Point"}
}