{
  "type": "Feature",
  "properties": {
    "gn:admin1_code":"6.0",
    "gn:asciiname":"Chungduru",
    "gn:country_code":"KR",
    "gn:dem":485,
    "gn:feature_class":"P",
    "gn:feature_code":"PPL",
    "gn:name":"Chungduru",
    "gn:population":0,
    "gn:timezone":"Asia/Seoul",
    "iso:country":"KR",
    "name:kor_x_preferred":[
        "\uc911\ub450\ub8e8"
    ],
    "wof:name":"Chungduru",
    "wof:placetype":"locality"
},
  "geometry": {"coordinates":[128.56299999999999,37.5502],"type":"Point"}
}