{
  "type": "Feature",
  "properties": {
    "gn:admin1_code":"14.0",
    "gn:asciiname":"Songhyon",
    "gn:cc2":"KR",
    "gn:country_code":"KR",
    "gn:dem":283,
    "gn:feature_class":"P",
    "gn:feature_code":"PPL",
    "gn:name":"S\u014fnghy\u014fn",
    "gn:population":0,
    "gn:timezone":"Asia/Seoul",
    "iso:country":"KR",
    "name:und_x_variant":[
        "Nams\u014fng-hy\u014fn",
        "S\u014fnghy\u014fn"
    ],
    "wof:name":"Songhyon",
    "wof:placetype":"locality"
},
  "geometry": {"coordinates":[128.71666999999999,35.71667],"type":"Point"}
}