{
  "type": "Feature",
  "properties": {
    "gn:admin1_code":"14.0",
    "gn:asciiname":"Malbawi",
    "gn:cc2":"KR",
    "gn:country_code":"KR",
    "gn:dem":221,
    "gn:feature_class":"P",
    "gn:feature_code":"PPL",
    "gn:name":"Malbawi",
    "gn:population":0,
    "gn:timezone":"Asia/Seoul",
    "iso:country":"KR",
    "name:und_x_variant":[
        "Maam-ni",
        "Malbawi"
    ],
    "wof:name":"Malbawi",
    "wof:placetype":"locality"
},
  "geometry": {"coordinates":[127.98556000000001,36.61167],"type":"Point"}
}