{
  "type": "Feature",
  "properties": {
    "gn:admin1_code":"14.0",
    "gn:asciiname":"Songp'yong-ni",
    "gn:country_code":"KR",
    "gn:dem":321,
    "gn:feature_class":"P",
    "gn:feature_code":"PPL",
    "gn:name":"Songp\u2019y\u014fng-ni",
    "gn:population":0,
    "gn:timezone":"Asia/Seoul",
    "iso:country":"KR",
    "wof:name":"Songp'yong-ni",
    "wof:placetype":"locality"
},
  "geometry": {"coordinates":[128.31666999999999,36.75],"type":"Point"}
}