{
  "type": "Feature",
  "properties": {
    "gn:admin1_code":"13.0",
    "gn:asciiname":"Bakkadyongmeo-ri",
    "gn:country_code":"KR",
    "gn:dem":67,
    "gn:feature_class":"P",
    "gn:feature_code":"PPL",
    "gn:name":"Bakkadyongmeo-ri",
    "gn:population":0,
    "gn:timezone":"Asia/Seoul",
    "iso:country":"KR",
    "name:und_x_variant":[
        "\ubc14\uae65\uc6a9\uba38\ub9ac",
        "Bakkadyongmeo-ri",
        "Pakkadyongm\u014f-ri"
    ],
    "wof:name":"Bakkadyongmeo-ri",
    "wof:placetype":"locality"
},
  "geometry": {"coordinates":[127.67361,37.36583],"type":"Point"}
}