{
  "type": "Feature",
  "properties": {
    "gn:admin1_code":"16.0",
    "gn:asciiname":"Songho",
    "gn:cc2":"KR",
    "gn:country_code":"KR",
    "gn:dem":3,
    "gn:feature_class":"P",
    "gn:feature_code":"PPL",
    "gn:name":"Songho",
    "gn:population":0,
    "gn:timezone":"Asia/Seoul",
    "iso:country":"KR",
    "name:und_x_variant":[
        "Sh\u014dko-ri",
        "Songho-ri",
        "Songho"
    ],
    "wof:name":"Songho",
    "wof:placetype":"locality"
},
  "geometry": {"coordinates":[126.46666999999999,34.56667],"type":"Point"}
}