{
  "type": "Feature",
  "properties": {
    "gn:admin1_code":"13.0",
    "gn:asciiname":"Paekkyo",
    "gn:country_code":"KR",
    "gn:dem":45,
    "gn:feature_class":"P",
    "gn:feature_code":"PPL",
    "gn:name":"Paekkyo",
    "gn:population":0,
    "gn:timezone":"Asia/Seoul",
    "iso:country":"KR",
    "name:kor_x_preferred":[
        "\ubc31\uad50"
    ],
    "name:und_x_variant":[
        "\ubc31\uad50",
        "Paekkyo"
    ],
    "wof:name":"Paekkyo",
    "wof:placetype":"locality"
},
  "geometry": {"coordinates":[127.12430000000001,37.5822],"type":"Point"}
}