{
  "type": "Feature",
  "properties": {
    "gn:admin1_code":"13.0",
    "gn:asciiname":"Odaegol",
    "gn:country_code":"KR",
    "gn:dem":60,
    "gn:feature_class":"P",
    "gn:feature_code":"PPL",
    "gn:name":"Odaegol",
    "gn:population":0,
    "gn:timezone":"Asia/Seoul",
    "iso:country":"KR",
    "name:kor_x_preferred":[
        "\uc624\ub300\uace8"
    ],
    "name:und_x_variant":[
        "Odaegol"
    ],
    "wof:name":"Odaegol",
    "wof:placetype":"locality"
},
  "geometry": {"coordinates":[127.42829999999999,37.72659],"type":"Point"}
}