{
  "type": "Feature",
  "properties": {
    "gn:admin1_code":"17.0",
    "gn:asciiname":"Yongbangch'igogae",
    "gn:country_code":"KR",
    "gn:dem":83,
    "gn:feature_class":"P",
    "gn:feature_code":"PPL",
    "gn:name":"Yongbangch\u2019igogae",
    "gn:population":0,
    "gn:timezone":"Asia/Seoul",
    "iso:country":"KR",
    "name:und_x_variant":[
        "\uc6a9\ubc29\uce58\uace0\uac1c",
        "Yongbangch\u2019igogae"
    ],
    "wof:name":"Yongbangch'igogae",
    "wof:placetype":"locality"
},
  "geometry": {"coordinates":[126.6593,36.6421],"type":"Point"}
}