{
  "type": "Feature",
  "properties": {
    "gn:admin1_code":"14.0",
    "gn:asciiname":"Deokjeom",
    "gn:country_code":"KR",
    "gn:dem":280,
    "gn:feature_class":"P",
    "gn:feature_code":"PPL",
    "gn:name":"Deokjeom",
    "gn:population":0,
    "gn:timezone":"Asia/Seoul",
    "iso:country":"KR",
    "name:kor_x_preferred":[
        "\ub355\uc810"
    ],
    "wof:name":"Deokjeom",
    "wof:placetype":"locality"
},
  "geometry": {"coordinates":[128.69046,36.92499],"type":"Point"}
}