{
  "type": "Feature",
  "properties": {
    "gn:admin1_code":"13.0",
    "gn:asciiname":"Jungpyeong",
    "gn:country_code":"KR",
    "gn:dem":69,
    "gn:feature_class":"P",
    "gn:feature_code":"PPL",
    "gn:name":"Jungpyeong",
    "gn:population":0,
    "gn:timezone":"Asia/Seoul",
    "iso:country":"KR",
    "name:kor_x_preferred":[
        "\uc911\ud3c9"
    ],
    "name:und_x_variant":[
        "\uc911\ud3c9",
        "Jungpyeong"
    ],
    "wof:name":"Jungpyeong",
    "wof:placetype":"locality"
},
  "geometry": {"coordinates":[127.49469999999999,37.5076],"type":"Point"}
}