{
  "type": "Feature",
  "properties": {
    "gn:admin1_code":"14.0",
    "gn:asciiname":"Deokchon",
    "gn:country_code":"KR",
    "gn:dem":68,
    "gn:feature_class":"P",
    "gn:feature_code":"PPL",
    "gn:name":"Deokchon",
    "gn:population":0,
    "gn:timezone":"Asia/Seoul",
    "iso:country":"KR",
    "name:kor_x_preferred":[
        "\ub355\ucd0c"
    ],
    "wof:name":"Deokchon",
    "wof:placetype":"locality"
},
  "geometry": {"coordinates":[128.83625000000001,35.94493],"type":"Point"}
}