{
  "type": "Feature",
  "properties": {
    "gn:admin1_code":"14.0",
    "gn:asciiname":"Maek-kol",
    "gn:country_code":"KR",
    "gn:dem":60,
    "gn:feature_class":"P",
    "gn:feature_code":"PPL",
    "gn:name":"Maek-kol",
    "gn:population":0,
    "gn:timezone":"Asia/Seoul",
    "iso:country":"KR",
    "name:und_x_variant":[
        "\ub9f7\uace8",
        "Maek-kol"
    ],
    "wof:name":"Maek-kol",
    "wof:placetype":"locality"
},
  "geometry": {"coordinates":[128.2578,36.4652],"type":"Point"}
}