{
  "type": "Feature",
  "properties": {
    "gn:admin1_code":"16.0",
    "gn:admin2_code":"Chindo-gun",
    "gn:asciiname":"Yeongsan",
    "gn:country_code":"KR",
    "gn:dem":39,
    "gn:feature_class":"P",
    "gn:feature_code":"PPL",
    "gn:name":"Yeongsan",
    "gn:population":0,
    "gn:timezone":"Asia/Seoul",
    "iso:country":"KR",
    "name:ceb_x_preferred":[
        "Yeongsan-myeon"
    ],
    "name:fra_x_preferred":[
        "Yongsan"
    ],
    "name:kor_x_preferred":[
        "\uc601\uc0b0"
    ],
    "name:kor_x_variant":[
        "\uc601\uc0b0\uba74"
    ],
    "name:swe_x_preferred":[
        "Yeongsan-myeon"
    ],
    "name:und_x_variant":[
        "Y\u014fngsal-li"
    ],
    "wof:name":"Yeongsan",
    "wof:placetype":"locality"
},
  "geometry": {"coordinates":[126.27443999999998,34.45056],"type":"Point"}
}