{
  "type": "Feature",
  "properties": {
    "gn:admin1_code":"14.0",
    "gn:asciiname":"Hwangjeong",
    "gn:country_code":"KR",
    "gn:dem":401,
    "gn:feature_class":"P",
    "gn:feature_code":"PPL",
    "gn:name":"Hwangjeong",
    "gn:population":0,
    "gn:timezone":"Asia/Seoul",
    "iso:country":"KR",
    "name:kor_x_preferred":[
        "\ud669\uc815"
    ],
    "wof:name":"Hwangjeong",
    "wof:placetype":"locality"
},
  "geometry": {"coordinates":[128.79411999999999,36.77169],"type":"Point"}
}