{
  "type": "Feature",
  "properties": {
    "gn:admin1_code":"16.0",
    "gn:asciiname":"Maryeon",
    "gn:country_code":"KR",
    "gn:dem":77,
    "gn:feature_class":"P",
    "gn:feature_code":"PPL",
    "gn:name":"Maryeon",
    "gn:population":0,
    "gn:timezone":"Asia/Seoul",
    "iso:country":"KR",
    "name:kor_x_preferred":[
        "\uc5ec\uc2dc\uace8"
    ],
    "name:kor_x_variant":[
        "\ub9c8\ub828"
    ],
    "name:und_x_variant":[
        "Mohangdo",
        "Maryeon"
    ],
    "wof:name":"Maryeon",
    "wof:placetype":"locality"
},
  "geometry": {"coordinates":[126.54778,34.34996],"type":"Point"}
}