{
  "type": "Feature",
  "properties": {
    "gn:admin1_code":"17.0",
    "gn:asciiname":"Husaengchon",
    "gn:country_code":"KR",
    "gn:dem":18,
    "gn:feature_class":"P",
    "gn:feature_code":"PPL",
    "gn:name":"Husaengchon",
    "gn:population":0,
    "gn:timezone":"Asia/Seoul",
    "iso:country":"KR",
    "name:und_x_variant":[
        "\ud6c4\uc0dd\ucd0c",
        "Husaeng-ch\u2019on",
        "Husaengchon"
    ],
    "wof:name":"Husaengchon",
    "wof:placetype":"locality"
},
  "geometry": {"coordinates":[127.17229,36.95527],"type":"Point"}
}