{
  "type": "Feature",
  "properties": {
    "gn:admin1_code":"14.0",
    "gn:asciiname":"Seodangmi",
    "gn:country_code":"KR",
    "gn:dem":118,
    "gn:feature_class":"P",
    "gn:feature_code":"PPL",
    "gn:name":"Seodangmi",
    "gn:population":0,
    "gn:timezone":"Asia/Seoul",
    "iso:country":"KR",
    "name:kor_x_preferred":[
        "\uc11c\ub2f9\ubbf8"
    ],
    "wof:name":"Seodangmi",
    "wof:placetype":"locality"
},
  "geometry": {"coordinates":[128.36673999999999,36.65369000000001],"type":"Point"}
}