{
  "type": "Feature",
  "properties": {
    "gn:admin1_code":"17.0",
    "gn:asciiname":"Manggeori",
    "gn:country_code":"KR",
    "gn:dem":28,
    "gn:feature_class":"P",
    "gn:feature_code":"PPL",
    "gn:name":"Manggeori",
    "gn:population":0,
    "gn:timezone":"Asia/Seoul",
    "iso:country":"KR",
    "name:kor_x_preferred":[
        "\ub9dd\uac70\ub9ac"
    ],
    "wof:name":"Manggeori",
    "wof:placetype":"locality"
},
  "geometry": {"coordinates":[127.15105,36.2829],"type":"Point"}
}