{
  "type": "Feature",
  "properties": {
    "gn:admin1_code":"14.0",
    "gn:asciiname":"Won-dong",
    "gn:country_code":"KR",
    "gn:dem":99,
    "gn:feature_class":"P",
    "gn:feature_code":"PPL",
    "gn:name":"W\u014fn-dong",
    "gn:population":0,
    "gn:timezone":"Asia/Seoul",
    "iso:country":"KR",
    "name:und_x_variant":[
        "\uc6d0\ub3d9",
        "W\u014fn-dong"
    ],
    "wof:name":"Won-dong",
    "wof:placetype":"locality"
},
  "geometry": {"coordinates":[128.19952000000001,35.96321],"type":"Point"}
}