{
  "type": "Feature",
  "properties": {
    "gn:admin1_code":"14.0",
    "gn:asciiname":"Saemnae",
    "gn:country_code":"KR",
    "gn:dem":329,
    "gn:feature_class":"P",
    "gn:feature_code":"PPL",
    "gn:name":"Saemnae",
    "gn:population":0,
    "gn:timezone":"Asia/Seoul",
    "iso:country":"KR",
    "name:und_x_variant":[
        "\uc0d8\ub0b4",
        "Saemnae"
    ],
    "wof:name":"Saemnae",
    "wof:placetype":"locality"
},
  "geometry": {"coordinates":[128.9024,36.2656],"type":"Point"}
}