{
  "type": "Feature",
  "properties": {
    "gn:admin1_code":"20.0",
    "gn:asciiname":"Maekchong",
    "gn:country_code":"KR",
    "gn:dem":207,
    "gn:feature_class":"P",
    "gn:feature_code":"PPL",
    "gn:name":"Maekch\u014fng",
    "gn:population":0,
    "gn:timezone":"Asia/Seoul",
    "iso:country":"KR",
    "name:und_x_variant":[
        "\ub9e5\uc815",
        "Maekch\u014fng"
    ],
    "wof:name":"Maekchong",
    "wof:placetype":"locality"
},
  "geometry": {"coordinates":[127.80168999999999,35.59535],"type":"Point"}
}