{
  "type": "Feature",
  "properties": {
    "gn:admin1_code":"6.0",
    "gn:asciiname":"Geojugye",
    "gn:country_code":"KR",
    "gn:dem":244,
    "gn:feature_class":"P",
    "gn:feature_code":"PPL",
    "gn:name":"Geojugye",
    "gn:population":0,
    "gn:timezone":"Asia/Seoul",
    "iso:country":"KR",
    "name:kor_x_preferred":[
        "\uac70\uc8fc\uac1c"
    ],
    "name:kor_x_variant":[
        "K\u014fjugae",
        "\uac70\uc8fc\uacc4"
    ],
    "wof:name":"Geojugye",
    "wof:placetype":"locality"
},
  "geometry": {"coordinates":[128.09589,37.82285],"type":"Point"}
}