{
  "type": "Feature",
  "properties": {
    "gn:admin1_code":"20.0",
    "gn:asciiname":"Widan-gol",
    "gn:country_code":"KR",
    "gn:dem":391,
    "gn:feature_class":"P",
    "gn:feature_code":"PPL",
    "gn:name":"Widan-gol",
    "gn:population":0,
    "gn:timezone":"Asia/Seoul",
    "iso:country":"KR",
    "name:und_x_variant":[
        "\uc717\uc548\uace8",
        "Widan-gol"
    ],
    "wof:name":"Widan-gol",
    "wof:placetype":"locality"
},
  "geometry": {"coordinates":[127.61301,35.5595],"type":"Point"}
}