{
  "type": "Feature",
  "properties": {
    "gn:admin1_code":"6.0",
    "gn:asciiname":"Witgwaeseok",
    "gn:country_code":"KR",
    "gn:dem":653,
    "gn:feature_class":"P",
    "gn:feature_code":"PPL",
    "gn:name":"Witgwaeseok",
    "gn:population":0,
    "gn:timezone":"Asia/Seoul",
    "iso:country":"KR",
    "name:kor_x_preferred":[
        "\uc0c1\uad18\uc11d"
    ],
    "name:kor_x_variant":[
        "Sanggwaes\u014fk",
        "\uc717\uad18\uc11d"
    ],
    "wof:name":"Witgwaeseok",
    "wof:placetype":"locality"
},
  "geometry": {"coordinates":[128.14626000000001,37.87954000000001],"type":"Point"}
}