{
  "type": "Feature",
  "properties": {
    "gn:admin1_code":"14.0",
    "gn:asciiname":"Chinsi-gol",
    "gn:country_code":"KR",
    "gn:dem":243,
    "gn:feature_class":"P",
    "gn:feature_code":"PPL",
    "gn:name":"Chinsi-gol",
    "gn:population":0,
    "gn:timezone":"Asia/Seoul",
    "iso:country":"KR",
    "name:und_x_variant":[
        "\uc9c4\uc2dc\uace8",
        "Chinsi-gol"
    ],
    "wof:name":"Chinsi-gol",
    "wof:placetype":"locality"
},
  "geometry": {"coordinates":[129.2758,36.5856],"type":"Point"}
}