{
  "type": "Feature",
  "properties": {
    "gn:admin1_code":"5.0",
    "gn:asciiname":"T'ok-kol",
    "gn:country_code":"KR",
    "gn:dem":148,
    "gn:feature_class":"P",
    "gn:feature_code":"PPL",
    "gn:name":"T\u2019\u014fk-kol",
    "gn:population":0,
    "gn:timezone":"Asia/Seoul",
    "iso:country":"KR",
    "name:und_x_variant":[
        "\ud143\uace8",
        "T\u2019\u014fk-kol"
    ],
    "wof:name":"T'ok-kol",
    "wof:placetype":"locality"
},
  "geometry": {"coordinates":[127.6786,36.139],"type":"Point"}
}