{
  "type": "Feature",
  "properties": {
    "gn:admin1_code":"6.0",
    "gn:asciiname":"Jageunmuran-gol",
    "gn:country_code":"KR",
    "gn:dem":290,
    "gn:feature_class":"P",
    "gn:feature_code":"PPL",
    "gn:name":"Jageunmuran-gol",
    "gn:population":0,
    "gn:timezone":"Asia/Seoul",
    "iso:country":"KR",
    "name:kor_x_preferred":[
        "\uc791\uc740\ubb3c\uc548\uace8"
    ],
    "name:kor_x_variant":[
        "Chag\u016dnmuran-gol"
    ],
    "wof:name":"Jageunmuran-gol",
    "wof:placetype":"locality"
},
  "geometry": {"coordinates":[127.87083,38.06528],"type":"Point"}
}