{
  "type": "Feature",
  "properties": {
    "gn:admin1_code":"20.0",
    "gn:asciiname":"Sohwa",
    "gn:country_code":"KR",
    "gn:dem":136,
    "gn:feature_class":"P",
    "gn:feature_code":"PPL",
    "gn:name":"Sohwa",
    "gn:population":0,
    "gn:timezone":"Asia/Seoul",
    "iso:country":"KR",
    "name:und_x_variant":[
        "\uc18c\ud654",
        "Sohwa"
    ],
    "wof:name":"Sohwa",
    "wof:placetype":"locality"
},
  "geometry": {"coordinates":[128.25763000000001,35.45994],"type":"Point"}
}