{
  "type": "Feature",
  "properties": {
    "gn:admin1_code":"17.0",
    "gn:asciiname":"Soksaemmal",
    "gn:country_code":"KR",
    "gn:dem":31,
    "gn:feature_class":"P",
    "gn:feature_code":"PPL",
    "gn:name":"Soksaemmal",
    "gn:population":0,
    "gn:timezone":"Asia/Seoul",
    "iso:country":"KR",
    "name:und_x_variant":[
        "\uc18d\uc0d8\ub9d0",
        "Soksaemmal"
    ],
    "wof:name":"Soksaemmal",
    "wof:placetype":"locality"
},
  "geometry": {"coordinates":[127.10509,36.77284],"type":"Point"}
}