{
  "type": "Feature",
  "properties": {
    "gn:admin1_code":"20.0",
    "gn:asciiname":"Gamgol",
    "gn:country_code":"KR",
    "gn:dem":144,
    "gn:feature_class":"P",
    "gn:feature_code":"PPL",
    "gn:name":"Gamgol",
    "gn:population":0,
    "gn:timezone":"Asia/Seoul",
    "iso:country":"KR",
    "name:kor_x_preferred":[
        "\uac10\uace8"
    ],
    "name:und_x_variant":[
        "\uac10\ub3d9",
        "Kam-dong",
        "Gamgol"
    ],
    "wof:name":"Gamgol",
    "wof:placetype":"locality"
},
  "geometry": {"coordinates":[128.56496000000001,35.56662],"type":"Point"}
}