{
  "type": "Feature",
  "properties": {
    "iso:country":"KR",
    "qs:name":"\uc625\ub8e1\ub3d9",
    "qs:name_adm0":"\ud55c\uad6d",
    "qs:name_adm1":"\ucda9\uccad\ub0a8\ub3c4",
    "qs:photos":14,
    "qs:photos_1k":3,
    "qs:photos_9k":1,
    "qs:photos_9r":1,
    "qs:photos_all":14,
    "qs:photos_sr":1,
    "qs:placetype":"LocalAdmin",
    "qs:pop_sr":"0",
    "wof:name":"\uc625\ub8e1\ub3d9",
    "wof:placetype":"localadmin"
},
  "geometry": {"coordinates":[127.174987,36.474306],"type":"Point"}
}