{
  "type": "Feature",
  "properties": {
    "gn:admin1_code":"17.0",
    "gn:asciiname":"Ch'iktok-kol",
    "gn:country_code":"KR",
    "gn:dem":53,
    "gn:feature_class":"P",
    "gn:feature_code":"PPL",
    "gn:name":"Ch\u2019ikt\u014fk-kol",
    "gn:population":0,
    "gn:timezone":"Asia/Seoul",
    "iso:country":"KR",
    "name:und_x_variant":[
        "\uce61\ub355\uace8",
        "Ch\u2019ikt\u014fk-kol"
    ],
    "wof:name":"Ch'iktok-kol",
    "wof:placetype":"locality"
},
  "geometry": {"coordinates":[126.9683,36.4222],"type":"Point"}
}