{
  "type": "Feature",
  "properties": {
    "gn:admin1_code":"14.0",
    "gn:asciiname":"Bosu",
    "gn:country_code":"KR",
    "gn:dem":74,
    "gn:feature_class":"P",
    "gn:feature_code":"PPL",
    "gn:name":"Bosu",
    "gn:population":0,
    "gn:timezone":"Asia/Seoul",
    "iso:country":"KR",
    "name:kor_x_preferred":[
        "\ubcf4\uc218"
    ],
    "wof:name":"Bosu",
    "wof:placetype":"locality"
},
  "geometry": {"coordinates":[128.32584,36.60113],"type":"Point"}
}