{
  "type": "Feature",
  "properties": {
    "gn:admin1_code":"5.0",
    "gn:asciiname":"Hwanghak-tong",
    "gn:country_code":"KR",
    "gn:dem":307,
    "gn:feature_class":"P",
    "gn:feature_code":"PPL",
    "gn:name":"Hwanghak-tong",
    "gn:population":0,
    "gn:timezone":"Asia/Seoul",
    "iso:country":"KR",
    "name:kor_x_preferred":[
        "\ud669\ud559\ub3d9"
    ],
    "wof:name":"Hwanghak-tong",
    "wof:placetype":"locality"
},
  "geometry": {"coordinates":[128.3357,37.1287],"type":"Point"}
}