{
  "type": "Feature",
  "properties": {
    "gn:admin1_code":"17.0",
    "gn:asciiname":"Hanam",
    "gn:country_code":"KR",
    "gn:dem":5,
    "gn:feature_class":"P",
    "gn:feature_code":"PPL",
    "gn:name":"Hanam",
    "gn:population":0,
    "gn:timezone":"Asia/Seoul",
    "iso:country":"KR",
    "name:ara_x_preferred":[
        "\u0647\u0627\u0646\u0627\u0645"
    ],
    "name:ceb_x_preferred":[
        "Hanam"
    ],
    "name:ces_x_preferred":[
        "Hanam"
    ],
    "name:ell_x_preferred":[
        "\u03a7\u03ac\u03bd\u03b1\u03bc"
    ],
    "name:epo_x_preferred":[
        "Hanam"
    ],
    "name:fas_x_preferred":[
        "\u0647\u0627\u0646\u0627\u0645"
    ],
    "name:fin_x_preferred":[
        "Hanam"
    ],
    "name:fra_x_preferred":[
        "Hanam"
    ],
    "name:hak_x_preferred":[
        "Hanam S\u1e73"
    ],
    "name:ind_x_preferred":[
        "Hanam"
    ],
    "name:ita_x_preferred":[
        "Hanam"
    ],
    "name:jpn_x_preferred":[
        "\u6cb3\u5357\u5e02"
    ],
    "name:kat_x_preferred":[
        "\u10f0\u10d0\u10dc\u10d0\u10db\u10d8"
    ],
    "name:kor_x_preferred":[
        "\ud558\ub0a8\uc2dc"
    ],
    "name:mon_x_preferred":[
        "\u0425\u0430\u043d\u0430\u043c"
    ],
    "name:nld_x_preferred":[
        "Hanam"
    ],
    "name:nor_x_preferred":[
        "Hanam"
    ],
    "name:pol_x_preferred":[
        "Hanam"
    ],
    "name:rus_x_preferred":[
        "\u0425\u0430\u043d\u0430\u043c"
    ],
    "name:sco_x_preferred":[
        "Hanam"
    ],
    "name:slk_x_preferred":[
        "Hanam"
    ],
    "name:spa_x_preferred":[
        "Hanam"
    ],
    "name:swe_x_preferred":[
        "Hanam"
    ],
    "name:tgl_x_preferred":[
        "Hanam"
    ],
    "name:tha_x_preferred":[
        "\u0e2e\u0e32\u0e19\u0e31\u0e21"
    ],
    "name:tur_x_preferred":[
        "Hanam"
    ],
    "name:und_x_variant":[
        "\ud558\ub0a8"
    ],
    "name:urd_x_preferred":[
        "\u06c1\u0627\u0646\u0627\u0645"
    ],
    "name:vie_x_preferred":[
        "Hanam"
    ],
    "name:war_x_preferred":[
        "Hanam"
    ],
    "name:zho_x_preferred":[
        "\u6cb3\u5357\u5e02"
    ],
    "wof:name":"Hanam",
    "wof:placetype":"locality"
},
  "geometry": {"coordinates":[126.6084,36.9613],"type":"Point"}
}