{
  "type": "Feature",
  "properties": {
    "gn:admin1_code":"17.0",
    "gn:asciiname":"Hanam",
    "gn:country_code":"KR",
    "gn:dem":5,
    "gn:feature_class":"P",
    "gn:feature_code":"PPL",
    "gn:name":"Hanam",
    "gn:population":0,
    "gn:timezone":"Asia/Seoul",
    "iso:country":"KR",
    "name:und_x_variant":[
        "\ud558\ub0a8",
        "Hanam"
    ],
    "wof:name":"Hanam",
    "wof:placetype":"locality"
},
  "geometry": {"coordinates":[126.6084,36.9613],"type":"Point"}
}