{
  "type": "Feature",
  "properties": {
    "gn:admin1_code":"14.0",
    "gn:asciiname":"Yorumsil",
    "gn:country_code":"KR",
    "gn:dem":91,
    "gn:feature_class":"P",
    "gn:feature_code":"PPL",
    "gn:name":"Y\u014fr\u016dmsil",
    "gn:population":0,
    "gn:timezone":"Asia/Seoul",
    "iso:country":"KR",
    "name:und_x_variant":[
        "\uc5ec\ub984\uc2e4",
        "Y\u014fr\u016dmsil"
    ],
    "wof:name":"Yorumsil",
    "wof:placetype":"locality"
},
  "geometry": {"coordinates":[128.09316999999999,36.08054],"type":"Point"}
}