{
  "type": "Feature",
  "properties": {
    "gn:admin1_code":"16.0",
    "gn:asciiname":"Danyang",
    "gn:country_code":"KR",
    "gn:dem":79,
    "gn:feature_class":"P",
    "gn:feature_code":"PPL",
    "gn:name":"Danyang",
    "gn:population":0,
    "gn:timezone":"Asia/Seoul",
    "iso:country":"KR",
    "name:ceb_x_preferred":[
        "Danyang"
    ],
    "name:deu_x_preferred":[
        "Danyang"
    ],
    "name:fra_x_preferred":[
        "Danyang"
    ],
    "name:kor_x_preferred":[
        "\ub2e8\uc591"
    ],
    "name:nor_x_preferred":[
        "Danyang"
    ],
    "name:pol_x_preferred":[
        "Danyang"
    ],
    "name:swe_x_preferred":[
        "Danyang"
    ],
    "name:und_x_variant":[
        "Tanyang-ni",
        "Tanyang"
    ],
    "wof:name":"Danyang",
    "wof:placetype":"locality"
},
  "geometry": {"coordinates":[126.93129,34.94815999999999],"type":"Point"}
}