{
  "type": "Feature",
  "properties": {
    "gn:admin1_code":"20.0",
    "gn:asciiname":"Suok",
    "gn:country_code":"KR",
    "gn:dem":227,
    "gn:feature_class":"P",
    "gn:feature_code":"PPL",
    "gn:name":"Suok",
    "gn:population":0,
    "gn:timezone":"Asia/Seoul",
    "iso:country":"KR",
    "name:und_x_variant":[
        "Hwaok-tong",
        "\uc218\uc625",
        "Suok"
    ],
    "wof:name":"Suok",
    "wof:placetype":"locality"
},
  "geometry": {"coordinates":[127.96402999999999,35.58367],"type":"Point"}
}