{
  "type": "Feature",
  "properties": {
    "gn:admin1_code":"15.0",
    "gn:asciiname":"Gochon",
    "gn:country_code":"KR",
    "gn:dem":29,
    "gn:feature_class":"P",
    "gn:feature_code":"PPL",
    "gn:name":"Gochon",
    "gn:population":0,
    "gn:timezone":"Asia/Seoul",
    "iso:country":"KR",
    "name:kor_x_preferred":[
        "\uace0\ucd0c"
    ],
    "wof:name":"Gochon",
    "wof:placetype":"locality"
},
  "geometry": {"coordinates":[128.59031000000002,35.91277],"type":"Point"}
}