{
  "type": "Feature",
  "properties": {
    "gn:admin1_code":"13.0",
    "gn:asciiname":"Tae-ch'on",
    "gn:country_code":"KR",
    "gn:dem":178,
    "gn:feature_class":"P",
    "gn:feature_code":"PPL",
    "gn:name":"Tae-ch\u2019on",
    "gn:population":0,
    "gn:timezone":"Asia/Seoul",
    "iso:country":"KR",
    "name:kor_x_preferred":[
        "\ub300\ucd0c"
    ],
    "name:kor_x_variant":[
        "Tae-ch\u2019on"
    ],
    "wof:name":"Tae-ch'on",
    "wof:placetype":"locality"
},
  "geometry": {"coordinates":[127.49160000000001,37.9241],"type":"Point"}
}