{
  "type": "Feature",
  "properties": {
    "gn:admin1_code":"16.0",
    "gn:asciiname":"Daegok",
    "gn:country_code":"KR",
    "gn:dem":17,
    "gn:feature_class":"P",
    "gn:feature_code":"PPL",
    "gn:name":"Daegok",
    "gn:population":0,
    "gn:timezone":"Asia/Seoul",
    "iso:country":"KR",
    "name:kor_x_preferred":[
        "\ub300\uace1"
    ],
    "name:und_x_variant":[
        "Taegong-ni",
        "Taegok",
        "Daegok"
    ],
    "wof:name":"Daegok",
    "wof:placetype":"locality"
},
  "geometry": {"coordinates":[126.79148000000001,34.38598],"type":"Point"}
}