{
  "type": "Feature",
  "properties": {
    "gn:admin1_code":"16.0",
    "gn:asciiname":"Hwachi-dong",
    "gn:country_code":"KR",
    "gn:dem":41,
    "gn:feature_class":"P",
    "gn:feature_code":"PPL",
    "gn:name":"Hwachi-dong",
    "gn:population":0,
    "gn:timezone":"Asia/Seoul",
    "iso:country":"KR",
    "name:kor_x_preferred":[
        "\ud654\uce58\ub3d9"
    ],
    "name:und_x_variant":[
        "Kachiri",
        "Hwajae-ri",
        "Kaji-ri",
        "Kaii-ri",
        "Hwach\u2019i-ri",
        "Hwachi-dong"
    ],
    "wof:name":"Hwachi-dong",
    "wof:placetype":"locality"
},
  "geometry": {"coordinates":[127.64415,34.8124],"type":"Point"}
}