{
  "type": "Feature",
  "properties": {
    "gn:admin1_code":"14.0",
    "gn:asciiname":"Baenamujeong",
    "gn:country_code":"KR",
    "gn:dem":38,
    "gn:feature_class":"P",
    "gn:feature_code":"PPL",
    "gn:name":"Baenamujeong",
    "gn:population":0,
    "gn:timezone":"Asia/Seoul",
    "iso:country":"KR",
    "name:kor_x_preferred":[
        "\ubc30\ub098\ubb34\uc815"
    ],
    "name:und_x_variant":[
        "Paenamuj\u014fng"
    ],
    "wof:name":"Baenamujeong",
    "wof:placetype":"locality"
},
  "geometry": {"coordinates":[128.36991,35.88507],"type":"Point"}
}