{
  "type": "Feature",
  "properties": {
    "gn:admin1_code":"12.0",
    "gn:asciiname":"Bongseong",
    "gn:country_code":"KR",
    "gn:dem":24,
    "gn:feature_class":"P",
    "gn:feature_code":"PPL",
    "gn:name":"Bongseong",
    "gn:population":0,
    "gn:timezone":"Asia/Seoul",
    "iso:country":"KR",
    "name:und_x_variant":[
        "\ubd09\uc131",
        "Bongseong",
        "Pongs\u014fng"
    ],
    "wof:name":"Bongseong",
    "wof:placetype":"locality"
},
  "geometry": {"coordinates":[126.37873999999999,37.72702],"type":"Point"}
}