{
  "type": "Feature",
  "properties": {
    "gn:admin1_code":"16.0",
    "gn:asciiname":"Yongam",
    "gn:country_code":"KR",
    "gn:dem":7,
    "gn:feature_class":"P",
    "gn:feature_code":"PPL",
    "gn:name":"Yongam",
    "gn:population":0,
    "gn:timezone":"Asia/Seoul",
    "iso:country":"KR",
    "name:kor_x_preferred":[
        "\ubc31\uc0ac"
    ],
    "wof:name":"Yongam",
    "wof:placetype":"locality"
},
  "geometry": {"coordinates":[126.79222,34.49722],"type":"Point"}
}