{
  "type": "Feature",
  "properties": {
    "gn:admin1_code":"17.0",
    "gn:asciiname":"Nungsan-gol",
    "gn:country_code":"KR",
    "gn:dem":70,
    "gn:feature_class":"P",
    "gn:feature_code":"PPL",
    "gn:name":"N\u016dngsan-gol",
    "gn:population":0,
    "gn:timezone":"Asia/Seoul",
    "iso:country":"KR",
    "name:und_x_variant":[
        "\ub2a5\uc0b0\uace8",
        "N\u016dngsan-gol"
    ],
    "wof:name":"Nungsan-gol",
    "wof:placetype":"locality"
},
  "geometry": {"coordinates":[126.96850000000001,36.2763],"type":"Point"}
}