{
  "type": "Feature",
  "properties": {
    "gn:admin1_code":"16.0",
    "gn:asciiname":"Seokpo",
    "gn:country_code":"KR",
    "gn:dem":5,
    "gn:feature_class":"P",
    "gn:feature_code":"PPL",
    "gn:name":"Seokpo",
    "gn:population":0,
    "gn:timezone":"Asia/Seoul",
    "iso:country":"KR",
    "name:kor_x_preferred":[
        "\uc11d\ud3ec"
    ],
    "name:und_x_variant":[
        "S\u014fkp\u2019o"
    ],
    "wof:name":"Seokpo",
    "wof:placetype":"locality"
},
  "geometry": {"coordinates":[126.52197,34.76872],"type":"Point"}
}