{
  "type": "Feature",
  "properties": {
    "gn:admin1_code":"17.0",
    "gn:asciiname":"Suhyon",
    "gn:country_code":"KR",
    "gn:dem":51,
    "gn:feature_class":"P",
    "gn:feature_code":"PPL",
    "gn:name":"Suhy\u014fn",
    "gn:population":0,
    "gn:timezone":"Asia/Seoul",
    "iso:country":"KR",
    "name:und_x_variant":[
        "Suhy\u014fn-ni",
        "\uc218\ud604",
        "Suhy\u014fn"
    ],
    "wof:name":"Suhyon",
    "wof:placetype":"locality"
},
  "geometry": {"coordinates":[126.3927,36.7519],"type":"Point"}
}