{
  "type": "Feature",
  "properties": {
    "gn:admin1_code":"17.0",
    "gn:asciiname":"Songsang-ni",
    "gn:country_code":"KR",
    "gn:dem":91,
    "gn:feature_class":"P",
    "gn:feature_code":"PPL",
    "gn:name":"S\u014fngsang-ni",
    "gn:population":0,
    "gn:timezone":"Asia/Seoul",
    "iso:country":"KR",
    "name:und_x_variant":[
        "\uc131\uc0c1\ub9ac",
        "S\u014fngsang-ni"
    ],
    "wof:name":"Songsang-ni",
    "wof:placetype":"locality"
},
  "geometry": {"coordinates":[126.65989999999999,36.8229],"type":"Point"}
}