{
  "type": "Feature",
  "properties": {
    "gn:admin1_code":"17.0",
    "gn:asciiname":"Koyang-gol",
    "gn:country_code":"KR",
    "gn:dem":75,
    "gn:feature_class":"P",
    "gn:feature_code":"PPL",
    "gn:name":"Koyang-gol",
    "gn:population":0,
    "gn:timezone":"Asia/Seoul",
    "iso:country":"KR",
    "name:und_x_variant":[
        "Koyang-ni",
        "\uace0\uc591\uace8",
        "Koyang-gol"
    ],
    "wof:name":"Koyang-gol",
    "wof:placetype":"locality"
},
  "geometry": {"coordinates":[127.00020000000001,36.4579],"type":"Point"}
}