{
  "type": "Feature",
  "properties": {
    "gn:admin1_code":"1.0",
    "gn:asciiname":"Ara-dong",
    "gn:country_code":"KR",
    "gn:dem":178,
    "gn:feature_class":"P",
    "gn:feature_code":"PPL",
    "gn:name":"Ara-dong",
    "gn:population":0,
    "gn:timezone":"Asia/Seoul",
    "iso:country":"KR",
    "name:und_x_variant":[
        "K\u014fma-dong",
        "Ara-ri",
        "Ara-dong"
    ],
    "wof:name":"Ara-dong",
    "wof:placetype":"locality"
},
  "geometry": {"coordinates":[126.5275,33.46889],"type":"Point"}
}