{
  "type": "Feature",
  "properties": {
    "gn:admin1_code":"17.0",
    "gn:asciiname":"Naengjong-gol",
    "gn:country_code":"KR",
    "gn:dem":94,
    "gn:feature_class":"P",
    "gn:feature_code":"PPL",
    "gn:name":"Naengj\u014fng-gol",
    "gn:population":0,
    "gn:timezone":"Asia/Seoul",
    "iso:country":"KR",
    "name:und_x_variant":[
        "\ub0c9\uc815\uace8",
        "Naengj\u014fng-gol"
    ],
    "wof:name":"Naengjong-gol",
    "wof:placetype":"locality"
},
  "geometry": {"coordinates":[126.6557,36.828],"type":"Point"}
}