{
  "type": "Feature",
  "properties": {
    "gn:admin1_code":"16.0",
    "gn:asciiname":"Suwol",
    "gn:country_code":"KR",
    "gn:dem":97,
    "gn:feature_class":"P",
    "gn:feature_code":"PPL",
    "gn:name":"Suwol",
    "gn:population":0,
    "gn:timezone":"Asia/Seoul",
    "iso:country":"KR",
    "name:kor_x_preferred":[
        "\uc218\uc6d4"
    ],
    "name:und_x_variant":[
        "Suw\u014fl"
    ],
    "wof:name":"Suwol",
    "wof:placetype":"locality"
},
  "geometry": {"coordinates":[127.17739,34.95401],"type":"Point"}
}