{
  "type": "Feature",
  "properties": {
    "gn:admin1_code":"13.0",
    "gn:asciiname":"Geumwol",
    "gn:country_code":"KR",
    "gn:dem":15,
    "gn:feature_class":"P",
    "gn:feature_code":"PPL",
    "gn:name":"Geumwol",
    "gn:population":0,
    "gn:timezone":"Asia/Seoul",
    "iso:country":"KR",
    "name:kor_x_preferred":[
        "\uae08\uc6d4"
    ],
    "name:kor_x_variant":[
        "K\u016dmw\u014fl"
    ],
    "wof:name":"Geumwol",
    "wof:placetype":"locality"
},
  "geometry": {"coordinates":[126.61861,37.74583],"type":"Point"}
}