{
  "type": "Feature",
  "properties": {
    "gn:admin1_code":"13.0",
    "gn:admin2_code":"Yongin-si",
    "gn:asciiname":"Koal-li",
    "gn:country_code":"KR",
    "gn:dem":100,
    "gn:feature_class":"P",
    "gn:feature_code":"PPLL",
    "gn:name":"Koal-li",
    "gn:population":0,
    "gn:timezone":"Asia/Seoul",
    "iso:country":"KR",
    "name:kor_x_preferred":[
        "\uace0\uc548\ub9ac"
    ],
    "name:und_x_variant":[
        "Goan-ri"
    ],
    "wof:name":"Koal-li",
    "wof:placetype":"locality"
},
  "geometry": {"coordinates":[127.41083,37.12139000000001],"type":"Point"}
}