{
  "type": "Feature",
  "properties": {
    "gn:admin1_code":"17.0",
    "gn:asciiname":"Paem-gol",
    "gn:country_code":"KR",
    "gn:dem":44,
    "gn:feature_class":"P",
    "gn:feature_code":"PPL",
    "gn:name":"Paem-gol",
    "gn:population":0,
    "gn:timezone":"Asia/Seoul",
    "iso:country":"KR",
    "name:und_x_variant":[
        "\ubc40\uace8",
        "Paem-gol"
    ],
    "wof:name":"Paem-gol",
    "wof:placetype":"locality"
},
  "geometry": {"coordinates":[127.0521,36.8819],"type":"Point"}
}