{
  "type": "Feature",
  "properties": {
    "gn:admin1_code":"16.0",
    "gn:asciiname":"Ipsok",
    "gn:country_code":"KR",
    "gn:dem":48,
    "gn:feature_class":"P",
    "gn:feature_code":"PPL",
    "gn:name":"Ips\u014fk",
    "gn:population":0,
    "gn:timezone":"Asia/Seoul",
    "iso:country":"KR",
    "name:kor_x_preferred":[
        "\uc785\uc11d"
    ],
    "name:kor_x_variant":[
        "Ips\u014fk"
    ],
    "wof:name":"Ipsok",
    "wof:placetype":"locality"
},
  "geometry": {"coordinates":[127.09168,34.59961],"type":"Point"}
}