{
  "type": "Feature",
  "properties": {
    "gn:admin1_code":"14.0",
    "gn:asciiname":"Bungye",
    "gn:country_code":"KR",
    "gn:dem":115,
    "gn:feature_class":"P",
    "gn:feature_code":"PPL",
    "gn:name":"Bungye",
    "gn:population":0,
    "gn:timezone":"Asia/Seoul",
    "iso:country":"KR",
    "name:kor_x_preferred":[
        "\ubd84\uacc4"
    ],
    "name:und_x_variant":[
        "Pun\u2019gye"
    ],
    "wof:name":"Bungye",
    "wof:placetype":"locality"
},
  "geometry": {"coordinates":[128.60116000000002,36.7193],"type":"Point"}
}