{
  "type": "Feature",
  "properties": {
    "gn:admin1_code":"14.0",
    "gn:asciiname":"Nungjom",
    "gn:country_code":"KR",
    "gn:dem":208,
    "gn:feature_class":"P",
    "gn:feature_code":"PPL",
    "gn:name":"N\u016dngj\u014fm",
    "gn:population":0,
    "gn:timezone":"Asia/Seoul",
    "iso:country":"KR",
    "name:und_x_variant":[
        "N\u016dngj\u014fm-dong",
        "\ub2a5\uc810",
        "N\u016dngj\u014fm"
    ],
    "wof:name":"Nungjom",
    "wof:placetype":"locality"
},
  "geometry": {"coordinates":[128.05600000000001,36.226],"type":"Point"}
}