{
  "type": "Feature",
  "properties": {
    "gn:admin1_code":"16.0",
    "gn:asciiname":"Ttabakgol",
    "gn:country_code":"KR",
    "gn:dem":100,
    "gn:feature_class":"P",
    "gn:feature_code":"PPL",
    "gn:name":"Ttabakgol",
    "gn:population":0,
    "gn:timezone":"Asia/Seoul",
    "iso:country":"KR",
    "name:kor_x_preferred":[
        "\ub530\ubc15\uace8"
    ],
    "wof:name":"Ttabakgol",
    "wof:placetype":"locality"
},
  "geometry": {"coordinates":[127.01206000000001,34.92881],"type":"Point"}
}