{
  "type": "Feature",
  "properties": {
    "gn:admin1_code":"17.0",
    "gn:asciiname":"Norigol",
    "gn:country_code":"KR",
    "gn:dem":173,
    "gn:feature_class":"P",
    "gn:feature_code":"PPL",
    "gn:name":"Norigol",
    "gn:population":0,
    "gn:timezone":"Asia/Seoul",
    "iso:country":"KR",
    "name:kor_x_preferred":[
        "\ub178\ub9ac\uace8"
    ],
    "wof:name":"Norigol",
    "wof:placetype":"locality"
},
  "geometry": {"coordinates":[127.21872999999999,36.31561],"type":"Point"}
}