{
  "type": "Feature",
  "properties": {
    "gn:admin1_code":"14.0",
    "gn:asciiname":"Hanbang",
    "gn:country_code":"KR",
    "gn:dem":315,
    "gn:feature_class":"P",
    "gn:feature_code":"PPL",
    "gn:name":"Hanbang",
    "gn:population":0,
    "gn:timezone":"Asia/Seoul",
    "iso:country":"KR",
    "name:und_x_variant":[
        "\ud55c\ubc29",
        "Hanbang"
    ],
    "wof:name":"Hanbang",
    "wof:placetype":"locality"
},
  "geometry": {"coordinates":[128.05483000000001,35.90541],"type":"Point"}
}