{
  "type": "Feature",
  "properties": {
    "gn:admin1_code":"5.0",
    "gn:asciiname":"Bongdori",
    "gn:country_code":"KR",
    "gn:dem":41,
    "gn:feature_class":"P",
    "gn:feature_code":"PPL",
    "gn:name":"Bongdori",
    "gn:population":0,
    "gn:timezone":"Asia/Seoul",
    "iso:country":"KR",
    "name:kor_x_preferred":[
        "\ubd09\ub3c4\ub9ac"
    ],
    "wof:name":"Bongdori",
    "wof:placetype":"locality"
},
  "geometry": {"coordinates":[127.34524,36.63982],"type":"Point"}
}