{
  "type": "Feature",
  "properties": {
    "gn:admin1_code":"1.0",
    "gn:admin2_code":"Namjeju-gun",
    "gn:asciiname":"Ungjon-dong",
    "gn:country_code":"KR",
    "gn:dem":135,
    "gn:feature_class":"P",
    "gn:feature_code":"PPL",
    "gn:name":"\u016cngj\u014fn-dong",
    "gn:population":0,
    "gn:timezone":"Asia/Seoul",
    "iso:country":"KR",
    "wof:name":"Ungjon-dong",
    "wof:placetype":"locality"
},
  "geometry": {"coordinates":[126.30583,33.28111],"type":"Point"}
}