{
  "type": "Feature",
  "properties": {
    "gn:admin1_code":"18.0",
    "gn:asciiname":"Sinyeong",
    "gn:country_code":"KR",
    "gn:dem":14,
    "gn:feature_class":"P",
    "gn:feature_code":"PPL",
    "gn:name":"Sinyeong",
    "gn:population":0,
    "gn:timezone":"Asia/Seoul",
    "iso:country":"KR",
    "name:kor_x_preferred":[
        "\uc2e0\uc601"
    ],
    "name:und_x_variant":[
        "Siny\u014fng"
    ],
    "wof:name":"Sinyeong",
    "wof:placetype":"locality"
},
  "geometry": {"coordinates":[126.81780000000001,35.12048],"type":"Point"}
}