{
  "type": "Feature",
  "properties": {
    "gn:admin1_code":"21.0",
    "gn:asciiname":"Seonjanggol",
    "gn:country_code":"KR",
    "gn:dem":51,
    "gn:feature_class":"P",
    "gn:feature_code":"PPL",
    "gn:name":"Seonjanggol",
    "gn:population":0,
    "gn:timezone":"Asia/Seoul",
    "iso:country":"KR",
    "name:kor_x_preferred":[
        "\uc120\uc7a5\uace8"
    ],
    "wof:name":"Seonjanggol",
    "wof:placetype":"locality"
},
  "geometry": {"coordinates":[129.32438999999999,35.64828],"type":"Point"}
}