{
  "type": "Feature",
  "properties": {
    "gn:admin1_code":"15.0",
    "gn:asciiname":"Anmojeong",
    "gn:country_code":"KR",
    "gn:dem":38,
    "gn:feature_class":"P",
    "gn:feature_code":"PPL",
    "gn:name":"Anmojeong",
    "gn:population":0,
    "gn:timezone":"Asia/Seoul",
    "iso:country":"KR",
    "name:und_x_variant":[
        "\uc548\ubaa8\uc815",
        "Anmoj\u014fng",
        "Anmojeong"
    ],
    "wof:name":"Anmojeong",
    "wof:placetype":"locality"
},
  "geometry": {"coordinates":[128.41511,35.63822000000001],"type":"Point"}
}