{
  "type": "Feature",
  "properties": {
    "gn:admin1_code":"16.0",
    "gn:asciiname":"Santei",
    "gn:country_code":"KR",
    "gn:dem":56,
    "gn:feature_class":"P",
    "gn:feature_code":"PPL",
    "gn:name":"Santei",
    "gn:population":0,
    "gn:timezone":"Asia/Seoul",
    "iso:country":"KR",
    "name:kor_x_preferred":[
        "\uc0b0\uc815"
    ],
    "name:kor_x_variant":[
        "Sanj\u014fng"
    ],
    "wof:name":"Santei",
    "wof:placetype":"locality"
},
  "geometry": {"coordinates":[126.99417,34.605],"type":"Point"}
}