{
  "type": "Feature",
  "properties": {
    "gn:admin1_code":"16.0",
    "gn:asciiname":"Sinoch'i",
    "gn:country_code":"KR",
    "gn:dem":18,
    "gn:feature_class":"P",
    "gn:feature_code":"PPL",
    "gn:name":"Sinoch\u2019i",
    "gn:population":0,
    "gn:timezone":"Asia/Seoul",
    "iso:country":"KR",
    "name:kor_x_preferred":[
        "\uc2e0\uc624\uce58"
    ],
    "name:kor_x_variant":[
        "Sinoch\u2019i"
    ],
    "wof:name":"Sinoch'i",
    "wof:placetype":"locality"
},
  "geometry": {"coordinates":[127.31909,34.51016],"type":"Point"}
}