{
  "type": "Feature",
  "properties": {
    "gn:admin1_code":"14.0",
    "gn:asciiname":"Munjang-gol",
    "gn:country_code":"KR",
    "gn:dem":60,
    "gn:feature_class":"P",
    "gn:feature_code":"PPL",
    "gn:name":"Munjang-gol",
    "gn:population":0,
    "gn:timezone":"Asia/Seoul",
    "iso:country":"KR",
    "name:und_x_variant":[
        "\ubb38\uc7a5\uace8",
        "Munjang-gol"
    ],
    "wof:name":"Munjang-gol",
    "wof:placetype":"locality"
},
  "geometry": {"coordinates":[128.25200000000001,36.3781],"type":"Point"}
}