{
  "type": "Feature",
  "properties": {
    "gn:admin1_code":"6.0",
    "gn:asciiname":"Oam",
    "gn:country_code":"KR",
    "gn:dem":313,
    "gn:feature_class":"P",
    "gn:feature_code":"PPL",
    "gn:name":"Oam",
    "gn:population":0,
    "gn:timezone":"Asia/Seoul",
    "iso:country":"KR",
    "name:kor_x_preferred":[
        "\uc624\uc554"
    ],
    "wof:name":"Oam",
    "wof:placetype":"locality"
},
  "geometry": {"coordinates":[128.64959999999999,37.3767],"type":"Point"}
}