{
  "type": "Feature",
  "properties": {
    "gn:admin1_code":"13.0",
    "gn:admin2_code":"P'aju-si",
    "gn:asciiname":"Chanumul",
    "gn:country_code":"KR",
    "gn:dem":42,
    "gn:feature_class":"P",
    "gn:feature_code":"PPL",
    "gn:name":"Chanumul",
    "gn:population":0,
    "gn:timezone":"Asia/Seoul",
    "iso:country":"KR",
    "name:kor_x_preferred":[
        "\ucc2c\uc6b0\ubb3c"
    ],
    "name:kor_x_variant":[
        "Ch\u2019anumul"
    ],
    "wof:name":"Chanumul",
    "wof:placetype":"locality"
},
  "geometry": {"coordinates":[126.74378,37.78958],"type":"Point"}
}