{
  "type": "Feature",
  "properties": {
    "gn:admin1_code":"20.0",
    "gn:asciiname":"Sondong-ni",
    "gn:country_code":"KR",
    "gn:dem":24,
    "gn:feature_class":"P",
    "gn:feature_code":"PPL",
    "gn:name":"S\u014fndong-ni",
    "gn:population":0,
    "gn:timezone":"Asia/Seoul",
    "iso:country":"KR",
    "name:eng_x_preferred":[
        "Sondong"
    ],
    "name:eng_x_variant":[
        "Sondong-ni"
    ],
    "name:und_x_variant":[
        "\uc120\ub3d9\ub9ac",
        "S\u014fn-dong",
        "S\u014fndong-ni"
    ],
    "wof:name":"Sondong",
    "wof:placetype":"locality"
},
  "geometry": {"coordinates":[128.30708999999999,34.9922],"type":"Point"}
}