{
  "type": "Feature",
  "properties": {
    "gn:admin1_code":"14.0",
    "gn:asciiname":"Araekkomsil",
    "gn:country_code":"KR",
    "gn:dem":35,
    "gn:feature_class":"P",
    "gn:feature_code":"PPL",
    "gn:name":"Araekkomsil",
    "gn:population":0,
    "gn:timezone":"Asia/Seoul",
    "iso:country":"KR",
    "name:und_x_variant":[
        "\uc544\ub7ab\uacf0\uc2e4",
        "Araekkomsil"
    ],
    "wof:name":"Araekkomsil",
    "wof:placetype":"locality"
},
  "geometry": {"coordinates":[129.4299,36.8077],"type":"Point"}
}