{
  "type": "Feature",
  "properties": {
    "gn:admin1_code":"0.0",
    "gn:asciiname":"Hach'on-ni",
    "gn:country_code":"KR",
    "gn:dem":204,
    "gn:feature_class":"P",
    "gn:feature_code":"PPL",
    "gn:name":"Hach\u2019\u014fn-ni",
    "gn:population":0,
    "gn:timezone":"Asia/Seoul",
    "iso:country":"KR",
    "wof:name":"Hach'on-ni",
    "wof:placetype":"locality"
},
  "geometry": {"coordinates":[127.21666999999999,35.65],"type":"Point"}
}