{
  "type": "Feature",
  "properties": {
    "gn:admin1_code":"3.0",
    "gn:asciiname":"Won'gusin",
    "gn:country_code":"KR",
    "gn:dem":339,
    "gn:feature_class":"P",
    "gn:feature_code":"PPL",
    "gn:name":"W\u014fn\u2019gusin",
    "gn:population":0,
    "gn:timezone":"Asia/Seoul",
    "iso:country":"KR",
    "name:und_x_variant":[
        "\uc6d0\uad6c\uc2e0",
        "W\u014fn\u2019gusin"
    ],
    "wof:name":"Won'gusin",
    "wof:placetype":"locality"
},
  "geometry": {"coordinates":[127.37069,35.67334],"type":"Point"}
}