{
  "type": "Feature",
  "properties": {
    "gn:admin1_code":"20.0",
    "gn:asciiname":"Kusonch'ang",
    "gn:country_code":"KR",
    "gn:dem":7,
    "gn:feature_class":"P",
    "gn:feature_code":"PPL",
    "gn:name":"Kus\u014fnch\u2019ang",
    "gn:population":0,
    "gn:timezone":"Asia/Seoul",
    "iso:country":"KR",
    "name:und_x_variant":[
        "\uad6c\uc120\ucc3d",
        "Kus\u014fnch\u2019ang"
    ],
    "wof:name":"Kusonch'ang",
    "wof:placetype":"locality"
},
  "geometry": {"coordinates":[128.33001999999999,34.94814],"type":"Point"}
}