{
  "type": "Feature",
  "properties": {
    "gn:admin1_code":"13.0",
    "gn:asciiname":"Baeuni",
    "gn:country_code":"KR",
    "gn:dem":80,
    "gn:feature_class":"P",
    "gn:feature_code":"PPL",
    "gn:name":"Baeuni",
    "gn:population":0,
    "gn:timezone":"Asia/Seoul",
    "iso:country":"KR",
    "name:kor_x_preferred":[
        "\uc6c3\ubc31\uc6b4\uc774"
    ],
    "name:kor_x_variant":[
        "\ubc30\uc6b0\ub2c8"
    ],
    "name:und_x_variant":[
        "N\u016dlmok-tong",
        "Uppaeguni",
        "Baeuni"
    ],
    "wof:name":"Baeuni",
    "wof:placetype":"locality"
},
  "geometry": {"coordinates":[126.95625,37.95905],"type":"Point"}
}