{
  "type": "Feature",
  "properties": {
    "gn:admin1_code":"13.0",
    "gn:asciiname":"Songjeong-dong",
    "gn:country_code":"KR",
    "gn:dem":106,
    "gn:feature_class":"P",
    "gn:feature_code":"PPLL",
    "gn:name":"Songjeong-dong",
    "gn:population":0,
    "gn:timezone":"Asia/Seoul",
    "iso:country":"KR",
    "name:ceb_x_preferred":[
        "Songjeong-dong"
    ],
    "name:kor_x_preferred":[
        "\uc1a1\uc815\ub3d9"
    ],
    "name:swe_x_preferred":[
        "Songjeong-dong"
    ],
    "name:und_x_variant":[
        "Songj\u014fng-dong"
    ],
    "wof:name":"Songjeong-dong",
    "wof:placetype":"locality"
},
  "geometry": {"coordinates":[127.23556000000001,37.43306],"type":"Point"}
}