{
  "type": "Feature",
  "properties": {
    "gn:admin1_code":"5.0",
    "gn:asciiname":"Saejae",
    "gn:country_code":"KR",
    "gn:dem":200,
    "gn:feature_class":"P",
    "gn:feature_code":"PPL",
    "gn:name":"Saejae",
    "gn:population":0,
    "gn:timezone":"Asia/Seoul",
    "iso:country":"KR",
    "name:und_x_variant":[
        "\uc0c8\uc7ac",
        "Saejae"
    ],
    "wof:name":"Saejae",
    "wof:placetype":"locality"
},
  "geometry": {"coordinates":[127.65479999999999,36.0945],"type":"Point"}
}