{
  "type": "Feature",
  "properties": {
    "gn:admin1_code":"14.0",
    "gn:asciiname":"Ian",
    "gn:country_code":"KR",
    "gn:dem":68,
    "gn:feature_class":"P",
    "gn:feature_code":"PPL",
    "gn:name":"Ian",
    "gn:population":0,
    "gn:timezone":"Asia/Seoul",
    "iso:country":"KR",
    "wof:name":"Ian",
    "wof:placetype":"locality"
},
  "geometry": {"coordinates":[128.15666999999999,36.54306],"type":"Point"}
}