{
  "type": "Feature",
  "properties": {
    "gn:admin1_code":"5.0",
    "gn:asciiname":"Soesil",
    "gn:country_code":"KR",
    "gn:dem":102,
    "gn:feature_class":"P",
    "gn:feature_code":"PPL",
    "gn:name":"Soesil",
    "gn:population":0,
    "gn:timezone":"Asia/Seoul",
    "iso:country":"KR",
    "name:und_x_variant":[
        "\uc1e0\uc2e4",
        "Soesil"
    ],
    "wof:name":"Soesil",
    "wof:placetype":"locality"
},
  "geometry": {"coordinates":[127.59399999999999,36.4564],"type":"Point"}
}