{
  "type": "Feature",
  "properties": {
    "gn:admin1_code":"20.0",
    "gn:asciiname":"Nolmigi",
    "gn:country_code":"KR",
    "gn:dem":637,
    "gn:feature_class":"P",
    "gn:feature_code":"PPL",
    "gn:name":"N\u014flmigi",
    "gn:population":0,
    "gn:timezone":"Asia/Seoul",
    "iso:country":"KR",
    "name:und_x_variant":[
        "\ub110\ubbf8\uae30",
        "N\u014flmigi"
    ],
    "wof:name":"Nolmigi",
    "wof:placetype":"locality"
},
  "geometry": {"coordinates":[127.90236000000002,35.54046],"type":"Point"}
}