{
  "type": "Feature",
  "properties": {
    "gn:admin1_code":"16.0",
    "gn:asciiname":"Buntodong",
    "gn:country_code":"KR",
    "gn:dem":62,
    "gn:feature_class":"P",
    "gn:feature_code":"PPL",
    "gn:name":"Buntodong",
    "gn:population":0,
    "gn:timezone":"Asia/Seoul",
    "iso:country":"KR",
    "name:kor_x_preferred":[
        "\ubd84\ud1a0\ub3d9"
    ],
    "wof:name":"Buntodong",
    "wof:placetype":"locality"
},
  "geometry": {"coordinates":[126.94282,35.23846],"type":"Point"}
}