{
  "type": "Feature",
  "properties": {
    "gn:admin1_code":"14.0",
    "gn:asciiname":"Ojon",
    "gn:country_code":"KR",
    "gn:dem":319,
    "gn:feature_class":"P",
    "gn:feature_code":"PPL",
    "gn:name":"\u014ej\u014fn",
    "gn:population":0,
    "gn:timezone":"Asia/Seoul",
    "iso:country":"KR",
    "name:und_x_variant":[
        "\uc5b4\uc804",
        "\u014ej\u014fn"
    ],
    "wof:name":"Ojon",
    "wof:placetype":"locality"
},
  "geometry": {"coordinates":[127.92877,35.97319],"type":"Point"}
}