{
  "type": "Feature",
  "properties": {
    "gn:admin1_code":"20.0",
    "gn:asciiname":"Tonji-ri",
    "gn:cc2":"KR",
    "gn:country_code":"KR",
    "gn:dem":41,
    "gn:feature_class":"P",
    "gn:feature_code":"PPL",
    "gn:name":"Tonji-ri",
    "gn:population":0,
    "gn:timezone":"Asia/Seoul",
    "iso:country":"KR",
    "name:und_x_variant":[
        "Tonchi",
        "Tonji",
        "Tonji-ni",
        "Tonchi-ri",
        "Tonji-ri"
    ],
    "wof:name":"Tonji-ri",
    "wof:placetype":"locality"
},
  "geometry": {"coordinates":[128.18388999999999,34.83778],"type":"Point"}
}