{
  "type": "Feature",
  "properties": {
    "gn:admin1_code":"13.0",
    "gn:asciiname":"Saetgol",
    "gn:country_code":"KR",
    "gn:dem":172,
    "gn:feature_class":"P",
    "gn:feature_code":"PPL",
    "gn:name":"Saetgol",
    "gn:population":0,
    "gn:timezone":"Asia/Seoul",
    "iso:country":"KR",
    "name:und_x_variant":[
        "\uc0db\uace8",
        "Saek-kol",
        "Saetgol"
    ],
    "wof:name":"Saetgol",
    "wof:placetype":"locality"
},
  "geometry": {"coordinates":[127.11709,37.77566],"type":"Point"}
}