{
  "type": "Feature",
  "properties": {
    "gn:admin1_code":"11.0",
    "gn:asciiname":"Yokch'onil-tong",
    "gn:country_code":"KR",
    "gn:dem":29,
    "gn:feature_class":"P",
    "gn:feature_code":"PPL",
    "gn:name":"Y\u014fkch\u2019onil-tong",
    "gn:population":0,
    "gn:timezone":"Asia/Seoul",
    "iso:country":"KR",
    "name:und_x_variant":[
        "\uc5ed\ucd0c1\ub3d9",
        "Y\u014fkch\u2019onil-tong"
    ],
    "wof:name":"Yokch'onil-tong",
    "wof:placetype":"locality"
},
  "geometry": {"coordinates":[126.91903000000001,37.60522],"type":"Point"}
}