{
  "type": "Feature",
  "properties": {
    "gn:admin1_code":"14.0",
    "gn:asciiname":"Mosan",
    "gn:country_code":"KR",
    "gn:dem":49,
    "gn:feature_class":"P",
    "gn:feature_code":"PPL",
    "gn:name":"Mosan",
    "gn:population":0,
    "gn:timezone":"Asia/Seoul",
    "iso:country":"KR",
    "name:ceb_x_preferred":[
        "Mosan"
    ],
    "name:swe_x_preferred":[
        "Mosan"
    ],
    "name:und_x_variant":[
        "\ubaa8\uc0b0"
    ],
    "wof:name":"Mosan",
    "wof:placetype":"locality"
},
  "geometry": {"coordinates":[128.33486000000002,35.85883],"type":"Point"}
}