{
  "type": "Feature",
  "properties": {
    "gn:admin1_code":"15.0",
    "gn:asciiname":"Yeochon",
    "gn:country_code":"KR",
    "gn:dem":141,
    "gn:feature_class":"P",
    "gn:feature_code":"PPL",
    "gn:name":"Yeochon",
    "gn:population":0,
    "gn:timezone":"Asia/Seoul",
    "iso:country":"KR",
    "name:kor_x_preferred":[
        "\uc5ec\ucd0c"
    ],
    "wof:name":"Yeochon",
    "wof:placetype":"locality"
},
  "geometry": {"coordinates":[128.64438000000001,35.77788],"type":"Point"}
}