{
  "type": "Feature",
  "properties": {
    "gn:admin1_code":"5.0",
    "gn:asciiname":"Nung-gol",
    "gn:country_code":"KR",
    "gn:dem":84,
    "gn:feature_class":"P",
    "gn:feature_code":"PPL",
    "gn:name":"N\u016dng-gol",
    "gn:population":0,
    "gn:timezone":"Asia/Seoul",
    "iso:country":"KR",
    "name:kor_x_preferred":[
        "\ub2a5\uace8"
    ],
    "name:kor_x_variant":[
        "N\u016dng-gol"
    ],
    "wof:name":"Nung-gol",
    "wof:placetype":"locality"
},
  "geometry": {"coordinates":[127.79940000000001,37.0894],"type":"Point"}
}