{
  "type": "Feature",
  "properties": {
    "gn:admin1_code":"5.0",
    "gn:asciiname":"Gangchon",
    "gn:country_code":"KR",
    "gn:dem":67,
    "gn:feature_class":"P",
    "gn:feature_code":"PPL",
    "gn:name":"Gangchon",
    "gn:population":0,
    "gn:timezone":"Asia/Seoul",
    "iso:country":"KR",
    "name:kor_x_preferred":[
        "\uac15\ucd0c"
    ],
    "name:kor_x_variant":[
        "Kang-ch\u2019on"
    ],
    "wof:name":"Gangchon",
    "wof:placetype":"locality"
},
  "geometry": {"coordinates":[127.78487,37.143],"type":"Point"}
}