{
  "type": "Feature",
  "properties": {
    "gn:admin1_code":"6.0",
    "gn:asciiname":"Asinae",
    "gn:country_code":"KR",
    "gn:dem":449,
    "gn:feature_class":"P",
    "gn:feature_code":"PPL",
    "gn:name":"Asinae",
    "gn:population":0,
    "gn:timezone":"Asia/Seoul",
    "iso:country":"KR",
    "name:kor_x_preferred":[
        "\uc544\uc2dc\ub0b4"
    ],
    "wof:name":"Asinae",
    "wof:placetype":"locality"
},
  "geometry": {"coordinates":[128.11700000000002,37.3622],"type":"Point"}
}