{
  "type": "Feature",
  "properties": {
    "gn:admin1_code":"17.0",
    "gn:asciiname":"Paekpal",
    "gn:country_code":"KR",
    "gn:dem":120,
    "gn:feature_class":"P",
    "gn:feature_code":"PPL",
    "gn:name":"Paekpal",
    "gn:population":0,
    "gn:timezone":"Asia/Seoul",
    "iso:country":"KR",
    "name:und_x_variant":[
        "\ubc31\ubc1c",
        "Paekpal"
    ],
    "wof:name":"Paekpal",
    "wof:placetype":"locality"
},
  "geometry": {"coordinates":[126.65049999999999,36.8451],"type":"Point"}
}