{
  "type": "Feature",
  "properties": {
    "gn:admin1_code":"17.0",
    "gn:asciiname":"Sanso",
    "gn:cc2":"KR",
    "gn:country_code":"KR",
    "gn:dem":13,
    "gn:feature_class":"P",
    "gn:feature_code":"PPL",
    "gn:name":"Sanso",
    "gn:population":0,
    "gn:timezone":"Asia/Seoul",
    "iso:country":"KR",
    "name:fin_x_preferred":[
        "Sanso"
    ],
    "name:fra_x_preferred":[
        "Sanso"
    ],
    "name:ita_x_preferred":[
        "Sanso"
    ],
    "name:nld_x_preferred":[
        "Sanso"
    ],
    "name:spa_x_preferred":[
        "Sanso"
    ],
    "name:und_x_variant":[
        "Sanso-ri",
        "Sanso"
    ],
    "wof:name":"Sanso",
    "wof:placetype":"locality"
},
  "geometry": {"coordinates":[126.65000000000001,36.06667],"type":"Point"}
}