{
  "type": "Feature",
  "properties": {
    "gn:admin1_code":"6.0",
    "gn:asciiname":"Bareungol",
    "gn:country_code":"KR",
    "gn:dem":225,
    "gn:feature_class":"P",
    "gn:feature_code":"PPL",
    "gn:name":"Bareungol",
    "gn:population":0,
    "gn:timezone":"Asia/Seoul",
    "iso:country":"KR",
    "name:und_x_variant":[
        "\ubc14\ub978\uace8",
        "Par\u016dn-gol",
        "Bareungol"
    ],
    "wof:name":"Bareungol",
    "wof:placetype":"locality"
},
  "geometry": {"coordinates":[127.61411,38.01189],"type":"Point"}
}