{
  "type": "Feature",
  "properties": {
    "gn:admin1_code":"6.0",
    "gn:asciiname":"Yangji-gol",
    "gn:country_code":"KR",
    "gn:dem":306,
    "gn:feature_class":"P",
    "gn:feature_code":"PPL",
    "gn:name":"Yangji-gol",
    "gn:population":0,
    "gn:timezone":"Asia/Seoul",
    "iso:country":"KR",
    "name:kor_x_preferred":[
        "\uc591\uc9c0\uace8"
    ],
    "wof:name":"Yangji-gol",
    "wof:placetype":"locality"
},
  "geometry": {"coordinates":[127.87269999999999,37.5763],"type":"Point"}
}