{
  "type": "Feature",
  "properties": {
    "gn:admin1_code":"14.0",
    "gn:asciiname":"Ch'ongno",
    "gn:country_code":"KR",
    "gn:dem":175,
    "gn:feature_class":"P",
    "gn:feature_code":"PPL",
    "gn:name":"Ch\u2019\u014fngno",
    "gn:population":0,
    "gn:timezone":"Asia/Seoul",
    "iso:country":"KR",
    "name:und_x_variant":[
        "Ch\u2019\u014fng-dong",
        "Ch\u2019ongno-dong",
        "Ch\u2019\u014fngno"
    ],
    "wof:name":"Ch'ongno",
    "wof:placetype":"locality"
},
  "geometry": {"coordinates":[128.67527999999999,36.23472],"type":"Point"}
}