{
  "type": "Feature",
  "properties": {
    "gn:admin1_code":"20.0",
    "gn:asciiname":"Ch'okponjong-ni",
    "gn:country_code":"KR",
    "gn:dem":82,
    "gn:feature_class":"P",
    "gn:feature_code":"PPL",
    "gn:name":"Ch\u2019\u014fkp\u014fnj\u014fng-ni",
    "gn:population":0,
    "gn:timezone":"Asia/Seoul",
    "iso:country":"KR",
    "name:und_x_variant":[
        "Choj\u014fng-ni",
        "Ch\u2019\u014fkp\u014fnj\u014fng-ni"
    ],
    "wof:name":"Ch'okponjong-ni",
    "wof:placetype":"locality"
},
  "geometry": {"coordinates":[128.18861000000001,34.99694],"type":"Point"}
}