{
  "type": "Feature",
  "properties": {
    "gn:admin1_code":"14.0",
    "gn:asciiname":"Changp'yong",
    "gn:country_code":"KR",
    "gn:dem":9,
    "gn:feature_class":"P",
    "gn:feature_code":"PPL",
    "gn:name":"Changp\u2019y\u014fng",
    "gn:population":0,
    "gn:timezone":"Asia/Seoul",
    "iso:country":"KR",
    "name:und_x_variant":[
        "\uc7a5\ud3c9",
        "Changp\u2019y\u014fng"
    ],
    "wof:name":"Changp'yong",
    "wof:placetype":"locality"
},
  "geometry": {"coordinates":[129.3989,36.9632],"type":"Point"}
}