{
  "type": "Feature",
  "properties": {
    "gn:admin1_code":"20.0",
    "gn:asciiname":"Sop'o",
    "gn:country_code":"KR",
    "gn:dem":10,
    "gn:feature_class":"P",
    "gn:feature_code":"PPL",
    "gn:name":"Sop\u2019o",
    "gn:population":0,
    "gn:timezone":"Asia/Seoul",
    "iso:country":"KR",
    "name:und_x_variant":[
        "\uc18c\ud3ec",
        "Sop\u2019o"
    ],
    "wof:name":"Sop'o",
    "wof:placetype":"locality"
},
  "geometry": {"coordinates":[128.40495000000001,34.86043],"type":"Point"}
}