{
  "type": "Feature",
  "properties": {
    "gn:admin1_code":"5.0",
    "gn:asciiname":"Cholt'o-gol",
    "gn:country_code":"KR",
    "gn:dem":471,
    "gn:feature_class":"P",
    "gn:feature_code":"PPL",
    "gn:name":"Ch\u014flt\u2019\u014f-gol",
    "gn:population":0,
    "gn:timezone":"Asia/Seoul",
    "iso:country":"KR",
    "name:kor_x_preferred":[
        "\uc808\ud130\uace8"
    ],
    "name:kor_x_variant":[
        "Ch\u014flt\u2019\u014f-gol"
    ],
    "wof:name":"Cholt'o-gol",
    "wof:placetype":"locality"
},
  "geometry": {"coordinates":[128.06010000000001,37.1339],"type":"Point"}
}