{
  "type": "Feature",
  "properties": {
    "gn:admin1_code":"16.0",
    "gn:asciiname":"Ttansom",
    "gn:country_code":"KR",
    "gn:dem":-9999,
    "gn:feature_class":"P",
    "gn:feature_code":"PPL",
    "gn:name":"Ttans\u014fm",
    "gn:population":0,
    "gn:timezone":"Asia/Seoul",
    "iso:country":"KR",
    "wof:name":"Ttansom",
    "wof:placetype":"locality"
},
  "geometry": {"coordinates":[125.95583000000001,34.72528],"type":"Point"}
}