{
  "type": "Feature",
  "properties": {
    "gn:admin1_code":"17.0",
    "gn:asciiname":"Manbok",
    "gn:country_code":"KR",
    "gn:dem":125,
    "gn:feature_class":"P",
    "gn:feature_code":"PPL",
    "gn:name":"Manbok",
    "gn:population":0,
    "gn:timezone":"Asia/Seoul",
    "iso:country":"KR",
    "name:kor_x_preferred":[
        "\ub9cc\ubcf5"
    ],
    "wof:name":"Manbok",
    "wof:placetype":"locality"
},
  "geometry": {"coordinates":[127.06207999999999,36.68597000000001],"type":"Point"}
}