{
  "type": "Feature",
  "properties": {
    "gn:admin1_code":"17.0",
    "gn:asciiname":"Moraebat",
    "gn:country_code":"KR",
    "gn:dem":139,
    "gn:feature_class":"P",
    "gn:feature_code":"PPL",
    "gn:name":"Moraebat",
    "gn:population":0,
    "gn:timezone":"Asia/Seoul",
    "iso:country":"KR",
    "name:kor_x_preferred":[
        "\ubaa8\ub798\ubc2d"
    ],
    "wof:name":"Moraebat",
    "wof:placetype":"locality"
},
  "geometry": {"coordinates":[127.28037,36.24119],"type":"Point"}
}