{
  "type": "Feature",
  "properties": {
    "gn:admin1_code":"13.0",
    "gn:asciiname":"Maehwaji",
    "gn:country_code":"KR",
    "gn:dem":57,
    "gn:feature_class":"P",
    "gn:feature_code":"PPL",
    "gn:name":"Maehwaji",
    "gn:population":0,
    "gn:timezone":"Asia/Seoul",
    "iso:country":"KR",
    "name:und_x_variant":[
        "\ub9e4\ud654\uc9c0",
        "Maehwaji"
    ],
    "wof:name":"Maehwaji",
    "wof:placetype":"locality"
},
  "geometry": {"coordinates":[127.54277999999999,37.27028],"type":"Point"}
}