{
  "type": "Feature",
  "properties": {
    "gn:admin1_code":"14.0",
    "gn:asciiname":"Milmotmit",
    "gn:country_code":"KR",
    "gn:dem":90,
    "gn:feature_class":"P",
    "gn:feature_code":"PPL",
    "gn:name":"Milmotmit",
    "gn:population":0,
    "gn:timezone":"Asia/Seoul",
    "iso:country":"KR",
    "name:kor_x_preferred":[
        "\ubc00\ubabb\ubc11"
    ],
    "wof:name":"Milmotmit",
    "wof:placetype":"locality"
},
  "geometry": {"coordinates":[128.83436,35.77425],"type":"Point"}
}