{
  "type": "Feature",
  "properties": {
    "gn:admin1_code":"3.0",
    "gn:asciiname":"Sangam",
    "gn:country_code":"KR",
    "gn:dem":38,
    "gn:feature_class":"P",
    "gn:feature_code":"PPL",
    "gn:name":"Sangam",
    "gn:population":0,
    "gn:timezone":"Asia/Seoul",
    "iso:country":"KR",
    "name:ben_x_preferred":[
        "\u09b8\u0999\u09cd\u0997\u09ae"
    ],
    "name:bih_x_preferred":[
        "\u0938\u0902\u0917\u092e"
    ],
    "name:deu_x_preferred":[
        "Sangam"
    ],
    "name:hin_x_preferred":[
        "\u0938\u0902\u0917\u092e"
    ],
    "name:kan_x_preferred":[
        "\u0cb8\u0c82\u0c97\u0cae"
    ],
    "name:und_x_variant":[
        "\uc0c1\uc554"
    ],
    "wof:name":"Sangam",
    "wof:placetype":"locality"
},
  "geometry": {"coordinates":[127.09211999999999,35.97806],"type":"Point"}
}