{
  "type": "Feature",
  "properties": {
    "gn:admin1_code":"6.0",
    "gn:asciiname":"Sangbuk-tong",
    "gn:country_code":"KR",
    "gn:dem":530,
    "gn:feature_class":"P",
    "gn:feature_code":"PPL",
    "gn:name":"Sangbuk-tong",
    "gn:population":0,
    "gn:timezone":"Asia/Seoul",
    "iso:country":"KR",
    "name:kor_x_preferred":[
        "\uc0c1\ubd81\ub3d9"
    ],
    "wof:name":"Sangbuk-tong",
    "wof:placetype":"locality"
},
  "geometry": {"coordinates":[128.7911,37.3795],"type":"Point"}
}