{
  "type": "Feature",
  "properties": {
    "gn:admin1_code":"11.0",
    "gn:asciiname":"Nonhyoni-dong",
    "gn:country_code":"KR",
    "gn:dem":60,
    "gn:feature_class":"P",
    "gn:feature_code":"PPL",
    "gn:name":"Nonhy\u014fni-dong",
    "gn:population":0,
    "gn:timezone":"Asia/Seoul",
    "iso:country":"KR",
    "name:und_x_variant":[
        "\ub17c\ud6042\ub3d9",
        "Nonhy\u014fni-dong"
    ],
    "wof:name":"Nonhyoni-dong",
    "wof:placetype":"locality"
},
  "geometry": {"coordinates":[127.03594,37.51515],"type":"Point"}
}