{
  "type": "Feature",
  "properties": {
    "gn:admin1_code":"20.0",
    "gn:asciiname":"Ogong-ni",
    "gn:country_code":"KR",
    "gn:dem":56,
    "gn:feature_class":"P",
    "gn:feature_code":"PPL",
    "gn:name":"\u014egong-ni",
    "gn:population":0,
    "gn:timezone":"Asia/Seoul",
    "iso:country":"KR",
    "name:eng_x_preferred":[
        "Ogong"
    ],
    "name:eng_x_variant":[
        "Ogong-ni"
    ],
    "wof:name":"Ogong",
    "wof:placetype":"locality"
},
  "geometry": {"coordinates":[129.02444,35.37583],"type":"Point"}
}