{
  "type": "Feature",
  "properties": {
    "gn:admin1_code":"17.0",
    "gn:asciiname":"Misangni",
    "gn:country_code":"KR",
    "gn:dem":205,
    "gn:feature_class":"P",
    "gn:feature_code":"PPL",
    "gn:name":"Misangni",
    "gn:population":0,
    "gn:timezone":"Asia/Seoul",
    "iso:country":"KR",
    "name:und_x_variant":[
        "\ubbf8\uc0ad\ub9ac",
        "Misangni"
    ],
    "wof:name":"Misangni",
    "wof:placetype":"locality"
},
  "geometry": {"coordinates":[127.46898,36.19922],"type":"Point"}
}