{
  "type": "Feature",
  "properties": {
    "gn:admin1_code":"14.0",
    "gn:asciiname":"Paeda-ri",
    "gn:country_code":"KR",
    "gn:dem":89,
    "gn:feature_class":"P",
    "gn:feature_code":"PPL",
    "gn:name":"Paeda-ri",
    "gn:population":0,
    "gn:timezone":"Asia/Seoul",
    "iso:country":"KR",
    "name:und_x_variant":[
        "\ubc30\ub2e4\ub9ac",
        "Paeda-ri"
    ],
    "wof:name":"Paeda-ri",
    "wof:placetype":"locality"
},
  "geometry": {"coordinates":[128.13919999999999,36.1216],"type":"Point"}
}