{
  "type": "Feature",
  "properties": {
    "gn:admin1_code":"14.0",
    "gn:asciiname":"Eumnae",
    "gn:country_code":"KR",
    "gn:dem":33,
    "gn:feature_class":"P",
    "gn:feature_code":"PPL",
    "gn:name":"Eumnae",
    "gn:population":0,
    "gn:timezone":"Asia/Seoul",
    "iso:country":"KR",
    "name:kor_x_preferred":[
        "\uc74d\ub0b4"
    ],
    "name:und_x_variant":[
        "\u016cmnae-ri"
    ],
    "wof:name":"Eumnae",
    "wof:placetype":"locality"
},
  "geometry": {"coordinates":[129.48963000000001,35.90015],"type":"Point"}
}