{
  "type": "Feature",
  "properties": {
    "gn:admin1_code":"13.0",
    "gn:asciiname":"Haejo",
    "gn:country_code":"KR",
    "gn:dem":20,
    "gn:feature_class":"P",
    "gn:feature_code":"PPL",
    "gn:name":"Haejo",
    "gn:population":0,
    "gn:timezone":"Asia/Seoul",
    "iso:country":"KR",
    "name:kor_x_preferred":[
        "\ud574\uc870"
    ],
    "name:und_x_variant":[
        "Haejo-ri",
        "Haejo"
    ],
    "wof:name":"Haejo",
    "wof:placetype":"locality"
},
  "geometry": {"coordinates":[126.90458,36.99278],"type":"Point"}
}