{
  "type": "Feature",
  "properties": {
    "gn:admin1_code":"3.0",
    "gn:asciiname":"Pangsong-gol",
    "gn:country_code":"KR",
    "gn:dem":233,
    "gn:feature_class":"P",
    "gn:feature_code":"PPL",
    "gn:name":"Pangs\u014fng-gol",
    "gn:population":0,
    "gn:timezone":"Asia/Seoul",
    "iso:country":"KR",
    "name:und_x_variant":[
        "\ubc29\uc131\uace8",
        "Pangs\u014fng-gol",
        "Bangseonggol"
    ],
    "wof:name":"Pangsong-gol",
    "wof:placetype":"locality"
},
  "geometry": {"coordinates":[127.06256999999999,35.58075],"type":"Point"}
}