{
  "type": "Feature",
  "properties": {
    "gn:admin1_code":"20.0",
    "gn:asciiname":"Sosa",
    "gn:country_code":"KR",
    "gn:dem":33,
    "gn:feature_class":"P",
    "gn:feature_code":"PPL",
    "gn:name":"Sosa",
    "gn:population":0,
    "gn:timezone":"Asia/Seoul",
    "iso:country":"KR",
    "name:cat_x_preferred":[
        "Sosa"
    ],
    "name:ceb_x_preferred":[
        "Sosa"
    ],
    "name:deu_x_preferred":[
        "Sosa"
    ],
    "name:est_x_preferred":[
        "Sosa"
    ],
    "name:fra_x_preferred":[
        "Sosa"
    ],
    "name:heb_x_preferred":[
        "\u05e1\u05d5\u05e1\u05d4"
    ],
    "name:ita_x_preferred":[
        "Sosa"
    ],
    "name:jpn_x_preferred":[
        "\u30bd\u30fc\u30b5"
    ],
    "name:nld_x_preferred":[
        "Sosa"
    ],
    "name:pol_x_preferred":[
        "Sosa"
    ],
    "name:rus_x_preferred":[
        "\u0421\u043e\u0441\u0430"
    ],
    "name:spa_x_preferred":[
        "Sosa"
    ],
    "name:srp_x_preferred":[
        "\u0421\u043e\u0441\u0430"
    ],
    "name:swa_x_preferred":[
        "Sosa"
    ],
    "name:swe_x_preferred":[
        "Sosa"
    ],
    "name:ukr_x_preferred":[
        "\u0421\u043e\u0441\u0430"
    ],
    "name:und_x_variant":[
        "\uc18c\uc0ac"
    ],
    "wof:name":"Sosa",
    "wof:placetype":"locality"
},
  "geometry": {"coordinates":[128.47364999999999,35.3317],"type":"Point"}
}