{
  "type": "Feature",
  "properties": {
    "gn:admin1_code":"14.0",
    "gn:asciiname":"Onggijom",
    "gn:country_code":"KR",
    "gn:dem":36,
    "gn:feature_class":"P",
    "gn:feature_code":"PPL",
    "gn:name":"Onggij\u014fm",
    "gn:population":0,
    "gn:timezone":"Asia/Seoul",
    "iso:country":"KR",
    "name:und_x_variant":[
        "\uc639\uae30\uc810",
        "Onggij\u014fm"
    ],
    "wof:name":"Onggijom",
    "wof:placetype":"locality"
},
  "geometry": {"coordinates":[129.38229999999999,37.008],"type":"Point"}
}