{
  "type": "Feature",
  "properties": {
    "gn:admin1_code":"17.0",
    "gn:asciiname":"Sonch'on",
    "gn:country_code":"KR",
    "gn:dem":3,
    "gn:feature_class":"P",
    "gn:feature_code":"PPL",
    "gn:name":"S\u014fnch\u2019on",
    "gn:population":0,
    "gn:timezone":"Asia/Seoul",
    "iso:country":"KR",
    "name:und_x_variant":[
        "S\u014fnch\u2019on-ni",
        "S\u014fnch\u2019on"
    ],
    "wof:name":"Sonch'on",
    "wof:placetype":"locality"
},
  "geometry": {"coordinates":[126.43333,36.38333],"type":"Point"}
}