{
  "type": "Feature",
  "properties": {
    "gn:admin1_code":"13.0",
    "gn:asciiname":"Seolmaesil",
    "gn:country_code":"KR",
    "gn:dem":148,
    "gn:feature_class":"P",
    "gn:feature_code":"PPL",
    "gn:name":"Seolmaesil",
    "gn:population":0,
    "gn:timezone":"Asia/Seoul",
    "iso:country":"KR",
    "name:und_x_variant":[
        "\uc124\ub9e4\uc2e4",
        "Seolmaesil",
        "S\u014flmaesil"
    ],
    "wof:name":"Seolmaesil",
    "wof:placetype":"locality"
},
  "geometry": {"coordinates":[127.72861,37.43944000000001],"type":"Point"}
}