{
  "type": "Feature",
  "properties": {
    "gn:admin1_code":"20.0",
    "gn:asciiname":"Changch'ok",
    "gn:country_code":"KR",
    "gn:dem":173,
    "gn:feature_class":"P",
    "gn:feature_code":"PPL",
    "gn:name":"Changch\u2019\u014fk",
    "gn:population":0,
    "gn:timezone":"Asia/Seoul",
    "iso:country":"KR",
    "name:und_x_variant":[
        "Changch\u2019\u014fng-ni",
        "Changch\u2019\u014fk"
    ],
    "wof:name":"Changch'ok",
    "wof:placetype":"locality"
},
  "geometry": {"coordinates":[128.91749999999999,35.28667],"type":"Point"}
}