{
  "type": "Feature",
  "properties": {
    "gn:admin1_code":"6.0",
    "gn:asciiname":"Tongnam",
    "gn:country_code":"KR",
    "gn:dem":87,
    "gn:feature_class":"P",
    "gn:feature_code":"PPL",
    "gn:name":"T\u014fngnam",
    "gn:population":0,
    "gn:timezone":"Asia/Seoul",
    "iso:country":"KR",
    "name:kor_x_preferred":[
        "\ub355\ub0a8"
    ],
    "name:kor_x_variant":[
        "T\u014fngnam"
    ],
    "wof:name":"Tongnam",
    "wof:placetype":"locality"
},
  "geometry": {"coordinates":[127.83580000000001,37.3269],"type":"Point"}
}