{
  "type": "Feature",
  "properties": {
    "gn:admin1_code":"17.0",
    "gn:asciiname":"Kwimissan",
    "gn:country_code":"KR",
    "gn:dem":35,
    "gn:feature_class":"P",
    "gn:feature_code":"PPL",
    "gn:name":"Kwimissan",
    "gn:population":0,
    "gn:timezone":"Asia/Seoul",
    "iso:country":"KR",
    "name:und_x_variant":[
        "\uadc0\ubc0b\uc0b0",
        "Kwimissan"
    ],
    "wof:name":"Kwimissan",
    "wof:placetype":"locality"
},
  "geometry": {"coordinates":[126.3111,36.728],"type":"Point"}
}