{
  "type": "Feature",
  "properties": {
    "gn:admin1_code":"14.0",
    "gn:asciiname":"Taeju-gol",
    "gn:country_code":"KR",
    "gn:dem":118,
    "gn:feature_class":"P",
    "gn:feature_code":"PPL",
    "gn:name":"Taeju-gol",
    "gn:population":0,
    "gn:timezone":"Asia/Seoul",
    "iso:country":"KR",
    "name:und_x_variant":[
        "\ub300\uc8fc\uace8",
        "Taeju-gol"
    ],
    "wof:name":"Taeju-gol",
    "wof:placetype":"locality"
},
  "geometry": {"coordinates":[129.01751999999999,36.00360999999999],"type":"Point"}
}