{
  "type": "Feature",
  "properties": {
    "gn:admin1_code":"3.0",
    "gn:asciiname":"Sang-dong",
    "gn:country_code":"KR",
    "gn:dem":359,
    "gn:feature_class":"P",
    "gn:feature_code":"PPL",
    "gn:name":"Sang-dong",
    "gn:population":0,
    "gn:timezone":"Asia/Seoul",
    "iso:country":"KR",
    "name:und_x_variant":[
        "\uc0c1\ub3d9",
        "Sang-dong"
    ],
    "wof:name":"Sang-dong",
    "wof:placetype":"locality"
},
  "geometry": {"coordinates":[127.55665999999999,35.57265],"type":"Point"}
}