{
  "type": "Feature",
  "properties": {
    "gn:admin1_code":"20.0",
    "gn:asciiname":"Naedo",
    "gn:country_code":"KR",
    "gn:dem":-9999,
    "gn:feature_class":"P",
    "gn:feature_code":"PPL",
    "gn:name":"Naedo",
    "gn:population":0,
    "gn:timezone":"Asia/Seoul",
    "iso:country":"KR",
    "name:kor_x_preferred":[
        "\ub0b4\ub3c4"
    ],
    "name:und_x_variant":[
        "Naedo-ri",
        "Naes\u014fm",
        "Naedo"
    ],
    "wof:name":"Naedo",
    "wof:placetype":"locality"
},
  "geometry": {"coordinates":[127.78728,34.95287],"type":"Point"}
}