{
  "type": "Feature",
  "properties": {
    "gn:admin1_code":"3.0",
    "gn:asciiname":"Mokjeom",
    "gn:country_code":"KR",
    "gn:dem":49,
    "gn:feature_class":"P",
    "gn:feature_code":"PPL",
    "gn:name":"Mokjeom",
    "gn:population":0,
    "gn:timezone":"Asia/Seoul",
    "iso:country":"KR",
    "name:kor_x_preferred":[
        "\ubaa9\uc810"
    ],
    "wof:name":"Mokjeom",
    "wof:placetype":"locality"
},
  "geometry": {"coordinates":[126.67408,35.38494],"type":"Point"}
}