{
  "type": "Feature",
  "properties": {
    "gn:admin1_code":"5.0",
    "gn:asciiname":"Tongmak-kol",
    "gn:country_code":"KR",
    "gn:dem":273,
    "gn:feature_class":"P",
    "gn:feature_code":"PPL",
    "gn:name":"Tongmak-kol",
    "gn:population":0,
    "gn:timezone":"Asia/Seoul",
    "iso:country":"KR",
    "name:kor_x_preferred":[
        "\ub3d9\ub9c9\uace8"
    ],
    "wof:name":"Tongmak-kol",
    "wof:placetype":"locality"
},
  "geometry": {"coordinates":[128.1728,37.1218],"type":"Point"}
}