{
  "type": "Feature",
  "properties": {
    "gn:admin1_code":"16.0",
    "gn:asciiname":"Kusang",
    "gn:cc2":"KR",
    "gn:country_code":"KR",
    "gn:dem":11,
    "gn:feature_class":"P",
    "gn:feature_code":"PPL",
    "gn:name":"Kusang",
    "gn:population":0,
    "gn:timezone":"Asia/Seoul",
    "iso:country":"KR",
    "name:und_x_variant":[
        "Kusang-ni",
        "Kusang"
    ],
    "wof:name":"Kusang",
    "wof:placetype":"locality"
},
  "geometry": {"coordinates":[127.56111,34.90389],"type":"Point"}
}