{
  "type": "Feature",
  "properties": {
    "gn:admin1_code":"13.0",
    "gn:asciiname":"Dumae",
    "gn:country_code":"KR",
    "gn:dem":13,
    "gn:feature_class":"P",
    "gn:feature_code":"PPL",
    "gn:name":"Dumae",
    "gn:population":0,
    "gn:timezone":"Asia/Seoul",
    "iso:country":"KR",
    "name:kor_x_preferred":[
        "\ub450\ub9e4"
    ],
    "name:kor_x_variant":[
        "\uc7a5\uc218"
    ],
    "name:und_x_variant":[
        "Tumae-ri",
        "Tumae",
        "Dumae",
        "Changsu"
    ],
    "wof:name":"Dumae",
    "wof:placetype":"locality"
},
  "geometry": {"coordinates":[126.89995,36.93917],"type":"Point"}
}