{
  "type": "Feature",
  "properties": {
    "gn:admin1_code":"6.0",
    "gn:asciiname":"Sangdubat",
    "gn:country_code":"KR",
    "gn:dem":661,
    "gn:feature_class":"P",
    "gn:feature_code":"PPL",
    "gn:name":"Sangdubat",
    "gn:population":0,
    "gn:timezone":"Asia/Seoul",
    "iso:country":"KR",
    "name:kor_x_preferred":[
        "\uc0c1\ub450\ubc2d"
    ],
    "wof:name":"Sangdubat",
    "wof:placetype":"locality"
},
  "geometry": {"coordinates":[128.91074,37.48305],"type":"Point"}
}