{
  "type": "Feature",
  "properties": {
    "gn:admin1_code":"14.0",
    "gn:asciiname":"Taet'ae",
    "gn:country_code":"KR",
    "gn:dem":479,
    "gn:feature_class":"P",
    "gn:feature_code":"PPL",
    "gn:name":"Taet\u2019ae",
    "gn:population":0,
    "gn:timezone":"Asia/Seoul",
    "iso:country":"KR",
    "name:und_x_variant":[
        "\ub300\ud0dc",
        "Taet\u2019ae"
    ],
    "wof:name":"Taet'ae",
    "wof:placetype":"locality"
},
  "geometry": {"coordinates":[129.03482,36.16406],"type":"Point"}
}