{
  "type": "Feature",
  "properties": {
    "gn:admin1_code":"6.0",
    "gn:asciiname":"Piasi",
    "gn:country_code":"KR",
    "gn:dem":284,
    "gn:feature_class":"P",
    "gn:feature_code":"PPL",
    "gn:name":"Piasi",
    "gn:population":0,
    "gn:timezone":"Asia/Seoul",
    "iso:country":"KR",
    "name:und_x_variant":[
        "P\u2019iasi",
        "\ud53c\uc544\uc2dc",
        "Piasi"
    ],
    "wof:name":"Piasi",
    "wof:placetype":"locality"
},
  "geometry": {"coordinates":[128.22416999999999,38.02937],"type":"Point"}
}