{
  "type": "Feature",
  "properties": {
    "gn:admin1_code":"6.0",
    "gn:asciiname":"Hachon",
    "gn:country_code":"KR",
    "gn:dem":241,
    "gn:feature_class":"P",
    "gn:feature_code":"PPL",
    "gn:name":"Hachon",
    "gn:population":0,
    "gn:timezone":"Asia/Seoul",
    "iso:country":"KR",
    "name:kor_x_preferred":[
        "\ud558\ucd0c"
    ],
    "name:kor_x_variant":[
        "Hach\u2019on"
    ],
    "wof:name":"Hachon",
    "wof:placetype":"locality"
},
  "geometry": {"coordinates":[128.02045000000001,37.88833],"type":"Point"}
}