{
  "type": "Feature",
  "properties": {
    "gn:admin1_code":"13.0",
    "gn:asciiname":"Dambaechon",
    "gn:country_code":"KR",
    "gn:dem":146,
    "gn:feature_class":"P",
    "gn:feature_code":"PPL",
    "gn:name":"Dambaechon",
    "gn:population":0,
    "gn:timezone":"Asia/Seoul",
    "iso:country":"KR",
    "name:und_x_variant":[
        "\ub2f4\ubc30\ucd0c",
        "Dambaechon",
        "Tambaech\u2019on"
    ],
    "wof:name":"Dambaechon",
    "wof:placetype":"locality"
},
  "geometry": {"coordinates":[126.90056,37.37306],"type":"Point"}
}