{
  "type": "Feature",
  "properties": {
    "gn:admin1_code":"13.0",
    "gn:asciiname":"Choridong",
    "gn:country_code":"KR",
    "gn:dem":131,
    "gn:feature_class":"P",
    "gn:feature_code":"PPL",
    "gn:name":"Choridong",
    "gn:population":0,
    "gn:timezone":"Asia/Seoul",
    "iso:country":"KR",
    "name:kor_x_preferred":[
        "\ucd08\ub9ac\ub3d9"
    ],
    "name:und_x_variant":[
        "\ucd08\ub9ac\uace8",
        "Ch\u2019ori-gol",
        "Choridong",
        "Chorigol"
    ],
    "wof:name":"Choridong",
    "wof:placetype":"locality"
},
  "geometry": {"coordinates":[126.90177,37.86446],"type":"Point"}
}