{
  "type": "Feature",
  "properties": {
    "gn:admin1_code":"5.0",
    "gn:asciiname":"Gomnimi",
    "gn:country_code":"KR",
    "gn:dem":211,
    "gn:feature_class":"P",
    "gn:feature_code":"PPL",
    "gn:name":"Gomnimi",
    "gn:population":0,
    "gn:timezone":"Asia/Seoul",
    "iso:country":"KR",
    "name:kor_x_preferred":[
        "\uacf0\ub2d8\uc774"
    ],
    "wof:name":"Gomnimi",
    "wof:placetype":"locality"
},
  "geometry": {"coordinates":[127.83201,36.71458],"type":"Point"}
}