{
  "type": "Feature",
  "properties": {
    "gn:admin1_code":"3.0",
    "gn:asciiname":"Wolsang-ni",
    "gn:country_code":"KR",
    "gn:dem":185,
    "gn:feature_class":"P",
    "gn:feature_code":"PPL",
    "gn:name":"W\u014flsang-ni",
    "gn:population":0,
    "gn:timezone":"Asia/Seoul",
    "iso:country":"KR",
    "name:und_x_variant":[
        "\uc6d4\uc0c1\ub9ac",
        "W\u014flsang-ni"
    ],
    "wof:name":"Wolsang-ni",
    "wof:placetype":"locality"
},
  "geometry": {"coordinates":[127.28028999999999,35.80436],"type":"Point"}
}