{
  "type": "Feature",
  "properties": {
    "gn:admin1_code":"6.0",
    "gn:asciiname":"Mach'ajae",
    "gn:country_code":"KR",
    "gn:dem":690,
    "gn:feature_class":"P",
    "gn:feature_code":"PPL",
    "gn:name":"Mach\u2019ajae",
    "gn:population":0,
    "gn:timezone":"Asia/Seoul",
    "iso:country":"KR",
    "name:kor_x_preferred":[
        "\ub9c8\ucc28\uc7ac"
    ],
    "name:kor_x_variant":[
        "Mach\u2019ajae"
    ],
    "name:und_x_variant":[
        "Mach\u2019a",
        "Mach\u2019ae"
    ],
    "wof:name":"Mach'ajae",
    "wof:placetype":"locality"
},
  "geometry": {"coordinates":[128.6712,37.27],"type":"Point"}
}