{
  "type": "Feature",
  "properties": {
    "gn:admin1_code":"17.0",
    "gn:asciiname":"Maeng-gol",
    "gn:country_code":"KR",
    "gn:dem":24,
    "gn:feature_class":"P",
    "gn:feature_code":"PPL",
    "gn:name":"Maeng-gol",
    "gn:population":0,
    "gn:timezone":"Asia/Seoul",
    "iso:country":"KR",
    "name:und_x_variant":[
        "\ub9f9\uace8",
        "Maeng-gol"
    ],
    "wof:name":"Maeng-gol",
    "wof:placetype":"locality"
},
  "geometry": {"coordinates":[127.08,36.7912],"type":"Point"}
}