{
  "type": "Feature",
  "properties": {
    "gn:admin1_code":"11.0",
    "gn:asciiname":"Yeoksam-dong",
    "gn:country_code":"KR",
    "gn:dem":29,
    "gn:feature_class":"P",
    "gn:feature_code":"PPL",
    "gn:name":"Yeoksam-dong",
    "gn:population":0,
    "gn:timezone":"Asia/Seoul",
    "iso:country":"KR",
    "name:fas_x_preferred":[
        "\u06cc\u0626\u0648\u06a9\u0633\u0627\u0645-\u062f\u0648\u0646\u06af"
    ],
    "name:kor_x_preferred":[
        "\uc5ed\uc0bc\ub3d9"
    ],
    "name:msa_x_preferred":[
        "Yeoksam-dong"
    ],
    "name:por_x_preferred":[
        "Yeoksam-dong"
    ],
    "name:sco_x_preferred":[
        "Yeoksam-dong"
    ],
    "name:und_x_variant":[
        "Y\u014fksam-dong"
    ],
    "name:urd_x_preferred":[
        "\u06cc\u0648\u06a9\u0633\u0645-\u0688\u0648\u0646\u06af"
    ],
    "name:vie_x_preferred":[
        "Yeoksam-dong"
    ],
    "wof:name":"Yeoksam-dong",
    "wof:placetype":"locality"
},
  "geometry": {"coordinates":[127.03528,37.49556],"type":"Point"}
}