{
  "type": "Feature",
  "properties": {
    "gn:admin1_code":"17.0",
    "gn:asciiname":"Majon",
    "gn:country_code":"KR",
    "gn:dem":48,
    "gn:feature_class":"P",
    "gn:feature_code":"PPL",
    "gn:name":"Maj\u014fn",
    "gn:population":0,
    "gn:timezone":"Asia/Seoul",
    "iso:country":"KR",
    "name:und_x_variant":[
        "\ub9c8\uc804",
        "Maj\u014fn"
    ],
    "wof:name":"Majon",
    "wof:placetype":"locality"
},
  "geometry": {"coordinates":[126.8147,36.5748],"type":"Point"}
}