{
  "type": "Feature",
  "properties": {
    "gn:admin1_code":"6.0",
    "gn:asciiname":"Cheongnyangnigol",
    "gn:country_code":"KR",
    "gn:dem":413,
    "gn:feature_class":"P",
    "gn:feature_code":"PPL",
    "gn:name":"Cheongnyangnigol",
    "gn:population":0,
    "gn:timezone":"Asia/Seoul",
    "iso:country":"KR",
    "name:kor_x_preferred":[
        "\uccad\ub7c9\ub9ac\uace8"
    ],
    "name:kor_x_variant":[
        "Ch\u2019\u014fngnyangni-gol"
    ],
    "wof:name":"Cheongnyangnigol",
    "wof:placetype":"locality"
},
  "geometry": {"coordinates":[127.95121,38.08939],"type":"Point"}
}