{
  "type": "Feature",
  "properties": {
    "gn:admin1_code":"0.0",
    "gn:asciiname":"Naema",
    "gn:cc2":"KR",
    "gn:country_code":"KR",
    "gn:dem":234,
    "gn:feature_class":"P",
    "gn:feature_code":"PPL",
    "gn:name":"Naema",
    "gn:population":0,
    "gn:timezone":"Asia/Seoul",
    "iso:country":"KR",
    "name:und_x_variant":[
        "Naema-ri",
        "Naema"
    ],
    "wof:name":"Naema",
    "wof:placetype":"locality"
},
  "geometry": {"coordinates":[127.13333,35.63333],"type":"Point"}
}