{
  "type": "Feature",
  "properties": {
    "gn:admin1_code":"16.0",
    "gn:asciiname":"Goeup",
    "gn:country_code":"KR",
    "gn:dem":29,
    "gn:feature_class":"P",
    "gn:feature_code":"PPL",
    "gn:name":"Goeup",
    "gn:population":0,
    "gn:timezone":"Asia/Seoul",
    "iso:country":"KR",
    "name:kor_x_preferred":[
        "\uace0\uc74d"
    ],
    "name:kor_x_variant":[
        "Ko\u016dp"
    ],
    "wof:name":"Goeup",
    "wof:placetype":"locality"
},
  "geometry": {"coordinates":[127.31515,34.86102],"type":"Point"}
}