{
  "type": "Feature",
  "properties": {
    "gn:admin1_code":"6.0",
    "gn:asciiname":"Dwinmal",
    "gn:country_code":"KR",
    "gn:dem":154,
    "gn:feature_class":"P",
    "gn:feature_code":"PPL",
    "gn:name":"Dwinmal",
    "gn:population":0,
    "gn:timezone":"Asia/Seoul",
    "iso:country":"KR",
    "name:kor_x_preferred":[
        "\ub4b7\ub9d0"
    ],
    "wof:name":"Dwinmal",
    "wof:placetype":"locality"
},
  "geometry": {"coordinates":[127.62069,37.98073],"type":"Point"}
}