{
  "type": "Feature",
  "properties": {
    "gn:admin1_code":"6.0",
    "gn:asciiname":"Ch'ongnyongp'o",
    "gn:country_code":"KR",
    "gn:dem":215,
    "gn:feature_class":"P",
    "gn:feature_code":"PPL",
    "gn:name":"Ch\u2019\u014fngny\u014fngp\u2019o",
    "gn:population":0,
    "gn:timezone":"Asia/Seoul",
    "iso:country":"KR",
    "name:kor_x_preferred":[
        "\uccad\ub839\ud3ec"
    ],
    "name:kor_x_variant":[
        "Ch\u2019\u014fngny\u014fngp\u2019o"
    ],
    "wof:name":"Ch'ongnyongp'o",
    "wof:placetype":"locality"
},
  "geometry": {"coordinates":[128.43459999999999,37.181],"type":"Point"}
}