{
  "type": "Feature",
  "properties": {
    "gn:admin1_code":"16.0",
    "gn:asciiname":"Puhung",
    "gn:country_code":"KR",
    "gn:dem":16,
    "gn:feature_class":"P",
    "gn:feature_code":"PPL",
    "gn:name":"Puh\u016dng",
    "gn:population":0,
    "gn:timezone":"Asia/Seoul",
    "iso:country":"KR",
    "name:kor_x_preferred":[
        "\ub3c4\uc11c"
    ],
    "name:kor_x_variant":[
        "Puh\u016dng"
    ],
    "wof:name":"Puhung",
    "wof:placetype":"locality"
},
  "geometry": {"coordinates":[126.88333,34.48917],"type":"Point"}
}