{
  "type": "Feature",
  "properties": {
    "iso:country":"KR",
    "qs:name":"\uc624\uac00\uba74",
    "qs:name_adm0":"\ud55c\uad6d",
    "qs:name_adm1":"\ucda9\uccad\ub0a8\ub3c4",
    "qs:photos":34,
    "qs:photos_1k":7,
    "qs:photos_9k":1,
    "qs:photos_9r":2,
    "qs:photos_all":34,
    "qs:photos_sr":2,
    "qs:placetype":"LocalAdmin",
    "qs:pop_sr":"0",
    "wof:name":"\uc624\uac00\uba74",
    "wof:placetype":"localadmin"
},
  "geometry": {"coordinates":[126.8179315,36.7190715],"type":"Point"}
}