{
  "type": "Feature",
  "properties": {
    "gn:admin1_code":"13.0",
    "gn:asciiname":"Witgachiraemi",
    "gn:country_code":"KR",
    "gn:dem":118,
    "gn:feature_class":"P",
    "gn:feature_code":"PPL",
    "gn:name":"Witgachiraemi",
    "gn:population":0,
    "gn:timezone":"Asia/Seoul",
    "iso:country":"KR",
    "name:kor_x_preferred":[
        "\uc717\uac00\uce58\ub798\ubbf8"
    ],
    "name:und_x_variant":[
        "Ukkajiraemi",
        "Wikkaraech\u2019iraemi",
        "Witgachiraemi"
    ],
    "wof:name":"Witgachiraemi",
    "wof:placetype":"locality"
},
  "geometry": {"coordinates":[127.32605,37.10494],"type":"Point"}
}