{
  "type": "Feature",
  "properties": {
    "gn:admin1_code":"14.0",
    "gn:asciiname":"Togago-ri",
    "gn:country_code":"KR",
    "gn:dem":164,
    "gn:feature_class":"P",
    "gn:feature_code":"PPL",
    "gn:name":"Togag\u014f-ri",
    "gn:population":0,
    "gn:timezone":"Asia/Seoul",
    "iso:country":"KR",
    "name:und_x_variant":[
        "\ub3c4\uac00\uac70\ub9ac",
        "Togag\u014f-ri"
    ],
    "wof:name":"Togago-ri",
    "wof:placetype":"locality"
},
  "geometry": {"coordinates":[129.01249999999999,36.5549],"type":"Point"}
}