{
  "type": "Feature",
  "properties": {
    "gn:admin1_code":"17.0",
    "gn:asciiname":"Sangch'on",
    "gn:country_code":"KR",
    "gn:dem":8,
    "gn:feature_class":"P",
    "gn:feature_code":"PPL",
    "gn:name":"Sangch\u2019on",
    "gn:population":0,
    "gn:timezone":"Asia/Seoul",
    "iso:country":"KR",
    "name:und_x_variant":[
        "Sangch\u2019on-ni",
        "Sangch\u2019on"
    ],
    "wof:name":"Sangch'on",
    "wof:placetype":"locality"
},
  "geometry": {"coordinates":[126.84999999999999,36.08333],"type":"Point"}
}