{
  "type": "Feature",
  "properties": {
    "gn:admin1_code":"14.0",
    "gn:asciiname":"Yeokjeon",
    "gn:country_code":"KR",
    "gn:dem":96,
    "gn:feature_class":"P",
    "gn:feature_code":"PPL",
    "gn:name":"Yeokjeon",
    "gn:population":0,
    "gn:timezone":"Asia/Seoul",
    "iso:country":"KR",
    "name:kor_x_preferred":[
        "\uc5ed\uc804"
    ],
    "wof:name":"Yeokjeon",
    "wof:placetype":"locality"
},
  "geometry": {"coordinates":[128.39491000000001,36.63693],"type":"Point"}
}