{
  "type": "Feature",
  "properties": {
    "gn:admin1_code":"11.0",
    "gn:asciiname":"Kongnung-dong",
    "gn:country_code":"KR",
    "gn:dem":32,
    "gn:feature_class":"P",
    "gn:feature_code":"PPL",
    "gn:name":"Kongn\u016dng-dong",
    "gn:population":0,
    "gn:timezone":"Asia/Seoul",
    "iso:country":"KR",
    "name:und_x_variant":[
        "\uacf5\ub989\ub3d9",
        "Kongn\u016dng-dong"
    ],
    "wof:name":"Kongnung-dong",
    "wof:placetype":"locality"
},
  "geometry": {"coordinates":[127.07640000000001,37.6221],"type":"Point"}
}