{
  "type": "Feature",
  "properties": {
    "gn:admin1_code":"6.0",
    "gn:asciiname":"Hwail-li",
    "gn:country_code":"KR",
    "gn:dem":73,
    "gn:feature_class":"P",
    "gn:feature_code":"PPL",
    "gn:name":"Hwail-li",
    "gn:population":0,
    "gn:timezone":"Asia/Seoul",
    "iso:country":"KR",
    "name:kor_x_preferred":[
        "\ud654\uc77c\ub9ac"
    ],
    "wof:name":"Hwail-li",
    "wof:placetype":"locality"
},
  "geometry": {"coordinates":[128.57361,38.10139],"type":"Point"}
}