{
  "type": "Feature",
  "properties": {
    "gn:admin1_code":"20.0",
    "gn:asciiname":"Geulbang",
    "gn:country_code":"KR",
    "gn:dem":49,
    "gn:feature_class":"P",
    "gn:feature_code":"PPL",
    "gn:name":"Geulbang",
    "gn:population":0,
    "gn:timezone":"Asia/Seoul",
    "iso:country":"KR",
    "name:und_x_variant":[
        "\uae00\ubc29",
        "K\u016dlbang",
        "Geulbang"
    ],
    "wof:name":"Geulbang",
    "wof:placetype":"locality"
},
  "geometry": {"coordinates":[128.36547999999999,35.56087],"type":"Point"}
}