{
  "type": "Feature",
  "properties": {
    "gn:admin1_code":"16.0",
    "gn:asciiname":"Hwangchi",
    "gn:country_code":"KR",
    "gn:dem":63,
    "gn:feature_class":"P",
    "gn:feature_code":"PPL",
    "gn:name":"Hwangchi",
    "gn:population":0,
    "gn:timezone":"Asia/Seoul",
    "iso:country":"KR",
    "name:kor_x_preferred":[
        "\ud669\uce58"
    ],
    "name:und_x_variant":[
        "Yongam",
        "Hwangjae",
        "Hwangchi"
    ],
    "wof:name":"Hwangchi",
    "wof:placetype":"locality"
},
  "geometry": {"coordinates":[126.77168,34.91586],"type":"Point"}
}