{
  "type": "Feature",
  "properties": {
    "gn:admin1_code":"14.0",
    "gn:asciiname":"Songgok",
    "gn:country_code":"KR",
    "gn:dem":43,
    "gn:feature_class":"P",
    "gn:feature_code":"PPL",
    "gn:name":"Songgok",
    "gn:population":0,
    "gn:timezone":"Asia/Seoul",
    "iso:country":"KR",
    "name:und_x_variant":[
        "Songgong-ni",
        "\uc1a1\uace1",
        "Songgok"
    ],
    "wof:name":"Songgok",
    "wof:placetype":"locality"
},
  "geometry": {"coordinates":[128.38221999999999,35.80392],"type":"Point"}
}