{
  "type": "Feature",
  "properties": {
    "gn:admin1_code":"14.0",
    "gn:asciiname":"Suyangjeong",
    "gn:country_code":"KR",
    "gn:dem":38,
    "gn:feature_class":"P",
    "gn:feature_code":"PPL",
    "gn:name":"Suyangjeong",
    "gn:population":0,
    "gn:timezone":"Asia/Seoul",
    "iso:country":"KR",
    "name:und_x_variant":[
        "\uc218\uc591\uc815",
        "Suyangj\u014fng",
        "Suyangjeong"
    ],
    "wof:name":"Suyangjeong",
    "wof:placetype":"locality"
},
  "geometry": {"coordinates":[128.34683999999999,35.82575],"type":"Point"}
}