{
  "type": "Feature",
  "properties": {
    "iso:country":"KR",
    "qs:name":"\uace0\uc554\uba74",
    "qs:name_adm0":"\ud55c\uad6d",
    "qs:name_adm1":"\uacbd\uc0c1\ub0a8\ub3c4",
    "qs:photos":1,
    "qs:photos_1k":1,
    "qs:photos_9k":1,
    "qs:photos_9r":1,
    "qs:photos_all":1,
    "qs:photos_sr":1,
    "qs:placetype":"LocalAdmin",
    "qs:pop_sr":"0",
    "wd:wordcount":869,
    "wof:name":"\uace0\uc554\uba74",
    "wof:placetype":"localadmin"
},
  "geometry": {"coordinates":[128.43429499999999,35.622698],"type":"Point"}
}