{
  "type": "Feature",
  "properties": {
    "gn:admin1_code":"17.0",
    "gn:asciiname":"Jeogam",
    "gn:country_code":"KR",
    "gn:dem":176,
    "gn:feature_class":"P",
    "gn:feature_code":"PPL",
    "gn:name":"Jeogam",
    "gn:population":0,
    "gn:timezone":"Asia/Seoul",
    "iso:country":"KR",
    "name:kor_x_preferred":[
        "\uc801\uc554"
    ],
    "wof:name":"Jeogam",
    "wof:placetype":"locality"
},
  "geometry": {"coordinates":[126.99156000000001,36.63992],"type":"Point"}
}