{
  "type": "Feature",
  "properties": {
    "gn:country":"KR",
    "gn:fcode":"ADM3",
    "gn:population":0,
    "iso:country":"KR",
    "name:eng_x_preferred":[
        "Sangnam-myeon"
    ],
    "name:kor_x_preferred":[
        "\uc0c1\ub0a8\uba74"
    ],
    "name:kor_x_variant":[
        "Sangnam-my\u014fn"
    ],
    "qs:name":"Sangnam-my\u014fn",
    "qs:photos_9r":0,
    "qs:photos_sr":0,
    "qs:pop_sr":"0",
    "wof:name":"Sangnam-my\u014fn",
    "wof:placetype":"localadmin",
    "wof:population":0
},
  "geometry": {"coordinates":[128.28487999999999,37.88211],"type":"Point"}
}