{
  "type": "Feature",
  "properties": {
    "gn:admin1_code":"5.0",
    "gn:asciiname":"Goksu",
    "gn:country_code":"KR",
    "gn:dem":60,
    "gn:feature_class":"P",
    "gn:feature_code":"PPL",
    "gn:name":"Goksu",
    "gn:population":0,
    "gn:timezone":"Asia/Seoul",
    "iso:country":"KR",
    "name:kor_x_preferred":[
        "\uace1\uc218"
    ],
    "wof:name":"Goksu",
    "wof:placetype":"locality"
},
  "geometry": {"coordinates":[127.32812,36.69514],"type":"Point"}
}