{
  "type": "Feature",
  "properties": {
    "gn:admin1_code":"17.0",
    "gn:asciiname":"Midong-gol",
    "gn:country_code":"KR",
    "gn:dem":69,
    "gn:feature_class":"P",
    "gn:feature_code":"PPL",
    "gn:name":"Midong-gol",
    "gn:population":0,
    "gn:timezone":"Asia/Seoul",
    "iso:country":"KR",
    "name:und_x_variant":[
        "Mi-dong",
        "\ubbf8\ub3d9\uace8",
        "Midong-gol"
    ],
    "wof:name":"Midong-gol",
    "wof:placetype":"locality"
},
  "geometry": {"coordinates":[126.8421,36.55],"type":"Point"}
}