{
  "type": "Feature",
  "properties": {
    "gn:admin1_code":"16.0",
    "gn:asciiname":"Madong",
    "gn:country_code":"KR",
    "gn:dem":90,
    "gn:feature_class":"P",
    "gn:feature_code":"PPL",
    "gn:name":"Madong",
    "gn:population":0,
    "gn:timezone":"Asia/Seoul",
    "iso:country":"KR",
    "name:kor_x_preferred":[
        "\ub9c8\ub3d9"
    ],
    "name:und_x_variant":[
        "Mahwa-ri",
        "Madong-ni",
        "Madong"
    ],
    "wof:name":"Madong",
    "wof:placetype":"locality"
},
  "geometry": {"coordinates":[127.29447999999999,34.82255],"type":"Point"}
}