{
  "type": "Feature",
  "properties": {
    "gn:admin1_code":"6.0",
    "gn:asciiname":"Pangt'o",
    "gn:country_code":"KR",
    "gn:dem":646,
    "gn:feature_class":"P",
    "gn:feature_code":"PPL",
    "gn:name":"Pangt\u2019\u014f",
    "gn:population":0,
    "gn:timezone":"Asia/Seoul",
    "iso:country":"KR",
    "name:und_x_variant":[
        "\ubc29\ud130",
        "Pangt\u2019\u014f"
    ],
    "wof:name":"Pangt'o",
    "wof:placetype":"locality"
},
  "geometry": {"coordinates":[129.0711,37.1054],"type":"Point"}
}