{
  "type": "Feature",
  "properties": {
    "gn:admin1_code":"5.0",
    "gn:asciiname":"Goran",
    "gn:country_code":"KR",
    "gn:dem":274,
    "gn:feature_class":"P",
    "gn:feature_code":"PPL",
    "gn:name":"Goran",
    "gn:population":0,
    "gn:timezone":"Asia/Seoul",
    "iso:country":"KR",
    "name:kor_x_preferred":[
        "\uace0\ub780"
    ],
    "wof:name":"Goran",
    "wof:placetype":"locality"
},
  "geometry": {"coordinates":[127.70941999999999,36.70662],"type":"Point"}
}