{
  "type": "Feature",
  "properties": {
    "gn:admin1_code":"17.0",
    "gn:asciiname":"Hang-dong",
    "gn:country_code":"KR",
    "gn:dem":35,
    "gn:feature_class":"P",
    "gn:feature_code":"PPL",
    "gn:name":"Hang-dong",
    "gn:population":0,
    "gn:timezone":"Asia/Seoul",
    "iso:country":"KR",
    "name:kor_x_preferred":[
        "\ud56d\ub3d9"
    ],
    "name:msa_x_preferred":[
        "Hang-dong"
    ],
    "name:sco_x_preferred":[
        "Hang-dong"
    ],
    "name:vie_x_preferred":[
        "Hang-dong"
    ],
    "wof:name":"Hang-dong",
    "wof:placetype":"locality"
},
  "geometry": {"coordinates":[126.33750000000001,36.7775],"type":"Point"}
}