{
  "type": "Feature",
  "properties": {
    "gn:admin1_code":"20.0",
    "gn:asciiname":"Geoje",
    "gn:country_code":"KR",
    "gn:dem":11,
    "gn:feature_class":"P",
    "gn:feature_code":"PPL",
    "gn:name":"Geoje",
    "gn:population":0,
    "gn:timezone":"Asia/Seoul",
    "iso:country":"KR",
    "name:ara_x_preferred":[
        "\u062c\u064a\u0648\u062c\u064a"
    ],
    "name:ces_x_preferred":[
        "Kod\u017ee"
    ],
    "name:deu_x_preferred":[
        "Geoje"
    ],
    "name:epo_x_preferred":[
        "Ko\u011de"
    ],
    "name:fas_x_preferred":[
        "\u06af\u0626\u0648\u062c\u0647"
    ],
    "name:fra_x_preferred":[
        "Geoje"
    ],
    "name:hun_x_preferred":[
        "Kodzse"
    ],
    "name:ile_x_preferred":[
        "Geoje"
    ],
    "name:ind_x_preferred":[
        "Geoje"
    ],
    "name:ita_x_preferred":[
        "Geoje"
    ],
    "name:jav_x_preferred":[
        "Geoje"
    ],
    "name:jpn_x_preferred":[
        "\u5de8\u6e08\u5e02"
    ],
    "name:kor_x_preferred":[
        "\uac70\uc81c\uc2dc"
    ],
    "name:lmo_x_preferred":[
        "Geoje"
    ],
    "name:nld_x_preferred":[
        "Geoje"
    ],
    "name:nor_x_preferred":[
        "Geoje"
    ],
    "name:pol_x_preferred":[
        "Geoje"
    ],
    "name:rus_x_preferred":[
        "\u041a\u043e\u0434\u0436\u0435"
    ],
    "name:spa_x_preferred":[
        "Geoje"
    ],
    "name:swe_x_preferred":[
        "Geoje"
    ],
    "name:szl_x_preferred":[
        "Geoje"
    ],
    "name:tgl_x_preferred":[
        "Geoje"
    ],
    "name:tur_x_preferred":[
        "Geoje"
    ],
    "name:urd_x_preferred":[
        "\u06af\u06cc\u0648\u062c\u06d2"
    ],
    "name:vie_x_preferred":[
        "Geoje"
    ],
    "name:war_x_preferred":[
        "Geoje"
    ],
    "name:zho_x_preferred":[
        "\u5de8\u6fdf\u5e02"
    ],
    "wof:name":"Geoje",
    "wof:placetype":"locality"
},
  "geometry": {"coordinates":[128.70556000000002,34.81379],"type":"Point"}
}