{
  "type": "Feature",
  "properties": {
    "gn:admin1_code":"6.0",
    "gn:asciiname":"Pukkuji",
    "gn:country_code":"KR",
    "gn:dem":119,
    "gn:feature_class":"P",
    "gn:feature_code":"PPL",
    "gn:name":"Pukkuji",
    "gn:population":0,
    "gn:timezone":"Asia/Seoul",
    "iso:country":"KR",
    "name:kor_x_preferred":[
        "\ubd93\uad6c\uc9c0"
    ],
    "wof:name":"Pukkuji",
    "wof:placetype":"locality"
},
  "geometry": {"coordinates":[127.66119999999999,37.681],"type":"Point"}
}