{
  "type": "Feature",
  "properties": {
    "gn:admin1_code":"17.0",
    "gn:asciiname":"Win-mal",
    "gn:country_code":"KR",
    "gn:dem":23,
    "gn:feature_class":"P",
    "gn:feature_code":"PPL",
    "gn:name":"Win-mal",
    "gn:population":0,
    "gn:timezone":"Asia/Seoul",
    "iso:country":"KR",
    "name:und_x_variant":[
        "Ch\u014fnggong-ni",
        "Wimal",
        "\uc717\ub9d0",
        "Win-mal"
    ],
    "wof:name":"Win-mal",
    "wof:placetype":"locality"
},
  "geometry": {"coordinates":[126.50790000000001,36.8985],"type":"Point"}
}