{
  "type": "Feature",
  "properties": {
    "gn:admin1_code":"17.0",
    "gn:asciiname":"Pyojeong-ri",
    "gn:country_code":"KR",
    "gn:dem":50,
    "gn:feature_class":"P",
    "gn:feature_code":"PPL",
    "gn:name":"Pyojeong-ri",
    "gn:population":0,
    "gn:timezone":"Asia/Seoul",
    "iso:country":"KR",
    "name:kor_x_preferred":[
        "\ud45c\uc815\ub9ac"
    ],
    "name:und_x_variant":[
        "P\u2019yoj\u014fng-ni"
    ],
    "wof:name":"Pyojeong-ri",
    "wof:placetype":"locality"
},
  "geometry": {"coordinates":[127.1932,36.22549],"type":"Point"}
}