{
  "type": "Feature",
  "properties": {
    "gn:admin1_code":"17.0",
    "gn:asciiname":"Oyangsil",
    "gn:country_code":"KR",
    "gn:dem":170,
    "gn:feature_class":"P",
    "gn:feature_code":"PPL",
    "gn:name":"Oyangsil",
    "gn:population":0,
    "gn:timezone":"Asia/Seoul",
    "iso:country":"KR",
    "name:und_x_variant":[
        "\uc624\uc591\uc2e4",
        "Oyangsil"
    ],
    "wof:name":"Oyangsil",
    "wof:placetype":"locality"
},
  "geometry": {"coordinates":[127.29773,36.18511],"type":"Point"}
}