{
  "type": "Feature",
  "properties": {
    "gn:admin1_code":"17.0",
    "gn:asciiname":"Nuk-tong",
    "gn:country_code":"KR",
    "gn:dem":81,
    "gn:feature_class":"P",
    "gn:feature_code":"PPL",
    "gn:name":"N\u016dk-tong",
    "gn:population":0,
    "gn:timezone":"Asia/Seoul",
    "iso:country":"KR",
    "name:eng_x_preferred":[
        "Nuk"
    ],
    "name:eng_x_variant":[
        "Nuk-tong"
    ],
    "wof:name":"Nuk",
    "wof:placetype":"locality"
},
  "geometry": {"coordinates":[126.76667,36.25],"type":"Point"}
}