{
  "type": "Feature",
  "properties": {
    "gn:admin1_code":"16.0",
    "gn:asciiname":"Samch'ung-ni",
    "gn:country_code":"KR",
    "gn:dem":23,
    "gn:feature_class":"P",
    "gn:feature_code":"PPL",
    "gn:name":"Samch\u2019ung-ni",
    "gn:population":0,
    "gn:timezone":"Asia/Seoul",
    "iso:country":"KR",
    "wof:name":"Samch'ung-ni",
    "wof:placetype":"locality"
},
  "geometry": {"coordinates":[126.61028,35.11306],"type":"Point"}
}