{
  "type": "Feature",
  "properties": {
    "gn:admin1_code":"14.0",
    "gn:asciiname":"Teotgol",
    "gn:country_code":"KR",
    "gn:dem":125,
    "gn:feature_class":"P",
    "gn:feature_code":"PPL",
    "gn:name":"Teotgol",
    "gn:population":0,
    "gn:timezone":"Asia/Seoul",
    "iso:country":"KR",
    "name:kor_x_preferred":[
        "\ud143\uace8"
    ],
    "wof:name":"Teotgol",
    "wof:placetype":"locality"
},
  "geometry": {"coordinates":[128.56663999999998,36.70879],"type":"Point"}
}