{
  "type": "Feature",
  "properties": {
    "gn:admin1_code":"14.0",
    "gn:asciiname":"Chirye",
    "gn:country_code":"KR",
    "gn:dem":140,
    "gn:feature_class":"P",
    "gn:feature_code":"PPL",
    "gn:name":"Chirye",
    "gn:population":0,
    "gn:timezone":"Asia/Seoul",
    "iso:country":"KR",
    "name:und_x_variant":[
        "Chirei",
        "Chire",
        "\uc9c0\ub840",
        "Chirye"
    ],
    "wof:name":"Chirye",
    "wof:placetype":"locality"
},
  "geometry": {"coordinates":[128.02741,35.98631],"type":"Point"}
}