{
  "type": "Feature",
  "properties": {
    "gn:admin1_code":"6.0",
    "gn:asciiname":"Darakteo",
    "gn:country_code":"KR",
    "gn:dem":210,
    "gn:feature_class":"P",
    "gn:feature_code":"PPL",
    "gn:name":"Darakteo",
    "gn:population":0,
    "gn:timezone":"Asia/Seoul",
    "iso:country":"KR",
    "name:und_x_variant":[
        "\ub2e4\ub77d\ud130",
        "Tarakt\u2019\u014f",
        "Darakteo"
    ],
    "wof:name":"Darakteo",
    "wof:placetype":"locality"
},
  "geometry": {"coordinates":[127.551,37.8171],"type":"Point"}
}