{
  "type": "Feature",
  "properties": {
    "gn:admin1_code":"3.0",
    "gn:asciiname":"Kong-dong",
    "gn:country_code":"KR",
    "gn:dem":51,
    "gn:feature_class":"P",
    "gn:feature_code":"PPL",
    "gn:name":"Kong-dong",
    "gn:population":0,
    "gn:timezone":"Asia/Seoul",
    "iso:country":"KR",
    "name:und_x_variant":[
        "Kong-gol",
        "\uacf5\ub3d9",
        "Kong-dong"
    ],
    "wof:name":"Kong-dong",
    "wof:placetype":"locality"
},
  "geometry": {"coordinates":[127.01918999999999,35.61709000000001],"type":"Point"}
}