{
  "type": "Feature",
  "properties": {
    "gn:admin1_code":"17.0",
    "gn:asciiname":"P'yonggu",
    "gn:country_code":"KR",
    "gn:dem":98,
    "gn:feature_class":"P",
    "gn:feature_code":"PPL",
    "gn:name":"P\u2019y\u014fnggu",
    "gn:population":0,
    "gn:timezone":"Asia/Seoul",
    "iso:country":"KR",
    "name:und_x_variant":[
        "\ud3c9\uad6c",
        "P\u2019y\u014fnggu"
    ],
    "wof:name":"P'yonggu",
    "wof:placetype":"locality"
},
  "geometry": {"coordinates":[126.7619,36.4052],"type":"Point"}
}