{
  "type": "Feature",
  "properties": {
    "gn:admin1_code":"17.0",
    "gn:asciiname":"Araeppaenamu-gol",
    "gn:country_code":"KR",
    "gn:dem":127,
    "gn:feature_class":"P",
    "gn:feature_code":"PPL",
    "gn:name":"Araeppaenamu-gol",
    "gn:population":0,
    "gn:timezone":"Asia/Seoul",
    "iso:country":"KR",
    "name:und_x_variant":[
        "\uc544\ub7ab\ubc30\ub098\ubb34\uace8",
        "Araeppaenamu-gol"
    ],
    "wof:name":"Araeppaenamu-gol",
    "wof:placetype":"locality"
},
  "geometry": {"coordinates":[126.7833,36.4812],"type":"Point"}
}