{
  "type": "Feature",
  "properties": {
    "gn:admin1_code":"17.0",
    "gn:asciiname":"Sugok",
    "gn:country_code":"KR",
    "gn:dem":41,
    "gn:feature_class":"P",
    "gn:feature_code":"PPL",
    "gn:name":"Sugok",
    "gn:population":0,
    "gn:timezone":"Asia/Seoul",
    "iso:country":"KR",
    "name:und_x_variant":[
        "\uc218\uace1",
        "Sugok"
    ],
    "wof:name":"Sugok",
    "wof:placetype":"locality"
},
  "geometry": {"coordinates":[126.5915,36.5047],"type":"Point"}
}