{
  "type": "Feature",
  "properties": {
    "gn:admin1_code":"13.0",
    "gn:asciiname":"Seoksuil-dong",
    "gn:country_code":"KR",
    "gn:dem":205,
    "gn:feature_class":"P",
    "gn:feature_code":"PPL",
    "gn:name":"Seoksuil-dong",
    "gn:population":0,
    "gn:timezone":"Asia/Seoul",
    "iso:country":"KR",
    "name:und_x_variant":[
        "\uc11d\uc2181\ub3d9",
        "Seoksuil-dong",
        "S\u014fksuil-tong"
    ],
    "wof:name":"Seoksuil-dong",
    "wof:placetype":"locality"
},
  "geometry": {"coordinates":[126.92528,37.43167],"type":"Point"}
}