{
  "type": "Feature",
  "properties": {
    "gn:admin1_code":"17.0",
    "gn:asciiname":"Hwang-gol",
    "gn:country_code":"KR",
    "gn:dem":12,
    "gn:feature_class":"P",
    "gn:feature_code":"PPL",
    "gn:name":"Hwang-gol",
    "gn:population":0,
    "gn:timezone":"Asia/Seoul",
    "iso:country":"KR",
    "name:und_x_variant":[
        "Hwangkol",
        "Hwanggol-li",
        "Hwanggong-ni",
        "\ud669\uace8",
        "Hwang-gol"
    ],
    "wof:name":"Hwang-gol",
    "wof:placetype":"locality"
},
  "geometry": {"coordinates":[126.20359999999999,36.8761],"type":"Point"}
}