{
  "type": "Feature",
  "properties": {
    "gn:admin1_code":"13.0",
    "gn:asciiname":"Yamang-ni",
    "gn:country_code":"KR",
    "gn:dem":16,
    "gn:feature_class":"P",
    "gn:feature_code":"PPL",
    "gn:name":"Yamang-ni",
    "gn:population":0,
    "gn:timezone":"Asia/Seoul",
    "iso:country":"KR",
    "name:und_x_variant":[
        "\uc57c\ub9c9\ub9ac",
        "Yamak-ri",
        "Yamang-ni"
    ],
    "wof:name":"Yamang-ni",
    "wof:placetype":"locality"
},
  "geometry": {"coordinates":[127.06083,37.12222],"type":"Point"}
}