{
  "type": "Feature",
  "properties": {
    "gn:admin1_code":"3.0",
    "gn:asciiname":"Sangajung",
    "gn:country_code":"KR",
    "gn:dem":104,
    "gn:feature_class":"P",
    "gn:feature_code":"PPL",
    "gn:name":"Sangajung",
    "gn:population":0,
    "gn:timezone":"Asia/Seoul",
    "iso:country":"KR",
    "name:und_x_variant":[
        "\uc0c1\uc544\uc911",
        "Sangajung"
    ],
    "wof:name":"Sangajung",
    "wof:placetype":"locality"
},
  "geometry": {"coordinates":[127.19873,35.82122000000001],"type":"Point"}
}