{
  "type": "Feature",
  "properties": {
    "gn:admin1_code":"13.0",
    "gn:admin2_code":"P'aju-si",
    "gn:asciiname":"Hyeonam",
    "gn:country_code":"KR",
    "gn:dem":32,
    "gn:feature_class":"P",
    "gn:feature_code":"PPL",
    "gn:name":"Hyeonam",
    "gn:population":0,
    "gn:timezone":"Asia/Seoul",
    "iso:country":"KR",
    "name:kor_x_preferred":[
        "\ud604\uc554"
    ],
    "name:und_x_variant":[
        "Hy\u014fnim"
    ],
    "wof:name":"Hyeonam",
    "wof:placetype":"locality"
},
  "geometry": {"coordinates":[126.82075,37.967],"type":"Point"}
}