{
  "type": "Feature",
  "properties": {
    "gn:admin1_code":"5.0",
    "gn:asciiname":"Hwangam",
    "gn:country_code":"KR",
    "gn:dem":329,
    "gn:feature_class":"P",
    "gn:feature_code":"PPL",
    "gn:name":"Hwangam",
    "gn:population":0,
    "gn:timezone":"Asia/Seoul",
    "iso:country":"KR",
    "name:kor_x_preferred":[
        "\ud669\uc554"
    ],
    "wof:name":"Hwangam",
    "wof:placetype":"locality"
},
  "geometry": {"coordinates":[127.68923999999998,36.77209000000001],"type":"Point"}
}