{
  "type": "Feature",
  "properties": {
    "gn:admin1_code":"6.0",
    "gn:asciiname":"Poksiul",
    "gn:country_code":"KR",
    "gn:dem":109,
    "gn:feature_class":"P",
    "gn:feature_code":"PPL",
    "gn:name":"Poksi\u016dl",
    "gn:population":0,
    "gn:timezone":"Asia/Seoul",
    "iso:country":"KR",
    "name:kor_x_preferred":[
        "\ubcf5\uc2dc\uc744"
    ],
    "name:kor_x_variant":[
        "Poksi\u016dl"
    ],
    "wof:name":"Poksiul",
    "wof:placetype":"locality"
},
  "geometry": {"coordinates":[127.8693,37.3307],"type":"Point"}
}