{
  "type": "Feature",
  "properties": {
    "gn:admin1_code":"17.0",
    "gn:asciiname":"Oemimal",
    "gn:country_code":"KR",
    "gn:dem":41,
    "gn:feature_class":"P",
    "gn:feature_code":"PPL",
    "gn:name":"Oemimal",
    "gn:population":0,
    "gn:timezone":"Asia/Seoul",
    "iso:country":"KR",
    "name:kor_x_preferred":[
        "\uc678\ubbf8\ub9d0"
    ],
    "wof:name":"Oemimal",
    "wof:placetype":"locality"
},
  "geometry": {"coordinates":[126.97512999999999,36.76203],"type":"Point"}
}