{
  "type": "Feature",
  "properties": {
    "gn:admin1_code":"20.0",
    "gn:asciiname":"Tosan",
    "gn:country_code":"KR",
    "gn:dem":19,
    "gn:feature_class":"P",
    "gn:feature_code":"PPL",
    "gn:name":"Tosan",
    "gn:population":0,
    "gn:timezone":"Asia/Seoul",
    "iso:country":"KR",
    "name:und_x_variant":[
        "\ub3c4\uc0b0",
        "Tosan"
    ],
    "wof:name":"Tosan",
    "wof:placetype":"locality"
},
  "geometry": {"coordinates":[128.42683,35.10852],"type":"Point"}
}