{
  "type": "Feature",
  "properties": {
    "gn:admin1_code":"6.0",
    "gn:asciiname":"Kach'irak-kol",
    "gn:country_code":"KR",
    "gn:dem":181,
    "gn:feature_class":"P",
    "gn:feature_code":"PPL",
    "gn:name":"Kach\u2019irak-kol",
    "gn:population":0,
    "gn:timezone":"Asia/Seoul",
    "iso:country":"KR",
    "name:kor_x_preferred":[
        "\uac00\uce58\ub77d\uace8"
    ],
    "name:kor_x_variant":[
        "Kach\u2019irak-kol"
    ],
    "wof:name":"Kach'irak-kol",
    "wof:placetype":"locality"
},
  "geometry": {"coordinates":[127.8886,37.185],"type":"Point"}
}