{
  "type": "Feature",
  "properties": {
    "gn:admin1_code":"20.0",
    "gn:asciiname":"Ch'awol",
    "gn:country_code":"KR",
    "gn:dem":29,
    "gn:feature_class":"P",
    "gn:feature_code":"PPL",
    "gn:name":"Ch\u2019aw\u014fl",
    "gn:population":0,
    "gn:timezone":"Asia/Seoul",
    "iso:country":"KR",
    "name:und_x_variant":[
        "Ch\u2019aw\u014fl-li",
        "Ch\u2019aw\u014fl"
    ],
    "wof:name":"Ch'awol",
    "wof:placetype":"locality"
},
  "geometry": {"coordinates":[128.66721999999999,35.38444000000001],"type":"Point"}
}