{
  "type": "Feature",
  "properties": {
    "gn:admin1_code":"0.0",
    "gn:asciiname":"Changdong",
    "gn:country_code":"KR",
    "gn:dem":257,
    "gn:feature_class":"P",
    "gn:feature_code":"PPL",
    "gn:name":"Changdong",
    "gn:population":0,
    "gn:timezone":"Asia/Seoul",
    "iso:country":"KR",
    "name:kor_x_preferred":[
        "\ucc3d\ub4f1"
    ],
    "name:und_x_variant":[
        "S\u014dt\u014d",
        "Changdong",
        "Ch\u2019angd\u016dng",
        "Changdeung"
    ],
    "wof:name":"Changdong",
    "wof:placetype":"locality"
},
  "geometry": {"coordinates":[126.98333,35.45],"type":"Point"}
}