{
  "type": "Feature",
  "properties": {
    "gn:admin1_code":"17.0",
    "gn:asciiname":"Yangch'onjae",
    "gn:country_code":"KR",
    "gn:dem":38,
    "gn:feature_class":"P",
    "gn:feature_code":"PPL",
    "gn:name":"Yangch\u2019\u014fnjae",
    "gn:population":0,
    "gn:timezone":"Asia/Seoul",
    "iso:country":"KR",
    "name:und_x_variant":[
        "\uc591\ucc9c\uc7ac",
        "Yangch\u2019\u014fnjae"
    ],
    "wof:name":"Yangch'onjae",
    "wof:placetype":"locality"
},
  "geometry": {"coordinates":[127.1508,36.4726],"type":"Point"}
}