{
  "type": "Feature",
  "properties": {
    "gn:admin1_code":"13.0",
    "gn:asciiname":"Mosan",
    "gn:country_code":"KR",
    "gn:dem":23,
    "gn:feature_class":"P",
    "gn:feature_code":"PPL",
    "gn:name":"Mosan",
    "gn:population":0,
    "gn:timezone":"Asia/Seoul",
    "iso:country":"KR",
    "name:kor_x_preferred":[
        "\ubaa8\uc0b0"
    ],
    "wof:name":"Mosan",
    "wof:placetype":"locality"
},
  "geometry": {"coordinates":[126.65223,37.64961],"type":"Point"}
}