{
  "type": "Feature",
  "properties": {
    "gn:admin1_code":"5.0",
    "gn:asciiname":"Bokjadong",
    "gn:country_code":"KR",
    "gn:dem":75,
    "gn:feature_class":"P",
    "gn:feature_code":"PPL",
    "gn:name":"Bokjadong",
    "gn:population":0,
    "gn:timezone":"Asia/Seoul",
    "iso:country":"KR",
    "name:kor_x_preferred":[
        "\ubcf5\uc790\ub3d9"
    ],
    "name:und_x_variant":[
        "Pokcha-dong"
    ],
    "wof:name":"Bokjadong",
    "wof:placetype":"locality"
},
  "geometry": {"coordinates":[127.64346999999999,37.14256],"type":"Point"}
}