{
  "type": "Feature",
  "properties": {
    "gn:admin1_code":"17.0",
    "gn:asciiname":"Odong-ni",
    "gn:country_code":"KR",
    "gn:dem":130,
    "gn:feature_class":"P",
    "gn:feature_code":"PPL",
    "gn:name":"Odong-ni",
    "gn:population":0,
    "gn:timezone":"Asia/Seoul",
    "iso:country":"KR",
    "wof:name":"Odong-ni",
    "wof:placetype":"locality"
},
  "geometry": {"coordinates":[126.66667,36.48333],"type":"Point"}
}