{
  "type": "Feature",
  "properties": {
    "gn:admin1_code":"16.0",
    "gn:asciiname":"Masal-li",
    "gn:cc2":"KR",
    "gn:country_code":"KR",
    "gn:dem":25,
    "gn:feature_class":"P",
    "gn:feature_code":"PPL",
    "gn:name":"Masal-li",
    "gn:population":0,
    "gn:timezone":"Asia/Seoul",
    "iso:country":"KR",
    "name:und_x_variant":[
        "Masan-ni",
        "Masan",
        "Masal-li"
    ],
    "wof:name":"Masal-li",
    "wof:placetype":"locality"
},
  "geometry": {"coordinates":[126.35611000000002,35.07361],"type":"Point"}
}