{
  "type": "Feature",
  "properties": {
    "gn:admin1_code":"14.0",
    "gn:asciiname":"Dojanggol",
    "gn:country_code":"KR",
    "gn:dem":73,
    "gn:feature_class":"P",
    "gn:feature_code":"PPL",
    "gn:name":"Dojanggol",
    "gn:population":0,
    "gn:timezone":"Asia/Seoul",
    "iso:country":"KR",
    "name:kor_x_preferred":[
        "\ub3c4\uc7a5\uace8"
    ],
    "wof:name":"Dojanggol",
    "wof:placetype":"locality"
},
  "geometry": {"coordinates":[128.51191,35.95627],"type":"Point"}
}