{
  "type": "Feature",
  "properties": {
    "gn:admin1_code":"14.0",
    "gn:asciiname":"Chukchon",
    "gn:country_code":"KR",
    "gn:dem":200,
    "gn:feature_class":"P",
    "gn:feature_code":"PPL",
    "gn:name":"Chukch\u014fn",
    "gn:population":0,
    "gn:timezone":"Asia/Seoul",
    "iso:country":"KR",
    "name:und_x_variant":[
        "\uc8fd\uc804",
        "Chukch\u014fn"
    ],
    "wof:name":"Chukchon",
    "wof:placetype":"locality"
},
  "geometry": {"coordinates":[129.34272000000001,36.80812],"type":"Point"}
}