{
  "type": "Feature",
  "properties": {
    "gn:admin1_code":"16.0",
    "gn:asciiname":"Chikuren-ri",
    "gn:country_code":"KR",
    "gn:dem":14,
    "gn:feature_class":"P",
    "gn:feature_code":"PPL",
    "gn:name":"Chikuren-ri",
    "gn:population":0,
    "gn:timezone":"Asia/Seoul",
    "iso:country":"KR",
    "name:und_x_variant":[
        "Chugy\u014fn-ni",
        "Chungny\u014fn-ni",
        "Chungny\u014fl-li"
    ],
    "wof:name":"Chikuren-ri",
    "wof:placetype":"locality"
},
  "geometry": {"coordinates":[125.97833,34.67722],"type":"Point"}
}