{
  "type": "Feature",
  "properties": {
    "gn:admin1_code":"20.0",
    "gn:asciiname":"Namgye-dong",
    "gn:country_code":"KR",
    "gn:dem":478,
    "gn:feature_class":"P",
    "gn:feature_code":"PPL",
    "gn:name":"Namgye-dong",
    "gn:population":0,
    "gn:timezone":"Asia/Seoul",
    "iso:country":"KR",
    "name:und_x_variant":[
        "\ub0a8\uacc4\ub3d9",
        "Namgye-dong"
    ],
    "wof:name":"Namgye-dong",
    "wof:placetype":"locality"
},
  "geometry": {"coordinates":[128.06946000000002,35.61992],"type":"Point"}
}