{
  "type": "Feature",
  "properties": {
    "gn:admin1_code":"13.0",
    "gn:asciiname":"Duribong",
    "gn:country_code":"KR",
    "gn:dem":66,
    "gn:feature_class":"P",
    "gn:feature_code":"PPL",
    "gn:name":"Duribong",
    "gn:population":0,
    "gn:timezone":"Asia/Seoul",
    "iso:country":"KR",
    "name:kor_x_preferred":[
        "\ub450\ub9ac\ubd09"
    ],
    "name:und_x_variant":[
        "Turibong"
    ],
    "wof:name":"Duribong",
    "wof:placetype":"locality"
},
  "geometry": {"coordinates":[127.57335999999999,37.23037],"type":"Point"}
}