{
  "type": "Feature",
  "properties": {
    "gn:admin1_code":"17.0",
    "gn:asciiname":"Jungmal",
    "gn:country_code":"KR",
    "gn:dem":47,
    "gn:feature_class":"P",
    "gn:feature_code":"PPL",
    "gn:name":"Jungmal",
    "gn:population":0,
    "gn:timezone":"Asia/Seoul",
    "iso:country":"KR",
    "name:und_x_variant":[
        "\uc911\ub9d0",
        "Chung-mal",
        "Jungmal"
    ],
    "wof:name":"Jungmal",
    "wof:placetype":"locality"
},
  "geometry": {"coordinates":[127.1524,36.4166],"type":"Point"}
}