{
  "type": "Feature",
  "properties": {
    "gn:admin1_code":"5.0",
    "gn:asciiname":"Tesan",
    "gn:country_code":"KR",
    "gn:dem":69,
    "gn:feature_class":"P",
    "gn:feature_code":"PPL",
    "gn:name":"Tesan",
    "gn:population":0,
    "gn:timezone":"Asia/Seoul",
    "iso:country":"KR",
    "name:kor_x_preferred":[
        "\ud14c\uc0b0"
    ],
    "wof:name":"Tesan",
    "wof:placetype":"locality"
},
  "geometry": {"coordinates":[127.51085,36.71016],"type":"Point"}
}