{
  "type": "Feature",
  "properties": {
    "gn:admin1_code":"13.0",
    "gn:asciiname":"Wondanggeo",
    "gn:country_code":"KR",
    "gn:dem":8,
    "gn:feature_class":"P",
    "gn:feature_code":"PPL",
    "gn:name":"Wondanggeo",
    "gn:population":0,
    "gn:timezone":"Asia/Seoul",
    "iso:country":"KR",
    "name:und_x_variant":[
        "\uc6d0\ub2f9\uac70",
        "W\u014fndangg\u014f",
        "Wondanggeo"
    ],
    "wof:name":"Wondanggeo",
    "wof:placetype":"locality"
},
  "geometry": {"coordinates":[126.98099999999999,36.9933],"type":"Point"}
}