{
  "type": "Feature",
  "properties": {
    "gn:admin1_code":"20.0",
    "gn:asciiname":"Ssak-kol",
    "gn:country_code":"KR",
    "gn:dem":35,
    "gn:feature_class":"P",
    "gn:feature_code":"PPL",
    "gn:name":"Ssak-kol",
    "gn:population":0,
    "gn:timezone":"Asia/Seoul",
    "iso:country":"KR",
    "name:und_x_variant":[
        "\uc2f9\uace8",
        "Ssak-kol"
    ],
    "wof:name":"Ssak-kol",
    "wof:placetype":"locality"
},
  "geometry": {"coordinates":[128.27603999999999,35.17675],"type":"Point"}
}