{
  "type": "Feature",
  "properties": {
    "gn:admin1_code":"13.0",
    "gn:asciiname":"Jeongmun-ri",
    "gn:country_code":"KR",
    "gn:dem":19,
    "gn:feature_class":"P",
    "gn:feature_code":"PPL",
    "gn:name":"Jeongmun-ri",
    "gn:population":0,
    "gn:timezone":"Asia/Seoul",
    "iso:country":"KR",
    "name:und_x_variant":[
        "\uc815\ubb38\ub9ac",
        "Jeongmun-ri",
        "Ch\u014fngmul-li"
    ],
    "wof:name":"Jeongmun-ri",
    "wof:placetype":"locality"
},
  "geometry": {"coordinates":[126.98917,37.0925],"type":"Point"}
}