{
  "type": "Feature",
  "properties": {
    "gn:admin1_code":"20.0",
    "gn:asciiname":"Tokko",
    "gn:country_code":"KR",
    "gn:dem":334,
    "gn:feature_class":"P",
    "gn:feature_code":"PPL",
    "gn:name":"T\u014fkk\u014f",
    "gn:population":0,
    "gn:timezone":"Asia/Seoul",
    "iso:country":"KR",
    "name:und_x_variant":[
        "\ub355\uac70",
        "T\u014fkk\u014f"
    ],
    "wof:name":"Tokko",
    "wof:placetype":"locality"
},
  "geometry": {"coordinates":[127.81735999999999,35.74399000000001],"type":"Point"}
}