{
  "type": "Feature",
  "properties": {
    "gn:admin1_code":"14.0",
    "gn:asciiname":"Songnim",
    "gn:country_code":"KR",
    "gn:dem":65,
    "gn:feature_class":"P",
    "gn:feature_code":"PPL",
    "gn:name":"Songnim",
    "gn:population":0,
    "gn:timezone":"Asia/Seoul",
    "iso:country":"KR",
    "name:und_x_variant":[
        "\uc1a1\ub9bc",
        "Songnim"
    ],
    "wof:name":"Songnim",
    "wof:placetype":"locality"
},
  "geometry": {"coordinates":[128.35678999999999,35.82263],"type":"Point"}
}