{
  "type": "Feature",
  "properties": {
    "gn:admin1_code":"13.0",
    "gn:asciiname":"Neungan",
    "gn:country_code":"KR",
    "gn:dem":117,
    "gn:feature_class":"P",
    "gn:feature_code":"PPL",
    "gn:name":"Neungan",
    "gn:population":0,
    "gn:timezone":"Asia/Seoul",
    "iso:country":"KR",
    "name:und_x_variant":[
        "\ub2a5\uc548",
        "Neungan",
        "N\u016dngan"
    ],
    "wof:name":"Neungan",
    "wof:placetype":"locality"
},
  "geometry": {"coordinates":[126.98888999999998,37.37111],"type":"Point"}
}