{
  "type": "Feature",
  "properties": {
    "gn:admin1_code":"16.0",
    "gn:asciiname":"Shinkyo-ri",
    "gn:country_code":"KR",
    "gn:dem":76,
    "gn:feature_class":"P",
    "gn:feature_code":"PPL",
    "gn:name":"Shinkyo-ri",
    "gn:population":0,
    "gn:timezone":"Asia/Seoul",
    "iso:country":"KR",
    "name:und_x_variant":[
        "Sinh\u016dng",
        "Shink\u014d-ri",
        "Sinh\u016dng-ni"
    ],
    "wof:name":"Shinkyo-ri",
    "wof:placetype":"locality"
},
  "geometry": {"coordinates":[126.80667,35.3775],"type":"Point"}
}