{
  "type": "Feature",
  "properties": {
    "gn:admin1_code":"17.0",
    "gn:asciiname":"Polt'i",
    "gn:country_code":"KR",
    "gn:dem":120,
    "gn:feature_class":"P",
    "gn:feature_code":"PPL",
    "gn:name":"P\u014flt\u2019i",
    "gn:population":0,
    "gn:timezone":"Asia/Seoul",
    "iso:country":"KR",
    "name:und_x_variant":[
        "\ubc8c\ud2f0",
        "P\u014flt\u2019i"
    ],
    "wof:name":"Polt'i",
    "wof:placetype":"locality"
},
  "geometry": {"coordinates":[126.7216,36.489],"type":"Point"}
}