{
  "type": "Feature",
  "properties": {
    "gn:admin1_code":"14.0",
    "gn:asciiname":"Yongjeong",
    "gn:country_code":"KR",
    "gn:dem":99,
    "gn:feature_class":"P",
    "gn:feature_code":"PPL",
    "gn:name":"Yongjeong",
    "gn:population":0,
    "gn:timezone":"Asia/Seoul",
    "iso:country":"KR",
    "name:kor_x_preferred":[
        "\uc6a9\uc815"
    ],
    "wof:name":"Yongjeong",
    "wof:placetype":"locality"
},
  "geometry": {"coordinates":[128.46777,36.63174],"type":"Point"}
}