{
  "type": "Feature",
  "properties": {
    "gn:admin1_code":"6.0",
    "gn:asciiname":"P'yongji-mal",
    "gn:country_code":"KR",
    "gn:dem":88,
    "gn:feature_class":"P",
    "gn:feature_code":"PPL",
    "gn:name":"P\u2019y\u014fngji-mal",
    "gn:population":0,
    "gn:timezone":"Asia/Seoul",
    "iso:country":"KR",
    "name:und_x_variant":[
        "P\u2019y\u014fnji-mal",
        "\ud3c9\uc9c0\ub9d0",
        "P\u2019y\u014fngji-mal"
    ],
    "wof:name":"P'yongji-mal",
    "wof:placetype":"locality"
},
  "geometry": {"coordinates":[129.06950000000001,37.4436],"type":"Point"}
}