{
  "type": "Feature",
  "properties": {
    "gn:admin1_code":"5.0",
    "gn:asciiname":"Chilgeumdong",
    "gn:country_code":"KR",
    "gn:dem":74,
    "gn:feature_class":"P",
    "gn:feature_code":"PPL",
    "gn:name":"Chilgeumdong",
    "gn:population":0,
    "gn:timezone":"Asia/Seoul",
    "iso:country":"KR",
    "name:kor_x_preferred":[
        "\uce60\uae08\ub3d9"
    ],
    "wof:name":"Chilgeumdong",
    "wof:placetype":"locality"
},
  "geometry": {"coordinates":[127.91357000000001,36.98874],"type":"Point"}
}