{
  "type": "Feature",
  "properties": {
    "gn:admin1_code":"14.0",
    "gn:asciiname":"Sang-ni",
    "gn:country_code":"KR",
    "gn:dem":176,
    "gn:feature_class":"P",
    "gn:feature_code":"PPL",
    "gn:name":"Sang-ni",
    "gn:population":0,
    "gn:timezone":"Asia/Seoul",
    "iso:country":"KR",
    "name:und_x_variant":[
        "Sangi\u016dm",
        "Sang-ni",
        "\uc0c1\ub9ac"
    ],
    "wof:name":"Sang-ni",
    "wof:placetype":"locality"
},
  "geometry": {"coordinates":[128.1062,36.2511],"type":"Point"}
}