{
  "type": "Feature",
  "properties": {
    "iso:country":"KR",
    "name:eng_x_preferred":[
        "Jeongja 3(sam)-dong"
    ],
    "name:kor_x_preferred":[
        "\uc815\uc7903\ub3d9"
    ],
    "qs:gn_fcode":"PPL",
    "qs:gn_local":0,
    "qs:gn_namadm1":"13",
    "qs:gn_name":"Jeongja-dong",
    "qs:local_max":599,
    "qs:local_sum":2052,
    "qs:localhoods":9,
    "qs:name":"\uc815\uc7903\ub3d9",
    "qs:name_adm0":"\ud55c\uad6d",
    "qs:name_adm1":"\uacbd\uae30\ub3c4",
    "qs:name_adm2":"\uc218\uc6d0\uc2dc",
    "qs:name_lau":"\uc7a5\uc548\uad6c",
    "qs:name_local":"\uc7a5\uc548\uad6c",
    "qs:photo_max":18,
    "qs:photo_sum":41,
    "qs:placetype":"Suburb",
    "qs:quad_count":6,
    "qs:woe_adm0":23424868,
    "qs:woe_adm1":2345969,
    "qs:woe_adm2":28289297,
    "qs:woe_lau":28997195,
    "qs:woe_local":28997195,
    "qs:woe_ver":"7.10.0",
    "wof:lang":[
        "kor"
    ],
    "wof:name":"Jeongja 3(sam)-dong",
    "wof:placetype":"neighbourhood"
},
  "geometry": {"coordinates":[126.98808699999999,37.280076],"type":"Point"}
}