{
  "type": "Feature",
  "properties": {
    "gn:admin1_code":"17.0",
    "gn:asciiname":"Hap'an-dong",
    "gn:country_code":"KR",
    "gn:dem":61,
    "gn:feature_class":"P",
    "gn:feature_code":"PPL",
    "gn:name":"Hap\u2019an-dong",
    "gn:population":0,
    "gn:timezone":"Asia/Seoul",
    "iso:country":"KR",
    "wof:name":"Hap'an-dong",
    "wof:placetype":"locality"
},
  "geometry": {"coordinates":[126.48333,36.48333],"type":"Point"}
}