{
  "type": "Feature",
  "properties": {
    "gn:admin1_code":"21.0",
    "gn:asciiname":"Bijo",
    "gn:country_code":"KR",
    "gn:dem":188,
    "gn:feature_class":"P",
    "gn:feature_code":"PPL",
    "gn:name":"Bijo",
    "gn:population":0,
    "gn:timezone":"Asia/Seoul",
    "iso:country":"KR",
    "name:kor_x_preferred":[
        "\ube44\uc870"
    ],
    "wof:name":"Bijo",
    "wof:placetype":"locality"
},
  "geometry": {"coordinates":[129.23625000000001,35.64751],"type":"Point"}
}