{
  "type": "Feature",
  "properties": {
    "gn:admin1_code":"3.0",
    "gn:asciiname":"Chosan",
    "gn:country_code":"KR",
    "gn:dem":18,
    "gn:feature_class":"P",
    "gn:feature_code":"PPL",
    "gn:name":"Chosan",
    "gn:population":0,
    "gn:timezone":"Asia/Seoul",
    "iso:country":"KR",
    "name:ara_x_preferred":[
        "\u062a\u0634\u0648\u0632\u0627\u0646"
    ],
    "name:ben_x_preferred":[
        "\u099a\u09cb\u09b8\u09be\u09a8"
    ],
    "name:deu_x_preferred":[
        "Chosan"
    ],
    "name:ell_x_preferred":[
        "\u03a4\u03c3\u03bf\u03c3\u03ac\u03bd"
    ],
    "name:eng_x_preferred":[
        "Chosan"
    ],
    "name:fas_x_preferred":[
        "\u0686\u0648\u0633\u0627\u0646"
    ],
    "name:fra_x_preferred":[
        "Chosan"
    ],
    "name:heb_x_preferred":[
        "\u05e6'\u05d5\u05e1\u05d0\u05df"
    ],
    "name:hin_x_preferred":[
        "\u091a\u094b\u0938\u093e\u0928"
    ],
    "name:hun_x_preferred":[
        "Chosan"
    ],
    "name:ind_x_preferred":[
        "Chosan"
    ],
    "name:ita_x_preferred":[
        "Chosan"
    ],
    "name:jpn_x_preferred":[
        "\u9577\u5c71"
    ],
    "name:kor_x_preferred":[
        "\ucd08\uc0b0"
    ],
    "name:nld_x_preferred":[
        "Chosan"
    ],
    "name:pol_x_preferred":[
        "Ch'osan"
    ],
    "name:por_x_preferred":[
        "Ch'osan"
    ],
    "name:rus_x_preferred":[
        "\u0427\u043e\u0441\u043e\u043d"
    ],
    "name:spa_x_preferred":[
        "Chosan"
    ],
    "name:swe_x_preferred":[
        "Chosan"
    ],
    "name:tur_x_preferred":[
        "Chosan"
    ],
    "name:ukr_x_preferred":[
        "\u0427\u0445\u043e\u0441\u0430\u043d"
    ],
    "name:und_x_variant":[
        "\uc870\uc0b0",
        "Chosan"
    ],
    "name:urd_x_preferred":[
        "\u0686\u0648\u0633\u0627\u0646"
    ],
    "name:vie_x_preferred":[
        "Chosan"
    ],
    "name:zho_cn_x_preferred":[
        "\u957f\u5c71"
    ],
    "name:zho_tw_x_preferred":[
        "\u695a\u5c71"
    ],
    "wof:name":"Chosan",
    "wof:placetype":"locality"
},
  "geometry": {"coordinates":[127.00286,35.94294],"type":"Point"}
}