{
  "type": "Feature",
  "properties": {
    "gn:admin1_code":"13.0",
    "gn:admin2_code":"Ich'\u014fn-si",
    "gn:asciiname":"Araen-mal",
    "gn:country_code":"KR",
    "gn:dem":96,
    "gn:feature_class":"P",
    "gn:feature_code":"PPL",
    "gn:name":"Araen-mal",
    "gn:population":0,
    "gn:timezone":"Asia/Seoul",
    "iso:country":"KR",
    "name:kor_x_preferred":[
        "\uc544\ub7ab\ub9d0"
    ],
    "name:und_x_variant":[
        "Araetmal"
    ],
    "wof:name":"Araen-mal",
    "wof:placetype":"locality"
},
  "geometry": {"coordinates":[127.3575,37.21444],"type":"Point"}
}