{
  "type": "Feature",
  "properties": {
    "gn:admin1_code":"16.0",
    "gn:asciiname":"Hul-tong",
    "gn:country_code":"KR",
    "gn:dem":14,
    "gn:feature_class":"P",
    "gn:feature_code":"PPL",
    "gn:name":"H\u016dl-tong",
    "gn:population":0,
    "gn:timezone":"Asia/Seoul",
    "iso:country":"KR",
    "name:kor_x_preferred":[
        "H\u016dl-tong"
    ],
    "wof:name":"Hul-tong",
    "wof:placetype":"locality"
},
  "geometry": {"coordinates":[126.60444,34.16167],"type":"Point"}
}