{
  "type": "Feature",
  "properties": {
    "gn:admin1_code":"5.0",
    "gn:asciiname":"Taech'ol-li",
    "gn:country_code":"KR",
    "gn:dem":102,
    "gn:feature_class":"P",
    "gn:feature_code":"PPLL",
    "gn:name":"Taech\u2019\u014fl-li",
    "gn:population":0,
    "gn:timezone":"Asia/Seoul",
    "iso:country":"KR",
    "name:und_x_variant":[
        "\ub300\ucc9c\ub9ac",
        "Taech\u2019\u014fl-li"
    ],
    "wof:name":"Taech'ol-li",
    "wof:placetype":"locality"
},
  "geometry": {"coordinates":[127.56690999999999,36.28855],"type":"Point"}
}