{
  "type": "Feature",
  "properties": {
    "gn:admin1_code":"15.0",
    "gn:asciiname":"Sambakgol",
    "gn:country_code":"KR",
    "gn:dem":42,
    "gn:feature_class":"P",
    "gn:feature_code":"PPL",
    "gn:name":"Sambakgol",
    "gn:population":0,
    "gn:timezone":"Asia/Seoul",
    "iso:country":"KR",
    "name:kor_x_preferred":[
        "\uc0bc\ubc15\uace8"
    ],
    "wof:name":"Sambakgol",
    "wof:placetype":"locality"
},
  "geometry": {"coordinates":[128.46441999999999,35.89012],"type":"Point"}
}