{
  "type": "Feature",
  "properties": {
    "gn:admin1_code":"12.0",
    "gn:asciiname":"Munhak-tong",
    "gn:cc2":"KR",
    "gn:country_code":"KR",
    "gn:dem":43,
    "gn:feature_class":"P",
    "gn:feature_code":"PPL",
    "gn:name":"Munhak-tong",
    "gn:population":0,
    "gn:timezone":"Asia/Seoul",
    "iso:country":"KR",
    "name:und_x_variant":[
        "Munhang-ni",
        "Munhak-tong"
    ],
    "wof:name":"Munhak-tong",
    "wof:placetype":"locality"
},
  "geometry": {"coordinates":[126.67972,37.43889],"type":"Point"}
}