{
  "type": "Feature",
  "properties": {
    "gn:admin1_code":"12.0",
    "gn:asciiname":"Jogye",
    "gn:country_code":"KR",
    "gn:dem":14,
    "gn:feature_class":"P",
    "gn:feature_code":"PPL",
    "gn:name":"Jogye",
    "gn:population":0,
    "gn:timezone":"Asia/Seoul",
    "iso:country":"KR",
    "name:und_x_variant":[
        "\uc870\uacc4",
        "Jogye",
        "Chogye"
    ],
    "wof:name":"Jogye",
    "wof:placetype":"locality"
},
  "geometry": {"coordinates":[126.39042999999999,37.72221],"type":"Point"}
}