{
  "type": "Feature",
  "properties": {
    "gn:admin1_code":"16.0",
    "gn:asciiname":"Sinnam",
    "gn:country_code":"KR",
    "gn:dem":129,
    "gn:feature_class":"P",
    "gn:feature_code":"PPL",
    "gn:name":"Sinnam",
    "gn:population":0,
    "gn:timezone":"Asia/Seoul",
    "iso:country":"KR",
    "name:kor_x_preferred":[
        "\uc2e0\uc554\uc815"
    ],
    "name:kor_x_variant":[
        "Sinamj\u014fng",
        "\uc2e0\ub0a8"
    ],
    "wof:name":"Sinnam",
    "wof:placetype":"locality"
},
  "geometry": {"coordinates":[127.16171,34.80543],"type":"Point"}
}