{
  "type": "Feature",
  "properties": {
    "gn:admin1_code":"20.0",
    "gn:asciiname":"Ojang",
    "gn:country_code":"KR",
    "gn:dem":40,
    "gn:feature_class":"P",
    "gn:feature_code":"PPL",
    "gn:name":"Ojang",
    "gn:population":0,
    "gn:timezone":"Asia/Seoul",
    "iso:country":"KR",
    "name:und_x_variant":[
        "\uc624\uc7a5",
        "Ojang-dong",
        "Ojang"
    ],
    "wof:name":"Ojang",
    "wof:placetype":"locality"
},
  "geometry": {"coordinates":[128.44117,34.97237],"type":"Point"}
}