{
  "type": "Feature",
  "properties": {
    "gn:admin1_code":"17.0",
    "gn:asciiname":"Chungsong-gol",
    "gn:cc2":"KR",
    "gn:country_code":"KR",
    "gn:dem":85,
    "gn:feature_class":"P",
    "gn:feature_code":"PPL",
    "gn:name":"Chungsong-gol",
    "gn:population":0,
    "gn:timezone":"Asia/Seoul",
    "iso:country":"KR",
    "name:und_x_variant":[
        "Chungsong-ni",
        "Chungsong-dong",
        "Chungsong-gol"
    ],
    "wof:name":"Chungsong-gol",
    "wof:placetype":"locality"
},
  "geometry": {"coordinates":[127.25,36.63333],"type":"Point"}
}