{
  "type": "Feature",
  "properties": {
    "gn:admin1_code":"14.0",
    "gn:asciiname":"P'yongji",
    "gn:country_code":"KR",
    "gn:dem":331,
    "gn:feature_class":"P",
    "gn:feature_code":"PPL",
    "gn:name":"P\u2019y\u014fngji",
    "gn:population":0,
    "gn:timezone":"Asia/Seoul",
    "iso:country":"KR",
    "name:und_x_variant":[
        "\ud3c9\uc9c0",
        "P\u2019y\u014fngji"
    ],
    "wof:name":"P'yongji",
    "wof:placetype":"locality"
},
  "geometry": {"coordinates":[129.05609999999999,36.9275],"type":"Point"}
}