{
  "type": "Feature",
  "properties": {
    "iso:country":"KR",
    "qs:name":"\uac15\uacbd\uc74d",
    "qs:name_adm0":"\ud55c\uad6d",
    "qs:name_adm1":"\ucda9\uccad\ub0a8\ub3c4",
    "qs:photos":25,
    "qs:photos_1k":5,
    "qs:photos_9k":1,
    "qs:photos_9r":1,
    "qs:photos_all":25,
    "qs:photos_sr":1,
    "qs:placetype":"LocalAdmin",
    "qs:pop_sr":"0",
    "wof:name":"\uac15\uacbd\uc74d",
    "wof:placetype":"localadmin"
},
  "geometry": {"coordinates":[127.101516,36.211925],"type":"Point"}
}