{
  "type": "Feature",
  "properties": {
    "gn:admin1_code":"5.0",
    "gn:asciiname":"Sangdeokcheon",
    "gn:country_code":"KR",
    "gn:dem":158,
    "gn:feature_class":"P",
    "gn:feature_code":"PPL",
    "gn:name":"Sangdeokcheon",
    "gn:population":0,
    "gn:timezone":"Asia/Seoul",
    "iso:country":"KR",
    "name:kor_x_preferred":[
        "\uc0c1\ub355\ucc9c"
    ],
    "name:kor_x_variant":[
        "Sangd\u014fkch\u2019\u014fn"
    ],
    "wof:name":"Sangdeokcheon",
    "wof:placetype":"locality"
},
  "geometry": {"coordinates":[128.38412,37.00271],"type":"Point"}
}