{
  "type": "Feature",
  "properties": {
    "gn:admin1_code":"13.0",
    "gn:asciiname":"Hambak-kol",
    "gn:country_code":"KR",
    "gn:dem":34,
    "gn:feature_class":"P",
    "gn:feature_code":"PPL",
    "gn:name":"Hambak-kol",
    "gn:population":0,
    "gn:timezone":"Asia/Seoul",
    "iso:country":"KR",
    "name:kor_x_preferred":[
        "\ud568\ubc15\uace8"
    ],
    "wof:name":"Hambak-kol",
    "wof:placetype":"locality"
},
  "geometry": {"coordinates":[126.83917,37.25083],"type":"Point"}
}