{
  "type": "Feature",
  "properties": {
    "gn:admin1_code":"11.0",
    "gn:asciiname":"Myonmogi-dong",
    "gn:country_code":"KR",
    "gn:dem":21,
    "gn:feature_class":"P",
    "gn:feature_code":"PPL",
    "gn:name":"My\u014fnmogi-dong",
    "gn:population":0,
    "gn:timezone":"Asia/Seoul",
    "iso:country":"KR",
    "name:und_x_variant":[
        "\uba74\ubaa92\ub3d9",
        "My\u014fnmogi-dong"
    ],
    "wof:name":"Myonmogi-dong",
    "wof:placetype":"locality"
},
  "geometry": {"coordinates":[127.07871000000002,37.58913],"type":"Point"}
}