{
  "type": "Feature",
  "properties": {
    "gn:admin1_code":"13.0",
    "gn:asciiname":"Ssari-mal",
    "gn:country_code":"KR",
    "gn:dem":40,
    "gn:feature_class":"P",
    "gn:feature_code":"PPL",
    "gn:name":"Ssari-mal",
    "gn:population":0,
    "gn:timezone":"Asia/Seoul",
    "iso:country":"KR",
    "name:und_x_variant":[
        "\uc2f8\ub9ac\ub9d0",
        "Ssari-mal"
    ],
    "wof:name":"Ssari-mal",
    "wof:placetype":"locality"
},
  "geometry": {"coordinates":[126.9259,37.6507],"type":"Point"}
}