{
  "type": "Feature",
  "properties": {
    "gn:admin1_code":"17.0",
    "gn:asciiname":"Chumangnae",
    "gn:country_code":"KR",
    "gn:dem":76,
    "gn:feature_class":"P",
    "gn:feature_code":"PPL",
    "gn:name":"Chumangnae",
    "gn:population":0,
    "gn:timezone":"Asia/Seoul",
    "iso:country":"KR",
    "name:und_x_variant":[
        "\uc8fc\ub9c9\ub0b4",
        "Chumangnae"
    ],
    "wof:name":"Chumangnae",
    "wof:placetype":"locality"
},
  "geometry": {"coordinates":[126.80500000000001,36.3287],"type":"Point"}
}