{
  "type": "Feature",
  "properties": {
    "gn:admin1_code":"13.0",
    "gn:asciiname":"Hyeonchon",
    "gn:country_code":"KR",
    "gn:dem":111,
    "gn:feature_class":"P",
    "gn:feature_code":"PPL",
    "gn:name":"Hyeonchon",
    "gn:population":0,
    "gn:timezone":"Asia/Seoul",
    "iso:country":"KR",
    "name:kor_x_preferred":[
        "\ud604\ucd0c"
    ],
    "name:und_x_variant":[
        "Hy\u014fn-ch\u2019on"
    ],
    "wof:name":"Hyeonchon",
    "wof:placetype":"locality"
},
  "geometry": {"coordinates":[127.09350999999999,38.20288],"type":"Point"}
}