{
  "type": "Feature",
  "properties": {
    "gn:admin1_code":"5.0",
    "gn:asciiname":"Gangdalmal",
    "gn:country_code":"KR",
    "gn:dem":84,
    "gn:feature_class":"P",
    "gn:feature_code":"PPL",
    "gn:name":"Gangdalmal",
    "gn:population":0,
    "gn:timezone":"Asia/Seoul",
    "iso:country":"KR",
    "name:kor_x_preferred":[
        "\uac15\ub2ec\ub9d0"
    ],
    "wof:name":"Gangdalmal",
    "wof:placetype":"locality"
},
  "geometry": {"coordinates":[127.50751,36.67677],"type":"Point"}
}