{
  "type": "Feature",
  "properties": {
    "gn:admin1_code":"13.0",
    "gn:asciiname":"Sagidong",
    "gn:country_code":"KR",
    "gn:dem":125,
    "gn:feature_class":"P",
    "gn:feature_code":"PPL",
    "gn:name":"Sagidong",
    "gn:population":0,
    "gn:timezone":"Asia/Seoul",
    "iso:country":"KR",
    "name:kor_x_preferred":[
        "\uc0ac\uae30\ub3d9"
    ],
    "wof:name":"Sagidong",
    "wof:placetype":"locality"
},
  "geometry": {"coordinates":[126.96081,37.67698],"type":"Point"}
}