{
  "type": "Feature",
  "properties": {
    "gn:admin1_code":"6.0",
    "gn:asciiname":"Hupyeong",
    "gn:country_code":"KR",
    "gn:dem":126,
    "gn:feature_class":"P",
    "gn:feature_code":"PPL",
    "gn:name":"Hupyeong",
    "gn:population":0,
    "gn:timezone":"Asia/Seoul",
    "iso:country":"KR",
    "name:und_x_variant":[
        "\ud6c4\ud3c9",
        "Hup\u2019y\u014fng",
        "Hupyeong"
    ],
    "wof:name":"Hupyeong",
    "wof:placetype":"locality"
},
  "geometry": {"coordinates":[127.68571,38.10959],"type":"Point"}
}