{
  "type": "Feature",
  "properties": {
    "gn:admin1_code":"13.0",
    "gn:asciiname":"Janggwae",
    "gn:country_code":"KR",
    "gn:dem":9,
    "gn:feature_class":"P",
    "gn:feature_code":"PPL",
    "gn:name":"Janggwae",
    "gn:population":0,
    "gn:timezone":"Asia/Seoul",
    "iso:country":"KR",
    "name:kor_x_preferred":[
        "\uc7a5\uad18"
    ],
    "wof:name":"Janggwae",
    "wof:placetype":"locality"
},
  "geometry": {"coordinates":[126.77974,37.83846],"type":"Point"}
}