{
  "type": "Feature",
  "properties": {
    "gn:admin1_code":"6.0",
    "gn:asciiname":"Sori-gol",
    "gn:country_code":"KR",
    "gn:dem":832,
    "gn:feature_class":"P",
    "gn:feature_code":"PPL",
    "gn:name":"Sori-gol",
    "gn:population":0,
    "gn:timezone":"Asia/Seoul",
    "iso:country":"KR",
    "name:kor_x_preferred":[
        "\uc18c\ub9ac\uace8"
    ],
    "wof:name":"Sori-gol",
    "wof:placetype":"locality"
},
  "geometry": {"coordinates":[128.63720000000001,37.7273],"type":"Point"}
}