{
  "type": "Feature",
  "properties": {
    "gn:admin1_code":"21.0",
    "gn:asciiname":"Eojeon",
    "gn:country_code":"KR",
    "gn:dem":260,
    "gn:feature_class":"P",
    "gn:feature_code":"PPL",
    "gn:name":"Eojeon",
    "gn:population":0,
    "gn:timezone":"Asia/Seoul",
    "iso:country":"KR",
    "name:kor_x_preferred":[
        "\uc5b4\uc804"
    ],
    "wof:name":"Eojeon",
    "wof:placetype":"locality"
},
  "geometry": {"coordinates":[129.4015,35.66611],"type":"Point"}
}