{
  "type": "Feature",
  "properties": {
    "gn:admin1_code":"1.0",
    "gn:asciiname":"Jeondong",
    "gn:country_code":"KR",
    "gn:dem":8,
    "gn:feature_class":"P",
    "gn:feature_code":"PPL",
    "gn:name":"Jeondong",
    "gn:population":0,
    "gn:timezone":"Asia/Seoul",
    "iso:country":"KR",
    "name:kor_x_preferred":[
        "\uc804\ub3d9"
    ],
    "wof:name":"Jeondong",
    "wof:placetype":"locality"
},
  "geometry": {"coordinates":[126.17028999999999,33.32379],"type":"Point"}
}