{
  "type": "Feature",
  "properties": {
    "gn:admin1_code":"17.0",
    "gn:asciiname":"Okho-ri",
    "gn:country_code":"KR",
    "gn:dem":42,
    "gn:feature_class":"P",
    "gn:feature_code":"PPL",
    "gn:name":"Okho-ri",
    "gn:population":0,
    "gn:timezone":"Asia/Seoul",
    "iso:country":"KR",
    "name:und_x_variant":[
        "\uc6d0\uc625\ud638",
        "W\u014fnokho"
    ],
    "wof:name":"Okho-ri",
    "wof:placetype":"locality"
},
  "geometry": {"coordinates":[126.7059,36.8617],"type":"Point"}
}