{
  "type": "Feature",
  "properties": {
    "gn:admin1_code":"6.0",
    "gn:asciiname":"Sangsogi",
    "gn:country_code":"KR",
    "gn:dem":234,
    "gn:feature_class":"P",
    "gn:feature_code":"PPL",
    "gn:name":"Sangs\u014fgi",
    "gn:population":0,
    "gn:timezone":"Asia/Seoul",
    "iso:country":"KR",
    "name:und_x_variant":[
        "\uc0c1\uc11c\uae30",
        "Sangs\u014fgi"
    ],
    "wof:name":"Sangsogi",
    "wof:placetype":"locality"
},
  "geometry": {"coordinates":[129.27404000000001,37.21648],"type":"Point"}
}