{
  "type": "Feature",
  "properties": {
    "gn:admin1_code":"14.0",
    "gn:asciiname":"Hap'ung",
    "gn:country_code":"KR",
    "gn:dem":202,
    "gn:feature_class":"P",
    "gn:feature_code":"PPL",
    "gn:name":"Hap\u2019ung",
    "gn:population":0,
    "gn:timezone":"Asia/Seoul",
    "iso:country":"KR",
    "name:und_x_variant":[
        "\ud558\ud48d",
        "Hap\u2019ung"
    ],
    "wof:name":"Hap'ung",
    "wof:placetype":"locality"
},
  "geometry": {"coordinates":[129.09219999999999,36.6182],"type":"Point"}
}