{
  "type": "Feature",
  "properties": {
    "gn:admin1_code":"16.0",
    "gn:asciiname":"Yujon",
    "gn:country_code":"KR",
    "gn:dem":15,
    "gn:feature_class":"P",
    "gn:feature_code":"PPL",
    "gn:name":"Yuj\u014fn",
    "gn:population":0,
    "gn:timezone":"Asia/Seoul",
    "iso:country":"KR",
    "name:kor_x_preferred":[
        "\uc720\uc804"
    ],
    "name:kor_x_variant":[
        "Yuj\u014fn"
    ],
    "wof:name":"Yujon",
    "wof:placetype":"locality"
},
  "geometry": {"coordinates":[127.14753,34.55587],"type":"Point"}
}