{
  "type": "Feature",
  "properties": {
    "gn:admin1_code":"5.0",
    "gn:asciiname":"Gumalli",
    "gn:country_code":"KR",
    "gn:dem":168,
    "gn:feature_class":"P",
    "gn:feature_code":"PPL",
    "gn:name":"Gumalli",
    "gn:population":0,
    "gn:timezone":"Asia/Seoul",
    "iso:country":"KR",
    "name:kor_x_preferred":[
        "\uad6c\ub9cc\ub9ac"
    ],
    "wof:name":"Gumalli",
    "wof:placetype":"locality"
},
  "geometry": {"coordinates":[128.30753000000001,37.03834000000001],"type":"Point"}
}