{
  "type": "Feature",
  "properties": {
    "gn:admin1_code":"17.0",
    "gn:asciiname":"Kumani",
    "gn:country_code":"KR",
    "gn:dem":77,
    "gn:feature_class":"P",
    "gn:feature_code":"PPL",
    "gn:name":"Kumani",
    "gn:population":0,
    "gn:timezone":"Asia/Seoul",
    "iso:country":"KR",
    "name:und_x_variant":[
        "\uad6c\ub9cc\uc774",
        "Kumani"
    ],
    "wof:name":"Kumani",
    "wof:placetype":"locality"
},
  "geometry": {"coordinates":[126.8416,36.5293],"type":"Point"}
}