{
  "type": "Feature",
  "properties": {
    "gn:admin1_code":"13.0",
    "gn:asciiname":"Seonchang",
    "gn:country_code":"KR",
    "gn:dem":12,
    "gn:feature_class":"P",
    "gn:feature_code":"PPL",
    "gn:name":"Seonchang",
    "gn:population":0,
    "gn:timezone":"Asia/Seoul",
    "iso:country":"KR",
    "name:kor_x_preferred":[
        "\uc120\ucc3d"
    ],
    "name:kor_x_variant":[
        "S\u014fnch\u2019ang"
    ],
    "wof:name":"Seonchang",
    "wof:placetype":"locality"
},
  "geometry": {"coordinates":[126.66636,37.23806],"type":"Point"}
}