{
  "type": "Feature",
  "properties": {
    "gn:admin1_code":"17.0",
    "gn:asciiname":"Kumdang-gol",
    "gn:country_code":"KR",
    "gn:dem":58,
    "gn:feature_class":"P",
    "gn:feature_code":"PPL",
    "gn:name":"K\u016dmdang-gol",
    "gn:population":0,
    "gn:timezone":"Asia/Seoul",
    "iso:country":"KR",
    "name:und_x_variant":[
        "\uae08\ub2f9\uace8",
        "K\u016dmdang-gol"
    ],
    "wof:name":"Kumdang-gol",
    "wof:placetype":"locality"
},
  "geometry": {"coordinates":[127.03959999999999,36.4405],"type":"Point"}
}