{
  "type": "Feature",
  "properties": {
    "gn:admin1_code":"12.0",
    "gn:asciiname":"Maaebul",
    "gn:country_code":"KR",
    "gn:dem":192,
    "gn:feature_class":"P",
    "gn:feature_code":"PPL",
    "gn:name":"Maaebul",
    "gn:population":0,
    "gn:timezone":"Asia/Seoul",
    "iso:country":"KR",
    "name:und_x_variant":[
        "\ub9c8\uc560\ubd88",
        "Maaebul"
    ],
    "wof:name":"Maaebul",
    "wof:placetype":"locality"
},
  "geometry": {"coordinates":[126.32243,37.69005],"type":"Point"}
}