{
  "type": "Feature",
  "properties": {
    "gn:admin1_code":"13.0",
    "gn:asciiname":"Ganeung sam dong",
    "gn:country_code":"KR",
    "gn:dem":63,
    "gn:feature_class":"P",
    "gn:feature_code":"PPL",
    "gn:name":"Ganeung sam dong",
    "gn:population":0,
    "gn:timezone":"Asia/Seoul",
    "iso:country":"KR",
    "name:kor_x_preferred":[
        "\uac00\ub2a5\uc0bc\ub3d9"
    ],
    "name:und_x_variant":[
        "\uac00\ub2a53\ub3d9",
        "Kan\u016dngsam-dong",
        "Ganeung sam dong",
        "Ganeung 3 dong"
    ],
    "wof:name":"Ganeung sam dong",
    "wof:placetype":"locality"
},
  "geometry": {"coordinates":[127.02907,37.74274000000001],"type":"Point"}
}