{
  "type": "Feature",
  "properties": {
    "gn:admin1_code":"13.0",
    "gn:asciiname":"Iljakkul",
    "gn:country_code":"KR",
    "gn:dem":128,
    "gn:feature_class":"P",
    "gn:feature_code":"PPL",
    "gn:name":"Iljakkul",
    "gn:population":0,
    "gn:timezone":"Asia/Seoul",
    "iso:country":"KR",
    "name:kor_x_preferred":[
        "\uc77c\uc790\uafc0"
    ],
    "name:und_x_variant":[
        "\uc77c\uc9dc\uad74",
        "Iltchagul",
        "Iljakkul"
    ],
    "wof:name":"Iljakkul",
    "wof:placetype":"locality"
},
  "geometry": {"coordinates":[126.97458,37.72136],"type":"Point"}
}