{
  "type": "Feature",
  "properties": {
    "gn:admin1_code":"11.0",
    "gn:asciiname":"Chamsilch'il-tong",
    "gn:country_code":"KR",
    "gn:dem":24,
    "gn:feature_class":"P",
    "gn:feature_code":"PPL",
    "gn:name":"Chamsilch\u2019il-tong",
    "gn:population":0,
    "gn:timezone":"Asia/Seoul",
    "iso:country":"KR",
    "name:und_x_variant":[
        "\uc7a0\uc2e47\ub3d9",
        "Chamsilch\u2019il-tong"
    ],
    "wof:name":"Chamsilch'il-tong",
    "wof:placetype":"locality"
},
  "geometry": {"coordinates":[127.07411,37.50698],"type":"Point"}
}