{
  "type": "Feature",
  "properties": {
    "gn:admin1_code":"17.0",
    "gn:asciiname":"Odu",
    "gn:country_code":"KR",
    "gn:dem":8,
    "gn:feature_class":"P",
    "gn:feature_code":"PPL",
    "gn:name":"Odu",
    "gn:population":0,
    "gn:timezone":"Asia/Seoul",
    "iso:country":"KR",
    "name:ceb_x_preferred":[
        "Odu"
    ],
    "name:swe_x_preferred":[
        "Odu"
    ],
    "name:und_x_variant":[
        "\uc624\ub450"
    ],
    "wof:name":"Odu",
    "wof:placetype":"locality"
},
  "geometry": {"coordinates":[126.51900000000001,36.6025],"type":"Point"}
}