{
  "type": "Feature",
  "properties": {
    "gn:admin1_code":"14.0",
    "gn:asciiname":"Gagok",
    "gn:country_code":"KR",
    "gn:dem":120,
    "gn:feature_class":"P",
    "gn:feature_code":"PPL",
    "gn:name":"Gagok",
    "gn:population":0,
    "gn:timezone":"Asia/Seoul",
    "iso:country":"KR",
    "name:und_x_variant":[
        "\uac00\uace1",
        "Kagok",
        "Gagok"
    ],
    "wof:name":"Gagok",
    "wof:placetype":"locality"
},
  "geometry": {"coordinates":[128.69138000000001,35.70228],"type":"Point"}
}