{
  "type": "Feature",
  "properties": {
    "gn:admin1_code":"6.0",
    "gn:asciiname":"Chosal-li",
    "gn:cc2":"KR",
    "gn:country_code":"KR",
    "gn:dem":7,
    "gn:feature_class":"P",
    "gn:feature_code":"PPL",
    "gn:name":"Chosal-li",
    "gn:population":0,
    "gn:timezone":"Asia/Seoul",
    "iso:country":"KR",
    "name:kor_x_preferred":[
        "\uc870\uc0b0\ub9ac"
    ],
    "name:und_x_variant":[
        "Chosan-ni",
        "Chosal-li"
    ],
    "wof:name":"Chosal-li",
    "wof:placetype":"locality"
},
  "geometry": {"coordinates":[128.63471999999999,38.10917],"type":"Point"}
}