{
  "type": "Feature",
  "properties": {
    "gn:admin1_code":"17.0",
    "gn:asciiname":"Pamdogi",
    "gn:country_code":"KR",
    "gn:dem":21,
    "gn:feature_class":"P",
    "gn:feature_code":"PPL",
    "gn:name":"Pamd\u014fgi",
    "gn:population":0,
    "gn:timezone":"Asia/Seoul",
    "iso:country":"KR",
    "name:und_x_variant":[
        "\ubc24\ub355\uc774",
        "Pamd\u014fgi"
    ],
    "wof:name":"Pamdogi",
    "wof:placetype":"locality"
},
  "geometry": {"coordinates":[126.8242,36.7488],"type":"Point"}
}