{
  "type": "Feature",
  "properties": {
    "gn:admin1_code":"20.0",
    "gn:asciiname":"Imsil",
    "gn:country_code":"KR",
    "gn:dem":287,
    "gn:feature_class":"P",
    "gn:feature_code":"PPL",
    "gn:name":"Imsil",
    "gn:population":0,
    "gn:timezone":"Asia/Seoul",
    "iso:country":"KR",
    "name:und_x_variant":[
        "Imshil",
        "\uc784\uc2e4",
        "Imsil"
    ],
    "wof:name":"Imsil",
    "wof:placetype":"locality"
},
  "geometry": {"coordinates":[127.89463000000001,35.74981],"type":"Point"}
}