{
  "type": "Feature",
  "properties": {
    "gn:admin1_code":"5.0",
    "gn:asciiname":"Daejeong-ri",
    "gn:country_code":"KR",
    "gn:dem":112,
    "gn:feature_class":"P",
    "gn:feature_code":"PPLL",
    "gn:name":"Daejeong-ri",
    "gn:population":0,
    "gn:timezone":"Asia/Seoul",
    "iso:country":"KR",
    "name:kor_x_preferred":[
        "\ub300\uc815\ub9ac"
    ],
    "name:kor_x_variant":[
        "Taej\u014fng-ni"
    ],
    "wof:name":"Daejeong-ri",
    "wof:placetype":"locality"
},
  "geometry": {"coordinates":[127.52086,37.02711],"type":"Point"}
}