{
  "type": "Feature",
  "properties": {
    "gn:admin1_code":"13.0",
    "gn:asciiname":"Anneungan",
    "gn:country_code":"KR",
    "gn:dem":107,
    "gn:feature_class":"P",
    "gn:feature_code":"PPL",
    "gn:name":"Anneungan",
    "gn:population":0,
    "gn:timezone":"Asia/Seoul",
    "iso:country":"KR",
    "name:und_x_variant":[
        "\uc548\ub2a5\uc548",
        "Ann\u016dngan",
        "Anneungan"
    ],
    "wof:name":"Anneungan",
    "wof:placetype":"locality"
},
  "geometry": {"coordinates":[126.99588,37.81045],"type":"Point"}
}