{
  "type": "Feature",
  "properties": {
    "gn:admin1_code":"13.0",
    "gn:asciiname":"Dongbakdong",
    "gn:country_code":"KR",
    "gn:dem":83,
    "gn:feature_class":"P",
    "gn:feature_code":"PPL",
    "gn:name":"Dongbakdong",
    "gn:population":0,
    "gn:timezone":"Asia/Seoul",
    "iso:country":"KR",
    "name:kor_x_preferred":[
        "\ub3d9\ubc15\ub3d9"
    ],
    "name:und_x_variant":[
        "\ub3d9\ub9c9\uace8",
        "Tongmak-kol",
        "Dongbakdong"
    ],
    "wof:name":"Dongbakdong",
    "wof:placetype":"locality"
},
  "geometry": {"coordinates":[127.06832,37.95592],"type":"Point"}
}