{
  "type": "Feature",
  "properties": {
    "gn:admin1_code":"6.0",
    "gn:asciiname":"Naenamsong",
    "gn:country_code":"KR",
    "gn:dem":191,
    "gn:feature_class":"P",
    "gn:feature_code":"PPL",
    "gn:name":"Naenamsong",
    "gn:population":0,
    "gn:timezone":"Asia/Seoul",
    "iso:country":"KR",
    "name:kor_x_preferred":[
        "\ub0b4\ub0a8\uc1a1"
    ],
    "wof:name":"Naenamsong",
    "wof:placetype":"locality"
},
  "geometry": {"coordinates":[127.94759999999999,37.3074],"type":"Point"}
}