{
  "type": "Feature",
  "properties": {
    "gn:admin1_code":"16.0",
    "gn:asciiname":"Gasin",
    "gn:country_code":"KR",
    "gn:dem":185,
    "gn:feature_class":"P",
    "gn:feature_code":"PPL",
    "gn:name":"Gasin",
    "gn:population":0,
    "gn:timezone":"Asia/Seoul",
    "iso:country":"KR",
    "name:kor_x_preferred":[
        "\uac00\uc2e0"
    ],
    "name:und_x_variant":[
        "Kasin",
        "Gasin"
    ],
    "wof:name":"Gasin",
    "wof:placetype":"locality"
},
  "geometry": {"coordinates":[127.03555,34.75449],"type":"Point"}
}