{
  "type": "Feature",
  "properties": {
    "gn:admin1_code":"14.0",
    "gn:asciiname":"Kobujae",
    "gn:country_code":"KR",
    "gn:dem":147,
    "gn:feature_class":"P",
    "gn:feature_code":"PPL",
    "gn:name":"Kobujae",
    "gn:population":0,
    "gn:timezone":"Asia/Seoul",
    "iso:country":"KR",
    "name:und_x_variant":[
        "Kokchung",
        "Kobujae",
        "\uace0\ubd80\uc7ac",
        "Kobutchae"
    ],
    "wof:name":"Kobujae",
    "wof:placetype":"locality"
},
  "geometry": {"coordinates":[128.1001,36.5009],"type":"Point"}
}