{
  "type": "Feature",
  "properties": {
    "gn:admin1_code":"20.0",
    "gn:asciiname":"P'anch'on",
    "gn:country_code":"KR",
    "gn:dem":256,
    "gn:feature_class":"P",
    "gn:feature_code":"PPL",
    "gn:name":"P\u2019anch\u2019on",
    "gn:population":0,
    "gn:timezone":"Asia/Seoul",
    "iso:country":"KR",
    "name:und_x_variant":[
        "P\u2019an\u2019gong",
        "P\u2019anch\u2019ol-li",
        "P\u2019anch\u2019on"
    ],
    "wof:name":"P'anch'on",
    "wof:placetype":"locality"
},
  "geometry": {"coordinates":[127.78556,35.23472],"type":"Point"}
}