{
  "type": "Feature",
  "properties": {
    "gn:admin1_code":"17.0",
    "gn:asciiname":"Geomsaul",
    "gn:country_code":"KR",
    "gn:dem":82,
    "gn:feature_class":"P",
    "gn:feature_code":"PPL",
    "gn:name":"Geomsaul",
    "gn:population":0,
    "gn:timezone":"Asia/Seoul",
    "iso:country":"KR",
    "name:kor_x_preferred":[
        "\uac80\uc0ac\uc6b8"
    ],
    "wof:name":"Geomsaul",
    "wof:placetype":"locality"
},
  "geometry": {"coordinates":[127.24082,36.74711],"type":"Point"}
}