{
  "type": "Feature",
  "properties": {
    "gn:admin1_code":"5.0",
    "gn:asciiname":"Song-ni",
    "gn:country_code":"KR",
    "gn:dem":206,
    "gn:feature_class":"P",
    "gn:feature_code":"PPLL",
    "gn:name":"S\u014fng-ni",
    "gn:population":0,
    "gn:timezone":"Asia/Seoul",
    "iso:country":"KR",
    "name:und_x_variant":[
        "\uc131\ub9ac",
        "S\u014fng-ni"
    ],
    "wof:name":"Song-ni",
    "wof:placetype":"locality"
},
  "geometry": {"coordinates":[127.68863,36.46134],"type":"Point"}
}