{
  "type": "Feature",
  "properties": {
    "gn:admin1_code":"6.0",
    "gn:asciiname":"Samhwa-dong",
    "gn:country_code":"KR",
    "gn:dem":325,
    "gn:feature_class":"P",
    "gn:feature_code":"PPL",
    "gn:name":"Samhwa-dong",
    "gn:population":0,
    "gn:timezone":"Asia/Seoul",
    "iso:country":"KR",
    "name:und_x_variant":[
        "\uc0bc\ud654\ub3d9",
        "Samhwa-dong"
    ],
    "wof:name":"Samhwa-dong",
    "wof:placetype":"locality"
},
  "geometry": {"coordinates":[129.01799,37.48818],"type":"Point"}
}