{
  "type": "Feature",
  "properties": {
    "gn:admin1_code":"13.0",
    "gn:asciiname":"Chungsan",
    "gn:country_code":"KR",
    "gn:dem":15,
    "gn:feature_class":"P",
    "gn:feature_code":"PPL",
    "gn:name":"Chungsan",
    "gn:population":0,
    "gn:timezone":"Asia/Seoul",
    "iso:country":"KR",
    "name:kor_x_preferred":[
        "\uc911\uc0b0"
    ],
    "wof:name":"Chungsan",
    "wof:placetype":"locality"
},
  "geometry": {"coordinates":[126.72221999999999,37.68361],"type":"Point"}
}