{
  "type": "Feature",
  "properties": {
    "gn:admin1_code":"13.0",
    "gn:asciiname":"Oryongdong",
    "gn:country_code":"KR",
    "gn:dem":24,
    "gn:feature_class":"P",
    "gn:feature_code":"PPL",
    "gn:name":"Oryongdong",
    "gn:population":0,
    "gn:timezone":"Asia/Seoul",
    "iso:country":"KR",
    "name:und_x_variant":[
        "\uc624\ub8e1\ub3d9",
        "Oryongdong"
    ],
    "wof:name":"Oryongdong",
    "wof:placetype":"locality"
},
  "geometry": {"coordinates":[127.08409,37.08501],"type":"Point"}
}