{
  "type": "Feature",
  "properties": {
    "gn:admin1_code":"6.0",
    "gn:asciiname":"Sahung",
    "gn:country_code":"KR",
    "gn:dem":117,
    "gn:feature_class":"P",
    "gn:feature_code":"PPL",
    "gn:name":"Sah\u016dng",
    "gn:population":0,
    "gn:timezone":"Asia/Seoul",
    "iso:country":"KR",
    "name:kor_x_preferred":[
        "\uc0ac\ud765"
    ],
    "name:kor_x_variant":[
        "Sah\u016dng"
    ],
    "wof:name":"Sahung",
    "wof:placetype":"locality"
},
  "geometry": {"coordinates":[127.8464,37.24],"type":"Point"}
}