{
  "type": "Feature",
  "properties": {
    "gn:admin1_code":"14.0",
    "gn:asciiname":"Oego",
    "gn:country_code":"KR",
    "gn:dem":351,
    "gn:feature_class":"P",
    "gn:feature_code":"PPL",
    "gn:name":"Oego",
    "gn:population":0,
    "gn:timezone":"Asia/Seoul",
    "iso:country":"KR",
    "name:und_x_variant":[
        "\uc678\uace0",
        "Oego"
    ],
    "wof:name":"Oego",
    "wof:placetype":"locality"
},
  "geometry": {"coordinates":[128.07571999999999,35.94604],"type":"Point"}
}