{
  "type": "Feature",
  "properties": {
    "gn:admin1_code":"6.0",
    "gn:asciiname":"Baegamni",
    "gn:country_code":"KR",
    "gn:dem":243,
    "gn:feature_class":"P",
    "gn:feature_code":"PPL",
    "gn:name":"Baegamni",
    "gn:population":0,
    "gn:timezone":"Asia/Seoul",
    "iso:country":"KR",
    "name:kor_x_preferred":[
        "\ubc31\uc554\ub9ac"
    ],
    "wof:name":"Baegamni",
    "wof:placetype":"locality"
},
  "geometry": {"coordinates":[128.50458999999998,38.07787],"type":"Point"}
}