{
  "type": "Feature",
  "properties": {
    "gn:admin1_code":"13.0",
    "gn:asciiname":"Soemok",
    "gn:country_code":"KR",
    "gn:dem":220,
    "gn:feature_class":"P",
    "gn:feature_code":"PPL",
    "gn:name":"Soemok",
    "gn:population":0,
    "gn:timezone":"Asia/Seoul",
    "iso:country":"KR",
    "name:und_x_variant":[
        "\uc1e0\ubaa9",
        "Soemok"
    ],
    "wof:name":"Soemok",
    "wof:placetype":"locality"
},
  "geometry": {"coordinates":[127.11315999999999,37.91012],"type":"Point"}
}