{
  "type": "Feature",
  "properties": {
    "gn:admin1_code":"18.0",
    "gn:asciiname":"Buram",
    "gn:country_code":"KR",
    "gn:dem":36,
    "gn:feature_class":"P",
    "gn:feature_code":"PPL",
    "gn:name":"Buram",
    "gn:population":0,
    "gn:timezone":"Asia/Seoul",
    "iso:country":"KR",
    "name:kor_x_preferred":[
        "\ubd88\uc554"
    ],
    "name:und_x_variant":[
        "Puram"
    ],
    "wof:name":"Buram",
    "wof:placetype":"locality"
},
  "geometry": {"coordinates":[126.83624,35.11088],"type":"Point"}
}