{
  "type": "Feature",
  "properties": {
    "gn:admin1_code":"6.0",
    "gn:asciiname":"T'apko-ri",
    "gn:country_code":"KR",
    "gn:dem":704,
    "gn:feature_class":"P",
    "gn:feature_code":"PPL",
    "gn:name":"T\u2019apk\u014f-ri",
    "gn:population":0,
    "gn:timezone":"Asia/Seoul",
    "iso:country":"KR",
    "name:kor_x_preferred":[
        "\ud0d1\uac70\ub9ac"
    ],
    "name:kor_x_variant":[
        "T\u2019apk\u014f-ri"
    ],
    "wof:name":"T'apko-ri",
    "wof:placetype":"locality"
},
  "geometry": {"coordinates":[128.88460000000001,37.4698],"type":"Point"}
}