{
  "type": "Feature",
  "properties": {
    "gn:admin1_code":"13.0",
    "gn:asciiname":"Samsongdang-ni",
    "gn:country_code":"KR",
    "gn:dem":96,
    "gn:feature_class":"P",
    "gn:feature_code":"PPLL",
    "gn:name":"Sams\u014fngdang-ni",
    "gn:population":0,
    "gn:timezone":"Asia/Seoul",
    "iso:country":"KR",
    "name:eng_x_preferred":[
        "Samsongdang"
    ],
    "name:eng_x_variant":[
        "Samsongdang-ni"
    ],
    "name:kor_x_preferred":[
        "\uc0bc\uc131\ub2f9\ub9ac"
    ],
    "name:kor_x_variant":[
        "Sams\u014fngdang-ni"
    ],
    "wof:name":"Samsongdang",
    "wof:placetype":"locality"
},
  "geometry": {"coordinates":[127.23949,37.97332],"type":"Point"}
}