{
  "type": "Feature",
  "properties": {
    "gn:admin1_code":"17.0",
    "gn:asciiname":"Mongnaemi",
    "gn:country_code":"KR",
    "gn:dem":29,
    "gn:feature_class":"P",
    "gn:feature_code":"PPL",
    "gn:name":"Mongnaemi",
    "gn:population":0,
    "gn:timezone":"Asia/Seoul",
    "iso:country":"KR",
    "name:und_x_variant":[
        "\ubaa9\ub0b4\ubbf8",
        "Mongnaemi"
    ],
    "wof:name":"Mongnaemi",
    "wof:placetype":"locality"
},
  "geometry": {"coordinates":[126.2762,36.8189],"type":"Point"}
}