{
  "type": "Feature",
  "properties": {
    "gn:admin1_code":"6.0",
    "gn:asciiname":"Neupmok",
    "gn:country_code":"KR",
    "gn:dem":640,
    "gn:feature_class":"P",
    "gn:feature_code":"PPL",
    "gn:name":"Neupmok",
    "gn:population":0,
    "gn:timezone":"Asia/Seoul",
    "iso:country":"KR",
    "name:kor_x_preferred":[
        "\ud070\uc0b0\uc18c\uace8"
    ],
    "name:kor_x_variant":[
        "K\u2019\u016dnsanso-gol",
        "\ub2aa\ubaa9",
        "\ub2a6\ubaa9"
    ],
    "name:und_x_variant":[
        "N\u016dnmok"
    ],
    "wof:name":"Neupmok",
    "wof:placetype":"locality"
},
  "geometry": {"coordinates":[128.5949,37.6471],"type":"Point"}
}