{
  "type": "Feature",
  "properties": {
    "gn:admin1_code":"19.0",
    "gn:asciiname":"Gugaemal",
    "gn:country_code":"KR",
    "gn:dem":114,
    "gn:feature_class":"P",
    "gn:feature_code":"PPL",
    "gn:name":"Gugaemal",
    "gn:population":0,
    "gn:timezone":"Asia/Seoul",
    "iso:country":"KR",
    "name:und_x_variant":[
        "\uad6c\uac1c\ub9d0",
        "Kugae-mal",
        "Gugaemal"
    ],
    "wof:name":"Gugaemal",
    "wof:placetype":"locality"
},
  "geometry": {"coordinates":[127.29438,36.29789],"type":"Point"}
}