{
  "type": "Feature",
  "properties": {
    "gn:admin1_code":"13.0",
    "gn:asciiname":"Yonggang-gol",
    "gn:country_code":"KR",
    "gn:dem":90,
    "gn:feature_class":"P",
    "gn:feature_code":"PPL",
    "gn:name":"Yonggang-gol",
    "gn:population":0,
    "gn:timezone":"Asia/Seoul",
    "iso:country":"KR",
    "name:und_x_variant":[
        "\uc6a9\uac15\uace8",
        "Yonggang-gol"
    ],
    "wof:name":"Yonggang-gol",
    "wof:placetype":"locality"
},
  "geometry": {"coordinates":[127.65000000000001,37.28528],"type":"Point"}
}