{
  "type": "Feature",
  "properties": {
    "gn:admin1_code":"17.0",
    "gn:asciiname":"Tumi",
    "gn:country_code":"KR",
    "gn:dem":41,
    "gn:feature_class":"P",
    "gn:feature_code":"PPL",
    "gn:name":"Tumi",
    "gn:population":0,
    "gn:timezone":"Asia/Seoul",
    "iso:country":"KR",
    "name:cat_x_preferred":[
        "Tumi"
    ],
    "name:deu_x_preferred":[
        "Tumi"
    ],
    "name:fra_x_preferred":[
        "Tumi"
    ],
    "name:ita_x_preferred":[
        "Tumi"
    ],
    "name:mkd_x_preferred":[
        "\u0422\u0443\u043c\u0438"
    ],
    "name:pap_x_preferred":[
        "Tumi"
    ],
    "name:pol_x_preferred":[
        "Tumi"
    ],
    "name:por_x_preferred":[
        "Tumi"
    ],
    "name:que_x_preferred":[
        "Tumi"
    ],
    "name:rus_x_preferred":[
        "\u0422\u0443\u043c\u0438"
    ],
    "name:spa_x_preferred":[
        "Tumi"
    ],
    "name:und_x_variant":[
        "\ub450\ubbf8"
    ],
    "wof:name":"Tumi",
    "wof:placetype":"locality"
},
  "geometry": {"coordinates":[127.0866,36.8934],"type":"Point"}
}