{
  "type": "Feature",
  "properties": {
    "gn:admin1_code":"17.0",
    "gn:asciiname":"Tumi",
    "gn:country_code":"KR",
    "gn:dem":41,
    "gn:feature_class":"P",
    "gn:feature_code":"PPL",
    "gn:name":"Tumi",
    "gn:population":0,
    "gn:timezone":"Asia/Seoul",
    "iso:country":"KR",
    "name:und_x_variant":[
        "\ub450\ubbf8",
        "Tumi"
    ],
    "wof:name":"Tumi",
    "wof:placetype":"locality"
},
  "geometry": {"coordinates":[127.0866,36.8934],"type":"Point"}
}