{
  "type": "Feature",
  "properties": {
    "gn:admin1_code":"16.0",
    "gn:asciiname":"Kahei",
    "gn:country_code":"KR",
    "gn:dem":76,
    "gn:feature_class":"P",
    "gn:feature_code":"PPL",
    "gn:name":"Kahei",
    "gn:population":0,
    "gn:timezone":"Asia/Seoul",
    "iso:country":"KR",
    "name:und_x_variant":[
        "Hap\u2019y\u014fng",
        "Haep\u2019y\u014fng",
        "Kahei",
        "Sup\u2019y\u014fng-ni"
    ],
    "wof:name":"Kahei",
    "wof:placetype":"locality"
},
  "geometry": {"coordinates":[127.55,35.16667],"type":"Point"}
}