{
  "type": "Feature",
  "properties": {
    "gn:admin1_code":"16.0",
    "gn:asciiname":"Saktun",
    "gn:country_code":"KR",
    "gn:dem":38,
    "gn:feature_class":"P",
    "gn:feature_code":"PPL",
    "gn:name":"Saktun",
    "gn:population":0,
    "gn:timezone":"Asia/Seoul",
    "iso:country":"KR",
    "name:kor_x_preferred":[
        "\uc0ad\ub454"
    ],
    "wof:name":"Saktun",
    "wof:placetype":"locality"
},
  "geometry": {"coordinates":[126.84104000000001,34.68953],"type":"Point"}
}