{
  "type": "Feature",
  "properties": {
    "gn:admin1_code":"16.0",
    "gn:asciiname":"Ungok",
    "gn:country_code":"KR",
    "gn:dem":106,
    "gn:feature_class":"P",
    "gn:feature_code":"PPL",
    "gn:name":"Ungok",
    "gn:population":0,
    "gn:timezone":"Asia/Seoul",
    "iso:country":"KR",
    "name:jpn_x_preferred":[
        "\u96f2\u8c37\u5730\u533a"
    ],
    "name:kor_x_preferred":[
        "\uc6b4\uace1\uc9c0\uad6c"
    ],
    "name:nor_x_preferred":[
        "Ungok"
    ],
    "name:sco_x_preferred":[
        "Ungok"
    ],
    "name:tur_x_preferred":[
        "Ungok"
    ],
    "name:vie_x_preferred":[
        "Ungok"
    ],
    "wof:name":"Ungok",
    "wof:placetype":"locality"
},
  "geometry": {"coordinates":[126.56305999999999,34.37306],"type":"Point"}
}