{
  "type": "Feature",
  "properties": {
    "gn:admin1_code":"11.0",
    "gn:asciiname":"Wonhyoroi-dong",
    "gn:country_code":"KR",
    "gn:dem":19,
    "gn:feature_class":"P",
    "gn:feature_code":"PPL",
    "gn:name":"W\u014fnhyoroi-dong",
    "gn:population":0,
    "gn:timezone":"Asia/Seoul",
    "iso:country":"KR",
    "name:und_x_variant":[
        "\uc6d0\ud6a8\ub85c2\ub3d9",
        "W\u014fnhyoroi-dong"
    ],
    "wof:name":"Wonhyoroi-dong",
    "wof:placetype":"locality"
},
  "geometry": {"coordinates":[126.95223,37.53257],"type":"Point"}
}