{
  "type": "Feature",
  "properties": {
    "gn:admin1_code":"5.0",
    "gn:asciiname":"Deongnyeon-ri",
    "gn:country_code":"KR",
    "gn:dem":155,
    "gn:feature_class":"P",
    "gn:feature_code":"PPLL",
    "gn:name":"Deongnyeon-ri",
    "gn:population":0,
    "gn:timezone":"Asia/Seoul",
    "iso:country":"KR",
    "name:kor_x_preferred":[
        "\ub355\ub828\ub9ac"
    ],
    "name:kor_x_variant":[
        "T\u014fngny\u014fl-li"
    ],
    "name:und_x_variant":[
        "T\u014fgy\u014fn-ni",
        "T\u014fngny\u014fn-ni",
        "Deongnyeon-ri"
    ],
    "wof:name":"Deongnyeon-ri",
    "wof:placetype":"locality"
},
  "geometry": {"coordinates":[127.77303999999999,37.01796],"type":"Point"}
}