{
  "type": "Feature",
  "properties": {
    "gn:admin1_code":"6.0",
    "gn:asciiname":"Nonmi-ri",
    "gn:country_code":"KR",
    "gn:dem":117,
    "gn:feature_class":"P",
    "gn:feature_code":"PPL",
    "gn:name":"Nonmi-ri",
    "gn:population":0,
    "gn:timezone":"Asia/Seoul",
    "iso:country":"KR",
    "name:und_x_variant":[
        "\ub17c\ubbf8\ub9ac",
        "Nonmi-ri"
    ],
    "wof:name":"Nonmi-ri",
    "wof:placetype":"locality"
},
  "geometry": {"coordinates":[127.67638999999998,38.09778],"type":"Point"}
}