{
  "type": "Feature",
  "properties": {
    "gn:admin1_code":"13.0",
    "gn:asciiname":"Sangchon",
    "gn:country_code":"KR",
    "gn:dem":95,
    "gn:feature_class":"P",
    "gn:feature_code":"PPL",
    "gn:name":"Sangchon",
    "gn:population":0,
    "gn:timezone":"Asia/Seoul",
    "iso:country":"KR",
    "name:kor_x_preferred":[
        "\uc0c1\ucd0c"
    ],
    "name:und_x_variant":[
        "Sangchon"
    ],
    "wof:name":"Sangchon",
    "wof:placetype":"locality"
},
  "geometry": {"coordinates":[127.28666,37.64186],"type":"Point"}
}